{
  "type": "Feature",
  "properties": {
    "iso:country":"US",
    "sg:address":"15721 W Dodge Rd",
    "sg:city":"Omaha",
    "sg:classifiers":[
        {
            "category":"Social Services",
            "subcategory":"Child Care",
            "type":"Services"
        }
    ],
    "sg:phone":"+1 402 330 9757",
    "sg:postcode":"68118",
    "sg:province":"NE",
    "sg:tags":[
        "day"
    ],
    "wof:name":"Childrens Corner",
    "wof:placetype":"venue"
},
  "geometry": {"coordinates":[-96.160196,41.262961],"type":"Point"}
}