{
  "type": "Feature",
  "properties": {
    "addr:full":"14643 Grover St Omaha NE 68144",
    "addr:housenumber":"14643",
    "addr:postcode":"68144",
    "addr:street":"Grover St",
    "iso:country":"US",
    "sg:address":"14643 Grover St",
    "sg:city":"Omaha",
    "sg:classifiers":[
        {
            "category":"Building & Trades",
            "subcategory":"Construction",
            "type":"Services"
        }
    ],
    "sg:phone":"+1 402 891 9887",
    "sg:postcode":"68144",
    "sg:province":"NE",
    "sg:tags":[
        "general",
        "contractor"
    ],
    "wof:name":"Carlson III Construction",
    "wof:placetype":"venue"
},
  "geometry": {"coordinates":[-96.14661099999999,41.227637],"type":"Point"}
}