{
  "type": "Feature",
  "properties": {
    "iso:country":"US",
    "sg:address":"10819 Prairie Brook Rd",
    "sg:city":"Omaha",
    "sg:classifiers":[
        {
            "category":"Personal",
            "subcategory":"Barber",
            "type":"Services"
        }
    ],
    "sg:phone":"+1 402 391 9994",
    "sg:postcode":"68144",
    "sg:province":"NE",
    "sg:tags":[
        "shop"
    ],
    "wof:name":"Rock Brook Barber Shop",
    "wof:placetype":"venue"
},
  "geometry": {"coordinates":[-96.082509,41.233168],"type":"Point"}
}