{
  "type": "Feature",
  "properties": {
    "addr:full":"2304 W Lincoln Hwy Grand Island NE 68803",
    "addr:housenumber":"2304",
    "addr:postcode":"68803",
    "addr:street":"W Lincoln Hwy",
    "iso:country":"US",
    "sg:address":"2304 W Lincoln Hwy",
    "sg:city":"Grand Island",
    "sg:classifiers":[
        {
            "category":"Building & Trades",
            "subcategory":"Plumbing",
            "type":"Services"
        }
    ],
    "sg:phone":"+1 308 384 2425",
    "sg:postcode":"68803",
    "sg:province":"NE",
    "sg:tags":[
        "heating",
        "contractor"
    ],
    "sg:website":"www.midwestheating-air.com",
    "wof:name":"Midwest Heating & Air Cond",
    "wof:placetype":"venue"
},
  "geometry": {"coordinates":[-98.364699,40.91691],"type":"Point"}
}