{
  "type": "Feature",
  "properties": {
    "iso:country":"US",
    "sg:address":"687 Halligan Dr",
    "sg:city":"North Platte",
    "sg:classifiers":[
        {
            "category":"Shopping",
            "type":"Retail Goods"
        }
    ],
    "sg:phone":"+1 308 534 7047",
    "sg:postcode":"69101",
    "sg:province":"NE",
    "sg:tags":[
        "factory",
        "outlet"
    ],
    "wof:name":"Van Heusen Factory Outlet",
    "wof:placetype":"venue"
},
  "geometry": {"coordinates":[-100.757085,41.110827],"type":"Point"}
}