{
  "type": "Feature",
  "properties": {
    "iso:country":"US",
    "sg:address":"2211 Co Rd 350",
    "sg:city":"Staplehurst",
    "sg:phone":"+1 402 535 2707",
    "sg:postcode":"68439",
    "sg:province":"NE",
    "sg:tags":[
        "farm",
        "corn"
    ],
    "wof:name":"Duer Seed",
    "wof:placetype":"venue"
},
  "geometry": {"coordinates":[-97.19697600000001,41.003924],"type":"Point"}
}