{
  "type": "Feature",
  "properties": {
    "iso:country":"US",
    "sg:address":"229 Vincent Ave",
    "sg:city":"Chappell",
    "sg:classifiers":[
        {
            "category":"Personal",
            "subcategory":"Beauty Salon",
            "type":"Services"
        }
    ],
    "sg:phone":"+1 308 874 2223",
    "sg:postcode":"69129",
    "sg:province":"NE",
    "wof:name":"Upper Cut",
    "wof:placetype":"venue"
},
  "geometry": {"coordinates":[-102.472357,41.092791],"type":"Point"}
}