{
  "type": "Feature",
  "properties": {
    "iso:country":"US",
    "sg:address":"790 Rd East R S",
    "sg:city":"Paxton",
    "sg:classifiers":[
        {
            "category":"Farming",
            "subcategory":"Livestock Farm",
            "type":"Manufacturing & Wholesale Goods"
        },
        {
            "category":"Farming",
            "subcategory":"Farm",
            "type":"Manufacturing & Wholesale Goods"
        }
    ],
    "sg:phone":"+1 308 239 4539",
    "sg:postcode":"69155",
    "sg:province":"NE",
    "sg:tags":[
        "grain",
        "feedlot",
        "cattle"
    ],
    "wof:name":"Spurgin Inc",
    "wof:placetype":"venue"
},
  "geometry": {"coordinates":[-101.38520200000001,41.101931],"type":"Point"}
}