{
  "type": "Feature",
  "properties": {
    "iso:country":"US",
    "sg:address":"5334 N 45th St",
    "sg:city":"Omaha",
    "sg:classifiers":[
        {
            "category":"Organizations",
            "subcategory":"Non-profit Organization",
            "type":"Services"
        }
    ],
    "sg:phone":"+1 402 453 8888",
    "sg:postcode":"68104",
    "sg:province":"NE",
    "wof:name":"Fresh Start",
    "wof:placetype":"venue"
},
  "geometry": {"coordinates":[-95.98115199999999,41.308871],"type":"Point"}
}