{
  "type": "Feature",
  "properties": {
    "addr:full":"3674 35th Ave Columbus NE 68601",
    "addr:housenumber":"3674",
    "addr:postcode":"68601",
    "addr:street":"35Th Ave",
    "iso:country":"US",
    "sg:address":"3674 35th Ave",
    "sg:city":"Columbus",
    "sg:classifiers":[
        {
            "category":"Social Services",
            "type":"Services"
        }
    ],
    "sg:phone":"+1 402 564 6248",
    "sg:postcode":"68601",
    "sg:province":"NE",
    "wof:name":"Teammates Mentoring Program",
    "wof:placetype":"venue"
},
  "geometry": {"coordinates":[-97.371934,41.452762],"type":"Point"}
}