{
  "type": "Feature",
  "properties": {
    "iso:country":"US",
    "sg:address":"2654 33rd Ave",
    "sg:city":"Columbus",
    "sg:classifiers":[
        {
            "category":"Insurance",
            "subcategory":"Insurance Agent",
            "type":"Services"
        }
    ],
    "sg:phone":"+1 402 358 0813",
    "sg:postcode":"68601",
    "sg:province":"NE",
    "wof:name":"Strategic Planning Inc",
    "wof:placetype":"venue"
},
  "geometry": {"coordinates":[-97.368295,41.441886],"type":"Point"}
}