{
  "type": "Feature",
  "properties": {
    "addr:full":"710 13th Ave Columbus NE 68601",
    "addr:housenumber":"710",
    "addr:postcode":"68601",
    "addr:street":"13Th Ave",
    "iso:country":"US",
    "sg:address":"710 13th Ave",
    "sg:city":"Columbus",
    "sg:classifiers":[
        {
            "category":"Shopping",
            "type":"Retail Goods"
        }
    ],
    "sg:phone":"+1 402 564 9068",
    "sg:postcode":"68601",
    "sg:province":"NE",
    "sg:tags":[
        "telephone",
        "cellular"
    ],
    "wof:name":"Telebeep Inc",
    "wof:placetype":"venue"
},
  "geometry": {"coordinates":[-97.343305,41.423315],"type":"Point"}
}