{
  "type": "Feature",
  "properties": {
    "addr:full":"30235 439th Ave Yankton NE 57078",
    "addr:housenumber":"30235",
    "addr:postcode":"57078",
    "addr:street":"439Th Ave",
    "iso:country":"US",
    "sg:address":"30235 439th Ave",
    "sg:city":"Yankton",
    "sg:phone":"+1 605 665 5434",
    "sg:postcode":"57078",
    "sg:province":"NE",
    "sg:tags":[
        "farm",
        "grain",
        "cash"
    ],
    "wof:name":"Marvin Mehlhaff",
    "wof:placetype":"venue"
},
  "geometry": {"coordinates":[-97.41667,42.996623],"type":"Point"}
}