{
  "type": "Feature",
  "properties": {
    "addr:full":"2018 Central Ave Kearney NE 68847",
    "addr:housenumber":"2018",
    "addr:postcode":"68847",
    "addr:street":"Central Ave",
    "iso:country":"US",
    "sg:address":"2018 Central Ave",
    "sg:city":"Kearney",
    "sg:classifiers":[
        {
            "category":"Personal",
            "subcategory":"Barber",
            "type":"Services"
        }
    ],
    "sg:phone":"+1 308 234 4888",
    "sg:postcode":"68847",
    "sg:province":"NE",
    "wof:name":"Lis's Barber & Beauty Shop",
    "wof:placetype":"venue"
},
  "geometry": {"coordinates":[-99.081766,40.69658],"type":"Point"}
}