{
  "type": "Feature",
  "properties": {
    "iso:country":"US",
    "sg:address":"3857 G Rd",
    "sg:city":"Dunbar",
    "sg:classifiers":[
        {
            "category":"Manufacturing",
            "subcategory":"Pet Food",
            "type":"Manufacturing & Wholesale Goods"
        }
    ],
    "sg:phone":"+1 402 265 2651",
    "sg:postcode":"68346",
    "sg:province":"NE",
    "sg:tags":[
        "feed",
        "mfg",
        "prepared"
    ],
    "wof:name":"Ross Feed Supply",
    "wof:placetype":"venue"
},
  "geometry": {"coordinates":[-96.09850900000001,40.69716],"type":"Point"}
}