{
  "type": "Feature",
  "properties": {
    "addr:full":"104 S Cherokee Mc Cook NE 69001",
    "addr:housenumber":"104",
    "addr:postcode":"69001",
    "addr:street":"S Cherokee Mc",
    "iso:country":"US",
    "sg:address":"104 S Cherokee",
    "sg:city":"Mc Cook",
    "sg:classifiers":[
        {
            "category":"Building & Trades",
            "subcategory":"Construction",
            "type":"Services"
        }
    ],
    "sg:phone":"+1 308 345 7532",
    "sg:postcode":"69001",
    "sg:province":"NE",
    "sg:tags":[
        "woodworker"
    ],
    "wof:name":"Wilcox Wood Art",
    "wof:placetype":"venue"
},
  "geometry": {"coordinates":[-100.61748299999999,40.213998],"type":"Point"}
}