{
  "type": "Feature",
  "properties": {
    "addr:full":"248 W 5th St Ainsworth NE 69210",
    "addr:housenumber":"248",
    "addr:postcode":"69210",
    "addr:street":"W 5Th St",
    "iso:country":"US",
    "sg:address":"248 W 5th St",
    "sg:city":"Ainsworth",
    "sg:classifiers":[
        {
            "category":"Shopping",
            "subcategory":"Musical Instruments",
            "type":"Retail Goods"
        }
    ],
    "sg:phone":"+1 402 387 1011",
    "sg:postcode":"69210",
    "sg:province":"NE",
    "wof:name":"Flying G Music Co",
    "wof:placetype":"venue"
},
  "geometry": {"coordinates":[-99.864611,42.551169],"type":"Point"}
}