{
  "type": "Feature",
  "properties": {
    "iso:country":"US",
    "sg:address":"505 S Minnesota Ave",
    "sg:city":"Hastings",
    "sg:classifiers":[
        {
            "category":"Building & Trades",
            "subcategory":"Landscaping Services",
            "type":"Services"
        }
    ],
    "sg:phone":"+1 402 462 4414",
    "sg:postcode":"68901",
    "sg:province":"NE",
    "sg:tags":[
        "tree"
    ],
    "wof:name":"Emson Tree Specialists Inc",
    "wof:placetype":"venue"
},
  "geometry": {"coordinates":[-98.383425,40.579574],"type":"Point"}
}