{
  "type": "Feature",
  "properties": {
    "addr:full":"14608 Grover St Omaha NE 68144",
    "addr:housenumber":"14608",
    "addr:postcode":"68144",
    "addr:street":"Grover St",
    "iso:country":"US",
    "sg:address":"14608 Grover St",
    "sg:city":"Omaha",
    "sg:classifiers":[
        {
            "category":"Wholesale",
            "subcategory":"Furniture",
            "type":"Manufacturing & Wholesale Goods"
        },
        {
            "category":"Manufacturing",
            "subcategory":"Furniture",
            "type":"Manufacturing & Wholesale Goods"
        },
        {
            "category":"Home & Garden",
            "subcategory":"Furniture",
            "type":"Retail Goods"
        }
    ],
    "sg:phone":"+1 402 330 5863",
    "sg:postcode":"68144",
    "sg:province":"NE",
    "sg:tags":[
        "designer",
        "builder",
        "furniture-wholesale",
        "custom",
        "store",
        "manufacturer"
    ],
    "wof:name":"Kustom Woods Inc",
    "wof:placetype":"venue"
},
  "geometry": {"coordinates":[-96.140248,41.224267],"type":"Point"}
}