{
  "type": "Feature",
  "properties": {
    "addr:full":"2431 Fairfield St Lincoln NE 68521",
    "addr:housenumber":"2431",
    "addr:postcode":"68521",
    "addr:street":"Fairfield St",
    "iso:country":"US",
    "sg:address":"2431 Fairfield St",
    "sg:city":"Lincoln",
    "sg:classifiers":[
        {
            "category":"Wholesale",
            "subcategory":"Hardware",
            "type":"Manufacturing & Wholesale Goods"
        },
        {
            "category":"Wholesale",
            "subcategory":"Electrical",
            "type":"Manufacturing & Wholesale Goods"
        }
    ],
    "sg:phone":"+1 402 476 4646",
    "sg:postcode":"68521",
    "sg:province":"NE",
    "sg:tags":[
        "extinguisher",
        "fire",
        "alarm",
        "system",
        "beverage",
        "dispensing",
        "retail"
    ],
    "sg:website":"www.general-fire.com",
    "wof:name":"A B Nebelsick Co",
    "wof:placetype":"venue"
},
  "geometry": {"coordinates":[-96.69041900000001,40.847634],"type":"Point"}
}