{
  "type": "Feature",
  "properties": {
    "iso:country":"US",
    "sg:address":"919 Galvin Rd S",
    "sg:city":"Bellevue",
    "sg:classifiers":[
        {
            "category":"Professional",
            "subcategory":"Computer Services",
            "type":"Services"
        }
    ],
    "sg:phone":"+1 402 293 8868",
    "sg:postcode":"68005",
    "sg:province":"NE",
    "sg:tags":[
        "internet"
    ],
    "wof:name":"Bellevue Data Communications",
    "wof:placetype":"venue"
},
  "geometry": {"coordinates":[-95.91794899999999,41.152388],"type":"Point"}
}