{
  "type": "Feature",
  "properties": {
    "iso:country":"US",
    "sg:address":"317 Main St",
    "sg:city":"Chadron",
    "sg:classifiers":[
        {
            "category":"Real Estate",
            "subcategory":"Real Estate Agent",
            "type":"Services"
        }
    ],
    "sg:phone":"+1 308 432 5555",
    "sg:postcode":"69337",
    "sg:province":"NE",
    "wof:name":"Daniels Agency",
    "wof:placetype":"venue"
},
  "geometry": {"coordinates":[-103.000901,42.828058],"type":"Point"}
}