{
  "type": "Feature",
  "properties": {
    "iso:country":"US",
    "sg:address":"823 Dimery Ave",
    "sg:city":"Beaver Crossing",
    "sg:classifiers":[
        {
            "category":"Government",
            "subcategory":"Post Office",
            "type":"Public Place"
        }
    ],
    "sg:phone":"+1 402 532 2135",
    "sg:postcode":"68313",
    "sg:province":"NE",
    "wof:name":"US Post Office",
    "wof:placetype":"venue"
},
  "geometry": {"coordinates":[-97.281183,40.778361],"type":"Point"}
}