{
  "type": "Feature",
  "properties": {
    "iso:country":"US",
    "sg:address":"201 Stagecoach Trl",
    "sg:city":"Ogallala",
    "sg:classifiers":[
        {
            "category":"Travel",
            "subcategory":"Hotels & Motels",
            "type":"Entertainment"
        }
    ],
    "sg:phone":"+1 308 284 3656",
    "sg:postcode":"69153",
    "sg:province":"NE",
    "wof:name":"Best Western Inn",
    "wof:placetype":"venue"
},
  "geometry": {"coordinates":[-101.71363100000001,41.117159],"type":"Point"}
}