{
  "type": "Feature",
  "properties": {
    "iso:country":"US",
    "sg:address":"9303 Ida St",
    "sg:city":"Omaha",
    "sg:classifiers":[
        {
            "category":"Autos & Motor Vehicles",
            "subcategory":"Fuel & Gas Station",
            "type":"Retail Goods"
        }
    ],
    "sg:phone":"+1 402 571 6740",
    "sg:postcode":"68122",
    "sg:province":"NE",
    "sg:tags":[
        "plaza",
        "truck",
        "stops"
    ],
    "sg:website":"www.sappbrosts.com",
    "wof:name":"Sapp Bros Truck Stops",
    "wof:placetype":"venue"
},
  "geometry": {"coordinates":[-96.063198,41.320918],"type":"Point"}
}