{
  "type": "Feature",
  "properties": {
    "iso:country":"US",
    "sg:address":"224 N Main St",
    "sg:city":"Valentine",
    "sg:classifiers":[
        {
            "category":"Shopping",
            "subcategory":"Used Merchandise",
            "type":"Retail Goods"
        }
    ],
    "sg:phone":"+1 402 376 1606",
    "sg:postcode":"69201",
    "sg:province":"NE",
    "sg:tags":[
        "antique"
    ],
    "wof:name":"Upland Trade Co",
    "wof:placetype":"venue"
},
  "geometry": {"coordinates":[-100.550586,42.874241],"type":"Point"}
}