{
  "type": "Feature",
  "properties": {
    "iso:country":"US",
    "sg:address":"3615 Woolworth Ave",
    "sg:city":"Omaha",
    "sg:classifiers":[
        {
            "category":"Recreation",
            "type":"Entertainment"
        }
    ],
    "sg:phone":"+1 402 345 6343",
    "sg:postcode":"68105",
    "sg:province":"NE",
    "sg:tags":[
        "course",
        "golf"
    ],
    "wof:name":"Field Club Of Omaha Inc",
    "wof:placetype":"venue"
},
  "geometry": {"coordinates":[-95.966887,41.245141],"type":"Point"}
}