{
  "type": "Feature",
  "properties": {
    "iso:country":"US",
    "sg:address":"316 N 5th St",
    "sg:city":"Seward",
    "sg:classifiers":[
        {
            "category":"Real Estate",
            "subcategory":"Real Estate Agent",
            "type":"Services"
        }
    ],
    "sg:phone":"+1 402 643 3300",
    "sg:postcode":"68434",
    "sg:province":"NE",
    "sg:website":"www.homerealestate.com",
    "wof:name":"Home Real Estate",
    "wof:placetype":"venue"
},
  "geometry": {"coordinates":[-97.097835,40.910493],"type":"Point"}
}