{
  "type": "Feature",
  "properties": {
    "iso:country":"US",
    "sg:address":"11606 Nicholas St",
    "sg:city":"Omaha",
    "sg:classifiers":[
        {
            "category":"Real Estate",
            "subcategory":"Developer",
            "type":"Services"
        }
    ],
    "sg:phone":"+1 402 431 0500",
    "sg:postcode":"68154",
    "sg:province":"NE",
    "sg:tags":[
        "development",
        "property",
        "management",
        "commercial"
    ],
    "wof:name":"Essex Corporation",
    "wof:placetype":"venue"
},
  "geometry": {"coordinates":[-96.09571099999999,41.269655],"type":"Point"}
}