{
  "type": "Feature",
  "properties": {
    "iso:country":"US",
    "sg:address":"11124 V St",
    "sg:city":"Omaha",
    "sg:classifiers":[
        {
            "category":"Building & Trades",
            "subcategory":"Landscaping Services",
            "type":"Services"
        }
    ],
    "sg:phone":"+1 402 331 0487",
    "sg:postcode":"68137",
    "sg:province":"NE",
    "sg:tags":[
        "lawn",
        "maintenance",
        "grounds"
    ],
    "wof:name":"Blue Sky Lawns",
    "wof:placetype":"venue"
},
  "geometry": {"coordinates":[-96.087743,41.201507],"type":"Point"}
}