{
  "type": "Feature",
  "properties": {
    "addr:full":"924 Alba Ave Ravenna NE 68869",
    "addr:housenumber":"924",
    "addr:postcode":"68869",
    "addr:street":"Alba Ave",
    "iso:country":"US",
    "sg:address":"924 Alba Ave",
    "sg:city":"Ravenna",
    "sg:classifiers":[
        {
            "category":"Professional",
            "type":"Services"
        }
    ],
    "sg:phone":"+1 308 452 3218",
    "sg:postcode":"68869",
    "sg:province":"NE",
    "wof:name":"Tkl Inc",
    "wof:placetype":"venue"
},
  "geometry": {"coordinates":[-98.91414,41.032187],"type":"Point"}
}