{
  "type": "Feature",
  "properties": {
    "addr:full":"104 E 11th St Schuyler NE 68661",
    "addr:housenumber":"104",
    "addr:postcode":"68661",
    "addr:street":"E 11Th St",
    "iso:country":"US",
    "sg:address":"104 E 11th St",
    "sg:city":"Schuyler",
    "sg:classifiers":[
        {
            "category":"Insurance",
            "subcategory":"Insurance Agent",
            "type":"Services"
        }
    ],
    "sg:phone":"+1 402 352 2116",
    "sg:postcode":"68661",
    "sg:province":"NE",
    "wof:name":"Neujahr Insurance",
    "wof:placetype":"venue"
},
  "geometry": {"coordinates":[-97.05968300000001,41.447412],"type":"Point"}
}