{
  "type": "Feature",
  "properties": {
    "addr:full":"8901 Andermatt Dr Lincoln NE 68526",
    "addr:housenumber":"8901",
    "addr:postcode":"68526",
    "addr:street":"Andermatt Dr",
    "iso:country":"US",
    "sg:address":"8901 Andermatt Dr",
    "sg:city":"Lincoln",
    "sg:classifiers":[
        {
            "category":"Restaurant",
            "type":"Food & Drink"
        }
    ],
    "sg:menulink":"http://www.allmenus.com/ne/lincoln/129567-subway/menu/",
    "sg:phone":"+1 402 483 4220",
    "sg:postcode":"68526",
    "sg:province":"NE",
    "sg:tags":[
        "american",
        "sandwich"
    ],
    "wof:name":"Subway",
    "wof:placetype":"venue"
},
  "geometry": {"coordinates":[-96.598939,40.733396],"type":"Point"}
}