{
  "type": "Feature",
  "properties": {
    "addr:full":"7110 Jones Cir Omaha NE 68106",
    "addr:housenumber":"7110",
    "addr:postcode":"68106",
    "addr:street":"Jones Cir",
    "iso:country":"US",
    "sg:address":"7110 Jones Cir",
    "sg:city":"Omaha",
    "sg:classifiers":[
        {
            "category":"Real Estate",
            "subcategory":"Real Estate Agent",
            "type":"Services"
        }
    ],
    "sg:phone":"+1 402 393 8811",
    "sg:postcode":"68106",
    "sg:province":"NE",
    "sg:tags":[
        "property",
        "management"
    ],
    "wof:name":"Columbian Villa Apts",
    "wof:placetype":"venue"
},
  "geometry": {"coordinates":[-96.02219100000001,41.25421],"type":"Point"}
}