{
  "type": "Feature",
  "properties": {
    "iso:country":"US",
    "sg:address":"2208 Jackson St",
    "sg:city":"Sidney",
    "sg:classifiers":[
        {
            "category":"Building & Trades",
            "subcategory":"Plumbing",
            "type":"Services"
        }
    ],
    "sg:phone":"+1 308 254 1008",
    "sg:postcode":"69162",
    "sg:province":"NE",
    "sg:tags":[
        "plumbing",
        "contractor"
    ],
    "wof:name":"Day & Night Plumbing & Heating",
    "wof:placetype":"venue"
},
  "geometry": {"coordinates":[-102.992181,41.14346],"type":"Point"}
}