{
  "type": "Feature",
  "properties": {
    "iso:country":"US",
    "sg:address":"206 S 7th St",
    "sg:city":"Wymore",
    "sg:classifiers":[
        {
            "category":"Shopping",
            "subcategory":"Used Merchandise",
            "type":"Retail Goods"
        },
        {
            "category":"Shopping",
            "subcategory":"Gifts & Souvenirs",
            "type":"Retail Goods"
        }
    ],
    "sg:phone":"+1 402 645 3933",
    "sg:postcode":"68466",
    "sg:province":"NE",
    "sg:tags":[
        "antique",
        "durable"
    ],
    "wof:name":"Treasures Yesterday and Today",
    "wof:placetype":"venue"
},
  "geometry": {"coordinates":[-96.661946,40.121254],"type":"Point"}
}