{
  "type": "Feature",
  "properties": {
    "iso:country":"US",
    "sg:address":"312 S Commercial Ave",
    "sg:city":"Superior",
    "sg:classifiers":[
        {
            "category":"Wholesale",
            "subcategory":"Auto Parts",
            "type":"Manufacturing & Wholesale Goods"
        }
    ],
    "sg:phone":"+1 402 879 3211",
    "sg:postcode":"68978",
    "sg:province":"NE",
    "sg:tags":[
        "automobile",
        "supply"
    ],
    "wof:name":"Superior Motor Parts",
    "wof:placetype":"venue"
},
  "geometry": {"coordinates":[-98.069896,40.013204],"type":"Point"}
}