{
  "type": "Feature",
  "properties": {
    "iso:country":"US",
    "sg:address":"225 N 4th St",
    "sg:city":"Hebron",
    "sg:classifiers":[
        {
            "category":"Government",
            "subcategory":"Office",
            "type":"Public Place"
        }
    ],
    "sg:phone":"+1 402 768 6417",
    "sg:postcode":"68370",
    "sg:province":"NE",
    "sg:tags":[
        "county",
        "taxation"
    ],
    "wof:name":"Thayer County Assessor",
    "wof:placetype":"venue"
},
  "geometry": {"coordinates":[-97.59048,40.168726],"type":"Point"}
}