{
  "type": "Feature",
  "properties": {
    "addr:full":"222 S 4th St Albion NE 68620",
    "addr:housenumber":"222",
    "addr:postcode":"68620",
    "addr:street":"S 4Th St",
    "iso:country":"US",
    "sg:address":"222 S 4th St",
    "sg:city":"Albion",
    "sg:classifiers":[
        {
            "category":"Government",
            "subcategory":"Court House",
            "type":"Public Place"
        }
    ],
    "sg:phone":"+1 402 395 6603",
    "sg:postcode":"68620",
    "sg:province":"NE",
    "sg:tags":[
        "county",
        "counsel"
    ],
    "wof:name":"Boone County Attorney",
    "wof:placetype":"venue"
},
  "geometry": {"coordinates":[-98.001232,41.69159],"type":"Point"}
}