{
  "type": "Feature",
  "properties": {
    "iso:country":"US",
    "sg:address":"1750 S 20th St",
    "sg:city":"Lincoln",
    "sg:classifiers":[
        {
            "category":"Health Services",
            "subcategory":"Nursing And Care Facility",
            "type":"Services"
        }
    ],
    "sg:phone":"+1 402 475 6791",
    "sg:postcode":"68502",
    "sg:province":"NE",
    "sg:tags":[
        "home",
        "convalescent"
    ],
    "wof:name":"Milder Manor",
    "wof:placetype":"venue"
},
  "geometry": {"coordinates":[-96.69194899999999,40.793985],"type":"Point"}
}