{
  "type": "Feature",
  "properties": {
    "addr:full":"5405 Roose St Lincoln NE 68506",
    "addr:postcode":"5405;68506",
    "addr:street":"Roose St",
    "iso:country":"US",
    "sg:address":"5405 Roose St",
    "sg:city":"Lincoln",
    "sg:classifiers":[
        {
            "category":"Building & Trades",
            "subcategory":"Construction",
            "type":"Services"
        }
    ],
    "sg:phone":"+1 402 432 2700",
    "sg:postcode":"68506",
    "sg:province":"NE",
    "sg:tags":[
        "residential",
        "general",
        "contractor"
    ],
    "wof:name":"Fuelling Contracting",
    "wof:placetype":"venue"
},
  "geometry": {"coordinates":[-96.645642,40.785091],"type":"Point"}
}