{
  "type": "Feature",
  "properties": {
    "iso:country":"US",
    "sg:address":"115 E 27th St",
    "sg:city":"South Sioux City",
    "sg:classifiers":[
        {
            "category":"Retail",
            "subcategory":"Auto Repair",
            "type":"Services"
        }
    ],
    "sg:phone":"+1 402 494 4408",
    "sg:postcode":"68776",
    "sg:province":"NE",
    "sg:tags":[
        "transmission"
    ],
    "wof:name":"Economy Transmission",
    "wof:placetype":"venue"
},
  "geometry": {"coordinates":[-96.413653,42.464508],"type":"Point"}
}