{
  "type": "Feature",
  "properties": {
    "addr:full":"1908 Elm St Omaha NE 68108",
    "addr:housenumber":"1908",
    "addr:postcode":"68108",
    "addr:street":"Elm St",
    "iso:country":"US",
    "sg:address":"1908 Elm St",
    "sg:city":"Omaha",
    "sg:classifiers":[
        {
            "category":"Building & Trades",
            "subcategory":"Locksmith",
            "type":"Services"
        }
    ],
    "sg:phone":"+1 402 881 3830",
    "sg:postcode":"68108",
    "sg:province":"NE",
    "sg:tags":[
        "key"
    ],
    "wof:name":"Aaronson Local Locksmith",
    "wof:placetype":"venue"
},
  "geometry": {"coordinates":[-95.941033,41.233184],"type":"Point"}
}