{
  "type": "Feature",
  "properties": {
    "iso:country":"US",
    "sg:address":"4215 S 43rd St",
    "sg:city":"Lincoln",
    "sg:classifiers":[
        {
            "category":"Social Services",
            "subcategory":"Child Care",
            "type":"Services"
        }
    ],
    "sg:phone":"+1 402 483 0291",
    "sg:postcode":"68506",
    "sg:province":"NE",
    "sg:tags":[
        "day"
    ],
    "wof:name":"Terris Child Care",
    "wof:placetype":"venue"
},
  "geometry": {"coordinates":[-96.66086199999999,40.769936],"type":"Point"}
}