{
  "type": "Feature",
  "properties": {
    "iso:country":"US",
    "sg:address":"1116 Co Rd 20",
    "sg:city":"Hooper",
    "sg:phone":"+1 402 654 3876",
    "sg:postcode":"68031",
    "sg:province":"NE",
    "sg:tags":[
        "farm",
        "corn"
    ],
    "wof:name":"R & M Partnershp",
    "wof:placetype":"venue"
},
  "geometry": {"coordinates":[-96.540716,41.593844],"type":"Point"}
}