{
  "type": "Feature",
  "properties": {
    "addr:full":"155 N Central Ave Superior NE 68978",
    "addr:housenumber":"155",
    "addr:postcode":"68978",
    "addr:street":"N Central Ave",
    "iso:country":"US",
    "sg:address":"155 N Central Ave",
    "sg:city":"Superior",
    "sg:classifiers":[
        {
            "category":"Home & Garden",
            "subcategory":"Building Materials",
            "type":"Retail Goods"
        }
    ],
    "sg:phone":"+1 402 879 3296",
    "sg:postcode":"68978",
    "sg:province":"NE",
    "sg:tags":[
        "lumber"
    ],
    "wof:name":"Valley Building Ctr",
    "wof:placetype":"venue"
},
  "geometry": {"coordinates":[-98.07142899999999,40.016845],"type":"Point"}
}