{
  "type": "Feature",
  "properties": {
    "iso:country":"US",
    "sg:address":"339 N 4th St",
    "sg:city":"Seward",
    "sg:classifiers":[
        {
            "category":"Organizations",
            "subcategory":"Religious Organization",
            "type":"Services"
        }
    ],
    "sg:phone":"+1 402 643 2615",
    "sg:postcode":"68434",
    "sg:province":"NE",
    "wof:name":"United Church Homes",
    "wof:placetype":"venue"
},
  "geometry": {"coordinates":[-97.09677000000001,40.910276],"type":"Point"}
}