{
  "type": "Feature",
  "properties": {
    "addr:full":"621 Penn St Cambridge NE 69022",
    "addr:housenumber":"621",
    "addr:postcode":"69022",
    "addr:street":"Penn St",
    "iso:country":"US",
    "sg:address":"621 Penn St",
    "sg:city":"Cambridge",
    "sg:classifiers":[
        {
            "category":"Education",
            "subcategory":"Library",
            "type":"Public Place"
        }
    ],
    "sg:phone":"+1 308 697 3836",
    "sg:postcode":"69022",
    "sg:province":"NE",
    "wof:name":"Butler Memorial Library",
    "wof:placetype":"venue"
},
  "geometry": {"coordinates":[-100.167529,40.282808],"type":"Point"}
}