{
  "type": "Feature",
  "properties": {
    "iso:country":"US",
    "sg:address":"305 W Klein St",
    "sg:city":"Shickley",
    "sg:classifiers":[
        {
            "category":"Farming",
            "subcategory":"Farm",
            "type":"Manufacturing & Wholesale Goods"
        }
    ],
    "sg:phone":"+1 402 627 2305",
    "sg:postcode":"68436",
    "sg:province":"NE",
    "sg:tags":[
        "crop",
        "general"
    ],
    "wof:name":"Roger Gerger",
    "wof:placetype":"venue"
},
  "geometry": {"coordinates":[-97.72856400000001,40.41433],"type":"Point"}
}