{
  "type": "Feature",
  "properties": {
    "iso:country":"US",
    "sg:address":"110 N Main St",
    "sg:city":"Hooper",
    "sg:classifiers":[
        {
            "category":"Bars & Pubs",
            "type":"Food & Drink"
        }
    ],
    "sg:phone":"+1 402 654 3824",
    "sg:postcode":"68031",
    "sg:province":"NE",
    "wof:name":"Sodbuster Saloon",
    "wof:placetype":"venue"
},
  "geometry": {"coordinates":[-96.547685,41.611706],"type":"Point"}
}