{
  "type": "Feature",
  "properties": {
    "iso:country":"US",
    "sg:address":"319 S 17th St Ste 220",
    "sg:city":"Omaha",
    "sg:classifiers":[
        {
            "category":"Professional",
            "subcategory":"Accounting & Tax Preparation",
            "type":"Services"
        }
    ],
    "sg:phone":"+1 402 422 0820",
    "sg:postcode":"68102",
    "sg:province":"NE",
    "sg:tags":[
        "accountant"
    ],
    "wof:name":"Kirchner Robert L & Associates Inc",
    "wof:placetype":"venue"
},
  "geometry": {"coordinates":[-95.9384,41.257301],"type":"Point"}
}