{
  "type": "Feature",
  "properties": {
    "iso:country":"US",
    "sg:address":"5602 S 22nd St",
    "sg:city":"Omaha",
    "sg:classifiers":[
        {
            "category":"Education",
            "subcategory":"School",
            "type":"Public Place"
        }
    ],
    "sg:phone":"+1 402 734 4504",
    "sg:postcode":"68107",
    "sg:province":"NE",
    "wof:name":"Assumption Church School",
    "wof:placetype":"venue"
},
  "geometry": {"coordinates":[-95.944371,41.200194],"type":"Point"}
}