{
  "type": "Feature",
  "properties": {
    "iso:country":"US",
    "sg:address":"2300 2nd Ave",
    "sg:city":"Nebraska City",
    "sg:classifiers":[
        {
            "category":"Recreation",
            "type":"Entertainment"
        }
    ],
    "sg:phone":"+1 402 873 7222",
    "sg:postcode":"68410",
    "sg:province":"NE",
    "sg:tags":[
        "parks"
    ],
    "wof:name":"Arbor Lodge State Park",
    "wof:placetype":"venue"
},
  "geometry": {"coordinates":[-95.87384900000001,40.678737],"type":"Point"}
}