{
  "type": "Feature",
  "properties": {
    "iso:country":"US",
    "sg:address":"4103 Leavenworth St",
    "sg:city":"Omaha",
    "sg:classifiers":[
        {
            "category":"Autos & Motor Vehicles",
            "subcategory":"Automobile Sales",
            "type":"Retail Goods"
        }
    ],
    "sg:phone":"+1 402 933 4005",
    "sg:postcode":"68105",
    "sg:province":"NE",
    "sg:tags":[
        "car",
        "dealer"
    ],
    "wof:name":"Incentive Auto Sales",
    "wof:placetype":"venue"
},
  "geometry": {"coordinates":[-95.975762,41.252329],"type":"Point"}
}