{
  "type": "Feature",
  "properties": {
    "iso:country":"US",
    "sg:address":"3016 S 130th Rd",
    "sg:city":"Wood River",
    "sg:phone":"+1 308 583 2853",
    "sg:postcode":"68883",
    "sg:province":"NE",
    "sg:tags":[
        "farm",
        "corn",
        "soybean"
    ],
    "wof:name":"James Turek",
    "wof:placetype":"venue"
},
  "geometry": {"coordinates":[-98.588739,40.891774],"type":"Point"}
}