{
  "type": "Feature",
  "properties": {
    "addr:full":"1008 S Burlington Ave Hastings NE 68901",
    "addr:housenumber":"1008",
    "addr:postcode":"68901",
    "addr:street":"S Burlington Ave",
    "iso:country":"US",
    "sg:address":"1008 S Burlington Ave",
    "sg:city":"Hastings",
    "sg:classifiers":[
        {
            "category":"Restaurant",
            "type":"Food & Drink"
        }
    ],
    "sg:phone":"+1 402 463 4543",
    "sg:postcode":"68901",
    "sg:province":"NE",
    "sg:tags":[
        "eating",
        "pizza"
    ],
    "wof:name":"Godfather's Pizza",
    "wof:placetype":"venue"
},
  "geometry": {"coordinates":[-98.39259199999999,40.569773],"type":"Point"}
}