{
  "type": "Feature",
  "properties": {
    "addr:full":"1622 F St Schuyler NE 68661",
    "addr:housenumber":"1622",
    "addr:postcode":"68661",
    "addr:street":"F St",
    "iso:country":"US",
    "sg:address":"1622 F St",
    "sg:city":"Schuyler",
    "sg:classifiers":[
        {
            "category":"Retail",
            "subcategory":"Funeral Services",
            "type":"Services"
        }
    ],
    "sg:phone":"+1 402 352 8700",
    "sg:postcode":"68661",
    "sg:province":"NE",
    "sg:tags":[
        "director"
    ],
    "wof:name":"Kracl Funeral Chapel Inc",
    "wof:placetype":"venue"
},
  "geometry": {"coordinates":[-97.052099,41.454106],"type":"Point"}
}