{
  "type": "Feature",
  "properties": {
    "iso:country":"US",
    "sg:address":"160076 Experiment Farm Rd",
    "sg:city":"Mitchell",
    "sg:phone":"+1 308 623 2814",
    "sg:postcode":"69357",
    "sg:province":"NE",
    "sg:tags":[
        "farm",
        "corn"
    ],
    "wof:name":"Ruth Grentz",
    "wof:placetype":"venue"
},
  "geometry": {"coordinates":[-103.770746,41.943199],"type":"Point"}
}