{
  "type": "Feature",
  "properties": {
    "iso:country":"US",
    "sg:address":"109 E 9th St",
    "sg:city":"Wood River",
    "sg:classifiers":[
        {
            "category":"Personal",
            "subcategory":"Beauty Salon",
            "type":"Services"
        }
    ],
    "sg:phone":"+1 308 583 2842",
    "sg:postcode":"68883",
    "sg:province":"NE",
    "wof:name":"Country Stylers",
    "wof:placetype":"venue"
},
  "geometry": {"coordinates":[-98.601569,40.820519],"type":"Point"}
}