{
  "type": "Feature",
  "properties": {
    "iso:country":"US",
    "sg:address":"2706 S 148th Avenue Cir",
    "sg:city":"Omaha",
    "sg:classifiers":[
        {
            "category":"Retail",
            "subcategory":"Veterinary Services",
            "type":"Services"
        }
    ],
    "sg:phone":"+1 402 334 0200",
    "sg:postcode":"68144",
    "sg:province":"NE",
    "sg:tags":[
        "veterinarian"
    ],
    "wof:name":"Animal Eye Clinic",
    "wof:placetype":"venue"
},
  "geometry": {"coordinates":[-96.147564,41.233947],"type":"Point"}
}