{
  "type": "Feature",
  "properties": {
    "iso:country":"US",
    "sg:address":"1309 S 3rd St",
    "sg:city":"Norfolk",
    "sg:classifiers":[
        {
            "category":"Professional",
            "type":"Services"
        }
    ],
    "sg:phone":"+1 402 371 7033",
    "sg:postcode":"68701",
    "sg:province":"NE",
    "wof:name":"Services Northstar",
    "wof:placetype":"venue"
},
  "geometry": {"coordinates":[-97.409717,42.018107],"type":"Point"}
}