{
  "type": "Feature",
  "properties": {
    "iso:country":"US",
    "sg:address":"620 E 6th St",
    "sg:city":"York",
    "sg:classifiers":[
        {
            "category":"Organizations",
            "subcategory":"Labor Organization",
            "type":"Services"
        }
    ],
    "sg:phone":"+1 402 362 6874",
    "sg:postcode":"68467",
    "sg:province":"NE",
    "wof:name":"Nebraska Frfightersbelt Buckle",
    "wof:placetype":"venue"
},
  "geometry": {"coordinates":[-97.58688600000001,40.866849],"type":"Point"}
}