{
  "type": "Feature",
  "properties": {
    "addr:full":"715 N Beadle St Papillion NE 68046",
    "addr:housenumber":"715",
    "addr:postcode":"68046",
    "addr:street":"N Beadle St",
    "iso:country":"US",
    "sg:address":"715 N Beadle St",
    "sg:city":"Papillion",
    "sg:classifiers":[
        {
            "category":"Home & Garden",
            "subcategory":"Carpets & Floor Coverings",
            "type":"Retail Goods"
        }
    ],
    "sg:phone":"+1 402 339 9429",
    "sg:postcode":"68046",
    "sg:province":"NE",
    "wof:name":"Sams Carpet",
    "wof:placetype":"venue"
},
  "geometry": {"coordinates":[-96.038025,41.164929],"type":"Point"}
}