{
  "type": "Feature",
  "properties": {
    "iso:country":"US",
    "sg:address":"11259 John Galt Blvd",
    "sg:city":"Omaha",
    "sg:classifiers":[
        {
            "category":"Wholesale",
            "subcategory":"Home Furnishings",
            "type":"Manufacturing & Wholesale Goods"
        }
    ],
    "sg:phone":"+1 402 597 3161",
    "sg:postcode":"68137",
    "sg:province":"NE",
    "sg:tags":[
        "floor",
        "covering"
    ],
    "wof:name":"Floor Fashions Inc",
    "wof:placetype":"venue"
},
  "geometry": {"coordinates":[-96.087642,41.208622],"type":"Point"}
}