{
  "type": "Feature",
  "properties": {
    "iso:country":"US",
    "sg:address":"3250 S Adams Central Ave",
    "sg:city":"Hastings",
    "sg:classifiers":[
        {
            "category":"Real Estate",
            "subcategory":"Real Estate Operator",
            "type":"Services"
        }
    ],
    "sg:phone":"+1 402 462 8249",
    "sg:postcode":"68901",
    "sg:province":"NE",
    "sg:tags":[
        "farm",
        "property",
        "crop",
        "lessor",
        "general"
    ],
    "wof:name":"KG Farms Partnership",
    "wof:placetype":"venue"
},
  "geometry": {"coordinates":[-98.45894199999999,40.543144],"type":"Point"}
}