{
  "type": "Feature",
  "properties": {
    "addr:full":"14810 Grover St Omaha NE 68144",
    "addr:housenumber":"14810",
    "addr:postcode":"68144",
    "addr:street":"Grover St",
    "iso:country":"US",
    "sg:address":"14810 Grover St",
    "sg:city":"Omaha",
    "sg:classifiers":[
        {
            "category":"Autos & Motor Vehicles",
            "subcategory":"Auto Supplies",
            "type":"Retail Goods"
        },
        {
            "category":"Retail",
            "subcategory":"Auto Repair",
            "type":"Services"
        }
    ],
    "sg:phone":"+1 402 884 2104",
    "sg:postcode":"68144",
    "sg:province":"NE",
    "sg:tags":[
        "automobile",
        "part",
        "truck"
    ],
    "sg:website":"http://clickserve.dartsearch.net/link/click?lid=43000000313868808&ds_s_kwgid=58000000006820725&ds_e_matchtype={MatchType}&ds_e_kwdid={OrderItemId}&ds_e_adid={AdId}&ds_url_v=2",
    "wof:name":"Powers Automotive Service Inc.",
    "wof:placetype":"venue"
},
  "geometry": {"coordinates":[-96.14229899999999,41.225131],"type":"Point"}
}