{
  "type": "Feature",
  "properties": {
    "iso:country":"US",
    "sg:address":"301 Industrial Row",
    "sg:city":"Beatrice",
    "sg:classifiers":[
        {
            "category":"Retail",
            "subcategory":"Auto Repair",
            "type":"Services"
        }
    ],
    "sg:phone":"+1 402 228 1300",
    "sg:postcode":"68310",
    "sg:province":"NE",
    "sg:tags":[
        "general"
    ],
    "wof:name":"Schoneweis Truck Repair",
    "wof:placetype":"venue"
},
  "geometry": {"coordinates":[-96.759193,40.289273],"type":"Point"}
}