{
  "type": "Feature",
  "properties": {
    "iso:country":"US",
    "sg:address":"508 Broad St",
    "sg:city":"Dalton",
    "sg:classifiers":[
        {
            "category":"Personal",
            "subcategory":"Beauty Salon",
            "type":"Services"
        }
    ],
    "sg:phone":"+1 308 377 2213",
    "sg:postcode":"69131",
    "sg:province":"NE",
    "sg:tags":[
        "shop"
    ],
    "wof:name":"B J's Stop & Style",
    "wof:placetype":"venue"
},
  "geometry": {"coordinates":[-102.97428499999999,41.407056],"type":"Point"}
}