{
  "type": "Feature",
  "properties": {
    "addr:full":"1520 S 70th St Lincoln NE 68506",
    "addr:housenumber":"1520",
    "addr:postcode":"68506",
    "addr:street":"S 70Th St",
    "iso:country":"US",
    "sg:address":"1520 S 70th St",
    "sg:city":"Lincoln",
    "sg:classifiers":[
        {
            "category":"Insurance",
            "subcategory":"Insurance Agent",
            "type":"Services"
        }
    ],
    "sg:phone":"+1 402 483 5005",
    "sg:postcode":"68506",
    "sg:province":"NE",
    "sg:website":"www.nfuic.com",
    "wof:name":"Farmers Union Insurance",
    "wof:placetype":"venue"
},
  "geometry": {"coordinates":[-96.62521599999999,40.793474],"type":"Point"}
}