{
  "type": "Feature",
  "properties": {
    "addr:full":"733 Rosedale Dr Scottsbluff NE 69361",
    "addr:housenumber":"733",
    "addr:postcode":"69361",
    "addr:street":"Rosedale Dr",
    "iso:country":"US",
    "sg:address":"733 Rosedale Dr",
    "sg:city":"Scottsbluff",
    "sg:classifiers":[
        {
            "category":"Health Services",
            "subcategory":"Doctor",
            "type":"Services"
        }
    ],
    "sg:phone":"+1 308 632 2493",
    "sg:postcode":"69361",
    "sg:province":"NE",
    "sg:tags":[
        "anesthetist"
    ],
    "wof:name":"Wyo-Braska Anesthesia",
    "wof:placetype":"venue"
},
  "geometry": {"coordinates":[-103.653701,41.879569],"type":"Point"}
}