{
  "type": "Feature",
  "properties": {
    "addr:full":"1539 20th Ave Sidney NE 69162",
    "addr:housenumber":"1539",
    "addr:postcode":"69162",
    "addr:street":"20Th Ave",
    "iso:country":"US",
    "sg:address":"1539 20th Ave",
    "sg:city":"Sidney",
    "sg:classifiers":[
        {
            "category":"Real Estate",
            "subcategory":"Real Estate Operator",
            "type":"Services"
        }
    ],
    "sg:phone":"+1 308 254 9104",
    "sg:postcode":"69162",
    "sg:province":"NE",
    "sg:tags":[
        "apartment"
    ],
    "wof:name":"Fort Sidney Apartments",
    "wof:placetype":"venue"
},
  "geometry": {"coordinates":[-102.98883499999999,41.138045],"type":"Point"}
}