{
  "type": "Feature",
  "properties": {
    "iso:country":"US",
    "sg:address":"1420 S Locust St",
    "sg:city":"Grand Island",
    "sg:classifiers":[
        {
            "category":"Food & Beverages",
            "subcategory":"Groceries & Convenience Stores",
            "type":"Retail Goods"
        }
    ],
    "sg:phone":"+1 308 381 7815",
    "sg:postcode":"68801",
    "sg:province":"NE",
    "wof:name":"Holiday Station Store",
    "wof:placetype":"venue"
},
  "geometry": {"coordinates":[-98.33985800000001,40.90727],"type":"Point"}
}