{
  "type": "Feature",
  "properties": {
    "addr:full":"808 E Eldora Ave Weeping Water NE 68463",
    "addr:housenumber":"808",
    "addr:postcode":"68463",
    "addr:street":"E Eldora Ave",
    "iso:country":"US",
    "sg:address":"808 E Eldora Ave",
    "sg:city":"Weeping Water",
    "sg:phone":"+1 402 267 7012",
    "sg:postcode":"68463",
    "sg:province":"NE",
    "sg:tags":[
        "farm",
        "grain",
        "cash"
    ],
    "wof:name":"Dietl Farms Inc",
    "wof:placetype":"venue"
},
  "geometry": {"coordinates":[-96.130799,40.869138],"type":"Point"}
}