{
  "type": "Feature",
  "properties": {
    "iso:country":"US",
    "sg:address":"953 Eagle Rd",
    "sg:city":"Saint Paul",
    "sg:phone":"+1 308 754 4163",
    "sg:postcode":"68873",
    "sg:province":"NE",
    "sg:tags":[
        "farm",
        "field",
        "crop"
    ],
    "wof:name":"Consolidated Blenders",
    "wof:placetype":"venue"
},
  "geometry": {"coordinates":[-98.383157,41.181523],"type":"Point"}
}