{
  "type": "Feature",
  "properties": {
    "addr:full":"5008 Dodge St Omaha NE 68132",
    "addr:housenumber":"5008",
    "addr:postcode":"68132",
    "addr:street":"Dodge St",
    "iso:country":"US",
    "sg:address":"5008 Dodge St",
    "sg:city":"Omaha",
    "sg:classifiers":[
        {
            "category":"Restaurant",
            "type":"Food & Drink"
        }
    ],
    "sg:phone":"+1 402 556 2006",
    "sg:postcode":"68132",
    "sg:province":"NE",
    "sg:tags":[
        "traditional",
        "american"
    ],
    "sg:website":"www.goldbergsindundee.com",
    "wof:name":"Goldbergs II",
    "wof:placetype":"venue"
},
  "geometry": {"coordinates":[-95.990972,41.259825],"type":"Point"}
}