{
  "type": "Feature",
  "properties": {
    "iso:country":"US",
    "sg:address":"522 Michael Dr",
    "sg:city":"Gretna",
    "sg:classifiers":[
        {
            "category":"Real Estate",
            "subcategory":"Real Estate Agent",
            "type":"Services"
        }
    ],
    "sg:phone":"+1 402 332 3830",
    "sg:postcode":"68028",
    "sg:province":"NE",
    "wof:name":"Camelot Realty Inc",
    "wof:placetype":"venue"
},
  "geometry": {"coordinates":[-96.244274,41.143901],"type":"Point"}
}