{
  "type": "Feature",
  "properties": {
    "addr:full":"408 E 1st St Kimball NE 69145",
    "addr:housenumber":"408",
    "addr:postcode":"69145",
    "addr:street":"E 1St St",
    "iso:country":"US",
    "sg:address":"408 E 1st St",
    "sg:city":"Kimball",
    "sg:classifiers":[
        {
            "category":"Retail",
            "subcategory":"Auto Repair",
            "type":"Services"
        }
    ],
    "sg:phone":"+1 308 235 4268",
    "sg:postcode":"69145",
    "sg:province":"NE",
    "sg:tags":[
        "body",
        "automobile",
        "painting"
    ],
    "wof:name":"Dale's Apint & Body Shop",
    "wof:placetype":"venue"
},
  "geometry": {"coordinates":[-103.65874599999999,41.238152],"type":"Point"}
}