{
  "type": "Feature",
  "properties": {
    "iso:country":"US",
    "sg:address":"1020 W 6th St",
    "sg:city":"North Bend",
    "sg:classifiers":[
        {
            "category":"Autos & Motor Vehicles",
            "subcategory":"Recreational Vehicle Sales",
            "type":"Retail Goods"
        }
    ],
    "sg:phone":"+1 402 652 3231",
    "sg:postcode":"68649",
    "sg:province":"NE",
    "sg:tags":[
        "canopy",
        "shell",
        "truck",
        "cap"
    ],
    "wof:name":"Weldon Truck Parts",
    "wof:placetype":"venue"
},
  "geometry": {"coordinates":[-96.789205,41.46167],"type":"Point"}
}