{
  "type": "Feature",
  "properties": {
    "addr:full":"858 Co Rd 16 Wahoo NE 68066",
    "addr:housenumber":"858;16",
    "addr:postcode":"68066",
    "addr:street":"Co Rd",
    "iso:country":"US",
    "sg:address":"858 Co Rd 16",
    "sg:city":"Wahoo",
    "sg:phone":"+1 402 443 5348",
    "sg:postcode":"68066",
    "sg:province":"NE",
    "sg:tags":[
        "farm",
        "corn",
        "soybean"
    ],
    "wof:name":"Charles Malm",
    "wof:placetype":"venue"
},
  "geometry": {"coordinates":[-96.601601,41.131061],"type":"Point"}
}