{
  "type": "Feature",
  "properties": {
    "addr:full":"1011 Grand Ave Ravenna NE 68869",
    "addr:housenumber":"1011",
    "addr:postcode":"68869",
    "addr:street":"Grand Ave",
    "iso:country":"US",
    "sg:address":"1011 Grand Ave",
    "sg:city":"Ravenna",
    "sg:classifiers":[
        {
            "category":"Real Estate",
            "subcategory":"Real Estate Agent",
            "type":"Services"
        }
    ],
    "sg:phone":"+1 308 452 4233",
    "sg:postcode":"68869",
    "sg:province":"NE",
    "wof:name":"Grand Manor",
    "wof:placetype":"venue"
},
  "geometry": {"coordinates":[-98.91251,41.03453],"type":"Point"}
}