{
  "type": "Feature",
  "properties": {
    "iso:country":"US",
    "sg:address":"11196 S Lakeshore Dr",
    "sg:city":"Blair",
    "sg:classifiers":[
        {
            "category":"Building & Trades",
            "subcategory":"Construction",
            "type":"Services"
        }
    ],
    "sg:phone":"+1 402 533 8431",
    "sg:postcode":"68008",
    "sg:province":"NE",
    "sg:tags":[
        "carpentry",
        "contractor"
    ],
    "wof:name":"Buchanan & Son Framing",
    "wof:placetype":"venue"
},
  "geometry": {"coordinates":[-96.12146799999999,41.439656],"type":"Point"}
}