{
  "type": "Feature",
  "properties": {
    "addr:full":"417 N Dewey St North Platte NE 69101",
    "addr:housenumber":"417",
    "addr:postcode":"69101",
    "addr:street":"N Dewey St",
    "iso:country":"US",
    "sg:address":"417 N Dewey St",
    "sg:city":"North Platte",
    "sg:classifiers":[
        {
            "category":"Shopping",
            "subcategory":"Musical Instruments",
            "type":"Retail Goods"
        }
    ],
    "sg:phone":"+1 308 534 8557",
    "sg:postcode":"69101",
    "sg:province":"NE",
    "wof:name":"Educational Musical Svc",
    "wof:placetype":"venue"
},
  "geometry": {"coordinates":[-100.76177199999999,41.137167],"type":"Point"}
}