{
  "type": "Feature",
  "properties": {
    "addr:full":"2520 Ave Q Kearney NE 68847",
    "addr:postcode":"68847",
    "addr:street":"2520 Ave Q",
    "iso:country":"US",
    "sg:address":"2520 Ave Q",
    "sg:city":"Kearney",
    "sg:classifiers":[
        {
            "category":"Retail",
            "subcategory":"Auto Repair",
            "type":"Services"
        }
    ],
    "sg:phone":"+1 308 236 8322",
    "sg:postcode":"68847",
    "sg:province":"NE",
    "sg:tags":[
        "repairing",
        "automobile"
    ],
    "wof:name":"Kearney Auto Repair",
    "wof:placetype":"venue"
},
  "geometry": {"coordinates":[-99.061238,40.700248],"type":"Point"}
}