{
  "type": "Feature",
  "properties": {
    "iso:country":"US",
    "sg:address":"505 D St",
    "sg:city":"Fairmont",
    "sg:classifiers":[
        {
            "category":"Personal",
            "subcategory":"Beauty Salon",
            "type":"Services"
        }
    ],
    "sg:phone":"+1 402 268 3176",
    "sg:postcode":"68354",
    "sg:province":"NE",
    "wof:name":"Hair Tracks",
    "wof:placetype":"venue"
},
  "geometry": {"coordinates":[-97.586038,40.636906],"type":"Point"}
}