{
  "type": "Feature",
  "properties": {
    "addr:full":"800 Village Sq Gretna NE 68028",
    "addr:housenumber":"800",
    "addr:postcode":"68028",
    "addr:street":"Village Sq;Ne",
    "iso:country":"US",
    "sg:address":"800 Village Sq",
    "sg:city":"Gretna",
    "sg:classifiers":[
        {
            "category":"Banks & Credit Unions",
            "subcategory":"Investment Brokerage",
            "type":"Services"
        }
    ],
    "sg:phone":"+1 402 332 4160",
    "sg:postcode":"68028",
    "sg:province":"NE",
    "sg:tags":[
        "stock",
        "bond"
    ],
    "wof:name":"Edward Jones Co",
    "wof:placetype":"venue"
},
  "geometry": {"coordinates":[-96.23956,41.145812],"type":"Point"}
}