{
  "type": "Feature",
  "properties": {
    "addr:full":"50775 SW 131st Rd Odell NE 68415",
    "addr:housenumber":"50775",
    "addr:postcode":"68415",
    "addr:street":"Sw 131St Rd",
    "iso:country":"US",
    "sg:address":"50775 SW 131st Rd",
    "sg:city":"Odell",
    "sg:classifiers":[
        {
            "category":"Food & Beverages",
            "subcategory":"Fruits & Vegetables",
            "type":"Retail Goods"
        }
    ],
    "sg:phone":"+1 402 766 3873",
    "sg:postcode":"68415",
    "sg:province":"NE",
    "sg:tags":[
        "produce"
    ],
    "wof:name":"Lottman's Fruity Hill",
    "wof:placetype":"venue"
},
  "geometry": {"coordinates":[-96.897516,40.006102],"type":"Point"}
}