{
  "type": "Feature",
  "properties": {
    "iso:country":"US",
    "sg:address":"312 N Elm St",
    "sg:city":"Grand Island",
    "sg:classifiers":[
        {
            "category":"Health Services",
            "subcategory":"Clinic",
            "type":"Services"
        }
    ],
    "sg:phone":"+1 308 398 1128",
    "sg:postcode":"68801",
    "sg:province":"NE",
    "sg:tags":[
        "home"
    ],
    "wof:name":"Heartland Home Care",
    "wof:placetype":"venue"
},
  "geometry": {"coordinates":[-98.34567300000001,40.923666],"type":"Point"}
}