{
  "type": "Feature",
  "properties": {
    "iso:country":"US",
    "sg:address":"2535 del Monte Ave",
    "sg:city":"Grand Island",
    "sg:classifiers":[
        {
            "category":"Building & Trades",
            "subcategory":"Construction",
            "type":"Services"
        }
    ],
    "sg:phone":"+1 308 383 1179",
    "sg:postcode":"68803",
    "sg:province":"NE",
    "sg:tags":[
        "handyman"
    ],
    "wof:name":"Dr Fix It Handyman Svc",
    "wof:placetype":"venue"
},
  "geometry": {"coordinates":[-98.36236700000001,40.903581],"type":"Point"}
}