{
  "type": "Feature",
  "properties": {
    "addr:full":"706 7th St St Paul NE 68873",
    "addr:housenumber":"706",
    "addr:postcode":"68873",
    "addr:street":"7Th St",
    "iso:country":"US",
    "sg:address":"706 7th St",
    "sg:city":"St Paul",
    "sg:classifiers":[
        {
            "category":"Bars & Pubs",
            "type":"Food & Drink"
        }
    ],
    "sg:phone":"+1 308 754 7805",
    "sg:postcode":"68873",
    "sg:province":"NE",
    "wof:name":"Office Bar",
    "wof:placetype":"venue"
},
  "geometry": {"coordinates":[-98.458022,41.21285],"type":"Point"}
}