{
  "type": "Feature",
  "properties": {
    "iso:country":"US",
    "sg:address":"425 5th St",
    "sg:city":"Syracuse",
    "sg:classifiers":[
        {
            "category":"Government",
            "subcategory":"Office",
            "type":"Public Place"
        }
    ],
    "sg:phone":"+1 402 269 2113",
    "sg:postcode":"68446",
    "sg:province":"NE",
    "wof:name":"Otoe County Weed Control Auth",
    "wof:placetype":"venue"
},
  "geometry": {"coordinates":[-96.18411,40.657076],"type":"Point"}
}