{
  "type": "Feature",
  "properties": {
    "iso:country":"US",
    "sg:address":"211 1st Ave",
    "sg:city":"Bayard",
    "sg:classifiers":[
        {
            "category":"Government",
            "subcategory":"Office",
            "type":"Public Place"
        }
    ],
    "sg:phone":"+1 308 586 1929",
    "sg:postcode":"69334",
    "sg:province":"NE",
    "wof:name":"Morrill County Shops",
    "wof:placetype":"venue"
},
  "geometry": {"coordinates":[-103.322828,41.754507],"type":"Point"}
}