{
  "type": "Feature",
  "properties": {
    "iso:country":"US",
    "sg:address":"1111 N 13th St Ste 123",
    "sg:city":"Omaha",
    "sg:classifiers":[
        {
            "category":"Building & Trades",
            "subcategory":"Construction",
            "type":"Services"
        },
        {
            "category":"Home & Garden",
            "subcategory":"Furniture",
            "type":"Retail Goods"
        }
    ],
    "sg:phone":"+1 402 577 0711",
    "sg:postcode":"68102",
    "sg:province":"NE",
    "sg:tags":[
        "interior",
        "design",
        "store"
    ],
    "sg:website":"birdhouseinteriors.com",
    "wof:name":"Birdhouse Interior Design/Birdhouse Collectible",
    "wof:placetype":"venue"
},
  "geometry": {"coordinates":[-95.932939,41.271178],"type":"Point"}
}