{
  "type": "Feature",
  "properties": {
    "iso:country":"US",
    "sg:address":"336 N Nebraska Ave",
    "sg:city":"Minden",
    "sg:classifiers":[
        {
            "category":"Retail",
            "subcategory":"Funeral Services",
            "type":"Services"
        }
    ],
    "sg:phone":"+1 308 832 2020",
    "sg:postcode":"68959",
    "sg:province":"NE",
    "sg:tags":[
        "director",
        "home"
    ],
    "wof:name":"Layton Funeral Home Inc",
    "wof:placetype":"venue"
},
  "geometry": {"coordinates":[-98.950368,40.498149],"type":"Point"}
}