{
  "type": "Feature",
  "properties": {
    "iso:country":"US",
    "sg:address":"8300 Wendell Way",
    "sg:city":"Lincoln",
    "sg:classifiers":[
        {
            "category":"Home & Garden",
            "subcategory":"Garden Supply",
            "type":"Retail Goods"
        }
    ],
    "sg:phone":"+1 402 475 5600",
    "sg:postcode":"68516",
    "sg:province":"NE",
    "sg:tags":[
        "sprinkler"
    ],
    "wof:name":"Darling Sprinklers Inc",
    "wof:placetype":"venue"
},
  "geometry": {"coordinates":[-96.606112,40.75747],"type":"Point"}
}