{
  "type": "Feature",
  "properties": {
    "iso:country":"US",
    "sg:address":"212 W High St",
    "sg:city":"Cairo",
    "sg:classifiers":[
        {
            "category":"Autos & Motor Vehicles",
            "subcategory":"Automobile Sales",
            "type":"Retail Goods"
        }
    ],
    "sg:phone":"+1 308 485 4271",
    "sg:postcode":"68850",
    "sg:province":"NE",
    "sg:tags":[
        "car",
        "dealer"
    ],
    "wof:name":"J & D Automotive Inc",
    "wof:placetype":"venue"
},
  "geometry": {"coordinates":[-99.744175,40.770834],"type":"Point"}
}