{
  "type": "Feature",
  "properties": {
    "iso:country":"US",
    "sg:address":"812 E 5th St",
    "sg:city":"North Platte",
    "sg:classifiers":[
        {
            "category":"Building & Trades",
            "subcategory":"Cleaning & Sanitation",
            "type":"Services"
        }
    ],
    "sg:phone":"+1 308 532 1470",
    "sg:postcode":"69101",
    "sg:province":"NE",
    "sg:tags":[
        "weather",
        "clean"
    ],
    "wof:name":"Hunt Stacei",
    "wof:placetype":"venue"
},
  "geometry": {"coordinates":[-100.754328,41.136272],"type":"Point"}
}