{
  "type": "Feature",
  "properties": {
    "addr:full":"3409 S 29th St Lincoln NE 68502",
    "addr:housenumber":"3409",
    "addr:postcode":"68502",
    "addr:street":"S 29Th St",
    "iso:country":"US",
    "sg:address":"3409 S 29th St",
    "sg:city":"Lincoln",
    "sg:classifiers":[
        {
            "category":"Banks & Credit Unions",
            "subcategory":"Financial Services",
            "type":"Services"
        }
    ],
    "sg:phone":"+1 402 420 1948",
    "sg:postcode":"68502",
    "sg:province":"NE",
    "sg:tags":[
        "investor"
    ],
    "wof:name":"Central Land Inv LLC A Nebrask",
    "wof:placetype":"venue"
},
  "geometry": {"coordinates":[-96.68016,40.777973],"type":"Point"}
}