{
  "type": "Feature",
  "properties": {
    "iso:country":"US",
    "sg:address":"9374 N St",
    "sg:city":"Omaha",
    "sg:classifiers":[
        {
            "category":"Retail",
            "subcategory":"Auto Repair",
            "type":"Services"
        }
    ],
    "sg:phone":"+1 402 331 2884",
    "sg:postcode":"68127",
    "sg:province":"NE",
    "sg:tags":[
        "body"
    ],
    "wof:name":"Smoliks MBL Apprance Repr Svcs",
    "wof:placetype":"venue"
},
  "geometry": {"coordinates":[-96.05940699999999,41.209261],"type":"Point"}
}