{
  "type": "Feature",
  "properties": {
    "iso:country":"US",
    "sg:address":"1620 Morningside Rd",
    "sg:city":"Fremont",
    "sg:classifiers":[
        {
            "category":"Freight",
            "type":"Transportation"
        }
    ],
    "sg:phone":"+1 402 721 0407",
    "sg:postcode":"68025",
    "sg:province":"NE",
    "sg:tags":[
        "trucking"
    ],
    "wof:name":"Hanson Transfer Inc",
    "wof:placetype":"venue"
},
  "geometry": {"coordinates":[-96.476517,41.422493],"type":"Point"}
}