{
  "type": "Feature",
  "properties": {
    "iso:country":"US",
    "sg:address":"401 Glenn St",
    "sg:city":"Elkhorn",
    "sg:classifiers":[
        {
            "category":"Government",
            "subcategory":"Office",
            "type":"Public Place"
        }
    ],
    "sg:phone":"+1 402 289 2678",
    "sg:postcode":"68022",
    "sg:province":"NE",
    "sg:tags":[
        "city"
    ],
    "wof:name":"Elkhorn City Clerk",
    "wof:placetype":"venue"
},
  "geometry": {"coordinates":[-96.237673,41.284669],"type":"Point"}
}