{
  "type": "Feature",
  "properties": {
    "addr:full":"511 S 5th St Norfolk NE 68701",
    "addr:housenumber":"511",
    "addr:postcode":"68701",
    "addr:street":"S 5Th St",
    "iso:country":"US",
    "sg:address":"511 S 5th St",
    "sg:city":"Norfolk",
    "sg:classifiers":[
        {
            "category":"Education",
            "subcategory":"School",
            "type":"Public Place"
        }
    ],
    "sg:phone":"+1 402 371 5536",
    "sg:postcode":"68701",
    "sg:province":"NE",
    "sg:tags":[
        "religious"
    ],
    "sg:website":"www.christlutherannorfolk.org",
    "wof:name":"Christ Luth Parochial School",
    "wof:placetype":"venue"
},
  "geometry": {"coordinates":[-97.413781,42.027521],"type":"Point"}
}