{
  "type": "Feature",
  "properties": {
    "iso:country":"US",
    "sg:address":"2423 Cornhusker Rd",
    "sg:city":"Bellevue",
    "sg:classifiers":[
        {
            "category":"Education",
            "subcategory":"School",
            "type":"Public Place"
        }
    ],
    "sg:phone":"+1 402 932 4308",
    "sg:postcode":"68133",
    "sg:province":"NE",
    "wof:name":"Aha Press",
    "wof:placetype":"venue"
},
  "geometry": {"coordinates":[-95.94565799999999,41.159238],"type":"Point"}
}