{
  "type": "Feature",
  "properties": {
    "addr:full":"19212 W Aquilla Ln Shelton NE 68876",
    "addr:housenumber":"19212",
    "addr:postcode":"68876",
    "addr:street":"W Aquilla Ln",
    "iso:country":"US",
    "sg:address":"19212 W Aquilla Ln",
    "sg:city":"Shelton",
    "sg:classifiers":[
        {
            "category":"Utilities",
            "subcategory":"Telephone",
            "type":"Services"
        }
    ],
    "sg:phone":"+1 308 647 5751",
    "sg:postcode":"68876",
    "sg:province":"NE",
    "sg:tags":[
        "product",
        "it",
        "related"
    ],
    "wof:name":"CPS Village",
    "wof:placetype":"venue"
},
  "geometry": {"coordinates":[-98.70686600000001,40.791176],"type":"Point"}
}