{
  "type": "Feature",
  "properties": {
    "iso:country":"US",
    "sg:address":"320 Norris Ave",
    "sg:city":"Mc Cook",
    "sg:classifiers":[
        {
            "category":"Professional",
            "subcategory":"Computer Services",
            "type":"Services"
        }
    ],
    "sg:phone":"+1 308 344 8884",
    "sg:postcode":"69001",
    "sg:province":"NE",
    "sg:tags":[
        "repair"
    ],
    "wof:name":"Professional Computer Svc",
    "wof:placetype":"venue"
},
  "geometry": {"coordinates":[-100.62590400000001,40.200437],"type":"Point"}
}