{
  "type": "Feature",
  "properties": {
    "iso:country":"US",
    "sg:address":"6030 Village Dr",
    "sg:city":"Lincoln",
    "sg:classifiers":[
        {
            "category":"Health Services",
            "subcategory":"Doctor",
            "type":"Services"
        }
    ],
    "sg:phone":"+1 402 421 6661",
    "sg:postcode":"68516",
    "sg:province":"NE",
    "sg:tags":[
        "dentist"
    ],
    "wof:name":"Dennis B Claridge DDS",
    "wof:placetype":"venue"
},
  "geometry": {"coordinates":[-96.66457800000001,40.751244],"type":"Point"}
}