{
  "type": "Feature",
  "properties": {
    "addr:full":"2801 33rd Ave Columbus NE 68601",
    "addr:housenumber":"2801",
    "addr:postcode":"68601",
    "addr:street":"33Rd Ave",
    "iso:country":"US",
    "sg:address":"2801 33rd Ave",
    "sg:city":"Columbus",
    "sg:classifiers":[
        {
            "category":"Home & Garden",
            "subcategory":"Building Materials",
            "type":"Retail Goods"
        }
    ],
    "sg:phone":"+1 402 562 8801",
    "sg:postcode":"68601",
    "sg:province":"NE",
    "sg:tags":[
        "glass",
        "window",
        "plate"
    ],
    "wof:name":"Nebraskaland Glass",
    "wof:placetype":"venue"
},
  "geometry": {"coordinates":[-97.368223,41.444652],"type":"Point"}
}