{
  "type": "Feature",
  "properties": {
    "addr:full":"1103 Galvin Rd S Bellevue NE 68005",
    "addr:housenumber":"1103",
    "addr:postcode":"68005",
    "addr:street":"Galvin Rd S",
    "iso:country":"US",
    "sg:address":"1103 Galvin Rd S",
    "sg:city":"Bellevue",
    "sg:classifiers":[
        {
            "category":"Health Services",
            "subcategory":"Health Practitioner",
            "type":"Services"
        }
    ],
    "sg:phone":"+1 402 292 3642",
    "sg:postcode":"68005",
    "sg:province":"NE",
    "sg:tags":[
        "physician",
        "assistant"
    ],
    "wof:name":"Sue Shade",
    "wof:placetype":"venue"
},
  "geometry": {"coordinates":[-95.916259,41.149538],"type":"Point"}
}