{
  "type": "Feature",
  "properties": {
    "iso:country":"US",
    "sg:address":"1811 W 2nd St",
    "sg:city":"Grand Island",
    "sg:classifiers":[
        {
            "category":"Social Services",
            "type":"Services"
        }
    ],
    "sg:phone":"+1 308 381 8163",
    "sg:postcode":"68803",
    "sg:province":"NE",
    "sg:tags":[
        "counselor",
        "marriage",
        "family"
    ],
    "wof:name":"Dan Novotny Counseling",
    "wof:placetype":"venue"
},
  "geometry": {"coordinates":[-98.358036,40.917218],"type":"Point"}
}