{
  "type": "Feature",
  "properties": {
    "iso:country":"US",
    "sg:address":"317 W 2nd St",
    "sg:city":"Grand Island",
    "sg:classifiers":[
        {
            "category":"Manufacturing",
            "subcategory":"Printing",
            "type":"Manufacturing & Wholesale Goods"
        }
    ],
    "sg:phone":"+1 308 384 5762",
    "sg:postcode":"68801",
    "sg:province":"NE",
    "sg:tags":[
        "publisher"
    ],
    "sg:website":"www.crosstrainingpub.com",
    "wof:name":"Cross Training Publishing",
    "wof:placetype":"venue"
},
  "geometry": {"coordinates":[-98.341646,40.923923],"type":"Point"}
}