{
  "type": "Feature",
  "properties": {
    "iso:country":"US",
    "sg:address":"7915 Chinawood Ave",
    "sg:city":"La Vista",
    "sg:classifiers":[
        {
            "category":"Real Estate",
            "subcategory":"Real Estate Operator",
            "type":"Services"
        }
    ],
    "sg:phone":"+1 402 592 2311",
    "sg:postcode":"68128",
    "sg:province":"NE",
    "sg:tags":[
        "building",
        "apartment"
    ],
    "wof:name":"Westfield Apartments",
    "wof:placetype":"venue"
},
  "geometry": {"coordinates":[-96.04738500000001,41.179962],"type":"Point"}
}