{
  "type": "Feature",
  "properties": {
    "addr:full":"2323 Harney St Omaha NE 68102",
    "addr:housenumber":"2323",
    "addr:postcode":"68102",
    "addr:street":"Harney St",
    "iso:country":"US",
    "sg:address":"2323 Harney St",
    "sg:city":"Omaha",
    "sg:classifiers":[
        {
            "category":"Autos & Motor Vehicles",
            "subcategory":"Automobile Sales",
            "type":"Retail Goods"
        },
        {
            "category":"Retail",
            "subcategory":"Auto Rental",
            "type":"Services"
        }
    ],
    "sg:phone":"+1 402 342 3800",
    "sg:postcode":"68102",
    "sg:province":"NE",
    "sg:tags":[
        "truck",
        "leasing",
        "car"
    ],
    "sg:website":"www.enterprise.com",
    "wof:name":"Enterprise Rent-A-Car",
    "wof:placetype":"venue"
},
  "geometry": {"coordinates":[-95.94662700000001,41.256193],"type":"Point"}
}