{
  "type": "Feature",
  "properties": {
    "iso:country":"US",
    "sg:address":"4052 Grand Ave",
    "sg:city":"Omaha",
    "sg:classifiers":[
        {
            "category":"Social Services",
            "subcategory":"Child Care",
            "type":"Services"
        }
    ],
    "sg:phone":"+1 402 453 8412",
    "sg:postcode":"68111",
    "sg:province":"NE",
    "sg:tags":[
        "day"
    ],
    "wof:name":"Better Educational Time",
    "wof:placetype":"venue"
},
  "geometry": {"coordinates":[-95.97370100000001,41.303299],"type":"Point"}
}