{
  "type": "Feature",
  "properties": {
    "iso:country":"US",
    "sg:address":"330 N Webster St",
    "sg:city":"Red Cloud",
    "sg:classifiers":[
        {
            "category":"Bars & Pubs",
            "type":"Food & Drink"
        }
    ],
    "sg:phone":"+1 402 746 2869",
    "sg:postcode":"68970",
    "sg:province":"NE",
    "sg:tags":[
        "grill",
        "bar"
    ],
    "wof:name":"South Bar & Grill",
    "wof:placetype":"venue"
},
  "geometry": {"coordinates":[-98.51924,40.08849],"type":"Point"}
}