{
  "type": "Feature",
  "properties": {
    "iso:country":"US",
    "sg:address":"1724 S 7th St",
    "sg:city":"Omaha",
    "sg:classifiers":[
        {
            "category":"Building & Trades",
            "subcategory":"Construction",
            "type":"Services"
        }
    ],
    "sg:phone":"+1 402 214 8384",
    "sg:postcode":"68108",
    "sg:province":"NE",
    "sg:tags":[
        "general",
        "contractor"
    ],
    "wof:name":"Advanced Carpentry Svc",
    "wof:placetype":"venue"
},
  "geometry": {"coordinates":[-95.925515,41.241857],"type":"Point"}
}