{
  "type": "Feature",
  "properties": {
    "addr:full":"1115 12th St Aurora NE 68818",
    "addr:housenumber":"1115",
    "addr:postcode":"68818",
    "addr:street":"12Th St",
    "iso:country":"US",
    "sg:address":"1115 12th St",
    "sg:city":"Aurora",
    "sg:classifiers":[
        {
            "category":"Cinema",
            "subcategory":"Movie Rental",
            "type":"Entertainment"
        }
    ],
    "sg:phone":"+1 402 694 4622",
    "sg:postcode":"68818",
    "sg:province":"NE",
    "sg:tags":[
        "video",
        "tape"
    ],
    "wof:name":"Nebraska Land Video",
    "wof:placetype":"venue"
},
  "geometry": {"coordinates":[-98.00317,40.868301],"type":"Point"}
}