{
  "type": "Feature",
  "properties": {
    "addr:full":"723 N 8th St Loup City NE 68853",
    "addr:housenumber":"723",
    "addr:postcode":"68853",
    "addr:street":"N 8Th St",
    "iso:country":"US",
    "sg:address":"723 N 8th St",
    "sg:city":"Loup City",
    "sg:classifiers":[
        {
            "category":"Organizations",
            "subcategory":"Religious Organization",
            "type":"Services"
        }
    ],
    "sg:phone":"+1 308 745 1486",
    "sg:postcode":"68853",
    "sg:province":"NE",
    "sg:tags":[
        "church"
    ],
    "sg:website":"www.stjosaphat.org",
    "wof:name":"St Josaphats Parish Center",
    "wof:placetype":"venue"
},
  "geometry": {"coordinates":[-98.96874699999999,41.282972],"type":"Point"}
}