{
  "type": "Feature",
  "properties": {
    "iso:country":"US",
    "sg:address":"411 E Fulton St",
    "sg:city":"Hooper",
    "sg:classifiers":[
        {
            "category":"Retail",
            "subcategory":"Auto Repair",
            "type":"Services"
        }
    ],
    "sg:phone":"+1 402 654 2217",
    "sg:postcode":"68031",
    "sg:province":"NE",
    "sg:tags":[
        "exchanging",
        "engine"
    ],
    "wof:name":"Jack's Automotive Svc",
    "wof:placetype":"venue"
},
  "geometry": {"coordinates":[-96.54381600000001,41.609754],"type":"Point"}
}