{
  "type": "Feature",
  "properties": {
    "addr:full":"71015 577th Ave Diller NE 68342",
    "addr:housenumber":"71015",
    "addr:postcode":"68342",
    "addr:street":"577Th Ave",
    "iso:country":"US",
    "sg:address":"71015 577th Ave",
    "sg:city":"Diller",
    "sg:classifiers":[
        {
            "category":"Real Estate",
            "subcategory":"Real Estate Operator",
            "type":"Services"
        }
    ],
    "sg:phone":"+1 402 793 5518",
    "sg:postcode":"68342",
    "sg:province":"NE",
    "sg:tags":[
        "property",
        "lessor"
    ],
    "wof:name":"Charles Barber",
    "wof:placetype":"venue"
},
  "geometry": {"coordinates":[-97.010744,40.118056],"type":"Point"}
}