{
  "type": "Feature",
  "properties": {
    "addr:full":"913 S 13th St Tekamah NE 68061",
    "addr:housenumber":"913",
    "addr:postcode":"68061",
    "addr:street":"S 13Th St",
    "iso:country":"US",
    "sg:address":"913 S 13th St",
    "sg:city":"Tekamah",
    "sg:classifiers":[
        {
            "category":"Retail",
            "subcategory":"Car Wash",
            "type":"Services"
        }
    ],
    "sg:phone":"+1 402 374 1529",
    "sg:postcode":"68061",
    "sg:province":"NE",
    "sg:tags":[
        "polishing",
        "washing"
    ],
    "wof:name":"Suds R Us",
    "wof:placetype":"venue"
},
  "geometry": {"coordinates":[-96.221358,41.769618],"type":"Point"}
}