{
  "type": "Feature",
  "properties": {
    "iso:country":"US",
    "sg:address":"8300 Pioneers Blvd",
    "sg:city":"Lincoln",
    "sg:classifiers":[
        {
            "category":"Building & Trades",
            "subcategory":"Construction",
            "type":"Services"
        }
    ],
    "sg:phone":"+1 402 486 3336",
    "sg:postcode":"68506",
    "sg:province":"NE",
    "sg:tags":[
        "steel"
    ],
    "wof:name":"National Detail Svc",
    "wof:placetype":"venue"
},
  "geometry": {"coordinates":[-96.60762200000001,40.769804],"type":"Point"}
}