{
  "type": "Feature",
  "properties": {
    "iso:country":"US",
    "sg:address":"512 N Grant St",
    "sg:city":"Lexington",
    "sg:classifiers":[
        {
            "category":"Personal",
            "subcategory":"Beauty Salon",
            "type":"Services"
        }
    ],
    "sg:phone":"+1 308 324 5598",
    "sg:postcode":"68850",
    "sg:province":"NE",
    "wof:name":"V-Man's Hair Tanning & Fitness",
    "wof:placetype":"venue"
},
  "geometry": {"coordinates":[-99.740083,40.778178],"type":"Point"}
}