{
  "type": "Feature",
  "properties": {
    "iso:country":"US",
    "sg:address":"580 Deborah Dr",
    "sg:city":"Sidney",
    "sg:classifiers":[
        {
            "category":"Professional",
            "subcategory":"Business Services",
            "type":"Services"
        }
    ],
    "sg:phone":"+1 308 254 6361",
    "sg:postcode":"69162",
    "sg:province":"NE",
    "wof:name":"Darnall Enterprises",
    "wof:placetype":"venue"
},
  "geometry": {"coordinates":[-102.96969300000001,41.140337],"type":"Point"}
}