{
  "type": "Feature",
  "properties": {
    "addr:full":"312 175th Pleasant Dale NE 68423",
    "addr:housenumber":"312",
    "addr:postcode":"68423",
    "addr:street":"175Th Pleasant Dale Ne",
    "iso:country":"US",
    "sg:address":"312 175th",
    "sg:city":"Pleasant Dale",
    "sg:classifiers":[
        {
            "category":"Building & Trades",
            "subcategory":"Construction",
            "type":"Services"
        }
    ],
    "sg:phone":"+1 402 826 5655",
    "sg:postcode":"68423",
    "sg:province":"NE",
    "sg:tags":[
        "nonresidential",
        "contractor"
    ],
    "wof:name":"Novak Construction Inc",
    "wof:placetype":"venue"
},
  "geometry": {"coordinates":[-96.95860999999999,40.740186],"type":"Point"}
}