{
  "type": "Feature",
  "properties": {
    "addr:full":"932 10th Ave Sidney NE 69162",
    "addr:housenumber":"932",
    "addr:postcode":"69162",
    "addr:street":"10Th Ave",
    "iso:country":"US",
    "sg:address":"932 10th Ave",
    "sg:city":"Sidney",
    "sg:classifiers":[
        {
            "category":"Shopping",
            "type":"Retail Goods"
        }
    ],
    "sg:phone":"+1 308 254 4323",
    "sg:postcode":"69162",
    "sg:province":"NE",
    "sg:tags":[
        "merchandise"
    ],
    "wof:name":"Fish Haven",
    "wof:placetype":"venue"
},
  "geometry": {"coordinates":[-102.97680699999999,41.144468],"type":"Point"}
}