{
  "type": "Feature",
  "properties": {
    "iso:country":"US",
    "sg:address":"15703 Bennington Rd",
    "sg:city":"Bennington",
    "sg:classifiers":[
        {
            "category":"Retail",
            "subcategory":"Auto Repair",
            "type":"Services"
        }
    ],
    "sg:phone":"+1 402 238 2255",
    "sg:postcode":"68007",
    "sg:province":"NE",
    "sg:tags":[
        "repairing",
        "automobile"
    ],
    "wof:name":"Bill's Highway Svc",
    "wof:placetype":"venue"
},
  "geometry": {"coordinates":[-96.15853,41.364527],"type":"Point"}
}