{
  "type": "Feature",
  "properties": {
    "iso:country":"US",
    "sg:address":"140 N 4th St",
    "sg:city":"Tecumseh",
    "sg:classifiers":[
        {
            "category":"Government",
            "subcategory":"Office",
            "type":"Public Place"
        }
    ],
    "sg:phone":"+1 402 335 3347",
    "sg:postcode":"68450",
    "sg:province":"NE",
    "wof:name":"US Conservation & Dev",
    "wof:placetype":"venue"
},
  "geometry": {"coordinates":[-96.19414399999999,40.368301],"type":"Point"}
}