{
  "type": "Feature",
  "properties": {
    "iso:country":"US",
    "sg:address":"105 S Webster St",
    "sg:city":"Kimball",
    "sg:classifiers":[
        {
            "category":"Manufacturing",
            "subcategory":"Tools & Machinery",
            "type":"Manufacturing & Wholesale Goods"
        }
    ],
    "sg:phone":"+1 308 235 3700",
    "sg:postcode":"69145",
    "sg:province":"NE",
    "sg:tags":[
        "farm",
        "equipment",
        "mfg"
    ],
    "wof:name":"Prestige Manufacturing Inc",
    "wof:placetype":"venue"
},
  "geometry": {"coordinates":[-103.664289,41.238382],"type":"Point"}
}