{
  "type": "Feature",
  "properties": {
    "addr:full":"310 Beech St Elgin NE 68636",
    "addr:housenumber":"310",
    "addr:postcode":"68636",
    "addr:street":"Beech St",
    "iso:country":"US",
    "sg:address":"310 Beech St",
    "sg:city":"Elgin",
    "sg:classifiers":[
        {
            "category":"Building & Trades",
            "subcategory":"Construction",
            "type":"Services"
        }
    ],
    "sg:phone":"+1 402 843 2307",
    "sg:postcode":"68636",
    "sg:province":"NE",
    "sg:tags":[
        "water",
        "main",
        "contractor"
    ],
    "wof:name":"Heithoff Irrigation",
    "wof:placetype":"venue"
},
  "geometry": {"coordinates":[-98.08107,41.985425],"type":"Point"}
}