{
  "type": "Feature",
  "properties": {
    "addr:full":"3205 Oak View Dr Omaha NE 68144",
    "addr:housenumber":"3205",
    "addr:postcode":"68144",
    "addr:street":"Oak View Dr",
    "iso:country":"US",
    "sg:address":"3205 Oak View Dr",
    "sg:city":"Omaha",
    "sg:classifiers":[
        {
            "category":"Restaurant",
            "type":"Food & Drink"
        }
    ],
    "sg:menulink":"http://www.allmenus.com/ne/omaha/65462-cicis-pizza-buffet/menu/",
    "sg:phone":"+1 402 991 2992",
    "sg:postcode":"68144",
    "sg:province":"NE",
    "sg:tags":[
        "american",
        "pizza"
    ],
    "wof:name":"CiCi's Pizza Buffet",
    "wof:placetype":"venue"
},
  "geometry": {"coordinates":[-96.132891,41.227033],"type":"Point"}
}