{
  "type": "Feature",
  "properties": {
    "iso:country":"US",
    "sg:address":"702 Co Rd K",
    "sg:city":"Yutan",
    "sg:classifiers":[
        {
            "category":"Building & Trades",
            "subcategory":"Plumbing",
            "type":"Services"
        }
    ],
    "sg:phone":"+1 402 625 2041",
    "sg:postcode":"68073",
    "sg:province":"NE",
    "sg:tags":[
        "plumbing",
        "contractor"
    ],
    "wof:name":"Cjk Enterprises Inc",
    "wof:placetype":"venue"
},
  "geometry": {"coordinates":[-96.42686399999999,41.204861],"type":"Point"}
}