{
  "type": "Feature",
  "properties": {
    "iso:country":"US",
    "sg:address":"6090 N 56th St",
    "sg:city":"Lincoln",
    "sg:classifiers":[
        {
            "category":"Home & Garden",
            "subcategory":"Building Materials",
            "type":"Retail Goods"
        }
    ],
    "sg:phone":"+1 402 434 5310",
    "sg:postcode":"68504",
    "sg:province":"NE",
    "sg:tags":[
        "glass",
        "window",
        "plate"
    ],
    "wof:name":"Husker Glass Inc",
    "wof:placetype":"venue"
},
  "geometry": {"coordinates":[-96.64344199999999,40.876387],"type":"Point"}
}