{
  "type": "Feature",
  "properties": {
    "addr:full":"2400 Nebraska Ave York NE 68467",
    "addr:housenumber":"2400",
    "addr:postcode":"68467",
    "addr:street":"Nebraska Ave",
    "iso:country":"US",
    "sg:address":"2400 Nebraska Ave",
    "sg:city":"York",
    "sg:classifiers":[
        {
            "category":"Recreation",
            "type":"Entertainment"
        }
    ],
    "sg:phone":"+1 402 362 7114",
    "sg:postcode":"68467",
    "sg:province":"NE",
    "sg:tags":[
        "carnival"
    ],
    "wof:name":"Fair Office",
    "wof:placetype":"venue"
},
  "geometry": {"coordinates":[-97.590193,40.885449],"type":"Point"}
}