{
  "type": "Feature",
  "properties": {
    "iso:country":"US",
    "sg:address":"510 Broadway",
    "sg:city":"Scottsbluff",
    "sg:classifiers":[
        {
            "category":"Professional",
            "subcategory":"Lawyer & Legal Services",
            "type":"Services"
        }
    ],
    "sg:phone":"+1 308 635 6896",
    "sg:postcode":"69361",
    "sg:province":"NE",
    "sg:tags":[
        "attorney"
    ],
    "wof:name":"Flower Law Office",
    "wof:placetype":"venue"
},
  "geometry": {"coordinates":[-103.662655,41.853944],"type":"Point"}
}