{
  "type": "Feature",
  "properties": {
    "iso:country":"US",
    "sg:address":"1003 5th St",
    "sg:city":"Oakdale",
    "sg:classifiers":[
        {
            "category":"Social Services",
            "subcategory":"Child Care",
            "type":"Services"
        }
    ],
    "sg:phone":"+1 402 776 2664",
    "sg:postcode":"68761",
    "sg:province":"NE",
    "wof:name":"Serenity Corners Day Care",
    "wof:placetype":"venue"
},
  "geometry": {"coordinates":[-97.96349600000001,42.069689],"type":"Point"}
}