{
  "type": "Feature",
  "properties": {
    "iso:country":"US",
    "sg:address":"444 S 16th St",
    "sg:city":"Omaha",
    "sg:classifiers":[
        {
            "category":"Utilities",
            "subcategory":"Electric",
            "type":"Services"
        },
        {
            "category":"Banks & Credit Unions",
            "subcategory":"Bank",
            "type":"Services"
        }
    ],
    "sg:phone":"+1 402 636 3747",
    "sg:postcode":"68102",
    "sg:province":"NE",
    "sg:tags":[
        "company"
    ],
    "wof:name":"Omaha Public Power District Cu",
    "wof:placetype":"venue"
},
  "geometry": {"coordinates":[-95.93726599999999,41.255962],"type":"Point"}
}