{
  "type": "Feature",
  "properties": {
    "iso:country":"US",
    "sg:address":"542 N 8th Rd",
    "sg:city":"Palmyra",
    "sg:classifiers":[
        {
            "category":"Manufacturing",
            "subcategory":"Lumber",
            "type":"Manufacturing & Wholesale Goods"
        }
    ],
    "sg:phone":"+1 402 450 7012",
    "sg:postcode":"68418",
    "sg:province":"NE",
    "sg:tags":[
        "mill"
    ],
    "wof:name":"Big Red Sawmill & Firewood",
    "wof:placetype":"venue"
},
  "geometry": {"coordinates":[-96.387394,40.704728],"type":"Point"}
}