{
  "type": "Feature",
  "properties": {
    "iso:country":"US",
    "sg:address":"501 State St",
    "sg:city":"Elkhorn",
    "sg:classifiers":[
        {
            "category":"Food & Beverages",
            "subcategory":"Groceries & Convenience Stores",
            "type":"Retail Goods"
        }
    ],
    "sg:phone":"+1 402 289 2111",
    "sg:postcode":"68022",
    "sg:province":"NE",
    "wof:name":"Kwik Shop 623",
    "wof:placetype":"venue"
},
  "geometry": {"coordinates":[-96.234369,41.287338],"type":"Point"}
}