{
  "type": "Feature",
  "properties": {
    "iso:country":"US",
    "sg:address":"121 S Linden St",
    "sg:city":"Springview",
    "sg:classifiers":[
        {
            "category":"Retail",
            "subcategory":"Auto Repair",
            "type":"Services"
        }
    ],
    "sg:phone":"+1 402 497 3855",
    "sg:postcode":"68778",
    "sg:province":"NE",
    "sg:tags":[
        "repairing",
        "automobile"
    ],
    "wof:name":"Hespe Auto Ctr",
    "wof:placetype":"venue"
},
  "geometry": {"coordinates":[-99.74999200000001,42.823982],"type":"Point"}
}