{
  "type": "Feature",
  "properties": {
    "iso:country":"US",
    "sg:address":"1307 B St",
    "sg:city":"Tekamah",
    "sg:classifiers":[
        {
            "category":"Home & Garden",
            "subcategory":"Building Materials",
            "type":"Retail Goods"
        }
    ],
    "sg:phone":"+1 402 374 1722",
    "sg:postcode":"68061",
    "sg:province":"NE",
    "sg:tags":[
        "ready",
        "concrete",
        "mfg"
    ],
    "wof:name":"Arps Red-E-Mix Inc",
    "wof:placetype":"venue"
},
  "geometry": {"coordinates":[-96.221835,41.767026],"type":"Point"}
}