{
  "type": "Feature",
  "properties": {
    "iso:country":"US",
    "sg:address":"206 E 4th St",
    "sg:city":"Yankton",
    "sg:classifiers":[
        {
            "category":"Social Services",
            "subcategory":"Job Training",
            "type":"Services"
        }
    ],
    "sg:phone":"+1 605 665 0199",
    "sg:postcode":"57078",
    "sg:province":"NE",
    "sg:tags":[
        "rehabilitation"
    ],
    "wof:name":"Yankton Area Adjustment Trnng",
    "wof:placetype":"venue"
},
  "geometry": {"coordinates":[-97.39042999999999,42.871115],"type":"Point"}
}