{
  "type": "Feature",
  "properties": {
    "iso:country":"US",
    "sg:address":"310 A St",
    "sg:city":"Aurora",
    "sg:classifiers":[
        {
            "category":"Farming",
            "subcategory":"Farm & Veterinary Services",
            "type":"Manufacturing & Wholesale Goods"
        }
    ],
    "sg:phone":"+1 402 694 3666",
    "sg:postcode":"68818",
    "sg:province":"NE",
    "sg:tags":[
        "executive",
        "crop"
    ],
    "wof:name":"Weed Control",
    "wof:placetype":"venue"
},
  "geometry": {"coordinates":[-98.01574599999999,40.857726],"type":"Point"}
}