{
  "type": "Feature",
  "properties": {
    "addr:full":"101 S Calvert St Lawrence NE 68957",
    "addr:housenumber":"101",
    "addr:postcode":"68957",
    "addr:street":"S Calvert St",
    "iso:country":"US",
    "sg:address":"101 S Calvert St",
    "sg:city":"Lawrence",
    "sg:classifiers":[
        {
            "category":"Banks & Credit Unions",
            "subcategory":"Bank",
            "type":"Services"
        }
    ],
    "sg:phone":"+1 402 756 7402",
    "sg:postcode":"68957",
    "sg:province":"NE",
    "wof:name":"Farmers & Merchants Bank",
    "wof:placetype":"venue"
},
  "geometry": {"coordinates":[-98.259884,40.291077],"type":"Point"}
}