{
  "type": "Feature",
  "properties": {
    "iso:country":"US",
    "sg:address":"1920 N 102nd St",
    "sg:city":"Omaha",
    "sg:classifiers":[
        {
            "category":"Organizations",
            "subcategory":"Religious Organization",
            "type":"Services"
        }
    ],
    "sg:phone":"+1 402 397 0407",
    "sg:postcode":"68114",
    "sg:province":"NE",
    "sg:tags":[
        "church"
    ],
    "sg:website":"www.stleo.net",
    "wof:name":"St Leos Church",
    "wof:placetype":"venue"
},
  "geometry": {"coordinates":[-96.07186799999999,41.276268],"type":"Point"}
}