{
  "type": "Feature",
  "properties": {
    "addr:full":"3507 S 84th St Omaha NE 68124",
    "addr:housenumber":"3507",
    "addr:postcode":"68124",
    "addr:street":"S 84Th St",
    "iso:country":"US",
    "sg:address":"3507 S 84th St",
    "sg:city":"Omaha",
    "sg:classifiers":[
        {
            "category":"Autos & Motor Vehicles",
            "subcategory":"Automobile Sales",
            "type":"Retail Goods"
        }
    ],
    "sg:phone":"+1 402 339 1991",
    "sg:postcode":"68124",
    "sg:province":"NE",
    "sg:tags":[
        "car",
        "dealer"
    ],
    "wof:name":"MVL Auto Sales",
    "wof:placetype":"venue"
},
  "geometry": {"coordinates":[-96.043031,41.22736],"type":"Point"}
}