{
  "type": "Feature",
  "properties": {
    "addr:full":"4150 Pace Blvd Lincoln NE 68502",
    "addr:housenumber":"4150",
    "addr:postcode":"68502",
    "addr:street":"Pace Blvd",
    "iso:country":"US",
    "sg:address":"4150 Pace Blvd",
    "sg:city":"Lincoln",
    "sg:classifiers":[
        {
            "category":"Farming",
            "subcategory":"Livestock Farm",
            "type":"Manufacturing & Wholesale Goods"
        }
    ],
    "sg:phone":"+1 402 245 3800",
    "sg:postcode":"68502",
    "sg:province":"NE",
    "sg:tags":[
        "hog",
        "or",
        "feedlot"
    ],
    "wof:name":"Hormel",
    "wof:placetype":"venue"
},
  "geometry": {"coordinates":[-96.687315,40.77091],"type":"Point"}
}