{
  "type": "Feature",
  "properties": {
    "iso:country":"US",
    "sg:address":"17927 Pierce Plz",
    "sg:city":"Omaha",
    "sg:classifiers":[
        {
            "category":"Home & Garden",
            "subcategory":"Building Materials",
            "type":"Retail Goods"
        }
    ],
    "sg:phone":"+1 402 758 0792",
    "sg:postcode":"68130",
    "sg:province":"NE",
    "sg:tags":[
        "lumber"
    ],
    "wof:name":"Christenson Lumber Inc",
    "wof:placetype":"venue"
},
  "geometry": {"coordinates":[-96.19436399999999,41.247338],"type":"Point"}
}