{
  "type": "Feature",
  "properties": {
    "iso:country":"US",
    "sg:address":"1416 A St",
    "sg:city":"Benkelman",
    "sg:classifiers":[
        {
            "category":"Restaurant",
            "type":"Food & Drink"
        }
    ],
    "sg:phone":"+1 308 423 2596",
    "sg:postcode":"69021",
    "sg:province":"NE",
    "wof:name":"Dub Drive-In",
    "wof:placetype":"venue"
},
  "geometry": {"coordinates":[-101.531589,40.057678],"type":"Point"}
}