{
  "type": "Feature",
  "properties": {
    "iso:country":"US",
    "sg:address":"1522 Broadway",
    "sg:city":"Scottsbluff",
    "sg:classifiers":[
        {
            "category":"Shopping",
            "subcategory":"Jewelry",
            "type":"Retail Goods"
        }
    ],
    "sg:phone":"+1 308 635 1814",
    "sg:postcode":"69361",
    "sg:province":"NE",
    "sg:tags":[
        "jeweler"
    ],
    "wof:name":"Bentley Donovan Fine Jewelry",
    "wof:placetype":"venue"
},
  "geometry": {"coordinates":[-103.662803,41.862066],"type":"Point"}
}