{
  "type": "Feature",
  "properties": {
    "iso:country":"US",
    "sg:address":"7775 Greenleaf Dr",
    "sg:city":"La Vista",
    "sg:classifiers":[
        {
            "category":"Social Services",
            "subcategory":"Child Care",
            "type":"Services"
        }
    ],
    "sg:phone":"+1 402 331 2156",
    "sg:postcode":"68128",
    "sg:province":"NE",
    "sg:tags":[
        "day"
    ],
    "wof:name":"Vodicka Kathleen Day Care",
    "wof:placetype":"venue"
},
  "geometry": {"coordinates":[-96.033181,41.176708],"type":"Point"}
}