{
  "type": "Feature",
  "properties": {
    "iso:country":"US",
    "sg:address":"721 5th St",
    "sg:city":"Peru",
    "sg:classifiers":[
        {
            "category":"Organizations",
            "subcategory":"Community Association",
            "type":"Services"
        }
    ],
    "sg:phone":"+1 402 872 6265",
    "sg:postcode":"68421",
    "sg:province":"NE",
    "sg:tags":[
        "military"
    ],
    "wof:name":"Veterans Of Foreign Wars 7299",
    "wof:placetype":"venue"
},
  "geometry": {"coordinates":[-95.73052,40.481332],"type":"Point"}
}