{
  "type": "Feature",
  "properties": {
    "iso:country":"US",
    "sg:address":"389 Q Rd",
    "sg:city":"Palmer",
    "sg:classifiers":[
        {
            "category":"Farming",
            "subcategory":"Livestock Farm",
            "type":"Manufacturing & Wholesale Goods"
        }
    ],
    "sg:phone":"+1 308 894 8485",
    "sg:postcode":"68864",
    "sg:province":"NE",
    "sg:tags":[
        "beef",
        "feedlot",
        "cattle"
    ],
    "wof:name":"Harold Rudolf",
    "wof:placetype":"venue"
},
  "geometry": {"coordinates":[-98.232336,41.162098],"type":"Point"}
}