{
  "type": "Feature",
  "properties": {
    "iso:country":"US",
    "sg:address":"910 3rd St",
    "sg:city":"Sutherland",
    "sg:classifiers":[
        {
            "category":"Organizations",
            "subcategory":"Religious Organization",
            "type":"Services"
        }
    ],
    "sg:phone":"+1 308 386 4362",
    "sg:postcode":"69165",
    "sg:province":"NE",
    "sg:tags":[
        "church"
    ],
    "wof:name":"Presbyterian Church",
    "wof:placetype":"venue"
},
  "geometry": {"coordinates":[-101.126628,41.159198],"type":"Point"}
}