{
  "type": "Feature",
  "properties": {
    "iso:country":"US",
    "sg:address":"919 Rd A",
    "sg:city":"Fairmont",
    "sg:classifiers":[
        {
            "category":"Farming",
            "subcategory":"Livestock Farm",
            "type":"Manufacturing & Wholesale Goods"
        }
    ],
    "sg:phone":"+1 402 724 2392",
    "sg:postcode":"68354",
    "sg:province":"NE",
    "sg:tags":[
        "beef",
        "far",
        "cash",
        "grain",
        "soybean",
        "cattle",
        "feedlot"
    ],
    "wof:name":"Luethke Elden",
    "wof:placetype":"venue"
},
  "geometry": {"coordinates":[-97.657157,40.698646],"type":"Point"}
}