{
  "type": "Feature",
  "properties": {
    "iso:country":"US",
    "sg:address":"101 S Charde Ave",
    "sg:city":"Oakland",
    "sg:classifiers":[
        {
            "category":"Food & Beverages",
            "subcategory":"Groceries & Convenience Stores",
            "type":"Retail Goods"
        }
    ],
    "sg:phone":"+1 402 685 5534",
    "sg:postcode":"68045",
    "sg:province":"NE",
    "wof:name":"Fred's Food & Fuel",
    "wof:placetype":"venue"
},
  "geometry": {"coordinates":[-96.46310800000001,41.831303],"type":"Point"}
}