{
  "type": "Feature",
  "properties": {
    "iso:country":"US",
    "sg:address":"116 E C St",
    "sg:city":"North Platte",
    "sg:classifiers":[
        {
            "category":"Shopping",
            "subcategory":"Used Merchandise",
            "type":"Retail Goods"
        },
        {
            "category":"Organizations",
            "subcategory":"Religious Organization",
            "type":"Services"
        }
    ],
    "sg:phone":"+1 308 534 7634",
    "sg:postcode":"69101",
    "sg:province":"NE",
    "sg:tags":[
        "shop",
        "membership",
        "thrift"
    ],
    "wof:name":"Thrift Connection",
    "wof:placetype":"venue"
},
  "geometry": {"coordinates":[-100.76385000000001,41.131545],"type":"Point"}
}