{
  "type": "Feature",
  "properties": {
    "addr:full":"3223 N 45th St Omaha NE 68104",
    "addr:housenumber":"3223",
    "addr:postcode":"68104",
    "addr:street":"N 45Th St",
    "iso:country":"US",
    "sg:address":"3223 N 45th St",
    "sg:city":"Omaha",
    "sg:classifiers":[
        {
            "category":"Social Services",
            "subcategory":"Child Care",
            "type":"Services"
        }
    ],
    "sg:phone":"+1 402 457 7830",
    "sg:postcode":"68104",
    "sg:province":"NE",
    "sg:tags":[
        "day"
    ],
    "wof:name":"Little Bears Preschool & Child Care Center",
    "wof:placetype":"venue"
},
  "geometry": {"coordinates":[-95.980598,41.2878],"type":"Point"}
}