{
  "type": "Feature",
  "properties": {
    "iso:country":"US",
    "sg:address":"13405 Redwood St",
    "sg:city":"Omaha",
    "sg:classifiers":[
        {
            "category":"Shopping",
            "type":"Retail Goods"
        }
    ],
    "sg:phone":"+1 402 895 4548",
    "sg:postcode":"68138",
    "sg:province":"NE",
    "sg:tags":[
        "merchandise"
    ],
    "wof:name":"P&S Coins",
    "wof:placetype":"venue"
},
  "geometry": {"coordinates":[-96.122332,41.188809],"type":"Point"}
}