{
  "type": "Feature",
  "properties": {
    "iso:country":"US",
    "sg:address":"516 Keller Dr",
    "sg:city":"Sidney",
    "sg:classifiers":[
        {
            "category":"Mining & Drilling",
            "type":"Manufacturing & Wholesale Goods"
        }
    ],
    "sg:phone":"+1 308 254 5824",
    "sg:postcode":"69162",
    "sg:province":"NE",
    "sg:tags":[
        "field"
    ],
    "wof:name":"Hardys Well Service",
    "wof:placetype":"venue"
},
  "geometry": {"coordinates":[-102.971406,41.138656],"type":"Point"}
}