{
  "type": "Feature",
  "properties": {
    "iso:country":"US",
    "sg:address":"55 River Rd",
    "sg:city":"Ogallala",
    "sg:classifiers":[
        {
            "category":"Health Services",
            "subcategory":"Doctor",
            "type":"Services"
        }
    ],
    "sg:phone":"+1 308 284 6054",
    "sg:postcode":"69153",
    "sg:province":"NE",
    "sg:tags":[
        "clinic"
    ],
    "wof:name":"Sandhills District Health Dept",
    "wof:placetype":"venue"
},
  "geometry": {"coordinates":[-101.716955,41.119959],"type":"Point"}
}