{
  "type": "Feature",
  "properties": {
    "iso:country":"US",
    "sg:address":"7401 Englewood Dr",
    "sg:city":"Lincoln",
    "sg:classifiers":[
        {
            "category":"Retail",
            "subcategory":"Repair Shop",
            "type":"Services"
        }
    ],
    "sg:phone":"+1 402 327 9461",
    "sg:postcode":"68510",
    "sg:province":"NE",
    "wof:name":"Lear Repair",
    "wof:placetype":"venue"
},
  "geometry": {"coordinates":[-96.619429,40.805204],"type":"Point"}
}