{
  "type": "Feature",
  "properties": {
    "iso:country":"US",
    "sg:address":"208 3rd St",
    "sg:city":"Firth",
    "sg:classifiers":[
        {
            "category":"Utilities",
            "subcategory":"Fuel Oil & Lpg",
            "type":"Services"
        }
    ],
    "sg:phone":"+1 402 791 5862",
    "sg:postcode":"68358",
    "sg:province":"NE",
    "sg:tags":[
        "petroleum",
        "gas"
    ],
    "sg:website":"www.nebraskatire.com",
    "wof:name":"Nebraska Tire Firth",
    "wof:placetype":"venue"
},
  "geometry": {"coordinates":[-96.604264,40.532815],"type":"Point"}
}