{
  "type": "Feature",
  "properties": {
    "iso:country":"US",
    "sg:address":"3801 Ames Ave",
    "sg:city":"Omaha",
    "sg:classifiers":[
        {
            "category":"Restaurant",
            "type":"Food & Drink"
        }
    ],
    "sg:phone":"+1 402 451 8061",
    "sg:postcode":"68111",
    "sg:province":"NE",
    "sg:tags":[
        "barbeque"
    ],
    "wof:name":"Jim's Rib Haven",
    "wof:placetype":"venue"
},
  "geometry": {"coordinates":[-95.97020000000001,41.2994],"type":"Point"}
}