{
  "type": "Feature",
  "properties": {
    "iso:country":"US",
    "sg:address":"5316 S 86th Plz",
    "sg:city":"Omaha",
    "sg:classifiers":[
        {
            "category":"Retail",
            "subcategory":"Repair Shop",
            "type":"Services"
        }
    ],
    "sg:phone":"+1 402 597 9010",
    "sg:postcode":"68127",
    "sg:province":"NE",
    "wof:name":"Johns Piano Service",
    "wof:placetype":"venue"
},
  "geometry": {"coordinates":[-96.04554,41.20528],"type":"Point"}
}