{
  "type": "Feature",
  "properties": {
    "iso:country":"US",
    "sg:address":"247 Bordeaux St",
    "sg:city":"Chadron",
    "sg:classifiers":[
        {
            "category":"Organizations",
            "subcategory":"Community Association",
            "type":"Services"
        }
    ],
    "sg:phone":"+1 308 432 2750",
    "sg:postcode":"69337",
    "sg:province":"NE",
    "sg:tags":[
        "fraternal"
    ],
    "wof:name":"Elks Lodge",
    "wof:placetype":"venue"
},
  "geometry": {"coordinates":[-102.999324,42.830132],"type":"Point"}
}