{
  "type": "Feature",
  "properties": {
    "iso:country":"US",
    "sg:address":"800 Greenwood Rd",
    "sg:city":"Sidney",
    "sg:classifiers":[
        {
            "category":"Wholesale",
            "subcategory":"Farm Supplies",
            "type":"Manufacturing & Wholesale Goods"
        }
    ],
    "sg:phone":"+1 308 254 4230",
    "sg:postcode":"69162",
    "sg:province":"NE",
    "sg:tags":[
        "grain"
    ],
    "sg:website":"www.crossroadscoop.com",
    "wof:name":"Crossroads Cooperative Assn",
    "wof:placetype":"venue"
},
  "geometry": {"coordinates":[-102.954325,41.147501],"type":"Point"}
}