{
  "type": "Feature",
  "properties": {
    "iso:country":"US",
    "sg:address":"934 Moraine Dr",
    "sg:city":"Lincoln",
    "sg:classifiers":[
        {
            "category":"Autos & Motor Vehicles",
            "subcategory":"Auto Supplies",
            "type":"Retail Goods"
        }
    ],
    "sg:phone":"+1 402 560 3900",
    "sg:postcode":"68510",
    "sg:province":"NE",
    "sg:tags":[
        "automobile",
        "stereo",
        "radio"
    ],
    "wof:name":"Mobil Sound",
    "wof:placetype":"venue"
},
  "geometry": {"coordinates":[-96.640271,40.805207],"type":"Point"}
}