{
  "type": "Feature",
  "properties": {
    "iso:country":"US",
    "sg:address":"2030 Martha St",
    "sg:city":"Omaha",
    "sg:classifiers":[
        {
            "category":"Shopping",
            "subcategory":"Musical Instruments",
            "type":"Retail Goods"
        }
    ],
    "sg:phone":"+1 402 408 0744",
    "sg:postcode":"68108",
    "sg:province":"NE",
    "sg:tags":[
        "music",
        "dealer"
    ],
    "wof:name":"Estrada Music Sales & Rental",
    "wof:placetype":"venue"
},
  "geometry": {"coordinates":[-95.94369399999999,41.238298],"type":"Point"}
}