{
  "type": "Feature",
  "properties": {
    "iso:country":"US",
    "sg:address":"7605 Cass St",
    "sg:city":"Omaha",
    "sg:classifiers":[
        {
            "category":"Restaurant",
            "type":"Food & Drink"
        }
    ],
    "sg:menulink":"http://www.allmenus.com/ne/omaha/97548-outback-steakhouse/menu/",
    "sg:phone":"+1 402 392 2212",
    "sg:postcode":"68114",
    "sg:province":"NE",
    "sg:tags":[
        "american",
        "steakhouse"
    ],
    "wof:name":"Outback Steakhouse",
    "wof:placetype":"venue"
},
  "geometry": {"coordinates":[-96.031813,41.262795],"type":"Point"}
}