{
  "type": "Feature",
  "properties": {
    "iso:country":"US",
    "sg:address":"510 E 1st St",
    "sg:city":"Ogallala",
    "sg:classifiers":[
        {
            "category":"Museum",
            "type":"Entertainment"
        }
    ],
    "sg:phone":"+1 308 284 2000",
    "sg:postcode":"69153",
    "sg:province":"NE",
    "wof:name":"Nebraska National Trls Museum",
    "wof:placetype":"venue"
},
  "geometry": {"coordinates":[-101.71319200000001,41.125387],"type":"Point"}
}