{
  "type": "Feature",
  "properties": {
    "iso:country":"US",
    "sg:address":"2514 S 140th St",
    "sg:city":"Omaha",
    "sg:classifiers":[
        {
            "category":"Retail",
            "subcategory":"Laundry & Dry Cleaning",
            "type":"Services"
        }
    ],
    "sg:phone":"+1 402 330 1987",
    "sg:postcode":"68144",
    "sg:province":"NE",
    "sg:tags":[
        "cleaners"
    ],
    "wof:name":"Camelot Cleaners",
    "wof:placetype":"venue"
},
  "geometry": {"coordinates":[-96.13416700000001,41.234973],"type":"Point"}
}