{
  "type": "Feature",
  "properties": {
    "addr:full":"703 W 3rd St Grand Island NE 68801",
    "addr:housenumber":"703",
    "addr:postcode":"68801",
    "addr:street":"W 3Rd St",
    "iso:country":"US",
    "sg:address":"703 W 3rd St",
    "sg:city":"Grand Island",
    "sg:classifiers":[
        {
            "category":"Wholesale",
            "subcategory":"Medical Equipment & Supplies",
            "type":"Manufacturing & Wholesale Goods"
        }
    ],
    "sg:phone":"+1 308 381 7030",
    "sg:postcode":"68801",
    "sg:province":"NE",
    "sg:tags":[
        "hospital"
    ],
    "wof:name":"Lincare",
    "wof:placetype":"venue"
},
  "geometry": {"coordinates":[-98.34654500000001,40.923067],"type":"Point"}
}