{
  "type": "Feature",
  "properties": {
    "iso:country":"US",
    "sg:address":"15005 Grover St",
    "sg:city":"Omaha",
    "sg:classifiers":[
        {
            "category":"Wholesale",
            "subcategory":"Hardware",
            "type":"Manufacturing & Wholesale Goods"
        }
    ],
    "sg:phone":"+1 402 330 1203",
    "sg:postcode":"68144",
    "sg:province":"NE",
    "sg:tags":[
        "plumbing",
        "fixture",
        "supply"
    ],
    "sg:website":"www.ferguson.com",
    "wof:name":"Ferguson Bath & Kitchen Gllry",
    "wof:placetype":"venue"
},
  "geometry": {"coordinates":[-96.148647,41.229083],"type":"Point"}
}