{
  "type": "Feature",
  "properties": {
    "addr:full":"1623 N 105th St Omaha NE 68114",
    "addr:housenumber":"1623",
    "addr:postcode":"68114",
    "addr:street":"N 105Th St",
    "iso:country":"US",
    "sg:address":"1623 N 105th St",
    "sg:city":"Omaha",
    "sg:classifiers":[
        {
            "category":"Organizations",
            "subcategory":"Community Association",
            "type":"Services"
        }
    ],
    "sg:phone":"+1 402 496 7567",
    "sg:postcode":"68114",
    "sg:province":"NE",
    "wof:name":"American Veterans",
    "wof:placetype":"venue"
},
  "geometry": {"coordinates":[-96.077179,41.274765],"type":"Point"}
}