{
  "type": "Feature",
  "properties": {
    "addr:city":"Omaha",
    "addr:full":"500 S 20Th St Omaha, Ne 68102-2508",
    "addr:house_number":"500",
    "addr:housenumber":"500",
    "addr:phone":"+1 402-342-6164",
    "addr:postcode":"68102-2508",
    "addr:road":"S 20Th St",
    "addr:state":"NE",
    "addr:street":"S 20Th St",
    "iso:country":"US",
    "sg:address":"500 S 20th St",
    "sg:city":"Omaha",
    "sg:classifiers":[
        {
            "category":"Museum",
            "type":"Entertainment"
        }
    ],
    "sg:phone":"+1 402 342 6164",
    "sg:postcode":"68102",
    "sg:province":"NE",
    "sg:website":"www.ocm.org",
    "wof:airports":[
        102524739,
        102531489,
        102529985
    ],
    "wof:name":"Omaha Children'S Museum",
    "wof:placetype":"venue"
},
  "geometry": {"coordinates":[-95.94311999999999,41.25483],"type":"Point"}
}