{
  "type": "Feature",
  "properties": {
    "iso:country":"US",
    "sg:address":"6931 Crooked Creek Ct",
    "sg:city":"Lincoln",
    "sg:classifiers":[
        {
            "category":"Social Services",
            "subcategory":"Child Care",
            "type":"Services"
        }
    ],
    "sg:phone":"+1 402 421 7202",
    "sg:postcode":"68516",
    "sg:province":"NE",
    "sg:tags":[
        "day"
    ],
    "wof:name":"Jenkins Janice Day Care",
    "wof:placetype":"venue"
},
  "geometry": {"coordinates":[-96.653936,40.741768],"type":"Point"}
}