{
  "type": "Feature",
  "properties": {
    "iso:country":"US",
    "sg:address":"42711 Rd 765",
    "sg:city":"Cozad",
    "sg:phone":"+1 308 784 5029",
    "sg:postcode":"69130",
    "sg:province":"NE",
    "sg:tags":[
        "farm",
        "corn"
    ],
    "wof:name":"O K Farm",
    "wof:placetype":"venue"
},
  "geometry": {"coordinates":[-99.862138,40.916315],"type":"Point"}
}