{
  "type": "Feature",
  "properties": {
    "addr:full":"105 S 53rd St Omaha NE 68132",
    "addr:housenumber":"105",
    "addr:postcode":"68132",
    "addr:street":"S 53Rd St",
    "iso:country":"US",
    "sg:address":"105 S 53rd St",
    "sg:city":"Omaha",
    "sg:classifiers":[
        {
            "category":"Professional",
            "subcategory":"Business Services",
            "type":"Services"
        }
    ],
    "sg:phone":"+1 402 556 9360",
    "sg:postcode":"68132",
    "sg:province":"NE",
    "wof:name":"Trifur Technologies Inc",
    "wof:placetype":"venue"
},
  "geometry": {"coordinates":[-95.996112,41.257862],"type":"Point"}
}