{
  "type": "Feature",
  "properties": {
    "iso:country":"US",
    "sg:address":"16911 US Hwy 75",
    "sg:city":"Plattsmouth",
    "sg:classifiers":[
        {
            "category":"Professional",
            "type":"Services"
        }
    ],
    "sg:phone":"+1 402 298 8555",
    "sg:postcode":"68048",
    "sg:province":"NE",
    "sg:tags":[
        "establishment"
    ],
    "wof:name":"Prestige Co Inc",
    "wof:placetype":"venue"
},
  "geometry": {"coordinates":[-95.908654,41.01569],"type":"Point"}
}