{
  "type": "Feature",
  "properties": {
    "iso:country":"US",
    "sg:address":"8518 Blondo St",
    "sg:city":"Omaha",
    "sg:classifiers":[
        {
            "category":"Wholesale",
            "subcategory":"Scrap",
            "type":"Manufacturing & Wholesale Goods"
        }
    ],
    "sg:phone":"+1 402 393 6620",
    "sg:postcode":"68134",
    "sg:province":"NE",
    "sg:tags":[
        "recycling",
        "center"
    ],
    "wof:name":"All About Recycling/Scrap Cntl",
    "wof:placetype":"venue"
},
  "geometry": {"coordinates":[-96.04730000000001,41.277881],"type":"Point"}
}