{
  "type": "Feature",
  "properties": {
    "addr:full":"1650 Farnam St Omaha NE 68102",
    "addr:housenumber":"1650",
    "addr:postcode":"68102",
    "addr:street":"Farnam St",
    "iso:country":"US",
    "sg:address":"1650 Farnam St",
    "sg:city":"Omaha",
    "sg:classifiers":[
        {
            "category":"Professional",
            "subcategory":"Lawyer & Legal Services",
            "type":"Services"
        }
    ],
    "sg:phone":"+1 402 346 6000",
    "sg:postcode":"68102",
    "sg:province":"NE",
    "wof:name":"Curry Michael L Atty",
    "wof:placetype":"venue"
},
  "geometry": {"coordinates":[-95.93789700000001,41.257599],"type":"Point"}
}