{
  "type": "Feature",
  "properties": {
    "iso:country":"US",
    "sg:address":"307 3rd St",
    "sg:city":"Nemaha",
    "sg:classifiers":[
        {
            "category":"Social Services",
            "subcategory":"Child Care",
            "type":"Services"
        }
    ],
    "sg:phone":"+1 402 824 5565",
    "sg:postcode":"68414",
    "sg:province":"NE",
    "sg:tags":[
        "day"
    ],
    "wof:name":"Faulks Tamra",
    "wof:placetype":"venue"
},
  "geometry": {"coordinates":[-95.67383,40.34141],"type":"Point"}
}