{
  "type": "Feature",
  "properties": {
    "addr:full":"5430 Linden St Lincoln NE 68516",
    "addr:housenumber":"5430",
    "addr:postcode":"68516",
    "addr:street":"Linden St",
    "iso:country":"US",
    "sg:address":"5430 Linden St",
    "sg:city":"Lincoln",
    "sg:phone":"+1 402 488 4443",
    "sg:postcode":"68516",
    "sg:province":"NE",
    "sg:tags":[
        "farm",
        "wheat",
        "grain",
        "cash",
        "soybean"
    ],
    "wof:name":"Kenneth Kaiser",
    "wof:placetype":"venue"
},
  "geometry": {"coordinates":[-96.644615,40.768004],"type":"Point"}
}