{
  "type": "Feature",
  "properties": {
    "iso:country":"US",
    "sg:address":"6150 S 182nd St",
    "sg:city":"Omaha",
    "sg:classifiers":[
        {
            "category":"Professional",
            "subcategory":"Advertising",
            "type":"Services"
        }
    ],
    "sg:phone":"+1 402 778 9993",
    "sg:postcode":"68135",
    "sg:province":"NE",
    "wof:name":"Adventures In Adverting-Innvtv",
    "wof:placetype":"venue"
},
  "geometry": {"coordinates":[-96.20031299999999,41.196459],"type":"Point"}
}