{
  "type": "Feature",
  "properties": {
    "iso:country":"US",
    "sg:address":"2010 S 13th St",
    "sg:city":"Norfolk",
    "sg:classifiers":[
        {
            "category":"Home & Garden",
            "subcategory":"Furniture",
            "type":"Retail Goods"
        }
    ],
    "sg:phone":"+1 402 371 1174",
    "sg:postcode":"68701",
    "sg:province":"NE",
    "wof:name":"Furniture & Bedding 4 Less Inc",
    "wof:placetype":"venue"
},
  "geometry": {"coordinates":[-97.42651600000001,42.008528],"type":"Point"}
}