{
  "type": "Feature",
  "properties": {
    "addr:full":"3220 Joy Ct Lincoln NE 68502",
    "addr:housenumber":"3220",
    "addr:postcode":"68502",
    "addr:street":"Joy Ct",
    "iso:country":"US",
    "sg:address":"3220 Joy Ct",
    "sg:city":"Lincoln",
    "sg:classifiers":[
        {
            "category":"Professional",
            "subcategory":"Management & Consulting",
            "type":"Services"
        }
    ],
    "sg:phone":"+1 402 434 2102",
    "sg:postcode":"68502",
    "sg:province":"NE",
    "wof:name":"JMS Assoc Inc",
    "wof:placetype":"venue"
},
  "geometry": {"coordinates":[-96.676,40.778549],"type":"Point"}
}