{
  "type": "Feature",
  "properties": {
    "iso:country":"US",
    "sg:address":"208 Broadway St",
    "sg:city":"Fullerton",
    "sg:classifiers":[
        {
            "category":"Shopping",
            "subcategory":"Florist",
            "type":"Retail Goods"
        }
    ],
    "sg:phone":"+1 308 536 2112",
    "sg:postcode":"68638",
    "sg:province":"NE",
    "wof:name":"Flower Barrel & Gift Gallery",
    "wof:placetype":"venue"
},
  "geometry": {"coordinates":[-97.96888199999999,41.364356],"type":"Point"}
}