{
  "type": "Feature",
  "properties": {
    "addr:full":"43665 Rd 745 Smithfield NE 68976",
    "addr:housenumber":"43665",
    "addr:postcode":"68976",
    "addr:street":"Rd 745",
    "iso:country":"US",
    "sg:address":"43665 Rd 745",
    "sg:city":"Smithfield",
    "sg:classifiers":[
        {
            "category":"Real Estate",
            "subcategory":"Real Estate Operator",
            "type":"Services"
        }
    ],
    "sg:phone":"+1 308 472 3709",
    "sg:postcode":"68976",
    "sg:province":"NE",
    "sg:tags":[
        "farm",
        "property",
        "lessor"
    ],
    "wof:name":"D Bergstraesse",
    "wof:placetype":"venue"
},
  "geometry": {"coordinates":[-99.66912600000001,40.626329],"type":"Point"}
}