{
  "type": "Feature",
  "properties": {
    "iso:country":"US",
    "sg:address":"18805 Walnut Dr",
    "sg:city":"Gretna",
    "sg:classifiers":[
        {
            "category":"Building & Trades",
            "subcategory":"Landscaping Services",
            "type":"Services"
        }
    ],
    "sg:phone":"+1 402 332 4499",
    "sg:postcode":"68028",
    "sg:province":"NE",
    "sg:tags":[
        "arborist"
    ],
    "wof:name":"Nature's Touch",
    "wof:placetype":"venue"
},
  "geometry": {"coordinates":[-96.250219,41.044013],"type":"Point"}
}