{
  "type": "Feature",
  "properties": {
    "iso:country":"US",
    "sg:address":"914 Ave D",
    "sg:city":"Gothenburg",
    "sg:classifiers":[
        {
            "category":"Personal",
            "subcategory":"Beauty Salon",
            "type":"Services"
        }
    ],
    "sg:phone":"+1 308 537 7800",
    "sg:postcode":"69138",
    "sg:province":"NE",
    "sg:tags":[
        "spa",
        "day"
    ],
    "wof:name":"Visage Skin Clinic & Day Spa",
    "wof:placetype":"venue"
},
  "geometry": {"coordinates":[-100.163043,40.928606],"type":"Point"}
}