{
  "type": "Feature",
  "properties": {
    "iso:country":"US",
    "sg:address":"1877 Rainbow Ave",
    "sg:city":"Seward",
    "sg:classifiers":[
        {
            "category":"Professional",
            "subcategory":"Detective & Security Services",
            "type":"Services"
        }
    ],
    "sg:phone":"+1 402 643 9476",
    "sg:postcode":"68434",
    "sg:province":"NE",
    "sg:tags":[
        "guard",
        "special"
    ],
    "wof:name":"Edward J Gonzalez",
    "wof:placetype":"venue"
},
  "geometry": {"coordinates":[-97.086984,40.923217],"type":"Point"}
}