{
  "type": "Feature",
  "properties": {
    "addr:full":"304 W 4th St Yankton NE 57078",
    "addr:housenumber":"304",
    "addr:postcode":"57078",
    "addr:street":"W 4Th St",
    "iso:country":"US",
    "sg:address":"304 W 4th St",
    "sg:city":"Yankton",
    "sg:classifiers":[
        {
            "category":"Social Services",
            "type":"Services"
        }
    ],
    "sg:phone":"+1 605 665 8994",
    "sg:postcode":"57078",
    "sg:province":"NE",
    "sg:tags":[
        "organization",
        "welfare"
    ],
    "wof:name":"Yankton Homeless Shelter",
    "wof:placetype":"venue"
},
  "geometry": {"coordinates":[-97.395402,42.871168],"type":"Point"}
}