{
  "type": "Feature",
  "properties": {
    "iso:country":"US",
    "sg:address":"3939 N 48th St",
    "sg:city":"Lincoln",
    "sg:classifiers":[
        {
            "category":"Wholesale",
            "subcategory":"Groceries",
            "type":"Manufacturing & Wholesale Goods"
        }
    ],
    "sg:phone":"+1 402 464 6566",
    "sg:postcode":"68504",
    "sg:province":"NE",
    "sg:tags":[
        "whole",
        "baked"
    ],
    "wof:name":"Garrison Coleman Bakery",
    "wof:placetype":"venue"
},
  "geometry": {"coordinates":[-96.65369099999999,40.852282],"type":"Point"}
}