{
  "type": "Feature",
  "properties": {
    "addr:full":"339 W 4th St Valentine NE 69201",
    "addr:housenumber":"339",
    "addr:postcode":"69201",
    "addr:street":"W 4Th St",
    "iso:country":"US",
    "sg:address":"339 W 4th St",
    "sg:city":"Valentine",
    "sg:classifiers":[
        {
            "category":"Organizations",
            "subcategory":"Religious Organization",
            "type":"Services"
        }
    ],
    "sg:phone":"+1 402 376 2671",
    "sg:postcode":"69201",
    "sg:province":"NE",
    "sg:tags":[
        "church"
    ],
    "wof:name":"Church Of Jesus Christ Of Lds",
    "wof:placetype":"venue"
},
  "geometry": {"coordinates":[-100.554429,42.876115],"type":"Point"}
}