{
  "type": "Feature",
  "properties": {
    "iso:country":"US",
    "sg:address":"10364 S 136th St",
    "sg:city":"Omaha",
    "sg:classifiers":[
        {
            "category":"Professional",
            "type":"Services"
        },
        {
            "category":"Personal",
            "type":"Services"
        },
        {
            "category":"Retail",
            "subcategory":"Event Space",
            "type":"Services"
        },
        {
            "category":"Freight",
            "type":"Transportation"
        }
    ],
    "sg:phone":"+1 402 597 3185",
    "sg:postcode":"68138",
    "sg:province":"NE",
    "sg:tags":[
        "box",
        "full",
        "material",
        "storage",
        "trucking",
        "moving",
        "services-labor",
        "mover",
        "local"
    ],
    "sg:website":"http://northamericanvanlines.com",
    "wof:name":"North American Van Lines",
    "wof:placetype":"venue"
},
  "geometry": {"coordinates":[-96.12709099999999,41.156308],"type":"Point"}
}