{
  "type": "Feature",
  "properties": {
    "addr:full":"101 W David Dr York NE 68467",
    "addr:housenumber":"101",
    "addr:postcode":"68467",
    "addr:street":"W David Dr",
    "iso:country":"US",
    "sg:address":"101 W David Dr",
    "sg:city":"York",
    "sg:classifiers":[
        {
            "category":"Shopping",
            "subcategory":"Department Store",
            "type":"Retail Goods"
        }
    ],
    "sg:phone":"+1 402 362 3366",
    "sg:postcode":"68467",
    "sg:province":"NE",
    "sg:website":"www.walmart.com",
    "wof:name":"Wal-Mart",
    "wof:placetype":"venue"
},
  "geometry": {"coordinates":[-97.59777099999999,40.826699],"type":"Point"}
}