{
  "type": "Feature",
  "properties": {
    "iso:country":"US",
    "sg:address":"1823 O St",
    "sg:city":"Lincoln",
    "sg:classifiers":[
        {
            "category":"Bars & Pubs",
            "type":"Food & Drink"
        }
    ],
    "sg:phone":"+1 402 435 5943",
    "sg:postcode":"68508",
    "sg:province":"NE",
    "sg:tags":[
        "club",
        "night"
    ],
    "wof:name":"Foxy Lady",
    "wof:placetype":"venue"
},
  "geometry": {"coordinates":[-96.694103,40.813479],"type":"Point"}
}