{
  "type": "Feature",
  "properties": {
    "iso:country":"US",
    "sg:address":"919 N B St",
    "sg:city":"Broken Bow",
    "sg:classifiers":[
        {
            "category":"Personal",
            "subcategory":"Beauty Salon",
            "type":"Services"
        }
    ],
    "sg:phone":"+1 308 872 5954",
    "sg:postcode":"68822",
    "sg:province":"NE",
    "sg:tags":[
        "shop"
    ],
    "wof:name":"Sheri's Shoppe",
    "wof:placetype":"venue"
},
  "geometry": {"coordinates":[-99.640964,41.4065],"type":"Point"}
}