{
  "type": "Feature",
  "properties": {
    "iso:country":"US",
    "sg:address":"1003 Chicago Ave",
    "sg:city":"Plattsmouth",
    "sg:classifiers":[
        {
            "category":"Sports & Exercise",
            "subcategory":"Bowling",
            "type":"Entertainment"
        }
    ],
    "sg:phone":"+1 402 296 2700",
    "sg:postcode":"68048",
    "sg:province":"NE",
    "sg:tags":[
        "center"
    ],
    "wof:name":"Cr Lanes",
    "wof:placetype":"venue"
},
  "geometry": {"coordinates":[-95.894952,41.002356],"type":"Point"}
}