{
  "type": "Feature",
  "properties": {
    "addr:full":"216 Lincoln Ave Hebron NE 68370",
    "addr:housenumber":"216",
    "addr:postcode":"68370",
    "addr:street":"Lincoln Ave",
    "iso:country":"US",
    "sg:address":"216 Lincoln Ave",
    "sg:city":"Hebron",
    "sg:classifiers":[
        {
            "category":"Organizations",
            "subcategory":"Professional Association",
            "type":"Services"
        }
    ],
    "sg:phone":"+1 402 768 7156",
    "sg:postcode":"68370",
    "sg:province":"NE",
    "sg:tags":[
        "chambers",
        "commerce"
    ],
    "wof:name":"Hebron Chamber Of Commerce",
    "wof:placetype":"venue"
},
  "geometry": {"coordinates":[-97.593181,40.166734],"type":"Point"}
}