{
  "type": "Feature",
  "properties": {
    "iso:country":"US",
    "sg:address":"3390 E 92nd St",
    "sg:city":"Kearney",
    "sg:classifiers":[
        {
            "category":"Building & Trades",
            "subcategory":"Construction",
            "type":"Services"
        }
    ],
    "sg:phone":"+1 308 338 1433",
    "sg:postcode":"68847",
    "sg:province":"NE",
    "sg:tags":[
        "fencing"
    ],
    "wof:name":"Mc Neil Fencing",
    "wof:placetype":"venue"
},
  "geometry": {"coordinates":[-99.038488,40.764629],"type":"Point"}
}