{
  "type": "Feature",
  "properties": {
    "iso:country":"US",
    "sg:address":"4003 Fox Ridge Cir",
    "sg:city":"Bellevue",
    "sg:classifiers":[
        {
            "category":"Professional",
            "subcategory":"Computer Services",
            "type":"Services"
        }
    ],
    "sg:phone":"+1 402 292 0399",
    "sg:postcode":"68123",
    "sg:province":"NE",
    "wof:name":"Thoma Computers",
    "wof:placetype":"venue"
},
  "geometry": {"coordinates":[-95.974756,41.105328],"type":"Point"}
}