{
  "type": "Feature",
  "properties": {
    "iso:country":"US",
    "sg:address":"3236 Bachman St",
    "sg:city":"Grand Island",
    "sg:classifiers":[
        {
            "category":"Building & Trades",
            "subcategory":"Construction",
            "type":"Services"
        }
    ],
    "sg:phone":"+1 308 389 4954",
    "sg:postcode":"68803",
    "sg:province":"NE",
    "sg:tags":[
        "ceiling"
    ],
    "wof:name":"T C Ceilings Inc",
    "wof:placetype":"venue"
},
  "geometry": {"coordinates":[-98.375888,40.907363],"type":"Point"}
}