{
  "type": "Feature",
  "properties": {
    "iso:country":"US",
    "sg:address":"202 N 5th St",
    "sg:city":"Plainview",
    "sg:classifiers":[
        {
            "category":"Freight",
            "type":"Transportation"
        }
    ],
    "sg:phone":"+1 402 582 3315",
    "sg:postcode":"68769",
    "sg:province":"NE",
    "sg:tags":[
        "livestock",
        "hauling"
    ],
    "wof:name":"Mosel Feed & Trucking",
    "wof:placetype":"venue"
},
  "geometry": {"coordinates":[-97.782309,42.353182],"type":"Point"}
}