{
  "type": "Feature",
  "properties": {
    "iso:country":"US",
    "sg:address":"803 N Kimball St",
    "sg:city":"Grand Island",
    "sg:classifiers":[
        {
            "category":"Social Services",
            "subcategory":"Child Care",
            "type":"Services"
        }
    ],
    "sg:phone":"+1 308 382 0382",
    "sg:postcode":"68801",
    "sg:province":"NE",
    "sg:tags":[
        "day"
    ],
    "wof:name":"Kimball Street Childcare",
    "wof:placetype":"venue"
},
  "geometry": {"coordinates":[-98.342405,40.933334],"type":"Point"}
}