{
  "type": "Feature",
  "properties": {
    "iso:country":"US",
    "sg:address":"2397 Q Rd",
    "sg:city":"Dwight",
    "sg:phone":"+1 402 566 2595",
    "sg:postcode":"68635",
    "sg:province":"NE",
    "sg:tags":[
        "farm",
        "corn"
    ],
    "wof:name":"Don Bohuslausky",
    "wof:placetype":"venue"
},
  "geometry": {"coordinates":[-97.062253,41.084485],"type":"Point"}
}