{
  "type": "Feature",
  "properties": {
    "iso:country":"US",
    "sg:address":"26404 W Center Rd",
    "sg:city":"Waterloo",
    "sg:classifiers":[
        {
            "category":"Food & Beverages",
            "subcategory":"Groceries & Convenience Stores",
            "type":"Retail Goods"
        }
    ],
    "sg:phone":"+1 402 359 5638",
    "sg:postcode":"68069",
    "sg:province":"NE",
    "sg:tags":[
        "station",
        "gasoline"
    ],
    "wof:name":"Merchant Of Venice",
    "wof:placetype":"venue"
},
  "geometry": {"coordinates":[-96.330375,41.233856],"type":"Point"}
}