{
  "type": "Feature",
  "properties": {
    "iso:country":"US",
    "sg:address":"121 S State St",
    "sg:city":"Osceola",
    "sg:classifiers":[
        {
            "category":"Education",
            "subcategory":"School",
            "type":"Public Place"
        }
    ],
    "sg:phone":"+1 402 747 2119",
    "sg:postcode":"68651",
    "sg:province":"NE",
    "wof:name":"Helping Hands Pre-School",
    "wof:placetype":"venue"
},
  "geometry": {"coordinates":[-97.54800899999999,41.176356],"type":"Point"}
}