{
  "type": "Feature",
  "properties": {
    "iso:country":"US",
    "sg:address":"52991 State Hwy 59",
    "sg:city":"Creighton",
    "sg:classifiers":[
        {
            "category":"Retail",
            "subcategory":"Animal Services",
            "type":"Services"
        }
    ],
    "sg:phone":"+1 402 358 5547",
    "sg:postcode":"68729",
    "sg:province":"NE",
    "sg:tags":[
        "pet",
        "grooming",
        "washing"
    ],
    "wof:name":"Wag N Tail Pet Parlor",
    "wof:placetype":"venue"
},
  "geometry": {"coordinates":[-97.919811,42.466559],"type":"Point"}
}