{
  "type": "Feature",
  "properties": {
    "iso:country":"US",
    "sg:address":"3920 2nd Ave",
    "sg:city":"Kearney",
    "sg:classifiers":[
        {
            "category":"Food & Beverages",
            "subcategory":"Bakery",
            "type":"Retail Goods"
        }
    ],
    "sg:phone":"+1 308 236 5488",
    "sg:postcode":"68847",
    "sg:province":"NE",
    "sg:tags":[
        "baker"
    ],
    "wof:name":"Sun Mart Foods",
    "wof:placetype":"venue"
},
  "geometry": {"coordinates":[-99.08404299999999,40.714264],"type":"Point"}
}