{
  "type": "Feature",
  "properties": {
    "iso:country":"US",
    "sg:address":"3520 N 20th St",
    "sg:city":"Lincoln",
    "sg:classifiers":[
        {
            "category":"Wholesale",
            "subcategory":"Meat",
            "type":"Manufacturing & Wholesale Goods"
        }
    ],
    "sg:phone":"+1 402 438 3560",
    "sg:postcode":"68521",
    "sg:province":"NE",
    "wof:name":"Hart Meat Brokers",
    "wof:placetype":"venue"
},
  "geometry": {"coordinates":[-96.691621,40.845442],"type":"Point"}
}