{
  "type": "Feature",
  "properties": {
    "addr:full":"629 N 98th St Omaha NE 68114",
    "addr:housenumber":"629",
    "addr:postcode":"68114",
    "addr:street":"N 98Th St",
    "iso:country":"US",
    "sg:address":"629 N 98th St",
    "sg:city":"Omaha",
    "sg:classifiers":[
        {
            "category":"Shopping",
            "subcategory":"Clothing, Apparel, & Fashions",
            "type":"Retail Goods"
        }
    ],
    "sg:phone":"+1 402 397 9394",
    "sg:postcode":"68114",
    "sg:province":"NE",
    "sg:tags":[
        "maternity"
    ],
    "wof:name":"Motherhood Maternity",
    "wof:placetype":"venue"
},
  "geometry": {"coordinates":[-96.06537299999999,41.265234],"type":"Point"}
}