{
  "type": "Feature",
  "properties": {
    "iso:country":"US",
    "sg:address":"225 N 4th St",
    "sg:city":"Lynch",
    "sg:classifiers":[
        {
            "category":"Utilities",
            "subcategory":"Telephone",
            "type":"Services"
        }
    ],
    "sg:phone":"+1 402 569 2666",
    "sg:postcode":"68758",
    "sg:province":"NE",
    "sg:tags":[
        "company"
    ],
    "sg:website":"www.threeriver.net",
    "wof:name":"Three River Telco",
    "wof:placetype":"venue"
},
  "geometry": {"coordinates":[-97.779325,41.748204],"type":"Point"}
}