{
  "type": "Feature",
  "properties": {
    "iso:country":"US",
    "sg:address":"704 W 11th St",
    "sg:city":"Grand Island",
    "sg:classifiers":[
        {
            "category":"Wholesale",
            "subcategory":"Vending Machines",
            "type":"Manufacturing & Wholesale Goods"
        },
        {
            "category":"Restaurant",
            "type":"Food & Drink"
        }
    ],
    "sg:phone":"+1 308 382 0084",
    "sg:postcode":"68801",
    "sg:province":"NE",
    "sg:tags":[
        "operator",
        "eating"
    ],
    "wof:name":"Tami's Treats",
    "wof:placetype":"venue"
},
  "geometry": {"coordinates":[-98.352823,40.931934],"type":"Point"}
}