{
  "type": "Feature",
  "properties": {
    "iso:country":"US",
    "sg:address":"14655 California St",
    "sg:city":"Omaha",
    "sg:classifiers":[
        {
            "category":"Freight",
            "type":"Transportation"
        }
    ],
    "sg:phone":"+1 402 493 7201",
    "sg:postcode":"68154",
    "sg:province":"NE",
    "sg:tags":[
        "truck"
    ],
    "sg:website":"www.tmanetwork.com",
    "wof:name":"Trans/Mid-America Inc",
    "wof:placetype":"venue"
},
  "geometry": {"coordinates":[-96.145207,41.264539],"type":"Point"}
}