{
  "type": "Feature",
  "properties": {
    "iso:country":"US",
    "sg:address":"106 S Podunk Ave",
    "sg:city":"Callaway",
    "sg:classifiers":[
        {
            "category":"Personal",
            "subcategory":"Beauty Salon",
            "type":"Services"
        }
    ],
    "sg:phone":"+1 308 836 2743",
    "sg:postcode":"68825",
    "sg:province":"NE",
    "wof:name":"Waleta's Hair World",
    "wof:placetype":"venue"
},
  "geometry": {"coordinates":[-99.927593,41.290366],"type":"Point"}
}