{
  "type": "Feature",
  "properties": {
    "iso:country":"US",
    "sg:address":"1347 N 38th St",
    "sg:city":"Lincoln",
    "sg:classifiers":[
        {
            "category":"Building & Trades",
            "subcategory":"Cleaning & Sanitation",
            "type":"Services"
        }
    ],
    "sg:phone":"+1 402 429 6643",
    "sg:postcode":"68503",
    "sg:province":"NE",
    "sg:tags":[
        "maintenance"
    ],
    "wof:name":"Fosters Cleaning Service",
    "wof:placetype":"venue"
},
  "geometry": {"coordinates":[-96.66637,40.827483],"type":"Point"}
}