{
  "type": "Feature",
  "properties": {
    "iso:country":"US",
    "sg:address":"775 Commercial Park Rd",
    "sg:city":"Wahoo",
    "sg:classifiers":[
        {
            "category":"Retail",
            "subcategory":"Repair Shop",
            "type":"Services"
        }
    ],
    "sg:phone":"+1 402 443 3123",
    "sg:postcode":"68066",
    "sg:province":"NE",
    "sg:tags":[
        "farm",
        "equipment",
        "parts"
    ],
    "sg:website":"www.wahooimplement.com",
    "wof:name":"Platte Valley Equipment Co",
    "wof:placetype":"venue"
},
  "geometry": {"coordinates":[-96.604378,41.234284],"type":"Point"}
}