{
  "type": "Feature",
  "properties": {
    "iso:country":"US",
    "sg:address":"3617 S 116th St",
    "sg:city":"Omaha",
    "sg:classifiers":[
        {
            "category":"Shopping",
            "subcategory":"Clothing, Apparel, & Fashions",
            "type":"Retail Goods"
        }
    ],
    "sg:phone":"+1 402 334 1605",
    "sg:postcode":"68144",
    "sg:province":"NE",
    "sg:tags":[
        "brassiere"
    ],
    "wof:name":"Cameo-Figurettes",
    "wof:placetype":"venue"
},
  "geometry": {"coordinates":[-96.094523,41.223485],"type":"Point"}
}