{
  "type": "Feature",
  "properties": {
    "addr:full":"1405 Jackson St Omaha NE 68102",
    "addr:housenumber":"1405",
    "addr:postcode":"68102",
    "addr:street":"Jackson St",
    "iso:country":"US",
    "sg:address":"1405 Jackson St",
    "sg:city":"Omaha",
    "sg:classifiers":[
        {
            "category":"Manufacturing",
            "subcategory":"Tools & Machinery",
            "type":"Manufacturing & Wholesale Goods"
        }
    ],
    "sg:phone":"+1 402 341 3177",
    "sg:postcode":"68102",
    "sg:province":"NE",
    "sg:tags":[
        "pattern",
        "industrial",
        "mfg"
    ],
    "wof:name":"Oehrle & Bergman Pattern Shop",
    "wof:placetype":"venue"
},
  "geometry": {"coordinates":[-95.935838,41.25436],"type":"Point"}
}