{
  "type": "Feature",
  "properties": {
    "iso:country":"US",
    "sg:address":"12201 W Holdrege St",
    "sg:city":"Lincoln",
    "sg:classifiers":[
        {
            "category":"Building & Trades",
            "subcategory":"Construction",
            "type":"Services"
        }
    ],
    "sg:phone":"+1 402 580 7490",
    "sg:postcode":"68528",
    "sg:province":"NE",
    "sg:tags":[
        "home",
        "builder"
    ],
    "wof:name":"Everson Construction Inc",
    "wof:placetype":"venue"
},
  "geometry": {"coordinates":[-96.887118,40.828391],"type":"Point"}
}