{
  "type": "Feature",
  "properties": {
    "addr:full":"1120 Arbor St Omaha NE 68108",
    "addr:housenumber":"1120",
    "addr:postcode":"68108",
    "addr:street":"Arbor St",
    "iso:country":"US",
    "sg:address":"1120 Arbor St",
    "sg:city":"Omaha",
    "sg:classifiers":[
        {
            "category":"Professional",
            "subcategory":"Business Services",
            "type":"Services"
        }
    ],
    "sg:phone":"+1 402 330 1866",
    "sg:postcode":"68108",
    "sg:province":"NE",
    "sg:tags":[
        "inbound",
        "call",
        "center"
    ],
    "wof:name":"Great Plains One-Call",
    "wof:placetype":"venue"
},
  "geometry": {"coordinates":[-95.93184599999999,41.236115],"type":"Point"}
}