{
  "type": "Feature",
  "properties": {
    "iso:country":"US",
    "sg:address":"4808 S 132nd St",
    "sg:city":"Omaha",
    "sg:classifiers":[
        {
            "category":"Insurance",
            "subcategory":"Insurance Agent",
            "type":"Services"
        },
        {
            "category":"Insurance",
            "subcategory":"Hazard Insurance",
            "type":"Services"
        },
        {
            "category":"Insurance",
            "subcategory":"Title Insurance",
            "type":"Services"
        }
    ],
    "sg:phone":"+1 402 398 9660",
    "sg:postcode":"68137",
    "sg:province":"NE",
    "sg:tags":[
        "auto",
        "homeowner"
    ],
    "sg:website":"http://apps.amfam.com/agentlocator/DKROUPA?sourceid=yp3",
    "wof:name":"American Family Insurance- David Kroupa Agency Inc",
    "wof:placetype":"venue"
},
  "geometry": {"coordinates":[-96.11953,41.211202],"type":"Point"}
}