{
  "type": "Feature",
  "properties": {
    "iso:country":"US",
    "sg:address":"3111 23rd St",
    "sg:city":"Columbus",
    "sg:classifiers":[
        {
            "category":"Restaurant",
            "type":"Food & Drink"
        }
    ],
    "sg:phone":"+1 402 564 6252",
    "sg:postcode":"68601",
    "sg:province":"NE",
    "sg:tags":[
        "eating"
    ],
    "wof:name":"Amigos",
    "wof:placetype":"venue"
},
  "geometry": {"coordinates":[-97.366669,41.438631],"type":"Point"}
}