{
  "type": "Feature",
  "properties": {
    "addr:full":"680 159th Pleasant Dale NE 68423",
    "addr:housenumber":"680",
    "addr:postcode":"68423",
    "addr:street":"159Th Pleasant Dale Ne",
    "iso:country":"US",
    "sg:address":"680 159th",
    "sg:city":"Pleasant Dale",
    "sg:classifiers":[
        {
            "category":"Freight",
            "type":"Transportation"
        }
    ],
    "sg:phone":"+1 402 795 3370",
    "sg:postcode":"68423",
    "sg:province":"NE",
    "sg:tags":[
        "grain",
        "elevator"
    ],
    "wof:name":"Farmers Cooperative",
    "wof:placetype":"venue"
},
  "geometry": {"coordinates":[-96.93533499999999,40.784737],"type":"Point"}
}