{
  "type": "Feature",
  "properties": {
    "addr:full":"3804 Dakota Ave South Sioux City NE 68776",
    "addr:housenumber":"3804",
    "addr:postcode":"68776",
    "addr:street":"Dakota Ave",
    "iso:country":"US",
    "sg:address":"3804 Dakota Ave",
    "sg:city":"South Sioux City",
    "sg:classifiers":[
        {
            "category":"Autos & Motor Vehicles",
            "subcategory":"Automobile Sales",
            "type":"Retail Goods"
        }
    ],
    "sg:phone":"+1 402 494 2266",
    "sg:postcode":"68776",
    "sg:province":"NE",
    "sg:tags":[
        "car",
        "dealer"
    ],
    "wof:name":"NTS Auto Sales",
    "wof:placetype":"venue"
},
  "geometry": {"coordinates":[-96.413944,42.453083],"type":"Point"}
}