{
  "type": "Feature",
  "properties": {
    "iso:country":"US",
    "sg:address":"125 E 23rd St",
    "sg:city":"Kearney",
    "sg:classifiers":[
        {
            "category":"Health Services",
            "subcategory":"Nursing And Care Facility",
            "type":"Services"
        }
    ],
    "sg:phone":"+1 308 234 2447",
    "sg:postcode":"68847",
    "sg:province":"NE",
    "sg:tags":[
        "home",
        "convalescent"
    ],
    "wof:name":"Mother Hull Home",
    "wof:placetype":"venue"
},
  "geometry": {"coordinates":[-99.080066,40.698569],"type":"Point"}
}