{
  "type": "Feature",
  "properties": {
    "addr:full":"805 N 13th St Beatrice NE 68310",
    "addr:housenumber":"805",
    "addr:postcode":"68310",
    "addr:street":"N 13Th St",
    "iso:country":"US",
    "sg:address":"805 N 13th St",
    "sg:city":"Beatrice",
    "sg:classifiers":[
        {
            "category":"Retail",
            "subcategory":"Animal Services",
            "type":"Services"
        }
    ],
    "sg:phone":"+1 402 223 3830",
    "sg:postcode":"68310",
    "sg:province":"NE",
    "sg:tags":[
        "pet",
        "grooming",
        "washing"
    ],
    "wof:name":"Ann's Grooming Svc",
    "wof:placetype":"venue"
},
  "geometry": {"coordinates":[-96.737325,40.273887],"type":"Point"}
}