{
  "type": "Feature",
  "properties": {
    "addr:full":"1309 Harlan Dr Bellevue NE 68005",
    "addr:housenumber":"1309",
    "addr:postcode":"68005",
    "addr:street":"Harlan Dr",
    "iso:country":"US",
    "sg:address":"1309 Harlan Dr",
    "sg:city":"Bellevue",
    "sg:classifiers":[
        {
            "category":"Education",
            "subcategory":"Special Training",
            "type":"Public Place"
        }
    ],
    "sg:phone":"+1 402 884 7092",
    "sg:postcode":"68005",
    "sg:province":"NE",
    "sg:tags":[
        "aircraft",
        "school"
    ],
    "wof:name":"Embry Riddle Aeronauticall",
    "wof:placetype":"venue"
},
  "geometry": {"coordinates":[-95.910465,41.141128],"type":"Point"}
}