{
  "type": "Feature",
  "properties": {
    "iso:country":"US",
    "sg:address":"702 Bordeaux Rd",
    "sg:city":"Chadron",
    "sg:classifiers":[
        {
            "category":"Farming",
            "subcategory":"Livestock Farm",
            "type":"Manufacturing & Wholesale Goods"
        }
    ],
    "sg:phone":"+1 308 432 5201",
    "sg:postcode":"69337",
    "sg:province":"NE",
    "sg:tags":[
        "ranch"
    ],
    "wof:name":"Rickenbach Bieganski Ranch",
    "wof:placetype":"venue"
},
  "geometry": {"coordinates":[-102.911297,42.760183],"type":"Point"}
}