{
  "type": "Feature",
  "properties": {
    "iso:country":"US",
    "sg:address":"8803 Berry Hill Rd",
    "sg:city":"Blair",
    "sg:classifiers":[
        {
            "category":"Autos & Motor Vehicles",
            "subcategory":"Recreational Vehicle Sales",
            "type":"Retail Goods"
        }
    ],
    "sg:phone":"+1 402 426 5550",
    "sg:postcode":"68008",
    "sg:province":"NE",
    "sg:tags":[
        "canopy",
        "shell",
        "truck",
        "cap"
    ],
    "sg:website":"www.bdtrucks.com",
    "wof:name":"B & D Truck Parts",
    "wof:placetype":"venue"
},
  "geometry": {"coordinates":[-96.158163,41.506313],"type":"Point"}
}