{
  "type": "Feature",
  "properties": {
    "iso:country":"US",
    "sg:address":"10402 S 15th St",
    "sg:city":"Bellevue",
    "sg:classifiers":[
        {
            "category":"Restaurant",
            "type":"Food & Drink"
        }
    ],
    "sg:menulink":"http://www.allmenus.com/ne/bellevue/89742-applebees/menu/",
    "sg:phone":"+1 402 293 8400",
    "sg:postcode":"68123",
    "sg:province":"NE",
    "sg:tags":[
        "burger",
        "american",
        "sandwich",
        "soup"
    ],
    "wof:name":"Applebee's",
    "wof:placetype":"venue"
},
  "geometry": {"coordinates":[-95.935452,41.159332],"type":"Point"}
}