{
  "type": "Feature",
  "properties": {
    "iso:country":"US",
    "sg:address":"13430 Industrial Rd",
    "sg:city":"Omaha",
    "sg:classifiers":[
        {
            "category":"Wholesale",
            "subcategory":"Office Equipment",
            "type":"Manufacturing & Wholesale Goods"
        }
    ],
    "sg:phone":"+1 402 697 1100",
    "sg:postcode":"68137",
    "sg:province":"NE",
    "sg:tags":[
        "product"
    ],
    "wof:name":"US Office Products",
    "wof:placetype":"venue"
},
  "geometry": {"coordinates":[-96.12830099999999,41.216855],"type":"Point"}
}