{
  "type": "Feature",
  "properties": {
    "iso:country":"US",
    "sg:address":"19052 Co Rd 5",
    "sg:city":"Herman",
    "sg:classifiers":[
        {
            "category":"Professional",
            "type":"Services"
        }
    ],
    "sg:phone":"+1 402 654 2400",
    "sg:postcode":"68029",
    "sg:province":"NE",
    "sg:tags":[
        "establishment"
    ],
    "wof:name":"Mcmains",
    "wof:placetype":"venue"
},
  "geometry": {"coordinates":[-96.405728,41.662382],"type":"Point"}
}