{
  "type": "Feature",
  "properties": {
    "iso:country":"US",
    "sg:address":"301 E 6th St",
    "sg:city":"Fremont",
    "sg:classifiers":[
        {
            "category":"Banks & Credit Unions",
            "subcategory":"Investment Brokerage",
            "type":"Services"
        }
    ],
    "sg:phone":"+1 402 721 0809",
    "sg:postcode":"68025",
    "sg:province":"NE",
    "sg:tags":[
        "security"
    ],
    "wof:name":"Calton & Assoc Inc",
    "wof:placetype":"venue"
},
  "geometry": {"coordinates":[-96.49476,41.434636],"type":"Point"}
}