{
  "type": "Feature",
  "properties": {
    "iso:country":"US",
    "sg:address":"2621 W 6th St",
    "sg:city":"Hastings",
    "sg:classifiers":[
        {
            "category":"Building & Trades",
            "subcategory":"Construction",
            "type":"Services"
        }
    ],
    "sg:phone":"+1 402 463 6517",
    "sg:postcode":"68901",
    "sg:province":"NE",
    "sg:tags":[
        "downspouts",
        "gutter"
    ],
    "wof:name":"Hastings Seamless Gutter Co",
    "wof:placetype":"venue"
},
  "geometry": {"coordinates":[-98.417241,40.589051],"type":"Point"}
}