{
  "type": "Feature",
  "properties": {
    "addr:full":"312 Norris Ave Mc Cook NE 69001",
    "addr:housenumber":"312",
    "addr:postcode":"69001",
    "addr:street":"Norris Ave Mc",
    "iso:country":"US",
    "sg:address":"312 Norris Ave",
    "sg:city":"Mc Cook",
    "sg:classifiers":[
        {
            "category":"Food & Beverages",
            "subcategory":"Bakery",
            "type":"Retail Goods"
        }
    ],
    "sg:phone":"+1 308 345 6500",
    "sg:postcode":"69001",
    "sg:province":"NE",
    "sg:tags":[
        "baker"
    ],
    "wof:name":"Sehnert Bakery & Bieroc Cafe",
    "wof:placetype":"venue"
},
  "geometry": {"coordinates":[-100.625902,40.20052],"type":"Point"}
}