{
  "type": "Feature",
  "properties": {
    "iso:country":"US",
    "sg:address":"1221 Ave B",
    "sg:city":"Plattsmouth",
    "sg:classifiers":[
        {
            "category":"Building & Trades",
            "subcategory":"Construction",
            "type":"Services"
        }
    ],
    "sg:phone":"+1 402 298 7197",
    "sg:postcode":"68048",
    "sg:province":"NE",
    "sg:tags":[
        "fish",
        "pool"
    ],
    "wof:name":"Pondscapes",
    "wof:placetype":"venue"
},
  "geometry": {"coordinates":[-95.89367900000001,41.013431],"type":"Point"}
}