{
  "type": "Feature",
  "properties": {
    "iso:country":"US",
    "sg:address":"505 N Madison St",
    "sg:city":"Lexington",
    "sg:classifiers":[
        {
            "category":"Insurance",
            "subcategory":"Insurance Agent",
            "type":"Services"
        }
    ],
    "sg:phone":"+1 308 324 6645",
    "sg:postcode":"68850",
    "sg:province":"NE",
    "wof:name":"Roger R Batt Insurance",
    "wof:placetype":"venue"
},
  "geometry": {"coordinates":[-99.74434599999999,40.778283],"type":"Point"}
}