{
  "type": "Feature",
  "properties": {
    "iso:country":"US",
    "sg:address":"8303 Dodge St Ste 225",
    "sg:city":"Omaha",
    "sg:classifiers":[
        {
            "category":"Health Services",
            "subcategory":"Doctor",
            "type":"Services"
        }
    ],
    "sg:phone":"+1 402 218 4123",
    "sg:postcode":"68114",
    "sg:province":"NE",
    "sg:tags":[
        "physician",
        "oncology",
        "family",
        "practice",
        "surgeons",
        "medicine",
        "surgeon"
    ],
    "sg:website":"http://www.oacancer.com",
    "wof:name":"Oncology Associates PC",
    "wof:placetype":"venue"
},
  "geometry": {"coordinates":[-96.041359,41.25967],"type":"Point"}
}