{
  "type": "Feature",
  "properties": {
    "iso:country":"US",
    "sg:address":"143 S 6th St",
    "sg:city":"Seward",
    "sg:classifiers":[
        {
            "category":"Professional",
            "subcategory":"Lawyer & Legal Services",
            "type":"Services"
        }
    ],
    "sg:phone":"+1 402 643 2552",
    "sg:postcode":"68434",
    "sg:province":"NE",
    "sg:tags":[
        "attorney"
    ],
    "wof:name":"Pollack & Ball",
    "wof:placetype":"venue"
},
  "geometry": {"coordinates":[-97.099142,40.907404],"type":"Point"}
}