{
  "type": "Feature",
  "properties": {
    "addr:full":"4222 Davenport St Omaha NE 68131",
    "addr:housenumber":"4222",
    "addr:postcode":"68131",
    "addr:street":"Davenport St",
    "iso:country":"US",
    "sg:address":"4222 Davenport St",
    "sg:city":"Omaha",
    "sg:classifiers":[
        {
            "category":"Professional",
            "subcategory":"Computer Services",
            "type":"Services"
        }
    ],
    "sg:phone":"+1 402 932 1664",
    "sg:postcode":"68131",
    "sg:province":"NE",
    "sg:tags":[
        "programing",
        "custom"
    ],
    "wof:name":"Turtle Software Solutions LLC",
    "wof:placetype":"venue"
},
  "geometry": {"coordinates":[-95.977102,41.261287],"type":"Point"}
}