{
  "type": "Feature",
  "properties": {
    "iso:country":"US",
    "sg:address":"6500 Princeton Rd",
    "sg:city":"Firth",
    "sg:classifiers":[
        {
            "category":"Building & Trades",
            "subcategory":"Construction",
            "type":"Services"
        }
    ],
    "sg:phone":"+1 402 430 6700",
    "sg:postcode":"68358",
    "sg:province":"NE",
    "sg:tags":[
        "carpentry",
        "general",
        "contract",
        "contractor"
    ],
    "wof:name":"Schroeder Construction Co",
    "wof:placetype":"venue"
},
  "geometry": {"coordinates":[-96.63603500000001,40.567071],"type":"Point"}
}