{
  "type": "Feature",
  "properties": {
    "addr:full":"2723 N 63rd St Omaha NE 68104",
    "addr:housenumber":"2723",
    "addr:postcode":"68104",
    "addr:street":"N 63Rd St",
    "iso:country":"US",
    "sg:address":"2723 N 63rd St",
    "sg:city":"Omaha",
    "sg:classifiers":[
        {
            "category":"Shopping",
            "subcategory":"Bicycles & Sporting Goods",
            "type":"Retail Goods"
        }
    ],
    "sg:phone":"+1 402 556 2453",
    "sg:postcode":"68104",
    "sg:province":"NE",
    "sg:tags":[
        "bike"
    ],
    "wof:name":"Bike Pedlar the",
    "wof:placetype":"venue"
},
  "geometry": {"coordinates":[-96.009697,41.283901],"type":"Point"}
}