{
  "type": "Feature",
  "properties": {
    "iso:country":"US",
    "sg:address":"3306 Lynnwood Dr",
    "sg:city":"Bellevue",
    "sg:classifiers":[
        {
            "category":"Professional",
            "subcategory":"Computer Services",
            "type":"Services"
        }
    ],
    "sg:phone":"+1 402 291 3416",
    "sg:postcode":"68123",
    "sg:province":"NE",
    "sg:tags":[
        "programing",
        "custom"
    ],
    "wof:name":"S&R PC Repair & Web Desig",
    "wof:placetype":"venue"
},
  "geometry": {"coordinates":[-95.96132,41.115026],"type":"Point"}
}