{
  "type": "Feature",
  "properties": {
    "addr:full":"401 W 3rd St Oshkosh NE 69154",
    "addr:housenumber":"401",
    "addr:postcode":"69154",
    "addr:street":"W 3Rd St",
    "iso:country":"US",
    "sg:address":"401 W 3rd St",
    "sg:city":"Oshkosh",
    "sg:classifiers":[
        {
            "category":"Organizations",
            "subcategory":"Religious Organization",
            "type":"Services"
        }
    ],
    "sg:phone":"+1 308 772 3537",
    "sg:postcode":"69154",
    "sg:province":"NE",
    "sg:tags":[
        "church"
    ],
    "wof:name":"United Methodist Church",
    "wof:placetype":"venue"
},
  "geometry": {"coordinates":[-102.348816,41.406909],"type":"Point"}
}