{
  "type": "Feature",
  "properties": {
    "iso:country":"US",
    "sg:address":"8 W 23rd St",
    "sg:city":"Kearney",
    "sg:classifiers":[
        {
            "category":"Shopping",
            "subcategory":"Used Merchandise",
            "type":"Retail Goods"
        }
    ],
    "sg:phone":"+1 308 293 0031",
    "sg:postcode":"68847",
    "sg:province":"NE",
    "sg:tags":[
        "book",
        "rare",
        "dealer"
    ],
    "wof:name":"Book Ends",
    "wof:placetype":"venue"
},
  "geometry": {"coordinates":[-99.083015,40.698613],"type":"Point"}
}