{
  "type": "Feature",
  "properties": {
    "iso:country":"US",
    "sg:address":"4300 O St",
    "sg:city":"Lincoln",
    "sg:classifiers":[
        {
            "category":"Retail",
            "subcategory":"Funeral Services",
            "type":"Services"
        }
    ],
    "sg:phone":"+1 402 476 1225",
    "sg:postcode":"68510",
    "sg:province":"NE",
    "sg:tags":[
        "director"
    ],
    "sg:website":"www.roperandsons.com",
    "wof:name":"Roper Inc Monuments",
    "wof:placetype":"venue"
},
  "geometry": {"coordinates":[-96.66031,40.813604],"type":"Point"}
}