{
  "type": "Feature",
  "properties": {
    "iso:country":"US",
    "sg:address":"1010 Ivy St",
    "sg:city":"Stanton",
    "sg:classifiers":[
        {
            "category":"Shopping",
            "subcategory":"Gifts & Souvenirs",
            "type":"Retail Goods"
        }
    ],
    "sg:phone":"+1 402 439 2700",
    "sg:postcode":"68779",
    "sg:province":"NE",
    "sg:tags":[
        "shop"
    ],
    "wof:name":"Footeworks",
    "wof:placetype":"venue"
},
  "geometry": {"coordinates":[-97.225025,41.950461],"type":"Point"}
}