{
  "type": "Feature",
  "properties": {
    "iso:country":"US",
    "sg:address":"610 Keene St",
    "sg:city":"Ansley",
    "sg:classifiers":[
        {
            "category":"Organizations",
            "subcategory":"Religious Organization",
            "type":"Services"
        }
    ],
    "sg:phone":"+1 308 935 1308",
    "sg:postcode":"68814",
    "sg:province":"NE",
    "sg:tags":[
        "church"
    ],
    "wof:name":"United Methodist Church",
    "wof:placetype":"venue"
},
  "geometry": {"coordinates":[-99.38096400000001,41.286937],"type":"Point"}
}