{
  "type": "Feature",
  "properties": {
    "iso:country":"US",
    "sg:address":"1751 US Hwy 6",
    "sg:city":"Saronville",
    "sg:phone":"+1 402 773 5483",
    "sg:postcode":"68901",
    "sg:province":"NE",
    "sg:tags":[
        "farm",
        "corn",
        "beef",
        "feedlot",
        "cattle"
    ],
    "wof:name":"Paul Drudik",
    "wof:placetype":"venue"
},
  "geometry": {"coordinates":[-98.40700699999999,40.567882],"type":"Point"}
}