{
  "type": "Feature",
  "properties": {
    "iso:country":"US",
    "sg:address":"8116 Park View Blvd",
    "sg:city":"La Vista",
    "sg:classifiers":[
        {
            "category":"Recreation",
            "type":"Entertainment"
        }
    ],
    "sg:phone":"+1 402 331 3455",
    "sg:postcode":"68128",
    "sg:province":"NE",
    "sg:tags":[
        "hall",
        "auditorium"
    ],
    "sg:website":"www.lavista.govoffice.com",
    "wof:name":"LA Vista Community Ctr",
    "wof:placetype":"venue"
},
  "geometry": {"coordinates":[-96.039334,41.187037],"type":"Point"}
}