{
  "type": "Feature",
  "properties": {
    "addr:full":"1115 E 25th St Kearney NE 68847",
    "addr:housenumber":"1115",
    "addr:postcode":"68847",
    "addr:street":"E 25Th St",
    "iso:country":"US",
    "sg:address":"1115 E 25th St",
    "sg:city":"Kearney",
    "sg:classifiers":[
        {
            "category":"Bars & Pubs",
            "type":"Food & Drink"
        }
    ],
    "sg:phone":"+1 308 236 6209",
    "sg:postcode":"68847",
    "sg:province":"NE",
    "wof:name":"Chug A Lug Bar & Grill",
    "wof:placetype":"venue"
},
  "geometry": {"coordinates":[-99.067189,40.700032],"type":"Point"}
}