{
  "type": "Feature",
  "properties": {
    "iso:country":"US",
    "sg:address":"707 15th St",
    "sg:city":"Auburn",
    "sg:classifiers":[
        {
            "category":"Retail",
            "subcategory":"Funeral Services",
            "type":"Services"
        }
    ],
    "sg:phone":"+1 402 274 3131",
    "sg:postcode":"68305",
    "sg:province":"NE",
    "sg:tags":[
        "director"
    ],
    "wof:name":"Hall Funeral Chapel",
    "wof:placetype":"venue"
},
  "geometry": {"coordinates":[-95.835987,40.389625],"type":"Point"}
}