{
  "type": "Feature",
  "properties": {
    "iso:country":"US",
    "sg:address":"1216 7th St",
    "sg:city":"Columbus",
    "sg:classifiers":[
        {
            "category":"Manufacturing",
            "subcategory":"Tools & Machinery",
            "type":"Manufacturing & Wholesale Goods"
        }
    ],
    "sg:phone":"+1 402 564 1007",
    "sg:postcode":"68601",
    "sg:province":"NE",
    "sg:tags":[
        "machine",
        "shop"
    ],
    "wof:name":"Mill Masters",
    "wof:placetype":"venue"
},
  "geometry": {"coordinates":[-97.34309500000001,41.423],"type":"Point"}
}