{
  "type": "Feature",
  "properties": {
    "iso:country":"US",
    "sg:address":"2551 24th Rd",
    "sg:city":"Clarks",
    "sg:classifiers":[
        {
            "category":"Professional",
            "type":"Services"
        }
    ],
    "sg:phone":"+1 308 548 2629",
    "sg:postcode":"68628",
    "sg:province":"NE",
    "sg:tags":[
        "establishment"
    ],
    "wof:name":"Wruble Inc",
    "wof:placetype":"venue"
},
  "geometry": {"coordinates":[-97.848072,41.222536],"type":"Point"}
}