{
  "type": "Feature",
  "properties": {
    "iso:country":"US",
    "sg:address":"141 M St",
    "sg:city":"Lincoln",
    "sg:classifiers":[
        {
            "category":"Building & Trades",
            "subcategory":"Construction",
            "type":"Services"
        }
    ],
    "sg:phone":"+1 402 475 5030",
    "sg:postcode":"68508",
    "sg:province":"NE",
    "sg:tags":[
        "heavy",
        "concrete",
        "contractor"
    ],
    "sg:website":"www.tcwconstruction.com",
    "wof:name":"TCW Construction Inc",
    "wof:placetype":"venue"
},
  "geometry": {"coordinates":[-96.71925,40.81137],"type":"Point"}
}