{
  "type": "Feature",
  "properties": {
    "iso:country":"US",
    "sg:address":"316 S 72nd St",
    "sg:city":"Omaha",
    "sg:classifiers":[
        {
            "category":"Shopping",
            "type":"Retail Goods"
        }
    ],
    "sg:phone":"+1 402 397 9636",
    "sg:postcode":"68114",
    "sg:province":"NE",
    "sg:tags":[
        "cosmetic",
        "perfume"
    ],
    "wof:name":"Avon",
    "wof:placetype":"venue"
},
  "geometry": {"coordinates":[-96.023973,41.256183],"type":"Point"}
}