{
  "type": "Feature",
  "properties": {
    "iso:country":"US",
    "sg:address":"212 S Chestnut St",
    "sg:city":"Kimball",
    "sg:classifiers":[
        {
            "category":"Home & Garden",
            "subcategory":"Hardware",
            "type":"Retail Goods"
        }
    ],
    "sg:phone":"+1 308 235 4449",
    "sg:postcode":"69145",
    "sg:province":"NE",
    "wof:name":"Hometown Hardware Inc",
    "wof:placetype":"venue"
},
  "geometry": {"coordinates":[-103.66306,41.23694],"type":"Point"}
}