{
  "type": "Feature",
  "properties": {
    "iso:country":"US",
    "sg:address":"111 Halligan Dr",
    "sg:city":"North Platte",
    "sg:classifiers":[
        {
            "category":"Restaurant",
            "type":"Food & Drink"
        }
    ],
    "sg:menulink":"http://www.allmenus.com/ne/north-platte/109403-village-inn/menu/",
    "sg:phone":"+1 308 534 7944",
    "sg:postcode":"69101",
    "sg:province":"NE",
    "sg:tags":[
        "new",
        "american"
    ],
    "wof:name":"Village Inn",
    "wof:placetype":"venue"
},
  "geometry": {"coordinates":[-100.763597,41.115448],"type":"Point"}
}