{
  "type": "Feature",
  "properties": {
    "addr:full":"44737 Hwy 30 Overton NE 68863",
    "addr:housenumber":"44737",
    "addr:postcode":"68863",
    "addr:street":"Hwy 30",
    "iso:country":"US",
    "sg:address":"44737 Hwy 30",
    "sg:city":"Overton",
    "sg:classifiers":[
        {
            "category":"Farming",
            "subcategory":"Farm",
            "type":"Manufacturing & Wholesale Goods"
        }
    ],
    "sg:phone":"+1 308 987 2213",
    "sg:postcode":"68863",
    "sg:province":"NE",
    "wof:name":"Brennan Farms & Livestock",
    "wof:placetype":"venue"
},
  "geometry": {"coordinates":[-99.47665000000001,40.730561],"type":"Point"}
}