{
  "type": "Feature",
  "properties": {
    "addr:full":"6113 Maple St Omaha NE 68104",
    "addr:housenumber":"6113",
    "addr:postcode":"68104",
    "addr:street":"Maple St",
    "iso:country":"US",
    "sg:address":"6113 Maple St",
    "sg:city":"Omaha",
    "sg:classifiers":[
        {
            "category":"Restaurant",
            "type":"Food & Drink"
        }
    ],
    "sg:phone":"+1 402 553 1266",
    "sg:postcode":"68104",
    "sg:province":"NE",
    "sg:tags":[
        "vegetarian",
        "vegan",
        "brunch",
        "breakfast"
    ],
    "sg:website":"www.miasbongoroom.com",
    "wof:name":"Mia's Bongo Room",
    "wof:placetype":"venue"
},
  "geometry": {"coordinates":[-96.007935,41.284988],"type":"Point"}
}