{
  "type": "Feature",
  "properties": {
    "iso:country":"US",
    "sg:address":"6916 North 97th Cir",
    "sg:city":"Omaha",
    "sg:classifiers":[
        {
            "category":"Professional",
            "subcategory":"Computer Services",
            "type":"Services"
        }
    ],
    "sg:phone":"+1 402 339 9972",
    "sg:postcode":"68122",
    "sg:province":"NE",
    "sg:website":"http://www.doculynxinc.com/",
    "wof:name":"Doculynx",
    "wof:placetype":"venue"
},
  "geometry": {"coordinates":[-96.06352200000001,41.321024],"type":"Point"}
}