{
  "type": "Feature",
  "properties": {
    "iso:country":"US",
    "sg:address":"930 Page Rd",
    "sg:city":"Dannebrog",
    "sg:phone":"+1 308 226 2264",
    "sg:postcode":"68831",
    "sg:province":"NE",
    "sg:tags":[
        "farm",
        "corn",
        "soybean"
    ],
    "wof:name":"Van Pelt Roger",
    "wof:placetype":"venue"
},
  "geometry": {"coordinates":[-98.595343,41.169232],"type":"Point"}
}