{
  "type": "Feature",
  "properties": {
    "iso:country":"US",
    "sg:address":"9425 Oakville Rd",
    "sg:city":"Lincoln",
    "sg:classifiers":[
        {
            "category":"Building & Trades",
            "subcategory":"Landscaping Services",
            "type":"Services"
        }
    ],
    "sg:phone":"+1 402 484 8884",
    "sg:postcode":"68526",
    "sg:province":"NE",
    "wof:name":"Nebraska Lawn Care",
    "wof:placetype":"venue"
},
  "geometry": {"coordinates":[-96.592921,40.744845],"type":"Point"}
}