{
  "type": "Feature",
  "properties": {
    "iso:country":"US",
    "sg:address":"308 W 4th St",
    "sg:city":"Fairbury",
    "sg:classifiers":[
        {
            "category":"Farming",
            "subcategory":"Nursery",
            "type":"Manufacturing & Wholesale Goods"
        }
    ],
    "sg:phone":"+1 402 729 3728",
    "sg:postcode":"68352",
    "sg:province":"NE",
    "sg:tags":[
        "greenhouse"
    ],
    "wof:name":"Sims Greenhouse",
    "wof:placetype":"venue"
},
  "geometry": {"coordinates":[-97.189902,40.135054],"type":"Point"}
}