{
  "type": "Feature",
  "properties": {
    "addr:full":"26 Gateway Mall Lincoln NE 68505",
    "addr:housenumber":"26",
    "addr:postcode":"68505",
    "addr:street":"Gateway Mall",
    "iso:country":"US",
    "sg:address":"26 Gateway Mall",
    "sg:city":"Lincoln",
    "sg:classifiers":[
        {
            "category":"Shopping",
            "subcategory":"Clothing, Apparel, & Fashions",
            "type":"Retail Goods"
        }
    ],
    "sg:phone":"+1 402 466 2388",
    "sg:postcode":"68505",
    "sg:province":"NE",
    "sg:tags":[
        "accessory"
    ],
    "sg:website":"www.hottopic.com",
    "wof:name":"Hot Topic",
    "wof:placetype":"venue"
},
  "geometry": {"coordinates":[-96.641294,40.814258],"type":"Point"}
}