{
  "type": "Feature",
  "properties": {
    "iso:country":"US",
    "sg:address":"511 Fort Crook Rd N",
    "sg:city":"Bellevue",
    "sg:classifiers":[
        {
            "category":"Restaurant",
            "type":"Food & Drink"
        }
    ],
    "sg:phone":"+1 402 733 1646",
    "sg:postcode":"68005",
    "sg:province":"NE",
    "wof:name":"Lums Restaurant",
    "wof:placetype":"venue"
},
  "geometry": {"coordinates":[-95.925059,41.167342],"type":"Point"}
}