{
  "type": "Feature",
  "properties": {
    "iso:country":"US",
    "sg:address":"16217 Woodland Dr",
    "sg:city":"Omaha",
    "sg:classifiers":[
        {
            "category":"Professional",
            "subcategory":"Accounting & Tax Preparation",
            "type":"Services"
        }
    ],
    "sg:phone":"+1 402 891 1319",
    "sg:postcode":"68136",
    "sg:province":"NE",
    "sg:tags":[
        "return"
    ],
    "wof:name":"Caruso Tax Service",
    "wof:placetype":"venue"
},
  "geometry": {"coordinates":[-96.172596,41.147757],"type":"Point"}
}