{
  "type": "Feature",
  "properties": {
    "iso:country":"US",
    "sg:address":"10938 Emiline St",
    "sg:city":"La Vista",
    "sg:classifiers":[
        {
            "category":"Wholesale",
            "subcategory":"Durable Goods & Equipment",
            "type":"Manufacturing & Wholesale Goods"
        }
    ],
    "sg:phone":"+1 402 339 3335",
    "sg:postcode":"68128",
    "sg:province":"NE",
    "sg:tags":[
        "representative",
        "manufacturer"
    ],
    "wof:name":"Central West Marketing",
    "wof:placetype":"venue"
},
  "geometry": {"coordinates":[-96.084947,41.189698],"type":"Point"}
}