{
  "type": "Feature",
  "properties": {
    "addr:full":"1645 N 27th St Lincoln NE 68503",
    "addr:housenumber":"1645",
    "addr:postcode":"68503",
    "addr:street":"N 27Th St",
    "iso:country":"US",
    "sg:address":"1645 N 27th St",
    "sg:city":"Lincoln",
    "sg:classifiers":[
        {
            "category":"Social Services",
            "type":"Services"
        }
    ],
    "sg:phone":"+1 402 435 3035",
    "sg:postcode":"68503",
    "sg:province":"NE",
    "sg:tags":[
        "organization",
        "welfare"
    ],
    "wof:name":"Salvation Army",
    "wof:placetype":"venue"
},
  "geometry": {"coordinates":[-96.682371,40.829412],"type":"Point"}
}