{
  "type": "Feature",
  "properties": {
    "iso:country":"US",
    "sg:address":"156 Dodge",
    "sg:city":"Omaha",
    "sg:classifiers":[
        {
            "category":"Food & Beverages",
            "subcategory":"Groceries & Convenience Stores",
            "type":"Retail Goods"
        }
    ],
    "sg:phone":"+1 402 697 0431",
    "sg:postcode":"68118",
    "sg:province":"NE",
    "wof:name":"Anderson Bp Food Shops",
    "wof:placetype":"venue"
},
  "geometry": {"coordinates":[-95.928623,41.259799],"type":"Point"}
}