{
  "type": "Feature",
  "properties": {
    "iso:country":"US",
    "sg:address":"2420 Grant St",
    "sg:city":"Omaha",
    "sg:classifiers":[
        {
            "category":"Manufacturing",
            "subcategory":"Apparel",
            "type":"Manufacturing & Wholesale Goods"
        }
    ],
    "sg:phone":"+1 402 342 0992",
    "sg:postcode":"68111",
    "sg:province":"NE",
    "sg:tags":[
        "textile",
        "bag"
    ],
    "sg:website":"www.frontierbagco.com",
    "wof:name":"Frontier Bag Co Inc",
    "wof:placetype":"venue"
},
  "geometry": {"coordinates":[-95.948325,41.28019],"type":"Point"}
}