{
  "type": "Feature",
  "properties": {
    "iso:country":"US",
    "sg:address":"1021 W 7th St",
    "sg:city":"Wayne",
    "sg:classifiers":[
        {
            "category":"Shopping",
            "subcategory":"Books",
            "type":"Retail Goods"
        }
    ],
    "sg:phone":"+1 402 375 1201",
    "sg:postcode":"68787",
    "sg:province":"NE",
    "wof:name":"Living Water Books & Gifts",
    "wof:placetype":"venue"
},
  "geometry": {"coordinates":[-97.030304,42.235328],"type":"Point"}
}