{
  "type": "Feature",
  "properties": {
    "iso:country":"US",
    "sg:address":"3600 W Burgess Ln",
    "sg:city":"Lincoln",
    "sg:classifiers":[
        {
            "category":"Professional",
            "subcategory":"Management & Consulting",
            "type":"Services"
        }
    ],
    "sg:phone":"+1 402 797 5101",
    "sg:postcode":"68523",
    "sg:province":"NE",
    "sg:tags":[
        "consultant"
    ],
    "wof:name":"Mc Keeman Consulting",
    "wof:placetype":"venue"
},
  "geometry": {"coordinates":[-96.773743,40.747448],"type":"Point"}
}