{
  "type": "Feature",
  "properties": {
    "iso:country":"US",
    "sg:address":"1518 S 32nd Rd",
    "sg:city":"Cook",
    "sg:phone":"+1 402 864 2001",
    "sg:postcode":"68329",
    "sg:province":"NE",
    "sg:tags":[
        "farm",
        "corn",
        "livestock",
        "soybean"
    ],
    "wof:name":"Noerrlinger Farm",
    "wof:placetype":"venue"
},
  "geometry": {"coordinates":[-96.16046900000001,40.56528],"type":"Point"}
}