{
  "type": "Feature",
  "properties": {
    "addr:full":"2701 NW 55th St Lincoln NE 68524",
    "addr:housenumber":"2701",
    "addr:postcode":"68524",
    "addr:street":"Nw 55Th St",
    "iso:country":"US",
    "sg:address":"2701 NW 55th St",
    "sg:city":"Lincoln",
    "sg:classifiers":[
        {
            "category":"Social Services",
            "subcategory":"Child Care",
            "type":"Services"
        }
    ],
    "sg:phone":"+1 402 470 2321",
    "sg:postcode":"68524",
    "sg:province":"NE",
    "sg:tags":[
        "day"
    ],
    "wof:name":"Nicole Ogden",
    "wof:placetype":"venue"
},
  "geometry": {"coordinates":[-96.795417,40.840776],"type":"Point"}
}