{
  "type": "Feature",
  "properties": {
    "iso:country":"US",
    "sg:address":"2332 N Cotner Blvd",
    "sg:city":"Lincoln",
    "sg:classifiers":[
        {
            "category":"Personal",
            "subcategory":"Beauty Salon",
            "type":"Services"
        }
    ],
    "sg:phone":"+1 402 466 4247",
    "sg:postcode":"68507",
    "sg:province":"NE",
    "sg:tags":[
        "shop"
    ],
    "wof:name":"Hairloom Salon Inc",
    "wof:placetype":"venue"
},
  "geometry": {"coordinates":[-96.630354,40.835917],"type":"Point"}
}