{
  "type": "Feature",
  "properties": {
    "addr:full":"1102 Mackensey Dr Papillion NE 68046",
    "addr:housenumber":"1102",
    "addr:postcode":"68046",
    "addr:street":"Mackensey Dr",
    "iso:country":"US",
    "sg:address":"1102 Mackensey Dr",
    "sg:city":"Papillion",
    "sg:classifiers":[
        {
            "category":"Professional",
            "type":"Services"
        }
    ],
    "sg:phone":"+1 402 593 1086",
    "sg:postcode":"68046",
    "sg:province":"NE",
    "wof:name":"Honey Killeen Co Inc",
    "wof:placetype":"venue"
},
  "geometry": {"coordinates":[-96.026979,41.17285],"type":"Point"}
}