{
  "type": "Feature",
  "properties": {
    "iso:country":"US",
    "sg:address":"21250 W Prairie Lake Rd",
    "sg:city":"Kenesaw",
    "sg:classifiers":[
        {
            "category":"Real Estate",
            "subcategory":"Real Estate Operator",
            "type":"Services"
        }
    ],
    "sg:phone":"+1 402 756 5330",
    "sg:postcode":"68956",
    "sg:province":"NE",
    "sg:tags":[
        "property",
        "lessor"
    ],
    "wof:name":"Hines Roman",
    "wof:placetype":"venue"
},
  "geometry": {"coordinates":[-98.723445,40.538788],"type":"Point"}
}