{
  "type": "Feature",
  "properties": {
    "iso:country":"US",
    "sg:address":"919 6th St",
    "sg:city":"Aurora",
    "sg:classifiers":[
        {
            "category":"Organizations",
            "subcategory":"Religious Organization",
            "type":"Services"
        }
    ],
    "sg:phone":"+1 402 694 2929",
    "sg:postcode":"68818",
    "sg:province":"NE",
    "wof:name":"Awana Clubs",
    "wof:placetype":"venue"
},
  "geometry": {"coordinates":[-98.01073,40.865843],"type":"Point"}
}