{
  "type": "Feature",
  "properties": {
    "iso:country":"US",
    "sg:address":"1207 Peabody Ave",
    "sg:city":"Creighton",
    "sg:classifiers":[
        {
            "category":"Personal",
            "subcategory":"Beauty Salon",
            "type":"Services"
        }
    ],
    "sg:phone":"+1 402 358 5318",
    "sg:postcode":"68729",
    "sg:province":"NE",
    "sg:tags":[
        "shop"
    ],
    "wof:name":"Marsha's Beauty Nook",
    "wof:placetype":"venue"
},
  "geometry": {"coordinates":[-97.903362,42.463357],"type":"Point"}
}