{
  "type": "Feature",
  "properties": {
    "iso:country":"US",
    "sg:address":"936 el Avado Ave",
    "sg:city":"Lincoln",
    "sg:classifiers":[
        {
            "category":"Organizations",
            "subcategory":"Religious Organization",
            "type":"Services"
        }
    ],
    "sg:phone":"+1 402 466 8016",
    "sg:postcode":"68504",
    "sg:province":"NE",
    "sg:tags":[
        "church"
    ],
    "wof:name":"Hollywood Heights Chapel",
    "wof:placetype":"venue"
},
  "geometry": {"coordinates":[-96.648814,40.821361],"type":"Point"}
}