{
  "type": "Feature",
  "properties": {
    "iso:country":"US",
    "sg:address":"418 N 13th St",
    "sg:city":"Geneva",
    "sg:classifiers":[
        {
            "category":"Food & Beverages",
            "subcategory":"Groceries & Convenience Stores",
            "type":"Retail Goods"
        }
    ],
    "sg:phone":"+1 402 759 3074",
    "sg:postcode":"68361",
    "sg:province":"NE",
    "wof:name":"Phil Mart",
    "wof:placetype":"venue"
},
  "geometry": {"coordinates":[-97.595888,40.530791],"type":"Point"}
}