{
  "type": "Feature",
  "properties": {
    "iso:country":"US",
    "sg:address":"800 Spruce St",
    "sg:city":"Wahoo",
    "sg:classifiers":[
        {
            "category":"Wholesale",
            "subcategory":"Farm Supplies",
            "type":"Manufacturing & Wholesale Goods"
        }
    ],
    "sg:phone":"+1 402 443 3797",
    "sg:postcode":"68066",
    "sg:province":"NE",
    "sg:tags":[
        "feed"
    ],
    "wof:name":"Farmers Union Co-Op",
    "wof:placetype":"venue"
},
  "geometry": {"coordinates":[-96.612576,41.212259],"type":"Point"}
}