{
  "type": "Feature",
  "properties": {
    "iso:country":"US",
    "sg:address":"930 Prairie Ln",
    "sg:city":"Beatrice",
    "sg:classifiers":[
        {
            "category":"Education",
            "subcategory":"School",
            "type":"Public Place"
        }
    ],
    "sg:phone":"+1 402 223 3414",
    "sg:postcode":"68310",
    "sg:province":"NE",
    "sg:tags":[
        "elementary",
        "religious",
        "private"
    ],
    "wof:name":"St Paul's Lutheran School",
    "wof:placetype":"venue"
},
  "geometry": {"coordinates":[-96.724586,40.275823],"type":"Point"}
}