{
  "type": "Feature",
  "properties": {
    "iso:country":"US",
    "sg:address":"4606 S 84th St",
    "sg:city":"Omaha",
    "sg:classifiers":[
        {
            "category":"Retail",
            "subcategory":"Auto Repair",
            "type":"Services"
        }
    ],
    "sg:phone":"+1 402 592 7666",
    "sg:postcode":"68127",
    "sg:province":"NE",
    "sg:tags":[
        "general"
    ],
    "wof:name":"Sparks Computerized Car Care",
    "wof:placetype":"venue"
},
  "geometry": {"coordinates":[-96.04310700000001,41.212603],"type":"Point"}
}