{
  "type": "Feature",
  "properties": {
    "addr:full":"600 Agnew Rd Ceresco NE 68017",
    "addr:housenumber":"600",
    "addr:postcode":"68017",
    "addr:street":"Agnew Rd",
    "iso:country":"US",
    "sg:address":"600 Agnew Rd",
    "sg:city":"Ceresco",
    "sg:classifiers":[
        {
            "category":"Farming",
            "subcategory":"Livestock Farm",
            "type":"Manufacturing & Wholesale Goods"
        }
    ],
    "sg:phone":"+1 402 785 7820",
    "sg:postcode":"68017",
    "sg:province":"NE",
    "sg:tags":[
        "beef",
        "feedlot",
        "cattle"
    ],
    "wof:name":"Darren Strizek Farm",
    "wof:placetype":"venue"
},
  "geometry": {"coordinates":[-96.707498,41.016912],"type":"Point"}
}