{
  "type": "Feature",
  "properties": {
    "iso:country":"US",
    "sg:address":"10194 California St",
    "sg:city":"Omaha",
    "sg:classifiers":[
        {
            "category":"Banks & Credit Unions",
            "subcategory":"Bank",
            "type":"Services"
        }
    ],
    "sg:phone":"+1 402 391 7204",
    "sg:postcode":"68114",
    "sg:province":"NE",
    "sg:tags":[
        "state",
        "commercial"
    ],
    "wof:name":"First Westroads Bank Inc",
    "wof:placetype":"venue"
},
  "geometry": {"coordinates":[-96.069225,41.26406],"type":"Point"}
}