{
  "type": "Feature",
  "properties": {
    "iso:country":"US",
    "sg:address":"701 Marina Bay Pl",
    "sg:city":"Lincoln",
    "sg:classifiers":[
        {
            "category":"Professional",
            "subcategory":"Advertising",
            "type":"Services"
        }
    ],
    "sg:phone":"+1 402 475 2493",
    "sg:postcode":"68528",
    "sg:province":"NE",
    "wof:name":"Comac Advertising",
    "wof:placetype":"venue"
},
  "geometry": {"coordinates":[-96.73466500000001,40.819543],"type":"Point"}
}