{
  "type": "Feature",
  "properties": {
    "iso:country":"US",
    "sg:address":"534 Seward St",
    "sg:city":"Seward",
    "sg:classifiers":[
        {
            "category":"Shopping",
            "subcategory":"Clothing, Apparel, & Fashions",
            "type":"Retail Goods"
        }
    ],
    "sg:phone":"+1 402 643 3237",
    "sg:postcode":"68434",
    "sg:province":"NE",
    "sg:tags":[
        "used",
        "merchandise"
    ],
    "wof:name":"Second Closet",
    "wof:placetype":"venue"
},
  "geometry": {"coordinates":[-97.098203,40.907866],"type":"Point"}
}