{
  "type": "Feature",
  "properties": {
    "addr:full":"1001 Alba Ave Ravenna NE 68869",
    "addr:housenumber":"1001",
    "addr:postcode":"68869",
    "addr:street":"Alba Ave",
    "iso:country":"US",
    "sg:address":"1001 Alba Ave",
    "sg:city":"Ravenna",
    "sg:classifiers":[
        {
            "category":"Personal",
            "subcategory":"Beauty Salon",
            "type":"Services"
        }
    ],
    "sg:phone":"+1 308 452 3431",
    "sg:postcode":"68869",
    "sg:province":"NE",
    "sg:tags":[
        "shop"
    ],
    "wof:name":"Alba Beauty Salon",
    "wof:placetype":"venue"
},
  "geometry": {"coordinates":[-98.91401399999999,41.033488],"type":"Point"}
}