{
  "type": "Feature",
  "properties": {
    "iso:country":"US",
    "sg:address":"1221 S Saddle Creek Rd",
    "sg:city":"Omaha",
    "sg:classifiers":[
        {
            "category":"Building & Trades",
            "subcategory":"Pest Control",
            "type":"Services"
        }
    ],
    "sg:phone":"+1 402 551 0524",
    "sg:postcode":"68106",
    "sg:province":"NE",
    "wof:name":"Presto-X-Company",
    "wof:placetype":"venue"
},
  "geometry": {"coordinates":[-95.988589,41.247145],"type":"Point"}
}