{
  "type": "Feature",
  "properties": {
    "iso:country":"US",
    "sg:address":"523 Delaware St",
    "sg:city":"Boelus",
    "sg:classifiers":[
        {
            "category":"Banks & Credit Unions",
            "subcategory":"Bank",
            "type":"Services"
        }
    ],
    "sg:phone":"+1 308 996 4283",
    "sg:postcode":"68820",
    "sg:province":"NE",
    "wof:name":"Boelus State Bank",
    "wof:placetype":"venue"
},
  "geometry": {"coordinates":[-98.71537499999999,41.072518],"type":"Point"}
}