{
  "type": "Feature",
  "properties": {
    "iso:country":"US",
    "sg:address":"11704 W Center Rd",
    "sg:city":"Omaha",
    "sg:classifiers":[
        {
            "category":"Health Services",
            "subcategory":"Health Practitioner",
            "type":"Services"
        }
    ],
    "sg:phone":"+1 402 691 0400",
    "sg:postcode":"68144",
    "sg:province":"NE",
    "sg:tags":[
        "therapist",
        "physical"
    ],
    "wof:name":"Ortho Sports",
    "wof:placetype":"venue"
},
  "geometry": {"coordinates":[-96.098248,41.234116],"type":"Point"}
}