{
  "type": "Feature",
  "properties": {
    "iso:country":"US",
    "sg:address":"6206 S 38th St",
    "sg:city":"Omaha",
    "sg:classifiers":[
        {
            "category":"Building & Trades",
            "subcategory":"Construction",
            "type":"Services"
        }
    ],
    "sg:phone":"+1 402 880 5424",
    "sg:postcode":"68107",
    "sg:province":"NE",
    "sg:tags":[
        "residential"
    ],
    "wof:name":"Recovery Construction",
    "wof:placetype":"venue"
},
  "geometry": {"coordinates":[-95.971048,41.194511],"type":"Point"}
}