{
  "type": "Feature",
  "properties": {
    "iso:country":"US",
    "sg:address":"5789 US Hwy 20",
    "sg:city":"Chadron",
    "sg:classifiers":[
        {
            "category":"Professional",
            "subcategory":"Management & Consulting",
            "type":"Services"
        }
    ],
    "sg:phone":"+1 308 432 4050",
    "sg:postcode":"69337",
    "sg:province":"NE",
    "sg:tags":[
        "consultant",
        "resource",
        "human"
    ],
    "wof:name":"Area 1 Office-Human Developmen",
    "wof:placetype":"venue"
},
  "geometry": {"coordinates":[-103.02767299999999,42.828475],"type":"Point"}
}