{
  "type": "Feature",
  "properties": {
    "iso:country":"US",
    "sg:address":"403 N 9th Ave",
    "sg:city":"Broken Bow",
    "sg:classifiers":[
        {
            "category":"Social Services",
            "subcategory":"Child Care",
            "type":"Services"
        }
    ],
    "sg:phone":"+1 308 872 6991",
    "sg:postcode":"68822",
    "sg:province":"NE",
    "sg:tags":[
        "day"
    ],
    "wof:name":"Ginnys Childcare",
    "wof:placetype":"venue"
},
  "geometry": {"coordinates":[-99.640596,41.409044],"type":"Point"}
}