{
  "type": "Feature",
  "properties": {
    "iso:country":"US",
    "sg:address":"34 Lincoln St",
    "sg:city":"Seward",
    "sg:classifiers":[
        {
            "category":"Health Services",
            "subcategory":"Health Practitioner",
            "type":"Services"
        }
    ],
    "sg:phone":"+1 402 643 4975",
    "sg:postcode":"68434",
    "sg:province":"NE",
    "sg:tags":[
        "nutrition",
        "consultant"
    ],
    "wof:name":"Amway Products Distr",
    "wof:placetype":"venue"
},
  "geometry": {"coordinates":[-97.09229000000001,40.912448],"type":"Point"}
}