{
  "type": "Feature",
  "properties": {
    "addr:full":"2208 J St Auburn NE 68305",
    "addr:housenumber":"2208",
    "addr:postcode":"68305",
    "addr:street":"J St",
    "iso:country":"US",
    "sg:address":"2208 J St",
    "sg:city":"Auburn",
    "sg:classifiers":[
        {
            "category":"Restaurant",
            "type":"Food & Drink"
        },
        {
            "category":"Food & Beverages",
            "subcategory":"Groceries & Convenience Stores",
            "type":"Retail Goods"
        }
    ],
    "sg:menulink":"http://www.allmenus.com/ne/auburn/225120-caseys-general-store/menu/",
    "sg:phone":"+1 402 274 3722",
    "sg:postcode":"68305",
    "sg:province":"NE",
    "sg:tags":[
        "american",
        "pizza"
    ],
    "wof:name":"Casey's General Store",
    "wof:placetype":"venue"
},
  "geometry": {"coordinates":[-95.83879399999999,40.382268],"type":"Point"}
}