{
  "type": "Feature",
  "properties": {
    "addr:full":"4610 S 44th St Lincoln NE 68516",
    "addr:housenumber":"4610",
    "addr:postcode":"68516",
    "addr:street":"S 44Th St",
    "iso:country":"US",
    "sg:address":"4610 S 44th St",
    "sg:city":"Lincoln",
    "sg:classifiers":[
        {
            "category":"Shopping",
            "type":"Retail Goods"
        }
    ],
    "sg:phone":"+1 402 483 4626",
    "sg:postcode":"68516",
    "sg:province":"NE",
    "sg:tags":[
        "merchandise"
    ],
    "wof:name":"Maxwell Technologies",
    "wof:placetype":"venue"
},
  "geometry": {"coordinates":[-96.65912,40.768132],"type":"Point"}
}