{
  "type": "Feature",
  "properties": {
    "iso:country":"US",
    "sg:address":"4800 Calvert St",
    "sg:city":"Lincoln",
    "sg:classifiers":[
        {
            "category":"Personal",
            "subcategory":"Barber",
            "type":"Services"
        }
    ],
    "sg:phone":"+1 402 488 4607",
    "sg:postcode":"68506",
    "sg:province":"NE",
    "sg:tags":[
        "shop"
    ],
    "wof:name":"College View Barbers",
    "wof:placetype":"venue"
},
  "geometry": {"coordinates":[-96.65228399999999,40.777035],"type":"Point"}
}