{
  "type": "Feature",
  "properties": {
    "iso:country":"US",
    "sg:address":"106 W Elm St",
    "sg:city":"Cedar Bluffs",
    "sg:classifiers":[
        {
            "category":"Personal",
            "subcategory":"Beauty Salon",
            "type":"Services"
        }
    ],
    "sg:phone":"+1 402 628 8147",
    "sg:postcode":"68015",
    "sg:province":"NE",
    "wof:name":"Dorothe's Beauty Salon",
    "wof:placetype":"venue"
},
  "geometry": {"coordinates":[-96.612369,41.398094],"type":"Point"}
}