{
  "type": "Feature",
  "properties": {
    "iso:country":"US",
    "sg:address":"1818 S 204th St",
    "sg:city":"Elkhorn",
    "sg:classifiers":[
        {
            "category":"Freight",
            "type":"Transportation"
        }
    ],
    "sg:phone":"+1 402 289 3100",
    "sg:postcode":"68022",
    "sg:province":"NE",
    "sg:tags":[
        "operator",
        "local",
        "trucking"
    ],
    "wof:name":"Custard Trucking",
    "wof:placetype":"venue"
},
  "geometry": {"coordinates":[-96.234498,41.241792],"type":"Point"}
}