{
  "type": "Feature",
  "properties": {
    "addr:full":"7800 W O St Lincoln NE 68528",
    "addr:housenumber":"7800",
    "addr:postcode":"68528",
    "addr:street":"W O St",
    "iso:country":"US",
    "sg:address":"7800 W O St",
    "sg:city":"Lincoln",
    "sg:classifiers":[
        {
            "category":"Insurance",
            "subcategory":"Insurance Agent",
            "type":"Services"
        }
    ],
    "sg:phone":"+1 402 483 1350",
    "sg:postcode":"68528",
    "sg:province":"NE",
    "sg:website":"www.farleywolfins.com",
    "wof:name":"Farley Wolf Insurance",
    "wof:placetype":"venue"
},
  "geometry": {"coordinates":[-96.842398,40.81396],"type":"Point"}
}