{
  "type": "Feature",
  "properties": {
    "addr:full":"3001 NW 12th St Lincoln NE 68521",
    "addr:housenumber":"3001",
    "addr:postcode":"68521",
    "addr:street":"Nw 12Th St",
    "iso:country":"US",
    "sg:address":"3001 NW 12th St",
    "sg:city":"Lincoln",
    "sg:classifiers":[
        {
            "category":"Travel",
            "subcategory":"Hotels & Motels",
            "type":"Entertainment"
        }
    ],
    "sg:phone":"+1 402 475 3211",
    "sg:postcode":"68521",
    "sg:province":"NE",
    "sg:tags":[
        "operation"
    ],
    "wof:name":"Motel 6",
    "wof:placetype":"venue"
},
  "geometry": {"coordinates":[-96.739639,40.842887],"type":"Point"}
}