{
  "type": "Feature",
  "properties": {
    "addr:full":"208 N Pine St Grand Island NE 68801",
    "addr:housenumber":"208",
    "addr:postcode":"68801",
    "addr:street":"N Pine St",
    "iso:country":"US",
    "sg:address":"208 N Pine St",
    "sg:city":"Grand Island",
    "sg:classifiers":[
        {
            "category":"Government",
            "subcategory":"Office",
            "type":"Public Place"
        }
    ],
    "sg:phone":"+1 308 385 6224",
    "sg:postcode":"68801",
    "sg:province":"NE",
    "sg:tags":[
        "state",
        "resource"
    ],
    "wof:name":"Developmental Disabilities Div",
    "wof:placetype":"venue"
},
  "geometry": {"coordinates":[-98.339705,40.925337],"type":"Point"}
}