{
  "type": "Feature",
  "properties": {
    "iso:country":"US",
    "sg:address":"221 US Hwy 30",
    "sg:city":"Shelton",
    "sg:classifiers":[
        {
            "category":"Autos & Motor Vehicles",
            "subcategory":"Automobile Sales",
            "type":"Retail Goods"
        }
    ],
    "sg:phone":"+1 308 647 6888",
    "sg:postcode":"68876",
    "sg:province":"NE",
    "sg:tags":[
        "car",
        "dealer"
    ],
    "wof:name":"Ryan's Used Cars Inc",
    "wof:placetype":"venue"
},
  "geometry": {"coordinates":[-98.72832099999999,40.782146],"type":"Point"}
}