{
  "type": "Feature",
  "properties": {
    "iso:country":"US",
    "sg:address":"600 N 12th St",
    "sg:city":"Norfolk",
    "sg:classifiers":[
        {
            "category":"Education",
            "subcategory":"School",
            "type":"Public Place"
        }
    ],
    "sg:phone":"+1 402 644 2553",
    "sg:postcode":"68701",
    "sg:province":"NE",
    "wof:name":"Northern Hills Elem School",
    "wof:placetype":"venue"
},
  "geometry": {"coordinates":[-97.42294099999999,42.03964],"type":"Point"}
}