{
  "type": "Feature",
  "properties": {
    "iso:country":"US",
    "sg:address":"5815 S 58th St",
    "sg:city":"Lincoln",
    "sg:classifiers":[
        {
            "category":"Insurance",
            "subcategory":"Insurance Agent",
            "type":"Services"
        }
    ],
    "sg:phone":"+1 402 421 9200",
    "sg:postcode":"68516",
    "sg:province":"NE",
    "wof:name":"Farm Bureau Financial Svc",
    "wof:placetype":"venue"
},
  "geometry": {"coordinates":[-96.64212499999999,40.753119],"type":"Point"}
}