{
  "type": "Feature",
  "properties": {
    "addr:full":"2022 Central Ave Kearney NE 68847",
    "addr:housenumber":"2022",
    "addr:postcode":"68847",
    "addr:street":"Central Ave",
    "iso:country":"US",
    "sg:address":"2022 Central Ave",
    "sg:city":"Kearney",
    "sg:classifiers":[
        {
            "category":"Retail",
            "subcategory":"Portrait Studio",
            "type":"Services"
        }
    ],
    "sg:phone":"+1 308 338 9664",
    "sg:postcode":"68847",
    "sg:province":"NE",
    "sg:tags":[
        "photographer"
    ],
    "wof:name":"Artisans",
    "wof:placetype":"venue"
},
  "geometry": {"coordinates":[-99.08184199999999,40.696515],"type":"Point"}
}