{
  "type": "Feature",
  "properties": {
    "iso:country":"US",
    "sg:address":"408 18th Ave",
    "sg:city":"Franklin",
    "sg:phone":"+1 308 425 3413",
    "sg:postcode":"68939",
    "sg:province":"NE",
    "sg:tags":[
        "farm",
        "corn",
        "soybean"
    ],
    "wof:name":"Leroy Harms",
    "wof:placetype":"venue"
},
  "geometry": {"coordinates":[-98.95013400000001,40.098009],"type":"Point"}
}