{
  "type": "Feature",
  "properties": {
    "iso:country":"US",
    "sg:address":"112 564th Ave",
    "sg:city":"Hartington",
    "sg:classifiers":[
        {
            "category":"Social Services",
            "subcategory":"Child Care",
            "type":"Services"
        }
    ],
    "sg:phone":"+1 402 254 3236",
    "sg:postcode":"68739",
    "sg:province":"NE",
    "sg:tags":[
        "day"
    ],
    "wof:name":"Childrens Hour Child Care",
    "wof:placetype":"venue"
},
  "geometry": {"coordinates":[-97.2495,42.728342],"type":"Point"}
}