{
  "type": "Feature",
  "properties": {
    "iso:country":"US",
    "sg:address":"2002 Hickory St",
    "sg:city":"Dakota City",
    "sg:classifiers":[
        {
            "category":"Social Services",
            "subcategory":"Child Care",
            "type":"Services"
        }
    ],
    "sg:phone":"+1 402 987 3887",
    "sg:postcode":"68731",
    "sg:province":"NE",
    "sg:tags":[
        "day"
    ],
    "wof:name":"Estochen Trudi Day Care",
    "wof:placetype":"venue"
},
  "geometry": {"coordinates":[-96.425752,42.412885],"type":"Point"}
}