{
  "type": "Feature",
  "properties": {
    "addr:full":"717 E St Fairbury NE 68352",
    "addr:housenumber":"717",
    "addr:postcode":"68352",
    "addr:street":"E St",
    "iso:country":"US",
    "sg:address":"717 E St",
    "sg:city":"Fairbury",
    "sg:classifiers":[
        {
            "category":"Building & Trades",
            "subcategory":"Pest Control",
            "type":"Services"
        }
    ],
    "sg:phone":"+1 402 729 2504",
    "sg:postcode":"68352",
    "sg:province":"NE",
    "sg:tags":[
        "disinfecting"
    ],
    "wof:name":"Williams Exterminating",
    "wof:placetype":"venue"
},
  "geometry": {"coordinates":[-97.17999,40.139141],"type":"Point"}
}