{
  "type": "Feature",
  "properties": {
    "iso:country":"US",
    "sg:address":"2456 32nd Ave",
    "sg:city":"Columbus",
    "sg:classifiers":[
        {
            "category":"Personal",
            "subcategory":"Beauty Salon",
            "type":"Services"
        }
    ],
    "sg:phone":"+1 402 564 0383",
    "sg:postcode":"68601",
    "sg:province":"NE",
    "sg:tags":[
        "shop"
    ],
    "wof:name":"Expressions",
    "wof:placetype":"venue"
},
  "geometry": {"coordinates":[-97.36684200000001,41.438873],"type":"Point"}
}