{
  "type": "Feature",
  "properties": {
    "addr:full":"10776 Berry Plz Omaha NE 68127",
    "addr:housenumber":"10776",
    "addr:postcode":"68127",
    "addr:street":"Berry Plz",
    "iso:country":"US",
    "sg:address":"10776 Berry Plz",
    "sg:city":"Omaha",
    "sg:classifiers":[
        {
            "category":"Professional",
            "subcategory":"Management & Consulting",
            "type":"Services"
        }
    ],
    "sg:phone":"+1 402 553 0555",
    "sg:postcode":"68127",
    "sg:province":"NE",
    "sg:tags":[
        "consultant",
        "educational"
    ],
    "wof:name":"Fuu Rspnsblity Edcatn Fndation",
    "wof:placetype":"venue"
},
  "geometry": {"coordinates":[-96.08139,41.198415],"type":"Point"}
}