{
  "type": "Feature",
  "properties": {
    "addr:full":"706 Central Ave Nebraska City NE 68410",
    "addr:housenumber":"706",
    "addr:postcode":"68410",
    "addr:street":"Central Ave",
    "iso:country":"US",
    "sg:address":"706 Central Ave",
    "sg:city":"Nebraska City",
    "sg:classifiers":[
        {
            "category":"Personal",
            "subcategory":"Beauty Salon",
            "type":"Services"
        }
    ],
    "sg:phone":"+1 402 873 7592",
    "sg:postcode":"68410",
    "sg:province":"NE",
    "sg:tags":[
        "shop"
    ],
    "wof:name":"New Visions Hairstylists Inc",
    "wof:placetype":"venue"
},
  "geometry": {"coordinates":[-95.85500399999999,40.676671],"type":"Point"}
}