{
  "type": "Feature",
  "properties": {
    "addr:full":"101 Ginger Cove Rd Valley NE 68064",
    "addr:housenumber":"101",
    "addr:postcode":"68064",
    "addr:street":"Ginger Cove Rd",
    "iso:country":"US",
    "sg:address":"101 Ginger Cove Rd",
    "sg:city":"Valley",
    "sg:classifiers":[
        {
            "category":"Professional",
            "subcategory":"Advertising",
            "type":"Services"
        }
    ],
    "sg:phone":"+1 402 359 5247",
    "sg:postcode":"68064",
    "sg:province":"NE",
    "wof:name":"B Sommer Advertising",
    "wof:placetype":"venue"
},
  "geometry": {"coordinates":[-96.385853,41.316942],"type":"Point"}
}