{
  "type": "Feature",
  "properties": {
    "iso:country":"US",
    "sg:address":"5201 Old Cheney Rd",
    "sg:city":"Lincoln",
    "sg:classifiers":[
        {
            "category":"Social Services",
            "subcategory":"Child Care",
            "type":"Services"
        }
    ],
    "sg:phone":"+1 402 420 7111",
    "sg:postcode":"68516",
    "sg:province":"NE",
    "sg:tags":[
        "day"
    ],
    "wof:name":"Wee Wisdom Christian Preschool",
    "wof:placetype":"venue"
},
  "geometry": {"coordinates":[-96.649598,40.75522],"type":"Point"}
}