{
  "type": "Feature",
  "properties": {
    "iso:country":"US",
    "sg:address":"541 N Linden St",
    "sg:city":"Wahoo",
    "sg:classifiers":[
        {
            "category":"Personal",
            "subcategory":"Beauty Salon",
            "type":"Services"
        }
    ],
    "sg:phone":"+1 402 443 4040",
    "sg:postcode":"68066",
    "sg:province":"NE",
    "sg:tags":[
        "shop"
    ],
    "wof:name":"Moriah's Style Salon",
    "wof:placetype":"venue"
},
  "geometry": {"coordinates":[-96.6187,41.210579],"type":"Point"}
}