{
  "type": "Feature",
  "properties": {
    "iso:country":"US",
    "sg:address":"717 N 12th St",
    "sg:city":"Beatrice",
    "sg:classifiers":[
        {
            "category":"Building & Trades",
            "subcategory":"Cleaning & Sanitation",
            "type":"Services"
        }
    ],
    "sg:phone":"+1 402 228 2795",
    "sg:postcode":"68310",
    "sg:province":"NE",
    "sg:tags":[
        "janitor"
    ],
    "wof:name":"So Clean",
    "wof:placetype":"venue"
},
  "geometry": {"coordinates":[-96.738551,40.272773],"type":"Point"}
}