{
  "type": "Feature",
  "properties": {
    "iso:country":"US",
    "sg:address":"15106 Burt St",
    "sg:city":"Omaha",
    "sg:classifiers":[
        {
            "category":"Professional",
            "subcategory":"Management & Consulting",
            "type":"Services"
        }
    ],
    "sg:phone":"+1 402 934 5737",
    "sg:postcode":"68154",
    "sg:province":"NE",
    "wof:name":"Corporate Massage Wellness Co",
    "wof:placetype":"venue"
},
  "geometry": {"coordinates":[-96.150722,41.266748],"type":"Point"}
}