{
  "type": "Feature",
  "properties": {
    "iso:country":"US",
    "sg:address":"220 N Saunders Ave",
    "sg:city":"Sutton",
    "sg:classifiers":[
        {
            "category":"Health Services",
            "subcategory":"Optometrist",
            "type":"Services"
        }
    ],
    "sg:phone":"+1 402 773 4397",
    "sg:postcode":"68979",
    "sg:province":"NE",
    "sg:tags":[
        "optical",
        "good"
    ],
    "wof:name":"John L McBride Dr",
    "wof:placetype":"venue"
},
  "geometry": {"coordinates":[-97.85944600000001,40.608564],"type":"Point"}
}