{
  "type": "Feature",
  "properties": {
    "addr:full":"2105 S 153rd St Omaha NE 68144",
    "addr:housenumber":"2105",
    "addr:postcode":"68144",
    "addr:street":"S 153Rd St",
    "iso:country":"US",
    "sg:address":"2105 S 153rd St",
    "sg:city":"Omaha",
    "sg:classifiers":[
        {
            "category":"Building & Trades",
            "subcategory":"Construction",
            "type":"Services"
        }
    ],
    "sg:phone":"+1 402 333 2656",
    "sg:postcode":"68144",
    "sg:province":"NE",
    "sg:tags":[
        "house",
        "builder",
        "operative"
    ],
    "wof:name":"R E Czerwinski Construction",
    "wof:placetype":"venue"
},
  "geometry": {"coordinates":[-96.15239200000001,41.238488],"type":"Point"}
}