{
  "type": "Feature",
  "properties": {
    "iso:country":"US",
    "sg:address":"610 Broadway St",
    "sg:city":"Imperial",
    "sg:classifiers":[
        {
            "category":"Professional",
            "subcategory":"Management & Consulting",
            "type":"Services"
        }
    ],
    "sg:phone":"+1 308 882 6600",
    "sg:postcode":"69033",
    "sg:province":"NE",
    "sg:tags":[
        "consultant",
        "telecommunication"
    ],
    "wof:name":"Allo Communications",
    "wof:placetype":"venue"
},
  "geometry": {"coordinates":[-101.643035,40.517099],"type":"Point"}
}