{
  "type": "Feature",
  "properties": {
    "addr:full":"401 Fir St Ashland NE 68003",
    "addr:housenumber":"401",
    "addr:postcode":"68003",
    "addr:street":"Fir St",
    "iso:country":"US",
    "sg:address":"401 Fir St",
    "sg:city":"Ashland",
    "sg:classifiers":[
        {
            "category":"Social Services",
            "subcategory":"Adult Care",
            "type":"Services"
        }
    ],
    "sg:phone":"+1 402 944 3291",
    "sg:postcode":"68003",
    "sg:province":"NE",
    "sg:tags":[
        "organization",
        "senior",
        "citizen"
    ],
    "wof:name":"Aging Services/Life",
    "wof:placetype":"venue"
},
  "geometry": {"coordinates":[-96.35610200000001,41.033034],"type":"Point"}
}