{
  "type": "Feature",
  "properties": {
    "addr:full":"2006 Locust St Yankton NE 57078",
    "addr:housenumber":"2006",
    "addr:postcode":"57078",
    "addr:street":"Locust St",
    "iso:country":"US",
    "sg:address":"2006 Locust St",
    "sg:city":"Yankton",
    "sg:classifiers":[
        {
            "category":"Insurance",
            "subcategory":"Insurance Agent",
            "type":"Services"
        }
    ],
    "sg:phone":"+1 605 665 5476",
    "sg:postcode":"57078",
    "sg:province":"NE",
    "wof:name":"Farmers Insurance Group",
    "wof:placetype":"venue"
},
  "geometry": {"coordinates":[-97.399772,42.889181],"type":"Point"}
}