{
  "type": "Feature",
  "properties": {
    "iso:country":"US",
    "sg:address":"1705 15th Ave",
    "sg:city":"Sidney",
    "sg:classifiers":[
        {
            "category":"Wholesale",
            "subcategory":"Construction Materials",
            "type":"Manufacturing & Wholesale Goods"
        }
    ],
    "sg:phone":"+1 308 254 2211",
    "sg:postcode":"69162",
    "sg:province":"NE",
    "sg:tags":[
        "rock"
    ],
    "wof:name":"Rocks Etc",
    "wof:placetype":"venue"
},
  "geometry": {"coordinates":[-102.98248700000001,41.136694],"type":"Point"}
}