{
  "type": "Feature",
  "properties": {
    "addr:full":"720 Madison Ave Norfolk NE 68701",
    "addr:housenumber":"720",
    "addr:postcode":"68701",
    "addr:street":"Madison Ave",
    "iso:country":"US",
    "sg:address":"720 Madison Ave",
    "sg:city":"Norfolk",
    "sg:classifiers":[
        {
            "category":"Utilities",
            "subcategory":"Electric",
            "type":"Services"
        }
    ],
    "sg:phone":"+1 402 371 9000",
    "sg:postcode":"68701",
    "sg:province":"NE",
    "sg:tags":[
        "company"
    ],
    "wof:name":"Nebraska Public Power Dist",
    "wof:placetype":"venue"
},
  "geometry": {"coordinates":[-97.41704300000001,42.031509],"type":"Point"}
}