{
  "type": "Feature",
  "properties": {
    "addr:full":"121 W 2nd St North Platte NE 69101",
    "addr:housenumber":"121",
    "addr:postcode":"69101",
    "addr:street":"W 2Nd St",
    "iso:country":"US",
    "sg:address":"121 W 2nd St",
    "sg:city":"North Platte",
    "sg:classifiers":[
        {
            "category":"Professional",
            "subcategory":"Lawyer & Legal Services",
            "type":"Services"
        }
    ],
    "sg:phone":"+1 308 532 0551",
    "sg:postcode":"69101",
    "sg:province":"NE",
    "sg:tags":[
        "attorney"
    ],
    "wof:name":"Mc Carthy Moore & Hall",
    "wof:placetype":"venue"
},
  "geometry": {"coordinates":[-100.764765,41.134786],"type":"Point"}
}