{
  "type": "Feature",
  "properties": {
    "addr:full":"5624 Hamilton St Omaha NE 68132",
    "addr:housenumber":"5624",
    "addr:postcode":"68132",
    "addr:street":"Hamilton St",
    "iso:country":"US",
    "sg:address":"5624 Hamilton St",
    "sg:city":"Omaha",
    "sg:classifiers":[
        {
            "category":"Professional",
            "subcategory":"Business Services",
            "type":"Services"
        }
    ],
    "sg:phone":"+1 402 556 0000",
    "sg:postcode":"68132",
    "sg:province":"NE",
    "sg:tags":[
        "telemarketing"
    ],
    "wof:name":"Aurora Telemarketing Inc",
    "wof:placetype":"venue"
},
  "geometry": {"coordinates":[-96.00137599999999,41.272327],"type":"Point"}
}