{
  "type": "Feature",
  "properties": {
    "iso:country":"US",
    "sg:address":"20607 Laramie Rd",
    "sg:city":"Elkhorn",
    "sg:classifiers":[
        {
            "category":"Building & Trades",
            "subcategory":"Landscaping Services",
            "type":"Services"
        }
    ],
    "sg:phone":"+1 402 289 5509",
    "sg:postcode":"68022",
    "sg:province":"NE",
    "sg:tags":[
        "landscape"
    ],
    "wof:name":"Antler Country Landscaping",
    "wof:placetype":"venue"
},
  "geometry": {"coordinates":[-96.23657,41.294848],"type":"Point"}
}