{
  "type": "Feature",
  "properties": {
    "iso:country":"US",
    "sg:address":"200 N 34th St",
    "sg:city":"Norfolk",
    "sg:classifiers":[
        {
            "category":"Restaurant",
            "type":"Food & Drink"
        }
    ],
    "sg:phone":"+1 402 371 6612",
    "sg:postcode":"68701",
    "sg:province":"NE",
    "sg:tags":[
        "eating"
    ],
    "wof:name":"JD Brothers Steak Hse & Lounge",
    "wof:placetype":"venue"
},
  "geometry": {"coordinates":[-97.461962,42.033699],"type":"Point"}
}