{
  "type": "Feature",
  "properties": {
    "iso:country":"US",
    "sg:address":"1201 Deer Run Ln",
    "sg:city":"Papillion",
    "sg:classifiers":[
        {
            "category":"Building & Trades",
            "subcategory":"Construction",
            "type":"Services"
        }
    ],
    "sg:phone":"+1 402 592 5217",
    "sg:postcode":"68046",
    "sg:province":"NE",
    "sg:tags":[
        "home",
        "residential",
        "contractor"
    ],
    "wof:name":"Ulrich Bros Construction",
    "wof:placetype":"venue"
},
  "geometry": {"coordinates":[-96.06039800000001,41.167019],"type":"Point"}
}