{
  "type": "Feature",
  "properties": {
    "addr:full":"4415 Prescott Ave Lincoln NE 68506",
    "addr:housenumber":"4415",
    "addr:postcode":"68506",
    "addr:street":"Prescott Ave",
    "iso:country":"US",
    "sg:address":"4415 Prescott Ave",
    "sg:city":"Lincoln",
    "sg:classifiers":[
        {
            "category":"Building & Trades",
            "subcategory":"Construction",
            "type":"Services"
        }
    ],
    "sg:phone":"+1 402 489 4333",
    "sg:postcode":"68506",
    "sg:province":"NE",
    "sg:tags":[
        "house"
    ],
    "wof:name":"Dturek Building & Remodeling I",
    "wof:placetype":"venue"
},
  "geometry": {"coordinates":[-96.65931500000001,40.772856],"type":"Point"}
}