{
  "type": "Feature",
  "properties": {
    "iso:country":"US",
    "sg:address":"1300 Military Rd",
    "sg:city":"Lincoln",
    "sg:classifiers":[
        {
            "category":"Government",
            "subcategory":"Office",
            "type":"Public Place"
        }
    ],
    "sg:phone":"+1 402 309 7210",
    "sg:postcode":"68508",
    "sg:province":"NE",
    "sg:tags":[
        "administration",
        "general"
    ],
    "wof:name":"Military Nebraska Department",
    "wof:placetype":"venue"
},
  "geometry": {"coordinates":[-96.704584,40.830444],"type":"Point"}
}