{
  "type": "Feature",
  "properties": {
    "iso:country":"US",
    "sg:address":"1041 Forrest St",
    "sg:city":"Sidney",
    "sg:classifiers":[
        {
            "category":"Wholesale",
            "subcategory":"Machinery & Supplies",
            "type":"Manufacturing & Wholesale Goods"
        }
    ],
    "sg:phone":"+1 308 254 3011",
    "sg:postcode":"69162",
    "sg:province":"NE",
    "sg:tags":[
        "farm",
        "equipment"
    ],
    "wof:name":"Foland Farm Machinery Inc",
    "wof:placetype":"venue"
},
  "geometry": {"coordinates":[-102.97775,41.147592],"type":"Point"}
}