{
  "type": "Feature",
  "properties": {
    "iso:country":"US",
    "sg:address":"4001 Farnam St",
    "sg:city":"Omaha",
    "sg:classifiers":[
        {
            "category":"Retail",
            "subcategory":"Photofinishing",
            "type":"Services"
        }
    ],
    "sg:phone":"+1 402 344 8758",
    "sg:postcode":"68131",
    "sg:province":"NE",
    "sg:tags":[
        "photo",
        "finishing"
    ],
    "wof:name":"Photo-Graphics",
    "wof:placetype":"venue"
},
  "geometry": {"coordinates":[-95.97456699999999,41.257804],"type":"Point"}
}