{
  "type": "Feature",
  "properties": {
    "iso:country":"US",
    "sg:address":"221 Oakcreek Dr",
    "sg:city":"Lincoln",
    "sg:classifiers":[
        {
            "category":"Building & Trades",
            "subcategory":"Construction",
            "type":"Services"
        }
    ],
    "sg:phone":"+1 402 474 1515",
    "sg:postcode":"68528",
    "sg:province":"NE",
    "sg:tags":[
        "water",
        "restoration",
        "damage"
    ],
    "sg:website":"www.pdrestoration.com",
    "wof:name":"Signature Professional Clean",
    "wof:placetype":"venue"
},
  "geometry": {"coordinates":[-96.72261399999999,40.819616],"type":"Point"}
}