{
  "type": "Feature",
  "properties": {
    "addr:full":"8676 N 130th Rd Cairo NE 68824",
    "addr:housenumber":"8676",
    "addr:postcode":"68824",
    "addr:street":"N 130Th Rd",
    "iso:country":"US",
    "sg:address":"8676 N 130th Rd",
    "sg:city":"Cairo",
    "sg:phone":"+1 308 485 4761",
    "sg:postcode":"68824",
    "sg:province":"NE",
    "sg:tags":[
        "farm",
        "corn"
    ],
    "wof:name":"R S Vieth Farms",
    "wof:placetype":"venue"
},
  "geometry": {"coordinates":[-98.58887199999999,41.033654],"type":"Point"}
}