{
  "type": "Feature",
  "properties": {
    "addr:full":"1835 E Military Ave Fremont NE 68025",
    "addr:housenumber":"1835",
    "addr:postcode":"68025",
    "addr:street":"E Military Ave",
    "iso:country":"US",
    "sg:address":"1835 E Military Ave",
    "sg:city":"Fremont",
    "sg:classifiers":[
        {
            "category":"Professional",
            "subcategory":"Accounting & Tax Preparation",
            "type":"Services"
        }
    ],
    "sg:phone":"+1 402 721 4224",
    "sg:postcode":"68025",
    "sg:province":"NE",
    "sg:tags":[
        "accountant"
    ],
    "wof:name":"Ric Ortmeier CPA",
    "wof:placetype":"venue"
},
  "geometry": {"coordinates":[-96.474394,41.434476],"type":"Point"}
}