{
  "type": "Feature",
  "properties": {
    "iso:country":"US",
    "sg:address":"1701 Farnam St",
    "sg:city":"Omaha",
    "sg:classifiers":[
        {
            "category":"Social Services",
            "type":"Services"
        }
    ],
    "sg:phone":"+1 402 444 7166",
    "sg:postcode":"68102",
    "sg:province":"NE",
    "sg:tags":[
        "probation"
    ],
    "wof:name":"District Probation Office 4",
    "wof:placetype":"venue"
},
  "geometry": {"coordinates":[-95.93983900000001,41.257616],"type":"Point"}
}