{
  "type": "Feature",
  "properties": {
    "iso:country":"US",
    "sg:address":"420 W 5th St",
    "sg:city":"Hastings",
    "sg:classifiers":[
        {
            "category":"Real Estate",
            "subcategory":"Real Estate Services",
            "type":"Services"
        }
    ],
    "sg:phone":"+1 402 463 6673",
    "sg:postcode":"68901",
    "sg:province":"NE",
    "sg:tags":[
        "company",
        "title"
    ],
    "wof:name":"Prairie Title Inc",
    "wof:placetype":"venue"
},
  "geometry": {"coordinates":[-98.387342,40.587982],"type":"Point"}
}