{
  "type": "Feature",
  "properties": {
    "addr:full":"715 Fall Creek Rd Papillion NE 68133",
    "addr:housenumber":"715",
    "addr:postcode":"68133",
    "addr:street":"Fall Creek Rd",
    "iso:country":"US",
    "sg:address":"715 Fall Creek Rd",
    "sg:city":"Papillion",
    "sg:classifiers":[
        {
            "category":"Building & Trades",
            "subcategory":"Construction",
            "type":"Services"
        }
    ],
    "sg:phone":"+1 402 537 0997",
    "sg:postcode":"68133",
    "sg:province":"NE",
    "sg:tags":[
        "house"
    ],
    "wof:name":"TW Builders",
    "wof:placetype":"venue"
},
  "geometry": {"coordinates":[-96.005042,41.165237],"type":"Point"}
}