{
  "type": "Feature",
  "properties": {
    "iso:country":"US",
    "sg:address":"502 Willard Ave",
    "sg:city":"Genoa",
    "sg:classifiers":[
        {
            "category":"Banks & Credit Unions",
            "subcategory":"Bank",
            "type":"Services"
        }
    ],
    "sg:phone":"+1 402 993 2231",
    "sg:postcode":"68640",
    "sg:province":"NE",
    "sg:website":"www.genoanationalbank.com",
    "wof:name":"Genoa National Bank",
    "wof:placetype":"venue"
},
  "geometry": {"coordinates":[-97.731831,41.448599],"type":"Point"}
}