{
  "type": "Feature",
  "properties": {
    "iso:country":"US",
    "sg:address":"16920 Wright Plz",
    "sg:city":"Omaha",
    "sg:classifiers":[
        {
            "category":"Health Services",
            "subcategory":"Doctor",
            "type":"Services"
        }
    ],
    "sg:phone":"+1 402 778 5800",
    "sg:postcode":"68130",
    "sg:province":"NE",
    "sg:tags":[
        "dentist"
    ],
    "wof:name":"Imagine Orthodontics",
    "wof:placetype":"venue"
},
  "geometry": {"coordinates":[-96.182328,41.232688],"type":"Point"}
}