{
  "type": "Feature",
  "properties": {
    "iso:country":"US",
    "sg:address":"3531 N 74th St",
    "sg:city":"Lincoln",
    "sg:classifiers":[
        {
            "category":"Building & Trades",
            "subcategory":"Construction",
            "type":"Services"
        }
    ],
    "sg:phone":"+1 402 560 8257",
    "sg:postcode":"68507",
    "sg:province":"NE",
    "sg:tags":[
        "contractor"
    ],
    "wof:name":"Excel Siding",
    "wof:placetype":"venue"
},
  "geometry": {"coordinates":[-96.62125,40.845506],"type":"Point"}
}