{
  "type": "Feature",
  "properties": {
    "iso:country":"US",
    "sg:address":"40 Ginger Cove Rd",
    "sg:city":"Valley",
    "sg:classifiers":[
        {
            "category":"Professional",
            "subcategory":"Lawyer & Legal Services",
            "type":"Services"
        }
    ],
    "sg:phone":"+1 402 359 5656",
    "sg:postcode":"68064",
    "sg:province":"NE",
    "sg:tags":[
        "attorney"
    ],
    "wof:name":"Demerath Law Offices",
    "wof:placetype":"venue"
},
  "geometry": {"coordinates":[-96.385988,41.31106],"type":"Point"}
}