{
  "type": "Feature",
  "properties": {
    "addr:full":"10250 Regency Cir Omaha NE 68114",
    "addr:housenumber":"10250",
    "addr:postcode":"68114",
    "addr:street":"Regency Cir",
    "iso:country":"US",
    "sg:address":"10250 Regency Cir",
    "sg:city":"Omaha",
    "sg:classifiers":[
        {
            "category":"Banks & Credit Unions",
            "subcategory":"Investment Brokerage",
            "type":"Services"
        }
    ],
    "sg:phone":"+1 402 392 7960",
    "sg:postcode":"68114",
    "sg:province":"NE",
    "sg:tags":[
        "advisory",
        "financial"
    ],
    "sg:website":"www.kirkpatrickpettis.com",
    "wof:name":"KPM Investment Mgmt Inc",
    "wof:placetype":"venue"
},
  "geometry": {"coordinates":[-96.07334299999999,41.258478],"type":"Point"}
}