{
  "type": "Feature",
  "properties": {
    "addr:full":"411 E 11th St Schuyler NE 68661",
    "addr:housenumber":"411",
    "addr:postcode":"68661",
    "addr:street":"E 11Th St",
    "iso:country":"US",
    "sg:address":"411 E 11th St",
    "sg:city":"Schuyler",
    "sg:classifiers":[
        {
            "category":"Government",
            "subcategory":"Office",
            "type":"Public Place"
        }
    ],
    "sg:phone":"+1 402 352 5041",
    "sg:postcode":"68661",
    "sg:province":"NE",
    "sg:tags":[
        "state",
        "program"
    ],
    "wof:name":"Drivers Exam Station",
    "wof:placetype":"venue"
},
  "geometry": {"coordinates":[-97.05585600000001,41.44725],"type":"Point"}
}