{
  "type": "Feature",
  "properties": {
    "iso:country":"US",
    "sg:address":"1730 Bellevue Blvd N",
    "sg:city":"Bellevue",
    "sg:classifiers":[
        {
            "category":"Organizations",
            "subcategory":"Labor Organization",
            "type":"Services"
        }
    ],
    "sg:phone":"+1 402 934 7540",
    "sg:postcode":"68005",
    "sg:province":"NE",
    "wof:name":"Roofers Local Union 85",
    "wof:placetype":"venue"
},
  "geometry": {"coordinates":[-95.93314100000001,41.190713],"type":"Point"}
}