{
  "type": "Feature",
  "properties": {
    "addr:full":"2662 Cornhusker Hwy Lincoln NE 68521",
    "addr:housenumber":"2662",
    "addr:postcode":"68521",
    "addr:street":"Cornhusker Hwy",
    "iso:country":"US",
    "sg:address":"2662 Cornhusker Hwy",
    "sg:city":"Lincoln",
    "sg:classifiers":[
        {
            "category":"Restaurant",
            "type":"Food & Drink"
        }
    ],
    "sg:phone":"+1 402 466 8242",
    "sg:postcode":"68521",
    "sg:province":"NE",
    "sg:tags":[
        "eating",
        "out"
    ],
    "wof:name":"China Inn",
    "wof:placetype":"venue"
},
  "geometry": {"coordinates":[-96.684856,40.842671],"type":"Point"}
}