{
  "type": "Feature",
  "properties": {
    "addr:full":"3405 S 204th St Elkhorn NE 68022",
    "addr:housenumber":"3405",
    "addr:postcode":"68022",
    "addr:street":"S 204Th St",
    "iso:country":"US",
    "sg:address":"3405 S 204th St",
    "sg:city":"Elkhorn",
    "sg:classifiers":[
        {
            "category":"Mining & Drilling",
            "type":"Manufacturing & Wholesale Goods"
        }
    ],
    "sg:phone":"+1 402 289 2862",
    "sg:postcode":"68022",
    "sg:province":"NE",
    "sg:tags":[
        "stone"
    ],
    "wof:name":"Rock Place",
    "wof:placetype":"venue"
},
  "geometry": {"coordinates":[-96.234273,41.223263],"type":"Point"}
}