{
  "type": "Feature",
  "properties": {
    "iso:country":"US",
    "sg:address":"715 N 155th St",
    "sg:city":"Omaha",
    "sg:classifiers":[
        {
            "category":"Building & Trades",
            "subcategory":"Construction",
            "type":"Services"
        }
    ],
    "sg:phone":"+1 402 707 5047",
    "sg:postcode":"68154",
    "sg:province":"NE",
    "sg:tags":[
        "restoration",
        "cleaning",
        "patio",
        "deck"
    ],
    "wof:name":"Squeaky Clean Pressure Washing",
    "wof:placetype":"venue"
},
  "geometry": {"coordinates":[-96.156254,41.267945],"type":"Point"}
}