{
  "type": "Feature",
  "properties": {
    "addr:full":"201 E Omaha Ave Norfolk NE 68701",
    "addr:housenumber":"201",
    "addr:postcode":"68701",
    "addr:street":"E Omaha Ave",
    "iso:country":"US",
    "sg:address":"201 E Omaha Ave",
    "sg:city":"Norfolk",
    "sg:classifiers":[
        {
            "category":"Insurance",
            "subcategory":"Insurance Agent",
            "type":"Services"
        }
    ],
    "sg:phone":"+1 402 379 5827",
    "sg:postcode":"68701",
    "sg:province":"NE",
    "wof:name":"Evert's Insurance Inc",
    "wof:placetype":"venue"
},
  "geometry": {"coordinates":[-97.40573500000001,42.018222],"type":"Point"}
}