{
  "type": "Feature",
  "properties": {
    "addr:full":"5035 S 36th St Omaha NE 68107",
    "addr:housenumber":"5035",
    "addr:postcode":"68107",
    "addr:street":"S 36Th St",
    "iso:country":"US",
    "sg:address":"5035 S 36th St",
    "sg:city":"Omaha",
    "sg:classifiers":[
        {
            "category":"Shopping",
            "subcategory":"Used Merchandise",
            "type":"Retail Goods"
        }
    ],
    "sg:phone":"+1 402 731 4888",
    "sg:postcode":"68107",
    "sg:province":"NE",
    "sg:tags":[
        "shop",
        "thrift"
    ],
    "wof:name":"Goodwill Industries",
    "wof:placetype":"venue"
},
  "geometry": {"coordinates":[-95.96717599999999,41.207527],"type":"Point"}
}