{
  "type": "Feature",
  "properties": {
    "iso:country":"US",
    "sg:address":"101 Church St",
    "sg:city":"Spalding",
    "sg:classifiers":[
        {
            "category":"Education",
            "subcategory":"School",
            "type":"Public Place"
        }
    ],
    "sg:phone":"+1 308 497 2103",
    "sg:postcode":"68643",
    "sg:province":"NE",
    "wof:name":"Spalding Academy",
    "wof:placetype":"venue"
},
  "geometry": {"coordinates":[-97.23406900000001,41.699638],"type":"Point"}
}