{
  "type": "Feature",
  "properties": {
    "iso:country":"US",
    "sg:address":"22108 Riverside Dr",
    "sg:city":"Elkhorn",
    "sg:classifiers":[
        {
            "category":"Professional",
            "subcategory":"Management & Consulting",
            "type":"Services"
        }
    ],
    "sg:phone":"+1 402 289 0909",
    "sg:postcode":"68022",
    "sg:province":"NE",
    "wof:name":"Focus Marketingretail Service",
    "wof:placetype":"venue"
},
  "geometry": {"coordinates":[-96.26140599999999,41.246691],"type":"Point"}
}