{
  "type": "Feature",
  "properties": {
    "addr:full":"3501 S 121st St Omaha NE 68144",
    "addr:housenumber":"3501",
    "addr:postcode":"68144",
    "addr:street":"S 121St St",
    "iso:country":"US",
    "sg:address":"3501 S 121st St",
    "sg:city":"Omaha",
    "sg:classifiers":[
        {
            "category":"Retail",
            "subcategory":"Laundry & Dry Cleaning",
            "type":"Services"
        }
    ],
    "sg:phone":"+1 402 333 2238",
    "sg:postcode":"68144",
    "sg:province":"NE",
    "wof:name":"Vanek Janitorial",
    "wof:placetype":"venue"
},
  "geometry": {"coordinates":[-96.101901,41.224871],"type":"Point"}
}