{
  "type": "Feature",
  "properties": {
    "addr:full":"18641 Gold Cir Omaha NE 68130",
    "addr:housenumber":"18641",
    "addr:postcode":"68130",
    "addr:street":"Gold Cir",
    "iso:country":"US",
    "sg:address":"18641 Gold Cir",
    "sg:city":"Omaha",
    "sg:classifiers":[
        {
            "category":"Utilities",
            "subcategory":"Telephone",
            "type":"Services"
        }
    ],
    "sg:phone":"+1 402 991 8641",
    "sg:postcode":"68130",
    "sg:province":"NE",
    "sg:tags":[
        "communications"
    ],
    "wof:name":"Kidstoysshopcom",
    "wof:placetype":"venue"
},
  "geometry": {"coordinates":[-96.20663999999999,41.235548],"type":"Point"}
}