{
  "type": "Feature",
  "properties": {
    "addr:full":"309 West Ave Holdrege NE 68949",
    "addr:housenumber":"309",
    "addr:postcode":"68949",
    "addr:street":"West Ave",
    "iso:country":"US",
    "sg:address":"309 West Ave",
    "sg:city":"Holdrege",
    "sg:classifiers":[
        {
            "category":"Shopping",
            "subcategory":"Catalog Store",
            "type":"Retail Goods"
        }
    ],
    "sg:phone":"+1 308 995 6565",
    "sg:postcode":"68949",
    "sg:province":"NE",
    "sg:tags":[
        "internet"
    ],
    "wof:name":"Sears Authorized Catalog",
    "wof:placetype":"venue"
},
  "geometry": {"coordinates":[-99.37139999999999,40.43786],"type":"Point"}
}