{
  "type": "Feature",
  "properties": {
    "iso:country":"US",
    "sg:address":"17452 Karen St",
    "sg:city":"Omaha",
    "sg:classifiers":[
        {
            "category":"Building & Trades",
            "subcategory":"Electrical",
            "type":"Services"
        }
    ],
    "sg:phone":"+1 402 891 8359",
    "sg:postcode":"68135",
    "sg:province":"NE",
    "sg:tags":[
        "electrical",
        "contractor"
    ],
    "wof:name":"TNT Electric Inc",
    "wof:placetype":"venue"
},
  "geometry": {"coordinates":[-96.187871,41.213746],"type":"Point"}
}