{
  "type": "Feature",
  "properties": {
    "iso:country":"US",
    "sg:address":"310 Reichmuth Rd",
    "sg:city":"Valley",
    "sg:classifiers":[
        {
            "category":"Food & Beverages",
            "subcategory":"Groceries & Convenience Stores",
            "type":"Retail Goods"
        }
    ],
    "sg:phone":"+1 402 359 4165",
    "sg:postcode":"68064",
    "sg:province":"NE",
    "wof:name":"Ericon",
    "wof:placetype":"venue"
},
  "geometry": {"coordinates":[-96.345924,41.316682],"type":"Point"}
}