{
  "type": "Feature",
  "properties": {
    "iso:country":"US",
    "sg:address":"1430 Central Ave",
    "sg:city":"Kearney",
    "sg:classifiers":[
        {
            "category":"Real Estate",
            "subcategory":"Surveying",
            "type":"Services"
        }
    ],
    "sg:phone":"+1 308 237 3785",
    "sg:postcode":"68847",
    "sg:province":"NE",
    "sg:tags":[
        "surveyor"
    ],
    "wof:name":"Buffalo Surveying Corp",
    "wof:placetype":"venue"
},
  "geometry": {"coordinates":[-99.082027,40.688936],"type":"Point"}
}