{
  "type": "Feature",
  "properties": {
    "addr:full":"609 E Cary St Papillion NE 68046",
    "addr:housenumber":"609",
    "addr:postcode":"68046",
    "addr:street":"E Cary St",
    "iso:country":"US",
    "sg:address":"609 E Cary St",
    "sg:city":"Papillion",
    "sg:classifiers":[
        {
            "category":"Food & Beverages",
            "subcategory":"Groceries & Convenience Stores",
            "type":"Retail Goods"
        }
    ],
    "sg:phone":"+1 402 331 3191",
    "sg:postcode":"68046",
    "sg:province":"NE",
    "wof:name":"Sanbow Inc",
    "wof:placetype":"venue"
},
  "geometry": {"coordinates":[-96.035971,41.172504],"type":"Point"}
}