{
  "type": "Feature",
  "properties": {
    "addr:full":"4006 Twin Creek Dr Bellevue NE 68123",
    "addr:housenumber":"4006",
    "addr:postcode":"68123",
    "addr:street":"Twin Creek Dr",
    "iso:country":"US",
    "sg:address":"4006 Twin Creek Dr",
    "sg:city":"Bellevue",
    "sg:classifiers":[
        {
            "category":"Restaurant",
            "type":"Food & Drink"
        }
    ],
    "sg:phone":"+1 402 291 8855",
    "sg:postcode":"68123",
    "sg:province":"NE",
    "sg:tags":[
        "chinese"
    ],
    "wof:name":"China Road Inc",
    "wof:placetype":"venue"
},
  "geometry": {"coordinates":[-95.972087,41.141043],"type":"Point"}
}