{
  "type": "Feature",
  "properties": {
    "iso:country":"US",
    "sg:address":"13448 L St",
    "sg:city":"Omaha",
    "sg:classifiers":[
        {
            "category":"Shopping",
            "subcategory":"Used Merchandise",
            "type":"Retail Goods"
        }
    ],
    "sg:phone":"+1 402 895 5455",
    "sg:postcode":"68137",
    "sg:province":"NE",
    "sg:tags":[
        "shop",
        "consignment"
    ],
    "wof:name":"Great Find Consignments Gllry",
    "wof:placetype":"venue"
},
  "geometry": {"coordinates":[-96.12699499999999,41.212475],"type":"Point"}
}