{
  "type": "Feature",
  "properties": {
    "iso:country":"US",
    "sg:address":"43351 Rd 760",
    "sg:city":"Lexington",
    "sg:classifiers":[
        {
            "category":"Education",
            "subcategory":"School",
            "type":"Public Place"
        }
    ],
    "sg:phone":"+1 308 324 3564",
    "sg:postcode":"68850",
    "sg:province":"NE",
    "wof:name":"District 7 School",
    "wof:placetype":"venue"
},
  "geometry": {"coordinates":[-99.73988,40.844855],"type":"Point"}
}