{
  "type": "Feature",
  "properties": {
    "iso:country":"US",
    "sg:address":"108 N Main St",
    "sg:city":"Rushville",
    "sg:classifiers":[
        {
            "category":"Wholesale",
            "subcategory":"Farm Supplies",
            "type":"Manufacturing & Wholesale Goods"
        }
    ],
    "sg:phone":"+1 308 327 2172",
    "sg:postcode":"69360",
    "sg:province":"NE",
    "sg:tags":[
        "feed"
    ],
    "wof:name":"H & B Lumber",
    "wof:placetype":"venue"
},
  "geometry": {"coordinates":[-102.463677,42.721097],"type":"Point"}
}