{
  "type": "Feature",
  "properties": {
    "iso:country":"US",
    "sg:address":"10101 N 60th St",
    "sg:city":"Omaha",
    "sg:classifiers":[
        {
            "category":"Wholesale",
            "subcategory":"Plants",
            "type":"Manufacturing & Wholesale Goods"
        }
    ],
    "sg:phone":"+1 402 572 0291",
    "sg:postcode":"68152",
    "sg:province":"NE",
    "sg:tags":[
        "supply"
    ],
    "wof:name":"Amber Valley Nursery",
    "wof:placetype":"venue"
},
  "geometry": {"coordinates":[-96.00465699999999,41.350892],"type":"Point"}
}