{
  "type": "Feature",
  "properties": {
    "addr:full":"288 Summit St Valley NE 68064",
    "addr:housenumber":"288",
    "addr:postcode":"68064",
    "addr:street":"Summit St",
    "iso:country":"US",
    "sg:address":"288 Summit St",
    "sg:city":"Valley",
    "sg:classifiers":[
        {
            "category":"Manufacturing",
            "subcategory":"Glass & Minerals",
            "type":"Manufacturing & Wholesale Goods"
        }
    ],
    "sg:phone":"+1 402 359 5923",
    "sg:postcode":"68064",
    "sg:province":"NE",
    "sg:tags":[
        "ready",
        "concrete",
        "mfg"
    ],
    "wof:name":"Lyman-Richey Corporation",
    "wof:placetype":"venue"
},
  "geometry": {"coordinates":[-96.43092900000001,41.328739],"type":"Point"}
}