{
  "type": "Feature",
  "properties": {
    "addr:full":"213 E 3rd St Superior NE 68978",
    "addr:housenumber":"213",
    "addr:postcode":"68978",
    "addr:street":"E 3Rd St",
    "iso:country":"US",
    "sg:address":"213 E 3rd St",
    "sg:city":"Superior",
    "sg:classifiers":[
        {
            "category":"Professional",
            "subcategory":"Lawyer & Legal Services",
            "type":"Services"
        }
    ],
    "sg:phone":"+1 402 879 4733",
    "sg:postcode":"68978",
    "sg:province":"NE",
    "sg:tags":[
        "attorney"
    ],
    "wof:name":"Timothy S Schmidt",
    "wof:placetype":"venue"
},
  "geometry": {"coordinates":[-98.069917,40.018789],"type":"Point"}
}