{
  "type": "Feature",
  "properties": {
    "addr:full":"43124 US Hwy 283 Lexington NE 68850",
    "addr:postcode":"43124;68850",
    "addr:street":"Us Hwy 283",
    "iso:country":"US",
    "sg:address":"43124 US Hwy 283",
    "sg:city":"Lexington",
    "sg:classifiers":[
        {
            "category":"Wholesale",
            "subcategory":"Farm Supplies",
            "type":"Manufacturing & Wholesale Goods"
        }
    ],
    "sg:phone":"+1 308 324 6393",
    "sg:postcode":"68850",
    "sg:province":"NE",
    "sg:tags":[
        "buyer",
        "livestock"
    ],
    "wof:name":"R & J Cattle Inc",
    "wof:placetype":"venue"
},
  "geometry": {"coordinates":[-99.779996,40.72928],"type":"Point"}
}