{
  "type": "Feature",
  "properties": {
    "iso:country":"US",
    "sg:address":"601 Student Dr",
    "sg:city":"Ogallala",
    "sg:classifiers":[
        {
            "category":"Insurance",
            "subcategory":"Life Insurance",
            "type":"Services"
        }
    ],
    "sg:phone":"+1 308 284 3055",
    "sg:postcode":"69153",
    "sg:province":"NE",
    "sg:tags":[
        "carrier"
    ],
    "wof:name":"Woodmen of World Life Ins",
    "wof:placetype":"venue"
},
  "geometry": {"coordinates":[-101.71440800000001,41.131454],"type":"Point"}
}