{
  "type": "Feature",
  "properties": {
    "iso:country":"US",
    "sg:address":"3605 10th St",
    "sg:city":"Gering",
    "sg:classifiers":[
        {
            "category":"Sports & Exercise",
            "subcategory":"Bowling",
            "type":"Entertainment"
        }
    ],
    "sg:phone":"+1 308 632 2626",
    "sg:postcode":"69341",
    "sg:province":"NE",
    "sg:tags":[
        "center"
    ],
    "wof:name":"Bowl Arena",
    "wof:placetype":"venue"
},
  "geometry": {"coordinates":[-103.66163,41.847691],"type":"Point"}
}