{
  "type": "Feature",
  "properties": {
    "addr:full":"100 N 56th St Lincoln NE 68504",
    "addr:housenumber":"100",
    "addr:postcode":"68504",
    "addr:street":"N 56Th St",
    "iso:country":"US",
    "sg:address":"100 N 56th St",
    "sg:city":"Lincoln",
    "sg:classifiers":[
        {
            "category":"Professional",
            "subcategory":"Accounting & Tax Preparation",
            "type":"Services"
        }
    ],
    "sg:phone":"+1 402 467 5655",
    "sg:postcode":"68504",
    "sg:province":"NE",
    "sg:tags":[
        "accountant"
    ],
    "wof:name":"Anderson Podwinski & Assoc",
    "wof:placetype":"venue"
},
  "geometry": {"coordinates":[-96.64414499999999,40.814606],"type":"Point"}
}