{
  "type": "Feature",
  "properties": {
    "addr:full":"12424 N 204th St Bennington NE 68007",
    "addr:housenumber":"12424",
    "addr:postcode":"68007",
    "addr:street":"N 204Th St",
    "iso:country":"US",
    "sg:address":"12424 N 204th St",
    "sg:city":"Bennington",
    "sg:classifiers":[
        {
            "category":"Shopping",
            "type":"Retail Goods"
        }
    ],
    "sg:phone":"+1 402 238 2755",
    "sg:postcode":"68007",
    "sg:province":"NE",
    "sg:tags":[
        "merchandise"
    ],
    "wof:name":"Susies Home Outlet",
    "wof:placetype":"venue"
},
  "geometry": {"coordinates":[-96.23432200000001,41.370261],"type":"Point"}
}