{
  "type": "Feature",
  "properties": {
    "iso:country":"US",
    "sg:address":"2103 S 60th St",
    "sg:city":"Omaha",
    "sg:classifiers":[
        {
            "category":"Building & Trades",
            "subcategory":"Landscaping Services",
            "type":"Services"
        }
    ],
    "sg:phone":"+1 402 630 5596",
    "sg:postcode":"68106",
    "sg:province":"NE",
    "sg:tags":[
        "lawn",
        "maintenance",
        "grounds"
    ],
    "wof:name":"Sw Complete Lawn Care",
    "wof:placetype":"venue"
},
  "geometry": {"coordinates":[-96.004671,41.239924],"type":"Point"}
}