{
  "type": "Feature",
  "properties": {
    "iso:country":"US",
    "sg:address":"6537 N 40th St",
    "sg:city":"Omaha",
    "sg:classifiers":[
        {
            "category":"Shopping",
            "subcategory":"Hobbies, Toys, & Games",
            "type":"Retail Goods"
        }
    ],
    "sg:phone":"+1 402 453 3104",
    "sg:postcode":"68112",
    "sg:province":"NE",
    "wof:name":"Mlf Finn Fair",
    "wof:placetype":"venue"
},
  "geometry": {"coordinates":[-95.97232,41.319107],"type":"Point"}
}