{
  "type": "Feature",
  "properties": {
    "iso:country":"US",
    "sg:address":"100037 Sugar Factory Rd",
    "sg:city":"Scottsbluff",
    "sg:classifiers":[
        {
            "category":"Wholesale",
            "subcategory":"Machinery & Supplies",
            "type":"Manufacturing & Wholesale Goods"
        }
    ],
    "sg:phone":"+1 308 635 2777",
    "sg:postcode":"69361",
    "sg:province":"NE",
    "sg:tags":[
        "equipment",
        "irrigation",
        "system"
    ],
    "wof:name":"Enterprise Irrigation District",
    "wof:placetype":"venue"
},
  "geometry": {"coordinates":[-103.636342,41.873768],"type":"Point"}
}