{
  "type": "Feature",
  "properties": {
    "addr:full":"502 5th St Alma NE 68949",
    "addr:housenumber":"502",
    "addr:postcode":"68949",
    "addr:street":"5Th St",
    "iso:country":"US",
    "sg:address":"502 5th St",
    "sg:city":"Alma",
    "sg:classifiers":[
        {
            "category":"Personal",
            "subcategory":"Beauty Salon",
            "type":"Services"
        }
    ],
    "sg:phone":"+1 308 928 2614",
    "sg:postcode":"68949",
    "sg:province":"NE",
    "wof:name":"Gwen's Beauty Salon",
    "wof:placetype":"venue"
},
  "geometry": {"coordinates":[-99.36086400000001,40.10229],"type":"Point"}
}