{
  "type": "Feature",
  "properties": {
    "addr:full":"416 W 3rd St Alliance NE 69301",
    "addr:housenumber":"416",
    "addr:postcode":"69301",
    "addr:street":"W 3Rd St",
    "iso:country":"US",
    "sg:address":"416 W 3rd St",
    "sg:city":"Alliance",
    "sg:classifiers":[
        {
            "category":"Professional",
            "subcategory":"Lawyer & Legal Services",
            "type":"Services"
        }
    ],
    "sg:phone":"+1 308 762 5484",
    "sg:postcode":"69301",
    "sg:province":"NE",
    "sg:tags":[
        "attorney"
    ],
    "wof:name":"Chaloupka Holyoke Hofmeister",
    "wof:placetype":"venue"
},
  "geometry": {"coordinates":[-102.87503700000001,42.09717],"type":"Point"}
}