{
  "type": "Feature",
  "properties": {
    "iso:country":"US",
    "sg:address":"618 Main St",
    "sg:city":"Bayard",
    "sg:classifiers":[
        {
            "category":"Food & Beverages",
            "subcategory":"Meat & Fish",
            "type":"Retail Goods"
        }
    ],
    "sg:phone":"+1 308 586 1665",
    "sg:postcode":"69334",
    "sg:province":"NE",
    "wof:name":"Bayard Processing",
    "wof:placetype":"venue"
},
  "geometry": {"coordinates":[-103.32416600000001,41.757268],"type":"Point"}
}