{
  "type": "Feature",
  "properties": {
    "iso:country":"US",
    "sg:address":"127 S Main St",
    "sg:city":"Rushville",
    "sg:classifiers":[
        {
            "category":"Shopping",
            "subcategory":"Discount & Variety Stores",
            "type":"Retail Goods"
        }
    ],
    "sg:phone":"+1 308 327 2269",
    "sg:postcode":"69360",
    "sg:province":"NE",
    "wof:name":"Discount Variety Store",
    "wof:placetype":"venue"
},
  "geometry": {"coordinates":[-102.463835,42.719214],"type":"Point"}
}