{
  "type": "Feature",
  "properties": {
    "iso:country":"US",
    "sg:address":"17601 Storage Rd",
    "sg:city":"Omaha",
    "sg:classifiers":[
        {
            "category":"Autos & Motor Vehicles",
            "subcategory":"Boat Sales",
            "type":"Retail Goods"
        }
    ],
    "sg:phone":"+1 402 593 9877",
    "sg:postcode":"68136",
    "sg:province":"NE",
    "sg:tags":[
        "dealer",
        "sales"
    ],
    "wof:name":"Al's Muddy Motors",
    "wof:placetype":"venue"
},
  "geometry": {"coordinates":[-96.190327,41.182799],"type":"Point"}
}