{
  "type": "Feature",
  "properties": {
    "iso:country":"US",
    "sg:address":"15611 Harrison St",
    "sg:city":"Omaha",
    "sg:classifiers":[
        {
            "category":"Food & Beverages",
            "subcategory":"Groceries & Convenience Stores",
            "type":"Retail Goods"
        }
    ],
    "sg:phone":"+1 402 891 0097",
    "sg:postcode":"68136",
    "sg:province":"NE",
    "wof:name":"Fantasy's Food & Fuel",
    "wof:placetype":"venue"
},
  "geometry": {"coordinates":[-96.15861599999999,41.190835],"type":"Point"}
}