{
  "type": "Feature",
  "properties": {
    "iso:country":"US",
    "sg:address":"3202 Detco Cir",
    "sg:city":"North Platte",
    "sg:classifiers":[
        {
            "category":"Food & Beverages",
            "subcategory":"Groceries & Convenience Stores",
            "type":"Retail Goods"
        }
    ],
    "sg:phone":"+1 308 532 2490",
    "sg:postcode":"69101",
    "sg:province":"NE",
    "wof:name":"Herbst Towing & Repair",
    "wof:placetype":"venue"
},
  "geometry": {"coordinates":[-100.764538,41.107481],"type":"Point"}
}