{
  "type": "Feature",
  "properties": {
    "iso:country":"US",
    "sg:address":"405 Galvin Rd N",
    "sg:city":"Bellevue",
    "sg:classifiers":[
        {
            "category":"Restaurant",
            "type":"Food & Drink"
        }
    ],
    "sg:phone":"+1 402 292 2028",
    "sg:postcode":"68005",
    "sg:province":"NE",
    "sg:tags":[
        "eating"
    ],
    "wof:name":"Romeos Mexican Food and Pizza",
    "wof:placetype":"venue"
},
  "geometry": {"coordinates":[-95.92392599999999,41.165901],"type":"Point"}
}