{
  "type": "Feature",
  "properties": {
    "addr:full":"1210 Nance Ave Lincoln NE 68521",
    "addr:housenumber":"1210",
    "addr:postcode":"68521",
    "addr:street":"Nance Ave",
    "iso:country":"US",
    "sg:address":"1210 Nance Ave",
    "sg:city":"Lincoln",
    "sg:classifiers":[
        {
            "category":"Wholesale",
            "subcategory":"Chemicals & Plastics",
            "type":"Manufacturing & Wholesale Goods"
        }
    ],
    "sg:phone":"+1 402 477 8791",
    "sg:postcode":"68521",
    "sg:province":"NE",
    "sg:tags":[
        "i",
        "industrial",
        "supply"
    ],
    "wof:name":"Praxair",
    "wof:placetype":"venue"
},
  "geometry": {"coordinates":[-96.705676,40.838458],"type":"Point"}
}