{
  "type": "Feature",
  "properties": {
    "iso:country":"US",
    "sg:address":"10818 Elm St",
    "sg:city":"Omaha",
    "sg:classifiers":[
        {
            "category":"Personal",
            "subcategory":"Beauty Salon",
            "type":"Services"
        }
    ],
    "sg:phone":"+1 402 934 2177",
    "sg:postcode":"68144",
    "sg:province":"NE",
    "sg:tags":[
        "unisex",
        "hair"
    ],
    "wof:name":"Seven Salon",
    "wof:placetype":"venue"
},
  "geometry": {"coordinates":[-96.08246,41.232833],"type":"Point"}
}