{
  "type": "Feature",
  "properties": {
    "iso:country":"US",
    "sg:address":"302 E Cornhusker Ave",
    "sg:city":"Anselmo",
    "sg:classifiers":[
        {
            "category":"Farming",
            "subcategory":"Farm & Veterinary Services",
            "type":"Manufacturing & Wholesale Goods"
        }
    ],
    "sg:phone":"+1 308 749 2507",
    "sg:postcode":"68813",
    "sg:province":"NE",
    "sg:tags":[
        "breeder",
        "livestock"
    ],
    "wof:name":"Direct Cattle",
    "wof:placetype":"venue"
},
  "geometry": {"coordinates":[-99.863156,41.622355],"type":"Point"}
}