{
  "type": "Feature",
  "properties": {
    "iso:country":"US",
    "sg:address":"301 Pine St",
    "sg:city":"Big Springs",
    "sg:classifiers":[
        {
            "category":"Government",
            "subcategory":"Fire Station",
            "type":"Public Place"
        }
    ],
    "sg:phone":"+1 308 889 3556",
    "sg:postcode":"69122",
    "sg:province":"NE",
    "sg:tags":[
        "dept",
        "v"
    ],
    "wof:name":"Big Springs Vlntr Fire Dept",
    "wof:placetype":"venue"
},
  "geometry": {"coordinates":[-102.07457599999999,41.062567],"type":"Point"}
}