{
  "type": "Feature",
  "properties": {
    "addr:full":"75670 Rd 430 Lexington NE 68850",
    "addr:postcode":"75670;68850",
    "addr:street":"Rd 430",
    "iso:country":"US",
    "sg:address":"75670 Rd 430",
    "sg:city":"Lexington",
    "sg:classifiers":[
        {
            "category":"Shopping",
            "subcategory":"Computers & Home Electronics",
            "type":"Retail Goods"
        }
    ],
    "sg:phone":"+1 308 324 5114",
    "sg:postcode":"68850",
    "sg:province":"NE",
    "wof:name":"Rt Electronics Inc",
    "wof:placetype":"venue"
},
  "geometry": {"coordinates":[-99.805926,40.795185],"type":"Point"}
}