{
  "type": "Feature",
  "properties": {
    "addr:full":"16100 River Rd Plattsmouth NE 68048",
    "addr:housenumber":"16100",
    "addr:postcode":"68048",
    "addr:street":"River Rd",
    "iso:country":"US",
    "sg:address":"16100 River Rd",
    "sg:city":"Plattsmouth",
    "sg:classifiers":[
        {
            "category":"Building & Trades",
            "subcategory":"Construction",
            "type":"Services"
        }
    ],
    "sg:phone":"+1 402 298 8050",
    "sg:postcode":"68048",
    "sg:province":"NE",
    "sg:tags":[
        "excavation",
        "excavating",
        "contractor"
    ],
    "wof:name":"Scholl Excavating",
    "wof:placetype":"venue"
},
  "geometry": {"coordinates":[-95.87763200000001,41.008044],"type":"Point"}
}