{
  "type": "Feature",
  "properties": {
    "iso:country":"US",
    "sg:address":"502 E Hwy 20",
    "sg:city":"Valentine",
    "sg:classifiers":[
        {
            "category":"Autos & Motor Vehicles",
            "subcategory":"Boat Sales",
            "type":"Retail Goods"
        }
    ],
    "sg:phone":"+1 402 376 2839",
    "sg:postcode":"69201",
    "sg:province":"NE",
    "sg:tags":[
        "canoe"
    ],
    "wof:name":"A & C Canoe Tube & Kayak Rntls",
    "wof:placetype":"venue"
},
  "geometry": {"coordinates":[-100.54545899999999,42.867834],"type":"Point"}
}