{
  "type": "Feature",
  "properties": {
    "iso:country":"US",
    "sg:address":"1123 S Cherry St",
    "sg:city":"Grand Island",
    "sg:classifiers":[
        {
            "category":"Banks & Credit Unions",
            "subcategory":"Investment Brokerage",
            "type":"Services"
        }
    ],
    "sg:phone":"+1 308 382 5414",
    "sg:postcode":"68801",
    "sg:province":"NE",
    "sg:tags":[
        "commodity",
        "contract"
    ],
    "wof:name":"Frontier Commodities LLC",
    "wof:placetype":"venue"
},
  "geometry": {"coordinates":[-98.32480200000001,40.910992],"type":"Point"}
}