{
  "type": "Feature",
  "properties": {
    "iso:country":"US",
    "sg:address":"921 E Donegal St",
    "sg:city":"Oneill",
    "sg:classifiers":[
        {
            "category":"Retail",
            "subcategory":"Auto Repair",
            "type":"Services"
        }
    ],
    "sg:phone":"+1 402 336 2767",
    "sg:postcode":"68763",
    "sg:province":"NE",
    "sg:tags":[
        "automotive"
    ],
    "wof:name":"Kustom Audio Works",
    "wof:placetype":"venue"
},
  "geometry": {"coordinates":[-98.63957600000001,42.467817],"type":"Point"}
}