{
  "type": "Feature",
  "properties": {
    "iso:country":"US",
    "sg:address":"1808 S Lincoln St",
    "sg:city":"Holdrege",
    "sg:classifiers":[
        {
            "category":"Professional",
            "type":"Services"
        }
    ],
    "sg:phone":"+1 308 995 4511",
    "sg:postcode":"68949",
    "sg:province":"NE",
    "wof:name":"K N Svc Inc",
    "wof:placetype":"venue"
},
  "geometry": {"coordinates":[-99.360525,40.417669],"type":"Point"}
}