{
  "type": "Feature",
  "properties": {
    "iso:country":"US",
    "sg:address":"509 W Norfolk Ave",
    "sg:city":"Norfolk",
    "sg:classifiers":[
        {
            "category":"Insurance",
            "subcategory":"Insurance Agent",
            "type":"Services"
        }
    ],
    "sg:phone":"+1 402 371 4505",
    "sg:postcode":"68701",
    "sg:province":"NE",
    "wof:name":"Tom Engelhaupt",
    "wof:placetype":"venue"
},
  "geometry": {"coordinates":[-97.415201,42.032594],"type":"Point"}
}