{
  "type": "Feature",
  "properties": {
    "iso:country":"US",
    "sg:address":"4815 Old Cheney Rd",
    "sg:city":"Lincoln",
    "sg:classifiers":[
        {
            "category":"Utilities",
            "subcategory":"Mobile Phone",
            "type":"Services"
        }
    ],
    "sg:phone":"+1 402 436 5050",
    "sg:postcode":"68516",
    "sg:province":"NE",
    "sg:tags":[
        "telephone",
        "cellular"
    ],
    "wof:name":"Alltel",
    "wof:placetype":"venue"
},
  "geometry": {"coordinates":[-96.652338,40.755153],"type":"Point"}
}