{
  "type": "Feature",
  "properties": {
    "iso:country":"US",
    "sg:address":"6321 N 38th St",
    "sg:city":"Omaha",
    "sg:classifiers":[
        {
            "category":"Building & Trades",
            "subcategory":"Locksmith",
            "type":"Services"
        }
    ],
    "sg:phone":"+1 402 881 3881",
    "sg:postcode":"68111",
    "sg:province":"NE",
    "sg:tags":[
        "key"
    ],
    "wof:name":"Locks A Locksmith",
    "wof:placetype":"venue"
},
  "geometry": {"coordinates":[-95.96951,41.315946],"type":"Point"}
}