{
  "type": "Feature",
  "properties": {
    "addr:full":"2249 Smith St Lincoln NE 68502",
    "addr:housenumber":"2249",
    "addr:postcode":"68502",
    "addr:street":"Smith St",
    "iso:country":"US",
    "sg:address":"2249 Smith St",
    "sg:city":"Lincoln",
    "sg:classifiers":[
        {
            "category":"Real Estate",
            "subcategory":"Real Estate Agent",
            "type":"Services"
        }
    ],
    "sg:phone":"+1 402 438 0313",
    "sg:postcode":"68502",
    "sg:province":"NE",
    "wof:name":"Southpaw Investments LLC",
    "wof:placetype":"venue"
},
  "geometry": {"coordinates":[-96.687804,40.786183],"type":"Point"}
}