{
  "type": "Feature",
  "properties": {
    "addr:full":"109 E 34th Ave Bellevue NE 68005",
    "addr:housenumber":"109",
    "addr:postcode":"68005",
    "addr:street":"E 34Th Ave",
    "iso:country":"US",
    "sg:address":"109 E 34th Ave",
    "sg:city":"Bellevue",
    "sg:classifiers":[
        {
            "category":"Freight",
            "type":"Transportation"
        }
    ],
    "sg:phone":"+1 402 292 6648",
    "sg:postcode":"68005",
    "sg:province":"NE",
    "sg:tags":[
        "special"
    ],
    "wof:name":"JS Storage LLC",
    "wof:placetype":"venue"
},
  "geometry": {"coordinates":[-95.89448299999999,41.124082],"type":"Point"}
}