{
  "type": "Feature",
  "properties": {
    "iso:country":"US",
    "sg:address":"610 S Polk St",
    "sg:city":"Papillion",
    "sg:classifiers":[
        {
            "category":"Health Services",
            "subcategory":"Nursing And Care Facility",
            "type":"Services"
        }
    ],
    "sg:phone":"+1 402 339 7700",
    "sg:postcode":"68046",
    "sg:province":"NE",
    "sg:tags":[
        "home",
        "convalescent"
    ],
    "wof:name":"Papillion Manor Inc",
    "wof:placetype":"venue"
},
  "geometry": {"coordinates":[-96.049553,41.151221],"type":"Point"}
}