{
  "type": "Feature",
  "properties": {
    "iso:country":"US",
    "sg:address":"1720 O St",
    "sg:city":"Lincoln",
    "sg:classifiers":[
        {
            "category":"Wholesale",
            "subcategory":"Non-durable Goods",
            "type":"Manufacturing & Wholesale Goods"
        }
    ],
    "sg:phone":"+1 402 477 4401",
    "sg:postcode":"68508",
    "sg:province":"NE",
    "wof:name":"Creation",
    "wof:placetype":"venue"
},
  "geometry": {"coordinates":[-96.695521,40.813697],"type":"Point"}
}