{
  "type": "Feature",
  "properties": {
    "addr:full":"5800 Old Cheney Rd Lincoln NE 68516",
    "addr:housenumber":"5800",
    "addr:postcode":"68516",
    "addr:street":"Old Cheney Rd",
    "iso:country":"US",
    "sg:address":"5800 Old Cheney Rd",
    "sg:city":"Lincoln",
    "sg:classifiers":[
        {
            "category":"Restaurant",
            "type":"Food & Drink"
        }
    ],
    "sg:menulink":"http://www.allmenus.com/ne/lincoln/194672-mcdonalds/menu/",
    "sg:phone":"+1 402 421 8303",
    "sg:postcode":"68516",
    "sg:province":"NE",
    "sg:tags":[
        "burger",
        "american"
    ],
    "wof:name":"McDonald's",
    "wof:placetype":"venue"
},
  "geometry": {"coordinates":[-96.64162,40.754387],"type":"Point"}
}