{
  "type": "Feature",
  "properties": {
    "iso:country":"US",
    "sg:address":"811 Peach St",
    "sg:city":"Lincoln",
    "sg:classifiers":[
        {
            "category":"Manufacturing",
            "subcategory":"Lumber",
            "type":"Manufacturing & Wholesale Goods"
        }
    ],
    "sg:phone":"+1 402 477 3091",
    "sg:postcode":"68502",
    "sg:province":"NE",
    "sg:tags":[
        "mill"
    ],
    "wof:name":"Brandlwood",
    "wof:placetype":"venue"
},
  "geometry": {"coordinates":[-96.70873,40.793643],"type":"Point"}
}