{
  "type": "Feature",
  "properties": {
    "addr:full":"1518 Monroe St Beatrice NE 68310",
    "addr:housenumber":"1518",
    "addr:postcode":"68310",
    "addr:street":"Monroe St",
    "iso:country":"US",
    "sg:address":"1518 Monroe St",
    "sg:city":"Beatrice",
    "sg:classifiers":[
        {
            "category":"Building & Trades",
            "subcategory":"Construction",
            "type":"Services"
        }
    ],
    "sg:phone":"+1 402 228 1749",
    "sg:postcode":"68310",
    "sg:province":"NE",
    "sg:tags":[
        "floor",
        "laying",
        "contractor"
    ],
    "wof:name":"Richs Floor Service",
    "wof:placetype":"venue"
},
  "geometry": {"coordinates":[-96.73446300000001,40.279037],"type":"Point"}
}