{
  "type": "Feature",
  "properties": {
    "iso:country":"US",
    "sg:address":"112 N Oak St",
    "sg:city":"Paxton",
    "sg:classifiers":[
        {
            "category":"Food & Beverages",
            "subcategory":"Bakery",
            "type":"Retail Goods"
        }
    ],
    "sg:phone":"+1 308 239 2203",
    "sg:postcode":"69155",
    "sg:province":"NE",
    "sg:tags":[
        "baker"
    ],
    "wof:name":"Sweet Shoppe",
    "wof:placetype":"venue"
},
  "geometry": {"coordinates":[-101.356278,41.123467],"type":"Point"}
}