{
  "type": "Feature",
  "properties": {
    "iso:country":"US",
    "sg:address":"231 N Main St",
    "sg:city":"Hay Springs",
    "sg:classifiers":[
        {
            "category":"Insurance",
            "subcategory":"Insurance Agent",
            "type":"Services"
        },
        {
            "category":"Banks & Credit Unions",
            "subcategory":"Bank",
            "type":"Services"
        }
    ],
    "sg:phone":"+1 308 638 4416",
    "sg:postcode":"69347",
    "sg:province":"NE",
    "wof:name":"Security First Bank",
    "wof:placetype":"venue"
},
  "geometry": {"coordinates":[-102.689843,42.685328],"type":"Point"}
}