{
  "type": "Feature",
  "properties": {
    "addr:full":"17908 Pierce Plz Omaha NE 68130",
    "addr:housenumber":"17908",
    "addr:postcode":"68130",
    "addr:street":"Pierce Plz",
    "iso:country":"US",
    "sg:address":"17908 Pierce Plz",
    "sg:city":"Omaha",
    "sg:classifiers":[
        {
            "category":"Social Services",
            "subcategory":"Child Care",
            "type":"Services"
        }
    ],
    "sg:phone":"+1 402 778 1134",
    "sg:postcode":"68130",
    "sg:province":"NE",
    "wof:name":"Imagination Station",
    "wof:placetype":"venue"
},
  "geometry": {"coordinates":[-96.194638,41.247595],"type":"Point"}
}