{
  "type": "Feature",
  "properties": {
    "iso:country":"US",
    "sg:address":"2400 S 11th St",
    "sg:city":"Lincoln",
    "sg:classifiers":[
        {
            "category":"Organizations",
            "subcategory":"Religious Organization",
            "type":"Services"
        }
    ],
    "sg:phone":"+1 402 474 5513",
    "sg:postcode":"68502",
    "sg:province":"NE",
    "sg:tags":[
        "church"
    ],
    "wof:name":"St James United Methodist",
    "wof:placetype":"venue"
},
  "geometry": {"coordinates":[-96.70559299999999,40.78809],"type":"Point"}
}