{
  "type": "Feature",
  "properties": {
    "addr:full":"4404 S 134th St Omaha NE 68137",
    "addr:housenumber":"4404",
    "addr:postcode":"68137",
    "addr:street":"S 134Th St",
    "iso:country":"US",
    "sg:address":"4404 S 134th St",
    "sg:city":"Omaha",
    "sg:classifiers":[
        {
            "category":"Wholesale",
            "subcategory":"Metals & Minerals",
            "type":"Manufacturing & Wholesale Goods"
        }
    ],
    "sg:phone":"+1 402 333 2200",
    "sg:postcode":"68137",
    "sg:province":"NE",
    "sg:tags":[
        "steel",
        "warehouse"
    ],
    "wof:name":"Ryerson",
    "wof:placetype":"venue"
},
  "geometry": {"coordinates":[-96.123497,41.216568],"type":"Point"}
}