{
  "type": "Feature",
  "properties": {
    "addr:full":"547 N Washington St Papillion NE 68046",
    "addr:housenumber":"547",
    "addr:postcode":"68046",
    "addr:street":"N Washington St",
    "iso:country":"US",
    "sg:address":"547 N Washington St",
    "sg:city":"Papillion",
    "sg:classifiers":[
        {
            "category":"Shopping",
            "subcategory":"Jewelry",
            "type":"Retail Goods"
        }
    ],
    "sg:phone":"+1 402 339 5046",
    "sg:postcode":"68046",
    "sg:province":"NE",
    "wof:name":"Malachis",
    "wof:placetype":"venue"
},
  "geometry": {"coordinates":[-96.042815,41.161098],"type":"Point"}
}