{
  "type": "Feature",
  "properties": {
    "iso:country":"US",
    "sg:address":"12075 24th Rd",
    "sg:city":"Elm Creek",
    "sg:phone":"+1 308 856 4642",
    "sg:postcode":"68836",
    "sg:province":"NE",
    "sg:tags":[
        "farm",
        "corn"
    ],
    "wof:name":"Ronald Knapp",
    "wof:placetype":"venue"
},
  "geometry": {"coordinates":[-99.299187,40.699736],"type":"Point"}
}