{
  "type": "Feature",
  "properties": {
    "addr:full":"209 S 4th St Elmwood NE 68349",
    "addr:housenumber":"209",
    "addr:postcode":"68349",
    "addr:street":"S 4Th St",
    "iso:country":"US",
    "sg:address":"209 S 4th St",
    "sg:city":"Elmwood",
    "sg:phone":"+1 402 994 3305",
    "sg:postcode":"68349",
    "sg:province":"NE",
    "sg:tags":[
        "oil"
    ],
    "wof:name":"Cenex Convenience Store",
    "wof:placetype":"venue"
},
  "geometry": {"coordinates":[-96.293651,40.84032],"type":"Point"}
}