{
  "type": "Feature",
  "properties": {
    "iso:country":"US",
    "sg:address":"2128 Cobblestone Rd",
    "sg:city":"Papillion",
    "sg:classifiers":[
        {
            "category":"Professional",
            "subcategory":"Computer Services",
            "type":"Services"
        }
    ],
    "sg:phone":"+1 402 339 8556",
    "sg:postcode":"68133",
    "sg:province":"NE",
    "sg:tags":[
        "programing",
        "custom"
    ],
    "wof:name":"Advanced Theories Applications",
    "wof:placetype":"venue"
},
  "geometry": {"coordinates":[-96.005848,41.152422],"type":"Point"}
}