{
  "type": "Feature",
  "properties": {
    "iso:country":"US",
    "sg:address":"4425 Center St",
    "sg:city":"Omaha",
    "sg:classifiers":[
        {
            "category":"Banks & Credit Unions",
            "subcategory":"Bank",
            "type":"Services"
        }
    ],
    "sg:phone":"+1 402 536 2625",
    "sg:postcode":"68105",
    "sg:province":"NE",
    "wof:name":"Wells Fargo Bank Nebraska N A",
    "wof:placetype":"venue"
},
  "geometry": {"coordinates":[-95.98049899999999,41.241402],"type":"Point"}
}