{
  "type": "Feature",
  "properties": {
    "iso:country":"US",
    "sg:address":"130 W 4th St",
    "sg:city":"Wahoo",
    "sg:classifiers":[
        {
            "category":"Manufacturing",
            "subcategory":"Tools & Machinery",
            "type":"Manufacturing & Wholesale Goods"
        }
    ],
    "sg:phone":"+1 402 443 3448",
    "sg:postcode":"68066",
    "sg:province":"NE",
    "sg:tags":[
        "shop",
        "industrial",
        "hard",
        "machine",
        "equipment",
        "welding"
    ],
    "wof:name":"Gerdts Welding",
    "wof:placetype":"venue"
},
  "geometry": {"coordinates":[-96.620921,41.209094],"type":"Point"}
}