{
  "type": "Feature",
  "properties": {
    "addr:full":"817 E 3rd St Alliance NE 69301",
    "addr:housenumber":"817",
    "addr:postcode":"69301",
    "addr:street":"E 3Rd St",
    "iso:country":"US",
    "sg:address":"817 E 3rd St",
    "sg:city":"Alliance",
    "sg:classifiers":[
        {
            "category":"Wholesale",
            "subcategory":"Electrical",
            "type":"Manufacturing & Wholesale Goods"
        }
    ],
    "sg:phone":"+1 308 762 1148",
    "sg:postcode":"69301",
    "sg:province":"NE",
    "sg:tags":[
        "electric",
        "motor"
    ],
    "wof:name":"Nelson Electric Motor Svc",
    "wof:placetype":"venue"
},
  "geometry": {"coordinates":[-102.860795,42.097239],"type":"Point"}
}