{
  "type": "Feature",
  "properties": {
    "addr:full":"736 South St Gretna NE 68028",
    "addr:housenumber":"736",
    "addr:postcode":"68028",
    "addr:street":"South St",
    "iso:country":"US",
    "sg:address":"736 South St",
    "sg:city":"Gretna",
    "sg:classifiers":[
        {
            "category":"Education",
            "subcategory":"Library",
            "type":"Public Place"
        }
    ],
    "sg:phone":"+1 402 332 4480",
    "sg:postcode":"68028",
    "sg:province":"NE",
    "wof:name":"Gretna Public Library",
    "wof:placetype":"venue"
},
  "geometry": {"coordinates":[-96.24873599999999,41.135974],"type":"Point"}
}