{
  "type": "Feature",
  "properties": {
    "iso:country":"US",
    "sg:address":"611 Gateway Rd",
    "sg:city":"Elkhorn",
    "sg:classifiers":[
        {
            "category":"Restaurant",
            "type":"Food & Drink"
        }
    ],
    "sg:phone":"+1 402 289 4414",
    "sg:postcode":"68022",
    "sg:province":"NE",
    "sg:tags":[
        "parlor",
        "ice",
        "cream"
    ],
    "wof:name":"Dairy Chef",
    "wof:placetype":"venue"
},
  "geometry": {"coordinates":[-96.234042,41.287385],"type":"Point"}
}