{
  "type": "Feature",
  "properties": {
    "addr:full":"207 S Main St Rushville NE 69360",
    "addr:housenumber":"207",
    "addr:postcode":"69360",
    "addr:street":"S Main St",
    "iso:country":"US",
    "sg:address":"207 S Main St",
    "sg:city":"Rushville",
    "sg:classifiers":[
        {
            "category":"Social Services",
            "type":"Services"
        }
    ],
    "sg:phone":"+1 308 327 2877",
    "sg:postcode":"69360",
    "sg:province":"NE",
    "sg:tags":[
        "organization",
        "welfare"
    ],
    "wof:name":"Sheridan County Public Transp",
    "wof:placetype":"venue"
},
  "geometry": {"coordinates":[-102.463841,42.71802],"type":"Point"}
}