{
  "type": "Feature",
  "properties": {
    "addr:full":"1939 N Broad St Fremont NE 68025",
    "addr:housenumber":"1939",
    "addr:postcode":"68025",
    "addr:street":"N Broad St",
    "iso:country":"US",
    "sg:address":"1939 N Broad St",
    "sg:city":"Fremont",
    "sg:classifiers":[
        {
            "category":"Wholesale",
            "subcategory":"Electrical",
            "type":"Manufacturing & Wholesale Goods"
        }
    ],
    "sg:phone":"+1 402 721 8052",
    "sg:postcode":"68025",
    "sg:province":"NE",
    "sg:tags":[
        "equipment"
    ],
    "wof:name":"James A Wiseman",
    "wof:placetype":"venue"
},
  "geometry": {"coordinates":[-96.49760000000001,41.447895],"type":"Point"}
}