{
  "type": "Feature",
  "properties": {
    "iso:country":"US",
    "sg:address":"4110 S 52nd St",
    "sg:city":"Omaha",
    "sg:classifiers":[
        {
            "category":"Wholesale",
            "subcategory":"Electrical",
            "type":"Manufacturing & Wholesale Goods"
        }
    ],
    "sg:phone":"+1 402 731 5252",
    "sg:postcode":"68117",
    "sg:province":"NE",
    "sg:tags":[
        "arts",
        "graphic",
        "mfg",
        "component",
        "product",
        "electronic"
    ],
    "wof:name":"Arrow Electronics Inc",
    "wof:placetype":"venue"
},
  "geometry": {"coordinates":[-95.995392,41.217514],"type":"Point"}
}