{
  "type": "Feature",
  "properties": {
    "iso:country":"US",
    "sg:address":"4362 S 87th St",
    "sg:city":"Omaha",
    "sg:classifiers":[
        {
            "category":"Home & Garden",
            "subcategory":"Furniture",
            "type":"Retail Goods"
        }
    ],
    "sg:phone":"+1 402 991 7258",
    "sg:postcode":"68127",
    "sg:province":"NE",
    "sg:tags":[
        "top",
        "counter"
    ],
    "wof:name":"Premier Countertops",
    "wof:placetype":"venue"
},
  "geometry": {"coordinates":[-96.04685600000001,41.217887],"type":"Point"}
}