{
  "type": "Feature",
  "properties": {
    "iso:country":"US",
    "sg:address":"525 1st St",
    "sg:city":"Milford",
    "sg:classifiers":[
        {
            "category":"Food & Beverages",
            "subcategory":"Groceries & Convenience Stores",
            "type":"Retail Goods"
        }
    ],
    "sg:phone":"+1 402 761 2191",
    "sg:postcode":"68405",
    "sg:province":"NE",
    "sg:tags":[
        "grocer"
    ],
    "wof:name":"Schlegel's Grocery & Meat",
    "wof:placetype":"venue"
},
  "geometry": {"coordinates":[-97.051507,40.774149],"type":"Point"}
}