{
  "type": "Feature",
  "properties": {
    "addr:full":"402 N Bridge St Randolph NE 68771",
    "addr:housenumber":"402",
    "addr:postcode":"68771",
    "addr:street":"N Bridge St",
    "iso:country":"US",
    "sg:address":"402 N Bridge St",
    "sg:city":"Randolph",
    "sg:classifiers":[
        {
            "category":"Organizations",
            "subcategory":"Religious Organization",
            "type":"Services"
        }
    ],
    "sg:phone":"+1 402 337 0341",
    "sg:postcode":"68771",
    "sg:province":"NE",
    "sg:tags":[
        "church"
    ],
    "wof:name":"St Frances Education Ctr",
    "wof:placetype":"venue"
},
  "geometry": {"coordinates":[-97.34929200000001,42.381793],"type":"Point"}
}