{
  "type": "Feature",
  "properties": {
    "iso:country":"US",
    "sg:address":"1601 P St",
    "sg:city":"Lincoln",
    "sg:classifiers":[
        {
            "category":"Shopping",
            "subcategory":"Music",
            "type":"Retail Goods"
        }
    ],
    "sg:phone":"+1 402 475 1601",
    "sg:postcode":"68508",
    "sg:province":"NE",
    "sg:tags":[
        "video",
        "disc",
        "tape",
        "cassette"
    ],
    "wof:name":"Lincoln Sound & Disc",
    "wof:placetype":"venue"
},
  "geometry": {"coordinates":[-96.69673899999999,40.814724],"type":"Point"}
}