{
  "type": "Feature",
  "properties": {
    "iso:country":"US",
    "sg:address":"505 E Walnut St",
    "sg:city":"Harvard",
    "sg:classifiers":[
        {
            "category":"Sports & Exercise",
            "subcategory":"Gym",
            "type":"Entertainment"
        }
    ],
    "sg:phone":"+1 402 772 2471",
    "sg:postcode":"68944",
    "sg:province":"NE",
    "sg:tags":[
        "gymnasium"
    ],
    "wof:name":"Park View Aqua Gym",
    "wof:placetype":"venue"
},
  "geometry": {"coordinates":[-98.091734,40.619013],"type":"Point"}
}