{
  "type": "Feature",
  "properties": {
    "addr:full":"5551 S 48th St Lincoln NE 68516",
    "addr:housenumber":"5551",
    "addr:postcode":"68516",
    "addr:street":"S 48Th St",
    "iso:country":"US",
    "sg:address":"5551 S 48th St",
    "sg:city":"Lincoln",
    "sg:classifiers":[
        {
            "category":"Bars & Pubs",
            "type":"Food & Drink"
        }
    ],
    "sg:phone":"+1 402 423 2996",
    "sg:postcode":"68516",
    "sg:province":"NE",
    "sg:tags":[
        "drinking"
    ],
    "sg:website":"www.penaltyboxpub.com",
    "wof:name":"Penalty Box Pub",
    "wof:placetype":"venue"
},
  "geometry": {"coordinates":[-96.653958,40.758219],"type":"Point"}
}