{
  "type": "Feature",
  "properties": {
    "addr:full":"3713 S 155th St Omaha NE 68144",
    "addr:housenumber":"3713",
    "addr:postcode":"68144",
    "addr:street":"S 155Th St",
    "iso:country":"US",
    "sg:address":"3713 S 155th St",
    "sg:city":"Omaha",
    "sg:classifiers":[
        {
            "category":"Home & Garden",
            "subcategory":"Garden Supply",
            "type":"Retail Goods"
        },
        {
            "category":"Building & Trades",
            "subcategory":"Landscaping Services",
            "type":"Services"
        }
    ],
    "sg:phone":"+1 402 691 8158",
    "sg:postcode":"68144",
    "sg:province":"NE",
    "sg:tags":[
        "sprinkler"
    ],
    "wof:name":"West Omaha Irrigation Lawn LLC",
    "wof:placetype":"venue"
},
  "geometry": {"coordinates":[-96.156988,41.224759],"type":"Point"}
}