{
  "type": "Feature",
  "properties": {
    "addr:full":"3201 S 13th St Norfolk NE 68701",
    "addr:housenumber":"3201",
    "addr:postcode":"68701",
    "addr:street":"S 13Th St",
    "iso:country":"US",
    "sg:address":"3201 S 13th St",
    "sg:city":"Norfolk",
    "sg:classifiers":[
        {
            "category":"Wholesale",
            "subcategory":"Machinery & Supplies",
            "type":"Manufacturing & Wholesale Goods"
        }
    ],
    "sg:phone":"+1 402 371 0144",
    "sg:postcode":"68701",
    "sg:province":"NE",
    "sg:tags":[
        "farm",
        "equipment"
    ],
    "wof:name":"Nebraska Dairy Systems",
    "wof:placetype":"venue"
},
  "geometry": {"coordinates":[-97.426726,41.994511],"type":"Point"}
}