{
  "type": "Feature",
  "properties": {
    "addr:full":"321 W 3rd St Yankton NE 57078",
    "addr:housenumber":"321",
    "addr:postcode":"57078",
    "addr:street":"W 3Rd St",
    "iso:country":"US",
    "sg:address":"321 W 3rd St",
    "sg:city":"Yankton",
    "sg:classifiers":[
        {
            "category":"Social Services",
            "type":"Services"
        }
    ],
    "sg:phone":"+1 605 665 4725",
    "sg:postcode":"57078",
    "sg:province":"NE",
    "sg:tags":[
        "organization",
        "welfare"
    ],
    "wof:name":"Contact Center",
    "wof:placetype":"venue"
},
  "geometry": {"coordinates":[-97.396609,42.869769],"type":"Point"}
}