{
  "type": "Feature",
  "properties": {
    "addr:full":"320 W Hynes Ave Oneill NE 68763",
    "addr:housenumber":"320",
    "addr:postcode":"68763",
    "addr:street":"W Hynes Ave",
    "iso:country":"US",
    "sg:address":"320 W Hynes Ave",
    "sg:city":"Oneill",
    "sg:classifiers":[
        {
            "category":"Real Estate",
            "subcategory":"Real Estate Operator",
            "type":"Services"
        }
    ],
    "sg:phone":"+1 402 336 3933",
    "sg:postcode":"68763",
    "sg:province":"NE",
    "sg:tags":[
        "apartment"
    ],
    "wof:name":"North Park Homes",
    "wof:placetype":"venue"
},
  "geometry": {"coordinates":[-98.65737,42.46502],"type":"Point"}
}