{
  "type": "Feature",
  "properties": {
    "addr:full":"2318 N 26th St Omaha NE 68111",
    "addr:housenumber":"2318",
    "addr:postcode":"68111",
    "addr:street":"N 26Th St",
    "iso:country":"US",
    "sg:address":"2318 N 26th St",
    "sg:city":"Omaha",
    "sg:classifiers":[
        {
            "category":"Organizations",
            "subcategory":"Religious Organization",
            "type":"Services"
        }
    ],
    "sg:phone":"+1 402 345 5285",
    "sg:postcode":"68111",
    "sg:province":"NE",
    "sg:tags":[
        "church"
    ],
    "wof:name":"Robinson Memorial Church",
    "wof:placetype":"venue"
},
  "geometry": {"coordinates":[-95.950158,41.280822],"type":"Point"}
}