{
  "type": "Feature",
  "properties": {
    "addr:full":"4406 Pony Express Rd Kearney NE 68847",
    "addr:housenumber":"4406",
    "addr:postcode":"68847",
    "addr:street":"Pony Express Rd",
    "iso:country":"US",
    "sg:address":"4406 Pony Express Rd",
    "sg:city":"Kearney",
    "sg:classifiers":[
        {
            "category":"Sports & Exercise",
            "subcategory":"Bowling",
            "type":"Entertainment"
        }
    ],
    "sg:phone":"+1 308 234 4231",
    "sg:postcode":"68847",
    "sg:province":"NE",
    "sg:tags":[
        "center"
    ],
    "wof:name":"American Bowling Congress",
    "wof:placetype":"venue"
},
  "geometry": {"coordinates":[-99.078965,40.718618],"type":"Point"}
}