{
  "type": "Feature",
  "properties": {
    "iso:country":"US",
    "sg:address":"205 W A Ave",
    "sg:city":"Red Cloud",
    "sg:classifiers":[
        {
            "category":"Restaurant",
            "type":"Food & Drink"
        }
    ],
    "sg:phone":"+1 308 772 0190",
    "sg:postcode":"68970",
    "sg:province":"NE",
    "sg:tags":[
        "cafe"
    ],
    "wof:name":"SNS Cafe & Lounge",
    "wof:placetype":"venue"
},
  "geometry": {"coordinates":[-98.521314,40.084706],"type":"Point"}
}