{
  "type": "Feature",
  "properties": {
    "iso:country":"US",
    "sg:address":"71365 570th Ave",
    "sg:city":"Fairbury",
    "sg:phone":"+1 402 729 3528",
    "sg:postcode":"68352",
    "sg:province":"NE",
    "sg:tags":[
        "farm",
        "corn"
    ],
    "wof:name":"Tb Farms",
    "wof:placetype":"venue"
},
  "geometry": {"coordinates":[-97.143294,40.168386],"type":"Point"}
}