{
  "type": "Feature",
  "properties": {
    "iso:country":"US",
    "sg:address":"911 Ave D",
    "sg:city":"Kearney",
    "sg:classifiers":[
        {
            "category":"Real Estate",
            "subcategory":"Real Estate Agent",
            "type":"Services"
        }
    ],
    "sg:phone":"+1 308 237 0138",
    "sg:postcode":"68847",
    "sg:province":"NE",
    "wof:name":"Hunt Realty",
    "wof:placetype":"venue"
},
  "geometry": {"coordinates":[-99.07663700000001,40.681821],"type":"Point"}
}