{
  "type": "Feature",
  "properties": {
    "iso:country":"US",
    "sg:address":"303 E 5th St",
    "sg:city":"York",
    "sg:classifiers":[
        {
            "category":"Shopping",
            "type":"Retail Goods"
        }
    ],
    "sg:phone":"+1 402 362 5173",
    "sg:postcode":"68467",
    "sg:province":"NE",
    "sg:tags":[
        "merchandise",
        "monument"
    ],
    "wof:name":"Desch W S Sons Monuments",
    "wof:placetype":"venue"
},
  "geometry": {"coordinates":[-97.590621,40.865934],"type":"Point"}
}