{
  "type": "Feature",
  "properties": {
    "addr:full":"5116 Lafayette Ave Omaha NE 68132",
    "addr:housenumber":"5116",
    "addr:postcode":"68132",
    "addr:street":"Lafayette Ave",
    "iso:country":"US",
    "sg:address":"5116 Lafayette Ave",
    "sg:city":"Omaha",
    "sg:classifiers":[
        {
            "category":"Building & Trades",
            "subcategory":"Locksmith",
            "type":"Services"
        }
    ],
    "sg:phone":"+1 402 715 9674",
    "sg:postcode":"68132",
    "sg:province":"NE",
    "sg:tags":[
        "key"
    ],
    "wof:name":"0 24 Hour A Locksmith",
    "wof:placetype":"venue"
},
  "geometry": {"coordinates":[-95.994343,41.271597],"type":"Point"}
}