{
  "type": "Feature",
  "properties": {
    "iso:country":"US",
    "sg:address":"1721 Stone St",
    "sg:city":"Falls City",
    "sg:classifiers":[
        {
            "category":"Shopping",
            "subcategory":"Computers & Home Electronics",
            "type":"Retail Goods"
        }
    ],
    "sg:phone":"+1 402 245 2878",
    "sg:postcode":"68355",
    "sg:province":"NE",
    "sg:tags":[
        "equipment",
        "dealer"
    ],
    "wof:name":"Affordable Computer Repair",
    "wof:placetype":"venue"
},
  "geometry": {"coordinates":[-95.602982,40.062492],"type":"Point"}
}