{
  "type": "Feature",
  "properties": {
    "addr:full":"764 N Linden St Wahoo NE 68066",
    "addr:housenumber":"764",
    "addr:postcode":"68066",
    "addr:street":"N Linden St",
    "iso:country":"US",
    "sg:address":"764 N Linden St",
    "sg:city":"Wahoo",
    "sg:classifiers":[
        {
            "category":"Organizations",
            "subcategory":"Religious Organization",
            "type":"Services"
        }
    ],
    "sg:phone":"+1 402 443 3369",
    "sg:postcode":"68066",
    "sg:province":"NE",
    "sg:tags":[
        "church"
    ],
    "wof:name":"First Congregational Church",
    "wof:placetype":"venue"
},
  "geometry": {"coordinates":[-96.618516,41.212739],"type":"Point"}
}