{
  "type": "Feature",
  "properties": {
    "iso:country":"US",
    "sg:address":"2903 N 84th St",
    "sg:city":"Omaha",
    "sg:classifiers":[
        {
            "category":"Building & Trades",
            "subcategory":"Pest Control",
            "type":"Services"
        }
    ],
    "sg:phone":"+1 402 397 8884",
    "sg:postcode":"68134",
    "sg:province":"NE",
    "sg:tags":[
        "termite"
    ],
    "wof:name":"Lien Termite & Pest Control Co",
    "wof:placetype":"venue"
},
  "geometry": {"coordinates":[-96.043764,41.286715],"type":"Point"}
}