{
  "type": "Feature",
  "properties": {
    "iso:country":"US",
    "sg:address":"611 W 2nd St",
    "sg:city":"Paxton",
    "sg:classifiers":[
        {
            "category":"Wholesale",
            "subcategory":"Farm Supplies",
            "type":"Manufacturing & Wholesale Goods"
        }
    ],
    "sg:phone":"+1 308 239 4712",
    "sg:postcode":"69155",
    "sg:province":"NE",
    "sg:tags":[
        "livestock"
    ],
    "wof:name":"B&B Livestock",
    "wof:placetype":"venue"
},
  "geometry": {"coordinates":[-101.364239,41.123394],"type":"Point"}
}