{
  "type": "Feature",
  "properties": {
    "iso:country":"US",
    "sg:address":"2825 Q St",
    "sg:city":"Lincoln",
    "sg:classifiers":[
        {
            "category":"Building & Trades",
            "subcategory":"Cleaning & Sanitation",
            "type":"Services"
        }
    ],
    "sg:phone":"+1 402 416 0688",
    "sg:postcode":"68503",
    "sg:province":"NE",
    "sg:tags":[
        "window"
    ],
    "wof:name":"Squeegee Clean Windows",
    "wof:placetype":"venue"
},
  "geometry": {"coordinates":[-96.67967,40.815685],"type":"Point"}
}