{
  "type": "Feature",
  "properties": {
    "addr:full":"1932 Maple St Sidney NE 69162",
    "addr:housenumber":"1932",
    "addr:postcode":"69162",
    "addr:street":"Maple St",
    "iso:country":"US",
    "sg:address":"1932 Maple St",
    "sg:city":"Sidney",
    "sg:classifiers":[
        {
            "category":"Social Services",
            "subcategory":"Child Care",
            "type":"Services"
        }
    ],
    "sg:phone":"+1 308 254 5597",
    "sg:postcode":"69162",
    "sg:province":"NE",
    "sg:tags":[
        "day"
    ],
    "wof:name":"Schaub Doreene Day Care",
    "wof:placetype":"venue"
},
  "geometry": {"coordinates":[-102.988725,41.140594],"type":"Point"}
}