{
  "type": "Feature",
  "properties": {
    "iso:country":"US",
    "sg:address":"11 W 31st St",
    "sg:city":"Kearney",
    "sg:classifiers":[
        {
            "category":"Health Services",
            "subcategory":"Doctor",
            "type":"Services"
        }
    ],
    "sg:phone":"+1 308 865 2555",
    "sg:postcode":"68847",
    "sg:province":"NE",
    "sg:tags":[
        "medical"
    ],
    "wof:name":"Badejo E Adeleke",
    "wof:placetype":"venue"
},
  "geometry": {"coordinates":[-99.081953,40.70652],"type":"Point"}
}