{
  "type": "Feature",
  "properties": {
    "addr:full":"3826 Giles Rd Bellevue NE 68147",
    "addr:housenumber":"3826",
    "addr:postcode":"68147",
    "addr:street":"Giles Rd",
    "iso:country":"US",
    "sg:address":"3826 Giles Rd",
    "sg:city":"Bellevue",
    "sg:classifiers":[
        {
            "category":"Real Estate",
            "subcategory":"Real Estate Agent",
            "type":"Services"
        }
    ],
    "sg:phone":"+1 402 733 5359",
    "sg:postcode":"68147",
    "sg:province":"NE",
    "sg:tags":[
        "finding",
        "apartment",
        "rental"
    ],
    "wof:name":"Temporary VIP Suites",
    "wof:placetype":"venue"
},
  "geometry": {"coordinates":[-95.969685,41.176327],"type":"Point"}
}