{
  "type": "Feature",
  "properties": {
    "addr:full":"1135 Benton St Lincoln NE 68521",
    "addr:housenumber":"1135",
    "addr:postcode":"68521",
    "addr:street":"Benton St",
    "iso:country":"US",
    "sg:address":"1135 Benton St",
    "sg:city":"Lincoln",
    "sg:classifiers":[
        {
            "category":"Freight",
            "type":"Transportation"
        }
    ],
    "sg:phone":"+1 402 438 1876",
    "sg:postcode":"68521",
    "sg:province":"NE",
    "sg:tags":[
        "operator",
        "local",
        "trucking"
    ],
    "wof:name":"Cowdin Trucking",
    "wof:placetype":"venue"
},
  "geometry": {"coordinates":[-96.705888,40.8502],"type":"Point"}
}