{
  "type": "Feature",
  "properties": {
    "iso:country":"US",
    "sg:address":"9707 Q St",
    "sg:city":"Omaha",
    "sg:classifiers":[
        {
            "category":"Banks & Credit Unions",
            "subcategory":"Bank",
            "type":"Services"
        }
    ],
    "sg:phone":"+1 402 331 6370",
    "sg:postcode":"68127",
    "sg:province":"NE",
    "sg:tags":[
        "money",
        "transfer"
    ],
    "sg:website":"www.hy-vee.com",
    "wof:name":"Western Union",
    "wof:placetype":"venue"
},
  "geometry": {"coordinates":[-96.06580200000001,41.20525],"type":"Point"}
}