{
  "type": "Feature",
  "properties": {
    "iso:country":"US",
    "sg:address":"15725 Q Plz",
    "sg:city":"Omaha",
    "sg:classifiers":[
        {
            "category":"Recreation",
            "type":"Entertainment"
        },
        {
            "category":"Sports & Exercise",
            "subcategory":"Skate Park",
            "type":"Entertainment"
        }
    ],
    "sg:phone":"+1 402 369 0770",
    "sg:postcode":"68135",
    "sg:province":"NE",
    "sg:tags":[
        "magician",
        "entertainers-family",
        "business"
    ],
    "sg:website":"http://www.joebrogielive.com",
    "wof:name":"Joe Brogie- Magician/ Menatlist/ Hypnotist",
    "wof:placetype":"venue"
},
  "geometry": {"coordinates":[-96.16066,41.204972],"type":"Point"}
}