{
  "type": "Feature",
  "properties": {
    "iso:country":"US",
    "sg:address":"702 Keystone Lake Rd",
    "sg:city":"Keystone",
    "sg:phone":"+1 308 726 2558",
    "sg:postcode":"69144",
    "sg:province":"NE",
    "sg:tags":[
        "farm",
        "corn"
    ],
    "wof:name":"Wayne Hansmeier",
    "wof:placetype":"venue"
},
  "geometry": {"coordinates":[-101.61496,41.220922],"type":"Point"}
}