{
  "type": "Feature",
  "properties": {
    "iso:country":"US",
    "sg:address":"945 N Adams St",
    "sg:city":"Papillion",
    "sg:classifiers":[
        {
            "category":"Health Services",
            "subcategory":"Chiropractor",
            "type":"Services"
        }
    ],
    "sg:phone":"+1 402 933 0867",
    "sg:postcode":"68046",
    "sg:province":"NE",
    "wof:name":"Worrell Chiropractic Clinic",
    "wof:placetype":"venue"
},
  "geometry": {"coordinates":[-96.04429,41.170338],"type":"Point"}
}