{
  "type": "Feature",
  "properties": {
    "addr:full":"102 E 9th St Cozad NE 69130",
    "addr:housenumber":"102",
    "addr:postcode":"69130",
    "addr:street":"E 9Th St",
    "iso:country":"US",
    "sg:address":"102 E 9th St",
    "sg:city":"Cozad",
    "sg:classifiers":[
        {
            "category":"Government",
            "subcategory":"Post Office",
            "type":"Public Place"
        }
    ],
    "sg:phone":"+1 308 000 1111",
    "sg:postcode":"69130",
    "sg:province":"NE",
    "wof:name":"US Post Office",
    "wof:placetype":"venue"
},
  "geometry": {"coordinates":[-99.985912,40.860685],"type":"Point"}
}