{
  "type": "Feature",
  "properties": {
    "iso:country":"US",
    "sg:address":"101 N 4th St",
    "sg:city":"Norfolk",
    "sg:classifiers":[
        {
            "category":"Organizations",
            "subcategory":"Religious Organization",
            "type":"Services"
        }
    ],
    "sg:phone":"+1 402 379 7859",
    "sg:postcode":"68701",
    "sg:province":"NE",
    "sg:tags":[
        "church"
    ],
    "wof:name":"Grace Community",
    "wof:placetype":"venue"
},
  "geometry": {"coordinates":[-97.411878,42.033359],"type":"Point"}
}