{
  "type": "Feature",
  "properties": {
    "iso:country":"US",
    "sg:address":"1540 US Hwy 20",
    "sg:city":"Chadron",
    "sg:classifiers":[
        {
            "category":"Wholesale",
            "subcategory":"Auto Parts",
            "type":"Manufacturing & Wholesale Goods"
        }
    ],
    "sg:phone":"+1 308 432 3383",
    "sg:postcode":"69337",
    "sg:province":"NE",
    "sg:tags":[
        "body",
        "automobile",
        "shop"
    ],
    "wof:name":"Marshall Auto Parts",
    "wof:placetype":"venue"
},
  "geometry": {"coordinates":[-103.023921,42.828519],"type":"Point"}
}