{
  "type": "Feature",
  "properties": {
    "addr:full":"300 South Rd Farwell NE 68838",
    "addr:housenumber":"300",
    "addr:postcode":"68838",
    "addr:street":"South Rd",
    "iso:country":"US",
    "sg:address":"300 South Rd",
    "sg:city":"Farwell",
    "sg:classifiers":[
        {
            "category":"Government",
            "subcategory":"Office",
            "type":"Public Place"
        }
    ],
    "sg:phone":"+1 308 336 3402",
    "sg:postcode":"68838",
    "sg:province":"NE",
    "sg:tags":[
        "village"
    ],
    "wof:name":"Village Of Farwell",
    "wof:placetype":"venue"
},
  "geometry": {"coordinates":[-98.629352,41.213218],"type":"Point"}
}