{
  "type": "Feature",
  "properties": {
    "iso:country":"US",
    "sg:address":"1410 US Hwy 30",
    "sg:city":"Blair",
    "sg:classifiers":[
        {
            "category":"Home & Garden",
            "subcategory":"Hardware",
            "type":"Retail Goods"
        }
    ],
    "sg:phone":"+1 402 533 8133",
    "sg:postcode":"68008",
    "sg:province":"NE",
    "sg:website":"www.bomgaars.com",
    "wof:name":"Bomgaars",
    "wof:placetype":"venue"
},
  "geometry": {"coordinates":[-96.133324,41.543761],"type":"Point"}
}