{
  "type": "Feature",
  "properties": {
    "addr:full":"2401 Jameson N Lincoln NE 68512",
    "addr:housenumber":"2401",
    "addr:postcode":"68512",
    "addr:street":"Jameson N",
    "iso:country":"US",
    "sg:address":"2401 Jameson N",
    "sg:city":"Lincoln",
    "sg:classifiers":[
        {
            "category":"Shopping",
            "subcategory":"Hobbies, Toys, & Games",
            "type":"Retail Goods"
        }
    ],
    "sg:phone":"+1 402 421 3868",
    "sg:postcode":"68512",
    "sg:province":"NE",
    "wof:name":"Marion Rumbolz Artist",
    "wof:placetype":"venue"
},
  "geometry": {"coordinates":[-96.685515,40.757961],"type":"Point"}
}