{
  "type": "Feature",
  "properties": {
    "addr:full":"413 S 11th St Omaha NE 68102",
    "addr:housenumber":"413",
    "addr:postcode":"68102",
    "addr:street":"S 11Th St",
    "iso:country":"US",
    "sg:address":"413 S 11th St",
    "sg:city":"Omaha",
    "sg:classifiers":[
        {
            "category":"Personal",
            "subcategory":"Hair Removal",
            "type":"Services"
        },
        {
            "category":"Personal",
            "subcategory":"Day Spa",
            "type":"Services"
        },
        {
            "category":"Personal",
            "subcategory":"Nail Salon",
            "type":"Services"
        },
        {
            "category":"Personal",
            "subcategory":"Skin Care",
            "type":"Services"
        },
        {
            "category":"Personal",
            "subcategory":"Beauty Salon",
            "type":"Services"
        },
        {
            "category":"Personal",
            "subcategory":"Massage",
            "type":"Services"
        }
    ],
    "sg:phone":"+1 402 345 3692",
    "sg:postcode":"68102",
    "sg:province":"NE",
    "sg:tags":[
        "stylist"
    ],
    "sg:website":"hairmarketsalon.com",
    "wof:name":"Hair Market Salon",
    "wof:placetype":"venue"
},
  "geometry": {"coordinates":[-95.930397,41.256199],"type":"Point"}
}