{
  "type": "Feature",
  "properties": {
    "iso:country":"US",
    "sg:address":"1483 1st Ave",
    "sg:city":"Jackson",
    "sg:classifiers":[
        {
            "category":"Retail",
            "subcategory":"Auto Repair",
            "type":"Services"
        }
    ],
    "sg:phone":"+1 402 632 4882",
    "sg:postcode":"68776",
    "sg:province":"NE",
    "sg:tags":[
        "truck"
    ],
    "wof:name":"Butch's Truck Repair",
    "wof:placetype":"venue"
},
  "geometry": {"coordinates":[-96.41399800000001,42.47621],"type":"Point"}
}