{
  "type": "Feature",
  "properties": {
    "addr:full":"56915 724th Rd Daykin NE 68338",
    "addr:housenumber":"56915",
    "addr:postcode":"68338",
    "addr:street":"724Th Rd",
    "iso:country":"US",
    "sg:address":"56915 724th Rd",
    "sg:city":"Daykin",
    "sg:classifiers":[
        {
            "category":"Farming",
            "subcategory":"Livestock Farm",
            "type":"Manufacturing & Wholesale Goods"
        }
    ],
    "sg:phone":"+1 402 446 7343",
    "sg:postcode":"68338",
    "sg:province":"NE",
    "sg:tags":[
        "beef",
        "feedlot",
        "soybean",
        "cattle"
    ],
    "wof:name":"Mark Koenig",
    "wof:placetype":"venue"
},
  "geometry": {"coordinates":[-97.144355,40.320688],"type":"Point"}
}