{
  "type": "Feature",
  "properties": {
    "iso:country":"US",
    "sg:address":"1742 Normandy Ln",
    "sg:city":"Lincoln",
    "sg:classifiers":[
        {
            "category":"Building & Trades",
            "subcategory":"Construction",
            "type":"Services"
        }
    ],
    "sg:phone":"+1 402 420 1640",
    "sg:postcode":"68512",
    "sg:province":"NE",
    "sg:tags":[
        "general",
        "contractor"
    ],
    "wof:name":"Kramer Homes",
    "wof:placetype":"venue"
},
  "geometry": {"coordinates":[-96.69454,40.756117],"type":"Point"}
}