{
  "type": "Feature",
  "properties": {
    "iso:country":"US",
    "sg:address":"1603 Broadway",
    "sg:city":"Scottsbluff",
    "sg:classifiers":[
        {
            "category":"Shopping",
            "subcategory":"Clothing, Apparel, & Fashions",
            "type":"Retail Goods"
        }
    ],
    "sg:phone":"+1 308 632 7259",
    "sg:postcode":"69361",
    "sg:province":"NE",
    "sg:tags":[
        "family"
    ],
    "wof:name":"Merry-Go-Round",
    "wof:placetype":"venue"
},
  "geometry": {"coordinates":[-103.66265799999999,41.863246],"type":"Point"}
}