{
  "type": "Feature",
  "properties": {
    "iso:country":"US",
    "sg:address":"309 Pine St",
    "sg:city":"Omaha",
    "sg:classifiers":[
        {
            "category":"Utilities",
            "subcategory":"Refuse",
            "type":"Services"
        }
    ],
    "sg:phone":"+1 402 612 3934",
    "sg:postcode":"68108",
    "sg:province":"NE",
    "sg:tags":[
        "garbage",
        "collection"
    ],
    "wof:name":"C & B Containers",
    "wof:placetype":"venue"
},
  "geometry": {"coordinates":[-95.920985,41.243723],"type":"Point"}
}