{
  "type": "Feature",
  "properties": {
    "iso:country":"US",
    "sg:address":"1402 Main St",
    "sg:city":"Bellevue",
    "sg:classifiers":[
        {
            "category":"Education",
            "subcategory":"School",
            "type":"Public Place"
        }
    ],
    "sg:phone":"+1 402 293 4560",
    "sg:postcode":"68005",
    "sg:province":"NE",
    "sg:website":"www.bellevuecia.org",
    "wof:name":"Bertha Barber Elementary",
    "wof:placetype":"venue"
},
  "geometry": {"coordinates":[-95.890933,41.144771],"type":"Point"}
}