{
  "type": "Feature",
  "properties": {
    "iso:country":"US",
    "sg:address":"2727 W 2nd St",
    "sg:city":"Hastings",
    "sg:classifiers":[
        {
            "category":"Insurance",
            "subcategory":"Hazard Insurance",
            "type":"Services"
        }
    ],
    "sg:phone":"+1 402 463 4245",
    "sg:postcode":"68901",
    "sg:province":"NE",
    "sg:tags":[
        "federal",
        "corporation",
        "crop"
    ],
    "wof:name":"Midwest Crop Growers Inc",
    "wof:placetype":"venue"
},
  "geometry": {"coordinates":[-98.419738,40.585171],"type":"Point"}
}