{
  "type": "Feature",
  "properties": {
    "iso:country":"US",
    "sg:address":"6950 J St",
    "sg:city":"Omaha",
    "sg:classifiers":[
        {
            "category":"Freight",
            "type":"Transportation"
        }
    ],
    "sg:phone":"+1 402 596 1181",
    "sg:postcode":"68117",
    "sg:province":"NE",
    "sg:tags":[
        "operator",
        "trucking"
    ],
    "sg:website":"www.vitran-express.com",
    "wof:name":"Vitran Express Inc",
    "wof:placetype":"venue"
},
  "geometry": {"coordinates":[-96.019237,41.21508],"type":"Point"}
}