{
  "type": "Feature",
  "properties": {
    "iso:country":"US",
    "sg:address":"417 Burlington St",
    "sg:city":"Holdrege",
    "sg:classifiers":[
        {
            "category":"Wholesale",
            "subcategory":"Machinery & Supplies",
            "type":"Manufacturing & Wholesale Goods"
        }
    ],
    "sg:phone":"+1 308 995 4800",
    "sg:postcode":"68949",
    "sg:province":"NE",
    "sg:tags":[
        "janitorial"
    ],
    "wof:name":"Clinch Enterprises",
    "wof:placetype":"venue"
},
  "geometry": {"coordinates":[-99.38014,40.438251],"type":"Point"}
}