{
  "type": "Feature",
  "properties": {
    "iso:country":"US",
    "sg:address":"1408 5th St",
    "sg:city":"Aurora",
    "sg:classifiers":[
        {
            "category":"Social Services",
            "subcategory":"Adult Care",
            "type":"Services"
        }
    ],
    "sg:phone":"+1 402 694 0180",
    "sg:postcode":"68818",
    "sg:province":"NE",
    "sg:tags":[
        "home"
    ],
    "wof:name":"Martin Luther Homes-Nebraska",
    "wof:placetype":"venue"
},
  "geometry": {"coordinates":[-98.012196,40.870681],"type":"Point"}
}