{
  "type": "Feature",
  "properties": {
    "iso:country":"US",
    "sg:address":"4600 N 27th St",
    "sg:city":"Lincoln",
    "sg:classifiers":[
        {
            "category":"Banks & Credit Unions",
            "subcategory":"Bank",
            "type":"Services"
        }
    ],
    "sg:phone":"+1 402 434 4900",
    "sg:postcode":"68521",
    "sg:province":"NE",
    "sg:tags":[
        "national",
        "commercial"
    ],
    "wof:name":"Wells Fargo",
    "wof:placetype":"venue"
},
  "geometry": {"coordinates":[-96.681963,40.857887],"type":"Point"}
}