{
  "type": "Feature",
  "properties": {
    "iso:country":"US",
    "sg:address":"9140 W Dodge Rd",
    "sg:city":"Omaha",
    "sg:classifiers":[
        {
            "category":"Insurance",
            "subcategory":"Insurance Agent",
            "type":"Services"
        }
    ],
    "sg:phone":"+1 402 391 0222",
    "sg:postcode":"68114",
    "sg:province":"NE",
    "sg:tags":[
        "legal"
    ],
    "wof:name":"Stock Bridge Associates",
    "wof:placetype":"venue"
},
  "geometry": {"coordinates":[-96.054029,41.263418],"type":"Point"}
}