{
  "type": "Feature",
  "properties": {
    "iso:country":"US",
    "sg:address":"3826 W Stolley Park Rd",
    "sg:city":"Grand Island",
    "sg:classifiers":[
        {
            "category":"Shopping",
            "type":"Retail Goods"
        }
    ],
    "sg:phone":"+1 308 382 5866",
    "sg:postcode":"68803",
    "sg:province":"NE",
    "sg:tags":[
        "merchandise"
    ],
    "wof:name":"Herstead Monuments",
    "wof:placetype":"venue"
},
  "geometry": {"coordinates":[-98.3934,40.902506],"type":"Point"}
}