{
  "type": "Feature",
  "properties": {
    "iso:country":"US",
    "sg:address":"6733 N 56th St",
    "sg:city":"Omaha",
    "sg:classifiers":[
        {
            "category":"Manufacturing",
            "subcategory":"Building Materials",
            "type":"Manufacturing & Wholesale Goods"
        }
    ],
    "sg:phone":"+1 402 571 1200",
    "sg:postcode":"68152",
    "sg:province":"NE",
    "sg:tags":[
        "cabinet"
    ],
    "wof:name":"Total Custom Cabinetry",
    "wof:placetype":"venue"
},
  "geometry": {"coordinates":[-95.999672,41.319252],"type":"Point"}
}