{
  "type": "Feature",
  "properties": {
    "iso:country":"US",
    "sg:address":"422 Norris Ave",
    "sg:city":"Mc Cook",
    "sg:classifiers":[
        {
            "category":"Professional",
            "subcategory":"Accounting & Tax Preparation",
            "type":"Services"
        }
    ],
    "sg:phone":"+1 308 345 4010",
    "sg:postcode":"69001",
    "sg:province":"NE",
    "sg:tags":[
        "accountant"
    ],
    "wof:name":"Terry Pettit CPA",
    "wof:placetype":"venue"
},
  "geometry": {"coordinates":[-100.62588100000001,40.201439],"type":"Point"}
}