{
  "type": "Feature",
  "properties": {
    "iso:country":"US",
    "sg:address":"136 N 15th St",
    "sg:city":"Ord",
    "sg:classifiers":[
        {
            "category":"Food & Beverages",
            "subcategory":"Groceries & Convenience Stores",
            "type":"Retail Goods"
        }
    ],
    "sg:phone":"+1 308 728 5861",
    "sg:postcode":"68862",
    "sg:province":"NE",
    "sg:tags":[
        "grocer"
    ],
    "wof:name":"Grocery Kart",
    "wof:placetype":"venue"
},
  "geometry": {"coordinates":[-98.928043,41.603114],"type":"Point"}
}