{
  "type": "Feature",
  "properties": {
    "iso:country":"US",
    "sg:address":"204 Sherwood Rd",
    "sg:city":"Norfolk",
    "sg:classifiers":[
        {
            "category":"Sports & Exercise",
            "subcategory":"Race Track",
            "type":"Entertainment"
        }
    ],
    "sg:phone":"+1 402 371 3936",
    "sg:postcode":"68701",
    "sg:province":"NE",
    "sg:tags":[
        "operation",
        "racing"
    ],
    "wof:name":"Riviera Raceway Inc",
    "wof:placetype":"venue"
},
  "geometry": {"coordinates":[-97.4085,41.989314],"type":"Point"}
}