{
  "type": "Feature",
  "properties": {
    "iso:country":"US",
    "sg:address":"900 N 17th St",
    "sg:city":"Lincoln",
    "sg:classifiers":[
        {
            "category":"Government",
            "subcategory":"Office",
            "type":"Public Place"
        }
    ],
    "sg:phone":"+1 402 441 7171",
    "sg:postcode":"68508",
    "sg:province":"NE",
    "wof:name":"Lancaster County Switchboard",
    "wof:placetype":"venue"
},
  "geometry": {"coordinates":[-96.696437,40.822202],"type":"Point"}
}