{
  "type": "Feature",
  "properties": {
    "iso:country":"US",
    "sg:address":"1488 Holdredge Rd",
    "sg:city":"Pleasant Dale",
    "sg:classifiers":[
        {
            "category":"Farming",
            "subcategory":"Livestock Farm",
            "type":"Manufacturing & Wholesale Goods"
        }
    ],
    "sg:phone":"+1 402 795 5305",
    "sg:postcode":"68423",
    "sg:province":"NE",
    "sg:tags":[
        "feedlot",
        "grain",
        "cash",
        "beef",
        "cattle"
    ],
    "wof:name":"Terry Klug",
    "wof:placetype":"venue"
},
  "geometry": {"coordinates":[-96.917029,40.828437],"type":"Point"}
}