{
  "type": "Feature",
  "properties": {
    "addr:full":"807 S 13th St Norfolk NE 68701",
    "addr:housenumber":"807",
    "addr:postcode":"68701",
    "addr:street":"S 13Th St",
    "iso:country":"US",
    "sg:address":"807 S 13th St",
    "sg:city":"Norfolk",
    "sg:classifiers":[
        {
            "category":"Retail",
            "subcategory":"Laundry & Dry Cleaning",
            "type":"Services"
        }
    ],
    "sg:phone":"+1 402 379 6762",
    "sg:postcode":"68701",
    "sg:province":"NE",
    "wof:name":"Clothes Hamper",
    "wof:placetype":"venue"
},
  "geometry": {"coordinates":[-97.426428,42.023438],"type":"Point"}
}