{
  "type": "Feature",
  "properties": {
    "iso:country":"US",
    "sg:address":"10901 Cromwell Dr",
    "sg:city":"Lincoln",
    "sg:classifiers":[
        {
            "category":"Social Services",
            "type":"Services"
        }
    ],
    "sg:phone":"+1 402 423 8456",
    "sg:postcode":"68516",
    "sg:province":"NE",
    "wof:name":"Superior Child Dlvelopment Ctr",
    "wof:placetype":"venue"
},
  "geometry": {"coordinates":[-96.65142299999999,40.701597],"type":"Point"}
}