{
  "type": "Feature",
  "properties": {
    "iso:country":"US",
    "sg:address":"621 N Cedar St",
    "sg:city":"Red Cloud",
    "sg:classifiers":[
        {
            "category":"Government",
            "subcategory":"Office",
            "type":"Public Place"
        }
    ],
    "sg:phone":"+1 402 746 2493",
    "sg:postcode":"68970",
    "sg:province":"NE",
    "wof:name":"Webster Veteran's Svc",
    "wof:placetype":"venue"
},
  "geometry": {"coordinates":[-98.520753,40.091717],"type":"Point"}
}