{
  "type": "Feature",
  "properties": {
    "iso:country":"US",
    "sg:address":"2242 Gaeth Ave",
    "sg:city":"Fremont",
    "sg:classifiers":[
        {
            "category":"Building & Trades",
            "subcategory":"Landscaping Services",
            "type":"Services"
        }
    ],
    "sg:phone":"+1 402 721 2727",
    "sg:postcode":"68025",
    "sg:province":"NE",
    "sg:tags":[
        "landscape"
    ],
    "wof:name":"Jessen Sodding Co",
    "wof:placetype":"venue"
},
  "geometry": {"coordinates":[-96.468835,41.443275],"type":"Point"}
}