{
  "type": "Feature",
  "properties": {
    "iso:country":"US",
    "sg:address":"6001 A St",
    "sg:city":"Lincoln",
    "sg:classifiers":[
        {
            "category":"Organizations",
            "subcategory":"Religious Organization",
            "type":"Services"
        }
    ],
    "sg:phone":"+1 402 488 7139",
    "sg:postcode":"68510",
    "sg:province":"NE",
    "sg:tags":[
        "church"
    ],
    "sg:website":"www.holytrinitylincoln.com",
    "wof:name":"Holy Trinity Episcopal Church",
    "wof:placetype":"venue"
},
  "geometry": {"coordinates":[-96.638727,40.798884],"type":"Point"}
}