{
  "type": "Feature",
  "properties": {
    "addr:full":"1465 Maple St Chadron NE 69337",
    "addr:housenumber":"1465",
    "addr:postcode":"69337",
    "addr:street":"Maple St",
    "iso:country":"US",
    "sg:address":"1465 Maple St",
    "sg:city":"Chadron",
    "sg:classifiers":[
        {
            "category":"Shopping",
            "subcategory":"Beauty & Cosmetics",
            "type":"Retail Goods"
        }
    ],
    "sg:phone":"+1 308 432 2287",
    "sg:postcode":"69337",
    "sg:province":"NE",
    "sg:tags":[
        "merchandise"
    ],
    "wof:name":"Mary-Kay",
    "wof:placetype":"venue"
},
  "geometry": {"coordinates":[-103.00850699999999,42.814575],"type":"Point"}
}