{
  "type": "Feature",
  "properties": {
    "iso:country":"US",
    "sg:address":"238 Elm St",
    "sg:city":"Crawford",
    "sg:classifiers":[
        {
            "category":"Organizations",
            "subcategory":"Religious Organization",
            "type":"Services"
        }
    ],
    "sg:phone":"+1 308 665 2067",
    "sg:postcode":"69339",
    "sg:province":"NE",
    "sg:tags":[
        "church"
    ],
    "wof:name":"United Methodist Church",
    "wof:placetype":"venue"
},
  "geometry": {"coordinates":[-103.41187499999999,42.685824],"type":"Point"}
}