{
  "type": "Feature",
  "properties": {
    "iso:country":"US",
    "sg:address":"711 E B St",
    "sg:city":"Mc Cook",
    "sg:classifiers":[
        {
            "category":"Retail",
            "subcategory":"Auto Repair",
            "type":"Services"
        }
    ],
    "sg:phone":"+1 308 345 6026",
    "sg:postcode":"69001",
    "sg:province":"NE",
    "sg:tags":[
        "repairing",
        "automobile",
        "radiator"
    ],
    "wof:name":"Babe's Radiator Repair",
    "wof:placetype":"venue"
},
  "geometry": {"coordinates":[-100.61762400000001,40.198523],"type":"Point"}
}