{
  "type": "Feature",
  "properties": {
    "addr:full":"6845 S 167th St Omaha NE 68135",
    "addr:housenumber":"6845",
    "addr:postcode":"68135",
    "addr:street":"S 167Th St",
    "iso:country":"US",
    "sg:address":"6845 S 167th St",
    "sg:city":"Omaha",
    "sg:classifiers":[
        {
            "category":"Food & Beverages",
            "subcategory":"Groceries & Convenience Stores",
            "type":"Retail Goods"
        }
    ],
    "sg:phone":"+1 402 895 8067",
    "sg:postcode":"68135",
    "sg:province":"NE",
    "wof:name":"KWIK Shop",
    "wof:placetype":"venue"
},
  "geometry": {"coordinates":[-96.17533299999999,41.190837],"type":"Point"}
}