{
  "type": "Feature",
  "properties": {
    "iso:country":"US",
    "sg:address":"1717 W 2nd St",
    "sg:city":"Grand Island",
    "sg:classifiers":[
        {
            "category":"Autos & Motor Vehicles",
            "subcategory":"Auto Supplies",
            "type":"Retail Goods"
        }
    ],
    "sg:phone":"+1 308 382 6500",
    "sg:postcode":"68803",
    "sg:province":"NE",
    "sg:tags":[
        "automobile",
        "parts"
    ],
    "wof:name":"Autozone",
    "wof:placetype":"venue"
},
  "geometry": {"coordinates":[-98.356996,40.917641],"type":"Point"}
}