{
  "type": "Feature",
  "properties": {
    "addr:full":"3901 S 27th St Lincoln NE 68502",
    "addr:housenumber":"3901",
    "addr:postcode":"68502",
    "addr:street":"S 27Th St",
    "iso:country":"US",
    "sg:address":"3901 S 27th St",
    "sg:city":"Lincoln",
    "sg:classifiers":[
        {
            "category":"Shopping",
            "subcategory":"Crafts & Fabrics",
            "type":"Retail Goods"
        }
    ],
    "sg:phone":"+1 402 423 2408",
    "sg:postcode":"68502",
    "sg:province":"NE",
    "sg:tags":[
        "sewing"
    ],
    "wof:name":"Newton Audrey",
    "wof:placetype":"venue"
},
  "geometry": {"coordinates":[-96.682592,40.774917],"type":"Point"}
}