{
  "type": "Feature",
  "properties": {
    "iso:country":"US",
    "sg:address":"7417 Poplar Rd",
    "sg:city":"Lincoln",
    "sg:classifiers":[
        {
            "category":"Organizations",
            "subcategory":"Membership Organization",
            "type":"Services"
        }
    ],
    "sg:phone":"+1 402 483 5150",
    "sg:postcode":"68506",
    "sg:province":"NE",
    "wof:name":"Richard & Patricia Stitcher",
    "wof:placetype":"venue"
},
  "geometry": {"coordinates":[-96.61810800000001,40.775081],"type":"Point"}
}