{
  "type": "Feature",
  "properties": {
    "iso:country":"US",
    "sg:address":"212 Court St",
    "sg:city":"Beatrice",
    "sg:classifiers":[
        {
            "category":"Bars & Pubs",
            "type":"Food & Drink"
        }
    ],
    "sg:phone":"+1 402 228 9857",
    "sg:postcode":"68310",
    "sg:province":"NE",
    "sg:tags":[
        "drinking"
    ],
    "wof:name":"Brass Rail",
    "wof:placetype":"venue"
},
  "geometry": {"coordinates":[-96.750694,40.265911],"type":"Point"}
}