{
  "type": "Feature",
  "properties": {
    "iso:country":"US",
    "sg:address":"706 Elm St",
    "sg:city":"Laurel",
    "sg:classifiers":[
        {
            "category":"Real Estate",
            "subcategory":"Real Estate Operator",
            "type":"Services"
        }
    ],
    "sg:phone":"+1 402 256 3254",
    "sg:postcode":"68745",
    "sg:province":"NE",
    "sg:tags":[
        "property",
        "lessor"
    ],
    "wof:name":"Marvin Wickett",
    "wof:placetype":"venue"
},
  "geometry": {"coordinates":[-97.091267,42.42328],"type":"Point"}
}