{
  "type": "Feature",
  "properties": {
    "addr:full":"303 W 26th St Scottsbluff NE 69361",
    "addr:housenumber":"303",
    "addr:postcode":"69361",
    "addr:street":"W 26Th St",
    "iso:country":"US",
    "sg:address":"303 W 26th St",
    "sg:city":"Scottsbluff",
    "sg:classifiers":[
        {
            "category":"Bakery",
            "type":"Food & Drink"
        }
    ],
    "sg:menulink":"http://www.allmenus.com/ne/scottsbluff/102307-perkins-restaurant--bakery/menu/",
    "sg:phone":"+1 308 635 2035",
    "sg:postcode":"69361",
    "sg:province":"NE",
    "sg:tags":[
        "sandwich",
        "salad",
        "soup",
        "american",
        "pastry",
        "wrap"
    ],
    "wof:name":"Perkins Restaurant & Bakery",
    "wof:placetype":"venue"
},
  "geometry": {"coordinates":[-103.66729599999999,41.872604],"type":"Point"}
}