{
  "type": "Feature",
  "properties": {
    "iso:country":"US",
    "sg:address":"410 W 11th St",
    "sg:city":"North Platte",
    "sg:classifiers":[
        {
            "category":"Retail",
            "subcategory":"Auto Repair",
            "type":"Services"
        }
    ],
    "sg:phone":"+1 308 532 5800",
    "sg:postcode":"69101",
    "sg:province":"NE",
    "sg:tags":[
        "automotive",
        "glass",
        "replacement"
    ],
    "wof:name":"Glass Shard Systems Inc",
    "wof:placetype":"venue"
},
  "geometry": {"coordinates":[-100.766077,41.145865],"type":"Point"}
}