{
  "type": "Feature",
  "properties": {
    "iso:country":"US",
    "sg:address":"667 S 42nd St",
    "sg:city":"Omaha",
    "sg:classifiers":[
        {
            "category":"Shopping",
            "subcategory":"Used Merchandise",
            "type":"Retail Goods"
        }
    ],
    "sg:phone":"+1 402 559 6486",
    "sg:postcode":"68105",
    "sg:province":"NE",
    "sg:tags":[
        "shop",
        "thrift"
    ],
    "wof:name":"NHS University Hosp Thrift",
    "wof:placetype":"venue"
},
  "geometry": {"coordinates":[-95.975705,41.252602],"type":"Point"}
}