{
  "type": "Feature",
  "properties": {
    "iso:country":"US",
    "sg:address":"5855 S 77th St",
    "sg:city":"Omaha",
    "sg:classifiers":[
        {
            "category":"Building & Trades",
            "subcategory":"Electrical",
            "type":"Services"
        }
    ],
    "sg:phone":"+1 402 331 3217",
    "sg:postcode":"68127",
    "sg:province":"NE",
    "sg:tags":[
        "electric",
        "contractor"
    ],
    "wof:name":"Sadler Electric Inc",
    "wof:placetype":"venue"
},
  "geometry": {"coordinates":[-96.031817,41.199663],"type":"Point"}
}