{
  "type": "Feature",
  "properties": {
    "iso:country":"US",
    "sg:address":"2500 California Plz",
    "sg:city":"Omaha",
    "sg:classifiers":[
        {
            "category":"Banks & Credit Unions",
            "subcategory":"Bank",
            "type":"Services"
        }
    ],
    "sg:phone":"+1 402 280 1709",
    "sg:postcode":"68178",
    "sg:province":"NE",
    "wof:name":"Creighton Federal Credit Union",
    "wof:placetype":"venue"
},
  "geometry": {"coordinates":[-95.945602,41.266899],"type":"Point"}
}