{
  "type": "Feature",
  "properties": {
    "addr:full":"210 E Nebraska St Ewing NE 68735",
    "addr:housenumber":"210",
    "addr:postcode":"68735",
    "addr:street":"E Nebraska St",
    "iso:country":"US",
    "sg:address":"210 E Nebraska St",
    "sg:city":"Ewing",
    "sg:classifiers":[
        {
            "category":"Food & Beverages",
            "subcategory":"Groceries & Convenience Stores",
            "type":"Retail Goods"
        }
    ],
    "sg:phone":"+1 402 626 7276",
    "sg:postcode":"68735",
    "sg:province":"NE",
    "sg:tags":[
        "grocer"
    ],
    "wof:name":"Larry's Market",
    "wof:placetype":"venue"
},
  "geometry": {"coordinates":[-98.342234,42.257871],"type":"Point"}
}