{
  "type": "Feature",
  "properties": {
    "addr:full":"2502 S 133rd Plz Omaha NE 68144",
    "addr:housenumber":"2502",
    "addr:postcode":"68144",
    "addr:street":"S 133Rd",
    "iso:country":"US",
    "sg:address":"2502 S 133rd Plz",
    "sg:city":"Omaha",
    "sg:classifiers":[
        {
            "category":"Professional",
            "subcategory":"Management & Consulting",
            "type":"Services"
        }
    ],
    "sg:phone":"+1 402 330 3980",
    "sg:postcode":"68144",
    "sg:province":"NE",
    "sg:tags":[
        "fuel"
    ],
    "wof:name":"First Management Inc",
    "wof:placetype":"venue"
},
  "geometry": {"coordinates":[-96.121599,41.235099],"type":"Point"}
}