{
  "type": "Feature",
  "properties": {
    "addr:full":"9800 S 56th St Lincoln NE 68516",
    "addr:housenumber":"9800",
    "addr:postcode":"68516",
    "addr:street":"S 56Th St",
    "iso:country":"US",
    "sg:address":"9800 S 56th St",
    "sg:city":"Lincoln",
    "sg:classifiers":[
        {
            "category":"Building & Trades",
            "subcategory":"Construction",
            "type":"Services"
        }
    ],
    "sg:phone":"+1 402 423 4438",
    "sg:postcode":"68516",
    "sg:province":"NE",
    "sg:tags":[
        "residential",
        "remodeling",
        "contractor"
    ],
    "wof:name":"Kearns Construction",
    "wof:placetype":"venue"
},
  "geometry": {"coordinates":[-96.64435899999999,40.713996],"type":"Point"}
}