{
  "type": "Feature",
  "properties": {
    "iso:country":"US",
    "sg:address":"1351 Rd West 40",
    "sg:city":"Brule",
    "sg:classifiers":[
        {
            "category":"Building & Trades",
            "subcategory":"Construction",
            "type":"Services"
        }
    ],
    "sg:phone":"+1 308 889 3417",
    "sg:postcode":"69127",
    "sg:province":"NE",
    "sg:tags":[
        "heavy"
    ],
    "wof:name":"Western Irrigation Inc",
    "wof:placetype":"venue"
},
  "geometry": {"coordinates":[-101.96907,41.047418],"type":"Point"}
}