{
  "type": "Feature",
  "properties": {
    "iso:country":"US",
    "sg:address":"1320 Lincoln Mall",
    "sg:city":"Lincoln",
    "sg:classifiers":[
        {
            "category":"Organizations",
            "subcategory":"Professional Association",
            "type":"Services"
        }
    ],
    "sg:phone":"+1 402 474 5233",
    "sg:postcode":"68508",
    "sg:province":"NE",
    "wof:name":"United Retail Liquor Assoc",
    "wof:placetype":"venue"
},
  "geometry": {"coordinates":[-96.702573,40.808083],"type":"Point"}
}