{
  "type": "Feature",
  "properties": {
    "addr:full":"13829 Millard Ave Omaha NE 68137",
    "addr:housenumber":"13829",
    "addr:postcode":"68137",
    "addr:street":"Millard Ave",
    "iso:country":"US",
    "sg:address":"13829 Millard Ave",
    "sg:city":"Omaha",
    "sg:classifiers":[
        {
            "category":"Insurance",
            "subcategory":"Hazard Insurance",
            "type":"Services"
        }
    ],
    "sg:phone":"+1 402 895 4424",
    "sg:postcode":"68137",
    "sg:province":"NE",
    "sg:website":"http://statefarm.mqgroup.com/url.asp?usr=277115",
    "wof:name":"State Farm Insurance Agent-Beau Iske",
    "wof:placetype":"venue"
},
  "geometry": {"coordinates":[-96.128801,41.206761],"type":"Point"}
}