{
  "type": "Feature",
  "properties": {
    "iso:country":"US",
    "sg:address":"401 Main St",
    "sg:city":"Ithaca",
    "sg:classifiers":[
        {
            "category":"Freight",
            "type":"Transportation"
        }
    ],
    "sg:phone":"+1 402 623 4260",
    "sg:postcode":"68033",
    "sg:province":"NE",
    "sg:tags":[
        "livestock",
        "hauling"
    ],
    "wof:name":"Hass Trucking",
    "wof:placetype":"venue"
},
  "geometry": {"coordinates":[-96.54055700000001,41.157221],"type":"Point"}
}