{
  "type": "Feature",
  "properties": {
    "iso:country":"US",
    "sg:address":"2108 Emmet St",
    "sg:city":"Omaha",
    "sg:classifiers":[
        {
            "category":"Organizations",
            "subcategory":"Religious Organization",
            "type":"Services"
        }
    ],
    "sg:phone":"+1 402 453 5255",
    "sg:postcode":"68110",
    "sg:province":"NE",
    "sg:tags":[
        "church"
    ],
    "wof:name":"Faith Temple Church Of God",
    "wof:placetype":"venue"
},
  "geometry": {"coordinates":[-95.94530399999999,41.289732],"type":"Point"}
}