{
  "type": "Feature",
  "properties": {
    "iso:country":"US",
    "sg:address":"811 Howell St",
    "sg:city":"Oxford",
    "sg:classifiers":[
        {
            "category":"Shopping",
            "subcategory":"Pharmacy",
            "type":"Retail Goods"
        }
    ],
    "sg:phone":"+1 308 824 3430",
    "sg:postcode":"68967",
    "sg:province":"NE",
    "wof:name":"Oxford Pharmacy",
    "wof:placetype":"venue"
},
  "geometry": {"coordinates":[-99.638137,40.255974],"type":"Point"}
}