{
  "type": "Feature",
  "properties": {
    "addr:full":"327 N Spruce St Valley NE 68064",
    "addr:housenumber":"327",
    "addr:postcode":"68064",
    "addr:street":"N Spruce St",
    "iso:country":"US",
    "sg:address":"327 N Spruce St",
    "sg:city":"Valley",
    "sg:classifiers":[
        {
            "category":"Bars & Pubs",
            "type":"Food & Drink"
        }
    ],
    "sg:phone":"+1 402 359 5734",
    "sg:postcode":"68064",
    "sg:province":"NE",
    "sg:tags":[
        "drinking"
    ],
    "wof:name":"Willie's Bar",
    "wof:placetype":"venue"
},
  "geometry": {"coordinates":[-96.344791,41.313962],"type":"Point"}
}