{
  "type": "Feature",
  "properties": {
    "iso:country":"US",
    "sg:address":"2115 Illinois St",
    "sg:city":"Sidney",
    "sg:classifiers":[
        {
            "category":"Travel",
            "subcategory":"Hotels & Motels",
            "type":"Entertainment"
        }
    ],
    "sg:phone":"+1 308 254 5262",
    "sg:postcode":"69162",
    "sg:province":"NE",
    "wof:name":"Best Value Inn & Suites",
    "wof:placetype":"venue"
},
  "geometry": {"coordinates":[-102.99057999999999,41.144291],"type":"Point"}
}