{
  "type": "Feature",
  "properties": {
    "addr:full":"740 N 129th St Omaha NE 68154",
    "addr:housenumber":"740",
    "addr:postcode":"68154",
    "addr:street":"N 129Th St",
    "iso:country":"US",
    "sg:address":"740 N 129th St",
    "sg:city":"Omaha",
    "sg:classifiers":[
        {
            "category":"Social Services",
            "type":"Services"
        }
    ],
    "sg:phone":"+1 402 431 4080",
    "sg:postcode":"68154",
    "sg:province":"NE",
    "wof:name":"United Behavioral Health",
    "wof:placetype":"venue"
},
  "geometry": {"coordinates":[-96.11664,41.267445],"type":"Point"}
}