{
  "type": "Feature",
  "properties": {
    "iso:country":"US",
    "sg:address":"2955 US Hwy 136",
    "sg:city":"Beatrice",
    "sg:classifiers":[
        {
            "category":"Retail",
            "subcategory":"Auto Repair",
            "type":"Services"
        }
    ],
    "sg:phone":"+1 402 228 6952",
    "sg:postcode":"68310",
    "sg:province":"NE",
    "sg:tags":[
        "repairing",
        "automobile"
    ],
    "wof:name":"Benash Service",
    "wof:placetype":"venue"
},
  "geometry": {"coordinates":[-96.722894,40.265717],"type":"Point"}
}