{
  "type": "Feature",
  "properties": {
    "iso:country":"US",
    "sg:address":"3105 N 90th St",
    "sg:city":"Omaha",
    "sg:classifiers":[
        {
            "category":"Freight",
            "type":"Transportation"
        }
    ],
    "sg:phone":"+1 402 571 5714",
    "sg:postcode":"68134",
    "sg:province":"NE",
    "sg:tags":[
        "commercial",
        "storage"
    ],
    "wof:name":"90th & Maple Self Storage",
    "wof:placetype":"venue"
},
  "geometry": {"coordinates":[-96.052533,41.287084],"type":"Point"}
}