{
  "type": "Feature",
  "properties": {
    "addr:full":"8801 A St Lincoln NE 68520",
    "addr:housenumber":"8801",
    "addr:postcode":"68520",
    "addr:street":"A St",
    "iso:country":"US",
    "sg:address":"8801 A St",
    "sg:city":"Lincoln",
    "sg:classifiers":[
        {
            "category":"Health Services",
            "subcategory":"Health Practitioner",
            "type":"Services"
        }
    ],
    "sg:phone":"+1 402 488 7336",
    "sg:postcode":"68520",
    "sg:province":"NE",
    "wof:name":"Donna Lee Collura",
    "wof:placetype":"venue"
},
  "geometry": {"coordinates":[-96.600362,40.798758],"type":"Point"}
}