{
  "type": "Feature",
  "properties": {
    "addr:full":"1811 Sunset Dr North Platte NE 69101",
    "addr:housenumber":"1811",
    "addr:postcode":"69101",
    "addr:street":"Sunset Dr",
    "iso:country":"US",
    "sg:address":"1811 Sunset Dr",
    "sg:city":"North Platte",
    "sg:classifiers":[
        {
            "category":"Real Estate",
            "subcategory":"Real Estate Operator",
            "type":"Services"
        }
    ],
    "sg:phone":"+1 308 534 6039",
    "sg:postcode":"69101",
    "sg:province":"NE",
    "sg:tags":[
        "building",
        "apartment"
    ],
    "wof:name":"Peggy Remus Rentals",
    "wof:placetype":"venue"
},
  "geometry": {"coordinates":[-100.785585,41.124598],"type":"Point"}
}