{
  "type": "Feature",
  "properties": {
    "iso:country":"US",
    "sg:address":"117 E 5th St",
    "sg:city":"Grand Island",
    "sg:classifiers":[
        {
            "category":"Autos & Motor Vehicles",
            "subcategory":"Automobile Sales",
            "type":"Retail Goods"
        }
    ],
    "sg:phone":"+1 308 382 5202",
    "sg:postcode":"68801",
    "sg:province":"NE",
    "sg:tags":[
        "car",
        "dealer"
    ],
    "wof:name":"Northside Motors",
    "wof:placetype":"venue"
},
  "geometry": {"coordinates":[-98.342094,40.929424],"type":"Point"}
}