{
  "type": "Feature",
  "properties": {
    "iso:country":"US",
    "sg:address":"927 23rd Ave",
    "sg:city":"Sidney",
    "sg:classifiers":[
        {
            "category":"Social Services",
            "subcategory":"Job Training",
            "type":"Services"
        }
    ],
    "sg:phone":"+1 308 254 6936",
    "sg:postcode":"69162",
    "sg:province":"NE",
    "sg:tags":[
        "rehab",
        "government"
    ],
    "wof:name":"Goodwill Employment Solutions",
    "wof:placetype":"venue"
},
  "geometry": {"coordinates":[-102.992802,41.144062],"type":"Point"}
}