{
  "type": "Feature",
  "properties": {
    "iso:country":"US",
    "sg:address":"830 Nemaha St",
    "sg:city":"Humboldt",
    "sg:classifiers":[
        {
            "category":"Manufacturing",
            "subcategory":"Pet Food",
            "type":"Manufacturing & Wholesale Goods"
        }
    ],
    "sg:phone":"+1 402 862 2243",
    "sg:postcode":"68376",
    "sg:province":"NE",
    "sg:tags":[
        "flour",
        "mills"
    ],
    "wof:name":"Humboldt Grain & Flour Co",
    "wof:placetype":"venue"
},
  "geometry": {"coordinates":[-95.944711,40.168162],"type":"Point"}
}