{
  "type": "Feature",
  "properties": {
    "iso:country":"US",
    "sg:address":"1440 M St",
    "sg:city":"Lincoln",
    "sg:classifiers":[
        {
            "category":"Professional",
            "subcategory":"Research",
            "type":"Services"
        }
    ],
    "sg:phone":"+1 402 436 5516",
    "sg:postcode":"68508",
    "sg:province":"NE",
    "sg:tags":[
        "foundation",
        "philanthropic"
    ],
    "wof:name":"Community Health Endowment",
    "wof:placetype":"venue"
},
  "geometry": {"coordinates":[-96.700146,40.811465],"type":"Point"}
}