{
  "type": "Feature",
  "properties": {
    "addr:full":"1320 Q St Bridgeport NE 69336",
    "addr:housenumber":"1320",
    "addr:postcode":"69336",
    "addr:street":"Q St",
    "iso:country":"US",
    "sg:address":"1320 Q St",
    "sg:city":"Bridgeport",
    "sg:classifiers":[
        {
            "category":"Organizations",
            "subcategory":"Religious Organization",
            "type":"Services"
        }
    ],
    "sg:phone":"+1 308 262 1780",
    "sg:postcode":"69336",
    "sg:province":"NE",
    "sg:tags":[
        "church"
    ],
    "wof:name":"Faith Baptist Church Indpndnt",
    "wof:placetype":"venue"
},
  "geometry": {"coordinates":[-103.093998,41.662048],"type":"Point"}
}