{
  "type": "Feature",
  "properties": {
    "addr:full":"310 Railroad St Benkelman NE 69021",
    "addr:housenumber":"310",
    "addr:postcode":"69021",
    "addr:street":"Railroad St",
    "iso:country":"US",
    "sg:address":"310 Railroad St",
    "sg:city":"Benkelman",
    "sg:classifiers":[
        {
            "category":"Personal",
            "subcategory":"Beauty Salon",
            "type":"Services"
        }
    ],
    "sg:phone":"+1 308 423 2315",
    "sg:postcode":"69021",
    "sg:province":"NE",
    "wof:name":"Val's Beauty Corner",
    "wof:placetype":"venue"
},
  "geometry": {"coordinates":[-101.53422500000001,40.046355],"type":"Point"}
}