{
  "type": "Feature",
  "properties": {
    "iso:country":"US",
    "sg:address":"614 N 108th Ct",
    "sg:city":"Omaha",
    "sg:classifiers":[
        {
            "category":"Social Services",
            "type":"Services"
        }
    ],
    "sg:phone":"+1 402 963 9699",
    "sg:postcode":"68154",
    "sg:province":"NE",
    "sg:tags":[
        "counselor",
        "marriage",
        "family"
    ],
    "wof:name":"Employee Assistance Program",
    "wof:placetype":"venue"
},
  "geometry": {"coordinates":[-96.08451700000001,41.266669],"type":"Point"}
}