{
  "type": "Feature",
  "properties": {
    "iso:country":"US",
    "sg:address":"3431 N Rd",
    "sg:city":"Syracuse",
    "sg:phone":"+1 402 269 3134",
    "sg:postcode":"68446",
    "sg:province":"NE",
    "sg:tags":[
        "farm",
        "field",
        "corn",
        "soybean",
        "crop"
    ],
    "wof:name":"Donald Rosenthal",
    "wof:placetype":"venue"
},
  "geometry": {"coordinates":[-96.140097,40.595801],"type":"Point"}
}