{
  "type": "Feature",
  "properties": {
    "iso:country":"US",
    "sg:address":"4830 S 137th St",
    "sg:city":"Omaha",
    "sg:classifiers":[
        {
            "category":"Building & Trades",
            "subcategory":"Construction",
            "type":"Services"
        }
    ],
    "sg:phone":"+1 402 894 2232",
    "sg:postcode":"68137",
    "sg:province":"NE",
    "sg:tags":[
        "roofing",
        "contractor"
    ],
    "wof:name":"TNT Construction",
    "wof:placetype":"venue"
},
  "geometry": {"coordinates":[-96.12653299999999,41.208199],"type":"Point"}
}