{
  "type": "Feature",
  "properties": {
    "addr:full":"16950 Wright Plz Omaha NE 68130",
    "addr:housenumber":"16950",
    "addr:postcode":"68130",
    "addr:street":"Wright",
    "iso:country":"US",
    "sg:address":"16950 Wright Plz",
    "sg:city":"Omaha",
    "sg:classifiers":[
        {
            "category":"Home & Garden",
            "subcategory":"Building Materials",
            "type":"Retail Goods"
        }
    ],
    "sg:phone":"+1 402 330 6900",
    "sg:postcode":"68130",
    "sg:province":"NE",
    "sg:tags":[
        "center"
    ],
    "wof:name":"PHG Premium Home & Garden",
    "wof:placetype":"venue"
},
  "geometry": {"coordinates":[-96.18189599999999,41.233024],"type":"Point"}
}