{
  "type": "Feature",
  "properties": {
    "iso:country":"US",
    "sg:address":"6613 Sunshine Dr",
    "sg:city":"Omaha",
    "sg:classifiers":[
        {
            "category":"Organizations",
            "subcategory":"Community Association",
            "type":"Services"
        }
    ],
    "sg:phone":"+1 402 738 9493",
    "sg:postcode":"68107",
    "sg:province":"NE",
    "wof:name":"Omaha South High Alumni Assn",
    "wof:placetype":"venue"
},
  "geometry": {"coordinates":[-95.97812399999999,41.192717],"type":"Point"}
}