{
  "type": "Feature",
  "properties": {
    "iso:country":"US",
    "sg:address":"105 4th St",
    "sg:city":"Hartington",
    "sg:classifiers":[
        {
            "category":"Real Estate",
            "subcategory":"Real Estate Operator",
            "type":"Services"
        }
    ],
    "sg:phone":"+1 402 254 3421",
    "sg:postcode":"68739",
    "sg:province":"NE",
    "sg:tags":[
        "property",
        "lessor"
    ],
    "wof:name":"Victor Nissen",
    "wof:placetype":"venue"
},
  "geometry": {"coordinates":[-96.866562,42.26806],"type":"Point"}
}