{
  "type": "Feature",
  "properties": {
    "iso:country":"US",
    "sg:address":"809 S 13th Pl",
    "sg:city":"Norfolk",
    "sg:classifiers":[
        {
            "category":"Retail",
            "subcategory":"Laundry & Dry Cleaning",
            "type":"Services"
        }
    ],
    "sg:phone":"+1 402 379 2011",
    "sg:postcode":"68701",
    "sg:province":"NE",
    "sg:tags":[
        "linen",
        "supply"
    ],
    "wof:name":"Commercial Laundry Svc",
    "wof:placetype":"venue"
},
  "geometry": {"coordinates":[-97.42806899999999,42.024851],"type":"Point"}
}