{
  "type": "Feature",
  "properties": {
    "iso:country":"US",
    "sg:address":"3508 Cornhusker Dr",
    "sg:city":"Omaha",
    "sg:classifiers":[
        {
            "category":"Social Services",
            "subcategory":"Child Care",
            "type":"Services"
        }
    ],
    "sg:phone":"+1 402 390 0844",
    "sg:postcode":"68124",
    "sg:province":"NE",
    "sg:tags":[
        "day"
    ],
    "wof:name":"Kristina Middleton Day Care",
    "wof:placetype":"venue"
},
  "geometry": {"coordinates":[-96.051818,41.226095],"type":"Point"}
}