{
  "type": "Feature",
  "properties": {
    "iso:country":"US",
    "sg:address":"3503 W 16th St",
    "sg:city":"North Platte",
    "sg:classifiers":[
        {
            "category":"Building & Trades",
            "subcategory":"Construction",
            "type":"Services"
        }
    ],
    "sg:phone":"+1 308 532 8572",
    "sg:postcode":"69101",
    "sg:province":"NE",
    "sg:tags":[
        "masonry",
        "contractor"
    ],
    "wof:name":"Henry Schwartz Masonary",
    "wof:placetype":"venue"
},
  "geometry": {"coordinates":[-100.79978699999999,41.154022],"type":"Point"}
}