{
  "type": "Feature",
  "properties": {
    "iso:country":"US",
    "sg:address":"1115 7th St",
    "sg:city":"Gibbon",
    "sg:classifiers":[
        {
            "category":"Real Estate",
            "subcategory":"Real Estate Operator",
            "type":"Services"
        }
    ],
    "sg:phone":"+1 308 468 5550",
    "sg:postcode":"68840",
    "sg:province":"NE",
    "sg:tags":[
        "mobile",
        "home",
        "site",
        "community"
    ],
    "wof:name":"L & J Mobile Home Court",
    "wof:placetype":"venue"
},
  "geometry": {"coordinates":[-98.84889699999999,40.742551],"type":"Point"}
}