{
  "type": "Feature",
  "properties": {
    "addr:full":"208 N 3rd St St Edward NE 68660",
    "addr:housenumber":"208",
    "addr:postcode":"68660",
    "addr:street":"N 3Rd St",
    "iso:country":"US",
    "sg:address":"208 N 3rd St",
    "sg:city":"St Edward",
    "sg:classifiers":[
        {
            "category":"Wholesale",
            "subcategory":"Machinery & Supplies",
            "type":"Manufacturing & Wholesale Goods"
        }
    ],
    "sg:phone":"+1 402 678 2277",
    "sg:postcode":"68660",
    "sg:province":"NE",
    "sg:tags":[
        "repairing"
    ],
    "wof:name":"G T Sales & Svc",
    "wof:placetype":"venue"
},
  "geometry": {"coordinates":[-97.865725,41.571797],"type":"Point"}
}