{
  "type": "Feature",
  "properties": {
    "addr:full":"2343 S 156th Cir Omaha NE 68130",
    "addr:housenumber":"2343",
    "addr:postcode":"68130",
    "addr:street":"S 156Th Cir",
    "iso:country":"US",
    "sg:address":"2343 S 156th Cir",
    "sg:city":"Omaha",
    "sg:classifiers":[
        {
            "category":"Retail",
            "subcategory":"Auto Repair",
            "type":"Services"
        }
    ],
    "sg:phone":"+1 402 333 4670",
    "sg:postcode":"68130",
    "sg:province":"NE",
    "sg:tags":[
        "repairing",
        "automobile"
    ],
    "wof:name":"Haver's Service Ctr",
    "wof:placetype":"venue"
},
  "geometry": {"coordinates":[-96.15837999999999,41.236692],"type":"Point"}
}