{
  "type": "Feature",
  "properties": {
    "iso:country":"US",
    "sg:address":"1400 Saltillo Rd",
    "sg:city":"Roca",
    "sg:classifiers":[
        {
            "category":"Banks & Credit Unions",
            "subcategory":"Bank",
            "type":"Services"
        }
    ],
    "sg:phone":"+1 402 423 2187",
    "sg:postcode":"68430",
    "sg:province":"NE",
    "wof:name":"Security First Bank",
    "wof:placetype":"venue"
},
  "geometry": {"coordinates":[-96.6999,40.697396],"type":"Point"}
}