{
  "type": "Feature",
  "properties": {
    "iso:country":"US",
    "sg:address":"247 State Hwy 12",
    "sg:city":"Niobrara",
    "sg:classifiers":[
        {
            "category":"Education",
            "subcategory":"School",
            "type":"Public Place"
        }
    ],
    "sg:phone":"+1 402 857 3322",
    "sg:postcode":"68760",
    "sg:province":"NE",
    "wof:name":"Niobrara Public Schools",
    "wof:placetype":"venue"
},
  "geometry": {"coordinates":[-98.191829,42.810844],"type":"Point"}
}