{
  "type": "Feature",
  "properties": {
    "addr:full":"11507 S 42nd St Bellevue NE 68123",
    "addr:housenumber":"11507",
    "addr:postcode":"68123",
    "addr:street":"S 42Nd St",
    "iso:country":"US",
    "sg:address":"11507 S 42nd St",
    "sg:city":"Bellevue",
    "sg:classifiers":[
        {
            "category":"Banks & Credit Unions",
            "subcategory":"Bank",
            "type":"Services"
        }
    ],
    "sg:phone":"+1 402 291 9595",
    "sg:postcode":"68123",
    "sg:province":"NE",
    "sg:tags":[
        "national",
        "commercial"
    ],
    "wof:name":"N A Teambank",
    "wof:placetype":"venue"
},
  "geometry": {"coordinates":[-95.97620999999999,41.140335],"type":"Point"}
}