{
  "type": "Feature",
  "properties": {
    "iso:country":"US",
    "sg:address":"1109 N Pine St",
    "sg:city":"Wahoo",
    "sg:classifiers":[
        {
            "category":"Government",
            "subcategory":"Office",
            "type":"Public Place"
        }
    ],
    "sg:phone":"+1 402 443 5360",
    "sg:postcode":"68066",
    "sg:province":"NE",
    "wof:name":"Region V Svc",
    "wof:placetype":"venue"
},
  "geometry": {"coordinates":[-96.613534,41.216049],"type":"Point"}
}