{
  "type": "Feature",
  "properties": {
    "addr:full":"15318 Parker Cir Omaha NE 68154",
    "addr:housenumber":"15318",
    "addr:postcode":"68154",
    "addr:street":"Parker Cir",
    "iso:country":"US",
    "sg:address":"15318 Parker Cir",
    "sg:city":"Omaha",
    "sg:classifiers":[
        {
            "category":"Shopping",
            "subcategory":"Gifts & Souvenirs",
            "type":"Retail Goods"
        }
    ],
    "sg:phone":"+1 402 496 3613",
    "sg:postcode":"68154",
    "sg:province":"NE",
    "wof:name":"Eggs Cursions",
    "wof:placetype":"venue"
},
  "geometry": {"coordinates":[-96.15406,41.27706],"type":"Point"}
}