{
  "type": "Feature",
  "properties": {
    "addr:full":"1439 State Hwy 133 Omaha NE 68142",
    "addr:housenumber":"1439",
    "addr:postcode":"68142",
    "addr:street":"State Hwy 133",
    "iso:country":"US",
    "sg:address":"1439 State Hwy 133",
    "sg:city":"Omaha",
    "sg:classifiers":[
        {
            "category":"Education",
            "subcategory":"School",
            "type":"Public Place"
        }
    ],
    "sg:phone":"+1 402 426 2882",
    "sg:postcode":"68142",
    "sg:province":"NE",
    "wof:name":"Prairie Gem Stables",
    "wof:placetype":"venue"
},
  "geometry": {"coordinates":[-96.098343,41.409985],"type":"Point"}
}