{
  "type": "Feature",
  "properties": {
    "addr:full":"72205 578th Ave Plymouth NE 68424",
    "addr:housenumber":"72205",
    "addr:postcode":"68424",
    "addr:street":"578Th Ave",
    "iso:country":"US",
    "sg:address":"72205 578th Ave",
    "sg:city":"Plymouth",
    "sg:classifiers":[
        {
            "category":"Real Estate",
            "subcategory":"Real Estate Operator",
            "type":"Services"
        }
    ],
    "sg:phone":"+1 402 656 3836",
    "sg:postcode":"68424",
    "sg:province":"NE",
    "sg:tags":[
        "property",
        "lessor"
    ],
    "wof:name":"Maynard Meyer",
    "wof:placetype":"venue"
},
  "geometry": {"coordinates":[-96.99178999999999,40.295726],"type":"Point"}
}