{
  "type": "Feature",
  "properties": {
    "iso:country":"US",
    "sg:address":"1331 W 7th St",
    "sg:city":"Hastings",
    "sg:classifiers":[
        {
            "category":"Recreation",
            "type":"Entertainment"
        }
    ],
    "sg:phone":"+1 402 463 7566",
    "sg:postcode":"68901",
    "sg:province":"NE",
    "sg:tags":[
        "club",
        "membership"
    ],
    "wof:name":"Online Success Club Inc",
    "wof:placetype":"venue"
},
  "geometry": {"coordinates":[-98.39898599999999,40.589687],"type":"Point"}
}