{
  "type": "Feature",
  "properties": {
    "addr:full":"9624 M St Omaha NE 68127",
    "addr:housenumber":"9624",
    "addr:postcode":"68127",
    "addr:street":"M St",
    "iso:country":"US",
    "sg:address":"9624 M St",
    "sg:city":"Omaha",
    "sg:classifiers":[
        {
            "category":"Manufacturing",
            "subcategory":"Printing",
            "type":"Manufacturing & Wholesale Goods"
        }
    ],
    "sg:phone":"+1 402 331 3408",
    "sg:postcode":"68127",
    "sg:province":"NE",
    "sg:tags":[
        "commercial",
        "offset"
    ],
    "wof:name":"PIP Printing",
    "wof:placetype":"venue"
},
  "geometry": {"coordinates":[-96.06437699999999,41.212119],"type":"Point"}
}