{
  "type": "Feature",
  "properties": {
    "iso:country":"US",
    "sg:address":"7742 Greenleaf Dr",
    "sg:city":"La Vista",
    "sg:classifiers":[
        {
            "category":"Recreation",
            "type":"Entertainment"
        }
    ],
    "sg:phone":"+1 402 339 0667",
    "sg:postcode":"68128",
    "sg:province":"NE",
    "sg:tags":[
        "martial",
        "arts",
        "instruction"
    ],
    "wof:name":"Caldwell's Shin Ryu Kan Karate",
    "wof:placetype":"venue"
},
  "geometry": {"coordinates":[-96.03582400000001,41.17843],"type":"Point"}
}