{
  "type": "Feature",
  "properties": {
    "iso:country":"US",
    "sg:address":"90189 Enterprise Dr",
    "sg:city":"Scottsbluff",
    "sg:classifiers":[
        {
            "category":"Building & Trades",
            "subcategory":"Construction",
            "type":"Services"
        }
    ],
    "sg:phone":"+1 308 635 6900",
    "sg:postcode":"69361",
    "sg:province":"NE",
    "sg:tags":[
        "masonry",
        "contractor"
    ],
    "wof:name":"Larry Ash Masonry Construction",
    "wof:placetype":"venue"
},
  "geometry": {"coordinates":[-103.60862899999999,41.883127],"type":"Point"}
}