{
  "type": "Feature",
  "properties": {
    "addr:full":"4500 S 70th St Lincoln NE 68516",
    "addr:housenumber":"4500",
    "addr:postcode":"68516",
    "addr:street":"S 70Th St",
    "iso:country":"US",
    "sg:address":"4500 S 70th St",
    "sg:city":"Lincoln",
    "sg:classifiers":[
        {
            "category":"Shopping",
            "type":"Retail Goods"
        }
    ],
    "sg:phone":"+1 402 484 6300",
    "sg:postcode":"68516",
    "sg:province":"NE",
    "sg:tags":[
        "merchandise"
    ],
    "wof:name":"Next Step Orthpd Designs Ftwr",
    "wof:placetype":"venue"
},
  "geometry": {"coordinates":[-96.625061,40.769069],"type":"Point"}
}