{
  "type": "Feature",
  "properties": {
    "iso:country":"US",
    "sg:address":"6224 Fort St",
    "sg:city":"Omaha",
    "sg:classifiers":[
        {
            "category":"Professional",
            "subcategory":"Business Services",
            "type":"Services"
        }
    ],
    "sg:phone":"+1 402 933 1949",
    "sg:postcode":"68104",
    "sg:province":"NE",
    "sg:tags":[
        "lettering",
        "monogramming"
    ],
    "wof:name":"Busy Bee Mnogramming Lettering",
    "wof:placetype":"venue"
},
  "geometry": {"coordinates":[-96.011078,41.306399],"type":"Point"}
}