{
  "type": "Feature",
  "properties": {
    "iso:country":"US",
    "sg:address":"45655 295th Rd",
    "sg:city":"Ravenna",
    "sg:phone":"+1 308 452 3606",
    "sg:postcode":"68869",
    "sg:province":"NE",
    "sg:tags":[
        "farm",
        "corn"
    ],
    "wof:name":"Steve Luth",
    "wof:placetype":"venue"
},
  "geometry": {"coordinates":[-98.873414,40.959825],"type":"Point"}
}