{
  "type": "Feature",
  "properties": {
    "iso:country":"US",
    "sg:address":"206 Co Rd 20",
    "sg:city":"Hooper",
    "sg:classifiers":[
        {
            "category":"Farming",
            "subcategory":"Livestock Farm",
            "type":"Manufacturing & Wholesale Goods"
        },
        {
            "category":"Farming",
            "subcategory":"Farm",
            "type":"Manufacturing & Wholesale Goods"
        }
    ],
    "sg:phone":"+1 402 567 2206",
    "sg:postcode":"68031",
    "sg:province":"NE",
    "wof:name":"Weitzenkamp Farms Inc",
    "wof:placetype":"venue"
},
  "geometry": {"coordinates":[-96.540386,41.72631],"type":"Point"}
}