{
  "type": "Feature",
  "properties": {
    "iso:country":"US",
    "sg:address":"1520 N 29th St",
    "sg:city":"Lincoln",
    "sg:classifiers":[
        {
            "category":"Education",
            "subcategory":"School",
            "type":"Public Place"
        }
    ],
    "sg:phone":"+1 402 436 1132",
    "sg:postcode":"68503",
    "sg:province":"NE",
    "wof:name":"Clinton Elementary School",
    "wof:placetype":"venue"
},
  "geometry": {"coordinates":[-96.679851,40.828736],"type":"Point"}
}