{
  "type": "Feature",
  "properties": {
    "iso:country":"US",
    "sg:address":"4701 Van Dorn St",
    "sg:city":"Lincoln",
    "sg:classifiers":[
        {
            "category":"Real Estate",
            "subcategory":"Real Estate Agent",
            "type":"Services"
        }
    ],
    "sg:phone":"+1 402 483 1214",
    "sg:postcode":"68506",
    "sg:province":"NE",
    "wof:name":"Double J Realty & Mgmt Inc",
    "wof:placetype":"venue"
},
  "geometry": {"coordinates":[-96.653853,40.784405],"type":"Point"}
}