{
  "type": "Feature",
  "properties": {
    "iso:country":"US",
    "sg:address":"20420 Sioux Rd",
    "sg:city":"Shelton",
    "sg:phone":"+1 308 647 5347",
    "sg:postcode":"68876",
    "sg:province":"NE",
    "sg:tags":[
        "farm",
        "corn"
    ],
    "wof:name":"James Prochaska",
    "wof:placetype":"venue"
},
  "geometry": {"coordinates":[-98.779115,40.873016],"type":"Point"}
}