{
  "type": "Feature",
  "properties": {
    "addr:full":"2013 Broadway Scottsbluff NE 69361",
    "addr:housenumber":"2013",
    "addr:postcode":"69361",
    "addr:street":"Broadway",
    "iso:country":"US",
    "sg:address":"2013 Broadway",
    "sg:city":"Scottsbluff",
    "sg:classifiers":[
        {
            "category":"Insurance",
            "subcategory":"Insurance Agent",
            "type":"Services"
        }
    ],
    "sg:phone":"+1 308 635 0521",
    "sg:postcode":"69361",
    "sg:province":"NE",
    "wof:name":"Eckert Insurance",
    "wof:placetype":"venue"
},
  "geometry": {"coordinates":[-103.662616,41.867471],"type":"Point"}
}