{
  "type": "Feature",
  "properties": {
    "iso:country":"US",
    "sg:address":"1920 23rd St",
    "sg:city":"Columbus",
    "sg:classifiers":[
        {
            "category":"Banks & Credit Unions",
            "subcategory":"Bank",
            "type":"Services"
        }
    ],
    "sg:phone":"+1 402 564 2731",
    "sg:postcode":"68601",
    "sg:province":"NE",
    "sg:tags":[
        "state",
        "commercial"
    ],
    "wof:name":"United Nebraska Bank",
    "wof:placetype":"venue"
},
  "geometry": {"coordinates":[-97.35040600000001,41.438584],"type":"Point"}
}