{
  "type": "Feature",
  "properties": {
    "iso:country":"US",
    "sg:address":"308 W 11th St",
    "sg:city":"York",
    "sg:classifiers":[
        {
            "category":"Utilities",
            "subcategory":"Refuse",
            "type":"Services"
        }
    ],
    "sg:phone":"+1 402 362 4435",
    "sg:postcode":"68467",
    "sg:province":"NE",
    "sg:tags":[
        "garbage",
        "collection"
    ],
    "wof:name":"Sprouse Sanitation",
    "wof:placetype":"venue"
},
  "geometry": {"coordinates":[-97.595871,40.871932],"type":"Point"}
}