{
  "type": "Feature",
  "properties": {
    "iso:country":"US",
    "sg:address":"200 Lincoln Ave",
    "sg:city":"Grant",
    "sg:classifiers":[
        {
            "category":"Education",
            "subcategory":"School",
            "type":"Public Place"
        }
    ],
    "sg:phone":"+1 308 352 4990",
    "sg:postcode":"69140",
    "sg:province":"NE",
    "wof:name":"Perkins County Superintendent",
    "wof:placetype":"venue"
},
  "geometry": {"coordinates":[-101.726449,40.840931],"type":"Point"}
}