{
  "type": "Feature",
  "properties": {
    "iso:country":"US",
    "sg:address":"810 E 2nd St",
    "sg:city":"Chadron",
    "sg:classifiers":[
        {
            "category":"Wholesale",
            "subcategory":"Farm Supplies",
            "type":"Manufacturing & Wholesale Goods"
        },
        {
            "category":"Food & Beverages",
            "subcategory":"Meat & Fish",
            "type":"Retail Goods"
        }
    ],
    "sg:phone":"+1 308 432 4063",
    "sg:postcode":"69337",
    "sg:province":"NE",
    "sg:tags":[
        "cattle"
    ],
    "wof:name":"Pioneer Beef Company",
    "wof:placetype":"venue"
},
  "geometry": {"coordinates":[-102.990021,42.829613],"type":"Point"}
}