{
  "type": "Feature",
  "properties": {
    "iso:country":"US",
    "sg:address":"3610 Norfolk Ave",
    "sg:city":"Norfolk",
    "sg:classifiers":[
        {
            "category":"Health Services",
            "subcategory":"Optometrist",
            "type":"Services"
        }
    ],
    "sg:phone":"+1 402 649 0157",
    "sg:postcode":"68701",
    "sg:province":"NE",
    "wof:name":"Authier Mller Eye Care Ctr LLC",
    "wof:placetype":"venue"
},
  "geometry": {"coordinates":[-97.359696,42.032964],"type":"Point"}
}