{
  "type": "Feature",
  "properties": {
    "addr:full":"150 E Military Ave Fremont NE 68025",
    "addr:housenumber":"150",
    "addr:postcode":"68025",
    "addr:street":"E Military Ave",
    "iso:country":"US",
    "sg:address":"150 E Military Ave",
    "sg:city":"Fremont",
    "sg:classifiers":[
        {
            "category":"Retail",
            "subcategory":"Auto Repair",
            "type":"Services"
        }
    ],
    "sg:phone":"+1 402 721 0523",
    "sg:postcode":"68025",
    "sg:province":"NE",
    "sg:tags":[
        "repairing",
        "automobile"
    ],
    "wof:name":"Longacres Inc",
    "wof:placetype":"venue"
},
  "geometry": {"coordinates":[-96.49671600000001,41.43583],"type":"Point"}
}