{
  "type": "Feature",
  "properties": {
    "addr:full":"309 Nebraska St Murdock NE 68407",
    "addr:housenumber":"309",
    "addr:postcode":"68407",
    "addr:street":"Nebraska St",
    "iso:country":"US",
    "sg:address":"309 Nebraska St",
    "sg:city":"Murdock",
    "sg:classifiers":[
        {
            "category":"Retail",
            "subcategory":"Repair Shop",
            "type":"Services"
        }
    ],
    "sg:phone":"+1 402 867 2088",
    "sg:postcode":"68407",
    "sg:province":"NE",
    "sg:tags":[
        "television",
        "radio"
    ],
    "wof:name":"Rob's Electronics",
    "wof:placetype":"venue"
},
  "geometry": {"coordinates":[-96.279721,40.926426],"type":"Point"}
}