{
  "type": "Feature",
  "properties": {
    "iso:country":"US",
    "sg:address":"808 S Oak St",
    "sg:city":"Grand Island",
    "sg:classifiers":[
        {
            "category":"Building & Trades",
            "subcategory":"Plumbing",
            "type":"Services"
        }
    ],
    "sg:phone":"+1 308 384 5451",
    "sg:postcode":"68801",
    "sg:province":"NE",
    "sg:tags":[
        "plumbing",
        "contractor"
    ],
    "wof:name":"Hoes' Plumbing & Heating",
    "wof:placetype":"venue"
},
  "geometry": {"coordinates":[-98.335025,40.915533],"type":"Point"}
}