{
  "type": "Feature",
  "properties": {
    "iso:country":"US",
    "sg:address":"1519 Co Rd A",
    "sg:city":"Ceresco",
    "sg:phone":"+1 402 665 3140",
    "sg:postcode":"68017",
    "sg:province":"NE",
    "sg:tags":[
        "farm",
        "grain",
        "cash",
        "soybean"
    ],
    "wof:name":"W Otto/Ray",
    "wof:placetype":"venue"
},
  "geometry": {"coordinates":[-96.58296199999999,41.059899],"type":"Point"}
}