{
  "type": "Feature",
  "properties": {
    "addr:full":"300 N 44th St Lincoln NE 68503",
    "addr:housenumber":"300",
    "addr:postcode":"68503",
    "addr:street":"N 44Th St",
    "iso:country":"US",
    "sg:address":"300 N 44th St",
    "sg:city":"Lincoln",
    "sg:classifiers":[
        {
            "category":"Health Services",
            "subcategory":"Doctor",
            "type":"Services"
        }
    ],
    "sg:phone":"+1 402 467 5335",
    "sg:postcode":"68503",
    "sg:province":"NE",
    "sg:tags":[
        "medical"
    ],
    "wof:name":"Envision Open M R I",
    "wof:placetype":"venue"
},
  "geometry": {"coordinates":[-96.658581,40.815268],"type":"Point"}
}