{
  "type": "Feature",
  "properties": {
    "iso:country":"US",
    "sg:address":"113 N Brown Ave",
    "sg:city":"Clay Center",
    "sg:classifiers":[
        {
            "category":"Retail",
            "subcategory":"Funeral Services",
            "type":"Services"
        }
    ],
    "sg:phone":"+1 402 762 3474",
    "sg:postcode":"68933",
    "sg:province":"NE",
    "sg:tags":[
        "director"
    ],
    "wof:name":"Mc Laughlin Funeral Home",
    "wof:placetype":"venue"
},
  "geometry": {"coordinates":[-98.05441399999999,40.522179],"type":"Point"}
}