{
  "type": "Feature",
  "properties": {
    "addr:full":"8614 Birch Dr La Vista NE 68128",
    "addr:housenumber":"8614",
    "addr:postcode":"68128",
    "addr:street":"Birch Dr",
    "iso:country":"US",
    "sg:address":"8614 Birch Dr",
    "sg:city":"La Vista",
    "sg:classifiers":[
        {
            "category":"Building & Trades",
            "subcategory":"Construction",
            "type":"Services"
        }
    ],
    "sg:phone":"+1 402 339 4177",
    "sg:postcode":"68128",
    "sg:province":"NE",
    "sg:tags":[
        "contractor"
    ],
    "wof:name":"Pfp Contracting",
    "wof:placetype":"venue"
},
  "geometry": {"coordinates":[-96.046752,41.185406],"type":"Point"}
}