{
  "type": "Feature",
  "properties": {
    "iso:country":"US",
    "sg:address":"570 Jefferson St",
    "sg:city":"Clatonia",
    "sg:phone":"+1 402 989 6345",
    "sg:postcode":"68328",
    "sg:province":"NE",
    "sg:tags":[
        "farm",
        "corn"
    ],
    "wof:name":"Henry A Baehr & Son",
    "wof:placetype":"venue"
},
  "geometry": {"coordinates":[-96.85449,40.467472],"type":"Point"}
}