{
  "type": "Feature",
  "properties": {
    "iso:country":"US",
    "sg:address":"2726 S 130th Rd",
    "sg:city":"Wood River",
    "sg:classifiers":[
        {
            "category":"Education",
            "subcategory":"School",
            "type":"Public Place"
        }
    ],
    "sg:phone":"+1 308 583 2325",
    "sg:postcode":"68883",
    "sg:province":"NE",
    "wof:name":"Plainview School",
    "wof:placetype":"venue"
},
  "geometry": {"coordinates":[-98.588752,40.894825],"type":"Point"}
}