{
  "type": "Feature",
  "properties": {
    "addr:full":"6803 N 68th Plz Omaha NE 68152",
    "addr:housenumber":"6803",
    "addr:postcode":"68152",
    "addr:street":"N 68Th",
    "iso:country":"US",
    "sg:address":"6803 N 68th Plz",
    "sg:city":"Omaha",
    "sg:classifiers":[
        {
            "category":"Social Services",
            "subcategory":"Adult Care",
            "type":"Services"
        }
    ],
    "sg:phone":"+1 402 572 2333",
    "sg:postcode":"68152",
    "sg:province":"NE",
    "sg:tags":[
        "residential"
    ],
    "wof:name":"Immanuel Village",
    "wof:placetype":"venue"
},
  "geometry": {"coordinates":[-96.016251,41.320542],"type":"Point"}
}