{
  "type": "Feature",
  "properties": {
    "addr:full":"202 Cherry St Louisville NE 68037",
    "addr:housenumber":"202",
    "addr:postcode":"68037",
    "addr:street":"Cherry St",
    "iso:country":"US",
    "sg:address":"202 Cherry St",
    "sg:city":"Louisville",
    "sg:classifiers":[
        {
            "category":"Government",
            "subcategory":"Post Office",
            "type":"Public Place"
        }
    ],
    "sg:phone":"+1 402 234 5595",
    "sg:postcode":"68037",
    "sg:province":"NE",
    "wof:name":"United States Post Office",
    "wof:placetype":"venue"
},
  "geometry": {"coordinates":[-96.1399,41.000801],"type":"Point"}
}