{
  "type": "Feature",
  "properties": {
    "addr:full":"4130 S 48th St Lincoln NE 68506",
    "addr:housenumber":"4130",
    "addr:postcode":"68506",
    "addr:street":"S 48Th St",
    "iso:country":"US",
    "sg:address":"4130 S 48th St",
    "sg:city":"Lincoln",
    "sg:classifiers":[
        {
            "category":"Restaurant",
            "type":"Food & Drink"
        },
        {
            "category":"Ice Cream",
            "type":"Food & Drink"
        }
    ],
    "sg:menulink":"http://www.allmenus.com/ne/lincoln/167738-dairy-queen/menu/",
    "sg:phone":"+1 402 488 1559",
    "sg:postcode":"68506",
    "sg:province":"NE",
    "sg:tags":[
        "burger",
        "american",
        "ice",
        "cream"
    ],
    "wof:name":"Dairy Queen",
    "wof:placetype":"venue"
},
  "geometry": {"coordinates":[-96.653623,40.771185],"type":"Point"}
}