{
  "type": "Feature",
  "properties": {
    "iso:country":"US",
    "sg:address":"6515 S 100th St",
    "sg:city":"Omaha",
    "sg:classifiers":[
        {
            "category":"Real Estate",
            "subcategory":"Real Estate Agent",
            "type":"Services"
        }
    ],
    "sg:phone":"+1 402 333 6100",
    "sg:postcode":"68127",
    "sg:province":"NE",
    "wof:name":"Huber Properties",
    "wof:placetype":"venue"
},
  "geometry": {"coordinates":[-96.0676,41.192636],"type":"Point"}
}