{
  "type": "Feature",
  "properties": {
    "iso:country":"US",
    "sg:address":"912 Medina Ave",
    "sg:city":"Bertrand",
    "sg:classifiers":[
        {
            "category":"Building & Trades",
            "subcategory":"Construction",
            "type":"Services"
        }
    ],
    "sg:phone":"+1 308 472 5291",
    "sg:postcode":"68927",
    "sg:province":"NE",
    "sg:tags":[
        "hanging",
        "contractor"
    ],
    "wof:name":"Renken Painting",
    "wof:placetype":"venue"
},
  "geometry": {"coordinates":[-99.63230299999999,40.529919],"type":"Point"}
}