{
  "type": "Feature",
  "properties": {
    "iso:country":"US",
    "sg:address":"501 W A St",
    "sg:city":"Lincoln",
    "sg:classifiers":[
        {
            "category":"Shopping",
            "subcategory":"Discount & Variety Stores",
            "type":"Retail Goods"
        }
    ],
    "sg:phone":"+1 402 476 2111",
    "sg:postcode":"68522",
    "sg:province":"NE",
    "wof:name":"Joe Dollar",
    "wof:placetype":"venue"
},
  "geometry": {"coordinates":[-96.725572,40.799038],"type":"Point"}
}