{
  "type": "Feature",
  "properties": {
    "addr:full":"80046 Nichols Dr Minatare NE 69356",
    "addr:housenumber":"80046",
    "addr:postcode":"69356",
    "addr:street":"Nichols Dr Minatare Ne",
    "iso:country":"US",
    "sg:address":"80046 Nichols Dr",
    "sg:city":"Minatare",
    "sg:classifiers":[
        {
            "category":"Professional",
            "type":"Services"
        }
    ],
    "sg:phone":"+1 308 783 2400",
    "sg:postcode":"69356",
    "sg:province":"NE",
    "wof:name":"Mike's Pro Door Svc",
    "wof:placetype":"venue"
},
  "geometry": {"coordinates":[-103.497822,41.891754],"type":"Point"}
}