{
  "type": "Feature",
  "properties": {
    "iso:country":"US",
    "sg:address":"1004 Lincoln Rd",
    "sg:city":"Bellevue",
    "sg:classifiers":[
        {
            "category":"Professional",
            "subcategory":"Advertising",
            "type":"Services"
        }
    ],
    "sg:phone":"+1 402 292 9293",
    "sg:postcode":"68005",
    "sg:province":"NE",
    "sg:tags":[
        "mailing",
        "shipping"
    ],
    "wof:name":"UPS Store",
    "wof:placetype":"venue"
},
  "geometry": {"coordinates":[-95.908029,41.150577],"type":"Point"}
}