{
  "type": "Feature",
  "properties": {
    "iso:country":"US",
    "sg:address":"35292 US Hwy 77",
    "sg:city":"Beatrice",
    "sg:phone":"+1 402 228 0531",
    "sg:postcode":"68310",
    "sg:province":"NE",
    "sg:tags":[
        "beef",
        "farm",
        "corn",
        "cash",
        "soybean",
        "cattle",
        "feedlot"
    ],
    "wof:name":"Darrel Rains",
    "wof:placetype":"venue"
},
  "geometry": {"coordinates":[-96.746583,40.169045],"type":"Point"}
}