{
  "type": "Feature",
  "properties": {
    "iso:country":"US",
    "sg:address":"440 Regency Parkway Dr",
    "sg:city":"Omaha",
    "sg:classifiers":[
        {
            "category":"Banks & Credit Unions",
            "subcategory":"Investment Brokerage",
            "type":"Services"
        }
    ],
    "sg:phone":"+1 402 384 8100",
    "sg:postcode":"68114",
    "sg:province":"NE",
    "sg:tags":[
        "security"
    ],
    "wof:name":"Ameritas Investment Instnl",
    "wof:placetype":"venue"
},
  "geometry": {"coordinates":[-96.073781,41.254243],"type":"Point"}
}