{
  "type": "Feature",
  "properties": {
    "iso:country":"US",
    "sg:address":"6123 A St",
    "sg:city":"Lincoln",
    "sg:classifiers":[
        {
            "category":"Real Estate",
            "subcategory":"Architect",
            "type":"Services"
        }
    ],
    "sg:phone":"+1 402 488 6555",
    "sg:postcode":"68510",
    "sg:province":"NE",
    "sg:tags":[
        "architectural"
    ],
    "wof:name":"Quantum Leap Architecture",
    "wof:placetype":"venue"
},
  "geometry": {"coordinates":[-96.633106,40.798899],"type":"Point"}
}