{
  "type": "Feature",
  "properties": {
    "addr:full":"7868 F St Omaha NE 68127",
    "addr:housenumber":"7868",
    "addr:postcode":"68127",
    "addr:street":"F St",
    "iso:country":"US",
    "sg:address":"7868 F St",
    "sg:city":"Omaha",
    "sg:classifiers":[
        {
            "category":"Retail",
            "subcategory":"Auto Repair",
            "type":"Services"
        }
    ],
    "sg:phone":"+1 402 339 1312",
    "sg:postcode":"68127",
    "sg:province":"NE",
    "sg:tags":[
        "repairing",
        "automobile"
    ],
    "wof:name":"Steering/Hydraulic/Machine",
    "wof:placetype":"venue"
},
  "geometry": {"coordinates":[-96.03256399999999,41.219802],"type":"Point"}
}