{
  "type": "Feature",
  "properties": {
    "iso:country":"US",
    "sg:address":"5016 Davenport St",
    "sg:city":"Omaha",
    "sg:classifiers":[
        {
            "category":"Banks & Credit Unions",
            "subcategory":"Financial Services",
            "type":"Services"
        }
    ],
    "sg:phone":"+1 402 556 9818",
    "sg:postcode":"68132",
    "sg:province":"NE",
    "sg:tags":[
        "investor",
        "insurance"
    ],
    "wof:name":"Finsure LLC",
    "wof:placetype":"venue"
},
  "geometry": {"coordinates":[-95.99238,41.261482],"type":"Point"}
}