{
  "type": "Feature",
  "properties": {
    "addr:full":"4902 NW Radial Hwy Omaha NE 68104",
    "addr:housenumber":"4902",
    "addr:postcode":"68104",
    "addr:street":"Nw Radial Hwy",
    "iso:country":"US",
    "sg:address":"4902 NW Radial Hwy",
    "sg:city":"Omaha",
    "sg:classifiers":[
        {
            "category":"Retail",
            "subcategory":"Auto Repair",
            "type":"Services"
        }
    ],
    "sg:phone":"+1 402 553 4480",
    "sg:postcode":"68104",
    "sg:province":"NE",
    "wof:name":"Midwest Automotive Sales & Service",
    "wof:placetype":"venue"
},
  "geometry": {"coordinates":[-95.988197,41.281601],"type":"Point"}
}