{
  "type": "Feature",
  "properties": {
    "iso:country":"US",
    "sg:address":"1510 Westwood Ave",
    "sg:city":"Oneill",
    "sg:classifiers":[
        {
            "category":"Building & Trades",
            "subcategory":"Construction",
            "type":"Services"
        }
    ],
    "sg:phone":"+1 402 336 4620",
    "sg:postcode":"68763",
    "sg:province":"NE",
    "sg:tags":[
        "house"
    ],
    "wof:name":"Tony Bosn Construction",
    "wof:placetype":"venue"
},
  "geometry": {"coordinates":[-98.656825,42.470642],"type":"Point"}
}