{
  "type": "Feature",
  "properties": {
    "addr:full":"2404 Dakota Ave South Sioux City NE 68776",
    "addr:housenumber":"2404",
    "addr:postcode":"68776",
    "addr:street":"Dakota Ave",
    "iso:country":"US",
    "sg:address":"2404 Dakota Ave",
    "sg:city":"South Sioux City",
    "sg:classifiers":[
        {
            "category":"Shopping",
            "subcategory":"Computers & Home Electronics",
            "type":"Retail Goods"
        }
    ],
    "sg:phone":"+1 402 494 1131",
    "sg:postcode":"68776",
    "sg:province":"NE",
    "sg:tags":[
        "equipment",
        "dealer"
    ],
    "wof:name":"Tri Tec Innovations",
    "wof:placetype":"venue"
},
  "geometry": {"coordinates":[-96.413972,42.466309],"type":"Point"}
}