{
  "type": "Feature",
  "properties": {
    "iso:country":"US",
    "sg:address":"509 S Bellevue Ave",
    "sg:city":"Hastings",
    "sg:classifiers":[
        {
            "category":"Social Services",
            "subcategory":"Adult Care",
            "type":"Services"
        }
    ],
    "sg:phone":"+1 402 463 5681",
    "sg:postcode":"68901",
    "sg:province":"NE",
    "sg:tags":[
        "organization",
        "senior",
        "citizen"
    ],
    "wof:name":"Adams County Senior Svc",
    "wof:placetype":"venue"
},
  "geometry": {"coordinates":[-98.395036,40.579415],"type":"Point"}
}