{
  "type": "Feature",
  "properties": {
    "iso:country":"US",
    "sg:address":"5043 2nd Ave",
    "sg:city":"Kearney",
    "sg:classifiers":[
        {
            "category":"Shopping",
            "subcategory":"Gifts & Souvenirs",
            "type":"Retail Goods"
        }
    ],
    "sg:phone":"+1 308 236 6332",
    "sg:postcode":"68847",
    "sg:province":"NE",
    "sg:tags":[
        "shop"
    ],
    "wof:name":"Applebys Cards & Gifts",
    "wof:placetype":"venue"
},
  "geometry": {"coordinates":[-99.083749,40.723404],"type":"Point"}
}