{
  "type": "Feature",
  "properties": {
    "addr:full":"10415 J St Ste 103 Omaha NE 68127",
    "addr:housenumber":"10415",
    "addr:postcode":"68127",
    "addr:street":"J St Ste 103",
    "iso:country":"US",
    "sg:address":"10415 J St Ste 103",
    "sg:city":"Omaha",
    "sg:classifiers":[
        {
            "category":"Building & Trades",
            "subcategory":"Equipment Rental",
            "type":"Services"
        },
        {
            "category":"Building & Trades",
            "subcategory":"Construction",
            "type":"Services"
        }
    ],
    "sg:phone":"+1 402 341 8086",
    "sg:postcode":"68127",
    "sg:province":"NE",
    "sg:tags":[
        "yard",
        "scaffolding",
        "lift",
        "leasing",
        "aerial",
        "store"
    ],
    "sg:website":"http://www.safway.com",
    "wof:name":"Safway Services",
    "wof:placetype":"venue"
},
  "geometry": {"coordinates":[-96.07532,41.214226],"type":"Point"}
}