{
  "type": "Feature",
  "properties": {
    "addr:full":"2085 N 120th St Omaha NE 68164",
    "addr:housenumber":"2085",
    "addr:postcode":"68164",
    "addr:street":"N 120Th St",
    "iso:country":"US",
    "sg:address":"2085 N 120th St",
    "sg:city":"Omaha",
    "sg:classifiers":[
        {
            "category":"Personal",
            "subcategory":"Beauty Salon",
            "type":"Services"
        }
    ],
    "sg:phone":"+1 402 493 0898",
    "sg:postcode":"68164",
    "sg:province":"NE",
    "wof:name":"Supercuts",
    "wof:placetype":"venue"
},
  "geometry": {"coordinates":[-96.100448,41.279574],"type":"Point"}
}