{
  "type": "Feature",
  "properties": {
    "iso:country":"US",
    "sg:address":"3417 Saint Paul Ave",
    "sg:city":"Lincoln",
    "sg:classifiers":[
        {
            "category":"Wholesale",
            "subcategory":"Construction Materials",
            "type":"Manufacturing & Wholesale Goods"
        }
    ],
    "sg:phone":"+1 402 560 2870",
    "sg:postcode":"68504",
    "sg:province":"NE",
    "sg:tags":[
        "fence"
    ],
    "wof:name":"Nebraska Fence Co",
    "wof:placetype":"venue"
},
  "geometry": {"coordinates":[-96.671566,40.839269],"type":"Point"}
}