{
  "type": "Feature",
  "properties": {
    "addr:full":"102 N West St Plainview NE 68769",
    "addr:housenumber":"102",
    "addr:postcode":"68769",
    "addr:street":"N West St",
    "iso:country":"US",
    "sg:address":"102 N West St",
    "sg:city":"Plainview",
    "sg:classifiers":[
        {
            "category":"Personal",
            "subcategory":"Beauty Salon",
            "type":"Services"
        }
    ],
    "sg:phone":"+1 402 582 3454",
    "sg:postcode":"68769",
    "sg:province":"NE",
    "wof:name":"Marla's Hair Affair",
    "wof:placetype":"venue"
},
  "geometry": {"coordinates":[-97.79588800000001,42.351295],"type":"Point"}
}