{
  "type": "Feature",
  "properties": {
    "iso:country":"US",
    "sg:address":"13055 W Center Rd",
    "sg:city":"Omaha",
    "sg:classifiers":[
        {
            "category":"Retail",
            "subcategory":"Portrait Studio",
            "type":"Services"
        }
    ],
    "sg:phone":"+1 402 884 0224",
    "sg:postcode":"68144",
    "sg:province":"NE",
    "sg:tags":[
        "photographer"
    ],
    "wof:name":"Peg's Portrait Studio",
    "wof:placetype":"venue"
},
  "geometry": {"coordinates":[-96.114716,41.233983],"type":"Point"}
}