{
  "type": "Feature",
  "properties": {
    "iso:country":"US",
    "sg:address":"4960 Grover St",
    "sg:city":"Omaha",
    "sg:classifiers":[
        {
            "category":"Wholesale",
            "subcategory":"Groceries",
            "type":"Manufacturing & Wholesale Goods"
        }
    ],
    "sg:phone":"+1 402 556 0659",
    "sg:postcode":"68106",
    "sg:province":"NE",
    "sg:tags":[
        "food",
        "store",
        "candy",
        "broker"
    ],
    "wof:name":"Johnson-Holmes & Associates",
    "wof:placetype":"venue"
},
  "geometry": {"coordinates":[-95.989998,41.2271],"type":"Point"}
}