{
  "type": "Feature",
  "properties": {
    "iso:country":"US",
    "sg:address":"14918 Ridgeview Dr",
    "sg:city":"Plattsmouth",
    "sg:classifiers":[
        {
            "category":"Retail",
            "subcategory":"Repair Shop",
            "type":"Services"
        }
    ],
    "sg:phone":"+1 402 298 8616",
    "sg:postcode":"68048",
    "sg:province":"NE",
    "sg:tags":[
        "lighting",
        "fixture"
    ],
    "wof:name":"Frontier Lighting Maintenance",
    "wof:placetype":"venue"
},
  "geometry": {"coordinates":[-95.87539700000001,40.993131],"type":"Point"}
}