{
  "type": "Feature",
  "properties": {
    "iso:country":"US",
    "sg:address":"406 W 2nd St",
    "sg:city":"Curtis",
    "sg:classifiers":[
        {
            "category":"Professional",
            "subcategory":"Business Services",
            "type":"Services"
        }
    ],
    "sg:phone":"+1 308 367 4499",
    "sg:postcode":"69025",
    "sg:province":"NE",
    "sg:tags":[
        "reservation",
        "motel",
        "hotel"
    ],
    "wof:name":"Lodge At Midwest",
    "wof:placetype":"venue"
},
  "geometry": {"coordinates":[-100.519541,40.630149],"type":"Point"}
}