{
  "type": "Feature",
  "properties": {
    "iso:country":"US",
    "sg:address":"2 W 42nd St",
    "sg:city":"Scottsbluff",
    "sg:classifiers":[
        {
            "category":"Health Services",
            "subcategory":"Doctor",
            "type":"Services"
        }
    ],
    "sg:phone":"+1 308 630 2600",
    "sg:postcode":"69361",
    "sg:province":"NE",
    "sg:tags":[
        "medical"
    ],
    "wof:name":"Robert Sprung MD",
    "wof:placetype":"venue"
},
  "geometry": {"coordinates":[-103.664536,41.88847],"type":"Point"}
}