{
  "type": "Feature",
  "properties": {
    "iso:country":"US",
    "sg:address":"203 Main St",
    "sg:city":"Odell",
    "sg:classifiers":[
        {
            "category":"Personal",
            "subcategory":"Beauty Salon",
            "type":"Services"
        }
    ],
    "sg:phone":"+1 402 766 4140",
    "sg:postcode":"68415",
    "sg:province":"NE",
    "wof:name":"Hair Dimensions",
    "wof:placetype":"venue"
},
  "geometry": {"coordinates":[-96.801844,40.04982],"type":"Point"}
}