{
  "type": "Feature",
  "properties": {
    "iso:country":"US",
    "sg:address":"721 E 4th St",
    "sg:city":"North Platte",
    "sg:classifiers":[
        {
            "category":"Travel",
            "subcategory":"Hotels & Motels",
            "type":"Entertainment"
        }
    ],
    "sg:phone":"+1 308 534 6960",
    "sg:postcode":"69101",
    "sg:province":"NE",
    "sg:tags":[
        "operation"
    ],
    "wof:name":"Husker Inn",
    "wof:placetype":"venue"
},
  "geometry": {"coordinates":[-100.75569400000001,41.135591],"type":"Point"}
}