{
  "type": "Feature",
  "properties": {
    "iso:country":"US",
    "sg:address":"332 N Oak St",
    "sg:city":"Genoa",
    "sg:classifiers":[
        {
            "category":"Freight",
            "type":"Transportation"
        }
    ],
    "sg:phone":"+1 402 993 6580",
    "sg:postcode":"68640",
    "sg:province":"NE",
    "sg:tags":[
        "operator",
        "trucking"
    ],
    "wof:name":"4s Trucking",
    "wof:placetype":"venue"
},
  "geometry": {"coordinates":[-97.73042100000001,41.451952],"type":"Point"}
}