{
  "type": "Feature",
  "properties": {
    "iso:country":"US",
    "sg:address":"351 N Minden Ave",
    "sg:city":"Minden",
    "sg:classifiers":[
        {
            "category":"Shopping",
            "subcategory":"Used Merchandise",
            "type":"Retail Goods"
        }
    ],
    "sg:phone":"+1 308 832 2144",
    "sg:postcode":"68959",
    "sg:province":"NE",
    "sg:tags":[
        "antique"
    ],
    "wof:name":"Granny's Antiques-Collectibles",
    "wof:placetype":"venue"
},
  "geometry": {"coordinates":[-98.947759,40.498026],"type":"Point"}
}