{
  "type": "Feature",
  "properties": {
    "iso:country":"US",
    "sg:address":"1070 James Dr",
    "sg:city":"Blair",
    "sg:classifiers":[
        {
            "category":"Building & Trades",
            "subcategory":"Construction",
            "type":"Services"
        }
    ],
    "sg:phone":"+1 402 533 4631",
    "sg:postcode":"68008",
    "sg:province":"NE",
    "sg:tags":[
        "general",
        "contractor"
    ],
    "wof:name":"Mc Caig Construction",
    "wof:placetype":"venue"
},
  "geometry": {"coordinates":[-96.138124,41.554872],"type":"Point"}
}