{
  "type": "Feature",
  "properties": {
    "iso:country":"US",
    "sg:address":"43544 Rd 755",
    "sg:city":"Lexington",
    "sg:classifiers":[
        {
            "category":"Building & Trades",
            "subcategory":"Construction",
            "type":"Services"
        }
    ],
    "sg:phone":"+1 308 324 7260",
    "sg:postcode":"68850",
    "sg:province":"NE",
    "sg:tags":[
        "excavating",
        "contractor"
    ],
    "wof:name":"G & V Inc",
    "wof:placetype":"venue"
},
  "geometry": {"coordinates":[-99.69538,40.772182],"type":"Point"}
}