{
  "type": "Feature",
  "properties": {
    "iso:country":"US",
    "sg:address":"508 Skyline Rd",
    "sg:city":"Elkhorn",
    "sg:classifiers":[
        {
            "category":"Recreation",
            "type":"Entertainment"
        }
    ],
    "sg:phone":"+1 402 289 4400",
    "sg:postcode":"68022",
    "sg:province":"NE",
    "sg:tags":[
        "amusement"
    ],
    "wof:name":"Chance Ridge Event Ctr",
    "wof:placetype":"venue"
},
  "geometry": {"coordinates":[-96.24762200000001,41.266403],"type":"Point"}
}