{
  "type": "Feature",
  "properties": {
    "addr:full":"145 S 10th St Geneva NE 68361",
    "addr:housenumber":"145",
    "addr:postcode":"68361",
    "addr:street":"S 10Th St",
    "iso:country":"US",
    "sg:address":"145 S 10th St",
    "sg:city":"Geneva",
    "sg:classifiers":[
        {
            "category":"Insurance",
            "subcategory":"Insurance Agent",
            "type":"Services"
        }
    ],
    "sg:phone":"+1 402 759 3300",
    "sg:postcode":"68361",
    "sg:province":"NE",
    "wof:name":"Richard Walter Real Estate",
    "wof:placetype":"venue"
},
  "geometry": {"coordinates":[-97.601032,40.525105],"type":"Point"}
}