{
  "type": "Feature",
  "properties": {
    "addr:full":"2223 N 91st Plz Omaha NE 68134",
    "addr:housenumber":"2223",
    "addr:postcode":"68134",
    "addr:street":"N 91St",
    "iso:country":"US",
    "sg:address":"2223 N 91st Plz",
    "sg:city":"Omaha",
    "sg:classifiers":[
        {
            "category":"Health Services",
            "subcategory":"Chiropractor",
            "type":"Services"
        }
    ],
    "sg:phone":"+1 402 397 0919",
    "sg:postcode":"68134",
    "sg:province":"NE",
    "wof:name":"Omaha Chiropractic Associates",
    "wof:placetype":"venue"
},
  "geometry": {"coordinates":[-96.053692,41.278366],"type":"Point"}
}