{
  "type": "Feature",
  "properties": {
    "iso:country":"US",
    "sg:address":"4835 S 24th St",
    "sg:city":"Omaha",
    "sg:classifiers":[
        {
            "category":"Restaurant",
            "type":"Food & Drink"
        }
    ],
    "sg:phone":"+1 402 734 9001",
    "sg:postcode":"68107",
    "sg:province":"NE",
    "sg:tags":[
        "eating"
    ],
    "wof:name":"El Sol Restaurante",
    "wof:placetype":"venue"
},
  "geometry": {"coordinates":[-95.946983,41.210175],"type":"Point"}
}