{
  "type": "Feature",
  "properties": {
    "iso:country":"US",
    "sg:address":"914 P St",
    "sg:city":"Geneva",
    "sg:classifiers":[
        {
            "category":"Social Services",
            "subcategory":"Adult Care",
            "type":"Services"
        }
    ],
    "sg:phone":"+1 402 759 4334",
    "sg:postcode":"68361",
    "sg:province":"NE",
    "sg:tags":[
        "home",
        "group"
    ],
    "wof:name":"Heartland Boys Home",
    "wof:placetype":"venue"
},
  "geometry": {"coordinates":[-97.60261300000001,40.536722],"type":"Point"}
}