{
  "type": "Feature",
  "properties": {
    "addr:full":"2410 Q St Omaha NE 68107",
    "addr:housenumber":"2410",
    "addr:postcode":"68107",
    "addr:street":"Q St",
    "iso:country":"US",
    "sg:address":"2410 Q St",
    "sg:city":"Omaha",
    "sg:classifiers":[
        {
            "category":"Shopping",
            "subcategory":"Music",
            "type":"Retail Goods"
        }
    ],
    "sg:phone":"+1 402 614 2118",
    "sg:postcode":"68107",
    "sg:province":"NE",
    "sg:tags":[
        "compact",
        "record",
        "disc",
        "tape"
    ],
    "wof:name":"Discoteca El Korita",
    "wof:placetype":"venue"
},
  "geometry": {"coordinates":[-95.94844000000001,41.205669],"type":"Point"}
}