{
  "type": "Feature",
  "properties": {
    "iso:country":"US",
    "sg:address":"542 Westridge Dr",
    "sg:city":"Broken Bow",
    "sg:classifiers":[
        {
            "category":"Farming",
            "subcategory":"Farm",
            "type":"Manufacturing & Wholesale Goods"
        }
    ],
    "sg:phone":"+1 308 872 6554",
    "sg:postcode":"68822",
    "sg:province":"NE",
    "sg:tags":[
        "crop",
        "general"
    ],
    "wof:name":"Gallentine Farms Inc",
    "wof:placetype":"venue"
},
  "geometry": {"coordinates":[-99.654967,41.410551],"type":"Point"}
}