{
  "type": "Feature",
  "properties": {
    "addr:full":"2449 Mary St Omaha NE 68112",
    "addr:housenumber":"2449",
    "addr:postcode":"68112",
    "addr:street":"Mary St",
    "iso:country":"US",
    "sg:address":"2449 Mary St",
    "sg:city":"Omaha",
    "sg:classifiers":[
        {
            "category":"Professional",
            "type":"Services"
        }
    ],
    "sg:phone":"+1 402 455 1296",
    "sg:postcode":"68112",
    "sg:province":"NE",
    "wof:name":"ABC Corporate Svc Inc",
    "wof:placetype":"venue"
},
  "geometry": {"coordinates":[-95.94843899999999,41.319829],"type":"Point"}
}