{
  "type": "Feature",
  "properties": {
    "addr:full":"1014 N 6th St Seward NE 68434",
    "addr:housenumber":"1014",
    "addr:postcode":"68434",
    "addr:street":"N 6Th St",
    "iso:country":"US",
    "sg:address":"1014 N 6th St",
    "sg:city":"Seward",
    "sg:classifiers":[
        {
            "category":"Organizations",
            "subcategory":"Religious Organization",
            "type":"Services"
        }
    ],
    "sg:phone":"+1 402 643 3829",
    "sg:postcode":"68434",
    "sg:province":"NE",
    "wof:name":"Saint Andrews Episcopal Church",
    "wof:placetype":"venue"
},
  "geometry": {"coordinates":[-97.099087,40.916707],"type":"Point"}
}