{
  "type": "Feature",
  "properties": {
    "iso:country":"US",
    "sg:address":"30013 Alvo Rd",
    "sg:city":"Murdock",
    "sg:classifiers":[
        {
            "category":"Farming",
            "subcategory":"Farm",
            "type":"Manufacturing & Wholesale Goods"
        }
    ],
    "sg:phone":"+1 402 867 3541",
    "sg:postcode":"68407",
    "sg:province":"NE",
    "sg:tags":[
        "crop",
        "general"
    ],
    "wof:name":"Jerry Daharsh",
    "wof:placetype":"venue"
},
  "geometry": {"coordinates":[-96.292198,40.884966],"type":"Point"}
}