{
  "type": "Feature",
  "properties": {
    "addr:full":"506 Main St Kennard NE 68034",
    "addr:housenumber":"506",
    "addr:postcode":"68034",
    "addr:street":"Main St",
    "iso:country":"US",
    "sg:address":"506 Main St",
    "sg:city":"Kennard",
    "sg:classifiers":[
        {
            "category":"Shopping",
            "type":"Retail Goods"
        }
    ],
    "sg:phone":"+1 402 427 7544",
    "sg:postcode":"68034",
    "sg:province":"NE",
    "sg:tags":[
        "miscellaneous",
        "store"
    ],
    "wof:name":"Sheila's",
    "wof:placetype":"venue"
},
  "geometry": {"coordinates":[-96.201699,41.476946],"type":"Point"}
}