{
  "type": "Feature",
  "properties": {
    "iso:country":"US",
    "sg:address":"5083 S 172nd St",
    "sg:city":"Omaha",
    "sg:classifiers":[
        {
            "category":"Manufacturing",
            "subcategory":"Tobacco Products",
            "type":"Manufacturing & Wholesale Goods"
        }
    ],
    "sg:phone":"+1 402 330 4900",
    "sg:postcode":"68135",
    "sg:province":"NE",
    "sg:tags":[
        "cigarette",
        "cigar"
    ],
    "sg:website":"www.rjrt.com",
    "wof:name":"R J Reynolds Tobacco Co",
    "wof:placetype":"venue"
},
  "geometry": {"coordinates":[-96.183328,41.206363],"type":"Point"}
}