{
  "type": "Feature",
  "properties": {
    "addr:full":"132 N Main St Fremont NE 68025",
    "addr:housenumber":"132",
    "addr:postcode":"68025",
    "addr:street":"N Main St",
    "iso:country":"US",
    "sg:address":"132 N Main St",
    "sg:city":"Fremont",
    "sg:classifiers":[
        {
            "category":"Manufacturing",
            "subcategory":"Printing",
            "type":"Manufacturing & Wholesale Goods"
        }
    ],
    "sg:phone":"+1 402 721 0190",
    "sg:postcode":"68025",
    "sg:province":"NE",
    "sg:tags":[
        "printer"
    ],
    "wof:name":"Don's Copy Ctr",
    "wof:placetype":"venue"
},
  "geometry": {"coordinates":[-96.49632099999999,41.430814],"type":"Point"}
}