{
  "type": "Feature",
  "properties": {
    "iso:country":"US",
    "sg:address":"4300 US Hwy 30",
    "sg:city":"Grand Island",
    "sg:classifiers":[
        {
            "category":"Autos & Motor Vehicles",
            "subcategory":"Auto Supplies",
            "type":"Retail Goods"
        }
    ],
    "sg:phone":"+1 308 398 0658",
    "sg:postcode":"68801",
    "sg:province":"NE",
    "sg:tags":[
        "automobile",
        "parts"
    ],
    "wof:name":"Parts Man",
    "wof:placetype":"venue"
},
  "geometry": {"coordinates":[-98.291777,40.944837],"type":"Point"}
}