{
  "type": "Feature",
  "properties": {
    "addr:full":"3509 Neerpark Dr Lincoln NE 68506",
    "addr:housenumber":"3509",
    "addr:postcode":"68506",
    "addr:street":"Neerpark Dr",
    "iso:country":"US",
    "sg:address":"3509 Neerpark Dr",
    "sg:city":"Lincoln",
    "sg:classifiers":[
        {
            "category":"Building & Trades",
            "subcategory":"Construction",
            "type":"Services"
        }
    ],
    "sg:phone":"+1 402 486 1132",
    "sg:postcode":"68506",
    "sg:province":"NE",
    "sg:tags":[
        "concrete",
        "cutting",
        "breaking",
        "sawing"
    ],
    "wof:name":"Contractor's Svc",
    "wof:placetype":"venue"
},
  "geometry": {"coordinates":[-96.643919,40.779387],"type":"Point"}
}