{
  "type": "Feature",
  "properties": {
    "addr:full":"11021 Prairie Hills Dr Omaha NE 68144",
    "addr:housenumber":"11021",
    "addr:postcode":"68144",
    "addr:street":"Prairie Hills Dr",
    "iso:country":"US",
    "sg:address":"11021 Prairie Hills Dr",
    "sg:city":"Omaha",
    "sg:classifiers":[
        {
            "category":"Personal",
            "subcategory":"Beauty Salon",
            "type":"Services"
        }
    ],
    "sg:phone":"+1 402 393 4888",
    "sg:postcode":"68144",
    "sg:province":"NE",
    "sg:tags":[
        "shop"
    ],
    "wof:name":"Sandys Beauty Salon",
    "wof:placetype":"venue"
},
  "geometry": {"coordinates":[-96.085185,41.230954],"type":"Point"}
}