{
  "type": "Feature",
  "properties": {
    "iso:country":"US",
    "sg:address":"701 W 1st St",
    "sg:city":"Hastings",
    "sg:classifiers":[
        {
            "category":"Building & Trades",
            "subcategory":"Plumbing",
            "type":"Services"
        }
    ],
    "sg:phone":"+1 402 462 9190",
    "sg:postcode":"68901",
    "sg:province":"NE",
    "sg:tags":[
        "contractor"
    ],
    "wof:name":"South Central Heating & AC",
    "wof:placetype":"venue"
},
  "geometry": {"coordinates":[-98.39117299999999,40.584267],"type":"Point"}
}