{
  "type": "Feature",
  "properties": {
    "addr:full":"4911 Dodge St Omaha NE 68132",
    "addr:housenumber":"4911",
    "addr:postcode":"68132",
    "addr:street":"Dodge St",
    "iso:country":"US",
    "sg:address":"4911 Dodge St",
    "sg:city":"Omaha",
    "sg:classifiers":[
        {
            "category":"Shopping",
            "subcategory":"Clothing, Apparel, & Fashions",
            "type":"Retail Goods"
        }
    ],
    "sg:phone":"+1 402 551 4831",
    "sg:postcode":"68132",
    "sg:province":"NE",
    "sg:tags":[
        "accessory"
    ],
    "wof:name":"Nan C",
    "wof:placetype":"venue"
},
  "geometry": {"coordinates":[-95.988238,41.259383],"type":"Point"}
}