{
  "type": "Feature",
  "properties": {
    "iso:country":"US",
    "sg:address":"413 S 38th Ave",
    "sg:city":"Omaha",
    "sg:classifiers":[
        {
            "category":"Arts & Performance",
            "subcategory":"Theater",
            "type":"Entertainment"
        }
    ],
    "sg:phone":"+1 402 345 1050",
    "sg:postcode":"68131",
    "sg:province":"NE",
    "sg:tags":[
        "entertainer",
        "group",
        "business"
    ],
    "wof:name":"Juggling By Renee Crosby",
    "wof:placetype":"venue"
},
  "geometry": {"coordinates":[-95.970392,41.256173],"type":"Point"}
}