{
  "type": "Feature",
  "properties": {
    "iso:country":"US",
    "sg:address":"4733 Prescott Ave",
    "sg:city":"Lincoln",
    "sg:classifiers":[
        {
            "category":"Banks & Credit Unions",
            "subcategory":"Bank",
            "type":"Services"
        }
    ],
    "sg:phone":"+1 402 489 8886",
    "sg:postcode":"68506",
    "sg:province":"NE",
    "sg:tags":[
        "state"
    ],
    "wof:name":"Lincoln SDA Credit Union",
    "wof:placetype":"venue"
},
  "geometry": {"coordinates":[-96.654405,40.772834],"type":"Point"}
}