{
  "type": "Feature",
  "properties": {
    "addr:full":"13259 Millard Ave Omaha NE 68137",
    "addr:housenumber":"13259",
    "addr:postcode":"68137",
    "addr:street":"Millard Ave",
    "iso:country":"US",
    "sg:address":"13259 Millard Ave",
    "sg:city":"Omaha",
    "sg:classifiers":[
        {
            "category":"Professional",
            "subcategory":"Management & Consulting",
            "type":"Services"
        },
        {
            "category":"Shopping",
            "subcategory":"Computers & Home Electronics",
            "type":"Retail Goods"
        }
    ],
    "sg:phone":"+1 402 895 2100",
    "sg:postcode":"68137",
    "sg:province":"NE",
    "sg:tags":[
        "marketing",
        "software",
        "merchandising",
        "developer"
    ],
    "sg:website":"www.direct-tech.com",
    "wof:name":"Direct Tech Inc",
    "wof:placetype":"venue"
},
  "geometry": {"coordinates":[-96.122337,41.210849],"type":"Point"}
}