{
  "type": "Feature",
  "properties": {
    "iso:country":"US",
    "sg:address":"4527 State Hwy 43",
    "sg:city":"Adams",
    "sg:classifiers":[
        {
            "category":"Building & Trades",
            "subcategory":"Construction",
            "type":"Services"
        }
    ],
    "sg:phone":"+1 402 988 2225",
    "sg:postcode":"68301",
    "sg:province":"NE",
    "sg:tags":[
        "home",
        "builder"
    ],
    "wof:name":"Artz & Ashelford Construction",
    "wof:placetype":"venue"
},
  "geometry": {"coordinates":[-96.50171,40.475955],"type":"Point"}
}