{
  "type": "Feature",
  "properties": {
    "iso:country":"US",
    "sg:address":"916 S 4th St",
    "sg:city":"Norfolk",
    "sg:classifiers":[
        {
            "category":"Organizations",
            "subcategory":"Non-profit Organization",
            "type":"Services"
        }
    ],
    "sg:phone":"+1 402 844 4710",
    "sg:postcode":"68701",
    "sg:province":"NE",
    "wof:name":"Well Link House",
    "wof:placetype":"venue"
},
  "geometry": {"coordinates":[-97.41195500000001,42.022659],"type":"Point"}
}