{
  "type": "Feature",
  "properties": {
    "addr:full":"9056 Westridge Dr Omaha NE 68124",
    "addr:housenumber":"9056",
    "addr:postcode":"68124",
    "addr:street":"Westridge Dr",
    "iso:country":"US",
    "sg:address":"9056 Westridge Dr",
    "sg:city":"Omaha",
    "sg:classifiers":[
        {
            "category":"Professional",
            "type":"Services"
        }
    ],
    "sg:phone":"+1 402 366 5532",
    "sg:postcode":"68124",
    "sg:province":"NE",
    "sg:tags":[
        "chemistry"
    ],
    "wof:name":"Walford Talia",
    "wof:placetype":"venue"
},
  "geometry": {"coordinates":[-96.054109,41.2303],"type":"Point"}
}