{
  "type": "Feature",
  "properties": {
    "iso:country":"US",
    "sg:address":"1710 N 144th St",
    "sg:city":"Omaha",
    "sg:classifiers":[
        {
            "category":"Health Services",
            "subcategory":"Dentist",
            "type":"Services"
        }
    ],
    "sg:phone":"+1 402 682 7858",
    "sg:postcode":"68154",
    "sg:province":"NE",
    "sg:tags":[
        "dentists-orthodontists"
    ],
    "sg:website":"http://longoorthodontics.com",
    "wof:name":"Longo Alfred T",
    "wof:placetype":"venue"
},
  "geometry": {"coordinates":[-96.138785,41.274348],"type":"Point"}
}