{
  "type": "Feature",
  "properties": {
    "iso:country":"US",
    "sg:address":"300 S Coddington Ave",
    "sg:city":"Lincoln",
    "sg:classifiers":[
        {
            "category":"Building & Trades",
            "subcategory":"Landscaping Services",
            "type":"Services"
        }
    ],
    "sg:phone":"+1 402 438 5115",
    "sg:postcode":"68522",
    "sg:province":"NE",
    "sg:tags":[
        "lawn",
        "maintenance",
        "grounds"
    ],
    "wof:name":"All Care Grounds Management",
    "wof:placetype":"venue"
},
  "geometry": {"coordinates":[-96.75068899999999,40.810403],"type":"Point"}
}