{
  "type": "Feature",
  "properties": {
    "iso:country":"US",
    "sg:address":"4701 N 64th St",
    "sg:city":"Omaha",
    "sg:classifiers":[
        {
            "category":"Building & Trades",
            "subcategory":"Locksmith",
            "type":"Services"
        }
    ],
    "sg:phone":"+1 402 715 9676",
    "sg:postcode":"68104",
    "sg:province":"NE",
    "sg:tags":[
        "key"
    ],
    "wof:name":"0 1 Emergency A Locksmith",
    "wof:placetype":"venue"
},
  "geometry": {"coordinates":[-96.01044899999999,41.301315],"type":"Point"}
}