{
  "type": "Feature",
  "properties": {
    "iso:country":"US",
    "sg:address":"206 Fraisier St",
    "sg:city":"Niobrara",
    "sg:classifiers":[
        {
            "category":"Education",
            "subcategory":"School",
            "type":"Public Place"
        }
    ],
    "sg:phone":"+1 402 857 2741",
    "sg:postcode":"68716",
    "sg:province":"NE",
    "wof:name":"Santee Cmty School Dist C5",
    "wof:placetype":"venue"
},
  "geometry": {"coordinates":[-96.80895700000001,41.929667],"type":"Point"}
}