{
  "type": "Feature",
  "properties": {
    "addr:full":"3333 Oak View Dr Omaha NE 68144",
    "addr:housenumber":"3333",
    "addr:postcode":"68144",
    "addr:street":"Oak View Dr",
    "iso:country":"US",
    "sg:address":"3333 Oak View Dr",
    "sg:city":"Omaha",
    "sg:classifiers":[
        {
            "category":"Shopping",
            "subcategory":"Books",
            "type":"Retail Goods"
        }
    ],
    "sg:phone":"+1 402 691 4557",
    "sg:postcode":"68144",
    "sg:province":"NE",
    "sg:tags":[
        "dealer"
    ],
    "wof:name":"Barnes & Noble Booksellers",
    "wof:placetype":"venue"
},
  "geometry": {"coordinates":[-96.13508400000001,41.226764],"type":"Point"}
}