{
  "type": "Feature",
  "properties": {
    "iso:country":"US",
    "sg:address":"1325 Elm Ave",
    "sg:city":"Norfolk",
    "sg:classifiers":[
        {
            "category":"Freight",
            "type":"Transportation"
        }
    ],
    "sg:phone":"+1 402 371 8854",
    "sg:postcode":"68701",
    "sg:province":"NE",
    "sg:tags":[
        "operator",
        "local",
        "trucking"
    ],
    "wof:name":"Rex & Mary Rogers Trucking",
    "wof:placetype":"venue"
},
  "geometry": {"coordinates":[-97.42944300000001,42.038078],"type":"Point"}
}