{
  "type": "Feature",
  "properties": {
    "iso:country":"US",
    "sg:address":"113 W B St",
    "sg:city":"North Platte",
    "sg:classifiers":[
        {
            "category":"Food & Beverages",
            "subcategory":"Groceries & Convenience Stores",
            "type":"Retail Goods"
        }
    ],
    "sg:phone":"+1 308 532 7480",
    "sg:postcode":"69101",
    "sg:province":"NE",
    "wof:name":"KWIK Stop",
    "wof:placetype":"venue"
},
  "geometry": {"coordinates":[-100.764504,41.132613],"type":"Point"}
}