{
  "type": "Feature",
  "properties": {
    "iso:country":"US",
    "sg:address":"4971 S 155th St",
    "sg:city":"Omaha",
    "sg:classifiers":[
        {
            "category":"Personal",
            "subcategory":"Beauty Salon",
            "type":"Services"
        }
    ],
    "sg:phone":"+1 402 896 2030",
    "sg:postcode":"68137",
    "sg:province":"NE",
    "sg:tags":[
        "shop"
    ],
    "sg:website":"www.greatclips.com",
    "wof:name":"Great Clips",
    "wof:placetype":"venue"
},
  "geometry": {"coordinates":[-96.15689399999999,41.207432],"type":"Point"}
}