{
  "type": "Feature",
  "properties": {
    "addr:full":"1544 S 1st St Lincoln NE 68502",
    "addr:housenumber":"1544",
    "addr:postcode":"68502",
    "addr:street":"S 1St St",
    "iso:country":"US",
    "sg:address":"1544 S 1st St",
    "sg:city":"Lincoln",
    "sg:classifiers":[
        {
            "category":"Building & Trades",
            "subcategory":"Construction",
            "type":"Services"
        }
    ],
    "sg:phone":"+1 402 434 3220",
    "sg:postcode":"68502",
    "sg:province":"NE",
    "sg:tags":[
        "general",
        "framing",
        "contractor"
    ],
    "wof:name":"Pride Homes",
    "wof:placetype":"venue"
},
  "geometry": {"coordinates":[-96.720519,40.798662],"type":"Point"}
}