{
  "type": "Feature",
  "properties": {
    "iso:country":"US",
    "sg:address":"304 E 17th St",
    "sg:city":"Grand Island",
    "sg:classifiers":[
        {
            "category":"Social Services",
            "subcategory":"Child Care",
            "type":"Services"
        }
    ],
    "sg:phone":"+1 308 384 4191",
    "sg:postcode":"68801",
    "sg:province":"NE",
    "sg:tags":[
        "day"
    ],
    "wof:name":"Steinmeyer Helen L Day Care",
    "wof:placetype":"venue"
},
  "geometry": {"coordinates":[-98.347262,40.940937],"type":"Point"}
}