{
  "type": "Feature",
  "properties": {
    "iso:country":"US",
    "sg:address":"4503 R St",
    "sg:city":"Omaha",
    "sg:classifiers":[
        {
            "category":"Retail",
            "subcategory":"Repair Shop",
            "type":"Services"
        }
    ],
    "sg:phone":"+1 402 731 8305",
    "sg:postcode":"68117",
    "sg:province":"NE",
    "sg:tags":[
        "upholsterer"
    ],
    "wof:name":"Ludlow's Upholstery Shop",
    "wof:placetype":"venue"
},
  "geometry": {"coordinates":[-95.98330900000001,41.204354],"type":"Point"}
}