{
  "type": "Feature",
  "properties": {
    "addr:full":"2284 Van Dorn Rd Milford NE 68405",
    "addr:housenumber":"2284",
    "addr:postcode":"68405",
    "addr:street":"Van Dorn Rd",
    "iso:country":"US",
    "sg:address":"2284 Van Dorn Rd",
    "sg:city":"Milford",
    "sg:classifiers":[
        {
            "category":"Professional",
            "subcategory":"Computer Services",
            "type":"Services"
        }
    ],
    "sg:phone":"+1 402 761 2884",
    "sg:postcode":"68405",
    "sg:province":"NE",
    "sg:tags":[
        "related"
    ],
    "wof:name":"B & R Electronics",
    "wof:placetype":"venue"
},
  "geometry": {"coordinates":[-97.030028,40.785265],"type":"Point"}
}