{
  "type": "Feature",
  "properties": {
    "iso:country":"US",
    "sg:address":"313 Prairie Rd",
    "sg:city":"Plattsmouth",
    "sg:classifiers":[
        {
            "category":"Social Services",
            "subcategory":"Child Care",
            "type":"Services"
        }
    ],
    "sg:phone":"+1 402 298 8894",
    "sg:postcode":"68048",
    "sg:province":"NE",
    "sg:tags":[
        "day"
    ],
    "wof:name":"Post Lori Day Care",
    "wof:placetype":"venue"
},
  "geometry": {"coordinates":[-95.90828999999999,40.968133],"type":"Point"}
}