{
  "type": "Feature",
  "properties": {
    "iso:country":"US",
    "sg:address":"8932 J St",
    "sg:city":"Omaha",
    "sg:classifiers":[
        {
            "category":"Professional",
            "subcategory":"Business Services",
            "type":"Services"
        }
    ],
    "sg:phone":"+1 402 657 7805",
    "sg:postcode":"68127",
    "sg:province":"NE",
    "wof:name":"David M Mangelsens Group",
    "wof:placetype":"venue"
},
  "geometry": {"coordinates":[-96.051677,41.215473],"type":"Point"}
}