{
  "type": "Feature",
  "properties": {
    "addr:full":"420 N H St Fremont NE 68025",
    "addr:housenumber":"420",
    "addr:postcode":"68025",
    "addr:street":"N H St",
    "iso:country":"US",
    "sg:address":"420 N H St",
    "sg:city":"Fremont",
    "sg:classifiers":[
        {
            "category":"Professional",
            "subcategory":"Business Services",
            "type":"Services"
        }
    ],
    "sg:phone":"+1 402 721 8724",
    "sg:postcode":"68025",
    "sg:province":"NE",
    "sg:tags":[
        "water",
        "treatment"
    ],
    "wof:name":"Ecowater Systems",
    "wof:placetype":"venue"
},
  "geometry": {"coordinates":[-96.499889,41.433771],"type":"Point"}
}