{
  "type": "Feature",
  "properties": {
    "addr:full":"3168 W Stolley Park Rd Grand Island NE 68801",
    "addr:housenumber":"3168",
    "addr:postcode":"68801",
    "addr:street":"W Stolley Park Rd",
    "iso:country":"US",
    "sg:address":"3168 W Stolley Park Rd",
    "sg:city":"Grand Island",
    "sg:classifiers":[
        {
            "category":"Real Estate",
            "subcategory":"Developer",
            "type":"Services"
        }
    ],
    "sg:phone":"+1 308 385 5359",
    "sg:postcode":"68801",
    "sg:province":"NE",
    "sg:tags":[
        "executive",
        "cemetery"
    ],
    "wof:name":"Grand Island City Cemetery",
    "wof:placetype":"venue"
},
  "geometry": {"coordinates":[-98.378275,40.902626],"type":"Point"}
}