{
  "type": "Feature",
  "properties": {
    "addr:full":"730 W Cornhusker Hwy Lincoln NE 68521",
    "addr:housenumber":"730",
    "addr:postcode":"68521",
    "addr:street":"W Cornhusker Hwy",
    "iso:country":"US",
    "sg:address":"730 W Cornhusker Hwy",
    "sg:city":"Lincoln",
    "sg:classifiers":[
        {
            "category":"Food & Beverages",
            "subcategory":"Groceries & Convenience Stores",
            "type":"Retail Goods"
        }
    ],
    "sg:phone":"+1 402 475 8838",
    "sg:postcode":"68521",
    "sg:province":"NE",
    "wof:name":"Kabredlo's Convenience Store",
    "wof:placetype":"venue"
},
  "geometry": {"coordinates":[-96.733104,40.835578],"type":"Point"}
}