{
  "type": "Feature",
  "properties": {
    "iso:country":"US",
    "sg:address":"14475 Sherwood Ave",
    "sg:city":"Omaha",
    "sg:phone":"+1 402 397 9400",
    "sg:postcode":"68116",
    "sg:province":"NE",
    "sg:tags":[
        "wholesale",
        "petroleum",
        "sales"
    ],
    "sg:website":"www.alfordcompanies.com",
    "wof:name":"Cornhusker Petroleum Inc",
    "wof:placetype":"venue"
},
  "geometry": {"coordinates":[-96.141366,41.281667],"type":"Point"}
}