{
  "type": "Feature",
  "properties": {
    "addr:full":"10901 S 63rd St Lincoln NE 68516",
    "addr:housenumber":"10901",
    "addr:postcode":"68516",
    "addr:street":"S 63Rd St",
    "iso:country":"US",
    "sg:address":"10901 S 63rd St",
    "sg:city":"Lincoln",
    "sg:classifiers":[
        {
            "category":"Arts & Performance",
            "subcategory":"Theater",
            "type":"Entertainment"
        }
    ],
    "sg:phone":"+1 402 421 8787",
    "sg:postcode":"68516",
    "sg:province":"NE",
    "sg:tags":[
        "live",
        "music"
    ],
    "wof:name":"Total Sound",
    "wof:placetype":"venue"
},
  "geometry": {"coordinates":[-96.63630999999999,40.702163],"type":"Point"}
}