{
  "type": "Feature",
  "properties": {
    "iso:country":"US",
    "sg:address":"31147 445th Ave",
    "sg:city":"Yankton",
    "sg:classifiers":[
        {
            "category":"Building & Trades",
            "subcategory":"Landscaping Services",
            "type":"Services"
        }
    ],
    "sg:phone":"+1 605 665 3963",
    "sg:postcode":"57078",
    "sg:province":"NE",
    "sg:tags":[
        "landscape",
        "contractor"
    ],
    "wof:name":"Sprinkler Systems Of Yankton",
    "wof:placetype":"venue"
},
  "geometry": {"coordinates":[-97.29880300000001,42.878877],"type":"Point"}
}