{
  "type": "Feature",
  "properties": {
    "addr:full":"9975 Bloomfield Dr Omaha NE 68114",
    "addr:housenumber":"9975",
    "addr:postcode":"68114",
    "addr:street":"Bloomfield Dr",
    "iso:country":"US",
    "sg:address":"9975 Bloomfield Dr",
    "sg:city":"Omaha",
    "sg:classifiers":[
        {
            "category":"Professional",
            "subcategory":"Art Services",
            "type":"Services"
        },
        {
            "category":"Home & Garden",
            "subcategory":"Furniture",
            "type":"Retail Goods"
        }
    ],
    "sg:phone":"+1 402 391 5383",
    "sg:postcode":"68114",
    "sg:province":"NE",
    "sg:tags":[
        "interior",
        "designer",
        "decorator",
        "store"
    ],
    "wof:name":"Albert-Krantz Interiors Inc",
    "wof:placetype":"venue"
},
  "geometry": {"coordinates":[-96.069512,41.270627],"type":"Point"}
}