{
  "type": "Feature",
  "properties": {
    "iso:country":"US",
    "sg:address":"313 E 12th St",
    "sg:city":"Cozad",
    "sg:classifiers":[
        {
            "category":"Health Services",
            "subcategory":"Hospital",
            "type":"Services"
        }
    ],
    "sg:phone":"+1 308 784 2231",
    "sg:postcode":"69130",
    "sg:province":"NE",
    "wof:name":"Physical Therapy",
    "wof:placetype":"venue"
},
  "geometry": {"coordinates":[-99.982979,40.863087],"type":"Point"}
}