{
  "type": "Feature",
  "properties": {
    "iso:country":"US",
    "sg:address":"5943 S 74th St",
    "sg:city":"Lincoln",
    "sg:classifiers":[
        {
            "category":"Manufacturing",
            "subcategory":"Food",
            "type":"Manufacturing & Wholesale Goods"
        }
    ],
    "sg:phone":"+1 402 489 8085",
    "sg:postcode":"68516",
    "sg:province":"NE",
    "sg:tags":[
        "liquor",
        "mfg"
    ],
    "wof:name":"Tranquil Goddess LLC",
    "wof:placetype":"venue"
},
  "geometry": {"coordinates":[-96.620689,40.751182],"type":"Point"}
}