{
  "type": "Feature",
  "properties": {
    "iso:country":"US",
    "sg:address":"41831 Rd 752",
    "sg:city":"Eustis",
    "sg:classifiers":[
        {
            "category":"Professional",
            "subcategory":"Management & Consulting",
            "type":"Services"
        }
    ],
    "sg:phone":"+1 308 486 5793",
    "sg:postcode":"69028",
    "sg:province":"NE",
    "sg:tags":[
        "business"
    ],
    "wof:name":"Stutterheim Crop Advisory",
    "wof:placetype":"venue"
},
  "geometry": {"coordinates":[-100.02196600000001,40.728649],"type":"Point"}
}