{
  "type": "Feature",
  "properties": {
    "iso:country":"US",
    "sg:address":"365 N Main St",
    "sg:city":"Valentine",
    "sg:classifiers":[
        {
            "category":"Government",
            "subcategory":"Office",
            "type":"Public Place"
        }
    ],
    "sg:phone":"+1 402 376 1630",
    "sg:postcode":"69201",
    "sg:province":"NE",
    "sg:tags":[
        "county",
        "taxation"
    ],
    "wof:name":"Cherry County Assessor",
    "wof:placetype":"venue"
},
  "geometry": {"coordinates":[-100.550771,42.875201],"type":"Point"}
}