{
  "type": "Feature",
  "properties": {
    "addr:full":"2700 W A St North Platte NE 69101",
    "addr:housenumber":"2700",
    "addr:postcode":"69101",
    "addr:street":"W A St",
    "iso:country":"US",
    "sg:address":"2700 W A St",
    "sg:city":"North Platte",
    "sg:classifiers":[
        {
            "category":"Organizations",
            "subcategory":"Religious Organization",
            "type":"Services"
        }
    ],
    "sg:phone":"+1 308 532 9258",
    "sg:postcode":"69101",
    "sg:province":"NE",
    "wof:name":"Messiah Lutheran Church",
    "wof:placetype":"venue"
},
  "geometry": {"coordinates":[-100.79516599999999,41.133573],"type":"Point"}
}