{
  "type": "Feature",
  "properties": {
    "iso:country":"US",
    "sg:address":"1702 O St",
    "sg:city":"Cozad",
    "sg:classifiers":[
        {
            "category":"Building & Trades",
            "subcategory":"Construction",
            "type":"Services"
        }
    ],
    "sg:phone":"+1 308 784 5232",
    "sg:postcode":"69130",
    "sg:province":"NE",
    "sg:tags":[
        "general",
        "contractor"
    ],
    "wof:name":"A L Enterprises",
    "wof:placetype":"venue"
},
  "geometry": {"coordinates":[-99.995318,40.868857],"type":"Point"}
}