{
  "type": "Feature",
  "properties": {
    "iso:country":"US",
    "sg:address":"825 E 8th St",
    "sg:city":"South Sioux City",
    "sg:classifiers":[
        {
            "category":"Wholesale",
            "subcategory":"Dairy",
            "type":"Manufacturing & Wholesale Goods"
        }
    ],
    "sg:phone":"+1 402 494 3823",
    "sg:postcode":"68776",
    "sg:province":"NE",
    "sg:tags":[
        "product"
    ],
    "wof:name":"Roberts Dairy Co",
    "wof:placetype":"venue"
},
  "geometry": {"coordinates":[-96.401315,42.481643],"type":"Point"}
}