{
  "type": "Feature",
  "properties": {
    "addr:full":"4831 Dodge St Omaha NE 68132",
    "addr:housenumber":"4831",
    "addr:postcode":"68132",
    "addr:street":"Dodge St",
    "iso:country":"US",
    "sg:address":"4831 Dodge St",
    "sg:city":"Omaha",
    "sg:classifiers":[
        {
            "category":"Professional",
            "subcategory":"Business Services",
            "type":"Services"
        }
    ],
    "sg:phone":"+1 402 345 7401",
    "sg:postcode":"68132",
    "sg:province":"NE",
    "sg:tags":[
        "recording",
        "studio"
    ],
    "wof:name":"Redeye Recording",
    "wof:placetype":"venue"
},
  "geometry": {"coordinates":[-95.98730999999999,41.25961],"type":"Point"}
}