{
  "type": "Feature",
  "properties": {
    "iso:country":"US",
    "sg:address":"44060 Rd 752",
    "sg:city":"Overton",
    "sg:classifiers":[
        {
            "category":"Real Estate",
            "subcategory":"Real Estate Operator",
            "type":"Services"
        }
    ],
    "sg:phone":"+1 308 324 3633",
    "sg:postcode":"68863",
    "sg:province":"NE",
    "sg:tags":[
        "property",
        "lessor"
    ],
    "wof:name":"Kearney John",
    "wof:placetype":"venue"
},
  "geometry": {"coordinates":[-99.606201,40.728989],"type":"Point"}
}