{
  "type": "Feature",
  "properties": {
    "iso:country":"US",
    "sg:address":"3536 S Locust St",
    "sg:city":"Grand Island",
    "sg:classifiers":[
        {
            "category":"Wholesale",
            "subcategory":"Machinery & Supplies",
            "type":"Manufacturing & Wholesale Goods"
        }
    ],
    "sg:phone":"+1 308 382 1300",
    "sg:postcode":"68801",
    "sg:province":"NE",
    "sg:tags":[
        "contractor"
    ],
    "wof:name":"Ditch Witch Of Nebraska Inc",
    "wof:placetype":"venue"
},
  "geometry": {"coordinates":[-98.339586,40.883936],"type":"Point"}
}