{
  "type": "Feature",
  "properties": {
    "iso:country":"US",
    "sg:address":"6918 N 63rd St",
    "sg:city":"Omaha",
    "sg:classifiers":[
        {
            "category":"Building & Trades",
            "subcategory":"Construction",
            "type":"Services"
        }
    ],
    "sg:phone":"+1 402 871 8089",
    "sg:postcode":"68152",
    "sg:province":"NE",
    "sg:tags":[
        "carpenter"
    ],
    "wof:name":"Jp Carpentry",
    "wof:placetype":"venue"
},
  "geometry": {"coordinates":[-96.010002,41.321416],"type":"Point"}
}