{
  "type": "Feature",
  "properties": {
    "addr:full":"2803 Ave I Kearney NE 68847",
    "addr:housenumber":"2803",
    "addr:postcode":"68847",
    "addr:street":"Ave I",
    "iso:country":"US",
    "sg:address":"2803 Ave I",
    "sg:city":"Kearney",
    "sg:classifiers":[
        {
            "category":"Social Services",
            "subcategory":"Child Care",
            "type":"Services"
        }
    ],
    "sg:phone":"+1 308 234 5778",
    "sg:postcode":"68847",
    "sg:province":"NE",
    "sg:tags":[
        "day"
    ],
    "wof:name":"Childrens Place Preschool",
    "wof:placetype":"venue"
},
  "geometry": {"coordinates":[-99.06959500000001,40.705136],"type":"Point"}
}