{
  "type": "Feature",
  "properties": {
    "addr:full":"2027 Dodge St Omaha NE 68102",
    "addr:housenumber":"2027",
    "addr:postcode":"68102",
    "addr:street":"Dodge St",
    "iso:country":"US",
    "sg:address":"2027 Dodge St",
    "sg:city":"Omaha",
    "sg:classifiers":[
        {
            "category":"Professional",
            "subcategory":"Computer Services",
            "type":"Services"
        }
    ],
    "sg:phone":"+1 402 346 1505",
    "sg:postcode":"68102",
    "sg:province":"NE",
    "sg:tags":[
        "consultant",
        "designer"
    ],
    "sg:website":"www.bass-inc.com",
    "wof:name":"Bass & Assoc Inc",
    "wof:placetype":"venue"
},
  "geometry": {"coordinates":[-95.944669,41.25969],"type":"Point"}
}