{
  "type": "Feature",
  "properties": {
    "iso:country":"US",
    "sg:address":"602 Park Ave",
    "sg:city":"Omaha",
    "sg:classifiers":[
        {
            "category":"Organizations",
            "subcategory":"Religious Organization",
            "type":"Services"
        }
    ],
    "sg:phone":"+1 402 345 7103",
    "sg:postcode":"68105",
    "sg:province":"NE",
    "sg:tags":[
        "church"
    ],
    "wof:name":"St John The Baptist Greek Orth",
    "wof:placetype":"venue"
},
  "geometry": {"coordinates":[-95.955915,41.253621],"type":"Point"}
}