{
  "type": "Feature",
  "properties": {
    "iso:country":"US",
    "sg:address":"3229 S 13th St",
    "sg:city":"Lincoln",
    "sg:classifiers":[
        {
            "category":"Retail",
            "subcategory":"Self-service Laundry",
            "type":"Services"
        }
    ],
    "sg:phone":"+1 402 421 2214",
    "sg:postcode":"68502",
    "sg:province":"NE",
    "sg:tags":[
        "coin"
    ],
    "wof:name":"Indian Village Laundromat",
    "wof:placetype":"venue"
},
  "geometry": {"coordinates":[-96.702898,40.779272],"type":"Point"}
}