{
  "type": "Feature",
  "properties": {
    "addr:full":"713 Central Ave Nebraska City NE 68410",
    "addr:housenumber":"713",
    "addr:postcode":"68410",
    "addr:street":"Central Ave",
    "iso:country":"US",
    "sg:address":"713 Central Ave",
    "sg:city":"Nebraska City",
    "sg:classifiers":[
        {
            "category":"Shopping",
            "subcategory":"Discount & Variety Stores",
            "type":"Retail Goods"
        }
    ],
    "sg:phone":"+1 402 873 5147",
    "sg:postcode":"68410",
    "sg:province":"NE",
    "wof:name":"LA Variedadez",
    "wof:placetype":"venue"
},
  "geometry": {"coordinates":[-95.854947,40.676519],"type":"Point"}
}