{
  "type": "Feature",
  "properties": {
    "addr:full":"4500 S 56th St Lincoln NE 68516",
    "addr:housenumber":"4500",
    "addr:postcode":"68516",
    "addr:street":"S 56Th St",
    "iso:country":"US",
    "sg:address":"4500 S 56th St",
    "sg:city":"Lincoln",
    "sg:classifiers":[
        {
            "category":"Real Estate",
            "subcategory":"Real Estate Agent",
            "type":"Services"
        }
    ],
    "sg:phone":"+1 402 489 9961",
    "sg:postcode":"68516",
    "sg:province":"NE",
    "wof:name":"S&N LLC",
    "wof:placetype":"venue"
},
  "geometry": {"coordinates":[-96.644186,40.766171],"type":"Point"}
}