{
  "type": "Feature",
  "properties": {
    "iso:country":"US",
    "sg:address":"1116 Grenoble Dr",
    "sg:city":"Bellevue",
    "sg:classifiers":[
        {
            "category":"Building & Trades",
            "subcategory":"Construction",
            "type":"Services"
        }
    ],
    "sg:phone":"+1 402 293 9625",
    "sg:postcode":"68123",
    "sg:province":"NE",
    "sg:tags":[
        "fire",
        "restoration",
        "damage"
    ],
    "wof:name":"Accurate Construction & Rstrtn",
    "wof:placetype":"venue"
},
  "geometry": {"coordinates":[-95.9271,41.092731],"type":"Point"}
}