{
  "type": "Feature",
  "properties": {
    "addr:full":"111 S 5th St Pierce NE 68767",
    "addr:housenumber":"111",
    "addr:postcode":"68767",
    "addr:street":"S 5Th St",
    "iso:country":"US",
    "sg:address":"111 S 5th St",
    "sg:city":"Pierce",
    "sg:classifiers":[
        {
            "category":"Government",
            "subcategory":"Office",
            "type":"Public Place"
        }
    ],
    "sg:phone":"+1 402 329 4215",
    "sg:postcode":"68767",
    "sg:province":"NE",
    "sg:tags":[
        "county",
        "taxation"
    ],
    "wof:name":"Pierce County Assessor",
    "wof:placetype":"venue"
},
  "geometry": {"coordinates":[-97.529894,42.198909],"type":"Point"}
}