{
  "type": "Feature",
  "properties": {
    "iso:country":"US",
    "sg:address":"915 S 54th St",
    "sg:city":"Omaha",
    "sg:classifiers":[
        {
            "category":"Building & Trades",
            "subcategory":"Locksmith",
            "type":"Services"
        }
    ],
    "sg:phone":"+1 402 881 3688",
    "sg:postcode":"68106",
    "sg:province":"NE",
    "sg:tags":[
        "key"
    ],
    "wof:name":"Aaland 24 Hour Locksmith",
    "wof:placetype":"venue"
},
  "geometry": {"coordinates":[-95.996418,41.250908],"type":"Point"}
}