{
  "type": "Feature",
  "properties": {
    "iso:country":"US",
    "sg:address":"508 Kountze Memorial Dr",
    "sg:city":"Bellevue",
    "sg:classifiers":[
        {
            "category":"Professional",
            "subcategory":"Management & Consulting",
            "type":"Services"
        }
    ],
    "sg:phone":"+1 402 291 5783",
    "sg:postcode":"68005",
    "sg:province":"NE",
    "sg:tags":[
        "advertising"
    ],
    "wof:name":"Oxford Industries Inc",
    "wof:placetype":"venue"
},
  "geometry": {"coordinates":[-95.88804,41.154665],"type":"Point"}
}