{
  "type": "Feature",
  "properties": {
    "addr:full":"3058 Golden Eagle Cir Blair NE 68008",
    "addr:housenumber":"3058",
    "addr:postcode":"68008",
    "addr:street":"Golden Eagle Cir",
    "iso:country":"US",
    "sg:address":"3058 Golden Eagle Cir",
    "sg:city":"Blair",
    "sg:classifiers":[
        {
            "category":"Banks & Credit Unions",
            "subcategory":"Bank",
            "type":"Services"
        }
    ],
    "sg:phone":"+1 402 426 7132",
    "sg:postcode":"68008",
    "sg:province":"NE",
    "wof:name":"Security National Bank",
    "wof:placetype":"venue"
},
  "geometry": {"coordinates":[-96.10821300000001,41.42155],"type":"Point"}
}