{
  "type": "Feature",
  "properties": {
    "addr:full":"291 S 5 Rd Morrill NE 69358",
    "addr:housenumber":"291;5",
    "addr:postcode":"69358",
    "addr:street":"S;Rd",
    "iso:country":"US",
    "sg:address":"291 S 5 Rd",
    "sg:city":"Morrill",
    "sg:phone":"+1 308 247 3130",
    "sg:postcode":"69358",
    "sg:province":"NE",
    "sg:tags":[
        "wheat",
        "farm",
        "corn",
        "cash",
        "crop",
        "field",
        "grain"
    ],
    "wof:name":"Lundgren Seed & Grn Producers",
    "wof:placetype":"venue"
},
  "geometry": {"coordinates":[-103.989355,42.020041],"type":"Point"}
}