{
  "type": "Feature",
  "properties": {
    "iso:country":"US",
    "sg:address":"15221 Cedar Cir",
    "sg:city":"Omaha",
    "sg:classifiers":[
        {
            "category":"Professional",
            "type":"Services"
        }
    ],
    "sg:phone":"+1 402 697 5121",
    "sg:postcode":"68144",
    "sg:province":"NE",
    "wof:name":"Caretech Inc",
    "wof:placetype":"venue"
},
  "geometry": {"coordinates":[-96.150282,41.239467],"type":"Point"}
}