{
  "type": "Feature",
  "properties": {
    "addr:full":"17030 Lakeside Hills Plz Omaha NE 68130",
    "addr:housenumber":"17030",
    "addr:postcode":"68130",
    "addr:street":"Lakeside Hills",
    "iso:country":"US",
    "sg:address":"17030 Lakeside Hills Plz",
    "sg:city":"Omaha",
    "sg:classifiers":[
        {
            "category":"Health Services",
            "subcategory":"Doctor",
            "type":"Services"
        }
    ],
    "sg:phone":"+1 402 894 9990",
    "sg:postcode":"68130",
    "sg:province":"NE",
    "sg:tags":[
        "physician",
        "surgeon"
    ],
    "wof:name":"Anesthesia Professionals",
    "wof:placetype":"venue"
},
  "geometry": {"coordinates":[-96.177238,41.23745],"type":"Point"}
}