{
  "type": "Feature",
  "properties": {
    "iso:country":"US",
    "sg:address":"849 S 16th St",
    "sg:city":"Blair",
    "sg:classifiers":[
        {
            "category":"Personal",
            "type":"Services"
        }
    ],
    "sg:phone":"+1 402 533 3448",
    "sg:postcode":"68008",
    "sg:province":"NE",
    "wof:name":"M P Services Mike Prochaska",
    "wof:placetype":"venue"
},
  "geometry": {"coordinates":[-96.136213,41.535214],"type":"Point"}
}