{
  "type": "Feature",
  "properties": {
    "iso:country":"US",
    "sg:address":"315 Laramie Ave",
    "sg:city":"Alliance",
    "sg:classifiers":[
        {
            "category":"Manufacturing",
            "subcategory":"Tools & Machinery",
            "type":"Manufacturing & Wholesale Goods"
        }
    ],
    "sg:phone":"+1 308 762 3488",
    "sg:postcode":"69301",
    "sg:province":"NE",
    "sg:tags":[
        "windmill"
    ],
    "wof:name":"Bernie's Supply Ace Hardware",
    "wof:placetype":"venue"
},
  "geometry": {"coordinates":[-102.872135,42.097156],"type":"Point"}
}