{
  "type": "Feature",
  "properties": {
    "iso:country":"US",
    "sg:address":"5610 Highland Dr",
    "sg:city":"Papillion",
    "sg:classifiers":[
        {
            "category":"Freight",
            "type":"Transportation"
        }
    ],
    "sg:phone":"+1 402 291 2490",
    "sg:postcode":"68133",
    "sg:province":"NE",
    "sg:tags":[
        "operator",
        "local",
        "trucking"
    ],
    "wof:name":"Jims Mvg & Delivery Co Inc",
    "wof:placetype":"venue"
},
  "geometry": {"coordinates":[-96.00100999999999,41.146532],"type":"Point"}
}