{
  "type": "Feature",
  "properties": {
    "addr:full":"137 N Brown Ave Minden NE 68959",
    "addr:housenumber":"137",
    "addr:postcode":"68959",
    "addr:street":"N Brown Ave",
    "iso:country":"US",
    "sg:address":"137 N Brown Ave",
    "sg:city":"Minden",
    "sg:classifiers":[
        {
            "category":"Government",
            "subcategory":"Office",
            "type":"Public Place"
        }
    ],
    "sg:phone":"+1 308 832 1523",
    "sg:postcode":"68959",
    "sg:province":"NE",
    "sg:tags":[
        "agricultural",
        "regulation",
        "marketing"
    ],
    "wof:name":"Two Farm Marketing",
    "wof:placetype":"venue"
},
  "geometry": {"coordinates":[-98.95184399999999,40.496314],"type":"Point"}
}