{
  "type": "Feature",
  "properties": {
    "addr:full":"710 S 13th St Norfolk NE 68701",
    "addr:housenumber":"710",
    "addr:postcode":"68701",
    "addr:street":"S 13Th St",
    "iso:country":"US",
    "sg:address":"710 S 13th St",
    "sg:city":"Norfolk",
    "sg:classifiers":[
        {
            "category":"Cinema",
            "subcategory":"Movie Rental",
            "type":"Entertainment"
        }
    ],
    "sg:phone":"+1 402 844 3964",
    "sg:postcode":"68701",
    "sg:province":"NE",
    "sg:tags":[
        "leasing",
        "video",
        "disc",
        "tape"
    ],
    "wof:name":"Blockbuster Video",
    "wof:placetype":"venue"
},
  "geometry": {"coordinates":[-97.426591,42.025045],"type":"Point"}
}