{
  "type": "Feature",
  "properties": {
    "iso:country":"US",
    "sg:address":"12100 Adams St",
    "sg:city":"Lincoln",
    "sg:classifiers":[
        {
            "category":"Organizations",
            "subcategory":"Religious Organization",
            "type":"Services"
        }
    ],
    "sg:phone":"+1 402 467 1526",
    "sg:postcode":"68527",
    "sg:province":"NE",
    "sg:tags":[
        "church"
    ],
    "wof:name":"First Mennonite Church",
    "wof:placetype":"venue"
},
  "geometry": {"coordinates":[-96.54853199999999,40.842093],"type":"Point"}
}