{
  "type": "Feature",
  "properties": {
    "addr:full":"7603 State Hwy 50 Weeping Water NE 68463",
    "addr:housenumber":"7603",
    "addr:postcode":"68463",
    "addr:street":"State Hwy 50 Weeping",
    "iso:country":"US",
    "sg:address":"7603 State Hwy 50",
    "sg:city":"Weeping Water",
    "sg:classifiers":[
        {
            "category":"Restaurant",
            "type":"Food & Drink"
        }
    ],
    "sg:phone":"+1 402 267 7777",
    "sg:postcode":"68463",
    "sg:province":"NE",
    "wof:name":"Hilltop Fill Stop",
    "wof:placetype":"venue"
},
  "geometry": {"coordinates":[-96.17809200000001,40.903339],"type":"Point"}
}