{
  "type": "Feature",
  "properties": {
    "addr:full":"1209 Nebraska Ave Arapahoe NE 68922",
    "addr:housenumber":"1209",
    "addr:postcode":"68922",
    "addr:street":"Nebraska Ave",
    "iso:country":"US",
    "sg:address":"1209 Nebraska Ave",
    "sg:city":"Arapahoe",
    "sg:classifiers":[
        {
            "category":"Freight",
            "type":"Transportation"
        }
    ],
    "sg:phone":"+1 308 962 7630",
    "sg:postcode":"68922",
    "sg:province":"NE",
    "sg:tags":[
        "special"
    ],
    "wof:name":"Arapahoe Storage",
    "wof:placetype":"venue"
},
  "geometry": {"coordinates":[-99.89787800000001,40.313392],"type":"Point"}
}