{
  "type": "Feature",
  "properties": {
    "iso:country":"US",
    "sg:address":"1206 N Monroe St",
    "sg:city":"Papillion",
    "sg:classifiers":[
        {
            "category":"Retail",
            "subcategory":"Auto Repair",
            "type":"Services"
        }
    ],
    "sg:phone":"+1 402 731 5757",
    "sg:postcode":"68046",
    "sg:province":"NE",
    "sg:tags":[
        "a",
        "as",
        "towing",
        "operates"
    ],
    "wof:name":"Daves Complete Towing",
    "wof:placetype":"venue"
},
  "geometry": {"coordinates":[-96.040238,41.172623],"type":"Point"}
}