{
  "type": "Feature",
  "properties": {
    "addr:full":"23301 Cary Rd Gretna NE 68028",
    "addr:postcode":"23301;68028",
    "addr:street":"Cary Rd",
    "iso:country":"US",
    "sg:address":"23301 Cary Rd",
    "sg:city":"Gretna",
    "sg:classifiers":[
        {
            "category":"Building & Trades",
            "subcategory":"Electrical",
            "type":"Services"
        }
    ],
    "sg:phone":"+1 402 332 4142",
    "sg:postcode":"68028",
    "sg:province":"NE",
    "sg:tags":[
        "electrical",
        "electric",
        "contractor"
    ],
    "wof:name":"Canon Electric Inc",
    "wof:placetype":"venue"
},
  "geometry": {"coordinates":[-96.27917600000001,41.172059],"type":"Point"}
}