{
  "type": "Feature",
  "properties": {
    "iso:country":"US",
    "sg:address":"535 N 87th St",
    "sg:city":"Omaha",
    "sg:classifiers":[
        {
            "category":"Health Services",
            "subcategory":"Doctor",
            "type":"Services"
        }
    ],
    "sg:phone":"+1 402 393 2300",
    "sg:postcode":"68114",
    "sg:province":"NE",
    "wof:name":"Conway Kelly Richard DDS",
    "wof:placetype":"venue"
},
  "geometry": {"coordinates":[-96.047656,41.264537],"type":"Point"}
}