{
  "type": "Feature",
  "properties": {
    "iso:country":"US",
    "sg:address":"157 4th St",
    "sg:city":"Ulysses",
    "sg:classifiers":[
        {
            "category":"Real Estate",
            "subcategory":"Real Estate Agent",
            "type":"Services"
        }
    ],
    "sg:phone":"+1 402 549 2358",
    "sg:postcode":"68669",
    "sg:province":"NE",
    "sg:tags":[
        "cooperative"
    ],
    "wof:name":"United Farmer's Co Op",
    "wof:placetype":"venue"
},
  "geometry": {"coordinates":[-97.20208,41.072737],"type":"Point"}
}