{
  "type": "Feature",
  "properties": {
    "addr:full":"506 Perry St Odell NE 68415",
    "addr:housenumber":"506",
    "addr:postcode":"68415",
    "addr:street":"Perry St",
    "iso:country":"US",
    "sg:address":"506 Perry St",
    "sg:city":"Odell",
    "sg:classifiers":[
        {
            "category":"Education",
            "subcategory":"School",
            "type":"Public Place"
        }
    ],
    "sg:phone":"+1 402 766 3710",
    "sg:postcode":"68415",
    "sg:province":"NE",
    "wof:name":"Diller Odell Jr-Sr High School",
    "wof:placetype":"venue"
},
  "geometry": {"coordinates":[-96.80305799999999,40.056011],"type":"Point"}
}