{
  "type": "Feature",
  "properties": {
    "iso:country":"US",
    "sg:address":"17913 Shirley Cir",
    "sg:city":"Omaha",
    "sg:classifiers":[
        {
            "category":"Personal",
            "subcategory":"Beauty Salon",
            "type":"Services"
        }
    ],
    "sg:phone":"+1 402 697 1431",
    "sg:postcode":"68130",
    "sg:province":"NE",
    "sg:tags":[
        "pedicurist",
        "manicurist"
    ],
    "wof:name":"Design of Times Salon Day Spa",
    "wof:placetype":"venue"
},
  "geometry": {"coordinates":[-96.195243,41.24168],"type":"Point"}
}