{
  "type": "Feature",
  "properties": {
    "addr:full":"3523 31st St Columbus NE 68601",
    "addr:housenumber":"3523",
    "addr:postcode":"68601",
    "addr:street":"31St St",
    "iso:country":"US",
    "sg:address":"3523 31st St",
    "sg:city":"Columbus",
    "sg:classifiers":[
        {
            "category":"Building & Trades",
            "subcategory":"Construction",
            "type":"Services"
        }
    ],
    "sg:phone":"+1 402 563 2047",
    "sg:postcode":"68601",
    "sg:province":"NE",
    "sg:tags":[
        "general",
        "contractor"
    ],
    "wof:name":"R D Long Construction",
    "wof:placetype":"venue"
},
  "geometry": {"coordinates":[-97.372469,41.446408],"type":"Point"}
}