{
  "type": "Feature",
  "properties": {
    "iso:country":"US",
    "sg:address":"527 Chestnut St",
    "sg:city":"Potter",
    "sg:classifiers":[
        {
            "category":"Social Services",
            "type":"Services"
        }
    ],
    "sg:phone":"+1 308 879 4216",
    "sg:postcode":"69156",
    "sg:province":"NE",
    "sg:tags":[
        "senior",
        "citizen"
    ],
    "wof:name":"Senior Citizens Ctr",
    "wof:placetype":"venue"
},
  "geometry": {"coordinates":[-103.315501,41.218594],"type":"Point"}
}