{
  "type": "Feature",
  "properties": {
    "iso:country":"US",
    "sg:address":"1326 Grant St",
    "sg:city":"Beatrice",
    "sg:classifiers":[
        {
            "category":"Organizations",
            "subcategory":"Religious Organization",
            "type":"Services"
        }
    ],
    "sg:phone":"+1 402 228 1923",
    "sg:postcode":"68310",
    "sg:province":"NE",
    "wof:name":"Bible Baptist Church",
    "wof:placetype":"venue"
},
  "geometry": {"coordinates":[-96.735868,40.270649],"type":"Point"}
}