{
  "type": "Feature",
  "properties": {
    "iso:country":"US",
    "sg:address":"1314 S 119th St",
    "sg:city":"Omaha",
    "sg:classifiers":[
        {
            "category":"Food & Beverages",
            "subcategory":"Bakery",
            "type":"Retail Goods"
        }
    ],
    "sg:phone":"+1 402 778 9296",
    "sg:postcode":"68144",
    "sg:province":"NE",
    "sg:tags":[
        "baker"
    ],
    "wof:name":"Bread Oven",
    "wof:placetype":"venue"
},
  "geometry": {"coordinates":[-96.098343,41.245653],"type":"Point"}
}