{
  "type": "Feature",
  "properties": {
    "iso:country":"US",
    "sg:address":"320 N 20th St",
    "sg:city":"Omaha",
    "sg:classifiers":[
        {
            "category":"Education",
            "subcategory":"University",
            "type":"Public Place"
        }
    ],
    "sg:phone":"+1 402 546 6300",
    "sg:postcode":"68178",
    "sg:province":"NE",
    "sg:tags":[
        "college"
    ],
    "sg:website":"www.creighton.edu",
    "wof:name":"Creighton University",
    "wof:placetype":"venue"
},
  "geometry": {"coordinates":[-95.94265799999999,41.261787],"type":"Point"}
}