{
  "type": "Feature",
  "properties": {
    "iso:country":"US",
    "sg:address":"35510 A St",
    "sg:city":"Avoca",
    "sg:classifiers":[
        {
            "category":"Farming",
            "subcategory":"Livestock Farm",
            "type":"Manufacturing & Wholesale Goods"
        }
    ],
    "sg:phone":"+1 402 275 3348",
    "sg:postcode":"68307",
    "sg:province":"NE",
    "sg:tags":[
        "corn",
        "beef",
        "feedlot",
        "cattle"
    ],
    "wof:name":"Allen Ahuschild",
    "wof:placetype":"venue"
},
  "geometry": {"coordinates":[-96.197678,40.798625],"type":"Point"}
}