{
  "type": "Feature",
  "properties": {
    "addr:full":"1845 Grove Ave Crete NE 68333",
    "addr:housenumber":"1845",
    "addr:postcode":"68333",
    "addr:street":"Grove Ave",
    "iso:country":"US",
    "sg:address":"1845 Grove Ave",
    "sg:city":"Crete",
    "sg:classifiers":[
        {
            "category":"Food & Beverages",
            "subcategory":"Groceries & Convenience Stores",
            "type":"Retail Goods"
        }
    ],
    "sg:phone":"+1 402 826 4799",
    "sg:postcode":"68333",
    "sg:province":"NE",
    "wof:name":"C-Mart",
    "wof:placetype":"venue"
},
  "geometry": {"coordinates":[-96.954365,40.630373],"type":"Point"}
}