{
  "type": "Feature",
  "properties": {
    "addr:full":"229 S Ash St Gordon NE 69343",
    "addr:housenumber":"229",
    "addr:postcode":"69343",
    "addr:street":"S Ash St",
    "iso:country":"US",
    "sg:address":"229 S Ash St",
    "sg:city":"Gordon",
    "sg:classifiers":[
        {
            "category":"Retail",
            "subcategory":"Repair Shop",
            "type":"Services"
        }
    ],
    "sg:phone":"+1 308 282 2222",
    "sg:postcode":"69343",
    "sg:province":"NE",
    "sg:tags":[
        "tractor"
    ],
    "wof:name":"Your Place Or Mine Repair",
    "wof:placetype":"venue"
},
  "geometry": {"coordinates":[-102.20064000000001,42.802032],"type":"Point"}
}