{
  "type": "Feature",
  "properties": {
    "iso:country":"US",
    "sg:address":"412 E Hynes Ave",
    "sg:city":"Oneill",
    "sg:classifiers":[
        {
            "category":"Farming",
            "subcategory":"Livestock Farm",
            "type":"Manufacturing & Wholesale Goods"
        }
    ],
    "sg:phone":"+1 402 336 4273",
    "sg:postcode":"68763",
    "sg:province":"NE",
    "sg:tags":[
        "beef",
        "feedlot",
        "cattle"
    ],
    "wof:name":"James Gotschall",
    "wof:placetype":"venue"
},
  "geometry": {"coordinates":[-98.64781600000001,42.465031],"type":"Point"}
}