{
  "type": "Feature",
  "properties": {
    "iso:country":"US",
    "sg:address":"42045 Elm Island Rd",
    "sg:city":"Gibbon",
    "sg:classifiers":[
        {
            "category":"Wholesale",
            "subcategory":"Scrap",
            "type":"Manufacturing & Wholesale Goods"
        }
    ],
    "sg:phone":"+1 308 468 5563",
    "sg:postcode":"68840",
    "sg:province":"NE",
    "sg:tags":[
        "material"
    ],
    "wof:name":"Midlands Iron & Metals",
    "wof:placetype":"venue"
},
  "geometry": {"coordinates":[-98.914143,40.661991],"type":"Point"}
}