{
  "type": "Feature",
  "properties": {
    "addr:full":"509 Martin Dr Bellevue NE 68005",
    "addr:housenumber":"509",
    "addr:postcode":"68005",
    "addr:street":"Martin Dr",
    "iso:country":"US",
    "sg:address":"509 Martin Dr",
    "sg:city":"Bellevue",
    "sg:classifiers":[
        {
            "category":"Health Services",
            "subcategory":"Doctor",
            "type":"Services"
        }
    ],
    "sg:phone":"+1 402 991 3497",
    "sg:postcode":"68005",
    "sg:province":"NE",
    "sg:tags":[
        "medical"
    ],
    "wof:name":"Peter T Silberstein Dr MD",
    "wof:placetype":"venue"
},
  "geometry": {"coordinates":[-95.90754800000001,41.163275],"type":"Point"}
}