{
  "type": "Feature",
  "properties": {
    "addr:full":"13207 N 72nd St Omaha NE 68122",
    "addr:housenumber":"13207",
    "addr:postcode":"68122",
    "addr:street":"N 72Nd St",
    "iso:country":"US",
    "sg:address":"13207 N 72nd St",
    "sg:city":"Omaha",
    "sg:classifiers":[
        {
            "category":"Building & Trades",
            "subcategory":"Construction",
            "type":"Services"
        }
    ],
    "sg:phone":"+1 402 573 1783",
    "sg:postcode":"68122",
    "sg:province":"NE",
    "sg:tags":[
        "contractor"
    ],
    "wof:name":"Wendland Masonry Restoration",
    "wof:placetype":"venue"
},
  "geometry": {"coordinates":[-96.023731,41.378816],"type":"Point"}
}