{
  "type": "Feature",
  "properties": {
    "addr:full":"108 W 2nd St Kennard NE 68034",
    "addr:housenumber":"108",
    "addr:postcode":"68034",
    "addr:street":"W 2Nd St",
    "iso:country":"US",
    "sg:address":"108 W 2nd St",
    "sg:city":"Kennard",
    "sg:classifiers":[
        {
            "category":"Building & Trades",
            "subcategory":"Construction",
            "type":"Services"
        }
    ],
    "sg:phone":"+1 402 427 7419",
    "sg:postcode":"68034",
    "sg:province":"NE",
    "sg:tags":[
        "roofing",
        "contractor"
    ],
    "wof:name":"Larry's Roofing",
    "wof:placetype":"venue"
},
  "geometry": {"coordinates":[-96.201757,41.472889],"type":"Point"}
}