{
  "type": "Feature",
  "properties": {
    "addr:full":"3043 N 70th St Lincoln NE 68507",
    "addr:housenumber":"3043",
    "addr:postcode":"68507",
    "addr:street":"N 70Th St",
    "iso:country":"US",
    "sg:address":"3043 N 70th St",
    "sg:city":"Lincoln",
    "sg:classifiers":[
        {
            "category":"Retail",
            "subcategory":"Portrait Studio",
            "type":"Services"
        }
    ],
    "sg:phone":"+1 402 498 0206",
    "sg:postcode":"68507",
    "sg:province":"NE",
    "sg:tags":[
        "photographer"
    ],
    "sg:website":"www.lifetouch.com",
    "wof:name":"Lifetouch National Schl Studio",
    "wof:placetype":"venue"
},
  "geometry": {"coordinates":[-96.624983,40.843323],"type":"Point"}
}