{
  "type": "Feature",
  "properties": {
    "iso:country":"US",
    "sg:address":"327 Douglas Ave",
    "sg:city":"Yankton",
    "sg:classifiers":[
        {
            "category":"Health Services",
            "subcategory":"Chiropractor",
            "type":"Services"
        }
    ],
    "sg:phone":"+1 605 665 8365",
    "sg:postcode":"57078",
    "sg:province":"NE",
    "wof:name":"Stevens Chiropractic Clinic",
    "wof:placetype":"venue"
},
  "geometry": {"coordinates":[-97.392167,42.870727],"type":"Point"}
}