{
  "type": "Feature",
  "properties": {
    "iso:country":"US",
    "sg:address":"115 Central Ave",
    "sg:city":"Kearney",
    "sg:classifiers":[
        {
            "category":"Building & Trades",
            "subcategory":"Plumbing",
            "type":"Services"
        }
    ],
    "sg:phone":"+1 308 338 8080",
    "sg:postcode":"68847",
    "sg:province":"NE",
    "sg:tags":[
        "contractor"
    ],
    "sg:website":"www.siemenscombustioncontrols.com",
    "wof:name":"Siemens Building Technologies",
    "wof:placetype":"venue"
},
  "geometry": {"coordinates":[-99.082393,40.67155],"type":"Point"}
}