{
  "type": "Feature",
  "properties": {
    "iso:country":"US",
    "sg:address":"509 E 14th St",
    "sg:city":"Bridgeport",
    "sg:classifiers":[
        {
            "category":"Building & Trades",
            "subcategory":"Construction",
            "type":"Services"
        }
    ],
    "sg:phone":"+1 308 262 1929",
    "sg:postcode":"69336",
    "sg:province":"NE",
    "sg:tags":[
        "road",
        "contractor"
    ],
    "wof:name":"Roads Dept",
    "wof:placetype":"venue"
},
  "geometry": {"coordinates":[-103.093965,41.66119],"type":"Point"}
}