{
  "type": "Feature",
  "properties": {
    "iso:country":"US",
    "sg:address":"1130 N Bell St",
    "sg:city":"Fremont",
    "sg:classifiers":[
        {
            "category":"Wholesale",
            "subcategory":"Toys & Hobbies",
            "type":"Manufacturing & Wholesale Goods"
        }
    ],
    "sg:phone":"+1 402 727 7348",
    "sg:postcode":"68025",
    "sg:province":"NE",
    "wof:name":"Countree Crafts",
    "wof:placetype":"venue"
},
  "geometry": {"coordinates":[-96.483429,41.440099],"type":"Point"}
}