{
  "type": "Feature",
  "properties": {
    "iso:country":"US",
    "sg:address":"307 Hardy St",
    "sg:city":"St Edward",
    "sg:classifiers":[
        {
            "category":"Retail",
            "subcategory":"Auto Repair",
            "type":"Services"
        }
    ],
    "sg:phone":"+1 402 678 2677",
    "sg:postcode":"68660",
    "sg:province":"NE",
    "sg:tags":[
        "repairing",
        "automobile"
    ],
    "wof:name":"Matson Auto",
    "wof:placetype":"venue"
},
  "geometry": {"coordinates":[-97.865784,41.574939],"type":"Point"}
}