{
  "type": "Feature",
  "properties": {
    "iso:country":"US",
    "sg:address":"23 E 16th St",
    "sg:city":"Scottsbluff",
    "sg:classifiers":[
        {
            "category":"Home & Garden",
            "subcategory":"Building Materials",
            "type":"Retail Goods"
        }
    ],
    "sg:phone":"+1 308 632 2314",
    "sg:postcode":"69361",
    "sg:province":"NE",
    "sg:tags":[
        "paint"
    ],
    "wof:name":"Diamond Vogel Paint 784",
    "wof:placetype":"venue"
},
  "geometry": {"coordinates":[-103.66220199999999,41.86236],"type":"Point"}
}