{
  "type": "Feature",
  "properties": {
    "iso:country":"US",
    "sg:address":"650 J St",
    "sg:city":"Lincoln",
    "sg:classifiers":[
        {
            "category":"Insurance",
            "subcategory":"Insurance Agent",
            "type":"Services"
        }
    ],
    "sg:phone":"+1 402 475 7553",
    "sg:postcode":"68508",
    "sg:province":"NE",
    "wof:name":"First International Benefits",
    "wof:placetype":"venue"
},
  "geometry": {"coordinates":[-96.712052,40.808169],"type":"Point"}
}