{
  "type": "Feature",
  "properties": {
    "addr:full":"11130 Q St Omaha NE 68137",
    "addr:housenumber":"11130",
    "addr:postcode":"68137",
    "addr:street":"Q St",
    "iso:country":"US",
    "sg:address":"11130 Q St",
    "sg:city":"Omaha",
    "sg:classifiers":[
        {
            "category":"Social Services",
            "type":"Services"
        }
    ],
    "sg:phone":"+1 402 597 2327",
    "sg:postcode":"68137",
    "sg:province":"NE",
    "sg:tags":[
        "counselor",
        "marriage",
        "family"
    ],
    "wof:name":"Spence Counseling Ctr",
    "wof:placetype":"venue"
},
  "geometry": {"coordinates":[-96.086468,41.205406],"type":"Point"}
}