{
  "type": "Feature",
  "properties": {
    "iso:country":"US",
    "sg:address":"615 E 3rd St",
    "sg:city":"Paxton",
    "sg:classifiers":[
        {
            "category":"Wholesale",
            "subcategory":"Farm Supplies",
            "type":"Manufacturing & Wholesale Goods"
        }
    ],
    "sg:phone":"+1 308 239 4373",
    "sg:postcode":"69155",
    "sg:province":"NE",
    "sg:tags":[
        "feed"
    ],
    "wof:name":"KRAB Inc Feedlot",
    "wof:placetype":"venue"
},
  "geometry": {"coordinates":[-101.349569,41.125389],"type":"Point"}
}