{
  "type": "Feature",
  "properties": {
    "iso:country":"US",
    "sg:address":"2506 S 32nd Ave",
    "sg:city":"Omaha",
    "sg:classifiers":[
        {
            "category":"Manufacturing",
            "subcategory":"Signs",
            "type":"Manufacturing & Wholesale Goods"
        }
    ],
    "sg:phone":"+1 402 341 0331",
    "sg:postcode":"68105",
    "sg:province":"NE",
    "sg:tags":[
        "specialty",
        "mfg"
    ],
    "wof:name":"J Design & Sign",
    "wof:placetype":"venue"
},
  "geometry": {"coordinates":[-95.960404,41.234813],"type":"Point"}
}