{
  "type": "Feature",
  "properties": {
    "addr:full":"3006 Rd 73 Potter NE 69156",
    "addr:postcode":"3006;69156",
    "addr:street":"Rd 73 Potter Ne",
    "iso:country":"US",
    "sg:address":"3006 Rd 73",
    "sg:city":"Potter",
    "sg:classifiers":[
        {
            "category":"Building & Trades",
            "subcategory":"Cleaning & Sanitation",
            "type":"Services"
        }
    ],
    "sg:phone":"+1 308 879 4523",
    "sg:postcode":"69156",
    "sg:province":"NE",
    "sg:tags":[
        "maintenance"
    ],
    "wof:name":"Air Quality Team",
    "wof:placetype":"venue"
},
  "geometry": {"coordinates":[-103.35682199999999,41.213154],"type":"Point"}
}