{
  "type": "Feature",
  "properties": {
    "addr:full":"108 W 16th St Falls City NE 68355",
    "addr:housenumber":"108",
    "addr:postcode":"68355",
    "addr:street":"W 16Th St",
    "iso:country":"US",
    "sg:address":"108 W 16th St",
    "sg:city":"Falls City",
    "sg:classifiers":[
        {
            "category":"Personal",
            "subcategory":"Beauty Salon",
            "type":"Services"
        }
    ],
    "sg:phone":"+1 402 245 6151",
    "sg:postcode":"68355",
    "sg:province":"NE",
    "wof:name":"Hair Expressions",
    "wof:placetype":"venue"
},
  "geometry": {"coordinates":[-95.603972,40.060807],"type":"Point"}
}