{
  "type": "Feature",
  "properties": {
    "addr:full":"8306 S Cherrywood Dr Lincoln NE 68510",
    "addr:housenumber":"8306",
    "addr:postcode":"68510",
    "addr:street":"S Cherrywood Dr",
    "iso:country":"US",
    "sg:address":"8306 S Cherrywood Dr",
    "sg:city":"Lincoln",
    "sg:classifiers":[
        {
            "category":"Autos & Motor Vehicles",
            "subcategory":"Auto Supplies",
            "type":"Retail Goods"
        }
    ],
    "sg:phone":"+1 402 489 5987",
    "sg:postcode":"68510",
    "sg:province":"NE",
    "sg:tags":[
        "home",
        "store"
    ],
    "wof:name":"Classic Truck Accessories",
    "wof:placetype":"venue"
},
  "geometry": {"coordinates":[-96.60848900000001,40.810497],"type":"Point"}
}