{
  "type": "Feature",
  "properties": {
    "iso:country":"US",
    "sg:address":"43485 Rd 757",
    "sg:city":"Lexington",
    "sg:classifiers":[
        {
            "category":"Social Services",
            "subcategory":"Child Care",
            "type":"Services"
        }
    ],
    "sg:phone":"+1 308 324 3507",
    "sg:postcode":"68850",
    "sg:province":"NE",
    "sg:tags":[
        "day"
    ],
    "wof:name":"Vance Rosella Day Care",
    "wof:placetype":"venue"
},
  "geometry": {"coordinates":[-99.71297199999999,40.800902],"type":"Point"}
}