{
  "type": "Feature",
  "properties": {
    "addr:full":"204 Broadway St Fullerton NE 68638",
    "addr:housenumber":"204",
    "addr:postcode":"68638",
    "addr:street":"Broadway St",
    "iso:country":"US",
    "sg:address":"204 Broadway St",
    "sg:city":"Fullerton",
    "sg:classifiers":[
        {
            "category":"Organizations",
            "subcategory":"Membership Organization",
            "type":"Services"
        }
    ],
    "sg:phone":"+1 308 536 2351",
    "sg:postcode":"68638",
    "sg:province":"NE",
    "wof:name":"Legionnaire Club",
    "wof:placetype":"venue"
},
  "geometry": {"coordinates":[-97.96888199999999,41.364402],"type":"Point"}
}