{
  "type": "Feature",
  "properties": {
    "iso:country":"US",
    "sg:address":"602 Broad St",
    "sg:city":"Dalton",
    "sg:classifiers":[
        {
            "category":"Retail",
            "subcategory":"Auto Repair",
            "type":"Services"
        }
    ],
    "sg:phone":"+1 308 377 2522",
    "sg:postcode":"69131",
    "sg:province":"NE",
    "sg:tags":[
        "repairing",
        "automobile"
    ],
    "wof:name":"FEC Farmers Elevator Co",
    "wof:placetype":"venue"
},
  "geometry": {"coordinates":[-102.97429099999999,41.406067],"type":"Point"}
}