{
  "type": "Feature",
  "properties": {
    "iso:country":"US",
    "sg:address":"6600 Rocky Ridge Rd",
    "sg:city":"Lincoln",
    "sg:classifiers":[
        {
            "category":"Building & Trades",
            "subcategory":"Construction",
            "type":"Services"
        }
    ],
    "sg:phone":"+1 402 488 3759",
    "sg:postcode":"68526",
    "sg:province":"NE",
    "sg:tags":[
        "hanging",
        "contractor"
    ],
    "wof:name":"DK Painters",
    "wof:placetype":"venue"
},
  "geometry": {"coordinates":[-96.57152000000001,40.743336],"type":"Point"}
}