{
  "type": "Feature",
  "properties": {
    "addr:full":"1417 S 133rd St Omaha NE 68144",
    "addr:housenumber":"1417",
    "addr:postcode":"68144",
    "addr:street":"S 133Rd St",
    "iso:country":"US",
    "sg:address":"1417 S 133rd St",
    "sg:city":"Omaha",
    "sg:classifiers":[
        {
            "category":"Retail",
            "subcategory":"Portrait Studio",
            "type":"Services"
        }
    ],
    "sg:phone":"+1 402 330 7649",
    "sg:postcode":"68144",
    "sg:province":"NE",
    "sg:tags":[
        "photo"
    ],
    "wof:name":"Regal Photography",
    "wof:placetype":"venue"
},
  "geometry": {"coordinates":[-96.12106900000001,41.245406],"type":"Point"}
}