{
  "type": "Feature",
  "properties": {
    "addr:full":"5707 S 122nd St Omaha NE 68137",
    "addr:housenumber":"5707",
    "addr:postcode":"68137",
    "addr:street":"S 122Nd St",
    "iso:country":"US",
    "sg:address":"5707 S 122nd St",
    "sg:city":"Omaha",
    "sg:classifiers":[
        {
            "category":"Building & Trades",
            "subcategory":"Construction",
            "type":"Services"
        }
    ],
    "sg:phone":"+1 402 895 4537",
    "sg:postcode":"68137",
    "sg:province":"NE",
    "sg:tags":[
        "real",
        "life",
        "house",
        "carrier",
        "insurance",
        "es"
    ],
    "wof:name":"Tl Enterprises",
    "wof:placetype":"venue"
},
  "geometry": {"coordinates":[-96.102918,41.200606],"type":"Point"}
}