{
  "type": "Feature",
  "properties": {
    "iso:country":"US",
    "sg:address":"5232 Goldenrod Cir",
    "sg:city":"Lincoln",
    "sg:classifiers":[
        {
            "category":"Social Services",
            "subcategory":"Child Care",
            "type":"Services"
        }
    ],
    "sg:phone":"+1 402 423 4532",
    "sg:postcode":"68512",
    "sg:province":"NE",
    "sg:tags":[
        "day"
    ],
    "wof:name":"Lori Muller",
    "wof:placetype":"venue"
},
  "geometry": {"coordinates":[-96.691073,40.76156],"type":"Point"}
}