{
  "type": "Feature",
  "properties": {
    "iso:country":"US",
    "sg:address":"14345 Fort St",
    "sg:city":"Omaha",
    "sg:classifiers":[
        {
            "category":"Insurance",
            "subcategory":"Insurance Agent",
            "type":"Services"
        },
        {
            "category":"Insurance",
            "subcategory":"Hazard Insurance",
            "type":"Services"
        },
        {
            "category":"Insurance",
            "subcategory":"Title Insurance",
            "type":"Services"
        }
    ],
    "sg:phone":"+1 402 445 6117",
    "sg:postcode":"68164",
    "sg:province":"NE",
    "sg:tags":[
        "auto",
        "homeowner"
    ],
    "sg:website":"http://apps.amfam.com/agentlocator/?sourceid=yp3",
    "wof:name":"American Family Insurance- Travis Prater",
    "wof:placetype":"venue"
},
  "geometry": {"coordinates":[-96.138191,41.306591],"type":"Point"}
}