{
  "type": "Feature",
  "properties": {
    "iso:country":"US",
    "sg:address":"2340 Paul St",
    "sg:city":"Omaha",
    "sg:classifiers":[
        {
            "category":"Retail",
            "subcategory":"Auto Repair",
            "type":"Services"
        }
    ],
    "sg:phone":"+1 402 344 2788",
    "sg:postcode":"68102",
    "sg:province":"NE",
    "sg:tags":[
        "body",
        "shop",
        "painting",
        "automobile"
    ],
    "wof:name":"Jobosh II",
    "wof:placetype":"venue"
},
  "geometry": {"coordinates":[-95.946198,41.271999],"type":"Point"}
}