{
  "type": "Feature",
  "properties": {
    "iso:country":"US",
    "sg:address":"7610 S 130th St",
    "sg:city":"Omaha",
    "sg:classifiers":[
        {
            "category":"Building & Trades",
            "subcategory":"Construction",
            "type":"Services"
        }
    ],
    "sg:phone":"+1 402 896 9578",
    "sg:postcode":"68138",
    "sg:province":"NE",
    "sg:tags":[
        "residential",
        "nonresidential"
    ],
    "wof:name":"Voller Contracting",
    "wof:placetype":"venue"
},
  "geometry": {"coordinates":[-96.118551,41.184525],"type":"Point"}
}