{
  "type": "Feature",
  "properties": {
    "iso:country":"US",
    "sg:address":"2254 30th Ave",
    "sg:city":"Columbus",
    "sg:classifiers":[
        {
            "category":"Personal",
            "subcategory":"Beauty Salon",
            "type":"Services"
        }
    ],
    "sg:phone":"+1 402 564 6424",
    "sg:postcode":"68601",
    "sg:province":"NE",
    "sg:tags":[
        "shop"
    ],
    "wof:name":"Dee Mar Beauty Salon",
    "wof:placetype":"venue"
},
  "geometry": {"coordinates":[-97.363692,41.438221],"type":"Point"}
}