{
  "type": "Feature",
  "properties": {
    "addr:full":"5421 S 96th St Omaha NE 68127",
    "addr:housenumber":"5421",
    "addr:postcode":"68127",
    "addr:street":"S 96Th St",
    "iso:country":"US",
    "sg:address":"5421 S 96th St",
    "sg:city":"Omaha",
    "sg:classifiers":[
        {
            "category":"Food & Beverages",
            "subcategory":"Groceries & Convenience Stores",
            "type":"Retail Goods"
        }
    ],
    "sg:phone":"+1 402 331 0144",
    "sg:postcode":"68127",
    "sg:province":"NE",
    "wof:name":"Quik Pik",
    "wof:placetype":"venue"
},
  "geometry": {"coordinates":[-96.061913,41.204311],"type":"Point"}
}