{
  "type": "Feature",
  "properties": {
    "iso:country":"US",
    "sg:address":"825 N 16th Rd",
    "sg:city":"Unadilla",
    "sg:classifiers":[
        {
            "category":"Real Estate",
            "subcategory":"Real Estate Operator",
            "type":"Services"
        }
    ],
    "sg:phone":"+1 402 828 4335",
    "sg:postcode":"68454",
    "sg:province":"NE",
    "sg:tags":[
        "land",
        "rent",
        "out"
    ],
    "wof:name":"Dale Lamb",
    "wof:placetype":"venue"
},
  "geometry": {"coordinates":[-96.31213200000001,40.725839],"type":"Point"}
}