{
  "type": "Feature",
  "properties": {
    "addr:full":"9020 Q St Omaha NE 68127",
    "addr:housenumber":"9020",
    "addr:postcode":"68127",
    "addr:street":"Q St",
    "iso:country":"US",
    "sg:address":"9020 Q St",
    "sg:city":"Omaha",
    "sg:classifiers":[
        {
            "category":"Organizations",
            "subcategory":"Religious Organization",
            "type":"Services"
        }
    ],
    "sg:phone":"+1 402 592 8005",
    "sg:postcode":"68127",
    "sg:province":"NE",
    "wof:name":"West Omaha School Association",
    "wof:placetype":"venue"
},
  "geometry": {"coordinates":[-96.052178,41.205405],"type":"Point"}
}