{
  "type": "Feature",
  "properties": {
    "addr:full":"511 N Spruce St Ogallala NE 69153",
    "addr:housenumber":"511",
    "addr:postcode":"69153",
    "addr:street":"N Spruce St",
    "iso:country":"US",
    "sg:address":"511 N Spruce St",
    "sg:city":"Ogallala",
    "sg:classifiers":[
        {
            "category":"Government",
            "subcategory":"Office",
            "type":"Public Place"
        }
    ],
    "sg:phone":"+1 308 284 3142",
    "sg:postcode":"69153",
    "sg:province":"NE",
    "wof:name":"Keith County Land Info",
    "wof:placetype":"venue"
},
  "geometry": {"coordinates":[-101.719897,41.129134],"type":"Point"}
}