{
  "type": "Feature",
  "properties": {
    "addr:full":"2550 Diers Ave Grand Island NE 68803",
    "addr:postcode":"2550;68803",
    "addr:street":"Diers Ave",
    "iso:country":"US",
    "sg:address":"2550 Diers Ave",
    "sg:city":"Grand Island",
    "sg:classifiers":[
        {
            "category":"Organizations",
            "subcategory":"Community Association",
            "type":"Services"
        }
    ],
    "sg:phone":"+1 308 382 8112",
    "sg:postcode":"68803",
    "sg:province":"NE",
    "sg:tags":[
        "consulting",
        "business"
    ],
    "wof:name":"Rainwater Basin Joint Venture",
    "wof:placetype":"venue"
},
  "geometry": {"coordinates":[-98.384473,40.948658],"type":"Point"}
}