{
  "type": "Feature",
  "properties": {
    "iso:country":"US",
    "sg:address":"1614 Ellis Dr",
    "sg:city":"Dakota City",
    "sg:classifiers":[
        {
            "category":"Bars & Pubs",
            "type":"Food & Drink"
        }
    ],
    "sg:phone":"+1 402 987 1085",
    "sg:postcode":"68731",
    "sg:province":"NE",
    "sg:tags":[
        "drinking"
    ],
    "wof:name":"Lakeside Saloon",
    "wof:placetype":"venue"
},
  "geometry": {"coordinates":[-96.44653599999999,42.434449],"type":"Point"}
}