{
  "type": "Feature",
  "properties": {
    "iso:country":"US",
    "sg:address":"2538 Parkview Dr",
    "sg:city":"Fremont",
    "sg:phone":"+1 402 721 8659",
    "sg:postcode":"68025",
    "sg:province":"NE",
    "sg:tags":[
        "farm",
        "corn",
        "soybean"
    ],
    "wof:name":"Otto & Wanda Brabec",
    "wof:placetype":"venue"
},
  "geometry": {"coordinates":[-96.464585,41.439102],"type":"Point"}
}