{
  "type": "Feature",
  "properties": {
    "addr:full":"4231 Industrial Ave Lincoln NE 68504",
    "addr:housenumber":"4231",
    "addr:postcode":"68504",
    "addr:street":"Industrial Ave",
    "iso:country":"US",
    "sg:address":"4231 Industrial Ave",
    "sg:city":"Lincoln",
    "sg:classifiers":[
        {
            "category":"Travel",
            "subcategory":"Hotels & Motels",
            "type":"Entertainment"
        }
    ],
    "sg:phone":"+1 402 476 8080",
    "sg:postcode":"68504",
    "sg:province":"NE",
    "wof:name":"Comfort Suites",
    "wof:placetype":"venue"
},
  "geometry": {"coordinates":[-96.679738,40.855608],"type":"Point"}
}