{
  "type": "Feature",
  "properties": {
    "addr:full":"135 W 4th St Superior NE 68978",
    "addr:housenumber":"135",
    "addr:postcode":"68978",
    "addr:street":"W 4Th St",
    "iso:country":"US",
    "sg:address":"135 W 4th St",
    "sg:city":"Superior",
    "sg:classifiers":[
        {
            "category":"Government",
            "subcategory":"Office",
            "type":"Public Place"
        }
    ],
    "sg:phone":"+1 402 879 4713",
    "sg:postcode":"68978",
    "sg:province":"NE",
    "sg:tags":[
        "city"
    ],
    "wof:name":"Superior City Clerk",
    "wof:placetype":"venue"
},
  "geometry": {"coordinates":[-98.07174000000001,40.019815],"type":"Point"}
}