{
  "type": "Feature",
  "properties": {
    "addr:full":"104 S Apollo St Alda NE 68810",
    "addr:housenumber":"104",
    "addr:postcode":"68810",
    "addr:street":"S Apollo St",
    "iso:country":"US",
    "sg:address":"104 S Apollo St",
    "sg:city":"Alda",
    "sg:classifiers":[
        {
            "category":"Manufacturing",
            "subcategory":"Tools & Machinery",
            "type":"Manufacturing & Wholesale Goods"
        }
    ],
    "sg:phone":"+1 308 384 1780",
    "sg:postcode":"68810",
    "sg:province":"NE",
    "wof:name":"Merrick Machine Co",
    "wof:placetype":"venue"
},
  "geometry": {"coordinates":[-98.474299,40.865915],"type":"Point"}
}