{
  "type": "Feature",
  "properties": {
    "iso:country":"US",
    "sg:address":"704 N A St",
    "sg:city":"Edgar",
    "sg:classifiers":[
        {
            "category":"Recreation",
            "type":"Entertainment"
        }
    ],
    "sg:phone":"+1 402 224 5035",
    "sg:postcode":"68935",
    "sg:province":"NE",
    "sg:tags":[
        "pool",
        "swimming"
    ],
    "wof:name":"Swimming Pool",
    "wof:placetype":"venue"
},
  "geometry": {"coordinates":[-97.96737899999999,40.375228],"type":"Point"}
}