{
  "type": "Feature",
  "properties": {
    "addr:full":"1014 E 1st St Ogallala NE 69153",
    "addr:housenumber":"1014",
    "addr:postcode":"69153",
    "addr:street":"E 1St St",
    "iso:country":"US",
    "sg:address":"1014 E 1st St",
    "sg:city":"Ogallala",
    "sg:classifiers":[
        {
            "category":"Shopping",
            "type":"Retail Goods"
        }
    ],
    "sg:phone":"+1 308 284 6870",
    "sg:postcode":"69153",
    "sg:province":"NE",
    "sg:tags":[
        "merchandise"
    ],
    "wof:name":"Hearth and Spa Works",
    "wof:placetype":"venue"
},
  "geometry": {"coordinates":[-101.707791,41.126031],"type":"Point"}
}