{
  "type": "Feature",
  "properties": {
    "iso:country":"US",
    "sg:address":"16857 Karen St",
    "sg:city":"Omaha",
    "sg:classifiers":[
        {
            "category":"Sports & Exercise",
            "subcategory":"Gym",
            "type":"Entertainment"
        }
    ],
    "sg:phone":"+1 402 895 7902",
    "sg:postcode":"68135",
    "sg:province":"NE",
    "sg:tags":[
        "fitness",
        "physical",
        "facility"
    ],
    "wof:name":"Fast Forward",
    "wof:placetype":"venue"
},
  "geometry": {"coordinates":[-96.17917199999999,41.212942],"type":"Point"}
}