{
  "type": "Feature",
  "properties": {
    "iso:country":"US",
    "sg:address":"3900 NW 12th St",
    "sg:city":"Lincoln",
    "sg:classifiers":[
        {
            "category":"Organizations",
            "subcategory":"Non-profit Organization",
            "type":"Services"
        },
        {
            "category":"Professional",
            "subcategory":"Management & Consulting",
            "type":"Services"
        }
    ],
    "sg:phone":"+1 402 435 3551",
    "sg:postcode":"68521",
    "sg:province":"NE",
    "sg:tags":[
        "relations",
        "association",
        "business",
        "public"
    ],
    "wof:name":"Nebraska Health Care Assn",
    "wof:placetype":"venue"
},
  "geometry": {"coordinates":[-96.738135,40.849763],"type":"Point"}
}