{
  "type": "Feature",
  "properties": {
    "iso:country":"US",
    "sg:address":"5062 S 107th St",
    "sg:city":"Omaha",
    "sg:classifiers":[
        {
            "category":"Freight",
            "type":"Transportation"
        }
    ],
    "sg:phone":"+1 402 537 1943",
    "sg:postcode":"68127",
    "sg:province":"NE",
    "sg:tags":[
        "delivery"
    ],
    "wof:name":"Midlands Messenger Svc",
    "wof:placetype":"venue"
},
  "geometry": {"coordinates":[-96.078907,41.205816],"type":"Point"}
}