{
  "type": "Feature",
  "properties": {
    "iso:country":"US",
    "sg:address":"2709 Leavenworth St",
    "sg:city":"Omaha",
    "sg:classifiers":[
        {
            "category":"Arts & Performance",
            "subcategory":"Art Gallery",
            "type":"Entertainment"
        }
    ],
    "sg:phone":"+1 402 345 3347",
    "sg:postcode":"68105",
    "sg:province":"NE",
    "wof:name":"Rogers Robert D",
    "wof:placetype":"venue"
},
  "geometry": {"coordinates":[-95.952103,41.2523],"type":"Point"}
}