{
  "type": "Feature",
  "properties": {
    "iso:country":"US",
    "sg:address":"309 W 20th St",
    "sg:city":"Lexington",
    "sg:phone":"+1 308 324 2497",
    "sg:postcode":"68850",
    "sg:province":"NE",
    "sg:tags":[
        "farm",
        "corn"
    ],
    "wof:name":"William Brinkman",
    "wof:placetype":"venue"
},
  "geometry": {"coordinates":[-99.743938,40.793802],"type":"Point"}
}