{
  "type": "Feature",
  "properties": {
    "addr:full":"323 West Ave Holdrege NE 68949",
    "addr:housenumber":"323",
    "addr:postcode":"68949",
    "addr:street":"West Ave",
    "iso:country":"US",
    "sg:address":"323 West Ave",
    "sg:city":"Holdrege",
    "sg:classifiers":[
        {
            "category":"Shopping",
            "subcategory":"Crafts & Fabrics",
            "type":"Retail Goods"
        }
    ],
    "sg:phone":"+1 308 995 2728",
    "sg:postcode":"68949",
    "sg:province":"NE",
    "sg:tags":[
        "building",
        "sewing",
        "quilting",
        "nonresidential",
        "material",
        "ope",
        "supply"
    ],
    "wof:name":"Quilter's Delight",
    "wof:placetype":"venue"
},
  "geometry": {"coordinates":[-99.371399,40.437716],"type":"Point"}
}