{
  "type": "Feature",
  "properties": {
    "iso:country":"US",
    "sg:address":"2514 S 10th St",
    "sg:city":"Omaha",
    "sg:classifiers":[
        {
            "category":"Building & Trades",
            "subcategory":"Cleaning & Sanitation",
            "type":"Services"
        }
    ],
    "sg:phone":"+1 402 933 4493",
    "sg:postcode":"68108",
    "sg:province":"NE",
    "sg:tags":[
        "maintenance"
    ],
    "wof:name":"All Clean Chimney Service Inc",
    "wof:placetype":"venue"
},
  "geometry": {"coordinates":[-95.92956599999999,41.234334],"type":"Point"}
}