{
  "type": "Feature",
  "properties": {
    "iso:country":"US",
    "sg:address":"14121 S 96th St",
    "sg:city":"Papillion",
    "sg:classifiers":[
        {
            "category":"Health Services",
            "subcategory":"Doctor",
            "type":"Services"
        }
    ],
    "sg:phone":"+1 402 339 5794",
    "sg:postcode":"68046",
    "sg:province":"NE",
    "sg:tags":[
        "surgeon",
        "oral"
    ],
    "wof:name":"Curry Roger K DDS",
    "wof:placetype":"venue"
},
  "geometry": {"coordinates":[-96.061798,41.1017],"type":"Point"}
}