{
  "type": "Feature",
  "properties": {
    "iso:country":"US",
    "sg:address":"120 E 8th St",
    "sg:city":"North Platte",
    "sg:classifiers":[
        {
            "category":"Building & Trades",
            "subcategory":"Construction",
            "type":"Services"
        }
    ],
    "sg:phone":"+1 308 532 3315",
    "sg:postcode":"69101",
    "sg:province":"NE",
    "sg:tags":[
        "contractor"
    ],
    "wof:name":"Valley Industrial Contrs LLC",
    "wof:placetype":"venue"
},
  "geometry": {"coordinates":[-100.761729,41.142266],"type":"Point"}
}