{
  "type": "Feature",
  "properties": {
    "addr:full":"625 9th St Unadilla NE 68454",
    "addr:housenumber":"625",
    "addr:postcode":"68454",
    "addr:street":"9Th St",
    "iso:country":"US",
    "sg:address":"625 9th St",
    "sg:city":"Unadilla",
    "sg:classifiers":[
        {
            "category":"Autos & Motor Vehicles",
            "subcategory":"Fuel & Gas Station",
            "type":"Retail Goods"
        }
    ],
    "sg:phone":"+1 402 828 3335",
    "sg:postcode":"68454",
    "sg:province":"NE",
    "sg:tags":[
        "oil"
    ],
    "wof:name":"Unadilla Mart",
    "wof:placetype":"venue"
},
  "geometry": {"coordinates":[-96.26957400000001,40.685535],"type":"Point"}
}