{
  "type": "Feature",
  "properties": {
    "iso:country":"US",
    "sg:address":"616 S 75th St",
    "sg:city":"Omaha",
    "sg:classifiers":[
        {
            "category":"Social Services",
            "type":"Services"
        }
    ],
    "sg:phone":"+1 402 393 7365",
    "sg:postcode":"68114",
    "sg:province":"NE",
    "sg:tags":[
        "organization",
        "welfare"
    ],
    "wof:name":"Community Alliance",
    "wof:placetype":"venue"
},
  "geometry": {"coordinates":[-96.02946,41.251701],"type":"Point"}
}