{
  "type": "Feature",
  "properties": {
    "iso:country":"US",
    "sg:address":"715 S 24th St",
    "sg:city":"Omaha",
    "sg:classifiers":[
        {
            "category":"Food & Beverages",
            "subcategory":"Liquor & Beverages",
            "type":"Retail Goods"
        }
    ],
    "sg:phone":"+1 402 346 6771",
    "sg:postcode":"68102",
    "sg:province":"NE",
    "sg:tags":[
        "fruit",
        "veggie"
    ],
    "wof:name":"All Nations",
    "wof:placetype":"venue"
},
  "geometry": {"coordinates":[-95.946765,41.253022],"type":"Point"}
}