{
  "type": "Feature",
  "properties": {
    "iso:country":"US",
    "sg:address":"8922 Cuming St",
    "sg:city":"Omaha",
    "sg:classifiers":[
        {
            "category":"Social Services",
            "subcategory":"Child Care",
            "type":"Services"
        }
    ],
    "sg:phone":"+1 402 926 4373",
    "sg:postcode":"68114",
    "sg:province":"NE",
    "sg:tags":[
        "day"
    ],
    "wof:name":"Behaven Day Center",
    "wof:placetype":"venue"
},
  "geometry": {"coordinates":[-96.051635,41.268392],"type":"Point"}
}