{
  "type": "Feature",
  "properties": {
    "iso:country":"US",
    "sg:address":"276 US Hwy 30",
    "sg:city":"Grand Island",
    "sg:classifiers":[
        {
            "category":"Building & Trades",
            "subcategory":"Cleaning & Sanitation",
            "type":"Services"
        }
    ],
    "sg:phone":"+1 308 384 4899",
    "sg:postcode":"68801",
    "sg:province":"NE",
    "sg:tags":[
        "maintenance"
    ],
    "wof:name":"Robin Benson",
    "wof:placetype":"venue"
},
  "geometry": {"coordinates":[-98.34050000000001,40.923349],"type":"Point"}
}