{
  "type": "Feature",
  "properties": {
    "iso:country":"US",
    "sg:address":"9996 Rd 24",
    "sg:city":"Sidney",
    "sg:classifiers":[
        {
            "category":"Farming",
            "subcategory":"Farm",
            "type":"Manufacturing & Wholesale Goods"
        }
    ],
    "sg:phone":"+1 308 254 4919",
    "sg:postcode":"69162",
    "sg:province":"NE",
    "sg:tags":[
        "crop",
        "general"
    ],
    "wof:name":"Frank Rauner",
    "wof:placetype":"venue"
},
  "geometry": {"coordinates":[-103.093811,41.1634],"type":"Point"}
}