{
  "type": "Feature",
  "properties": {
    "iso:country":"US",
    "sg:address":"15909 Bancroft Ct",
    "sg:city":"Omaha",
    "sg:classifiers":[
        {
            "category":"Wholesale",
            "subcategory":"Electrical",
            "type":"Manufacturing & Wholesale Goods"
        }
    ],
    "sg:phone":"+1 402 330 8951",
    "sg:postcode":"68130",
    "sg:province":"NE",
    "sg:tags":[
        "control",
        "security",
        "system"
    ],
    "wof:name":"Sia Management Alarm",
    "wof:placetype":"venue"
},
  "geometry": {"coordinates":[-96.163518,41.233711],"type":"Point"}
}