{
  "type": "Feature",
  "properties": {
    "addr:full":"309 E 4th St Lexington NE 68850",
    "addr:housenumber":"309",
    "addr:postcode":"68850",
    "addr:street":"E 4Th St",
    "iso:country":"US",
    "sg:address":"309 E 4th St",
    "sg:city":"Lexington",
    "sg:classifiers":[
        {
            "category":"Autos & Motor Vehicles",
            "subcategory":"Auto Supplies",
            "type":"Retail Goods"
        }
    ],
    "sg:phone":"+1 308 324 4661",
    "sg:postcode":"68850",
    "sg:province":"NE",
    "sg:tags":[
        "automobile",
        "parts"
    ],
    "wof:name":"Mr Automotive",
    "wof:placetype":"venue"
},
  "geometry": {"coordinates":[-99.738732,40.777013],"type":"Point"}
}