{
  "type": "Feature",
  "properties": {
    "iso:country":"US",
    "sg:address":"4720 Lowell Ave",
    "sg:city":"Lincoln",
    "sg:classifiers":[
        {
            "category":"Building & Trades",
            "subcategory":"Plumbing",
            "type":"Services"
        }
    ],
    "sg:phone":"+1 402 489 2274",
    "sg:postcode":"68506",
    "sg:province":"NE",
    "sg:tags":[
        "heating",
        "contractor"
    ],
    "wof:name":"Wentz Heating & Air Cond",
    "wof:placetype":"venue"
},
  "geometry": {"coordinates":[-96.654284,40.771889],"type":"Point"}
}