{
  "type": "Feature",
  "properties": {
    "addr:full":"708 Beaver St Beaver Crossing NE 68313",
    "addr:housenumber":"708",
    "addr:postcode":"68313",
    "addr:street":"Beaver St",
    "iso:country":"US",
    "sg:address":"708 Beaver St",
    "sg:city":"Beaver Crossing",
    "sg:classifiers":[
        {
            "category":"Organizations",
            "subcategory":"Religious Organization",
            "type":"Services"
        }
    ],
    "sg:phone":"+1 402 532 2255",
    "sg:postcode":"68313",
    "sg:province":"NE",
    "wof:name":"United Methodist Church",
    "wof:placetype":"venue"
},
  "geometry": {"coordinates":[-97.281863,40.777305],"type":"Point"}
}