{
  "type": "Feature",
  "properties": {
    "iso:country":"US",
    "sg:address":"11502 Westmont Dr",
    "sg:city":"Omaha",
    "sg:classifiers":[
        {
            "category":"Arts & Performance",
            "subcategory":"Theater",
            "type":"Entertainment"
        }
    ],
    "sg:phone":"+1 402 895 3432",
    "sg:postcode":"68138",
    "sg:province":"NE",
    "sg:tags":[
        "live",
        "music"
    ],
    "wof:name":"Premier Music",
    "wof:placetype":"venue"
},
  "geometry": {"coordinates":[-96.127055,41.141946],"type":"Point"}
}