{
  "type": "Feature",
  "properties": {
    "iso:country":"US",
    "sg:address":"408 S V Rd",
    "sg:city":"Aurora",
    "sg:classifiers":[
        {
            "category":"Farming",
            "subcategory":"Farm",
            "type":"Manufacturing & Wholesale Goods"
        }
    ],
    "sg:phone":"+1 402 723 5241",
    "sg:postcode":"68818",
    "sg:province":"NE",
    "sg:tags":[
        "crop",
        "general"
    ],
    "wof:name":"Blue River Feeding",
    "wof:placetype":"venue"
},
  "geometry": {"coordinates":[-97.901785,40.743509],"type":"Point"}
}