{
  "type": "Feature",
  "properties": {
    "iso:country":"US",
    "sg:address":"1316 S 52nd Ave",
    "sg:city":"Omaha",
    "sg:classifiers":[
        {
            "category":"Wholesale",
            "subcategory":"Office Equipment",
            "type":"Manufacturing & Wholesale Goods"
        }
    ],
    "sg:phone":"+1 402 449 1700",
    "sg:postcode":"68106",
    "sg:province":"NE",
    "wof:name":"Independent Cash Register",
    "wof:placetype":"venue"
},
  "geometry": {"coordinates":[-95.994308,41.245097],"type":"Point"}
}