{
  "type": "Feature",
  "properties": {
    "iso:country":"US",
    "sg:address":"10618 190th St",
    "sg:city":"Waverly",
    "sg:phone":"+1 402 789 3620",
    "sg:postcode":"68462",
    "sg:province":"NE",
    "sg:tags":[
        "farm",
        "corn",
        "soybean"
    ],
    "wof:name":"Alan Hilt",
    "wof:placetype":"venue"
},
  "geometry": {"coordinates":[-96.46380000000001,40.912232],"type":"Point"}
}