{
  "type": "Feature",
  "properties": {
    "addr:full":"515 Wilson St Bassett NE 68714",
    "addr:housenumber":"515",
    "addr:postcode":"68714",
    "addr:street":"Wilson St",
    "iso:country":"US",
    "sg:address":"515 Wilson St",
    "sg:city":"Bassett",
    "sg:classifiers":[
        {
            "category":"Autos & Motor Vehicles",
            "subcategory":"Auto Supplies",
            "type":"Retail Goods"
        }
    ],
    "sg:phone":"+1 402 684 3281",
    "sg:postcode":"68714",
    "sg:province":"NE",
    "sg:tags":[
        "tire",
        "accessory"
    ],
    "wof:name":"Mikes Supply",
    "wof:placetype":"venue"
},
  "geometry": {"coordinates":[-99.53365599999999,42.579733],"type":"Point"}
}