{
  "type": "Feature",
  "properties": {
    "addr:full":"5018 S Antelope Dr Grand Island NE 68803",
    "addr:housenumber":"5018",
    "addr:postcode":"68803",
    "addr:street":"S Antelope Dr",
    "iso:country":"US",
    "sg:address":"5018 S Antelope Dr",
    "sg:city":"Grand Island",
    "sg:classifiers":[
        {
            "category":"Wholesale",
            "subcategory":"Machinery & Supplies",
            "type":"Manufacturing & Wholesale Goods"
        }
    ],
    "sg:phone":"+1 308 381 4266",
    "sg:postcode":"68803",
    "sg:province":"NE",
    "sg:tags":[
        "industrial"
    ],
    "wof:name":"Fairbank Equipment Inc",
    "wof:placetype":"venue"
},
  "geometry": {"coordinates":[-98.379007,40.856873],"type":"Point"}
}