{
  "type": "Feature",
  "properties": {
    "iso:country":"US",
    "sg:address":"1258 27th Ave",
    "sg:city":"Columbus",
    "sg:classifiers":[
        {
            "category":"Personal",
            "subcategory":"Beauty Salon",
            "type":"Services"
        }
    ],
    "sg:phone":"+1 402 562 8227",
    "sg:postcode":"68601",
    "sg:province":"NE",
    "sg:tags":[
        "manicuring"
    ],
    "wof:name":"Nail Boutique",
    "wof:placetype":"venue"
},
  "geometry": {"coordinates":[-97.360742,41.429202],"type":"Point"}
}