{
  "type": "Feature",
  "properties": {
    "addr:full":"517 Oak St Norfolk NE 68701",
    "addr:housenumber":"517",
    "addr:postcode":"68701",
    "addr:street":"Oak St",
    "iso:country":"US",
    "sg:address":"517 Oak St",
    "sg:city":"Norfolk",
    "sg:classifiers":[
        {
            "category":"Building & Trades",
            "subcategory":"Construction",
            "type":"Services"
        }
    ],
    "sg:phone":"+1 402 379 0427",
    "sg:postcode":"68701",
    "sg:province":"NE",
    "sg:tags":[
        "restoration",
        "cleaning",
        "patio",
        "deck"
    ],
    "wof:name":"Proclean",
    "wof:placetype":"venue"
},
  "geometry": {"coordinates":[-97.405147,42.037921],"type":"Point"}
}