{
  "type": "Feature",
  "properties": {
    "iso:country":"US",
    "sg:address":"302 N Fuller St",
    "sg:city":"Fullerton",
    "sg:classifiers":[
        {
            "category":"Home & Garden",
            "subcategory":"Building Materials",
            "type":"Retail Goods"
        }
    ],
    "sg:phone":"+1 308 536 2434",
    "sg:postcode":"68638",
    "sg:province":"NE",
    "wof:name":"Cedar Valley Lumber Co",
    "wof:placetype":"venue"
},
  "geometry": {"coordinates":[-97.969903,41.369072],"type":"Point"}
}