{
  "type": "Feature",
  "properties": {
    "iso:country":"US",
    "sg:address":"3702 23rd St",
    "sg:city":"Columbus",
    "sg:classifiers":[
        {
            "category":"Health Services",
            "subcategory":"Optometrist",
            "type":"Services"
        }
    ],
    "sg:phone":"+1 402 564 2020",
    "sg:postcode":"68601",
    "sg:province":"NE",
    "wof:name":"Optometric Center Of Columbus",
    "wof:placetype":"venue"
},
  "geometry": {"coordinates":[-97.374191,41.438791],"type":"Point"}
}