{
  "type": "Feature",
  "properties": {
    "iso:country":"US",
    "sg:address":"2929 Farnam St",
    "sg:city":"Omaha",
    "sg:classifiers":[
        {
            "category":"Restaurant",
            "type":"Food & Drink"
        }
    ],
    "sg:phone":"+1 402 346 1110",
    "sg:postcode":"68131",
    "sg:province":"NE",
    "sg:tags":[
        "drinking",
        "eating",
        "pizza"
    ],
    "wof:name":"Romeo's Mexican Food & Pizza",
    "wof:placetype":"venue"
},
  "geometry": {"coordinates":[-95.95500199999999,41.257599],"type":"Point"}
}