{
  "type": "Feature",
  "properties": {
    "addr:full":"1014 Central Ave Auburn NE 68305",
    "addr:housenumber":"1014",
    "addr:postcode":"68305",
    "addr:street":"Central Ave",
    "iso:country":"US",
    "sg:address":"1014 Central Ave",
    "sg:city":"Auburn",
    "sg:classifiers":[
        {
            "category":"Shopping",
            "subcategory":"Used Merchandise",
            "type":"Retail Goods"
        }
    ],
    "sg:phone":"+1 402 274 4818",
    "sg:postcode":"68305",
    "sg:province":"NE",
    "sg:tags":[
        "shop",
        "thrift"
    ],
    "wof:name":"St Francis Gift & Thrift",
    "wof:placetype":"venue"
},
  "geometry": {"coordinates":[-95.840014,40.392877],"type":"Point"}
}