{
  "type": "Feature",
  "properties": {
    "iso:country":"US",
    "sg:address":"170492 Carter Canyon Rd",
    "sg:city":"Gering",
    "sg:phone":"+1 308 436 2058",
    "sg:postcode":"69341",
    "sg:province":"NE",
    "sg:tags":[
        "farm",
        "corn",
        "beef",
        "feedlot",
        "cattle"
    ],
    "wof:name":"Glen & Nancy Ross",
    "wof:placetype":"venue"
},
  "geometry": {"coordinates":[-103.741922,41.786324],"type":"Point"}
}