{
  "type": "Feature",
  "properties": {
    "iso:country":"US",
    "sg:address":"4145 Manchester Rd",
    "sg:city":"Grand Island",
    "sg:classifiers":[
        {
            "category":"Building & Trades",
            "subcategory":"Construction",
            "type":"Services"
        }
    ],
    "sg:phone":"+1 308 384 8557",
    "sg:postcode":"68803",
    "sg:province":"NE",
    "sg:tags":[
        "house"
    ],
    "wof:name":"Reis Construction Inc",
    "wof:placetype":"venue"
},
  "geometry": {"coordinates":[-98.406633,40.939726],"type":"Point"}
}