{
  "type": "Feature",
  "properties": {
    "addr:full":"518 N Jeffers St North Platte NE 69101",
    "addr:housenumber":"518",
    "addr:postcode":"69101",
    "addr:street":"N Jeffers St",
    "iso:country":"US",
    "sg:address":"518 N Jeffers St",
    "sg:city":"North Platte",
    "sg:classifiers":[
        {
            "category":"Personal",
            "type":"Services"
        }
    ],
    "sg:phone":"+1 308 534 3265",
    "sg:postcode":"69101",
    "sg:province":"NE",
    "sg:tags":[
        "therapist",
        "massage"
    ],
    "wof:name":"Ballance By Masasge",
    "wof:placetype":"venue"
},
  "geometry": {"coordinates":[-100.76294799999999,41.138346],"type":"Point"}
}