{
  "type": "Feature",
  "properties": {
    "iso:country":"US",
    "sg:address":"1818 Broadway St",
    "sg:city":"Yankton",
    "sg:classifiers":[
        {
            "category":"Shopping",
            "subcategory":"Discount & Variety Stores",
            "type":"Retail Goods"
        }
    ],
    "sg:phone":"+1 605 668 1672",
    "sg:postcode":"57078",
    "sg:province":"NE",
    "wof:name":"Family Dollar Stores",
    "wof:placetype":"venue"
},
  "geometry": {"coordinates":[-97.396514,42.885878],"type":"Point"}
}