{
  "type": "Feature",
  "properties": {
    "addr:full":"1725 10th St Gering NE 69341",
    "addr:housenumber":"1725",
    "addr:postcode":"69341",
    "addr:street":"10Th St",
    "iso:country":"US",
    "sg:address":"1725 10th St",
    "sg:city":"Gering",
    "sg:classifiers":[
        {
            "category":"Government",
            "subcategory":"Court House",
            "type":"Public Place"
        }
    ],
    "sg:phone":"+1 308 436 6674",
    "sg:postcode":"69341",
    "sg:province":"NE",
    "sg:tags":[
        "county",
        "counsel"
    ],
    "wof:name":"Scotts Bluff County Attorney",
    "wof:placetype":"venue"
},
  "geometry": {"coordinates":[-103.660434,41.826547],"type":"Point"}
}