{
  "type": "Feature",
  "properties": {
    "iso:country":"US",
    "sg:address":"1770 State Hwy 40",
    "sg:city":"Kearney",
    "sg:classifiers":[
        {
            "category":"Retail",
            "subcategory":"Veterinary Services",
            "type":"Services"
        }
    ],
    "sg:phone":"+1 308 234 1475",
    "sg:postcode":"68845",
    "sg:province":"NE",
    "wof:name":"Glenwood Veterinary Clinic",
    "wof:placetype":"venue"
},
  "geometry": {"coordinates":[-99.099772,40.754963],"type":"Point"}
}