{
  "type": "Feature",
  "properties": {
    "iso:country":"US",
    "sg:address":"16511 Iske Dr",
    "sg:city":"Bellevue",
    "sg:classifiers":[
        {
            "category":"Retail",
            "subcategory":"Auto Repair",
            "type":"Services"
        }
    ],
    "sg:phone":"+1 402 933 4034",
    "sg:postcode":"68123",
    "sg:province":"NE",
    "sg:tags":[
        "body",
        "automobile",
        "painting"
    ],
    "wof:name":"Bullseye Pdr",
    "wof:placetype":"venue"
},
  "geometry": {"coordinates":[-95.93241500000001,41.072888],"type":"Point"}
}