{
  "type": "Feature",
  "properties": {
    "addr:full":"323 Main St Chadron NE 69337",
    "addr:housenumber":"323",
    "addr:postcode":"69337",
    "addr:street":"Main St",
    "iso:country":"US",
    "sg:address":"323 Main St",
    "sg:city":"Chadron",
    "sg:classifiers":[
        {
            "category":"Insurance",
            "subcategory":"Insurance Agent",
            "type":"Services"
        }
    ],
    "sg:phone":"+1 308 432 5507",
    "sg:postcode":"69337",
    "sg:province":"NE",
    "sg:tags":[
        "agency"
    ],
    "wof:name":"State Farm Insurance",
    "wof:placetype":"venue"
},
  "geometry": {"coordinates":[-103.000889,42.828155],"type":"Point"}
}