{
  "type": "Feature",
  "properties": {
    "iso:country":"US",
    "sg:address":"50960 190th Rd",
    "sg:city":"Gibbon",
    "sg:classifiers":[
        {
            "category":"Farming",
            "subcategory":"Livestock Farm",
            "type":"Manufacturing & Wholesale Goods"
        }
    ],
    "sg:phone":"+1 308 647 5348",
    "sg:postcode":"68840",
    "sg:province":"NE",
    "sg:tags":[
        "ranch"
    ],
    "wof:name":"Vanvleet Ranch",
    "wof:placetype":"venue"
},
  "geometry": {"coordinates":[-98.80664,40.85858],"type":"Point"}
}