{
  "type": "Feature",
  "properties": {
    "iso:country":"US",
    "sg:address":"573 Rd East A S",
    "sg:city":"Ogallala",
    "sg:classifiers":[
        {
            "category":"Farming",
            "subcategory":"Livestock Farm",
            "type":"Manufacturing & Wholesale Goods"
        }
    ],
    "sg:phone":"+1 308 284 4569",
    "sg:postcode":"69153",
    "sg:province":"NE",
    "sg:tags":[
        "wheat",
        "beef",
        "far",
        "corn",
        "crop",
        "field",
        "cattle",
        "feedlot"
    ],
    "wof:name":"Dwaine Most",
    "wof:placetype":"venue"
},
  "geometry": {"coordinates":[-101.710751,41.063284],"type":"Point"}
}