{
  "type": "Feature",
  "properties": {
    "addr:full":"221 S Locust St Grand Island NE 68801",
    "addr:housenumber":"221",
    "addr:postcode":"68801",
    "addr:street":"S Locust St",
    "iso:country":"US",
    "sg:address":"221 S Locust St",
    "sg:city":"Grand Island",
    "sg:classifiers":[
        {
            "category":"Banks & Credit Unions",
            "subcategory":"Investment Brokerage",
            "type":"Services"
        }
    ],
    "sg:phone":"+1 308 398 4946",
    "sg:postcode":"68801",
    "sg:province":"NE",
    "sg:tags":[
        "security"
    ],
    "wof:name":"Principal Financial Group",
    "wof:placetype":"venue"
},
  "geometry": {"coordinates":[-98.339749,40.922764],"type":"Point"}
}