{
  "type": "Feature",
  "properties": {
    "addr:full":"1406 Rd 5 Grafton NE 68365",
    "addr:housenumber":"1406",
    "addr:postcode":"68365",
    "addr:street":"Rd 5",
    "iso:country":"US",
    "sg:address":"1406 Rd 5",
    "sg:city":"Grafton",
    "sg:classifiers":[
        {
            "category":"Wholesale",
            "subcategory":"Farm Supplies",
            "type":"Manufacturing & Wholesale Goods"
        }
    ],
    "sg:phone":"+1 402 759 4801",
    "sg:postcode":"68365",
    "sg:province":"NE",
    "sg:tags":[
        "livestock"
    ],
    "wof:name":"Mark Obrien",
    "wof:placetype":"venue"
},
  "geometry": {"coordinates":[-97.74793099999999,40.541795],"type":"Point"}
}