{
  "type": "Feature",
  "properties": {
    "iso:country":"US",
    "sg:address":"1400 E 8th St",
    "sg:city":"North Platte",
    "sg:classifiers":[
        {
            "category":"Professional",
            "subcategory":"Business Services",
            "type":"Services"
        }
    ],
    "sg:phone":"+1 308 532 4004",
    "sg:postcode":"69101",
    "sg:province":"NE",
    "sg:tags":[
        "interior",
        "consultant",
        "design",
        "decorator"
    ],
    "sg:website":"www.americantiredistributors.com",
    "wof:name":"American Tire Distributors",
    "wof:placetype":"venue"
},
  "geometry": {"coordinates":[-100.745834,41.14024],"type":"Point"}
}