{
  "type": "Feature",
  "properties": {
    "addr:full":"2737 N 49th St Lincoln NE 68504",
    "addr:housenumber":"2737",
    "addr:postcode":"68504",
    "addr:street":"N 49Th St",
    "iso:country":"US",
    "sg:address":"2737 N 49th St",
    "sg:city":"Lincoln",
    "sg:classifiers":[
        {
            "category":"Health Services",
            "subcategory":"Doctor",
            "type":"Services"
        }
    ],
    "sg:phone":"+1 402 466 6404",
    "sg:postcode":"68504",
    "sg:province":"NE",
    "sg:tags":[
        "physician",
        "surgeon"
    ],
    "wof:name":"Stoney Ridge Day Treatment Ctr",
    "wof:placetype":"venue"
},
  "geometry": {"coordinates":[-96.65242499999999,40.839935],"type":"Point"}
}