{
  "type": "Feature",
  "properties": {
    "iso:country":"US",
    "sg:address":"1520 Ave D",
    "sg:city":"Gothenburg",
    "sg:classifiers":[
        {
            "category":"Organizations",
            "subcategory":"Religious Organization",
            "type":"Services"
        }
    ],
    "sg:phone":"+1 308 537 3339",
    "sg:postcode":"69138",
    "sg:province":"NE",
    "sg:tags":[
        "church"
    ],
    "wof:name":"Seventh Day Adventist Church",
    "wof:placetype":"venue"
},
  "geometry": {"coordinates":[-100.162064,40.933217],"type":"Point"}
}