{
  "type": "Feature",
  "properties": {
    "iso:country":"US",
    "sg:address":"110 W 1st St",
    "sg:city":"Pilger",
    "sg:classifiers":[
        {
            "category":"Professional",
            "subcategory":"Accounting & Tax Preparation",
            "type":"Services"
        }
    ],
    "sg:phone":"+1 402 396 3223",
    "sg:postcode":"68768",
    "sg:province":"NE",
    "sg:tags":[
        "accountant"
    ],
    "wof:name":"Morrow Davies & Toelle",
    "wof:placetype":"venue"
},
  "geometry": {"coordinates":[-97.053969,42.007613],"type":"Point"}
}