{
  "type": "Feature",
  "properties": {
    "addr:full":"202 W 2nd St Curtis NE 69025",
    "addr:housenumber":"202",
    "addr:postcode":"69025",
    "addr:street":"W 2Nd St",
    "iso:country":"US",
    "sg:address":"202 W 2nd St",
    "sg:city":"Curtis",
    "sg:classifiers":[
        {
            "category":"Freight",
            "type":"Transportation"
        }
    ],
    "sg:phone":"+1 308 367 4266",
    "sg:postcode":"69025",
    "sg:province":"NE",
    "sg:tags":[
        "grain",
        "elevator"
    ],
    "wof:name":"Ag Valley Co-Op Curtis Branch",
    "wof:placetype":"venue"
},
  "geometry": {"coordinates":[-100.516941,40.630116],"type":"Point"}
}