{
  "type": "Feature",
  "properties": {
    "addr:full":"111 N Main St West Point NE 68788",
    "addr:housenumber":"111",
    "addr:postcode":"68788",
    "addr:street":"N Main St",
    "iso:country":"US",
    "sg:address":"111 N Main St",
    "sg:city":"West Point",
    "sg:classifiers":[
        {
            "category":"Shopping",
            "subcategory":"Clothing, Apparel, & Fashions",
            "type":"Retail Goods"
        }
    ],
    "sg:phone":"+1 402 372 2117",
    "sg:postcode":"68788",
    "sg:province":"NE",
    "sg:tags":[
        "shoes",
        "family"
    ],
    "wof:name":"Style Plus",
    "wof:placetype":"venue"
},
  "geometry": {"coordinates":[-96.71221799999999,41.841017],"type":"Point"}
}