{
  "type": "Feature",
  "properties": {
    "iso:country":"US",
    "sg:address":"3726 Jackson St",
    "sg:city":"Omaha",
    "sg:classifiers":[
        {
            "category":"Building & Trades",
            "subcategory":"Locksmith",
            "type":"Services"
        }
    ],
    "sg:phone":"+1 402 881 3668",
    "sg:postcode":"68105",
    "sg:province":"NE",
    "sg:tags":[
        "key"
    ],
    "wof:name":"3 Always A Emerg Locksmith",
    "wof:placetype":"venue"
},
  "geometry": {"coordinates":[-95.967963,41.254964],"type":"Point"}
}