{
  "type": "Feature",
  "properties": {
    "addr:full":"2700 F St Lincoln NE 68510",
    "addr:housenumber":"2700",
    "addr:postcode":"68510",
    "addr:street":"F St",
    "iso:country":"US",
    "sg:address":"2700 F St",
    "sg:city":"Lincoln",
    "sg:classifiers":[
        {
            "category":"Real Estate",
            "subcategory":"Real Estate Agent",
            "type":"Services"
        }
    ],
    "sg:phone":"+1 402 476 8418",
    "sg:postcode":"68510",
    "sg:province":"NE",
    "wof:name":"J L Mc Master Co Inc",
    "wof:placetype":"venue"
},
  "geometry": {"coordinates":[-96.68001099999999,40.804846],"type":"Point"}
}