{
  "type": "Feature",
  "properties": {
    "addr:full":"2711 S 48th St Lincoln NE 68506",
    "addr:housenumber":"2711",
    "addr:postcode":"68506",
    "addr:street":"S 48Th St",
    "iso:country":"US",
    "sg:address":"2711 S 48th St",
    "sg:city":"Lincoln",
    "sg:classifiers":[
        {
            "category":"Banks & Credit Unions",
            "subcategory":"Bank",
            "type":"Services"
        }
    ],
    "sg:phone":"+1 402 484 6776",
    "sg:postcode":"68506",
    "sg:province":"NE",
    "sg:tags":[
        "cashing",
        "check"
    ],
    "wof:name":"Express Check Advance",
    "wof:placetype":"venue"
},
  "geometry": {"coordinates":[-96.653916,40.786294],"type":"Point"}
}