{
  "type": "Feature",
  "properties": {
    "iso:country":"US",
    "sg:address":"701 Sioux Meadows Dr",
    "sg:city":"North Platte",
    "sg:classifiers":[
        {
            "category":"Sports & Exercise",
            "subcategory":"Race Track",
            "type":"Entertainment"
        }
    ],
    "sg:phone":"+1 308 532 6740",
    "sg:postcode":"69101",
    "sg:province":"NE",
    "sg:website":"www.bigdogchassis.com",
    "wof:name":"Big Dog Chassis & Fabrication",
    "wof:placetype":"venue"
},
  "geometry": {"coordinates":[-100.75465699999999,41.103009],"type":"Point"}
}