{
  "type": "Feature",
  "properties": {
    "iso:country":"US",
    "sg:address":"102 E Cedar St",
    "sg:city":"Coleridge",
    "sg:classifiers":[
        {
            "category":"Manufacturing",
            "subcategory":"Motor Vehicles & Parts",
            "type":"Manufacturing & Wholesale Goods"
        }
    ],
    "sg:phone":"+1 402 283 4849",
    "sg:postcode":"68727",
    "sg:province":"NE",
    "sg:tags":[
        "designer",
        "trailer"
    ],
    "wof:name":"D & K Trailer Inc",
    "wof:placetype":"venue"
},
  "geometry": {"coordinates":[-97.20288600000001,42.507248],"type":"Point"}
}