{
  "type": "Feature",
  "properties": {
    "addr:full":"11307 Oakland Dr Papillion NE 68133",
    "addr:housenumber":"11307",
    "addr:postcode":"68133",
    "addr:street":"Oakland Dr",
    "iso:country":"US",
    "sg:address":"11307 Oakland Dr",
    "sg:city":"Papillion",
    "sg:classifiers":[
        {
            "category":"Building & Trades",
            "subcategory":"Construction",
            "type":"Services"
        }
    ],
    "sg:phone":"+1 402 740 4440",
    "sg:postcode":"68133",
    "sg:province":"NE",
    "sg:tags":[
        "excavation",
        "contractor"
    ],
    "wof:name":"Geis Co",
    "wof:placetype":"venue"
},
  "geometry": {"coordinates":[-96.002613,41.14454],"type":"Point"}
}