{
  "type": "Feature",
  "properties": {
    "iso:country":"US",
    "sg:address":"112 S 20th St",
    "sg:city":"Omaha",
    "sg:classifiers":[
        {
            "category":"Retail",
            "subcategory":"Auto Rental",
            "type":"Services"
        }
    ],
    "sg:phone":"+1 402 342 3800",
    "sg:postcode":"68102",
    "sg:province":"NE",
    "sg:tags":[
        "renting",
        "automobile"
    ],
    "wof:name":"Enterprise Rent A Car",
    "wof:placetype":"venue"
},
  "geometry": {"coordinates":[-95.94240000000001,41.258745],"type":"Point"}
}