{
  "type": "Feature",
  "properties": {
    "addr:full":"214 W 4th Ave Holdrege NE 68949",
    "addr:housenumber":"214",
    "addr:postcode":"68949",
    "addr:street":"W 4Th Ave",
    "iso:country":"US",
    "sg:address":"214 W 4th Ave",
    "sg:city":"Holdrege",
    "sg:classifiers":[
        {
            "category":"Shopping",
            "subcategory":"Pharmacy",
            "type":"Retail Goods"
        }
    ],
    "sg:phone":"+1 308 995 4401",
    "sg:postcode":"68949",
    "sg:province":"NE",
    "wof:name":"Mikes Medi-Save Pharmacy Inc",
    "wof:placetype":"venue"
},
  "geometry": {"coordinates":[-99.382676,40.437964],"type":"Point"}
}