{
  "type": "Feature",
  "properties": {
    "iso:country":"US",
    "sg:address":"3410 Central Ave",
    "sg:city":"Kearney",
    "sg:classifiers":[
        {
            "category":"Health Services",
            "subcategory":"Nursing And Care Facility",
            "type":"Services"
        }
    ],
    "sg:phone":"+1 308 234 1888",
    "sg:postcode":"68847",
    "sg:province":"NE",
    "sg:tags":[
        "home",
        "skilled",
        "convalescent"
    ],
    "wof:name":"St Johns Good Samaritan Center",
    "wof:placetype":"venue"
},
  "geometry": {"coordinates":[-99.082148,40.709113],"type":"Point"}
}