{
  "type": "Feature",
  "properties": {
    "iso:country":"US",
    "sg:address":"900 E 10th St",
    "sg:city":"North Platte",
    "sg:classifiers":[
        {
            "category":"Organizations",
            "subcategory":"Professional Association",
            "type":"Services"
        }
    ],
    "sg:phone":"+1 308 532 3250",
    "sg:postcode":"69101",
    "sg:province":"NE",
    "wof:name":"Community Action Partnership",
    "wof:placetype":"venue"
},
  "geometry": {"coordinates":[-100.751621,41.143027],"type":"Point"}
}