{
  "type": "Feature",
  "properties": {
    "addr:full":"1903 O St Lincoln NE 68510",
    "addr:housenumber":"1903",
    "addr:postcode":"68510",
    "addr:street":"O St",
    "iso:country":"US",
    "sg:address":"1903 O St",
    "sg:city":"Lincoln",
    "sg:classifiers":[
        {
            "category":"Banks & Credit Unions",
            "subcategory":"Bank",
            "type":"Services"
        }
    ],
    "sg:phone":"+1 402 416 6309",
    "sg:postcode":"68510",
    "sg:province":"NE",
    "sg:tags":[
        "cashing",
        "check"
    ],
    "wof:name":"Cash In A Snap",
    "wof:placetype":"venue"
},
  "geometry": {"coordinates":[-96.692441,40.813471],"type":"Point"}
}