{
  "type": "Feature",
  "properties": {
    "addr:full":"1621 N 74th St Omaha NE 68114",
    "addr:housenumber":"1621",
    "addr:postcode":"68114",
    "addr:street":"N 74Th St",
    "iso:country":"US",
    "sg:address":"1621 N 74th St",
    "sg:city":"Omaha",
    "sg:classifiers":[
        {
            "category":"Building & Trades",
            "subcategory":"Plumbing",
            "type":"Services"
        }
    ],
    "sg:phone":"+1 402 305 5756",
    "sg:postcode":"68114",
    "sg:province":"NE",
    "sg:tags":[
        "conditioning",
        "air",
        "system",
        "contractor"
    ],
    "wof:name":"P & L Heating & Cooling",
    "wof:placetype":"venue"
},
  "geometry": {"coordinates":[-96.02699,41.275001],"type":"Point"}
}