{
  "type": "Feature",
  "properties": {
    "iso:country":"US",
    "sg:address":"610 N 11th St",
    "sg:city":"Nebraska City",
    "sg:classifiers":[
        {
            "category":"Food & Beverages",
            "subcategory":"Groceries & Convenience Stores",
            "type":"Retail Goods"
        }
    ],
    "sg:phone":"+1 402 873 5780",
    "sg:postcode":"68410",
    "sg:province":"NE",
    "sg:tags":[
        "grocer"
    ],
    "sg:website":"www.mycountrymart.com",
    "wof:name":"Norman's Market",
    "wof:placetype":"venue"
},
  "geometry": {"coordinates":[-95.85894399999999,40.68225],"type":"Point"}
}