{
  "type": "Feature",
  "properties": {
    "iso:country":"US",
    "sg:address":"415 S F St",
    "sg:city":"Broken Bow",
    "sg:classifiers":[
        {
            "category":"Professional",
            "type":"Services"
        }
    ],
    "sg:phone":"+1 308 872 5700",
    "sg:postcode":"68822",
    "sg:province":"NE",
    "sg:tags":[
        "establishment"
    ],
    "wof:name":"Robert Winn Office",
    "wof:placetype":"venue"
},
  "geometry": {"coordinates":[-99.635643,41.400923],"type":"Point"}
}