{
  "type": "Feature",
  "properties": {
    "addr:full":"5132 Madison Ave Lincoln NE 68504",
    "addr:housenumber":"5132",
    "addr:postcode":"68504",
    "addr:street":"Madison Ave",
    "iso:country":"US",
    "sg:address":"5132 Madison Ave",
    "sg:city":"Lincoln",
    "sg:classifiers":[
        {
            "category":"Organizations",
            "subcategory":"Community Association",
            "type":"Services"
        }
    ],
    "sg:phone":"+1 402 466 1198",
    "sg:postcode":"68504",
    "sg:province":"NE",
    "wof:name":"Zeta PSI Frat",
    "wof:placetype":"venue"
},
  "geometry": {"coordinates":[-96.64876700000001,40.840371],"type":"Point"}
}