{
  "type": "Feature",
  "properties": {
    "addr:full":"2635 Verde Ln Sidney NE 69162",
    "addr:housenumber":"2635",
    "addr:postcode":"69162",
    "addr:street":"Verde Ln",
    "iso:country":"US",
    "sg:address":"2635 Verde Ln",
    "sg:city":"Sidney",
    "sg:classifiers":[
        {
            "category":"Home & Garden",
            "subcategory":"Household Appliances",
            "type":"Retail Goods"
        }
    ],
    "sg:phone":"+1 308 254 4229",
    "sg:postcode":"69162",
    "sg:province":"NE",
    "sg:tags":[
        "used",
        "merchandise"
    ],
    "wof:name":"Gales Appliance",
    "wof:placetype":"venue"
},
  "geometry": {"coordinates":[-102.98012,41.124759],"type":"Point"}
}