{
  "type": "Feature",
  "properties": {
    "iso:country":"US",
    "sg:address":"116 E 9th St",
    "sg:city":"Wood River",
    "sg:classifiers":[
        {
            "category":"Professional",
            "subcategory":"Accounting & Tax Preparation",
            "type":"Services"
        }
    ],
    "sg:phone":"+1 308 583 2206",
    "sg:postcode":"68883",
    "sg:province":"NE",
    "sg:tags":[
        "accountant"
    ],
    "wof:name":"Bangs & Stewart LLC",
    "wof:placetype":"venue"
},
  "geometry": {"coordinates":[-98.601483,40.820669],"type":"Point"}
}