{
  "type": "Feature",
  "properties": {
    "iso:country":"US",
    "sg:address":"2051 Harney St",
    "sg:city":"Omaha",
    "sg:classifiers":[
        {
            "category":"Professional",
            "subcategory":"Lawyer & Legal Services",
            "type":"Services"
        }
    ],
    "sg:phone":"+1 402 345 7600",
    "sg:postcode":"68102",
    "sg:province":"NE",
    "wof:name":"Vs Properties Llc",
    "wof:placetype":"venue"
},
  "geometry": {"coordinates":[-95.942852,41.256444],"type":"Point"}
}