{
  "type": "Feature",
  "properties": {
    "addr:full":"1215 Splitt Dr Murray NE 68409",
    "addr:housenumber":"1215",
    "addr:postcode":"68409",
    "addr:street":"Splitt Dr",
    "iso:country":"US",
    "sg:address":"1215 Splitt Dr",
    "sg:city":"Murray",
    "sg:classifiers":[
        {
            "category":"Building & Trades",
            "subcategory":"Electrical",
            "type":"Services"
        }
    ],
    "sg:phone":"+1 402 235 3226",
    "sg:postcode":"68409",
    "sg:province":"NE",
    "sg:tags":[
        "house",
        "electrical",
        "contractor"
    ],
    "wof:name":"Choice Electric Inc",
    "wof:placetype":"venue"
},
  "geometry": {"coordinates":[-95.900031,40.871332],"type":"Point"}
}