{
  "type": "Feature",
  "properties": {
    "addr:full":"101 Rd 123 Grant NE 69162",
    "addr:housenumber":"101",
    "addr:postcode":"69162",
    "addr:street":"Rd 123",
    "iso:country":"US",
    "sg:address":"101 Rd 123",
    "sg:city":"Grant",
    "sg:classifiers":[
        {
            "category":"Freight",
            "type":"Transportation"
        }
    ],
    "sg:phone":"+1 308 352 4617",
    "sg:postcode":"69162",
    "sg:province":"NE",
    "sg:tags":[
        "grain",
        "elevator"
    ],
    "wof:name":"Frenchman Valley Coop",
    "wof:placetype":"venue"
},
  "geometry": {"coordinates":[-102.887595,41.007754],"type":"Point"}
}