{
  "type": "Feature",
  "properties": {
    "iso:country":"US",
    "sg:address":"2001 Farnam St",
    "sg:city":"Omaha",
    "sg:classifiers":[
        {
            "category":"Shopping",
            "subcategory":"Clothing, Apparel, & Fashions",
            "type":"Retail Goods"
        },
        {
            "category":"Arts & Performance",
            "subcategory":"Arts Center",
            "type":"Entertainment"
        }
    ],
    "sg:phone":"+1 402 345 0147",
    "sg:postcode":"68102",
    "sg:province":"NE",
    "sg:tags":[
        "performing",
        "costume"
    ],
    "wof:name":"The Rose Costume Rentals",
    "wof:placetype":"venue"
},
  "geometry": {"coordinates":[-95.94229900000001,41.257599],"type":"Point"}
}