{
  "type": "Feature",
  "properties": {
    "iso:country":"US",
    "sg:address":"301 Capital St",
    "sg:city":"Yankton",
    "sg:classifiers":[
        {
            "category":"Personal",
            "type":"Services"
        }
    ],
    "sg:phone":"+1 605 660 3205",
    "sg:postcode":"57078",
    "sg:province":"NE",
    "sg:tags":[
        "therapist",
        "massage"
    ],
    "wof:name":"Yankton Therapeutic Massge",
    "wof:placetype":"venue"
},
  "geometry": {"coordinates":[-97.390495,42.871041],"type":"Point"}
}