{
  "type": "Feature",
  "properties": {
    "iso:country":"US",
    "sg:address":"2790 26th Ave",
    "sg:city":"Columbus",
    "sg:classifiers":[
        {
            "category":"Building & Trades",
            "subcategory":"Landscaping Services",
            "type":"Services"
        }
    ],
    "sg:phone":"+1 402 844 5000",
    "sg:postcode":"68601",
    "sg:province":"NE",
    "sg:tags":[
        "landscape",
        "contractor"
    ],
    "wof:name":"Landmark Landscapes",
    "wof:placetype":"venue"
},
  "geometry": {"coordinates":[-97.358829,41.442347],"type":"Point"}
}