{
  "type": "Feature",
  "properties": {
    "iso:country":"US",
    "sg:address":"2509 N 88th St",
    "sg:city":"Omaha",
    "sg:classifiers":[
        {
            "category":"Building & Trades",
            "subcategory":"Construction",
            "type":"Services"
        }
    ],
    "sg:phone":"+1 402 926 3381",
    "sg:postcode":"68134",
    "sg:province":"NE",
    "sg:tags":[
        "concrete",
        "sporting",
        "c",
        "contractor"
    ],
    "wof:name":"Suitco",
    "wof:placetype":"venue"
},
  "geometry": {"coordinates":[-96.04869600000001,41.283184],"type":"Point"}
}