{
  "type": "Feature",
  "properties": {
    "iso:country":"US",
    "sg:address":"1120 Jackson St",
    "sg:city":"Omaha",
    "sg:classifiers":[
        {
            "category":"Ice Cream",
            "type":"Food & Drink"
        }
    ],
    "sg:phone":"+1 402 341 5827",
    "sg:postcode":"68102",
    "sg:province":"NE",
    "sg:tags":[
        "frozen",
        "yogurt"
    ],
    "wof:name":"Ted and Wally's Ice Cream",
    "wof:placetype":"venue"
},
  "geometry": {"coordinates":[-95.930801,41.254398],"type":"Point"}
}