{
  "type": "Feature",
  "properties": {
    "addr:full":"1010 S 74th Plz Omaha NE 68114",
    "addr:housenumber":"1010",
    "addr:postcode":"68114",
    "addr:street":"S 74Th",
    "iso:country":"US",
    "sg:address":"1010 S 74th Plz",
    "sg:city":"Omaha",
    "sg:classifiers":[
        {
            "category":"Shopping",
            "subcategory":"Shoes",
            "type":"Retail Goods"
        }
    ],
    "sg:phone":"+1 402 392 2952",
    "sg:postcode":"68114",
    "sg:province":"NE",
    "wof:name":"Comfort Plus Shoe Center Inc",
    "wof:placetype":"venue"
},
  "geometry": {"coordinates":[-96.027854,41.250691],"type":"Point"}
}