{
  "type": "Feature",
  "properties": {
    "addr:full":"5512 N Oaks Blvd Omaha NE 68134",
    "addr:housenumber":"5512",
    "addr:postcode":"68134",
    "addr:street":"N Oaks Blvd",
    "iso:country":"US",
    "sg:address":"5512 N Oaks Blvd",
    "sg:city":"Omaha",
    "sg:classifiers":[
        {
            "category":"Professional",
            "subcategory":"Art Services",
            "type":"Services"
        }
    ],
    "sg:phone":"+1 402 573 5421",
    "sg:postcode":"68134",
    "sg:province":"NE",
    "sg:tags":[
        "commercial",
        "design"
    ],
    "wof:name":"Connie Yates Graphics",
    "wof:placetype":"venue"
},
  "geometry": {"coordinates":[-96.060688,41.309681],"type":"Point"}
}