{
  "type": "Feature",
  "properties": {
    "addr:full":"3324 20th St Columbus NE 68601",
    "addr:housenumber":"3324",
    "addr:postcode":"68601",
    "addr:street":"20Th St",
    "iso:country":"US",
    "sg:address":"3324 20th St",
    "sg:city":"Columbus",
    "sg:classifiers":[
        {
            "category":"Travel",
            "subcategory":"Hotels & Motels",
            "type":"Entertainment"
        }
    ],
    "sg:phone":"+1 402 563 3456",
    "sg:postcode":"68601",
    "sg:province":"NE",
    "sg:website":"www.super8.com",
    "wof:name":"Super 8 Motel",
    "wof:placetype":"venue"
},
  "geometry": {"coordinates":[-97.369297,41.436036],"type":"Point"}
}