{
  "type": "Feature",
  "properties": {
    "iso:country":"US",
    "sg:address":"310 S Court St",
    "sg:city":"Craig",
    "sg:classifiers":[
        {
            "category":"Professional",
            "type":"Services"
        }
    ],
    "sg:phone":"+1 402 377 2763",
    "sg:postcode":"68019",
    "sg:province":"NE",
    "sg:tags":[
        "establishment"
    ],
    "wof:name":"LGM Cycles",
    "wof:placetype":"venue"
},
  "geometry": {"coordinates":[-96.358073,41.783356],"type":"Point"}
}