{
  "type": "Feature",
  "properties": {
    "iso:country":"US",
    "sg:address":"501 S Sunset St",
    "sg:city":"Pierce",
    "sg:classifiers":[
        {
            "category":"Building & Trades",
            "subcategory":"Construction",
            "type":"Services"
        }
    ],
    "sg:phone":"+1 402 329 4688",
    "sg:postcode":"68767",
    "sg:province":"NE",
    "sg:tags":[
        "excavating",
        "contractor"
    ],
    "wof:name":"Witzel & Sons Construction",
    "wof:placetype":"venue"
},
  "geometry": {"coordinates":[-97.53841799999999,42.193155],"type":"Point"}
}