{
  "type": "Feature",
  "properties": {
    "addr:full":"1466 S D Rd Mitchell NE 69357",
    "addr:housenumber":"1466",
    "addr:postcode":"69357",
    "addr:street":"S D Rd",
    "iso:country":"US",
    "sg:address":"1466 S D Rd",
    "sg:city":"Mitchell",
    "sg:classifiers":[
        {
            "category":"Wholesale",
            "subcategory":"Machinery & Supplies",
            "type":"Manufacturing & Wholesale Goods"
        }
    ],
    "sg:phone":"+1 308 623 0120",
    "sg:postcode":"69357",
    "sg:province":"NE",
    "sg:tags":[
        "equipment",
        "mining"
    ],
    "wof:name":"Two Bits",
    "wof:placetype":"venue"
},
  "geometry": {"coordinates":[-103.800687,42.049599],"type":"Point"}
}