{
  "type": "Feature",
  "properties": {
    "addr:full":"812 154th Pleasant Dale NE 68423",
    "addr:housenumber":"812",
    "addr:postcode":"68423",
    "addr:street":"154Th Pleasant Dale Ne",
    "iso:country":"US",
    "sg:address":"812 154th",
    "sg:city":"Pleasant Dale",
    "sg:phone":"+1 402 795 5585",
    "sg:postcode":"68423",
    "sg:province":"NE",
    "sg:tags":[
        "farm",
        "corn",
        "wheat"
    ],
    "wof:name":"Elmer Danker",
    "wof:placetype":"venue"
},
  "geometry": {"coordinates":[-96.929757,40.799436],"type":"Point"}
}