{
  "type": "Feature",
  "properties": {
    "iso:country":"US",
    "sg:address":"2121 W O St",
    "sg:city":"Lincoln",
    "sg:classifiers":[
        {
            "category":"Building & Trades",
            "subcategory":"Construction",
            "type":"Services"
        }
    ],
    "sg:phone":"+1 402 421 7070",
    "sg:postcode":"68528",
    "sg:province":"NE",
    "sg:tags":[
        "dry wall",
        "contractor"
    ],
    "wof:name":"American Drywall",
    "wof:placetype":"venue"
},
  "geometry": {"coordinates":[-96.752821,40.813729],"type":"Point"}
}