{
  "type": "Feature",
  "properties": {
    "iso:country":"US",
    "sg:address":"2206 Longo Dr Ste 201",
    "sg:city":"Bellevue",
    "sg:classifiers":[
        {
            "category":"Health Services",
            "subcategory":"Doctor",
            "type":"Services"
        }
    ],
    "sg:phone":"+1 402 292 9170",
    "sg:postcode":"68005",
    "sg:province":"NE",
    "sg:tags":[
        "physician",
        "family",
        "practice",
        "surgeons",
        "medicine",
        "surgeon"
    ],
    "wof:name":"Ferguson Lorin E",
    "wof:placetype":"venue"
},
  "geometry": {"coordinates":[-95.923851,41.155867],"type":"Point"}
}