{
  "type": "Feature",
  "properties": {
    "addr:full":"2541 N 11th St Lincoln NE 68521",
    "addr:housenumber":"2541",
    "addr:postcode":"68521",
    "addr:street":"N 11Th St",
    "iso:country":"US",
    "sg:address":"2541 N 11th St",
    "sg:city":"Lincoln",
    "sg:classifiers":[
        {
            "category":"Shopping",
            "subcategory":"Discount & Variety Stores",
            "type":"Retail Goods"
        },
        {
            "category":"Shopping",
            "subcategory":"Department Store",
            "type":"Retail Goods"
        }
    ],
    "sg:phone":"+1 402 438 1409",
    "sg:postcode":"68521",
    "sg:province":"NE",
    "wof:name":"Family Dollar Stores",
    "wof:placetype":"venue"
},
  "geometry": {"coordinates":[-96.706115,40.839129],"type":"Point"}
}