{
  "type": "Feature",
  "properties": {
    "iso:country":"US",
    "sg:address":"4052 Washington St",
    "sg:city":"Lincoln",
    "sg:classifiers":[
        {
            "category":"Organizations",
            "subcategory":"Community Association",
            "type":"Services"
        }
    ],
    "sg:phone":"+1 402 489 9187",
    "sg:postcode":"68506",
    "sg:province":"NE",
    "wof:name":"Kiwanis International Inc",
    "wof:placetype":"venue"
},
  "geometry": {"coordinates":[-96.65871,40.797982],"type":"Point"}
}