{
  "type": "Feature",
  "properties": {
    "iso:country":"US",
    "sg:address":"11251 N 141st St",
    "sg:city":"Waverly",
    "sg:classifiers":[
        {
            "category":"Government",
            "subcategory":"Office",
            "type":"Public Place"
        }
    ],
    "sg:phone":"+1 402 786 2421",
    "sg:postcode":"68462",
    "sg:province":"NE",
    "wof:name":"Lancaster County Engineer Shop",
    "wof:placetype":"venue"
},
  "geometry": {"coordinates":[-96.530599,40.928225],"type":"Point"}
}