{
  "type": "Feature",
  "properties": {
    "addr:full":"6303 Center St Omaha NE 68106",
    "addr:housenumber":"6303",
    "addr:postcode":"68106",
    "addr:street":"Center St",
    "iso:country":"US",
    "sg:address":"6303 Center St",
    "sg:city":"Omaha",
    "sg:classifiers":[
        {
            "category":"Restaurant",
            "type":"Food & Drink"
        }
    ],
    "sg:phone":"+1 402 391 2011",
    "sg:postcode":"68106",
    "sg:province":"NE",
    "sg:tags":[
        "italian"
    ],
    "sg:website":"www.jimids.com",
    "wof:name":"Jimi D's",
    "wof:placetype":"venue"
},
  "geometry": {"coordinates":[-96.01016,41.237804],"type":"Point"}
}