{
  "type": "Feature",
  "properties": {
    "iso:country":"US",
    "sg:address":"6001 Dodge St",
    "sg:city":"Omaha",
    "sg:classifiers":[
        {
            "category":"Communications",
            "subcategory":"Radio Station",
            "type":"Services"
        }
    ],
    "sg:phone":"+1 402 559 5866",
    "sg:postcode":"68182",
    "sg:province":"NE",
    "wof:name":"Kvno 907 Fm Radio",
    "wof:placetype":"venue"
},
  "geometry": {"coordinates":[-96.004898,41.259602],"type":"Point"}
}