{
  "type": "Feature",
  "properties": {
    "iso:country":"US",
    "sg:address":"2820 Court St",
    "sg:city":"Beatrice",
    "sg:classifiers":[
        {
            "category":"Home & Garden",
            "subcategory":"Hardware",
            "type":"Retail Goods"
        }
    ],
    "sg:phone":"+1 402 223 3545",
    "sg:postcode":"68310",
    "sg:province":"NE",
    "wof:name":"Sack Do It Best Lumber",
    "wof:placetype":"venue"
},
  "geometry": {"coordinates":[-96.723071,40.265865],"type":"Point"}
}