{
  "type": "Feature",
  "properties": {
    "iso:country":"US",
    "sg:address":"3544 M Rd",
    "sg:city":"Syracuse",
    "sg:classifiers":[
        {
            "category":"Farming",
            "subcategory":"Livestock Farm",
            "type":"Manufacturing & Wholesale Goods"
        }
    ],
    "sg:phone":"+1 402 269 2689",
    "sg:postcode":"68446",
    "sg:province":"NE",
    "sg:tags":[
        "beef",
        "corn",
        "cash",
        "grain",
        "soybean",
        "cattle",
        "feedlot"
    ],
    "wof:name":"Dwight Eisenhouer",
    "wof:placetype":"venue"
},
  "geometry": {"coordinates":[-96.14127999999999,40.610181],"type":"Point"}
}