{
  "type": "Feature",
  "properties": {
    "iso:country":"US",
    "sg:address":"1510 17th Ave",
    "sg:city":"Sidney",
    "sg:classifiers":[
        {
            "category":"Manufacturing",
            "subcategory":"Motor Vehicles & Parts",
            "type":"Manufacturing & Wholesale Goods"
        }
    ],
    "sg:phone":"+1 308 254 0939",
    "sg:postcode":"69162",
    "sg:province":"NE",
    "sg:tags":[
        "body",
        "mfg"
    ],
    "wof:name":"Richard Nestor Inc",
    "wof:placetype":"venue"
},
  "geometry": {"coordinates":[-102.98524399999999,41.138578],"type":"Point"}
}