{
  "type": "Feature",
  "properties": {
    "addr:full":"8638 Keystone Dr Omaha NE 68134",
    "addr:housenumber":"8638",
    "addr:postcode":"68134",
    "addr:street":"Keystone Dr",
    "iso:country":"US",
    "sg:address":"8638 Keystone Dr",
    "sg:city":"Omaha",
    "sg:classifiers":[
        {
            "category":"Utilities",
            "subcategory":"Refuse",
            "type":"Services"
        }
    ],
    "sg:phone":"+1 402 571 0835",
    "sg:postcode":"68134",
    "sg:province":"NE",
    "sg:tags":[
        "collection",
        "garbage",
        "sanitation"
    ],
    "wof:name":"Weekly Pick Up Svc",
    "wof:placetype":"venue"
},
  "geometry": {"coordinates":[-96.047093,41.293933],"type":"Point"}
}