{
  "type": "Feature",
  "properties": {
    "iso:country":"US",
    "sg:address":"16019 Lamp St",
    "sg:city":"Omaha",
    "sg:classifiers":[
        {
            "category":"Shopping",
            "type":"Retail Goods"
        }
    ],
    "sg:phone":"+1 402 330 2724",
    "sg:postcode":"68118",
    "sg:province":"NE",
    "sg:tags":[
        "merchandise"
    ],
    "wof:name":"Classic Sportswear Awards LLC",
    "wof:placetype":"venue"
},
  "geometry": {"coordinates":[-96.167233,41.256119],"type":"Point"}
}