{
  "type": "Feature",
  "properties": {
    "iso:country":"US",
    "sg:address":"136 3rd Rd",
    "sg:city":"Howells",
    "sg:classifiers":[
        {
            "category":"Autos & Motor Vehicles",
            "subcategory":"Auto Supplies",
            "type":"Retail Goods"
        }
    ],
    "sg:phone":"+1 402 986 1101",
    "sg:postcode":"68641",
    "sg:province":"NE",
    "sg:tags":[
        "automobile",
        "parts"
    ],
    "wof:name":"Howell's Auto Supply NAPA",
    "wof:placetype":"venue"
},
  "geometry": {"coordinates":[-96.981106,41.746036],"type":"Point"}
}