{
  "type": "Feature",
  "properties": {
    "iso:country":"US",
    "sg:address":"7430 Joseph Ave",
    "sg:city":"La Vista",
    "sg:classifiers":[
        {
            "category":"Utilities",
            "subcategory":"Telephone",
            "type":"Services"
        }
    ],
    "sg:phone":"+1 402 597 8760",
    "sg:postcode":"68128",
    "sg:province":"NE",
    "sg:tags":[
        "communications"
    ],
    "wof:name":"Kevin Pufall",
    "wof:placetype":"venue"
},
  "geometry": {"coordinates":[-96.028683,41.18676],"type":"Point"}
}