{
  "type": "Feature",
  "properties": {
    "iso:country":"US",
    "sg:address":"323 W 4th Ave",
    "sg:city":"Holdrege",
    "sg:classifiers":[
        {
            "category":"Professional",
            "subcategory":"Accounting & Tax Preparation",
            "type":"Services"
        }
    ],
    "sg:phone":"+1 308 995 6117",
    "sg:postcode":"68949",
    "sg:province":"NE",
    "sg:tags":[
        "bookkeeping",
        "general"
    ],
    "wof:name":"Books & Balances Inc",
    "wof:placetype":"venue"
},
  "geometry": {"coordinates":[-99.384748,40.437805],"type":"Point"}
}