{
  "type": "Feature",
  "properties": {
    "addr:full":"408 Elk St Schuyler NE 68661",
    "addr:housenumber":"408",
    "addr:postcode":"68661",
    "addr:street":"Elk St",
    "iso:country":"US",
    "sg:address":"408 Elk St",
    "sg:city":"Schuyler",
    "sg:classifiers":[
        {
            "category":"Government",
            "subcategory":"Office",
            "type":"Public Place"
        }
    ],
    "sg:phone":"+1 402 471 2719",
    "sg:postcode":"68661",
    "sg:province":"NE",
    "wof:name":"Senator Chris Langemeier",
    "wof:placetype":"venue"
},
  "geometry": {"coordinates":[-97.066247,41.44148],"type":"Point"}
}