{
  "type": "Feature",
  "properties": {
    "addr:full":"2105 W 2nd St Grand Island NE 68803",
    "addr:housenumber":"2105",
    "addr:postcode":"68803",
    "addr:street":"W 2Nd St",
    "iso:country":"US",
    "sg:address":"2105 W 2nd St",
    "sg:city":"Grand Island",
    "sg:classifiers":[
        {
            "category":"Autos & Motor Vehicles",
            "subcategory":"Fuel & Gas Station",
            "type":"Retail Goods"
        }
    ],
    "sg:phone":"+1 308 382 9911",
    "sg:postcode":"68803",
    "sg:province":"NE",
    "sg:tags":[
        "oil"
    ],
    "wof:name":"Conoco 1 Stop",
    "wof:placetype":"venue"
},
  "geometry": {"coordinates":[-98.361259,40.91589],"type":"Point"}
}