{
  "type": "Feature",
  "properties": {
    "iso:country":"US",
    "sg:address":"14735 W Plz",
    "sg:city":"Omaha",
    "sg:classifiers":[
        {
            "category":"Real Estate",
            "subcategory":"Real Estate Operator",
            "type":"Services"
        }
    ],
    "sg:phone":"+1 402 895 4888",
    "sg:postcode":"68137",
    "sg:province":"NE",
    "sg:tags":[
        "apartment"
    ],
    "wof:name":"Stonybrook Apartments",
    "wof:placetype":"venue"
},
  "geometry": {"coordinates":[-96.14410700000001,41.199935],"type":"Point"}
}