{
  "type": "Feature",
  "properties": {
    "addr:full":"16683 Davenport Plz Omaha NE 68118",
    "addr:housenumber":"16683",
    "addr:postcode":"68118",
    "addr:street":"Davenport Plz",
    "iso:country":"US",
    "sg:address":"16683 Davenport Plz",
    "sg:city":"Omaha",
    "sg:classifiers":[
        {
            "category":"Restaurant",
            "type":"Food & Drink"
        }
    ],
    "sg:menulink":"http://www.allmenus.com/ne/mcardle/26449-melting-pot/menu/",
    "sg:phone":"+1 412 391 6358",
    "sg:postcode":"68118",
    "sg:province":"NE",
    "sg:tags":[
        "new",
        "american"
    ],
    "wof:name":"Melting Pot",
    "wof:placetype":"venue"
},
  "geometry": {"coordinates":[-96.176895,41.26138],"type":"Point"}
}