{
  "type": "Feature",
  "properties": {
    "iso:country":"US",
    "sg:address":"5000 S 73rd St",
    "sg:city":"Lincoln",
    "sg:classifiers":[
        {
            "category":"Professional",
            "subcategory":"Art Services",
            "type":"Services"
        }
    ],
    "sg:phone":"+1 402 435 8424",
    "sg:postcode":"68516",
    "sg:province":"NE",
    "sg:tags":[
        "graphic",
        "designer"
    ],
    "wof:name":"Slide Arts Graphic Design",
    "wof:placetype":"venue"
},
  "geometry": {"coordinates":[-96.62092699999999,40.764535],"type":"Point"}
}