{
  "type": "Feature",
  "properties": {
    "iso:country":"US",
    "sg:address":"2501 13th St",
    "sg:city":"Columbus",
    "sg:classifiers":[
        {
            "category":"Banks & Credit Unions",
            "subcategory":"Bank",
            "type":"Services"
        }
    ],
    "sg:phone":"+1 402 564 1234",
    "sg:postcode":"68601",
    "sg:province":"NE",
    "wof:name":"Columbus Bank & Trust Co",
    "wof:placetype":"venue"
},
  "geometry": {"coordinates":[-97.35939399999999,41.429271],"type":"Point"}
}