{
  "type": "Feature",
  "properties": {
    "addr:full":"983025 Nebraska Medical Ctr Omaha NE 68198",
    "addr:housenumber":"983025",
    "addr:postcode":"68198",
    "addr:street":"Medical",
    "iso:country":"US",
    "sg:address":"983025 Nebraska Medical Ctr",
    "sg:city":"Omaha",
    "sg:classifiers":[
        {
            "category":"Health Services",
            "subcategory":"Doctor",
            "type":"Services"
        }
    ],
    "sg:phone":"+1 402 559 4015",
    "sg:postcode":"68198",
    "sg:province":"NE",
    "sg:tags":[
        "medicine",
        "internal"
    ],
    "wof:name":"O'dell James R MD",
    "wof:placetype":"venue"
},
  "geometry": {"coordinates":[-95.975899,41.2551],"type":"Point"}
}