{
  "type": "Feature",
  "properties": {
    "addr:full":"6300 Pratt St Omaha NE 68104",
    "addr:housenumber":"6300",
    "addr:postcode":"68104",
    "addr:street":"Pratt St",
    "iso:country":"US",
    "sg:address":"6300 Pratt St",
    "sg:city":"Omaha",
    "sg:classifiers":[
        {
            "category":"Building & Trades",
            "subcategory":"Locksmith",
            "type":"Services"
        }
    ],
    "sg:phone":"+1 402 715 9825",
    "sg:postcode":"68104",
    "sg:province":"NE",
    "sg:tags":[
        "key"
    ],
    "wof:name":"A Locksmith 1 24 7",
    "wof:placetype":"venue"
},
  "geometry": {"coordinates":[-96.009519,41.292407],"type":"Point"}
}