{
  "type": "Feature",
  "properties": {
    "iso:country":"US",
    "sg:address":"74059 L Rd",
    "sg:city":"Holdrege",
    "sg:classifiers":[
        {
            "category":"Organizations",
            "subcategory":"Religious Organization",
            "type":"Services"
        }
    ],
    "sg:phone":"+1 308 995 4617",
    "sg:postcode":"68949",
    "sg:province":"NE",
    "sg:tags":[
        "church"
    ],
    "wof:name":"Holcomb Evangelical Free Chr",
    "wof:placetype":"venue"
},
  "geometry": {"coordinates":[-99.417805,40.55504],"type":"Point"}
}