{
  "type": "Feature",
  "properties": {
    "iso:country":"US",
    "sg:address":"2424 K St",
    "sg:city":"Omaha",
    "sg:classifiers":[
        {
            "category":"Organizations",
            "subcategory":"Religious Organization",
            "type":"Services"
        }
    ],
    "sg:phone":"+1 402 733 1224",
    "sg:postcode":"68107",
    "sg:province":"NE",
    "wof:name":"New Life S Omaha Frsqare Chrch",
    "wof:placetype":"venue"
},
  "geometry": {"coordinates":[-95.948213,41.213535],"type":"Point"}
}