{
  "type": "Feature",
  "properties": {
    "addr:full":"401 W 4th St Kearney NE 68845",
    "addr:housenumber":"401",
    "addr:postcode":"68845",
    "addr:street":"W 4Th St",
    "iso:country":"US",
    "sg:address":"401 W 4th St",
    "sg:city":"Kearney",
    "sg:classifiers":[
        {
            "category":"Wholesale",
            "subcategory":"Groceries",
            "type":"Manufacturing & Wholesale Goods"
        }
    ],
    "sg:phone":"+1 308 237 3151",
    "sg:postcode":"68845",
    "sg:province":"NE",
    "sg:tags":[
        "food",
        "product"
    ],
    "sg:website":"www.cashwa.com",
    "wof:name":"Cash-WA Distribution Inc",
    "wof:placetype":"venue"
},
  "geometry": {"coordinates":[-99.087102,40.678264],"type":"Point"}
}