{
  "type": "Feature",
  "properties": {
    "iso:country":"US",
    "sg:address":"4061 Teri Ln",
    "sg:city":"Lincoln",
    "sg:classifiers":[
        {
            "category":"Building & Trades",
            "subcategory":"Construction",
            "type":"Services"
        }
    ],
    "sg:phone":"+1 402 489 1885",
    "sg:postcode":"68502",
    "sg:province":"NE",
    "sg:tags":[
        "house",
        "industrial",
        "co"
    ],
    "wof:name":"Wooledge & Sons",
    "wof:placetype":"venue"
},
  "geometry": {"coordinates":[-96.678212,40.772274],"type":"Point"}
}