{
  "type": "Feature",
  "properties": {
    "iso:country":"US",
    "sg:address":"205 N Wheeler Ave",
    "sg:city":"Grand Island",
    "sg:classifiers":[
        {
            "category":"Government",
            "subcategory":"Office",
            "type":"Public Place"
        }
    ],
    "sg:phone":"+1 308 385 5095",
    "sg:postcode":"68801",
    "sg:province":"NE",
    "sg:tags":[
        "village"
    ],
    "sg:website":"www.cleancommunity.org",
    "wof:name":"Grand Island Clean Community",
    "wof:placetype":"venue"
},
  "geometry": {"coordinates":[-98.341689,40.924332],"type":"Point"}
}