{
  "type": "Feature",
  "properties": {
    "iso:country":"US",
    "sg:address":"3240 S 10th St",
    "sg:city":"Lincoln",
    "sg:classifiers":[
        {
            "category":"Communications",
            "subcategory":"Television Station",
            "type":"Services"
        }
    ],
    "sg:phone":"+1 402 434 8000",
    "sg:postcode":"68502",
    "sg:province":"NE",
    "wof:name":"Klkn-TV",
    "wof:placetype":"venue"
},
  "geometry": {"coordinates":[-96.70618,40.779571],"type":"Point"}
}