{
  "type": "Feature",
  "properties": {
    "iso:country":"US",
    "sg:address":"1701 Farnam St",
    "sg:city":"Omaha",
    "sg:classifiers":[
        {
            "category":"Government",
            "subcategory":"Office",
            "type":"Public Place"
        }
    ],
    "sg:phone":"+1 402 444 7168",
    "sg:postcode":"68102",
    "sg:province":"NE",
    "wof:name":"Douglas County Conciliation",
    "wof:placetype":"venue"
},
  "geometry": {"coordinates":[-95.93983900000001,41.257616],"type":"Point"}
}