{
  "type": "Feature",
  "properties": {
    "iso:country":"US",
    "sg:address":"22959 S 1 Rd",
    "sg:city":"Beatrice",
    "sg:classifiers":[
        {
            "category":"Building & Trades",
            "subcategory":"Landscaping Services",
            "type":"Services"
        }
    ],
    "sg:phone":"+1 402 228 1289",
    "sg:postcode":"68310",
    "sg:province":"NE",
    "sg:tags":[
        "lawn",
        "landscape",
        "maintenance",
        "grounds"
    ],
    "wof:name":"Greenkeeper Grounds Maint Co",
    "wof:placetype":"venue"
},
  "geometry": {"coordinates":[-96.72784299999999,40.300552],"type":"Point"}
}