{
  "type": "Feature",
  "properties": {
    "iso:country":"US",
    "sg:address":"2423 W Lincoln Hwy",
    "sg:city":"Grand Island",
    "sg:classifiers":[
        {
            "category":"Building & Trades",
            "subcategory":"Cleaning & Sanitation",
            "type":"Services"
        },
        {
            "category":"Building & Trades",
            "subcategory":"Landscaping Services",
            "type":"Services"
        }
    ],
    "sg:phone":"+1 308 384 2250",
    "sg:postcode":"68803",
    "sg:province":"NE",
    "sg:tags":[
        "operator",
        "sanitary",
        "dwelling",
        "snow",
        "removal"
    ],
    "wof:name":"Grand Island & Toms Tree Svc",
    "wof:placetype":"venue"
},
  "geometry": {"coordinates":[-98.365996,40.916781],"type":"Point"}
}