{
  "type": "Feature",
  "properties": {
    "addr:full":"4458 S 84th St Omaha NE 68127",
    "addr:housenumber":"4458",
    "addr:postcode":"68127",
    "addr:street":"S 84Th St",
    "iso:country":"US",
    "sg:address":"4458 S 84th St",
    "sg:city":"Omaha",
    "sg:classifiers":[
        {
            "category":"Organizations",
            "subcategory":"Religious Organization",
            "type":"Services"
        }
    ],
    "sg:phone":"+1 402 597 9323",
    "sg:postcode":"68127",
    "sg:province":"NE",
    "wof:name":"Youth For Christ",
    "wof:placetype":"venue"
},
  "geometry": {"coordinates":[-96.04316300000001,41.215966],"type":"Point"}
}