{
  "type": "Feature",
  "properties": {
    "iso:country":"US",
    "sg:address":"7425 Pacific St",
    "sg:city":"Omaha",
    "sg:classifiers":[
        {
            "category":"Restaurant",
            "type":"Food & Drink"
        }
    ],
    "sg:menulink":"http://www.allmenus.com/ne/omaha/11054-mckennas-bbq/menu/",
    "sg:phone":"+1 402 393 7427",
    "sg:postcode":"68114",
    "sg:province":"NE",
    "sg:tags":[
        "american"
    ],
    "wof:name":"McKenna's BBQ",
    "wof:placetype":"venue"
},
  "geometry": {"coordinates":[-96.02809600000001,41.248783],"type":"Point"}
}