{
  "type": "Feature",
  "properties": {
    "iso:country":"US",
    "sg:address":"23318 Adams St",
    "sg:city":"Eagle",
    "sg:classifiers":[
        {
            "category":"Building & Trades",
            "subcategory":"Construction",
            "type":"Services"
        }
    ],
    "sg:phone":"+1 402 781 9367",
    "sg:postcode":"68347",
    "sg:province":"NE",
    "sg:tags":[
        "house"
    ],
    "wof:name":"Brad Rolofson Const",
    "wof:placetype":"venue"
},
  "geometry": {"coordinates":[-96.403871,40.841995],"type":"Point"}
}