{
  "type": "Feature",
  "properties": {
    "addr:full":"14525 Industrial Rd Omaha NE 68144",
    "addr:housenumber":"14525",
    "addr:postcode":"68144",
    "addr:street":"Industrial Rd",
    "iso:country":"US",
    "sg:address":"14525 Industrial Rd",
    "sg:city":"Omaha",
    "sg:classifiers":[
        {
            "category":"Recreation",
            "subcategory":"Dog Park",
            "type":"Entertainment"
        },
        {
            "category":"Shopping",
            "subcategory":"Pets & Pet Supplies",
            "type":"Retail Goods"
        },
        {
            "category":"Building & Trades",
            "subcategory":"Construction",
            "type":"Services"
        },
        {
            "category":"Retail",
            "subcategory":"Animal Services",
            "type":"Services"
        }
    ],
    "sg:phone":"+1 402 392 1869",
    "sg:postcode":"68144",
    "sg:province":"NE",
    "sg:tags":[
        "training",
        "fence-sales",
        "contractor"
    ],
    "sg:website":"http://www.backyard-adventures.com",
    "wof:name":"Backyard Adventures",
    "wof:placetype":"venue"
},
  "geometry": {"coordinates":[-96.14000299999999,41.225533],"type":"Point"}
}