{
  "type": "Feature",
  "properties": {
    "iso:country":"US",
    "sg:address":"3821 20th St",
    "sg:city":"Columbus",
    "sg:classifiers":[
        {
            "category":"Organizations",
            "subcategory":"Religious Organization",
            "type":"Services"
        }
    ],
    "sg:phone":"+1 402 564 8334",
    "sg:postcode":"68601",
    "sg:province":"NE",
    "sg:tags":[
        "church"
    ],
    "wof:name":"St Isidore Church",
    "wof:placetype":"venue"
},
  "geometry": {"coordinates":[-97.37719199999999,41.435567],"type":"Point"}
}