{
  "type": "Feature",
  "properties": {
    "iso:country":"US",
    "sg:address":"6902 Aylesworth Ave",
    "sg:city":"Lincoln",
    "sg:classifiers":[
        {
            "category":"Retail",
            "subcategory":"Repair Shop",
            "type":"Services"
        }
    ],
    "sg:phone":"+1 402 466 4025",
    "sg:postcode":"68505",
    "sg:province":"NE",
    "sg:tags":[
        "trade",
        "contractor"
    ],
    "wof:name":"Phoenix Furniture & Upholstery",
    "wof:placetype":"venue"
},
  "geometry": {"coordinates":[-96.62500300000001,40.830011],"type":"Point"}
}