{
  "type": "Feature",
  "properties": {
    "addr:full":"625 S Pine St Valley NE 68064",
    "addr:housenumber":"625",
    "addr:postcode":"68064",
    "addr:street":"S Pine St",
    "iso:country":"US",
    "sg:address":"625 S Pine St",
    "sg:city":"Valley",
    "sg:classifiers":[
        {
            "category":"Health Services",
            "subcategory":"Doctor",
            "type":"Services"
        }
    ],
    "sg:phone":"+1 402 359 2277",
    "sg:postcode":"68064",
    "sg:province":"NE",
    "sg:tags":[
        "physician",
        "surgeon"
    ],
    "wof:name":"Physicians Clinic",
    "wof:placetype":"venue"
},
  "geometry": {"coordinates":[-96.343999,41.307505],"type":"Point"}
}