{
  "type": "Feature",
  "properties": {
    "iso:country":"US",
    "sg:address":"210 W 3rd St",
    "sg:city":"Alliance",
    "sg:classifiers":[
        {
            "category":"Utilities",
            "subcategory":"Cable",
            "type":"Services"
        }
    ],
    "sg:phone":"+1 308 762 4830",
    "sg:postcode":"69301",
    "sg:province":"NE",
    "sg:tags":[
        "television"
    ],
    "wof:name":"Cable Television",
    "wof:placetype":"venue"
},
  "geometry": {"coordinates":[-102.872243,42.097228],"type":"Point"}
}