{
  "type": "Feature",
  "properties": {
    "iso:country":"US",
    "sg:address":"615 Main St",
    "sg:city":"Verdigre",
    "sg:classifiers":[
        {
            "category":"Real Estate",
            "subcategory":"Real Estate Agent",
            "type":"Services"
        }
    ],
    "sg:phone":"+1 402 668 2237",
    "sg:postcode":"68783",
    "sg:province":"NE",
    "sg:tags":[
        "authorities",
        "housing"
    ],
    "wof:name":"Verdigre Housing Authority",
    "wof:placetype":"venue"
},
  "geometry": {"coordinates":[-98.033272,42.592483],"type":"Point"}
}