{
  "type": "Feature",
  "properties": {
    "iso:country":"US",
    "sg:address":"14540 Jamestown St",
    "sg:city":"Waverly",
    "sg:classifiers":[
        {
            "category":"Food & Beverages",
            "subcategory":"Fruits & Vegetables",
            "type":"Retail Goods"
        }
    ],
    "sg:phone":"+1 402 786 2304",
    "sg:postcode":"68462",
    "sg:province":"NE",
    "sg:tags":[
        "produce"
    ],
    "wof:name":"Page Produce",
    "wof:placetype":"venue"
},
  "geometry": {"coordinates":[-96.522177,40.916693],"type":"Point"}
}