{
  "type": "Feature",
  "properties": {
    "iso:country":"US",
    "sg:address":"210 Germand St",
    "sg:city":"Fullerton",
    "sg:classifiers":[
        {
            "category":"Organizations",
            "subcategory":"Religious Organization",
            "type":"Services"
        }
    ],
    "sg:phone":"+1 308 536 2450",
    "sg:postcode":"68638",
    "sg:province":"NE",
    "sg:tags":[
        "church"
    ],
    "wof:name":"Victory Baptist Church",
    "wof:placetype":"venue"
},
  "geometry": {"coordinates":[-97.975245,41.364271],"type":"Point"}
}