{
  "type": "Feature",
  "properties": {
    "iso:country":"US",
    "sg:address":"3845 W Lincoln Ave",
    "sg:city":"Ayr",
    "sg:classifiers":[
        {
            "category":"Manufacturing",
            "subcategory":"Tools & Machinery",
            "type":"Manufacturing & Wholesale Goods"
        }
    ],
    "sg:phone":"+1 402 463 6545",
    "sg:postcode":"68925",
    "sg:province":"NE",
    "sg:tags":[
        "machine",
        "shop"
    ],
    "wof:name":"Phelps Manufacturing",
    "wof:placetype":"venue"
},
  "geometry": {"coordinates":[-98.434185,40.437316],"type":"Point"}
}