{
  "type": "Feature",
  "properties": {
    "iso:country":"US",
    "sg:address":"16481 E Sargent Rd",
    "sg:city":"Filley",
    "sg:classifiers":[
        {
            "category":"Farming",
            "subcategory":"Farm",
            "type":"Manufacturing & Wholesale Goods"
        }
    ],
    "sg:phone":"+1 402 662 3515",
    "sg:postcode":"68357",
    "sg:province":"NE",
    "sg:tags":[
        "crop",
        "general"
    ],
    "wof:name":"Busboom Farms",
    "wof:placetype":"venue"
},
  "geometry": {"coordinates":[-96.499335,40.291182],"type":"Point"}
}