{
  "type": "Feature",
  "properties": {
    "addr:full":"36033 W Nelson Rd Wallace NE 69169",
    "addr:housenumber":"36033",
    "addr:postcode":"69169",
    "addr:street":"W Nelson Rd",
    "iso:country":"US",
    "sg:address":"36033 W Nelson Rd",
    "sg:city":"Wallace",
    "sg:classifiers":[
        {
            "category":"Building & Trades",
            "subcategory":"Construction",
            "type":"Services"
        }
    ],
    "sg:phone":"+1 308 387 4671",
    "sg:postcode":"69169",
    "sg:province":"NE",
    "sg:tags":[
        "general",
        "contractor"
    ],
    "wof:name":"Tim Vapenik Construction",
    "wof:placetype":"venue"
},
  "geometry": {"coordinates":[-101.189769,40.84292],"type":"Point"}
}