{
  "type": "Feature",
  "properties": {
    "addr:full":"11620 Arbor St Omaha NE 68144",
    "addr:housenumber":"11620",
    "addr:postcode":"68144",
    "addr:street":"Arbor St",
    "iso:country":"US",
    "sg:address":"11620 Arbor St",
    "sg:city":"Omaha",
    "sg:classifiers":[
        {
            "category":"Utilities",
            "type":"Services"
        }
    ],
    "sg:phone":"+1 402 330 1866",
    "sg:postcode":"68144",
    "sg:province":"NE",
    "sg:tags":[
        "locating"
    ],
    "sg:website":"www.ne-diggers.com",
    "wof:name":"Great Plains One-Call",
    "wof:placetype":"venue"
},
  "geometry": {"coordinates":[-96.094137,41.23604],"type":"Point"}
}