{
  "type": "Feature",
  "properties": {
    "addr:full":"1402 Martha St Omaha NE 68108",
    "addr:housenumber":"1402",
    "addr:postcode":"68108",
    "addr:street":"Martha St",
    "iso:country":"US",
    "sg:address":"1402 Martha St",
    "sg:city":"Omaha",
    "sg:classifiers":[
        {
            "category":"Social Services",
            "subcategory":"Job Training",
            "type":"Services"
        }
    ],
    "sg:phone":"+1 402 991 9544",
    "sg:postcode":"68108",
    "sg:province":"NE",
    "sg:tags":[
        "rehabilitation"
    ],
    "wof:name":"Grove Rehab Svc",
    "wof:placetype":"venue"
},
  "geometry": {"coordinates":[-95.93600499999999,41.238274],"type":"Point"}
}