{
  "type": "Feature",
  "properties": {
    "iso:country":"US",
    "sg:address":"5935 Henninger Dr",
    "sg:city":"Omaha",
    "sg:classifiers":[
        {
            "category":"Local Transit",
            "type":"Transportation"
        }
    ],
    "sg:phone":"+1 402 342 0404",
    "sg:postcode":"68104",
    "sg:province":"NE",
    "sg:tags":[
        "ambulance"
    ],
    "wof:name":"American Ambulance Svc",
    "wof:placetype":"venue"
},
  "geometry": {"coordinates":[-96.00162899999999,41.315548],"type":"Point"}
}