{
  "type": "Feature",
  "properties": {
    "addr:full":"6001 Kenwood Cir Lincoln NE 68516",
    "addr:housenumber":"6001",
    "addr:postcode":"68516",
    "addr:street":"Kenwood Cir",
    "iso:country":"US",
    "sg:address":"6001 Kenwood Cir",
    "sg:city":"Lincoln",
    "sg:classifiers":[
        {
            "category":"Professional",
            "subcategory":"Accounting & Tax Preparation",
            "type":"Services"
        }
    ],
    "sg:phone":"+1 402 483 1224",
    "sg:postcode":"68516",
    "sg:province":"NE",
    "sg:tags":[
        "return"
    ],
    "wof:name":"General Business Services",
    "wof:placetype":"venue"
},
  "geometry": {"coordinates":[-96.638972,40.768767],"type":"Point"}
}