{
  "type": "Feature",
  "properties": {
    "addr:full":"830 E 23rd St Fremont NE 68025",
    "addr:housenumber":"830",
    "addr:postcode":"68025",
    "addr:street":"E 23Rd St",
    "iso:country":"US",
    "sg:address":"830 E 23rd St",
    "sg:city":"Fremont",
    "sg:classifiers":[
        {
            "category":"Restaurant",
            "type":"Food & Drink"
        }
    ],
    "sg:phone":"+1 402 721 4422",
    "sg:postcode":"68025",
    "sg:province":"NE",
    "sg:tags":[
        "eating"
    ],
    "sg:website":"www.usasteakbuffet.net",
    "wof:name":"USA Steak Buffet 109",
    "wof:placetype":"venue"
},
  "geometry": {"coordinates":[-96.48705200000001,41.451589],"type":"Point"}
}