{
  "type": "Feature",
  "properties": {
    "addr:full":"3701 N 16th St Omaha NE 68110",
    "addr:housenumber":"3701",
    "addr:postcode":"68110",
    "addr:street":"N 16Th St",
    "iso:country":"US",
    "sg:address":"3701 N 16th St",
    "sg:city":"Omaha",
    "sg:classifiers":[
        {
            "category":"Freight",
            "type":"Transportation"
        }
    ],
    "sg:phone":"+1 402 453 8281",
    "sg:postcode":"68110",
    "sg:province":"NE",
    "sg:tags":[
        "fluid",
        "power",
        "mfg"
    ],
    "sg:website":"www.ahigears.com",
    "wof:name":"American Hydraulics Inc",
    "wof:placetype":"venue"
},
  "geometry": {"coordinates":[-95.937348,41.293338],"type":"Point"}
}