{
  "type": "Feature",
  "properties": {
    "iso:country":"US",
    "sg:address":"407 Saint James Ave",
    "sg:city":"Wynot",
    "sg:classifiers":[
        {
            "category":"Home & Garden",
            "subcategory":"Hardware",
            "type":"Retail Goods"
        }
    ],
    "sg:phone":"+1 402 357 2308",
    "sg:postcode":"68792",
    "sg:province":"NE",
    "wof:name":"Wynot Farm Store",
    "wof:placetype":"venue"
},
  "geometry": {"coordinates":[-97.16940700000001,42.740128],"type":"Point"}
}