{
  "type": "Feature",
  "properties": {
    "addr:full":"100 W 56th St Kearney NE 68847",
    "addr:housenumber":"100",
    "addr:postcode":"68847",
    "addr:street":"W 56Th St",
    "iso:country":"US",
    "sg:address":"100 W 56th St",
    "sg:city":"Kearney",
    "sg:classifiers":[
        {
            "category":"Restaurant",
            "type":"Food & Drink"
        }
    ],
    "sg:menulink":"http://www.allmenus.com/ne/kearney/158930-arbys/menu/",
    "sg:phone":"+1 308 234 4559",
    "sg:postcode":"68847",
    "sg:province":"NE",
    "sg:tags":[
        "burger",
        "american"
    ],
    "wof:name":"Arby's",
    "wof:placetype":"venue"
},
  "geometry": {"coordinates":[-99.08191600000001,40.72837],"type":"Point"}
}