{
  "type": "Feature",
  "properties": {
    "iso:country":"US",
    "sg:address":"301 Industrial Dr",
    "sg:city":"Bellevue",
    "sg:classifiers":[
        {
            "category":"Wholesale",
            "subcategory":"Non-durable Goods",
            "type":"Manufacturing & Wholesale Goods"
        }
    ],
    "sg:phone":"+1 402 291 3100",
    "sg:postcode":"68005",
    "sg:province":"NE",
    "wof:name":"Packaging Film Group",
    "wof:placetype":"venue"
},
  "geometry": {"coordinates":[-95.890984,41.125954],"type":"Point"}
}