{
  "type": "Feature",
  "properties": {
    "iso:country":"US",
    "sg:address":"643 N 98th St",
    "sg:city":"Omaha",
    "sg:classifiers":[
        {
            "category":"Professional",
            "subcategory":"Business Services",
            "type":"Services"
        },
        {
            "category":"Professional",
            "subcategory":"Management & Consulting",
            "type":"Services"
        }
    ],
    "sg:phone":"+1 402 390 9111",
    "sg:postcode":"68114",
    "sg:province":"NE",
    "sg:tags":[
        "lecture",
        "bureau",
        "seminar"
    ],
    "wof:name":"Greenelight Professional Dev",
    "wof:placetype":"venue"
},
  "geometry": {"coordinates":[-96.065471,41.265222],"type":"Point"}
}