{
  "type": "Feature",
  "properties": {
    "iso:country":"US",
    "sg:address":"7865 S 84th St",
    "sg:city":"La Vista",
    "sg:classifiers":[
        {
            "category":"Restaurant",
            "type":"Food & Drink"
        }
    ],
    "sg:phone":"+1 402 592 8800",
    "sg:postcode":"68128",
    "sg:province":"NE",
    "sg:tags":[
        "drinking",
        "eating"
    ],
    "wof:name":"Chilis",
    "wof:placetype":"venue"
},
  "geometry": {"coordinates":[-96.04289799999999,41.180175],"type":"Point"}
}