{
  "type": "Feature",
  "properties": {
    "iso:country":"US",
    "sg:address":"4224 S 133rd St",
    "sg:city":"Omaha",
    "sg:classifiers":[
        {
            "category":"Professional",
            "subcategory":"Computer Services",
            "type":"Services"
        }
    ],
    "sg:phone":"+1 402 334 0333",
    "sg:postcode":"68137",
    "sg:province":"NE",
    "sg:tags":[
        "consultant",
        "consulting",
        "designer",
        "sales",
        "retail"
    ],
    "wof:name":"Kalos Group Inc",
    "wof:placetype":"venue"
},
  "geometry": {"coordinates":[-96.12150200000001,41.218128],"type":"Point"}
}