{
  "type": "Feature",
  "properties": {
    "iso:country":"US",
    "sg:address":"700 N Webb Rd",
    "sg:city":"Grand Island",
    "sg:classifiers":[
        {
            "category":"Banks & Credit Unions",
            "subcategory":"Financial Services",
            "type":"Services"
        }
    ],
    "sg:phone":"+1 308 381 1554",
    "sg:postcode":"68803",
    "sg:province":"NE",
    "sg:tags":[
        "company",
        "holding"
    ],
    "sg:website":"www.tieronebank.com/",
    "wof:name":"United Nebraska Financial Co",
    "wof:placetype":"venue"
},
  "geometry": {"coordinates":[-98.378575,40.923758],"type":"Point"}
}