{
  "type": "Feature",
  "properties": {
    "iso:country":"US",
    "sg:address":"4832 B Rd",
    "sg:city":"Nehawka",
    "sg:phone":"+1 402 227 2009",
    "sg:postcode":"68413",
    "sg:province":"NE",
    "sg:tags":[
        "farm",
        "corn"
    ],
    "wof:name":"King Hill Farms Ltd",
    "wof:placetype":"venue"
},
  "geometry": {"coordinates":[-96.00498,40.769091],"type":"Point"}
}