{
  "type": "Feature",
  "properties": {
    "iso:country":"US",
    "sg:address":"302 Elm St",
    "sg:city":"Laurel",
    "sg:classifiers":[
        {
            "category":"Organizations",
            "subcategory":"Religious Organization",
            "type":"Services"
        }
    ],
    "sg:phone":"+1 402 256 3781",
    "sg:postcode":"68745",
    "sg:province":"NE",
    "sg:tags":[
        "church"
    ],
    "wof:name":"United Methodist Church",
    "wof:placetype":"venue"
},
  "geometry": {"coordinates":[-97.091196,42.428419],"type":"Point"}
}