{
  "type": "Feature",
  "properties": {
    "addr:full":"3878 California St Omaha NE 68131",
    "addr:housenumber":"3878",
    "addr:postcode":"68131",
    "addr:street":"California St",
    "iso:country":"US",
    "sg:address":"3878 California St",
    "sg:city":"Omaha",
    "sg:classifiers":[
        {
            "category":"Organizations",
            "subcategory":"Religious Organization",
            "type":"Services"
        }
    ],
    "sg:phone":"+1 402 551 0290",
    "sg:postcode":"68131",
    "sg:province":"NE",
    "sg:tags":[
        "monastery",
        "convent"
    ],
    "wof:name":"Dominican Sisters",
    "wof:placetype":"venue"
},
  "geometry": {"coordinates":[-95.97163399999999,41.264847],"type":"Point"}
}