{
  "type": "Feature",
  "properties": {
    "iso:country":"US",
    "sg:address":"537 Morehead St",
    "sg:city":"Chadron",
    "sg:classifiers":[
        {
            "category":"Retail",
            "subcategory":"Auto Repair",
            "type":"Services"
        }
    ],
    "sg:phone":"+1 308 432 2008",
    "sg:postcode":"69337",
    "sg:province":"NE",
    "sg:tags":[
        "automotive"
    ],
    "wof:name":"Schott Repairs",
    "wof:placetype":"venue"
},
  "geometry": {"coordinates":[-103.003978,42.826349],"type":"Point"}
}