{
  "type": "Feature",
  "properties": {
    "iso:country":"US",
    "sg:address":"5882 State Hwy 133",
    "sg:city":"Blair",
    "sg:classifiers":[
        {
            "category":"Building & Trades",
            "subcategory":"Plumbing",
            "type":"Services"
        }
    ],
    "sg:phone":"+1 402 426 4056",
    "sg:postcode":"68008",
    "sg:province":"NE",
    "sg:tags":[
        "contractor"
    ],
    "wof:name":"Suverkrubbe Plumbing",
    "wof:placetype":"venue"
},
  "geometry": {"coordinates":[-96.13976,41.464321],"type":"Point"}
}