{
  "type": "Feature",
  "properties": {
    "iso:country":"US",
    "sg:address":"1208 Central Ave",
    "sg:city":"Auburn",
    "sg:classifiers":[
        {
            "category":"Health Services",
            "subcategory":"Chiropractor",
            "type":"Services"
        }
    ],
    "sg:phone":"+1 402 274 5001",
    "sg:postcode":"68305",
    "sg:province":"NE",
    "sg:tags":[
        "chiropractic"
    ],
    "wof:name":"Allgood Family Chiropractic Pc",
    "wof:placetype":"venue"
},
  "geometry": {"coordinates":[-95.841672,40.392808],"type":"Point"}
}