{
  "type": "Feature",
  "properties": {
    "iso:country":"US",
    "sg:address":"2520 S 130th Ave",
    "sg:city":"Omaha",
    "sg:classifiers":[
        {
            "category":"Shopping",
            "subcategory":"Florist",
            "type":"Retail Goods"
        }
    ],
    "sg:phone":"+1 402 397 4536",
    "sg:postcode":"68144",
    "sg:province":"NE",
    "sg:website":"www.gobeyondthevine.com",
    "wof:name":"Beyond The Vine",
    "wof:placetype":"venue"
},
  "geometry": {"coordinates":[-96.117535,41.234284],"type":"Point"}
}