{
  "type": "Feature",
  "properties": {
    "addr:full":"9318 N 34th St Omaha NE 68112",
    "addr:housenumber":"9318",
    "addr:postcode":"68112",
    "addr:street":"N 34Th St",
    "iso:country":"US",
    "sg:address":"9318 N 34th St",
    "sg:city":"Omaha",
    "sg:classifiers":[
        {
            "category":"Organizations",
            "subcategory":"Community Association",
            "type":"Services"
        }
    ],
    "sg:phone":"+1 402 457 5007",
    "sg:postcode":"68112",
    "sg:province":"NE",
    "sg:tags":[
        "veteran",
        "membership"
    ],
    "wof:name":"Veterans Of Foreign Wars",
    "wof:placetype":"venue"
},
  "geometry": {"coordinates":[-95.969742,41.344428],"type":"Point"}
}