{
  "type": "Feature",
  "properties": {
    "iso:country":"US",
    "sg:address":"405 2nd St",
    "sg:city":"Brunswick",
    "sg:classifiers":[
        {
            "category":"Bars & Pubs",
            "type":"Food & Drink"
        }
    ],
    "sg:phone":"+1 402 842 2020",
    "sg:postcode":"68770",
    "sg:province":"NE",
    "wof:name":"B & R Bar & Grill",
    "wof:placetype":"venue"
},
  "geometry": {"coordinates":[-96.711068,42.564535],"type":"Point"}
}