{
  "type": "Feature",
  "properties": {
    "iso:country":"US",
    "sg:address":"2204 E 28 Rd",
    "sg:city":"Hordville",
    "sg:classifiers":[
        {
            "category":"Personal",
            "subcategory":"Beauty Salon",
            "type":"Services"
        }
    ],
    "sg:phone":"+1 402 757 3240",
    "sg:postcode":"68846",
    "sg:province":"NE",
    "wof:name":"Backdoor",
    "wof:placetype":"venue"
},
  "geometry": {"coordinates":[-97.879034,41.089928],"type":"Point"}
}