{
  "type": "Feature",
  "properties": {
    "iso:country":"US",
    "sg:address":"109 Patterson St",
    "sg:city":"Cambridge",
    "sg:classifiers":[
        {
            "category":"Wholesale",
            "subcategory":"Farm Supplies",
            "type":"Manufacturing & Wholesale Goods"
        },
        {
            "category":"Shopping",
            "type":"Retail Goods"
        }
    ],
    "sg:phone":"+1 308 697 4813",
    "sg:postcode":"69022",
    "sg:province":"NE",
    "sg:tags":[
        "feed",
        "merchandise"
    ],
    "wof:name":"Whipple Feeds Inc",
    "wof:placetype":"venue"
},
  "geometry": {"coordinates":[-100.16597400000001,40.278943],"type":"Point"}
}