{
  "type": "Feature",
  "properties": {
    "addr:full":"8031 W Center Rd Rmp Omaha NE 68124",
    "addr:housenumber":"8031",
    "addr:postcode":"68124",
    "addr:street":"W Center Rd",
    "iso:country":"US",
    "sg:address":"8031 W Center Rd Rmp",
    "sg:city":"Omaha",
    "sg:classifiers":[
        {
            "category":"Personal",
            "subcategory":"Hair Removal",
            "type":"Services"
        }
    ],
    "sg:phone":"+1 402 397 3710",
    "sg:postcode":"68124",
    "sg:province":"NE",
    "wof:name":"Assoction Nn-Profit Cr Counsel",
    "wof:placetype":"venue"
},
  "geometry": {"coordinates":[-96.03728099999999,41.234035],"type":"Point"}
}