{
  "type": "Feature",
  "properties": {
    "addr:full":"21757 Platteview Rd Gretna NE 68028",
    "addr:postcode":"21757;68028",
    "addr:street":"Platteview Rd",
    "iso:country":"US",
    "sg:address":"21757 Platteview Rd",
    "sg:city":"Gretna",
    "sg:classifiers":[
        {
            "category":"Retail",
            "subcategory":"Auto Repair",
            "type":"Services"
        }
    ],
    "sg:phone":"+1 402 332 0340",
    "sg:postcode":"68028",
    "sg:province":"NE",
    "sg:tags":[
        "truck"
    ],
    "wof:name":"Williams Truck & Trailer Rpr",
    "wof:placetype":"venue"
},
  "geometry": {"coordinates":[-96.253845,41.088641],"type":"Point"}
}