{
  "type": "Feature",
  "properties": {
    "addr:full":"103 E Main St Pierce NE 68767",
    "addr:housenumber":"103",
    "addr:postcode":"68767",
    "addr:street":"E Main St",
    "iso:country":"US",
    "sg:address":"103 E Main St",
    "sg:city":"Pierce",
    "sg:classifiers":[
        {
            "category":"Sports & Exercise",
            "subcategory":"Gym",
            "type":"Entertainment"
        }
    ],
    "sg:phone":"+1 402 329 6630",
    "sg:postcode":"68767",
    "sg:province":"NE",
    "sg:tags":[
        "club",
        "health",
        "studio",
        "gymnasium"
    ],
    "wof:name":"Fitness 4U",
    "wof:placetype":"venue"
},
  "geometry": {"coordinates":[-97.526076,42.19912],"type":"Point"}
}