{
  "type": "Feature",
  "properties": {
    "iso:country":"US",
    "sg:address":"1722 E 20th St",
    "sg:city":"Scottsbluff",
    "sg:classifiers":[
        {
            "category":"Retail",
            "subcategory":"Auto Repair",
            "type":"Services"
        }
    ],
    "sg:phone":"+1 308 632 6911",
    "sg:postcode":"69361",
    "sg:province":"NE",
    "sg:tags":[
        "automotive",
        "wrecker"
    ],
    "wof:name":"Al's Towing Inc",
    "wof:placetype":"venue"
},
  "geometry": {"coordinates":[-103.64169800000001,41.866724],"type":"Point"}
}