{
  "type": "Feature",
  "properties": {
    "addr:full":"4725 Prescott Ave Lincoln NE 68506",
    "addr:housenumber":"4725",
    "addr:postcode":"68506",
    "addr:street":"Prescott Ave",
    "iso:country":"US",
    "sg:address":"4725 Prescott Ave",
    "sg:city":"Lincoln",
    "sg:classifiers":[
        {
            "category":"Food & Beverages",
            "subcategory":"Bakery",
            "type":"Retail Goods"
        }
    ],
    "sg:phone":"+1 402 488 7349",
    "sg:postcode":"68506",
    "sg:province":"NE",
    "sg:tags":[
        "baker"
    ],
    "wof:name":"Conroy's Bakery Shoppe",
    "wof:placetype":"venue"
},
  "geometry": {"coordinates":[-96.654319,40.772834],"type":"Point"}
}