{
  "type": "Feature",
  "properties": {
    "iso:country":"US",
    "sg:address":"2818 Ave G",
    "sg:city":"Scottsbluff",
    "sg:classifiers":[
        {
            "category":"Social Services",
            "subcategory":"Child Care",
            "type":"Services"
        }
    ],
    "sg:phone":"+1 308 635 7397",
    "sg:postcode":"69361",
    "sg:province":"NE",
    "sg:tags":[
        "day"
    ],
    "wof:name":"Lollipop Lane CC",
    "wof:placetype":"venue"
},
  "geometry": {"coordinates":[-103.671954,41.875513],"type":"Point"}
}