{
  "type": "Feature",
  "properties": {
    "iso:country":"US",
    "sg:address":"1107 Redmond St",
    "sg:city":"Yankton",
    "sg:classifiers":[
        {
            "category":"Building & Trades",
            "subcategory":"Construction",
            "type":"Services"
        }
    ],
    "sg:phone":"+1 605 668 0905",
    "sg:postcode":"57078",
    "sg:province":"NE",
    "sg:tags":[
        "concrete",
        "contractor"
    ],
    "wof:name":"CSC Construction Inc",
    "wof:placetype":"venue"
},
  "geometry": {"coordinates":[-97.411461,42.881368],"type":"Point"}
}