{
  "type": "Feature",
  "properties": {
    "addr:full":"612 Hill View Dr Sutherland NE 69165",
    "addr:housenumber":"612",
    "addr:postcode":"69165",
    "addr:street":"Hill View Dr",
    "iso:country":"US",
    "sg:address":"612 Hill View Dr",
    "sg:city":"Sutherland",
    "sg:classifiers":[
        {
            "category":"Building & Trades",
            "subcategory":"Electrical",
            "type":"Services"
        }
    ],
    "sg:phone":"+1 308 386 2308",
    "sg:postcode":"69165",
    "sg:province":"NE",
    "sg:tags":[
        "electric",
        "contractor"
    ],
    "wof:name":"Tory Copeland Electric",
    "wof:placetype":"venue"
},
  "geometry": {"coordinates":[-101.11882,41.162278],"type":"Point"}
}