{
  "type": "Feature",
  "properties": {
    "addr:full":"109 N 5th St Page NE 68767",
    "addr:housenumber":"109",
    "addr:postcode":"68767",
    "addr:street":"N 5Th St",
    "iso:country":"US",
    "sg:address":"109 N 5th St",
    "sg:city":"Page",
    "sg:classifiers":[
        {
            "category":"Personal",
            "subcategory":"Beauty Salon",
            "type":"Services"
        }
    ],
    "sg:phone":"+1 402 338 5353",
    "sg:postcode":"68767",
    "sg:province":"NE",
    "wof:name":"Rita's Hair Hut",
    "wof:placetype":"venue"
},
  "geometry": {"coordinates":[-97.5299,42.199397],"type":"Point"}
}