{
  "type": "Feature",
  "properties": {
    "iso:country":"US",
    "sg:address":"1025 S Saddle Creek Rd",
    "sg:city":"Omaha",
    "sg:classifiers":[
        {
            "category":"Social Services",
            "subcategory":"Child Care",
            "type":"Services"
        }
    ],
    "sg:phone":"+1 402 558 7050",
    "sg:postcode":"68106",
    "sg:province":"NE",
    "sg:tags":[
        "day"
    ],
    "sg:website":"www.donnaslittledarlings.com",
    "wof:name":"Donna's Little Darlings",
    "wof:placetype":"venue"
},
  "geometry": {"coordinates":[-95.987396,41.249298],"type":"Point"}
}