{
  "type": "Feature",
  "properties": {
    "addr:full":"14421 Jamestown St Waverly NE 68462",
    "addr:housenumber":"14421",
    "addr:postcode":"68462",
    "addr:street":"Jamestown St",
    "iso:country":"US",
    "sg:address":"14421 Jamestown St",
    "sg:city":"Waverly",
    "sg:classifiers":[
        {
            "category":"Freight",
            "type":"Transportation"
        }
    ],
    "sg:phone":"+1 402 416 6140",
    "sg:postcode":"68462",
    "sg:province":"NE",
    "sg:tags":[
        "operator",
        "local",
        "hauling",
        "trucking"
    ],
    "wof:name":"Lode Star Hauling",
    "wof:placetype":"venue"
},
  "geometry": {"coordinates":[-96.521095,40.916546],"type":"Point"}
}