{
  "type": "Feature",
  "properties": {
    "iso:country":"US",
    "sg:address":"1660 E 23rd St",
    "sg:city":"Fremont",
    "sg:classifiers":[
        {
            "category":"Home & Garden",
            "subcategory":"Hardware",
            "type":"Retail Goods"
        }
    ],
    "sg:phone":"+1 402 727 7067",
    "sg:postcode":"68025",
    "sg:province":"NE",
    "sg:tags":[
        "repair",
        "r",
        "equipment"
    ],
    "wof:name":"Ace Hardware",
    "wof:placetype":"venue"
},
  "geometry": {"coordinates":[-96.47718,41.451382],"type":"Point"}
}