{
  "type": "Feature",
  "properties": {
    "iso:country":"US",
    "sg:address":"11634 1st St",
    "sg:city":"Beatrice",
    "sg:classifiers":[
        {
            "category":"Farming",
            "subcategory":"Livestock Farm",
            "type":"Manufacturing & Wholesale Goods"
        }
    ],
    "sg:phone":"+1 402 228 0431",
    "sg:postcode":"68310",
    "sg:province":"NE",
    "sg:tags":[
        "hog",
        "beef",
        "corn",
        "cash",
        "cattle",
        "or",
        "feedlot"
    ],
    "wof:name":"Brod Hog Farm",
    "wof:placetype":"venue"
},
  "geometry": {"coordinates":[-96.876603,40.218724],"type":"Point"}
}