{
  "type": "Feature",
  "properties": {
    "iso:country":"US",
    "sg:address":"4700 S Lincoln Ave",
    "sg:city":"York",
    "sg:classifiers":[
        {
            "category":"Restaurant",
            "type":"Food & Drink"
        }
    ],
    "sg:phone":"+1 402 362 6331",
    "sg:postcode":"68467",
    "sg:province":"NE",
    "sg:tags":[
        "eating"
    ],
    "wof:name":"Pizza Hut",
    "wof:placetype":"venue"
},
  "geometry": {"coordinates":[-97.597872,40.818116],"type":"Point"}
}