{
  "type": "Feature",
  "properties": {
    "iso:country":"US",
    "sg:address":"1821 B St",
    "sg:city":"Schuyler",
    "sg:classifiers":[
        {
            "category":"Retail",
            "subcategory":"Auto Repair",
            "type":"Services"
        }
    ],
    "sg:phone":"+1 402 352 3116",
    "sg:postcode":"68661",
    "sg:province":"NE",
    "sg:tags":[
        "general"
    ],
    "wof:name":"Kroeger Auto Repair",
    "wof:placetype":"venue"
},
  "geometry": {"coordinates":[-97.05723,41.456947],"type":"Point"}
}