{
  "type": "Feature",
  "properties": {
    "addr:full":"3440 Saint Paul Ave Lincoln NE 68504",
    "addr:housenumber":"3440",
    "addr:postcode":"68504",
    "addr:street":"Saint Paul Ave",
    "iso:country":"US",
    "sg:address":"3440 Saint Paul Ave",
    "sg:city":"Lincoln",
    "sg:classifiers":[
        {
            "category":"Real Estate",
            "subcategory":"Surveying",
            "type":"Services"
        }
    ],
    "sg:phone":"+1 402 467 3675",
    "sg:postcode":"68504",
    "sg:province":"NE",
    "sg:tags":[
        "surveyor"
    ],
    "wof:name":"Bates & Assoc",
    "wof:placetype":"venue"
},
  "geometry": {"coordinates":[-96.67177100000001,40.839419],"type":"Point"}
}