{
  "type": "Feature",
  "properties": {
    "iso:country":"US",
    "sg:address":"3406 S 43rd St",
    "sg:city":"Omaha",
    "sg:classifiers":[
        {
            "category":"Real Estate",
            "subcategory":"Real Estate Operator",
            "type":"Services"
        }
    ],
    "sg:phone":"+1 402 553 5800",
    "sg:postcode":"68105",
    "sg:province":"NE",
    "sg:tags":[
        "building",
        "apartment"
    ],
    "wof:name":"Dwayne H & Carol A Paustian",
    "wof:placetype":"venue"
},
  "geometry": {"coordinates":[-95.977293,41.227062],"type":"Point"}
}