{
  "type": "Feature",
  "properties": {
    "iso:country":"US",
    "sg:address":"4334 S 67th St",
    "sg:city":"Omaha",
    "sg:classifiers":[
        {
            "category":"Manufacturing",
            "subcategory":"Rubber & Plastics",
            "type":"Manufacturing & Wholesale Goods"
        }
    ],
    "sg:phone":"+1 402 331 1175",
    "sg:postcode":"68117",
    "sg:province":"NE",
    "sg:tags":[
        "plumbing",
        "a",
        "mfg"
    ],
    "sg:website":"www.wmharvey.com",
    "wof:name":"William H Harvey Co",
    "wof:placetype":"venue"
},
  "geometry": {"coordinates":[-96.01562,41.217574],"type":"Point"}
}