{
  "type": "Feature",
  "properties": {
    "addr:full":"6116 O St Omaha NE 68117",
    "addr:housenumber":"6116",
    "addr:postcode":"68117",
    "addr:street":"O St",
    "iso:country":"US",
    "sg:address":"6116 O St",
    "sg:city":"Omaha",
    "sg:classifiers":[
        {
            "category":"Building & Trades",
            "subcategory":"Cleaning & Sanitation",
            "type":"Services"
        }
    ],
    "sg:phone":"+1 402 558 8589",
    "sg:postcode":"68117",
    "sg:province":"NE",
    "sg:tags":[
        "ventilating",
        "system"
    ],
    "wof:name":"Don Kallhoff Deck Washing",
    "wof:placetype":"venue"
},
  "geometry": {"coordinates":[-96.008084,41.208515],"type":"Point"}
}