{
  "type": "Feature",
  "properties": {
    "iso:country":"US",
    "sg:address":"2505 US Hwy 30",
    "sg:city":"Kearney",
    "sg:classifiers":[
        {
            "category":"Wholesale",
            "subcategory":"Construction Materials",
            "type":"Manufacturing & Wholesale Goods"
        }
    ],
    "sg:phone":"+1 308 236 6977",
    "sg:postcode":"68847",
    "sg:province":"NE",
    "sg:tags":[
        "fence"
    ],
    "wof:name":"Hurricane Fence Of Nebraska",
    "wof:placetype":"venue"
},
  "geometry": {"coordinates":[-99.04849,40.702637],"type":"Point"}
}