{
  "type": "Feature",
  "properties": {
    "iso:country":"US",
    "sg:address":"607 Winterburn Rd",
    "sg:city":"Elkhorn",
    "sg:classifiers":[
        {
            "category":"Freight",
            "type":"Transportation"
        }
    ],
    "sg:phone":"+1 402 289 1115",
    "sg:postcode":"68022",
    "sg:province":"NE",
    "sg:tags":[
        "consultant"
    ],
    "wof:name":"Pokorny Logistic LLC",
    "wof:placetype":"venue"
},
  "geometry": {"coordinates":[-96.225982,41.289577],"type":"Point"}
}