{
  "type": "Feature",
  "properties": {
    "addr:full":"1929 South St Blair NE 68008",
    "addr:housenumber":"1929",
    "addr:postcode":"68008",
    "addr:street":"South St",
    "iso:country":"US",
    "sg:address":"1929 South St",
    "sg:city":"Blair",
    "sg:classifiers":[
        {
            "category":"Professional",
            "subcategory":"Lawyer & Legal Services",
            "type":"Services"
        }
    ],
    "sg:phone":"+1 402 426 9471",
    "sg:postcode":"68008",
    "sg:province":"NE",
    "sg:tags":[
        "attorney"
    ],
    "wof:name":"Robert F Martin Law Offices",
    "wof:placetype":"venue"
},
  "geometry": {"coordinates":[-96.14145000000001,41.539555],"type":"Point"}
}