{
  "type": "Feature",
  "properties": {
    "iso:country":"US",
    "sg:address":"704 23rd St",
    "sg:city":"Columbus",
    "sg:classifiers":[
        {
            "category":"Autos & Motor Vehicles",
            "subcategory":"Boat Sales",
            "type":"Retail Goods"
        }
    ],
    "sg:phone":"+1 402 562 6615",
    "sg:postcode":"68601",
    "sg:province":"NE",
    "sg:tags":[
        "dealer",
        "sales"
    ],
    "wof:name":"Sealand Marine & Recreation",
    "wof:placetype":"venue"
},
  "geometry": {"coordinates":[-97.333123,41.438382],"type":"Point"}
}