{
  "type": "Feature",
  "properties": {
    "addr:full":"806 C Ave Central City NE 68826",
    "addr:housenumber":"806",
    "addr:postcode":"68826",
    "addr:street":"C Ave",
    "iso:country":"US",
    "sg:address":"806 C Ave",
    "sg:city":"Central City",
    "sg:classifiers":[
        {
            "category":"Personal",
            "subcategory":"Barber",
            "type":"Services"
        }
    ],
    "sg:phone":"+1 308 946 2929",
    "sg:postcode":"68826",
    "sg:province":"NE",
    "sg:tags":[
        "shop"
    ],
    "wof:name":"Head-Quarters Hair Care",
    "wof:placetype":"venue"
},
  "geometry": {"coordinates":[-98.002567,41.114478],"type":"Point"}
}