{
  "type": "Feature",
  "properties": {
    "addr:full":"808 Beacon Dr Plattsmouth NE 68048",
    "addr:housenumber":"808",
    "addr:postcode":"68048",
    "addr:street":"Beacon Dr",
    "iso:country":"US",
    "sg:address":"808 Beacon Dr",
    "sg:city":"Plattsmouth",
    "sg:classifiers":[
        {
            "category":"Manufacturing",
            "subcategory":"Printing",
            "type":"Manufacturing & Wholesale Goods"
        }
    ],
    "sg:phone":"+1 402 298 8001",
    "sg:postcode":"68048",
    "sg:province":"NE",
    "sg:tags":[
        "newspaper"
    ],
    "wof:name":"Cassgram",
    "wof:placetype":"venue"
},
  "geometry": {"coordinates":[-95.899131,41.024251],"type":"Point"}
}