{
  "type": "Feature",
  "properties": {
    "addr:full":"22401 Harrison St Gretna NE 68028",
    "addr:housenumber":"22401",
    "addr:postcode":"68028",
    "addr:street":"Harrison St",
    "iso:country":"US",
    "sg:address":"22401 Harrison St",
    "sg:city":"Gretna",
    "sg:classifiers":[
        {
            "category":"Professional",
            "type":"Services"
        }
    ],
    "sg:phone":"+1 402 216 6443",
    "sg:postcode":"68028",
    "sg:province":"NE",
    "wof:name":"Ostransky Support Services",
    "wof:placetype":"venue"
},
  "geometry": {"coordinates":[-96.26592599999999,41.190416],"type":"Point"}
}