{
  "type": "Feature",
  "properties": {
    "iso:country":"US",
    "sg:address":"358 N 41st St",
    "sg:city":"Omaha",
    "sg:classifiers":[
        {
            "category":"Education",
            "subcategory":"Special Training",
            "type":"Public Place"
        }
    ],
    "sg:phone":"+1 402 553 4003",
    "sg:postcode":"68131",
    "sg:province":"NE",
    "sg:tags":[
        "child",
        "day",
        "care"
    ],
    "sg:website":"www.smallwonderstutorial.com",
    "wof:name":"Small Wonders",
    "wof:placetype":"venue"
},
  "geometry": {"coordinates":[-95.974085,41.263123],"type":"Point"}
}