{
  "type": "Feature",
  "properties": {
    "addr:full":"11016 Y St Omaha NE 68137",
    "addr:housenumber":"11016",
    "addr:postcode":"68137",
    "addr:street":"Y St",
    "iso:country":"US",
    "sg:address":"11016 Y St",
    "sg:city":"Omaha",
    "sg:classifiers":[
        {
            "category":"Retail",
            "subcategory":"Portrait Studio",
            "type":"Services"
        }
    ],
    "sg:phone":"+1 402 321 0890",
    "sg:postcode":"68137",
    "sg:province":"NE",
    "sg:tags":[
        "photographer"
    ],
    "wof:name":"Ckimages Photography",
    "wof:placetype":"venue"
},
  "geometry": {"coordinates":[-96.084045,41.197747],"type":"Point"}
}