{
  "type": "Feature",
  "properties": {
    "iso:country":"US",
    "sg:address":"302 3rd St",
    "sg:city":"Ponca",
    "sg:classifiers":[
        {
            "category":"Government",
            "subcategory":"Office",
            "type":"Public Place"
        }
    ],
    "sg:phone":"+1 402 755 4291",
    "sg:postcode":"68770",
    "sg:province":"NE",
    "sg:tags":[
        "state",
        "program"
    ],
    "wof:name":"Motor Vehicles Dept",
    "wof:placetype":"venue"
},
  "geometry": {"coordinates":[-96.70917799999999,42.563117],"type":"Point"}
}