{
  "type": "Feature",
  "properties": {
    "iso:country":"US",
    "sg:address":"616 13th St",
    "sg:city":"Aurora",
    "sg:classifiers":[
        {
            "category":"Professional",
            "type":"Services"
        }
    ],
    "sg:phone":"+1 402 694 2585",
    "sg:postcode":"68818",
    "sg:province":"NE",
    "wof:name":"Central Nebraska Community Svc",
    "wof:placetype":"venue"
},
  "geometry": {"coordinates":[-98.00080800000001,40.86345],"type":"Point"}
}