{
  "type": "Feature",
  "properties": {
    "iso:country":"US",
    "sg:address":"25749 S Branting Rd",
    "sg:city":"Wellfleet",
    "sg:classifiers":[
        {
            "category":"Building & Trades",
            "subcategory":"Landscaping Services",
            "type":"Services"
        }
    ],
    "sg:phone":"+1 308 696 6685",
    "sg:postcode":"69170",
    "sg:province":"NE",
    "sg:tags":[
        "tree"
    ],
    "wof:name":"Weaver Tree Svc",
    "wof:placetype":"venue"
},
  "geometry": {"coordinates":[-100.71606,40.897903],"type":"Point"}
}