{
  "type": "Feature",
  "properties": {
    "iso:country":"US",
    "sg:address":"5400 N 72nd St",
    "sg:city":"Omaha",
    "sg:classifiers":[
        {
            "category":"Communications",
            "subcategory":"Radio Station",
            "type":"Services"
        }
    ],
    "sg:phone":"+1 402 573 1567",
    "sg:postcode":"68122",
    "sg:province":"NE",
    "sg:tags":[
        "broadcast"
    ],
    "wof:name":"Valley Broadcasting",
    "wof:placetype":"venue"
},
  "geometry": {"coordinates":[-96.023781,41.321091],"type":"Point"}
}