{
  "type": "Feature",
  "properties": {
    "iso:country":"US",
    "sg:address":"4010 6th Ave",
    "sg:city":"Kearney",
    "sg:classifiers":[
        {
            "category":"Health Services",
            "subcategory":"Health Practitioner",
            "type":"Services"
        }
    ],
    "sg:phone":"+1 308 237 7877",
    "sg:postcode":"68845",
    "sg:province":"NE",
    "sg:tags":[
        "therapist",
        "physical"
    ],
    "wof:name":"Physical Therapy Professionals",
    "wof:placetype":"venue"
},
  "geometry": {"coordinates":[-99.089567,40.714839],"type":"Point"}
}