{
  "type": "Feature",
  "properties": {
    "iso:country":"US",
    "sg:address":"10675 Bedford Ave",
    "sg:city":"Omaha",
    "sg:classifiers":[
        {
            "category":"Insurance",
            "subcategory":"Insurance Agent",
            "type":"Services"
        }
    ],
    "sg:phone":"+1 402 963 0206",
    "sg:postcode":"68134",
    "sg:province":"NE",
    "wof:name":"Securus",
    "wof:placetype":"venue"
},
  "geometry": {"coordinates":[-96.07943400000001,41.288655],"type":"Point"}
}