{
  "type": "Feature",
  "properties": {
    "iso:country":"US",
    "sg:address":"5940 Platte Ave",
    "sg:city":"Lincoln",
    "sg:classifiers":[
        {
            "category":"Freight",
            "type":"Transportation"
        },
        {
            "category":"Manufacturing",
            "subcategory":"Metals",
            "type":"Manufacturing & Wholesale Goods"
        }
    ],
    "sg:phone":"+1 402 466 5120",
    "sg:postcode":"68507",
    "sg:province":"NE",
    "sg:tags":[
        "screen",
        "special"
    ],
    "wof:name":"Have Lock Aluminum",
    "wof:placetype":"venue"
},
  "geometry": {"coordinates":[-96.638924,40.858209],"type":"Point"}
}