{
  "type": "Feature",
  "properties": {
    "iso:country":"US",
    "sg:address":"808 Howard Ave",
    "sg:city":"St Paul",
    "sg:classifiers":[
        {
            "category":"Social Services",
            "type":"Services"
        }
    ],
    "sg:phone":"+1 308 754 5452",
    "sg:postcode":"68873",
    "sg:province":"NE",
    "sg:tags":[
        "senior",
        "citizen"
    ],
    "wof:name":"Midland Area Agency On Aging",
    "wof:placetype":"venue"
},
  "geometry": {"coordinates":[-98.460044,41.213453],"type":"Point"}
}