{
  "type": "Feature",
  "properties": {
    "iso:country":"US",
    "sg:address":"4940 Aylesworth Ave",
    "sg:city":"Lincoln",
    "sg:classifiers":[
        {
            "category":"Wholesale",
            "subcategory":"Electrical",
            "type":"Manufacturing & Wholesale Goods"
        }
    ],
    "sg:phone":"+1 402 891 7018",
    "sg:postcode":"68504",
    "sg:province":"NE",
    "sg:tags":[
        "control",
        "security",
        "system"
    ],
    "wof:name":"AKL Security Systems",
    "wof:placetype":"venue"
},
  "geometry": {"coordinates":[-96.651453,40.829428],"type":"Point"}
}