{
  "type": "Feature",
  "properties": {
    "addr:full":"5122 J St Lincoln NE 68510",
    "addr:housenumber":"5122",
    "addr:postcode":"68510",
    "addr:street":"J St",
    "iso:country":"US",
    "sg:address":"5122 J St",
    "sg:city":"Lincoln",
    "sg:classifiers":[
        {
            "category":"Building & Trades",
            "subcategory":"Construction",
            "type":"Services"
        }
    ],
    "sg:phone":"+1 402 430 6434",
    "sg:postcode":"68510",
    "sg:province":"NE",
    "sg:tags":[
        "house",
        "industrial",
        "co"
    ],
    "wof:name":"Zw Homes",
    "wof:placetype":"venue"
},
  "geometry": {"coordinates":[-96.649126,40.808082],"type":"Point"}
}