{
  "type": "Feature",
  "properties": {
    "iso:country":"US",
    "sg:address":"942 W 24th St",
    "sg:city":"Kearney",
    "sg:classifiers":[
        {
            "category":"Restaurant",
            "type":"Food & Drink"
        }
    ],
    "sg:phone":"+1 308 233 5949",
    "sg:postcode":"68845",
    "sg:province":"NE",
    "sg:tags":[
        "shop",
        "coffee"
    ],
    "wof:name":"Jumping Juice & Java",
    "wof:placetype":"venue"
},
  "geometry": {"coordinates":[-99.09484500000001,40.699368],"type":"Point"}
}