{
  "type": "Feature",
  "properties": {
    "iso:country":"US",
    "sg:address":"301 E 11th St",
    "sg:city":"Schuyler",
    "sg:classifiers":[
        {
            "category":"Banks & Credit Unions",
            "subcategory":"Investment Brokerage",
            "type":"Services"
        }
    ],
    "sg:phone":"+1 402 352 2675",
    "sg:postcode":"68661",
    "sg:province":"NE",
    "sg:tags":[
        "security"
    ],
    "sg:website":"www.securitiesamerica.org",
    "wof:name":"Securities America Inc",
    "wof:placetype":"venue"
},
  "geometry": {"coordinates":[-97.05721,41.447326],"type":"Point"}
}