{
  "type": "Feature",
  "properties": {
    "addr:full":"3521 N 22nd St Lincoln NE 68521",
    "addr:housenumber":"3521",
    "addr:postcode":"68521",
    "addr:street":"N 22Nd St",
    "iso:country":"US",
    "sg:address":"3521 N 22nd St",
    "sg:city":"Lincoln",
    "sg:classifiers":[
        {
            "category":"Building & Trades",
            "subcategory":"Electrical",
            "type":"Services"
        }
    ],
    "sg:phone":"+1 402 476 6463",
    "sg:postcode":"68521",
    "sg:province":"NE",
    "sg:tags":[
        "electrical",
        "electric",
        "contractor"
    ],
    "wof:name":"Gregg Electric Company",
    "wof:placetype":"venue"
},
  "geometry": {"coordinates":[-96.68984399999999,40.846771],"type":"Point"}
}