{
  "type": "Feature",
  "properties": {
    "iso:country":"US",
    "sg:address":"1490 N Chestnut St",
    "sg:city":"Wahoo",
    "sg:classifiers":[
        {
            "category":"Manufacturing",
            "subcategory":"Metals",
            "type":"Manufacturing & Wholesale Goods"
        }
    ],
    "sg:phone":"+1 402 443 4522",
    "sg:postcode":"68066",
    "sg:province":"NE",
    "sg:tags":[
        "plate",
        "work",
        "fabricated",
        "mfg"
    ],
    "wof:name":"Otte Oil & Propane",
    "wof:placetype":"venue"
},
  "geometry": {"coordinates":[-96.621622,41.218893],"type":"Point"}
}