{
  "type": "Feature",
  "properties": {
    "addr:full":"2405 Z St Omaha NE 68107",
    "addr:housenumber":"2405",
    "addr:postcode":"68107",
    "addr:street":"Z St",
    "iso:country":"US",
    "sg:address":"2405 Z St",
    "sg:city":"Omaha",
    "sg:classifiers":[
        {
            "category":"Retail",
            "subcategory":"Auto Repair",
            "type":"Services"
        }
    ],
    "sg:phone":"+1 402 933 4034",
    "sg:postcode":"68107",
    "sg:province":"NE",
    "sg:tags":[
        "body"
    ],
    "wof:name":"Mutzenberger Restorations",
    "wof:placetype":"venue"
},
  "geometry": {"coordinates":[-95.948063,41.197241],"type":"Point"}
}