{
  "type": "Feature",
  "properties": {
    "addr:full":"1651 N 2nd Rd Eagle NE 68347",
    "addr:housenumber":"1651",
    "addr:postcode":"68347",
    "addr:street":"N 2Nd Rd",
    "iso:country":"US",
    "sg:address":"1651 N 2nd Rd",
    "sg:city":"Eagle",
    "sg:classifiers":[
        {
            "category":"Farming",
            "subcategory":"Livestock Farm",
            "type":"Manufacturing & Wholesale Goods"
        }
    ],
    "sg:phone":"+1 402 781 2410",
    "sg:postcode":"68347",
    "sg:province":"NE",
    "sg:tags":[
        "wheat",
        "beef",
        "corn",
        "soybean",
        "cattle",
        "feedlot"
    ],
    "wof:name":"Gary Earl",
    "wof:placetype":"venue"
},
  "geometry": {"coordinates":[-96.444858,40.776714],"type":"Point"}
}