{
  "type": "Feature",
  "properties": {
    "iso:country":"US",
    "sg:address":"201 S Washington St",
    "sg:city":"Lexington",
    "sg:classifiers":[
        {
            "category":"Wholesale",
            "subcategory":"Farm Supplies",
            "type":"Manufacturing & Wholesale Goods"
        }
    ],
    "sg:phone":"+1 308 324 2325",
    "sg:postcode":"68850",
    "sg:province":"NE",
    "sg:tags":[
        "feed"
    ],
    "wof:name":"Crawford Grain Inc",
    "wof:placetype":"venue"
},
  "geometry": {"coordinates":[-99.741801,40.775314],"type":"Point"}
}