{
  "type": "Feature",
  "properties": {
    "iso:country":"US",
    "sg:address":"4556 Leavenworth St",
    "sg:city":"Omaha",
    "sg:classifiers":[
        {
            "category":"Bars & Pubs",
            "type":"Food & Drink"
        }
    ],
    "sg:phone":"+1 402 551 4850",
    "sg:postcode":"68106",
    "sg:province":"NE",
    "sg:tags":[
        "drinking",
        "hall",
        "pool"
    ],
    "wof:name":"Leavenworth Bar",
    "wof:placetype":"venue"
},
  "geometry": {"coordinates":[-95.982697,41.252499],"type":"Point"}
}