{
  "type": "Feature",
  "properties": {
    "iso:country":"US",
    "sg:address":"327 Platte Ave",
    "sg:city":"York",
    "sg:classifiers":[
        {
            "category":"Manufacturing",
            "subcategory":"Printing",
            "type":"Manufacturing & Wholesale Goods"
        }
    ],
    "sg:phone":"+1 402 362 4478",
    "sg:postcode":"68467",
    "sg:province":"NE",
    "sg:tags":[
        "newspaper"
    ],
    "sg:website":"www.yorknewstimes.com",
    "wof:name":"York News Times/Advantage",
    "wof:placetype":"venue"
},
  "geometry": {"coordinates":[-97.59427100000001,40.863983],"type":"Point"}
}