{
  "type": "Feature",
  "properties": {
    "iso:country":"US",
    "sg:address":"2520 N 84th St",
    "sg:city":"Omaha",
    "sg:classifiers":[
        {
            "category":"Retail",
            "subcategory":"Repair Shop",
            "type":"Services"
        }
    ],
    "sg:phone":"+1 402 740 8685",
    "sg:postcode":"68134",
    "sg:province":"NE",
    "sg:tags":[
        "welding"
    ],
    "wof:name":"Judd Performance Welding & Fab",
    "wof:placetype":"venue"
},
  "geometry": {"coordinates":[-96.043468,41.283074],"type":"Point"}
}