{
  "type": "Feature",
  "properties": {
    "iso:country":"US",
    "sg:address":"517 1st St",
    "sg:city":"Milford",
    "sg:classifiers":[
        {
            "category":"Farming",
            "subcategory":"Farm & Veterinary Services",
            "type":"Manufacturing & Wholesale Goods"
        }
    ],
    "sg:phone":"+1 402 761 3361",
    "sg:postcode":"68405",
    "sg:province":"NE",
    "sg:tags":[
        "management"
    ],
    "wof:name":"Austin Co",
    "wof:placetype":"venue"
},
  "geometry": {"coordinates":[-97.051593,40.774151],"type":"Point"}
}