{
  "type": "Feature",
  "properties": {
    "iso:country":"US",
    "sg:address":"615 S 78th St",
    "sg:city":"Omaha",
    "sg:classifiers":[
        {
            "category":"Insurance",
            "subcategory":"Insurance Agent",
            "type":"Services"
        }
    ],
    "sg:phone":"+1 402 343 1114",
    "sg:postcode":"68114",
    "sg:province":"NE",
    "wof:name":"Midlands Med-Psych Accounts",
    "wof:placetype":"venue"
},
  "geometry": {"coordinates":[-96.033394,41.250739],"type":"Point"}
}