{
  "type": "Feature",
  "properties": {
    "iso:country":"US",
    "sg:address":"1501 Superior St",
    "sg:city":"Lincoln",
    "sg:classifiers":[
        {
            "category":"Real Estate",
            "subcategory":"Real Estate Operator",
            "type":"Services"
        }
    ],
    "sg:phone":"+1 402 476 3287",
    "sg:postcode":"68521",
    "sg:province":"NE",
    "sg:tags":[
        "apartment"
    ],
    "wof:name":"Superior Place Apartments",
    "wof:placetype":"venue"
},
  "geometry": {"coordinates":[-96.69850700000001,40.857281],"type":"Point"}
}