{
  "type": "Feature",
  "properties": {
    "iso:country":"US",
    "sg:address":"13114 Edna St",
    "sg:city":"Omaha",
    "sg:classifiers":[
        {
            "category":"Shopping",
            "subcategory":"Hobbies, Toys, & Games",
            "type":"Retail Goods"
        }
    ],
    "sg:phone":"+1 402 896 6712",
    "sg:postcode":"68138",
    "sg:province":"NE",
    "wof:name":"Pams Creations",
    "wof:placetype":"venue"
},
  "geometry": {"coordinates":[-96.118088,41.188161],"type":"Point"}
}