{
  "type": "Feature",
  "properties": {
    "iso:country":"US",
    "sg:address":"705 S Adams St",
    "sg:city":"Kimball",
    "sg:classifiers":[
        {
            "category":"Professional",
            "subcategory":"Employment Agencies",
            "type":"Services"
        }
    ],
    "sg:phone":"+1 308 235 4587",
    "sg:postcode":"69145",
    "sg:province":"NE",
    "sg:tags":[
        "help",
        "supply"
    ],
    "wof:name":"TLC Staffing Services LLC",
    "wof:placetype":"venue"
},
  "geometry": {"coordinates":[-103.647831,41.229326],"type":"Point"}
}