{
  "type": "Feature",
  "properties": {
    "iso:country":"US",
    "sg:address":"6100 O St Spc 508",
    "sg:city":"Lincoln",
    "sg:classifiers":[
        {
            "category":"Shopping",
            "subcategory":"Clothing, Apparel, & Fashions",
            "type":"Retail Goods"
        },
        {
            "category":"Sports & Exercise",
            "subcategory":"Swimming Pool",
            "type":"Entertainment"
        }
    ],
    "sg:phone":"+1 402 466 2148",
    "sg:postcode":"68510",
    "sg:province":"NE",
    "sg:tags":[
        "apparel",
        "handbag",
        "women's",
        "swimwear",
        "accessory"
    ],
    "sg:website":"http://www.lanebryant.com",
    "wof:name":"Lane Bryant",
    "wof:placetype":"venue"
},
  "geometry": {"coordinates":[-96.638542,40.813431],"type":"Point"}
}