{
  "type": "Feature",
  "properties": {
    "iso:country":"US",
    "sg:address":"910 Jefferson Ave",
    "sg:city":"Hastings",
    "sg:classifiers":[
        {
            "category":"Organizations",
            "subcategory":"Community Association",
            "type":"Services"
        }
    ],
    "sg:phone":"+1 402 463 2015",
    "sg:postcode":"68901",
    "sg:province":"NE",
    "wof:name":"Order of Eastern Star",
    "wof:placetype":"venue"
},
  "geometry": {"coordinates":[-98.40492500000001,40.595373],"type":"Point"}
}