{
  "type": "Feature",
  "properties": {
    "iso:country":"US",
    "sg:address":"500 S 11th St",
    "sg:city":"Beatrice",
    "sg:classifiers":[
        {
            "category":"Shopping",
            "subcategory":"Bicycles & Sporting Goods",
            "type":"Retail Goods"
        }
    ],
    "sg:phone":"+1 402 223 3867",
    "sg:postcode":"68310",
    "sg:province":"NE",
    "wof:name":"Festers Bait Tackle",
    "wof:placetype":"venue"
},
  "geometry": {"coordinates":[-96.73985399999999,40.261172],"type":"Point"}
}