{
  "type": "Feature",
  "properties": {
    "iso:country":"US",
    "sg:address":"500 W Leota St",
    "sg:city":"North Platte",
    "sg:classifiers":[
        {
            "category":"Health Services",
            "subcategory":"Doctor",
            "type":"Services"
        }
    ],
    "sg:phone":"+1 308 532 4866",
    "sg:postcode":"69101",
    "sg:province":"NE",
    "sg:tags":[
        "medical"
    ],
    "wof:name":"North Pltte Ostoporosis Clinic",
    "wof:placetype":"venue"
},
  "geometry": {"coordinates":[-100.76924699999999,41.120834],"type":"Point"}
}