{
  "type": "Feature",
  "properties": {
    "iso:country":"US",
    "sg:address":"9211 Maple St",
    "sg:city":"Omaha",
    "sg:classifiers":[
        {
            "category":"Retail",
            "subcategory":"Laundry & Dry Cleaning",
            "type":"Services"
        }
    ],
    "sg:phone":"+1 402 391 9299",
    "sg:postcode":"68134",
    "sg:province":"NE",
    "sg:tags":[
        "cleaners"
    ],
    "sg:website":"www.maxiwalker.com",
    "wof:name":"Max I Walker",
    "wof:placetype":"venue"
},
  "geometry": {"coordinates":[-96.05414500000001,41.284992],"type":"Point"}
}