{
  "type": "Feature",
  "properties": {
    "addr:full":"1080 W 78th St Kearney NE 68845",
    "addr:housenumber":"1080",
    "addr:postcode":"68845",
    "addr:street":"W 78Th St",
    "iso:country":"US",
    "sg:address":"1080 W 78th St",
    "sg:city":"Kearney",
    "sg:classifiers":[
        {
            "category":"Building & Trades",
            "subcategory":"Construction",
            "type":"Services"
        },
        {
            "category":"Home & Garden",
            "subcategory":"Furniture",
            "type":"Retail Goods"
        }
    ],
    "sg:phone":"+1 308 237 7241",
    "sg:postcode":"68845",
    "sg:province":"NE",
    "sg:tags":[
        "maker",
        "cabinet"
    ],
    "wof:name":"Garrison Custom Cabinets Inc",
    "wof:placetype":"venue"
},
  "geometry": {"coordinates":[-99.087476,40.750203],"type":"Point"}
}