{
  "type": "Feature",
  "properties": {
    "iso:country":"US",
    "sg:address":"10658 US Hwy 136",
    "sg:city":"Beatrice",
    "sg:classifiers":[
        {
            "category":"Wholesale",
            "subcategory":"Machinery & Supplies",
            "type":"Manufacturing & Wholesale Goods"
        }
    ],
    "sg:phone":"+1 402 223 5303",
    "sg:postcode":"68310",
    "sg:province":"NE",
    "wof:name":"Weins Farms",
    "wof:placetype":"venue"
},
  "geometry": {"coordinates":[-96.87648299999999,40.219345],"type":"Point"}
}