{
  "type": "Feature",
  "properties": {
    "addr:full":"107 N 50th St Omaha NE 68132",
    "addr:housenumber":"107",
    "addr:postcode":"68132",
    "addr:street":"N 50Th St",
    "iso:country":"US",
    "sg:address":"107 N 50th St",
    "sg:city":"Omaha",
    "sg:classifiers":[
        {
            "category":"Shopping",
            "subcategory":"Gifts & Souvenirs",
            "type":"Retail Goods"
        }
    ],
    "sg:phone":"+1 402 558 0380",
    "sg:postcode":"68132",
    "sg:province":"NE",
    "wof:name":"Beyond Ireland",
    "wof:placetype":"venue"
},
  "geometry": {"coordinates":[-95.990196,41.260453],"type":"Point"}
}