{
  "type": "Feature",
  "properties": {
    "iso:country":"US",
    "sg:address":"1030 N St",
    "sg:city":"Loup City",
    "sg:classifiers":[
        {
            "category":"Government",
            "subcategory":"Office",
            "type":"Public Place"
        }
    ],
    "sg:phone":"+1 308 745 1007",
    "sg:postcode":"68853",
    "sg:province":"NE",
    "sg:tags":[
        "village"
    ],
    "wof:name":"Loup City Garage",
    "wof:placetype":"venue"
},
  "geometry": {"coordinates":[-98.970893,41.275951],"type":"Point"}
}