{
  "type": "Feature",
  "properties": {
    "addr:full":"3111 O St Lincoln NE 68510",
    "addr:housenumber":"3111",
    "addr:postcode":"68510",
    "addr:street":"O St",
    "iso:country":"US",
    "sg:address":"3111 O St",
    "sg:city":"Lincoln",
    "sg:classifiers":[
        {
            "category":"Shopping",
            "subcategory":"Jewelry",
            "type":"Retail Goods"
        }
    ],
    "sg:phone":"+1 402 474 6044",
    "sg:postcode":"68510",
    "sg:province":"NE",
    "sg:tags":[
        "stone"
    ],
    "wof:name":"Elder Jewelry",
    "wof:placetype":"venue"
},
  "geometry": {"coordinates":[-96.675168,40.813348],"type":"Point"}
}