{
  "type": "Feature",
  "properties": {
    "iso:country":"US",
    "sg:address":"4370 Rd R",
    "sg:city":"Linwood",
    "sg:phone":"+1 402 539 3425",
    "sg:postcode":"68036",
    "sg:province":"NE",
    "sg:tags":[
        "farm",
        "corn"
    ],
    "wof:name":"Jerry Hoelscher Farm",
    "wof:placetype":"venue"
},
  "geometry": {"coordinates":[-97.04207599999999,41.379374],"type":"Point"}
}