{
  "type": "Feature",
  "properties": {
    "iso:country":"US",
    "sg:address":"17404 Burke St",
    "sg:city":"Omaha",
    "sg:classifiers":[
        {
            "category":"Health Services",
            "subcategory":"Dentist",
            "type":"Services"
        }
    ],
    "sg:phone":"+1 402 493 2112",
    "sg:postcode":"68118",
    "sg:province":"NE",
    "wof:name":"Dudzinski Bernie",
    "wof:placetype":"venue"
},
  "geometry": {"coordinates":[-96.187535,41.259867],"type":"Point"}
}