{
  "type": "Feature",
  "properties": {
    "iso:country":"US",
    "sg:address":"4617 S 29th Plz",
    "sg:city":"Omaha",
    "sg:classifiers":[
        {
            "category":"Manufacturing",
            "subcategory":"Metals",
            "type":"Manufacturing & Wholesale Goods"
        }
    ],
    "sg:phone":"+1 402 733 6695",
    "sg:postcode":"68107",
    "sg:province":"NE",
    "sg:tags":[
        "plating"
    ],
    "wof:name":"Special Metal Svc Inc",
    "wof:placetype":"venue"
},
  "geometry": {"coordinates":[-95.95501299999999,41.209646],"type":"Point"}
}