{
  "type": "Feature",
  "properties": {
    "iso:country":"US",
    "sg:address":"8631 F St",
    "sg:city":"Omaha",
    "sg:classifiers":[
        {
            "category":"Building & Trades",
            "subcategory":"Construction",
            "type":"Services"
        }
    ],
    "sg:phone":"+1 402 331 1874",
    "sg:postcode":"68127",
    "sg:province":"NE",
    "sg:tags":[
        "painter"
    ],
    "wof:name":"Frank Bevins Painting Inc",
    "wof:placetype":"venue"
},
  "geometry": {"coordinates":[-96.045461,41.219662],"type":"Point"}
}