{
  "type": "Feature",
  "properties": {
    "iso:country":"US",
    "sg:address":"601 E Benjamin Ave",
    "sg:city":"Norfolk",
    "sg:classifiers":[
        {
            "category":"Education",
            "subcategory":"College",
            "type":"Public Place"
        }
    ],
    "sg:phone":"+1 402 370 3567",
    "sg:postcode":"68701",
    "sg:province":"NE",
    "sg:tags":[
        "academic",
        "school"
    ],
    "wof:name":"Wayne State College Regionial",
    "wof:placetype":"venue"
},
  "geometry": {"coordinates":[-97.398073,42.047387],"type":"Point"}
}