{
  "type": "Feature",
  "properties": {
    "iso:country":"US",
    "sg:address":"821 Front St",
    "sg:city":"Gibbon",
    "sg:classifiers":[
        {
            "category":"Health Services",
            "subcategory":"Chiropractor",
            "type":"Services"
        }
    ],
    "sg:phone":"+1 308 468 6080",
    "sg:postcode":"68840",
    "sg:province":"NE",
    "wof:name":"Gibbon Chiropractic",
    "wof:placetype":"venue"
},
  "geometry": {"coordinates":[-98.844943,40.749051],"type":"Point"}
}