{
  "type": "Feature",
  "properties": {
    "iso:country":"US",
    "sg:address":"2245 Co Rd 400",
    "sg:city":"Tobias",
    "sg:classifiers":[
        {
            "category":"Education",
            "subcategory":"School",
            "type":"Public Place"
        }
    ],
    "sg:phone":"+1 402 243 2354",
    "sg:postcode":"68453",
    "sg:province":"NE",
    "sg:tags":[
        "elementary"
    ],
    "wof:name":"Zion Lutheran School",
    "wof:placetype":"venue"
},
  "geometry": {"coordinates":[-97.311921,40.387493],"type":"Point"}
}