{
  "type": "Feature",
  "properties": {
    "iso:country":"US",
    "sg:address":"1141 US Hwy 30",
    "sg:city":"Blair",
    "sg:classifiers":[
        {
            "category":"Personal",
            "subcategory":"Beauty Salon",
            "type":"Services"
        }
    ],
    "sg:phone":"+1 402 426 4060",
    "sg:postcode":"68008",
    "sg:province":"NE",
    "wof:name":"Julie Ann Shop",
    "wof:placetype":"venue"
},
  "geometry": {"coordinates":[-96.12913,41.543608],"type":"Point"}
}