{
  "type": "Feature",
  "properties": {
    "addr:full":"106 W 12th St Wood River NE 68883",
    "addr:housenumber":"106",
    "addr:postcode":"68883",
    "addr:street":"W 12Th St",
    "iso:country":"US",
    "sg:address":"106 W 12th St",
    "sg:city":"Wood River",
    "sg:classifiers":[
        {
            "category":"Professional",
            "subcategory":"Business Services",
            "type":"Services"
        }
    ],
    "sg:phone":"+1 308 583 0168",
    "sg:postcode":"68883",
    "sg:province":"NE",
    "wof:name":"Jam Pressure Washing",
    "wof:placetype":"venue"
},
  "geometry": {"coordinates":[-98.60289400000001,40.82359],"type":"Point"}
}