{
  "type": "Feature",
  "properties": {
    "iso:country":"US",
    "sg:address":"6220 N 160th Ave",
    "sg:city":"Omaha",
    "sg:classifiers":[
        {
            "category":"Sports & Exercise",
            "subcategory":"Golf",
            "type":"Entertainment"
        }
    ],
    "sg:phone":"+1 402 965 9000",
    "sg:postcode":"68116",
    "sg:province":"NE",
    "sg:tags":[
        "course"
    ],
    "sg:website":"www.golfstonecreek.com",
    "wof:name":"Stone Creek Golf Course",
    "wof:placetype":"venue"
},
  "geometry": {"coordinates":[-96.163663,41.313306],"type":"Point"}
}