{
  "type": "Feature",
  "properties": {
    "addr:full":"1333 Illinois St Sidney NE 69162",
    "addr:housenumber":"1333",
    "addr:postcode":"69162",
    "addr:street":"Illinois St",
    "iso:country":"US",
    "sg:address":"1333 Illinois St",
    "sg:city":"Sidney",
    "sg:classifiers":[
        {
            "category":"Building & Trades",
            "subcategory":"Plumbing",
            "type":"Services"
        }
    ],
    "sg:phone":"+1 308 254 0448",
    "sg:postcode":"69162",
    "sg:province":"NE",
    "sg:tags":[
        "conditioning",
        "air",
        "system",
        "contractor"
    ],
    "wof:name":"Russell Repair",
    "wof:placetype":"venue"
},
  "geometry": {"coordinates":[-102.980797,41.144586],"type":"Point"}
}