{
  "type": "Feature",
  "properties": {
    "iso:country":"US",
    "sg:address":"10316 S 177th St",
    "sg:city":"Omaha",
    "sg:classifiers":[
        {
            "category":"Wholesale",
            "subcategory":"Machinery & Supplies",
            "type":"Manufacturing & Wholesale Goods"
        }
    ],
    "sg:phone":"+1 402 891 9777",
    "sg:postcode":"68136",
    "sg:province":"NE",
    "sg:tags":[
        "tool"
    ],
    "sg:website":"www.boschusa.com/home.asp",
    "wof:name":"Robert Bosch Tool Corp",
    "wof:placetype":"venue"
},
  "geometry": {"coordinates":[-96.194425,41.157604],"type":"Point"}
}