{
  "type": "Feature",
  "properties": {
    "addr:full":"342 E 13th St Crete NE 68333",
    "addr:housenumber":"342",
    "addr:postcode":"68333",
    "addr:street":"E 13Th St",
    "iso:country":"US",
    "sg:address":"342 E 13th St",
    "sg:city":"Crete",
    "sg:classifiers":[
        {
            "category":"Restaurant",
            "type":"Food & Drink"
        }
    ],
    "sg:phone":"+1 402 826 5511",
    "sg:postcode":"68333",
    "sg:province":"NE",
    "wof:name":"Amigos",
    "wof:placetype":"venue"
},
  "geometry": {"coordinates":[-96.95869999999999,40.625311],"type":"Point"}
}