{
  "type": "Feature",
  "properties": {
    "addr:full":"14010 Fnb Pkwy Omaha NE 68154",
    "addr:housenumber":"14010",
    "addr:postcode":"68154",
    "addr:street":"Fnb Pkwy",
    "iso:country":"US",
    "sg:address":"14010 Fnb Pkwy",
    "sg:city":"Omaha",
    "sg:classifiers":[
        {
            "category":"Insurance",
            "subcategory":"Insurance Agent",
            "type":"Services"
        }
    ],
    "sg:phone":"+1 402 964 8000",
    "sg:postcode":"68154",
    "sg:province":"NE",
    "wof:name":"First Line Insurance Svc",
    "wof:placetype":"venue"
},
  "geometry": {"coordinates":[-96.13298,41.263851],"type":"Point"}
}