{
  "type": "Feature",
  "properties": {
    "iso:country":"US",
    "sg:address":"2904 14th St",
    "sg:city":"Columbus",
    "sg:classifiers":[
        {
            "category":"Health Services",
            "subcategory":"Hospital",
            "type":"Services"
        }
    ],
    "sg:phone":"+1 402 562 7933",
    "sg:postcode":"68601",
    "sg:province":"NE",
    "sg:tags":[
        "mental"
    ],
    "sg:website":"www.omnibehavioralhealth.com",
    "wof:name":"Omni Behavioral Health",
    "wof:placetype":"venue"
},
  "geometry": {"coordinates":[-97.364363,41.430445],"type":"Point"}
}