{
  "type": "Feature",
  "properties": {
    "iso:country":"US",
    "sg:address":"14001 Chalco Valley Pkwy",
    "sg:city":"Omaha",
    "sg:classifiers":[
        {
            "category":"Wholesale",
            "subcategory":"Machinery & Supplies",
            "type":"Manufacturing & Wholesale Goods"
        }
    ],
    "sg:phone":"+1 402 334 2011",
    "sg:postcode":"68138",
    "sg:province":"NE",
    "sg:tags":[
        "equipment",
        "industrial"
    ],
    "sg:website":"www.midwestool.com",
    "wof:name":"Midwest Industrial Tools Inc",
    "wof:placetype":"venue"
},
  "geometry": {"coordinates":[-96.134495,41.181947],"type":"Point"}
}