{
  "type": "Feature",
  "properties": {
    "iso:country":"US",
    "sg:address":"637 N 21st St",
    "sg:city":"Blair",
    "sg:classifiers":[
        {
            "category":"Professional",
            "subcategory":"Management & Consulting",
            "type":"Services"
        }
    ],
    "sg:phone":"+1 402 426 7102",
    "sg:postcode":"68008",
    "sg:province":"NE",
    "wof:name":"Drd Resources",
    "wof:placetype":"venue"
},
  "geometry": {"coordinates":[-96.144306,41.549717],"type":"Point"}
}