{
  "type": "Feature",
  "properties": {
    "iso:country":"US",
    "sg:address":"1559 Colfax St",
    "sg:city":"Blair",
    "sg:classifiers":[
        {
            "category":"Social Services",
            "type":"Services"
        }
    ],
    "sg:phone":"+1 402 426 6818",
    "sg:postcode":"68008",
    "sg:province":"NE",
    "sg:tags":[
        "probation"
    ],
    "wof:name":"Washington County Probation",
    "wof:placetype":"venue"
},
  "geometry": {"coordinates":[-96.13539400000001,41.540659],"type":"Point"}
}