{
  "type": "Feature",
  "properties": {
    "addr:full":"6835 N 27th St Lincoln NE 68521",
    "addr:housenumber":"6835",
    "addr:postcode":"68521",
    "addr:street":"N 27Th St",
    "iso:country":"US",
    "sg:address":"6835 N 27th St",
    "sg:city":"Lincoln",
    "sg:classifiers":[
        {
            "category":"Restaurant",
            "type":"Food & Drink"
        }
    ],
    "sg:menulink":"http://www.allmenus.com/ne/lincoln/181602-wendys/menu/",
    "sg:phone":"+1 402 435 2260",
    "sg:postcode":"68521",
    "sg:province":"NE",
    "sg:tags":[
        "burger",
        "american",
        "soup"
    ],
    "wof:name":"Wendy's",
    "wof:placetype":"venue"
},
  "geometry": {"coordinates":[-96.682473,40.880729],"type":"Point"}
}