{
  "type": "Feature",
  "properties": {
    "addr:full":"317 N Main St Ainsworth NE 69210",
    "addr:housenumber":"317",
    "addr:postcode":"69210",
    "addr:street":"N Main St",
    "iso:country":"US",
    "sg:address":"317 N Main St",
    "sg:city":"Ainsworth",
    "sg:classifiers":[
        {
            "category":"Banks & Credit Unions",
            "subcategory":"Bank",
            "type":"Services"
        }
    ],
    "sg:phone":"+1 402 387 1842",
    "sg:postcode":"69210",
    "sg:province":"NE",
    "wof:name":"First National Bank",
    "wof:placetype":"venue"
},
  "geometry": {"coordinates":[-99.862602,42.549595],"type":"Point"}
}