{
  "type": "Feature",
  "properties": {
    "iso:country":"US",
    "sg:address":"736 W Cornhusker Hwy",
    "sg:city":"Lincoln",
    "sg:classifiers":[
        {
            "category":"Food & Beverages",
            "subcategory":"Liquor & Beverages",
            "type":"Retail Goods"
        }
    ],
    "sg:phone":"+1 402 479 9935",
    "sg:postcode":"68521",
    "sg:province":"NE",
    "sg:tags":[
        "beer",
        "ale"
    ],
    "wof:name":"Top Hat Tavern",
    "wof:placetype":"venue"
},
  "geometry": {"coordinates":[-96.733013,40.835654],"type":"Point"}
}