{
  "type": "Feature",
  "properties": {
    "iso:country":"US",
    "sg:address":"412 Ella St",
    "sg:city":"Beatrice",
    "sg:classifiers":[
        {
            "category":"Cinema",
            "subcategory":"Movie Theater",
            "type":"Entertainment"
        }
    ],
    "sg:phone":"+1 402 228 1801",
    "sg:postcode":"68310",
    "sg:province":"NE",
    "wof:name":"Community Players",
    "wof:placetype":"venue"
},
  "geometry": {"coordinates":[-96.747985,40.266962],"type":"Point"}
}