{
  "type": "Feature",
  "properties": {
    "iso:country":"US",
    "sg:address":"4423 Pacific St",
    "sg:city":"Omaha",
    "sg:classifiers":[
        {
            "category":"Professional",
            "subcategory":"Accounting & Tax Preparation",
            "type":"Services"
        }
    ],
    "sg:phone":"+1 402 813 7736",
    "sg:postcode":"68105",
    "sg:province":"NE",
    "sg:tags":[
        "accountant"
    ],
    "sg:website":"accountabilityomaha.com",
    "wof:name":"Account Ability",
    "wof:placetype":"venue"
},
  "geometry": {"coordinates":[-95.98005999999999,41.24851],"type":"Point"}
}