{
  "type": "Feature",
  "properties": {
    "iso:country":"US",
    "sg:address":"1627 S 17th St",
    "sg:city":"Lincoln",
    "sg:classifiers":[
        {
            "category":"Insurance",
            "subcategory":"Insurance Agent",
            "type":"Services"
        }
    ],
    "sg:phone":"+1 402 477 4226",
    "sg:postcode":"68502",
    "sg:province":"NE",
    "wof:name":"Kim Mulder & Assoc",
    "wof:placetype":"venue"
},
  "geometry": {"coordinates":[-96.696758,40.796237],"type":"Point"}
}