{
  "type": "Feature",
  "properties": {
    "addr:full":"5341 E Nelson Rd Wellfleet NE 69170",
    "addr:housenumber":"5341",
    "addr:postcode":"69170",
    "addr:street":"E Nelson Rd",
    "iso:country":"US",
    "sg:address":"5341 E Nelson Rd",
    "sg:city":"Wellfleet",
    "sg:phone":"+1 308 963 4336",
    "sg:postcode":"69170",
    "sg:province":"NE",
    "sg:tags":[
        "farm",
        "grain",
        "cash"
    ],
    "wof:name":"Scott C Christian",
    "wof:placetype":"venue"
},
  "geometry": {"coordinates":[-100.70187900000001,40.843796],"type":"Point"}
}