{
  "type": "Feature",
  "properties": {
    "addr:full":"448 N Shore Dr South Sioux City NE 68776",
    "addr:housenumber":"448",
    "addr:postcode":"68776",
    "addr:street":"N Shore Dr",
    "iso:country":"US",
    "sg:address":"448 N Shore Dr",
    "sg:city":"South Sioux City",
    "sg:classifiers":[
        {
            "category":"Wholesale",
            "subcategory":"Auto Parts",
            "type":"Manufacturing & Wholesale Goods"
        }
    ],
    "sg:phone":"+1 402 494 5869",
    "sg:postcode":"68776",
    "sg:province":"NE",
    "sg:tags":[
        "automobile",
        "rebuilt"
    ],
    "wof:name":"De Lao Atokad Parts & Sales",
    "wof:placetype":"venue"
},
  "geometry": {"coordinates":[-96.438332,42.439151],"type":"Point"}
}