{
  "type": "Feature",
  "properties": {
    "iso:country":"US",
    "sg:address":"11448 Frances St",
    "sg:city":"Omaha",
    "sg:classifiers":[
        {
            "category":"Social Services",
            "type":"Services"
        }
    ],
    "sg:phone":"+1 402 333 2543",
    "sg:postcode":"68144",
    "sg:province":"NE",
    "sg:tags":[
        "senior",
        "citizen"
    ],
    "sg:website":"www.qualsolutions.com",
    "wof:name":"Quality Solutions",
    "wof:placetype":"venue"
},
  "geometry": {"coordinates":[-96.092213,41.239686],"type":"Point"}
}