{
  "type": "Feature",
  "properties": {
    "addr:full":"1905 Harney St Omaha NE 68102",
    "addr:housenumber":"1905",
    "addr:postcode":"68102",
    "addr:street":"Harney St",
    "iso:country":"US",
    "sg:address":"1905 Harney St",
    "sg:city":"Omaha",
    "sg:classifiers":[
        {
            "category":"Government",
            "subcategory":"Office",
            "type":"Public Place"
        }
    ],
    "sg:phone":"+1 402 444 7793",
    "sg:postcode":"68102",
    "sg:province":"NE",
    "sg:tags":[
        "county"
    ],
    "wof:name":"Douglas County Ofc Warrant Div",
    "wof:placetype":"venue"
},
  "geometry": {"coordinates":[-95.94099900000001,41.256495],"type":"Point"}
}