{
  "type": "Feature",
  "properties": {
    "addr:full":"445 N 5th St Hebron NE 68370",
    "addr:housenumber":"445",
    "addr:postcode":"68370",
    "addr:street":"N 5Th St",
    "iso:country":"US",
    "sg:address":"445 N 5th St",
    "sg:city":"Hebron",
    "sg:classifiers":[
        {
            "category":"Professional",
            "subcategory":"Accounting & Tax Preparation",
            "type":"Services"
        }
    ],
    "sg:phone":"+1 402 768 6000",
    "sg:postcode":"68370",
    "sg:province":"NE",
    "sg:tags":[
        "bookkeeping",
        "general"
    ],
    "wof:name":"Lisa's Bookkeeping",
    "wof:placetype":"venue"
},
  "geometry": {"coordinates":[-97.589062,40.170881],"type":"Point"}
}