{
  "type": "Feature",
  "properties": {
    "addr:full":"4400 Center St Omaha NE 68105",
    "addr:housenumber":"4400",
    "addr:postcode":"68105",
    "addr:street":"Center St",
    "iso:country":"US",
    "sg:address":"4400 Center St",
    "sg:city":"Omaha",
    "sg:classifiers":[
        {
            "category":"Education",
            "subcategory":"Library",
            "type":"Public Place"
        }
    ],
    "sg:phone":"+1 402 444 4851",
    "sg:postcode":"68105",
    "sg:province":"NE",
    "wof:name":"Omaha Public Library System",
    "wof:placetype":"venue"
},
  "geometry": {"coordinates":[-95.98061800000001,41.241527],"type":"Point"}
}