{
  "type": "Feature",
  "properties": {
    "addr:full":"113 S 9th St Nebraska City NE 68410",
    "addr:housenumber":"113",
    "addr:postcode":"68410",
    "addr:street":"S 9Th St",
    "iso:country":"US",
    "sg:address":"113 S 9th St",
    "sg:city":"Nebraska City",
    "sg:classifiers":[
        {
            "category":"Professional",
            "subcategory":"Engineering",
            "type":"Services"
        }
    ],
    "sg:phone":"+1 402 873 5859",
    "sg:postcode":"68410",
    "sg:province":"NE",
    "sg:tags":[
        "engineer"
    ],
    "wof:name":"Integrated Resources",
    "wof:placetype":"venue"
},
  "geometry": {"coordinates":[-95.856273,40.676498],"type":"Point"}
}