{
  "type": "Feature",
  "properties": {
    "iso:country":"US",
    "sg:address":"2101 17th Ave",
    "sg:city":"Central City",
    "sg:classifiers":[
        {
            "category":"Building & Trades",
            "subcategory":"Construction",
            "type":"Services"
        }
    ],
    "sg:phone":"+1 308 946 3840",
    "sg:postcode":"68826",
    "sg:province":"NE",
    "sg:tags":[
        "contractor"
    ],
    "wof:name":"Bay Plastering",
    "wof:placetype":"venue"
},
  "geometry": {"coordinates":[-98.001751,41.111112],"type":"Point"}
}