{
  "type": "Feature",
  "properties": {
    "addr:full":"920 Pine Tree Ln Lincoln NE 68521",
    "addr:housenumber":"920",
    "addr:postcode":"68521",
    "addr:street":"Pine Tree Ln",
    "iso:country":"US",
    "sg:address":"920 Pine Tree Ln",
    "sg:city":"Lincoln",
    "sg:classifiers":[
        {
            "category":"Building & Trades",
            "subcategory":"Construction",
            "type":"Services"
        }
    ],
    "sg:phone":"+1 402 477 2971",
    "sg:postcode":"68521",
    "sg:province":"NE",
    "sg:tags":[
        "hanging",
        "contractor"
    ],
    "wof:name":"2lk Horse & Cattle Co",
    "wof:placetype":"venue"
},
  "geometry": {"coordinates":[-96.709221,40.861184],"type":"Point"}
}