{
  "type": "Feature",
  "properties": {
    "iso:country":"US",
    "sg:address":"1136 W J St",
    "sg:city":"Hastings",
    "sg:classifiers":[
        {
            "category":"Autos & Motor Vehicles",
            "subcategory":"Automobile Sales",
            "type":"Retail Goods"
        }
    ],
    "sg:phone":"+1 402 462 4045",
    "sg:postcode":"68901",
    "sg:province":"NE",
    "sg:tags":[
        "car",
        "dealer"
    ],
    "wof:name":"Highway 6 Auto Sales",
    "wof:placetype":"venue"
},
  "geometry": {"coordinates":[-98.395698,40.568108],"type":"Point"}
}