{
  "type": "Feature",
  "properties": {
    "iso:country":"US",
    "sg:address":"2443 S 186th Cir",
    "sg:city":"Omaha",
    "sg:classifiers":[
        {
            "category":"Professional",
            "subcategory":"Advertising",
            "type":"Services"
        }
    ],
    "sg:phone":"+1 402 933 1422",
    "sg:postcode":"68130",
    "sg:province":"NE",
    "sg:tags":[
        "mail",
        "direct"
    ],
    "wof:name":"Cornerstone Customer Solutions",
    "wof:placetype":"venue"
},
  "geometry": {"coordinates":[-96.207515,41.236117],"type":"Point"}
}