{
  "type": "Feature",
  "properties": {
    "iso:country":"US",
    "sg:address":"14222 Hillsdale Cir",
    "sg:city":"Omaha",
    "sg:classifiers":[
        {
            "category":"Real Estate",
            "subcategory":"Real Estate Operator",
            "type":"Services"
        },
        {
            "category":"Insurance",
            "subcategory":"Insurance Agent",
            "type":"Services"
        }
    ],
    "sg:phone":"+1 402 991 1005",
    "sg:postcode":"68137",
    "sg:province":"NE",
    "sg:website":"www.visionairesite.com",
    "wof:name":"Visionaire Insurance Services",
    "wof:placetype":"venue"
},
  "geometry": {"coordinates":[-96.13721099999999,41.215205],"type":"Point"}
}