{
  "type": "Feature",
  "properties": {
    "iso:country":"US",
    "sg:address":"8805 Indian Hls Dr",
    "sg:city":"Omaha",
    "sg:classifiers":[
        {
            "category":"Banks & Credit Unions",
            "subcategory":"Investment Brokerage",
            "type":"Services"
        }
    ],
    "sg:phone":"+1 402 392 2606",
    "sg:postcode":"68114",
    "sg:province":"NE",
    "sg:tags":[
        "advisory",
        "financial"
    ],
    "wof:name":"Lawson Kroeker Management Inc",
    "wof:placetype":"venue"
},
  "geometry": {"coordinates":[-96.049031,41.261712],"type":"Point"}
}