{
  "type": "Feature",
  "properties": {
    "iso:country":"US",
    "sg:address":"512 Vernon St",
    "sg:city":"Trumbull",
    "sg:classifiers":[
        {
            "category":"Wholesale",
            "subcategory":"Machinery & Supplies",
            "type":"Manufacturing & Wholesale Goods"
        }
    ],
    "sg:phone":"+1 402 743 2377",
    "sg:postcode":"68980",
    "sg:province":"NE",
    "wof:name":"Samuelson Equipment Co",
    "wof:placetype":"venue"
},
  "geometry": {"coordinates":[-98.27109299999999,40.677544],"type":"Point"}
}