{
  "type": "Feature",
  "properties": {
    "addr:full":"1407 Alpha St North Platte NE 69101",
    "addr:housenumber":"1407",
    "addr:postcode":"69101",
    "addr:street":"Alpha St",
    "iso:country":"US",
    "sg:address":"1407 Alpha St",
    "sg:city":"North Platte",
    "sg:classifiers":[
        {
            "category":"Personal",
            "type":"Services"
        }
    ],
    "sg:phone":"+1 308 532 5632",
    "sg:postcode":"69101",
    "sg:province":"NE",
    "wof:name":"Carpentry Creations",
    "wof:placetype":"venue"
},
  "geometry": {"coordinates":[-100.78089300000001,41.135071],"type":"Point"}
}