{
  "type": "Feature",
  "properties": {
    "iso:country":"US",
    "sg:address":"119 N Lexington Ave",
    "sg:city":"Hastings",
    "sg:classifiers":[
        {
            "category":"Building & Trades",
            "subcategory":"Landscaping Services",
            "type":"Services"
        }
    ],
    "sg:phone":"+1 402 463 3001",
    "sg:postcode":"68901",
    "sg:province":"NE",
    "sg:tags":[
        "lawn",
        "maintenance",
        "grounds"
    ],
    "wof:name":"Highland Park Lawn Company",
    "wof:placetype":"venue"
},
  "geometry": {"coordinates":[-98.393857,40.585065],"type":"Point"}
}