{
  "type": "Feature",
  "properties": {
    "addr:full":"208 E Bek Ave Seward NE 68434",
    "addr:housenumber":"208",
    "addr:postcode":"68434",
    "addr:street":"E Bek Ave",
    "iso:country":"US",
    "sg:address":"208 E Bek Ave",
    "sg:city":"Seward",
    "sg:classifiers":[
        {
            "category":"Organizations",
            "subcategory":"Religious Organization",
            "type":"Services"
        }
    ],
    "sg:phone":"+1 402 643 3575",
    "sg:postcode":"68434",
    "sg:province":"NE",
    "wof:name":"Calvary Baptist Church",
    "wof:placetype":"venue"
},
  "geometry": {"coordinates":[-97.09066199999999,40.919692],"type":"Point"}
}