{
  "type": "Feature",
  "properties": {
    "iso:country":"US",
    "sg:address":"716 Tara Rd",
    "sg:city":"Papillion",
    "sg:classifiers":[
        {
            "category":"Professional",
            "subcategory":"Business Services",
            "type":"Services"
        }
    ],
    "sg:phone":"+1 402 593 1397",
    "sg:postcode":"68046",
    "sg:province":"NE",
    "wof:name":"Fast Track",
    "wof:placetype":"venue"
},
  "geometry": {"coordinates":[-96.037143,41.16485],"type":"Point"}
}