{
  "type": "Feature",
  "properties": {
    "addr:full":"2110 Central Ave Nebraska City NE 68410",
    "addr:housenumber":"2110",
    "addr:postcode":"68410",
    "addr:street":"Central Ave",
    "iso:country":"US",
    "sg:address":"2110 Central Ave",
    "sg:city":"Nebraska City",
    "sg:classifiers":[
        {
            "category":"Government",
            "subcategory":"Office",
            "type":"Public Place"
        }
    ],
    "sg:phone":"+1 402 873 9535",
    "sg:postcode":"68410",
    "sg:province":"NE",
    "sg:tags":[
        "county",
        "resource"
    ],
    "wof:name":"Otoe County Child Support",
    "wof:placetype":"venue"
},
  "geometry": {"coordinates":[-95.87240300000001,40.676904],"type":"Point"}
}