{
  "type": "Feature",
  "properties": {
    "iso:country":"US",
    "sg:address":"11329 P St",
    "sg:city":"Omaha",
    "sg:classifiers":[
        {
            "category":"Social Services",
            "type":"Services"
        }
    ],
    "sg:phone":"+1 402 597 2122",
    "sg:postcode":"68137",
    "sg:province":"NE",
    "sg:tags":[
        "worker"
    ],
    "wof:name":"Ann Lamb",
    "wof:placetype":"venue"
},
  "geometry": {"coordinates":[-96.089805,41.206206],"type":"Point"}
}