{
  "type": "Feature",
  "properties": {
    "addr:full":"7636 Glenvale Dr Omaha NE 68134",
    "addr:housenumber":"7636",
    "addr:postcode":"68134",
    "addr:street":"Glenvale Dr",
    "iso:country":"US",
    "sg:address":"7636 Glenvale Dr",
    "sg:city":"Omaha",
    "sg:classifiers":[
        {
            "category":"Manufacturing",
            "subcategory":"Electronics",
            "type":"Manufacturing & Wholesale Goods"
        }
    ],
    "sg:phone":"+1 402 493 2497",
    "sg:postcode":"68134",
    "sg:province":"NE",
    "sg:tags":[
        "equipment",
        "electronic",
        "supply"
    ],
    "wof:name":"Quanah 1 Technologies",
    "wof:placetype":"venue"
},
  "geometry": {"coordinates":[-96.030466,41.294719],"type":"Point"}
}