{
  "type": "Feature",
  "properties": {
    "iso:country":"US",
    "sg:address":"43566 Rd 754",
    "sg:city":"Lexington",
    "sg:classifiers":[
        {
            "category":"Utilities",
            "subcategory":"Refuse",
            "type":"Services"
        }
    ],
    "sg:phone":"+1 308 324 6693",
    "sg:postcode":"68850",
    "sg:province":"NE",
    "sg:tags":[
        "garbage",
        "collection"
    ],
    "wof:name":"Dan's Sanitation Inc",
    "wof:placetype":"venue"
},
  "geometry": {"coordinates":[-99.856111,40.75717],"type":"Point"}
}