{
  "type": "Feature",
  "properties": {
    "addr:full":"13013 W Center Rd Omaha NE 68144",
    "addr:housenumber":"13013",
    "addr:postcode":"68144",
    "addr:street":"W Center Rd",
    "iso:country":"US",
    "sg:address":"13013 W Center Rd",
    "sg:city":"Omaha",
    "sg:classifiers":[
        {
            "category":"Shopping",
            "subcategory":"Computers & Home Electronics",
            "type":"Retail Goods"
        }
    ],
    "sg:phone":"+1 402 330 0240",
    "sg:postcode":"68144",
    "sg:province":"NE",
    "wof:name":"Radio Shack",
    "wof:placetype":"venue"
},
  "geometry": {"coordinates":[-96.115618,41.233978],"type":"Point"}
}