{
  "type": "Feature",
  "properties": {
    "addr:full":"301 S G St Milford NE 68405",
    "addr:housenumber":"301",
    "addr:postcode":"68405",
    "addr:street":"S G St",
    "iso:country":"US",
    "sg:address":"301 S G St",
    "sg:city":"Milford",
    "sg:classifiers":[
        {
            "category":"Education",
            "subcategory":"School",
            "type":"Public Place"
        }
    ],
    "sg:phone":"+1 402 761 2525",
    "sg:postcode":"68405",
    "sg:province":"NE",
    "sg:website":"www.milford.esu6.k12.ne.us",
    "wof:name":"Milford High School",
    "wof:placetype":"venue"
},
  "geometry": {"coordinates":[-97.05900099999999,40.77225],"type":"Point"}
}