{
  "type": "Feature",
  "properties": {
    "iso:country":"US",
    "sg:address":"5422 S 174th St",
    "sg:city":"Omaha",
    "sg:classifiers":[
        {
            "category":"Building & Trades",
            "subcategory":"Construction",
            "type":"Services"
        }
    ],
    "sg:phone":"+1 402 390 2346",
    "sg:postcode":"68135",
    "sg:province":"NE",
    "sg:tags":[
        "general",
        "contractor"
    ],
    "wof:name":"Mike OHearn Construction",
    "wof:placetype":"venue"
},
  "geometry": {"coordinates":[-96.18646,41.201136],"type":"Point"}
}