{
  "type": "Feature",
  "properties": {
    "addr:full":"81 W 5th St Fremont NE 68025",
    "addr:housenumber":"81",
    "addr:postcode":"68025",
    "addr:street":"W 5Th St",
    "iso:country":"US",
    "sg:address":"81 W 5th St",
    "sg:city":"Fremont",
    "sg:classifiers":[
        {
            "category":"Real Estate",
            "subcategory":"Real Estate Operator",
            "type":"Services"
        }
    ],
    "sg:phone":"+1 402 721 6160",
    "sg:postcode":"68025",
    "sg:province":"NE",
    "sg:tags":[
        "property",
        "commercial",
        "lessor"
    ],
    "wof:name":"Schafersman Yost Lamme",
    "wof:placetype":"venue"
},
  "geometry": {"coordinates":[-96.498321,41.433803],"type":"Point"}
}