{
  "type": "Feature",
  "properties": {
    "iso:country":"US",
    "sg:address":"1002 Sioux Ln",
    "sg:city":"North Platte",
    "sg:classifiers":[
        {
            "category":"Professional",
            "type":"Services"
        },
        {
            "category":"Professional",
            "subcategory":"Management & Consulting",
            "type":"Services"
        }
    ],
    "sg:phone":"+1 308 532 9625",
    "sg:postcode":"69101",
    "sg:province":"NE",
    "sg:tags":[
        "writer",
        "business"
    ],
    "wof:name":"Buckland Consulting LLC",
    "wof:placetype":"venue"
},
  "geometry": {"coordinates":[-100.78956100000001,41.080455],"type":"Point"}
}