{
  "type": "Feature",
  "properties": {
    "iso:country":"US",
    "sg:address":"11725 W A St",
    "sg:city":"Lincoln",
    "sg:classifiers":[
        {
            "category":"Building & Trades",
            "subcategory":"Construction",
            "type":"Services"
        }
    ],
    "sg:phone":"+1 402 488 1122",
    "sg:postcode":"68532",
    "sg:province":"NE",
    "sg:tags":[
        "designer",
        "dealer",
        "pool",
        "swimming"
    ],
    "wof:name":"Hermsmeyer Pool Co",
    "wof:placetype":"venue"
},
  "geometry": {"coordinates":[-96.868016,40.799317],"type":"Point"}
}