{
  "type": "Feature",
  "properties": {
    "iso:country":"US",
    "sg:address":"1220 Central Ave",
    "sg:city":"Kearney",
    "sg:classifiers":[
        {
            "category":"Organizations",
            "subcategory":"Religious Organization",
            "type":"Services"
        }
    ],
    "sg:phone":"+1 308 237 0220",
    "sg:postcode":"68847",
    "sg:province":"NE",
    "sg:tags":[
        "church"
    ],
    "wof:name":"New Hope Family Church",
    "wof:placetype":"venue"
},
  "geometry": {"coordinates":[-99.082071,40.686961],"type":"Point"}
}