{
  "type": "Feature",
  "properties": {
    "addr:full":"105 N Wheeler Ave Grand Island NE 68801",
    "addr:housenumber":"105",
    "addr:postcode":"68801",
    "addr:street":"N Wheeler Ave",
    "iso:country":"US",
    "sg:address":"105 N Wheeler Ave",
    "sg:city":"Grand Island",
    "sg:classifiers":[
        {
            "category":"Utilities",
            "subcategory":"Mobile Phone",
            "type":"Services"
        }
    ],
    "sg:phone":"+1 308 381 3021",
    "sg:postcode":"68801",
    "sg:province":"NE",
    "sg:tags":[
        "communication",
        "radiotelephone"
    ],
    "wof:name":"Qwest",
    "wof:placetype":"venue"
},
  "geometry": {"coordinates":[-98.341166,40.923656],"type":"Point"}
}