{
  "type": "Feature",
  "properties": {
    "addr:full":"13800 Giles Rd Omaha NE 68138",
    "addr:housenumber":"13800",
    "addr:postcode":"68138",
    "addr:street":"Giles Rd",
    "iso:country":"US",
    "sg:address":"13800 Giles Rd",
    "sg:city":"Omaha",
    "sg:classifiers":[
        {
            "category":"Manufacturing",
            "subcategory":"Glass & Minerals",
            "type":"Manufacturing & Wholesale Goods"
        }
    ],
    "sg:phone":"+1 402 895 3848",
    "sg:postcode":"68138",
    "sg:province":"NE",
    "sg:tags":[
        "product",
        "mfg",
        "concrete",
        "precast",
        "brick",
        "prod",
        "block"
    ],
    "sg:website":"www.enterpriseprecast.com",
    "wof:name":"Enterprises Precast Concrete",
    "wof:placetype":"venue"
},
  "geometry": {"coordinates":[-96.13193800000001,41.176286],"type":"Point"}
}