{
  "type": "Feature",
  "properties": {
    "iso:country":"US",
    "sg:address":"229 E Douglas St",
    "sg:city":"Oneill",
    "sg:classifiers":[
        {
            "category":"Government",
            "subcategory":"Police Station",
            "type":"Public Place"
        }
    ],
    "sg:phone":"+1 402 336 3956",
    "sg:postcode":"68763",
    "sg:province":"NE",
    "sg:tags":[
        "state"
    ],
    "wof:name":"State Patrol",
    "wof:placetype":"venue"
},
  "geometry": {"coordinates":[-98.65074199999999,42.457572],"type":"Point"}
}