{
  "type": "Feature",
  "properties": {
    "iso:country":"US",
    "sg:address":"233 J Rd",
    "sg:city":"Axtell",
    "sg:classifiers":[
        {
            "category":"Professional",
            "subcategory":"Research",
            "type":"Services"
        }
    ],
    "sg:phone":"+1 308 743 2245",
    "sg:postcode":"68924",
    "sg:province":"NE",
    "sg:tags":[
        "commercial",
        "physical"
    ],
    "wof:name":"Corn Husker Agronomics",
    "wof:placetype":"venue"
},
  "geometry": {"coordinates":[-99.15674,40.466846],"type":"Point"}
}