{
  "type": "Feature",
  "properties": {
    "iso:country":"US",
    "sg:address":"706 Liberty Rd",
    "sg:city":"Dannebrog",
    "sg:classifiers":[
        {
            "category":"Retail",
            "subcategory":"Laundry & Dry Cleaning",
            "type":"Services"
        }
    ],
    "sg:phone":"+1 308 226 2516",
    "sg:postcode":"68831",
    "sg:province":"NE",
    "sg:tags":[
        "cleaners"
    ],
    "wof:name":"St Paul Cleaners",
    "wof:placetype":"venue"
},
  "geometry": {"coordinates":[-98.518733,41.13549],"type":"Point"}
}