{
  "type": "Feature",
  "properties": {
    "iso:country":"US",
    "sg:address":"601 N Tabor Ave",
    "sg:city":"North Platte",
    "sg:classifiers":[
        {
            "category":"Organizations",
            "subcategory":"Non-profit Organization",
            "type":"Services"
        }
    ],
    "sg:phone":"+1 308 534 5939",
    "sg:postcode":"69101",
    "sg:province":"NE",
    "wof:name":"Catholic Schools Endowment Trs",
    "wof:placetype":"venue"
},
  "geometry": {"coordinates":[-100.75157,41.137758],"type":"Point"}
}