{
  "type": "Feature",
  "properties": {
    "iso:country":"US",
    "sg:address":"2801 Cornhusker Hwy",
    "sg:city":"Lincoln",
    "sg:classifiers":[
        {
            "category":"Professional",
            "type":"Services"
        }
    ],
    "sg:phone":"+1 402 466 9010",
    "sg:postcode":"68504",
    "sg:province":"NE",
    "sg:tags":[
        "establishment"
    ],
    "wof:name":"Hoppe & Assoc",
    "wof:placetype":"venue"
},
  "geometry": {"coordinates":[-96.680761,40.842413],"type":"Point"}
}