{
  "type": "Feature",
  "properties": {
    "iso:country":"US",
    "sg:address":"4311 A St",
    "sg:city":"Lincoln",
    "sg:classifiers":[
        {
            "category":"Shopping",
            "subcategory":"Gifts & Souvenirs",
            "type":"Retail Goods"
        }
    ],
    "sg:phone":"+1 402 488 8010",
    "sg:postcode":"68510",
    "sg:province":"NE",
    "wof:name":"Its Moore Wood",
    "wof:placetype":"venue"
},
  "geometry": {"coordinates":[-96.661506,40.798867],"type":"Point"}
}