{
  "type": "Feature",
  "properties": {
    "iso:country":"US",
    "sg:address":"33207 Kimberly Dr",
    "sg:city":"Louisville",
    "sg:classifiers":[
        {
            "category":"Personal",
            "subcategory":"Beauty Salon",
            "type":"Services"
        }
    ],
    "sg:phone":"+1 402 234 4148",
    "sg:postcode":"68003",
    "sg:province":"NE",
    "sg:tags":[
        "shop"
    ],
    "wof:name":"Chics-N-Chaps",
    "wof:placetype":"venue"
},
  "geometry": {"coordinates":[-96.24136900000001,40.993782],"type":"Point"}
}