{
  "type": "Feature",
  "properties": {
    "iso:country":"US",
    "sg:address":"1313 Parkview Dr",
    "sg:city":"Norfolk",
    "sg:classifiers":[
        {
            "category":"Insurance",
            "subcategory":"Insurance Agent",
            "type":"Services"
        }
    ],
    "sg:phone":"+1 402 379 3022",
    "sg:postcode":"68701",
    "sg:province":"NE",
    "wof:name":"Larry E Rosenbaum",
    "wof:placetype":"venue"
},
  "geometry": {"coordinates":[-97.427296,42.044447],"type":"Point"}
}