{
  "type": "Feature",
  "properties": {
    "iso:country":"US",
    "sg:address":"2611 W M Ct",
    "sg:city":"Lincoln",
    "sg:classifiers":[
        {
            "category":"Building & Trades",
            "subcategory":"Construction",
            "type":"Services"
        }
    ],
    "sg:phone":"+1 402 742 3310",
    "sg:postcode":"68522",
    "sg:province":"NE",
    "sg:tags":[
        "concrete",
        "contractor"
    ],
    "wof:name":"R & T Poured Walls",
    "wof:placetype":"venue"
},
  "geometry": {"coordinates":[-96.758802,40.812036],"type":"Point"}
}