{
  "type": "Feature",
  "properties": {
    "addr:full":"2727 W 2nd St Hastings NE 68901",
    "addr:housenumber":"2727",
    "addr:postcode":"68901",
    "addr:street":"W 2Nd St",
    "iso:country":"US",
    "sg:address":"2727 W 2nd St",
    "sg:city":"Hastings",
    "sg:classifiers":[
        {
            "category":"Organizations",
            "subcategory":"Non-profit Organization",
            "type":"Services"
        }
    ],
    "sg:phone":"+1 402 462 3031",
    "sg:postcode":"68901",
    "sg:province":"NE",
    "sg:tags":[
        "charitable",
        "institution"
    ],
    "wof:name":"Easter Seals Nebraska",
    "wof:placetype":"venue"
},
  "geometry": {"coordinates":[-98.419738,40.585171],"type":"Point"}
}