{
  "type": "Feature",
  "properties": {
    "addr:full":"617 O St Loup City NE 68853",
    "addr:housenumber":"617",
    "addr:postcode":"68853",
    "addr:street":"O St",
    "iso:country":"US",
    "sg:address":"617 O St",
    "sg:city":"Loup City",
    "sg:classifiers":[
        {
            "category":"Social Services",
            "type":"Services"
        }
    ],
    "sg:phone":"+1 308 745 1810",
    "sg:postcode":"68853",
    "sg:province":"NE",
    "sg:tags":[
        "senior",
        "citizen"
    ],
    "wof:name":"Senior Center",
    "wof:placetype":"venue"
},
  "geometry": {"coordinates":[-98.965558,41.274689],"type":"Point"}
}