{
  "type": "Feature",
  "properties": {
    "iso:country":"US",
    "sg:address":"844 S 16th St",
    "sg:city":"Lincoln",
    "sg:classifiers":[
        {
            "category":"Education",
            "subcategory":"University",
            "type":"Public Place"
        }
    ],
    "sg:phone":"+1 402 472 1963",
    "sg:postcode":"68508",
    "sg:province":"NE",
    "sg:tags":[
        "college"
    ],
    "sg:website":"http://www.unomaha.edu",
    "wof:name":"University Of Nebraska",
    "wof:placetype":"venue"
},
  "geometry": {"coordinates":[-96.698246,40.805339],"type":"Point"}
}