{
  "type": "Feature",
  "properties": {
    "iso:country":"US",
    "sg:address":"10303 Crown Point Ave",
    "sg:city":"Omaha",
    "sg:classifiers":[
        {
            "category":"Banks & Credit Unions",
            "subcategory":"Bank",
            "type":"Services"
        }
    ],
    "sg:phone":"+1 402 496 4001",
    "sg:postcode":"68134",
    "sg:province":"NE",
    "sg:tags":[
        "loan",
        "real estate"
    ],
    "wof:name":"Mortgage Smartz",
    "wof:placetype":"venue"
},
  "geometry": {"coordinates":[-96.074496,41.312221],"type":"Point"}
}