{
  "type": "Feature",
  "properties": {
    "iso:country":"US",
    "sg:address":"2118 Market Ln",
    "sg:city":"Norfolk",
    "sg:classifiers":[
        {
            "category":"Bars & Pubs",
            "type":"Food & Drink"
        }
    ],
    "sg:phone":"+1 402 844 4917",
    "sg:postcode":"68701",
    "sg:province":"NE",
    "wof:name":"Players Lounge & Grill",
    "wof:placetype":"venue"
},
  "geometry": {"coordinates":[-97.43766100000001,42.022192],"type":"Point"}
}