{
  "type": "Feature",
  "properties": {
    "iso:country":"US",
    "sg:address":"1103 G St",
    "sg:city":"Aurora",
    "sg:classifiers":[
        {
            "category":"Building & Trades",
            "subcategory":"Construction",
            "type":"Services"
        }
    ],
    "sg:phone":"+1 402 694 2511",
    "sg:postcode":"68818",
    "sg:province":"NE",
    "sg:tags":[
        "marking",
        "maintenance",
        "parking"
    ],
    "wof:name":"Aurora Street Dept",
    "wof:placetype":"venue"
},
  "geometry": {"coordinates":[-98.002689,40.863522],"type":"Point"}
}