{
  "type": "Feature",
  "properties": {
    "addr:full":"2609 S 132nd St Omaha NE 68144",
    "addr:housenumber":"2609",
    "addr:postcode":"68144",
    "addr:street":"S 132Nd St",
    "iso:country":"US",
    "sg:address":"2609 S 132nd St",
    "sg:city":"Omaha",
    "sg:classifiers":[
        {
            "category":"Shopping",
            "subcategory":"Clothing, Apparel, & Fashions",
            "type":"Retail Goods"
        }
    ],
    "sg:phone":"+1 402 333 5206",
    "sg:postcode":"68144",
    "sg:province":"NE",
    "sg:tags":[
        "furnishing"
    ],
    "wof:name":"Post & Nickel",
    "wof:placetype":"venue"
},
  "geometry": {"coordinates":[-96.119427,41.235025],"type":"Point"}
}