{
  "type": "Feature",
  "properties": {
    "addr:full":"13908 S 226th Ave Gretna NE 68028",
    "addr:housenumber":"13908",
    "addr:postcode":"68028",
    "addr:street":"S 226Th Ave",
    "iso:country":"US",
    "sg:address":"13908 S 226th Ave",
    "sg:city":"Gretna",
    "sg:classifiers":[
        {
            "category":"Shopping",
            "subcategory":"Computers & Home Electronics",
            "type":"Retail Goods"
        }
    ],
    "sg:phone":"+1 402 332 5600",
    "sg:postcode":"68028",
    "sg:province":"NE",
    "sg:tags":[
        "software"
    ],
    "wof:name":"Turn Key Solutions",
    "wof:placetype":"venue"
},
  "geometry": {"coordinates":[-96.270252,41.10412],"type":"Point"}
}