{
  "type": "Feature",
  "properties": {
    "addr:full":"1901 Fulton St Falls City NE 68355",
    "addr:housenumber":"1901",
    "addr:postcode":"68355",
    "addr:street":"Fulton St",
    "iso:country":"US",
    "sg:address":"1901 Fulton St",
    "sg:city":"Falls City",
    "sg:classifiers":[
        {
            "category":"Retail",
            "subcategory":"Car Wash",
            "type":"Services"
        }
    ],
    "sg:phone":"+1 402 245 2367",
    "sg:postcode":"68355",
    "sg:province":"NE",
    "sg:tags":[
        "carwash"
    ],
    "wof:name":"Bmrs Ltd",
    "wof:placetype":"venue"
},
  "geometry": {"coordinates":[-95.59574499999999,40.064684],"type":"Point"}
}