{
  "type": "Feature",
  "properties": {
    "iso:country":"US",
    "sg:address":"508 S U Rd",
    "sg:city":"Aurora",
    "sg:classifiers":[
        {
            "category":"Retail",
            "subcategory":"Animal Services",
            "type":"Services"
        }
    ],
    "sg:phone":"+1 402 723 4213",
    "sg:postcode":"68843",
    "sg:province":"NE",
    "sg:tags":[
        "breeder",
        "horse"
    ],
    "wof:name":"Oakgrove Clydesdales",
    "wof:placetype":"venue"
},
  "geometry": {"coordinates":[-97.920917,40.762093],"type":"Point"}
}