{
  "type": "Feature",
  "properties": {
    "addr:full":"808 E Philip Ave North Platte NE 69101",
    "addr:housenumber":"808",
    "addr:postcode":"69101",
    "addr:street":"E Philip Ave",
    "iso:country":"US",
    "sg:address":"808 E Philip Ave",
    "sg:city":"North Platte",
    "sg:classifiers":[
        {
            "category":"Organizations",
            "subcategory":"Religious Organization",
            "type":"Services"
        }
    ],
    "sg:phone":"+1 308 532 3286",
    "sg:postcode":"69101",
    "sg:province":"NE",
    "sg:tags":[
        "church"
    ],
    "wof:name":"First Assembly Of God",
    "wof:placetype":"venue"
},
  "geometry": {"coordinates":[-100.755612,41.126097],"type":"Point"}
}