{
  "type": "Feature",
  "properties": {
    "iso:country":"US",
    "sg:address":"516 Ridge St",
    "sg:city":"Dawson",
    "sg:classifiers":[
        {
            "category":"Government",
            "subcategory":"Post Office",
            "type":"Public Place"
        }
    ],
    "sg:phone":"+1 402 855 2555",
    "sg:postcode":"68337",
    "sg:province":"NE",
    "wof:name":"US Post Office",
    "wof:placetype":"venue"
},
  "geometry": {"coordinates":[-95.830568,40.131885],"type":"Point"}
}