{
  "type": "Feature",
  "properties": {
    "iso:country":"US",
    "sg:address":"11732 W Dodge Rd",
    "sg:city":"Omaha",
    "sg:classifiers":[
        {
            "category":"Restaurant",
            "type":"Food & Drink"
        }
    ],
    "sg:menulink":"http://www.allmenus.com/ne/omaha/9930-jericos/menu/",
    "sg:phone":"+1 402 496 0222",
    "sg:postcode":"68154",
    "sg:province":"NE",
    "sg:tags":[
        "american",
        "steakhouse"
    ],
    "wof:name":"Jerico's",
    "wof:placetype":"venue"
},
  "geometry": {"coordinates":[-96.09661199999999,41.26353],"type":"Point"}
}