{
  "type": "Feature",
  "properties": {
    "iso:country":"US",
    "sg:address":"3700 Touzalin Ave",
    "sg:city":"Lincoln",
    "sg:classifiers":[
        {
            "category":"Professional",
            "subcategory":"Computer Services",
            "type":"Services"
        }
    ],
    "sg:phone":"+1 402 466 5954",
    "sg:postcode":"68507",
    "sg:province":"NE",
    "sg:tags":[
        "consulting",
        "programing",
        "business",
        "custom"
    ],
    "wof:name":"Business Computer Cons Inc",
    "wof:placetype":"venue"
},
  "geometry": {"coordinates":[-96.63991300000001,40.850719],"type":"Point"}
}