{
  "type": "Feature",
  "properties": {
    "iso:country":"US",
    "sg:address":"208 E 6th St",
    "sg:city":"Ainsworth",
    "sg:classifiers":[
        {
            "category":"Farming",
            "subcategory":"Farm",
            "type":"Manufacturing & Wholesale Goods"
        }
    ],
    "sg:phone":"+1 402 387 1248",
    "sg:postcode":"69210",
    "sg:province":"NE",
    "sg:tags":[
        "crop",
        "general"
    ],
    "wof:name":"Arens J",
    "wof:placetype":"venue"
},
  "geometry": {"coordinates":[-99.86112300000001,42.552385],"type":"Point"}
}