{
  "type": "Feature",
  "properties": {
    "addr:full":"229 US Hwy 275 West Point NE 68788",
    "addr:housenumber":"229",
    "addr:postcode":"68788",
    "addr:street":"Us Hwy 275",
    "iso:country":"US",
    "sg:address":"229 US Hwy 275",
    "sg:city":"West Point",
    "sg:classifiers":[
        {
            "category":"Home & Garden",
            "subcategory":"Garden Supply",
            "type":"Retail Goods"
        }
    ],
    "sg:phone":"+1 402 372 9086",
    "sg:postcode":"68788",
    "sg:province":"NE",
    "sg:tags":[
        "nurseryman"
    ],
    "wof:name":"Branch Office Tree Farm",
    "wof:placetype":"venue"
},
  "geometry": {"coordinates":[-96.71094100000001,41.838903],"type":"Point"}
}