{
  "type": "Feature",
  "properties": {
    "iso:country":"US",
    "sg:address":"550 Turner Blvd",
    "sg:city":"Omaha",
    "sg:classifiers":[
        {
            "category":"Government",
            "subcategory":"Fire Station",
            "type":"Public Place"
        }
    ],
    "sg:phone":"+1 402 444 4284",
    "sg:postcode":"68105",
    "sg:province":"NE",
    "sg:tags":[
        "department"
    ],
    "sg:website":"http://www.omagro.com",
    "wof:name":"Omaha Fire Department",
    "wof:placetype":"venue"
},
  "geometry": {"coordinates":[-95.960822,41.254353],"type":"Point"}
}