{
  "type": "Feature",
  "properties": {
    "iso:country":"US",
    "sg:address":"7209 S 53rd St",
    "sg:city":"Omaha",
    "sg:classifiers":[
        {
            "category":"Building & Trades",
            "subcategory":"Construction",
            "type":"Services"
        }
    ],
    "sg:phone":"+1 402 731 3660",
    "sg:postcode":"68157",
    "sg:province":"NE",
    "sg:tags":[
        "house"
    ],
    "wof:name":"Mkm Construction Inc",
    "wof:placetype":"venue"
},
  "geometry": {"coordinates":[-95.99782500000001,41.18605],"type":"Point"}
}