{
  "type": "Feature",
  "properties": {
    "iso:country":"US",
    "sg:address":"503 Lincoln St",
    "sg:city":"Concord",
    "sg:classifiers":[
        {
            "category":"Organizations",
            "subcategory":"Religious Organization",
            "type":"Services"
        }
    ],
    "sg:phone":"+1 402 584 2467",
    "sg:postcode":"68728",
    "sg:province":"NE",
    "sg:tags":[
        "church"
    ],
    "wof:name":"Concordia Lutheran Church",
    "wof:placetype":"venue"
},
  "geometry": {"coordinates":[-96.98829499999999,42.384898],"type":"Point"}
}