{
  "type": "Feature",
  "properties": {
    "addr:full":"5200 S 16th St Lincoln NE 68512",
    "addr:housenumber":"5200",
    "addr:postcode":"68512",
    "addr:street":"S 16Th St",
    "iso:country":"US",
    "sg:address":"5200 S 16th St",
    "sg:city":"Lincoln",
    "sg:classifiers":[
        {
            "category":"Professional",
            "subcategory":"Management & Consulting",
            "type":"Services"
        }
    ],
    "sg:phone":"+1 402 328 2283",
    "sg:postcode":"68512",
    "sg:province":"NE",
    "sg:tags":[
        "consultant",
        "lighting"
    ],
    "wof:name":"Voss Lighting",
    "wof:placetype":"venue"
},
  "geometry": {"coordinates":[-96.69918199999999,40.760715],"type":"Point"}
}