{
  "type": "Feature",
  "properties": {
    "iso:country":"US",
    "sg:address":"2824 S 148th Avenue Cir",
    "sg:city":"Omaha",
    "sg:classifiers":[
        {
            "category":"Wholesale",
            "subcategory":"Electrical",
            "type":"Manufacturing & Wholesale Goods"
        }
    ],
    "sg:phone":"+1 402 333 2111",
    "sg:postcode":"68144",
    "sg:province":"NE",
    "sg:tags":[
        "telecommunication"
    ],
    "sg:website":"www.locomaha.com",
    "wof:name":"Lines Of Communication Inc",
    "wof:placetype":"venue"
},
  "geometry": {"coordinates":[-96.147587,41.23307],"type":"Point"}
}