{
  "type": "Feature",
  "properties": {
    "iso:country":"US",
    "sg:address":"405 E Pacific St",
    "sg:city":"Lexington",
    "sg:classifiers":[
        {
            "category":"Bars & Pubs",
            "type":"Food & Drink"
        }
    ],
    "sg:phone":"+1 308 324 8926",
    "sg:postcode":"68850",
    "sg:province":"NE",
    "sg:tags":[
        "drinking"
    ],
    "wof:name":"El Penamba Bar",
    "wof:placetype":"venue"
},
  "geometry": {"coordinates":[-99.737408,40.775806],"type":"Point"}
}