{
  "type": "Feature",
  "properties": {
    "addr:full":"713 16th Ave Franklin NE 68939",
    "addr:housenumber":"713",
    "addr:postcode":"68939",
    "addr:street":"16Th Ave",
    "iso:country":"US",
    "sg:address":"713 16th Ave",
    "sg:city":"Franklin",
    "sg:classifiers":[
        {
            "category":"Retail",
            "subcategory":"Repair Shop",
            "type":"Services"
        }
    ],
    "sg:phone":"+1 308 425 3462",
    "sg:postcode":"68939",
    "sg:province":"NE",
    "sg:tags":[
        "welding"
    ],
    "wof:name":"Raymond Duncan Welding Shop",
    "wof:placetype":"venue"
},
  "geometry": {"coordinates":[-98.952398,40.094429],"type":"Point"}
}