{
  "type": "Feature",
  "properties": {
    "iso:country":"US",
    "sg:address":"3701 S 10th St",
    "sg:city":"Omaha",
    "sg:classifiers":[
        {
            "category":"Museum",
            "subcategory":"Zoo",
            "type":"Entertainment"
        }
    ],
    "sg:phone":"+1 402 733 8401",
    "sg:postcode":"68107",
    "sg:province":"NE",
    "sg:website":"www.omahazoo.com",
    "wof:name":"Omaha Zoo",
    "wof:placetype":"venue"
},
  "geometry": {"coordinates":[-95.929451,41.224706],"type":"Point"}
}