{
  "type": "Feature",
  "properties": {
    "iso:country":"US",
    "sg:address":"404 E Wicklow Ave",
    "sg:city":"Greeley",
    "sg:classifiers":[
        {
            "category":"Recreation",
            "type":"Entertainment"
        }
    ],
    "sg:phone":"+1 308 428 2206",
    "sg:postcode":"68842",
    "sg:province":"NE",
    "sg:tags":[
        "pool",
        "swimming"
    ],
    "wof:name":"Greeley Municipal Pool",
    "wof:placetype":"venue"
},
  "geometry": {"coordinates":[-98.527461,41.550719],"type":"Point"}
}