{
  "type": "Feature",
  "properties": {
    "iso:country":"US",
    "sg:address":"915 N Cotner Blvd",
    "sg:city":"Lincoln",
    "sg:classifiers":[
        {
            "category":"Wholesale",
            "subcategory":"Medical Equipment & Supplies",
            "type":"Manufacturing & Wholesale Goods"
        }
    ],
    "sg:phone":"+1 402 467 1428",
    "sg:postcode":"68505",
    "sg:province":"NE",
    "sg:tags":[
        "physician",
        "surgeon"
    ],
    "wof:name":"RJV Distributing",
    "wof:placetype":"venue"
},
  "geometry": {"coordinates":[-96.633319,40.822661],"type":"Point"}
}