{
  "type": "Feature",
  "properties": {
    "addr:full":"1320 N 37th St Lincoln NE 68503",
    "addr:housenumber":"1320",
    "addr:postcode":"68503",
    "addr:street":"N 37Th St",
    "iso:country":"US",
    "sg:address":"1320 N 37th St",
    "sg:city":"Lincoln",
    "sg:classifiers":[
        {
            "category":"Manufacturing",
            "subcategory":"Toys & Sporting Goods",
            "type":"Manufacturing & Wholesale Goods"
        }
    ],
    "sg:phone":"+1 402 467 5356",
    "sg:postcode":"68503",
    "sg:province":"NE",
    "sg:tags":[
        "mfg"
    ],
    "wof:name":"Andis Critter Dolls",
    "wof:placetype":"venue"
},
  "geometry": {"coordinates":[-96.667412,40.827848],"type":"Point"}
}