{
  "type": "Feature",
  "properties": {
    "iso:country":"US",
    "sg:address":"5039 Charles St",
    "sg:city":"Omaha",
    "sg:classifiers":[
        {
            "category":"Shopping",
            "subcategory":"Bicycles & Sporting Goods",
            "type":"Retail Goods"
        }
    ],
    "sg:phone":"+1 402 991 1103",
    "sg:postcode":"68132",
    "sg:province":"NE",
    "sg:tags":[
        "repair"
    ],
    "wof:name":"Bike N Trike",
    "wof:placetype":"venue"
},
  "geometry": {"coordinates":[-95.99194300000001,41.273074],"type":"Point"}
}