{
  "type": "Feature",
  "properties": {
    "addr:full":"256 G St Platte Center NE 68653",
    "addr:housenumber":"256",
    "addr:postcode":"68653",
    "addr:street":"G St",
    "iso:country":"US",
    "sg:address":"256 G St",
    "sg:city":"Platte Center",
    "sg:classifiers":[
        {
            "category":"Freight",
            "type":"Transportation"
        }
    ],
    "sg:phone":"+1 402 246 3145",
    "sg:postcode":"68653",
    "sg:province":"NE",
    "sg:tags":[
        "livestock",
        "hauling"
    ],
    "wof:name":"A J & Sons Trucking Inc",
    "wof:placetype":"venue"
},
  "geometry": {"coordinates":[-97.492746,41.537922],"type":"Point"}
}