{
  "type": "Feature",
  "properties": {
    "iso:country":"US",
    "sg:address":"3004 US Hwy 30",
    "sg:city":"Kearney",
    "sg:classifiers":[
        {
            "category":"Restaurant",
            "type":"Food & Drink"
        }
    ],
    "sg:phone":"+1 308 234 6554",
    "sg:postcode":"68845",
    "sg:province":"NE",
    "wof:name":"Quiznos Sub",
    "wof:placetype":"venue"
},
  "geometry": {"coordinates":[-99.038365,40.705111],"type":"Point"}
}