{
  "type": "Feature",
  "properties": {
    "addr:full":"12100 W Center Rd Omaha NE 68144",
    "addr:housenumber":"12100",
    "addr:postcode":"68144",
    "addr:street":"W Center Rd",
    "iso:country":"US",
    "sg:address":"12100 W Center Rd",
    "sg:city":"Omaha",
    "sg:classifiers":[
        {
            "category":"Real Estate",
            "subcategory":"Surveying",
            "type":"Services"
        }
    ],
    "sg:phone":"+1 402 334 7982",
    "sg:postcode":"68144",
    "sg:province":"NE",
    "sg:tags":[
        "surveyor"
    ],
    "wof:name":"Louis Surveying",
    "wof:placetype":"venue"
},
  "geometry": {"coordinates":[-96.10303,41.234102],"type":"Point"}
}