{
  "type": "Feature",
  "properties": {
    "iso:country":"US",
    "sg:address":"12303 W Center Rd",
    "sg:city":"Omaha",
    "sg:classifiers":[
        {
            "category":"Shopping",
            "subcategory":"Pharmacy",
            "type":"Retail Goods"
        }
    ],
    "sg:phone":"+1 402 333 8895",
    "sg:postcode":"68144",
    "sg:province":"NE",
    "wof:name":"Kmart Pharmacies Inc",
    "wof:placetype":"venue"
},
  "geometry": {"coordinates":[-96.105904,41.23394],"type":"Point"}
}