{
  "type": "Feature",
  "properties": {
    "addr:full":"6610 Northern Hills Dr Omaha NE 68152",
    "addr:housenumber":"6610",
    "addr:postcode":"68152",
    "addr:street":"Northern Hills Dr",
    "iso:country":"US",
    "sg:address":"6610 Northern Hills Dr",
    "sg:city":"Omaha",
    "sg:classifiers":[
        {
            "category":"Building & Trades",
            "subcategory":"Electrical",
            "type":"Services"
        }
    ],
    "sg:phone":"+1 402 571 1034",
    "sg:postcode":"68152",
    "sg:province":"NE",
    "sg:tags":[
        "electrical",
        "electric",
        "contractor"
    ],
    "wof:name":"Integrity Electric Service",
    "wof:placetype":"venue"
},
  "geometry": {"coordinates":[-96.023703,41.37565],"type":"Point"}
}