{
  "type": "Feature",
  "properties": {
    "iso:country":"US",
    "sg:address":"801 S 48th St",
    "sg:city":"Lincoln",
    "sg:classifiers":[
        {
            "category":"Health Services",
            "subcategory":"Doctor",
            "type":"Services"
        }
    ],
    "sg:phone":"+1 402 484 8787",
    "sg:postcode":"68510",
    "sg:province":"NE",
    "sg:tags":[
        "medical"
    ],
    "wof:name":"Nebraska Diagnostics Inc",
    "wof:placetype":"venue"
},
  "geometry": {"coordinates":[-96.65369099999999,40.804987],"type":"Point"}
}