{
  "type": "Feature",
  "properties": {
    "iso:country":"US",
    "sg:address":"3418 5th Ave",
    "sg:city":"Kearney",
    "sg:classifiers":[
        {
            "category":"Restaurant",
            "type":"Food & Drink"
        }
    ],
    "sg:phone":"+1 308 234 3623",
    "sg:postcode":"68845",
    "sg:province":"NE",
    "sg:tags":[
        "eating"
    ],
    "wof:name":"B&B Yogurt Inc",
    "wof:placetype":"venue"
},
  "geometry": {"coordinates":[-99.088283,40.709195],"type":"Point"}
}