{
  "type": "Feature",
  "properties": {
    "addr:full":"4645 Dodge St Omaha NE 68132",
    "addr:housenumber":"4645",
    "addr:postcode":"68132",
    "addr:street":"Dodge St",
    "iso:country":"US",
    "sg:address":"4645 Dodge St",
    "sg:city":"Omaha",
    "sg:phone":"+1 402 553 2121",
    "sg:postcode":"68132",
    "sg:province":"NE",
    "sg:website":"http://www.century21.com",
    "wof:name":"Century 21 Dundee Realty Co",
    "wof:placetype":"venue"
},
  "geometry": {"coordinates":[-95.983295,41.259702],"type":"Point"}
}