{
  "type": "Feature",
  "properties": {
    "iso:country":"US",
    "sg:address":"802 McDonald Rd",
    "sg:city":"North Platte",
    "sg:classifiers":[
        {
            "category":"Professional",
            "subcategory":"Detective & Security Services",
            "type":"Services"
        }
    ],
    "sg:phone":"+1 308 532 1860",
    "sg:postcode":"69101",
    "sg:province":"NE",
    "sg:tags":[
        "guard"
    ],
    "wof:name":"George Ripple",
    "wof:placetype":"venue"
},
  "geometry": {"coordinates":[-100.782121,41.127184],"type":"Point"}
}