{
  "type": "Feature",
  "properties": {
    "iso:country":"US",
    "sg:address":"15770 Q St",
    "sg:city":"Omaha",
    "sg:classifiers":[
        {
            "category":"Organizations",
            "subcategory":"Religious Organization",
            "type":"Services"
        }
    ],
    "sg:phone":"+1 402 895 7433",
    "sg:postcode":"68135",
    "sg:province":"NE",
    "wof:name":"Community Covenant Church",
    "wof:placetype":"venue"
},
  "geometry": {"coordinates":[-96.161235,41.205409],"type":"Point"}
}