{
  "type": "Feature",
  "properties": {
    "iso:country":"US",
    "sg:address":"1538 S 15th St",
    "sg:city":"Plattsmouth",
    "sg:classifiers":[
        {
            "category":"Wholesale",
            "subcategory":"Farm Supplies",
            "type":"Manufacturing & Wholesale Goods"
        }
    ],
    "sg:phone":"+1 402 296 2696",
    "sg:postcode":"68048",
    "sg:province":"NE",
    "wof:name":"Bomgaars",
    "wof:placetype":"venue"
},
  "geometry": {"coordinates":[-95.896731,40.997138],"type":"Point"}
}