{
  "type": "Feature",
  "properties": {
    "iso:country":"US",
    "sg:address":"1210 Golden Gate Dr",
    "sg:city":"Papillion",
    "sg:classifiers":[
        {
            "category":"Government",
            "subcategory":"Court House",
            "type":"Public Place"
        }
    ],
    "sg:phone":"+1 402 593 4491",
    "sg:postcode":"68046",
    "sg:province":"NE",
    "sg:tags":[
        "county"
    ],
    "wof:name":"Ne Court Of Appeals",
    "wof:placetype":"venue"
},
  "geometry": {"coordinates":[-96.041828,41.14335],"type":"Point"}
}