{
  "type": "Feature",
  "properties": {
    "iso:country":"US",
    "sg:address":"2489 N Nye Ave",
    "sg:city":"Fremont",
    "sg:classifiers":[
        {
            "category":"Personal",
            "type":"Services"
        }
    ],
    "sg:phone":"+1 402 721 7371",
    "sg:postcode":"68025",
    "sg:province":"NE",
    "sg:tags":[
        "control",
        "weight"
    ],
    "wof:name":"Pat's Better Weigh",
    "wof:placetype":"venue"
},
  "geometry": {"coordinates":[-96.50233799999999,41.453315],"type":"Point"}
}