{
  "type": "Feature",
  "properties": {
    "iso:country":"US",
    "sg:address":"224 N 18th St",
    "sg:city":"Plattsmouth",
    "sg:classifiers":[
        {
            "category":"Organizations",
            "subcategory":"Community Association",
            "type":"Services"
        }
    ],
    "sg:phone":"+1 402 296 4017",
    "sg:postcode":"68048",
    "sg:province":"NE",
    "sg:tags":[
        "club"
    ],
    "wof:name":"Plattsmouth Soccer Club",
    "wof:placetype":"venue"
},
  "geometry": {"coordinates":[-95.90145800000001,41.012666],"type":"Point"}
}