{
  "type": "Feature",
  "properties": {
    "iso:country":"US",
    "sg:address":"1941 S 42nd St",
    "sg:city":"Omaha",
    "sg:classifiers":[
        {
            "category":"Banks & Credit Unions",
            "subcategory":"Bank",
            "type":"Services"
        }
    ],
    "sg:phone":"+1 402 342 2400",
    "sg:postcode":"68105",
    "sg:province":"NE",
    "sg:tags":[
        "mortgage"
    ],
    "wof:name":"A-1 Mortgage Corp",
    "wof:placetype":"venue"
},
  "geometry": {"coordinates":[-95.975739,41.240289],"type":"Point"}
}