{
  "type": "Feature",
  "properties": {
    "iso:country":"US",
    "sg:address":"2716 13th St",
    "sg:city":"Columbus",
    "sg:classifiers":[
        {
            "category":"Organizations",
            "subcategory":"Professional Association",
            "type":"Services"
        }
    ],
    "sg:phone":"+1 402 564 3700",
    "sg:postcode":"68601",
    "sg:province":"NE",
    "wof:name":"Teen Mom's",
    "wof:placetype":"venue"
},
  "geometry": {"coordinates":[-97.361771,41.429387],"type":"Point"}
}