{
  "type": "Feature",
  "properties": {
    "iso:country":"US",
    "sg:address":"1420 S 16th St",
    "sg:city":"Omaha",
    "sg:classifiers":[
        {
            "category":"Manufacturing",
            "subcategory":"Printing",
            "type":"Manufacturing & Wholesale Goods"
        }
    ],
    "sg:phone":"+1 402 342 3345",
    "sg:postcode":"68108",
    "sg:province":"NE",
    "sg:tags":[
        "job",
        "printer",
        "commercial"
    ],
    "wof:name":"Blair House of Printing Inc",
    "wof:placetype":"venue"
},
  "geometry": {"coordinates":[-95.937406,41.244785],"type":"Point"}
}