{
  "type": "Feature",
  "properties": {
    "iso:country":"US",
    "sg:address":"2016 Ave A",
    "sg:city":"Scottsbluff",
    "sg:classifiers":[
        {
            "category":"Social Services",
            "type":"Services"
        }
    ],
    "sg:phone":"+1 308 632 3736",
    "sg:postcode":"69361",
    "sg:province":"NE",
    "sg:tags":[
        "organization",
        "welfare"
    ],
    "wof:name":"Scotts Bluff County Volunteer",
    "wof:placetype":"venue"
},
  "geometry": {"coordinates":[-103.664258,41.867426],"type":"Point"}
}