{
  "type": "Feature",
  "properties": {
    "iso:country":"US",
    "sg:address":"1512 Central Ave",
    "sg:city":"Miller",
    "sg:classifiers":[
        {
            "category":"Government",
            "subcategory":"Office",
            "type":"Public Place"
        }
    ],
    "sg:phone":"+1 308 457 2915",
    "sg:postcode":"68847",
    "sg:province":"NE",
    "wof:name":"Buffalo County Offices",
    "wof:placetype":"venue"
},
  "geometry": {"coordinates":[-99.082002,40.690185],"type":"Point"}
}