{
  "type": "Feature",
  "properties": {
    "iso:country":"US",
    "sg:address":"3001 W 12th St",
    "sg:city":"Hastings",
    "sg:classifiers":[
        {
            "category":"Shopping",
            "subcategory":"Department Store",
            "type":"Retail Goods"
        }
    ],
    "sg:phone":"+1 402 461 4460",
    "sg:postcode":"68901",
    "sg:province":"NE",
    "sg:tags":[
        "photo",
        "eating",
        "studio",
        "portrait"
    ],
    "wof:name":"Kmart",
    "wof:placetype":"venue"
},
  "geometry": {"coordinates":[-98.424685,40.596922],"type":"Point"}
}