{
  "type": "Feature",
  "properties": {
    "addr:full":"6510 S 84th St Omaha NE 68127",
    "addr:housenumber":"6510",
    "addr:postcode":"68127",
    "addr:street":"S 84Th St",
    "iso:country":"US",
    "sg:address":"6510 S 84th St",
    "sg:city":"Omaha",
    "sg:classifiers":[
        {
            "category":"Shopping",
            "subcategory":"Tobacco",
            "type":"Retail Goods"
        }
    ],
    "sg:phone":"+1 402 592 3700",
    "sg:postcode":"68127",
    "sg:province":"NE",
    "sg:tags":[
        "product"
    ],
    "wof:name":"Tobacco Hut",
    "wof:placetype":"venue"
},
  "geometry": {"coordinates":[-96.043038,41.194446],"type":"Point"}
}