{
  "type": "Feature",
  "properties": {
    "iso:country":"US",
    "sg:address":"10912 Washington St",
    "sg:city":"Omaha",
    "sg:classifiers":[
        {
            "category":"Building & Trades",
            "subcategory":"Construction",
            "type":"Services"
        }
    ],
    "sg:phone":"+1 402 592 6980",
    "sg:postcode":"68137",
    "sg:province":"NE",
    "sg:tags":[
        "house"
    ],
    "wof:name":"Hands On Design & Const",
    "wof:placetype":"venue"
},
  "geometry": {"coordinates":[-96.08235000000001,41.196641],"type":"Point"}
}