{
  "type": "Feature",
  "properties": {
    "addr:full":"4911 S 72nd St Omaha NE 68127",
    "addr:housenumber":"4911",
    "addr:postcode":"68127",
    "addr:street":"S 72Nd St",
    "iso:country":"US",
    "sg:address":"4911 S 72nd St",
    "sg:city":"Omaha",
    "sg:classifiers":[
        {
            "category":"Building & Trades",
            "subcategory":"Equipment Rental",
            "type":"Services"
        }
    ],
    "sg:phone":"+1 402 331 1928",
    "sg:postcode":"68127",
    "sg:province":"NE",
    "wof:name":"R KS Rent-To-Own",
    "wof:placetype":"venue"
},
  "geometry": {"coordinates":[-96.02377,41.211504],"type":"Point"}
}