{
  "type": "Feature",
  "properties": {
    "iso:country":"US",
    "sg:address":"1535 Colfax St",
    "sg:city":"Blair",
    "sg:classifiers":[
        {
            "category":"Government",
            "subcategory":"Police Station",
            "type":"Public Place"
        }
    ],
    "sg:phone":"+1 402 426 6866",
    "sg:postcode":"68008",
    "sg:province":"NE",
    "sg:tags":[
        "protection"
    ],
    "wof:name":"County of Washington",
    "wof:placetype":"venue"
},
  "geometry": {"coordinates":[-96.13570300000001,41.540658],"type":"Point"}
}