{
  "type": "Feature",
  "properties": {
    "iso:country":"US",
    "sg:address":"1201 1st Ave",
    "sg:city":"South Sioux City",
    "sg:classifiers":[
        {
            "category":"Travel",
            "subcategory":"Hotels & Motels",
            "type":"Entertainment"
        }
    ],
    "sg:phone":"+1 402 494 2021",
    "sg:postcode":"68776",
    "sg:province":"NE",
    "wof:name":"Park Plaza Motel",
    "wof:placetype":"venue"
},
  "geometry": {"coordinates":[-96.413922,42.476765],"type":"Point"}
}