{
  "type": "Feature",
  "properties": {
    "iso:country":"US",
    "sg:address":"118 18th St N",
    "sg:city":"Wisner",
    "sg:classifiers":[
        {
            "category":"Professional",
            "subcategory":"Management & Consulting",
            "type":"Services"
        }
    ],
    "sg:phone":"+1 402 529 3572",
    "sg:postcode":"68791",
    "sg:province":"NE",
    "sg:tags":[
        "consultant"
    ],
    "wof:name":"Bellar Feed Lots Inc",
    "wof:placetype":"venue"
},
  "geometry": {"coordinates":[-96.921243,41.98687],"type":"Point"}
}