{
  "type": "Feature",
  "properties": {
    "iso:country":"US",
    "sg:address":"8401 W Dodge Rd",
    "sg:city":"Omaha",
    "sg:classifiers":[
        {
            "category":"Health Services",
            "subcategory":"Hospital",
            "type":"Services"
        }
    ],
    "sg:phone":"+1 402 955 5555",
    "sg:postcode":"68114",
    "sg:province":"NE",
    "wof:name":"Ne Regional Poison Ctr",
    "wof:placetype":"venue"
},
  "geometry": {"coordinates":[-96.044595,41.262449],"type":"Point"}
}