{
  "type": "Feature",
  "properties": {
    "iso:country":"US",
    "sg:address":"1020 Diamond St",
    "sg:city":"Lyons",
    "sg:classifiers":[
        {
            "category":"Wholesale",
            "subcategory":"Motor Vehicles",
            "type":"Manufacturing & Wholesale Goods"
        }
    ],
    "sg:phone":"+1 402 687 2279",
    "sg:postcode":"68038",
    "sg:province":"NE",
    "sg:tags":[
        "truck"
    ],
    "wof:name":"Mikes Auto Sales Inc",
    "wof:placetype":"venue"
},
  "geometry": {"coordinates":[-96.463611,41.932634],"type":"Point"}
}