{
  "type": "Feature",
  "properties": {
    "iso:country":"US",
    "sg:address":"4420 S 24th St",
    "sg:city":"Omaha",
    "sg:classifiers":[
        {
            "category":"Autos & Motor Vehicles",
            "subcategory":"Automobile Sales",
            "type":"Retail Goods"
        }
    ],
    "sg:phone":"+1 402 933 5585",
    "sg:postcode":"68107",
    "sg:province":"NE",
    "sg:tags":[
        "car",
        "dealer"
    ],
    "wof:name":"Car Hop Auto Sales",
    "wof:placetype":"venue"
},
  "geometry": {"coordinates":[-95.947125,41.214981],"type":"Point"}
}