{
  "type": "Feature",
  "properties": {
    "addr:full":"3908 22nd St Columbus NE 68601",
    "addr:housenumber":"3908",
    "addr:postcode":"68601",
    "addr:street":"22Nd St",
    "iso:country":"US",
    "sg:address":"3908 22nd St",
    "sg:city":"Columbus",
    "sg:classifiers":[
        {
            "category":"Shopping",
            "subcategory":"Gifts & Souvenirs",
            "type":"Retail Goods"
        }
    ],
    "sg:phone":"+1 402 563 1262",
    "sg:postcode":"68601",
    "sg:province":"NE",
    "sg:tags":[
        "shop",
        "novelty"
    ],
    "wof:name":"Shadow Box",
    "wof:placetype":"venue"
},
  "geometry": {"coordinates":[-97.376628,41.437711],"type":"Point"}
}