{
  "type": "Feature",
  "properties": {
    "iso:country":"US",
    "sg:address":"2205 Osborne Dr E",
    "sg:city":"Hastings",
    "sg:classifiers":[
        {
            "category":"Travel",
            "subcategory":"Hotels & Motels",
            "type":"Entertainment"
        }
    ],
    "sg:phone":"+1 402 463 6721",
    "sg:postcode":"68901",
    "sg:province":"NE",
    "wof:name":"H0liday Inn Hastings",
    "wof:placetype":"venue"
},
  "geometry": {"coordinates":[-98.382552,40.611589],"type":"Point"}
}