{
  "type": "Feature",
  "properties": {
    "addr:full":"2474 Co Rd 26 Morse Bluff NE 68648",
    "addr:housenumber":"2474;26",
    "addr:postcode":"68648",
    "addr:street":"Co Rd;Morse Bluff Ne",
    "iso:country":"US",
    "sg:address":"2474 Co Rd 26",
    "sg:city":"Morse Bluff",
    "sg:classifiers":[
        {
            "category":"Wholesale",
            "subcategory":"Farm Supplies",
            "type":"Manufacturing & Wholesale Goods"
        }
    ],
    "sg:phone":"+1 402 663 4695",
    "sg:postcode":"68648",
    "sg:province":"NE",
    "wof:name":"Sandcreek Spraying",
    "wof:placetype":"venue"
},
  "geometry": {"coordinates":[-96.793618,41.359159],"type":"Point"}
}