{
  "type": "Feature",
  "properties": {
    "iso:country":"US",
    "sg:address":"2323 W 5th St",
    "sg:city":"Hastings",
    "sg:classifiers":[
        {
            "category":"Building & Trades",
            "subcategory":"Construction",
            "type":"Services"
        }
    ],
    "sg:phone":"+1 402 462 9610",
    "sg:postcode":"68901",
    "sg:province":"NE",
    "sg:tags":[
        "hanging",
        "contractor"
    ],
    "wof:name":"Meyer Painting",
    "wof:placetype":"venue"
},
  "geometry": {"coordinates":[-98.41794400000001,40.588135],"type":"Point"}
}