{
  "type": "Feature",
  "properties": {
    "iso:country":"US",
    "sg:address":"3550 Cape Charles Rd E",
    "sg:city":"Lincoln",
    "sg:classifiers":[
        {
            "category":"Professional",
            "subcategory":"Management & Consulting",
            "type":"Services"
        }
    ],
    "sg:phone":"+1 402 421 2116",
    "sg:postcode":"68516",
    "sg:province":"NE",
    "sg:tags":[
        "business"
    ],
    "wof:name":"D L S Services Inc",
    "wof:placetype":"venue"
},
  "geometry": {"coordinates":[-96.66712699999999,40.747636],"type":"Point"}
}