{
  "type": "Feature",
  "properties": {
    "iso:country":"US",
    "sg:address":"1510 N Saddle Creek Rd",
    "sg:city":"Omaha",
    "sg:classifiers":[
        {
            "category":"Bars & Pubs",
            "subcategory":"Dive Bar",
            "type":"Food & Drink"
        },
        {
            "category":"Bars & Pubs",
            "subcategory":"Champagne Bar",
            "type":"Food & Drink"
        }
    ],
    "sg:phone":"+1 402 554 5815",
    "sg:postcode":"68104",
    "sg:province":"NE",
    "wof:name":"Homy Inn",
    "wof:placetype":"venue"
},
  "geometry": {"coordinates":[-95.988297,41.2733],"type":"Point"}
}