{
  "type": "Feature",
  "properties": {
    "addr:full":"2400 N Nebraska Ave York NE 68467",
    "addr:housenumber":"2400",
    "addr:postcode":"68467",
    "addr:street":"N Nebraska Ave",
    "iso:country":"US",
    "sg:address":"2400 N Nebraska Ave",
    "sg:city":"York",
    "sg:classifiers":[
        {
            "category":"Professional",
            "subcategory":"Business Services",
            "type":"Services"
        }
    ],
    "sg:phone":"+1 402 362 6400",
    "sg:postcode":"68467",
    "sg:province":"NE",
    "sg:tags":[
        "event"
    ],
    "wof:name":"Cornerstone Ag & Event Ctr",
    "wof:placetype":"venue"
},
  "geometry": {"coordinates":[-97.590193,40.885449],"type":"Point"}
}