{
  "type": "Feature",
  "properties": {
    "addr:full":"1601 Dodge St Omaha NE 68102",
    "addr:housenumber":"1601",
    "addr:postcode":"68102",
    "addr:street":"Dodge St",
    "iso:country":"US",
    "sg:address":"1601 Dodge St",
    "sg:city":"Omaha",
    "sg:classifiers":[
        {
            "category":"Shopping",
            "subcategory":"Gifts & Souvenirs",
            "type":"Retail Goods"
        }
    ],
    "sg:phone":"+1 402 341 5555",
    "sg:postcode":"68102",
    "sg:province":"NE",
    "sg:tags":[
        "shop"
    ],
    "wof:name":"Summit",
    "wof:placetype":"venue"
},
  "geometry": {"coordinates":[-95.93849,41.259715],"type":"Point"}
}