{
  "type": "Feature",
  "properties": {
    "iso:country":"US",
    "sg:address":"900 N Platte Ave",
    "sg:city":"Juniata",
    "sg:classifiers":[
        {
            "category":"Organizations",
            "subcategory":"Religious Organization",
            "type":"Services"
        }
    ],
    "sg:phone":"+1 402 751 2440",
    "sg:postcode":"68955",
    "sg:province":"NE",
    "sg:tags":[
        "church"
    ],
    "wof:name":"Juniata Community Church",
    "wof:placetype":"venue"
},
  "geometry": {"coordinates":[-98.50917800000001,40.591702],"type":"Point"}
}