{
  "type": "Feature",
  "properties": {
    "iso:country":"US",
    "sg:address":"210 S 16th St",
    "sg:city":"Omaha",
    "sg:classifiers":[
        {
            "category":"Freight",
            "type":"Transportation"
        }
    ],
    "sg:phone":"+1 402 346 4662",
    "sg:postcode":"68102",
    "sg:province":"NE",
    "sg:tags":[
        "repair",
        "parts",
        "component",
        "rail",
        "car"
    ],
    "wof:name":"Progress Rail Services Corp",
    "wof:placetype":"venue"
},
  "geometry": {"coordinates":[-95.937271,41.257709],"type":"Point"}
}