{
  "type": "Feature",
  "properties": {
    "iso:country":"US",
    "sg:address":"209 S 19th St Ste 440",
    "sg:city":"Omaha",
    "sg:classifiers":[
        {
            "category":"Professional",
            "subcategory":"Lawyer & Legal Services",
            "type":"Services"
        }
    ],
    "sg:phone":"+1 402 342 4433",
    "sg:postcode":"68102",
    "sg:province":"NE",
    "wof:name":"Lefler & Kuehl",
    "wof:placetype":"venue"
},
  "geometry": {"coordinates":[-95.94094800000001,41.258584],"type":"Point"}
}