{
  "type": "Feature",
  "properties": {
    "iso:country":"US",
    "sg:address":"302 East Ave",
    "sg:city":"Holdrege",
    "sg:classifiers":[
        {
            "category":"Building & Trades",
            "subcategory":"Construction",
            "type":"Services"
        }
    ],
    "sg:phone":"+1 308 995 2443",
    "sg:postcode":"68949",
    "sg:province":"NE",
    "sg:tags":[
        "general",
        "contractor"
    ],
    "wof:name":"Mike Buettner Construction",
    "wof:placetype":"venue"
},
  "geometry": {"coordinates":[-99.36980200000001,40.437938],"type":"Point"}
}