{
  "type": "Feature",
  "properties": {
    "iso:country":"US",
    "sg:address":"1015 Capitol Ave",
    "sg:city":"Omaha",
    "sg:classifiers":[
        {
            "category":"Communications",
            "subcategory":"Radio Station",
            "type":"Services"
        }
    ],
    "sg:phone":"+1 402 348 1959",
    "sg:postcode":"68102",
    "sg:province":"NE",
    "sg:tags":[
        "company",
        "broadcasting"
    ],
    "wof:name":"Metro Networks",
    "wof:placetype":"venue"
},
  "geometry": {"coordinates":[-95.93033800000001,41.260556],"type":"Point"}
}