{
  "type": "Feature",
  "properties": {
    "addr:full":"4830 S 137th St Omaha NE 68137",
    "addr:housenumber":"4830",
    "addr:postcode":"68137",
    "addr:street":"S 137Th St",
    "iso:country":"US",
    "sg:address":"4830 S 137th St",
    "sg:city":"Omaha",
    "sg:classifiers":[
        {
            "category":"Real Estate",
            "subcategory":"Developer",
            "type":"Services"
        }
    ],
    "sg:phone":"+1 402 330 5530",
    "sg:postcode":"68137",
    "sg:province":"NE",
    "sg:tags":[
        "mobile",
        "home"
    ],
    "wof:name":"Millard Mobile Home Park",
    "wof:placetype":"venue"
},
  "geometry": {"coordinates":[-96.12653299999999,41.208199],"type":"Point"}
}