{
  "type": "Feature",
  "properties": {
    "iso:country":"US",
    "sg:address":"222 S 4th St",
    "sg:city":"Albion",
    "sg:classifiers":[
        {
            "category":"Government",
            "subcategory":"Office",
            "type":"Public Place"
        }
    ],
    "sg:phone":"+1 402 395 2045",
    "sg:postcode":"68620",
    "sg:province":"NE",
    "wof:name":"Boone County Assessor's Office",
    "wof:placetype":"venue"
},
  "geometry": {"coordinates":[-98.001232,41.69159],"type":"Point"}
}