{
  "type": "Feature",
  "properties": {
    "iso:country":"US",
    "sg:address":"648 G St",
    "sg:city":"Pawnee City",
    "sg:classifiers":[
        {
            "category":"Insurance",
            "subcategory":"Insurance Agent",
            "type":"Services"
        }
    ],
    "sg:phone":"+1 402 852 2405",
    "sg:postcode":"68420",
    "sg:province":"NE",
    "wof:name":"Hofmann Agency",
    "wof:placetype":"venue"
},
  "geometry": {"coordinates":[-96.152913,40.108986],"type":"Point"}
}