{
  "type": "Feature",
  "properties": {
    "iso:country":"US",
    "sg:address":"251 Pine St",
    "sg:city":"Chadron",
    "sg:classifiers":[
        {
            "category":"Shopping",
            "type":"Retail Goods"
        }
    ],
    "sg:phone":"+1 308 432 2734",
    "sg:postcode":"69337",
    "sg:province":"NE",
    "sg:tags":[
        "hearing",
        "equipment",
        "supply",
        "impaired"
    ],
    "sg:website":"www.miracle-ear.com",
    "wof:name":"Miracle-Ear",
    "wof:placetype":"venue"
},
  "geometry": {"coordinates":[-103.00909299999999,42.830907],"type":"Point"}
}