{
  "type": "Feature",
  "properties": {
    "iso:country":"US",
    "sg:address":"308 W 10th St",
    "sg:city":"Mc Cook",
    "sg:classifiers":[
        {
            "category":"Professional",
            "subcategory":"Accounting & Tax Preparation",
            "type":"Services"
        }
    ],
    "sg:phone":"+1 308 345 5717",
    "sg:postcode":"69001",
    "sg:province":"NE",
    "sg:tags":[
        "accountant"
    ],
    "wof:name":"Gifford & Cox",
    "wof:placetype":"venue"
},
  "geometry": {"coordinates":[-100.63927,40.199822],"type":"Point"}
}