{
  "type": "Feature",
  "properties": {
    "iso:country":"US",
    "sg:address":"217 Main St",
    "sg:city":"Brownville",
    "sg:classifiers":[
        {
            "category":"Professional",
            "subcategory":"Business Services",
            "type":"Services"
        },
        {
            "category":"Government",
            "subcategory":"Post Office",
            "type":"Public Place"
        }
    ],
    "sg:phone":"+1 800 275 8777",
    "sg:postcode":"68321",
    "sg:province":"NE",
    "sg:tags":[
        "mail",
        "shipping"
    ],
    "sg:website":"http://www.usps.com",
    "wof:name":"USPS - United States Post Office - Brownville Main Office",
    "wof:placetype":"venue"
},
  "geometry": {"coordinates":[-95.657089,40.397483],"type":"Point"}
}