{
  "type": "Feature",
  "properties": {
    "iso:country":"US",
    "sg:address":"1661 N Chestnut St",
    "sg:city":"Wahoo",
    "sg:classifiers":[
        {
            "category":"Building & Trades",
            "subcategory":"Construction",
            "type":"Services"
        }
    ],
    "sg:phone":"+1 402 443 3838",
    "sg:postcode":"68066",
    "sg:province":"NE",
    "sg:tags":[
        "house"
    ],
    "wof:name":"Syverson Construction",
    "wof:placetype":"venue"
},
  "geometry": {"coordinates":[-96.621748,41.220939],"type":"Point"}
}