{
  "type": "Feature",
  "properties": {
    "iso:country":"US",
    "sg:address":"310 S 13th St",
    "sg:city":"Norfolk",
    "sg:classifiers":[
        {
            "category":"Building & Trades",
            "subcategory":"Electrical",
            "type":"Services"
        }
    ],
    "sg:phone":"+1 402 371 6614",
    "sg:postcode":"68701",
    "sg:province":"NE",
    "sg:tags":[
        "electrical",
        "contractor"
    ],
    "wof:name":"Klug Electric",
    "wof:placetype":"venue"
},
  "geometry": {"coordinates":[-97.42662799999999,42.030093],"type":"Point"}
}