{
  "type": "Feature",
  "properties": {
    "addr:full":"210615 State Hwy 71 Gering NE 69341",
    "addr:housenumber":"210615",
    "addr:postcode":"69341",
    "addr:street":"State Hwy 71",
    "iso:country":"US",
    "sg:address":"210615 State Hwy 71",
    "sg:city":"Gering",
    "sg:classifiers":[
        {
            "category":"Government",
            "subcategory":"Office",
            "type":"Public Place"
        }
    ],
    "sg:phone":"+1 308 436 3777",
    "sg:postcode":"69341",
    "sg:province":"NE",
    "wof:name":"Wildcat Hills State Recreation",
    "wof:placetype":"venue"
},
  "geometry": {"coordinates":[-103.671138,41.69885],"type":"Point"}
}