{
  "type": "Feature",
  "properties": {
    "iso:country":"US",
    "sg:address":"3930 S 147th St",
    "sg:city":"Omaha",
    "sg:classifiers":[
        {
            "category":"Insurance",
            "subcategory":"Insurance Agent",
            "type":"Services"
        }
    ],
    "sg:phone":"+1 402 895 0555",
    "sg:postcode":"68144",
    "sg:province":"NE",
    "sg:website":"www.cwiins.com",
    "wof:name":"Countrywide Insurance Inc",
    "wof:placetype":"venue"
},
  "geometry": {"coordinates":[-96.142229,41.221039],"type":"Point"}
}