{
  "type": "Feature",
  "properties": {
    "iso:country":"US",
    "sg:address":"1509 Sheridan Dr",
    "sg:city":"Norfolk",
    "sg:classifiers":[
        {
            "category":"Wholesale",
            "subcategory":"Durable Goods & Equipment",
            "type":"Manufacturing & Wholesale Goods"
        }
    ],
    "sg:phone":"+1 402 379 4895",
    "sg:postcode":"68701",
    "sg:province":"NE",
    "sg:tags":[
        "importer"
    ],
    "wof:name":"Core Inc",
    "wof:placetype":"venue"
},
  "geometry": {"coordinates":[-97.43135100000001,42.053635],"type":"Point"}
}