{
  "type": "Feature",
  "properties": {
    "addr:full":"2316 S 105th Ave Omaha NE 68124",
    "addr:housenumber":"2316",
    "addr:postcode":"68124",
    "addr:street":"S 105Th Ave",
    "iso:country":"US",
    "sg:address":"2316 S 105th Ave",
    "sg:city":"Omaha",
    "sg:classifiers":[
        {
            "category":"Professional",
            "subcategory":"Art Services",
            "type":"Services"
        }
    ],
    "sg:phone":"+1 402 391 1344",
    "sg:postcode":"68124",
    "sg:province":"NE",
    "sg:tags":[
        "interior",
        "designer",
        "decorator"
    ],
    "sg:website":"http://www.ahutton.com",
    "wof:name":"Indoff, Incorporated",
    "wof:placetype":"venue"
},
  "geometry": {"coordinates":[-96.076853,41.237319],"type":"Point"}
}