{
  "type": "Feature",
  "properties": {
    "iso:country":"US",
    "sg:address":"5421 S 60th St",
    "sg:city":"Omaha",
    "sg:classifiers":[
        {
            "category":"Building & Trades",
            "subcategory":"Construction",
            "type":"Services"
        }
    ],
    "sg:phone":"+1 402 734 3140",
    "sg:postcode":"68117",
    "sg:province":"NE",
    "sg:tags":[
        "house"
    ],
    "wof:name":"B B Construction",
    "wof:placetype":"venue"
},
  "geometry": {"coordinates":[-96.004566,41.202402],"type":"Point"}
}