{
  "type": "Feature",
  "properties": {
    "addr:full":"3056 33rd Ave Columbus NE 68601",
    "addr:housenumber":"3056",
    "addr:postcode":"68601",
    "addr:street":"33Rd Ave",
    "iso:country":"US",
    "sg:address":"3056 33rd Ave",
    "sg:city":"Columbus",
    "sg:classifiers":[
        {
            "category":"Organizations",
            "subcategory":"Non-profit Organization",
            "type":"Services"
        }
    ],
    "sg:phone":"+1 402 562 7089",
    "sg:postcode":"68601",
    "sg:province":"NE",
    "wof:name":"Project Extra Mile Platte",
    "wof:placetype":"venue"
},
  "geometry": {"coordinates":[-97.368317,41.446328],"type":"Point"}
}