{
  "type": "Feature",
  "properties": {
    "addr:full":"4601 S 50th St Ste 200 Omaha NE 68117",
    "addr:housenumber":"4601",
    "addr:postcode":"68117",
    "addr:street":"S 50Th St Ste 200",
    "iso:country":"US",
    "sg:address":"4601 S 50th St Ste 200",
    "sg:city":"Omaha",
    "sg:classifiers":[
        {
            "category":"Restaurant",
            "type":"Food & Drink"
        }
    ],
    "sg:phone":"+1 402 731 5243",
    "sg:postcode":"68117",
    "sg:province":"NE",
    "sg:tags":[
        "traditional",
        "american"
    ],
    "wof:name":"Horizon Restaurant",
    "wof:placetype":"venue"
},
  "geometry": {"coordinates":[-95.99010699999999,41.21317],"type":"Point"}
}