{
  "type": "Feature",
  "properties": {
    "addr:full":"1002 Bellewood Ct Bellevue NE 68005",
    "addr:housenumber":"1002",
    "addr:postcode":"68005",
    "addr:street":"Bellewood Ct",
    "iso:country":"US",
    "sg:address":"1002 Bellewood Ct",
    "sg:city":"Bellevue",
    "sg:classifiers":[
        {
            "category":"Health Services",
            "subcategory":"Nursing And Care Facility",
            "type":"Services"
        },
        {
            "category":"Real Estate",
            "subcategory":"Real Estate Operator",
            "type":"Services"
        }
    ],
    "sg:phone":"+1 402 292 3300",
    "sg:postcode":"68005",
    "sg:province":"NE",
    "sg:tags":[
        "independent",
        "retirement",
        "housing",
        "elderly",
        "community",
        "home"
    ],
    "wof:name":"Bellewood Courts",
    "wof:placetype":"venue"
},
  "geometry": {"coordinates":[-95.90562300000001,41.141873],"type":"Point"}
}