{
  "type": "Feature",
  "properties": {
    "iso:country":"US",
    "sg:address":"4100 Industrial Ave",
    "sg:city":"Lincoln",
    "sg:classifiers":[
        {
            "category":"Communications",
            "subcategory":"Radio Station",
            "type":"Services"
        }
    ],
    "sg:phone":"+1 402 465 0241",
    "sg:postcode":"68504",
    "sg:province":"NE",
    "sg:tags":[
        "company",
        "broadcasting"
    ],
    "wof:name":"Three Angels Broadcasting",
    "wof:placetype":"venue"
},
  "geometry": {"coordinates":[-96.67965599999999,40.85702],"type":"Point"}
}