{
  "type": "Feature",
  "properties": {
    "iso:country":"US",
    "sg:address":"3803 2nd Ave",
    "sg:city":"Kearney",
    "sg:classifiers":[
        {
            "category":"Shopping",
            "type":"Retail Goods"
        }
    ],
    "sg:phone":"+1 308 234 2810",
    "sg:postcode":"68847",
    "sg:province":"NE",
    "sg:tags":[
        "hearing",
        "equipment",
        "supply",
        "impaired"
    ],
    "wof:name":"Kearney Hearing Aid Ctr",
    "wof:placetype":"venue"
},
  "geometry": {"coordinates":[-99.083911,40.713552],"type":"Point"}
}