{
  "type": "Feature",
  "properties": {
    "iso:country":"US",
    "sg:address":"645 S E St",
    "sg:city":"Broken Bow",
    "sg:classifiers":[
        {
            "category":"Professional",
            "subcategory":"Accounting & Tax Preparation",
            "type":"Services"
        }
    ],
    "sg:phone":"+1 308 872 6249",
    "sg:postcode":"68822",
    "sg:province":"NE",
    "sg:tags":[
        "return",
        "filing"
    ],
    "wof:name":"H & R Block Tax Svc",
    "wof:placetype":"venue"
},
  "geometry": {"coordinates":[-99.637837,41.401832],"type":"Point"}
}