{
  "type": "Feature",
  "properties": {
    "addr:full":"721 W 6th St Papillion NE 68046",
    "addr:housenumber":"721",
    "addr:postcode":"68046",
    "addr:street":"W 6Th St",
    "iso:country":"US",
    "sg:address":"721 W 6th St",
    "sg:city":"Papillion",
    "sg:classifiers":[
        {
            "category":"Wholesale",
            "subcategory":"Machinery & Supplies",
            "type":"Manufacturing & Wholesale Goods"
        }
    ],
    "sg:phone":"+1 402 505 1387",
    "sg:postcode":"68046",
    "sg:province":"NE",
    "wof:name":"American Trailer",
    "wof:placetype":"venue"
},
  "geometry": {"coordinates":[-96.04873000000001,41.161762],"type":"Point"}
}