{
  "type": "Feature",
  "properties": {
    "addr:full":"400 W Norfolk Ave Norfolk NE 68701",
    "addr:housenumber":"400",
    "addr:postcode":"68701",
    "addr:street":"W Norfolk Ave",
    "iso:country":"US",
    "sg:address":"400 W Norfolk Ave",
    "sg:city":"Norfolk",
    "sg:classifiers":[
        {
            "category":"Shopping",
            "subcategory":"Musical Instruments",
            "type":"Retail Goods"
        }
    ],
    "sg:phone":"+1 402 379 5252",
    "sg:postcode":"68701",
    "sg:province":"NE",
    "sg:website":"www.midwestmusic-center.com",
    "wof:name":"Midwest Music Ctr",
    "wof:placetype":"venue"
},
  "geometry": {"coordinates":[-97.41377799999999,42.032759],"type":"Point"}
}