{
  "type": "Feature",
  "properties": {
    "addr:full":"211 S 84th St Lincoln NE 68510",
    "addr:housenumber":"211",
    "addr:postcode":"68510",
    "addr:street":"S 84Th St",
    "iso:country":"US",
    "sg:address":"211 S 84th St",
    "sg:city":"Lincoln",
    "sg:classifiers":[
        {
            "category":"Social Services",
            "type":"Services"
        }
    ],
    "sg:phone":"+1 402 484 8898",
    "sg:postcode":"68510",
    "sg:province":"NE",
    "sg:tags":[
        "counseling"
    ],
    "wof:name":"Affiliated Counseling Services",
    "wof:placetype":"venue"
},
  "geometry": {"coordinates":[-96.606049,40.810896],"type":"Point"}
}