{
  "type": "Feature",
  "properties": {
    "addr:full":"703 S Y Rd Henderson NE 68371",
    "addr:housenumber":"703",
    "addr:postcode":"68371",
    "addr:street":"S Y Rd",
    "iso:country":"US",
    "sg:address":"703 S Y Rd",
    "sg:city":"Henderson",
    "sg:phone":"+1 402 723 4465",
    "sg:postcode":"68371",
    "sg:province":"NE",
    "sg:tags":[
        "farm",
        "corn"
    ],
    "wof:name":"Robert Wayne Friesen",
    "wof:placetype":"venue"
},
  "geometry": {"coordinates":[-97.844942,40.789269],"type":"Point"}
}