{
  "type": "Feature",
  "properties": {
    "iso:country":"US",
    "sg:address":"501 S 13th St",
    "sg:city":"Omaha",
    "sg:classifiers":[
        {
            "category":"Professional",
            "subcategory":"Business Services",
            "type":"Services"
        }
    ],
    "sg:phone":"+1 402 344 7311",
    "sg:postcode":"68102",
    "sg:province":"NE",
    "sg:tags":[
        "food",
        "broker"
    ],
    "wof:name":"Food Marketing Inc",
    "wof:placetype":"venue"
},
  "geometry": {"coordinates":[-95.933234,41.254419],"type":"Point"}
}