{
  "type": "Feature",
  "properties": {
    "addr:full":"1422 Broadway Scottsbluff NE 69361",
    "addr:housenumber":"1422",
    "addr:postcode":"69361",
    "addr:street":"Broadway",
    "iso:country":"US",
    "sg:address":"1422 Broadway",
    "sg:city":"Scottsbluff",
    "sg:classifiers":[
        {
            "category":"Professional",
            "type":"Services"
        }
    ],
    "sg:phone":"+1 308 632 2222",
    "sg:postcode":"69361",
    "sg:province":"NE",
    "sg:tags":[
        "establishment"
    ],
    "wof:name":"Airline Ticket Office",
    "wof:placetype":"venue"
},
  "geometry": {"coordinates":[-103.66280399999999,41.861127],"type":"Point"}
}