{
  "type": "Feature",
  "properties": {
    "iso:country":"US",
    "sg:address":"1030 Toledo St",
    "sg:city":"Sidney",
    "sg:classifiers":[
        {
            "category":"Cinema",
            "subcategory":"Movie Rental",
            "type":"Entertainment"
        }
    ],
    "sg:phone":"+1 308 254 6190",
    "sg:postcode":"69162",
    "sg:province":"NE",
    "sg:tags":[
        "video",
        "tape",
        "equipment"
    ],
    "wof:name":"Adventure Land Video",
    "wof:placetype":"venue"
},
  "geometry": {"coordinates":[-102.97716699999999,41.134479],"type":"Point"}
}