{
  "type": "Feature",
  "properties": {
    "iso:country":"US",
    "sg:address":"1111 N. 13th Street",
    "sg:city":"Omaha",
    "sg:classifiers":[
        {
            "category":"Professional",
            "subcategory":"Computer Services",
            "type":"Services"
        }
    ],
    "sg:phone":"+1 402 802 8374",
    "sg:postcode":"68102",
    "sg:province":"NE",
    "sg:tags":[
        "gov-2-0",
        "community-engagement",
        "public-involvement"
    ],
    "sg:website":"http://www.mindmixer.com",
    "wof:name":"MindMixer",
    "wof:placetype":"venue"
},
  "geometry": {"coordinates":[-95.933035,41.270481],"type":"Point"}
}