{
  "type": "Feature",
  "properties": {
    "addr:full":"133 E 3rd St Ainsworth NE 69210",
    "addr:housenumber":"133",
    "addr:postcode":"69210",
    "addr:street":"E 3Rd St",
    "iso:country":"US",
    "sg:address":"133 E 3rd St",
    "sg:city":"Ainsworth",
    "sg:classifiers":[
        {
            "category":"Building & Trades",
            "subcategory":"Landscaping Services",
            "type":"Services"
        }
    ],
    "sg:phone":"+1 402 387 2402",
    "sg:postcode":"69210",
    "sg:province":"NE",
    "sg:tags":[
        "sanitary"
    ],
    "wof:name":"Frontier Land Care",
    "wof:placetype":"venue"
},
  "geometry": {"coordinates":[-99.861468,42.547993],"type":"Point"}
}