{
  "type": "Feature",
  "properties": {
    "addr:full":"2201 W Van Dorn St Lincoln NE 68522",
    "addr:housenumber":"2201",
    "addr:postcode":"68522",
    "addr:street":"W Van Dorn St",
    "iso:country":"US",
    "sg:address":"2201 W Van Dorn St",
    "sg:city":"Lincoln",
    "sg:classifiers":[
        {
            "category":"Professional",
            "subcategory":"Engineering",
            "type":"Services"
        }
    ],
    "sg:phone":"+1 402 438 1851",
    "sg:postcode":"68522",
    "sg:province":"NE",
    "wof:name":"Rmg Tech",
    "wof:placetype":"venue"
},
  "geometry": {"coordinates":[-96.75819300000001,40.784532],"type":"Point"}
}