{
  "type": "Feature",
  "properties": {
    "addr:full":"13115 Brookside Dr Bellevue NE 68123",
    "addr:housenumber":"13115",
    "addr:postcode":"68123",
    "addr:street":"Brookside Dr",
    "iso:country":"US",
    "sg:address":"13115 Brookside Dr",
    "sg:city":"Bellevue",
    "sg:classifiers":[
        {
            "category":"Building & Trades",
            "subcategory":"Construction",
            "type":"Services"
        }
    ],
    "sg:phone":"+1 402 212 8509",
    "sg:postcode":"68123",
    "sg:province":"NE",
    "sg:tags":[
        "contractor"
    ],
    "wof:name":"Reavis Corp",
    "wof:placetype":"venue"
},
  "geometry": {"coordinates":[-95.96761600000001,41.112902],"type":"Point"}
}