{
  "type": "Feature",
  "properties": {
    "iso:country":"US",
    "sg:address":"511 Bradford St",
    "sg:city":"Seward",
    "sg:classifiers":[
        {
            "category":"Food & Beverages",
            "subcategory":"Groceries & Convenience Stores",
            "type":"Retail Goods"
        }
    ],
    "sg:phone":"+1 402 643 4564",
    "sg:postcode":"68434",
    "sg:province":"NE",
    "sg:website":"www.nashfinch.com",
    "wof:name":"Sun Mart Foods",
    "wof:placetype":"venue"
},
  "geometry": {"coordinates":[-97.099029,40.909648],"type":"Point"}
}