{
  "type": "Feature",
  "properties": {
    "iso:country":"US",
    "sg:address":"771 S Broad St",
    "sg:city":"Fremont",
    "sg:classifiers":[
        {
            "category":"Banks & Credit Unions",
            "subcategory":"Bank",
            "type":"Services"
        }
    ],
    "sg:phone":"+1 402 721 0430",
    "sg:postcode":"68025",
    "sg:province":"NE",
    "sg:tags":[
        "depository",
        "banking"
    ],
    "wof:name":"Speedee Bucks",
    "wof:placetype":"venue"
},
  "geometry": {"coordinates":[-96.49977699999999,41.422326],"type":"Point"}
}