{
  "type": "Feature",
  "properties": {
    "iso:country":"US",
    "sg:address":"405 W 2nd St",
    "sg:city":"Hastings",
    "sg:classifiers":[
        {
            "category":"Museum",
            "type":"Entertainment"
        }
    ],
    "sg:phone":"+1 402 463 3300",
    "sg:postcode":"68901",
    "sg:province":"NE",
    "wof:name":"Children's Museum-Central Ne",
    "wof:placetype":"venue"
},
  "geometry": {"coordinates":[-98.387559,40.5851],"type":"Point"}
}