{
  "type": "Feature",
  "properties": {
    "iso:country":"US",
    "sg:address":"3658 X St",
    "sg:city":"Lincoln",
    "sg:classifiers":[
        {
            "category":"Building & Trades",
            "subcategory":"Construction",
            "type":"Services"
        }
    ],
    "sg:phone":"+1 402 540 1975",
    "sg:postcode":"68503",
    "sg:province":"NE",
    "sg:tags":[
        "repairing",
        "remodeling",
        "contractor"
    ],
    "wof:name":"Titus Construction",
    "wof:placetype":"venue"
},
  "geometry": {"coordinates":[-96.66717,40.822846],"type":"Point"}
}