{
  "type": "Feature",
  "properties": {
    "addr:full":"1215 6th Corso Nebraska City NE 68410",
    "addr:housenumber":"1215",
    "addr:postcode":"68410",
    "addr:street":"Corso",
    "iso:country":"US",
    "sg:address":"1215 6th Corso",
    "sg:city":"Nebraska City",
    "sg:classifiers":[
        {
            "category":"Recreation",
            "type":"Entertainment"
        }
    ],
    "sg:phone":"+1 402 873 4040",
    "sg:postcode":"68410",
    "sg:province":"NE",
    "sg:tags":[
        "center"
    ],
    "wof:name":"Big Apple Family Fun Ctr",
    "wof:placetype":"venue"
},
  "geometry": {"coordinates":[-95.861465,40.671045],"type":"Point"}
}