{
  "type": "Feature",
  "properties": {
    "addr:full":"1634 N 59th St Lincoln NE 68505",
    "addr:housenumber":"1634",
    "addr:postcode":"68505",
    "addr:street":"N 59Th St",
    "iso:country":"US",
    "sg:address":"1634 N 59th St",
    "sg:city":"Lincoln",
    "sg:classifiers":[
        {
            "category":"Restaurant",
            "type":"Food & Drink"
        }
    ],
    "sg:phone":"+1 402 464 0146",
    "sg:postcode":"68505",
    "sg:province":"NE",
    "sg:tags":[
        "eating"
    ],
    "wof:name":"Los Mendoza Mexican Restaurant",
    "wof:placetype":"venue"
},
  "geometry": {"coordinates":[-96.640473,40.828588],"type":"Point"}
}