{
  "type": "Feature",
  "properties": {
    "iso:country":"US",
    "sg:address":"15318 Hillsdale Ave",
    "sg:city":"Omaha",
    "sg:classifiers":[
        {
            "category":"Real Estate",
            "subcategory":"Real Estate Operator",
            "type":"Services"
        }
    ],
    "sg:phone":"+1 402 895 7201",
    "sg:postcode":"68137",
    "sg:province":"NE",
    "sg:tags":[
        "property",
        "lessor"
    ],
    "wof:name":"John B Holmquist",
    "wof:placetype":"venue"
},
  "geometry": {"coordinates":[-96.152536,41.217491],"type":"Point"}
}