{
  "type": "Feature",
  "properties": {
    "iso:country":"US",
    "sg:address":"225 S Grant St",
    "sg:city":"Fremont",
    "sg:classifiers":[
        {
            "category":"Building & Trades",
            "subcategory":"Equipment Rental",
            "type":"Services"
        }
    ],
    "sg:phone":"+1 402 727 4830",
    "sg:postcode":"68025",
    "sg:province":"NE",
    "sg:tags":[
        "automotive",
        "repair"
    ],
    "wof:name":"Gutschow Repair",
    "wof:placetype":"venue"
},
  "geometry": {"coordinates":[-96.48203700000001,41.428115],"type":"Point"}
}