{
  "type": "Feature",
  "properties": {
    "iso:country":"US",
    "sg:address":"3925 2nd Ave",
    "sg:city":"Scottsbluff",
    "sg:classifiers":[
        {
            "category":"Real Estate",
            "subcategory":"Real Estate Operator",
            "type":"Services"
        }
    ],
    "sg:phone":"+1 308 630 0138",
    "sg:postcode":"69361",
    "sg:province":"NE",
    "sg:tags":[
        "property",
        "lessor"
    ],
    "wof:name":"Loughry Rentals",
    "wof:placetype":"venue"
},
  "geometry": {"coordinates":[-103.66027,41.88545],"type":"Point"}
}