{
  "type": "Feature",
  "properties": {
    "iso:country":"US",
    "sg:address":"4410 S 37th St",
    "sg:city":"Lincoln",
    "sg:classifiers":[
        {
            "category":"Food & Beverages",
            "subcategory":"Bakery",
            "type":"Retail Goods"
        }
    ],
    "sg:phone":"+1 402 488 6424",
    "sg:postcode":"68516",
    "sg:province":"NE",
    "wof:name":"Mettler Family Bakery Inc",
    "wof:placetype":"venue"
},
  "geometry": {"coordinates":[-96.666876,40.769429],"type":"Point"}
}