{
  "type": "Feature",
  "properties": {
    "iso:country":"US",
    "sg:address":"70804 Hwy 26",
    "sg:city":"Morrill",
    "sg:classifiers":[
        {
            "category":"Home & Garden",
            "subcategory":"Garden Supply",
            "type":"Retail Goods"
        }
    ],
    "sg:phone":"+1 308 247 2017",
    "sg:postcode":"69358",
    "sg:province":"NE",
    "sg:tags":[
        "bulb",
        "seed"
    ],
    "wof:name":"Dillman's Pioneer Brand",
    "wof:placetype":"venue"
},
  "geometry": {"coordinates":[-103.916725,41.963576],"type":"Point"}
}