{
  "type": "Feature",
  "properties": {
    "addr:full":"547 N 48th St Lincoln NE 68504",
    "addr:housenumber":"547",
    "addr:postcode":"68504",
    "addr:street":"N 48Th St",
    "iso:country":"US",
    "sg:address":"547 N 48th St",
    "sg:city":"Lincoln",
    "sg:classifiers":[
        {
            "category":"Restaurant",
            "type":"Food & Drink"
        }
    ],
    "sg:menulink":"http://www.allmenus.com/ne/lincoln/194660-mcdonalds/menu/",
    "sg:phone":"+1 402 464 2290",
    "sg:postcode":"68504",
    "sg:province":"NE",
    "sg:tags":[
        "burger",
        "american"
    ],
    "wof:name":"McDonald's",
    "wof:placetype":"venue"
},
  "geometry": {"coordinates":[-96.654375,40.818701],"type":"Point"}
}