{
  "type": "Feature",
  "properties": {
    "iso:country":"US",
    "sg:address":"549 N Central Ave",
    "sg:city":"Superior",
    "sg:classifiers":[
        {
            "category":"Organizations",
            "subcategory":"Religious Organization",
            "type":"Services"
        }
    ],
    "sg:phone":"+1 402 879 3733",
    "sg:postcode":"68978",
    "sg:province":"NE",
    "sg:tags":[
        "church"
    ],
    "wof:name":"Presbyterian Church First",
    "wof:placetype":"venue"
},
  "geometry": {"coordinates":[-98.071485,40.021465],"type":"Point"}
}