{
  "type": "Feature",
  "properties": {
    "addr:full":"666 N 59th St Omaha NE 68132",
    "addr:housenumber":"666",
    "addr:postcode":"68132",
    "addr:street":"N 59Th St",
    "iso:country":"US",
    "sg:address":"666 N 59th St",
    "sg:city":"Omaha",
    "sg:classifiers":[
        {
            "category":"Professional",
            "subcategory":"Lawyer & Legal Services",
            "type":"Services"
        }
    ],
    "sg:phone":"+1 402 556 8249",
    "sg:postcode":"68132",
    "sg:province":"NE",
    "wof:name":"McDonnell Patrick H Atty",
    "wof:placetype":"venue"
},
  "geometry": {"coordinates":[-96.00369999999999,41.266499],"type":"Point"}
}