{
  "type": "Feature",
  "properties": {
    "addr:full":"700 E 3rd St North Platte NE 69101",
    "addr:housenumber":"700",
    "addr:postcode":"69101",
    "addr:street":"E 3Rd St",
    "iso:country":"US",
    "sg:address":"700 E 3rd St",
    "sg:city":"North Platte",
    "sg:classifiers":[
        {
            "category":"Education",
            "subcategory":"School",
            "type":"Public Place"
        }
    ],
    "sg:phone":"+1 308 535 7136",
    "sg:postcode":"69101",
    "sg:province":"NE",
    "wof:name":"Jefferson Elementary School",
    "wof:placetype":"venue"
},
  "geometry": {"coordinates":[-100.756108,41.134584],"type":"Point"}
}