{
  "type": "Feature",
  "properties": {
    "iso:country":"US",
    "sg:address":"1973 G Ave",
    "sg:city":"Dakota City",
    "sg:classifiers":[
        {
            "category":"Retail",
            "subcategory":"Auto Repair",
            "type":"Services"
        }
    ],
    "sg:phone":"+1 402 987 3515",
    "sg:postcode":"68731",
    "sg:province":"NE",
    "sg:tags":[
        "automotive",
        "wrecker"
    ],
    "wof:name":"Curt's Towing",
    "wof:placetype":"venue"
},
  "geometry": {"coordinates":[-96.482784,42.383385],"type":"Point"}
}