{
  "type": "Feature",
  "properties": {
    "addr:full":"610 Dean St Grand Island NE 68801",
    "addr:housenumber":"610",
    "addr:postcode":"68801",
    "addr:street":"Dean St",
    "iso:country":"US",
    "sg:address":"610 Dean St",
    "sg:city":"Grand Island",
    "sg:classifiers":[
        {
            "category":"Professional",
            "subcategory":"Business Services",
            "type":"Services"
        }
    ],
    "sg:phone":"+1 308 382 3823",
    "sg:postcode":"68801",
    "sg:province":"NE",
    "sg:tags":[
        "embroidery"
    ],
    "wof:name":"Designs For You Embroidery",
    "wof:placetype":"venue"
},
  "geometry": {"coordinates":[-98.337603,40.949086],"type":"Point"}
}