{
  "type": "Feature",
  "properties": {
    "iso:country":"US",
    "sg:address":"525 Langdon Ave",
    "sg:city":"Gretna",
    "sg:classifiers":[
        {
            "category":"Freight",
            "type":"Transportation"
        }
    ],
    "sg:phone":"+1 402 332 3115",
    "sg:postcode":"68028",
    "sg:province":"NE",
    "sg:tags":[
        "grain",
        "hauling"
    ],
    "wof:name":"Marv's Transfer",
    "wof:placetype":"venue"
},
  "geometry": {"coordinates":[-96.245276,41.138311],"type":"Point"}
}