{
  "type": "Feature",
  "properties": {
    "addr:full":"502 Broadway St Yankton NE 57078",
    "addr:housenumber":"502",
    "addr:postcode":"57078",
    "addr:street":"Broadway St",
    "iso:country":"US",
    "sg:address":"502 Broadway St",
    "sg:city":"Yankton",
    "sg:classifiers":[
        {
            "category":"Autos & Motor Vehicles",
            "subcategory":"Automobile Sales",
            "type":"Retail Goods"
        }
    ],
    "sg:phone":"+1 605 665 3334",
    "sg:postcode":"57078",
    "sg:province":"NE",
    "sg:tags":[
        "car",
        "used",
        "dealer"
    ],
    "wof:name":"Berkeley Motors",
    "wof:placetype":"venue"
},
  "geometry": {"coordinates":[-97.39676300000001,42.873752],"type":"Point"}
}