{
  "type": "Feature",
  "properties": {
    "addr:full":"2011 P St Auburn NE 68305",
    "addr:housenumber":"2011 p",
    "addr:postcode":"68305",
    "addr:street":"St",
    "iso:country":"US",
    "sg:address":"2011 P St",
    "sg:city":"Auburn",
    "sg:classifiers":[
        {
            "category":"Retail",
            "subcategory":"Repair Shop",
            "type":"Services"
        }
    ],
    "sg:phone":"+1 402 274 3300",
    "sg:postcode":"68305",
    "sg:province":"NE",
    "sg:tags":[
        "lock",
        "locksmith"
    ],
    "wof:name":"Last Chance Locksmith",
    "wof:placetype":"venue"
},
  "geometry": {"coordinates":[-95.846661,40.384271],"type":"Point"}
}