{
  "type": "Feature",
  "properties": {
    "addr:full":"128 N 3rd St Hampton NE 68843",
    "addr:housenumber":"128",
    "addr:postcode":"68843",
    "addr:street":"N 3Rd St",
    "iso:country":"US",
    "sg:address":"128 N 3rd St",
    "sg:city":"Hampton",
    "sg:classifiers":[
        {
            "category":"Building & Trades",
            "subcategory":"Plumbing",
            "type":"Services"
        }
    ],
    "sg:phone":"+1 402 725 3138",
    "sg:postcode":"68843",
    "sg:province":"NE",
    "sg:tags":[
        "plumbing",
        "contractor"
    ],
    "wof:name":"Tune Dog Plumbing",
    "wof:placetype":"venue"
},
  "geometry": {"coordinates":[-97.88587699999999,40.879252],"type":"Point"}
}