{
  "type": "Feature",
  "properties": {
    "iso:country":"US",
    "sg:address":"7338 Ira Ct",
    "sg:city":"La Vista",
    "sg:classifiers":[
        {
            "category":"Social Services",
            "subcategory":"Child Care",
            "type":"Services"
        }
    ],
    "sg:phone":"+1 402 339 2014",
    "sg:postcode":"68128",
    "sg:province":"NE",
    "sg:tags":[
        "day"
    ],
    "wof:name":"Wetzel Day Care",
    "wof:placetype":"venue"
},
  "geometry": {"coordinates":[-96.026554,41.185147],"type":"Point"}
}