{
  "type": "Feature",
  "properties": {
    "addr:full":"2004 W Division St Grand Island NE 68803",
    "addr:housenumber":"2004",
    "addr:postcode":"68803",
    "addr:street":"W Division St",
    "iso:country":"US",
    "sg:address":"2004 W Division St",
    "sg:city":"Grand Island",
    "sg:classifiers":[
        {
            "category":"Shopping",
            "subcategory":"Used Merchandise",
            "type":"Retail Goods"
        }
    ],
    "sg:phone":"+1 308 384 8686",
    "sg:postcode":"68803",
    "sg:province":"NE",
    "wof:name":"Nan S Antiques",
    "wof:placetype":"venue"
},
  "geometry": {"coordinates":[-98.35903,40.91476],"type":"Point"}
}