{
  "type": "Feature",
  "properties": {
    "iso:country":"US",
    "sg:address":"223 2nd St S",
    "sg:city":"Dannebrog",
    "sg:classifiers":[
        {
            "category":"Government",
            "subcategory":"Office",
            "type":"Public Place"
        }
    ],
    "sg:phone":"+1 308 226 2304",
    "sg:postcode":"68831",
    "sg:province":"NE",
    "sg:tags":[
        "county"
    ],
    "wof:name":"Dannebrog County Road Mntnnc",
    "wof:placetype":"venue"
},
  "geometry": {"coordinates":[-98.54491,41.117951],"type":"Point"}
}