{
  "type": "Feature",
  "properties": {
    "iso:country":"US",
    "sg:address":"715 Meridian Ave",
    "sg:city":"Cozad",
    "sg:classifiers":[
        {
            "category":"Building & Trades",
            "subcategory":"Equipment Rental",
            "type":"Services"
        }
    ],
    "sg:phone":"+1 308 784 3200",
    "sg:postcode":"69130",
    "sg:province":"NE",
    "wof:name":"Drive In Videos",
    "wof:placetype":"venue"
},
  "geometry": {"coordinates":[-99.985983,40.85884],"type":"Point"}
}