{
  "type": "Feature",
  "properties": {
    "addr:full":"210 E 5th St Hastings NE 68901",
    "addr:housenumber":"210",
    "addr:postcode":"68901",
    "addr:street":"E 5Th St",
    "iso:country":"US",
    "sg:address":"210 E 5th St",
    "sg:city":"Hastings",
    "sg:classifiers":[
        {
            "category":"Building & Trades",
            "subcategory":"Construction",
            "type":"Services"
        }
    ],
    "sg:phone":"+1 402 462 6207",
    "sg:postcode":"68901",
    "sg:province":"NE",
    "wof:name":"Moonlight Services",
    "wof:placetype":"venue"
},
  "geometry": {"coordinates":[-98.380561,40.587753],"type":"Point"}
}