{
  "type": "Feature",
  "properties": {
    "iso:country":"US",
    "sg:address":"4618 S 139th St",
    "sg:city":"Omaha",
    "sg:classifiers":[
        {
            "category":"Organizations",
            "subcategory":"Community Association",
            "type":"Services"
        }
    ],
    "sg:phone":"+1 402 895 1324",
    "sg:postcode":"68137",
    "sg:province":"NE",
    "sg:tags":[
        "military"
    ],
    "wof:name":"American Legion",
    "wof:placetype":"venue"
},
  "geometry": {"coordinates":[-96.13240999999999,41.21572],"type":"Point"}
}