{
  "type": "Feature",
  "properties": {
    "iso:country":"US",
    "sg:address":"301 W Sq",
    "sg:city":"Humboldt",
    "sg:classifiers":[
        {
            "category":"Manufacturing",
            "subcategory":"Printing",
            "type":"Manufacturing & Wholesale Goods"
        }
    ],
    "sg:phone":"+1 402 862 2490",
    "sg:postcode":"68376",
    "sg:province":"NE",
    "sg:tags":[
        "commercial"
    ],
    "wof:name":"Best Printing",
    "wof:placetype":"venue"
},
  "geometry": {"coordinates":[-95.947732,40.16379],"type":"Point"}
}