{
  "type": "Feature",
  "properties": {
    "iso:country":"US",
    "sg:address":"4553 S 88th St",
    "sg:city":"Omaha",
    "sg:classifiers":[
        {
            "category":"Wholesale",
            "subcategory":"Machinery & Supplies",
            "type":"Manufacturing & Wholesale Goods"
        }
    ],
    "sg:phone":"+1 402 597 5777",
    "sg:postcode":"68127",
    "sg:province":"NE",
    "sg:tags":[
        "product",
        "processing",
        "meat",
        "grating"
    ],
    "sg:website":"www.mbasuppliers.com",
    "wof:name":"MBA Suppliers Inc",
    "wof:placetype":"venue"
},
  "geometry": {"coordinates":[-96.04799199999999,41.213534],"type":"Point"}
}