{
  "type": "Feature",
  "properties": {
    "addr:full":"3636 S 138th St Omaha NE 68144",
    "addr:housenumber":"3636",
    "addr:postcode":"68144",
    "addr:street":"S 138Th St",
    "iso:country":"US",
    "sg:address":"3636 S 138th St",
    "sg:city":"Omaha",
    "sg:classifiers":[
        {
            "category":"Wholesale",
            "subcategory":"Electrical",
            "type":"Manufacturing & Wholesale Goods"
        }
    ],
    "sg:phone":"+1 402 330 9170",
    "sg:postcode":"68144",
    "sg:province":"NE",
    "sg:tags":[
        "telecommunication"
    ],
    "wof:name":"Kidwell Technologies",
    "wof:placetype":"venue"
},
  "geometry": {"coordinates":[-96.128052,41.223853],"type":"Point"}
}