{
  "type": "Feature",
  "properties": {
    "addr:full":"4916 Underwood Ave Lowr Omaha NE 68132",
    "addr:housenumber":"4916",
    "addr:postcode":"68132",
    "addr:street":"Underwood Ave",
    "iso:country":"US",
    "sg:address":"4916 Underwood Ave Lowr",
    "sg:city":"Omaha",
    "sg:classifiers":[
        {
            "category":"Arts & Performance",
            "subcategory":"Art Gallery",
            "type":"Entertainment"
        }
    ],
    "sg:phone":"+1 402 505 8333",
    "sg:postcode":"68132",
    "sg:province":"NE",
    "wof:name":"Dundee Gallery",
    "wof:placetype":"venue"
},
  "geometry": {"coordinates":[-95.988265,41.265224],"type":"Point"}
}