{
  "type": "Feature",
  "properties": {
    "iso:country":"US",
    "sg:address":"1014 N 17th St",
    "sg:city":"Omaha",
    "sg:classifiers":[
        {
            "category":"Retail",
            "subcategory":"Repair Shop",
            "type":"Services"
        }
    ],
    "sg:phone":"+1 402 734 7717",
    "sg:postcode":"68102",
    "sg:province":"NE",
    "sg:tags":[
        "plumbing",
        "drain",
        "cleaning",
        "sewer"
    ],
    "wof:name":"Sullivan Sewer Svc",
    "wof:placetype":"venue"
},
  "geometry": {"coordinates":[-95.938485,41.269386],"type":"Point"}
}