{
  "type": "Feature",
  "properties": {
    "addr:full":"1703 Broadway Scottsbluff NE 69361",
    "addr:housenumber":"1703",
    "addr:postcode":"69361",
    "addr:street":"Broadway",
    "iso:country":"US",
    "sg:address":"1703 Broadway",
    "sg:city":"Scottsbluff",
    "sg:classifiers":[
        {
            "category":"Restaurant",
            "type":"Food & Drink"
        }
    ],
    "sg:phone":"+1 308 635 9997",
    "sg:postcode":"69361",
    "sg:province":"NE",
    "sg:tags":[
        "shop",
        "coffee",
        "eating"
    ],
    "wof:name":"Cappuccino & Co",
    "wof:placetype":"venue"
},
  "geometry": {"coordinates":[-103.662674,41.864236],"type":"Point"}
}