{
  "type": "Feature",
  "properties": {
    "addr:full":"105 W 5th St Fairbury NE 68352",
    "addr:housenumber":"105",
    "addr:postcode":"68352",
    "addr:street":"W 5Th St",
    "iso:country":"US",
    "sg:address":"105 W 5th St",
    "sg:city":"Fairbury",
    "sg:classifiers":[
        {
            "category":"Social Services",
            "subcategory":"Adult Care",
            "type":"Services"
        }
    ],
    "sg:phone":"+1 402 729 3451",
    "sg:postcode":"68352",
    "sg:province":"NE",
    "sg:tags":[
        "personal",
        "residential"
    ],
    "wof:name":"Park View Apts",
    "wof:placetype":"venue"
},
  "geometry": {"coordinates":[-97.187218,40.136385],"type":"Point"}
}