{
  "type": "Feature",
  "properties": {
    "iso:country":"US",
    "sg:address":"1515 M St",
    "sg:city":"Omaha",
    "sg:classifiers":[
        {
            "category":"Retail",
            "subcategory":"Auto Repair",
            "type":"Services"
        }
    ],
    "sg:phone":"+1 402 734 4865",
    "sg:postcode":"68107",
    "sg:province":"NE",
    "sg:tags":[
        "automotive",
        "wrecker"
    ],
    "wof:name":"Tanner's Towing",
    "wof:placetype":"venue"
},
  "geometry": {"coordinates":[-95.936761,41.210959],"type":"Point"}
}