{
  "type": "Feature",
  "properties": {
    "iso:country":"US",
    "sg:address":"15724 Hascall Cir",
    "sg:city":"Omaha",
    "sg:classifiers":[
        {
            "category":"Banks & Credit Unions",
            "subcategory":"Financial Services",
            "type":"Services"
        }
    ],
    "sg:phone":"+1 402 334 8296",
    "sg:postcode":"68130",
    "sg:province":"NE",
    "sg:tags":[
        "investor"
    ],
    "wof:name":"Investment Properties Nebra",
    "wof:placetype":"venue"
},
  "geometry": {"coordinates":[-96.159933,41.228524],"type":"Point"}
}