{
  "type": "Feature",
  "properties": {
    "iso:country":"US",
    "sg:address":"85 W 4th St",
    "sg:city":"Fremont",
    "sg:classifiers":[
        {
            "category":"Restaurant",
            "type":"Food & Drink"
        }
    ],
    "sg:phone":"+1 402 753 3867",
    "sg:postcode":"68025",
    "sg:province":"NE",
    "sg:tags":[
        "eating"
    ],
    "wof:name":"The Brass Nugget",
    "wof:placetype":"venue"
},
  "geometry": {"coordinates":[-96.49839299999999,41.43284],"type":"Point"}
}