{
  "type": "Feature",
  "properties": {
    "iso:country":"US",
    "sg:address":"4021 Commercial Ave",
    "sg:city":"Giltner",
    "sg:classifiers":[
        {
            "category":"Government",
            "subcategory":"Office",
            "type":"Public Place"
        }
    ],
    "sg:phone":"+1 402 849 2800",
    "sg:postcode":"68841",
    "sg:province":"NE",
    "sg:tags":[
        "village"
    ],
    "wof:name":"Giltner Clerk's Office",
    "wof:placetype":"venue"
},
  "geometry": {"coordinates":[-98.153513,40.774648],"type":"Point"}
}