{
  "type": "Feature",
  "properties": {
    "addr:full":"1910 Washington St Beatrice NE 68310",
    "addr:housenumber":"1910",
    "addr:postcode":"68310",
    "addr:street":"Washington St",
    "iso:country":"US",
    "sg:address":"1910 Washington St",
    "sg:city":"Beatrice",
    "sg:classifiers":[
        {
            "category":"Personal",
            "subcategory":"Beauty Salon",
            "type":"Services"
        }
    ],
    "sg:phone":"+1 402 228 4522",
    "sg:postcode":"68310",
    "sg:province":"NE",
    "wof:name":"Shear Style Salon",
    "wof:placetype":"venue"
},
  "geometry": {"coordinates":[-96.72775,40.272687],"type":"Point"}
}