{
  "type": "Feature",
  "properties": {
    "iso:country":"US",
    "sg:address":"1910 Washington St",
    "sg:city":"Beatrice",
    "sg:classifiers":[
        {
            "category":"Personal",
            "subcategory":"Beauty Salon",
            "type":"Services"
        }
    ],
    "sg:phone":"+1 402 228 4522",
    "sg:postcode":"68310",
    "sg:province":"NE",
    "wof:name":"Shear Style Salon",
    "wof:placetype":"venue"
},
  "geometry": {"coordinates":[-96.72775,40.272687],"type":"Point"}
}