{
  "type": "Feature",
  "properties": {
    "iso:country":"US",
    "sg:address":"4070 Dack Ave",
    "sg:city":"Grand Island",
    "sg:classifiers":[
        {
            "category":"Professional",
            "subcategory":"Management & Consulting",
            "type":"Services"
        }
    ],
    "sg:phone":"+1 308 384 9462",
    "sg:postcode":"68803",
    "sg:province":"NE",
    "wof:name":"Warehouse Management Inc",
    "wof:placetype":"venue"
},
  "geometry": {"coordinates":[-98.400713,40.947567],"type":"Point"}
}