{
  "type": "Feature",
  "properties": {
    "addr:full":"2269 E 23rd St Fremont NE 68025",
    "addr:housenumber":"2269",
    "addr:postcode":"68025",
    "addr:street":"E 23Rd St",
    "iso:country":"US",
    "sg:address":"2269 E 23rd St",
    "sg:city":"Fremont",
    "sg:classifiers":[
        {
            "category":"Retail",
            "subcategory":"Auto Rental",
            "type":"Services"
        }
    ],
    "sg:phone":"+1 402 727 4160",
    "sg:postcode":"68025",
    "sg:province":"NE",
    "sg:tags":[
        "renting",
        "automobile",
        "agency",
        "leasing"
    ],
    "wof:name":"Enterprise Rent A Car",
    "wof:placetype":"venue"
},
  "geometry": {"coordinates":[-96.46779600000001,41.451177],"type":"Point"}
}