{
  "type": "Feature",
  "properties": {
    "iso:country":"US",
    "sg:address":"5616 N 103rd St",
    "sg:city":"Omaha",
    "sg:classifiers":[
        {
            "category":"Shopping",
            "subcategory":"Bicycles & Sporting Goods",
            "type":"Retail Goods"
        }
    ],
    "sg:phone":"+1 402 491 0355",
    "sg:postcode":"68134",
    "sg:province":"NE",
    "sg:tags":[
        "equipment",
        "playground"
    ],
    "wof:name":"Rainbow Play Systems",
    "wof:placetype":"venue"
},
  "geometry": {"coordinates":[-96.075596,41.30961],"type":"Point"}
}