{
  "type": "Feature",
  "properties": {
    "addr:full":"4604 S 25th St Omaha NE 68107",
    "addr:housenumber":"4604",
    "addr:postcode":"68107",
    "addr:street":"S 25Th St",
    "iso:country":"US",
    "sg:address":"4604 S 25th St",
    "sg:city":"Omaha",
    "sg:classifiers":[
        {
            "category":"Banks & Credit Unions",
            "subcategory":"Financial Services",
            "type":"Services"
        }
    ],
    "sg:phone":"+1 402 731 8600",
    "sg:postcode":"68107",
    "sg:province":"NE",
    "sg:tags":[
        "broker",
        "mortgage"
    ],
    "sg:website":"www.firstmortgageco.com",
    "wof:name":"First Mortgage Company Llc",
    "wof:placetype":"venue"
},
  "geometry": {"coordinates":[-95.948713,41.213448],"type":"Point"}
}