{
  "type": "Feature",
  "properties": {
    "iso:country":"US",
    "sg:address":"141 N Calvert St",
    "sg:city":"Lawrence",
    "sg:classifiers":[
        {
            "category":"Building & Trades",
            "subcategory":"Landscaping Services",
            "type":"Services"
        }
    ],
    "sg:phone":"+1 402 756 7255",
    "sg:postcode":"68957",
    "sg:province":"NE",
    "sg:tags":[
        "lawn",
        "maintenance",
        "grounds"
    ],
    "wof:name":"Weedman",
    "wof:placetype":"venue"
},
  "geometry": {"coordinates":[-98.25996499999999,40.291654],"type":"Point"}
}