{
  "type": "Feature",
  "properties": {
    "iso:country":"US",
    "sg:address":"6041 Village Dr",
    "sg:city":"Lincoln",
    "sg:classifiers":[
        {
            "category":"Health Services",
            "subcategory":"Doctor",
            "type":"Services"
        }
    ],
    "sg:phone":"+1 402 423 1382",
    "sg:postcode":"68516",
    "sg:province":"NE",
    "sg:tags":[
        "medical"
    ],
    "wof:name":"Jirovec Richard MD",
    "wof:placetype":"venue"
},
  "geometry": {"coordinates":[-96.664728,40.751174],"type":"Point"}
}