{
  "type": "Feature",
  "properties": {
    "addr:full":"8550 Andermatt Dr Ste 1 Lincoln NE 68526",
    "addr:postcode":"8550;68526",
    "addr:street":"Andermatt Dr Ste 1",
    "iso:country":"US",
    "sg:address":"8550 Andermatt Dr Ste 1",
    "sg:city":"Lincoln",
    "sg:classifiers":[
        {
            "category":"Fast Food",
            "type":"Food & Drink"
        },
        {
            "category":"Restaurant",
            "type":"Food & Drink"
        }
    ],
    "sg:phone":"+1 402 489 9993",
    "sg:postcode":"68526",
    "sg:province":"NE",
    "sg:tags":[
        "menu",
        "chinese"
    ],
    "sg:website":"http://www.chinawallne.com",
    "wof:name":"China Wall",
    "wof:placetype":"venue"
},
  "geometry": {"coordinates":[-96.604023,40.736313],"type":"Point"}
}