{
  "type": "Feature",
  "properties": {
    "iso:country":"US",
    "sg:address":"221 Willard Ave",
    "sg:city":"Genoa",
    "sg:classifiers":[
        {
            "category":"Food & Beverages",
            "subcategory":"Groceries & Convenience Stores",
            "type":"Retail Goods"
        }
    ],
    "sg:phone":"+1 402 993 2344",
    "sg:postcode":"68640",
    "sg:province":"NE",
    "wof:name":"Aj's Of Genoa",
    "wof:placetype":"venue"
},
  "geometry": {"coordinates":[-97.72790500000001,41.448433],"type":"Point"}
}