{
  "type": "Feature",
  "properties": {
    "iso:country":"US",
    "sg:address":"2275 State Hwy 35",
    "sg:city":"Hubbard",
    "sg:classifiers":[
        {
            "category":"Building & Trades",
            "subcategory":"Construction",
            "type":"Services"
        }
    ],
    "sg:phone":"+1 402 695 2218",
    "sg:postcode":"68741",
    "sg:province":"NE",
    "sg:tags":[
        "house"
    ],
    "wof:name":"Koopman Enterprises Inc",
    "wof:placetype":"venue"
},
  "geometry": {"coordinates":[-96.657195,42.338189],"type":"Point"}
}