{
  "type": "Feature",
  "properties": {
    "iso:country":"US",
    "sg:address":"114 E C St",
    "sg:city":"Mc Cook",
    "sg:classifiers":[
        {
            "category":"Professional",
            "type":"Services"
        }
    ],
    "sg:phone":"+1 308 345 5414",
    "sg:postcode":"69001",
    "sg:province":"NE",
    "sg:tags":[
        "establishment"
    ],
    "wof:name":"Volentine Inc",
    "wof:placetype":"venue"
},
  "geometry": {"coordinates":[-100.62570100000001,40.199549],"type":"Point"}
}