{
  "type": "Feature",
  "properties": {
    "iso:country":"US",
    "sg:address":"9018 Raven Oaks Dr",
    "sg:city":"Omaha",
    "sg:classifiers":[
        {
            "category":"Organizations",
            "subcategory":"Religious Organization",
            "type":"Services"
        }
    ],
    "sg:phone":"+1 402 571 5819",
    "sg:postcode":"68152",
    "sg:province":"NE",
    "sg:tags":[
        "church"
    ],
    "wof:name":"Gould Ministries",
    "wof:placetype":"venue"
},
  "geometry": {"coordinates":[-95.997179,41.342966],"type":"Point"}
}