{
  "type": "Feature",
  "properties": {
    "iso:country":"US",
    "sg:address":"2045 Co Rd K",
    "sg:city":"Wahoo",
    "sg:classifiers":[
        {
            "category":"Education",
            "subcategory":"Dance Studio",
            "type":"Public Place"
        }
    ],
    "sg:phone":"+1 402 443 3533",
    "sg:postcode":"68066",
    "sg:province":"NE",
    "sg:tags":[
        "personal"
    ],
    "sg:website":"www.starliteballroom.net",
    "wof:name":"Starlite Ballroom Inc",
    "wof:placetype":"venue"
},
  "geometry": {"coordinates":[-96.68643899999999,41.205444],"type":"Point"}
}