{
  "type": "Feature",
  "properties": {
    "iso:country":"US",
    "sg:address":"1818 Lincoln St",
    "sg:city":"Blair",
    "sg:classifiers":[
        {
            "category":"Restaurant",
            "type":"Food & Drink"
        }
    ],
    "sg:phone":"+1 402 426 3235",
    "sg:postcode":"68008",
    "sg:province":"NE",
    "sg:tags":[
        "caterer"
    ],
    "wof:name":"Catering Catering",
    "wof:placetype":"venue"
},
  "geometry": {"coordinates":[-96.14030200000001,41.542902],"type":"Point"}
}