{
  "type": "Feature",
  "properties": {
    "addr:full":"2809 S 160th St Omaha NE 68130",
    "addr:housenumber":"2809",
    "addr:postcode":"68130",
    "addr:street":"S 160Th St",
    "iso:country":"US",
    "sg:address":"2809 S 160th St",
    "sg:city":"Omaha",
    "sg:classifiers":[
        {
            "category":"Professional",
            "subcategory":"Accounting & Tax Preparation",
            "type":"Services"
        }
    ],
    "sg:phone":"+1 402 691 0731",
    "sg:postcode":"68130",
    "sg:province":"NE",
    "sg:tags":[
        "firm",
        "return",
        "filing"
    ],
    "wof:name":"Baumert Tax Accounting Inc",
    "wof:placetype":"venue"
},
  "geometry": {"coordinates":[-96.164952,41.232629],"type":"Point"}
}