{
  "type": "Feature",
  "properties": {
    "addr:full":"8109 W Denton Rd Denton NE 68339",
    "addr:housenumber":"8109",
    "addr:postcode":"68339",
    "addr:street":"W Denton Rd",
    "iso:country":"US",
    "sg:address":"8109 W Denton Rd",
    "sg:city":"Denton",
    "sg:classifiers":[
        {
            "category":"Building & Trades",
            "subcategory":"Cleaning & Sanitation",
            "type":"Services"
        }
    ],
    "sg:phone":"+1 402 797 8109",
    "sg:postcode":"68339",
    "sg:province":"NE",
    "sg:tags":[
        "janitorial"
    ],
    "wof:name":"Shinebright Cleaning Service",
    "wof:placetype":"venue"
},
  "geometry": {"coordinates":[-96.831204,40.741129],"type":"Point"}
}