{
  "type": "Feature",
  "properties": {
    "iso:country":"US",
    "sg:address":"41665 Coal Chute Rd",
    "sg:city":"Gibbon",
    "sg:classifiers":[
        {
            "category":"Government",
            "subcategory":"Office",
            "type":"Public Place"
        }
    ],
    "sg:phone":"+1 308 468 6193",
    "sg:postcode":"68840",
    "sg:province":"NE",
    "sg:tags":[
        "executive"
    ],
    "wof:name":"Gibbon Township",
    "wof:placetype":"venue"
},
  "geometry": {"coordinates":[-98.92268300000001,40.699039],"type":"Point"}
}