{
  "type": "Feature",
  "properties": {
    "iso:country":"US",
    "sg:address":"12836 Drexel St",
    "sg:city":"Omaha",
    "sg:classifiers":[
        {
            "category":"Shopping",
            "subcategory":"Jewelry",
            "type":"Retail Goods"
        }
    ],
    "sg:phone":"+1 402 330 2918",
    "sg:postcode":"68137",
    "sg:province":"NE",
    "sg:tags":[
        "jeweler"
    ],
    "wof:name":"Icing By Claire's",
    "wof:placetype":"venue"
},
  "geometry": {"coordinates":[-96.11324500000001,41.191886],"type":"Point"}
}