{
  "type": "Feature",
  "properties": {
    "iso:country":"US",
    "sg:address":"73646 Rd 435",
    "sg:city":"Bertrand",
    "sg:phone":"+1 308 472 5216",
    "sg:postcode":"68927",
    "sg:province":"NE",
    "sg:tags":[
        "farm",
        "corn"
    ],
    "wof:name":"Randall Rabe",
    "wof:placetype":"venue"
},
  "geometry": {"coordinates":[-99.700498,40.510145],"type":"Point"}
}