{
  "type": "Feature",
  "properties": {
    "iso:country":"US",
    "sg:address":"320 E 9th St",
    "sg:city":"Hastings",
    "sg:classifiers":[
        {
            "category":"Building & Trades",
            "subcategory":"Construction",
            "type":"Services"
        }
    ],
    "sg:phone":"+1 402 461 0377",
    "sg:postcode":"68901",
    "sg:province":"NE",
    "sg:tags":[
        "house",
        "carpentry",
        "contractor"
    ],
    "wof:name":"C L Wimer Construction",
    "wof:placetype":"venue"
},
  "geometry": {"coordinates":[-98.37813800000001,40.593361],"type":"Point"}
}