{
  "type": "Feature",
  "properties": {
    "addr:full":"722 S Lincoln Ave York NE 68467",
    "addr:housenumber":"722",
    "addr:postcode":"68467",
    "addr:street":"S Lincoln Ave",
    "iso:country":"US",
    "sg:address":"722 S Lincoln Ave",
    "sg:city":"York",
    "sg:classifiers":[
        {
            "category":"Home & Garden",
            "subcategory":"Garden Supply",
            "type":"Retail Goods"
        }
    ],
    "sg:phone":"+1 402 362 3394",
    "sg:postcode":"68467",
    "sg:province":"NE",
    "sg:tags":[
        "nurseryman"
    ],
    "wof:name":"Earl May Nursery & Garden Ctr",
    "wof:placetype":"venue"
},
  "geometry": {"coordinates":[-97.59308799999999,40.858658],"type":"Point"}
}