{
  "type": "Feature",
  "properties": {
    "iso:country":"US",
    "sg:address":"801 N Grant St",
    "sg:city":"Lexington",
    "sg:classifiers":[
        {
            "category":"Health Services",
            "subcategory":"Optometrist",
            "type":"Services"
        }
    ],
    "sg:phone":"+1 308 324 5631",
    "sg:postcode":"68850",
    "sg:province":"NE",
    "wof:name":"Moomey & Harvey",
    "wof:placetype":"venue"
},
  "geometry": {"coordinates":[-99.740127,40.781425],"type":"Point"}
}