{
  "type": "Feature",
  "properties": {
    "addr:full":"204 Fairfield St Lincoln NE 68521",
    "addr:housenumber":"204",
    "addr:postcode":"68521",
    "addr:street":"Fairfield St",
    "iso:country":"US",
    "sg:address":"204 Fairfield St",
    "sg:city":"Lincoln",
    "sg:classifiers":[
        {
            "category":"Education",
            "subcategory":"College",
            "type":"Public Place"
        }
    ],
    "sg:phone":"+1 402 472 4787",
    "sg:postcode":"68521",
    "sg:province":"NE",
    "wof:name":"University of Nebraska",
    "wof:placetype":"venue"
},
  "geometry": {"coordinates":[-96.719849,40.849444],"type":"Point"}
}