{
  "type": "Feature",
  "properties": {
    "iso:country":"US",
    "sg:address":"400 1st St",
    "sg:city":"Morse Bluff",
    "sg:classifiers":[
        {
            "category":"Freight",
            "type":"Transportation"
        }
    ],
    "sg:phone":"+1 402 666 5210",
    "sg:postcode":"68648",
    "sg:province":"NE",
    "sg:tags":[
        "hauling",
        "trucking"
    ],
    "wof:name":"Hampl Transportation",
    "wof:placetype":"venue"
},
  "geometry": {"coordinates":[-96.76674800000001,41.432469],"type":"Point"}
}