{
  "type": "Feature",
  "properties": {
    "addr:full":"1707 N 211th St Elkhorn NE 68022",
    "addr:housenumber":"1707",
    "addr:postcode":"68022",
    "addr:street":"N 211Th St",
    "iso:country":"US",
    "sg:address":"1707 N 211th St",
    "sg:city":"Elkhorn",
    "sg:classifiers":[
        {
            "category":"Professional",
            "subcategory":"Accounting & Tax Preparation",
            "type":"Services"
        }
    ],
    "sg:phone":"+1 402 289 3667",
    "sg:postcode":"68022",
    "sg:province":"NE",
    "wof:name":"Houston & Houston",
    "wof:placetype":"venue"
},
  "geometry": {"coordinates":[-96.244704,41.275863],"type":"Point"}
}