{
  "type": "Feature",
  "properties": {
    "iso:country":"US",
    "sg:address":"715 E 9th St",
    "sg:city":"South Sioux City",
    "sg:classifiers":[
        {
            "category":"Manufacturing",
            "subcategory":"Tools & Machinery",
            "type":"Manufacturing & Wholesale Goods"
        }
    ],
    "sg:phone":"+1 402 494 2530",
    "sg:postcode":"68776",
    "sg:province":"NE",
    "sg:tags":[
        "conveyor",
        "parts",
        "supply"
    ],
    "wof:name":"Gateway Engineering Inc",
    "wof:placetype":"venue"
},
  "geometry": {"coordinates":[-96.404183,42.480934],"type":"Point"}
}