{
  "type": "Feature",
  "properties": {
    "addr:full":"2417 Central Ave Nebraska City NE 68410",
    "addr:housenumber":"2417",
    "addr:postcode":"68410",
    "addr:street":"Central Ave",
    "iso:country":"US",
    "sg:address":"2417 Central Ave",
    "sg:city":"Nebraska City",
    "sg:classifiers":[
        {
            "category":"Organizations",
            "subcategory":"Religious Organization",
            "type":"Services"
        }
    ],
    "sg:phone":"+1 402 873 6217",
    "sg:postcode":"68410",
    "sg:province":"NE",
    "sg:tags":[
        "church"
    ],
    "wof:name":"Bethel United Chr - Christ",
    "wof:placetype":"venue"
},
  "geometry": {"coordinates":[-95.878181,40.676817],"type":"Point"}
}