{
  "type": "Feature",
  "properties": {
    "iso:country":"US",
    "sg:address":"4151 Harrison St",
    "sg:city":"Bellevue",
    "sg:classifiers":[
        {
            "category":"Health Services",
            "subcategory":"Doctor",
            "type":"Services"
        }
    ],
    "sg:phone":"+1 402 898 8599",
    "sg:postcode":"68147",
    "sg:province":"NE",
    "sg:tags":[
        "practice",
        "family",
        "general"
    ],
    "wof:name":"Saqueton Clinic",
    "wof:placetype":"venue"
},
  "geometry": {"coordinates":[-95.976119,41.190807],"type":"Point"}
}