{
  "type": "Feature",
  "properties": {
    "addr:full":"772 N 155th Ave Omaha NE 68154",
    "addr:housenumber":"772",
    "addr:postcode":"68154",
    "addr:street":"N 155Th Ave",
    "iso:country":"US",
    "sg:address":"772 N 155th Ave",
    "sg:city":"Omaha",
    "sg:classifiers":[
        {
            "category":"Social Services",
            "subcategory":"Child Care",
            "type":"Services"
        }
    ],
    "sg:phone":"+1 402 493 1186",
    "sg:postcode":"68154",
    "sg:province":"NE",
    "sg:tags":[
        "day"
    ],
    "wof:name":"Bobbies Day Care",
    "wof:placetype":"venue"
},
  "geometry": {"coordinates":[-96.15742299999999,41.26969],"type":"Point"}
}