{
  "type": "Feature",
  "properties": {
    "addr:full":"2008 Carmel Dr Norfolk NE 68701",
    "addr:housenumber":"2008",
    "addr:postcode":"68701",
    "addr:street":"Carmel Dr",
    "iso:country":"US",
    "sg:address":"2008 Carmel Dr",
    "sg:city":"Norfolk",
    "sg:classifiers":[
        {
            "category":"Real Estate",
            "subcategory":"Real Estate Operator",
            "type":"Services"
        }
    ],
    "sg:phone":"+1 402 371 7328",
    "sg:postcode":"68701",
    "sg:province":"NE",
    "sg:tags":[
        "property",
        "lessor"
    ],
    "wof:name":"Leonard Doffin",
    "wof:placetype":"venue"
},
  "geometry": {"coordinates":[-97.372574,42.036005],"type":"Point"}
}