{
  "type": "Feature",
  "properties": {
    "addr:full":"916 E 23rd St Fremont NE 68025",
    "addr:housenumber":"916",
    "addr:postcode":"68025",
    "addr:street":"E 23Rd St",
    "iso:country":"US",
    "sg:address":"916 E 23rd St",
    "sg:city":"Fremont",
    "sg:classifiers":[
        {
            "category":"Shopping",
            "subcategory":"Clothing, Apparel, & Fashions",
            "type":"Retail Goods"
        }
    ],
    "sg:phone":"+1 402 721 8900",
    "sg:postcode":"68025",
    "sg:province":"NE",
    "wof:name":"Schweser's",
    "wof:placetype":"venue"
},
  "geometry": {"coordinates":[-96.485202,41.451561],"type":"Point"}
}