{
  "type": "Feature",
  "properties": {
    "iso:country":"US",
    "sg:address":"11902 W Center Rd",
    "sg:city":"Omaha",
    "sg:classifiers":[
        {
            "category":"Retail",
            "subcategory":"Funeral Services",
            "type":"Services"
        }
    ],
    "sg:phone":"+1 402 333 7200",
    "sg:postcode":"68144",
    "sg:province":"NE",
    "wof:name":"SCI",
    "wof:placetype":"venue"
},
  "geometry": {"coordinates":[-96.100661,41.234105],"type":"Point"}
}