{
  "type": "Feature",
  "properties": {
    "iso:country":"US",
    "sg:address":"1172 Foothill Rd",
    "sg:city":"North Bend",
    "sg:classifiers":[
        {
            "category":"Building & Trades",
            "subcategory":"Construction",
            "type":"Services"
        }
    ],
    "sg:phone":"+1 402 652 8342",
    "sg:postcode":"68649",
    "sg:province":"NE",
    "sg:tags":[
        "water",
        "well",
        "drilling"
    ],
    "wof:name":"Dvoark Well LLC",
    "wof:placetype":"venue"
},
  "geometry": {"coordinates":[-96.69989700000001,41.535046],"type":"Point"}
}