{
  "type": "Feature",
  "properties": {
    "iso:country":"US",
    "sg:address":"200 US Hwy 20",
    "sg:city":"Gordon",
    "sg:phone":"+1 308 282 0161",
    "sg:postcode":"69343",
    "sg:province":"NE",
    "sg:tags":[
        "oil"
    ],
    "wof:name":"Hix Oil Co",
    "wof:placetype":"venue"
},
  "geometry": {"coordinates":[-102.201954,42.799884],"type":"Point"}
}