{
  "type": "Feature",
  "properties": {
    "iso:country":"US",
    "sg:address":"428 Main St",
    "sg:city":"Bridgeport",
    "sg:classifiers":[
        {
            "category":"Sports & Exercise",
            "subcategory":"Gym",
            "type":"Entertainment"
        }
    ],
    "sg:phone":"+1 308 262 1825",
    "sg:postcode":"69356",
    "sg:province":"NE",
    "sg:tags":[
        "club",
        "health",
        "studio",
        "gymnasium"
    ],
    "wof:name":"Prairie Winds Community Ctr",
    "wof:placetype":"venue"
},
  "geometry": {"coordinates":[-103.503254,41.810177],"type":"Point"}
}