{
  "type": "Feature",
  "properties": {
    "iso:country":"US",
    "sg:address":"703 Main St",
    "sg:city":"Milligan",
    "sg:classifiers":[
        {
            "category":"Organizations",
            "subcategory":"Religious Organization",
            "type":"Services"
        }
    ],
    "sg:phone":"+1 402 629 4237",
    "sg:postcode":"68406",
    "sg:province":"NE",
    "sg:tags":[
        "church"
    ],
    "wof:name":"St Wenceslaus Catholic",
    "wof:placetype":"venue"
},
  "geometry": {"coordinates":[-97.38902299999999,40.502567],"type":"Point"}
}