{
  "type": "Feature",
  "properties": {
    "iso:country":"US",
    "sg:address":"7021 S 30th Pl",
    "sg:city":"Lincoln",
    "sg:classifiers":[
        {
            "category":"Social Services",
            "subcategory":"Job Training",
            "type":"Services"
        }
    ],
    "sg:phone":"+1 402 421 7206",
    "sg:postcode":"68516",
    "sg:province":"NE",
    "sg:tags":[
        "career",
        "counseling",
        "vocational"
    ],
    "wof:name":"Career & Life Transitions",
    "wof:placetype":"venue"
},
  "geometry": {"coordinates":[-96.676006,40.740205],"type":"Point"}
}