{
  "type": "Feature",
  "properties": {
    "iso:country":"US",
    "sg:address":"208 W Main St",
    "sg:city":"Battle Creek",
    "sg:classifiers":[
        {
            "category":"Health Services",
            "subcategory":"Doctor",
            "type":"Services"
        }
    ],
    "sg:phone":"+1 402 675 3075",
    "sg:postcode":"68715",
    "sg:province":"NE",
    "sg:tags":[
        "dentist"
    ],
    "wof:name":"R M Wade DDS",
    "wof:placetype":"venue"
},
  "geometry": {"coordinates":[-97.599395,41.99956],"type":"Point"}
}