{
  "type": "Feature",
  "properties": {
    "iso:country":"US",
    "sg:address":"310 Bridge St",
    "sg:city":"Arcadia",
    "sg:classifiers":[
        {
            "category":"Building & Trades",
            "subcategory":"Construction",
            "type":"Services"
        }
    ],
    "sg:phone":"+1 308 789 6172",
    "sg:postcode":"68815",
    "sg:province":"NE",
    "sg:tags":[
        "contractor"
    ],
    "wof:name":"Sillivan Contracting",
    "wof:placetype":"venue"
},
  "geometry": {"coordinates":[-99.12131599999999,41.423338],"type":"Point"}
}