{
  "type": "Feature",
  "properties": {
    "addr:full":"15950 Wright Plz Omaha NE 68130",
    "addr:housenumber":"15950",
    "addr:postcode":"68130",
    "addr:street":"Wright",
    "iso:country":"US",
    "sg:address":"15950 Wright Plz",
    "sg:city":"Omaha",
    "sg:classifiers":[
        {
            "category":"Real Estate",
            "subcategory":"Real Estate Operator",
            "type":"Services"
        }
    ],
    "sg:phone":"+1 402 778 9090",
    "sg:postcode":"68130",
    "sg:province":"NE",
    "sg:tags":[
        "building",
        "apartment"
    ],
    "wof:name":"Breckenridge",
    "wof:placetype":"venue"
},
  "geometry": {"coordinates":[-96.161367,41.232987],"type":"Point"}
}