{
  "type": "Feature",
  "properties": {
    "iso:country":"US",
    "sg:address":"1650 9th St",
    "sg:city":"Gering",
    "sg:classifiers":[
        {
            "category":"Organizations",
            "subcategory":"Religious Organization",
            "type":"Services"
        }
    ],
    "sg:phone":"+1 308 436 4972",
    "sg:postcode":"69341",
    "sg:province":"NE",
    "sg:tags":[
        "church"
    ],
    "wof:name":"St Timothy's Episcopal Church",
    "wof:placetype":"venue"
},
  "geometry": {"coordinates":[-103.65882999999999,41.825249],"type":"Point"}
}