{
  "type": "Feature",
  "properties": {
    "addr:full":"4217 Progressive Ave Lincoln NE 68504",
    "addr:housenumber":"4217",
    "addr:postcode":"68504",
    "addr:street":"Progressive Ave",
    "iso:country":"US",
    "sg:address":"4217 Progressive Ave",
    "sg:city":"Lincoln",
    "sg:classifiers":[
        {
            "category":"Retail",
            "subcategory":"Laundry & Dry Cleaning",
            "type":"Services"
        }
    ],
    "sg:phone":"+1 402 434 8150",
    "sg:postcode":"68504",
    "sg:province":"NE",
    "sg:tags":[
        "cleaners",
        "rug",
        "carpet"
    ],
    "wof:name":"Deluxe Carpet Cleaners",
    "wof:placetype":"venue"
},
  "geometry": {"coordinates":[-96.657579,40.856884],"type":"Point"}
}