{
  "type": "Feature",
  "properties": {
    "addr:full":"15505 Warehouse St Bennington NE 68007",
    "addr:housenumber":"15505",
    "addr:postcode":"68007",
    "addr:street":"Warehouse St",
    "iso:country":"US",
    "sg:address":"15505 Warehouse St",
    "sg:city":"Bennington",
    "sg:classifiers":[
        {
            "category":"Education",
            "subcategory":"Library",
            "type":"Public Place"
        }
    ],
    "sg:phone":"+1 402 238 2201",
    "sg:postcode":"68007",
    "sg:province":"NE",
    "wof:name":"Bennington Public Library",
    "wof:placetype":"venue"
},
  "geometry": {"coordinates":[-96.15783,41.363407],"type":"Point"}
}