{
  "type": "Feature",
  "properties": {
    "iso:country":"US",
    "sg:address":"118 N Main St",
    "sg:city":"Hay Springs",
    "sg:classifiers":[
        {
            "category":"Restaurant",
            "type":"Food & Drink"
        }
    ],
    "sg:phone":"+1 308 638 7108",
    "sg:postcode":"69347",
    "sg:province":"NE",
    "wof:name":"Pheasant Run",
    "wof:placetype":"venue"
},
  "geometry": {"coordinates":[-102.690003,42.683743],"type":"Point"}
}