{
  "type": "Feature",
  "properties": {
    "iso:country":"US",
    "sg:address":"1425 H St",
    "sg:city":"Lincoln",
    "sg:classifiers":[
        {
            "category":"Recreation",
            "type":"Entertainment"
        }
    ],
    "sg:phone":"+1 402 471 3466",
    "sg:postcode":"68508",
    "sg:province":"NE",
    "sg:tags":[
        "historical"
    ],
    "wof:name":"Governor's Mansion",
    "wof:placetype":"venue"
},
  "geometry": {"coordinates":[-96.699986,40.80686],"type":"Point"}
}