{
  "type": "Feature",
  "properties": {
    "iso:country":"US",
    "sg:address":"711 Douglas Ave",
    "sg:city":"Yankton",
    "sg:classifiers":[
        {
            "category":"Education",
            "subcategory":"Special Training",
            "type":"Public Place"
        }
    ],
    "sg:phone":"+1 605 668 0531",
    "sg:postcode":"57078",
    "sg:province":"NE",
    "wof:name":"Soothing Touch Massage Therapy",
    "wof:placetype":"venue"
},
  "geometry": {"coordinates":[-97.392008,42.876233],"type":"Point"}
}