{
  "type": "Feature",
  "properties": {
    "addr:full":"621 N Lincoln Ave Hastings NE 68901",
    "addr:housenumber":"621",
    "addr:postcode":"68901",
    "addr:street":"N Lincoln Ave",
    "iso:country":"US",
    "sg:address":"621 N Lincoln Ave",
    "sg:city":"Hastings",
    "sg:classifiers":[
        {
            "category":"Education",
            "subcategory":"Library",
            "type":"Public Place"
        }
    ],
    "sg:phone":"+1 402 462 5147",
    "sg:postcode":"68901",
    "sg:province":"NE",
    "wof:name":"First Presbyterian Church",
    "wof:placetype":"venue"
},
  "geometry": {"coordinates":[-98.39114600000001,40.589592],"type":"Point"}
}