{
  "type": "Feature",
  "properties": {
    "addr:full":"208 E 5th St York NE 68467",
    "addr:housenumber":"208",
    "addr:postcode":"68467",
    "addr:street":"E 5Th St",
    "iso:country":"US",
    "sg:address":"208 E 5th St",
    "sg:city":"York",
    "sg:classifiers":[
        {
            "category":"Organizations",
            "subcategory":"Professional Association",
            "type":"Services"
        }
    ],
    "sg:phone":"+1 402 362 2477",
    "sg:postcode":"68467",
    "sg:province":"NE",
    "wof:name":"Towne House Condominium Assn",
    "wof:placetype":"venue"
},
  "geometry": {"coordinates":[-97.591741,40.86578],"type":"Point"}
}