{
  "type": "Feature",
  "properties": {
    "iso:country":"US",
    "sg:address":"50265 Panorama Dr",
    "sg:city":"Scottsbluff",
    "sg:classifiers":[
        {
            "category":"Wholesale",
            "subcategory":"Non-durable Goods",
            "type":"Manufacturing & Wholesale Goods"
        }
    ],
    "sg:phone":"+1 308 632 2643",
    "sg:postcode":"69361",
    "sg:province":"NE",
    "sg:tags":[
        "advertising"
    ],
    "wof:name":"Advertising Concepts",
    "wof:placetype":"venue"
},
  "geometry": {"coordinates":[-103.663133,41.934448],"type":"Point"}
}