{
  "type": "Feature",
  "properties": {
    "iso:country":"US",
    "sg:address":"3801 Harney St",
    "sg:city":"Omaha",
    "sg:classifiers":[
        {
            "category":"Freight",
            "type":"Transportation"
        }
    ],
    "sg:phone":"+1 402 898 1110",
    "sg:postcode":"68131",
    "sg:province":"NE",
    "sg:tags":[
        "commercial",
        "storage"
    ],
    "sg:website":"www.omahastorage.com",
    "wof:name":"OMAHASTORAGE.COM",
    "wof:placetype":"venue"
},
  "geometry": {"coordinates":[-95.970462,41.257233],"type":"Point"}
}