{
  "type": "Feature",
  "properties": {
    "iso:country":"US",
    "sg:address":"1801 S 40th St",
    "sg:city":"Lincoln",
    "sg:classifiers":[
        {
            "category":"Education",
            "subcategory":"School",
            "type":"Public Place"
        }
    ],
    "sg:phone":"+1 402 436 1308",
    "sg:postcode":"68506",
    "sg:province":"NE",
    "wof:name":"Bryan Community School",
    "wof:placetype":"venue"
},
  "geometry": {"coordinates":[-96.663357,40.794221],"type":"Point"}
}