{
  "type": "Feature",
  "properties": {
    "iso:country":"US",
    "sg:address":"7799 L St",
    "sg:city":"Omaha",
    "sg:classifiers":[
        {
            "category":"Professional",
            "subcategory":"Computer Services",
            "type":"Services"
        }
    ],
    "sg:phone":"+1 402 393 4548",
    "sg:postcode":"68127",
    "sg:province":"NE",
    "sg:tags":[
        "consultant",
        "designer",
        "related"
    ],
    "sg:website":"www.personalpc.com",
    "wof:name":"Personal PC Consultants Inc",
    "wof:placetype":"venue"
},
  "geometry": {"coordinates":[-96.036998,41.212456],"type":"Point"}
}