{
  "type": "Feature",
  "properties": {
    "iso:country":"US",
    "sg:address":"545 S 4th St",
    "sg:city":"Lincoln",
    "sg:classifiers":[
        {
            "category":"Food & Beverages",
            "subcategory":"Groceries & Convenience Stores",
            "type":"Retail Goods"
        }
    ],
    "sg:phone":"+1 402 781 2325",
    "sg:postcode":"68508",
    "sg:province":"NE",
    "sg:tags":[
        "grocer"
    ],
    "wof:name":"Lou's Eagle Grocery",
    "wof:placetype":"venue"
},
  "geometry": {"coordinates":[-96.716128,40.808648],"type":"Point"}
}