{
  "type": "Feature",
  "properties": {
    "iso:country":"US",
    "sg:address":"4710 Madison Ave",
    "sg:city":"Lincoln",
    "sg:classifiers":[
        {
            "category":"Retail",
            "subcategory":"Auto Repair",
            "type":"Services"
        }
    ],
    "sg:phone":"+1 402 466 3722",
    "sg:postcode":"68504",
    "sg:province":"NE",
    "sg:tags":[
        "repairing",
        "automobile"
    ],
    "sg:website":"www.hallmotors.com",
    "wof:name":"John Hall Motors Inc",
    "wof:placetype":"venue"
},
  "geometry": {"coordinates":[-96.65371399999999,40.840298],"type":"Point"}
}