{
  "type": "Feature",
  "properties": {
    "addr:full":"1923 Delta Dr Scottsbluff NE 69361",
    "addr:housenumber":"1923",
    "addr:postcode":"69361",
    "addr:street":"Delta Dr",
    "iso:country":"US",
    "sg:address":"1923 Delta Dr",
    "sg:city":"Scottsbluff",
    "sg:classifiers":[
        {
            "category":"Retail",
            "subcategory":"Auto Rental",
            "type":"Services"
        }
    ],
    "sg:phone":"+1 308 635 7300",
    "sg:postcode":"69361",
    "sg:province":"NE",
    "sg:tags":[
        "renting",
        "automobile"
    ],
    "wof:name":"Enterprise Rent A Car",
    "wof:placetype":"venue"
},
  "geometry": {"coordinates":[-103.63761700000001,41.866649],"type":"Point"}
}