{
  "type": "Feature",
  "properties": {
    "iso:country":"US",
    "sg:address":"847 S Broad St",
    "sg:city":"Fremont",
    "sg:classifiers":[
        {
            "category":"Retail",
            "subcategory":"Auto Repair",
            "type":"Services"
        }
    ],
    "sg:phone":"+1 402 721 6063",
    "sg:postcode":"68025",
    "sg:province":"NE",
    "sg:tags":[
        "automotive",
        "general"
    ],
    "wof:name":"South Broad Auto & Truck Repr",
    "wof:placetype":"venue"
},
  "geometry": {"coordinates":[-96.49988399999999,41.421214],"type":"Point"}
}