{
  "type": "Feature",
  "properties": {
    "iso:country":"US",
    "sg:address":"6572 Ames Ave",
    "sg:city":"Omaha",
    "sg:classifiers":[
        {
            "category":"Health Services",
            "subcategory":"Doctor",
            "type":"Services"
        }
    ],
    "sg:phone":"+1 402 453 0477",
    "sg:postcode":"68104",
    "sg:province":"NE",
    "sg:tags":[
        "clinic"
    ],
    "sg:website":"www.gambro.com",
    "wof:name":"Gambro Healthcare",
    "wof:placetype":"venue"
},
  "geometry": {"coordinates":[-96.013892,41.299601],"type":"Point"}
}