{
  "type": "Feature",
  "properties": {
    "addr:full":"1801 W N St Mc Cook NE 69001",
    "addr:housenumber":"1801",
    "addr:postcode":"69001",
    "addr:street":"W N St Mc Cook Ne",
    "iso:country":"US",
    "sg:address":"1801 W N St",
    "sg:city":"Mc Cook",
    "sg:classifiers":[
        {
            "category":"Wholesale",
            "subcategory":"Office Equipment",
            "type":"Manufacturing & Wholesale Goods"
        }
    ],
    "sg:phone":"+1 308 345 7826",
    "sg:postcode":"69001",
    "sg:province":"NE",
    "sg:tags":[
        "machine",
        "mailing"
    ],
    "sg:website":"www.midwestmailingsolutions.com",
    "wof:name":"Midwest Mailing Solutions",
    "wof:placetype":"venue"
},
  "geometry": {"coordinates":[-100.647587,40.211029],"type":"Point"}
}