{
  "type": "Feature",
  "properties": {
    "iso:country":"US",
    "sg:address":"212 10th St",
    "sg:city":"Wakefield",
    "sg:classifiers":[
        {
            "category":"Insurance",
            "subcategory":"Insurance Agent",
            "type":"Services"
        }
    ],
    "sg:phone":"+1 402 287 2784",
    "sg:postcode":"68784",
    "sg:province":"NE",
    "wof:name":"Farm Bureau Insurance",
    "wof:placetype":"venue"
},
  "geometry": {"coordinates":[-96.863343,42.261889],"type":"Point"}
}