{
  "type": "Feature",
  "properties": {
    "iso:country":"US",
    "sg:address":"1809 N 115th Plz",
    "sg:city":"Omaha",
    "sg:classifiers":[
        {
            "category":"Banks & Credit Unions",
            "subcategory":"Investment Brokerage",
            "type":"Services"
        }
    ],
    "sg:phone":"+1 402 330 6006",
    "sg:postcode":"68154",
    "sg:province":"NE",
    "sg:tags":[
        "commodity"
    ],
    "wof:name":"Switzer Trading Co",
    "wof:placetype":"venue"
},
  "geometry": {"coordinates":[-96.091613,41.275852],"type":"Point"}
}