{
  "type": "Feature",
  "properties": {
    "iso:country":"US",
    "sg:address":"1219 E 3rd St",
    "sg:city":"Alliance",
    "sg:classifiers":[
        {
            "category":"Freight",
            "type":"Transportation"
        }
    ],
    "sg:phone":"+1 308 762 1866",
    "sg:postcode":"69301",
    "sg:province":"NE",
    "sg:tags":[
        "bean",
        "elevator"
    ],
    "wof:name":"Trinidad Bean & Elevator Co",
    "wof:placetype":"venue"
},
  "geometry": {"coordinates":[-102.854308,42.09754],"type":"Point"}
}