{
  "type": "Feature",
  "properties": {
    "iso:country":"US",
    "sg:address":"1210 Logan St",
    "sg:city":"Emerson",
    "sg:classifiers":[
        {
            "category":"Home & Garden",
            "subcategory":"Hardware",
            "type":"Retail Goods"
        }
    ],
    "sg:phone":"+1 402 695 2343",
    "sg:postcode":"68733",
    "sg:province":"NE",
    "sg:tags":[
        "tool",
        "used"
    ],
    "wof:name":"Truck Tools",
    "wof:placetype":"venue"
},
  "geometry": {"coordinates":[-96.728109,42.275954],"type":"Point"}
}