{
  "type": "Feature",
  "properties": {
    "addr:full":"906 Packard Rd Arthur NE 69121",
    "addr:housenumber":"906",
    "addr:postcode":"69121",
    "addr:street":"Packard Rd",
    "iso:country":"US",
    "sg:address":"906 Packard Rd",
    "sg:city":"Arthur",
    "sg:phone":"+1 308 726 3576",
    "sg:postcode":"69121",
    "sg:province":"NE",
    "sg:tags":[
        "farm",
        "corn"
    ],
    "wof:name":"Terry Vasa",
    "wof:placetype":"venue"
},
  "geometry": {"coordinates":[-101.54732799999999,41.471897],"type":"Point"}
}