{
  "type": "Feature",
  "properties": {
    "iso:country":"US",
    "sg:address":"4260 N Broad St",
    "sg:city":"Fremont",
    "sg:classifiers":[
        {
            "category":"Autos & Motor Vehicles",
            "subcategory":"Fuel & Gas Station",
            "type":"Retail Goods"
        }
    ],
    "sg:phone":"+1 402 721 7620",
    "sg:postcode":"68025",
    "sg:province":"NE",
    "sg:tags":[
        "plaza",
        "truck",
        "stops"
    ],
    "sg:website":"www.sappbrosts.com",
    "wof:name":"Sapp Bros Truck Stops",
    "wof:placetype":"venue"
},
  "geometry": {"coordinates":[-96.49732400000001,41.465942],"type":"Point"}
}