{
  "type": "Feature",
  "properties": {
    "iso:country":"US",
    "sg:address":"213 S 15th St",
    "sg:city":"Ord",
    "sg:classifiers":[
        {
            "category":"Government",
            "subcategory":"Office",
            "type":"Public Place"
        }
    ],
    "sg:phone":"+1 308 728 3685",
    "sg:postcode":"68862",
    "sg:province":"NE",
    "sg:tags":[
        "state",
        "resource"
    ],
    "wof:name":"Social Service Dept",
    "wof:placetype":"venue"
},
  "geometry": {"coordinates":[-98.92821600000001,41.602016],"type":"Point"}
}