{
  "type": "Feature",
  "properties": {
    "addr:full":"1403 W O St Mc Cook NE 69001",
    "addr:housenumber":"1403",
    "addr:postcode":"69001",
    "addr:street":"W O St Mc Cook Ne",
    "iso:country":"US",
    "sg:address":"1403 W O St",
    "sg:city":"Mc Cook",
    "sg:classifiers":[
        {
            "category":"Building & Trades",
            "subcategory":"Construction",
            "type":"Services"
        }
    ],
    "sg:phone":"+1 308 345 6029",
    "sg:postcode":"69001",
    "sg:province":"NE",
    "sg:tags":[
        "home",
        "builder"
    ],
    "wof:name":"Mc Cook Contracting",
    "wof:placetype":"venue"
},
  "geometry": {"coordinates":[-100.643945,40.212581],"type":"Point"}
}