{
  "type": "Feature",
  "properties": {
    "iso:country":"US",
    "sg:address":"4807 Rd 117",
    "sg:city":"Gurley",
    "sg:phone":"+1 308 884 2426",
    "sg:postcode":"69141",
    "sg:province":"NE",
    "sg:tags":[
        "farm",
        "wheat"
    ],
    "wof:name":"Steve J Draper",
    "wof:placetype":"venue"
},
  "geometry": {"coordinates":[-102.934473,41.351287],"type":"Point"}
}