{
  "type": "Feature",
  "properties": {
    "iso:country":"US",
    "sg:address":"115 Broadway St",
    "sg:city":"Yankton",
    "sg:classifiers":[
        {
            "category":"Health Services",
            "subcategory":"Podiatrist",
            "type":"Services"
        }
    ],
    "sg:phone":"+1 605 665 3869",
    "sg:postcode":"57078",
    "sg:province":"NE",
    "wof:name":"Shindler Foot Clinic",
    "wof:placetype":"venue"
},
  "geometry": {"coordinates":[-97.397245,42.867719],"type":"Point"}
}