{
  "type": "Feature",
  "properties": {
    "addr:full":"101 N Pine St Norfolk NE 68701",
    "addr:housenumber":"101",
    "addr:postcode":"68701",
    "addr:street":"N Pine St",
    "iso:country":"US",
    "sg:address":"101 N Pine St",
    "sg:city":"Norfolk",
    "sg:classifiers":[
        {
            "category":"Building & Trades",
            "subcategory":"Construction",
            "type":"Services"
        }
    ],
    "sg:phone":"+1 402 644 2910",
    "sg:postcode":"68701",
    "sg:province":"NE",
    "sg:tags":[
        "paving",
        "contractor"
    ],
    "wof:name":"General Paving Co",
    "wof:placetype":"venue"
},
  "geometry": {"coordinates":[-97.40196,42.03344],"type":"Point"}
}