{
  "type": "Feature",
  "properties": {
    "addr:full":"14550 Jamestown St Waverly NE 68462",
    "addr:housenumber":"14550",
    "addr:postcode":"68462",
    "addr:street":"Jamestown St",
    "iso:country":"US",
    "sg:address":"14550 Jamestown St",
    "sg:city":"Waverly",
    "sg:classifiers":[
        {
            "category":"Farming",
            "subcategory":"Farm",
            "type":"Manufacturing & Wholesale Goods"
        }
    ],
    "sg:phone":"+1 402 786 0416",
    "sg:postcode":"68462",
    "sg:province":"NE",
    "sg:tags":[
        "crop",
        "general"
    ],
    "wof:name":"Cedar Lake Farm",
    "wof:placetype":"venue"
},
  "geometry": {"coordinates":[-96.522267,40.916692],"type":"Point"}
}