{
  "type": "Feature",
  "properties": {
    "addr:full":"10831 Old Mill Rd Omaha NE 68154",
    "addr:housenumber":"10831",
    "addr:postcode":"68154",
    "addr:street":"Old Mill Rd",
    "iso:country":"US",
    "sg:address":"10831 Old Mill Rd",
    "sg:city":"Omaha",
    "sg:classifiers":[
        {
            "category":"Health Services",
            "subcategory":"Health Practitioner",
            "type":"Services"
        }
    ],
    "sg:phone":"+1 402 505 6820",
    "sg:postcode":"68154",
    "sg:province":"NE",
    "sg:tags":[
        "nutritionist"
    ],
    "wof:name":"Wellness Insight",
    "wof:placetype":"venue"
},
  "geometry": {"coordinates":[-96.082081,41.260838],"type":"Point"}
}