{
  "type": "Feature",
  "properties": {
    "iso:country":"US",
    "sg:address":"907 Ave C",
    "sg:city":"Kearney",
    "sg:classifiers":[
        {
            "category":"Retail",
            "subcategory":"Laundry & Dry Cleaning",
            "type":"Services"
        }
    ],
    "sg:phone":"+1 308 234 2777",
    "sg:postcode":"68847",
    "sg:province":"NE",
    "sg:tags":[
        "cleaners",
        "rug",
        "carpet"
    ],
    "wof:name":"Carpet Pros",
    "wof:placetype":"venue"
},
  "geometry": {"coordinates":[-99.07790300000001,40.682727],"type":"Point"}
}