{
  "type": "Feature",
  "properties": {
    "iso:country":"US",
    "sg:address":"550 550th Ave",
    "sg:city":"Pierce",
    "sg:classifiers":[
        {
            "category":"Shopping",
            "subcategory":"Gifts & Souvenirs",
            "type":"Retail Goods"
        }
    ],
    "sg:phone":"+1 402 329 6642",
    "sg:postcode":"68767",
    "sg:province":"NE",
    "wof:name":"Home & Garden Party",
    "wof:placetype":"venue"
},
  "geometry": {"coordinates":[-97.52451499999999,42.195105],"type":"Point"}
}