{
  "type": "Feature",
  "properties": {
    "iso:country":"US",
    "sg:address":"1012 W 36th St",
    "sg:city":"Scottsbluff",
    "sg:classifiers":[
        {
            "category":"Utilities",
            "subcategory":"Mobile Phone",
            "type":"Services"
        }
    ],
    "sg:phone":"+1 308 635 1120",
    "sg:postcode":"69361",
    "sg:province":"NE",
    "sg:tags":[
        "telephone",
        "cellular"
    ],
    "wof:name":"Viaero Wireless",
    "wof:placetype":"venue"
},
  "geometry": {"coordinates":[-103.67730299999999,41.882245],"type":"Point"}
}