{
  "type": "Feature",
  "properties": {
    "iso:country":"US",
    "sg:address":"125 S 15th St",
    "sg:city":"Ord",
    "sg:classifiers":[
        {
            "category":"Education",
            "subcategory":"School",
            "type":"Public Place"
        }
    ],
    "sg:phone":"+1 308 728 5736",
    "sg:postcode":"68862",
    "sg:province":"NE",
    "wof:name":"Valley Co Schools",
    "wof:placetype":"venue"
},
  "geometry": {"coordinates":[-98.928212,41.602806],"type":"Point"}
}