{
  "type": "Feature",
  "properties": {
    "iso:country":"US",
    "sg:address":"223 S 111th St",
    "sg:city":"Omaha",
    "sg:classifiers":[
        {
            "category":"Professional",
            "subcategory":"Management & Consulting",
            "type":"Services"
        }
    ],
    "sg:phone":"+1 402 334 9020",
    "sg:postcode":"68154",
    "sg:province":"NE",
    "sg:tags":[
        "retail",
        "direct",
        "sales"
    ],
    "wof:name":"Pampered Chef Ltd",
    "wof:placetype":"venue"
},
  "geometry": {"coordinates":[-96.088526,41.257444],"type":"Point"}
}