{
  "type": "Feature",
  "properties": {
    "iso:country":"US",
    "sg:address":"705 N Jeffers St",
    "sg:city":"North Platte",
    "sg:classifiers":[
        {
            "category":"Shopping",
            "subcategory":"Discount & Variety Stores",
            "type":"Retail Goods"
        }
    ],
    "sg:phone":"+1 308 532 5135",
    "sg:postcode":"69101",
    "sg:province":"NE",
    "wof:name":"Dollar General",
    "wof:placetype":"venue"
},
  "geometry": {"coordinates":[-100.761836,41.142322],"type":"Point"}
}