{
  "type": "Feature",
  "properties": {
    "iso:country":"US",
    "sg:address":"2222 N Lincoln Ave",
    "sg:city":"York",
    "sg:classifiers":[
        {
            "category":"Health Services",
            "subcategory":"Doctor",
            "type":"Services"
        }
    ],
    "sg:phone":"+1 402 362 4339",
    "sg:postcode":"68467",
    "sg:province":"NE",
    "sg:tags":[
        "physician",
        "surgeon",
        "medical"
    ],
    "wof:name":"Daniel Growney MD",
    "wof:placetype":"venue"
},
  "geometry": {"coordinates":[-97.592975,40.882242],"type":"Point"}
}