{
  "type": "Feature",
  "properties": {
    "iso:country":"US",
    "sg:address":"7821 Sycamore Dr",
    "sg:city":"Lincoln",
    "sg:classifiers":[
        {
            "category":"Professional",
            "subcategory":"Testing Lab",
            "type":"Services"
        }
    ],
    "sg:phone":"+1 402 430 4260",
    "sg:postcode":"68506",
    "sg:province":"NE",
    "sg:tags":[
        "calibration"
    ],
    "wof:name":"Nebtech Calibration",
    "wof:placetype":"venue"
},
  "geometry": {"coordinates":[-96.611075,40.797931],"type":"Point"}
}