{
  "type": "Feature",
  "properties": {
    "iso:country":"US",
    "sg:address":"645 S Burlington Ave",
    "sg:city":"Hastings",
    "sg:classifiers":[
        {
            "category":"Building & Trades",
            "subcategory":"Construction",
            "type":"Services"
        }
    ],
    "sg:phone":"+1 402 463 7383",
    "sg:postcode":"68901",
    "sg:province":"NE",
    "sg:tags":[
        "masonry",
        "contractor"
    ],
    "wof:name":"Thomas J Miller Masonry",
    "wof:placetype":"venue"
},
  "geometry": {"coordinates":[-98.39240100000001,40.577894],"type":"Point"}
}