{
  "type": "Feature",
  "properties": {
    "addr:full":"1715 N Sycamore St Wahoo NE 68066",
    "addr:housenumber":"1715",
    "addr:postcode":"68066",
    "addr:street":"N Sycamore St",
    "iso:country":"US",
    "sg:address":"1715 N Sycamore St",
    "sg:city":"Wahoo",
    "sg:classifiers":[
        {
            "category":"Building & Trades",
            "subcategory":"Construction",
            "type":"Services"
        }
    ],
    "sg:phone":"+1 402 443 1380",
    "sg:postcode":"68066",
    "sg:province":"NE",
    "sg:tags":[
        "house"
    ],
    "wof:name":"Tim Maly Construction LLC",
    "wof:placetype":"venue"
},
  "geometry": {"coordinates":[-96.62422100000001,41.222771],"type":"Point"}
}