{
  "type": "Feature",
  "properties": {
    "addr:full":"7955 Rd 8 Potter NE 69156",
    "addr:housenumber":"7955",
    "addr:postcode":"69156",
    "addr:street":"Rd 8 Potter Ne",
    "iso:country":"US",
    "sg:address":"7955 Rd 8",
    "sg:city":"Potter",
    "sg:classifiers":[
        {
            "category":"Farming",
            "subcategory":"Livestock Farm",
            "type":"Manufacturing & Wholesale Goods"
        }
    ],
    "sg:phone":"+1 308 879 4590",
    "sg:postcode":"69156",
    "sg:province":"NE",
    "sg:tags":[
        "beef",
        "feedlot",
        "cattle"
    ],
    "wof:name":"Wilfred Nelson",
    "wof:placetype":"venue"
},
  "geometry": {"coordinates":[-103.298486,41.047531],"type":"Point"}
}