{
  "type": "Feature",
  "properties": {
    "iso:country":"US",
    "sg:address":"256 N Main St",
    "sg:city":"Hay Springs",
    "sg:classifiers":[
        {
            "category":"Organizations",
            "subcategory":"Community Association",
            "type":"Services"
        }
    ],
    "sg:phone":"+1 308 638 7135",
    "sg:postcode":"69347",
    "sg:province":"NE",
    "sg:tags":[
        "fraternal"
    ],
    "wof:name":"Masonic Lodge",
    "wof:placetype":"venue"
},
  "geometry": {"coordinates":[-102.689995,42.684839],"type":"Point"}
}