{
  "type": "Feature",
  "properties": {
    "iso:country":"US",
    "sg:address":"10605 Mill Rd",
    "sg:city":"Louisville",
    "sg:classifiers":[
        {
            "category":"Shopping",
            "subcategory":"Clothing, Apparel, & Fashions",
            "type":"Retail Goods"
        }
    ],
    "sg:phone":"+1 402 267 7305",
    "sg:postcode":"68037",
    "sg:province":"NE",
    "wof:name":"Bimms Inc",
    "wof:placetype":"venue"
},
  "geometry": {"coordinates":[-96.079802,40.943695],"type":"Point"}
}