{
  "type": "Feature",
  "properties": {
    "iso:country":"US",
    "sg:address":"824 4th Ave",
    "sg:city":"Holdrege",
    "sg:classifiers":[
        {
            "category":"Food & Beverages",
            "subcategory":"Groceries & Convenience Stores",
            "type":"Retail Goods"
        }
    ],
    "sg:phone":"+1 308 995 5202",
    "sg:postcode":"68949",
    "sg:province":"NE",
    "wof:name":"Gas 'n Shop",
    "wof:placetype":"venue"
},
  "geometry": {"coordinates":[-99.369621,40.437881],"type":"Point"}
}