{
  "type": "Feature",
  "properties": {
    "iso:country":"US",
    "sg:address":"401 Park St",
    "sg:city":"Tilden",
    "sg:classifiers":[
        {
            "category":"Health Services",
            "subcategory":"Nursing And Care Facility",
            "type":"Services"
        }
    ],
    "sg:phone":"+1 402 368 5335",
    "sg:postcode":"68747",
    "sg:province":"NE",
    "sg:tags":[
        "home",
        "convalescent"
    ],
    "wof:name":"Beverly Healthcare",
    "wof:placetype":"venue"
},
  "geometry": {"coordinates":[-97.471543,42.453918],"type":"Point"}
}