{
  "type": "Feature",
  "properties": {
    "addr:full":"53757 State Hwy 59 Creighton NE 68729",
    "addr:housenumber":"53757",
    "addr:postcode":"68729",
    "addr:street":"State Hwy 59",
    "iso:country":"US",
    "sg:address":"53757 State Hwy 59",
    "sg:city":"Creighton",
    "sg:classifiers":[
        {
            "category":"Farming",
            "subcategory":"Livestock Farm",
            "type":"Manufacturing & Wholesale Goods"
        }
    ],
    "sg:phone":"+1 402 358 5563",
    "sg:postcode":"68729",
    "sg:province":"NE",
    "sg:tags":[
        "feedlot",
        "hog",
        "or",
        "beef",
        "cattle"
    ],
    "wof:name":"Frisch Farms",
    "wof:placetype":"venue"
},
  "geometry": {"coordinates":[-97.761769,42.466955],"type":"Point"}
}