{
  "type": "Feature",
  "properties": {
    "iso:country":"US",
    "sg:address":"1135 Co Rd 10",
    "sg:city":"Mead",
    "sg:classifiers":[
        {
            "category":"Education",
            "subcategory":"College",
            "type":"Public Place"
        }
    ],
    "sg:phone":"+1 402 624 8068",
    "sg:postcode":"68041",
    "sg:province":"NE",
    "sg:tags":[
        "academic",
        "school"
    ],
    "wof:name":"University Of Nebraska Dairy",
    "wof:placetype":"venue"
},
  "geometry": {"coordinates":[-96.48290799999999,41.163676],"type":"Point"}
}