{
  "type": "Feature",
  "properties": {
    "iso:country":"US",
    "sg:address":"2309 Hanscom Blvd",
    "sg:city":"Omaha",
    "sg:classifiers":[
        {
            "category":"Cinema",
            "subcategory":"Movie Theater",
            "type":"Entertainment"
        }
    ],
    "sg:phone":"+1 402 932 3821",
    "sg:postcode":"68105",
    "sg:province":"NE",
    "sg:tags":[
        "live"
    ],
    "wof:name":"Omaha Magic Theatre Inc",
    "wof:placetype":"venue"
},
  "geometry": {"coordinates":[-95.958955,41.236651],"type":"Point"}
}