{
  "type": "Feature",
  "properties": {
    "addr:full":"7325 Pinkney St Omaha NE 68134",
    "addr:housenumber":"7325",
    "addr:postcode":"68134",
    "addr:street":"Pinkney St",
    "iso:country":"US",
    "sg:address":"7325 Pinkney St",
    "sg:city":"Omaha",
    "sg:classifiers":[
        {
            "category":"Building & Trades",
            "subcategory":"Construction",
            "type":"Services"
        }
    ],
    "sg:phone":"+1 402 397 9618",
    "sg:postcode":"68134",
    "sg:province":"NE",
    "sg:tags":[
        "house",
        "construct",
        "contractor"
    ],
    "wof:name":"Lanes Construction",
    "wof:placetype":"venue"
},
  "geometry": {"coordinates":[-96.02848899999999,41.290423],"type":"Point"}
}