{
  "type": "Feature",
  "properties": {
    "addr:full":"307 E Norfolk Ave Norfolk NE 68701",
    "addr:housenumber":"307",
    "addr:postcode":"68701",
    "addr:street":"E Norfolk Ave",
    "iso:country":"US",
    "sg:address":"307 E Norfolk Ave",
    "sg:city":"Norfolk",
    "sg:classifiers":[
        {
            "category":"Autos & Motor Vehicles",
            "subcategory":"Automobile Sales",
            "type":"Retail Goods"
        }
    ],
    "sg:phone":"+1 402 371 3002",
    "sg:postcode":"68701",
    "sg:province":"NE",
    "sg:tags":[
        "new",
        "used",
        "dealer",
        "car"
    ],
    "wof:name":"Imports",
    "wof:placetype":"venue"
},
  "geometry": {"coordinates":[-97.40348,42.032857],"type":"Point"}
}