{
  "type": "Feature",
  "properties": {
    "addr:full":"3455 S 66th St Omaha NE 68106",
    "addr:housenumber":"3455",
    "addr:postcode":"68106",
    "addr:street":"S 66Th St",
    "iso:country":"US",
    "sg:address":"3455 S 66th St",
    "sg:city":"Omaha",
    "sg:classifiers":[
        {
            "category":"Building & Trades",
            "subcategory":"Construction",
            "type":"Services"
        }
    ],
    "sg:phone":"+1 402 393 8803",
    "sg:postcode":"68106",
    "sg:province":"NE",
    "sg:tags":[
        "waterproofing",
        "contractor"
    ],
    "wof:name":"Thrasher Basement Systems Inc",
    "wof:placetype":"venue"
},
  "geometry": {"coordinates":[-96.014259,41.226357],"type":"Point"}
}