{
  "type": "Feature",
  "properties": {
    "addr:full":"4535 Normal Blvd Ste 158 Lincoln NE 68506",
    "addr:housenumber":"4535",
    "addr:postcode":"68506",
    "addr:street":"Normal Blvd Ste 158",
    "iso:country":"US",
    "sg:address":"4535 Normal Blvd Ste 158",
    "sg:city":"Lincoln",
    "sg:classifiers":[
        {
            "category":"Health Services",
            "subcategory":"Doctor",
            "type":"Services"
        },
        {
            "category":"Health Services",
            "subcategory":"Health Practitioner",
            "type":"Services"
        }
    ],
    "sg:phone":"+1 402 483 4770",
    "sg:postcode":"68506",
    "sg:province":"NE",
    "sg:tags":[
        "control",
        "physician",
        "management",
        "weight",
        "loss",
        "surgeons",
        "nutritionist",
        "reducing"
    ],
    "sg:website":"http://www.nebraskaweightmanagement.com",
    "wof:name":"Nebraska Weight Management Institute",
    "wof:placetype":"venue"
},
  "geometry": {"coordinates":[-96.656981,40.789071],"type":"Point"}
}