{
  "type": "Feature",
  "properties": {
    "iso:country":"US",
    "sg:address":"3912 J St",
    "sg:city":"Lincoln",
    "sg:classifiers":[
        {
            "category":"Building & Trades",
            "subcategory":"Construction",
            "type":"Services"
        }
    ],
    "sg:phone":"+1 402 430 8095",
    "sg:postcode":"68510",
    "sg:province":"NE",
    "sg:tags":[
        "contractor"
    ],
    "wof:name":"MIE Builders",
    "wof:placetype":"venue"
},
  "geometry": {"coordinates":[-96.663371,40.80809],"type":"Point"}
}