{
  "type": "Feature",
  "properties": {
    "iso:country":"US",
    "sg:address":"1941 Vinton St",
    "sg:city":"Omaha",
    "sg:classifiers":[
        {
            "category":"Banks & Credit Unions",
            "subcategory":"Bank",
            "type":"Services"
        }
    ],
    "sg:phone":"+1 402 342 3654",
    "sg:postcode":"68108",
    "sg:province":"NE",
    "sg:tags":[
        "broker",
        "foreign",
        "dealer",
        "exchange"
    ],
    "wof:name":"Associated Foreign Exchange",
    "wof:placetype":"venue"
},
  "geometry": {"coordinates":[-95.941976,41.231024],"type":"Point"}
}