{
  "type": "Feature",
  "properties": {
    "addr:full":"506 W S St Mc Cook NE 69001",
    "addr:housenumber":"506",
    "addr:postcode":"69001",
    "addr:street":"W S St Mc",
    "iso:country":"US",
    "sg:address":"506 W S St",
    "sg:city":"Mc Cook",
    "sg:classifiers":[
        {
            "category":"Mining & Drilling",
            "type":"Manufacturing & Wholesale Goods"
        }
    ],
    "sg:phone":"+1 308 345 1756",
    "sg:postcode":"69001",
    "sg:province":"NE",
    "sg:tags":[
        "field"
    ],
    "wof:name":"Cheney Testing Company Inc",
    "wof:placetype":"venue"
},
  "geometry": {"coordinates":[-100.629898,40.215331],"type":"Point"}
}