{
  "type": "Feature",
  "properties": {
    "iso:country":"US",
    "sg:address":"134 N 36th St",
    "sg:city":"Omaha",
    "sg:classifiers":[
        {
            "category":"Professional",
            "subcategory":"Accounting & Tax Preparation",
            "type":"Services"
        }
    ],
    "sg:phone":"+1 402 346 1212",
    "sg:postcode":"68131",
    "sg:province":"NE",
    "sg:tags":[
        "accountant"
    ],
    "wof:name":"Vetick Gary CPA",
    "wof:placetype":"venue"
},
  "geometry": {"coordinates":[-95.966499,41.260201],"type":"Point"}
}