{
  "type": "Feature",
  "properties": {
    "iso:country":"US",
    "sg:address":"215 W J St",
    "sg:city":"Hastings",
    "sg:classifiers":[
        {
            "category":"Manufacturing",
            "subcategory":"Tools & Machinery",
            "type":"Manufacturing & Wholesale Goods"
        }
    ],
    "sg:phone":"+1 402 463 8688",
    "sg:postcode":"68901",
    "sg:province":"NE",
    "sg:tags":[
        "shop",
        "die",
        "job",
        "maker",
        "dye"
    ],
    "wof:name":"Drake Tool and Design Inc",
    "wof:placetype":"venue"
},
  "geometry": {"coordinates":[-98.384108,40.567922],"type":"Point"}
}