{
  "type": "Feature",
  "properties": {
    "addr:full":"130 Front St Weston NE 68070",
    "addr:housenumber":"130",
    "addr:postcode":"68070",
    "addr:street":"Front St",
    "iso:country":"US",
    "sg:address":"130 Front St",
    "sg:city":"Weston",
    "sg:classifiers":[
        {
            "category":"Education",
            "subcategory":"School",
            "type":"Public Place"
        }
    ],
    "sg:phone":"+1 402 642 5234",
    "sg:postcode":"68070",
    "sg:province":"NE",
    "wof:name":"St John Elementary School",
    "wof:placetype":"venue"
},
  "geometry": {"coordinates":[-96.740951,41.191514],"type":"Point"}
}