{
  "type": "Feature",
  "properties": {
    "iso:country":"US",
    "sg:address":"8434 Park Dr",
    "sg:city":"Omaha",
    "sg:classifiers":[
        {
            "category":"Shopping",
            "subcategory":"Clothing, Apparel, & Fashions",
            "type":"Retail Goods"
        }
    ],
    "sg:phone":"+1 402 502 0099",
    "sg:postcode":"68127",
    "sg:province":"NE",
    "sg:tags":[
        "shop",
        "bridal"
    ],
    "wof:name":"Bridal Details Inc",
    "wof:placetype":"venue"
},
  "geometry": {"coordinates":[-96.04370900000001,41.200878],"type":"Point"}
}