{
  "type": "Feature",
  "properties": {
    "addr:full":"650 J St Lincoln NE 68508",
    "addr:housenumber":"650",
    "addr:postcode":"68508",
    "addr:street":"J St",
    "iso:country":"US",
    "sg:address":"650 J St",
    "sg:city":"Lincoln",
    "sg:classifiers":[
        {
            "category":"Wholesale",
            "subcategory":"Farm Supplies",
            "type":"Manufacturing & Wholesale Goods"
        }
    ],
    "sg:phone":"+1 402 476 3404",
    "sg:postcode":"68508",
    "sg:province":"NE",
    "sg:tags":[
        "import",
        "export",
        "livestock"
    ],
    "wof:name":"America China Agriculture Assn",
    "wof:placetype":"venue"
},
  "geometry": {"coordinates":[-96.712052,40.808169],"type":"Point"}
}