{
  "type": "Feature",
  "properties": {
    "addr:full":"114 E 10th St Bridgeport NE 69336",
    "addr:housenumber":"114",
    "addr:postcode":"69336",
    "addr:street":"E 10Th St",
    "iso:country":"US",
    "sg:address":"114 E 10th St",
    "sg:city":"Bridgeport",
    "sg:classifiers":[
        {
            "category":"Government",
            "subcategory":"Post Office",
            "type":"Public Place"
        }
    ],
    "sg:phone":"+1 308 262 0468",
    "sg:postcode":"69336",
    "sg:province":"NE",
    "wof:name":"US Post Office",
    "wof:placetype":"venue"
},
  "geometry": {"coordinates":[-103.09899,41.665252],"type":"Point"}
}