{
  "type": "Feature",
  "properties": {
    "iso:country":"US",
    "sg:address":"113 N Woodward St",
    "sg:city":"Ainsworth",
    "sg:classifiers":[
        {
            "category":"Professional",
            "type":"Services"
        }
    ],
    "sg:phone":"+1 402 387 2872",
    "sg:postcode":"69210",
    "sg:province":"NE",
    "sg:tags":[
        "establishment"
    ],
    "wof:name":"Nebraska Public Power District",
    "wof:placetype":"venue"
},
  "geometry": {"coordinates":[-99.863902,42.546696],"type":"Point"}
}