{
  "type": "Feature",
  "properties": {
    "iso:country":"US",
    "sg:address":"808 R St",
    "sg:city":"Humboldt",
    "sg:classifiers":[
        {
            "category":"Freight",
            "type":"Transportation"
        }
    ],
    "sg:phone":"+1 402 862 2932",
    "sg:postcode":"68361",
    "sg:province":"NE",
    "sg:tags":[
        "grain",
        "elevator"
    ],
    "wof:name":"Wilhelm Grain Inc",
    "wof:placetype":"venue"
},
  "geometry": {"coordinates":[-97.604849,40.538778],"type":"Point"}
}