{
  "type": "Feature",
  "properties": {
    "iso:country":"US",
    "sg:address":"2104 Park St",
    "sg:city":"Blair",
    "sg:classifiers":[
        {
            "category":"Social Services",
            "subcategory":"Child Care",
            "type":"Services"
        }
    ],
    "sg:phone":"+1 402 426 1732",
    "sg:postcode":"68008",
    "sg:province":"NE",
    "sg:tags":[
        "day"
    ],
    "wof:name":"Debra Woolman",
    "wof:placetype":"venue"
},
  "geometry": {"coordinates":[-96.144296,41.548054],"type":"Point"}
}