{
  "type": "Feature",
  "properties": {
    "addr:full":"1909 Campanile Rd Waterloo NE 68069",
    "addr:housenumber":"1909",
    "addr:postcode":"68069",
    "addr:street":"Campanile Rd",
    "iso:country":"US",
    "sg:address":"1909 Campanile Rd",
    "sg:city":"Waterloo",
    "sg:classifiers":[
        {
            "category":"Professional",
            "subcategory":"Business Services",
            "type":"Services"
        }
    ],
    "sg:phone":"+1 402 359 9170",
    "sg:postcode":"68069",
    "sg:province":"NE",
    "sg:tags":[
        "motion",
        "picture"
    ],
    "wof:name":"Innerviews Corporation",
    "wof:placetype":"venue"
},
  "geometry": {"coordinates":[-96.35210600000001,41.244149],"type":"Point"}
}