{
  "type": "Feature",
  "properties": {
    "iso:country":"US",
    "sg:address":"454 N Bloom St",
    "sg:city":"Superior",
    "sg:classifiers":[
        {
            "category":"Professional",
            "subcategory":"Accounting & Tax Preparation",
            "type":"Services"
        }
    ],
    "sg:phone":"+1 402 879 4764",
    "sg:postcode":"68978",
    "sg:province":"NE",
    "sg:tags":[
        "return",
        "filing"
    ],
    "wof:name":"M & R Bookkeeping & Tax Svc",
    "wof:placetype":"venue"
},
  "geometry": {"coordinates":[-98.06657,40.020368],"type":"Point"}
}