{
  "type": "Feature",
  "properties": {
    "iso:country":"US",
    "sg:address":"15111 T Cir",
    "sg:city":"Omaha",
    "sg:classifiers":[
        {
            "category":"Shopping",
            "subcategory":"Clothing, Apparel, & Fashions",
            "type":"Retail Goods"
        }
    ],
    "sg:phone":"+1 402 896 9332",
    "sg:postcode":"68137",
    "sg:province":"NE",
    "wof:name":"Delta Uniform Inc",
    "wof:placetype":"venue"
},
  "geometry": {"coordinates":[-96.150637,41.202945],"type":"Point"}
}