{
  "type": "Feature",
  "properties": {
    "iso:country":"US",
    "sg:address":"12120 Shamrock Plz",
    "sg:city":"Omaha",
    "sg:classifiers":[
        {
            "category":"Professional",
            "subcategory":"Lawyer & Legal Services",
            "type":"Services"
        }
    ],
    "sg:phone":"+1 402 331 4600",
    "sg:postcode":"68154",
    "sg:province":"NE",
    "wof:name":"Liberty Mutal Insurance",
    "wof:placetype":"venue"
},
  "geometry": {"coordinates":[-96.10191399999999,41.249489],"type":"Point"}
}