{
  "type": "Feature",
  "properties": {
    "iso:country":"US",
    "sg:address":"190367 Co Rd H",
    "sg:city":"Scottsbluff",
    "sg:classifiers":[
        {
            "category":"Professional",
            "type":"Services"
        }
    ],
    "sg:phone":"+1 308 632 3746",
    "sg:postcode":"69361",
    "sg:province":"NE",
    "wof:name":"Gwen & Orin Yung",
    "wof:placetype":"venue"
},
  "geometry": {"coordinates":[-103.707599,41.902448],"type":"Point"}
}