{
  "type": "Feature",
  "properties": {
    "iso:country":"US",
    "sg:address":"2810 SW 6th St",
    "sg:city":"Lincoln",
    "sg:classifiers":[
        {
            "category":"Building & Trades",
            "subcategory":"Construction",
            "type":"Services"
        }
    ],
    "sg:phone":"+1 402 438 4422",
    "sg:postcode":"68522",
    "sg:province":"NE",
    "sg:tags":[
        "operator",
        "contractor",
        "local",
        "trucking"
    ],
    "wof:name":"Mail Contractors Of America",
    "wof:placetype":"venue"
},
  "geometry": {"coordinates":[-96.728353,40.781785],"type":"Point"}
}