{
  "type": "Feature",
  "properties": {
    "iso:country":"US",
    "sg:address":"901 N 24th St",
    "sg:city":"Omaha",
    "sg:classifiers":[
        {
            "category":"Restaurant",
            "type":"Food & Drink"
        }
    ],
    "sg:menulink":"http://www.allmenus.com/ne/omaha/129568-subway/menu/",
    "sg:phone":"+1 402 345 7808",
    "sg:postcode":"68102",
    "sg:province":"NE",
    "sg:tags":[
        "american",
        "sandwich"
    ],
    "wof:name":"Subway",
    "wof:placetype":"venue"
},
  "geometry": {"coordinates":[-95.94676200000001,41.268291],"type":"Point"}
}