{
  "type": "Feature",
  "properties": {
    "addr:full":"825 W 21st St South Sioux City NE 68776",
    "addr:housenumber":"825",
    "addr:postcode":"68776",
    "addr:street":"W 21St St",
    "iso:country":"US",
    "sg:address":"825 W 21st St",
    "sg:city":"South Sioux City",
    "sg:classifiers":[
        {
            "category":"Retail",
            "subcategory":"Auto Repair",
            "type":"Services"
        }
    ],
    "sg:phone":"+1 402 494 6669",
    "sg:postcode":"68776",
    "sg:province":"NE",
    "sg:tags":[
        "general"
    ],
    "wof:name":"Grandsons Auto & Repair",
    "wof:placetype":"venue"
},
  "geometry": {"coordinates":[-96.423046,42.470009],"type":"Point"}
}