{
  "type": "Feature",
  "properties": {
    "iso:country":"US",
    "sg:address":"1415 Sage St",
    "sg:city":"Gering",
    "sg:classifiers":[
        {
            "category":"Health Services",
            "subcategory":"Doctor",
            "type":"Services"
        }
    ],
    "sg:phone":"+1 308 436 3491",
    "sg:postcode":"69341",
    "sg:province":"NE",
    "sg:tags":[
        "dentist"
    ],
    "sg:website":"www.dentalgentlecare.com",
    "wof:name":"Family Gentle Dental Care",
    "wof:placetype":"venue"
},
  "geometry": {"coordinates":[-103.66701399999999,41.820608],"type":"Point"}
}