{
  "type": "Feature",
  "properties": {
    "iso:country":"US",
    "sg:address":"1309 Rd 19",
    "sg:city":"York",
    "sg:classifiers":[
        {
            "category":"Farming",
            "subcategory":"Livestock Farm",
            "type":"Manufacturing & Wholesale Goods"
        }
    ],
    "sg:phone":"+1 402 362 6626",
    "sg:postcode":"68467",
    "sg:province":"NE",
    "sg:tags":[
        "ranch"
    ],
    "wof:name":"Southranch",
    "wof:placetype":"venue"
},
  "geometry": {"coordinates":[-97.59747,40.959113],"type":"Point"}
}