{
  "type": "Feature",
  "properties": {
    "iso:country":"US",
    "sg:address":"601 Howard Ave",
    "sg:city":"St Paul",
    "sg:classifiers":[
        {
            "category":"Personal",
            "subcategory":"Beauty Salon",
            "type":"Services"
        }
    ],
    "sg:phone":"+1 308 754 4045",
    "sg:postcode":"68873",
    "sg:province":"NE",
    "wof:name":"Total Perfection Full Svc Sln",
    "wof:placetype":"venue"
},
  "geometry": {"coordinates":[-98.45809800000001,41.213381],"type":"Point"}
}