{
  "type": "Feature",
  "properties": {
    "iso:country":"US",
    "sg:address":"2820 N 90th St",
    "sg:city":"Omaha",
    "sg:classifiers":[
        {
            "category":"Shopping",
            "subcategory":"Gifts & Souvenirs",
            "type":"Retail Goods"
        }
    ],
    "sg:phone":"+1 402 393 2733",
    "sg:postcode":"68134",
    "sg:province":"NE",
    "sg:tags":[
        "shop"
    ],
    "wof:name":"Westlake Hallmark Shop",
    "wof:placetype":"venue"
},
  "geometry": {"coordinates":[-96.052688,41.283843],"type":"Point"}
}