{
  "type": "Feature",
  "properties": {
    "addr:full":"4205 S 33rd St Lincoln NE 68506",
    "addr:housenumber":"4205",
    "addr:postcode":"68506",
    "addr:street":"S 33Rd St",
    "iso:country":"US",
    "sg:address":"4205 S 33rd St",
    "sg:city":"Lincoln",
    "sg:classifiers":[
        {
            "category":"Personal",
            "subcategory":"Beauty Salon",
            "type":"Services"
        }
    ],
    "sg:phone":"+1 402 489 8282",
    "sg:postcode":"68506",
    "sg:province":"NE",
    "wof:name":"Hana's Salon",
    "wof:placetype":"venue"
},
  "geometry": {"coordinates":[-96.67294800000001,40.768849],"type":"Point"}
}