{
  "type": "Feature",
  "properties": {
    "iso:country":"US",
    "sg:address":"405 N Broad St",
    "sg:city":"Fremont",
    "sg:classifiers":[
        {
            "category":"Autos & Motor Vehicles",
            "subcategory":"Auto Supplies",
            "type":"Retail Goods"
        },
        {
            "category":"Retail",
            "subcategory":"Auto Repair",
            "type":"Services"
        }
    ],
    "sg:phone":"+1 402 727 7700",
    "sg:postcode":"68025",
    "sg:province":"NE",
    "sg:tags":[
        "tire",
        "general"
    ],
    "wof:name":"Team Tires Plus",
    "wof:placetype":"venue"
},
  "geometry": {"coordinates":[-96.498795,41.433872],"type":"Point"}
}