{
  "type": "Feature",
  "properties": {
    "iso:country":"US",
    "sg:address":"2000 N 76th St",
    "sg:city":"Lincoln",
    "sg:classifiers":[
        {
            "category":"Building & Trades",
            "subcategory":"Plumbing",
            "type":"Services"
        }
    ],
    "sg:phone":"+1 402 464 4120",
    "sg:postcode":"68505",
    "sg:province":"NE",
    "sg:tags":[
        "contractor"
    ],
    "wof:name":"Murkle Plumbing",
    "wof:placetype":"venue"
},
  "geometry": {"coordinates":[-96.61775299999999,40.832478],"type":"Point"}
}