{
  "type": "Feature",
  "properties": {
    "addr:full":"1916 W 11th Ave Grand Island NE 68803",
    "addr:housenumber":"1916",
    "addr:postcode":"68803",
    "addr:street":"W 11Th Ave",
    "iso:country":"US",
    "sg:address":"1916 W 11th Ave",
    "sg:city":"Grand Island",
    "sg:classifiers":[
        {
            "category":"Manufacturing",
            "subcategory":"Building Materials",
            "type":"Manufacturing & Wholesale Goods"
        }
    ],
    "sg:phone":"+1 308 384 7393",
    "sg:postcode":"68803",
    "sg:province":"NE",
    "sg:tags":[
        "mfg",
        "wood",
        "kitchen",
        "cabinet"
    ],
    "wof:name":"CM Custom Cabinets",
    "wof:placetype":"venue"
},
  "geometry": {"coordinates":[-98.362016,40.929771],"type":"Point"}
}