{
  "type": "Feature",
  "properties": {
    "iso:country":"US",
    "sg:address":"3001 Dodge St",
    "sg:city":"Omaha",
    "sg:phone":"+1 402 342 3301",
    "sg:postcode":"68131",
    "sg:province":"NE",
    "sg:website":"http://www.walgreens.com/default.jsp?ec=iyp_yellowpages_trademark",
    "wof:name":"Walgreens Pharmacies",
    "wof:placetype":"venue"
},
  "geometry": {"coordinates":[-95.95657300000001,41.25972],"type":"Point"}
}