{
  "type": "Feature",
  "properties": {
    "iso:country":"US",
    "sg:address":"507 Hastings Ave",
    "sg:city":"Norfolk",
    "sg:classifiers":[
        {
            "category":"Shopping",
            "subcategory":"Computers & Home Electronics",
            "type":"Retail Goods"
        }
    ],
    "sg:phone":"+1 402 371 6394",
    "sg:postcode":"68701",
    "sg:province":"NE",
    "sg:tags":[
        "equipment",
        "satellite",
        "system"
    ],
    "wof:name":"Nick's TV & Small Appliance",
    "wof:placetype":"venue"
},
  "geometry": {"coordinates":[-97.415863,42.01635],"type":"Point"}
}