{
  "type": "Feature",
  "properties": {
    "iso:country":"US",
    "sg:address":"4501 S 36th St",
    "sg:city":"Omaha",
    "sg:classifiers":[
        {
            "category":"Food & Beverages",
            "subcategory":"Meat & Fish",
            "type":"Retail Goods"
        }
    ],
    "sg:phone":"+1 402 734 6901",
    "sg:postcode":"68107",
    "sg:province":"NE",
    "sg:tags":[
        "shop"
    ],
    "wof:name":"All American Meat Inc",
    "wof:placetype":"venue"
},
  "geometry": {"coordinates":[-95.966202,41.214401],"type":"Point"}
}