{
  "type": "Feature",
  "properties": {
    "addr:full":"1302 Ave F Gothenburg NE 69138",
    "addr:housenumber":"1302",
    "addr:postcode":"69138",
    "addr:street":"Ave F",
    "iso:country":"US",
    "sg:address":"1302 Ave F",
    "sg:city":"Gothenburg",
    "sg:classifiers":[
        {
            "category":"Real Estate",
            "subcategory":"Real Estate Operator",
            "type":"Services"
        }
    ],
    "sg:phone":"+1 308 537 2081",
    "sg:postcode":"69138",
    "sg:province":"NE",
    "sg:tags":[
        "property",
        "lessor"
    ],
    "wof:name":"Leonard Widholm",
    "wof:placetype":"venue"
},
  "geometry": {"coordinates":[-100.158748,40.932001],"type":"Point"}
}