{
  "type": "Feature",
  "properties": {
    "iso:country":"US",
    "sg:address":"7010 S 108th St",
    "sg:city":"La Vista",
    "sg:classifiers":[
        {
            "category":"Wholesale",
            "subcategory":"Machinery & Supplies",
            "type":"Manufacturing & Wholesale Goods"
        }
    ],
    "sg:phone":"+1 402 331 5540",
    "sg:postcode":"68128",
    "sg:province":"NE",
    "sg:tags":[
        "equipment",
        "industrial"
    ],
    "sg:website":"www.mscdirect.com",
    "wof:name":"MSC Industrial Supply Co",
    "wof:placetype":"venue"
},
  "geometry": {"coordinates":[-96.081481,41.190629],"type":"Point"}
}