{
  "type": "Feature",
  "properties": {
    "iso:country":"US",
    "sg:address":"624 Depot St E",
    "sg:city":"Dannebrog",
    "sg:phone":"+1 308 226 8244",
    "sg:postcode":"68831",
    "sg:province":"NE",
    "sg:tags":[
        "farm",
        "corn"
    ],
    "wof:name":"Casperson Farms",
    "wof:placetype":"venue"
},
  "geometry": {"coordinates":[-98.540409,41.116516],"type":"Point"}
}