{
  "type": "Feature",
  "properties": {
    "iso:country":"US",
    "sg:address":"2250 S 60th St",
    "sg:city":"Lincoln",
    "sg:classifiers":[
        {
            "category":"Building & Trades",
            "subcategory":"Construction",
            "type":"Services"
        }
    ],
    "sg:phone":"+1 402 483 4698",
    "sg:postcode":"68506",
    "sg:province":"NE",
    "sg:tags":[
        "excavation",
        "contractor"
    ],
    "wof:name":"TEC",
    "wof:placetype":"venue"
},
  "geometry": {"coordinates":[-96.638126,40.789834],"type":"Point"}
}