{
  "type": "Feature",
  "properties": {
    "addr:full":"1005 1st St Crawford NE 69339",
    "addr:housenumber":"1005",
    "addr:postcode":"69339",
    "addr:street":"1St St",
    "iso:country":"US",
    "sg:address":"1005 1st St",
    "sg:city":"Crawford",
    "sg:classifiers":[
        {
            "category":"Recreation",
            "type":"Entertainment"
        }
    ],
    "sg:phone":"+1 308 665 9915",
    "sg:postcode":"69339",
    "sg:province":"NE",
    "sg:tags":[
        "hall",
        "auditorium"
    ],
    "wof:name":"Crawford Community Building",
    "wof:placetype":"venue"
},
  "geometry": {"coordinates":[-103.416284,42.679858],"type":"Point"}
}