{
  "type": "Feature",
  "properties": {
    "iso:country":"US",
    "sg:address":"1713 Crawford Rd",
    "sg:city":"Omaha",
    "sg:classifiers":[
        {
            "category":"Professional",
            "type":"Services"
        }
    ],
    "sg:phone":"+1 402 330 7310",
    "sg:postcode":"68144",
    "sg:province":"NE",
    "wof:name":"Kaj Corp",
    "wof:placetype":"venue"
},
  "geometry": {"coordinates":[-96.09228899999999,41.241591],"type":"Point"}
}