{
  "type": "Feature",
  "properties": {
    "addr:full":"117 E Brook Dr Whiteclay NE 69337",
    "addr:housenumber":"117",
    "addr:postcode":"69337",
    "addr:street":"E Brook Dr Whiteclay Ne",
    "iso:country":"US",
    "sg:address":"117 E Brook Dr",
    "sg:city":"Whiteclay",
    "sg:classifiers":[
        {
            "category":"Retail",
            "subcategory":"Auto Repair",
            "type":"Services"
        }
    ],
    "sg:phone":"+1 308 862 4287",
    "sg:postcode":"69337",
    "sg:province":"NE",
    "sg:tags":[
        "repairing",
        "automobile"
    ],
    "wof:name":"C & C Svc",
    "wof:placetype":"venue"
},
  "geometry": {"coordinates":[-102.940251,42.826373],"type":"Point"}
}