{
  "type": "Feature",
  "properties": {
    "iso:country":"US",
    "sg:address":"1612 14th St",
    "sg:city":"Columbus",
    "sg:classifiers":[
        {
            "category":"Social Services",
            "type":"Services"
        }
    ],
    "sg:phone":"+1 402 564 9520",
    "sg:postcode":"68601",
    "sg:province":"NE",
    "wof:name":"Columbus Counseling Growth Ctr",
    "wof:placetype":"venue"
},
  "geometry": {"coordinates":[-97.34791,41.430165],"type":"Point"}
}