{
  "type": "Feature",
  "properties": {
    "addr:full":"7217 Wood River Dr Omaha NE 68157",
    "addr:housenumber":"7217",
    "addr:postcode":"68157",
    "addr:street":"Wood River Dr",
    "iso:country":"US",
    "sg:address":"7217 Wood River Dr",
    "sg:city":"Omaha",
    "sg:classifiers":[
        {
            "category":"Wholesale",
            "subcategory":"Groceries",
            "type":"Manufacturing & Wholesale Goods"
        }
    ],
    "sg:phone":"+1 402 731 9402",
    "sg:postcode":"68157",
    "sg:province":"NE",
    "sg:tags":[
        "confectionery"
    ],
    "wof:name":"Martens Distributing",
    "wof:placetype":"venue"
},
  "geometry": {"coordinates":[-95.995406,41.187103],"type":"Point"}
}