{
  "type": "Feature",
  "properties": {
    "iso:country":"US",
    "sg:address":"603 W Pacific St",
    "sg:city":"Lexington",
    "sg:classifiers":[
        {
            "category":"Food & Beverages",
            "subcategory":"Groceries & Convenience Stores",
            "type":"Retail Goods"
        }
    ],
    "sg:phone":"+1 308 324 6018",
    "sg:postcode":"68850",
    "sg:province":"NE",
    "wof:name":"KWIK Stop Food Stores",
    "wof:placetype":"venue"
},
  "geometry": {"coordinates":[-99.75033999999999,40.778675],"type":"Point"}
}