{
  "type": "Feature",
  "properties": {
    "iso:country":"US",
    "sg:address":"125 E 1st St",
    "sg:city":"Papillion",
    "sg:classifiers":[
        {
            "category":"Manufacturing",
            "subcategory":"Motor Vehicles & Parts",
            "type":"Manufacturing & Wholesale Goods"
        }
    ],
    "sg:phone":"+1 402 331 0897",
    "sg:postcode":"68046",
    "sg:province":"NE",
    "sg:tags":[
        "automobile",
        "supply"
    ],
    "wof:name":"Don's Radiator Auto & Truck",
    "wof:placetype":"venue"
},
  "geometry": {"coordinates":[-96.041793,41.156338],"type":"Point"}
}