{
  "type": "Feature",
  "properties": {
    "addr:full":"115 8th Ave Holdrege NE 68949",
    "addr:housenumber":"115",
    "addr:postcode":"68949",
    "addr:street":"8Th Ave",
    "iso:country":"US",
    "sg:address":"115 8th Ave",
    "sg:city":"Holdrege",
    "sg:classifiers":[
        {
            "category":"Education",
            "subcategory":"School",
            "type":"Public Place"
        }
    ],
    "sg:phone":"+1 308 995 4339",
    "sg:postcode":"68949",
    "sg:province":"NE",
    "sg:website":"www.thedusters.org",
    "wof:name":"Washington Elementary School",
    "wof:placetype":"venue"
},
  "geometry": {"coordinates":[-99.379659,40.442059],"type":"Point"}
}