{
  "type": "Feature",
  "properties": {
    "iso:country":"US",
    "sg:address":"1707 N 5th St",
    "sg:city":"Beatrice",
    "sg:classifiers":[
        {
            "category":"Insurance",
            "subcategory":"Hazard Insurance",
            "type":"Services"
        },
        {
            "category":"Insurance",
            "subcategory":"Health Insurance",
            "type":"Services"
        }
    ],
    "sg:phone":"+1 402 223 4143",
    "sg:postcode":"68310",
    "sg:province":"NE",
    "sg:tags":[
        "commercial",
        "business"
    ],
    "sg:website":"http://www.aflac.com",
    "wof:name":"Aflac",
    "wof:placetype":"venue"
},
  "geometry": {"coordinates":[-96.74787600000001,40.282681],"type":"Point"}
}