{
  "type": "Feature",
  "properties": {
    "iso:country":"US",
    "sg:address":"500 N 1st St",
    "sg:city":"Springfield",
    "sg:classifiers":[
        {
            "category":"Retail",
            "subcategory":"Auto Repair",
            "type":"Services"
        }
    ],
    "sg:phone":"+1 402 253 8369",
    "sg:postcode":"68059",
    "sg:province":"NE",
    "sg:tags":[
        "general"
    ],
    "wof:name":"Nolte Repair",
    "wof:placetype":"venue"
},
  "geometry": {"coordinates":[-96.134675,41.08533],"type":"Point"}
}