{
  "type": "Feature",
  "properties": {
    "addr:full":"505 E Pacific St Lexington NE 68850",
    "addr:housenumber":"505",
    "addr:postcode":"68850",
    "addr:street":"E Pacific St",
    "iso:country":"US",
    "sg:address":"505 E Pacific St",
    "sg:city":"Lexington",
    "sg:classifiers":[
        {
            "category":"Travel",
            "subcategory":"Hotels & Motels",
            "type":"Entertainment"
        }
    ],
    "sg:phone":"+1 308 324 3915",
    "sg:postcode":"68850",
    "sg:province":"NE",
    "wof:name":"Hollingsworth Motel",
    "wof:placetype":"venue"
},
  "geometry": {"coordinates":[-99.736048,40.775514],"type":"Point"}
}