{
  "type": "Feature",
  "properties": {
    "iso:country":"US",
    "sg:address":"1241 N K St",
    "sg:city":"Broken Bow",
    "sg:classifiers":[
        {
            "category":"Restaurant",
            "type":"Food & Drink"
        }
    ],
    "sg:phone":"+1 308 872 0098",
    "sg:postcode":"68822",
    "sg:province":"NE",
    "sg:tags":[
        "eating"
    ],
    "wof:name":"Ae Custom Catering",
    "wof:placetype":"venue"
},
  "geometry": {"coordinates":[-99.64421900000001,41.413533],"type":"Point"}
}