{
  "type": "Feature",
  "properties": {
    "iso:country":"US",
    "sg:address":"3400 O St",
    "sg:city":"Lincoln",
    "sg:classifiers":[
        {
            "category":"Professional",
            "subcategory":"Lawyer & Legal Services",
            "type":"Services"
        }
    ],
    "sg:phone":"+1 402 434 9444",
    "sg:postcode":"68510",
    "sg:province":"NE",
    "sg:tags":[
        "attorney"
    ],
    "wof:name":"Harris Law Offices",
    "wof:placetype":"venue"
},
  "geometry": {"coordinates":[-96.67018899999999,40.813541],"type":"Point"}
}