{
  "type": "Feature",
  "properties": {
    "addr:full":"830 Pine St Sidney NE 69162",
    "addr:housenumber":"830",
    "addr:postcode":"69162",
    "addr:street":"Pine St",
    "iso:country":"US",
    "sg:address":"830 Pine St",
    "sg:city":"Sidney",
    "sg:classifiers":[
        {
            "category":"Health Services",
            "subcategory":"Doctor",
            "type":"Services"
        }
    ],
    "sg:phone":"+1 308 254 9192",
    "sg:postcode":"69162",
    "sg:province":"NE",
    "sg:tags":[
        "physician",
        "surgeon"
    ],
    "wof:name":"Dorwart Cancer Care Ctr",
    "wof:placetype":"venue"
},
  "geometry": {"coordinates":[-102.97526999999999,41.138026],"type":"Point"}
}