{
  "type": "Feature",
  "properties": {
    "addr:full":"1427 E 1st St Ainsworth NE 69210",
    "addr:housenumber":"1427",
    "addr:postcode":"69210",
    "addr:street":"E 1St St",
    "iso:country":"US",
    "sg:address":"1427 E 1st St",
    "sg:city":"Ainsworth",
    "sg:classifiers":[
        {
            "category":"Social Services",
            "subcategory":"Child Care",
            "type":"Services"
        }
    ],
    "sg:phone":"+1 402 387 2289",
    "sg:postcode":"69210",
    "sg:province":"NE",
    "sg:tags":[
        "day"
    ],
    "wof:name":"Tiny Tots Day Care",
    "wof:placetype":"venue"
},
  "geometry": {"coordinates":[-99.845123,42.545825],"type":"Point"}
}