{
  "type": "Feature",
  "properties": {
    "iso:country":"US",
    "sg:address":"43135 Rd 763",
    "sg:city":"Lexington",
    "sg:phone":"+1 308 324 3718",
    "sg:postcode":"68850",
    "sg:province":"NE",
    "sg:tags":[
        "farm",
        "corn"
    ],
    "wof:name":"KG Farms Inc",
    "wof:placetype":"venue"
},
  "geometry": {"coordinates":[-99.780017,40.888236],"type":"Point"}
}