{
  "type": "Feature",
  "properties": {
    "iso:country":"US",
    "sg:address":"310 S 13th St",
    "sg:city":"Geneva",
    "sg:classifiers":[
        {
            "category":"Food & Beverages",
            "subcategory":"Groceries & Convenience Stores",
            "type":"Retail Goods"
        }
    ],
    "sg:phone":"+1 402 759 3964",
    "sg:postcode":"68361",
    "sg:province":"NE",
    "wof:name":"Country Store",
    "wof:placetype":"venue"
},
  "geometry": {"coordinates":[-97.595885,40.522877],"type":"Point"}
}