{
  "type": "Feature",
  "properties": {
    "addr:full":"7529 Highland St Omaha NE 68127",
    "addr:housenumber":"7529",
    "addr:postcode":"68127",
    "addr:street":"Highland St",
    "iso:country":"US",
    "sg:address":"7529 Highland St",
    "sg:city":"Omaha",
    "sg:classifiers":[
        {
            "category":"Professional",
            "subcategory":"Art Services",
            "type":"Services"
        }
    ],
    "sg:phone":"+1 402 331 4176",
    "sg:postcode":"68127",
    "sg:province":"NE",
    "sg:tags":[
        "commercial",
        "design",
        "business"
    ],
    "wof:name":"Classic Calligraphy",
    "wof:placetype":"venue"
},
  "geometry": {"coordinates":[-96.02934399999999,41.204774],"type":"Point"}
}