{
  "type": "Feature",
  "properties": {
    "iso:country":"US",
    "sg:address":"666 N Broadway St",
    "sg:city":"Wahoo",
    "sg:classifiers":[
        {
            "category":"Professional",
            "subcategory":"Lawyer & Legal Services",
            "type":"Services"
        }
    ],
    "sg:phone":"+1 402 443 4181",
    "sg:postcode":"68066",
    "sg:province":"NE",
    "sg:tags":[
        "attorney"
    ],
    "wof:name":"Haessler Sullivan Klein",
    "wof:placetype":"venue"
},
  "geometry": {"coordinates":[-96.61983499999999,41.211784],"type":"Point"}
}