{
  "type": "Feature",
  "properties": {
    "iso:country":"US",
    "sg:address":"324 Kufus Ave",
    "sg:city":"Ravenna",
    "sg:classifiers":[
        {
            "category":"Organizations",
            "subcategory":"Religious Organization",
            "type":"Services"
        }
    ],
    "sg:phone":"+1 308 452 3685",
    "sg:postcode":"68869",
    "sg:province":"NE",
    "sg:website":"www.bethlehemravenna.com",
    "wof:name":"Bethlehem Lutheran Church",
    "wof:placetype":"venue"
},
  "geometry": {"coordinates":[-98.918335,41.026087],"type":"Point"}
}