{
  "type": "Feature",
  "properties": {
    "addr:full":"1516 23rd St Columbus NE 68601",
    "addr:housenumber":"1516",
    "addr:postcode":"68601",
    "addr:street":"23Rd St",
    "iso:country":"US",
    "sg:address":"1516 23rd St",
    "sg:city":"Columbus",
    "sg:classifiers":[
        {
            "category":"Manufacturing",
            "subcategory":"Signs",
            "type":"Manufacturing & Wholesale Goods"
        },
        {
            "category":"Professional",
            "subcategory":"Art Services",
            "type":"Services"
        }
    ],
    "sg:phone":"+1 402 564 5081",
    "sg:postcode":"68601",
    "sg:province":"NE",
    "sg:tags":[
        "commercial",
        "design"
    ],
    "wof:name":"Schieffer Signs Inc",
    "wof:placetype":"venue"
},
  "geometry": {"coordinates":[-97.345159,41.438362],"type":"Point"}
}