{
  "type": "Feature",
  "properties": {
    "iso:country":"US",
    "sg:address":"3902 Ave D",
    "sg:city":"Scottsbluff",
    "sg:classifiers":[
        {
            "category":"Real Estate",
            "subcategory":"Real Estate Operator",
            "type":"Services"
        }
    ],
    "sg:phone":"+1 308 632 7742",
    "sg:postcode":"69361",
    "sg:province":"NE",
    "sg:tags":[
        "building",
        "apartment"
    ],
    "wof:name":"Scottsfield Estates",
    "wof:placetype":"venue"
},
  "geometry": {"coordinates":[-103.66924299999999,41.885884],"type":"Point"}
}