{
  "type": "Feature",
  "properties": {
    "iso:country":"US",
    "sg:address":"5002 S 33rd St",
    "sg:city":"Omaha",
    "sg:phone":"+1 402 733 3440",
    "sg:postcode":"68107",
    "sg:province":"NE",
    "sg:website":"http://www.guaca-maya.com",
    "wof:name":"Guaca Maya Restaurant",
    "wof:placetype":"venue"
},
  "geometry": {"coordinates":[-95.962932,41.209445],"type":"Point"}
}