{
  "type": "Feature",
  "properties": {
    "iso:country":"US",
    "sg:address":"210 E 4th St",
    "sg:city":"Lexington",
    "sg:classifiers":[
        {
            "category":"Manufacturing",
            "subcategory":"Chemicals & Compounds",
            "type":"Manufacturing & Wholesale Goods"
        }
    ],
    "sg:phone":"+1 308 324 4571",
    "sg:postcode":"68850",
    "sg:province":"NE",
    "sg:tags":[
        "packaging",
        "pharmaceutical",
        "labeling"
    ],
    "sg:website":"www.med-pro-inc.com",
    "wof:name":"Med-Pro Inc",
    "wof:placetype":"venue"
},
  "geometry": {"coordinates":[-99.74007400000001,40.776879],"type":"Point"}
}