{
  "type": "Feature",
  "properties": {
    "addr:full":"503 S Saunders Ave Sutton NE 68979",
    "addr:housenumber":"503",
    "addr:postcode":"68979",
    "addr:street":"S Saunders Ave",
    "iso:country":"US",
    "sg:address":"503 S Saunders Ave",
    "sg:city":"Sutton",
    "sg:classifiers":[
        {
            "category":"Real Estate",
            "subcategory":"Real Estate Operator",
            "type":"Services"
        }
    ],
    "sg:phone":"+1 402 773 5441",
    "sg:postcode":"68979",
    "sg:province":"NE",
    "sg:tags":[
        "property",
        "lessor"
    ],
    "wof:name":"Donald Trautman",
    "wof:placetype":"venue"
},
  "geometry": {"coordinates":[-97.85956299999999,40.602473],"type":"Point"}
}