{
  "type": "Feature",
  "properties": {
    "addr:full":"1611 N Garfield St Fremont NE 68025",
    "addr:housenumber":"1611",
    "addr:postcode":"68025",
    "addr:street":"N Garfield St",
    "iso:country":"US",
    "sg:address":"1611 N Garfield St",
    "sg:city":"Fremont",
    "sg:classifiers":[
        {
            "category":"Professional",
            "type":"Services"
        }
    ],
    "sg:phone":"+1 402 753 0370",
    "sg:postcode":"68025",
    "sg:province":"NE",
    "wof:name":"ADS Services Inc",
    "wof:placetype":"venue"
},
  "geometry": {"coordinates":[-96.47928400000001,41.447213],"type":"Point"}
}