{
  "type": "Feature",
  "properties": {
    "iso:country":"US",
    "sg:address":"1902 N 90th St",
    "sg:city":"Omaha",
    "sg:classifiers":[
        {
            "category":"Wholesale",
            "subcategory":"Groceries",
            "type":"Manufacturing & Wholesale Goods"
        }
    ],
    "sg:phone":"+1 402 393 1908",
    "sg:postcode":"68114",
    "sg:province":"NE",
    "sg:tags":[
        "bakery",
        "retail"
    ],
    "wof:name":"Dolly Madison Bakery",
    "wof:placetype":"venue"
},
  "geometry": {"coordinates":[-96.052688,41.277779],"type":"Point"}
}