{
  "type": "Feature",
  "properties": {
    "iso:country":"US",
    "sg:address":"422 Commanche Ave",
    "sg:city":"Grand Island",
    "sg:classifiers":[
        {
            "category":"Retail",
            "subcategory":"Auto Repair",
            "type":"Services"
        }
    ],
    "sg:phone":"+1 308 384 4015",
    "sg:postcode":"68803",
    "sg:province":"NE",
    "sg:tags":[
        "general"
    ],
    "wof:name":"Kevin Salpas",
    "wof:placetype":"venue"
},
  "geometry": {"coordinates":[-98.411177,40.923234],"type":"Point"}
}