{
  "type": "Feature",
  "properties": {
    "iso:country":"US",
    "sg:address":"14121 Pierce Plz",
    "sg:city":"Omaha",
    "sg:classifiers":[
        {
            "category":"Real Estate",
            "subcategory":"Real Estate Agent",
            "type":"Services"
        }
    ],
    "sg:phone":"+1 402 333 6800",
    "sg:postcode":"68144",
    "sg:province":"NE",
    "sg:tags":[
        "apartment",
        "complex"
    ],
    "wof:name":"Pacific West Apartments",
    "wof:placetype":"venue"
},
  "geometry": {"coordinates":[-96.13663200000001,41.247492],"type":"Point"}
}