{
  "type": "Feature",
  "properties": {
    "addr:full":"2011 N 55th St Omaha NE 68104",
    "addr:housenumber":"2011",
    "addr:postcode":"68104",
    "addr:street":"N 55Th St",
    "iso:country":"US",
    "sg:address":"2011 N 55th St",
    "sg:city":"Omaha",
    "sg:classifiers":[
        {
            "category":"Professional",
            "subcategory":"Advertising",
            "type":"Services"
        }
    ],
    "sg:phone":"+1 402 556 4396",
    "sg:postcode":"68104",
    "sg:province":"NE",
    "sg:tags":[
        "counselor"
    ],
    "wof:name":"Nellie Mac Callum",
    "wof:placetype":"venue"
},
  "geometry": {"coordinates":[-95.998546,41.279568],"type":"Point"}
}