{
  "type": "Feature",
  "properties": {
    "iso:country":"US",
    "sg:address":"1211 Maberly St",
    "sg:city":"Holdrege",
    "sg:classifiers":[
        {
            "category":"Building & Trades",
            "subcategory":"Pest Control",
            "type":"Services"
        }
    ],
    "sg:phone":"+1 308 995 6773",
    "sg:postcode":"68949",
    "sg:province":"NE",
    "wof:name":"Reliable Pest Control Services",
    "wof:placetype":"venue"
},
  "geometry": {"coordinates":[-99.38566899999999,40.448683],"type":"Point"}
}