{
  "type": "Feature",
  "properties": {
    "addr:full":"14060 W Center Rd Omaha NE 68144",
    "addr:housenumber":"14060",
    "addr:postcode":"68144",
    "addr:street":"W Center Rd",
    "iso:country":"US",
    "sg:address":"14060 W Center Rd",
    "sg:city":"Omaha",
    "sg:classifiers":[
        {
            "category":"Home & Garden",
            "subcategory":"Hardware",
            "type":"Retail Goods"
        }
    ],
    "sg:phone":"+1 402 330 0610",
    "sg:postcode":"68144",
    "sg:province":"NE",
    "sg:website":"www.westlakehardware.com",
    "wof:name":"Westlake Ace Hardware",
    "wof:placetype":"venue"
},
  "geometry": {"coordinates":[-96.13105,41.234045],"type":"Point"}
}