{
  "type": "Feature",
  "properties": {
    "iso:country":"US",
    "sg:address":"3219 Plymouth Ave",
    "sg:city":"Lincoln",
    "sg:classifiers":[
        {
            "category":"Real Estate",
            "subcategory":"Real Estate Agent",
            "type":"Services"
        }
    ],
    "sg:phone":"+1 402 488 8112",
    "sg:postcode":"68502",
    "sg:province":"NE",
    "sg:tags":[
        "inspection"
    ],
    "wof:name":"Homebiz Inspection Team",
    "wof:placetype":"venue"
},
  "geometry": {"coordinates":[-96.674904,40.787961],"type":"Point"}
}