{
  "type": "Feature",
  "properties": {
    "addr:full":"701 4th Ave Holdrege NE 68949",
    "addr:housenumber":"701",
    "addr:postcode":"68949",
    "addr:street":"4Th Ave",
    "iso:country":"US",
    "sg:address":"701 4th Ave",
    "sg:city":"Holdrege",
    "sg:classifiers":[
        {
            "category":"Personal",
            "subcategory":"Beauty Salon",
            "type":"Services"
        }
    ],
    "sg:phone":"+1 308 995 6630",
    "sg:postcode":"68949",
    "sg:province":"NE",
    "wof:name":"Cutting Room",
    "wof:placetype":"venue"
},
  "geometry": {"coordinates":[-99.371326,40.437943],"type":"Point"}
}