{
  "type": "Feature",
  "properties": {
    "iso:country":"US",
    "sg:address":"810 S Ash St",
    "sg:city":"North Platte",
    "sg:classifiers":[
        {
            "category":"Freight",
            "type":"Transportation"
        }
    ],
    "sg:phone":"+1 308 534 3933",
    "sg:postcode":"69101",
    "sg:province":"NE",
    "sg:tags":[
        "operator",
        "local",
        "trucking"
    ],
    "wof:name":"CA Baker Trucking Inc",
    "wof:placetype":"venue"
},
  "geometry": {"coordinates":[-100.76911800000001,41.127005],"type":"Point"}
}