{
  "type": "Feature",
  "properties": {
    "iso:country":"US",
    "sg:address":"133 N Main St",
    "sg:city":"West Point",
    "sg:classifiers":[
        {
            "category":"Shopping",
            "subcategory":"Computers & Home Electronics",
            "type":"Retail Goods"
        }
    ],
    "sg:phone":"+1 402 372 9009",
    "sg:postcode":"68788",
    "sg:province":"NE",
    "sg:tags":[
        "equipment",
        "dealer"
    ],
    "wof:name":"Quality Computers & Consulting",
    "wof:placetype":"venue"
},
  "geometry": {"coordinates":[-96.712222,41.840818],"type":"Point"}
}