{
  "type": "Feature",
  "properties": {
    "iso:country":"US",
    "sg:address":"1014 Illinois St",
    "sg:city":"Sidney",
    "sg:classifiers":[
        {
            "category":"Shopping",
            "subcategory":"Computers & Home Electronics",
            "type":"Retail Goods"
        }
    ],
    "sg:phone":"+1 308 254 7485",
    "sg:postcode":"69162",
    "sg:province":"NE",
    "sg:tags":[
        "equipment",
        "satellite",
        "system"
    ],
    "wof:name":"Discount Satellites",
    "wof:placetype":"venue"
},
  "geometry": {"coordinates":[-102.977861,41.144912],"type":"Point"}
}