{
  "type": "Feature",
  "properties": {
    "iso:country":"US",
    "sg:address":"520 E Francis St",
    "sg:city":"North Platte",
    "sg:classifiers":[
        {
            "category":"Professional",
            "subcategory":"Engineering",
            "type":"Services"
        }
    ],
    "sg:phone":"+1 308 534 9245",
    "sg:postcode":"69101",
    "sg:province":"NE",
    "sg:tags":[
        "engineer"
    ],
    "wof:name":"T C Engineering Co",
    "wof:placetype":"venue"
},
  "geometry": {"coordinates":[-100.758124,41.122487],"type":"Point"}
}