{
  "type": "Feature",
  "properties": {
    "addr:full":"506 S Main St Madison NE 68748",
    "addr:housenumber":"506",
    "addr:postcode":"68748",
    "addr:street":"S Main St",
    "iso:country":"US",
    "sg:address":"506 S Main St",
    "sg:city":"Madison",
    "sg:classifiers":[
        {
            "category":"Organizations",
            "subcategory":"Religious Organization",
            "type":"Services"
        }
    ],
    "sg:phone":"+1 402 454 2514",
    "sg:postcode":"68748",
    "sg:province":"NE",
    "sg:tags":[
        "church"
    ],
    "wof:name":"United Methodist Church",
    "wof:placetype":"venue"
},
  "geometry": {"coordinates":[-97.454916,41.826062],"type":"Point"}
}