{
  "type": "Feature",
  "properties": {
    "iso:country":"US",
    "sg:address":"203 E 5th St",
    "sg:city":"Lexington",
    "sg:classifiers":[
        {
            "category":"Retail",
            "subcategory":"Car Wash",
            "type":"Services"
        }
    ],
    "sg:phone":"+1 308 324 3497",
    "sg:postcode":"68850",
    "sg:province":"NE",
    "sg:tags":[
        "polishing",
        "washing"
    ],
    "wof:name":"Gary's Kleen & Shine",
    "wof:placetype":"venue"
},
  "geometry": {"coordinates":[-99.74014200000001,40.77785],"type":"Point"}
}