{
  "type": "Feature",
  "properties": {
    "iso:country":"US",
    "sg:address":"6800 P St",
    "sg:city":"Lincoln",
    "sg:classifiers":[
        {
            "category":"Home & Garden",
            "subcategory":"Household Appliances",
            "type":"Retail Goods"
        }
    ],
    "sg:phone":"+1 402 464 0505",
    "sg:postcode":"68505",
    "sg:province":"NE",
    "sg:tags":[
        "machine",
        "sewing"
    ],
    "wof:name":"Bernina Sewing Studio",
    "wof:placetype":"venue"
},
  "geometry": {"coordinates":[-96.625135,40.814429],"type":"Point"}
}