{
  "type": "Feature",
  "properties": {
    "iso:country":"US",
    "sg:address":"4850 S 137th St",
    "sg:city":"Omaha",
    "sg:classifiers":[
        {
            "category":"Wholesale",
            "subcategory":"Durable Goods & Equipment",
            "type":"Manufacturing & Wholesale Goods"
        }
    ],
    "sg:phone":"+1 402 895 6697",
    "sg:postcode":"68137",
    "sg:province":"NE",
    "sg:tags":[
        "representative",
        "manufacturer"
    ],
    "wof:name":"Power Con Co",
    "wof:placetype":"venue"
},
  "geometry": {"coordinates":[-96.126829,41.208411],"type":"Point"}
}