{
  "type": "Feature",
  "properties": {
    "iso:country":"US",
    "sg:address":"816 S Denver Ave",
    "sg:city":"Hastings",
    "sg:classifiers":[
        {
            "category":"Freight",
            "type":"Transportation"
        }
    ],
    "sg:phone":"+1 402 463 9389",
    "sg:postcode":"68901",
    "sg:province":"NE",
    "sg:tags":[
        "trucking"
    ],
    "wof:name":"Alloway & Son Trucking",
    "wof:placetype":"venue"
},
  "geometry": {"coordinates":[-98.38878,40.575031],"type":"Point"}
}