{
  "type": "Feature",
  "properties": {
    "iso:country":"US",
    "sg:address":"50965 355th Rd",
    "sg:city":"Ravenna",
    "sg:classifiers":[
        {
            "category":"Real Estate",
            "subcategory":"Real Estate Operator",
            "type":"Services"
        }
    ],
    "sg:phone":"+1 308 452 3527",
    "sg:postcode":"68869",
    "sg:province":"NE",
    "sg:tags":[
        "farm",
        "corn",
        "property",
        "lessor"
    ],
    "wof:name":"Roth Dewey Farm",
    "wof:placetype":"venue"
},
  "geometry": {"coordinates":[-98.80506200000001,41.01783],"type":"Point"}
}