{
  "type": "Feature",
  "properties": {
    "iso:country":"US",
    "sg:address":"2804 Stagecoach Pl",
    "sg:city":"Grand Island",
    "sg:classifiers":[
        {
            "category":"Social Services",
            "subcategory":"Child Care",
            "type":"Services"
        }
    ],
    "sg:phone":"+1 308 381 1044",
    "sg:postcode":"68801",
    "sg:province":"NE",
    "sg:tags":[
        "day"
    ],
    "wof:name":"Jean Kaslon Day Care",
    "wof:placetype":"venue"
},
  "geometry": {"coordinates":[-98.361386,40.892116],"type":"Point"}
}