{
  "type": "Feature",
  "properties": {
    "iso:country":"US",
    "sg:address":"5331 NW Fairway Dr",
    "sg:city":"Lincoln",
    "sg:classifiers":[
        {
            "category":"Government",
            "subcategory":"Office",
            "type":"Public Place"
        }
    ],
    "sg:phone":"+1 402 477 0988",
    "sg:postcode":"68521",
    "sg:province":"NE",
    "sg:tags":[
        "management"
    ],
    "wof:name":"Advanced Air Quality Service L",
    "wof:placetype":"venue"
},
  "geometry": {"coordinates":[-96.73661,40.862298],"type":"Point"}
}