{
  "type": "Feature",
  "properties": {
    "iso:country":"US",
    "sg:address":"7141 Thorn Apple Ln",
    "sg:city":"La Vista",
    "sg:classifiers":[
        {
            "category":"Building & Trades",
            "subcategory":"Construction",
            "type":"Services"
        }
    ],
    "sg:phone":"+1 402 597 2660",
    "sg:postcode":"68128",
    "sg:province":"NE",
    "sg:tags":[
        "house"
    ],
    "wof:name":"Eischeid Construction",
    "wof:placetype":"venue"
},
  "geometry": {"coordinates":[-96.056608,41.188051],"type":"Point"}
}