{
  "type": "Feature",
  "properties": {
    "iso:country":"US",
    "sg:address":"3960 Dunn Ave",
    "sg:city":"Lincoln",
    "sg:classifiers":[
        {
            "category":"Manufacturing",
            "subcategory":"Toys & Sporting Goods",
            "type":"Manufacturing & Wholesale Goods"
        }
    ],
    "sg:phone":"+1 402 423 9359",
    "sg:postcode":"68502",
    "sg:province":"NE",
    "sg:tags":[
        "mfg"
    ],
    "wof:name":"First & Goal Sports",
    "wof:placetype":"venue"
},
  "geometry": {"coordinates":[-96.69013,40.773314],"type":"Point"}
}