{
  "type": "Feature",
  "properties": {
    "iso:country":"US",
    "sg:address":"255 N Cotner Blvd",
    "sg:city":"Lincoln",
    "sg:classifiers":[
        {
            "category":"Real Estate",
            "subcategory":"Real Estate Agent",
            "type":"Services"
        }
    ],
    "sg:phone":"+1 402 437 7503",
    "sg:postcode":"68505",
    "sg:province":"NE",
    "wof:name":"Home Realty",
    "wof:placetype":"venue"
},
  "geometry": {"coordinates":[-96.641869,40.814752],"type":"Point"}
}