{
  "type": "Feature",
  "properties": {
    "addr:full":"1307 Galvin Rd S Bellevue NE 68005",
    "addr:housenumber":"1307",
    "addr:postcode":"68005",
    "addr:street":"Galvin Rd S",
    "iso:country":"US",
    "sg:address":"1307 Galvin Rd S",
    "sg:city":"Bellevue",
    "sg:classifiers":[
        {
            "category":"Real Estate",
            "subcategory":"Real Estate Operator",
            "type":"Services"
        }
    ],
    "sg:phone":"+1 402 291 4100",
    "sg:postcode":"68005",
    "sg:province":"NE",
    "sg:tags":[
        "building",
        "apartment"
    ],
    "wof:name":"Royal Oaks Apts",
    "wof:placetype":"venue"
},
  "geometry": {"coordinates":[-95.91480799999999,41.147973],"type":"Point"}
}