{
  "type": "Feature",
  "properties": {
    "iso:country":"US",
    "sg:address":"7840 Maple St",
    "sg:city":"Omaha",
    "sg:classifiers":[
        {
            "category":"Organizations",
            "subcategory":"Religious Organization",
            "type":"Services"
        }
    ],
    "sg:phone":"+1 402 397 1714",
    "sg:postcode":"68134",
    "sg:province":"NE",
    "wof:name":"Keystone Bible Chapel",
    "wof:placetype":"venue"
},
  "geometry": {"coordinates":[-96.035696,41.285139],"type":"Point"}
}