{
  "type": "Feature",
  "properties": {
    "iso:country":"US",
    "sg:address":"5323 Franklin Rd",
    "sg:city":"Alliance",
    "sg:classifiers":[
        {
            "category":"Freight",
            "type":"Transportation"
        }
    ],
    "sg:phone":"+1 308 762 3249",
    "sg:postcode":"69301",
    "sg:province":"NE",
    "sg:tags":[
        "broker"
    ],
    "wof:name":"Hills View Inc",
    "wof:placetype":"venue"
},
  "geometry": {"coordinates":[-102.75993800000001,42.299153],"type":"Point"}
}