{
  "type": "Feature",
  "properties": {
    "addr:full":"2900 L St Lincoln NE 68510",
    "addr:housenumber":"2900",
    "addr:postcode":"68510",
    "addr:street":"L St",
    "iso:country":"US",
    "sg:address":"2900 L St",
    "sg:city":"Lincoln",
    "sg:classifiers":[
        {
            "category":"Education",
            "subcategory":"Special Training",
            "type":"Public Place"
        }
    ],
    "sg:phone":"+1 402 477 5933",
    "sg:postcode":"68510",
    "sg:province":"NE",
    "sg:tags":[
        "instruction",
        "driving"
    ],
    "wof:name":"Road-Ready Driver Training",
    "wof:placetype":"venue"
},
  "geometry": {"coordinates":[-96.678344,40.809874],"type":"Point"}
}