{
  "type": "Feature",
  "properties": {
    "addr:full":"730 S 75th St Omaha NE 68114",
    "addr:housenumber":"730",
    "addr:postcode":"68114",
    "addr:street":"S 75Th St",
    "iso:country":"US",
    "sg:address":"730 S 75th St",
    "sg:city":"Omaha",
    "sg:classifiers":[
        {
            "category":"Wholesale",
            "subcategory":"Office Equipment",
            "type":"Manufacturing & Wholesale Goods"
        },
        {
            "category":"Professional",
            "subcategory":"Printing & Photocopies",
            "type":"Services"
        },
        {
            "category":"Shopping",
            "subcategory":"Computers & Home Electronics",
            "type":"Retail Goods"
        }
    ],
    "sg:phone":"+1 402 392 2400",
    "sg:postcode":"68114",
    "sg:province":"NE",
    "sg:tags":[
        "scanning",
        "printer",
        "supply",
        "services-commercial",
        "lithographer",
        "plotting"
    ],
    "sg:website":"http://www.msmprint.com",
    "wof:name":"Msm Printing",
    "wof:placetype":"venue"
},
  "geometry": {"coordinates":[-96.02951899999999,41.252049],"type":"Point"}
}