{
  "type": "Feature",
  "properties": {
    "iso:country":"US",
    "sg:address":"6363 John J Pershing Dr",
    "sg:city":"Omaha",
    "sg:classifiers":[
        {
            "category":"Manufacturing",
            "subcategory":"Paper Products",
            "type":"Manufacturing & Wholesale Goods"
        }
    ],
    "sg:phone":"+1 402 455 0101",
    "sg:postcode":"68110",
    "sg:province":"NE",
    "sg:tags":[
        "corrugated",
        "container",
        "mfg"
    ],
    "wof:name":"Packaging Corporation America",
    "wof:placetype":"venue"
},
  "geometry": {"coordinates":[-95.932135,41.317602],"type":"Point"}
}