{
  "type": "Feature",
  "properties": {
    "iso:country":"US",
    "sg:address":"5631 S 48th St",
    "sg:city":"Lincoln",
    "sg:classifiers":[
        {
            "category":"Organizations",
            "subcategory":"Community Association",
            "type":"Services"
        }
    ],
    "sg:phone":"+1 402 420 4017",
    "sg:postcode":"68516",
    "sg:province":"NE",
    "sg:tags":[
        "military"
    ],
    "wof:name":"Paralyzed Veterans Of America",
    "wof:placetype":"venue"
},
  "geometry": {"coordinates":[-96.653943,40.757269],"type":"Point"}
}