{
  "type": "Feature",
  "properties": {
    "iso:country":"US",
    "sg:address":"3555 10th St",
    "sg:city":"Gering",
    "sg:classifiers":[
        {
            "category":"Building & Trades",
            "subcategory":"Equipment Rental",
            "type":"Services"
        }
    ],
    "sg:phone":"+1 308 635 7877",
    "sg:postcode":"69341",
    "sg:province":"NE",
    "sg:tags":[
        "contractor"
    ],
    "wof:name":"A-1 Rental",
    "wof:placetype":"venue"
},
  "geometry": {"coordinates":[-103.66088999999999,41.845989],"type":"Point"}
}