{
  "type": "Feature",
  "properties": {
    "addr:full":"502 Paxton Ave Hayes Center NE 69032",
    "addr:housenumber":"502",
    "addr:postcode":"69032",
    "addr:street":"Paxton Ave",
    "iso:country":"US",
    "sg:address":"502 Paxton Ave",
    "sg:city":"Hayes Center",
    "sg:classifiers":[
        {
            "category":"Government",
            "subcategory":"Office",
            "type":"Public Place"
        }
    ],
    "sg:phone":"+1 308 286 3214",
    "sg:postcode":"69032",
    "sg:province":"NE",
    "sg:tags":[
        "county",
        "taxation"
    ],
    "wof:name":"Hayes County Treasurer",
    "wof:placetype":"venue"
},
  "geometry": {"coordinates":[-101.01836299999999,40.510893],"type":"Point"}
}