{
  "type": "Feature",
  "properties": {
    "addr:full":"13514 Giles Rd Omaha NE 68138",
    "addr:housenumber":"13514",
    "addr:postcode":"68138",
    "addr:street":"Giles Rd",
    "iso:country":"US",
    "sg:address":"13514 Giles Rd",
    "sg:city":"Omaha",
    "sg:classifiers":[
        {
            "category":"Building & Trades",
            "subcategory":"Construction",
            "type":"Services"
        }
    ],
    "sg:phone":"+1 402 672 6484",
    "sg:postcode":"68138",
    "sg:province":"NE",
    "sg:tags":[
        "designer",
        "contractor",
        "spa",
        "dealer",
        "pool",
        "swimming"
    ],
    "wof:name":"New Wave Pools & Spas Inc",
    "wof:placetype":"venue"
},
  "geometry": {"coordinates":[-96.124015,41.176202],"type":"Point"}
}