{
  "type": "Feature",
  "properties": {
    "iso:country":"US",
    "sg:address":"16400 24th Rd",
    "sg:city":"Kearney",
    "sg:classifiers":[
        {
            "category":"Professional",
            "subcategory":"Management & Consulting",
            "type":"Services"
        }
    ],
    "sg:phone":"+1 308 237 5500",
    "sg:postcode":"68847",
    "sg:province":"NE",
    "sg:tags":[
        "agricultural",
        "consultant"
    ],
    "wof:name":"Big Flag Farm Supply",
    "wof:placetype":"venue"
},
  "geometry": {"coordinates":[-98.984561,40.69929],"type":"Point"}
}