{
  "type": "Feature",
  "properties": {
    "iso:country":"US",
    "sg:address":"2815 River Road Dr",
    "sg:city":"Waterloo",
    "sg:classifiers":[
        {
            "category":"Wholesale",
            "subcategory":"Durable Goods & Equipment",
            "type":"Manufacturing & Wholesale Goods"
        }
    ],
    "sg:phone":"+1 402 779 2040",
    "sg:postcode":"68069",
    "sg:province":"NE",
    "sg:tags":[
        "representative",
        "manufacturer"
    ],
    "wof:name":"Hamel Mfg Inc",
    "wof:placetype":"venue"
},
  "geometry": {"coordinates":[-96.28246900000001,41.283368],"type":"Point"}
}