{
  "type": "Feature",
  "properties": {
    "iso:country":"US",
    "sg:address":"402 N 3rd St",
    "sg:city":"Norfolk",
    "sg:classifiers":[
        {
            "category":"Wholesale",
            "subcategory":"Meat",
            "type":"Manufacturing & Wholesale Goods"
        }
    ],
    "sg:phone":"+1 402 371 1150",
    "sg:postcode":"68701",
    "sg:province":"NE",
    "sg:tags":[
        "product"
    ],
    "wof:name":"Henningsen Foods Inc",
    "wof:placetype":"venue"
},
  "geometry": {"coordinates":[-97.410184,42.036948],"type":"Point"}
}