{
  "type": "Feature",
  "properties": {
    "iso:country":"US",
    "sg:address":"321 D St",
    "sg:city":"Fairbury",
    "sg:classifiers":[
        {
            "category":"Bars & Pubs",
            "type":"Food & Drink"
        }
    ],
    "sg:phone":"+1 402 729 9925",
    "sg:postcode":"68352",
    "sg:province":"NE",
    "wof:name":"Tooley's Lounge",
    "wof:placetype":"venue"
},
  "geometry": {"coordinates":[-97.181342,40.135112],"type":"Point"}
}