{
  "type": "Feature",
  "properties": {
    "iso:country":"US",
    "sg:address":"4037 L St",
    "sg:city":"Omaha",
    "sg:classifiers":[
        {
            "category":"Shopping",
            "subcategory":"Tobacco",
            "type":"Retail Goods"
        }
    ],
    "sg:phone":"+1 402 502 2550",
    "sg:postcode":"68107",
    "sg:province":"NE",
    "sg:tags":[
        "shop"
    ],
    "wof:name":"Bizarre Tobacco",
    "wof:placetype":"venue"
},
  "geometry": {"coordinates":[-95.973694,41.212463],"type":"Point"}
}