{
  "type": "Feature",
  "properties": {
    "addr:full":"4037 L St Omaha NE 68107",
    "addr:housenumber":"4037",
    "addr:postcode":"68107",
    "addr:street":"L St",
    "iso:country":"US",
    "sg:address":"4037 L St",
    "sg:city":"Omaha",
    "sg:classifiers":[
        {
            "category":"Shopping",
            "subcategory":"Tobacco",
            "type":"Retail Goods"
        }
    ],
    "sg:phone":"+1 402 502 2550",
    "sg:postcode":"68107",
    "sg:province":"NE",
    "sg:tags":[
        "shop"
    ],
    "wof:name":"Bizarre Tobacco",
    "wof:placetype":"venue"
},
  "geometry": {"coordinates":[-95.97369399999999,41.212463],"type":"Point"}
}