{
  "type": "Feature",
  "properties": {
    "addr:full":"5029 S 108th St Omaha NE 68137",
    "addr:housenumber":"5029",
    "addr:postcode":"68137",
    "addr:street":"S 108Th St",
    "iso:country":"US",
    "sg:address":"5029 S 108th St",
    "sg:city":"Omaha",
    "sg:classifiers":[
        {
            "category":"Restaurant",
            "type":"Food & Drink"
        }
    ],
    "sg:menulink":"http://www.allmenus.com/ne/omaha/158947-arbys/menu/",
    "sg:phone":"+1 402 339 4626",
    "sg:postcode":"68137",
    "sg:province":"NE",
    "sg:tags":[
        "burger",
        "american"
    ],
    "wof:name":"Arby's",
    "wof:placetype":"venue"
},
  "geometry": {"coordinates":[-96.08063799999999,41.208448],"type":"Point"}
}