{
  "type": "Feature",
  "properties": {
    "iso:country":"US",
    "sg:address":"1908 Betz Rd",
    "sg:city":"Bellevue",
    "sg:classifiers":[
        {
            "category":"Insurance",
            "subcategory":"Insurance Agent",
            "type":"Services"
        }
    ],
    "sg:phone":"+1 402 291 8766",
    "sg:postcode":"68005",
    "sg:province":"NE",
    "wof:name":"American Family",
    "wof:placetype":"venue"
},
  "geometry": {"coordinates":[-95.92214199999999,41.141424],"type":"Point"}
}