{
  "type": "Feature",
  "properties": {
    "iso:country":"US",
    "sg:address":"4001 Holdrege St",
    "sg:city":"Lincoln",
    "sg:classifiers":[
        {
            "category":"Travel",
            "subcategory":"Hotels & Motels",
            "type":"Entertainment"
        },
        {
            "category":"Organizations",
            "subcategory":"Community Association",
            "type":"Services"
        }
    ],
    "sg:phone":"+1 402 436 7155",
    "sg:postcode":"68503",
    "sg:province":"NE",
    "sg:tags":[
        "sorority",
        "fraternity"
    ],
    "wof:name":"Alpha Gamma Sigma Fraternity",
    "wof:placetype":"venue"
},
  "geometry": {"coordinates":[-96.66211699999999,40.828039],"type":"Point"}
}