{
  "type": "Feature",
  "properties": {
    "iso:country":"US",
    "sg:address":"2201 Jones St",
    "sg:city":"Omaha",
    "sg:classifiers":[
        {
            "category":"Real Estate",
            "subcategory":"Real Estate Operator",
            "type":"Services"
        }
    ],
    "sg:phone":"+1 402 422 0747",
    "sg:postcode":"68102",
    "sg:province":"NE",
    "sg:tags":[
        "apartment"
    ],
    "wof:name":"K T Co",
    "wof:placetype":"venue"
},
  "geometry": {"coordinates":[-95.94550700000001,41.253122],"type":"Point"}
}