{
  "type": "Feature",
  "properties": {
    "iso:country":"US",
    "sg:address":"3018 S 87th St",
    "sg:city":"Omaha",
    "sg:classifiers":[
        {
            "category":"Health Services",
            "subcategory":"Doctor",
            "type":"Services"
        }
    ],
    "sg:phone":"+1 402 397 3411",
    "sg:postcode":"68124",
    "sg:province":"NE",
    "sg:tags":[
        "dentist"
    ],
    "wof:name":"Optimal Health PC",
    "wof:placetype":"venue"
},
  "geometry": {"coordinates":[-96.048749,41.231151],"type":"Point"}
}