{
  "type": "Feature",
  "properties": {
    "addr:full":"5225 S 23rd St Omaha NE 68107",
    "addr:housenumber":"5225",
    "addr:postcode":"68107",
    "addr:street":"S 23Rd St",
    "iso:country":"US",
    "sg:address":"5225 S 23rd St",
    "sg:city":"Omaha",
    "sg:classifiers":[
        {
            "category":"Organizations",
            "subcategory":"Religious Organization",
            "type":"Services"
        }
    ],
    "sg:phone":"+1 402 738 8240",
    "sg:postcode":"68107",
    "sg:province":"NE",
    "sg:tags":[
        "church"
    ],
    "wof:name":"Guadalupe Our Lady-Religious",
    "wof:placetype":"venue"
},
  "geometry": {"coordinates":[-95.945502,41.203986],"type":"Point"}
}