{
  "type": "Feature",
  "properties": {
    "addr:full":"4822 Dodge St Omaha NE 68132",
    "addr:housenumber":"4822",
    "addr:postcode":"68132",
    "addr:street":"Dodge St",
    "iso:country":"US",
    "sg:address":"4822 Dodge St",
    "sg:city":"Omaha",
    "sg:classifiers":[
        {
            "category":"Professional",
            "subcategory":"Engineering",
            "type":"Services"
        }
    ],
    "sg:phone":"+1 402 551 8353",
    "sg:postcode":"68132",
    "sg:province":"NE",
    "sg:tags":[
        "manage",
        "construction",
        "architect",
        "architectural",
        "surveying",
        "engineer"
    ],
    "sg:website":"www.batheja.com",
    "wof:name":"Batheja & Associates Inc",
    "wof:placetype":"venue"
},
  "geometry": {"coordinates":[-95.98690000000001,41.2598],"type":"Point"}
}