{
  "type": "Feature",
  "properties": {
    "iso:country":"US",
    "sg:address":"325 N Victoria St",
    "sg:city":"Valentine",
    "sg:classifiers":[
        {
            "category":"Organizations",
            "subcategory":"Religious Organization",
            "type":"Services"
        }
    ],
    "sg:phone":"+1 402 376 1305",
    "sg:postcode":"69201",
    "sg:province":"NE",
    "sg:tags":[
        "church"
    ],
    "wof:name":"Presbyterian Church U S A",
    "wof:placetype":"venue"
},
  "geometry": {"coordinates":[-100.55667099999999,42.875751],"type":"Point"}
}