{
  "type": "Feature",
  "properties": {
    "iso:country":"US",
    "sg:address":"2631 S 70th St",
    "sg:city":"Lincoln",
    "sg:classifiers":[
        {
            "category":"Health Services",
            "subcategory":"Doctor",
            "type":"Services"
        }
    ],
    "sg:phone":"+1 402 483 7226",
    "sg:postcode":"68506",
    "sg:province":"NE",
    "sg:tags":[
        "physician"
    ],
    "wof:name":"Bashir Rifaat MD",
    "wof:placetype":"venue"
},
  "geometry": {"coordinates":[-96.62525599999999,40.787079],"type":"Point"}
}