{
  "type": "Feature",
  "properties": {
    "addr:full":"12665 Burke St Omaha NE 68154",
    "addr:housenumber":"12665",
    "addr:postcode":"68154",
    "addr:street":"Burke St",
    "iso:country":"US",
    "sg:address":"12665 Burke St",
    "sg:city":"Omaha",
    "sg:classifiers":[
        {
            "category":"Insurance",
            "subcategory":"Insurance Agent",
            "type":"Services"
        }
    ],
    "sg:phone":"+1 402 592 9400",
    "sg:postcode":"68154",
    "sg:province":"NE",
    "wof:name":"AFLAC",
    "wof:placetype":"venue"
},
  "geometry": {"coordinates":[-96.10910800000001,41.260317],"type":"Point"}
}