{
  "type": "Feature",
  "properties": {
    "addr:full":"1500 Court St Beatrice NE 68310",
    "addr:housenumber":"1500",
    "addr:postcode":"68310",
    "addr:street":"Court St",
    "iso:country":"US",
    "sg:address":"1500 Court St",
    "sg:city":"Beatrice",
    "sg:classifiers":[
        {
            "category":"Food & Beverages",
            "subcategory":"Groceries & Convenience Stores",
            "type":"Retail Goods"
        }
    ],
    "sg:phone":"+1 402 228 9985",
    "sg:postcode":"68310",
    "sg:province":"NE",
    "sg:tags":[
        "carry",
        "out",
        "station",
        "gas",
        "pizza"
    ],
    "wof:name":"Casey's General Store",
    "wof:placetype":"venue"
},
  "geometry": {"coordinates":[-96.731238,40.265883],"type":"Point"}
}