{
  "type": "Feature",
  "properties": {
    "addr:full":"2700 W 13th St Grand Island NE 68803",
    "addr:housenumber":"2700",
    "addr:postcode":"68803",
    "addr:street":"W 13Th St",
    "iso:country":"US",
    "sg:address":"2700 W 13th St",
    "sg:city":"Grand Island",
    "sg:classifiers":[
        {
            "category":"Education",
            "subcategory":"School",
            "type":"Public Place"
        }
    ],
    "sg:phone":"+1 308 385 5905",
    "sg:postcode":"68803",
    "sg:province":"NE",
    "sg:website":"www.esu10.org",
    "wof:name":"A-B Newell Elementary School",
    "wof:placetype":"venue"
},
  "geometry": {"coordinates":[-98.372135,40.931464],"type":"Point"}
}