{
  "type": "Feature",
  "properties": {
    "addr:full":"1019 W 2nd St Hastings NE 68901",
    "addr:housenumber":"1019",
    "addr:postcode":"68901",
    "addr:street":"W 2Nd St",
    "iso:country":"US",
    "sg:address":"1019 W 2nd St",
    "sg:city":"Hastings",
    "sg:classifiers":[
        {
            "category":"Banks & Credit Unions",
            "subcategory":"Investment Brokerage",
            "type":"Services"
        }
    ],
    "sg:phone":"+1 402 462 9119",
    "sg:postcode":"68901",
    "sg:province":"NE",
    "sg:tags":[
        "stock",
        "bond"
    ],
    "wof:name":"Edward Jones Co",
    "wof:placetype":"venue"
},
  "geometry": {"coordinates":[-98.39492199999999,40.585169],"type":"Point"}
}