{
  "type": "Feature",
  "properties": {
    "addr:full":"2504 S 32nd Ave Omaha NE 68105",
    "addr:housenumber":"2504",
    "addr:postcode":"68105",
    "addr:street":"S 32Nd Ave",
    "iso:country":"US",
    "sg:address":"2504 S 32nd Ave",
    "sg:city":"Omaha",
    "sg:phone":"+1 402 346 6341",
    "sg:postcode":"68105",
    "sg:province":"NE",
    "sg:tags":[
        "neon",
        "sign"
    ],
    "sg:website":"www.allaboutneon.com",
    "wof:name":"All About Neon",
    "wof:placetype":"venue"
},
  "geometry": {"coordinates":[-95.960404,41.234792],"type":"Point"}
}