{
  "type": "Feature",
  "properties": {
    "iso:country":"US",
    "sg:address":"1002 W Gage St",
    "sg:city":"Blue Hill",
    "sg:classifiers":[
        {
            "category":"Building & Trades",
            "subcategory":"Construction",
            "type":"Services"
        }
    ],
    "sg:phone":"+1 402 756 2134",
    "sg:postcode":"68930",
    "sg:province":"NE",
    "sg:tags":[
        "siding",
        "contractor"
    ],
    "wof:name":"Wes Siding",
    "wof:placetype":"venue"
},
  "geometry": {"coordinates":[-98.455799,40.332594],"type":"Point"}
}