{
  "type": "Feature",
  "properties": {
    "addr:full":"2602 N 24th St Omaha NE 68110",
    "addr:housenumber":"2602",
    "addr:postcode":"68110",
    "addr:street":"N 24Th St",
    "iso:country":"US",
    "sg:address":"2602 N 24th St",
    "sg:city":"Omaha",
    "sg:classifiers":[
        {
            "category":"Organizations",
            "subcategory":"Religious Organization",
            "type":"Services"
        }
    ],
    "sg:phone":"+1 402 451 8800",
    "sg:postcode":"68110",
    "sg:province":"NE",
    "sg:tags":[
        "church"
    ],
    "wof:name":"Mount Moriah Baptist Church",
    "wof:placetype":"venue"
},
  "geometry": {"coordinates":[-95.947087,41.283317],"type":"Point"}
}