{
  "type": "Feature",
  "properties": {
    "iso:country":"US",
    "sg:address":"11902 Elm St",
    "sg:city":"Omaha",
    "sg:classifiers":[
        {
            "category":"Recreation",
            "type":"Entertainment"
        }
    ],
    "sg:phone":"+1 402 758 1342",
    "sg:postcode":"68144",
    "sg:province":"NE",
    "sg:tags":[
        "astrologer"
    ],
    "wof:name":"Stars-N-You",
    "wof:placetype":"venue"
},
  "geometry": {"coordinates":[-96.099326,41.232802],"type":"Point"}
}