{
  "type": "Feature",
  "properties": {
    "iso:country":"US",
    "sg:address":"2831 D Rd",
    "sg:city":"Rising City",
    "sg:classifiers":[
        {
            "category":"Farming",
            "subcategory":"Farm",
            "type":"Manufacturing & Wholesale Goods"
        }
    ],
    "sg:phone":"+1 402 542 2485",
    "sg:postcode":"68658",
    "sg:province":"NE",
    "sg:tags":[
        "crop",
        "general"
    ],
    "wof:name":"Paul Vavra",
    "wof:placetype":"venue"
},
  "geometry": {"coordinates":[-97.311526,41.151355],"type":"Point"}
}