{
  "type": "Feature",
  "properties": {
    "addr:full":"1304 State Hwy 14 Aurora NE 68818",
    "addr:housenumber":"1304",
    "addr:postcode":"68818",
    "addr:street":"State Hwy 14",
    "iso:country":"US",
    "sg:address":"1304 State Hwy 14",
    "sg:city":"Aurora",
    "sg:classifiers":[
        {
            "category":"Organizations",
            "subcategory":"Religious Organization",
            "type":"Services"
        }
    ],
    "sg:phone":"+1 402 694 5494",
    "sg:postcode":"68818",
    "sg:province":"NE",
    "sg:tags":[
        "church"
    ],
    "wof:name":"First Evangelical Lutheran Chr",
    "wof:placetype":"venue"
},
  "geometry": {"coordinates":[-97.99764999999999,40.870617],"type":"Point"}
}