{
  "type": "Feature",
  "properties": {
    "iso:country":"US",
    "sg:address":"108th & Center",
    "sg:city":"Omaha",
    "sg:classifiers":[
        {
            "category":"Fast Food",
            "type":"Food & Drink"
        },
        {
            "category":"Food & Beverages",
            "subcategory":"Bakery",
            "type":"Retail Goods"
        }
    ],
    "sg:phone":"+1 402 926 4103",
    "sg:postcode":"68102",
    "sg:province":"NE",
    "sg:tags":[
        "sandwich"
    ],
    "wof:name":"Blimpie",
    "wof:placetype":"venue"
},
  "geometry": {"coordinates":[-95.937202,41.257198],"type":"Point"}
}