{
  "type": "Feature",
  "properties": {
    "addr:full":"13425 I Cir Omaha NE 68137",
    "addr:housenumber":"13425",
    "addr:postcode":"68137",
    "addr:street":"I Cir",
    "iso:country":"US",
    "sg:address":"13425 I Cir",
    "sg:city":"Omaha",
    "sg:classifiers":[
        {
            "category":"Wholesale",
            "subcategory":"Construction Materials",
            "type":"Manufacturing & Wholesale Goods"
        }
    ],
    "sg:phone":"+1 402 334 9400",
    "sg:postcode":"68137",
    "sg:province":"NE",
    "sg:tags":[
        "door",
        "aluminum",
        "windows",
        "metal",
        "hollow",
        "glass"
    ],
    "wof:name":"Aluminum & Window Products Inc",
    "wof:placetype":"venue"
},
  "geometry": {"coordinates":[-96.12527300000001,41.217783],"type":"Point"}
}