{
  "type": "Feature",
  "properties": {
    "addr:full":"2121 S 80th Ave Omaha NE 68124",
    "addr:housenumber":"2121",
    "addr:postcode":"68124",
    "addr:street":"S 80Th Ave",
    "iso:country":"US",
    "sg:address":"2121 S 80th Ave",
    "sg:city":"Omaha",
    "sg:classifiers":[
        {
            "category":"Professional",
            "subcategory":"Management & Consulting",
            "type":"Services"
        }
    ],
    "sg:phone":"+1 402 393 3919",
    "sg:postcode":"68124",
    "sg:province":"NE",
    "sg:tags":[
        "business"
    ],
    "wof:name":"Beaming LLC",
    "wof:placetype":"venue"
},
  "geometry": {"coordinates":[-96.03881,41.240913],"type":"Point"}
}