{
  "type": "Feature",
  "properties": {
    "addr:full":"76411 Rd 423 Cozad NE 69130",
    "addr:postcode":"76411;69130",
    "addr:street":"Rd 423 Cozad Ne",
    "iso:country":"US",
    "sg:address":"76411 Rd 423",
    "sg:city":"Cozad",
    "sg:phone":"+1 308 784 2408",
    "sg:postcode":"69130",
    "sg:province":"NE",
    "sg:tags":[
        "farm",
        "field",
        "corn",
        "crop"
    ],
    "wof:name":"Ronald Stear",
    "wof:placetype":"venue"
},
  "geometry": {"coordinates":[-99.93834200000001,40.903545],"type":"Point"}
}