{
  "type": "Feature",
  "properties": {
    "iso:country":"US",
    "sg:address":"206 N 16th St",
    "sg:city":"Ord",
    "sg:classifiers":[
        {
            "category":"Social Services",
            "subcategory":"Adult Care",
            "type":"Services"
        },
        {
            "category":"Social Services",
            "type":"Services"
        }
    ],
    "sg:phone":"+1 308 728 5436",
    "sg:postcode":"68862",
    "sg:province":"NE",
    "sg:tags":[
        "organization",
        "senior",
        "citizen"
    ],
    "wof:name":"Senior Classics Valley County",
    "wof:placetype":"venue"
},
  "geometry": {"coordinates":[-98.929202,41.604387],"type":"Point"}
}