{
  "type": "Feature",
  "properties": {
    "iso:country":"US",
    "sg:address":"12923 Corby St",
    "sg:city":"Omaha",
    "sg:classifiers":[
        {
            "category":"Professional",
            "subcategory":"Computer Services",
            "type":"Services"
        }
    ],
    "sg:phone":"+1 858 565 6758",
    "sg:postcode":"68164",
    "sg:province":"NE",
    "sg:tags":[
        "prepackaged",
        "software"
    ],
    "wof:name":"Sharper Logic Software",
    "wof:placetype":"venue"
},
  "geometry": {"coordinates":[-96.117013,41.284451],"type":"Point"}
}