{
  "type": "Feature",
  "properties": {
    "iso:country":"US",
    "sg:address":"1010 E 7th St",
    "sg:city":"North Platte",
    "sg:classifiers":[
        {
            "category":"Wholesale",
            "subcategory":"Hardware",
            "type":"Manufacturing & Wholesale Goods"
        }
    ],
    "sg:phone":"+1 308 534 6845",
    "sg:postcode":"69101",
    "sg:province":"NE",
    "sg:tags":[
        "plumbing"
    ],
    "wof:name":"Briggs-North Platte",
    "wof:placetype":"venue"
},
  "geometry": {"coordinates":[-100.750969,41.139893],"type":"Point"}
}