{
  "type": "Feature",
  "properties": {
    "iso:country":"US",
    "sg:address":"4128 Garfield St",
    "sg:city":"Lincoln",
    "sg:classifiers":[
        {
            "category":"Building & Trades",
            "subcategory":"Construction",
            "type":"Services"
        }
    ],
    "sg:phone":"+1 402 488 1900",
    "sg:postcode":"68506",
    "sg:province":"NE",
    "sg:tags":[
        "contractor"
    ],
    "wof:name":"Eagle Roofing & Construction",
    "wof:placetype":"venue"
},
  "geometry": {"coordinates":[-96.65992900000001,40.796289],"type":"Point"}
}