{
  "type": "Feature",
  "properties": {
    "addr:full":"7805 L St Omaha NE 68127",
    "addr:housenumber":"7805",
    "addr:postcode":"68127",
    "addr:street":"L St",
    "iso:country":"US",
    "sg:address":"7805 L St",
    "sg:city":"Omaha",
    "sg:classifiers":[
        {
            "category":"Personal",
            "type":"Services"
        }
    ],
    "sg:phone":"+1 402 991 3883",
    "sg:postcode":"68127",
    "sg:province":"NE",
    "sg:tags":[
        "therapist",
        "massage"
    ],
    "wof:name":"Tranquil Moment Massage Thrpy",
    "wof:placetype":"venue"
},
  "geometry": {"coordinates":[-96.036902,41.212456],"type":"Point"}
}