{
  "type": "Feature",
  "properties": {
    "iso:country":"US",
    "sg:address":"3747 S 27th St",
    "sg:city":"Lincoln",
    "sg:classifiers":[
        {
            "category":"Food & Beverages",
            "subcategory":"Groceries & Convenience Stores",
            "type":"Retail Goods"
        }
    ],
    "sg:phone":"+1 402 420 5290",
    "sg:postcode":"68502",
    "sg:province":"NE",
    "wof:name":"U-Stop Convenience Shop",
    "wof:placetype":"venue"
},
  "geometry": {"coordinates":[-96.682593,40.773476],"type":"Point"}
}