{
  "type": "Feature",
  "properties": {
    "iso:country":"US",
    "sg:address":"310 W 38th St",
    "sg:city":"Scottsbluff",
    "sg:classifiers":[
        {
            "category":"Health Services",
            "subcategory":"Doctor",
            "type":"Services"
        }
    ],
    "sg:phone":"+1 308 632 7720",
    "sg:postcode":"69361",
    "sg:province":"NE",
    "sg:tags":[
        "medical"
    ],
    "wof:name":"Daniel W Gillette",
    "wof:placetype":"venue"
},
  "geometry": {"coordinates":[-103.66620899999999,41.884483],"type":"Point"}
}