{
  "type": "Feature",
  "properties": {
    "addr:full":"5624 Ames Ave Omaha NE 68104",
    "addr:housenumber":"5624",
    "addr:postcode":"68104",
    "addr:street":"Ames Ave",
    "iso:country":"US",
    "sg:address":"5624 Ames Ave",
    "sg:city":"Omaha",
    "sg:classifiers":[
        {
            "category":"Retail",
            "subcategory":"Laundry & Dry Cleaning",
            "type":"Services"
        }
    ],
    "sg:phone":"+1 402 451 1141",
    "sg:postcode":"68104",
    "sg:province":"NE",
    "sg:tags":[
        "cleaners"
    ],
    "wof:name":"Martinizing Dry Cleaning",
    "wof:placetype":"venue"
},
  "geometry": {"coordinates":[-96.00306999999999,41.299577],"type":"Point"}
}