{
  "type": "Feature",
  "properties": {
    "iso:country":"US",
    "sg:address":"824 N 164th St",
    "sg:city":"Omaha",
    "sg:classifiers":[
        {
            "category":"Building & Trades",
            "subcategory":"Construction",
            "type":"Services"
        }
    ],
    "sg:phone":"+1 402 431 1497",
    "sg:postcode":"68118",
    "sg:province":"NE",
    "sg:tags":[
        "hanging",
        "contractor"
    ],
    "wof:name":"Matt Moragues Painting",
    "wof:placetype":"venue"
},
  "geometry": {"coordinates":[-96.170783,41.270963],"type":"Point"}
}