{
  "type": "Feature",
  "properties": {
    "iso:country":"US",
    "sg:address":"9988 F St",
    "sg:city":"Omaha",
    "sg:classifiers":[
        {
            "category":"Manufacturing",
            "subcategory":"Signs",
            "type":"Manufacturing & Wholesale Goods"
        }
    ],
    "sg:phone":"+1 402 331 3181",
    "sg:postcode":"68127",
    "sg:province":"NE",
    "sg:tags":[
        "mfg",
        "advertising",
        "specialty",
        "rent"
    ],
    "wof:name":"Signs & Shapes International",
    "wof:placetype":"venue"
},
  "geometry": {"coordinates":[-96.06523,41.219738],"type":"Point"}
}