{
  "type": "Feature",
  "properties": {
    "iso:country":"US",
    "sg:address":"9840 S 140th St",
    "sg:city":"Omaha",
    "sg:classifiers":[
        {
            "category":"Building & Trades",
            "subcategory":"Construction",
            "type":"Services"
        }
    ],
    "sg:phone":"+1 402 861 1710",
    "sg:postcode":"68138",
    "sg:province":"NE",
    "sg:tags":[
        "contractor"
    ],
    "wof:name":"Centimark Corporation",
    "wof:placetype":"venue"
},
  "geometry": {"coordinates":[-96.134118,41.171232],"type":"Point"}
}