{
  "type": "Feature",
  "properties": {
    "addr:full":"5411 2nd Ave Kearney NE 68847",
    "addr:housenumber":"5411",
    "addr:postcode":"68847",
    "addr:street":"2Nd Ave",
    "iso:country":"US",
    "sg:address":"5411 2nd Ave",
    "sg:city":"Kearney",
    "sg:classifiers":[
        {
            "category":"Restaurant",
            "type":"Food & Drink"
        }
    ],
    "sg:menulink":"http://www.allmenus.com/ne/kearney/129540-subway/menu/",
    "sg:phone":"+1 308 234 6655",
    "sg:postcode":"68847",
    "sg:province":"NE",
    "sg:tags":[
        "american",
        "sandwich"
    ],
    "wof:name":"Subway",
    "wof:placetype":"venue"
},
  "geometry": {"coordinates":[-99.083718,40.727463],"type":"Point"}
}