{
  "type": "Feature",
  "properties": {
    "addr:full":"1116 Jackson St Omaha NE 68102",
    "addr:housenumber":"1116",
    "addr:postcode":"68102",
    "addr:street":"Jackson St",
    "iso:country":"US",
    "sg:address":"1116 Jackson St",
    "sg:city":"Omaha",
    "sg:classifiers":[
        {
            "category":"Shopping Center",
            "type":"Public Place"
        }
    ],
    "sg:phone":"+1 402 346 9212",
    "sg:postcode":"68102",
    "sg:province":"NE",
    "wof:name":"Second Chance",
    "wof:placetype":"venue"
},
  "geometry": {"coordinates":[-95.931602,41.254501],"type":"Point"}
}