{
  "type": "Feature",
  "properties": {
    "iso:country":"US",
    "sg:address":"311 W 3rd St",
    "sg:city":"Alliance",
    "sg:classifiers":[
        {
            "category":"Retail",
            "subcategory":"Auto Repair",
            "type":"Services"
        },
        {
            "category":"Autos & Motor Vehicles",
            "subcategory":"Auto Supplies",
            "type":"Retail Goods"
        }
    ],
    "sg:phone":"+1 308 762 1516",
    "sg:postcode":"69301",
    "sg:province":"NE",
    "sg:tags":[
        "automotive",
        "parts",
        "automobile"
    ],
    "wof:name":"Carquest Auto Parts Stores",
    "wof:placetype":"venue"
},
  "geometry": {"coordinates":[-102.87483899999999,42.096955],"type":"Point"}
}