{
  "type": "Feature",
  "properties": {
    "addr:full":"40830 Rd 770 Gothenburg NE 69138",
    "addr:postcode":"40830;69138",
    "addr:street":"Rd 770",
    "iso:country":"US",
    "sg:address":"40830 Rd 770",
    "sg:city":"Gothenburg",
    "sg:phone":"+1 308 537 2951",
    "sg:postcode":"69138",
    "sg:province":"NE",
    "sg:tags":[
        "farm",
        "corn"
    ],
    "wof:name":"Roger Pramberg",
    "wof:placetype":"venue"
},
  "geometry": {"coordinates":[-100.223663,40.987755],"type":"Point"}
}