{
  "type": "Feature",
  "properties": {
    "iso:country":"US",
    "sg:address":"20371 Patton St",
    "sg:city":"Gretna",
    "sg:classifiers":[
        {
            "category":"Freight",
            "type":"Transportation"
        }
    ],
    "sg:phone":"+1 402 332 0505",
    "sg:postcode":"68028",
    "sg:province":"NE",
    "sg:tags":[
        "broker",
        "trucking"
    ],
    "wof:name":"Collier Transportation Inc",
    "wof:placetype":"venue"
},
  "geometry": {"coordinates":[-96.23353299999999,41.149625],"type":"Point"}
}