{
  "type": "Feature",
  "properties": {
    "iso:country":"US",
    "sg:address":"802 W 10th St",
    "sg:city":"Yankton",
    "sg:classifiers":[
        {
            "category":"Real Estate",
            "subcategory":"Real Estate Operator",
            "type":"Services"
        }
    ],
    "sg:phone":"+1 605 665 1243",
    "sg:postcode":"57078",
    "sg:province":"NE",
    "sg:tags":[
        "building",
        "apartment"
    ],
    "wof:name":"Park 50 & River Heights",
    "wof:placetype":"venue"
},
  "geometry": {"coordinates":[-97.404808,42.878911],"type":"Point"}
}