{
  "type": "Feature",
  "properties": {
    "addr:full":"3800 Old Cheney Rd Lincoln NE 68516",
    "addr:housenumber":"3800",
    "addr:postcode":"68516",
    "addr:street":"Old Cheney Rd",
    "iso:country":"US",
    "sg:address":"3800 Old Cheney Rd",
    "sg:city":"Lincoln",
    "sg:classifiers":[
        {
            "category":"Building & Trades",
            "subcategory":"Construction",
            "type":"Services"
        }
    ],
    "sg:phone":"+1 402 310 1628",
    "sg:postcode":"68516",
    "sg:province":"NE",
    "sg:tags":[
        "contractor"
    ],
    "wof:name":"J & L Drywall Contracting Inc",
    "wof:placetype":"venue"
},
  "geometry": {"coordinates":[-96.66466800000001,40.755446],"type":"Point"}
}