{
  "type": "Feature",
  "properties": {
    "addr:full":"11425 P St Omaha NE 68137",
    "addr:housenumber":"11425",
    "addr:postcode":"68137",
    "addr:street":"P St",
    "iso:country":"US",
    "sg:address":"11425 P St",
    "sg:city":"Omaha",
    "sg:classifiers":[
        {
            "category":"Freight",
            "type":"Transportation"
        }
    ],
    "sg:phone":"+1 402 331 8850",
    "sg:postcode":"68137",
    "sg:province":"NE",
    "sg:tags":[
        "commercial",
        "storage",
        "special"
    ],
    "wof:name":"Milt's Mini Storage",
    "wof:placetype":"venue"
},
  "geometry": {"coordinates":[-96.092157,41.207026],"type":"Point"}
}