{
  "type": "Feature",
  "properties": {
    "iso:country":"US",
    "sg:address":"5220 NW 38th St",
    "sg:city":"Lincoln",
    "sg:classifiers":[
        {
            "category":"Wholesale",
            "subcategory":"Dairy",
            "type":"Manufacturing & Wholesale Goods"
        }
    ],
    "sg:phone":"+1 402 470 2424",
    "sg:postcode":"68524",
    "sg:province":"NE",
    "sg:tags":[
        "product"
    ],
    "wof:name":"Roberts Dairy Co",
    "wof:placetype":"venue"
},
  "geometry": {"coordinates":[-96.77525900000001,40.862375],"type":"Point"}
}