{
  "type": "Feature",
  "properties": {
    "iso:country":"US",
    "sg:address":"702 Fort Crook Rd N",
    "sg:city":"Bellevue",
    "sg:classifiers":[
        {
            "category":"Health Services",
            "subcategory":"Nursing And Care Facility",
            "type":"Services"
        }
    ],
    "sg:phone":"+1 402 291 9800",
    "sg:postcode":"68005",
    "sg:province":"NE",
    "sg:tags":[
        "intermediate"
    ],
    "wof:name":"Richmont Village Ind Living",
    "wof:placetype":"venue"
},
  "geometry": {"coordinates":[-95.92559,41.171997],"type":"Point"}
}