{
  "type": "Feature",
  "properties": {
    "iso:country":"US",
    "sg:address":"1621 SW 24th St",
    "sg:city":"Lincoln",
    "sg:classifiers":[
        {
            "category":"Building & Trades",
            "subcategory":"Construction",
            "type":"Services"
        }
    ],
    "sg:phone":"+1 402 440 6785",
    "sg:postcode":"68522",
    "sg:province":"NE",
    "sg:tags":[
        "contractor"
    ],
    "wof:name":"Bond Custom Siding",
    "wof:placetype":"venue"
},
  "geometry": {"coordinates":[-96.75371800000001,40.796817],"type":"Point"}
}