{
  "type": "Feature",
  "properties": {
    "iso:country":"US",
    "sg:address":"515 Ridgewood Dr",
    "sg:city":"Bellevue",
    "sg:classifiers":[
        {
            "category":"Professional",
            "type":"Services"
        }
    ],
    "sg:phone":"+1 402 292 0217",
    "sg:postcode":"68005",
    "sg:province":"NE",
    "wof:name":"Olson Mandler Studio/ Gallery",
    "wof:placetype":"venue"
},
  "geometry": {"coordinates":[-95.90407,41.167794],"type":"Point"}
}