{
  "type": "Feature",
  "properties": {
    "iso:country":"US",
    "sg:address":"5522 N 103rd St",
    "sg:city":"Omaha",
    "sg:classifiers":[
        {
            "category":"Restaurant",
            "type":"Food & Drink"
        }
    ],
    "sg:phone":"+1 402 965 3333",
    "sg:postcode":"68134",
    "sg:province":"NE",
    "sg:tags":[
        "eating"
    ],
    "wof:name":"Chopsticks House Inc",
    "wof:placetype":"venue"
},
  "geometry": {"coordinates":[-96.07384500000001,41.306857],"type":"Point"}
}