{
  "type": "Feature",
  "properties": {
    "iso:country":"US",
    "sg:address":"6515 Davenport Plz",
    "sg:city":"Omaha",
    "sg:classifiers":[
        {
            "category":"Wholesale",
            "subcategory":"Drugs",
            "type":"Manufacturing & Wholesale Goods"
        }
    ],
    "sg:phone":"+1 402 346 1506",
    "sg:postcode":"68132",
    "sg:province":"NE",
    "wof:name":"Belmont Medical Supply Co",
    "wof:placetype":"venue"
},
  "geometry": {"coordinates":[-96.012969,41.260678],"type":"Point"}
}