{
  "type": "Feature",
  "properties": {
    "iso:country":"US",
    "sg:address":"5260 Drexel St",
    "sg:city":"Omaha",
    "sg:classifiers":[
        {
            "category":"Recreation",
            "type":"Entertainment"
        }
    ],
    "sg:phone":"+1 402 731 2574",
    "sg:postcode":"68117",
    "sg:province":"NE",
    "wof:name":"Cosmic Monsters Inc",
    "wof:placetype":"venue"
},
  "geometry": {"coordinates":[-95.999087,41.192513],"type":"Point"}
}