{
  "type": "Feature",
  "properties": {
    "iso:country":"US",
    "sg:address":"2212 Chandler Rd W",
    "sg:city":"Bellevue",
    "sg:classifiers":[
        {
            "category":"Wholesale",
            "subcategory":"Scrap",
            "type":"Manufacturing & Wholesale Goods"
        }
    ],
    "sg:phone":"+1 402 734 7544",
    "sg:postcode":"68147",
    "sg:province":"NE",
    "sg:tags":[
        "recycling",
        "center"
    ],
    "wof:name":"Can Pak Recycling Inc South",
    "wof:placetype":"venue"
},
  "geometry": {"coordinates":[-95.944996,41.183732],"type":"Point"}
}