{
  "type": "Feature",
  "properties": {
    "addr:full":"623 S 56th St Omaha NE 68106",
    "addr:housenumber":"623",
    "addr:postcode":"68106",
    "addr:street":"S 56Th St",
    "iso:country":"US",
    "sg:address":"623 S 56th St",
    "sg:city":"Omaha",
    "sg:classifiers":[
        {
            "category":"Social Services",
            "type":"Services"
        }
    ],
    "sg:phone":"+1 402 558 7788",
    "sg:postcode":"68106",
    "sg:province":"NE",
    "wof:name":"Lisa Basile",
    "wof:placetype":"venue"
},
  "geometry": {"coordinates":[-95.999456,41.254016],"type":"Point"}
}