{
  "type": "Feature",
  "properties": {
    "iso:country":"US",
    "sg:address":"8800 S 55th St",
    "sg:city":"Lincoln",
    "sg:classifiers":[
        {
            "category":"Real Estate",
            "subcategory":"Real Estate Agent",
            "type":"Services"
        }
    ],
    "sg:phone":"+1 402 440 5064",
    "sg:postcode":"68516",
    "sg:province":"NE",
    "sg:tags":[
        "inspection"
    ],
    "wof:name":"Code-Pro",
    "wof:placetype":"venue"
},
  "geometry": {"coordinates":[-96.646169,40.723597],"type":"Point"}
}