{
  "type": "Feature",
  "properties": {
    "iso:country":"US",
    "sg:address":"13423 F St",
    "sg:city":"Omaha",
    "sg:classifiers":[
        {
            "category":"Banks & Credit Unions",
            "subcategory":"Investment Brokerage",
            "type":"Services"
        }
    ],
    "sg:phone":"+1 402 343 0400",
    "sg:postcode":"68137",
    "sg:province":"NE",
    "sg:tags":[
        "advisory"
    ],
    "wof:name":"Alvano Capital LLC",
    "wof:placetype":"venue"
},
  "geometry": {"coordinates":[-96.126195,41.219476],"type":"Point"}
}