{
  "type": "Feature",
  "properties": {
    "addr:full":"1116 10th Ave Sidney NE 69162",
    "addr:housenumber":"1116",
    "addr:postcode":"69162",
    "addr:street":"10Th Ave",
    "iso:country":"US",
    "sg:address":"1116 10th Ave",
    "sg:city":"Sidney",
    "sg:classifiers":[
        {
            "category":"Health Services",
            "subcategory":"Doctor",
            "type":"Services"
        }
    ],
    "sg:phone":"+1 308 254 5575",
    "sg:postcode":"69162",
    "sg:province":"NE",
    "sg:tags":[
        "physician",
        "surgeon"
    ],
    "wof:name":"Harold W Keenan MD",
    "wof:placetype":"venue"
},
  "geometry": {"coordinates":[-102.976707,41.142688],"type":"Point"}
}