{
  "type": "Feature",
  "properties": {
    "iso:country":"US",
    "sg:address":"153 Bordeaux St",
    "sg:city":"Chadron",
    "sg:classifiers":[
        {
            "category":"Professional",
            "subcategory":"Business Services",
            "type":"Services"
        }
    ],
    "sg:phone":"+1 308 432 9582",
    "sg:postcode":"69337",
    "sg:province":"NE",
    "sg:website":"www.nature.org",
    "wof:name":"Nature Conservancy",
    "wof:placetype":"venue"
},
  "geometry": {"coordinates":[-102.999104,42.831589],"type":"Point"}
}