{
  "type": "Feature",
  "properties": {
    "iso:country":"US",
    "sg:address":"1109 S Baltimore Ave",
    "sg:city":"Hastings",
    "sg:classifiers":[
        {
            "category":"Restaurant",
            "type":"Food & Drink"
        }
    ],
    "sg:phone":"+1 402 463 4666",
    "sg:postcode":"68901",
    "sg:province":"NE",
    "wof:name":"Bernardo's Steak House",
    "wof:placetype":"venue"
},
  "geometry": {"coordinates":[-98.402052,40.569521],"type":"Point"}
}