{
  "type": "Feature",
  "properties": {
    "addr:full":"14522 Saratoga St Omaha NE 68116",
    "addr:housenumber":"14522",
    "addr:postcode":"68116",
    "addr:street":"Saratoga St",
    "iso:country":"US",
    "sg:address":"14522 Saratoga St",
    "sg:city":"Omaha",
    "sg:classifiers":[
        {
            "category":"Building & Trades",
            "subcategory":"Construction",
            "type":"Services"
        }
    ],
    "sg:phone":"+1 402 991 4777",
    "sg:postcode":"68116",
    "sg:province":"NE",
    "sg:tags":[
        "house"
    ],
    "wof:name":"Environmental Builders Inc",
    "wof:placetype":"venue"
},
  "geometry": {"coordinates":[-96.141997,41.303024],"type":"Point"}
}