{
  "type": "Feature",
  "properties": {
    "iso:country":"US",
    "sg:address":"6139 O St",
    "sg:city":"Omaha",
    "sg:classifiers":[
        {
            "category":"Building & Trades",
            "subcategory":"Construction",
            "type":"Services"
        }
    ],
    "sg:phone":"+1 402 731 5622",
    "sg:postcode":"68117",
    "sg:province":"NE",
    "sg:tags":[
        "excavating",
        "contractor"
    ],
    "wof:name":"T & R Excavating Inc",
    "wof:placetype":"venue"
},
  "geometry": {"coordinates":[-96.00788300000001,41.208366],"type":"Point"}
}