{
  "type": "Feature",
  "properties": {
    "iso:country":"US",
    "sg:address":"1410 Wall St",
    "sg:city":"Bellevue",
    "sg:classifiers":[
        {
            "category":"Professional",
            "subcategory":"Computer Services",
            "type":"Services"
        }
    ],
    "sg:phone":"+1 402 827 5800",
    "sg:postcode":"68005",
    "sg:province":"NE",
    "sg:tags":[
        "consultant",
        "designer"
    ],
    "wof:name":"BAE Systems",
    "wof:placetype":"venue"
},
  "geometry": {"coordinates":[-95.911017,41.142929],"type":"Point"}
}