{
  "type": "Feature",
  "properties": {
    "addr:full":"724 S D St Broken Bow NE 68822",
    "addr:housenumber":"724",
    "addr:postcode":"68822",
    "addr:street":"S D St",
    "iso:country":"US",
    "sg:address":"724 S D St",
    "sg:city":"Broken Bow",
    "sg:classifiers":[
        {
            "category":"Autos & Motor Vehicles",
            "subcategory":"Auto Supplies",
            "type":"Retail Goods"
        }
    ],
    "sg:phone":"+1 308 872 3233",
    "sg:postcode":"68822",
    "sg:province":"NE",
    "wof:name":"Joshua Tree Wood Trim LLC",
    "wof:placetype":"venue"
},
  "geometry": {"coordinates":[-99.639186,41.402592],"type":"Point"}
}