{
  "type": "Feature",
  "properties": {
    "iso:country":"US",
    "sg:address":"1824 N St",
    "sg:city":"Auburn",
    "sg:classifiers":[
        {
            "category":"Government",
            "subcategory":"Office",
            "type":"Public Place"
        }
    ],
    "sg:phone":"+1 402 274 4756",
    "sg:postcode":"68305",
    "sg:province":"NE",
    "wof:name":"Nemaha County Weed Control",
    "wof:placetype":"venue"
},
  "geometry": {"coordinates":[-95.84407899999999,40.386275],"type":"Point"}
}