{
  "type": "Feature",
  "properties": {
    "addr:full":"4225 S 57th St Omaha NE 68117",
    "addr:housenumber":"4225",
    "addr:postcode":"68117",
    "addr:street":"S 57Th St",
    "iso:country":"US",
    "sg:address":"4225 S 57th St",
    "sg:city":"Omaha",
    "sg:classifiers":[
        {
            "category":"Shopping",
            "subcategory":"Pharmacy",
            "type":"Retail Goods"
        }
    ],
    "sg:phone":"+1 402 734 4117",
    "sg:postcode":"68117",
    "sg:province":"NE",
    "sg:website":"www.cardinal.com",
    "wof:name":"Cardinal Health",
    "wof:placetype":"venue"
},
  "geometry": {"coordinates":[-96.001003,41.217838],"type":"Point"}
}