{
  "type": "Feature",
  "properties": {
    "iso:country":"US",
    "sg:address":"2127 S 156th Cir",
    "sg:city":"Omaha",
    "sg:classifiers":[
        {
            "category":"Building & Trades",
            "subcategory":"Construction",
            "type":"Services"
        }
    ],
    "sg:phone":"+1 402 492 9494",
    "sg:postcode":"68130",
    "sg:province":"NE",
    "sg:tags":[
        "roofing",
        "contractor"
    ],
    "wof:name":"Millard Roofing Co",
    "wof:placetype":"venue"
},
  "geometry": {"coordinates":[-96.157184,41.235387],"type":"Point"}
}