{
  "type": "Feature",
  "properties": {
    "addr:full":"4464 US Hwy 30 Kearney NE 68845",
    "addr:housenumber":"4464",
    "addr:postcode":"68845",
    "addr:street":"Us Hwy 30",
    "iso:country":"US",
    "sg:address":"4464 US Hwy 30",
    "sg:city":"Kearney",
    "sg:classifiers":[
        {
            "category":"Real Estate",
            "subcategory":"Real Estate Operator",
            "type":"Services"
        }
    ],
    "sg:phone":"+1 308 237 3585",
    "sg:postcode":"68845",
    "sg:province":"NE",
    "sg:tags":[
        "mobile",
        "home",
        "community"
    ],
    "wof:name":"Sheen's Trailer Court",
    "wof:placetype":"venue"
},
  "geometry": {"coordinates":[-99.131062,40.699331],"type":"Point"}
}