{
  "type": "Feature",
  "properties": {
    "addr:full":"925 Pierce St Omaha NE 68108",
    "addr:housenumber":"925",
    "addr:postcode":"68108",
    "addr:street":"Pierce St",
    "iso:country":"US",
    "sg:address":"925 Pierce St",
    "sg:city":"Omaha",
    "sg:classifiers":[
        {
            "category":"Autos & Motor Vehicles",
            "subcategory":"Automobile Sales",
            "type":"Retail Goods"
        }
    ],
    "sg:phone":"+1 402 346 6753",
    "sg:postcode":"68108",
    "sg:province":"NE",
    "sg:tags":[
        "car",
        "dealer"
    ],
    "wof:name":"Sunrise Used Car Lot",
    "wof:placetype":"venue"
},
  "geometry": {"coordinates":[-95.929079,41.248003],"type":"Point"}
}