{
  "type": "Feature",
  "properties": {
    "iso:country":"US",
    "sg:address":"7355 Dodge St",
    "sg:city":"Omaha",
    "sg:classifiers":[
        {
            "category":"Shopping",
            "subcategory":"Musical Instruments",
            "type":"Retail Goods"
        },
        {
            "category":"Arts & Performance",
            "subcategory":"Music",
            "type":"Entertainment"
        },
        {
            "category":"Retail",
            "subcategory":"Repair Shop",
            "type":"Services"
        },
        {
            "category":"Manufacturing",
            "subcategory":"Musical Instruments",
            "type":"Manufacturing & Wholesale Goods"
        }
    ],
    "sg:phone":"+1 402 391 5588",
    "sg:postcode":"68114",
    "sg:province":"NE",
    "sg:tags":[
        "sheet",
        "organ",
        "supply",
        "instruments-repair",
        "pianos-parts",
        "instruments-rental",
        "piano"
    ],
    "sg:website":"http://www.schmittmusic.com",
    "wof:name":"Schmitt Music",
    "wof:placetype":"venue"
},
  "geometry": {"coordinates":[-96.027011,41.259659],"type":"Point"}
}