{
  "type": "Feature",
  "properties": {
    "addr:full":"7880 L St Omaha NE 68127",
    "addr:housenumber":"7880",
    "addr:postcode":"68127",
    "addr:street":"L St",
    "iso:country":"US",
    "sg:address":"7880 L St",
    "sg:city":"Omaha",
    "sg:classifiers":[
        {
            "category":"Restaurant",
            "type":"Food & Drink"
        }
    ],
    "sg:phone":"+1 402 339 5050",
    "sg:postcode":"68127",
    "sg:province":"NE",
    "sg:tags":[
        "drinking",
        "eating"
    ],
    "wof:name":"Johnnys Sortinos Pizza",
    "wof:placetype":"venue"
},
  "geometry": {"coordinates":[-96.03497400000001,41.212598],"type":"Point"}
}