{
  "type": "Feature",
  "properties": {
    "iso:country":"US",
    "sg:address":"810 N 107th Ave",
    "sg:city":"Omaha",
    "sg:classifiers":[
        {
            "category":"Building & Trades",
            "subcategory":"Construction",
            "type":"Services"
        }
    ],
    "sg:phone":"+1 402 498 0980",
    "sg:postcode":"68114",
    "sg:province":"NE",
    "sg:tags":[
        "home",
        "builder"
    ],
    "wof:name":"J Z Jizba Builder",
    "wof:placetype":"venue"
},
  "geometry": {"coordinates":[-96.08071,41.268109],"type":"Point"}
}