{
  "type": "Feature",
  "properties": {
    "iso:country":"US",
    "sg:address":"2401 N 51st St",
    "sg:city":"Lincoln",
    "sg:classifiers":[
        {
            "category":"Education",
            "subcategory":"College",
            "type":"Public Place"
        }
    ],
    "sg:phone":"+1 402 464 9809",
    "sg:postcode":"68504",
    "sg:province":"NE",
    "wof:name":"University of Nebraska",
    "wof:placetype":"venue"
},
  "geometry": {"coordinates":[-96.649749,40.837274],"type":"Point"}
}