{
  "type": "Feature",
  "properties": {
    "addr:full":"1245 Libra Dr Lincoln NE 68512",
    "addr:housenumber":"1245",
    "addr:postcode":"68512",
    "addr:street":"Libra Dr",
    "iso:country":"US",
    "sg:address":"1245 Libra Dr",
    "sg:city":"Lincoln",
    "sg:classifiers":[
        {
            "category":"Bars & Pubs",
            "type":"Food & Drink"
        }
    ],
    "sg:menulink":"http://www.allmenus.com/ne/lincoln/244707-slapshotz-bar--grill/menu/",
    "sg:phone":"+1 402 420 7825",
    "sg:postcode":"68512",
    "sg:province":"NE",
    "sg:tags":[
        "american"
    ],
    "wof:name":"Slapshotz Bar & Grill",
    "wof:placetype":"venue"
},
  "geometry": {"coordinates":[-96.70290799999999,40.734501],"type":"Point"}
}