{
  "type": "Feature",
  "properties": {
    "iso:country":"US",
    "sg:address":"4766 Crestview Dr",
    "sg:city":"Blair",
    "sg:classifiers":[
        {
            "category":"Manufacturing",
            "subcategory":"Printing",
            "type":"Manufacturing & Wholesale Goods"
        }
    ],
    "sg:phone":"+1 402 426 4538",
    "sg:postcode":"68008",
    "sg:province":"NE",
    "sg:tags":[
        "commercial"
    ],
    "wof:name":"Maragaret Stoltz & Marlys",
    "wof:placetype":"venue"
},
  "geometry": {"coordinates":[-96.119135,41.445989],"type":"Point"}
}