{
  "type": "Feature",
  "properties": {
    "iso:country":"US",
    "sg:address":"710 12th St",
    "sg:city":"Gothenburg",
    "sg:classifiers":[
        {
            "category":"Social Services",
            "type":"Services"
        }
    ],
    "sg:phone":"+1 308 537 2633",
    "sg:postcode":"69138",
    "sg:province":"NE",
    "wof:name":"Building Blocks Child Care",
    "wof:placetype":"venue"
},
  "geometry": {"coordinates":[-100.155738,40.930192],"type":"Point"}
}