{
  "type": "Feature",
  "properties": {
    "addr:full":"4235 S 48th St Lincoln NE 68506",
    "addr:housenumber":"4235",
    "addr:postcode":"68506",
    "addr:street":"S 48Th St",
    "iso:country":"US",
    "sg:address":"4235 S 48th St",
    "sg:city":"Lincoln",
    "sg:classifiers":[
        {
            "category":"Autos & Motor Vehicles",
            "subcategory":"Fuel & Gas Station",
            "type":"Retail Goods"
        }
    ],
    "sg:phone":"+1 402 488 5115",
    "sg:postcode":"68506",
    "sg:province":"NE",
    "sg:tags":[
        "station",
        "gasoline"
    ],
    "wof:name":"Pioneers 66 Inc",
    "wof:placetype":"venue"
},
  "geometry": {"coordinates":[-96.654156,40.770535],"type":"Point"}
}