{
  "type": "Feature",
  "properties": {
    "addr:full":"980 E St Utica NE 68456",
    "addr:housenumber":"980",
    "addr:postcode":"68456",
    "addr:street":"E St",
    "iso:country":"US",
    "sg:address":"980 E St",
    "sg:city":"Utica",
    "sg:classifiers":[
        {
            "category":"Freight",
            "type":"Transportation"
        }
    ],
    "sg:phone":"+1 402 534 2013",
    "sg:postcode":"68456",
    "sg:province":"NE",
    "sg:tags":[
        "broker",
        "trucking"
    ],
    "wof:name":"M & G Leasing",
    "wof:placetype":"venue"
},
  "geometry": {"coordinates":[-97.34604299999999,40.893125],"type":"Point"}
}