{
  "type": "Feature",
  "properties": {
    "iso:country":"US",
    "sg:address":"416 S 14th St",
    "sg:city":"Omaha",
    "sg:classifiers":[
        {
            "category":"Wholesale",
            "subcategory":"Construction Materials",
            "type":"Manufacturing & Wholesale Goods"
        },
        {
            "category":"Wholesale",
            "subcategory":"Durable Goods & Equipment",
            "type":"Manufacturing & Wholesale Goods"
        }
    ],
    "sg:phone":"+1 402 342 2920",
    "sg:postcode":"68102",
    "sg:province":"NE",
    "sg:tags":[
        "product",
        "representative",
        "manufacturer"
    ],
    "sg:website":"www.emanuelcs.com",
    "wof:name":"Emanuel Construction Spec",
    "wof:placetype":"venue"
},
  "geometry": {"coordinates":[-95.934624,41.255653],"type":"Point"}
}