{
  "type": "Feature",
  "properties": {
    "addr:full":"1008 Scott St Plattsmouth NE 68048",
    "addr:housenumber":"1008",
    "addr:postcode":"68048",
    "addr:street":"Scott St",
    "iso:country":"US",
    "sg:address":"1008 Scott St",
    "sg:city":"Plattsmouth",
    "sg:classifiers":[
        {
            "category":"Building & Trades",
            "subcategory":"Cleaning & Sanitation",
            "type":"Services"
        }
    ],
    "sg:phone":"+1 402 296 2352",
    "sg:postcode":"68048",
    "sg:province":"NE",
    "sg:tags":[
        "janitorial"
    ],
    "wof:name":"Cipag Partners LLC",
    "wof:placetype":"venue"
},
  "geometry": {"coordinates":[-95.893822,41.001752],"type":"Point"}
}