{
  "type": "Feature",
  "properties": {
    "iso:country":"US",
    "sg:address":"800 S 10th St",
    "sg:city":"Beatrice",
    "sg:classifiers":[
        {
            "category":"Building & Trades",
            "subcategory":"Construction",
            "type":"Services"
        }
    ],
    "sg:phone":"+1 402 228 2381",
    "sg:postcode":"68310",
    "sg:province":"NE",
    "sg:tags":[
        "general",
        "contractor"
    ],
    "wof:name":"D-K Contracting",
    "wof:placetype":"venue"
},
  "geometry": {"coordinates":[-96.74122300000001,40.259472],"type":"Point"}
}