{
  "type": "Feature",
  "properties": {
    "iso:country":"US",
    "sg:address":"1100 Niobrara Ave",
    "sg:city":"Hemingford",
    "sg:classifiers":[
        {
            "category":"Recreation",
            "type":"Entertainment"
        }
    ],
    "sg:phone":"+1 308 487 5223",
    "sg:postcode":"69348",
    "sg:province":"NE",
    "sg:tags":[
        "carnival"
    ],
    "wof:name":"Box Butte Co Fair Mangr",
    "wof:placetype":"venue"
},
  "geometry": {"coordinates":[-103.08093,42.321543],"type":"Point"}
}