{
  "type": "Feature",
  "properties": {
    "iso:country":"US",
    "sg:address":"145 S Kansas St",
    "sg:city":"Superior",
    "sg:classifiers":[
        {
            "category":"Wholesale",
            "subcategory":"Toys & Hobbies",
            "type":"Manufacturing & Wholesale Goods"
        }
    ],
    "sg:phone":"+1 402 879 4989",
    "sg:postcode":"68978",
    "sg:province":"NE",
    "wof:name":"Woodworking & Crafts",
    "wof:placetype":"venue"
},
  "geometry": {"coordinates":[-98.068743,40.015912],"type":"Point"}
}