{
  "type": "Feature",
  "properties": {
    "iso:country":"US",
    "sg:address":"6105 O St",
    "sg:city":"Lincoln",
    "sg:classifiers":[
        {
            "category":"Restaurant",
            "type":"Food & Drink"
        }
    ],
    "sg:phone":"+1 402 483 6688",
    "sg:postcode":"68510",
    "sg:province":"NE",
    "sg:tags":[
        "eating"
    ],
    "wof:name":"Big Apple Bagels",
    "wof:placetype":"venue"
},
  "geometry": {"coordinates":[-96.635682,40.813254],"type":"Point"}
}