{
  "type": "Feature",
  "properties": {
    "iso:country":"US",
    "sg:address":"13911 Gold Cir",
    "sg:city":"Omaha",
    "sg:classifiers":[
        {
            "category":"Personal",
            "type":"Services"
        }
    ],
    "sg:phone":"+1 402 758 7074",
    "sg:postcode":"68144",
    "sg:province":"NE",
    "sg:tags":[
        "control",
        "weight"
    ],
    "wof:name":"Mind Your Potential Hypnthrpy",
    "wof:placetype":"venue"
},
  "geometry": {"coordinates":[-96.13057000000001,41.234905],"type":"Point"}
}