{
  "type": "Feature",
  "properties": {
    "iso:country":"US",
    "sg:address":"10334 P St",
    "sg:city":"Omaha",
    "sg:classifiers":[
        {
            "category":"Utilities",
            "subcategory":"Telephone",
            "type":"Services"
        }
    ],
    "sg:phone":"+1 402 593 0691",
    "sg:postcode":"68127",
    "sg:province":"NE",
    "sg:tags":[
        "communications"
    ],
    "wof:name":"Gary Thompson",
    "wof:placetype":"venue"
},
  "geometry": {"coordinates":[-96.073993,41.207313],"type":"Point"}
}