{
  "type": "Feature",
  "properties": {
    "addr:full":"7711 L St Omaha NE 68127",
    "addr:housenumber":"7711",
    "addr:postcode":"68127",
    "addr:street":"L St",
    "iso:country":"US",
    "sg:address":"7711 L St",
    "sg:city":"Omaha",
    "sg:classifiers":[
        {
            "category":"Insurance",
            "subcategory":"Insurance Agent",
            "type":"Services"
        }
    ],
    "sg:phone":"+1 402 339 6348",
    "sg:postcode":"68127",
    "sg:province":"NE",
    "wof:name":"Farm Bureau Insurance",
    "wof:placetype":"venue"
},
  "geometry": {"coordinates":[-96.03309400000001,41.212446],"type":"Point"}
}