{
  "type": "Feature",
  "properties": {
    "iso:country":"US",
    "sg:address":"5317 W Kingsley St",
    "sg:city":"Lincoln",
    "sg:classifiers":[
        {
            "category":"Retail",
            "subcategory":"Repair Shop",
            "type":"Services"
        }
    ],
    "sg:phone":"+1 402 470 3429",
    "sg:postcode":"68524",
    "sg:province":"NE",
    "sg:tags":[
        "cleaning"
    ],
    "wof:name":"Marys Cleaning Service",
    "wof:placetype":"venue"
},
  "geometry": {"coordinates":[-96.793823,40.84452],"type":"Point"}
}