{
  "type": "Feature",
  "properties": {
    "iso:country":"US",
    "sg:address":"2151 32nd Ave",
    "sg:city":"Columbus",
    "sg:classifiers":[
        {
            "category":"Shopping",
            "type":"Retail Goods"
        }
    ],
    "sg:phone":"+1 402 564 6698",
    "sg:postcode":"68601",
    "sg:province":"NE",
    "sg:tags":[
        "merchandise"
    ],
    "wof:name":"B L TS",
    "wof:placetype":"venue"
},
  "geometry": {"coordinates":[-97.366778,41.437883],"type":"Point"}
}