{
  "type": "Feature",
  "properties": {
    "addr:full":"135 N 5th St Albion NE 68620",
    "addr:housenumber":"135",
    "addr:postcode":"68620",
    "addr:street":"N 5Th St",
    "iso:country":"US",
    "sg:address":"135 N 5th St",
    "sg:city":"Albion",
    "sg:classifiers":[
        {
            "category":"Autos & Motor Vehicles",
            "subcategory":"Auto Supplies",
            "type":"Retail Goods"
        }
    ],
    "sg:phone":"+1 402 395 2169",
    "sg:postcode":"68620",
    "sg:province":"NE",
    "sg:tags":[
        "automobile",
        "parts"
    ],
    "wof:name":"NAPA Auto Parts",
    "wof:placetype":"venue"
},
  "geometry": {"coordinates":[-98.002481,41.693024],"type":"Point"}
}