{
  "type": "Feature",
  "properties": {
    "iso:country":"US",
    "sg:address":"2509 S 11th St",
    "sg:city":"Nebraska City",
    "sg:classifiers":[
        {
            "category":"Restaurant",
            "type":"Food & Drink"
        }
    ],
    "sg:menulink":"http://www.allmenus.com/ne/nebraska-city/129499-subway/menu/",
    "sg:phone":"+1 402 873 4200",
    "sg:postcode":"68410",
    "sg:province":"NE",
    "sg:tags":[
        "american",
        "sandwich"
    ],
    "wof:name":"Subway",
    "wof:placetype":"venue"
},
  "geometry": {"coordinates":[-95.859054,40.653843],"type":"Point"}
}