{
  "type": "Feature",
  "properties": {
    "iso:country":"US",
    "sg:address":"295 N 8th Ave",
    "sg:city":"Burwell",
    "sg:classifiers":[
        {
            "category":"Health Services",
            "subcategory":"Nursing And Care Facility",
            "type":"Services"
        }
    ],
    "sg:phone":"+1 308 346 4444",
    "sg:postcode":"68823",
    "sg:province":"NE",
    "sg:tags":[
        "home",
        "convalescent"
    ],
    "wof:name":"Community Memorial Health Ctr",
    "wof:placetype":"venue"
},
  "geometry": {"coordinates":[-99.13525799999999,41.783562],"type":"Point"}
}