{
  "type": "Feature",
  "properties": {
    "iso:country":"US",
    "sg:address":"244 S 13th St",
    "sg:city":"Geneva",
    "sg:classifiers":[
        {
            "category":"Retail",
            "subcategory":"Auto Repair",
            "type":"Services"
        }
    ],
    "sg:phone":"+1 402 759 4068",
    "sg:postcode":"68361",
    "sg:province":"NE",
    "sg:tags":[
        "repairing",
        "automobile"
    ],
    "wof:name":"B & J Automotive",
    "wof:placetype":"venue"
},
  "geometry": {"coordinates":[-97.59587500000001,40.523762],"type":"Point"}
}