{
  "type": "Feature",
  "properties": {
    "iso:country":"US",
    "sg:address":"2411 N Howard Ave",
    "sg:city":"Grand Island",
    "sg:classifiers":[
        {
            "category":"Farming",
            "subcategory":"Farm",
            "type":"Manufacturing & Wholesale Goods"
        }
    ],
    "sg:phone":"+1 308 389 4732",
    "sg:postcode":"68803",
    "sg:province":"NE",
    "sg:tags":[
        "crop",
        "general"
    ],
    "wof:name":"Three D Farms",
    "wof:placetype":"venue"
},
  "geometry": {"coordinates":[-98.369643,40.945834],"type":"Point"}
}