{
  "type": "Feature",
  "properties": {
    "iso:country":"US",
    "sg:address":"1314 N 70th Ave",
    "sg:city":"Omaha",
    "sg:classifiers":[
        {
            "category":"Manufacturing",
            "subcategory":"Signs",
            "type":"Manufacturing & Wholesale Goods"
        }
    ],
    "sg:phone":"+1 402 895 8918",
    "sg:postcode":"68132",
    "sg:province":"NE",
    "wof:name":"Signs & Stuff",
    "wof:placetype":"venue"
},
  "geometry": {"coordinates":[-96.02155,41.272228],"type":"Point"}
}