{
  "type": "Feature",
  "properties": {
    "iso:country":"US",
    "sg:address":"127 A Rd",
    "sg:city":"Grand Island",
    "sg:classifiers":[
        {
            "category":"Farming",
            "subcategory":"Livestock Farm",
            "type":"Manufacturing & Wholesale Goods"
        }
    ],
    "sg:phone":"+1 308 382 0381",
    "sg:postcode":"68801",
    "sg:province":"NE",
    "sg:tags":[
        "beef",
        "feedlot",
        "cattle"
    ],
    "wof:name":"Mark & Gerald Sweeley",
    "wof:placetype":"venue"
},
  "geometry": {"coordinates":[-98.281176,40.930376],"type":"Point"}
}