{
  "type": "Feature",
  "properties": {
    "addr:full":"4611 W Adams St Lincoln NE 68524",
    "addr:housenumber":"4611",
    "addr:postcode":"68524",
    "addr:street":"W Adams St",
    "iso:country":"US",
    "sg:address":"4611 W Adams St",
    "sg:city":"Lincoln",
    "sg:classifiers":[
        {
            "category":"Wholesale",
            "subcategory":"Meat",
            "type":"Manufacturing & Wholesale Goods"
        }
    ],
    "sg:phone":"+1 402 470 4300",
    "sg:postcode":"68524",
    "sg:province":"NE",
    "sg:tags":[
        "plant",
        "processing"
    ],
    "wof:name":"Standard Meat Company LLC",
    "wof:placetype":"venue"
},
  "geometry": {"coordinates":[-96.788178,40.842705],"type":"Point"}
}