{
  "type": "Feature",
  "properties": {
    "iso:country":"US",
    "sg:address":"7207 Graceland Dr",
    "sg:city":"Omaha",
    "sg:classifiers":[
        {
            "category":"Professional",
            "type":"Services"
        }
    ],
    "sg:phone":"+1 402 572 9250",
    "sg:postcode":"68134",
    "sg:province":"NE",
    "sg:tags":[
        "machinery"
    ],
    "wof:name":"Pride Home Services Inc",
    "wof:placetype":"venue"
},
  "geometry": {"coordinates":[-96.024147,41.295793],"type":"Point"}
}