{
  "type": "Feature",
  "properties": {
    "addr:full":"8114 N 30th St Omaha NE 68112",
    "addr:housenumber":"8114",
    "addr:postcode":"68112",
    "addr:street":"N 30Th St",
    "iso:country":"US",
    "sg:address":"8114 N 30th St",
    "sg:city":"Omaha",
    "sg:classifiers":[
        {
            "category":"Building & Trades",
            "subcategory":"Construction",
            "type":"Services"
        }
    ],
    "sg:phone":"+1 402 457 6959",
    "sg:postcode":"68112",
    "sg:province":"NE",
    "sg:tags":[
        "carpentry",
        "contractor"
    ],
    "wof:name":"Architectural Woodworking Spc",
    "wof:placetype":"venue"
},
  "geometry": {"coordinates":[-95.9599,41.334211],"type":"Point"}
}