{
  "type": "Feature",
  "properties": {
    "addr:full":"1220 Peach St Lincoln NE 68502",
    "addr:housenumber":"1220",
    "addr:postcode":"68502",
    "addr:street":"Peach St",
    "iso:country":"US",
    "sg:address":"1220 Peach St",
    "sg:city":"Lincoln",
    "sg:classifiers":[
        {
            "category":"Building & Trades",
            "subcategory":"Construction",
            "type":"Services"
        }
    ],
    "sg:phone":"+1 402 525 6345",
    "sg:postcode":"68502",
    "sg:province":"NE",
    "sg:tags":[
        "water",
        "restoration",
        "damage"
    ],
    "wof:name":"Disaster Restoration Systems",
    "wof:placetype":"venue"
},
  "geometry": {"coordinates":[-96.702996,40.793783],"type":"Point"}
}