{
  "type": "Feature",
  "properties": {
    "addr:full":"3215 Cuming St Omaha NE 68131",
    "addr:housenumber":"3215",
    "addr:postcode":"68131",
    "addr:street":"Cuming St",
    "iso:country":"US",
    "sg:address":"3215 Cuming St",
    "sg:city":"Omaha",
    "sg:classifiers":[
        {
            "category":"Professional",
            "subcategory":"Management & Consulting",
            "type":"Services"
        }
    ],
    "sg:phone":"+1 402 554 1111",
    "sg:postcode":"68131",
    "sg:province":"NE",
    "sg:tags":[
        "consultant",
        "safety"
    ],
    "wof:name":"Ops Crisis Line",
    "wof:placetype":"venue"
},
  "geometry": {"coordinates":[-95.961046,41.267901],"type":"Point"}
}