{
  "type": "Feature",
  "properties": {
    "addr:full":"3310 P St Lincoln NE 68503",
    "addr:housenumber":"3310 p",
    "addr:postcode":"68503",
    "addr:street":"St",
    "iso:country":"US",
    "sg:address":"3310 P St",
    "sg:city":"Lincoln",
    "sg:classifiers":[
        {
            "category":"Professional",
            "subcategory":"Business Services",
            "type":"Services"
        }
    ],
    "sg:phone":"+1 402 742 3404",
    "sg:postcode":"68503",
    "sg:province":"NE",
    "wof:name":"Wendy Duerfeldt",
    "wof:placetype":"venue"
},
  "geometry": {"coordinates":[-96.67161400000001,40.814588],"type":"Point"}
}