{
  "type": "Feature",
  "properties": {
    "addr:full":"4105 B Rd Avoca NE 68307",
    "addr:housenumber":"4105 b",
    "addr:postcode":"68307",
    "addr:street":"Rd",
    "iso:country":"US",
    "sg:address":"4105 B Rd",
    "sg:city":"Avoca",
    "sg:classifiers":[
        {
            "category":"Farming",
            "subcategory":"Farm",
            "type":"Manufacturing & Wholesale Goods"
        }
    ],
    "sg:phone":"+1 402 275 3226",
    "sg:postcode":"68307",
    "sg:province":"NE",
    "sg:tags":[
        "crop",
        "general"
    ],
    "wof:name":"Thoms Terry",
    "wof:placetype":"venue"
},
  "geometry": {"coordinates":[-96.072881,40.769681],"type":"Point"}
}