{
  "type": "Feature",
  "properties": {
    "addr:full":"7300 Dodge St Omaha NE 68114",
    "addr:housenumber":"7300",
    "addr:postcode":"68114",
    "addr:street":"Dodge St",
    "iso:country":"US",
    "sg:address":"7300 Dodge St",
    "sg:city":"Omaha",
    "sg:classifiers":[
        {
            "category":"Home & Garden",
            "subcategory":"Home Furnishings",
            "type":"Retail Goods"
        }
    ],
    "sg:phone":"+1 402 991 3420",
    "sg:postcode":"68114",
    "sg:province":"NE",
    "sg:tags":[
        "cutlery"
    ],
    "wof:name":"Baubles & Blades",
    "wof:placetype":"venue"
},
  "geometry": {"coordinates":[-96.025746,41.259725],"type":"Point"}
}