{
  "type": "Feature",
  "properties": {
    "iso:country":"US",
    "sg:address":"273 Co Rd 19",
    "sg:city":"Hooper",
    "sg:phone":"+1 402 567 2204",
    "sg:postcode":"68031",
    "sg:province":"NE",
    "sg:tags":[
        "farm",
        "operator",
        "grain",
        "cash",
        "trucking"
    ],
    "wof:name":"Ferguson Trucking",
    "wof:placetype":"venue"
},
  "geometry": {"coordinates":[-96.559085,41.716108],"type":"Point"}
}