{
  "type": "Feature",
  "properties": {
    "iso:country":"US",
    "sg:address":"9023 Ohio St",
    "sg:city":"Omaha",
    "sg:classifiers":[
        {
            "category":"Personal",
            "subcategory":"Beauty Salon",
            "type":"Services"
        }
    ],
    "sg:phone":"+1 402 391 3193",
    "sg:postcode":"68134",
    "sg:province":"NE",
    "wof:name":"Maple View Salon",
    "wof:placetype":"venue"
},
  "geometry": {"coordinates":[-96.055426,41.282015],"type":"Point"}
}