{
  "type": "Feature",
  "properties": {
    "iso:country":"US",
    "sg:address":"2914 R St",
    "sg:city":"Omaha",
    "sg:classifiers":[
        {
            "category":"Building & Trades",
            "subcategory":"Construction",
            "type":"Services"
        }
    ],
    "sg:phone":"+1 402 734 6156",
    "sg:postcode":"68107",
    "sg:province":"NE",
    "sg:tags":[
        "excavating",
        "demolition",
        "hauling",
        "contractor"
    ],
    "wof:name":"Navarro Enterprise Cnstr Inc",
    "wof:placetype":"venue"
},
  "geometry": {"coordinates":[-95.957548,41.204554],"type":"Point"}
}