{
  "type": "Feature",
  "properties": {
    "iso:country":"US",
    "sg:address":"117 N 1st Ave",
    "sg:city":"Mc Cool Junction",
    "sg:classifiers":[
        {
            "category":"Food & Beverages",
            "subcategory":"Liquor & Beverages",
            "type":"Retail Goods"
        }
    ],
    "sg:phone":"+1 402 724 2540",
    "sg:postcode":"68401",
    "sg:province":"NE",
    "wof:name":"Smitty's Drive-In Liquor",
    "wof:placetype":"venue"
},
  "geometry": {"coordinates":[-97.59761899999999,40.744028],"type":"Point"}
}