{
  "type": "Feature",
  "properties": {
    "addr:full":"9419 I St Omaha NE 68127",
    "addr:housenumber":"9419",
    "addr:postcode":"68127",
    "addr:street":"I St",
    "iso:country":"US",
    "sg:address":"9419 I St",
    "sg:city":"Omaha",
    "sg:classifiers":[
        {
            "category":"Building & Trades",
            "subcategory":"Construction",
            "type":"Services"
        }
    ],
    "sg:phone":"+1 402 593 9269",
    "sg:postcode":"68127",
    "sg:province":"NE",
    "sg:tags":[
        "roofing",
        "coating",
        "m",
        "specialty",
        "contractor"
    ],
    "wof:name":"Midwest Thermal Coatings",
    "wof:placetype":"venue"
},
  "geometry": {"coordinates":[-96.05967,41.216147],"type":"Point"}
}