{
  "type": "Feature",
  "properties": {
    "iso:country":"US",
    "sg:address":"509 N 13th St",
    "sg:city":"Norfolk",
    "sg:classifiers":[
        {
            "category":"Manufacturing",
            "subcategory":"Lumber",
            "type":"Manufacturing & Wholesale Goods"
        }
    ],
    "sg:phone":"+1 402 379 3015",
    "sg:postcode":"68701",
    "sg:province":"NE",
    "wof:name":"Arens Stump Removal",
    "wof:placetype":"venue"
},
  "geometry": {"coordinates":[-97.426742,42.038084],"type":"Point"}
}