{
  "type": "Feature",
  "properties": {
    "iso:country":"US",
    "sg:address":"601 E State Farm Rd",
    "sg:city":"North Platte",
    "sg:classifiers":[
        {
            "category":"Education",
            "subcategory":"Junior College",
            "type":"Public Place"
        }
    ],
    "sg:phone":"+1 308 535 3758",
    "sg:postcode":"69101",
    "sg:province":"NE",
    "wof:name":"Knights Cage Club",
    "wof:placetype":"venue"
},
  "geometry": {"coordinates":[-100.75846300000001,41.090158],"type":"Point"}
}