{
  "type": "Feature",
  "properties": {
    "addr:full":"5402 L St Omaha NE 68117",
    "addr:housenumber":"5402",
    "addr:postcode":"68117",
    "addr:street":"L St",
    "iso:country":"US",
    "sg:address":"5402 L St",
    "sg:city":"Omaha",
    "sg:classifiers":[
        {
            "category":"Autos & Motor Vehicles",
            "subcategory":"Automobile Sales",
            "type":"Retail Goods"
        }
    ],
    "sg:phone":"+1 402 734 5402",
    "sg:postcode":"68117",
    "sg:province":"NE",
    "sg:tags":[
        "use",
        "supply"
    ],
    "wof:name":"Jims Dodge Country",
    "wof:placetype":"venue"
},
  "geometry": {"coordinates":[-96.000398,41.212564],"type":"Point"}
}