{
  "type": "Feature",
  "properties": {
    "addr:full":"156 H & Blondo Omaha NE 68102",
    "addr:housenumber":"156",
    "addr:postcode":"68102",
    "iso:country":"US",
    "sg:address":"156 H & Blondo",
    "sg:city":"Omaha",
    "sg:classifiers":[
        {
            "category":"Health Services",
            "subcategory":"Chiropractor",
            "type":"Services"
        }
    ],
    "sg:phone":"+1 402 493 6777",
    "sg:postcode":"68102",
    "sg:province":"NE",
    "wof:name":"Back and Neck Pain Relief Center",
    "wof:placetype":"venue"
},
  "geometry": {"coordinates":[-95.937202,41.257198],"type":"Point"}
}