{
  "type": "Feature",
  "properties": {
    "addr:full":"700 E 23rd St Fremont NE 68025",
    "addr:housenumber":"700",
    "addr:postcode":"68025",
    "addr:street":"E 23Rd St",
    "iso:country":"US",
    "sg:address":"700 E 23rd St",
    "sg:city":"Fremont",
    "sg:classifiers":[
        {
            "category":"Cinema",
            "subcategory":"Movie Theater",
            "type":"Entertainment"
        }
    ],
    "sg:phone":"+1 402 727 0533",
    "sg:postcode":"68025",
    "sg:province":"NE",
    "wof:name":"Cinema 3 Theatres",
    "wof:placetype":"venue"
},
  "geometry": {"coordinates":[-96.48913899999999,41.451562],"type":"Point"}
}