{
  "type": "Feature",
  "properties": {
    "addr:full":"515 S 2nd St Norfolk NE 68701",
    "addr:housenumber":"515",
    "addr:postcode":"68701",
    "addr:street":"S 2Nd St",
    "iso:country":"US",
    "sg:address":"515 S 2nd St",
    "sg:city":"Norfolk",
    "sg:classifiers":[
        {
            "category":"Building & Trades",
            "subcategory":"Construction",
            "type":"Services"
        }
    ],
    "sg:phone":"+1 402 371 4541",
    "sg:postcode":"68701",
    "sg:province":"NE",
    "sg:tags":[
        "hanging",
        "contractor"
    ],
    "wof:name":"Obanion Painting",
    "wof:placetype":"venue"
},
  "geometry": {"coordinates":[-97.408548,42.027988],"type":"Point"}
}