{
  "type": "Feature",
  "properties": {
    "iso:country":"US",
    "sg:address":"990 Co Rd M",
    "sg:city":"Mead",
    "sg:classifiers":[
        {
            "category":"Autos & Motor Vehicles",
            "subcategory":"Fuel & Gas Station",
            "type":"Retail Goods"
        }
    ],
    "sg:phone":"+1 402 624 2455",
    "sg:postcode":"68041",
    "sg:province":"NE",
    "sg:tags":[
        "gasoline",
        "product",
        "station",
        "petroleum"
    ],
    "wof:name":"Sinclair",
    "wof:placetype":"venue"
},
  "geometry": {"coordinates":[-96.47726900000001,41.23392],"type":"Point"}
}