{
  "type": "Feature",
  "properties": {
    "iso:country":"US",
    "sg:address":"19880 Antelope Rd",
    "sg:city":"Riverdale",
    "sg:classifiers":[
        {
            "category":"Building & Trades",
            "subcategory":"Construction",
            "type":"Services"
        }
    ],
    "sg:phone":"+1 308 237 7441",
    "sg:postcode":"68870",
    "sg:province":"NE",
    "sg:tags":[
        "water",
        "well",
        "drilling"
    ],
    "wof:name":"Dennis Gibbons Well Drilling",
    "wof:placetype":"venue"
},
  "geometry": {"coordinates":[-99.045734,40.867438],"type":"Point"}
}