{
  "type": "Feature",
  "properties": {
    "addr:full":"75795 State Hwy 21 Cozad NE 69130",
    "addr:housenumber":"75795",
    "addr:postcode":"69130",
    "addr:street":"State Hwy 21 Cozad Ne",
    "iso:country":"US",
    "sg:address":"75795 State Hwy 21",
    "sg:city":"Cozad",
    "sg:classifiers":[
        {
            "category":"Education",
            "subcategory":"School",
            "type":"Public Place"
        }
    ],
    "sg:phone":"+1 308 784 2741",
    "sg:postcode":"69130",
    "sg:province":"NE",
    "wof:name":"District 29 School",
    "wof:placetype":"venue"
},
  "geometry": {"coordinates":[-99.995431,40.815632],"type":"Point"}
}