{
  "type": "Feature",
  "properties": {
    "iso:country":"US",
    "sg:address":"7838 US Hwy 281",
    "sg:city":"Grand Island",
    "sg:classifiers":[
        {
            "category":"Travel",
            "subcategory":"Hotels & Motels",
            "type":"Entertainment"
        }
    ],
    "sg:phone":"+1 308 384 7770",
    "sg:postcode":"68803",
    "sg:province":"NE",
    "wof:name":"Holiday Inn Grand Island/I-80",
    "wof:placetype":"venue"
},
  "geometry": {"coordinates":[-98.359347,41.029608],"type":"Point"}
}