{
  "type": "Feature",
  "properties": {
    "addr:full":"3302 20th Ave Kearney NE 68845",
    "addr:housenumber":"3302",
    "addr:postcode":"68845",
    "addr:street":"20Th Ave",
    "iso:country":"US",
    "sg:address":"3302 20th Ave",
    "sg:city":"Kearney",
    "sg:classifiers":[
        {
            "category":"Restaurant",
            "type":"Food & Drink"
        }
    ],
    "sg:phone":"+1 308 236 7878",
    "sg:postcode":"68845",
    "sg:province":"NE",
    "wof:name":"Famous Fillmore's",
    "wof:placetype":"venue"
},
  "geometry": {"coordinates":[-99.106904,40.708603],"type":"Point"}
}