{
  "type": "Feature",
  "properties": {
    "addr:full":"2614 S 13th St Omaha NE 68108",
    "addr:housenumber":"2614",
    "addr:postcode":"68108",
    "addr:street":"S 13Th St",
    "iso:country":"US",
    "sg:address":"2614 S 13th St",
    "sg:city":"Omaha",
    "sg:classifiers":[
        {
            "category":"Restaurant",
            "type":"Food & Drink"
        }
    ],
    "sg:phone":"+1 402 991 1190",
    "sg:postcode":"68108",
    "sg:province":"NE",
    "sg:tags":[
        "mexican"
    ],
    "wof:name":"Los Portales",
    "wof:placetype":"venue"
},
  "geometry": {"coordinates":[-95.933492,41.234913],"type":"Point"}
}