{
  "type": "Feature",
  "properties": {
    "iso:country":"US",
    "sg:address":"10062 Wirt Plz",
    "sg:city":"Omaha",
    "sg:classifiers":[
        {
            "category":"Professional",
            "subcategory":"Management & Consulting",
            "type":"Services"
        }
    ],
    "sg:phone":"+1 402 571 7634",
    "sg:postcode":"68134",
    "sg:province":"NE",
    "sg:tags":[
        "consultant",
        "safety"
    ],
    "wof:name":"Compliance Safety & Health",
    "wof:placetype":"venue"
},
  "geometry": {"coordinates":[-96.068622,41.286876],"type":"Point"}
}