{
  "type": "Feature",
  "properties": {
    "addr:full":"1420 Center Park Rd Lincoln NE 68512",
    "addr:housenumber":"1420",
    "addr:postcode":"68512",
    "addr:street":"Center Park Rd",
    "iso:country":"US",
    "sg:address":"1420 Center Park Rd",
    "sg:city":"Lincoln",
    "sg:classifiers":[
        {
            "category":"Building & Trades",
            "subcategory":"Construction",
            "type":"Services"
        }
    ],
    "sg:phone":"+1 402 423 6631",
    "sg:postcode":"68512",
    "sg:province":"NE",
    "sg:tags":[
        "asbestos",
        "removal"
    ],
    "wof:name":"Asbestos Removers Inc",
    "wof:placetype":"venue"
},
  "geometry": {"coordinates":[-96.699665,40.766103],"type":"Point"}
}