{
  "type": "Feature",
  "properties": {
    "iso:country":"US",
    "sg:address":"108 N Madison St",
    "sg:city":"Brainard",
    "sg:classifiers":[
        {
            "category":"Building & Trades",
            "subcategory":"Plumbing",
            "type":"Services"
        }
    ],
    "sg:phone":"+1 402 545 3501",
    "sg:postcode":"68626",
    "sg:province":"NE",
    "sg:tags":[
        "heating",
        "contractor"
    ],
    "wof:name":"Ron's Plumbing & Heating",
    "wof:placetype":"venue"
},
  "geometry": {"coordinates":[-97.002438,41.184135],"type":"Point"}
}