{
  "type": "Feature",
  "properties": {
    "iso:country":"US",
    "sg:address":"5225 S 170th St",
    "sg:city":"Omaha",
    "sg:classifiers":[
        {
            "category":"Social Services",
            "subcategory":"Child Care",
            "type":"Services"
        }
    ],
    "sg:phone":"+1 402 896 5158",
    "sg:postcode":"68135",
    "sg:province":"NE",
    "sg:tags":[
        "kindergarten",
        "academic",
        "school",
        "preschool"
    ],
    "wof:name":"Millard Learning Center",
    "wof:placetype":"venue"
},
  "geometry": {"coordinates":[-96.179892,41.204137],"type":"Point"}
}