{
  "type": "Feature",
  "properties": {
    "iso:country":"US",
    "sg:address":"1743 Dodge St",
    "sg:city":"Sidney",
    "sg:classifiers":[
        {
            "category":"Wholesale",
            "subcategory":"Machinery & Supplies",
            "type":"Manufacturing & Wholesale Goods"
        }
    ],
    "sg:phone":"+1 308 254 4215",
    "sg:postcode":"69162",
    "sg:province":"NE",
    "sg:tags":[
        "equipment",
        "establishment"
    ],
    "wof:name":"G S Vending",
    "wof:placetype":"venue"
},
  "geometry": {"coordinates":[-102.98613899999999,41.149171],"type":"Point"}
}