{
  "type": "Feature",
  "properties": {
    "addr:full":"1624 7th Ave Scottsbluff NE 69361",
    "addr:housenumber":"1624",
    "addr:postcode":"69361",
    "addr:street":"7Th Ave",
    "iso:country":"US",
    "sg:address":"1624 7th Ave",
    "sg:city":"Scottsbluff",
    "sg:classifiers":[
        {
            "category":"Building & Trades",
            "subcategory":"Cleaning & Sanitation",
            "type":"Services"
        }
    ],
    "sg:phone":"+1 308 635 7578",
    "sg:postcode":"69361",
    "sg:province":"NE",
    "sg:tags":[
        "janitor"
    ],
    "wof:name":"Praise Windows",
    "wof:placetype":"venue"
},
  "geometry": {"coordinates":[-103.653609,41.862737],"type":"Point"}
}