{
  "type": "Feature",
  "properties": {
    "iso:country":"US",
    "sg:address":"1012 N 45th St",
    "sg:city":"Omaha",
    "sg:classifiers":[
        {
            "category":"Building & Trades",
            "subcategory":"Plumbing",
            "type":"Services"
        }
    ],
    "sg:phone":"+1 402 714 2717",
    "sg:postcode":"68132",
    "sg:province":"NE",
    "sg:tags":[
        "contractor"
    ],
    "wof:name":"A M Heating & Air",
    "wof:placetype":"venue"
},
  "geometry": {"coordinates":[-95.980422,41.269879],"type":"Point"}
}