{
  "type": "Feature",
  "properties": {
    "iso:country":"US",
    "sg:address":"2323 Pershing Rd",
    "sg:city":"Columbus",
    "sg:classifiers":[
        {
            "category":"Real Estate",
            "subcategory":"Real Estate Operator",
            "type":"Services"
        }
    ],
    "sg:phone":"+1 402 564 2771",
    "sg:postcode":"68601",
    "sg:province":"NE",
    "sg:tags":[
        "building",
        "manager",
        "apartment"
    ],
    "wof:name":"Beacher Place Apartments",
    "wof:placetype":"venue"
},
  "geometry": {"coordinates":[-97.35147000000001,41.4389],"type":"Point"}
}