{
  "type": "Feature",
  "properties": {
    "iso:country":"US",
    "sg:address":"111 N Dewey St",
    "sg:city":"North Platte",
    "sg:classifiers":[
        {
            "category":"Health Services",
            "subcategory":"Doctor",
            "type":"Services"
        }
    ],
    "sg:phone":"+1 308 696 1201",
    "sg:postcode":"69101",
    "sg:province":"NE",
    "sg:tags":[
        "clinic"
    ],
    "sg:website":"www.wcdhd.org",
    "wof:name":"West Central District Health",
    "wof:placetype":"venue"
},
  "geometry": {"coordinates":[-100.762429,41.134303],"type":"Point"}
}