{
  "type": "Feature",
  "properties": {
    "iso:country":"US",
    "sg:address":"3300 N 176th St",
    "sg:city":"Lincoln",
    "sg:phone":"+1 402 781 2546",
    "sg:postcode":"68527",
    "sg:province":"NE",
    "sg:tags":[
        "farm",
        "corn",
        "soybean"
    ],
    "wof:name":"Estel Schroeder Farm",
    "wof:placetype":"venue"
},
  "geometry": {"coordinates":[-96.482722,40.846412],"type":"Point"}
}