{
  "type": "Feature",
  "properties": {
    "iso:country":"US",
    "sg:address":"2337 State Hwy 15",
    "sg:city":"Western",
    "sg:classifiers":[
        {
            "category":"Building & Trades",
            "subcategory":"Plumbing",
            "type":"Services"
        }
    ],
    "sg:phone":"+1 402 450 1011",
    "sg:postcode":"68464",
    "sg:province":"NE",
    "sg:tags":[
        "conditioning",
        "air",
        "system",
        "contractor"
    ],
    "wof:name":"Wahl Heating Air Conditioning",
    "wof:placetype":"venue"
},
  "geometry": {"coordinates":[-97.178794,40.374167],"type":"Point"}
}