{
  "type": "Feature",
  "properties": {
    "iso:country":"US",
    "sg:address":"2035 17th Rd",
    "sg:city":"Central City",
    "sg:classifiers":[
        {
            "category":"Farming",
            "subcategory":"Farm",
            "type":"Manufacturing & Wholesale Goods"
        }
    ],
    "sg:phone":"+1 308 946 3910",
    "sg:postcode":"68826",
    "sg:province":"NE",
    "wof:name":"Herbig Farms Inc",
    "wof:placetype":"venue"
},
  "geometry": {"coordinates":[-97.982592,41.161293],"type":"Point"}
}