{
  "type": "Feature",
  "properties": {
    "iso:country":"US",
    "sg:address":"2217 Central Ave",
    "sg:city":"Kearney",
    "sg:classifiers":[
        {
            "category":"Shopping",
            "subcategory":"Books",
            "type":"Retail Goods"
        }
    ],
    "sg:phone":"+1 308 236 6973",
    "sg:postcode":"68847",
    "sg:province":"NE",
    "sg:tags":[
        "dealer"
    ],
    "wof:name":"Scrapbook Garden",
    "wof:placetype":"venue"
},
  "geometry": {"coordinates":[-99.08163399999999,40.698496],"type":"Point"}
}