{
  "type": "Feature",
  "properties": {
    "iso:country":"US",
    "sg:address":"2425 Chicago Ave",
    "sg:city":"Plattsmouth",
    "sg:classifiers":[
        {
            "category":"Real Estate",
            "subcategory":"Real Estate Operator",
            "type":"Services"
        }
    ],
    "sg:phone":"+1 402 298 8660",
    "sg:postcode":"68048",
    "sg:province":"NE",
    "sg:tags":[
        "mobile",
        "home",
        "community"
    ],
    "wof:name":"Robert's Mobile Home Court",
    "wof:placetype":"venue"
},
  "geometry": {"coordinates":[-95.896682,40.986221],"type":"Point"}
}