{
  "type": "Feature",
  "properties": {
    "iso:country":"US",
    "sg:address":"2229 Alvo Rd",
    "sg:city":"Seward",
    "sg:phone":"+1 402 643 4658",
    "sg:postcode":"68434",
    "sg:province":"NE",
    "sg:tags":[
        "farm",
        "corn",
        "wheat",
        "soybean"
    ],
    "wof:name":"Jack Broderick",
    "wof:placetype":"venue"
},
  "geometry": {"coordinates":[-97.023512,40.886638],"type":"Point"}
}