{
  "type": "Feature",
  "properties": {
    "iso:country":"US",
    "sg:address":"1208 5th Ave",
    "sg:city":"South Sioux City",
    "sg:classifiers":[
        {
            "category":"Professional",
            "type":"Services"
        }
    ],
    "sg:phone":"+1 402 494 4080",
    "sg:postcode":"68776",
    "sg:province":"NE",
    "sg:tags":[
        "establishment"
    ],
    "wof:name":"ACS Inc",
    "wof:placetype":"venue"
},
  "geometry": {"coordinates":[-96.41888,42.477386],"type":"Point"}
}