{
  "type": "Feature",
  "properties": {
    "iso:country":"US",
    "sg:address":"12100 W Center Rd",
    "sg:city":"Omaha",
    "sg:classifiers":[
        {
            "category":"Shopping",
            "subcategory":"Department Store",
            "type":"Retail Goods"
        }
    ],
    "sg:phone":"+1 402 333 3200",
    "sg:postcode":"68144",
    "sg:province":"NE",
    "wof:name":"Bel-Air Plaza",
    "wof:placetype":"venue"
},
  "geometry": {"coordinates":[-96.10303,41.234102],"type":"Point"}
}