{
  "type": "Feature",
  "properties": {
    "iso:country":"US",
    "sg:address":"7900 Serum Ave",
    "sg:city":"Omaha",
    "sg:classifiers":[
        {
            "category":"Home & Garden",
            "subcategory":"Garden Supply",
            "type":"Retail Goods"
        }
    ],
    "sg:phone":"+1 402 333 7713",
    "sg:postcode":"68127",
    "sg:province":"NE",
    "sg:tags":[
        "sprinkler"
    ],
    "wof:name":"J & J Lawn Sprinkler & Fence",
    "wof:placetype":"venue"
},
  "geometry": {"coordinates":[-96.039377,41.198078],"type":"Point"}
}