{
  "type": "Feature",
  "properties": {
    "addr:full":"3828 Dodge St Omaha NE 68131",
    "addr:housenumber":"3828",
    "addr:postcode":"68131",
    "addr:street":"Dodge St",
    "iso:country":"US",
    "sg:address":"3828 Dodge St",
    "sg:city":"Omaha",
    "sg:classifiers":[
        {
            "category":"Professional",
            "subcategory":"Lawyer & Legal Services",
            "type":"Services"
        }
    ],
    "sg:phone":"+1 402 551 8700",
    "sg:postcode":"68131",
    "sg:province":"NE",
    "wof:name":"Sederstrom Law Office",
    "wof:placetype":"venue"
},
  "geometry": {"coordinates":[-95.970299,41.2598],"type":"Point"}
}