{
  "type": "Feature",
  "properties": {
    "iso:country":"US",
    "sg:address":"13606 S 42nd Cir",
    "sg:city":"Bellevue",
    "sg:classifiers":[
        {
            "category":"Building & Trades",
            "subcategory":"Landscaping Services",
            "type":"Services"
        }
    ],
    "sg:phone":"+1 402 680 6309",
    "sg:postcode":"68123",
    "sg:province":"NE",
    "wof:name":"Addison Enterprises",
    "wof:placetype":"venue"
},
  "geometry": {"coordinates":[-95.97560300000001,41.107755],"type":"Point"}
}