{
  "type": "Feature",
  "properties": {
    "iso:country":"US",
    "sg:address":"9909 S 9th Cir",
    "sg:city":"Bellevue",
    "sg:classifiers":[
        {
            "category":"Building & Trades",
            "subcategory":"Cleaning & Sanitation",
            "type":"Services"
        }
    ],
    "sg:phone":"+1 402 291 3153",
    "sg:postcode":"68123",
    "sg:province":"NE",
    "sg:tags":[
        "maintenance"
    ],
    "wof:name":"Sunshine Cleaning Services",
    "wof:placetype":"venue"
},
  "geometry": {"coordinates":[-95.92817100000001,41.162447],"type":"Point"}
}