{
  "type": "Feature",
  "properties": {
    "iso:country":"US",
    "sg:address":"3578 Farnam St",
    "sg:city":"Omaha",
    "sg:classifiers":[
        {
            "category":"Bars & Pubs",
            "type":"Food & Drink"
        }
    ],
    "sg:phone":"+1 402 345 0162",
    "sg:postcode":"68131",
    "sg:province":"NE",
    "sg:website":"www.beercornerusa.com",
    "wof:name":"Huber Haus",
    "wof:placetype":"venue"
},
  "geometry": {"coordinates":[-95.966066,41.257746],"type":"Point"}
}