{
  "type": "Feature",
  "properties": {
    "iso:country":"US",
    "sg:address":"1316 E 32nd St",
    "sg:city":"Kearney",
    "sg:classifiers":[
        {
            "category":"Freight",
            "type":"Transportation"
        }
    ],
    "sg:phone":"+1 308 233 5786",
    "sg:postcode":"68847",
    "sg:province":"NE",
    "sg:tags":[
        "hauler",
        "contract",
        "long",
        "trucking"
    ],
    "wof:name":"Vasquez Trucking Co",
    "wof:placetype":"venue"
},
  "geometry": {"coordinates":[-99.06468700000001,40.707107],"type":"Point"}
}