{
  "type": "Feature",
  "properties": {
    "iso:country":"US",
    "sg:address":"2901 Pine Lake Rd",
    "sg:city":"Lincoln",
    "sg:classifiers":[
        {
            "category":"Health Services",
            "subcategory":"Health Practitioner",
            "type":"Services"
        },
        {
            "category":"Personal",
            "subcategory":"Beauty Salon",
            "type":"Services"
        }
    ],
    "sg:phone":"+1 402 328 0777",
    "sg:postcode":"68516",
    "sg:province":"NE",
    "wof:name":"Tranquility Salon & Day Spa",
    "wof:placetype":"venue"
},
  "geometry": {"coordinates":[-96.67922299999999,40.74017],"type":"Point"}
}