{
  "type": "Feature",
  "properties": {
    "iso:country":"US",
    "sg:address":"14216 Pierce Plz",
    "sg:city":"Omaha",
    "sg:classifiers":[
        {
            "category":"Insurance",
            "subcategory":"Insurance Agent",
            "type":"Services"
        },
        {
            "category":"Insurance",
            "subcategory":"Hazard Insurance",
            "type":"Services"
        },
        {
            "category":"Insurance",
            "subcategory":"Title Insurance",
            "type":"Services"
        },
        {
            "category":"Insurance",
            "subcategory":"Health Insurance",
            "type":"Services"
        },
        {
            "category":"Insurance",
            "subcategory":"Life Insurance",
            "type":"Services"
        }
    ],
    "sg:phone":"+1 402 334 5170",
    "sg:postcode":"68144",
    "sg:province":"NE",
    "sg:tags":[
        "business",
        "auto",
        "commercial",
        "homeowner",
        "benefit",
        "employee",
        "property",
        "casualty"
    ],
    "sg:website":"http://www.farmersagent.com/sdodds",
    "wof:name":"Dodds, Stephen R - Farmers Insurance Group",
    "wof:placetype":"venue"
},
  "geometry": {"coordinates":[-96.13702000000001,41.247549],"type":"Point"}
}