{
  "type": "Feature",
  "properties": {
    "addr:full":"613 S 16th St Omaha NE 68102",
    "addr:housenumber":"613",
    "addr:postcode":"68102",
    "addr:street":"S 16Th St",
    "iso:country":"US",
    "sg:address":"613 S 16th St",
    "sg:city":"Omaha",
    "sg:classifiers":[
        {
            "category":"Education",
            "subcategory":"Special Training",
            "type":"Public Place"
        }
    ],
    "sg:phone":"+1 402 341 4555",
    "sg:postcode":"68102",
    "sg:province":"NE",
    "sg:tags":[
        "instruction",
        "driving",
        "legal"
    ],
    "sg:website":"www.cornhuskerdriving.com",
    "wof:name":"Cornshusker Driving School",
    "wof:placetype":"venue"
},
  "geometry": {"coordinates":[-95.93713099999999,41.253525],"type":"Point"}
}