{
  "type": "Feature",
  "properties": {
    "iso:country":"US",
    "sg:address":"221 Mill Rd",
    "sg:city":"Crawford",
    "sg:classifiers":[
        {
            "category":"Wholesale",
            "subcategory":"Farm Supplies",
            "type":"Manufacturing & Wholesale Goods"
        }
    ],
    "sg:phone":"+1 308 665 3974",
    "sg:postcode":"69339",
    "sg:province":"NE",
    "sg:tags":[
        "equipment",
        "livestock"
    ],
    "wof:name":"Bob's Welding & Repair",
    "wof:placetype":"venue"
},
  "geometry": {"coordinates":[-103.398644,42.712019],"type":"Point"}
}