{
  "type": "Feature",
  "properties": {
    "iso:country":"US",
    "sg:address":"219 Main St",
    "sg:city":"Chadron",
    "sg:classifiers":[
        {
            "category":"Home & Garden",
            "subcategory":"Building Materials",
            "type":"Retail Goods"
        }
    ],
    "sg:phone":"+1 308 432 3465",
    "sg:postcode":"69337",
    "sg:province":"NE",
    "sg:tags":[
        "modular"
    ],
    "wof:name":"Urwin Enterprises",
    "wof:placetype":"venue"
},
  "geometry": {"coordinates":[-103.00064500000001,42.829679],"type":"Point"}
}