{
  "type": "Feature",
  "properties": {
    "iso:country":"US",
    "sg:address":"610 US Hwy 30",
    "sg:city":"North Bend",
    "sg:classifiers":[
        {
            "category":"Building & Trades",
            "subcategory":"Construction",
            "type":"Services"
        }
    ],
    "sg:phone":"+1 402 652 3264",
    "sg:postcode":"68649",
    "sg:province":"NE",
    "sg:tags":[
        "well",
        "drilling"
    ],
    "wof:name":"Grosch Irrigation Co Inc",
    "wof:placetype":"venue"
},
  "geometry": {"coordinates":[-96.774067,41.461667],"type":"Point"}
}