{
  "type": "Feature",
  "properties": {
    "addr:full":"15234 W Maple Rd Omaha NE 68116",
    "addr:housenumber":"15234",
    "addr:postcode":"68116",
    "addr:street":"W Maple Rd",
    "iso:country":"US",
    "sg:address":"15234 W Maple Rd",
    "sg:city":"Omaha",
    "sg:classifiers":[
        {
            "category":"Restaurant",
            "type":"Food & Drink"
        }
    ],
    "sg:phone":"+1 402 496 7770",
    "sg:postcode":"68116",
    "sg:province":"NE",
    "sg:tags":[
        "pizza"
    ],
    "sg:website":"www.godfathers.com",
    "wof:name":"Godfather's Pizza",
    "wof:placetype":"venue"
},
  "geometry": {"coordinates":[-96.151706,41.292188],"type":"Point"}
}