{
  "type": "Feature",
  "properties": {
    "iso:country":"US",
    "sg:address":"1410 Western Hills Dr",
    "sg:city":"Papillion",
    "sg:classifiers":[
        {
            "category":"Sports & Exercise",
            "subcategory":"Golf",
            "type":"Entertainment"
        }
    ],
    "sg:phone":"+1 402 592 7550",
    "sg:postcode":"68046",
    "sg:province":"NE",
    "sg:tags":[
        "course",
        "drinking",
        "eating",
        "public"
    ],
    "sg:website":"www.tarahillsgolf.com",
    "wof:name":"Tara Hills Golf Course",
    "wof:placetype":"venue"
},
  "geometry": {"coordinates":[-96.055215,41.175434],"type":"Point"}
}