{
  "type": "Feature",
  "properties": {
    "addr:full":"1876 S 74th St Omaha NE 68124",
    "addr:housenumber":"1876",
    "addr:postcode":"68124",
    "addr:street":"S 74Th St",
    "iso:country":"US",
    "sg:address":"1876 S 74th St",
    "sg:city":"Omaha",
    "sg:classifiers":[
        {
            "category":"Professional",
            "subcategory":"Computer Services",
            "type":"Services"
        }
    ],
    "sg:phone":"+1 402 393 2057",
    "sg:postcode":"68124",
    "sg:province":"NE",
    "sg:tags":[
        "related"
    ],
    "wof:name":"Black Falkon Industries",
    "wof:placetype":"venue"
},
  "geometry": {"coordinates":[-96.027134,41.24182],"type":"Point"}
}