{
  "type": "Feature",
  "properties": {
    "iso:country":"US",
    "sg:address":"1015 Farnam St.",
    "sg:city":"Omaha",
    "sg:classifiers":[
        {
            "category":"Bars & Pubs",
            "type":"Food & Drink"
        },
        {
            "category":"Restaurant",
            "type":"Food & Drink"
        }
    ],
    "sg:phone":"+1 402 502 7888",
    "sg:postcode":"68102",
    "sg:province":"NE",
    "sg:tags":[
        "fusion",
        "asian"
    ],
    "sg:website":"www.odining.com",
    "wof:name":"O Dining & Lounge",
    "wof:placetype":"venue"
},
  "geometry": {"coordinates":[-95.929964,41.257252],"type":"Point"}
}