{
  "type": "Feature",
  "properties": {
    "iso:country":"US",
    "sg:address":"611 E 4th St",
    "sg:city":"Ainsworth",
    "sg:classifiers":[
        {
            "category":"Food & Beverages",
            "subcategory":"Groceries & Convenience Stores",
            "type":"Retail Goods"
        }
    ],
    "sg:phone":"+1 402 387 1450",
    "sg:postcode":"69210",
    "sg:province":"NE",
    "sg:tags":[
        "grocer"
    ],
    "wof:name":"Red & White Super Market",
    "wof:placetype":"venue"
},
  "geometry": {"coordinates":[-99.855199,42.549818],"type":"Point"}
}