{
  "type": "Feature",
  "properties": {
    "iso:country":"US",
    "sg:address":"5141 F St",
    "sg:city":"Omaha",
    "sg:classifiers":[
        {
            "category":"Education",
            "subcategory":"University",
            "type":"Public Place"
        }
    ],
    "sg:phone":"+1 800 433 3243",
    "sg:postcode":"68117",
    "sg:province":"NE",
    "sg:tags":[
        "college"
    ],
    "wof:name":"Vatterott College",
    "wof:placetype":"venue"
},
  "geometry": {"coordinates":[-95.99372,41.219742],"type":"Point"}
}