{
  "type": "Feature",
  "properties": {
    "iso:country":"US",
    "sg:address":"1600 US Hwy 30",
    "sg:city":"Kearney",
    "sg:classifiers":[
        {
            "category":"Banks & Credit Unions",
            "subcategory":"Bank",
            "type":"Services"
        }
    ],
    "sg:phone":"+1 308 234 4440",
    "sg:postcode":"68847",
    "sg:province":"NE",
    "sg:tags":[
        "cashing",
        "check"
    ],
    "wof:name":"Kearney Cash",
    "wof:placetype":"venue"
},
  "geometry": {"coordinates":[-99.05950199999999,40.70023],"type":"Point"}
}