{
  "type": "Feature",
  "properties": {
    "addr:full":"1910 Market Ln Norfolk NE 68701",
    "addr:housenumber":"1910",
    "addr:postcode":"68701",
    "addr:street":"Market Ln",
    "iso:country":"US",
    "sg:address":"1910 Market Ln",
    "sg:city":"Norfolk",
    "sg:classifiers":[
        {
            "category":"Restaurant",
            "type":"Food & Drink"
        }
    ],
    "sg:phone":"+1 402 844 4010",
    "sg:postcode":"68701",
    "sg:province":"NE",
    "wof:name":"Sonic Drive-In",
    "wof:placetype":"venue"
},
  "geometry": {"coordinates":[-97.434427,42.020066],"type":"Point"}
}