{
  "type": "Feature",
  "properties": {
    "iso:country":"US",
    "sg:address":"222 S Chestnut St",
    "sg:city":"Kimball",
    "sg:classifiers":[
        {
            "category":"Shopping",
            "subcategory":"Clothing, Apparel, & Fashions",
            "type":"Retail Goods"
        }
    ],
    "sg:phone":"+1 308 235 2042",
    "sg:postcode":"69145",
    "sg:province":"NE",
    "wof:name":"Vogue Shoppe",
    "wof:placetype":"venue"
},
  "geometry": {"coordinates":[-103.663059,41.23679],"type":"Point"}
}