{
  "type": "Feature",
  "properties": {
    "addr:full":"6201 Ames Ave Omaha NE 68104",
    "addr:housenumber":"6201",
    "addr:postcode":"68104",
    "addr:street":"Ames Ave",
    "iso:country":"US",
    "sg:address":"6201 Ames Ave",
    "sg:city":"Omaha",
    "sg:classifiers":[
        {
            "category":"Shopping",
            "subcategory":"Clothing, Apparel, & Fashions",
            "type":"Retail Goods"
        }
    ],
    "sg:phone":"+1 402 554 0800",
    "sg:postcode":"68104",
    "sg:province":"NE",
    "sg:tags":[
        "lingerie"
    ],
    "wof:name":"Shoe Shop",
    "wof:placetype":"venue"
},
  "geometry": {"coordinates":[-96.009474,41.299507],"type":"Point"}
}