{
  "type": "Feature",
  "properties": {
    "iso:country":"US",
    "sg:address":"440 N 8th St Ste 130",
    "sg:city":"Lincoln",
    "sg:classifiers":[
        {
            "category":"Professional",
            "subcategory":"Art Services",
            "type":"Services"
        }
    ],
    "sg:phone":"+1 402 474 0400",
    "sg:postcode":"68508",
    "sg:province":"NE",
    "sg:tags":[
        "interior",
        "designer",
        "decorator"
    ],
    "wof:name":"New Age Design Inc",
    "wof:placetype":"venue"
},
  "geometry": {"coordinates":[-96.709926,40.817387],"type":"Point"}
}