{
  "type": "Feature",
  "properties": {
    "addr:full":"2631 S 156th Cir Omaha NE 68130",
    "addr:housenumber":"2631",
    "addr:postcode":"68130",
    "addr:street":"S 156Th Cir",
    "iso:country":"US",
    "sg:address":"2631 S 156th Cir",
    "sg:city":"Omaha",
    "sg:phone":"+1 402 333 9099",
    "sg:postcode":"68130",
    "sg:province":"NE",
    "sg:tags":[
        "equipment",
        "supply"
    ],
    "sg:website":"www.laruecoffee.com",
    "wof:name":"LA Rue Beverage Specialists",
    "wof:placetype":"venue"
},
  "geometry": {"coordinates":[-96.159367,41.238632],"type":"Point"}
}