{
  "type": "Feature",
  "properties": {
    "iso:country":"US",
    "sg:address":"224 W 6th St",
    "sg:city":"York",
    "sg:classifiers":[
        {
            "category":"Professional",
            "subcategory":"Employment Agencies",
            "type":"Services"
        }
    ],
    "sg:phone":"+1 402 362 7638",
    "sg:postcode":"68467",
    "sg:province":"NE",
    "sg:tags":[
        "temporary",
        "staffing"
    ],
    "wof:name":"Advance Services Inc",
    "wof:placetype":"venue"
},
  "geometry": {"coordinates":[-97.594572,40.866961],"type":"Point"}
}