{
  "type": "Feature",
  "properties": {
    "iso:country":"US",
    "sg:address":"6201 Queens Dr",
    "sg:city":"Lincoln",
    "sg:classifiers":[
        {
            "category":"Social Services",
            "subcategory":"Child Care",
            "type":"Services"
        }
    ],
    "sg:phone":"+1 402 421 7308",
    "sg:postcode":"68516",
    "sg:province":"NE",
    "sg:tags":[
        "day"
    ],
    "wof:name":"Wilhite Day Care",
    "wof:placetype":"venue"
},
  "geometry": {"coordinates":[-96.64961099999999,40.751222],"type":"Point"}
}