{
  "type": "Feature",
  "properties": {
    "iso:country":"US",
    "sg:address":"1403 Illinois St",
    "sg:city":"Sidney",
    "sg:classifiers":[
        {
            "category":"Building & Trades",
            "subcategory":"Construction",
            "type":"Services"
        }
    ],
    "sg:phone":"+1 308 254 4142",
    "sg:postcode":"69162",
    "sg:province":"NE",
    "sg:tags":[
        "general",
        "contractor"
    ],
    "wof:name":"Wamsley Construction",
    "wof:placetype":"venue"
},
  "geometry": {"coordinates":[-102.982964,41.144517],"type":"Point"}
}