{
  "type": "Feature",
  "properties": {
    "iso:country":"US",
    "sg:address":"13704 P St",
    "sg:city":"Omaha",
    "sg:classifiers":[
        {
            "category":"Retail",
            "subcategory":"Auto Repair",
            "type":"Services"
        }
    ],
    "sg:phone":"+1 402 933 1776",
    "sg:postcode":"68137",
    "sg:province":"NE",
    "sg:tags":[
        "glass",
        "coating",
        "tinting"
    ],
    "wof:name":"C J Customs",
    "wof:placetype":"venue"
},
  "geometry": {"coordinates":[-96.12652300000001,41.205301],"type":"Point"}
}