{
  "type": "Feature",
  "properties": {
    "iso:country":"US",
    "sg:address":"7810 Terry Dr",
    "sg:city":"La Vista",
    "sg:classifiers":[
        {
            "category":"Building & Trades",
            "subcategory":"Construction",
            "type":"Services"
        }
    ],
    "sg:phone":"+1 402 592 2004",
    "sg:postcode":"68128",
    "sg:province":"NE",
    "sg:tags":[
        "restoration",
        "cleaning",
        "patio",
        "deck"
    ],
    "wof:name":"Revive Your Deck Co",
    "wof:placetype":"venue"
},
  "geometry": {"coordinates":[-96.035404,41.185797],"type":"Point"}
}