{
  "type": "Feature",
  "properties": {
    "iso:country":"US",
    "sg:address":"4210 McCarty Loup",
    "sg:city":"Bellevue",
    "sg:classifiers":[
        {
            "category":"Banks & Credit Unions",
            "subcategory":"Investment Brokerage",
            "type":"Services"
        }
    ],
    "sg:phone":"+1 402 291 5171",
    "sg:postcode":"68123",
    "sg:province":"NE",
    "sg:tags":[
        "advisory",
        "financial"
    ],
    "wof:name":"Ferdig Financial LTD",
    "wof:placetype":"venue"
},
  "geometry": {"coordinates":[-95.97674499999999,41.134047],"type":"Point"}
}