{
  "type": "Feature",
  "properties": {
    "iso:country":"US",
    "sg:address":"1140 S G St",
    "sg:city":"Broken Bow",
    "sg:classifiers":[
        {
            "category":"Insurance",
            "subcategory":"Insurance Agent",
            "type":"Services"
        }
    ],
    "sg:phone":"+1 308 872 6668",
    "sg:postcode":"68822",
    "sg:province":"NE",
    "wof:name":"John Smith & Assoc",
    "wof:placetype":"venue"
},
  "geometry": {"coordinates":[-99.643123,41.399922],"type":"Point"}
}