{
  "type": "Feature",
  "properties": {
    "iso:country":"US",
    "sg:address":"4026 Old Coach Rd",
    "sg:city":"Elkhorn",
    "sg:classifiers":[
        {
            "category":"Home & Garden",
            "subcategory":"Garden Supply",
            "type":"Retail Goods"
        }
    ],
    "sg:phone":"+1 402 216 9990",
    "sg:postcode":"68022",
    "sg:province":"NE",
    "sg:tags":[
        "sprinkler"
    ],
    "wof:name":"Aqua Tech Irrigation Inc",
    "wof:placetype":"venue"
},
  "geometry": {"coordinates":[-96.24486,41.295758],"type":"Point"}
}