{
  "type": "Feature",
  "properties": {
    "iso:country":"US",
    "sg:address":"1401 W Bond Cir",
    "sg:city":"Lincoln",
    "sg:classifiers":[
        {
            "category":"Professional",
            "subcategory":"Management & Consulting",
            "type":"Services"
        }
    ],
    "sg:phone":"+1 402 474 8060",
    "sg:postcode":"68521",
    "sg:province":"NE",
    "sg:tags":[
        "marketing",
        "program"
    ],
    "sg:website":"www.landandsky.com",
    "wof:name":"Land & Sky Mfg",
    "wof:placetype":"venue"
},
  "geometry": {"coordinates":[-96.740454,40.844373],"type":"Point"}
}