{
  "type": "Feature",
  "properties": {
    "iso:country":"US",
    "sg:address":"515 N Dewey St",
    "sg:city":"North Platte",
    "sg:classifiers":[
        {
            "category":"Shopping",
            "subcategory":"Used Merchandise",
            "type":"Retail Goods"
        }
    ],
    "sg:phone":"+1 308 534 6050",
    "sg:postcode":"69101",
    "sg:province":"NE",
    "sg:tags":[
        "clothing"
    ],
    "wof:name":"2nd Act",
    "wof:placetype":"venue"
},
  "geometry": {"coordinates":[-100.761532,41.138165],"type":"Point"}
}