{
  "type": "Feature",
  "properties": {
    "iso:country":"US",
    "sg:address":"107 Main St",
    "sg:city":"Crofton",
    "sg:classifiers":[
        {
            "category":"Bars & Pubs",
            "type":"Food & Drink"
        }
    ],
    "sg:phone":"+1 402 388 4546",
    "sg:postcode":"68730",
    "sg:province":"NE",
    "sg:tags":[
        "lounge",
        "cocktail"
    ],
    "wof:name":"Fritz's Bar",
    "wof:placetype":"venue"
},
  "geometry": {"coordinates":[-97.495948,42.732304],"type":"Point"}
}