{
  "type": "Feature",
  "properties": {
    "iso:country":"US",
    "sg:address":"21430 Buckeye Rd",
    "sg:city":"Gibbon",
    "sg:phone":"+1 308 452 3023",
    "sg:postcode":"68840",
    "sg:province":"NE",
    "sg:tags":[
        "farm",
        "corn"
    ],
    "wof:name":"Donald Stittle",
    "wof:placetype":"venue"
},
  "geometry": {"coordinates":[-98.93134499999999,40.876665],"type":"Point"}
}