{
  "type": "Feature",
  "properties": {
    "addr:full":"543 E 7th St Superior NE 68978",
    "addr:housenumber":"543",
    "addr:postcode":"68978",
    "addr:street":"E 7Th St",
    "iso:country":"US",
    "sg:address":"543 E 7th St",
    "sg:city":"Superior",
    "sg:classifiers":[
        {
            "category":"Recreation",
            "type":"Entertainment"
        }
    ],
    "sg:phone":"+1 402 879 3895",
    "sg:postcode":"68978",
    "sg:province":"NE",
    "sg:tags":[
        "pool",
        "swimming"
    ],
    "wof:name":"Swimming Pool",
    "wof:placetype":"venue"
},
  "geometry": {"coordinates":[-98.065549,40.022948],"type":"Point"}
}