{
  "type": "Feature",
  "properties": {
    "iso:country":"US",
    "sg:address":"416 Center Ave",
    "sg:city":"Holbrook",
    "sg:classifiers":[
        {
            "category":"Banks & Credit Unions",
            "subcategory":"Investment Brokerage",
            "type":"Services"
        }
    ],
    "sg:phone":"+1 308 493 5605",
    "sg:postcode":"68948",
    "sg:province":"NE",
    "sg:tags":[
        "commodity"
    ],
    "sg:website":"www.powergenetics.com",
    "wof:name":"Anderson Livestock",
    "wof:placetype":"venue"
},
  "geometry": {"coordinates":[-100.01023499999999,40.30569],"type":"Point"}
}