{
  "type": "Feature",
  "properties": {
    "iso:country":"US",
    "sg:address":"4815 S 107th Ave",
    "sg:city":"Omaha",
    "sg:classifiers":[
        {
            "category":"Professional",
            "subcategory":"Accounting & Tax Preparation",
            "type":"Services"
        }
    ],
    "sg:phone":"+1 402 592 3800",
    "sg:postcode":"68127",
    "sg:province":"NE",
    "sg:tags":[
        "firm",
        "accountant"
    ],
    "sg:website":"www.ofwf.com",
    "wof:name":"O'Donnell Ficenec Wills Ferdig",
    "wof:placetype":"venue"
},
  "geometry": {"coordinates":[-96.07905,41.21018],"type":"Point"}
}