{
  "type": "Feature",
  "properties": {
    "iso:country":"US",
    "sg:address":"180 Co Rd 18",
    "sg:city":"Scribner",
    "sg:phone":"+1 402 567 2244",
    "sg:postcode":"68057",
    "sg:province":"NE",
    "sg:tags":[
        "farm",
        "corn",
        "soybean"
    ],
    "wof:name":"Stephen Popken",
    "wof:placetype":"venue"
},
  "geometry": {"coordinates":[-96.578675,41.730065],"type":"Point"}
}