{
  "type": "Feature",
  "properties": {
    "iso:country":"US",
    "sg:address":"17021 Pierce St",
    "sg:city":"Omaha",
    "sg:classifiers":[
        {
            "category":"Shopping",
            "subcategory":"Beauty & Cosmetics",
            "type":"Retail Goods"
        }
    ],
    "sg:phone":"+1 402 758 1847",
    "sg:postcode":"68130",
    "sg:province":"NE",
    "sg:tags":[
        "merchandise"
    ],
    "wof:name":"Mary Kay Scebold-",
    "wof:placetype":"venue"
},
  "geometry": {"coordinates":[-96.18003899999999,41.247865],"type":"Point"}
}