{
  "type": "Feature",
  "properties": {
    "iso:country":"US",
    "sg:address":"1573 C Ave",
    "sg:city":"Dakota City",
    "sg:classifiers":[
        {
            "category":"Retail",
            "subcategory":"Auto Repair",
            "type":"Services"
        }
    ],
    "sg:phone":"+1 402 494 5888",
    "sg:postcode":"68731",
    "sg:province":"NE",
    "sg:tags":[
        "repairing",
        "automobile"
    ],
    "wof:name":"Siouxland Auto Svc Ctr",
    "wof:placetype":"venue"
},
  "geometry": {"coordinates":[-96.404416,42.437321],"type":"Point"}
}