{
  "type": "Feature",
  "properties": {
    "addr:full":"1651 N 42nd St Omaha NE 68111",
    "addr:housenumber":"1651",
    "addr:postcode":"68111",
    "addr:street":"N 42Nd St",
    "iso:country":"US",
    "sg:address":"1651 N 42nd St",
    "sg:city":"Omaha",
    "sg:classifiers":[
        {
            "category":"Manufacturing",
            "subcategory":"Building Materials",
            "type":"Manufacturing & Wholesale Goods"
        }
    ],
    "sg:phone":"+1 402 551 1551",
    "sg:postcode":"68111",
    "sg:province":"NE",
    "wof:name":"Z & S Architectural Inc",
    "wof:placetype":"venue"
},
  "geometry": {"coordinates":[-95.976477,41.274644],"type":"Point"}
}