{
  "type": "Feature",
  "properties": {
    "addr:full":"311 Rd 7 Henderson NE 68371",
    "addr:housenumber":"311",
    "addr:postcode":"68371",
    "addr:street":"Rd 7",
    "iso:country":"US",
    "sg:address":"311 Rd 7",
    "sg:city":"Henderson",
    "sg:phone":"+1 402 723 5206",
    "sg:postcode":"68371",
    "sg:province":"NE",
    "sg:tags":[
        "farm",
        "corn",
        "soybean"
    ],
    "wof:name":"Mark W Edelman",
    "wof:placetype":"venue"
},
  "geometry": {"coordinates":[-97.782399,40.785407],"type":"Point"}
}