{
  "type": "Feature",
  "properties": {
    "addr:full":"8210 F St Omaha NE 68127",
    "addr:housenumber":"8210",
    "addr:postcode":"68127",
    "addr:street":"F St",
    "iso:country":"US",
    "sg:address":"8210 F St",
    "sg:city":"Omaha",
    "sg:phone":"+1 402 342 4956",
    "sg:postcode":"68127",
    "sg:province":"NE",
    "sg:tags":[
        "bulk",
        "gas"
    ],
    "wof:name":"Praxair Inc",
    "wof:placetype":"venue"
},
  "geometry": {"coordinates":[-96.041785,41.21981],"type":"Point"}
}