{
  "type": "Feature",
  "properties": {
    "iso:country":"US",
    "sg:address":"1403 Farnam St Ste 232",
    "sg:city":"Omaha",
    "sg:classifiers":[
        {
            "category":"Professional",
            "subcategory":"Lawyer & Legal Services",
            "type":"Services"
        }
    ],
    "sg:phone":"+1 402 884 7044",
    "sg:postcode":"68102",
    "sg:province":"NE",
    "wof:name":"Dornan Stuart",
    "wof:placetype":"venue"
},
  "geometry": {"coordinates":[-95.93455899999999,41.257453],"type":"Point"}
}