{
  "type": "Feature",
  "properties": {
    "addr:full":"959 Co Rd 15 Schuyler NE 68661",
    "addr:housenumber":"959;15",
    "addr:postcode":"68661",
    "addr:street":"Co Rd",
    "iso:country":"US",
    "sg:address":"959 Co Rd 15",
    "sg:city":"Schuyler",
    "sg:classifiers":[
        {
            "category":"Building & Trades",
            "subcategory":"Construction",
            "type":"Services"
        }
    ],
    "sg:phone":"+1 402 352 5779",
    "sg:postcode":"68661",
    "sg:province":"NE",
    "sg:tags":[
        "excavation",
        "contractor"
    ],
    "wof:name":"Kohl Construction  Inc",
    "wof:placetype":"venue"
},
  "geometry": {"coordinates":[-96.98347,41.518257],"type":"Point"}
}