{
  "type": "Feature",
  "properties": {
    "iso:country":"US",
    "sg:address":"2115 S 214th St",
    "sg:city":"Eagle",
    "sg:classifiers":[
        {
            "category":"Farming",
            "subcategory":"Livestock Farm",
            "type":"Manufacturing & Wholesale Goods"
        }
    ],
    "sg:phone":"+1 402 797 2111",
    "sg:postcode":"68347",
    "sg:province":"NE",
    "sg:tags":[
        "horse",
        "ranch"
    ],
    "wof:name":"Sunrise Equitherapy Inc",
    "wof:placetype":"venue"
},
  "geometry": {"coordinates":[-96.426368,40.785579],"type":"Point"}
}