{
  "type": "Feature",
  "properties": {
    "addr:full":"3201 S 7th St Lincoln NE 68502",
    "addr:housenumber":"3201",
    "addr:postcode":"68502",
    "addr:street":"S 7Th St",
    "iso:country":"US",
    "sg:address":"3201 S 7th St",
    "sg:city":"Lincoln",
    "sg:classifiers":[
        {
            "category":"Retail",
            "subcategory":"Auto Repair",
            "type":"Services"
        }
    ],
    "sg:phone":"+1 402 525 0418",
    "sg:postcode":"68502",
    "sg:province":"NE",
    "sg:tags":[
        "general"
    ],
    "wof:name":"Chucks Repair",
    "wof:placetype":"venue"
},
  "geometry": {"coordinates":[-96.711619,40.790126],"type":"Point"}
}