{
  "type": "Feature",
  "properties": {
    "iso:country":"US",
    "sg:address":"2515 3rd Ave",
    "sg:city":"Kearney",
    "sg:classifiers":[
        {
            "category":"Health Services",
            "subcategory":"Optometrist",
            "type":"Services"
        }
    ],
    "sg:phone":"+1 308 234 3331",
    "sg:postcode":"68845",
    "sg:province":"NE",
    "wof:name":"Howard L Christman Od",
    "wof:placetype":"venue"
},
  "geometry": {"coordinates":[-99.085671,40.700485],"type":"Point"}
}