{
  "type": "Feature",
  "properties": {
    "iso:country":"US",
    "sg:address":"2464 S 54 Rd",
    "sg:city":"Firth",
    "sg:classifiers":[
        {
            "category":"Manufacturing",
            "subcategory":"Tools & Machinery",
            "type":"Manufacturing & Wholesale Goods"
        }
    ],
    "sg:phone":"+1 402 791 2150",
    "sg:postcode":"68358",
    "sg:province":"NE",
    "sg:tags":[
        "machine",
        "shop"
    ],
    "wof:name":"Rosene Machine",
    "wof:placetype":"venue"
},
  "geometry": {"coordinates":[-96.647901,40.49765],"type":"Point"}
}