{
  "type": "Feature",
  "properties": {
    "iso:country":"US",
    "sg:address":"111 N 56th St",
    "sg:city":"Lincoln",
    "sg:classifiers":[
        {
            "category":"Social Services",
            "type":"Services"
        }
    ],
    "sg:phone":"+1 402 730 7158",
    "sg:postcode":"68504",
    "sg:province":"NE",
    "sg:tags":[
        "counseling"
    ],
    "wof:name":"Labyrinth Inc Christian",
    "wof:placetype":"venue"
},
  "geometry": {"coordinates":[-96.64422,40.81455],"type":"Point"}
}