{
  "type": "Feature",
  "properties": {
    "iso:country":"US",
    "sg:address":"55551 State Hwy 84",
    "sg:city":"Hartington",
    "sg:classifiers":[
        {
            "category":"Farming",
            "subcategory":"Farm",
            "type":"Manufacturing & Wholesale Goods"
        }
    ],
    "sg:phone":"+1 402 254 6707",
    "sg:postcode":"68739",
    "sg:province":"NE",
    "sg:tags":[
        "crop",
        "general"
    ],
    "wof:name":"Vernon Lammers",
    "wof:placetype":"venue"
},
  "geometry": {"coordinates":[-97.424435,42.612888],"type":"Point"}
}