{
  "type": "Feature",
  "properties": {
    "iso:country":"US",
    "sg:address":"120189 Co Rd H",
    "sg:city":"Mitchell",
    "sg:classifiers":[
        {
            "category":"Farming",
            "subcategory":"Farm",
            "type":"Manufacturing & Wholesale Goods"
        }
    ],
    "sg:phone":"+1 308 623 2619",
    "sg:postcode":"69357",
    "sg:province":"NE",
    "sg:tags":[
        "crop",
        "general"
    ],
    "wof:name":"Hessler Farms",
    "wof:placetype":"venue"
},
  "geometry": {"coordinates":[-103.84474400000001,41.900854],"type":"Point"}
}