{
  "type": "Feature",
  "properties": {
    "addr:full":"515 N 13th St Beatrice NE 68310",
    "addr:housenumber":"515",
    "addr:postcode":"68310",
    "addr:street":"N 13Th St",
    "iso:country":"US",
    "sg:address":"515 N 13th St",
    "sg:city":"Beatrice",
    "sg:classifiers":[
        {
            "category":"Professional",
            "subcategory":"Business Services",
            "type":"Services"
        }
    ],
    "sg:phone":"+1 402 228 6499",
    "sg:postcode":"68310",
    "sg:province":"NE",
    "sg:tags":[
        "broker",
        "merchandise"
    ],
    "wof:name":"K & S Brokerage",
    "wof:placetype":"venue"
},
  "geometry": {"coordinates":[-96.737225,40.270574],"type":"Point"}
}