{
  "type": "Feature",
  "properties": {
    "addr:full":"1615 N Bell St Fremont NE 68025",
    "addr:housenumber":"1615",
    "addr:postcode":"68025",
    "addr:street":"N Bell St",
    "iso:country":"US",
    "sg:address":"1615 N Bell St",
    "sg:city":"Fremont",
    "sg:classifiers":[
        {
            "category":"Food & Beverages",
            "subcategory":"Groceries & Convenience Stores",
            "type":"Retail Goods"
        }
    ],
    "sg:phone":"+1 402 727 5202",
    "sg:postcode":"68025",
    "sg:province":"NE",
    "wof:name":"KWIK Shop",
    "wof:placetype":"venue"
},
  "geometry": {"coordinates":[-96.483587,41.44528],"type":"Point"}
}