{
  "type": "Feature",
  "properties": {
    "iso:country":"US",
    "sg:address":"215 Centennial Mall S",
    "sg:city":"Lincoln",
    "sg:classifiers":[
        {
            "category":"Social Services",
            "type":"Services"
        }
    ],
    "sg:phone":"+1 402 476 5024",
    "sg:postcode":"68508",
    "sg:province":"NE",
    "sg:tags":[
        "youth",
        "organization",
        "center"
    ],
    "wof:name":"Youth Development Program",
    "wof:placetype":"venue"
},
  "geometry": {"coordinates":[-96.69976200000001,40.811544],"type":"Point"}
}