{
  "type": "Feature",
  "properties": {
    "iso:country":"US",
    "sg:address":"4041 N 72nd St",
    "sg:city":"Omaha",
    "sg:classifiers":[
        {
            "category":"Education",
            "subcategory":"Special Training",
            "type":"Public Place"
        }
    ],
    "sg:phone":"+1 402 557 2800",
    "sg:postcode":"68134",
    "sg:province":"NE",
    "wof:name":"Omaha Public School Svc Ctr",
    "wof:placetype":"venue"
},
  "geometry": {"coordinates":[-96.023815,41.294498],"type":"Point"}
}