{
  "type": "Feature",
  "properties": {
    "iso:country":"US",
    "sg:address":"2305 S 84th St",
    "sg:city":"Omaha",
    "sg:classifiers":[
        {
            "category":"Real Estate",
            "subcategory":"Real Estate Operator",
            "type":"Services"
        }
    ],
    "sg:phone":"+1 402 391 8728",
    "sg:postcode":"68124",
    "sg:province":"NE",
    "sg:tags":[
        "building",
        "nonresidential"
    ],
    "wof:name":"Hynek Properties LLC",
    "wof:placetype":"venue"
},
  "geometry": {"coordinates":[-96.043632,41.236634],"type":"Point"}
}