{
  "type": "Feature",
  "properties": {
    "iso:country":"US",
    "sg:address":"510 D St",
    "sg:city":"Fairbury",
    "sg:classifiers":[
        {
            "category":"Social Services",
            "type":"Services"
        }
    ],
    "sg:phone":"+1 402 729 6379",
    "sg:postcode":"68352",
    "sg:province":"NE",
    "wof:name":"Lincolin Family Practice",
    "wof:placetype":"venue"
},
  "geometry": {"coordinates":[-97.181206,40.137143],"type":"Point"}
}