{
  "type": "Feature",
  "properties": {
    "addr:full":"9341 G Ct Omaha NE 68127",
    "addr:housenumber":"9341",
    "addr:postcode":"68127",
    "addr:street":"G Ct",
    "iso:country":"US",
    "sg:address":"9341 G Ct",
    "sg:city":"Omaha",
    "sg:classifiers":[
        {
            "category":"Wholesale",
            "subcategory":"Auto Parts",
            "type":"Manufacturing & Wholesale Goods"
        }
    ],
    "sg:phone":"+1 402 592 5400",
    "sg:postcode":"68127",
    "sg:province":"NE",
    "sg:tags":[
        "equipment",
        "truck"
    ],
    "wof:name":"Heavy Duty Specialists Inc",
    "wof:placetype":"venue"
},
  "geometry": {"coordinates":[-96.05775199999999,41.218287],"type":"Point"}
}