{
  "type": "Feature",
  "properties": {
    "addr:full":"902 E 7th St North Platte NE 69101",
    "addr:housenumber":"902",
    "addr:postcode":"69101",
    "addr:street":"E 7Th St",
    "iso:country":"US",
    "sg:address":"902 E 7th St",
    "sg:city":"North Platte",
    "sg:classifiers":[
        {
            "category":"Autos & Motor Vehicles",
            "subcategory":"Auto Supplies",
            "type":"Retail Goods"
        }
    ],
    "sg:phone":"+1 308 532 6660",
    "sg:postcode":"69101",
    "sg:province":"NE",
    "sg:tags":[
        "automobile",
        "parts"
    ],
    "wof:name":"Maxwell's Off-Road Ctr",
    "wof:placetype":"venue"
},
  "geometry": {"coordinates":[-100.752264,41.140065],"type":"Point"}
}