{
  "type": "Feature",
  "properties": {
    "addr:full":"425 N Colorado Ave Minden NE 68959",
    "addr:housenumber":"425",
    "addr:postcode":"68959",
    "addr:street":"N Colorado Ave",
    "iso:country":"US",
    "sg:address":"425 N Colorado Ave",
    "sg:city":"Minden",
    "sg:classifiers":[
        {
            "category":"Manufacturing",
            "subcategory":"Printing",
            "type":"Manufacturing & Wholesale Goods"
        }
    ],
    "sg:phone":"+1 308 832 1205",
    "sg:postcode":"68959",
    "sg:province":"NE",
    "sg:tags":[
        "screen"
    ],
    "wof:name":"D & D Custom Screen Printing",
    "wof:placetype":"venue"
},
  "geometry": {"coordinates":[-98.949185,40.499183],"type":"Point"}
}