{
  "type": "Feature",
  "properties": {
    "iso:country":"US",
    "sg:address":"2808 32nd St",
    "sg:city":"Columbus",
    "sg:classifiers":[
        {
            "category":"Building & Trades",
            "subcategory":"Construction",
            "type":"Services"
        }
    ],
    "sg:phone":"+1 402 563 2765",
    "sg:postcode":"68601",
    "sg:province":"NE",
    "sg:tags":[
        "roofing",
        "contractor"
    ],
    "wof:name":"Christopher Roofing",
    "wof:placetype":"venue"
},
  "geometry": {"coordinates":[-97.36105999999999,41.446854],"type":"Point"}
}