{
  "type": "Feature",
  "properties": {
    "iso:country":"US",
    "sg:address":"603 Park Ave",
    "sg:city":"Norfolk",
    "sg:classifiers":[
        {
            "category":"Building & Trades",
            "subcategory":"Construction",
            "type":"Services"
        }
    ],
    "sg:phone":"+1 402 379 1847",
    "sg:postcode":"68701",
    "sg:province":"NE",
    "sg:tags":[
        "residential"
    ],
    "wof:name":"B & K Construction",
    "wof:placetype":"venue"
},
  "geometry": {"coordinates":[-97.416078,42.028987],"type":"Point"}
}