{
  "type": "Feature",
  "properties": {
    "iso:country":"US",
    "sg:address":"710 Diers Ave",
    "sg:city":"Grand Island",
    "sg:classifiers":[
        {
            "category":"Wholesale",
            "subcategory":"Office Equipment",
            "type":"Manufacturing & Wholesale Goods"
        }
    ],
    "sg:phone":"+1 308 382 7712",
    "sg:postcode":"68803",
    "sg:province":"NE",
    "sg:tags":[
        "machine",
        "duplicating",
        "copying"
    ],
    "wof:name":"Imagistics International Inc",
    "wof:placetype":"venue"
},
  "geometry": {"coordinates":[-98.384642,40.923002],"type":"Point"}
}