{
  "type": "Feature",
  "properties": {
    "iso:country":"US",
    "sg:address":"315 W Riverside Dr",
    "sg:city":"Yankton",
    "sg:classifiers":[
        {
            "category":"Government",
            "subcategory":"Office",
            "type":"Public Place"
        }
    ],
    "sg:phone":"+1 605 668 5272",
    "sg:postcode":"57078",
    "sg:province":"NE",
    "sg:tags":[
        "village"
    ],
    "wof:name":"Yankton Water Plant #1 Mntnc",
    "wof:placetype":"venue"
},
  "geometry": {"coordinates":[-97.396823,42.867434],"type":"Point"}
}