{
  "type": "Feature",
  "properties": {
    "addr:full":"8456 Freedom Ln Fort Calhoun NE 68023",
    "addr:housenumber":"8456",
    "addr:postcode":"68023",
    "addr:street":"Freedom Ln",
    "iso:country":"US",
    "sg:address":"8456 Freedom Ln",
    "sg:city":"Fort Calhoun",
    "sg:classifiers":[
        {
            "category":"Recreation",
            "type":"Entertainment"
        }
    ],
    "sg:phone":"+1 402 468 4832",
    "sg:postcode":"68023",
    "sg:province":"NE",
    "wof:name":"Liberty Stables",
    "wof:placetype":"venue"
},
  "geometry": {"coordinates":[-96.06599300000001,41.465335],"type":"Point"}
}