{
  "type": "Feature",
  "properties": {
    "addr:full":"1523 M St Ord NE 68862",
    "addr:housenumber":"1523",
    "addr:postcode":"68862",
    "addr:street":"M St",
    "iso:country":"US",
    "sg:address":"1523 M St",
    "sg:city":"Ord",
    "sg:classifiers":[
        {
            "category":"Shopping",
            "subcategory":"Gifts & Souvenirs",
            "type":"Retail Goods"
        }
    ],
    "sg:phone":"+1 308 728 5770",
    "sg:postcode":"68862",
    "sg:province":"NE",
    "wof:name":"Creative Designs",
    "wof:placetype":"venue"
},
  "geometry": {"coordinates":[-98.92912099999999,41.602062],"type":"Point"}
}