{
  "type": "Feature",
  "properties": {
    "iso:country":"US",
    "sg:address":"4491 O Rd",
    "sg:city":"Talmage",
    "sg:phone":"+1 402 259 4195",
    "sg:postcode":"68448",
    "sg:province":"NE",
    "sg:tags":[
        "farm",
        "corn",
        "soybean"
    ],
    "wof:name":"Edward Damme",
    "wof:placetype":"venue"
},
  "geometry": {"coordinates":[-96.02940099999999,40.581173],"type":"Point"}
}