{
  "type": "Feature",
  "properties": {
    "addr:full":"4019 S 48th St Lincoln NE 68506",
    "addr:housenumber":"4019",
    "addr:postcode":"68506",
    "addr:street":"S 48Th St",
    "iso:country":"US",
    "sg:address":"4019 S 48th St",
    "sg:city":"Lincoln",
    "sg:classifiers":[
        {
            "category":"Home & Garden",
            "subcategory":"Building Materials",
            "type":"Retail Goods"
        }
    ],
    "sg:phone":"+1 402 486 4688",
    "sg:postcode":"68506",
    "sg:province":"NE",
    "sg:tags":[
        "windows"
    ],
    "wof:name":"New Windows Now",
    "wof:placetype":"venue"
},
  "geometry": {"coordinates":[-96.654143,40.772014],"type":"Point"}
}