{
  "type": "Feature",
  "properties": {
    "iso:country":"US",
    "sg:address":"801 Ivy St",
    "sg:city":"Stanton",
    "sg:phone":"+1 402 439 2099",
    "sg:postcode":"68779",
    "sg:province":"NE",
    "sg:tags":[
        "oil"
    ],
    "wof:name":"Luedeke Oil Co",
    "wof:placetype":"venue"
},
  "geometry": {"coordinates":[-97.222511,41.950395],"type":"Point"}
}