{
  "type": "Feature",
  "properties": {
    "iso:country":"US",
    "sg:address":"1202 N Jeffers St",
    "sg:city":"North Platte",
    "sg:classifiers":[
        {
            "category":"Restaurant",
            "type":"Food & Drink"
        }
    ],
    "sg:phone":"+1 308 534 5543",
    "sg:postcode":"69101",
    "sg:province":"NE",
    "sg:tags":[
        "fast"
    ],
    "wof:name":"Wendys",
    "wof:placetype":"venue"
},
  "geometry": {"coordinates":[-100.760867,41.147211],"type":"Point"}
}