{
  "type": "Feature",
  "properties": {
    "iso:country":"US",
    "sg:address":"13915 W Pony Express Rd",
    "sg:city":"Roseland",
    "sg:phone":"+1 402 756 6741",
    "sg:postcode":"68973",
    "sg:province":"NE",
    "sg:tags":[
        "farm",
        "grain",
        "cash"
    ],
    "wof:name":"Edward Bourg",
    "wof:placetype":"venue"
},
  "geometry": {"coordinates":[-98.589651,40.451634],"type":"Point"}
}