{
  "type": "Feature",
  "properties": {
    "addr:full":"1830 N Bell St Fremont NE 68025",
    "addr:housenumber":"1830",
    "addr:postcode":"68025",
    "addr:street":"N Bell St",
    "iso:country":"US",
    "sg:address":"1830 N Bell St",
    "sg:city":"Fremont",
    "sg:classifiers":[
        {
            "category":"Wholesale",
            "subcategory":"Sporting Goods",
            "type":"Manufacturing & Wholesale Goods"
        },
        {
            "category":"Shopping",
            "subcategory":"Catalog Store",
            "type":"Retail Goods"
        },
        {
            "category":"Shopping",
            "subcategory":"Bicycles & Sporting Goods",
            "type":"Retail Goods"
        }
    ],
    "sg:phone":"+1 402 721 8864",
    "sg:postcode":"68025",
    "sg:province":"NE",
    "sg:tags":[
        "mail",
        "house"
    ],
    "wof:name":"Wisners Sports Supply Inc",
    "wof:placetype":"venue"
},
  "geometry": {"coordinates":[-96.48342700000001,41.447065],"type":"Point"}
}