{
  "type": "Feature",
  "properties": {
    "addr:full":"25108 Adams St Elmwood NE 68349",
    "addr:housenumber":"25108",
    "addr:postcode":"68349",
    "addr:street":"Adams St",
    "iso:country":"US",
    "sg:address":"25108 Adams St",
    "sg:city":"Elmwood",
    "sg:classifiers":[
        {
            "category":"Professional",
            "subcategory":"Management & Consulting",
            "type":"Services"
        }
    ],
    "sg:phone":"+1 402 781 2263",
    "sg:postcode":"68349",
    "sg:province":"NE",
    "sg:tags":[
        "consultant",
        "business"
    ],
    "wof:name":"Synchrotech",
    "wof:placetype":"venue"
},
  "geometry": {"coordinates":[-96.37001100000001,40.841929],"type":"Point"}
}