{
  "type": "Feature",
  "properties": {
    "iso:country":"US",
    "sg:address":"5900 S 58th St",
    "sg:city":"Lincoln",
    "sg:classifiers":[
        {
            "category":"Professional",
            "subcategory":"Management & Consulting",
            "type":"Services"
        }
    ],
    "sg:phone":"+1 402 421 6767",
    "sg:postcode":"68516",
    "sg:province":"NE",
    "sg:tags":[
        "agricultural",
        "consultant"
    ],
    "wof:name":"Cattlemen's Nutrition Svc",
    "wof:placetype":"venue"
},
  "geometry": {"coordinates":[-96.64191599999999,40.752641],"type":"Point"}
}