{
  "type": "Feature",
  "properties": {
    "addr:full":"4428 S 140th St Omaha NE 68137",
    "addr:housenumber":"4428",
    "addr:postcode":"68137",
    "addr:street":"S 140Th St",
    "iso:country":"US",
    "sg:address":"4428 S 140th St",
    "sg:city":"Omaha",
    "sg:classifiers":[
        {
            "category":"Restaurant",
            "type":"Food & Drink"
        }
    ],
    "sg:menulink":"http://www.allmenus.com/ne/omaha/241802-the-digz/menu/",
    "sg:phone":"+1 402 896 3663",
    "sg:postcode":"68137",
    "sg:province":"NE",
    "sg:tags":[
        "american"
    ],
    "wof:name":"The Digz",
    "wof:placetype":"venue"
},
  "geometry": {"coordinates":[-96.13365899999999,41.21515],"type":"Point"}
}