{
  "type": "Feature",
  "properties": {
    "iso:country":"US",
    "sg:address":"1112 E Linden Ave",
    "sg:city":"Fremont",
    "sg:classifiers":[
        {
            "category":"Professional",
            "type":"Services"
        }
    ],
    "sg:phone":"+1 402 320 5156",
    "sg:postcode":"68025",
    "sg:province":"NE",
    "sg:tags":[
        "translation",
        "interpretation"
    ],
    "wof:name":"La Raza",
    "wof:placetype":"venue"
},
  "geometry": {"coordinates":[-96.483339,41.441505],"type":"Point"}
}