{
  "type": "Feature",
  "properties": {
    "iso:country":"US",
    "sg:address":"211 N Tilden St",
    "sg:city":"Grand Island",
    "sg:classifiers":[
        {
            "category":"Building & Trades",
            "subcategory":"Construction",
            "type":"Services"
        }
    ],
    "sg:phone":"+1 308 385 6265",
    "sg:postcode":"68803",
    "sg:province":"NE",
    "sg:tags":[
        "road",
        "contractor"
    ],
    "wof:name":"Roads Dept",
    "wof:placetype":"venue"
},
  "geometry": {"coordinates":[-98.36036799999999,40.916816],"type":"Point"}
}