{
  "type": "Feature",
  "properties": {
    "addr:full":"22708 Bluff Rd Alvo NE 68366",
    "addr:housenumber":"22708",
    "addr:postcode":"68366",
    "addr:street":"Bluff Rd",
    "iso:country":"US",
    "sg:address":"22708 Bluff Rd",
    "sg:city":"Alvo",
    "sg:phone":"+1 402 781 9287",
    "sg:postcode":"68366",
    "sg:province":"NE",
    "sg:tags":[
        "farm",
        "grain",
        "cash"
    ],
    "wof:name":"Eikerman Farms",
    "wof:placetype":"venue"
},
  "geometry": {"coordinates":[-96.40816599999999,40.9144],"type":"Point"}
}