{
  "type": "Feature",
  "properties": {
    "iso:country":"US",
    "sg:address":"2316 Lane St",
    "sg:city":"Falls City",
    "sg:phone":"+1 402 245 4284",
    "sg:postcode":"68355",
    "sg:province":"NE",
    "sg:tags":[
        "farm",
        "corn",
        "soybean"
    ],
    "wof:name":"Neal Parsons",
    "wof:placetype":"venue"
},
  "geometry": {"coordinates":[-95.600493,40.068472],"type":"Point"}
}