{
  "type": "Feature",
  "properties": {
    "iso:country":"US",
    "sg:address":"2913 Blackhawk Dr",
    "sg:city":"Bellevue",
    "sg:classifiers":[
        {
            "category":"Professional",
            "subcategory":"Management & Consulting",
            "type":"Services"
        }
    ],
    "sg:phone":"+1 402 292 9610",
    "sg:postcode":"68123",
    "sg:province":"NE",
    "sg:tags":[
        "technical",
        "field",
        "intelligence"
    ],
    "wof:name":"Spiral Solutions and Tech Inc",
    "wof:placetype":"venue"
},
  "geometry": {"coordinates":[-95.954413,41.109716],"type":"Point"}
}