{
  "type": "Feature",
  "properties": {
    "addr:full":"1402 Lake St Creighton NE 68729",
    "addr:housenumber":"1402",
    "addr:postcode":"68729",
    "addr:street":"Lake St",
    "iso:country":"US",
    "sg:address":"1402 Lake St",
    "sg:city":"Creighton",
    "sg:classifiers":[
        {
            "category":"Government",
            "subcategory":"Office",
            "type":"Public Place"
        }
    ],
    "sg:phone":"+1 402 358 3230",
    "sg:postcode":"68729",
    "sg:province":"NE",
    "wof:name":"KNOX County Shop District",
    "wof:placetype":"venue"
},
  "geometry": {"coordinates":[-97.916055,42.469583],"type":"Point"}
}