{
  "type": "Feature",
  "properties": {
    "addr:full":"1546 I St Geneva NE 68361",
    "addr:housenumber":"1546",
    "addr:postcode":"68361",
    "addr:street":"I St",
    "iso:country":"US",
    "sg:address":"1546 I St",
    "sg:city":"Geneva",
    "sg:phone":"+1 402 366 1691",
    "sg:postcode":"68361",
    "sg:province":"NE",
    "sg:tags":[
        "farm",
        "corn",
        "bean",
        "livestock"
    ],
    "wof:name":"Kleinschmidt Farms Inc",
    "wof:placetype":"venue"
},
  "geometry": {"coordinates":[-97.592006,40.528447],"type":"Point"}
}