{
  "type": "Feature",
  "properties": {
    "iso:country":"US",
    "sg:address":"2007 Maurer Dr",
    "sg:city":"Norfolk",
    "sg:classifiers":[
        {
            "category":"Wholesale",
            "subcategory":"Meat",
            "type":"Manufacturing & Wholesale Goods"
        }
    ],
    "sg:phone":"+1 402 371 8203",
    "sg:postcode":"68701",
    "sg:province":"NE",
    "wof:name":"Select Pork Inc",
    "wof:placetype":"venue"
},
  "geometry": {"coordinates":[-97.371431,42.035096],"type":"Point"}
}