{
  "type": "Feature",
  "properties": {
    "iso:country":"US",
    "sg:address":"509 Donner Pass",
    "sg:city":"Wayne",
    "sg:classifiers":[
        {
            "category":"Building & Trades",
            "subcategory":"Construction",
            "type":"Services"
        }
    ],
    "sg:phone":"+1 402 375 2062",
    "sg:postcode":"68787",
    "sg:province":"NE",
    "sg:tags":[
        "house"
    ],
    "wof:name":"Sebade Construction",
    "wof:placetype":"venue"
},
  "geometry": {"coordinates":[-97.030974,42.23453],"type":"Point"}
}