{
  "type": "Feature",
  "properties": {
    "iso:country":"US",
    "sg:address":"710 Howard Ave",
    "sg:city":"St Paul",
    "sg:classifiers":[
        {
            "category":"Real Estate",
            "subcategory":"Real Estate Services",
            "type":"Services"
        }
    ],
    "sg:phone":"+1 308 754 4922",
    "sg:postcode":"68873",
    "sg:province":"NE",
    "sg:tags":[
        "abstract",
        "title"
    ],
    "wof:name":"Saint Paul Abstract & Title",
    "wof:placetype":"venue"
},
  "geometry": {"coordinates":[-98.459316,41.213453],"type":"Point"}
}