{
  "type": "Feature",
  "properties": {
    "iso:country":"US",
    "sg:address":"251 Main St",
    "sg:city":"Chadron",
    "sg:classifiers":[
        {
            "category":"Restaurant",
            "type":"Food & Drink"
        }
    ],
    "sg:phone":"+1 308 432 5500",
    "sg:postcode":"69337",
    "sg:province":"NE",
    "wof:name":"Angela's Eatery",
    "wof:placetype":"venue"
},
  "geometry": {"coordinates":[-103.000578,42.830204],"type":"Point"}
}