{
  "type": "Feature",
  "properties": {
    "iso:country":"US",
    "sg:address":"9672 11th Ave",
    "sg:city":"Columbus",
    "sg:classifiers":[
        {
            "category":"Shopping",
            "subcategory":"Beauty & Cosmetics",
            "type":"Retail Goods"
        }
    ],
    "sg:phone":"+1 402 563 3713",
    "sg:postcode":"68601",
    "sg:province":"NE",
    "sg:tags":[
        "merchandise"
    ],
    "wof:name":"Mary Kay Cosmetics",
    "wof:placetype":"venue"
},
  "geometry": {"coordinates":[-97.34073600000001,41.507903],"type":"Point"}
}