{
  "type": "Feature",
  "properties": {
    "iso:country":"US",
    "sg:address":"3500 Rolling Hills Dr",
    "sg:city":"Norfolk",
    "sg:classifiers":[
        {
            "category":"Building & Trades",
            "subcategory":"Construction",
            "type":"Services"
        }
    ],
    "sg:phone":"+1 402 379 1781",
    "sg:postcode":"68701",
    "sg:province":"NE",
    "sg:tags":[
        "concrete",
        "contractor"
    ],
    "wof:name":"Wragge's Construction",
    "wof:placetype":"venue"
},
  "geometry": {"coordinates":[-97.46212300000001,42.042331],"type":"Point"}
}