{
  "type": "Feature",
  "properties": {
    "addr:full":"6930 Dudley St Lincoln NE 68505",
    "addr:housenumber":"6930",
    "addr:postcode":"68505",
    "addr:street":"Dudley St",
    "iso:country":"US",
    "sg:address":"6930 Dudley St",
    "sg:city":"Lincoln",
    "sg:classifiers":[
        {
            "category":"Shopping",
            "subcategory":"Computers & Home Electronics",
            "type":"Retail Goods"
        }
    ],
    "sg:phone":"+1 402 464 0901",
    "sg:postcode":"68505",
    "sg:province":"NE",
    "wof:name":"Pro Voice Solutions",
    "wof:placetype":"venue"
},
  "geometry": {"coordinates":[-96.62534100000001,40.825957],"type":"Point"}
}