{
  "type": "Feature",
  "properties": {
    "addr:full":"2401 11th St Columbus NE 68601",
    "addr:housenumber":"2401",
    "addr:postcode":"68601",
    "addr:street":"11Th St",
    "iso:country":"US",
    "sg:address":"2401 11th St",
    "sg:city":"Columbus",
    "sg:classifiers":[
        {
            "category":"Home & Garden",
            "subcategory":"Furniture",
            "type":"Retail Goods"
        }
    ],
    "sg:phone":"+1 402 562 7929",
    "sg:postcode":"68601",
    "sg:province":"NE",
    "wof:name":"Bird & Garden Haven",
    "wof:placetype":"venue"
},
  "geometry": {"coordinates":[-97.35821199999999,41.427263],"type":"Point"}
}