{
  "type": "Feature",
  "properties": {
    "iso:country":"US",
    "sg:address":"4817 S 24th St",
    "sg:city":"Omaha",
    "sg:classifiers":[
        {
            "category":"Retail",
            "subcategory":"Repair Shop",
            "type":"Services"
        }
    ],
    "sg:phone":"+1 402 556 2900",
    "sg:postcode":"68107",
    "sg:province":"NE",
    "sg:tags":[
        "appliance"
    ],
    "wof:name":"Ackron Appliance Svc & Sales",
    "wof:placetype":"venue"
},
  "geometry": {"coordinates":[-95.946983,41.209923],"type":"Point"}
}