{
  "type": "Feature",
  "properties": {
    "iso:country":"US",
    "sg:address":"2525 N 90th St",
    "sg:city":"Omaha",
    "sg:classifiers":[
        {
            "category":"Autos & Motor Vehicles",
            "subcategory":"Automobile Sales",
            "type":"Retail Goods"
        }
    ],
    "sg:phone":"+1 402 397 0644",
    "sg:postcode":"68134",
    "sg:province":"NE",
    "sg:tags":[
        "car",
        "dealer"
    ],
    "wof:name":"Bob Eaton Auto Sales",
    "wof:placetype":"venue"
},
  "geometry": {"coordinates":[-96.05261299999999,41.281863],"type":"Point"}
}