{
  "type": "Feature",
  "properties": {
    "iso:country":"US",
    "sg:address":"21648 SW 45 Rd",
    "sg:city":"Beatrice",
    "sg:classifiers":[
        {
            "category":"Farming",
            "subcategory":"Farm",
            "type":"Manufacturing & Wholesale Goods"
        }
    ],
    "sg:phone":"+1 402 228 0631",
    "sg:postcode":"68310",
    "sg:province":"NE",
    "sg:tags":[
        "crop",
        "general"
    ],
    "wof:name":"Regier Gayland",
    "wof:placetype":"venue"
},
  "geometry": {"coordinates":[-96.784778,40.314419],"type":"Point"}
}