{
  "type": "Feature",
  "properties": {
    "iso:country":"US",
    "sg:address":"305 N 6th St",
    "sg:city":"Loup City",
    "sg:classifiers":[
        {
            "category":"Organizations",
            "subcategory":"Religious Organization",
            "type":"Services"
        }
    ],
    "sg:phone":"+1 308 745 1408",
    "sg:postcode":"68853",
    "sg:province":"NE",
    "sg:tags":[
        "church"
    ],
    "wof:name":"First Baptist Church",
    "wof:placetype":"venue"
},
  "geometry": {"coordinates":[-98.96591100000001,41.277244],"type":"Point"}
}