{
  "type": "Feature",
  "properties": {
    "iso:country":"US",
    "sg:address":"3810 Ave A",
    "sg:city":"Kearney",
    "sg:classifiers":[
        {
            "category":"Banks & Credit Unions",
            "subcategory":"Investment Brokerage",
            "type":"Services"
        }
    ],
    "sg:phone":"+1 308 234 2437",
    "sg:postcode":"68847",
    "sg:province":"NE",
    "sg:tags":[
        "stock",
        "bond"
    ],
    "wof:name":"Multi Financial Securities",
    "wof:placetype":"venue"
},
  "geometry": {"coordinates":[-99.080213,40.713455],"type":"Point"}
}