{
  "type": "Feature",
  "properties": {
    "iso:country":"US",
    "sg:address":"2510 SW 18th St",
    "sg:city":"Lincoln",
    "sg:classifiers":[
        {
            "category":"Freight",
            "type":"Transportation"
        }
    ],
    "sg:phone":"+1 402 450 2021",
    "sg:postcode":"68522",
    "sg:province":"NE",
    "sg:tags":[
        "packing",
        "crating"
    ],
    "wof:name":"Jensen Arts Svc",
    "wof:placetype":"venue"
},
  "geometry": {"coordinates":[-96.747371,40.787984],"type":"Point"}
}