{
  "type": "Feature",
  "properties": {
    "addr:full":"1700 Market Ln Norfolk NE 68701",
    "addr:housenumber":"1700",
    "addr:postcode":"68701",
    "addr:street":"Market Ln",
    "iso:country":"US",
    "sg:address":"1700 Market Ln",
    "sg:city":"Norfolk",
    "sg:classifiers":[
        {
            "category":"Restaurant",
            "type":"Food & Drink"
        }
    ],
    "sg:menulink":"http://www.allmenus.com/ne/norfolk/155542-runza/menu/",
    "sg:phone":"+1 402 379 1663",
    "sg:postcode":"68701",
    "sg:province":"NE",
    "sg:tags":[
        "wrap",
        "american",
        "sandwich"
    ],
    "wof:name":"Runza",
    "wof:placetype":"venue"
},
  "geometry": {"coordinates":[-97.432102,42.018926],"type":"Point"}
}