{
  "type": "Feature",
  "properties": {
    "addr:full":"4111 4th Ave Kearney NE 68845",
    "addr:housenumber":"4111",
    "addr:postcode":"68845",
    "addr:street":"4Th Ave",
    "iso:country":"US",
    "sg:address":"4111 4th Ave",
    "sg:city":"Kearney",
    "sg:classifiers":[
        {
            "category":"Health Services",
            "subcategory":"Doctor",
            "type":"Services"
        }
    ],
    "sg:phone":"+1 308 236 6170",
    "sg:postcode":"68845",
    "sg:province":"NE",
    "sg:tags":[
        "physician",
        "surgeon"
    ],
    "wof:name":"W V Fattig MD",
    "wof:placetype":"venue"
},
  "geometry": {"coordinates":[-99.086692,40.715677],"type":"Point"}
}