{
  "type": "Feature",
  "properties": {
    "iso:country":"US",
    "sg:address":"7438 N 55th Plz",
    "sg:city":"Omaha",
    "sg:classifiers":[
        {
            "category":"Professional",
            "subcategory":"Management & Consulting",
            "type":"Services"
        }
    ],
    "sg:phone":"+1 402 933 7438",
    "sg:postcode":"68152",
    "sg:province":"NE",
    "sg:tags":[
        "business"
    ],
    "wof:name":"William Hayford",
    "wof:placetype":"venue"
},
  "geometry": {"coordinates":[-95.999441,41.325836],"type":"Point"}
}