{
  "type": "Feature",
  "properties": {
    "iso:country":"US",
    "sg:address":"2902 S 16th St",
    "sg:city":"Omaha",
    "sg:classifiers":[
        {
            "category":"Real Estate",
            "subcategory":"Real Estate Operator",
            "type":"Services"
        }
    ],
    "sg:phone":"+1 402 345 4906",
    "sg:postcode":"68108",
    "sg:province":"NE",
    "sg:tags":[
        "building",
        "apartment"
    ],
    "wof:name":"Zadina Land Heights",
    "wof:placetype":"venue"
},
  "geometry": {"coordinates":[-95.93743499999999,41.232247],"type":"Point"}
}