{
  "type": "Feature",
  "properties": {
    "addr:full":"4301 N 30th St Omaha NE 68111",
    "addr:housenumber":"4301",
    "addr:postcode":"68111",
    "addr:street":"N 30Th St",
    "iso:country":"US",
    "sg:address":"4301 N 30th St",
    "sg:city":"Omaha",
    "sg:classifiers":[
        {
            "category":"Education",
            "subcategory":"School",
            "type":"Public Place"
        }
    ],
    "sg:phone":"+1 402 554 6590",
    "sg:postcode":"68111",
    "sg:province":"NE",
    "sg:website":"www.ops.org",
    "wof:name":"Jefferson Elementary School",
    "wof:placetype":"venue"
},
  "geometry": {"coordinates":[-95.956474,41.297754],"type":"Point"}
}