{
  "type": "Feature",
  "properties": {
    "iso:country":"US",
    "sg:address":"360 SW 27th St",
    "sg:city":"Lincoln",
    "sg:classifiers":[
        {
            "category":"Manufacturing",
            "subcategory":"Electronics",
            "type":"Manufacturing & Wholesale Goods"
        }
    ],
    "sg:phone":"+1 402 474 2858",
    "sg:postcode":"68522",
    "sg:province":"NE",
    "sg:tags":[
        "electronic",
        "component",
        "mfg"
    ],
    "wof:name":"M I S Engineering",
    "wof:placetype":"venue"
},
  "geometry": {"coordinates":[-96.758833,40.811734],"type":"Point"}
}