{
  "type": "Feature",
  "properties": {
    "iso:country":"US",
    "sg:address":"4424 Bel-Ridge Dr",
    "sg:city":"Lincoln",
    "sg:classifiers":[
        {
            "category":"Building & Trades",
            "subcategory":"Construction",
            "type":"Services"
        }
    ],
    "sg:phone":"+1 402 477 4021",
    "sg:postcode":"68521",
    "sg:province":"NE",
    "sg:tags":[
        "roofing",
        "contractor"
    ],
    "wof:name":"Larry's Roofing",
    "wof:placetype":"venue"
},
  "geometry": {"coordinates":[-96.696851,40.85542],"type":"Point"}
}