{
  "type": "Feature",
  "properties": {
    "iso:country":"US",
    "sg:address":"20085 Co Rd 23",
    "sg:city":"Scottsbluff",
    "sg:classifiers":[
        {
            "category":"Real Estate",
            "subcategory":"Real Estate Operator",
            "type":"Services"
        }
    ],
    "sg:phone":"+1 308 632 2989",
    "sg:postcode":"69361",
    "sg:province":"NE",
    "sg:tags":[
        "property",
        "lessor"
    ],
    "wof:name":"G Mc Hale",
    "wof:placetype":"venue"
},
  "geometry": {"coordinates":[-103.638677,41.987036],"type":"Point"}
}