{
  "type": "Feature",
  "properties": {
    "iso:country":"US",
    "sg:address":"1921 SW 11th St",
    "sg:city":"Lincoln",
    "sg:classifiers":[
        {
            "category":"Real Estate",
            "subcategory":"Real Estate Agent",
            "type":"Services"
        }
    ],
    "sg:phone":"+1 402 477 6468",
    "sg:postcode":"68522",
    "sg:province":"NE",
    "sg:tags":[
        "management"
    ],
    "wof:name":"Cherry Hill Office Plaza",
    "wof:placetype":"venue"
},
  "geometry": {"coordinates":[-96.739369,40.79522],"type":"Point"}
}