{
  "type": "Feature",
  "properties": {
    "iso:country":"US",
    "sg:address":"7337 L St",
    "sg:city":"Omaha",
    "sg:classifiers":[
        {
            "category":"Autos & Motor Vehicles",
            "subcategory":"Motorcycle Sales",
            "type":"Retail Goods"
        }
    ],
    "sg:phone":"+1 402 331 0022",
    "sg:postcode":"68127",
    "sg:province":"NE",
    "wof:name":"Harley-Davidson",
    "wof:placetype":"venue"
},
  "geometry": {"coordinates":[-96.02736400000001,41.212429],"type":"Point"}
}