{
  "type": "Feature",
  "properties": {
    "addr:full":"6303 Center St Ste 103 Omaha NE 68106",
    "addr:housenumber":"6303",
    "addr:postcode":"68106",
    "addr:street":"Center St Ste 103",
    "iso:country":"US",
    "sg:address":"6303 Center St Ste 103",
    "sg:city":"Omaha",
    "sg:classifiers":[
        {
            "category":"Health Services",
            "subcategory":"Chiropractor",
            "type":"Services"
        }
    ],
    "sg:phone":"+1 402 933 1933",
    "sg:postcode":"68106",
    "sg:province":"NE",
    "sg:website":"aksarbenchiropractic.com/",
    "wof:name":"Pearson Chiropractic",
    "wof:placetype":"venue"
},
  "geometry": {"coordinates":[-96.010217,41.237806],"type":"Point"}
}