{
  "type": "Feature",
  "properties": {
    "addr:full":"1511 W 1st St Mc Cook NE 69001",
    "addr:housenumber":"1511",
    "addr:postcode":"69001",
    "addr:street":"W 1St St Mc Cook Ne",
    "iso:country":"US",
    "sg:address":"1511 W 1st St",
    "sg:city":"Mc Cook",
    "sg:classifiers":[
        {
            "category":"Retail",
            "subcategory":"Laundry & Dry Cleaning",
            "type":"Services"
        }
    ],
    "sg:phone":"+1 308 345 2838",
    "sg:postcode":"69001",
    "sg:province":"NE",
    "sg:tags":[
        "cleaners",
        "rug",
        "carpet"
    ],
    "wof:name":"Gillen's Carpet & Air Duct",
    "wof:placetype":"venue"
},
  "geometry": {"coordinates":[-100.626699,40.213792],"type":"Point"}
}