{
  "type": "Feature",
  "properties": {
    "iso:country":"US",
    "sg:address":"422 Main St",
    "sg:city":"Minatare",
    "sg:classifiers":[
        {
            "category":"Real Estate",
            "subcategory":"Real Estate Operator",
            "type":"Services"
        }
    ],
    "sg:phone":"+1 308 783 2797",
    "sg:postcode":"69356",
    "sg:province":"NE",
    "sg:tags":[
        "mobile",
        "home",
        "community"
    ],
    "wof:name":"Advanced Technology Repairs",
    "wof:placetype":"venue"
},
  "geometry": {"coordinates":[-103.503253,41.810237],"type":"Point"}
}