{
  "type": "Feature",
  "properties": {
    "iso:country":"US",
    "sg:address":"889 18th Rd",
    "sg:city":"West Point",
    "sg:classifiers":[
        {
            "category":"Farming",
            "subcategory":"Livestock Farm",
            "type":"Manufacturing & Wholesale Goods"
        }
    ],
    "sg:phone":"+1 402 372 3264",
    "sg:postcode":"68788",
    "sg:province":"NE",
    "sg:tags":[
        "beef",
        "feedlot",
        "cattle"
    ],
    "wof:name":"Feyerherm Farms Inc",
    "wof:placetype":"venue"
},
  "geometry": {"coordinates":[-96.690344,41.855112],"type":"Point"}
}