{
  "type": "Feature",
  "properties": {
    "iso:country":"US",
    "sg:address":"1412 H St",
    "sg:city":"Fairbury",
    "sg:classifiers":[
        {
            "category":"Cinema",
            "subcategory":"Movie Theater",
            "type":"Entertainment"
        }
    ],
    "sg:phone":"+1 402 729 3779",
    "sg:postcode":"68352",
    "sg:province":"NE",
    "sg:tags":[
        "motion",
        "picture"
    ],
    "wof:name":"Eugene Mueller",
    "wof:placetype":"venue"
},
  "geometry": {"coordinates":[-97.17577300000001,40.147574],"type":"Point"}
}