{
  "type": "Feature",
  "properties": {
    "addr:full":"410 N Minnesota Ave Hastings NE 68901",
    "addr:housenumber":"410",
    "addr:postcode":"68901",
    "addr:street":"N Minnesota Ave",
    "iso:country":"US",
    "sg:address":"410 N Minnesota Ave",
    "sg:city":"Hastings",
    "sg:classifiers":[
        {
            "category":"Insurance",
            "subcategory":"Insurance Agent",
            "type":"Services"
        }
    ],
    "sg:phone":"+1 402 463 5408",
    "sg:postcode":"68901",
    "sg:province":"NE",
    "wof:name":"Laura Schneider Insurance",
    "wof:placetype":"venue"
},
  "geometry": {"coordinates":[-98.38336700000001,40.587769],"type":"Point"}
}