{
  "type": "Feature",
  "properties": {
    "iso:country":"US",
    "sg:address":"610 Galvin Rd S",
    "sg:city":"Bellevue",
    "sg:classifiers":[
        {
            "category":"Restaurant",
            "type":"Food & Drink"
        }
    ],
    "sg:menulink":"http://www.allmenus.com/ne/bellevue/181586-wendys/menu/",
    "sg:phone":"+1 402 291 7157",
    "sg:postcode":"68005",
    "sg:province":"NE",
    "sg:tags":[
        "burger",
        "american",
        "soup"
    ],
    "wof:name":"Wendy's",
    "wof:placetype":"venue"
},
  "geometry": {"coordinates":[-95.918966,41.155159],"type":"Point"}
}