{
  "type": "Feature",
  "properties": {
    "iso:country":"US",
    "sg:address":"631 W 23rd St",
    "sg:city":"Yankton",
    "sg:classifiers":[
        {
            "category":"Professional",
            "subcategory":"Management & Consulting",
            "type":"Services"
        }
    ],
    "sg:phone":"+1 605 665 8425",
    "sg:postcode":"57078",
    "sg:province":"NE",
    "sg:tags":[
        "marketing",
        "program",
        "gas"
    ],
    "wof:name":"Plains Marketing Co",
    "wof:placetype":"venue"
},
  "geometry": {"coordinates":[-97.400063,42.894236],"type":"Point"}
}