{
  "type": "Feature",
  "properties": {
    "iso:country":"US",
    "sg:address":"306 E 6th St",
    "sg:city":"North Platte",
    "sg:classifiers":[
        {
            "category":"Government",
            "subcategory":"Office",
            "type":"Public Place"
        }
    ],
    "sg:phone":"+1 308 535 8320",
    "sg:postcode":"69101",
    "sg:province":"NE",
    "sg:tags":[
        "state",
        "inspection"
    ],
    "wof:name":"Labor Dept",
    "wof:placetype":"venue"
},
  "geometry": {"coordinates":[-100.76031,41.13806],"type":"Point"}
}