{
  "type": "Feature",
  "properties": {
    "iso:country":"US",
    "sg:address":"8106 Vernon Ave",
    "sg:city":"Omaha",
    "sg:classifiers":[
        {
            "category":"Building & Trades",
            "subcategory":"Cleaning & Sanitation",
            "type":"Services"
        }
    ],
    "sg:phone":"+1 402 573 0201",
    "sg:postcode":"68134",
    "sg:province":"NE",
    "sg:tags":[
        "janitor",
        "maintenance"
    ],
    "wof:name":"Sudds Cleaning Svc",
    "wof:placetype":"venue"
},
  "geometry": {"coordinates":[-96.03962799999999,41.316669],"type":"Point"}
}