{
  "type": "Feature",
  "properties": {
    "iso:country":"US",
    "sg:address":"700 Maple St",
    "sg:city":"Chadron",
    "sg:classifiers":[
        {
            "category":"Building & Trades",
            "subcategory":"Construction",
            "type":"Services"
        }
    ],
    "sg:phone":"+1 308 432 6141",
    "sg:postcode":"69337",
    "sg:province":"NE",
    "sg:tags":[
        "road",
        "contractor"
    ],
    "wof:name":"Roads Dept",
    "wof:placetype":"venue"
},
  "geometry": {"coordinates":[-103.008241,42.824952],"type":"Point"}
}