{
  "type": "Feature",
  "properties": {
    "iso:country":"US",
    "sg:address":"11465 Co Rd 40",
    "sg:city":"Bennington",
    "sg:classifiers":[
        {
            "category":"Building & Trades",
            "subcategory":"Construction",
            "type":"Services"
        }
    ],
    "sg:phone":"+1 402 238 3277",
    "sg:postcode":"68142",
    "sg:province":"NE",
    "sg:tags":[
        "tile",
        "remodeling",
        "contractor"
    ],
    "wof:name":"Christensen Contracting",
    "wof:placetype":"venue"
},
  "geometry": {"coordinates":[-96.131311,41.40763],"type":"Point"}
}