{
  "type": "Feature",
  "properties": {
    "iso:country":"US",
    "sg:address":"9301 Duane Ln",
    "sg:city":"Lincoln",
    "sg:classifiers":[
        {
            "category":"Shopping",
            "subcategory":"Beauty & Cosmetics",
            "type":"Retail Goods"
        }
    ],
    "sg:phone":"+1 402 486 3360",
    "sg:postcode":"68505",
    "sg:province":"NE",
    "sg:tags":[
        "merchandise"
    ],
    "wof:name":"Mary Kay Sales Director",
    "wof:placetype":"venue"
},
  "geometry": {"coordinates":[-96.595592,40.825736],"type":"Point"}
}