{
  "type": "Feature",
  "properties": {
    "iso:country":"US",
    "sg:address":"5801 S 58th St",
    "sg:city":"Lincoln",
    "sg:classifiers":[
        {
            "category":"Health Services",
            "subcategory":"Doctor",
            "type":"Services"
        }
    ],
    "sg:phone":"+1 402 420 0999",
    "sg:postcode":"68516",
    "sg:province":"NE",
    "sg:tags":[
        "dentist"
    ],
    "wof:name":"Frazier Family Dental Ctr",
    "wof:placetype":"venue"
},
  "geometry": {"coordinates":[-96.64203500000001,40.753031],"type":"Point"}
}