{
  "type": "Feature",
  "properties": {
    "addr:full":"305 Chestnut Dr Gretna NE 68028",
    "addr:housenumber":"305",
    "addr:postcode":"68028",
    "addr:street":"Chestnut Dr",
    "iso:country":"US",
    "sg:address":"305 Chestnut Dr",
    "sg:city":"Gretna",
    "sg:classifiers":[
        {
            "category":"Manufacturing",
            "subcategory":"Metals",
            "type":"Manufacturing & Wholesale Goods"
        }
    ],
    "sg:phone":"+1 402 332 2756",
    "sg:postcode":"68028",
    "sg:province":"NE",
    "sg:tags":[
        "steel",
        "mfg",
        "food",
        "stainless",
        "processing",
        "equipment"
    ],
    "wof:name":"Innovative Motion Systems Inc",
    "wof:placetype":"venue"
},
  "geometry": {"coordinates":[-96.237723,41.142603],"type":"Point"}
}