{
  "type": "Feature",
  "properties": {
    "addr:full":"8616 Grover St Omaha NE 68124",
    "addr:housenumber":"8616",
    "addr:postcode":"68124",
    "addr:street":"Grover St",
    "iso:country":"US",
    "sg:address":"8616 Grover St",
    "sg:city":"Omaha",
    "sg:classifiers":[
        {
            "category":"Building & Trades",
            "subcategory":"Construction",
            "type":"Services"
        }
    ],
    "sg:phone":"+1 402 393 7752",
    "sg:postcode":"68124",
    "sg:province":"NE",
    "sg:tags":[
        "house"
    ],
    "wof:name":"Larrys Building and Remodeling",
    "wof:placetype":"venue"
},
  "geometry": {"coordinates":[-96.049227,41.226455],"type":"Point"}
}