{
  "type": "Feature",
  "properties": {
    "addr:full":"7655 Burlington St Omaha NE 68127",
    "addr:housenumber":"7655",
    "addr:postcode":"68127",
    "addr:street":"Burlington St",
    "iso:country":"US",
    "sg:address":"7655 Burlington St",
    "sg:city":"Omaha",
    "sg:classifiers":[
        {
            "category":"Shopping",
            "subcategory":"Computers & Home Electronics",
            "type":"Retail Goods"
        }
    ],
    "sg:phone":"+1 402 592 2710",
    "sg:postcode":"68127",
    "sg:province":"NE",
    "sg:tags":[
        "software"
    ],
    "sg:website":"www.modernbanking.com",
    "wof:name":"Interstate Business Equipment",
    "wof:placetype":"venue"
},
  "geometry": {"coordinates":[-96.03086399999999,41.199839],"type":"Point"}
}