{
  "type": "Feature",
  "properties": {
    "iso:country":"US",
    "sg:address":"2205 Joyce Cir",
    "sg:city":"Bellevue",
    "sg:classifiers":[
        {
            "category":"Professional",
            "subcategory":"Research",
            "type":"Services"
        }
    ],
    "sg:phone":"+1 402 292 3395",
    "sg:postcode":"68005",
    "sg:province":"NE",
    "sg:tags":[
        "commercial",
        "physical"
    ],
    "wof:name":"Pro Environmental Abatemn",
    "wof:placetype":"venue"
},
  "geometry": {"coordinates":[-95.923579,41.146357],"type":"Point"}
}