{
  "type": "Feature",
  "properties": {
    "addr:full":"421 S C St Broken Bow NE 68822",
    "addr:housenumber":"421",
    "addr:postcode":"68822",
    "addr:street":"S C St",
    "iso:country":"US",
    "sg:address":"421 S C St",
    "sg:city":"Broken Bow",
    "sg:classifiers":[
        {
            "category":"Retail",
            "subcategory":"Auto Repair",
            "type":"Services"
        }
    ],
    "sg:phone":"+1 308 872 2267",
    "sg:postcode":"68822",
    "sg:province":"NE",
    "sg:tags":[
        "carburetor"
    ],
    "wof:name":"Bill's Auto Svc & Sales",
    "wof:placetype":"venue"
},
  "geometry": {"coordinates":[-99.635611,41.403615],"type":"Point"}
}