{
  "type": "Feature",
  "properties": {
    "addr:full":"300 Hamilton St Rising City NE 68658",
    "addr:housenumber":"300",
    "addr:postcode":"68658",
    "addr:street":"Hamilton St",
    "iso:country":"US",
    "sg:address":"300 Hamilton St",
    "sg:city":"Rising City",
    "sg:classifiers":[
        {
            "category":"Organizations",
            "subcategory":"Religious Organization",
            "type":"Services"
        }
    ],
    "sg:phone":"+1 402 542 2526",
    "sg:postcode":"68658",
    "sg:province":"NE",
    "sg:tags":[
        "church"
    ],
    "wof:name":"Faith Evangelical Lutheran Chr",
    "wof:placetype":"venue"
},
  "geometry": {"coordinates":[-97.29918499999999,41.192455],"type":"Point"}
}