{
  "type": "Feature",
  "properties": {
    "iso:country":"US",
    "sg:address":"488 Cody Rd",
    "sg:city":"Saint Libory",
    "sg:phone":"+1 308 687 6457",
    "sg:postcode":"68872",
    "sg:province":"NE",
    "sg:tags":[
        "farm",
        "field",
        "corn",
        "soybean",
        "crop"
    ],
    "wof:name":"Needmore Land and Cattle Co",
    "wof:placetype":"venue"
},
  "geometry": {"coordinates":[-98.344644,41.098712],"type":"Point"}
}