{
  "type": "Feature",
  "properties": {
    "iso:country":"US",
    "sg:address":"13561 Gold St",
    "sg:city":"Omaha",
    "sg:classifiers":[
        {
            "category":"Shopping",
            "subcategory":"Clothing, Apparel, & Fashions",
            "type":"Retail Goods"
        }
    ],
    "sg:phone":"+1 402 331 3878",
    "sg:postcode":"68144",
    "sg:province":"NE",
    "sg:tags":[
        "lingerie"
    ],
    "wof:name":"Warm Sensations",
    "wof:placetype":"venue"
},
  "geometry": {"coordinates":[-96.12727,41.234639],"type":"Point"}
}