{
  "type": "Feature",
  "properties": {
    "iso:country":"US",
    "sg:address":"840 Co Rd 27",
    "sg:city":"Tekamah",
    "sg:phone":"+1 402 374 1382",
    "sg:postcode":"68061",
    "sg:province":"NE",
    "sg:tags":[
        "farm",
        "corn",
        "soybean"
    ],
    "wof:name":"Dan Bowland",
    "wof:placetype":"venue"
},
  "geometry": {"coordinates":[-96.308657,41.797323],"type":"Point"}
}