{
  "type": "Feature",
  "properties": {
    "addr:full":"618 6th St Deshler NE 68340",
    "addr:housenumber":"618",
    "addr:postcode":"68340",
    "addr:street":"6Th St",
    "iso:country":"US",
    "sg:address":"618 6th St",
    "sg:city":"Deshler",
    "sg:classifiers":[
        {
            "category":"Professional",
            "subcategory":"Business Services",
            "type":"Services"
        }
    ],
    "sg:phone":"+1 402 365 4126",
    "sg:postcode":"68340",
    "sg:province":"NE",
    "sg:tags":[
        "auctioneer"
    ],
    "wof:name":"Lyle E Pitts Auctioneers Svc",
    "wof:placetype":"venue"
},
  "geometry": {"coordinates":[-97.720168,40.141757],"type":"Point"}
}