{
  "type": "Feature",
  "properties": {
    "iso:country":"US",
    "sg:address":"10220 Regency Cir",
    "sg:city":"Omaha",
    "sg:classifiers":[
        {
            "category":"Restaurant",
            "type":"Food & Drink"
        }
    ],
    "sg:menulink":"http://www.allmenus.com/ne/omaha/10960-the-chop-house/menu/",
    "sg:phone":"+1 402 516 3600",
    "sg:postcode":"68114",
    "sg:province":"NE",
    "sg:tags":[
        "american",
        "steakhouse"
    ],
    "wof:name":"The Chop House",
    "wof:placetype":"venue"
},
  "geometry": {"coordinates":[-96.073283,41.261169],"type":"Point"}
}