{
  "type": "Feature",
  "properties": {
    "iso:country":"US",
    "sg:address":"520 E Tipperary St",
    "sg:city":"Oneill",
    "sg:classifiers":[
        {
            "category":"Shopping",
            "subcategory":"Gifts & Souvenirs",
            "type":"Retail Goods"
        }
    ],
    "sg:phone":"+1 402 336 2869",
    "sg:postcode":"68763",
    "sg:province":"NE",
    "wof:name":"Seevers Gifts Marlene",
    "wof:placetype":"venue"
},
  "geometry": {"coordinates":[-98.643389,42.467067],"type":"Point"}
}