{
  "type": "Feature",
  "properties": {
    "iso:country":"US",
    "sg:address":"2424 Pratt St",
    "sg:city":"Omaha",
    "sg:classifiers":[
        {
            "category":"Social Services",
            "type":"Services"
        }
    ],
    "sg:phone":"+1 402 933 2062",
    "sg:postcode":"68111",
    "sg:province":"NE",
    "sg:tags":[
        "organization",
        "welfare"
    ],
    "wof:name":"Relief Association",
    "wof:placetype":"venue"
},
  "geometry": {"coordinates":[-95.948965,41.292459],"type":"Point"}
}