{
  "type": "Feature",
  "properties": {
    "addr:full":"1535 E 1st St Fremont NE 68025",
    "addr:housenumber":"1535",
    "addr:postcode":"68025",
    "addr:street":"E 1St St",
    "iso:country":"US",
    "sg:address":"1535 E 1st St",
    "sg:city":"Fremont",
    "sg:classifiers":[
        {
            "category":"Organizations",
            "subcategory":"Professional Association",
            "type":"Services"
        }
    ],
    "sg:phone":"+1 402 721 5328",
    "sg:postcode":"68025",
    "sg:province":"NE",
    "sg:tags":[
        "membership"
    ],
    "wof:name":"Fremont Area Rtred Tacher Assn",
    "wof:placetype":"venue"
},
  "geometry": {"coordinates":[-96.478441,41.429528],"type":"Point"}
}