{
  "type": "Feature",
  "properties": {
    "addr:full":"1005 W 14 Rd Aurora NE 68818",
    "addr:housenumber":"1005",
    "addr:postcode":"68818",
    "addr:street":"W 14 Rd",
    "iso:country":"US",
    "sg:address":"1005 W 14 Rd",
    "sg:city":"Aurora",
    "sg:classifiers":[
        {
            "category":"Farming",
            "subcategory":"Farm",
            "type":"Manufacturing & Wholesale Goods"
        }
    ],
    "sg:phone":"+1 402 694 3949",
    "sg:postcode":"68818",
    "sg:province":"NE",
    "sg:tags":[
        "crop",
        "general"
    ],
    "wof:name":"Greg Luthy Farms Inc",
    "wof:placetype":"venue"
},
  "geometry": {"coordinates":[-98.111695,40.886853],"type":"Point"}
}