{
  "type": "Feature",
  "properties": {
    "addr:full":"18940 S 68th St Hickman NE 68372",
    "addr:housenumber":"18940",
    "addr:postcode":"68372",
    "addr:street":"S 68Th St",
    "iso:country":"US",
    "sg:address":"18940 S 68th St",
    "sg:city":"Hickman",
    "sg:classifiers":[
        {
            "category":"Restaurant",
            "type":"Food & Drink"
        }
    ],
    "sg:phone":"+1 402 792 2400",
    "sg:postcode":"68372",
    "sg:province":"NE",
    "wof:name":"K C's Carry Out Pizza",
    "wof:placetype":"venue"
},
  "geometry": {"coordinates":[-96.62927000000001,40.626526],"type":"Point"}
}