{
  "type": "Feature",
  "properties": {
    "iso:country":"US",
    "sg:address":"101 W 31st St",
    "sg:city":"Kearney",
    "sg:classifiers":[
        {
            "category":"Social Services",
            "type":"Services"
        }
    ],
    "sg:phone":"+1 308 236 5353",
    "sg:postcode":"68847",
    "sg:province":"NE",
    "sg:tags":[
        "organization",
        "welfare"
    ],
    "sg:website":"www.redcross.org",
    "wof:name":"American Red Cross",
    "wof:placetype":"venue"
},
  "geometry": {"coordinates":[-99.08341799999999,40.706465],"type":"Point"}
}