{
  "type": "Feature",
  "properties": {
    "iso:country":"US",
    "sg:address":"15405 S 2nd St",
    "sg:city":"Bennington",
    "sg:classifiers":[
        {
            "category":"Social Services",
            "subcategory":"Child Care",
            "type":"Services"
        }
    ],
    "sg:phone":"+1 402 238 3336",
    "sg:postcode":"68007",
    "sg:province":"NE",
    "wof:name":"Koala T Day Care",
    "wof:placetype":"venue"
},
  "geometry": {"coordinates":[-96.156971,41.363176],"type":"Point"}
}