{
  "type": "Feature",
  "properties": {
    "iso:country":"US",
    "sg:address":"16584 Hascall St",
    "sg:city":"Omaha",
    "sg:classifiers":[
        {
            "category":"Professional",
            "subcategory":"Art Services",
            "type":"Services"
        }
    ],
    "sg:phone":"+1 402 758 9120",
    "sg:postcode":"68130",
    "sg:province":"NE",
    "sg:tags":[
        "commercial"
    ],
    "wof:name":"Kapow Design",
    "wof:placetype":"venue"
},
  "geometry": {"coordinates":[-96.171898,41.227737],"type":"Point"}
}