{
  "type": "Feature",
  "properties": {
    "addr:full":"2921 S 168th St Omaha NE 68130",
    "addr:housenumber":"2921",
    "addr:postcode":"68130",
    "addr:street":"S 168Th St",
    "iso:country":"US",
    "sg:address":"2921 S 168th St",
    "sg:city":"Omaha",
    "sg:classifiers":[
        {
            "category":"Banks & Credit Unions",
            "subcategory":"Bank",
            "type":"Services"
        }
    ],
    "sg:phone":"+1 402 330 9388",
    "sg:postcode":"68130",
    "sg:province":"NE",
    "sg:tags":[
        "loan",
        "real estate"
    ],
    "wof:name":"Marine Bank Fsb",
    "wof:placetype":"venue"
},
  "geometry": {"coordinates":[-96.17682600000001,41.23208],"type":"Point"}
}