{
  "type": "Feature",
  "properties": {
    "iso:country":"US",
    "sg:address":"1101 Arapahoe St",
    "sg:city":"Lincoln",
    "sg:classifiers":[
        {
            "category":"Personal",
            "subcategory":"Barber",
            "type":"Services"
        }
    ],
    "sg:phone":"+1 402 423 7011",
    "sg:postcode":"68502",
    "sg:province":"NE",
    "sg:tags":[
        "shop"
    ],
    "wof:name":"Barbers On Arapahoe Street",
    "wof:placetype":"venue"
},
  "geometry": {"coordinates":[-96.70513099999999,40.77914],"type":"Point"}
}