{
  "type": "Feature",
  "properties": {
    "iso:country":"US",
    "sg:address":"15757 C W Hadan Dr",
    "sg:city":"Bennington",
    "sg:classifiers":[
        {
            "category":"Restaurant",
            "type":"Food & Drink"
        }
    ],
    "sg:phone":"+1 402 238 3323",
    "sg:postcode":"68007",
    "sg:province":"NE",
    "wof:name":"Goodrich Deli",
    "wof:placetype":"venue"
},
  "geometry": {"coordinates":[-96.160858,41.372197],"type":"Point"}
}