{
  "type": "Feature",
  "properties": {
    "iso:country":"US",
    "sg:address":"1425 W 11th St",
    "sg:city":"Crete",
    "sg:classifiers":[
        {
            "category":"Retail",
            "subcategory":"Car Wash",
            "type":"Services"
        }
    ],
    "sg:phone":"+1 402 826 2728",
    "sg:postcode":"68333",
    "sg:province":"NE",
    "sg:tags":[
        "truck",
        "cleaning"
    ],
    "wof:name":"Willi's Washout & Truck Lube",
    "wof:placetype":"venue"
},
  "geometry": {"coordinates":[-96.97935099999999,40.622724],"type":"Point"}
}