{
  "type": "Feature",
  "properties": {
    "iso:country":"US",
    "sg:address":"2017 Lincoln Ave",
    "sg:city":"Cozad",
    "sg:classifiers":[
        {
            "category":"Health Services",
            "subcategory":"Optometrist",
            "type":"Services"
        }
    ],
    "sg:phone":"+1 308 784 3237",
    "sg:postcode":"69130",
    "sg:province":"NE",
    "wof:name":"James E Acker OD",
    "wof:placetype":"venue"
},
  "geometry": {"coordinates":[-99.981098,40.871384],"type":"Point"}
}