{
  "type": "Feature",
  "properties": {
    "iso:country":"US",
    "sg:address":"27015 Bluff Rd",
    "sg:city":"Murdock",
    "sg:phone":"+1 402 867 3491",
    "sg:postcode":"68407",
    "sg:province":"NE",
    "sg:tags":[
        "wheat",
        "farm",
        "corn",
        "cash",
        "crop",
        "field",
        "grain"
    ],
    "wof:name":"William A Zoz",
    "wof:placetype":"venue"
},
  "geometry": {"coordinates":[-96.331901,40.914314],"type":"Point"}
}