{
  "type": "Feature",
  "properties": {
    "addr:full":"743 E 6th St Hastings NE 68901",
    "addr:housenumber":"743",
    "addr:postcode":"68901",
    "addr:street":"E 6Th St",
    "iso:country":"US",
    "sg:address":"743 E 6th St",
    "sg:city":"Hastings",
    "sg:classifiers":[
        {
            "category":"Building & Trades",
            "subcategory":"Construction",
            "type":"Services"
        }
    ],
    "sg:phone":"+1 402 831 6285",
    "sg:postcode":"68901",
    "sg:province":"NE",
    "sg:tags":[
        "repairing",
        "remodeling",
        "contractor"
    ],
    "wof:name":"T Maul Handcrafted Cabinetry",
    "wof:placetype":"venue"
},
  "geometry": {"coordinates":[-98.373114,40.588732],"type":"Point"}
}