{
  "type": "Feature",
  "properties": {
    "addr:full":"6001 Cornhusker Hwy Lincoln NE 68507",
    "addr:housenumber":"6001",
    "addr:postcode":"68507",
    "addr:street":"Cornhusker Hwy",
    "iso:country":"US",
    "sg:address":"6001 Cornhusker Hwy",
    "sg:city":"Lincoln",
    "sg:classifiers":[
        {
            "category":"Restaurant",
            "type":"Food & Drink"
        }
    ],
    "sg:menulink":"http://www.allmenus.com/ne/lincoln/115879-quiznos-sub/menu/",
    "sg:phone":"+1 402 464 0110",
    "sg:postcode":"68507",
    "sg:province":"NE",
    "sg:tags":[
        "wrap",
        "american",
        "sandwich"
    ],
    "wof:name":"Quiznos Sub",
    "wof:placetype":"venue"
},
  "geometry": {"coordinates":[-96.63782500000001,40.862915],"type":"Point"}
}