{
  "type": "Feature",
  "properties": {
    "iso:country":"US",
    "sg:address":"1650 Rd East 250",
    "sg:city":"Paxton",
    "sg:classifiers":[
        {
            "category":"Farming",
            "subcategory":"Livestock Farm",
            "type":"Manufacturing & Wholesale Goods"
        }
    ],
    "sg:phone":"+1 308 726 3166",
    "sg:postcode":"69155",
    "sg:province":"NE",
    "sg:tags":[
        "ranch"
    ],
    "wof:name":"Barnt Ranch",
    "wof:placetype":"venue"
},
  "geometry": {"coordinates":[-101.431271,41.347581],"type":"Point"}
}