{
  "type": "Feature",
  "properties": {
    "iso:country":"US",
    "sg:address":"4450 Rd 89",
    "sg:city":"Potter",
    "sg:classifiers":[
        {
            "category":"Organizations",
            "subcategory":"Religious Organization",
            "type":"Services"
        }
    ],
    "sg:phone":"+1 308 879 4532",
    "sg:postcode":"69156",
    "sg:province":"NE",
    "sg:tags":[
        "church"
    ],
    "wof:name":"Saint Pauls Lutheran Church",
    "wof:placetype":"venue"
},
  "geometry": {"coordinates":[-103.203468,41.311765],"type":"Point"}
}