{
  "type": "Feature",
  "properties": {
    "addr:full":"202 S 10th St Oneill NE 68763",
    "addr:housenumber":"202",
    "addr:postcode":"68763",
    "addr:street":"S 10Th St",
    "iso:country":"US",
    "sg:address":"202 S 10th St",
    "sg:city":"Oneill",
    "sg:classifiers":[
        {
            "category":"Social Services",
            "subcategory":"Child Care",
            "type":"Services"
        }
    ],
    "sg:phone":"+1 402 336 4309",
    "sg:postcode":"68763",
    "sg:province":"NE",
    "sg:tags":[
        "kindergarten",
        "academic",
        "school"
    ],
    "wof:name":"Head Start",
    "wof:placetype":"venue"
},
  "geometry": {"coordinates":[-98.63798300000001,42.456459],"type":"Point"}
}