{
  "type": "Feature",
  "properties": {
    "iso:country":"US",
    "sg:address":"1820 N 6th St",
    "sg:city":"Beatrice",
    "sg:classifiers":[
        {
            "category":"Travel",
            "subcategory":"Hotels & Motels",
            "type":"Entertainment"
        }
    ],
    "sg:phone":"+1 402 223 4036",
    "sg:postcode":"68310",
    "sg:province":"NE",
    "sg:tags":[
        "operation"
    ],
    "wof:name":"Holiday Villa",
    "wof:placetype":"venue"
},
  "geometry": {"coordinates":[-96.746616,40.282991],"type":"Point"}
}