{
  "type": "Feature",
  "properties": {
    "addr:full":"10715 Mockingbird Dr Omaha NE 68127",
    "addr:housenumber":"10715",
    "addr:postcode":"68127",
    "addr:street":"Mockingbird Dr",
    "iso:country":"US",
    "sg:address":"10715 Mockingbird Dr",
    "sg:city":"Omaha",
    "sg:classifiers":[
        {
            "category":"Wholesale",
            "subcategory":"Electrical",
            "type":"Manufacturing & Wholesale Goods"
        }
    ],
    "sg:phone":"+1 402 339 0655",
    "sg:postcode":"68127",
    "sg:province":"NE",
    "sg:tags":[
        "control",
        "security",
        "system"
    ],
    "wof:name":"Webco Security",
    "wof:placetype":"venue"
},
  "geometry": {"coordinates":[-96.08110000000001,41.207514],"type":"Point"}
}