{
  "type": "Feature",
  "properties": {
    "iso:country":"US",
    "sg:address":"1890 Hat Creek Rd",
    "sg:city":"Harrison",
    "sg:classifiers":[
        {
            "category":"Farming",
            "subcategory":"Livestock Farm",
            "type":"Manufacturing & Wholesale Goods"
        }
    ],
    "sg:phone":"+1 308 453 2615",
    "sg:postcode":"69346",
    "sg:province":"NE",
    "sg:tags":[
        "beef",
        "feedlot",
        "cattle"
    ],
    "wof:name":"Ray Semroska Ranch",
    "wof:placetype":"venue"
},
  "geometry": {"coordinates":[-103.729129,42.908458],"type":"Point"}
}