{
  "type": "Feature",
  "properties": {
    "addr:full":"4426 Florence Blvd Omaha NE 68110",
    "addr:housenumber":"4426",
    "addr:postcode":"68110",
    "addr:street":"Florence Blvd",
    "iso:country":"US",
    "sg:address":"4426 Florence Blvd",
    "sg:city":"Omaha",
    "sg:classifiers":[
        {
            "category":"Shopping",
            "subcategory":"Clothing, Apparel, & Fashions",
            "type":"Retail Goods"
        }
    ],
    "sg:phone":"+1 402 453 8608",
    "sg:postcode":"68110",
    "sg:province":"NE",
    "sg:tags":[
        "furnishing"
    ],
    "wof:name":"White's Hip Hop Shop",
    "wof:placetype":"venue"
},
  "geometry": {"coordinates":[-95.942229,41.297934],"type":"Point"}
}