{
  "type": "Feature",
  "properties": {
    "addr:full":"6111 Old Cheney Rd Lincoln NE 68516",
    "addr:housenumber":"6111",
    "addr:postcode":"68516",
    "addr:street":"Old Cheney Rd",
    "iso:country":"US",
    "sg:address":"6111 Old Cheney Rd",
    "sg:city":"Lincoln",
    "sg:classifiers":[
        {
            "category":"Freight",
            "type":"Transportation"
        }
    ],
    "sg:phone":"+1 402 421 2600",
    "sg:postcode":"68516",
    "sg:province":"NE",
    "sg:tags":[
        "local",
        "trucking"
    ],
    "wof:name":"Rlw Trucking Inc",
    "wof:placetype":"venue"
},
  "geometry": {"coordinates":[-96.636348,40.755169],"type":"Point"}
}