{
  "type": "Feature",
  "properties": {
    "iso:country":"US",
    "sg:address":"3384 Prairie Ln",
    "sg:city":"Columbus",
    "sg:classifiers":[
        {
            "category":"Personal",
            "subcategory":"Beauty Salon",
            "type":"Services"
        }
    ],
    "sg:phone":"+1 402 564 2790",
    "sg:postcode":"68601",
    "sg:province":"NE",
    "sg:tags":[
        "shop"
    ],
    "wof:name":"Personalized Electrolysis",
    "wof:placetype":"venue"
},
  "geometry": {"coordinates":[-97.371838,41.446611],"type":"Point"}
}