{
  "type": "Feature",
  "properties": {
    "addr:full":"219 E 1st St Papillion NE 68046",
    "addr:housenumber":"219",
    "addr:postcode":"68046",
    "addr:street":"E 1St St",
    "iso:country":"US",
    "sg:address":"219 E 1st St",
    "sg:city":"Papillion",
    "sg:classifiers":[
        {
            "category":"Retail",
            "subcategory":"Auto Repair",
            "type":"Services"
        }
    ],
    "sg:phone":"+1 402 339 6460",
    "sg:postcode":"68046",
    "sg:province":"NE",
    "sg:tags":[
        "repairing",
        "automobile",
        "general"
    ],
    "wof:name":"Papillion Foreign Motors Inc",
    "wof:placetype":"venue"
},
  "geometry": {"coordinates":[-96.042412,41.156332],"type":"Point"}
}