{
  "type": "Feature",
  "properties": {
    "addr:full":"317 Fraisier St Beemer NE 68716",
    "addr:housenumber":"317",
    "addr:postcode":"68716",
    "addr:street":"Fraisier St",
    "iso:country":"US",
    "sg:address":"317 Fraisier St",
    "sg:city":"Beemer",
    "sg:classifiers":[
        {
            "category":"Professional",
            "type":"Services"
        }
    ],
    "sg:phone":"+1 402 528 7272",
    "sg:postcode":"68716",
    "sg:province":"NE",
    "wof:name":"Arcadian Marksmanship Club",
    "wof:placetype":"venue"
},
  "geometry": {"coordinates":[-96.809122,41.930999],"type":"Point"}
}