{
  "type": "Feature",
  "properties": {
    "iso:country":"US",
    "sg:address":"514 2nd St",
    "sg:city":"Friend",
    "sg:classifiers":[
        {
            "category":"Insurance",
            "subcategory":"Insurance Agent",
            "type":"Services"
        }
    ],
    "sg:phone":"+1 402 947 4811",
    "sg:postcode":"68359",
    "sg:province":"NE",
    "wof:name":"State Farm Insurance",
    "wof:placetype":"venue"
},
  "geometry": {"coordinates":[-97.286502,40.653788],"type":"Point"}
}