{
  "type": "Feature",
  "properties": {
    "iso:country":"US",
    "sg:address":"4360 Nicholas St",
    "sg:city":"Omaha",
    "sg:classifiers":[
        {
            "category":"Building & Trades",
            "subcategory":"Construction",
            "type":"Services"
        }
    ],
    "sg:phone":"+1 402 553 1804",
    "sg:postcode":"68131",
    "sg:province":"NE",
    "sg:tags":[
        "contractor"
    ],
    "wof:name":"Boyd Jones Construction Co",
    "wof:placetype":"venue"
},
  "geometry": {"coordinates":[-95.978104,41.2701],"type":"Point"}
}