{
  "type": "Feature",
  "properties": {
    "iso:country":"US",
    "sg:address":"8815 Maple St",
    "sg:city":"Omaha",
    "sg:classifiers":[
        {
            "category":"Retail",
            "subcategory":"Auto Repair",
            "type":"Services"
        }
    ],
    "sg:phone":"+1 402 390 2570",
    "sg:postcode":"68134",
    "sg:province":"NE",
    "sg:tags":[
        "repairing",
        "automobile"
    ],
    "wof:name":"E M Transmission & Repair",
    "wof:placetype":"venue"
},
  "geometry": {"coordinates":[-96.05134200000001,41.284991],"type":"Point"}
}