{
  "type": "Feature",
  "properties": {
    "addr:full":"204 N 4th St Oneill NE 68763",
    "addr:housenumber":"204",
    "addr:postcode":"68763",
    "addr:street":"N 4Th St",
    "iso:country":"US",
    "sg:address":"204 N 4th St",
    "sg:city":"Oneill",
    "sg:classifiers":[
        {
            "category":"Government",
            "subcategory":"Court House",
            "type":"Public Place"
        }
    ],
    "sg:phone":"+1 402 336 1662",
    "sg:postcode":"68763",
    "sg:province":"NE",
    "sg:tags":[
        "county"
    ],
    "wof:name":"Holt County Judge",
    "wof:placetype":"venue"
},
  "geometry": {"coordinates":[-98.647828,42.460015],"type":"Point"}
}