{
  "type": "Feature",
  "properties": {
    "iso:country":"US",
    "sg:address":"1210 5th Ave",
    "sg:city":"South Sioux City",
    "sg:classifiers":[
        {
            "category":"Retail",
            "subcategory":"Self-service Laundry",
            "type":"Services"
        }
    ],
    "sg:phone":"+1 402 494 9798",
    "sg:postcode":"68776",
    "sg:province":"NE",
    "sg:tags":[
        "coin"
    ],
    "wof:name":"Parkview Laundromat",
    "wof:placetype":"venue"
},
  "geometry": {"coordinates":[-96.41887199999999,42.477411],"type":"Point"}
}