{
  "type": "Feature",
  "properties": {
    "iso:country":"US",
    "sg:address":"104 S 6th St",
    "sg:city":"Newman Grove",
    "sg:classifiers":[
        {
            "category":"Retail",
            "subcategory":"Auto Repair",
            "type":"Services"
        }
    ],
    "sg:phone":"+1 402 447 2400",
    "sg:postcode":"68758",
    "sg:province":"NE",
    "sg:tags":[
        "body",
        "automobile",
        "painting"
    ],
    "wof:name":"Schumaker Body Shop",
    "wof:placetype":"venue"
},
  "geometry": {"coordinates":[-97.776662,41.7466],"type":"Point"}
}