{
  "type": "Feature",
  "properties": {
    "iso:country":"US",
    "sg:address":"7204 S 141st St",
    "sg:city":"Omaha",
    "sg:classifiers":[
        {
            "category":"Professional",
            "subcategory":"Research",
            "type":"Services"
        }
    ],
    "sg:phone":"+1 402 894 5445",
    "sg:postcode":"68138",
    "sg:province":"NE",
    "sg:tags":[
        "market",
        "analysis"
    ],
    "wof:name":"SK&a Information Services Inc",
    "wof:placetype":"venue"
},
  "geometry": {"coordinates":[-96.13551200000001,41.188017],"type":"Point"}
}