{
  "type": "Feature",
  "properties": {
    "iso:country":"US",
    "sg:address":"307 W 1st St",
    "sg:city":"Oshkosh",
    "sg:classifiers":[
        {
            "category":"Education",
            "subcategory":"Library",
            "type":"Public Place"
        }
    ],
    "sg:phone":"+1 308 772 4554",
    "sg:postcode":"69154",
    "sg:province":"NE",
    "wof:name":"Oshkosh City Library",
    "wof:placetype":"venue"
},
  "geometry": {"coordinates":[-102.345614,41.405816],"type":"Point"}
}