{
  "type": "Feature",
  "properties": {
    "addr:full":"7224 Maple St Omaha NE 68134",
    "addr:housenumber":"7224",
    "addr:postcode":"68134",
    "addr:street":"Maple St",
    "iso:country":"US",
    "sg:address":"7224 Maple St",
    "sg:city":"Omaha",
    "sg:classifiers":[
        {
            "category":"Food & Beverages",
            "subcategory":"Groceries & Convenience Stores",
            "type":"Retail Goods"
        }
    ],
    "sg:phone":"+1 402 934 3004",
    "sg:postcode":"68134",
    "sg:province":"NE",
    "wof:name":"Al-Tayyibat Intl Gr Str",
    "wof:placetype":"venue"
},
  "geometry": {"coordinates":[-96.02402600000001,41.28514],"type":"Point"}
}