{
  "type": "Feature",
  "properties": {
    "iso:country":"US",
    "sg:address":"1314 Pamela Ave",
    "sg:city":"Holdrege",
    "sg:classifiers":[
        {
            "category":"Building & Trades",
            "subcategory":"Construction",
            "type":"Services"
        }
    ],
    "sg:phone":"+1 308 995 5517",
    "sg:postcode":"68949",
    "sg:province":"NE",
    "sg:tags":[
        "carpentry",
        "contractor"
    ],
    "wof:name":"Wolfes Enterprises",
    "wof:placetype":"venue"
},
  "geometry": {"coordinates":[-99.362476,40.447351],"type":"Point"}
}