{
  "type": "Feature",
  "properties": {
    "iso:country":"US",
    "sg:address":"5700 Culwells Rd",
    "sg:city":"Lincoln",
    "sg:classifiers":[
        {
            "category":"Shopping",
            "subcategory":"Computers & Home Electronics",
            "type":"Retail Goods"
        }
    ],
    "sg:phone":"+1 402 489 9911",
    "sg:postcode":"68516",
    "sg:province":"NE",
    "sg:tags":[
        "radio",
        "television",
        "electronic",
        "store"
    ],
    "wof:name":"Racom",
    "wof:placetype":"venue"
},
  "geometry": {"coordinates":[-96.62063999999999,40.753599],"type":"Point"}
}