{
  "type": "Feature",
  "properties": {
    "iso:country":"US",
    "sg:address":"3869 Webster St",
    "sg:city":"Omaha",
    "sg:classifiers":[
        {
            "category":"Education",
            "subcategory":"School",
            "type":"Public Place"
        }
    ],
    "sg:phone":"+1 402 556 6655",
    "sg:postcode":"68131",
    "sg:province":"NE",
    "sg:tags":[
        "high",
        "middle",
        "elementary"
    ],
    "wof:name":"St Cecilia Cathedral Grade School",
    "wof:placetype":"venue"
},
  "geometry": {"coordinates":[-95.97035,41.265713],"type":"Point"}
}