{
  "type": "Feature",
  "properties": {
    "addr:full":"10780 V St Omaha NE 68127",
    "addr:housenumber":"10780",
    "addr:postcode":"68127",
    "addr:street":"V St",
    "iso:country":"US",
    "sg:address":"10780 V St",
    "sg:city":"Omaha",
    "sg:classifiers":[
        {
            "category":"Health Services",
            "subcategory":"Health Practitioner",
            "type":"Services"
        }
    ],
    "sg:phone":"+1 402 592 5626",
    "sg:postcode":"68127",
    "sg:province":"NE",
    "sg:tags":[
        "psychologist"
    ],
    "wof:name":"Oak Heights Counseling",
    "wof:placetype":"venue"
},
  "geometry": {"coordinates":[-96.079615,41.203311],"type":"Point"}
}