{
  "type": "Feature",
  "properties": {
    "addr:full":"1510 E 4th St North Platte NE 69101",
    "addr:housenumber":"1510",
    "addr:postcode":"69101",
    "addr:street":"E 4Th St",
    "iso:country":"US",
    "sg:address":"1510 E 4th St",
    "sg:city":"North Platte",
    "sg:classifiers":[
        {
            "category":"Freight",
            "type":"Transportation"
        }
    ],
    "sg:phone":"+1 308 650 0864",
    "sg:postcode":"69101",
    "sg:province":"NE",
    "sg:tags":[
        "operator",
        "distance",
        "local",
        "long",
        "trucking"
    ],
    "wof:name":"Flat Rock Trucking LLC",
    "wof:placetype":"venue"
},
  "geometry": {"coordinates":[-100.745943,41.134165],"type":"Point"}
}