{
  "type": "Feature",
  "properties": {
    "addr:full":"210832 Co Rd D Scottsbluff NE 69361",
    "addr:postcode":"210832;69361",
    "addr:street":"Co Rd D",
    "iso:country":"US",
    "sg:address":"210832 Co Rd D",
    "sg:city":"Scottsbluff",
    "sg:classifiers":[
        {
            "category":"Professional",
            "subcategory":"Management & Consulting",
            "type":"Services"
        }
    ],
    "sg:phone":"+1 308 632 6338",
    "sg:postcode":"69361",
    "sg:province":"NE",
    "sg:tags":[
        "retail",
        "direct",
        "sales"
    ],
    "wof:name":"Mary Kay Cosmetics",
    "wof:placetype":"venue"
},
  "geometry": {"coordinates":[-103.662206,41.958007],"type":"Point"}
}