{
  "type": "Feature",
  "properties": {
    "iso:country":"US",
    "sg:address":"14911 A Cir",
    "sg:city":"Omaha",
    "sg:classifiers":[
        {
            "category":"Manufacturing",
            "subcategory":"Chemicals & Compounds",
            "type":"Manufacturing & Wholesale Goods"
        }
    ],
    "sg:phone":"+1 402 554 9876",
    "sg:postcode":"68144",
    "sg:province":"NE",
    "sg:tags":[
        "product",
        "mfg",
        "cleaning",
        "carpet"
    ],
    "wof:name":"Whitney Plastic",
    "wof:placetype":"venue"
},
  "geometry": {"coordinates":[-96.150082,41.227638],"type":"Point"}
}