{
  "type": "Feature",
  "properties": {
    "iso:country":"US",
    "sg:address":"808 Russell Cir",
    "sg:city":"Firth",
    "sg:classifiers":[
        {
            "category":"Building & Trades",
            "subcategory":"Cleaning & Sanitation",
            "type":"Services"
        }
    ],
    "sg:phone":"+1 402 791 0132",
    "sg:postcode":"68358",
    "sg:province":"NE",
    "sg:tags":[
        "janitor"
    ],
    "wof:name":"Prefection Cleaning",
    "wof:placetype":"venue"
},
  "geometry": {"coordinates":[-96.60332,40.538825],"type":"Point"}
}