{
  "type": "Feature",
  "properties": {
    "iso:country":"US",
    "sg:address":"53919 US Hwy 275",
    "sg:city":"Meadow Grove",
    "sg:classifiers":[
        {
            "category":"Real Estate",
            "subcategory":"Real Estate Operator",
            "type":"Services"
        }
    ],
    "sg:phone":"+1 402 634 2483",
    "sg:postcode":"68752",
    "sg:province":"NE",
    "sg:tags":[
        "property",
        "lessor"
    ],
    "wof:name":"Wayne Tegeler",
    "wof:placetype":"venue"
},
  "geometry": {"coordinates":[-97.728403,42.032324],"type":"Point"}
}