{
  "type": "Feature",
  "properties": {
    "iso:country":"US",
    "sg:address":"6409 N Quandt Rd",
    "sg:city":"Grand Island",
    "sg:classifiers":[
        {
            "category":"Shopping",
            "subcategory":"Gifts & Souvenirs",
            "type":"Retail Goods"
        }
    ],
    "sg:phone":"+1 308 384 6913",
    "sg:postcode":"68801",
    "sg:province":"NE",
    "sg:tags":[
        "shop"
    ],
    "wof:name":"The Prairie House",
    "wof:placetype":"venue"
},
  "geometry": {"coordinates":[-98.30182499999999,41.008283],"type":"Point"}
}