{
  "type": "Feature",
  "properties": {
    "iso:country":"US",
    "sg:address":"2491 US Hwy 385",
    "sg:city":"Alliance",
    "sg:classifiers":[
        {
            "category":"Building & Trades",
            "subcategory":"Landscaping Services",
            "type":"Services"
        }
    ],
    "sg:phone":"+1 308 762 3860",
    "sg:postcode":"69301",
    "sg:province":"NE",
    "sg:tags":[
        "lawn",
        "maintenance",
        "grounds"
    ],
    "wof:name":"J & C Lawn Svc & Rv Park",
    "wof:placetype":"venue"
},
  "geometry": {"coordinates":[-102.89830600000001,42.092013],"type":"Point"}
}