{
  "type": "Feature",
  "properties": {
    "iso:country":"US",
    "sg:address":"1818 Broadway",
    "sg:city":"Scottsbluff",
    "sg:classifiers":[
        {
            "category":"Shopping",
            "subcategory":"Clothing, Apparel, & Fashions",
            "type":"Retail Goods"
        }
    ],
    "sg:phone":"+1 308 632 3621",
    "sg:postcode":"69361",
    "sg:province":"NE",
    "sg:tags":[
        "shop",
        "bridal"
    ],
    "wof:name":"Boutique Bridal",
    "wof:placetype":"venue"
},
  "geometry": {"coordinates":[-103.662829,41.865057],"type":"Point"}
}