{
  "type": "Feature",
  "properties": {
    "iso:country":"US",
    "sg:address":"2400 W Mill Rd",
    "sg:city":"Raymond",
    "sg:classifiers":[
        {
            "category":"Building & Trades",
            "subcategory":"Construction",
            "type":"Services"
        }
    ],
    "sg:phone":"+1 402 783 3432",
    "sg:postcode":"68428",
    "sg:province":"NE",
    "sg:tags":[
        "contractor"
    ],
    "wof:name":"Buresh Contractors Inc",
    "wof:placetype":"venue"
},
  "geometry": {"coordinates":[-96.746663,40.944476],"type":"Point"}
}