{
  "type": "Feature",
  "properties": {
    "addr:full":"1105 S Broad St Fremont NE 68025",
    "addr:housenumber":"1105",
    "addr:postcode":"68025",
    "addr:street":"S Broad St",
    "iso:country":"US",
    "sg:address":"1105 S Broad St",
    "sg:city":"Fremont",
    "sg:classifiers":[
        {
            "category":"Food & Beverages",
            "subcategory":"Groceries & Convenience Stores",
            "type":"Retail Goods"
        }
    ],
    "sg:phone":"+1 402 721 9815",
    "sg:postcode":"68025",
    "sg:province":"NE",
    "sg:tags":[
        "station",
        "gasoline"
    ],
    "wof:name":"Texaco",
    "wof:placetype":"venue"
},
  "geometry": {"coordinates":[-96.500287,41.417416],"type":"Point"}
}