{
  "type": "Feature",
  "properties": {
    "iso:country":"US",
    "sg:address":"600 Hoyt St",
    "sg:city":"Peru",
    "sg:classifiers":[
        {
            "category":"Organizations",
            "subcategory":"Religious Organization",
            "type":"Services"
        }
    ],
    "sg:phone":"+1 402 872 7515",
    "sg:postcode":"68421",
    "sg:province":"NE",
    "wof:name":"United Ministry In Higher",
    "wof:placetype":"venue"
},
  "geometry": {"coordinates":[-95.73191199999999,40.475679],"type":"Point"}
}