{
  "type": "Feature",
  "properties": {
    "iso:country":"US",
    "sg:address":"87294 State Hwy 57",
    "sg:city":"Laurel",
    "sg:phone":"+1 402 256 9333",
    "sg:postcode":"68745",
    "sg:province":"NE",
    "sg:tags":[
        "farm",
        "corn",
        "soybean"
    ],
    "wof:name":"Bloom Farms",
    "wof:placetype":"venue"
},
  "geometry": {"coordinates":[-97.094341,42.481408],"type":"Point"}
}