{
  "type": "Feature",
  "properties": {
    "iso:country":"US",
    "sg:address":"724 W 2nd St",
    "sg:city":"Grand Island",
    "sg:classifiers":[
        {
            "category":"Shopping",
            "subcategory":"Florist",
            "type":"Retail Goods"
        }
    ],
    "sg:phone":"+1 308 381 8940",
    "sg:postcode":"68801",
    "sg:province":"NE",
    "wof:name":"D J Shop",
    "wof:placetype":"venue"
},
  "geometry": {"coordinates":[-98.34618399999999,40.922214],"type":"Point"}
}