{
  "type": "Feature",
  "properties": {
    "iso:country":"US",
    "sg:address":"224 N Main St",
    "sg:city":"Litchfield",
    "sg:classifiers":[
        {
            "category":"Banks & Credit Unions",
            "subcategory":"Bank",
            "type":"Services"
        }
    ],
    "sg:phone":"+1 308 446 2522",
    "sg:postcode":"68852",
    "sg:province":"NE",
    "wof:name":"Town & Country Bank",
    "wof:placetype":"venue"
},
  "geometry": {"coordinates":[-99.155839,41.157253],"type":"Point"}
}