{
  "type": "Feature",
  "properties": {
    "iso:country":"US",
    "sg:address":"302 West Ave",
    "sg:city":"Holdrege",
    "sg:classifiers":[
        {
            "category":"Professional",
            "subcategory":"Management & Consulting",
            "type":"Services"
        }
    ],
    "sg:phone":"+1 308 995 8652",
    "sg:postcode":"68949",
    "sg:province":"NE",
    "sg:tags":[
        "pa",
        "local"
    ],
    "wof:name":"Bethphage Mission of Holdrege",
    "wof:placetype":"venue"
},
  "geometry": {"coordinates":[-99.371251,40.437923],"type":"Point"}
}