{
  "type": "Feature",
  "properties": {
    "iso:country":"US",
    "sg:address":"16318 Elm St",
    "sg:city":"Omaha",
    "sg:classifiers":[
        {
            "category":"Building & Trades",
            "subcategory":"Landscaping Services",
            "type":"Services"
        }
    ],
    "sg:phone":"+1 402 330 7811",
    "sg:postcode":"68130",
    "sg:province":"NE",
    "sg:tags":[
        "landscape",
        "contractor"
    ],
    "wof:name":"Elite Landscaping LLC",
    "wof:placetype":"venue"
},
  "geometry": {"coordinates":[-96.16927800000001,41.231133],"type":"Point"}
}