{
  "type": "Feature",
  "properties": {
    "addr:full":"1525 Furnas St Ashland NE 68003",
    "addr:housenumber":"1525",
    "addr:postcode":"68003",
    "addr:street":"Furnas St",
    "iso:country":"US",
    "sg:address":"1525 Furnas St",
    "sg:city":"Ashland",
    "sg:classifiers":[
        {
            "category":"Building & Trades",
            "subcategory":"Construction",
            "type":"Services"
        }
    ],
    "sg:phone":"+1 402 430 5754",
    "sg:postcode":"68003",
    "sg:province":"NE",
    "sg:tags":[
        "home",
        "builder"
    ],
    "wof:name":"K & J Construction",
    "wof:placetype":"venue"
},
  "geometry": {"coordinates":[-96.36971,41.045],"type":"Point"}
}