{
  "type": "Feature",
  "properties": {
    "iso:country":"US",
    "sg:address":"508 N 13th St",
    "sg:city":"Hebron",
    "sg:classifiers":[
        {
            "category":"Retail",
            "subcategory":"Veterinary Services",
            "type":"Services"
        }
    ],
    "sg:phone":"+1 402 768 6770",
    "sg:postcode":"68370",
    "sg:province":"NE",
    "wof:name":"Sasse Gerald & Cindy Dvm Ofc",
    "wof:placetype":"venue"
},
  "geometry": {"coordinates":[-97.57654100000001,40.172019],"type":"Point"}
}