{
  "type": "Feature",
  "properties": {
    "iso:country":"US",
    "sg:address":"311 Indiana St",
    "sg:city":"Hubbell",
    "sg:classifiers":[
        {
            "category":"Retail",
            "subcategory":"Auto Repair",
            "type":"Services"
        }
    ],
    "sg:phone":"+1 402 324 4111",
    "sg:postcode":"68375",
    "sg:province":"NE",
    "sg:tags":[
        "transmission"
    ],
    "wof:name":"Mark Tipton Auto Svc",
    "wof:placetype":"venue"
},
  "geometry": {"coordinates":[-97.49755999999999,40.012462],"type":"Point"}
}