{
  "type": "Feature",
  "properties": {
    "addr:full":"105 N Park Ave Murray NE 68409",
    "addr:housenumber":"105",
    "addr:postcode":"68409",
    "addr:street":"N Park Ave",
    "iso:country":"US",
    "sg:address":"105 N Park Ave",
    "sg:city":"Murray",
    "sg:classifiers":[
        {
            "category":"Restaurant",
            "type":"Food & Drink"
        }
    ],
    "sg:phone":"+1 402 235 3322",
    "sg:postcode":"68409",
    "sg:province":"NE",
    "wof:name":"English Rose",
    "wof:placetype":"venue"
},
  "geometry": {"coordinates":[-95.928837,40.915462],"type":"Point"}
}