{
  "type": "Feature",
  "properties": {
    "addr:full":"100 N Aurora Ave Oakland NE 68045",
    "addr:housenumber":"100",
    "addr:postcode":"68045",
    "addr:street":"N Aurora Ave",
    "iso:country":"US",
    "sg:address":"100 N Aurora Ave",
    "sg:city":"Oakland",
    "sg:classifiers":[
        {
            "category":"Organizations",
            "subcategory":"Community Association",
            "type":"Services"
        }
    ],
    "sg:phone":"+1 402 685 5440",
    "sg:postcode":"68045",
    "sg:province":"NE",
    "wof:name":"Oak Land Housing Authorty",
    "wof:placetype":"venue"
},
  "geometry": {"coordinates":[-96.45738299999999,41.834877],"type":"Point"}
}