{
  "type": "Feature",
  "properties": {
    "addr:full":"6839 S 73rd Ave Omaha NE 68127",
    "addr:housenumber":"6839",
    "addr:postcode":"68127",
    "addr:street":"S 73Rd Ave",
    "iso:country":"US",
    "sg:address":"6839 S 73rd Ave",
    "sg:city":"Omaha",
    "sg:classifiers":[
        {
            "category":"Building & Trades",
            "subcategory":"Construction",
            "type":"Services"
        }
    ],
    "sg:phone":"+1 402 339 3445",
    "sg:postcode":"68127",
    "sg:province":"NE",
    "sg:tags":[
        "hanging",
        "contractor"
    ],
    "wof:name":"Hagedorn Painting",
    "wof:placetype":"venue"
},
  "geometry": {"coordinates":[-96.027913,41.191879],"type":"Point"}
}