{
  "type": "Feature",
  "properties": {
    "addr:full":"2200 Pine Lake Rd Lincoln NE 68516",
    "addr:housenumber":"2200",
    "addr:postcode":"68516",
    "addr:street":"Pine Lake Rd",
    "iso:country":"US",
    "sg:address":"2200 Pine Lake Rd",
    "sg:city":"Lincoln",
    "sg:classifiers":[
        {
            "category":"Education",
            "subcategory":"School",
            "type":"Public Place"
        }
    ],
    "sg:phone":"+1 402 436 1218",
    "sg:postcode":"68516",
    "sg:province":"NE",
    "sg:website":"www.lps.org",
    "wof:name":"Scott Middle School",
    "wof:placetype":"venue"
},
  "geometry": {"coordinates":[-96.68948899999999,40.739056],"type":"Point"}
}