{
  "type": "Feature",
  "properties": {
    "addr:full":"366 Regency Pkwy Omaha NE 68114",
    "addr:housenumber":"366",
    "addr:postcode":"68114",
    "addr:street":"Regency Pkwy",
    "iso:country":"US",
    "sg:address":"366 Regency Pkwy",
    "sg:city":"Omaha",
    "sg:classifiers":[
        {
            "category":"Health Services",
            "subcategory":"Doctor",
            "type":"Services"
        }
    ],
    "sg:phone":"+1 402 397 0670",
    "sg:postcode":"68114",
    "sg:province":"NE",
    "sg:tags":[
        "physician",
        "surgeon"
    ],
    "wof:name":"ENT Specialists",
    "wof:placetype":"venue"
},
  "geometry": {"coordinates":[-96.073401,41.256759],"type":"Point"}
}