{
  "type": "Feature",
  "properties": {
    "iso:country":"US",
    "sg:address":"3600 N 24th St",
    "sg:city":"Omaha",
    "sg:classifiers":[
        {
            "category":"Real Estate",
            "subcategory":"Real Estate Agent",
            "type":"Services"
        }
    ],
    "sg:phone":"+1 402 444 3265",
    "sg:postcode":"68110",
    "sg:province":"NE",
    "sg:tags":[
        "authorities",
        "housing"
    ],
    "wof:name":"Omaha Housing Auth Evans Tower",
    "wof:placetype":"venue"
},
  "geometry": {"coordinates":[-95.94697499999999,41.292305],"type":"Point"}
}