{
  "type": "Feature",
  "properties": {
    "addr:full":"1402 N Jeffers St North Platte NE 69101",
    "addr:housenumber":"1402",
    "addr:postcode":"69101",
    "addr:street":"N Jeffers St",
    "iso:country":"US",
    "sg:address":"1402 N Jeffers St",
    "sg:city":"North Platte",
    "sg:classifiers":[
        {
            "category":"Government",
            "subcategory":"Office",
            "type":"Public Place"
        }
    ],
    "sg:phone":"+1 308 535 6719",
    "sg:postcode":"69101",
    "sg:province":"NE",
    "sg:tags":[
        "village"
    ],
    "wof:name":"Cody Park Railroad Museum",
    "wof:placetype":"venue"
},
  "geometry": {"coordinates":[-100.760598,41.148368],"type":"Point"}
}