{
  "type": "Feature",
  "properties": {
    "iso:country":"US",
    "sg:address":"818 Village Sq",
    "sg:city":"Gretna",
    "sg:classifiers":[
        {
            "category":"Health Services",
            "subcategory":"Doctor",
            "type":"Services"
        },
        {
            "category":"Health Services",
            "subcategory":"Clinic",
            "type":"Services"
        }
    ],
    "sg:phone":"+1 402 332 4559",
    "sg:postcode":"68028",
    "sg:province":"NE",
    "sg:tags":[
        "physician",
        "family",
        "practice",
        "surgeons",
        "manipulative",
        "osteopathic",
        "treatment",
        "medicine",
        "surgeon"
    ],
    "sg:website":"http://www.thewellnessplace.org",
    "wof:name":"The Wellness Place PC",
    "wof:placetype":"venue"
},
  "geometry": {"coordinates":[-96.23964100000001,41.145894],"type":"Point"}
}