{
  "type": "Feature",
  "properties": {
    "iso:country":"US",
    "sg:address":"1508 23rd St",
    "sg:city":"Columbus",
    "sg:classifiers":[
        {
            "category":"Autos & Motor Vehicles",
            "subcategory":"Automobile Sales",
            "type":"Retail Goods"
        }
    ],
    "sg:phone":"+1 402 564 2113",
    "sg:postcode":"68601",
    "sg:province":"NE",
    "sg:tags":[
        "used"
    ],
    "wof:name":"Bills Auto Sales Inc",
    "wof:placetype":"venue"
},
  "geometry": {"coordinates":[-97.34522699999999,41.438363],"type":"Point"}
}