{
  "type": "Feature",
  "properties": {
    "addr:full":"1009 Jackson St Yankton NE 57078",
    "addr:housenumber":"1009",
    "addr:postcode":"57078",
    "addr:street":"Jackson St",
    "iso:country":"US",
    "sg:address":"1009 Jackson St",
    "sg:city":"Yankton",
    "sg:classifiers":[
        {
            "category":"Organizations",
            "subcategory":"Religious Organization",
            "type":"Services"
        }
    ],
    "sg:phone":"+1 605 665 7337",
    "sg:postcode":"57078",
    "sg:province":"NE",
    "sg:tags":[
        "church"
    ],
    "wof:name":"St John's Luth Chr & Pre-Schl",
    "wof:placetype":"venue"
},
  "geometry": {"coordinates":[-97.410031,42.880055],"type":"Point"}
}