{
  "type": "Feature",
  "properties": {
    "iso:country":"US",
    "sg:address":"348 24th Rd",
    "sg:city":"Oakland",
    "sg:phone":"+1 402 685 5847",
    "sg:postcode":"68045",
    "sg:province":"NE",
    "sg:tags":[
        "farm",
        "corn"
    ],
    "wof:name":"Anderson Livestock",
    "wof:placetype":"venue"
},
  "geometry": {"coordinates":[-96.574359,41.782455],"type":"Point"}
}