{
  "type": "Feature",
  "properties": {
    "iso:country":"US",
    "sg:address":"2120 Cornhusker Hwy",
    "sg:city":"Lincoln",
    "sg:classifiers":[
        {
            "category":"Retail",
            "subcategory":"Auto Repair",
            "type":"Services"
        }
    ],
    "sg:phone":"+1 402 438 4499",
    "sg:postcode":"68521",
    "sg:province":"NE",
    "sg:tags":[
        "wrecker"
    ],
    "wof:name":"T J Husky Towing",
    "wof:placetype":"venue"
},
  "geometry": {"coordinates":[-96.69000699999999,40.842766],"type":"Point"}
}