{
  "type": "Feature",
  "properties": {
    "iso:country":"US",
    "sg:address":"2110 Central Ave",
    "sg:city":"Kearney",
    "sg:classifiers":[
        {
            "category":"Shopping",
            "subcategory":"Jewelry",
            "type":"Retail Goods"
        }
    ],
    "sg:phone":"+1 308 237 3226",
    "sg:postcode":"68847",
    "sg:province":"NE",
    "sg:tags":[
        "repair"
    ],
    "wof:name":"KS Jewelry Partnership",
    "wof:placetype":"venue"
},
  "geometry": {"coordinates":[-99.081812,40.697519],"type":"Point"}
}