{
  "type": "Feature",
  "properties": {
    "addr:full":"13833 Capehart Rd Springfield NE 68059",
    "addr:housenumber":"13833",
    "addr:postcode":"68059",
    "addr:street":"Capehart Rd",
    "iso:country":"US",
    "sg:address":"13833 Capehart Rd",
    "sg:city":"Springfield",
    "sg:classifiers":[
        {
            "category":"Wholesale",
            "subcategory":"Construction Materials",
            "type":"Manufacturing & Wholesale Goods"
        },
        {
            "category":"Freight",
            "type":"Transportation"
        }
    ],
    "sg:phone":"+1 402 253 2349",
    "sg:postcode":"68059",
    "sg:province":"NE",
    "sg:tags":[
        "operator",
        "sand",
        "gravel",
        "trucking"
    ],
    "wof:name":"Tim Gruhn Trucking Inc",
    "wof:placetype":"venue"
},
  "geometry": {"coordinates":[-96.131798,41.11803],"type":"Point"}
}