{
  "type": "Feature",
  "properties": {
    "addr:full":"3200 N 20th St Lincoln NE 68521",
    "addr:housenumber":"3200",
    "addr:postcode":"68521",
    "addr:street":"N 20Th St",
    "iso:country":"US",
    "sg:address":"3200 N 20th St",
    "sg:city":"Lincoln",
    "sg:classifiers":[
        {
            "category":"Wholesale",
            "subcategory":"Machinery & Supplies",
            "type":"Manufacturing & Wholesale Goods"
        }
    ],
    "sg:phone":"+1 402 476 7900",
    "sg:postcode":"68521",
    "sg:province":"NE",
    "sg:tags":[
        "fastener",
        "industrial"
    ],
    "wof:name":"Fastenal Company",
    "wof:placetype":"venue"
},
  "geometry": {"coordinates":[-96.691547,40.845254],"type":"Point"}
}