{
  "type": "Feature",
  "properties": {
    "addr:full":"17923 Pierce Plz Omaha NE 68130",
    "addr:housenumber":"17923",
    "addr:postcode":"68130",
    "addr:street":"Pierce Plz",
    "iso:country":"US",
    "sg:address":"17923 Pierce Plz",
    "sg:city":"Omaha",
    "sg:classifiers":[
        {
            "category":"Recreation",
            "type":"Entertainment"
        }
    ],
    "sg:phone":"+1 402 697 5037",
    "sg:postcode":"68130",
    "sg:province":"NE",
    "sg:tags":[
        "martial",
        "arts",
        "instruction"
    ],
    "wof:name":"Christopher N Geary's Shaolin",
    "wof:placetype":"venue"
},
  "geometry": {"coordinates":[-96.194475,41.247361],"type":"Point"}
}