{
  "type": "Feature",
  "properties": {
    "iso:country":"US",
    "sg:address":"412 E 8th St",
    "sg:city":"Wayne",
    "sg:classifiers":[
        {
            "category":"Organizations",
            "subcategory":"Religious Organization",
            "type":"Services"
        }
    ],
    "sg:phone":"+1 402 375 2000",
    "sg:postcode":"68787",
    "sg:province":"NE",
    "sg:tags":[
        "church"
    ],
    "wof:name":"Saint Marys Catholic Church",
    "wof:placetype":"venue"
},
  "geometry": {"coordinates":[-97.012817,42.236621],"type":"Point"}
}