{
  "type": "Feature",
  "properties": {
    "iso:country":"US",
    "sg:address":"4212 S 133rd St",
    "sg:city":"Omaha",
    "sg:classifiers":[
        {
            "category":"Building & Trades",
            "subcategory":"Construction",
            "type":"Services"
        }
    ],
    "sg:phone":"+1 402 330 2751",
    "sg:postcode":"68137",
    "sg:province":"NE",
    "sg:tags":[
        "tile",
        "dealer"
    ],
    "wof:name":"Yankee Hill Brick & Tile",
    "wof:placetype":"venue"
},
  "geometry": {"coordinates":[-96.12150200000001,41.21799],"type":"Point"}
}