{
  "type": "Feature",
  "properties": {
    "iso:country":"US",
    "sg:address":"217 W 3rd St",
    "sg:city":"Alliance",
    "sg:classifiers":[
        {
            "category":"Retail",
            "subcategory":"Auto Repair",
            "type":"Services"
        }
    ],
    "sg:phone":"+1 308 762 5263",
    "sg:postcode":"69301",
    "sg:province":"NE",
    "sg:tags":[
        "repairing",
        "automobile"
    ],
    "wof:name":"Triple M Tire & Automotive",
    "wof:placetype":"venue"
},
  "geometry": {"coordinates":[-102.873361,42.096988],"type":"Point"}
}