{
  "type": "Feature",
  "properties": {
    "iso:country":"US",
    "sg:address":"2115 State St",
    "sg:city":"Grand Island",
    "sg:classifiers":[
        {
            "category":"Banks & Credit Unions",
            "subcategory":"Bank",
            "type":"Services"
        }
    ],
    "sg:phone":"+1 308 381 2281",
    "sg:postcode":"68803",
    "sg:province":"NE",
    "wof:name":"NAFCO Credit Union",
    "wof:placetype":"venue"
},
  "geometry": {"coordinates":[-98.363056,40.938439],"type":"Point"}
}