{
  "type": "Feature",
  "properties": {
    "iso:country":"US",
    "sg:address":"7600 S 142nd St",
    "sg:city":"Omaha",
    "sg:classifiers":[
        {
            "category":"Freight",
            "type":"Transportation"
        }
    ],
    "sg:phone":"+1 402 896 6500",
    "sg:postcode":"68138",
    "sg:province":"NE",
    "sg:tags":[
        "commercial",
        "storage"
    ],
    "wof:name":"Dino's Storage",
    "wof:placetype":"venue"
},
  "geometry": {"coordinates":[-96.13704199999999,41.183727],"type":"Point"}
}