{
  "type": "Feature",
  "properties": {
    "iso:country":"US",
    "sg:address":"4623 N 54th Cir",
    "sg:city":"Omaha",
    "sg:classifiers":[
        {
            "category":"Building & Trades",
            "subcategory":"Construction",
            "type":"Services"
        }
    ],
    "sg:phone":"+1 402 578 6280",
    "sg:postcode":"68144",
    "sg:province":"NE",
    "sg:tags":[
        "contractor",
        "painter",
        "hanging"
    ],
    "sg:website":"www.jandjpainting.com",
    "wof:name":"J & J Painting & Remodeling",
    "wof:placetype":"venue"
},
  "geometry": {"coordinates":[-95.99669299999999,41.301201],"type":"Point"}
}