{
  "type": "Feature",
  "properties": {
    "iso:country":"US",
    "sg:address":"1014 W 24th Ave",
    "sg:city":"Bellevue",
    "sg:classifiers":[
        {
            "category":"Wholesale",
            "subcategory":"Electrical",
            "type":"Manufacturing & Wholesale Goods"
        }
    ],
    "sg:phone":"+1 402 291 1123",
    "sg:postcode":"68005",
    "sg:province":"NE",
    "sg:tags":[
        "fire",
        "alarm",
        "system"
    ],
    "wof:name":"Ideal Systems",
    "wof:placetype":"venue"
},
  "geometry": {"coordinates":[-95.906505,41.134514],"type":"Point"}
}