{
  "type": "Feature",
  "properties": {
    "iso:country":"US",
    "sg:address":"1900 Rodeo Rd",
    "sg:city":"North Platte",
    "sg:classifiers":[
        {
            "category":"Wholesale",
            "subcategory":"Machinery & Supplies",
            "type":"Manufacturing & Wholesale Goods"
        }
    ],
    "sg:phone":"+1 308 532 1148",
    "sg:postcode":"69101",
    "sg:province":"NE",
    "sg:tags":[
        "farm",
        "equipment"
    ],
    "wof:name":"Sunco",
    "wof:placetype":"venue"
},
  "geometry": {"coordinates":[-100.78343700000001,41.148185],"type":"Point"}
}