{
  "type": "Feature",
  "properties": {
    "iso:country":"US",
    "sg:address":"4327 S 90th St",
    "sg:city":"Omaha",
    "sg:classifiers":[
        {
            "category":"Manufacturing",
            "subcategory":"Tools & Machinery",
            "type":"Manufacturing & Wholesale Goods"
        }
    ],
    "sg:phone":"+1 402 339 3550",
    "sg:postcode":"68127",
    "sg:province":"NE",
    "sg:tags":[
        "industrial",
        "mfg"
    ],
    "wof:name":"American Machine Products Inc",
    "wof:placetype":"venue"
},
  "geometry": {"coordinates":[-96.05256900000001,41.216429],"type":"Point"}
}