{
  "type": "Feature",
  "properties": {
    "iso:country":"US",
    "sg:address":"16217 6th St",
    "sg:city":"Plattsmouth",
    "sg:classifiers":[
        {
            "category":"Building & Trades",
            "subcategory":"Construction",
            "type":"Services"
        }
    ],
    "sg:phone":"+1 402 677 7984",
    "sg:postcode":"68048",
    "sg:province":"NE",
    "sg:tags":[
        "contractor"
    ],
    "wof:name":"Cr Gutters Inc",
    "wof:placetype":"venue"
},
  "geometry": {"coordinates":[-95.92070099999999,41.008722],"type":"Point"}
}