{
  "type": "Feature",
  "properties": {
    "addr:full":"8031 W Center Rd Rmp Omaha NE 68124",
    "addr:housenumber":"8031",
    "addr:postcode":"68124",
    "addr:street":"W Center Rd",
    "iso:country":"US",
    "sg:address":"8031 W Center Rd Rmp",
    "sg:city":"Omaha",
    "sg:classifiers":[
        {
            "category":"Recreation",
            "type":"Entertainment"
        }
    ],
    "sg:phone":"+1 402 991 8774",
    "sg:postcode":"68124",
    "sg:province":"NE",
    "sg:tags":[
        "ticket"
    ],
    "wof:name":"Red Zone Tickets",
    "wof:placetype":"venue"
},
  "geometry": {"coordinates":[-96.03728099999999,41.234035],"type":"Point"}
}