{
  "type": "Feature",
  "properties": {
    "iso:country":"US",
    "sg:address":"1420 Military Ave",
    "sg:city":"Omaha",
    "sg:classifiers":[
        {
            "category":"Shopping",
            "subcategory":"Bicycles & Sporting Goods",
            "type":"Retail Goods"
        }
    ],
    "sg:phone":"+1 402 556 0226",
    "sg:postcode":"68131",
    "sg:province":"NE",
    "wof:name":"Moneymakers Guncraft Corp",
    "wof:placetype":"venue"
},
  "geometry": {"coordinates":[-95.977097,41.272202],"type":"Point"}
}