{
  "type": "Feature",
  "properties": {
    "iso:country":"US",
    "sg:address":"407 4th St",
    "sg:city":"Yutan",
    "sg:classifiers":[
        {
            "category":"Retail",
            "subcategory":"Funeral Services",
            "type":"Services"
        }
    ],
    "sg:phone":"+1 402 625 2222",
    "sg:postcode":"68073",
    "sg:province":"NE",
    "sg:tags":[
        "director"
    ],
    "wof:name":"Reichmuth Funeral Home",
    "wof:placetype":"venue"
},
  "geometry": {"coordinates":[-96.39987000000001,41.245687],"type":"Point"}
}