{
  "type": "Feature",
  "properties": {
    "addr:full":"2121 Douglas St Omaha NE 68102",
    "addr:housenumber":"2121",
    "addr:postcode":"68102",
    "addr:street":"Douglas St",
    "iso:country":"US",
    "sg:address":"2121 Douglas St",
    "sg:city":"Omaha",
    "sg:classifiers":[
        {
            "category":"Building & Trades",
            "subcategory":"Locksmith",
            "type":"Services"
        }
    ],
    "sg:phone":"+1 402 881 3514",
    "sg:postcode":"68102",
    "sg:province":"NE",
    "sg:tags":[
        "key"
    ],
    "wof:name":"Locksmith Asap",
    "wof:placetype":"venue"
},
  "geometry": {"coordinates":[-95.94370000000001,41.258531],"type":"Point"}
}