{
  "type": "Feature",
  "properties": {
    "iso:country":"US",
    "sg:address":"505 N 27th St",
    "sg:city":"Lincoln",
    "sg:classifiers":[
        {
            "category":"Food & Beverages",
            "subcategory":"Meat & Fish",
            "type":"Retail Goods"
        },
        {
            "category":"Wholesale",
            "subcategory":"Seafood",
            "type":"Manufacturing & Wholesale Goods"
        }
    ],
    "sg:phone":"+1 402 435 1200",
    "sg:postcode":"68503",
    "sg:province":"NE",
    "wof:name":"Midwest Seafood",
    "wof:placetype":"venue"
},
  "geometry": {"coordinates":[-96.682461,40.818046],"type":"Point"}
}