{
  "type": "Feature",
  "properties": {
    "iso:country":"US",
    "sg:address":"810 US Hwy 30",
    "sg:city":"Kimball",
    "sg:classifiers":[
        {
            "category":"Manufacturing",
            "subcategory":"Tools & Machinery",
            "type":"Manufacturing & Wholesale Goods"
        }
    ],
    "sg:phone":"+1 308 235 2278",
    "sg:postcode":"69145",
    "sg:province":"NE",
    "sg:tags":[
        "machine",
        "shop"
    ],
    "wof:name":"TMR Machine",
    "wof:placetype":"venue"
},
  "geometry": {"coordinates":[-103.67396599999999,41.237689],"type":"Point"}
}