{
  "type": "Feature",
  "properties": {
    "iso:country":"US",
    "sg:address":"3285 W Belvidere Rd",
    "sg:city":"Beatrice",
    "sg:classifiers":[
        {
            "category":"Freight",
            "type":"Transportation"
        }
    ],
    "sg:phone":"+1 402 223 4040",
    "sg:postcode":"68310",
    "sg:province":"NE",
    "sg:tags":[
        "operator",
        "trucking"
    ],
    "wof:name":"Bills Creek Express",
    "wof:placetype":"venue"
},
  "geometry": {"coordinates":[-96.768653,40.248292],"type":"Point"}
}