{
  "type": "Feature",
  "properties": {
    "iso:country":"US",
    "sg:address":"1239 Main Ave",
    "sg:city":"Crete",
    "sg:classifiers":[
        {
            "category":"Real Estate",
            "subcategory":"Real Estate Services",
            "type":"Services"
        }
    ],
    "sg:phone":"+1 402 826 2007",
    "sg:postcode":"68333",
    "sg:province":"NE",
    "sg:tags":[
        "company",
        "title"
    ],
    "wof:name":"Nebraska Title Co",
    "wof:placetype":"venue"
},
  "geometry": {"coordinates":[-96.961585,40.624867],"type":"Point"}
}