{
  "type": "Feature",
  "properties": {
    "addr:full":"107 Forest Blvd Hastings NE 68901",
    "addr:housenumber":"107",
    "addr:postcode":"68901",
    "addr:street":"Forest Blvd",
    "iso:country":"US",
    "sg:address":"107 Forest Blvd",
    "sg:city":"Hastings",
    "sg:classifiers":[
        {
            "category":"Government",
            "subcategory":"Office",
            "type":"Public Place"
        }
    ],
    "sg:phone":"+1 402 773 4386",
    "sg:postcode":"68901",
    "sg:province":"NE",
    "sg:tags":[
        "civil",
        "defense",
        "agency"
    ],
    "wof:name":"Sutton Civil Defense",
    "wof:placetype":"venue"
},
  "geometry": {"coordinates":[-98.382268,40.594591],"type":"Point"}
}