{
  "type": "Feature",
  "properties": {
    "iso:country":"US",
    "sg:address":"7447 Farnam St",
    "sg:city":"Omaha",
    "sg:classifiers":[
        {
            "category":"Recreation",
            "type":"Entertainment"
        }
    ],
    "sg:phone":"+1 402 706 1935",
    "sg:postcode":"68114",
    "sg:province":"NE",
    "sg:tags":[
        "amusement"
    ],
    "wof:name":"Solutions",
    "wof:placetype":"venue"
},
  "geometry": {"coordinates":[-96.027411,41.258049],"type":"Point"}
}