{
  "type": "Feature",
  "properties": {
    "iso:country":"US",
    "sg:address":"3147 N 84th Cir",
    "sg:city":"Omaha",
    "sg:classifiers":[
        {
            "category":"Retail",
            "subcategory":"Laundry & Dry Cleaning",
            "type":"Services"
        }
    ],
    "sg:phone":"+1 402 734 4620",
    "sg:postcode":"68134",
    "sg:province":"NE",
    "sg:website":"www.crdn.com",
    "wof:name":"Nu Trend Dry Cleaners",
    "wof:placetype":"venue"
},
  "geometry": {"coordinates":[-96.04376000000001,41.286905],"type":"Point"}
}