{
  "type": "Feature",
  "properties": {
    "iso:country":"US",
    "sg:address":"14647 Monroe St",
    "sg:city":"Omaha",
    "sg:classifiers":[
        {
            "category":"Professional",
            "type":"Services"
        }
    ],
    "sg:phone":"+1 402 896 9861",
    "sg:postcode":"68137",
    "sg:province":"NE",
    "wof:name":"Turner Designs Sue",
    "wof:placetype":"venue"
},
  "geometry": {"coordinates":[-96.142337,41.194145],"type":"Point"}
}