{
  "type": "Feature",
  "properties": {
    "iso:country":"US",
    "sg:address":"915 N York Ave",
    "sg:city":"York",
    "sg:classifiers":[
        {
            "category":"Insurance",
            "subcategory":"Insurance Agent",
            "type":"Services"
        }
    ],
    "sg:phone":"+1 402 362 3422",
    "sg:postcode":"68467",
    "sg:province":"NE",
    "wof:name":"Horace Mann Insurance Co",
    "wof:placetype":"venue"
},
  "geometry": {"coordinates":[-97.596598,40.870729],"type":"Point"}
}