{
  "type": "Feature",
  "properties": {
    "addr:full":"340 E 4th St Ainsworth NE 69210",
    "addr:housenumber":"340",
    "addr:postcode":"69210",
    "addr:street":"E 4Th St",
    "iso:country":"US",
    "sg:address":"340 E 4th St",
    "sg:city":"Ainsworth",
    "sg:classifiers":[
        {
            "category":"Autos & Motor Vehicles",
            "subcategory":"Auto Supplies",
            "type":"Retail Goods"
        }
    ],
    "sg:phone":"+1 402 387 0203",
    "sg:postcode":"69210",
    "sg:province":"NE",
    "sg:tags":[
        "sporting"
    ],
    "wof:name":"Moodys Tire & Supply",
    "wof:placetype":"venue"
},
  "geometry": {"coordinates":[-99.859278,42.549967],"type":"Point"}
}