{
  "type": "Feature",
  "properties": {
    "iso:country":"US",
    "sg:address":"212 Wyandotte St",
    "sg:city":"Grand Island",
    "sg:classifiers":[
        {
            "category":"Retail",
            "subcategory":"Auto Repair",
            "type":"Services"
        }
    ],
    "sg:phone":"+1 308 382 2028",
    "sg:postcode":"68801",
    "sg:province":"NE",
    "sg:tags":[
        "body",
        "automobile",
        "painting"
    ],
    "wof:name":"Sorensen's Body Paint & Frame",
    "wof:placetype":"venue"
},
  "geometry": {"coordinates":[-98.340225,40.899279],"type":"Point"}
}