{
  "type": "Feature",
  "properties": {
    "iso:country":"US",
    "sg:address":"1317 W 3rd St",
    "sg:city":"Alliance",
    "sg:classifiers":[
        {
            "category":"Health Services",
            "subcategory":"Optometrist",
            "type":"Services"
        }
    ],
    "sg:phone":"+1 308 762 4056",
    "sg:postcode":"69301",
    "sg:province":"NE",
    "sg:website":"www.familyvisionalliance.com",
    "wof:name":"Family Vision Clinic",
    "wof:placetype":"venue"
},
  "geometry": {"coordinates":[-102.88995,42.096703],"type":"Point"}
}