{
  "type": "Feature",
  "properties": {
    "addr:full":"15619 W Dodge Rd Omaha NE 68118",
    "addr:housenumber":"15619",
    "addr:postcode":"68118",
    "addr:street":"W Dodge Rd",
    "iso:country":"US",
    "sg:address":"15619 W Dodge Rd",
    "sg:city":"Omaha",
    "sg:classifiers":[
        {
            "category":"Restaurant",
            "type":"Food & Drink"
        }
    ],
    "sg:menulink":"http://www.allmenus.com/ne/omaha/87128-little-caesars-pizza/menu/",
    "sg:phone":"+1 402 330 8112",
    "sg:postcode":"68118",
    "sg:province":"NE",
    "sg:tags":[
        "american",
        "pizza"
    ],
    "wof:name":"Little Caesar's Pizza",
    "wof:placetype":"venue"
},
  "geometry": {"coordinates":[-96.162218,41.262699],"type":"Point"}
}