{
  "type": "Feature",
  "properties": {
    "addr:full":"1310 N 13th St Norfolk NE 68701",
    "addr:housenumber":"1310",
    "addr:postcode":"68701",
    "addr:street":"N 13Th St",
    "iso:country":"US",
    "sg:address":"1310 N 13th St",
    "sg:city":"Norfolk",
    "sg:classifiers":[
        {
            "category":"Professional",
            "subcategory":"Lawyer & Legal Services",
            "type":"Services"
        }
    ],
    "sg:phone":"+1 402 371 9045",
    "sg:postcode":"68701",
    "sg:province":"NE",
    "sg:tags":[
        "attorney"
    ],
    "wof:name":"Johnson Morland & Easland",
    "wof:placetype":"venue"
},
  "geometry": {"coordinates":[-97.426511,42.048147],"type":"Point"}
}