{
  "type": "Feature",
  "properties": {
    "iso:country":"US",
    "sg:address":"10357 Pacific St",
    "sg:city":"Omaha",
    "sg:classifiers":[
        {
            "category":"Shopping",
            "subcategory":"Clothing, Apparel, & Fashions",
            "type":"Retail Goods"
        }
    ],
    "sg:phone":"+1 402 391 4620",
    "sg:postcode":"68114",
    "sg:province":"NE",
    "sg:tags":[
        "paper"
    ],
    "wof:name":"Harolds Stores Inc",
    "wof:placetype":"venue"
},
  "geometry": {"coordinates":[-96.07573600000001,41.248684],"type":"Point"}
}