{
  "type": "Feature",
  "properties": {
    "iso:country":"US",
    "sg:address":"410 S Webb Rd",
    "sg:city":"Grand Island",
    "sg:classifiers":[
        {
            "category":"Shopping",
            "type":"Retail Goods"
        }
    ],
    "sg:phone":"+1 308 382 6010",
    "sg:postcode":"68803",
    "sg:province":"NE",
    "sg:tags":[
        "stone",
        "monument"
    ],
    "wof:name":"Palmer-Scheffel Monuments Co",
    "wof:placetype":"venue"
},
  "geometry": {"coordinates":[-98.378489,40.914162],"type":"Point"}
}