{
  "type": "Feature",
  "properties": {
    "addr:full":"1016 E 25th St Kearney NE 68847",
    "addr:housenumber":"1016",
    "addr:postcode":"68847",
    "addr:street":"E 25Th St",
    "iso:country":"US",
    "sg:address":"1016 E 25th St",
    "sg:city":"Kearney",
    "sg:classifiers":[
        {
            "category":"Retail",
            "subcategory":"Auto Repair",
            "type":"Services"
        }
    ],
    "sg:phone":"+1 308 233 5825",
    "sg:postcode":"68847",
    "sg:province":"NE",
    "sg:tags":[
        "repairing",
        "automobile"
    ],
    "wof:name":"Gibbon Transmissions",
    "wof:placetype":"venue"
},
  "geometry": {"coordinates":[-99.06858099999999,40.700208],"type":"Point"}
}