{
  "type": "Feature",
  "properties": {
    "addr:full":"2105 S 161st Cir Omaha NE 68130",
    "addr:housenumber":"2105",
    "addr:postcode":"68130",
    "addr:street":"S 161St Cir",
    "iso:country":"US",
    "sg:address":"2105 S 161st Cir",
    "sg:city":"Omaha",
    "sg:classifiers":[
        {
            "category":"Arts & Performance",
            "subcategory":"Theater",
            "type":"Entertainment"
        }
    ],
    "sg:phone":"+1 402 697 8561",
    "sg:postcode":"68130",
    "sg:province":"NE",
    "sg:tags":[
        "group"
    ],
    "wof:name":"Maggie McAll Bar & Grill",
    "wof:placetype":"venue"
},
  "geometry": {"coordinates":[-96.16622099999999,41.238182],"type":"Point"}
}