{
  "type": "Feature",
  "properties": {
    "addr:full":"158 N Main St Valentine NE 69201",
    "addr:housenumber":"158",
    "addr:postcode":"69201",
    "addr:street":"N Main St",
    "iso:country":"US",
    "sg:address":"158 N Main St",
    "sg:city":"Valentine",
    "sg:classifiers":[
        {
            "category":"Retail",
            "subcategory":"Repair Shop",
            "type":"Services"
        }
    ],
    "sg:phone":"+1 402 376 1313",
    "sg:postcode":"69201",
    "sg:province":"NE",
    "sg:tags":[
        "lock",
        "locksmith"
    ],
    "wof:name":"Heart City Lock & Key",
    "wof:placetype":"venue"
},
  "geometry": {"coordinates":[-100.550528,42.872228],"type":"Point"}
}