{
  "type": "Feature",
  "properties": {
    "iso:country":"US",
    "sg:address":"221 N Jeffers St",
    "sg:city":"North Platte",
    "sg:classifiers":[
        {
            "category":"Professional",
            "subcategory":"Employment Agencies",
            "type":"Services"
        }
    ],
    "sg:phone":"+1 308 532 9236",
    "sg:postcode":"69101",
    "sg:province":"NE",
    "sg:tags":[
        "help",
        "contractor"
    ],
    "wof:name":"Donna's Office Svc",
    "wof:placetype":"venue"
},
  "geometry": {"coordinates":[-100.76357400000001,41.134655],"type":"Point"}
}