{
  "type": "Feature",
  "properties": {
    "iso:country":"US",
    "sg:address":"717 Brown Ave",
    "sg:city":"Alma",
    "sg:classifiers":[
        {
            "category":"Health Services",
            "subcategory":"Hospital",
            "type":"Services"
        }
    ],
    "sg:phone":"+1 308 928 2151",
    "sg:postcode":"68920",
    "sg:province":"NE",
    "wof:name":"Harlan County Health System",
    "wof:placetype":"venue"
},
  "geometry": {"coordinates":[-99.364313,40.103677],"type":"Point"}
}