{
  "type": "Feature",
  "properties": {
    "iso:country":"US",
    "sg:address":"35665 Pine Rd",
    "sg:city":"Ravenna",
    "sg:classifiers":[
        {
            "category":"Restaurant",
            "type":"Food & Drink"
        }
    ],
    "sg:phone":"+1 308 452 3448",
    "sg:postcode":"68869",
    "sg:province":"NE",
    "wof:name":"Steaks-N-More",
    "wof:placetype":"venue"
},
  "geometry": {"coordinates":[-98.922078,41.02167],"type":"Point"}
}