{
  "type": "Feature",
  "properties": {
    "iso:country":"US",
    "sg:address":"3423 L St",
    "sg:city":"Omaha",
    "sg:classifiers":[
        {
            "category":"Shopping",
            "subcategory":"Mobile Phones",
            "type":"Retail Goods"
        }
    ],
    "sg:phone":"+1 402 733 7534",
    "sg:postcode":"68107",
    "sg:province":"NE",
    "sg:website":"www.radioshack.com",
    "wof:name":"Radioshack",
    "wof:placetype":"venue"
},
  "geometry": {"coordinates":[-95.96401,41.212105],"type":"Point"}
}