{
  "type": "Feature",
  "properties": {
    "iso:country":"US",
    "sg:address":"2905 10th St",
    "sg:city":"Gering",
    "sg:classifiers":[
        {
            "category":"Autos & Motor Vehicles",
            "subcategory":"Auto Supplies",
            "type":"Retail Goods"
        }
    ],
    "sg:phone":"+1 308 436 5858",
    "sg:postcode":"69341",
    "sg:province":"NE",
    "sg:tags":[
        "tire"
    ],
    "wof:name":"Budget Tire & Svc",
    "wof:placetype":"venue"
},
  "geometry": {"coordinates":[-103.66076099999999,41.843393],"type":"Point"}
}