{
  "type": "Feature",
  "properties": {
    "addr:full":"2523 Edward Babe Gomez Ave Omaha NE 68107",
    "addr:housenumber":"2523",
    "addr:postcode":"68107",
    "addr:street":"Edward Babe Gomez Ave",
    "iso:country":"US",
    "sg:address":"2523 Edward Babe Gomez Ave",
    "sg:city":"Omaha",
    "sg:classifiers":[
        {
            "category":"Freight",
            "type":"Transportation"
        }
    ],
    "sg:phone":"+1 402 733 8370",
    "sg:postcode":"68107",
    "sg:province":"NE",
    "sg:tags":[
        "warehouse",
        "storage"
    ],
    "sg:website":"www.millardref.com",
    "wof:name":"Millard Refrigerated Svc",
    "wof:placetype":"venue"
},
  "geometry": {"coordinates":[-95.949652,41.20031],"type":"Point"}
}