{
  "type": "Feature",
  "properties": {
    "addr:full":"1602 Harlan St Falls City NE 68355",
    "addr:housenumber":"1602",
    "addr:postcode":"68355",
    "addr:street":"Harlan St",
    "iso:country":"US",
    "sg:address":"1602 Harlan St",
    "sg:city":"Falls City",
    "sg:classifiers":[
        {
            "category":"Organizations",
            "subcategory":"Religious Organization",
            "type":"Services"
        }
    ],
    "sg:phone":"+1 402 245 2868",
    "sg:postcode":"68355",
    "sg:province":"NE",
    "sg:tags":[
        "church"
    ],
    "wof:name":"Saint Thomas Episcopal Church",
    "wof:placetype":"venue"
},
  "geometry": {"coordinates":[-95.60170599999999,40.061696],"type":"Point"}
}