{
  "type": "Feature",
  "properties": {
    "addr:full":"3519 Center St Omaha NE 68105",
    "addr:housenumber":"3519",
    "addr:postcode":"68105",
    "addr:street":"Center St",
    "iso:country":"US",
    "sg:address":"3519 Center St",
    "sg:city":"Omaha",
    "sg:classifiers":[
        {
            "category":"Manufacturing",
            "subcategory":"Apparel",
            "type":"Manufacturing & Wholesale Goods"
        }
    ],
    "sg:phone":"+1 402 345 4062",
    "sg:postcode":"68105",
    "sg:province":"NE",
    "sg:tags":[
        "blind",
        "bedspread",
        "shade"
    ],
    "wof:name":"Personal Touch",
    "wof:placetype":"venue"
},
  "geometry": {"coordinates":[-95.96489699999999,41.241402],"type":"Point"}
}