{
  "type": "Feature",
  "properties": {
    "iso:country":"US",
    "sg:address":"641 N Cedar St",
    "sg:city":"Red Cloud",
    "sg:classifiers":[
        {
            "category":"Government",
            "subcategory":"Police Station",
            "type":"Public Place"
        }
    ],
    "sg:phone":"+1 402 746 3612",
    "sg:postcode":"68970",
    "sg:province":"NE",
    "sg:tags":[
        "department"
    ],
    "wof:name":"Red Cloud Police Dept",
    "wof:placetype":"venue"
},
  "geometry": {"coordinates":[-98.520749,40.091503],"type":"Point"}
}