{
  "type": "Feature",
  "properties": {
    "iso:country":"US",
    "sg:address":"6400 O St",
    "sg:city":"Lincoln",
    "sg:classifiers":[
        {
            "category":"Shopping",
            "subcategory":"Optical Goods",
            "type":"Retail Goods"
        }
    ],
    "sg:phone":"+1 402 465 3368",
    "sg:postcode":"68510",
    "sg:province":"NE",
    "wof:name":"Sears Optical",
    "wof:placetype":"venue"
},
  "geometry": {"coordinates":[-96.633999,40.813508],"type":"Point"}
}