{
  "type": "Feature",
  "properties": {
    "addr:full":"706 Broadway St Holdrege NE 68949",
    "addr:housenumber":"706",
    "addr:postcode":"68949",
    "addr:street":"Broadway St",
    "iso:country":"US",
    "sg:address":"706 Broadway St",
    "sg:city":"Holdrege",
    "sg:classifiers":[
        {
            "category":"Organizations",
            "subcategory":"Religious Organization",
            "type":"Services"
        }
    ],
    "sg:phone":"+1 308 995 6213",
    "sg:postcode":"68949",
    "sg:province":"NE",
    "wof:name":"Bethphage Mission Great Plains",
    "wof:placetype":"venue"
},
  "geometry": {"coordinates":[-99.387293,40.442141],"type":"Point"}
}