{
  "type": "Feature",
  "properties": {
    "addr:full":"617 W 3rd St Grand Island NE 68801",
    "addr:housenumber":"617",
    "addr:postcode":"68801",
    "addr:street":"W 3Rd St",
    "iso:country":"US",
    "sg:address":"617 W 3rd St",
    "sg:city":"Grand Island",
    "sg:classifiers":[
        {
            "category":"Shopping",
            "subcategory":"Stationery & Office Supplies",
            "type":"Retail Goods"
        }
    ],
    "sg:phone":"+1 308 382 8026",
    "sg:postcode":"68801",
    "sg:province":"NE",
    "sg:website":"www.eakes.com",
    "wof:name":"Eakes Office Plus",
    "wof:placetype":"venue"
},
  "geometry": {"coordinates":[-98.345568,40.923454],"type":"Point"}
}