{
  "type": "Feature",
  "properties": {
    "iso:country":"US",
    "sg:address":"1410 Garfield St",
    "sg:city":"Lincoln",
    "sg:classifiers":[
        {
            "category":"Museum",
            "type":"Entertainment"
        }
    ],
    "sg:phone":"+1 402 477 4403",
    "sg:postcode":"68502",
    "sg:province":"NE",
    "wof:name":"Clarke Design Svc",
    "wof:placetype":"venue"
},
  "geometry": {"coordinates":[-96.699911,40.797261],"type":"Point"}
}