{
  "type": "Feature",
  "properties": {
    "addr:full":"2101 Q St Omaha NE 68107",
    "addr:housenumber":"2101",
    "addr:postcode":"68107",
    "addr:street":"Q St",
    "iso:country":"US",
    "sg:address":"2101 Q St",
    "sg:city":"Omaha",
    "sg:classifiers":[
        {
            "category":"Wholesale",
            "subcategory":"Hardware",
            "type":"Manufacturing & Wholesale Goods"
        }
    ],
    "sg:phone":"+1 402 397 9707",
    "sg:postcode":"68107",
    "sg:province":"NE",
    "sg:tags":[
        "equipment",
        "heating",
        "system"
    ],
    "wof:name":"Floyd's",
    "wof:placetype":"venue"
},
  "geometry": {"coordinates":[-95.944294,41.205585],"type":"Point"}
}