{
  "type": "Feature",
  "properties": {
    "addr:full":"4151 S 94th St Omaha NE 68127",
    "addr:housenumber":"4151",
    "addr:postcode":"68127",
    "addr:street":"S 94Th St",
    "iso:country":"US",
    "sg:address":"4151 S 94th St",
    "sg:city":"Omaha",
    "sg:classifiers":[
        {
            "category":"Manufacturing",
            "subcategory":"Printing",
            "type":"Manufacturing & Wholesale Goods"
        }
    ],
    "sg:phone":"+1 402 884 3481",
    "sg:postcode":"68127",
    "sg:province":"NE",
    "sg:tags":[
        "publishing"
    ],
    "wof:name":"Prairie Publishing Co",
    "wof:placetype":"venue"
},
  "geometry": {"coordinates":[-96.058694,41.21916],"type":"Point"}
}