{
  "type": "Feature",
  "properties": {
    "iso:country":"US",
    "sg:address":"2416 Davenport St",
    "sg:city":"Omaha",
    "sg:classifiers":[
        {
            "category":"Bars & Pubs",
            "subcategory":"Sports Bar",
            "type":"Food & Drink"
        }
    ],
    "sg:phone":"+1 402 345 1979",
    "sg:postcode":"68131",
    "sg:province":"NE",
    "sg:website":"www.facebook.com/bluejaybar",
    "wof:name":"Blue Jay",
    "wof:placetype":"venue"
},
  "geometry": {"coordinates":[-95.947098,41.261799],"type":"Point"}
}