{
  "type": "Feature",
  "properties": {
    "iso:country":"US",
    "sg:address":"13685 S Conestoga Ave",
    "sg:city":"Roseland",
    "sg:phone":"+1 402 756 6446",
    "sg:postcode":"68973",
    "sg:province":"NE",
    "sg:tags":[
        "farm",
        "corn"
    ],
    "wof:name":"Jeff Grabill",
    "wof:placetype":"venue"
},
  "geometry": {"coordinates":[-98.534082,40.417052],"type":"Point"}
}