{
  "type": "Feature",
  "properties": {
    "iso:country":"US",
    "sg:address":"1609 Fort St",
    "sg:city":"Schuyler",
    "sg:classifiers":[
        {
            "category":"Retail",
            "subcategory":"Auto Repair",
            "type":"Services"
        }
    ],
    "sg:phone":"+1 402 352 3186",
    "sg:postcode":"68661",
    "sg:province":"NE",
    "wof:name":"Dubskys Auto Center",
    "wof:placetype":"venue"
},
  "geometry": {"coordinates":[-97.067218,41.454432],"type":"Point"}
}