{
  "type": "Feature",
  "properties": {
    "iso:country":"US",
    "sg:address":"507 S Butler Ave",
    "sg:city":"Sutton",
    "sg:phone":"+1 402 773 5216",
    "sg:postcode":"68979",
    "sg:province":"NE",
    "sg:tags":[
        "farm",
        "grain",
        "cash"
    ],
    "wof:name":"Gerald Ochsner",
    "wof:placetype":"venue"
},
  "geometry": {"coordinates":[-97.86100999999999,40.602425],"type":"Point"}
}