{
  "type": "Feature",
  "properties": {
    "iso:country":"US",
    "sg:address":"30852 Co Rd 29",
    "sg:city":"Minatare",
    "sg:classifiers":[
        {
            "category":"Retail",
            "subcategory":"Animal Services",
            "type":"Services"
        }
    ],
    "sg:phone":"+1 308 783 5304",
    "sg:postcode":"69356",
    "sg:province":"NE",
    "wof:name":"Horsetooth Stables Inc",
    "wof:placetype":"venue"
},
  "geometry": {"coordinates":[-103.519755,41.964526],"type":"Point"}
}