{
  "type": "Feature",
  "properties": {
    "addr:full":"56807 Golf Course Rd Stanton NE 68779",
    "addr:housenumber":"56807",
    "addr:postcode":"68779",
    "addr:street":"Golf Course Rd",
    "iso:country":"US",
    "sg:address":"56807 Golf Course Rd",
    "sg:city":"Stanton",
    "sg:classifiers":[
        {
            "category":"Farming",
            "subcategory":"Farm",
            "type":"Manufacturing & Wholesale Goods"
        }
    ],
    "sg:phone":"+1 402 439 2665",
    "sg:postcode":"68779",
    "sg:province":"NE",
    "sg:tags":[
        "crop",
        "general"
    ],
    "wof:name":"Kment Rudolph",
    "wof:placetype":"venue"
},
  "geometry": {"coordinates":[-97.17615600000001,41.938949],"type":"Point"}
}