{
  "type": "Feature",
  "properties": {
    "iso:country":"US",
    "sg:address":"3311 S Oak St",
    "sg:city":"North Platte",
    "sg:classifiers":[
        {
            "category":"Organizations",
            "subcategory":"Religious Organization",
            "type":"Services"
        }
    ],
    "sg:phone":"+1 308 532 3776",
    "sg:postcode":"69101",
    "sg:province":"NE",
    "wof:name":"Church Of Christ",
    "wof:placetype":"venue"
},
  "geometry": {"coordinates":[-100.772746,41.103662],"type":"Point"}
}