{
  "type": "Feature",
  "properties": {
    "addr:full":"716 Fort Crook Rd N Bellevue NE 68005",
    "addr:housenumber":"716",
    "addr:postcode":"68005",
    "addr:street":"Fort Crook Rd N",
    "iso:country":"US",
    "sg:address":"716 Fort Crook Rd N",
    "sg:city":"Bellevue",
    "sg:classifiers":[
        {
            "category":"Retail",
            "subcategory":"Veterinary Services",
            "type":"Services"
        }
    ],
    "sg:phone":"+1 402 731 6655",
    "sg:postcode":"68005",
    "sg:province":"NE",
    "wof:name":"Heartland Animal Hospital",
    "wof:placetype":"venue"
},
  "geometry": {"coordinates":[-95.92556999999999,41.171728],"type":"Point"}
}