{
  "type": "Feature",
  "properties": {
    "addr:full":"730 E 1st St Ogallala NE 69153",
    "addr:housenumber":"730",
    "addr:postcode":"69153",
    "addr:street":"E 1St St",
    "iso:country":"US",
    "sg:address":"730 E 1st St",
    "sg:city":"Ogallala",
    "sg:classifiers":[
        {
            "category":"Travel",
            "subcategory":"Hotels & Motels",
            "type":"Entertainment"
        }
    ],
    "sg:phone":"+1 308 284 6117",
    "sg:postcode":"69153",
    "sg:province":"NE",
    "wof:name":"Pump & Pantry",
    "wof:placetype":"venue"
},
  "geometry": {"coordinates":[-101.711125,41.12562],"type":"Point"}
}