{
  "type": "Feature",
  "properties": {
    "iso:country":"US",
    "sg:address":"5627 Ames Ave",
    "sg:city":"Omaha",
    "sg:classifiers":[
        {
            "category":"Food & Beverages",
            "subcategory":"Liquor & Beverages",
            "type":"Retail Goods"
        }
    ],
    "sg:phone":"+1 402 451 5652",
    "sg:postcode":"68104",
    "sg:province":"NE",
    "sg:tags":[
        "beer",
        "spirit",
        "wine"
    ],
    "wof:name":"Sugar Hill Package Liquor",
    "wof:placetype":"venue"
},
  "geometry": {"coordinates":[-96.001404,41.2994],"type":"Point"}
}