{
  "type": "Feature",
  "properties": {
    "iso:country":"US",
    "sg:address":"3230 Burt St",
    "sg:city":"Omaha",
    "sg:classifiers":[
        {
            "category":"Education",
            "subcategory":"School",
            "type":"Public Place"
        }
    ],
    "sg:phone":"+1 402 557 3700",
    "sg:postcode":"68131",
    "sg:province":"NE",
    "sg:tags":[
        "elementary"
    ],
    "sg:website":"www.ops.org",
    "wof:name":"Career Center",
    "wof:placetype":"venue"
},
  "geometry": {"coordinates":[-95.960403,41.266998],"type":"Point"}
}