{
  "type": "Feature",
  "properties": {
    "addr:full":"13305 Birch Dr Ste 200 Omaha NE 68164",
    "addr:housenumber":"13305",
    "addr:postcode":"68164",
    "addr:street":"Birch Dr Ste 200",
    "iso:country":"US",
    "sg:address":"13305 Birch Dr Ste 200",
    "sg:city":"Omaha",
    "sg:classifiers":[
        {
            "category":"Banks & Credit Unions",
            "subcategory":"Investment Brokerage",
            "type":"Services"
        },
        {
            "category":"Banks & Credit Unions",
            "subcategory":"Financial Services",
            "type":"Services"
        }
    ],
    "sg:phone":"+1 402 391 5400",
    "sg:postcode":"68164",
    "sg:province":"NE",
    "sg:tags":[
        "planning",
        "consultant",
        "retirement",
        "planner"
    ],
    "sg:website":"http://www.ameriprise.com",
    "wof:name":"Ameriprise Financial Services Inc.",
    "wof:placetype":"venue"
},
  "geometry": {"coordinates":[-96.120015,41.291119],"type":"Point"}
}