{
  "type": "Feature",
  "properties": {
    "addr:full":"100 8th St Beaver City NE 68926",
    "addr:housenumber":"100",
    "addr:postcode":"68926",
    "addr:street":"8Th St",
    "iso:country":"US",
    "sg:address":"100 8th St",
    "sg:city":"Beaver City",
    "sg:classifiers":[
        {
            "category":"Real Estate",
            "subcategory":"Real Estate Agent",
            "type":"Services"
        }
    ],
    "sg:phone":"+1 308 268 6665",
    "sg:postcode":"68926",
    "sg:province":"NE",
    "sg:tags":[
        "authorities",
        "housing"
    ],
    "wof:name":"Beaver City Housing Authority",
    "wof:placetype":"venue"
},
  "geometry": {"coordinates":[-99.82988400000001,40.132813],"type":"Point"}
}