{
  "type": "Feature",
  "properties": {
    "iso:country":"US",
    "sg:address":"6000 W Roca Rd",
    "sg:city":"Martell",
    "sg:classifiers":[
        {
            "category":"Building & Trades",
            "subcategory":"Plumbing",
            "type":"Services"
        }
    ],
    "sg:phone":"+1 402 826 2677",
    "sg:postcode":"68404",
    "sg:province":"NE",
    "sg:tags":[
        "contractor"
    ],
    "wof:name":"Foster Plumbing Heating & AC",
    "wof:placetype":"venue"
},
  "geometry": {"coordinates":[-96.787183,40.65377],"type":"Point"}
}