{
  "type": "Feature",
  "properties": {
    "iso:country":"US",
    "sg:address":"1523 Stone St",
    "sg:city":"Falls City",
    "sg:classifiers":[
        {
            "category":"Home & Garden",
            "subcategory":"Furniture",
            "type":"Retail Goods"
        }
    ],
    "sg:phone":"+1 402 245 3912",
    "sg:postcode":"68355",
    "sg:province":"NE",
    "wof:name":"Chaney Furniture Co",
    "wof:placetype":"venue"
},
  "geometry": {"coordinates":[-95.602971,40.060508],"type":"Point"}
}