{
  "type": "Feature",
  "properties": {
    "iso:country":"US",
    "sg:address":"321 N 8th St",
    "sg:city":"Lincoln",
    "sg:classifiers":[
        {
            "category":"Professional",
            "subcategory":"Management & Consulting",
            "type":"Services"
        }
    ],
    "sg:phone":"+1 402 476 7232",
    "sg:postcode":"68508",
    "sg:province":"NE",
    "sg:tags":[
        "consultant",
        "lighting"
    ],
    "wof:name":"Light Works Studio Inc",
    "wof:placetype":"venue"
},
  "geometry": {"coordinates":[-96.710019,40.816743],"type":"Point"}
}