{
  "type": "Feature",
  "properties": {
    "iso:country":"US",
    "sg:address":"630 N Cotner Blvd",
    "sg:city":"Lincoln",
    "sg:classifiers":[
        {
            "category":"Health Services",
            "subcategory":"Doctor",
            "type":"Services"
        }
    ],
    "sg:phone":"+1 402 464 8636",
    "sg:postcode":"68505",
    "sg:province":"NE",
    "sg:tags":[
        "physician",
        "surgeon"
    ],
    "wof:name":"Ear Nose & Throat Medicine",
    "wof:placetype":"venue"
},
  "geometry": {"coordinates":[-96.63574300000001,40.820211],"type":"Point"}
}