{
  "type": "Feature",
  "properties": {
    "iso:country":"US",
    "sg:address":"116 E 6th St",
    "sg:city":"Kearney",
    "sg:classifiers":[
        {
            "category":"Building & Trades",
            "subcategory":"Cleaning & Sanitation",
            "type":"Services"
        }
    ],
    "sg:phone":"+1 308 234 9658",
    "sg:postcode":"68847",
    "sg:province":"NE",
    "sg:tags":[
        "janitor"
    ],
    "wof:name":"Yellow Van Cleaning Svc",
    "wof:placetype":"venue"
},
  "geometry": {"coordinates":[-99.080495,40.67994],"type":"Point"}
}