{
  "type": "Feature",
  "properties": {
    "iso:country":"US",
    "sg:address":"223 E 14th St",
    "sg:city":"Hastings",
    "sg:classifiers":[
        {
            "category":"Health Services",
            "subcategory":"Chiropractor",
            "type":"Services"
        }
    ],
    "sg:phone":"+1 402 462 9999",
    "sg:postcode":"68901",
    "sg:province":"NE",
    "wof:name":"Anderson Chiropractic Clinic",
    "wof:placetype":"venue"
},
  "geometry": {"coordinates":[-98.37952199999999,40.600793],"type":"Point"}
}