{
  "type": "Feature",
  "properties": {
    "addr:full":"315 W 8th St Kearney NE 68845",
    "addr:housenumber":"315",
    "addr:postcode":"68845",
    "addr:street":"W 8Th St",
    "iso:country":"US",
    "sg:address":"315 W 8th St",
    "sg:city":"Kearney",
    "sg:classifiers":[
        {
            "category":"Wholesale",
            "subcategory":"Petroleum",
            "type":"Manufacturing & Wholesale Goods"
        }
    ],
    "sg:phone":"+1 308 236 5919",
    "sg:postcode":"68845",
    "sg:province":"NE",
    "sg:tags":[
        "bulk",
        "product"
    ],
    "wof:name":"Clevenger Petroleum",
    "wof:placetype":"venue"
},
  "geometry": {"coordinates":[-99.086389,40.681953],"type":"Point"}
}