{
  "type": "Feature",
  "properties": {
    "addr:full":"429 Sherwood Dr Gretna NE 68028",
    "addr:housenumber":"429",
    "addr:postcode":"68028",
    "addr:street":"Sherwood Dr",
    "iso:country":"US",
    "sg:address":"429 Sherwood Dr",
    "sg:city":"Gretna",
    "sg:classifiers":[
        {
            "category":"Building & Trades",
            "subcategory":"Construction",
            "type":"Services"
        }
    ],
    "sg:phone":"+1 402 332 4217",
    "sg:postcode":"68028",
    "sg:province":"NE",
    "sg:tags":[
        "contractor"
    ],
    "wof:name":"Steel Ceilings Inc",
    "wof:placetype":"venue"
},
  "geometry": {"coordinates":[-96.232961,41.137614],"type":"Point"}
}