{
  "type": "Feature",
  "properties": {
    "iso:country":"US",
    "sg:address":"415 Silver St",
    "sg:city":"Oxford",
    "sg:classifiers":[
        {
            "category":"Professional",
            "subcategory":"Lawyer & Legal Services",
            "type":"Services"
        }
    ],
    "sg:phone":"+1 308 824 3816",
    "sg:postcode":"68967",
    "sg:province":"NE",
    "sg:tags":[
        "attorney"
    ],
    "wof:name":"Benjamin Law Office",
    "wof:placetype":"venue"
},
  "geometry": {"coordinates":[-99.62583100000001,40.250893],"type":"Point"}
}