{
  "type": "Feature",
  "properties": {
    "addr:full":"271 State Spur 76A Friend NE 68359",
    "addr:housenumber":"271;76a",
    "addr:postcode":"68359",
    "addr:street":"State Spur",
    "iso:country":"US",
    "sg:address":"271 State Spur 76A",
    "sg:city":"Friend",
    "sg:phone":"+1 402 947 8531",
    "sg:postcode":"68359",
    "sg:province":"NE",
    "sg:tags":[
        "farm",
        "corn",
        "soybean"
    ],
    "wof:name":"Jeff Stutzman",
    "wof:placetype":"venue"
},
  "geometry": {"coordinates":[-97.349498,40.673429],"type":"Point"}
}