{
  "type": "Feature",
  "properties": {
    "iso:country":"US",
    "sg:address":"815 Co Rd 57",
    "sg:city":"Dix",
    "sg:classifiers":[
        {
            "category":"Retail",
            "subcategory":"Repair Shop",
            "type":"Services"
        }
    ],
    "sg:phone":"+1 308 682 5671",
    "sg:postcode":"69133",
    "sg:province":"NE",
    "wof:name":"Recovery",
    "wof:placetype":"venue"
},
  "geometry": {"coordinates":[-103.509958,41.048764],"type":"Point"}
}