{
  "type": "Feature",
  "properties": {
    "addr:full":"1200 N East Ave York NE 68467",
    "addr:housenumber":"1200",
    "addr:postcode":"68467",
    "addr:street":"N East Ave",
    "iso:country":"US",
    "sg:address":"1200 N East Ave",
    "sg:city":"York",
    "sg:classifiers":[
        {
            "category":"Education",
            "subcategory":"School",
            "type":"Public Place"
        }
    ],
    "sg:phone":"+1 402 362 6655",
    "sg:postcode":"68467",
    "sg:province":"NE",
    "sg:website":"www.yorkpublic.org",
    "wof:name":"York Middle School",
    "wof:placetype":"venue"
},
  "geometry": {"coordinates":[-97.587238,40.873455],"type":"Point"}
}