{
  "type": "Feature",
  "properties": {
    "addr:full":"1465 27th Ave Columbus NE 68601",
    "addr:housenumber":"1465",
    "addr:postcode":"68601",
    "addr:street":"27Th Ave",
    "iso:country":"US",
    "sg:address":"1465 27th Ave",
    "sg:city":"Columbus",
    "sg:classifiers":[
        {
            "category":"Banks & Credit Unions",
            "subcategory":"Investment Brokerage",
            "type":"Services"
        }
    ],
    "sg:phone":"+1 402 564 4246",
    "sg:postcode":"68601",
    "sg:province":"NE",
    "sg:tags":[
        "security"
    ],
    "wof:name":"Giebelhaus Investment Svc",
    "wof:placetype":"venue"
},
  "geometry": {"coordinates":[-97.360536,41.431137],"type":"Point"}
}