{
  "type": "Feature",
  "properties": {
    "iso:country":"US",
    "sg:address":"1120 Fort Crook Rd S",
    "sg:city":"Bellevue",
    "sg:classifiers":[
        {
            "category":"Autos & Motor Vehicles",
            "subcategory":"Recreational Vehicle Sales",
            "type":"Retail Goods"
        }
    ],
    "sg:phone":"+1 402 292 1455",
    "sg:postcode":"68123",
    "sg:province":"NE",
    "sg:website":"www.apachecamper.com",
    "wof:name":"Apache Camper Center",
    "wof:placetype":"venue"
},
  "geometry": {"coordinates":[-95.927469,41.150325],"type":"Point"}
}