{
  "type": "Feature",
  "properties": {
    "iso:country":"US",
    "sg:address":"1346 Midland St",
    "sg:city":"Syracuse",
    "sg:classifiers":[
        {
            "category":"Building & Trades",
            "subcategory":"Landscaping Services",
            "type":"Services"
        }
    ],
    "sg:phone":"+1 402 782 8929",
    "sg:postcode":"68446",
    "sg:province":"NE",
    "sg:tags":[
        "lawn"
    ],
    "wof:name":"T M S",
    "wof:placetype":"venue"
},
  "geometry": {"coordinates":[-96.186117,40.665119],"type":"Point"}
}