{
  "type": "Feature",
  "properties": {
    "iso:country":"US",
    "sg:address":"1716 N 110th St",
    "sg:city":"Omaha",
    "sg:classifiers":[
        {
            "category":"Building & Trades",
            "subcategory":"Landscaping Services",
            "type":"Services"
        }
    ],
    "sg:phone":"+1 402 493 5024",
    "sg:postcode":"68154",
    "sg:province":"NE",
    "wof:name":"Father Son Lawn Service Inc",
    "wof:placetype":"venue"
},
  "geometry": {"coordinates":[-96.083468,41.277674],"type":"Point"}
}