{
  "type": "Feature",
  "properties": {
    "iso:country":"US",
    "sg:address":"1744 L St",
    "sg:city":"Lincoln",
    "sg:classifiers":[
        {
            "category":"Professional",
            "subcategory":"Research",
            "type":"Services"
        }
    ],
    "sg:phone":"+1 402 438 7503",
    "sg:postcode":"68508",
    "sg:province":"NE",
    "sg:tags":[
        "organization",
        "noncommercial"
    ],
    "wof:name":"ITR Technologies Inc",
    "wof:placetype":"venue"
},
  "geometry": {"coordinates":[-96.695807,40.810347],"type":"Point"}
}