{
  "type": "Feature",
  "properties": {
    "iso:country":"US",
    "sg:address":"2715 13th St",
    "sg:city":"Columbus",
    "sg:classifiers":[
        {
            "category":"Building & Trades",
            "subcategory":"Equipment Rental",
            "type":"Services"
        }
    ],
    "sg:phone":"+1 402 564 8383",
    "sg:postcode":"68601",
    "sg:province":"NE",
    "sg:website":"www.irwinfc.com",
    "wof:name":"Irwin Franchise Capital Corp",
    "wof:placetype":"venue"
},
  "geometry": {"coordinates":[-97.36179199999999,41.429237],"type":"Point"}
}