{
  "type": "Feature",
  "properties": {
    "iso:country":"US",
    "sg:address":"13324 Madison St",
    "sg:city":"Omaha",
    "sg:classifiers":[
        {
            "category":"Personal",
            "type":"Services"
        }
    ],
    "sg:phone":"+1 402 895 3766",
    "sg:postcode":"68137",
    "sg:province":"NE",
    "sg:tags":[
        "animal"
    ],
    "wof:name":"Vasko Family Enterprises",
    "wof:placetype":"venue"
},
  "geometry": {"coordinates":[-96.121821,41.192885],"type":"Point"}
}