{
  "type": "Feature",
  "properties": {
    "iso:country":"US",
    "sg:address":"2323 14th St",
    "sg:city":"Columbus",
    "sg:classifiers":[
        {
            "category":"Health Services",
            "subcategory":"Chiropractor",
            "type":"Services"
        }
    ],
    "sg:phone":"+1 402 564 2622",
    "sg:postcode":"68601",
    "sg:province":"NE",
    "wof:name":"Ricket Chropractic Acupuncture",
    "wof:placetype":"venue"
},
  "geometry": {"coordinates":[-97.356667,41.430159],"type":"Point"}
}