{
  "type": "Feature",
  "properties": {
    "iso:country":"US",
    "sg:address":"4000 S 56th St",
    "sg:city":"Lincoln",
    "sg:classifiers":[
        {
            "category":"Real Estate",
            "subcategory":"Real Estate Operator",
            "type":"Services"
        }
    ],
    "sg:phone":"+1 402 488 0410",
    "sg:postcode":"68506",
    "sg:province":"NE",
    "sg:tags":[
        "dwelling"
    ],
    "wof:name":"Lake Park Condominiums",
    "wof:placetype":"venue"
},
  "geometry": {"coordinates":[-96.644257,40.771156],"type":"Point"}
}