{
  "type": "Feature",
  "properties": {
    "addr:full":"3925 N 17th St Lincoln NE 68521",
    "addr:housenumber":"3925",
    "addr:postcode":"68521",
    "addr:street":"N 17Th St",
    "iso:country":"US",
    "sg:address":"3925 N 17th St",
    "sg:city":"Lincoln",
    "sg:classifiers":[
        {
            "category":"Building & Trades",
            "subcategory":"Construction",
            "type":"Services"
        }
    ],
    "sg:phone":"+1 402 476 1068",
    "sg:postcode":"68521",
    "sg:province":"NE",
    "sg:tags":[
        "contractor"
    ],
    "wof:name":"Lear Tile",
    "wof:placetype":"venue"
},
  "geometry": {"coordinates":[-96.697211,40.851904],"type":"Point"}
}