{
  "type": "Feature",
  "properties": {
    "addr:full":"5705 South 108th Street Omaha NE 68137",
    "addr:housenumber":"5705",
    "addr:postcode":"68137",
    "addr:street":"South 108Th Street",
    "iso:country":"US",
    "sg:address":"5705 South 108th Street",
    "sg:city":"Omaha",
    "sg:classifiers":[
        {
            "category":"Professional",
            "subcategory":"Computer Services",
            "type":"Services"
        }
    ],
    "sg:postcode":"68137",
    "sg:province":"NE",
    "sg:website":"http://www.gogameplan.com",
    "wof:name":"GamePlan Technologies",
    "wof:placetype":"venue"
},
  "geometry": {"coordinates":[-96.08132999999999,41.201537],"type":"Point"}
}