{
  "type": "Feature",
  "properties": {
    "iso:country":"US",
    "sg:address":"1020 1st St",
    "sg:city":"Crawford",
    "sg:classifiers":[
        {
            "category":"Food & Beverages",
            "subcategory":"Candy",
            "type":"Retail Goods"
        }
    ],
    "sg:phone":"+1 308 665 2271",
    "sg:postcode":"69339",
    "sg:province":"NE",
    "wof:name":"Candy Store",
    "wof:placetype":"venue"
},
  "geometry": {"coordinates":[-103.41627699999999,42.679691],"type":"Point"}
}