{
  "type": "Feature",
  "properties": {
    "iso:country":"US",
    "sg:address":"2905 State Hwy 40",
    "sg:city":"Kearney",
    "sg:classifiers":[
        {
            "category":"Building & Trades",
            "subcategory":"Construction",
            "type":"Services"
        }
    ],
    "sg:phone":"+1 308 233 5583",
    "sg:postcode":"68845",
    "sg:province":"NE",
    "sg:tags":[
        "general",
        "contractor"
    ],
    "wof:name":"Superior Foundations Inc",
    "wof:placetype":"venue"
},
  "geometry": {"coordinates":[-99.12115900000001,40.764744],"type":"Point"}
}