{
  "type": "Feature",
  "properties": {
    "addr:full":"7301 Walker Ave Lincoln NE 68507",
    "addr:housenumber":"7301",
    "addr:postcode":"68507",
    "addr:street":"Walker Ave",
    "iso:country":"US",
    "sg:address":"7301 Walker Ave",
    "sg:city":"Lincoln",
    "sg:classifiers":[
        {
            "category":"Building & Trades",
            "subcategory":"Construction",
            "type":"Services"
        }
    ],
    "sg:phone":"+1 402 432 3110",
    "sg:postcode":"68507",
    "sg:province":"NE",
    "sg:tags":[
        "nonresidential"
    ],
    "wof:name":"Cleveland Construction",
    "wof:placetype":"venue"
},
  "geometry": {"coordinates":[-96.62115300000001,40.837236],"type":"Point"}
}