{
  "type": "Feature",
  "properties": {
    "iso:country":"US",
    "sg:address":"1265 S Cotner Blvd",
    "sg:city":"Lincoln",
    "sg:classifiers":[
        {
            "category":"Shopping",
            "type":"Retail Goods"
        }
    ],
    "sg:phone":"+1 402 477 7877",
    "sg:postcode":"68510",
    "sg:province":"NE",
    "sg:tags":[
        "cat",
        "gift",
        "for",
        "supply"
    ],
    "wof:name":"All About Cats Inc",
    "wof:placetype":"venue"
},
  "geometry": {"coordinates":[-96.650583,40.799962],"type":"Point"}
}