{
  "type": "Feature",
  "properties": {
    "iso:country":"US",
    "sg:address":"308 N Locust St",
    "sg:city":"Grand Island",
    "sg:classifiers":[
        {
            "category":"Professional",
            "subcategory":"Management & Consulting",
            "type":"Services"
        }
    ],
    "sg:phone":"+1 308 381 7500",
    "sg:postcode":"68801",
    "sg:province":"NE",
    "sg:tags":[
        "development",
        "economic",
        "agency"
    ],
    "wof:name":"G I Area Economic Development",
    "wof:placetype":"venue"
},
  "geometry": {"coordinates":[-98.341421,40.925699],"type":"Point"}
}