{
  "type": "Feature",
  "properties": {
    "iso:country":"US",
    "sg:address":"5211 Calvert St",
    "sg:city":"Lincoln",
    "sg:classifiers":[
        {
            "category":"Social Services",
            "subcategory":"Adult Care",
            "type":"Services"
        }
    ],
    "sg:phone":"+1 402 483 4504",
    "sg:postcode":"68506",
    "sg:province":"NE",
    "sg:tags":[
        "residential"
    ],
    "wof:name":"Union Manor",
    "wof:placetype":"venue"
},
  "geometry": {"coordinates":[-96.647696,40.776933],"type":"Point"}
}