{
  "type": "Feature",
  "properties": {
    "addr:full":"7925 Pasadena Ave Omaha NE 68124",
    "addr:housenumber":"7925",
    "addr:postcode":"68124",
    "addr:street":"Pasadena Ave",
    "iso:country":"US",
    "sg:address":"7925 Pasadena Ave",
    "sg:city":"Omaha",
    "sg:classifiers":[
        {
            "category":"Professional",
            "subcategory":"Business Services",
            "type":"Services"
        }
    ],
    "sg:phone":"+1 402 651 2474",
    "sg:postcode":"68124",
    "sg:province":"NE",
    "wof:name":"Inspirit Art & Design",
    "wof:placetype":"venue"
},
  "geometry": {"coordinates":[-96.037594,41.225264],"type":"Point"}
}