{
  "type": "Feature",
  "properties": {
    "addr:full":"14738 Ames Ave Omaha NE 68116",
    "addr:housenumber":"14738",
    "addr:postcode":"68116",
    "addr:street":"Ames Ave",
    "iso:country":"US",
    "sg:address":"14738 Ames Ave",
    "sg:city":"Omaha",
    "sg:classifiers":[
        {
            "category":"Retail",
            "subcategory":"Animal Services",
            "type":"Services"
        },
        {
            "category":"Building & Trades",
            "subcategory":"Landscaping Services",
            "type":"Services"
        }
    ],
    "sg:phone":"+1 402 554 1515",
    "sg:postcode":"68116",
    "sg:province":"NE",
    "sg:tags":[
        "pet"
    ],
    "wof:name":"Canine Waste Removal Company",
    "wof:placetype":"venue"
},
  "geometry": {"coordinates":[-96.14604199999999,41.298984],"type":"Point"}
}