{
  "type": "Feature",
  "properties": {
    "iso:country":"US",
    "sg:address":"13911 Gold Cir",
    "sg:city":"Omaha",
    "sg:classifiers":[
        {
            "category":"Professional",
            "subcategory":"Business Services",
            "type":"Services"
        }
    ],
    "sg:phone":"+1 402 758 0041",
    "sg:postcode":"68144",
    "sg:province":"NE",
    "wof:name":"Tom Denham & Assoc",
    "wof:placetype":"venue"
},
  "geometry": {"coordinates":[-96.13057000000001,41.234905],"type":"Point"}
}