{
  "type": "Feature",
  "properties": {
    "iso:country":"US",
    "sg:address":"20701 Pflug Rd",
    "sg:city":"Gretna",
    "sg:phone":"+1 402 332 5941",
    "sg:postcode":"68028",
    "sg:province":"NE",
    "sg:tags":[
        "wheat",
        "farm",
        "corn",
        "crop",
        "field",
        "soybean"
    ],
    "wof:name":"Koke John",
    "wof:placetype":"venue"
},
  "geometry": {"coordinates":[-96.238962,41.0743],"type":"Point"}
}