{
  "type": "Feature",
  "properties": {
    "addr:full":"2109 State Hwy 2 Lincoln NE 68502",
    "addr:housenumber":"2109",
    "addr:postcode":"68502",
    "addr:street":"State Hwy 2",
    "iso:country":"US",
    "sg:address":"2109 State Hwy 2",
    "sg:city":"Lincoln",
    "sg:classifiers":[
        {
            "category":"Bars & Pubs",
            "type":"Food & Drink"
        }
    ],
    "sg:phone":"+1 402 421 2186",
    "sg:postcode":"68502",
    "sg:province":"NE",
    "sg:tags":[
        "drinking"
    ],
    "wof:name":"Silver Fox",
    "wof:placetype":"venue"
},
  "geometry": {"coordinates":[-96.70715800000001,40.789218],"type":"Point"}
}