{
  "type": "Feature",
  "properties": {
    "iso:country":"US",
    "sg:address":"1633 13th St",
    "sg:city":"Mitchell",
    "sg:classifiers":[
        {
            "category":"Social Services",
            "subcategory":"Child Care",
            "type":"Services"
        }
    ],
    "sg:phone":"+1 308 623 2999",
    "sg:postcode":"69357",
    "sg:province":"NE",
    "sg:tags":[
        "day"
    ],
    "wof:name":"Golden Child Development Ctr",
    "wof:placetype":"venue"
},
  "geometry": {"coordinates":[-103.810231,41.940208],"type":"Point"}
}