{
  "type": "Feature",
  "properties": {
    "iso:country":"US",
    "sg:address":"1825 10th St",
    "sg:city":"Gering",
    "sg:classifiers":[
        {
            "category":"Government",
            "subcategory":"Office",
            "type":"Public Place"
        }
    ],
    "sg:phone":"+1 308 436 6636",
    "sg:postcode":"69341",
    "sg:province":"NE",
    "sg:tags":[
        "county",
        "program",
        "health"
    ],
    "sg:website":"www.scottsbluffcounty.org",
    "wof:name":"Scotts Bluff County Health Ofc",
    "wof:placetype":"venue"
},
  "geometry": {"coordinates":[-103.660447,41.827593],"type":"Point"}
}