{
  "type": "Feature",
  "properties": {
    "iso:country":"US",
    "sg:address":"1922 Colfax St",
    "sg:city":"Schuyler",
    "sg:classifiers":[
        {
            "category":"Organizations",
            "subcategory":"Religious Organization",
            "type":"Services"
        }
    ],
    "sg:phone":"+1 402 352 3560",
    "sg:postcode":"68661",
    "sg:province":"NE",
    "sg:tags":[
        "church"
    ],
    "wof:name":"Christ United Methodist",
    "wof:placetype":"venue"
},
  "geometry": {"coordinates":[-97.059596,41.457526],"type":"Point"}
}