{
  "type": "Feature",
  "properties": {
    "addr:full":"88181 State Hwy 14 Verdigre NE 68783",
    "addr:housenumber":"88181",
    "addr:postcode":"68783",
    "addr:street":"State Hwy 14 Verdigre Ne",
    "iso:country":"US",
    "sg:address":"88181 State Hwy 14",
    "sg:city":"Verdigre",
    "sg:classifiers":[
        {
            "category":"Social Services",
            "subcategory":"Child Care",
            "type":"Services"
        }
    ],
    "sg:phone":"+1 402 668 2692",
    "sg:postcode":"68783",
    "sg:province":"NE",
    "sg:tags":[
        "day"
    ],
    "wof:name":"Wesche Ladonna",
    "wof:placetype":"venue"
},
  "geometry": {"coordinates":[-98.032838,42.611207],"type":"Point"}
}