{
  "type": "Feature",
  "properties": {
    "iso:country":"US",
    "sg:address":"1040 N Main St",
    "sg:city":"North Bend",
    "sg:classifiers":[
        {
            "category":"Retail",
            "subcategory":"Funeral Services",
            "type":"Services"
        }
    ],
    "sg:phone":"+1 402 652 8159",
    "sg:postcode":"68649",
    "sg:province":"NE",
    "sg:tags":[
        "director"
    ],
    "wof:name":"Moser Memorial Chapel",
    "wof:placetype":"venue"
},
  "geometry": {"coordinates":[-96.780311,41.465872],"type":"Point"}
}