{
  "type": "Feature",
  "properties": {
    "iso:country":"US",
    "sg:address":"250094 Robertson Rd",
    "sg:city":"Scottsbluff",
    "sg:classifiers":[
        {
            "category":"Airport",
            "type":"Transportation"
        }
    ],
    "sg:phone":"+1 308 635 4941",
    "sg:postcode":"69361",
    "sg:province":"NE",
    "wof:name":"Scotts Bluff County Airport",
    "wof:placetype":"venue"
},
  "geometry": {"coordinates":[-103.59498600000001,41.866246],"type":"Point"}
}