{
  "type": "Feature",
  "properties": {
    "addr:full":"3268 Branched Oak Rd Staplehurst NE 68439",
    "addr:housenumber":"3268",
    "addr:postcode":"68439",
    "addr:street":"Branched Oak Rd",
    "iso:country":"US",
    "sg:address":"3268 Branched Oak Rd",
    "sg:city":"Staplehurst",
    "sg:classifiers":[
        {
            "category":"Real Estate",
            "subcategory":"Real Estate Operator",
            "type":"Services"
        }
    ],
    "sg:phone":"+1 402 535 2274",
    "sg:postcode":"68439",
    "sg:province":"NE",
    "sg:tags":[
        "property",
        "lessor"
    ],
    "wof:name":"Gerald Hegeholz",
    "wof:placetype":"venue"
},
  "geometry": {"coordinates":[-97.162998,40.972785],"type":"Point"}
}