{
  "type": "Feature",
  "properties": {
    "iso:country":"US",
    "sg:address":"3001 S 144th St",
    "sg:city":"Omaha",
    "sg:classifiers":[
        {
            "category":"Ice Cream",
            "type":"Food & Drink"
        }
    ],
    "sg:menulink":"http://www.allmenus.com/ne/omaha/167762-dairy-queen/menu/",
    "sg:phone":"+1 402 697 0155",
    "sg:postcode":"68144",
    "sg:province":"NE",
    "sg:tags":[
        "burger",
        "american"
    ],
    "wof:name":"Dairy Queen",
    "wof:placetype":"venue"
},
  "geometry": {"coordinates":[-96.13826400000001,41.2291],"type":"Point"}
}