{
  "type": "Feature",
  "properties": {
    "iso:country":"US",
    "sg:address":"200 E 23rd St",
    "sg:city":"Yankton",
    "sg:classifiers":[
        {
            "category":"Building & Trades",
            "subcategory":"Construction",
            "type":"Services"
        }
    ],
    "sg:phone":"+1 605 665 6745",
    "sg:postcode":"57078",
    "sg:province":"NE",
    "sg:tags":[
        "contractor"
    ],
    "wof:name":"Goetz Drywall",
    "wof:placetype":"venue"
},
  "geometry": {"coordinates":[-97.390413,42.894284],"type":"Point"}
}