{
  "type": "Feature",
  "properties": {
    "iso:country":"US",
    "sg:address":"122 S 5th St",
    "sg:city":"Norfolk",
    "sg:classifiers":[
        {
            "category":"Professional",
            "type":"Services"
        }
    ],
    "sg:phone":"+1 402 634 2354",
    "sg:postcode":"68701",
    "sg:province":"NE",
    "wof:name":"Erics Tattoos",
    "wof:placetype":"venue"
},
  "geometry": {"coordinates":[-97.413855,42.032387],"type":"Point"}
}