{
  "type": "Feature",
  "properties": {
    "iso:country":"US",
    "sg:address":"324 Greenhouse Ct",
    "sg:city":"Hastings",
    "sg:classifiers":[
        {
            "category":"Education",
            "subcategory":"School",
            "type":"Public Place"
        }
    ],
    "sg:phone":"+1 402 463 0571",
    "sg:postcode":"68901",
    "sg:province":"NE",
    "sg:tags":[
        "study",
        "mycology"
    ],
    "wof:name":"Sne Tech",
    "wof:placetype":"venue"
},
  "geometry": {"coordinates":[-98.36614899999999,40.586944],"type":"Point"}
}