{
  "type": "Feature",
  "properties": {
    "addr:full":"3139 N Hill Rd Lincoln NE 68504",
    "addr:housenumber":"3139",
    "addr:postcode":"68504",
    "addr:street":"N Hill Rd",
    "iso:country":"US",
    "sg:address":"3139 N Hill Rd",
    "sg:city":"Lincoln",
    "sg:classifiers":[
        {
            "category":"Shopping",
            "subcategory":"Computers & Home Electronics",
            "type":"Retail Goods"
        }
    ],
    "sg:phone":"+1 402 477 4105",
    "sg:postcode":"68504",
    "sg:province":"NE",
    "sg:tags":[
        "equipment",
        "dealer"
    ],
    "sg:website":"www.buysolid.com",
    "wof:name":"Solid Computer Systmes",
    "wof:placetype":"venue"
},
  "geometry": {"coordinates":[-96.67905500000001,40.864275],"type":"Point"}
}