{
  "type": "Feature",
  "properties": {
    "addr:full":"9615 Ida St Omaha NE 68122",
    "addr:housenumber":"9615",
    "addr:postcode":"68122",
    "addr:street":"Ida St",
    "iso:country":"US",
    "sg:address":"9615 Ida St",
    "sg:city":"Omaha",
    "sg:classifiers":[
        {
            "category":"Professional",
            "subcategory":"Lawyer & Legal Services",
            "type":"Services"
        }
    ],
    "sg:phone":"+1 402 345 9449",
    "sg:postcode":"68122",
    "sg:province":"NE",
    "sg:tags":[
        "attorney"
    ],
    "wof:name":"Blake & Uhlig",
    "wof:placetype":"venue"
},
  "geometry": {"coordinates":[-96.059394,41.321106],"type":"Point"}
}