{
  "type": "Feature",
  "properties": {
    "iso:country":"US",
    "sg:address":"17 E 21st St",
    "sg:city":"Kearney",
    "sg:classifiers":[
        {
            "category":"Retail",
            "subcategory":"Repair Shop",
            "type":"Services"
        }
    ],
    "sg:phone":"+1 308 338 8463",
    "sg:postcode":"68847",
    "sg:province":"NE",
    "sg:tags":[
        "clocks",
        "parts"
    ],
    "wof:name":"Time Center",
    "wof:placetype":"venue"
},
  "geometry": {"coordinates":[-99.081597,40.696503],"type":"Point"}
}