{
  "type": "Feature",
  "properties": {
    "iso:country":"US",
    "sg:address":"210 S 17th St",
    "sg:city":"Norfolk",
    "sg:classifiers":[
        {
            "category":"Social Services",
            "subcategory":"Child Care",
            "type":"Services"
        }
    ],
    "sg:phone":"+1 402 371 2658",
    "sg:postcode":"68701",
    "sg:province":"NE",
    "sg:tags":[
        "day"
    ],
    "wof:name":"Beutler Deborah Day Care",
    "wof:placetype":"venue"
},
  "geometry": {"coordinates":[-97.432727,42.031239],"type":"Point"}
}