{
  "type": "Feature",
  "properties": {
    "addr:full":"12116 N 156th Ave Bennington NE 68007",
    "addr:housenumber":"12116",
    "addr:postcode":"68007",
    "addr:street":"N 156Th Ave",
    "iso:country":"US",
    "sg:address":"12116 N 156th Ave",
    "sg:city":"Bennington",
    "sg:classifiers":[
        {
            "category":"Real Estate",
            "subcategory":"Real Estate Operator",
            "type":"Services"
        }
    ],
    "sg:phone":"+1 402 238 2142",
    "sg:postcode":"68007",
    "sg:province":"NE",
    "sg:tags":[
        "property",
        "lessor"
    ],
    "wof:name":"Lester Logemann",
    "wof:placetype":"venue"
},
  "geometry": {"coordinates":[-96.160149,41.370591],"type":"Point"}
}