{
  "type": "Feature",
  "properties": {
    "addr:full":"310 Brentwood Dr Norfolk NE 68701",
    "addr:housenumber":"310",
    "addr:postcode":"68701",
    "addr:street":"Brentwood Dr",
    "iso:country":"US",
    "sg:address":"310 Brentwood Dr",
    "sg:city":"Norfolk",
    "sg:classifiers":[
        {
            "category":"Retail",
            "subcategory":"Portrait Studio",
            "type":"Services"
        }
    ],
    "sg:phone":"+1 402 379 3911",
    "sg:postcode":"68701",
    "sg:province":"NE",
    "sg:tags":[
        "photographer"
    ],
    "wof:name":"First Impressions Photography",
    "wof:placetype":"venue"
},
  "geometry": {"coordinates":[-97.354823,42.05183],"type":"Point"}
}