{
  "type": "Feature",
  "properties": {
    "iso:country":"US",
    "sg:address":"305 9th Ave",
    "sg:city":"Scottsbluff",
    "sg:classifiers":[
        {
            "category":"Recreation",
            "type":"Entertainment"
        }
    ],
    "sg:phone":"+1 308 632 0812",
    "sg:postcode":"69361",
    "sg:province":"NE",
    "sg:tags":[
        "amusement"
    ],
    "wof:name":"S S Classics Motorsports",
    "wof:placetype":"venue"
},
  "geometry": {"coordinates":[-103.650845,41.850558],"type":"Point"}
}