{
  "type": "Feature",
  "properties": {
    "iso:country":"US",
    "sg:address":"209 W 10th St",
    "sg:city":"Cozad",
    "sg:classifiers":[
        {
            "category":"Retail",
            "subcategory":"Laundry & Dry Cleaning",
            "type":"Services"
        }
    ],
    "sg:phone":"+1 308 784 3708",
    "sg:postcode":"69130",
    "sg:province":"NE",
    "sg:tags":[
        "cleaners",
        "rug",
        "carpet"
    ],
    "wof:name":"Cozad Carpet & Upholstery Clea",
    "wof:placetype":"venue"
},
  "geometry": {"coordinates":[-99.98853699999999,40.861547],"type":"Point"}
}