{
  "type": "Feature",
  "properties": {
    "iso:country":"US",
    "sg:address":"818 S Kindschuh St",
    "sg:city":"West Point",
    "sg:classifiers":[
        {
            "category":"Education",
            "subcategory":"Special Training",
            "type":"Public Place"
        }
    ],
    "sg:phone":"+1 402 372 3609",
    "sg:postcode":"68788",
    "sg:province":"NE",
    "wof:name":"Pointmasters",
    "wof:placetype":"venue"
},
  "geometry": {"coordinates":[-96.70899900000001,41.83247],"type":"Point"}
}