{
  "type": "Feature",
  "properties": {
    "addr:full":"1521 B St Aurora NE 68818",
    "addr:housenumber":"1521",
    "addr:postcode":"68818",
    "addr:street":"B St",
    "iso:country":"US",
    "sg:address":"1521 B St",
    "sg:city":"Aurora",
    "sg:classifiers":[
        {
            "category":"Organizations",
            "subcategory":"Religious Organization",
            "type":"Services"
        }
    ],
    "sg:phone":"+1 402 694 2347",
    "sg:postcode":"68818",
    "sg:province":"NE",
    "sg:tags":[
        "church"
    ],
    "wof:name":"LDS Missionaries",
    "wof:placetype":"venue"
},
  "geometry": {"coordinates":[-97.997696,40.858797],"type":"Point"}
}