{
  "type": "Feature",
  "properties": {
    "iso:country":"US",
    "sg:address":"4009 6th Ave",
    "sg:city":"Kearney",
    "sg:classifiers":[
        {
            "category":"Professional",
            "subcategory":"Management & Consulting",
            "type":"Services"
        }
    ],
    "sg:phone":"+1 308 338 8606",
    "sg:postcode":"68845",
    "sg:province":"NE",
    "wof:name":"Macro International Inc",
    "wof:placetype":"venue"
},
  "geometry": {"coordinates":[-99.089417,40.714856],"type":"Point"}
}