{
  "type": "Feature",
  "properties": {
    "iso:country":"US",
    "sg:address":"20643 Co Rd 12",
    "sg:city":"Mitchell",
    "sg:classifiers":[
        {
            "category":"Farming",
            "subcategory":"Livestock Farm",
            "type":"Manufacturing & Wholesale Goods"
        }
    ],
    "sg:phone":"+1 308 623 1386",
    "sg:postcode":"69357",
    "sg:province":"NE",
    "sg:tags":[
        "beef",
        "feedlot",
        "cattle"
    ],
    "wof:name":"M Gompert Farms",
    "wof:placetype":"venue"
},
  "geometry": {"coordinates":[-103.85307,41.978604],"type":"Point"}
}