{
  "type": "Feature",
  "properties": {
    "addr:full":"215 Fort Kearney Rd Grand Island NE 68801",
    "addr:housenumber":"215",
    "addr:postcode":"68801",
    "addr:street":"Fort Kearney Rd",
    "iso:country":"US",
    "sg:address":"215 Fort Kearney Rd",
    "sg:city":"Grand Island",
    "sg:classifiers":[
        {
            "category":"Building & Trades",
            "subcategory":"Plumbing",
            "type":"Services"
        }
    ],
    "sg:phone":"+1 308 381 4500",
    "sg:postcode":"68801",
    "sg:province":"NE",
    "sg:tags":[
        "plumbing",
        "contractor"
    ],
    "wof:name":"Eberl Plumbing & Drain",
    "wof:placetype":"venue"
},
  "geometry": {"coordinates":[-98.246679,40.949303],"type":"Point"}
}