{
  "type": "Feature",
  "properties": {
    "iso:country":"US",
    "sg:address":"13211 Chandler Rd",
    "sg:city":"Omaha",
    "sg:classifiers":[
        {
            "category":"Home & Garden",
            "subcategory":"Building Materials",
            "type":"Retail Goods"
        },
        {
            "category":"Building & Trades",
            "subcategory":"Construction",
            "type":"Services"
        }
    ],
    "sg:phone":"+1 402 403 4322",
    "sg:postcode":"68138",
    "sg:province":"NE",
    "sg:tags":[
        "granite",
        "top",
        "counter",
        "tile-contractors"
    ],
    "sg:website":"http://www.katelotile.com",
    "wof:name":"Kate-Lo-Tile & Stone Showroom",
    "wof:placetype":"venue"
},
  "geometry": {"coordinates":[-96.119858,41.182464],"type":"Point"}
}