{
  "type": "Feature",
  "properties": {
    "iso:country":"US",
    "sg:address":"43711 Rd 771",
    "sg:city":"Eddyville",
    "sg:phone":"+1 308 858 4697",
    "sg:postcode":"68834",
    "sg:province":"NE",
    "sg:tags":[
        "farm",
        "wheat"
    ],
    "wof:name":"Bayne R USS",
    "wof:placetype":"venue"
},
  "geometry": {"coordinates":[-99.69054199999999,41.002875],"type":"Point"}
}