{
  "type": "Feature",
  "properties": {
    "iso:country":"US",
    "sg:address":"839 S 1st St",
    "sg:city":"Hebron",
    "sg:classifiers":[
        {
            "category":"Building & Trades",
            "subcategory":"Construction",
            "type":"Services"
        }
    ],
    "sg:phone":"+1 402 768 6157",
    "sg:postcode":"68370",
    "sg:province":"NE",
    "sg:tags":[
        "contractor"
    ],
    "wof:name":"Sterba Welding Shop",
    "wof:placetype":"venue"
},
  "geometry": {"coordinates":[-97.594942,40.158808],"type":"Point"}
}