{
  "type": "Feature",
  "properties": {
    "iso:country":"US",
    "sg:address":"71075 578th Ave",
    "sg:city":"Diller",
    "sg:phone":"+1 402 793 5595",
    "sg:postcode":"68342",
    "sg:province":"NE",
    "sg:tags":[
        "farm",
        "wheat",
        "soybean"
    ],
    "wof:name":"Weers Angus Farm",
    "wof:placetype":"venue"
},
  "geometry": {"coordinates":[-96.991663,40.127841],"type":"Point"}
}