{
  "type": "Feature",
  "properties": {
    "iso:country":"US",
    "sg:address":"3540 Cleveland Ave",
    "sg:city":"Lincoln",
    "sg:classifiers":[
        {
            "category":"Manufacturing",
            "subcategory":"Apparel",
            "type":"Manufacturing & Wholesale Goods"
        }
    ],
    "sg:phone":"+1 402 467 5255",
    "sg:postcode":"68504",
    "sg:province":"NE",
    "sg:tags":[
        "tarpaulin"
    ],
    "wof:name":"B C Tarps & Custom Covers",
    "wof:placetype":"venue"
},
  "geometry": {"coordinates":[-96.669648,40.841384],"type":"Point"}
}