{
  "type": "Feature",
  "properties": {
    "addr:full":"3672 H Rd Dunbar NE 68346",
    "addr:housenumber":"3672 h",
    "addr:postcode":"68346",
    "addr:street":"Rd",
    "iso:country":"US",
    "sg:address":"3672 H Rd",
    "sg:city":"Dunbar",
    "sg:phone":"+1 402 269 2616",
    "sg:postcode":"68346",
    "sg:province":"NE",
    "sg:tags":[
        "farm",
        "corn"
    ],
    "wof:name":"Rudolph John",
    "wof:placetype":"venue"
},
  "geometry": {"coordinates":[-96.116821,40.682732],"type":"Point"}
}