{
  "type": "Feature",
  "properties": {
    "addr:full":"3014 N 102nd St Omaha NE 68134",
    "addr:housenumber":"3014",
    "addr:postcode":"68134",
    "addr:street":"N 102Nd St",
    "iso:country":"US",
    "sg:address":"3014 N 102nd St",
    "sg:city":"Omaha",
    "sg:classifiers":[
        {
            "category":"Personal",
            "subcategory":"Beauty Salon",
            "type":"Services"
        }
    ],
    "sg:phone":"+1 402 571 9111",
    "sg:postcode":"68134",
    "sg:province":"NE",
    "sg:tags":[
        "shop"
    ],
    "wof:name":"Sculptured Nails Training Ctr",
    "wof:placetype":"venue"
},
  "geometry": {"coordinates":[-96.07192999999999,41.286507],"type":"Point"}
}