{
  "type": "Feature",
  "properties": {
    "iso:country":"US",
    "sg:address":"1525 N Garfield St",
    "sg:city":"Fremont",
    "sg:classifiers":[
        {
            "category":"Shopping",
            "subcategory":"Shoes",
            "type":"Retail Goods"
        }
    ],
    "sg:phone":"+1 402 727 4370",
    "sg:postcode":"68025",
    "sg:province":"NE",
    "wof:name":"Meldisco K-M Fremont Neb Inc",
    "wof:placetype":"venue"
},
  "geometry": {"coordinates":[-96.47924999999999,41.442096],"type":"Point"}
}