{
  "type": "Feature",
  "properties": {
    "iso:country":"US",
    "sg:address":"7813 Molokai Dr",
    "sg:city":"Papillion",
    "sg:classifiers":[
        {
            "category":"Banks & Credit Unions",
            "subcategory":"Financial Services",
            "type":"Services"
        }
    ],
    "sg:phone":"+1 402 592 8667",
    "sg:postcode":"68046",
    "sg:province":"NE",
    "sg:tags":[
        "broker",
        "mortgage"
    ],
    "wof:name":"Quaestor Capital Funding",
    "wof:placetype":"venue"
},
  "geometry": {"coordinates":[-96.036499,41.0732],"type":"Point"}
}