{
  "type": "Feature",
  "properties": {
    "iso:country":"US",
    "sg:address":"105 W 9th St",
    "sg:city":"Wood River",
    "sg:classifiers":[
        {
            "category":"Manufacturing",
            "subcategory":"Printing",
            "type":"Manufacturing & Wholesale Goods"
        }
    ],
    "sg:phone":"+1 308 583 2241",
    "sg:postcode":"68883",
    "sg:province":"NE",
    "sg:tags":[
        "newspaper"
    ],
    "wof:name":"Wood River Sunbeam",
    "wof:placetype":"venue"
},
  "geometry": {"coordinates":[-98.60302299999999,40.820528],"type":"Point"}
}