{
  "type": "Feature",
  "properties": {
    "addr:full":"4242 Cornhusker Hwy Lincoln NE 68504",
    "addr:housenumber":"4242",
    "addr:postcode":"68504",
    "addr:street":"Cornhusker Hwy",
    "iso:country":"US",
    "sg:address":"4242 Cornhusker Hwy",
    "sg:city":"Lincoln",
    "sg:classifiers":[
        {
            "category":"Building & Trades",
            "subcategory":"Construction",
            "type":"Services"
        }
    ],
    "sg:phone":"+1 402 466 9280",
    "sg:postcode":"68504",
    "sg:province":"NE",
    "sg:tags":[
        "excavation",
        "excavating",
        "contractor",
        "grading"
    ],
    "wof:name":"Irons Grading Inc",
    "wof:placetype":"venue"
},
  "geometry": {"coordinates":[-96.659356,40.848644],"type":"Point"}
}