{
  "type": "Feature",
  "properties": {
    "iso:country":"US",
    "sg:address":"1242 Pelican Bay Pl",
    "sg:city":"Lincoln",
    "sg:classifiers":[
        {
            "category":"Building & Trades",
            "subcategory":"Construction",
            "type":"Services"
        }
    ],
    "sg:phone":"+1 402 730 7342",
    "sg:postcode":"68528",
    "sg:province":"NE",
    "sg:tags":[
        "residential",
        "apartment",
        "commercial",
        "construct"
    ],
    "wof:name":"Moser M R Construction",
    "wof:placetype":"venue"
},
  "geometry": {"coordinates":[-96.735026,40.829363],"type":"Point"}
}