{
  "type": "Feature",
  "properties": {
    "iso:country":"US",
    "sg:address":"926 P St",
    "sg:city":"Lincoln",
    "sg:classifiers":[
        {
            "category":"Manufacturing",
            "subcategory":"Printing",
            "type":"Manufacturing & Wholesale Goods"
        }
    ],
    "sg:phone":"+1 402 473 7153",
    "sg:postcode":"68508",
    "sg:province":"NE",
    "sg:tags":[
        "newspaper"
    ],
    "wof:name":"Neighborhood Extra",
    "wof:placetype":"venue"
},
  "geometry": {"coordinates":[-96.70733300000001,40.814828],"type":"Point"}
}