{
  "type": "Feature",
  "properties": {
    "iso:country":"US",
    "sg:address":"349 S Main St",
    "sg:city":"Fremont",
    "sg:classifiers":[
        {
            "category":"Recreation",
            "type":"Entertainment"
        }
    ],
    "sg:phone":"+1 402 727 0393",
    "sg:postcode":"68025",
    "sg:province":"NE",
    "sg:tags":[
        "amusement"
    ],
    "wof:name":"Slots O Fun",
    "wof:placetype":"venue"
},
  "geometry": {"coordinates":[-96.496646,41.42725],"type":"Point"}
}