{
  "type": "Feature",
  "properties": {
    "iso:country":"US",
    "sg:address":"1653 Colfax St",
    "sg:city":"Blair",
    "sg:classifiers":[
        {
            "category":"Social Services",
            "subcategory":"Child Care",
            "type":"Services"
        }
    ],
    "sg:phone":"+1 402 426 2253",
    "sg:postcode":"68008",
    "sg:province":"NE",
    "sg:tags":[
        "kindergarten",
        "academic",
        "school"
    ],
    "wof:name":"Blair Pre-School",
    "wof:placetype":"venue"
},
  "geometry": {"coordinates":[-96.137156,41.540653],"type":"Point"}
}