{
  "type": "Feature",
  "properties": {
    "iso:country":"US",
    "sg:address":"140 S Jefferson St",
    "sg:city":"Bruning",
    "sg:classifiers":[
        {
            "category":"Building & Trades",
            "subcategory":"Construction",
            "type":"Services"
        }
    ],
    "sg:phone":"+1 402 353 2245",
    "sg:postcode":"68322",
    "sg:province":"NE",
    "sg:tags":[
        "general",
        "contractor"
    ],
    "wof:name":"Krest Contractors Inc",
    "wof:placetype":"venue"
},
  "geometry": {"coordinates":[-97.564262,40.335763],"type":"Point"}
}