{
  "type": "Feature",
  "properties": {
    "addr:full":"5200 N 20th St Lincoln NE 68521",
    "addr:housenumber":"5200",
    "addr:postcode":"68521",
    "addr:street":"N 20Th St",
    "iso:country":"US",
    "sg:address":"5200 N 20th St",
    "sg:city":"Lincoln",
    "sg:classifiers":[
        {
            "category":"Building & Trades",
            "subcategory":"Construction",
            "type":"Services"
        }
    ],
    "sg:phone":"+1 402 438 6776",
    "sg:postcode":"68521",
    "sg:province":"NE",
    "sg:tags":[
        "contractor"
    ],
    "wof:name":"Rgr Contracting",
    "wof:placetype":"venue"
},
  "geometry": {"coordinates":[-96.69127899999999,40.864145],"type":"Point"}
}