{
  "type": "Feature",
  "properties": {
    "addr:full":"319 Grand Ave Seward NE 68434",
    "addr:housenumber":"319",
    "addr:postcode":"68434",
    "addr:street":"Grand Ave",
    "iso:country":"US",
    "sg:address":"319 Grand Ave",
    "sg:city":"Seward",
    "sg:classifiers":[
        {
            "category":"Autos & Motor Vehicles",
            "subcategory":"Auto Supplies",
            "type":"Retail Goods"
        }
    ],
    "sg:phone":"+1 402 643 4135",
    "sg:postcode":"68434",
    "sg:province":"NE",
    "sg:tags":[
        "tire"
    ],
    "wof:name":"Tire Mart",
    "wof:placetype":"venue"
},
  "geometry": {"coordinates":[-97.088447,40.910431],"type":"Point"}
}