{
  "type": "Feature",
  "properties": {
    "addr:full":"2211 Devonshire Dr Lincoln NE 68506",
    "addr:housenumber":"2211",
    "addr:postcode":"68506",
    "addr:street":"Devonshire Dr",
    "iso:country":"US",
    "sg:address":"2211 Devonshire Dr",
    "sg:city":"Lincoln",
    "sg:classifiers":[
        {
            "category":"Professional",
            "subcategory":"Advertising",
            "type":"Services"
        }
    ],
    "sg:phone":"+1 402 489 1777",
    "sg:postcode":"68506",
    "sg:province":"NE",
    "wof:name":"A J's Mobile Signs",
    "wof:placetype":"venue"
},
  "geometry": {"coordinates":[-96.61843399999999,40.787266],"type":"Point"}
}