{
  "type": "Feature",
  "properties": {
    "iso:country":"US",
    "sg:address":"954 N 27th St",
    "sg:city":"Blair",
    "sg:classifiers":[
        {
            "category":"Professional",
            "subcategory":"Business Services",
            "type":"Services"
        }
    ],
    "sg:phone":"+1 402 426 3231",
    "sg:postcode":"68008",
    "sg:province":"NE",
    "wof:name":"Macman Graphics",
    "wof:placetype":"venue"
},
  "geometry": {"coordinates":[-96.15294799999999,41.551632],"type":"Point"}
}