{
  "type": "Feature",
  "properties": {
    "iso:country":"US",
    "sg:address":"3256 J Rd",
    "sg:city":"Syracuse",
    "sg:classifiers":[
        {
            "category":"Farming",
            "subcategory":"Farm",
            "type":"Manufacturing & Wholesale Goods"
        }
    ],
    "sg:phone":"+1 402 269 3161",
    "sg:postcode":"68446",
    "sg:province":"NE",
    "sg:tags":[
        "crop",
        "soybean",
        "general"
    ],
    "wof:name":"Lone Pine Ranch",
    "wof:placetype":"venue"
},
  "geometry": {"coordinates":[-96.15469,40.653497],"type":"Point"}
}