{
  "type": "Feature",
  "properties": {
    "iso:country":"US",
    "sg:address":"4640 Champlain Dr",
    "sg:city":"Lincoln",
    "sg:classifiers":[
        {
            "category":"Education",
            "subcategory":"Special Training",
            "type":"Public Place"
        }
    ],
    "sg:phone":"+1 402 477 5111",
    "sg:postcode":"68521",
    "sg:province":"NE",
    "sg:tags":[
        "tutoring"
    ],
    "sg:website":"www.learningrx.com",
    "wof:name":"Learning Rx",
    "wof:placetype":"venue"
},
  "geometry": {"coordinates":[-96.683004,40.858221],"type":"Point"}
}