{
  "type": "Feature",
  "properties": {
    "iso:country":"US",
    "sg:address":"345 Hector St",
    "sg:city":"Cordova",
    "sg:classifiers":[
        {
            "category":"Bars & Pubs",
            "type":"Food & Drink"
        }
    ],
    "sg:phone":"+1 402 576 9511",
    "sg:postcode":"68330",
    "sg:province":"NE",
    "wof:name":"Cordova Bar & Grill",
    "wof:placetype":"venue"
},
  "geometry": {"coordinates":[-97.35141900000001,40.717321],"type":"Point"}
}