{
  "type": "Feature",
  "properties": {
    "iso:country":"US",
    "sg:address":"1350 N 48th St",
    "sg:city":"Lincoln",
    "sg:classifiers":[
        {
            "category":"Health Services",
            "subcategory":"Health Practitioner",
            "type":"Services"
        }
    ],
    "sg:phone":"+1 402 466 8844",
    "sg:postcode":"68504",
    "sg:province":"NE",
    "wof:name":"Massage Wellness Clinic",
    "wof:placetype":"venue"
},
  "geometry": {"coordinates":[-96.65364599999999,40.826653],"type":"Point"}
}