{
  "type": "Feature",
  "properties": {
    "iso:country":"US",
    "sg:address":"25205 Harrison St",
    "sg:city":"Waterloo",
    "sg:classifiers":[
        {
            "category":"Building & Trades",
            "subcategory":"Plumbing",
            "type":"Services"
        },
        {
            "category":"Manufacturing",
            "subcategory":"Tools & Machinery",
            "type":"Manufacturing & Wholesale Goods"
        }
    ],
    "sg:phone":"+1 402 359 4173",
    "sg:postcode":"68069",
    "sg:province":"NE",
    "sg:tags":[
        "plumbing",
        "equipment",
        "contractor",
        "mfg"
    ],
    "sg:website":"www.esu3.org",
    "wof:name":"Dave's Quality Plumbing",
    "wof:placetype":"venue"
},
  "geometry": {"coordinates":[-96.31270000000001,41.190073],"type":"Point"}
}