{
  "type": "Feature",
  "properties": {
    "iso:country":"US",
    "sg:address":"2315 Park Ln",
    "sg:city":"Nebraska City",
    "sg:classifiers":[
        {
            "category":"Professional",
            "subcategory":"Research",
            "type":"Services"
        }
    ],
    "sg:phone":"+1 402 873 3844",
    "sg:postcode":"68410",
    "sg:province":"NE",
    "sg:tags":[
        "nonphysical",
        "commercial"
    ],
    "wof:name":"Market Demographics Research",
    "wof:placetype":"venue"
},
  "geometry": {"coordinates":[-95.873925,40.677718],"type":"Point"}
}