{
  "type": "Feature",
  "properties": {
    "iso:country":"US",
    "sg:address":"6672 Country Club Dr",
    "sg:city":"Columbus",
    "sg:classifiers":[
        {
            "category":"Real Estate",
            "subcategory":"Real Estate Operator",
            "type":"Services"
        }
    ],
    "sg:phone":"+1 402 564 3023",
    "sg:postcode":"68601",
    "sg:province":"NE",
    "sg:tags":[
        "farm",
        "corn",
        "property",
        "soybean",
        "lessor"
    ],
    "wof:name":"Lavern Wetgen",
    "wof:placetype":"venue"
},
  "geometry": {"coordinates":[-97.389341,41.478416],"type":"Point"}
}