{
  "type": "Feature",
  "properties": {
    "addr:full":"100 E 11th St Ogallala NE 69153",
    "addr:housenumber":"100",
    "addr:postcode":"69153",
    "addr:street":"E 11Th St",
    "iso:country":"US",
    "sg:address":"100 E 11th St",
    "sg:city":"Ogallala",
    "sg:classifiers":[
        {
            "category":"Real Estate",
            "subcategory":"Real Estate Agent",
            "type":"Services"
        }
    ],
    "sg:phone":"+1 308 284 2800",
    "sg:postcode":"69153",
    "sg:province":"NE",
    "wof:name":"Bayside Realty",
    "wof:placetype":"venue"
},
  "geometry": {"coordinates":[-101.720939,41.13369],"type":"Point"}
}