{
  "type": "Feature",
  "properties": {
    "addr:full":"1431 E 69th St Kearney NE 68847",
    "addr:housenumber":"1431",
    "addr:postcode":"68847",
    "addr:street":"E 69Th St",
    "iso:country":"US",
    "sg:address":"1431 E 69th St",
    "sg:city":"Kearney",
    "sg:classifiers":[
        {
            "category":"Social Services",
            "subcategory":"Child Care",
            "type":"Services"
        }
    ],
    "sg:phone":"+1 308 236 7561",
    "sg:postcode":"68847",
    "sg:province":"NE",
    "sg:tags":[
        "day"
    ],
    "wof:name":"Townsends Peggy J Day Care",
    "wof:placetype":"venue"
},
  "geometry": {"coordinates":[-99.062664,40.741989],"type":"Point"}
}