{
  "type": "Feature",
  "properties": {
    "iso:country":"US",
    "sg:address":"1512 Rd 12",
    "sg:city":"York",
    "sg:classifiers":[
        {
            "category":"Professional",
            "subcategory":"Management & Consulting",
            "type":"Services"
        }
    ],
    "sg:phone":"+1 402 362 3738",
    "sg:postcode":"68467",
    "sg:province":"NE",
    "wof:name":"Double D Crop Consultants",
    "wof:placetype":"venue"
},
  "geometry": {"coordinates":[-97.575633,40.858029],"type":"Point"}
}