{
  "type": "Feature",
  "properties": {
    "iso:country":"US",
    "sg:address":"1952 R Rd",
    "sg:city":"Heartwell",
    "sg:phone":"+1 308 563 2459",
    "sg:postcode":"68945",
    "sg:province":"NE",
    "sg:tags":[
        "farm",
        "corn"
    ],
    "wof:name":"Ronald Dornhoff",
    "wof:placetype":"venue"
},
  "geometry": {"coordinates":[-98.83061600000001,40.582505],"type":"Point"}
}