{
  "type": "Feature",
  "properties": {
    "addr:full":"1236 Main Ave Crete NE 68333",
    "addr:housenumber":"1236",
    "addr:postcode":"68333",
    "addr:street":"Main Ave",
    "iso:country":"US",
    "sg:address":"1236 Main Ave",
    "sg:city":"Crete",
    "sg:classifiers":[
        {
            "category":"Restaurant",
            "type":"Food & Drink"
        }
    ],
    "sg:phone":"+1 402 826 2311",
    "sg:postcode":"68333",
    "sg:province":"NE",
    "wof:name":"Indio's",
    "wof:placetype":"venue"
},
  "geometry": {"coordinates":[-96.96143499999999,40.624885],"type":"Point"}
}