{
  "type": "Feature",
  "properties": {
    "iso:country":"US",
    "sg:address":"5000 L St",
    "sg:city":"Omaha",
    "sg:classifiers":[
        {
            "category":"Shopping",
            "subcategory":"Pharmacy",
            "type":"Retail Goods"
        }
    ],
    "sg:phone":"+1 402 733 6935",
    "sg:postcode":"68117",
    "sg:province":"NE",
    "sg:tags":[
        "drugstore"
    ],
    "wof:name":"Kmart Stores",
    "wof:placetype":"venue"
},
  "geometry": {"coordinates":[-95.990898,41.212601],"type":"Point"}
}