{
  "type": "Feature",
  "properties": {
    "iso:country":"US",
    "sg:address":"2344 Rd 16",
    "sg:city":"Howells",
    "sg:phone":"+1 402 986 1582",
    "sg:postcode":"68641",
    "sg:province":"NE",
    "sg:tags":[
        "farm",
        "corn"
    ],
    "wof:name":"Kampschnieder Farm",
    "wof:placetype":"venue"
},
  "geometry": {"coordinates":[-96.964006,41.728259],"type":"Point"}
}