{
  "type": "Feature",
  "properties": {
    "iso:country":"US",
    "sg:address":"106 Maple St",
    "sg:city":"Norfolk",
    "sg:classifiers":[
        {
            "category":"Building & Trades",
            "subcategory":"Plumbing",
            "type":"Services"
        }
    ],
    "sg:phone":"+1 402 371 4025",
    "sg:postcode":"68701",
    "sg:province":"NE",
    "sg:tags":[
        "plumbing",
        "contractor"
    ],
    "wof:name":"Gall Plumbing Inc",
    "wof:placetype":"venue"
},
  "geometry": {"coordinates":[-97.45312,42.101662],"type":"Point"}
}