{
  "type": "Feature",
  "properties": {
    "iso:country":"US",
    "sg:address":"145 W 13th St",
    "sg:city":"Crete",
    "sg:classifiers":[
        {
            "category":"Professional",
            "subcategory":"Accounting & Tax Preparation",
            "type":"Services"
        }
    ],
    "sg:phone":"+1 402 826 2001",
    "sg:postcode":"68333",
    "sg:province":"NE",
    "sg:tags":[
        "bookkeeping",
        "general"
    ],
    "wof:name":"Robert L Malone",
    "wof:placetype":"venue"
},
  "geometry": {"coordinates":[-96.961917,40.625147],"type":"Point"}
}