{
  "type": "Feature",
  "properties": {
    "iso:country":"US",
    "sg:address":"1310 W Norfolk Ave",
    "sg:city":"Norfolk",
    "sg:classifiers":[
        {
            "category":"Shopping",
            "subcategory":"Hobbies, Toys, & Games",
            "type":"Retail Goods"
        }
    ],
    "sg:phone":"+1 402 371 2240",
    "sg:postcode":"68701",
    "sg:province":"NE",
    "sg:tags":[
        "model",
        "supply"
    ],
    "sg:website":"www.hobbytown.com",
    "wof:name":"Hobbytown USA",
    "wof:placetype":"venue"
},
  "geometry": {"coordinates":[-97.4268,42.032766],"type":"Point"}
}