{
  "type": "Feature",
  "properties": {
    "iso:country":"US",
    "sg:address":"305 E Hughson St",
    "sg:city":"Randolph",
    "sg:classifiers":[
        {
            "category":"Shopping",
            "subcategory":"Computers & Home Electronics",
            "type":"Retail Goods"
        }
    ],
    "sg:phone":"+1 402 337 0380",
    "sg:postcode":"68771",
    "sg:province":"NE",
    "sg:tags":[
        "equipment",
        "dealer"
    ],
    "wof:name":"Randolph Computers & Netwrkng",
    "wof:placetype":"venue"
},
  "geometry": {"coordinates":[-97.352757,42.379685],"type":"Point"}
}