{
  "type": "Feature",
  "properties": {
    "iso:country":"US",
    "sg:address":"4985 W Blue Hill Rd",
    "sg:city":"Ayr",
    "sg:classifiers":[
        {
            "category":"Manufacturing",
            "subcategory":"Tools & Machinery",
            "type":"Manufacturing & Wholesale Goods"
        }
    ],
    "sg:phone":"+1 402 756 4355",
    "sg:postcode":"68925",
    "sg:province":"NE",
    "sg:tags":[
        "equipment",
        "electric"
    ],
    "wof:name":"MEF Control",
    "wof:placetype":"venue"
},
  "geometry": {"coordinates":[-98.446118,40.379375],"type":"Point"}
}