{
  "type": "Feature",
  "properties": {
    "addr:full":"3845 N 132nd St Omaha NE 68164",
    "addr:housenumber":"3845",
    "addr:postcode":"68164",
    "addr:street":"N 132Nd St",
    "iso:country":"US",
    "sg:address":"3845 N 132nd St",
    "sg:city":"Omaha",
    "sg:classifiers":[
        {
            "category":"Retail",
            "subcategory":"Auto Repair",
            "type":"Services"
        }
    ],
    "sg:phone":"+1 402 445 0070",
    "sg:postcode":"68164",
    "sg:province":"NE",
    "sg:tags":[
        "automobile",
        "lubrication"
    ],
    "wof:name":"Valvoline Instant Oil Change",
    "wof:placetype":"venue"
},
  "geometry": {"coordinates":[-96.119573,41.294621],"type":"Point"}
}