{
  "type": "Feature",
  "properties": {
    "iso:country":"US",
    "sg:address":"800 Dimery Ave",
    "sg:city":"Beaver Crossing",
    "sg:classifiers":[
        {
            "category":"Government",
            "subcategory":"Office",
            "type":"Public Place"
        }
    ],
    "sg:phone":"+1 402 532 3925",
    "sg:postcode":"68313",
    "sg:province":"NE",
    "sg:tags":[
        "village"
    ],
    "wof:name":"City Of Beaver Crossing",
    "wof:placetype":"venue"
},
  "geometry": {"coordinates":[-97.281419,40.778438],"type":"Point"}
}