{
  "type": "Feature",
  "properties": {
    "iso:country":"US",
    "sg:address":"2921 Roselawn Dr",
    "sg:city":"Grand Island",
    "sg:classifiers":[
        {
            "category":"Organizations",
            "subcategory":"Religious Organization",
            "type":"Services"
        }
    ],
    "sg:phone":"+1 308 382 6133",
    "sg:postcode":"68801",
    "sg:province":"NE",
    "sg:tags":[
        "church"
    ],
    "wof:name":"Centro De Vida Cristiana",
    "wof:placetype":"venue"
},
  "geometry": {"coordinates":[-98.302573,40.892663],"type":"Point"}
}