{
  "type": "Feature",
  "properties": {
    "addr:full":"1031 Manchester Dr Lincoln NE 68528",
    "addr:housenumber":"1031",
    "addr:postcode":"68528",
    "addr:street":"Manchester Dr",
    "iso:country":"US",
    "sg:address":"1031 Manchester Dr",
    "sg:city":"Lincoln",
    "sg:classifiers":[
        {
            "category":"Building & Trades",
            "subcategory":"Landscaping Services",
            "type":"Services"
        }
    ],
    "sg:phone":"+1 402 580 6585",
    "sg:postcode":"68528",
    "sg:province":"NE",
    "sg:tags":[
        "lawn",
        "maintenance",
        "grounds"
    ],
    "wof:name":"Dahlheim Irrigation",
    "wof:placetype":"venue"
},
  "geometry": {"coordinates":[-96.740572,40.820177],"type":"Point"}
}