{
  "type": "Feature",
  "properties": {
    "addr:full":"17392 W Center Rd Omaha NE 68130",
    "addr:housenumber":"17392",
    "addr:postcode":"68130",
    "addr:street":"W Center Rd",
    "iso:country":"US",
    "sg:address":"17392 W Center Rd",
    "sg:city":"Omaha",
    "sg:classifiers":[
        {
            "category":"Restaurant",
            "type":"Food & Drink"
        }
    ],
    "sg:phone":"+1 402 697 5500",
    "sg:postcode":"68130",
    "sg:province":"NE",
    "wof:name":"Planet Sub",
    "wof:placetype":"venue"
},
  "geometry": {"coordinates":[-96.186697,41.234202],"type":"Point"}
}