{
  "type": "Feature",
  "properties": {
    "iso:country":"US",
    "sg:address":"8625 Whitmore Cir Ste 124",
    "sg:city":"Omaha",
    "sg:classifiers":[
        {
            "category":"Autos & Motor Vehicles",
            "subcategory":"Auto Supplies",
            "type":"Retail Goods"
        },
        {
            "category":"Retail",
            "subcategory":"Auto Repair",
            "type":"Services"
        }
    ],
    "sg:phone":"+1 402 571 1401",
    "sg:postcode":"68122",
    "sg:province":"NE",
    "sg:tags":[
        "automobile",
        "part",
        "truck"
    ],
    "sg:website":"http://clickserve.dartsearch.net/link/click?lid=43000000313868787&ds_s_kwgid=58000000006820725&ds_e_matchtype={MatchType}&ds_e_kwdid={OrderItemId}&ds_e_adid={AdId}&ds_url_v=2",
    "wof:name":"The Car Shop",
    "wof:placetype":"venue"
},
  "geometry": {"coordinates":[-96.046708,41.322296],"type":"Point"}
}