{
  "type": "Feature",
  "properties": {
    "iso:country":"US",
    "sg:address":"203 S 9th St",
    "sg:city":"Blair",
    "sg:classifiers":[
        {
            "category":"Autos & Motor Vehicles",
            "subcategory":"Auto Supplies",
            "type":"Retail Goods"
        }
    ],
    "sg:phone":"+1 402 426 9431",
    "sg:postcode":"68008",
    "sg:province":"NE",
    "sg:tags":[
        "automobile",
        "parts"
    ],
    "wof:name":"Bi State Motor Parts & Machine",
    "wof:placetype":"venue"
},
  "geometry": {"coordinates":[-96.124886,41.542789],"type":"Point"}
}