{
  "type": "Feature",
  "properties": {
    "addr:full":"12219 Westover Rd Omaha NE 68154",
    "addr:housenumber":"12219",
    "addr:postcode":"68154",
    "addr:street":"Westover Rd",
    "iso:country":"US",
    "sg:address":"12219 Westover Rd",
    "sg:city":"Omaha",
    "sg:classifiers":[
        {
            "category":"Real Estate",
            "subcategory":"Developer",
            "type":"Services"
        }
    ],
    "sg:phone":"+1 402 691 0691",
    "sg:postcode":"68154",
    "sg:province":"NE",
    "wof:name":"CAP Investments Inc",
    "wof:placetype":"venue"
},
  "geometry": {"coordinates":[-96.105352,41.255374],"type":"Point"}
}