{
  "type": "Feature",
  "properties": {
    "addr:full":"2511 State Hwy 50 Yankton NE 57078",
    "addr:housenumber":"2511",
    "addr:postcode":"57078",
    "addr:street":"State Hwy 50",
    "iso:country":"US",
    "sg:address":"2511 State Hwy 50",
    "sg:city":"Yankton",
    "sg:classifiers":[
        {
            "category":"Retail",
            "subcategory":"Auto Repair",
            "type":"Services"
        }
    ],
    "sg:phone":"+1 605 665 4142",
    "sg:postcode":"57078",
    "sg:province":"NE",
    "sg:tags":[
        "wrecker"
    ],
    "wof:name":"Pro Auto Inc",
    "wof:placetype":"venue"
},
  "geometry": {"coordinates":[-97.39751,42.895364],"type":"Point"}
}