{
  "type": "Feature",
  "properties": {
    "addr:full":"3151 A St Lincoln NE 68502",
    "addr:housenumber":"3151",
    "addr:postcode":"68502",
    "addr:street":"A St",
    "iso:country":"US",
    "sg:address":"3151 A St",
    "sg:city":"Lincoln",
    "sg:classifiers":[
        {
            "category":"Sports & Exercise",
            "subcategory":"Gym",
            "type":"Entertainment"
        }
    ],
    "sg:phone":"+1 402 488 8788",
    "sg:postcode":"68502",
    "sg:province":"NE",
    "sg:tags":[
        "fitness",
        "physical",
        "facility"
    ],
    "wof:name":"Nebraska Sport Acceleration",
    "wof:placetype":"venue"
},
  "geometry": {"coordinates":[-96.67621699999999,40.798739],"type":"Point"}
}