{
  "type": "Feature",
  "properties": {
    "addr:full":"14012 Giles Rd Omaha NE 68138",
    "addr:housenumber":"14012",
    "addr:postcode":"68138",
    "addr:street":"Giles Rd",
    "iso:country":"US",
    "sg:address":"14012 Giles Rd",
    "sg:city":"Omaha",
    "sg:classifiers":[
        {
            "category":"Building & Trades",
            "subcategory":"Construction",
            "type":"Services"
        }
    ],
    "sg:phone":"+1 402 895 5195",
    "sg:postcode":"68138",
    "sg:province":"NE",
    "sg:tags":[
        "road",
        "contractor"
    ],
    "wof:name":"NIK Construction Svc",
    "wof:placetype":"venue"
},
  "geometry": {"coordinates":[-96.13258999999999,41.176297],"type":"Point"}
}