{
  "type": "Feature",
  "properties": {
    "iso:country":"US",
    "sg:address":"840 E 4th St",
    "sg:city":"Superior",
    "sg:classifiers":[
        {
            "category":"Recreation",
            "type":"Entertainment"
        }
    ],
    "sg:phone":"+1 402 879 4582",
    "sg:postcode":"68978",
    "sg:province":"NE",
    "sg:tags":[
        "parks"
    ],
    "wof:name":"Superior City Park Dept",
    "wof:placetype":"venue"
},
  "geometry": {"coordinates":[-98.060801,40.019978],"type":"Point"}
}