{
  "type": "Feature",
  "properties": {
    "addr:full":"3932 N 36th Ave Omaha NE 68111",
    "addr:housenumber":"3932",
    "addr:postcode":"68111",
    "addr:street":"N 36Th Ave",
    "iso:country":"US",
    "sg:address":"3932 N 36th Ave",
    "sg:city":"Omaha",
    "sg:classifiers":[
        {
            "category":"Home & Garden",
            "subcategory":"Carpets & Floor Coverings",
            "type":"Retail Goods"
        }
    ],
    "sg:phone":"+1 402 451 3410",
    "sg:postcode":"68111",
    "sg:province":"NE",
    "sg:tags":[
        "mosaic"
    ],
    "sg:website":"http://www.ozmosaics.com",
    "wof:name":"Mosaic Emporium",
    "wof:placetype":"venue"
},
  "geometry": {"coordinates":[-95.967361,41.294328],"type":"Point"}
}