{
  "type": "Feature",
  "properties": {
    "iso:country":"US",
    "sg:address":"421 N Saddle Creek Rd",
    "sg:city":"Omaha",
    "sg:classifiers":[
        {
            "category":"Personal",
            "subcategory":"Beauty Salon",
            "type":"Services"
        }
    ],
    "sg:phone":"+1 402 556 6482",
    "sg:postcode":"68131",
    "sg:province":"NE",
    "sg:tags":[
        "nail",
        "manicuring"
    ],
    "wof:name":"Wonder Nails",
    "wof:placetype":"venue"
},
  "geometry": {"coordinates":[-95.980904,41.263901],"type":"Point"}
}