{
  "type": "Feature",
  "properties": {
    "iso:country":"US",
    "sg:address":"4740 N 132nd St",
    "sg:city":"Omaha",
    "sg:classifiers":[
        {
            "category":"Building & Trades",
            "subcategory":"Construction",
            "type":"Services"
        }
    ],
    "sg:phone":"+1 402 496 0111",
    "sg:postcode":"68164",
    "sg:province":"NE",
    "sg:tags":[
        "hanging",
        "contractor"
    ],
    "wof:name":"Vecchio Painting",
    "wof:placetype":"venue"
},
  "geometry": {"coordinates":[-96.119714,41.302363],"type":"Point"}
}