{
  "type": "Feature",
  "properties": {
    "iso:country":"US",
    "sg:address":"321 Riverside Dr",
    "sg:city":"North Platte",
    "sg:classifiers":[
        {
            "category":"Health Services",
            "subcategory":"Doctor",
            "type":"Services"
        }
    ],
    "sg:phone":"+1 308 534 8088",
    "sg:postcode":"69101",
    "sg:province":"NE",
    "wof:name":"David G Manary DDS Ms",
    "wof:placetype":"venue"
},
  "geometry": {"coordinates":[-100.766453,41.121583],"type":"Point"}
}