{
  "type": "Feature",
  "properties": {
    "addr:full":"2501 S 32nd Ave Omaha NE 68105",
    "addr:housenumber":"2501",
    "addr:postcode":"68105",
    "addr:street":"S 32Nd Ave",
    "iso:country":"US",
    "sg:address":"2501 S 32nd Ave",
    "sg:city":"Omaha",
    "sg:classifiers":[
        {
            "category":"Retail",
            "subcategory":"Auto Rental",
            "type":"Services"
        }
    ],
    "sg:phone":"+1 402 345 3180",
    "sg:postcode":"68105",
    "sg:province":"NE",
    "sg:tags":[
        "renting",
        "truck",
        "leasing"
    ],
    "wof:name":"U-Haul Co",
    "wof:placetype":"venue"
},
  "geometry": {"coordinates":[-95.960329,41.23475],"type":"Point"}
}