{
  "type": "Feature",
  "properties": {
    "iso:country":"US",
    "sg:address":"775 Crescent Dr",
    "sg:city":"Gering",
    "sg:classifiers":[
        {
            "category":"Recreation",
            "type":"Entertainment"
        }
    ],
    "sg:phone":"+1 308 632 5996",
    "sg:postcode":"69341",
    "sg:province":"NE",
    "sg:tags":[
        "skating",
        "rink"
    ],
    "wof:name":"Playhouse",
    "wof:placetype":"venue"
},
  "geometry": {"coordinates":[-103.659638,41.843324],"type":"Point"}
}