{
  "type": "Feature",
  "properties": {
    "addr:full":"1608 Co Rd 18 Rogers NE 68659",
    "addr:housenumber":"1608;18",
    "addr:postcode":"68659",
    "addr:street":"Co Rd",
    "iso:country":"US",
    "sg:address":"1608 Co Rd 18",
    "sg:city":"Rogers",
    "sg:classifiers":[
        {
            "category":"Farming",
            "subcategory":"Livestock Farm",
            "type":"Manufacturing & Wholesale Goods"
        }
    ],
    "sg:phone":"+1 402 986 1191",
    "sg:postcode":"68659",
    "sg:province":"NE",
    "sg:tags":[
        "beef",
        "feedlot",
        "cattle"
    ],
    "wof:name":"D & B Farms",
    "wof:placetype":"venue"
},
  "geometry": {"coordinates":[-96.925251,41.618864],"type":"Point"}
}