{
  "type": "Feature",
  "properties": {
    "iso:country":"US",
    "sg:address":"415 E Norfolk Ave",
    "sg:city":"Norfolk",
    "sg:classifiers":[
        {
            "category":"Retail",
            "subcategory":"Auto Repair",
            "type":"Services"
        }
    ],
    "sg:phone":"+1 402 379 2656",
    "sg:postcode":"68701",
    "sg:province":"NE",
    "sg:tags":[
        "muffler",
        "exhaust",
        "rental",
        "system",
        "car"
    ],
    "wof:name":"Avenue Muffler and Car Rental",
    "wof:placetype":"venue"
},
  "geometry": {"coordinates":[-97.401392,42.032878],"type":"Point"}
}