{
  "type": "Feature",
  "properties": {
    "iso:country":"US",
    "sg:address":"5110 S 33rd St",
    "sg:city":"Omaha",
    "sg:classifiers":[
        {
            "category":"Professional",
            "subcategory":"Accounting & Tax Preparation",
            "type":"Services"
        }
    ],
    "sg:phone":"+1 402 731 1420",
    "sg:postcode":"68107",
    "sg:province":"NE",
    "sg:tags":[
        "return",
        "filing"
    ],
    "wof:name":"A Green Income Tax Svc",
    "wof:placetype":"venue"
},
  "geometry": {"coordinates":[-95.9631,41.209408],"type":"Point"}
}