{
  "type": "Feature",
  "properties": {
    "addr:full":"1608 E 26 Rd Marquette NE 68854",
    "addr:housenumber":"1608;26",
    "addr:postcode":"68854",
    "addr:street":"E;Rd",
    "iso:country":"US",
    "sg:address":"1608 E 26 Rd",
    "sg:city":"Marquette",
    "sg:classifiers":[
        {
            "category":"Farming",
            "subcategory":"Farm",
            "type":"Manufacturing & Wholesale Goods"
        }
    ],
    "sg:phone":"+1 308 946 2610",
    "sg:postcode":"68854",
    "sg:province":"NE",
    "wof:name":"Andlor Inc",
    "wof:placetype":"venue"
},
  "geometry": {"coordinates":[-97.99050699999999,41.060908],"type":"Point"}
}