{
  "type": "Feature",
  "properties": {
    "addr:full":"2727 S 144th St Omaha NE 68144",
    "addr:housenumber":"2727",
    "addr:postcode":"68144",
    "addr:street":"S 144Th St",
    "iso:country":"US",
    "sg:address":"2727 S 144th St",
    "sg:city":"Omaha",
    "sg:classifiers":[
        {
            "category":"Health Services",
            "subcategory":"Doctor",
            "type":"Services"
        }
    ],
    "sg:phone":"+1 402 778 5555",
    "sg:postcode":"68144",
    "sg:province":"NE",
    "sg:tags":[
        "physician",
        "surgeon"
    ],
    "wof:name":"Aesthetic & Reconstructive PC",
    "wof:placetype":"venue"
},
  "geometry": {"coordinates":[-96.138509,41.233449],"type":"Point"}
}