{
  "type": "Feature",
  "properties": {
    "iso:country":"US",
    "sg:address":"121 Fall Creek Rd",
    "sg:city":"Papillion",
    "sg:phone":"+1 402 592 5487",
    "sg:postcode":"68046",
    "sg:province":"NE",
    "sg:tags":[
        "farm",
        "corn",
        "soybean"
    ],
    "wof:name":"Cedar Island Acres",
    "wof:placetype":"venue"
},
  "geometry": {"coordinates":[-96.005088,41.155612],"type":"Point"}
}