{
  "type": "Feature",
  "properties": {
    "addr:full":"2307 N 134th St Omaha NE 68164",
    "addr:housenumber":"2307",
    "addr:postcode":"68164",
    "addr:street":"N 134Th St",
    "iso:country":"US",
    "sg:address":"2307 N 134th St",
    "sg:city":"Omaha",
    "sg:classifiers":[
        {
            "category":"Real Estate",
            "subcategory":"Real Estate Agent",
            "type":"Services"
        }
    ],
    "sg:phone":"+1 402 498 2808",
    "sg:postcode":"68164",
    "sg:province":"NE",
    "sg:tags":[
        "finding",
        "apartment",
        "rental"
    ],
    "wof:name":"Recorp Corp Suites",
    "wof:placetype":"venue"
},
  "geometry": {"coordinates":[-96.12186800000001,41.279296],"type":"Point"}
}