{
  "type": "Feature",
  "properties": {
    "iso:country":"US",
    "sg:address":"520 N 5th St",
    "sg:city":"Beatrice",
    "sg:classifiers":[
        {
            "category":"Organizations",
            "subcategory":"Religious Organization",
            "type":"Services"
        }
    ],
    "sg:phone":"+1 402 223 5515",
    "sg:postcode":"68310",
    "sg:province":"NE",
    "sg:tags":[
        "church"
    ],
    "wof:name":"Homestead Cluster",
    "wof:placetype":"venue"
},
  "geometry": {"coordinates":[-96.74801600000001,40.270633],"type":"Point"}
}