{
  "type": "Feature",
  "properties": {
    "addr:full":"304 State St Brule NE 69127",
    "addr:housenumber":"304",
    "addr:postcode":"69127",
    "addr:street":"State St",
    "iso:country":"US",
    "sg:address":"304 State St",
    "sg:city":"Brule",
    "sg:classifiers":[
        {
            "category":"Home & Garden",
            "subcategory":"Hardware",
            "type":"Retail Goods"
        }
    ],
    "sg:phone":"+1 308 287 2350",
    "sg:postcode":"69127",
    "sg:province":"NE",
    "wof:name":"Burklund Hardware",
    "wof:placetype":"venue"
},
  "geometry": {"coordinates":[-101.888147,41.093366],"type":"Point"}
}