{
  "type": "Feature",
  "properties": {
    "iso:country":"US",
    "sg:address":"730 Triangle Rd",
    "sg:city":"Hyannis",
    "sg:classifiers":[
        {
            "category":"Shopping",
            "subcategory":"Gifts & Souvenirs",
            "type":"Retail Goods"
        }
    ],
    "sg:phone":"+1 308 764 2268",
    "sg:postcode":"69350",
    "sg:province":"NE",
    "wof:name":"Susan Steel",
    "wof:placetype":"venue"
},
  "geometry": {"coordinates":[-101.571786,41.715812],"type":"Point"}
}