{
  "type": "Feature",
  "properties": {
    "addr:full":"12030 Pacific St Omaha NE 68154",
    "addr:housenumber":"12030",
    "addr:postcode":"68154",
    "addr:street":"Pacific St",
    "iso:country":"US",
    "sg:address":"12030 Pacific St",
    "sg:city":"Omaha",
    "sg:classifiers":[
        {
            "category":"Professional",
            "subcategory":"Computer Services",
            "type":"Services"
        }
    ],
    "sg:phone":"+1 402 431 5432",
    "sg:postcode":"68154",
    "sg:province":"NE",
    "wof:name":"Advanced Network Technologies",
    "wof:placetype":"venue"
},
  "geometry": {"coordinates":[-96.10342,41.248707],"type":"Point"}
}