{
  "type": "Feature",
  "properties": {
    "iso:country":"US",
    "sg:address":"1543 Co Rd 13",
    "sg:city":"Lyons",
    "sg:classifiers":[
        {
            "category":"Organizations",
            "subcategory":"Religious Organization",
            "type":"Services"
        }
    ],
    "sg:phone":"+1 402 685 6260",
    "sg:postcode":"68038",
    "sg:province":"NE",
    "sg:tags":[
        "church"
    ],
    "wof:name":"St John's Lutheran Church",
    "wof:placetype":"venue"
},
  "geometry": {"coordinates":[-96.44431899999999,41.893542],"type":"Point"}
}