{
  "type": "Feature",
  "properties": {
    "addr:full":"10508 S 144th St Omaha NE 68138",
    "addr:housenumber":"10508",
    "addr:postcode":"68138",
    "addr:street":"S 144Th St",
    "iso:country":"US",
    "sg:address":"10508 S 144th St",
    "sg:city":"Omaha",
    "sg:classifiers":[
        {
            "category":"Real Estate",
            "subcategory":"Real Estate Operator",
            "type":"Services"
        }
    ],
    "sg:phone":"+1 402 895 1440",
    "sg:postcode":"68138",
    "sg:province":"NE",
    "sg:tags":[
        "hall",
        "reception",
        "social"
    ],
    "wof:name":"Millard Social Hall",
    "wof:placetype":"venue"
},
  "geometry": {"coordinates":[-96.139025,41.149775],"type":"Point"}
}