{
  "type": "Feature",
  "properties": {
    "addr:full":"4040 Hamilton St Omaha NE 68131",
    "addr:housenumber":"4040",
    "addr:postcode":"68131",
    "addr:street":"Hamilton St",
    "iso:country":"US",
    "sg:address":"4040 Hamilton St",
    "sg:city":"Omaha",
    "sg:classifiers":[
        {
            "category":"Shopping",
            "subcategory":"Tobacco",
            "type":"Retail Goods"
        }
    ],
    "sg:phone":"+1 402 561 1468",
    "sg:postcode":"68131",
    "sg:province":"NE",
    "sg:tags":[
        "cigarette",
        "cigar",
        "dealer"
    ],
    "wof:name":"Hamilton Outlet Tobacco",
    "wof:placetype":"venue"
},
  "geometry": {"coordinates":[-95.97489400000001,41.27215],"type":"Point"}
}