{
  "type": "Feature",
  "properties": {
    "iso:country":"US",
    "sg:address":"150265 Co Rd F",
    "sg:city":"Mitchell",
    "sg:classifiers":[
        {
            "category":"Wholesale",
            "subcategory":"Machinery & Supplies",
            "type":"Manufacturing & Wholesale Goods"
        }
    ],
    "sg:phone":"+1 308 623 1094",
    "sg:postcode":"69357",
    "sg:province":"NE",
    "sg:tags":[
        "equipment",
        "irrigation",
        "system"
    ],
    "wof:name":"Farmer's Irrigation Dist",
    "wof:placetype":"venue"
},
  "geometry": {"coordinates":[-103.787244,41.928558],"type":"Point"}
}