{
  "type": "Feature",
  "properties": {
    "addr:full":"5001 Russell Cir Lincoln NE 68507",
    "addr:housenumber":"5001",
    "addr:postcode":"68507",
    "addr:street":"Russell Cir",
    "iso:country":"US",
    "sg:address":"5001 Russell Cir",
    "sg:city":"Lincoln",
    "sg:classifiers":[
        {
            "category":"Wholesale",
            "subcategory":"Construction Materials",
            "type":"Manufacturing & Wholesale Goods"
        }
    ],
    "sg:phone":"+1 402 464 6348",
    "sg:postcode":"68507",
    "sg:province":"NE",
    "sg:tags":[
        "building"
    ],
    "wof:name":"Midwest Door & Hardware Inc",
    "wof:placetype":"venue"
},
  "geometry": {"coordinates":[-96.639686,40.862491],"type":"Point"}
}