{
  "type": "Feature",
  "properties": {
    "iso:country":"US",
    "sg:address":"4849 Rd 105",
    "sg:city":"Dalton",
    "sg:classifiers":[
        {
            "category":"Professional",
            "subcategory":"Research",
            "type":"Services"
        }
    ],
    "sg:phone":"+1 308 377 2727",
    "sg:postcode":"69131",
    "sg:province":"NE",
    "sg:tags":[
        "environmental",
        "ecological"
    ],
    "wof:name":"Berry Environmental Svc",
    "wof:placetype":"venue"
},
  "geometry": {"coordinates":[-103.050102,41.341076],"type":"Point"}
}