{
  "type": "Feature",
  "properties": {
    "addr:full":"814 US Hwy 183 Alma NE 68949",
    "addr:housenumber":"814",
    "addr:postcode":"68949",
    "addr:street":"Us Hwy 183",
    "iso:country":"US",
    "sg:address":"814 US Hwy 183",
    "sg:city":"Alma",
    "sg:classifiers":[
        {
            "category":"Autos & Motor Vehicles",
            "subcategory":"Automobile Sales",
            "type":"Retail Goods"
        }
    ],
    "sg:phone":"+1 308 928 2106",
    "sg:postcode":"68949",
    "sg:province":"NE",
    "sg:tags":[
        "car",
        "dealer"
    ],
    "wof:name":"Tripe Motor Co",
    "wof:placetype":"venue"
},
  "geometry": {"coordinates":[-99.379767,40.442319],"type":"Point"}
}