{
  "type": "Feature",
  "properties": {
    "addr:full":"4958 Grover St Omaha NE 68106",
    "addr:housenumber":"4958",
    "addr:postcode":"68106",
    "addr:street":"Grover St",
    "iso:country":"US",
    "sg:address":"4958 Grover St",
    "sg:city":"Omaha",
    "sg:classifiers":[
        {
            "category":"Personal",
            "subcategory":"Tattoo Parlor",
            "type":"Services"
        }
    ],
    "sg:phone":"+1 402 934 7871",
    "sg:postcode":"68106",
    "sg:province":"NE",
    "sg:website":"www.hebegbtattoo.com",
    "wof:name":"Hebe Gb Tattoo",
    "wof:placetype":"venue"
},
  "geometry": {"coordinates":[-95.98926,41.227127],"type":"Point"}
}