{
  "type": "Feature",
  "properties": {
    "iso:country":"US",
    "sg:address":"8930 L St",
    "sg:city":"Omaha",
    "sg:classifiers":[
        {
            "category":"Wholesale",
            "subcategory":"Painting Supplies",
            "type":"Manufacturing & Wholesale Goods"
        },
        {
            "category":"Home & Garden",
            "subcategory":"Building Materials",
            "type":"Retail Goods"
        },
        {
            "category":"Manufacturing",
            "subcategory":"Building Materials",
            "type":"Manufacturing & Wholesale Goods"
        }
    ],
    "sg:phone":"+1 402 331 1133",
    "sg:postcode":"68127",
    "sg:province":"NE",
    "sg:tags":[
        "paint",
        "wallpaper",
        "wallcoverings",
        "painter",
        "equipment"
    ],
    "wof:name":"Werner Paint Company",
    "wof:placetype":"venue"
},
  "geometry": {"coordinates":[-96.051734,41.21297],"type":"Point"}
}