{
  "type": "Feature",
  "properties": {
    "iso:country":"US",
    "sg:address":"918 W Holmes St",
    "sg:city":"Pierce",
    "sg:classifiers":[
        {
            "category":"Sports & Exercise",
            "subcategory":"Golf",
            "type":"Entertainment"
        }
    ],
    "sg:phone":"+1 402 329 4534",
    "sg:postcode":"68767",
    "sg:province":"NE",
    "sg:tags":[
        "course"
    ],
    "wof:name":"Pierce Community Golf Course",
    "wof:placetype":"venue"
},
  "geometry": {"coordinates":[-97.53736000000001,42.195363],"type":"Point"}
}