{
  "type": "Feature",
  "properties": {
    "addr:full":"1449 Center Ave Mitchell NE 69357",
    "addr:housenumber":"1449",
    "addr:postcode":"69357",
    "addr:street":"Center Ave",
    "iso:country":"US",
    "sg:address":"1449 Center Ave",
    "sg:city":"Mitchell",
    "sg:classifiers":[
        {
            "category":"Education",
            "subcategory":"Library",
            "type":"Public Place"
        }
    ],
    "sg:phone":"+1 308 623 2222",
    "sg:postcode":"69357",
    "sg:province":"NE",
    "wof:name":"Mitchell Public Library",
    "wof:placetype":"venue"
},
  "geometry": {"coordinates":[-103.808707,41.942752],"type":"Point"}
}