{
  "type": "Feature",
  "properties": {
    "iso:country":"US",
    "sg:address":"2601 Harlan St",
    "sg:city":"Falls City",
    "sg:classifiers":[
        {
            "category":"Food & Beverages",
            "subcategory":"Liquor & Beverages",
            "type":"Retail Goods"
        }
    ],
    "sg:phone":"+1 402 245 3228",
    "sg:postcode":"68355",
    "sg:province":"NE",
    "sg:tags":[
        "alcoholic"
    ],
    "wof:name":"Bottle Shop",
    "wof:placetype":"venue"
},
  "geometry": {"coordinates":[-95.60200500000001,40.071475],"type":"Point"}
}