{
  "type": "Feature",
  "properties": {
    "addr:full":"10520 Burt Cir Omaha NE 68114",
    "addr:housenumber":"10520",
    "addr:postcode":"68114",
    "addr:street":"Burt Cir",
    "iso:country":"US",
    "sg:address":"10520 Burt Cir",
    "sg:city":"Omaha",
    "sg:classifiers":[
        {
            "category":"Health Services",
            "subcategory":"Doctor",
            "type":"Services"
        }
    ],
    "sg:phone":"+1 402 496 2300",
    "sg:postcode":"68114",
    "sg:province":"NE",
    "sg:tags":[
        "medical"
    ],
    "wof:name":"David E Abisror MD",
    "wof:placetype":"venue"
},
  "geometry": {"coordinates":[-96.078135,41.267191],"type":"Point"}
}