{
  "type": "Feature",
  "properties": {
    "addr:full":"21311 Fieldcrest Rd Elkhorn NE 68022",
    "addr:housenumber":"21311",
    "addr:postcode":"68022",
    "addr:street":"Fieldcrest Rd",
    "iso:country":"US",
    "sg:address":"21311 Fieldcrest Rd",
    "sg:city":"Elkhorn",
    "sg:classifiers":[
        {
            "category":"Social Services",
            "subcategory":"Child Care",
            "type":"Services"
        }
    ],
    "sg:phone":"+1 402 289 3645",
    "sg:postcode":"68022",
    "sg:province":"NE",
    "sg:tags":[
        "day"
    ],
    "wof:name":"McKensie Dee Day Care",
    "wof:placetype":"venue"
},
  "geometry": {"coordinates":[-96.24918099999999,41.249794],"type":"Point"}
}