{
  "type": "Feature",
  "properties": {
    "addr:full":"1320 16th St Aurora NE 68818",
    "addr:housenumber":"1320",
    "addr:postcode":"68818",
    "addr:street":"16Th St",
    "iso:country":"US",
    "sg:address":"1320 16th St",
    "sg:city":"Aurora",
    "sg:classifiers":[
        {
            "category":"Restaurant",
            "type":"Food & Drink"
        }
    ],
    "sg:menulink":"http://www.allmenus.com/ne/aurora/129461-subway/menu/",
    "sg:phone":"+1 402 694 6585",
    "sg:postcode":"68818",
    "sg:province":"NE",
    "sg:tags":[
        "american",
        "sandwich"
    ],
    "wof:name":"Subway",
    "wof:placetype":"venue"
},
  "geometry": {"coordinates":[-97.997848,40.869881],"type":"Point"}
}