{
  "type": "Feature",
  "properties": {
    "iso:country":"US",
    "sg:address":"4318 S 24th St",
    "sg:city":"Omaha",
    "sg:classifiers":[
        {
            "category":"Restaurant",
            "type":"Food & Drink"
        }
    ],
    "sg:phone":"+1 402 731 9717",
    "sg:postcode":"68107",
    "sg:province":"NE",
    "sg:tags":[
        "mexican",
        "eating"
    ],
    "wof:name":"El Ranchito",
    "wof:placetype":"venue"
},
  "geometry": {"coordinates":[-95.947197,41.216702],"type":"Point"}
}