{
  "type": "Feature",
  "properties": {
    "iso:country":"US",
    "sg:address":"693 N 132nd St",
    "sg:city":"Omaha",
    "sg:classifiers":[
        {
            "category":"Health Services",
            "subcategory":"Doctor",
            "type":"Services"
        }
    ],
    "sg:phone":"+1 402 333 0186",
    "sg:postcode":"68154",
    "sg:province":"NE",
    "sg:tags":[
        "dentist"
    ],
    "wof:name":"Erich J Trumm DDS",
    "wof:placetype":"venue"
},
  "geometry": {"coordinates":[-96.119545,41.266169],"type":"Point"}
}