{
  "type": "Feature",
  "properties": {
    "addr:full":"16934 Frances St Omaha NE 68130",
    "addr:housenumber":"16934",
    "addr:postcode":"68130",
    "addr:street":"Frances St",
    "iso:country":"US",
    "sg:address":"16934 Frances St",
    "sg:city":"Omaha",
    "sg:classifiers":[
        {
            "category":"Professional",
            "subcategory":"Advertising",
            "type":"Services"
        }
    ],
    "sg:phone":"+1 402 334 6969",
    "sg:postcode":"68130",
    "sg:province":"NE",
    "sg:tags":[
        "counselor"
    ],
    "sg:website":"www.ervinandsmith.com",
    "wof:name":"Ervin & Smith",
    "wof:placetype":"venue"
},
  "geometry": {"coordinates":[-96.178667,41.240156],"type":"Point"}
}