{
  "type": "Feature",
  "properties": {
    "iso:country":"US",
    "sg:address":"1719 W 2nd St",
    "sg:city":"Hastings",
    "sg:classifiers":[
        {
            "category":"Shopping",
            "type":"Retail Goods"
        },
        {
            "category":"Home & Garden",
            "subcategory":"Home Furnishings",
            "type":"Retail Goods"
        }
    ],
    "sg:phone":"+1 402 463 0057",
    "sg:postcode":"68901",
    "sg:province":"NE",
    "sg:tags":[
        "sewing",
        "appliance",
        "machine",
        "hot",
        "vacuum",
        "spa",
        "tub",
        "fireplace"
    ],
    "wof:name":"Alan L Witte Sales & Service",
    "wof:placetype":"venue"
},
  "geometry": {"coordinates":[-98.406068,40.58528],"type":"Point"}
}