{
  "type": "Feature",
  "properties": {
    "addr:full":"1951 S 11th St Omaha NE 68108",
    "addr:housenumber":"1951",
    "addr:postcode":"68108",
    "addr:street":"S 11Th St",
    "iso:country":"US",
    "sg:address":"1951 S 11th St",
    "sg:city":"Omaha",
    "sg:classifiers":[
        {
            "category":"Building & Trades",
            "subcategory":"Locksmith",
            "type":"Services"
        }
    ],
    "sg:phone":"+1 402 881 3818",
    "sg:postcode":"68108",
    "sg:province":"NE",
    "sg:tags":[
        "key"
    ],
    "wof:name":"Abbe Locks 24 Locksmith",
    "wof:placetype":"venue"
},
  "geometry": {"coordinates":[-95.930539,41.241069],"type":"Point"}
}