{
  "type": "Feature",
  "properties": {
    "iso:country":"US",
    "sg:address":"1840 N 48th St",
    "sg:city":"Lincoln",
    "sg:classifiers":[
        {
            "category":"Professional",
            "subcategory":"Employment Agencies",
            "type":"Services"
        }
    ],
    "sg:phone":"+1 402 465 9060",
    "sg:postcode":"68504",
    "sg:province":"NE",
    "sg:tags":[
        "opportunity"
    ],
    "wof:name":"Staffing Services Inc",
    "wof:placetype":"venue"
},
  "geometry": {"coordinates":[-96.65363000000001,40.830924],"type":"Point"}
}