{
  "type": "Feature",
  "properties": {
    "iso:country":"US",
    "sg:address":"22 E 28th St",
    "sg:city":"Kearney",
    "sg:classifiers":[
        {
            "category":"Building & Trades",
            "subcategory":"Construction",
            "type":"Services"
        }
    ],
    "sg:phone":"+1 308 234 5642",
    "sg:postcode":"68847",
    "sg:province":"NE",
    "sg:tags":[
        "industrial"
    ],
    "wof:name":"Beatty Construction",
    "wof:placetype":"venue"
},
  "geometry": {"coordinates":[-99.08134699999999,40.704041],"type":"Point"}
}