{
  "type": "Feature",
  "properties": {
    "iso:country":"US",
    "sg:address":"507 N 13th St",
    "sg:city":"Norfolk",
    "sg:classifiers":[
        {
            "category":"Food & Beverages",
            "subcategory":"Liquor & Beverages",
            "type":"Retail Goods"
        }
    ],
    "sg:phone":"+1 402 371 5195",
    "sg:postcode":"68701",
    "sg:province":"NE",
    "sg:tags":[
        "alcoholic"
    ],
    "wof:name":"Budget Bottle Shop Inc",
    "wof:placetype":"venue"
},
  "geometry": {"coordinates":[-97.426742,42.038104],"type":"Point"}
}