{
  "type": "Feature",
  "properties": {
    "iso:country":"US",
    "sg:address":"2670 3rd Ave",
    "sg:city":"Columbus",
    "sg:classifiers":[
        {
            "category":"Freight",
            "type":"Transportation"
        }
    ],
    "sg:phone":"+1 402 564 4622",
    "sg:postcode":"68601",
    "sg:province":"NE",
    "sg:tags":[
        "commercial",
        "storage"
    ],
    "wof:name":"Che Mini Storage",
    "wof:placetype":"venue"
},
  "geometry": {"coordinates":[-97.32983,41.441347],"type":"Point"}
}