{
  "type": "Feature",
  "properties": {
    "addr:full":"18484 Cornhusker Rd Omaha NE 68136",
    "addr:housenumber":"18484",
    "addr:postcode":"68136",
    "addr:street":"Cornhusker Rd",
    "iso:country":"US",
    "sg:address":"18484 Cornhusker Rd",
    "sg:city":"Omaha",
    "sg:phone":"+1 402 332 3594",
    "sg:postcode":"68136",
    "sg:province":"NE",
    "sg:tags":[
        "farm",
        "corn",
        "soybean"
    ],
    "wof:name":"Barkley Farms",
    "wof:placetype":"venue"
},
  "geometry": {"coordinates":[-96.20387100000001,41.16158],"type":"Point"}
}