{
  "type": "Feature",
  "properties": {
    "iso:country":"US",
    "sg:address":"3912 Linden Dr",
    "sg:city":"Kearney",
    "sg:classifiers":[
        {
            "category":"Building & Trades",
            "subcategory":"Construction",
            "type":"Services"
        }
    ],
    "sg:phone":"+1 308 234 4599",
    "sg:postcode":"68847",
    "sg:province":"NE",
    "sg:tags":[
        "hanging",
        "contractor"
    ],
    "wof:name":"BR Painting",
    "wof:placetype":"venue"
},
  "geometry": {"coordinates":[-99.075416,40.715965],"type":"Point"}
}