{
  "type": "Feature",
  "properties": {
    "iso:country":"US",
    "sg:address":"710 Ord Ave",
    "sg:city":"Curtis",
    "sg:classifiers":[
        {
            "category":"Wholesale",
            "subcategory":"Farm Supplies",
            "type":"Manufacturing & Wholesale Goods"
        }
    ],
    "sg:phone":"+1 308 367 5518",
    "sg:postcode":"69025",
    "sg:province":"NE",
    "wof:name":"Thompson's Farm Supply",
    "wof:placetype":"venue"
},
  "geometry": {"coordinates":[-100.518064,40.635095],"type":"Point"}
}