{
  "type": "Feature",
  "properties": {
    "iso:country":"US",
    "sg:address":"1720 Ave B",
    "sg:city":"Scottsbluff",
    "sg:classifiers":[
        {
            "category":"Retail",
            "subcategory":"Auto Repair",
            "type":"Services"
        }
    ],
    "sg:phone":"+1 308 632 4169",
    "sg:postcode":"69361",
    "sg:province":"NE",
    "sg:tags":[
        "brake"
    ],
    "wof:name":"Wholesale Motive Svc",
    "wof:placetype":"venue"
},
  "geometry": {"coordinates":[-103.66559100000001,41.864043],"type":"Point"}
}