{
  "type": "Feature",
  "properties": {
    "addr:full":"12510 S 29th Ave Bellevue NE 68123",
    "addr:housenumber":"12510",
    "addr:postcode":"68123",
    "addr:street":"S 29Th Ave",
    "iso:country":"US",
    "sg:address":"12510 S 29th Ave",
    "sg:city":"Bellevue",
    "sg:classifiers":[
        {
            "category":"Restaurant",
            "type":"Food & Drink"
        }
    ],
    "sg:phone":"+1 402 292 0102",
    "sg:postcode":"68123",
    "sg:province":"NE",
    "sg:tags":[
        "eating"
    ],
    "wof:name":"Lil' Burro",
    "wof:placetype":"venue"
},
  "geometry": {"coordinates":[-95.956793,41.126152],"type":"Point"}
}