{
  "type": "Feature",
  "properties": {
    "iso:country":"US",
    "sg:address":"2701 S 49th St",
    "sg:city":"Omaha",
    "sg:classifiers":[
        {
            "category":"Building & Trades",
            "subcategory":"Landscaping Services",
            "type":"Services"
        }
    ],
    "sg:phone":"+1 402 884 2517",
    "sg:postcode":"68106",
    "sg:province":"NE",
    "sg:tags":[
        "lawn",
        "maintenance",
        "grounds"
    ],
    "wof:name":"Great Plains Turf Inc",
    "wof:placetype":"venue"
},
  "geometry": {"coordinates":[-95.987837,41.230626],"type":"Point"}
}