{
  "type": "Feature",
  "properties": {
    "addr:full":"105 State Hwy 44 Wilcox NE 68924",
    "addr:housenumber":"105",
    "addr:postcode":"68924",
    "addr:street":"State Hwy 44",
    "iso:country":"US",
    "sg:address":"105 State Hwy 44",
    "sg:city":"Wilcox",
    "sg:classifiers":[
        {
            "category":"Retail",
            "subcategory":"Veterinary Services",
            "type":"Services"
        }
    ],
    "sg:phone":"+1 308 478 5427",
    "sg:postcode":"68924",
    "sg:province":"NE",
    "wof:name":"Adam Veterinary Services",
    "wof:placetype":"venue"
},
  "geometry": {"coordinates":[-99.16052000000001,40.360108],"type":"Point"}
}