{
  "type": "Feature",
  "properties": {
    "addr:full":"1015 S Webb Rd Grand Island NE 68803",
    "addr:housenumber":"1015",
    "addr:postcode":"68803",
    "addr:street":"S Webb Rd",
    "iso:country":"US",
    "sg:address":"1015 S Webb Rd",
    "sg:city":"Grand Island",
    "sg:classifiers":[
        {
            "category":"Autos & Motor Vehicles",
            "subcategory":"Automobile Sales",
            "type":"Retail Goods"
        }
    ],
    "sg:phone":"+1 308 384 9775",
    "sg:postcode":"68803",
    "sg:province":"NE",
    "sg:tags":[
        "car",
        "dealer"
    ],
    "wof:name":"Express Auto Sales",
    "wof:placetype":"venue"
},
  "geometry": {"coordinates":[-98.378342,40.910083],"type":"Point"}
}