{
  "type": "Feature",
  "properties": {
    "iso:country":"US",
    "sg:address":"345 Barger Ave",
    "sg:city":"Hebron",
    "sg:classifiers":[
        {
            "category":"Utilities",
            "subcategory":"Refuse",
            "type":"Services"
        }
    ],
    "sg:phone":"+1 402 768 7233",
    "sg:postcode":"68370",
    "sg:province":"NE",
    "sg:tags":[
        "garbage",
        "collection"
    ],
    "wof:name":"Garbage Co South",
    "wof:placetype":"venue"
},
  "geometry": {"coordinates":[-97.59135499999999,40.172568],"type":"Point"}
}