{
  "type": "Feature",
  "properties": {
    "iso:country":"US",
    "sg:address":"1717 S 56th St",
    "sg:city":"Omaha",
    "sg:classifiers":[
        {
            "category":"Internet Cafe",
            "subcategory":"None",
            "type":"Food & Drink"
        },
        {
            "category":"Professional",
            "subcategory":"Computer Services",
            "type":"Services"
        }
    ],
    "sg:phone":"+1 402 933 5330",
    "sg:postcode":"68106",
    "sg:province":"NE",
    "sg:tags":[
        "product",
        "designer",
        "network",
        "consultant",
        "system",
        "design",
        "software"
    ],
    "wof:name":"Sandhills Technologies Bruce Botkin",
    "wof:placetype":"venue"
},
  "geometry": {"coordinates":[-95.999864,41.243294],"type":"Point"}
}