{
  "type": "Feature",
  "properties": {
    "addr:full":"767 N Main St Long Pine NE 69217",
    "addr:housenumber":"767",
    "addr:postcode":"69217",
    "addr:street":"N Main St",
    "iso:country":"US",
    "sg:address":"767 N Main St",
    "sg:city":"Long Pine",
    "sg:classifiers":[
        {
            "category":"Retail",
            "subcategory":"Portrait Studio",
            "type":"Services"
        }
    ],
    "sg:phone":"+1 402 273 4189",
    "sg:postcode":"69217",
    "sg:province":"NE",
    "sg:tags":[
        "photographer"
    ],
    "wof:name":"Lohmeyer Photography",
    "wof:placetype":"venue"
},
  "geometry": {"coordinates":[-99.700907,42.538735],"type":"Point"}
}