{
  "type": "Feature",
  "properties": {
    "iso:country":"US",
    "sg:address":"219 N Dewey St",
    "sg:city":"North Platte",
    "sg:classifiers":[
        {
            "category":"Professional",
            "subcategory":"Business Services",
            "type":"Services"
        }
    ],
    "sg:phone":"+1 308 532 4729",
    "sg:postcode":"69101",
    "sg:province":"NE",
    "sg:tags":[
        "executive"
    ],
    "wof:name":"North Platte/Lincoln County",
    "wof:placetype":"venue"
},
  "geometry": {"coordinates":[-100.762333,41.134706],"type":"Point"}
}