{
  "type": "Feature",
  "properties": {
    "iso:country":"US",
    "sg:address":"1133 Q St",
    "sg:city":"Lincoln",
    "sg:classifiers":[
        {
            "category":"Restaurant",
            "type":"Food & Drink"
        }
    ],
    "sg:menulink":"http://www.allmenus.com/ne/lincoln/89748-applebees/menu/",
    "sg:phone":"+1 402 476 5165",
    "sg:postcode":"68508",
    "sg:province":"NE",
    "sg:tags":[
        "burger",
        "american",
        "sandwich",
        "soup"
    ],
    "wof:name":"Applebee's",
    "wof:placetype":"venue"
},
  "geometry": {"coordinates":[-96.70489000000001,40.815688],"type":"Point"}
}