{
  "type": "Feature",
  "properties": {
    "iso:country":"US",
    "sg:address":"3439 23rd St",
    "sg:city":"Columbus",
    "sg:classifiers":[
        {
            "category":"Manufacturing",
            "subcategory":"Tools & Machinery",
            "type":"Manufacturing & Wholesale Goods"
        }
    ],
    "sg:phone":"+1 402 564 7161",
    "sg:postcode":"68601",
    "sg:province":"NE",
    "sg:tags":[
        "farm",
        "equipment",
        "mfg"
    ],
    "wof:name":"Kosch Co",
    "wof:placetype":"venue"
},
  "geometry": {"coordinates":[-97.370327,41.438655],"type":"Point"}
}