{
  "type": "Feature",
  "properties": {
    "iso:country":"US",
    "sg:address":"190520 Hwy 26",
    "sg:city":"Scottsbluff",
    "sg:classifiers":[
        {
            "category":"Autos & Motor Vehicles",
            "subcategory":"Auto Supplies",
            "type":"Retail Goods"
        },
        {
            "category":"Wholesale",
            "subcategory":"Auto Parts",
            "type":"Manufacturing & Wholesale Goods"
        }
    ],
    "sg:phone":"+1 308 635 7310",
    "sg:postcode":"69361",
    "sg:province":"NE",
    "sg:tags":[
        "hitch",
        "installation",
        "sales",
        "trailer",
        "pick"
    ],
    "wof:name":"Hitches Galore",
    "wof:placetype":"venue"
},
  "geometry": {"coordinates":[-103.703864,41.889191],"type":"Point"}
}