{
  "type": "Feature",
  "properties": {
    "addr:full":"2428 Franklin St Omaha NE 68111",
    "addr:housenumber":"2428",
    "addr:postcode":"68111",
    "addr:street":"Franklin St",
    "iso:country":"US",
    "sg:address":"2428 Franklin St",
    "sg:city":"Omaha",
    "sg:classifiers":[
        {
            "category":"Organizations",
            "subcategory":"Religious Organization",
            "type":"Services"
        }
    ],
    "sg:phone":"+1 402 342 0297",
    "sg:postcode":"68111",
    "sg:province":"NE",
    "sg:tags":[
        "church"
    ],
    "wof:name":"Bethel A M E Church",
    "wof:placetype":"venue"
},
  "geometry": {"coordinates":[-95.948196,41.274785],"type":"Point"}
}