{
  "type": "Feature",
  "properties": {
    "iso:country":"US",
    "sg:address":"2413 S 43rd St",
    "sg:city":"Omaha",
    "sg:classifiers":[
        {
            "category":"Building & Trades",
            "subcategory":"Locksmith",
            "type":"Services"
        }
    ],
    "sg:phone":"+1 402 881 3642",
    "sg:postcode":"68105",
    "sg:province":"NE",
    "sg:tags":[
        "key"
    ],
    "wof:name":"A B C 24 Hour Locksmith",
    "wof:placetype":"venue"
},
  "geometry": {"coordinates":[-95.976827,41.236891],"type":"Point"}
}