{
  "type": "Feature",
  "properties": {
    "addr:full":"114 W Mission Ave Bellevue NE 68005",
    "addr:housenumber":"114",
    "addr:postcode":"68005",
    "addr:street":"W Mission Ave",
    "iso:country":"US",
    "sg:address":"114 W Mission Ave",
    "sg:city":"Bellevue",
    "sg:classifiers":[
        {
            "category":"Building & Trades",
            "subcategory":"Plumbing",
            "type":"Services"
        }
    ],
    "sg:phone":"+1 402 291 5808",
    "sg:postcode":"68005",
    "sg:province":"NE",
    "sg:tags":[
        "cont",
        "duct",
        "work",
        "system",
        "air",
        "ventilation",
        "heating",
        "conditioning",
        "contractor"
    ],
    "wof:name":"Apollo Heating & Air",
    "wof:placetype":"venue"
},
  "geometry": {"coordinates":[-95.894914,41.136554],"type":"Point"}
}