{
  "type": "Feature",
  "properties": {
    "addr:full":"14306 Giles Rd Omaha NE 68138",
    "addr:housenumber":"14306",
    "addr:postcode":"68138",
    "addr:street":"Giles Rd",
    "iso:country":"US",
    "sg:address":"14306 Giles Rd",
    "sg:city":"Omaha",
    "sg:classifiers":[
        {
            "category":"Manufacturing",
            "subcategory":"Glass & Minerals",
            "type":"Manufacturing & Wholesale Goods"
        }
    ],
    "sg:phone":"+1 402 896 0900",
    "sg:postcode":"68138",
    "sg:province":"NE",
    "sg:tags":[
        "building",
        "mfg",
        "concrete",
        "brick",
        "block",
        "structural"
    ],
    "wof:name":"Watkins Concrete Block Company",
    "wof:placetype":"venue"
},
  "geometry": {"coordinates":[-96.137152,41.176345],"type":"Point"}
}