{
  "type": "Feature",
  "properties": {
    "iso:country":"US",
    "sg:address":"6000 N Front Rd",
    "sg:city":"North Platte",
    "sg:classifiers":[
        {
            "category":"Building & Trades",
            "subcategory":"Construction",
            "type":"Services"
        }
    ],
    "sg:phone":"+1 308 534 3689",
    "sg:postcode":"69101",
    "sg:province":"NE",
    "sg:tags":[
        "railroad",
        "contractor"
    ],
    "wof:name":"Mobile Rail Svc",
    "wof:placetype":"venue"
},
  "geometry": {"coordinates":[-100.887372,41.187384],"type":"Point"}
}