{
  "type": "Feature",
  "properties": {
    "addr:full":"310 6th St Arapahoe NE 68922",
    "addr:housenumber":"310",
    "addr:postcode":"68922",
    "addr:street":"6Th St",
    "iso:country":"US",
    "sg:address":"310 6th St",
    "sg:city":"Arapahoe",
    "sg:classifiers":[
        {
            "category":"Freight",
            "type":"Transportation"
        }
    ],
    "sg:phone":"+1 308 962 7981",
    "sg:postcode":"68922",
    "sg:province":"NE",
    "sg:tags":[
        "trucking"
    ],
    "wof:name":"W J Carpenter Inc",
    "wof:placetype":"venue"
},
  "geometry": {"coordinates":[-99.89615999999999,40.301589],"type":"Point"}
}