{
  "type": "Feature",
  "properties": {
    "iso:country":"US",
    "sg:address":"9609 N 156th St",
    "sg:city":"Bennington",
    "sg:classifiers":[
        {
            "category":"Building & Trades",
            "subcategory":"Construction",
            "type":"Services"
        }
    ],
    "sg:phone":"+1 402 238 3247",
    "sg:postcode":"68007",
    "sg:province":"NE",
    "sg:tags":[
        "house"
    ],
    "wof:name":"Tom Nick",
    "wof:placetype":"venue"
},
  "geometry": {"coordinates":[-96.15839200000001,41.346727],"type":"Point"}
}