{
  "type": "Feature",
  "properties": {
    "addr:full":"4865 S 136th St Omaha NE 68137",
    "addr:housenumber":"4865",
    "addr:postcode":"68137",
    "addr:street":"S 136Th St",
    "iso:country":"US",
    "sg:address":"4865 S 136th St",
    "sg:city":"Omaha",
    "sg:classifiers":[
        {
            "category":"Building & Trades",
            "subcategory":"Plumbing",
            "type":"Services"
        }
    ],
    "sg:phone":"+1 402 895 4722",
    "sg:postcode":"68137",
    "sg:province":"NE",
    "sg:tags":[
        "plumbing",
        "contractor"
    ],
    "wof:name":"Plambeck Plumbing Inc",
    "wof:placetype":"venue"
},
  "geometry": {"coordinates":[-96.125686,41.209095],"type":"Point"}
}