{
  "type": "Feature",
  "properties": {
    "iso:country":"US",
    "sg:address":"2116 N Custer Ave",
    "sg:city":"Grand Island",
    "sg:classifiers":[
        {
            "category":"Building & Trades",
            "subcategory":"Plumbing",
            "type":"Services"
        }
    ],
    "sg:phone":"+1 308 384 4467",
    "sg:postcode":"68803",
    "sg:province":"NE",
    "sg:tags":[
        "contractor"
    ],
    "wof:name":"ONeill Heating & AC",
    "wof:placetype":"venue"
},
  "geometry": {"coordinates":[-98.368522,40.941117],"type":"Point"}
}