{
  "type": "Feature",
  "properties": {
    "iso:country":"US",
    "sg:address":"4544 S 133rd St",
    "sg:city":"Omaha",
    "sg:classifiers":[
        {
            "category":"Professional",
            "subcategory":"Detective & Security Services",
            "type":"Services"
        },
        {
            "category":"Building & Trades",
            "subcategory":"Electrical",
            "type":"Services"
        },
        {
            "category":"Government",
            "subcategory":"Fire Station",
            "type":"Public Place"
        },
        {
            "category":"Home & Garden",
            "subcategory":"Hardware",
            "type":"Retail Goods"
        },
        {
            "category":"Manufacturing",
            "subcategory":"Electronics",
            "type":"Manufacturing & Wholesale Goods"
        },
        {
            "category":"Personal",
            "type":"Services"
        },
        {
            "category":"Manufacturing",
            "subcategory":"Building Materials",
            "type":"Manufacturing & Wholesale Goods"
        }
    ],
    "sg:phone":"+1 402 333 4600",
    "sg:postcode":"68137",
    "sg:province":"NE",
    "sg:tags":[
        "control",
        "industrial",
        "monitoring",
        "supply",
        "equipment-wholesale",
        "consultant",
        "medical",
        "commercial",
        "system",
        "systems-wholesale",
        "equipment",
        "protection",
        "smoke",
        "sprinklers-residential",
        "detector",
        "automatic",
        "alarm",
        "manufacturer"
    ],
    "wof:name":"Continental Alarm & Detection Company",
    "wof:placetype":"venue"
},
  "geometry": {"coordinates":[-96.121407,41.213987],"type":"Point"}
}