{
  "type": "Feature",
  "properties": {
    "addr:full":"313 Main St Neligh NE 68756",
    "addr:housenumber":"313",
    "addr:postcode":"68756",
    "addr:street":"Main St",
    "iso:country":"US",
    "sg:address":"313 Main St",
    "sg:city":"Neligh",
    "sg:classifiers":[
        {
            "category":"Professional",
            "subcategory":"Accounting & Tax Preparation",
            "type":"Services"
        }
    ],
    "sg:phone":"+1 402 887 4404",
    "sg:postcode":"68756",
    "sg:province":"NE",
    "sg:tags":[
        "accountant"
    ],
    "wof:name":"Auten Sehi Pruss & Beckmann",
    "wof:placetype":"venue"
},
  "geometry": {"coordinates":[-98.02982,42.128464],"type":"Point"}
}