{
  "type": "Feature",
  "properties": {
    "addr:full":"3500 Central Ave Kearney NE 68847",
    "addr:housenumber":"3500",
    "addr:postcode":"68847",
    "addr:street":"Central Ave",
    "iso:country":"US",
    "sg:address":"3500 Central Ave",
    "sg:city":"Kearney",
    "sg:classifiers":[
        {
            "category":"Professional",
            "type":"Services"
        }
    ],
    "sg:phone":"+1 308 865 1414",
    "sg:postcode":"68847",
    "sg:province":"NE",
    "sg:tags":[
        "establishment"
    ],
    "wof:name":"Nebraska Joint Replacement Ctr",
    "wof:placetype":"venue"
},
  "geometry": {"coordinates":[-99.082054,40.710467],"type":"Point"}
}