{
  "type": "Feature",
  "properties": {
    "addr:full":"9002 Maple St Omaha NE 68134",
    "addr:housenumber":"9002",
    "addr:postcode":"68134",
    "addr:street":"Maple St",
    "iso:country":"US",
    "sg:address":"9002 Maple St",
    "sg:city":"Omaha",
    "sg:classifiers":[
        {
            "category":"Cinema",
            "subcategory":"Movie Rental",
            "type":"Entertainment"
        }
    ],
    "sg:phone":"+1 402 571 0919",
    "sg:postcode":"68134",
    "sg:province":"NE",
    "sg:tags":[
        "leasing",
        "video",
        "disc",
        "tape"
    ],
    "wof:name":"Blockbuster Video",
    "wof:placetype":"venue"
},
  "geometry": {"coordinates":[-96.055857,41.285142],"type":"Point"}
}