{
  "type": "Feature",
  "properties": {
    "iso:country":"US",
    "sg:address":"1307 N Juniata Ave",
    "sg:city":"Juniata",
    "sg:classifiers":[
        {
            "category":"Restaurant",
            "type":"Food & Drink"
        }
    ],
    "sg:phone":"+1 402 751 2414",
    "sg:postcode":"68955",
    "sg:province":"NE",
    "sg:tags":[
        "out"
    ],
    "wof:name":"Casey's Carry Out Pizza",
    "wof:placetype":"venue"
},
  "geometry": {"coordinates":[-98.506697,40.601094],"type":"Point"}
}