{
  "type": "Feature",
  "properties": {
    "addr:full":"521 N 3rd St Hebron NE 68370",
    "addr:housenumber":"521",
    "addr:postcode":"68370",
    "addr:street":"N 3Rd St",
    "iso:country":"US",
    "sg:address":"521 N 3rd St",
    "sg:city":"Hebron",
    "sg:classifiers":[
        {
            "category":"Real Estate",
            "subcategory":"Real Estate Operator",
            "type":"Services"
        }
    ],
    "sg:phone":"+1 402 768 6034",
    "sg:postcode":"68370",
    "sg:province":"NE",
    "sg:tags":[
        "property",
        "lessor"
    ],
    "wof:name":"Ralph Schardt",
    "wof:placetype":"venue"
},
  "geometry": {"coordinates":[-97.592055,40.172403],"type":"Point"}
}