{
  "type": "Feature",
  "properties": {
    "iso:country":"US",
    "sg:address":"1923 Ave B",
    "sg:city":"Kearney",
    "sg:classifiers":[
        {
            "category":"Wholesale",
            "subcategory":"Office Equipment",
            "type":"Manufacturing & Wholesale Goods"
        }
    ],
    "sg:phone":"+1 308 236 4207",
    "sg:postcode":"68847",
    "sg:province":"NE",
    "sg:tags":[
        "machine",
        "mailing"
    ],
    "sg:website":"www.businessofficesystems.com",
    "wof:name":"Business Office Systems",
    "wof:placetype":"venue"
},
  "geometry": {"coordinates":[-99.078993,40.693906],"type":"Point"}
}