{
  "type": "Feature",
  "properties": {
    "addr:full":"2499 Co Rd 18 Ames NE 68621",
    "addr:housenumber":"2499;18",
    "addr:postcode":"68621",
    "addr:street":"Co Rd",
    "iso:country":"US",
    "sg:address":"2499 Co Rd 18",
    "sg:city":"Ames",
    "sg:classifiers":[
        {
            "category":"Building & Trades",
            "subcategory":"Plumbing",
            "type":"Services"
        }
    ],
    "sg:phone":"+1 402 721 5466",
    "sg:postcode":"68621",
    "sg:province":"NE",
    "sg:tags":[
        "septic"
    ],
    "wof:name":"Ruda Septic",
    "wof:placetype":"venue"
},
  "geometry": {"coordinates":[-96.577906,41.452638],"type":"Point"}
}