{
  "type": "Feature",
  "properties": {
    "addr:full":"306 Main St Louisville NE 68037",
    "addr:housenumber":"306",
    "addr:postcode":"68037",
    "addr:street":"Main St",
    "iso:country":"US",
    "sg:address":"306 Main St",
    "sg:city":"Louisville",
    "sg:classifiers":[
        {
            "category":"Autos & Motor Vehicles",
            "subcategory":"Automobile Sales",
            "type":"Retail Goods"
        }
    ],
    "sg:phone":"+1 402 234 2000",
    "sg:postcode":"68037",
    "sg:province":"NE",
    "sg:tags":[
        "car"
    ],
    "wof:name":"Copple Chevrolet-GMC Inc",
    "wof:placetype":"venue"
},
  "geometry": {"coordinates":[-96.1399,41.000801],"type":"Point"}
}