{
  "type": "Feature",
  "properties": {
    "addr:full":"5108 Valley Forge Rd Lincoln NE 68521",
    "addr:housenumber":"5108",
    "addr:postcode":"68521",
    "addr:street":"Valley Forge Rd",
    "iso:country":"US",
    "sg:address":"5108 Valley Forge Rd",
    "sg:city":"Lincoln",
    "sg:classifiers":[
        {
            "category":"Personal",
            "type":"Services"
        }
    ],
    "sg:phone":"+1 402 476 6333",
    "sg:postcode":"68521",
    "sg:province":"NE",
    "sg:tags":[
        "interpreter",
        "language",
        "sign"
    ],
    "wof:name":"Kelly Brakenhoff",
    "wof:placetype":"venue"
},
  "geometry": {"coordinates":[-96.688138,40.861832],"type":"Point"}
}