{
  "type": "Feature",
  "properties": {
    "iso:country":"US",
    "sg:address":"1005 W Court St",
    "sg:city":"Beatrice",
    "sg:classifiers":[
        {
            "category":"Home & Garden",
            "subcategory":"Building Materials",
            "type":"Retail Goods"
        }
    ],
    "sg:phone":"+1 402 223 2877",
    "sg:postcode":"68310",
    "sg:province":"NE",
    "sg:tags":[
        "glass",
        "window",
        "plate"
    ],
    "wof:name":"Fisher Auto Glass Inc",
    "wof:placetype":"venue"
},
  "geometry": {"coordinates":[-96.778683,40.265845],"type":"Point"}
}