{
  "type": "Feature",
  "properties": {
    "iso:country":"US",
    "sg:address":"6100 W Little Salt Rd",
    "sg:city":"Valparaiso",
    "sg:classifiers":[
        {
            "category":"Farming",
            "subcategory":"Farm",
            "type":"Manufacturing & Wholesale Goods"
        }
    ],
    "sg:phone":"+1 402 784 2007",
    "sg:postcode":"68065",
    "sg:province":"NE",
    "sg:tags":[
        "crop",
        "general"
    ],
    "wof:name":"Edward Barry",
    "wof:placetype":"venue"
},
  "geometry": {"coordinates":[-96.797763,41.031425],"type":"Point"}
}