{
  "type": "Feature",
  "properties": {
    "addr:full":"320 W Prospect Ave Fremont NE 68025",
    "addr:housenumber":"320",
    "addr:postcode":"68025",
    "addr:street":"W Prospect Ave",
    "iso:country":"US",
    "sg:address":"320 W Prospect Ave",
    "sg:city":"Fremont",
    "sg:classifiers":[
        {
            "category":"Arena",
            "subcategory":"Sports Club",
            "type":"Entertainment"
        }
    ],
    "sg:phone":"+1 402 727 5394",
    "sg:postcode":"68025",
    "sg:province":"NE",
    "wof:name":"Fremont Wrestling Club In",
    "wof:placetype":"venue"
},
  "geometry": {"coordinates":[-96.50196200000001,41.41622],"type":"Point"}
}