{
  "type": "Feature",
  "properties": {
    "addr:full":"304 W E St Hastings NE 68901",
    "addr:housenumber":"304",
    "addr:postcode":"68901",
    "addr:street":"W E St",
    "iso:country":"US",
    "sg:address":"304 W E St",
    "sg:city":"Hastings",
    "sg:classifiers":[
        {
            "category":"Organizations",
            "subcategory":"Religious Organization",
            "type":"Services"
        }
    ],
    "sg:phone":"+1 402 462 8684",
    "sg:postcode":"68901",
    "sg:province":"NE",
    "sg:tags":[
        "church"
    ],
    "wof:name":"United Pentecostal Church",
    "wof:placetype":"venue"
},
  "geometry": {"coordinates":[-98.38618700000001,40.577238],"type":"Point"}
}