{
  "type": "Feature",
  "properties": {
    "iso:country":"US",
    "sg:address":"330 Seward St",
    "sg:city":"Seward",
    "sg:classifiers":[
        {
            "category":"Building & Trades",
            "subcategory":"Plumbing",
            "type":"Services"
        }
    ],
    "sg:phone":"+1 402 643 7501",
    "sg:postcode":"68434",
    "sg:province":"NE",
    "sg:tags":[
        "conditioning",
        "air",
        "system",
        "contractor"
    ],
    "wof:name":"Milford A/C & Appliance Inc",
    "wof:placetype":"venue"
},
  "geometry": {"coordinates":[-97.09639199999999,40.90786],"type":"Point"}
}