{
  "type": "Feature",
  "properties": {
    "addr:full":"17837 Pierce Plz Omaha NE 68130",
    "addr:housenumber":"17837",
    "addr:postcode":"68130",
    "addr:street":"Pierce Plz",
    "iso:country":"US",
    "sg:address":"17837 Pierce Plz",
    "sg:city":"Omaha",
    "sg:classifiers":[
        {
            "category":"Personal",
            "subcategory":"Beauty Salon",
            "type":"Services"
        }
    ],
    "sg:phone":"+1 402 330 3899",
    "sg:postcode":"68130",
    "sg:province":"NE",
    "sg:tags":[
        "spa",
        "day"
    ],
    "sg:website":"www.mconstantinosalon.com",
    "wof:name":"M Constantino Salon & Day Spa",
    "wof:placetype":"venue"
},
  "geometry": {"coordinates":[-96.19555099999999,41.246917],"type":"Point"}
}