{
  "type": "Feature",
  "properties": {
    "iso:country":"US",
    "sg:address":"701 Tara Rd",
    "sg:city":"Papillion",
    "sg:classifiers":[
        {
            "category":"Shopping",
            "subcategory":"Clothing, Apparel, & Fashions",
            "type":"Retail Goods"
        }
    ],
    "sg:phone":"+1 402 339 2189",
    "sg:postcode":"68046",
    "sg:province":"NE",
    "sg:tags":[
        "tailor"
    ],
    "wof:name":"Diane's Tailoring",
    "wof:placetype":"venue"
},
  "geometry": {"coordinates":[-96.03678600000001,41.165321],"type":"Point"}
}