{
  "type": "Feature",
  "properties": {
    "addr:full":"1005 N 4th St Oneill NE 68763",
    "addr:housenumber":"1005",
    "addr:postcode":"68763",
    "addr:street":"N 4Th St",
    "iso:country":"US",
    "sg:address":"1005 N 4th St",
    "sg:city":"Oneill",
    "sg:classifiers":[
        {
            "category":"Farming",
            "subcategory":"Livestock Farm",
            "type":"Manufacturing & Wholesale Goods"
        }
    ],
    "sg:phone":"+1 402 336 2509",
    "sg:postcode":"68763",
    "sg:province":"NE",
    "sg:tags":[
        "beef",
        "feedlot",
        "cattle"
    ],
    "wof:name":"Michael Shoemaker",
    "wof:placetype":"venue"
},
  "geometry": {"coordinates":[-98.647966,42.464954],"type":"Point"}
}