{
  "type": "Feature",
  "properties": {
    "addr:full":"8742 Frederick St Omaha NE 68124",
    "addr:housenumber":"8742",
    "addr:postcode":"68124",
    "addr:street":"Frederick St",
    "iso:country":"US",
    "sg:address":"8742 Frederick St",
    "sg:city":"Omaha",
    "sg:classifiers":[
        {
            "category":"Professional",
            "subcategory":"Lawyer & Legal Services",
            "type":"Services"
        }
    ],
    "sg:phone":"+1 402 393 5600",
    "sg:postcode":"68124",
    "sg:province":"NE",
    "sg:tags":[
        "attorney"
    ],
    "wof:name":"Young & White",
    "wof:placetype":"venue"
},
  "geometry": {"coordinates":[-96.050332,41.231375],"type":"Point"}
}