{
  "type": "Feature",
  "properties": {
    "iso:country":"US",
    "sg:address":"2050 E 23rd St",
    "sg:city":"Fremont",
    "sg:classifiers":[
        {
            "category":"Retail",
            "subcategory":"Auto Repair",
            "type":"Services"
        }
    ],
    "sg:phone":"+1 402 721 5782",
    "sg:postcode":"68025",
    "sg:province":"NE",
    "sg:tags":[
        "truck"
    ],
    "sg:website":"www.larsenintl.com",
    "wof:name":"Larsen International Inc",
    "wof:placetype":"venue"
},
  "geometry": {"coordinates":[-96.472126,41.451284],"type":"Point"}
}