{
  "type": "Feature",
  "properties": {
    "addr:full":"4990 G St Omaha NE 68117",
    "addr:housenumber":"4990",
    "addr:postcode":"68117",
    "addr:street":"G St",
    "iso:country":"US",
    "sg:address":"4990 G St",
    "sg:city":"Omaha",
    "sg:classifiers":[
        {
            "category":"Personal",
            "type":"Services"
        }
    ],
    "sg:phone":"+1 402 734 8880",
    "sg:postcode":"68117",
    "sg:province":"NE",
    "sg:tags":[
        "party",
        "planning",
        "event"
    ],
    "sg:website":"www.fundways-tops.com",
    "wof:name":"Fundways Tops",
    "wof:placetype":"venue"
},
  "geometry": {"coordinates":[-95.990239,41.217378],"type":"Point"}
}