{
  "type": "Feature",
  "properties": {
    "iso:country":"US",
    "sg:address":"14172 N St",
    "sg:city":"Omaha",
    "sg:classifiers":[
        {
            "category":"Professional",
            "subcategory":"Research",
            "type":"Services"
        }
    ],
    "sg:phone":"+1 402 896 0638",
    "sg:postcode":"68137",
    "sg:province":"NE",
    "sg:tags":[
        "nonphysical",
        "commercial"
    ],
    "wof:name":"Nelson Marketing",
    "wof:placetype":"venue"
},
  "geometry": {"coordinates":[-96.13506099999999,41.209589],"type":"Point"}
}