{
  "type": "Feature",
  "properties": {
    "addr:full":"1303 E 32nd St Kearney NE 68847",
    "addr:housenumber":"1303",
    "addr:postcode":"68847",
    "addr:street":"E 32Nd St",
    "iso:country":"US",
    "sg:address":"1303 E 32nd St",
    "sg:city":"Kearney",
    "sg:classifiers":[
        {
            "category":"Wholesale",
            "subcategory":"Hardware",
            "type":"Manufacturing & Wholesale Goods"
        }
    ],
    "sg:phone":"+1 308 237 7766",
    "sg:postcode":"68847",
    "sg:province":"NE",
    "sg:tags":[
        "refrigerating"
    ],
    "wof:name":"Cool-Tech Refrigeration",
    "wof:placetype":"venue"
},
  "geometry": {"coordinates":[-99.064848,40.706959],"type":"Point"}
}