{
  "type": "Feature",
  "properties": {
    "iso:country":"US",
    "sg:address":"502 East Ave",
    "sg:city":"Holdrege",
    "sg:classifiers":[
        {
            "category":"Government",
            "subcategory":"Office",
            "type":"Public Place"
        }
    ],
    "sg:phone":"+1 308 995 4148",
    "sg:postcode":"68949",
    "sg:province":"NE",
    "sg:tags":[
        "county"
    ],
    "wof:name":"Phelps County Development Corp",
    "wof:placetype":"venue"
},
  "geometry": {"coordinates":[-99.369781,40.439969],"type":"Point"}
}