{
  "type": "Feature",
  "properties": {
    "addr:full":"830 S Sumner St Beatrice NE 68310",
    "addr:housenumber":"830",
    "addr:postcode":"68310",
    "addr:street":"S Sumner St",
    "iso:country":"US",
    "sg:address":"830 S Sumner St",
    "sg:city":"Beatrice",
    "sg:classifiers":[
        {
            "category":"Retail",
            "subcategory":"Repair Shop",
            "type":"Services"
        }
    ],
    "sg:phone":"+1 402 223 5443",
    "sg:postcode":"68310",
    "sg:province":"NE",
    "sg:tags":[
        "welding"
    ],
    "wof:name":"Vans Welding Fabg & Sndblst",
    "wof:placetype":"venue"
},
  "geometry": {"coordinates":[-96.765473,40.257267],"type":"Point"}
}