{
  "type": "Feature",
  "properties": {
    "iso:country":"US",
    "sg:address":"247 Rutland Ave",
    "sg:city":"Malmo",
    "sg:classifiers":[
        {
            "category":"Organizations",
            "subcategory":"Religious Organization",
            "type":"Services"
        }
    ],
    "sg:phone":"+1 402 642 5842",
    "sg:postcode":"68040",
    "sg:province":"NE",
    "sg:tags":[
        "church"
    ],
    "wof:name":"Edensburg Lutheran Church",
    "wof:placetype":"venue"
},
  "geometry": {"coordinates":[-96.723491,41.266382],"type":"Point"}
}