{
  "type": "Feature",
  "properties": {
    "iso:country":"US",
    "sg:address":"2276 N Webb Rd",
    "sg:city":"Grand Island",
    "sg:classifiers":[
        {
            "category":"Shopping",
            "subcategory":"Shoes",
            "type":"Retail Goods"
        }
    ],
    "sg:phone":"+1 308 398 2668",
    "sg:postcode":"68803",
    "sg:province":"NE",
    "wof:name":"Industrial Outfitters",
    "wof:placetype":"venue"
},
  "geometry": {"coordinates":[-98.37876799999999,40.943483],"type":"Point"}
}