{
  "type": "Feature",
  "properties": {
    "addr:full":"501 W Jefferson St Beatrice NE 68310",
    "addr:housenumber":"501",
    "addr:postcode":"68310",
    "addr:street":"W Jefferson St",
    "iso:country":"US",
    "sg:address":"501 W Jefferson St",
    "sg:city":"Beatrice",
    "sg:classifiers":[
        {
            "category":"Retail",
            "subcategory":"Repair Shop",
            "type":"Services"
        }
    ],
    "sg:phone":"+1 402 228 4632",
    "sg:postcode":"68310",
    "sg:province":"NE",
    "wof:name":"Garys Repair",
    "wof:placetype":"venue"
},
  "geometry": {"coordinates":[-96.75787,40.274074],"type":"Point"}
}