{
  "type": "Feature",
  "properties": {
    "addr:full":"520 Meridian St Chester NE 68327",
    "addr:housenumber":"520",
    "addr:postcode":"68327",
    "addr:street":"Meridian St",
    "iso:country":"US",
    "sg:address":"520 Meridian St",
    "sg:city":"Chester",
    "sg:classifiers":[
        {
            "category":"Autos & Motor Vehicles",
            "subcategory":"Fuel & Gas Station",
            "type":"Retail Goods"
        }
    ],
    "sg:phone":"+1 402 324 5364",
    "sg:postcode":"68327",
    "sg:province":"NE",
    "sg:tags":[
        "oil"
    ],
    "wof:name":"Foote Service Inc",
    "wof:placetype":"venue"
},
  "geometry": {"coordinates":[-97.61399400000001,40.0098],"type":"Point"}
}