{
  "type": "Feature",
  "properties": {
    "iso:country":"US",
    "sg:address":"8029 S 83rd Ave",
    "sg:city":"La Vista",
    "sg:classifiers":[
        {
            "category":"Deli",
            "type":"Food & Drink"
        }
    ],
    "sg:menulink":"http://www.allmenus.com/ne/la-vista/126244-blimpie-subs--sandwiches/menu/",
    "sg:phone":"+1 402 592 4800",
    "sg:postcode":"68128",
    "sg:province":"NE",
    "sg:tags":[
        "wrap",
        "american",
        "sandwich"
    ],
    "wof:name":"Blimpie Subs & Sandwiches",
    "wof:placetype":"venue"
},
  "geometry": {"coordinates":[-96.04003299999999,41.182109],"type":"Point"}
}