{
  "type": "Feature",
  "properties": {
    "iso:country":"US",
    "sg:address":"4396 West St",
    "sg:city":"Blair",
    "sg:classifiers":[
        {
            "category":"Real Estate",
            "subcategory":"Real Estate Agent",
            "type":"Services"
        }
    ],
    "sg:phone":"+1 402 533 9088",
    "sg:postcode":"68008",
    "sg:province":"NE",
    "wof:name":"Motel California",
    "wof:placetype":"venue"
},
  "geometry": {"coordinates":[-96.121486,41.439615],"type":"Point"}
}