{
  "type": "Feature",
  "properties": {
    "addr:full":"3423 2nd Ave Kearney NE 68847",
    "addr:housenumber":"3423",
    "addr:postcode":"68847",
    "addr:street":"2Nd Ave",
    "iso:country":"US",
    "sg:address":"3423 2nd Ave",
    "sg:city":"Kearney",
    "sg:classifiers":[
        {
            "category":"Government",
            "subcategory":"Office",
            "type":"Public Place"
        }
    ],
    "sg:phone":"+1 308 865 5363",
    "sg:postcode":"68847",
    "sg:province":"NE",
    "sg:tags":[
        "state",
        "program",
        "health"
    ],
    "wof:name":"Health & Human Svc",
    "wof:placetype":"venue"
},
  "geometry": {"coordinates":[-99.083945,40.710339],"type":"Point"}
}