{
  "type": "Feature",
  "properties": {
    "addr:full":"1311 Harlan Dr Bellevue NE 68005",
    "addr:housenumber":"1311",
    "addr:postcode":"68005",
    "addr:street":"Harlan Dr",
    "iso:country":"US",
    "sg:address":"1311 Harlan Dr",
    "sg:city":"Bellevue",
    "sg:classifiers":[
        {
            "category":"Insurance",
            "subcategory":"Insurance Agent",
            "type":"Services"
        }
    ],
    "sg:phone":"+1 402 291 3550",
    "sg:postcode":"68005",
    "sg:province":"NE",
    "sg:website":"www.bellevueinsurance.com",
    "wof:name":"Bellevue Insurance",
    "wof:placetype":"venue"
},
  "geometry": {"coordinates":[-95.91044100000001,41.141143],"type":"Point"}
}