{
  "type": "Feature",
  "properties": {
    "addr:full":"2208 Broadway Scottsbluff NE 69361",
    "addr:housenumber":"2208",
    "addr:postcode":"69361",
    "addr:street":"Broadway",
    "iso:country":"US",
    "sg:address":"2208 Broadway",
    "sg:city":"Scottsbluff",
    "sg:classifiers":[
        {
            "category":"Health Services",
            "subcategory":"Health Practitioner",
            "type":"Services"
        }
    ],
    "sg:phone":"+1 308 632 8084",
    "sg:postcode":"69361",
    "sg:province":"NE",
    "sg:tags":[
        "psychologist"
    ],
    "wof:name":"Jeanna D Townsend",
    "wof:placetype":"venue"
},
  "geometry": {"coordinates":[-103.662955,41.86948],"type":"Point"}
}