{
  "type": "Feature",
  "properties": {
    "iso:country":"US",
    "sg:address":"6679 Sorensen Pkwy",
    "sg:city":"Omaha",
    "sg:classifiers":[
        {
            "category":"Building & Trades",
            "subcategory":"Cleaning & Sanitation",
            "type":"Services"
        }
    ],
    "sg:phone":"+1 402 572 5657",
    "sg:postcode":"68152",
    "sg:province":"NE",
    "sg:tags":[
        "carpet"
    ],
    "wof:name":"Lovely's Steam & Clean",
    "wof:placetype":"venue"
},
  "geometry": {"coordinates":[-96.014496,41.317423],"type":"Point"}
}