{
  "type": "Feature",
  "properties": {
    "iso:country":"US",
    "sg:address":"1720 E 34th St",
    "sg:city":"Kearney",
    "sg:classifiers":[
        {
            "category":"Manufacturing",
            "subcategory":"Building Materials",
            "type":"Manufacturing & Wholesale Goods"
        }
    ],
    "sg:phone":"+1 308 234 2932",
    "sg:postcode":"68847",
    "sg:province":"NE",
    "sg:tags":[
        "mfg",
        "wood",
        "kitchen",
        "cabinet"
    ],
    "wof:name":"Don G Schroer Co",
    "wof:placetype":"venue"
},
  "geometry": {"coordinates":[-99.059541,40.709139],"type":"Point"}
}