{
  "type": "Feature",
  "properties": {
    "iso:country":"US",
    "sg:address":"520 9th St",
    "sg:city":"Gothenburg",
    "sg:classifiers":[
        {
            "category":"Organizations",
            "subcategory":"Religious Organization",
            "type":"Services"
        }
    ],
    "sg:phone":"+1 308 537 7516",
    "sg:postcode":"69138",
    "sg:province":"NE",
    "wof:name":"Faith Chapel",
    "wof:placetype":"venue"
},
  "geometry": {"coordinates":[-100.161008,40.927368],"type":"Point"}
}