{
  "type": "Feature",
  "properties": {
    "addr:full":"1223 S 119th St Omaha NE 68144",
    "addr:housenumber":"1223",
    "addr:postcode":"68144",
    "addr:street":"S 119Th St",
    "iso:country":"US",
    "sg:address":"1223 S 119th St",
    "sg:city":"Omaha",
    "sg:classifiers":[
        {
            "category":"Wholesale",
            "subcategory":"Construction Materials",
            "type":"Manufacturing & Wholesale Goods"
        }
    ],
    "sg:phone":"+1 402 330 4000",
    "sg:postcode":"68144",
    "sg:province":"NE",
    "sg:tags":[
        "fence"
    ],
    "wof:name":"Invisible Fence",
    "wof:placetype":"venue"
},
  "geometry": {"coordinates":[-96.098123,41.24545],"type":"Point"}
}