{
  "type": "Feature",
  "properties": {
    "iso:country":"US",
    "sg:address":"3142 Sequoia Ln",
    "sg:city":"Lincoln",
    "sg:classifiers":[
        {
            "category":"Utilities",
            "type":"Services"
        }
    ],
    "sg:phone":"+1 402 430 6293",
    "sg:postcode":"68516",
    "sg:province":"NE",
    "sg:tags":[
        "sanitary"
    ],
    "wof:name":"Crosstown Plowing Inc",
    "wof:placetype":"venue"
},
  "geometry": {"coordinates":[-96.67496199999999,40.760476],"type":"Point"}
}