{
  "type": "Feature",
  "properties": {
    "iso:country":"US",
    "sg:address":"15431 Co Rd 11",
    "sg:city":"Arlington",
    "sg:phone":"+1 402 478 4838",
    "sg:postcode":"68002",
    "sg:province":"NE",
    "sg:tags":[
        "farm",
        "soybean"
    ],
    "wof:name":"Dean Lallman",
    "wof:placetype":"venue"
},
  "geometry": {"coordinates":[-96.34786800000001,41.607921],"type":"Point"}
}