{
  "type": "Feature",
  "properties": {
    "addr:full":"1516 S Locust St Grand Island NE 68801",
    "addr:housenumber":"1516",
    "addr:postcode":"68801",
    "addr:street":"S Locust St",
    "iso:country":"US",
    "sg:address":"1516 S Locust St",
    "sg:city":"Grand Island",
    "sg:classifiers":[
        {
            "category":"Shopping",
            "subcategory":"Department Store",
            "type":"Retail Goods"
        }
    ],
    "sg:phone":"+1 308 384 3100",
    "sg:postcode":"68801",
    "sg:province":"NE",
    "wof:name":"Family Dollar Store",
    "wof:placetype":"venue"
},
  "geometry": {"coordinates":[-98.339872,40.905106],"type":"Point"}
}