{
  "type": "Feature",
  "properties": {
    "iso:country":"US",
    "sg:address":"204 W Mission Ave",
    "sg:city":"Bellevue",
    "sg:classifiers":[
        {
            "category":"Government",
            "subcategory":"Office",
            "type":"Public Place"
        }
    ],
    "sg:phone":"+1 402 293 3054",
    "sg:postcode":"68005",
    "sg:province":"NE",
    "sg:tags":[
        "village"
    ],
    "wof:name":"Code Enforcement",
    "wof:placetype":"venue"
},
  "geometry": {"coordinates":[-95.896388,41.136557],"type":"Point"}
}