{
  "type": "Feature",
  "properties": {
    "iso:country":"US",
    "sg:address":"12111 Shirley St",
    "sg:city":"Omaha",
    "sg:classifiers":[
        {
            "category":"Communications",
            "subcategory":"Film & Video Production",
            "type":"Services"
        }
    ],
    "sg:phone":"+1 402 333 1598",
    "sg:postcode":"68144",
    "sg:province":"NE",
    "sg:tags":[
        "motion"
    ],
    "wof:name":"Snowy Range Productions",
    "wof:placetype":"venue"
},
  "geometry": {"coordinates":[-96.10293900000001,41.240824],"type":"Point"}
}