{
  "type": "Feature",
  "properties": {
    "iso:country":"US",
    "sg:address":"4034 Hamilton St",
    "sg:city":"Omaha",
    "sg:classifiers":[
        {
            "category":"Building & Trades",
            "subcategory":"Plumbing",
            "type":"Services"
        }
    ],
    "sg:phone":"+1 402 346 0235",
    "sg:postcode":"68131",
    "sg:province":"NE",
    "sg:tags":[
        "plumbing",
        "contractor"
    ],
    "wof:name":"Brooke Peters Plumbing",
    "wof:placetype":"venue"
},
  "geometry": {"coordinates":[-95.973434,41.272215],"type":"Point"}
}