{
  "type": "Feature",
  "properties": {
    "iso:country":"US",
    "sg:address":"709 E 10th St",
    "sg:city":"Wayne",
    "sg:classifiers":[
        {
            "category":"Social Services",
            "subcategory":"Child Care",
            "type":"Services"
        }
    ],
    "sg:phone":"+1 402 375 2704",
    "sg:postcode":"68787",
    "sg:province":"NE",
    "sg:tags":[
        "day"
    ],
    "wof:name":"Jill Bessmer",
    "wof:placetype":"venue"
},
  "geometry": {"coordinates":[-97.008092,42.23906],"type":"Point"}
}