{
  "type": "Feature",
  "properties": {
    "iso:country":"US",
    "sg:address":"4103 R St",
    "sg:city":"Omaha",
    "sg:classifiers":[
        {
            "category":"Building & Trades",
            "subcategory":"Cleaning & Sanitation",
            "type":"Services"
        }
    ],
    "sg:phone":"+1 402 932 1526",
    "sg:postcode":"68107",
    "sg:province":"NE",
    "sg:tags":[
        "janitor"
    ],
    "wof:name":"C & D Cleaning",
    "wof:placetype":"venue"
},
  "geometry": {"coordinates":[-95.976934,41.204399],"type":"Point"}
}