{
  "type": "Feature",
  "properties": {
    "addr:full":"2329 N Nebraska Ave York NE 68467",
    "addr:housenumber":"2329",
    "addr:postcode":"68467",
    "addr:street":"N Nebraska Ave",
    "iso:country":"US",
    "sg:address":"2329 N Nebraska Ave",
    "sg:city":"York",
    "sg:classifiers":[
        {
            "category":"Organizations",
            "subcategory":"Professional Association",
            "type":"Services"
        }
    ],
    "sg:phone":"+1 402 362 2990",
    "sg:postcode":"68467",
    "sg:province":"NE",
    "wof:name":"York County Historical Assn",
    "wof:placetype":"venue"
},
  "geometry": {"coordinates":[-97.59026,40.883632],"type":"Point"}
}