{
  "type": "Feature",
  "properties": {
    "addr:full":"2300 N Webb Rd Grand Island NE 68803",
    "addr:housenumber":"2300",
    "addr:postcode":"68803",
    "addr:street":"N Webb Rd",
    "iso:country":"US",
    "sg:address":"2300 N Webb Rd",
    "sg:city":"Grand Island",
    "sg:classifiers":[
        {
            "category":"Shopping",
            "subcategory":"Bicycles & Sporting Goods",
            "type":"Retail Goods"
        }
    ],
    "sg:phone":"+1 308 384 8500",
    "sg:postcode":"68803",
    "sg:province":"NE",
    "sg:website":"www.hibbett.com",
    "wof:name":"Hibbett Sporting Goods Inc",
    "wof:placetype":"venue"
},
  "geometry": {"coordinates":[-98.378766,40.943207],"type":"Point"}
}