{
  "type": "Feature",
  "properties": {
    "iso:country":"US",
    "sg:address":"12303 US Hwy 6",
    "sg:city":"Waverly",
    "sg:classifiers":[
        {
            "category":"Building & Trades",
            "subcategory":"Construction",
            "type":"Services"
        }
    ],
    "sg:phone":"+1 402 786 5900",
    "sg:postcode":"68462",
    "sg:province":"NE",
    "sg:tags":[
        "paving",
        "contractor"
    ],
    "wof:name":"Pavers Inc",
    "wof:placetype":"venue"
},
  "geometry": {"coordinates":[-96.52789,40.916439],"type":"Point"}
}