{
  "type": "Feature",
  "properties": {
    "addr:full":"106 Main St Palisade NE 69029",
    "addr:housenumber":"106",
    "addr:postcode":"69029",
    "addr:street":"Main St",
    "iso:country":"US",
    "sg:address":"106 Main St",
    "sg:city":"Palisade",
    "sg:classifiers":[
        {
            "category":"Personal",
            "subcategory":"Beauty Salon",
            "type":"Services"
        }
    ],
    "sg:phone":"+1 308 285 3210",
    "sg:postcode":"69029",
    "sg:province":"NE",
    "wof:name":"Beauty Nook",
    "wof:placetype":"venue"
},
  "geometry": {"coordinates":[-100.214771,40.703806],"type":"Point"}
}