{
  "type": "Feature",
  "properties": {
    "iso:country":"US",
    "sg:address":"22233 W Angus Rd",
    "sg:city":"Gretna",
    "sg:classifiers":[
        {
            "category":"Professional",
            "subcategory":"Art Services",
            "type":"Services"
        }
    ],
    "sg:phone":"+1 402 332 3706",
    "sg:postcode":"68028",
    "sg:province":"NE",
    "sg:tags":[
        "commercial",
        "design"
    ],
    "wof:name":"Words & Design",
    "wof:placetype":"venue"
},
  "geometry": {"coordinates":[-96.27502699999999,41.139411],"type":"Point"}
}