{
  "type": "Feature",
  "properties": {
    "iso:country":"US",
    "sg:address":"8787 Pacific St",
    "sg:city":"Omaha",
    "sg:classifiers":[
        {
            "category":"Organizations",
            "subcategory":"Religious Organization",
            "type":"Services"
        }
    ],
    "sg:phone":"+1 402 391 0350",
    "sg:postcode":"68114",
    "sg:province":"NE",
    "sg:tags":[
        "church"
    ],
    "sg:website":"www.countrysideucc.org",
    "wof:name":"Countryside Community Church",
    "wof:placetype":"venue"
},
  "geometry": {"coordinates":[-96.052583,41.248723],"type":"Point"}
}