{
  "type": "Feature",
  "properties": {
    "addr:full":"310 E Military Ave Fremont NE 68025",
    "addr:housenumber":"310",
    "addr:postcode":"68025",
    "addr:street":"E Military Ave",
    "iso:country":"US",
    "sg:address":"310 E Military Ave",
    "sg:city":"Fremont",
    "sg:classifiers":[
        {
            "category":"Professional",
            "subcategory":"Business Services",
            "type":"Services"
        }
    ],
    "sg:phone":"+1 402 721 7351",
    "sg:postcode":"68025",
    "sg:province":"NE",
    "sg:tags":[
        "interior",
        "design"
    ],
    "wof:name":"Interiors By Joan Inc",
    "wof:placetype":"venue"
},
  "geometry": {"coordinates":[-96.49456000000001,41.435718],"type":"Point"}
}