{
  "type": "Feature",
  "properties": {
    "iso:country":"US",
    "sg:address":"405 E Everett St",
    "sg:city":"Oneill",
    "sg:classifiers":[
        {
            "category":"Retail",
            "subcategory":"Repair Shop",
            "type":"Services"
        }
    ],
    "sg:phone":"+1 402 336 4588",
    "sg:postcode":"68763",
    "sg:province":"NE",
    "sg:tags":[
        "machine",
        "sewing"
    ],
    "wof:name":"House Of Sewing",
    "wof:placetype":"venue"
},
  "geometry": {"coordinates":[-98.647841,42.456359],"type":"Point"}
}