{
  "type": "Feature",
  "properties": {
    "addr:full":"213 N 5th St Beatrice NE 68310",
    "addr:housenumber":"213",
    "addr:postcode":"68310",
    "addr:street":"N 5Th St",
    "iso:country":"US",
    "sg:address":"213 N 5th St",
    "sg:city":"Beatrice",
    "sg:classifiers":[
        {
            "category":"Education",
            "subcategory":"School",
            "type":"Public Place"
        }
    ],
    "sg:phone":"+1 402 223 1500",
    "sg:postcode":"68310",
    "sg:province":"NE",
    "wof:name":"Beatrice Board Of Education",
    "wof:placetype":"venue"
},
  "geometry": {"coordinates":[-96.74817299999999,40.267826],"type":"Point"}
}