{
  "type": "Feature",
  "properties": {
    "iso:country":"US",
    "sg:address":"719 W 3rd St",
    "sg:city":"Alliance",
    "sg:classifiers":[
        {
            "category":"Building & Trades",
            "subcategory":"Plumbing",
            "type":"Services"
        }
    ],
    "sg:phone":"+1 308 762 3791",
    "sg:postcode":"69301",
    "sg:province":"NE",
    "sg:tags":[
        "plumbing",
        "contractor"
    ],
    "wof:name":"Tuck's Plumbing & Supplies",
    "wof:placetype":"venue"
},
  "geometry": {"coordinates":[-102.880351,42.096846],"type":"Point"}
}