{
  "type": "Feature",
  "properties": {
    "iso:country":"US",
    "sg:address":"2217 Home St",
    "sg:city":"Hastings",
    "sg:classifiers":[
        {
            "category":"Real Estate",
            "subcategory":"Real Estate Operator",
            "type":"Services"
        }
    ],
    "sg:phone":"+1 402 463 8672",
    "sg:postcode":"68901",
    "sg:province":"NE",
    "sg:tags":[
        "property",
        "lessor"
    ],
    "wof:name":"Eugene Kort",
    "wof:placetype":"venue"
},
  "geometry": {"coordinates":[-98.41258500000001,40.595977],"type":"Point"}
}