{
  "type": "Feature",
  "properties": {
    "iso:country":"US",
    "sg:address":"1750 SW 84th St",
    "sg:city":"Lincoln",
    "sg:classifiers":[
        {
            "category":"Autos & Motor Vehicles",
            "subcategory":"Automobile Sales",
            "type":"Retail Goods"
        }
    ],
    "sg:phone":"+1 402 476 5544",
    "sg:postcode":"68532",
    "sg:province":"NE",
    "sg:tags":[
        "truck"
    ],
    "wof:name":"Performance Truck Sales Inc",
    "wof:placetype":"venue"
},
  "geometry": {"coordinates":[-96.83475799999999,40.791282],"type":"Point"}
}