{
  "type": "Feature",
  "properties": {
    "addr:full":"525 Oak Ave Crete NE 68333",
    "addr:housenumber":"525",
    "addr:postcode":"68333",
    "addr:street":"Oak Ave",
    "iso:country":"US",
    "sg:address":"525 Oak Ave",
    "sg:city":"Crete",
    "sg:classifiers":[
        {
            "category":"Real Estate",
            "subcategory":"Real Estate Operator",
            "type":"Services"
        }
    ],
    "sg:phone":"+1 402 826 5222",
    "sg:postcode":"68333",
    "sg:province":"NE",
    "sg:tags":[
        "property",
        "lessor"
    ],
    "wof:name":"Carl Boden",
    "wof:placetype":"venue"
},
  "geometry": {"coordinates":[-96.96395699999999,40.618634],"type":"Point"}
}