{
  "type": "Feature",
  "properties": {
    "addr:full":"803 E 3rd St Chadron NE 69337",
    "addr:housenumber":"803",
    "addr:postcode":"69337",
    "addr:street":"E 3Rd St",
    "iso:country":"US",
    "sg:address":"803 E 3rd St",
    "sg:city":"Chadron",
    "sg:classifiers":[
        {
            "category":"Organizations",
            "subcategory":"Non-profit Organization",
            "type":"Services"
        }
    ],
    "sg:phone":"+1 308 432 5373",
    "sg:postcode":"69337",
    "sg:province":"NE",
    "sg:tags":[
        "alternative",
        "abortion"
    ],
    "wof:name":"Birthright Of Chadron",
    "wof:placetype":"venue"
},
  "geometry": {"coordinates":[-102.990973,42.828445],"type":"Point"}
}