{
  "type": "Feature",
  "properties": {
    "iso:country":"US",
    "sg:address":"1646 N St",
    "sg:city":"Lincoln",
    "sg:classifiers":[
        {
            "category":"Retail",
            "subcategory":"Auto Repair",
            "type":"Services"
        }
    ],
    "sg:phone":"+1 402 476 9466",
    "sg:postcode":"68508",
    "sg:province":"NE",
    "sg:tags":[
        "automotive"
    ],
    "wof:name":"N Street Express Lube",
    "wof:placetype":"venue"
},
  "geometry": {"coordinates":[-96.697266,40.812551],"type":"Point"}
}