{
  "type": "Feature",
  "properties": {
    "iso:country":"US",
    "sg:address":"1820 Glynn Cir",
    "sg:city":"Lincoln",
    "sg:classifiers":[
        {
            "category":"Real Estate",
            "subcategory":"Real Estate Operator",
            "type":"Services"
        }
    ],
    "sg:phone":"+1 402 476 7154",
    "sg:postcode":"68522",
    "sg:province":"NE",
    "sg:tags":[
        "property",
        "lessor"
    ],
    "wof:name":"Ron Veskrna Farm",
    "wof:placetype":"venue"
},
  "geometry": {"coordinates":[-96.74787000000001,40.788732],"type":"Point"}
}