{
  "type": "Feature",
  "properties": {
    "iso:country":"US",
    "sg:address":"1001 W Overland",
    "sg:city":"Scottsbluff",
    "sg:classifiers":[
        {
            "category":"Retail",
            "subcategory":"Auto Repair",
            "type":"Services"
        }
    ],
    "sg:phone":"+1 308 632 5523",
    "sg:postcode":"69361",
    "sg:province":"NE",
    "sg:tags":[
        "body",
        "automobile",
        "painting"
    ],
    "wof:name":"J D's Ace Body Shop",
    "wof:placetype":"venue"
},
  "geometry": {"coordinates":[-103.677966,41.859247],"type":"Point"}
}