{
  "type": "Feature",
  "properties": {
    "addr:full":"2806 S 110th Ct Omaha NE 68144",
    "addr:housenumber":"2806",
    "addr:postcode":"68144",
    "addr:street":"S 110Th Ct",
    "iso:country":"US",
    "sg:address":"2806 S 110th Ct",
    "sg:city":"Omaha",
    "sg:classifiers":[
        {
            "category":"Professional",
            "subcategory":"Employment Agencies",
            "type":"Services"
        }
    ],
    "sg:phone":"+1 402 399 8480",
    "sg:postcode":"68144",
    "sg:province":"NE",
    "sg:tags":[
        "help",
        "supply"
    ],
    "wof:name":"American Model & Talent",
    "wof:placetype":"venue"
},
  "geometry": {"coordinates":[-96.08556299999999,41.233085],"type":"Point"}
}