{
  "type": "Feature",
  "properties": {
    "addr:full":"4508 38th St Columbus NE 68601",
    "addr:housenumber":"4508",
    "addr:postcode":"68601",
    "addr:street":"38Th St",
    "iso:country":"US",
    "sg:address":"4508 38th St",
    "sg:city":"Columbus",
    "sg:classifiers":[
        {
            "category":"Health Services",
            "subcategory":"Doctor",
            "type":"Services"
        }
    ],
    "sg:phone":"+1 402 563 3379",
    "sg:postcode":"68601",
    "sg:province":"NE",
    "sg:tags":[
        "medical"
    ],
    "wof:name":"Medical Clinic",
    "wof:placetype":"venue"
},
  "geometry": {"coordinates":[-97.382578,41.453342],"type":"Point"}
}