{
  "type": "Feature",
  "properties": {
    "addr:full":"16501 Main St Bellevue NE 68123",
    "addr:housenumber":"16501",
    "addr:postcode":"68123",
    "addr:street":"Main St",
    "iso:country":"US",
    "sg:address":"16501 Main St",
    "sg:city":"Bellevue",
    "sg:classifiers":[
        {
            "category":"Retail",
            "subcategory":"Repair Shop",
            "type":"Services"
        }
    ],
    "sg:phone":"+1 402 291 3018",
    "sg:postcode":"68123",
    "sg:province":"NE",
    "sg:tags":[
        "taxidermist"
    ],
    "wof:name":"Rivercity Taxidermy",
    "wof:placetype":"venue"
},
  "geometry": {"coordinates":[-95.924325,41.071807],"type":"Point"}
}