{
  "type": "Feature",
  "properties": {
    "iso:country":"US",
    "sg:address":"181 Clay St",
    "sg:city":"Tecumseh",
    "sg:classifiers":[
        {
            "category":"Retail",
            "subcategory":"Auto Repair",
            "type":"Services"
        }
    ],
    "sg:phone":"+1 402 335 3700",
    "sg:postcode":"68450",
    "sg:province":"NE",
    "sg:tags":[
        "body",
        "automobile",
        "painting"
    ],
    "wof:name":"KWK Collision Inc",
    "wof:placetype":"venue"
},
  "geometry": {"coordinates":[-96.197458,40.366652],"type":"Point"}
}