{
  "type": "Feature",
  "properties": {
    "iso:country":"US",
    "sg:address":"2714 S 106th St",
    "sg:city":"Omaha",
    "sg:classifiers":[
        {
            "category":"Professional",
            "subcategory":"Management & Consulting",
            "type":"Services"
        }
    ],
    "sg:phone":"+1 402 968 9061",
    "sg:postcode":"68124",
    "sg:province":"NE",
    "wof:name":"Schmalenbach Properties Inc",
    "wof:placetype":"venue"
},
  "geometry": {"coordinates":[-96.07834099999999,41.232262],"type":"Point"}
}