{
  "type": "Feature",
  "properties": {
    "iso:country":"US",
    "sg:address":"771 N Whitney Lake Rd",
    "sg:city":"Whitney",
    "sg:classifiers":[
        {
            "category":"Farming",
            "subcategory":"Farm & Veterinary Services",
            "type":"Manufacturing & Wholesale Goods"
        }
    ],
    "sg:phone":"+1 308 432 5396",
    "sg:postcode":"69367",
    "sg:province":"NE",
    "sg:tags":[
        "preparation",
        "crop",
        "for",
        "market"
    ],
    "wof:name":"Mandelko Ranch/Custom Hay Grnd",
    "wof:placetype":"venue"
},
  "geometry": {"coordinates":[-103.16941799999999,42.79939],"type":"Point"}
}