{
  "type": "Feature",
  "properties": {
    "addr:full":"10323 Y St Omaha NE 68127",
    "addr:housenumber":"10323",
    "addr:postcode":"68127",
    "addr:street":"Y St",
    "iso:country":"US",
    "sg:address":"10323 Y St",
    "sg:city":"Omaha",
    "sg:classifiers":[
        {
            "category":"Building & Trades",
            "subcategory":"Equipment Rental",
            "type":"Services"
        }
    ],
    "sg:phone":"+1 402 331 2827",
    "sg:postcode":"68127",
    "sg:province":"NE",
    "wof:name":"McCollom Rentals",
    "wof:placetype":"venue"
},
  "geometry": {"coordinates":[-96.075577,41.197569],"type":"Point"}
}