{
  "type": "Feature",
  "properties": {
    "iso:country":"US",
    "sg:address":"103 S Thatcher St",
    "sg:city":"Valentine",
    "sg:classifiers":[
        {
            "category":"Wholesale",
            "subcategory":"Medical Equipment & Supplies",
            "type":"Manufacturing & Wholesale Goods"
        }
    ],
    "sg:phone":"+1 402 376 3186",
    "sg:postcode":"69201",
    "sg:province":"NE",
    "sg:tags":[
        "hospital"
    ],
    "wof:name":"Sandhills Medical Supply",
    "wof:placetype":"venue"
},
  "geometry": {"coordinates":[-100.56446099999999,42.869967],"type":"Point"}
}