{
  "type": "Feature",
  "properties": {
    "addr:full":"8529 K St Omaha NE 68127",
    "addr:housenumber":"8529",
    "addr:postcode":"68127",
    "addr:street":"K St",
    "iso:country":"US",
    "sg:address":"8529 K St",
    "sg:city":"Omaha",
    "sg:classifiers":[
        {
            "category":"Professional",
            "subcategory":"Printing & Photocopies",
            "type":"Services"
        }
    ],
    "sg:phone":"+1 402 597 2400",
    "sg:postcode":"68127",
    "sg:province":"NE",
    "sg:tags":[
        "duplicating",
        "copying"
    ],
    "sg:website":"www.rkdigital.com",
    "wof:name":"R K Digital",
    "wof:placetype":"venue"
},
  "geometry": {"coordinates":[-96.04421600000001,41.214194],"type":"Point"}
}