{
  "type": "Feature",
  "properties": {
    "addr:full":"5608 S 174th St Omaha NE 68135",
    "addr:housenumber":"5608",
    "addr:postcode":"68135",
    "addr:street":"S 174Th St",
    "iso:country":"US",
    "sg:address":"5608 S 174th St",
    "sg:city":"Omaha",
    "sg:classifiers":[
        {
            "category":"Shopping",
            "subcategory":"Clothing, Apparel, & Fashions",
            "type":"Retail Goods"
        }
    ],
    "sg:phone":"+1 402 891 9141",
    "sg:postcode":"68135",
    "sg:province":"NE",
    "wof:name":"Tom James Company",
    "wof:placetype":"venue"
},
  "geometry": {"coordinates":[-96.186481,41.198404],"type":"Point"}
}