{
  "type": "Feature",
  "properties": {
    "iso:country":"US",
    "sg:address":"16410 Pacific St",
    "sg:city":"Omaha",
    "sg:classifiers":[
        {
            "category":"Government",
            "subcategory":"Fire Station",
            "type":"Public Place"
        }
    ],
    "sg:phone":"+1 402 330 8612",
    "sg:postcode":"68118",
    "sg:province":"NE",
    "sg:tags":[
        "department"
    ],
    "wof:name":"Fire Station 56",
    "wof:placetype":"venue"
},
  "geometry": {"coordinates":[-96.171977,41.248593],"type":"Point"}
}