{
  "type": "Feature",
  "properties": {
    "iso:country":"US",
    "sg:address":"13215 Birch Dr",
    "sg:city":"Omaha",
    "sg:classifiers":[
        {
            "category":"Health Services",
            "subcategory":"Doctor",
            "type":"Services"
        }
    ],
    "sg:phone":"+1 402 390 0770",
    "sg:postcode":"68164",
    "sg:province":"NE",
    "sg:tags":[
        "dentist"
    ],
    "sg:website":"www.oralmaxfacialplastic.com",
    "wof:name":"Oral Maxillofacial & Facial",
    "wof:placetype":"venue"
},
  "geometry": {"coordinates":[-96.120074,41.290359],"type":"Point"}
}