{
  "type": "Feature",
  "properties": {
    "addr:full":"6622 Binney St Omaha NE 68104",
    "addr:housenumber":"6622",
    "addr:postcode":"68104",
    "addr:street":"Binney St",
    "iso:country":"US",
    "sg:address":"6622 Binney St",
    "sg:city":"Omaha",
    "sg:classifiers":[
        {
            "category":"Building & Trades",
            "subcategory":"Construction",
            "type":"Services"
        }
    ],
    "sg:phone":"+1 402 390 9905",
    "sg:postcode":"68104",
    "sg:province":"NE",
    "sg:tags":[
        "repair",
        "patio",
        "deck"
    ],
    "wof:name":"Deck Pros",
    "wof:placetype":"venue"
},
  "geometry": {"coordinates":[-96.016369,41.286018],"type":"Point"}
}