{
  "type": "Feature",
  "properties": {
    "iso:country":"US",
    "sg:address":"21169 SW 80 Ln",
    "sg:city":"Beatrice",
    "sg:classifiers":[
        {
            "category":"Wholesale",
            "subcategory":"Farm Supplies",
            "type":"Manufacturing & Wholesale Goods"
        }
    ],
    "sg:phone":"+1 402 223 5100",
    "sg:postcode":"68310",
    "sg:province":"NE",
    "sg:tags":[
        "bean"
    ],
    "wof:name":"Farmers Cooperative",
    "wof:placetype":"venue"
},
  "geometry": {"coordinates":[-96.832075,40.320525],"type":"Point"}
}