{
  "type": "Feature",
  "properties": {
    "addr:full":"1405 280th Seward NE 68434",
    "addr:housenumber":"1405",
    "addr:postcode":"68434",
    "addr:street":"280Th Seward Ne",
    "iso:country":"US",
    "sg:address":"1405 280th",
    "sg:city":"Seward",
    "sg:classifiers":[
        {
            "category":"Shopping",
            "subcategory":"Department Store",
            "type":"Retail Goods"
        }
    ],
    "sg:phone":"+1 402 643 6631",
    "sg:postcode":"68434",
    "sg:province":"NE",
    "sg:website":"www.wal-mart.com",
    "wof:name":"Wal-Mart",
    "wof:placetype":"venue"
},
  "geometry": {"coordinates":[-97.10161100000001,40.887215],"type":"Point"}
}