{
  "type": "Feature",
  "properties": {
    "addr:full":"115 S 66th St Lincoln NE 68510",
    "addr:housenumber":"115",
    "addr:postcode":"68510",
    "addr:street":"S 66Th St",
    "iso:country":"US",
    "sg:address":"115 S 66th St",
    "sg:city":"Lincoln",
    "sg:classifiers":[
        {
            "category":"Home & Garden",
            "subcategory":"Building Materials",
            "type":"Retail Goods"
        }
    ],
    "sg:phone":"+1 402 483 6244",
    "sg:postcode":"68510",
    "sg:province":"NE",
    "sg:tags":[
        "wallpaper"
    ],
    "wof:name":"Wallpaper Now",
    "wof:placetype":"venue"
},
  "geometry": {"coordinates":[-96.63073799999999,40.812397],"type":"Point"}
}