{
  "type": "Feature",
  "properties": {
    "addr:full":"15010 State Hwy 31 Gretna NE 68028",
    "addr:housenumber":"15010",
    "addr:postcode":"68028",
    "addr:street":"State Hwy 31;Ne",
    "iso:country":"US",
    "sg:address":"15010 State Hwy 31",
    "sg:city":"Gretna",
    "sg:classifiers":[
        {
            "category":"Autos & Motor Vehicles",
            "subcategory":"Fuel & Gas Station",
            "type":"Retail Goods"
        }
    ],
    "sg:phone":"+1 402 332 4483",
    "sg:postcode":"68028",
    "sg:province":"NE",
    "sg:tags":[
        "gasoline",
        "grocery",
        "station",
        "eating"
    ],
    "sg:website":"www.flyingj.com",
    "wof:name":"Flying J Travel Plaza",
    "wof:placetype":"venue"
},
  "geometry": {"coordinates":[-96.253434,41.091906],"type":"Point"}
}