{
  "type": "Feature",
  "properties": {
    "iso:country":"US",
    "sg:address":"1305 W 20th St",
    "sg:city":"Scottsbluff",
    "sg:classifiers":[
        {
            "category":"Organizations",
            "subcategory":"Religious Organization",
            "type":"Services"
        }
    ],
    "sg:phone":"+1 308 632 8237",
    "sg:postcode":"69361",
    "sg:province":"NE",
    "wof:name":"Church of The Nazarene Inc",
    "wof:placetype":"venue"
},
  "geometry": {"coordinates":[-103.67972399999999,41.866472],"type":"Point"}
}