{
  "type": "Feature",
  "properties": {
    "iso:country":"US",
    "sg:address":"888 E Eilenstine Rd",
    "sg:city":"Grand Island",
    "sg:classifiers":[
        {
            "category":"Manufacturing",
            "subcategory":"Electronics",
            "type":"Manufacturing & Wholesale Goods"
        }
    ],
    "sg:phone":"+1 308 382 3743",
    "sg:postcode":"68801",
    "sg:province":"NE",
    "sg:tags":[
        "parts",
        "radio",
        "supply"
    ],
    "wof:name":"G I Electronic Supply Co",
    "wof:placetype":"venue"
},
  "geometry": {"coordinates":[-98.334318,40.949405],"type":"Point"}
}