{
  "type": "Feature",
  "properties": {
    "addr:full":"3006 Webster St Omaha NE 68131",
    "addr:housenumber":"3006",
    "addr:postcode":"68131",
    "addr:street":"Webster St",
    "iso:country":"US",
    "sg:address":"3006 Webster St",
    "sg:city":"Omaha",
    "sg:classifiers":[
        {
            "category":"Health Services",
            "subcategory":"Doctor",
            "type":"Services"
        }
    ],
    "sg:phone":"+1 402 280 4566",
    "sg:postcode":"68131",
    "sg:province":"NE",
    "sg:tags":[
        "medical"
    ],
    "wof:name":"Creighton Cardiac Center",
    "wof:placetype":"venue"
},
  "geometry": {"coordinates":[-95.959807,41.265914],"type":"Point"}
}