{
  "type": "Feature",
  "properties": {
    "iso:country":"US",
    "sg:address":"201 E Omaha Ave",
    "sg:city":"Norfolk",
    "sg:classifiers":[
        {
            "category":"Building & Trades",
            "subcategory":"Construction",
            "type":"Services"
        }
    ],
    "sg:phone":"+1 402 379 7916",
    "sg:postcode":"68701",
    "sg:province":"NE",
    "sg:tags":[
        "roofing",
        "contractor"
    ],
    "wof:name":"Don Home Repair",
    "wof:placetype":"venue"
},
  "geometry": {"coordinates":[-97.40573500000001,42.018222],"type":"Point"}
}