{
  "type": "Feature",
  "properties": {
    "iso:country":"US",
    "sg:address":"1732 N Huston Ave",
    "sg:city":"Grand Island",
    "sg:classifiers":[
        {
            "category":"Building & Trades",
            "subcategory":"Construction",
            "type":"Services"
        }
    ],
    "sg:phone":"+1 308 384 0435",
    "sg:postcode":"68803",
    "sg:province":"NE",
    "sg:tags":[
        "specializing",
        "remodeling",
        "contractor"
    ],
    "wof:name":"ONeill Construction Co",
    "wof:placetype":"venue"
},
  "geometry": {"coordinates":[-98.360319,40.936603],"type":"Point"}
}