{
  "type": "Feature",
  "properties": {
    "iso:country":"US",
    "sg:address":"500 Park St",
    "sg:city":"Yankton",
    "sg:classifiers":[
        {
            "category":"Travel",
            "subcategory":"Hotels & Motels",
            "type":"Entertainment"
        }
    ],
    "sg:phone":"+1 605 665 7828",
    "sg:postcode":"57078",
    "sg:province":"NE",
    "wof:name":"Star-Lite Inn Motel",
    "wof:placetype":"venue"
},
  "geometry": {"coordinates":[-97.40578499999999,42.871325],"type":"Point"}
}