{
  "type": "Feature",
  "properties": {
    "iso:country":"US",
    "sg:address":"124 Mill St N",
    "sg:city":"Dannebrog",
    "sg:classifiers":[
        {
            "category":"Sports & Exercise",
            "subcategory":"Gym",
            "type":"Entertainment"
        }
    ],
    "sg:phone":"+1 308 226 2378",
    "sg:postcode":"68831",
    "sg:province":"NE",
    "sg:tags":[
        "club",
        "health",
        "studio",
        "gymnasium"
    ],
    "wof:name":"Healthy Woman",
    "wof:placetype":"venue"
},
  "geometry": {"coordinates":[-98.547454,41.119839],"type":"Point"}
}