{
  "type": "Feature",
  "properties": {
    "iso:country":"US",
    "sg:address":"8150 O St",
    "sg:city":"Lincoln",
    "sg:classifiers":[
        {
            "category":"Food & Beverages",
            "subcategory":"Groceries & Convenience Stores",
            "type":"Retail Goods"
        }
    ],
    "sg:phone":"+1 402 488 3225",
    "sg:postcode":"68510",
    "sg:province":"NE",
    "wof:name":"Express Stop",
    "wof:placetype":"venue"
},
  "geometry": {"coordinates":[-96.601495,40.813472],"type":"Point"}
}