{
  "type": "Feature",
  "properties": {
    "addr:full":"10938 Emiline St La Vista NE 68128",
    "addr:housenumber":"10938",
    "addr:postcode":"68128",
    "addr:street":"Emiline St",
    "iso:country":"US",
    "sg:address":"10938 Emiline St",
    "sg:city":"La Vista",
    "sg:classifiers":[
        {
            "category":"Building & Trades",
            "subcategory":"Construction",
            "type":"Services"
        }
    ],
    "sg:phone":"+1 402 592 9388",
    "sg:postcode":"68128",
    "sg:province":"NE",
    "sg:tags":[
        "modification",
        "home",
        "medical",
        "apparatus",
        "contractor"
    ],
    "wof:name":"Barrier Breakers",
    "wof:placetype":"venue"
},
  "geometry": {"coordinates":[-96.084947,41.189698],"type":"Point"}
}