{
  "type": "Feature",
  "properties": {
    "iso:country":"US",
    "sg:address":"2829 N 90th St",
    "sg:city":"Omaha",
    "sg:classifiers":[
        {
            "category":"Insurance",
            "subcategory":"Insurance Agent",
            "type":"Services"
        }
    ],
    "sg:phone":"+1 402 572 6877",
    "sg:postcode":"68134",
    "sg:province":"NE",
    "wof:name":"Mephisto Of Omaha",
    "wof:placetype":"venue"
},
  "geometry": {"coordinates":[-96.052538,41.28389],"type":"Point"}
}