{
  "type": "Feature",
  "properties": {
    "iso:country":"US",
    "sg:address":"110 3rd St",
    "sg:city":"Max",
    "sg:classifiers":[
        {
            "category":"Shopping",
            "subcategory":"Used Merchandise",
            "type":"Retail Goods"
        }
    ],
    "sg:phone":"+1 308 423 2814",
    "sg:postcode":"69034",
    "sg:province":"NE",
    "sg:tags":[
        "second",
        "store",
        "hand"
    ],
    "wof:name":"Treasure Cove",
    "wof:placetype":"venue"
},
  "geometry": {"coordinates":[-100.415887,40.233514],"type":"Point"}
}