{
  "type": "Feature",
  "properties": {
    "iso:country":"US",
    "sg:address":"3225 California St",
    "sg:city":"Omaha",
    "sg:classifiers":[
        {
            "category":"Arts & Performance",
            "subcategory":"Arts Center",
            "type":"Entertainment"
        }
    ],
    "sg:phone":"+1 402 391 2270",
    "sg:postcode":"68131",
    "sg:province":"NE",
    "sg:tags":[
        "performing"
    ],
    "sg:website":"www.theatreartsguild.com",
    "wof:name":"Theatre Arts Guild",
    "wof:placetype":"venue"
},
  "geometry": {"coordinates":[-95.960541,41.264702],"type":"Point"}
}