{
  "type": "Feature",
  "properties": {
    "iso:country":"US",
    "sg:address":"3911 7th Ave",
    "sg:city":"Kearney",
    "sg:classifiers":[
        {
            "category":"Health Services",
            "subcategory":"Medical Lab",
            "type":"Services"
        }
    ],
    "sg:phone":"+1 308 234 4393",
    "sg:postcode":"68845",
    "sg:province":"NE",
    "sg:tags":[
        "laboratory"
    ],
    "wof:name":"Sickler Dental Studio",
    "wof:placetype":"venue"
},
  "geometry": {"coordinates":[-99.09119699999999,40.715129],"type":"Point"}
}