{
  "type": "Feature",
  "properties": {
    "iso:country":"US",
    "sg:address":"1360 S Broad St",
    "sg:city":"Fremont",
    "sg:classifiers":[
        {
            "category":"Building & Trades",
            "subcategory":"Construction",
            "type":"Services"
        }
    ],
    "sg:phone":"+1 402 727 9001",
    "sg:postcode":"68025",
    "sg:province":"NE",
    "sg:tags":[
        "siding",
        "contractor"
    ],
    "wof:name":"ABC Seamless Kranz Exteriors",
    "wof:placetype":"venue"
},
  "geometry": {"coordinates":[-96.50026699999999,41.416078],"type":"Point"}
}