{
  "type": "Feature",
  "properties": {
    "iso:country":"US",
    "sg:address":"440 J St",
    "sg:city":"Lincoln",
    "sg:classifiers":[
        {
            "category":"Wholesale",
            "subcategory":"Scrap",
            "type":"Manufacturing & Wholesale Goods"
        }
    ],
    "sg:phone":"+1 402 476 8502",
    "sg:postcode":"68508",
    "sg:province":"NE",
    "sg:tags":[
        "recycling",
        "center"
    ],
    "wof:name":"Midland Recycling",
    "wof:placetype":"venue"
},
  "geometry": {"coordinates":[-96.715802,40.808183],"type":"Point"}
}