{
  "type": "Feature",
  "properties": {
    "iso:country":"US",
    "sg:address":"816 Washington St",
    "sg:city":"Blair",
    "sg:classifiers":[
        {
            "category":"Autos & Motor Vehicles",
            "subcategory":"Boat Sales",
            "type":"Retail Goods"
        }
    ],
    "sg:phone":"+1 402 426 4550",
    "sg:postcode":"68008",
    "sg:province":"NE",
    "sg:tags":[
        "dealer",
        "sales"
    ],
    "wof:name":"Steinbaugh Boats & Motors",
    "wof:placetype":"venue"
},
  "geometry": {"coordinates":[-96.12295,41.543744],"type":"Point"}
}