{
  "type": "Feature",
  "properties": {
    "iso:country":"US",
    "sg:address":"2202 Broadway St",
    "sg:city":"Dakota City",
    "sg:classifiers":[
        {
            "category":"Freight",
            "type":"Transportation"
        }
    ],
    "sg:phone":"+1 402 987 3073",
    "sg:postcode":"68731",
    "sg:province":"NE",
    "sg:tags":[
        "grain",
        "elevator"
    ],
    "wof:name":"H & W Inc",
    "wof:placetype":"venue"
},
  "geometry": {"coordinates":[-96.42688800000001,42.415235],"type":"Point"}
}