{
  "type": "Feature",
  "properties": {
    "iso:country":"US",
    "sg:address":"5636 S 96th St",
    "sg:city":"Omaha",
    "sg:classifiers":[
        {
            "category":"Real Estate",
            "subcategory":"Real Estate Operator",
            "type":"Services"
        }
    ],
    "sg:phone":"+1 402 331 3953",
    "sg:postcode":"68127",
    "sg:province":"NE",
    "sg:tags":[
        "apartment"
    ],
    "wof:name":"Studio 96 Apartments",
    "wof:placetype":"venue"
},
  "geometry": {"coordinates":[-96.06206299999999,41.202004],"type":"Point"}
}