{
  "type": "Feature",
  "properties": {
    "addr:full":"203 E Roberts St Grand Island NE 68803",
    "addr:housenumber":"203",
    "addr:postcode":"68803",
    "addr:street":"E Roberts St",
    "iso:country":"US",
    "sg:address":"203 E Roberts St",
    "sg:city":"Grand Island",
    "sg:classifiers":[
        {
            "category":"Wholesale",
            "subcategory":"Groceries",
            "type":"Manufacturing & Wholesale Goods"
        }
    ],
    "sg:phone":"+1 308 384 8888",
    "sg:postcode":"68803",
    "sg:province":"NE",
    "sg:tags":[
        "grocer"
    ],
    "wof:name":"Swift Distribution Ctr",
    "wof:placetype":"venue"
},
  "geometry": {"coordinates":[-98.351288,40.95111],"type":"Point"}
}