{
  "type": "Feature",
  "properties": {
    "addr:full":"903 Central Ave Auburn NE 68305",
    "addr:housenumber":"903",
    "addr:postcode":"68305",
    "addr:street":"Central Ave",
    "iso:country":"US",
    "sg:address":"903 Central Ave",
    "sg:city":"Auburn",
    "sg:classifiers":[
        {
            "category":"Restaurant",
            "type":"Food & Drink"
        }
    ],
    "sg:phone":"+1 402 274 4757",
    "sg:postcode":"68305",
    "sg:province":"NE",
    "wof:name":"Avenue Grill",
    "wof:placetype":"venue"
},
  "geometry": {"coordinates":[-95.83878199999999,40.392734],"type":"Point"}
}