{
  "type": "Feature",
  "properties": {
    "iso:country":"US",
    "sg:address":"120 Rd 18",
    "sg:city":"Bradshaw",
    "sg:phone":"+1 402 736 4431",
    "sg:postcode":"68319",
    "sg:province":"NE",
    "sg:tags":[
        "farm"
    ],
    "wof:name":"Lamar Newton",
    "wof:placetype":"venue"
},
  "geometry": {"coordinates":[-97.817364,40.945023],"type":"Point"}
}