{
  "type": "Feature",
  "properties": {
    "iso:country":"US",
    "sg:address":"200 Rd East 85",
    "sg:city":"Ogallala",
    "sg:classifiers":[
        {
            "category":"Retail",
            "subcategory":"Auto Repair",
            "type":"Services"
        }
    ],
    "sg:phone":"+1 308 284 2027",
    "sg:postcode":"69153",
    "sg:province":"NE",
    "sg:tags":[
        "repairing",
        "automobile"
    ],
    "wof:name":"MCM Truck Repair",
    "wof:placetype":"venue"
},
  "geometry": {"coordinates":[-101.71087,41.11284],"type":"Point"}
}