{
  "type": "Feature",
  "properties": {
    "addr:full":"2406 Main Ave Crete NE 68333",
    "addr:housenumber":"2406",
    "addr:postcode":"68333",
    "addr:street":"Main Ave",
    "iso:country":"US",
    "sg:address":"2406 Main Ave",
    "sg:city":"Crete",
    "sg:classifiers":[
        {
            "category":"Building & Trades",
            "subcategory":"Construction",
            "type":"Services"
        }
    ],
    "sg:phone":"+1 402 432 1193",
    "sg:postcode":"68333",
    "sg:province":"NE",
    "sg:tags":[
        "roofing",
        "contractor"
    ],
    "wof:name":"Lifetime Roofing & Consulting",
    "wof:placetype":"venue"
},
  "geometry": {"coordinates":[-96.961382,40.63589],"type":"Point"}
}