{
  "type": "Feature",
  "properties": {
    "addr:full":"2821 N 56th St Omaha NE 68104",
    "addr:housenumber":"2821",
    "addr:postcode":"68104",
    "addr:street":"N 56Th St",
    "iso:country":"US",
    "sg:address":"2821 N 56th St",
    "sg:city":"Omaha",
    "sg:classifiers":[
        {
            "category":"Health Services",
            "subcategory":"Doctor",
            "type":"Services"
        }
    ],
    "sg:phone":"+1 402 554 0404",
    "sg:postcode":"68104",
    "sg:province":"NE",
    "sg:tags":[
        "surgeon",
        "oral"
    ],
    "wof:name":"Kelley Lawrence J DDS",
    "wof:placetype":"venue"
},
  "geometry": {"coordinates":[-95.99990099999999,41.2841],"type":"Point"}
}