{
  "type": "Feature",
  "properties": {
    "addr:full":"43970 Rd 758 Lexington NE 68850",
    "addr:postcode":"43970;68850",
    "addr:street":"Rd 758",
    "iso:country":"US",
    "sg:address":"43970 Rd 758",
    "sg:city":"Lexington",
    "sg:classifiers":[
        {
            "category":"Farming",
            "subcategory":"Livestock Farm",
            "type":"Manufacturing & Wholesale Goods"
        }
    ],
    "sg:phone":"+1 308 324 4381",
    "sg:postcode":"68850",
    "sg:province":"NE",
    "sg:tags":[
        "feedlot"
    ],
    "wof:name":"Anthony Land Co Inc",
    "wof:placetype":"venue"
},
  "geometry": {"coordinates":[-99.62214299999999,40.81583],"type":"Point"}
}