{
  "type": "Feature",
  "properties": {
    "iso:country":"US",
    "sg:address":"209 W 23rd St",
    "sg:city":"Fremont",
    "sg:classifiers":[
        {
            "category":"Autos & Motor Vehicles",
            "subcategory":"Fuel & Gas Station",
            "type":"Retail Goods"
        }
    ],
    "sg:phone":"+1 402 727 5527",
    "sg:postcode":"68025",
    "sg:province":"NE",
    "sg:tags":[
        "oil"
    ],
    "wof:name":"M & H Gas Station",
    "wof:placetype":"venue"
},
  "geometry": {"coordinates":[-96.498643,41.451337],"type":"Point"}
}