{
  "type": "Feature",
  "properties": {
    "iso:country":"US",
    "sg:address":"5078 S 136th St",
    "sg:city":"Omaha",
    "sg:classifiers":[
        {
            "category":"Wholesale",
            "subcategory":"Non-durable Goods",
            "type":"Manufacturing & Wholesale Goods"
        }
    ],
    "sg:phone":"+1 402 934 8488",
    "sg:postcode":"68137",
    "sg:province":"NE",
    "wof:name":"Reef Tectronics",
    "wof:placetype":"venue"
},
  "geometry": {"coordinates":[-96.12172,41.205245],"type":"Point"}
}