{
  "type": "Feature",
  "properties": {
    "addr:full":"23803 S 162nd St Adams NE 68301",
    "addr:housenumber":"23803",
    "addr:postcode":"68301",
    "addr:street":"S 162Nd St",
    "iso:country":"US",
    "sg:address":"23803 S 162nd St",
    "sg:city":"Adams",
    "sg:classifiers":[
        {
            "category":"Communications",
            "subcategory":"Film & Video Production",
            "type":"Services"
        }
    ],
    "sg:phone":"+1 402 788 2556",
    "sg:postcode":"68301",
    "sg:province":"NE",
    "sg:tags":[
        "taping"
    ],
    "wof:name":"Rainbow Video Productions Inc",
    "wof:placetype":"venue"
},
  "geometry": {"coordinates":[-96.501659,40.578218],"type":"Point"}
}