{
  "type": "Feature",
  "properties": {
    "addr:full":"1018 Dodge St Omaha NE 68102",
    "addr:housenumber":"1018",
    "addr:postcode":"68102",
    "addr:street":"Dodge St",
    "iso:country":"US",
    "sg:address":"1018 Dodge St",
    "sg:city":"Omaha",
    "sg:classifiers":[
        {
            "category":"Professional",
            "subcategory":"Business Services",
            "type":"Services"
        }
    ],
    "sg:phone":"+1 402 455 1101",
    "sg:postcode":"68102",
    "sg:province":"NE",
    "sg:tags":[
        "recording",
        "studio"
    ],
    "wof:name":"Digital Age Recording",
    "wof:placetype":"venue"
},
  "geometry": {"coordinates":[-95.93034299999999,41.259744],"type":"Point"}
}