{
  "type": "Feature",
  "properties": {
    "iso:country":"US",
    "sg:address":"2379 Co Rd 27",
    "sg:city":"Prague",
    "sg:classifiers":[
        {
            "category":"Manufacturing",
            "subcategory":"Tools & Machinery",
            "type":"Manufacturing & Wholesale Goods"
        }
    ],
    "sg:phone":"+1 402 663 4380",
    "sg:postcode":"68050",
    "sg:province":"NE",
    "sg:tags":[
        "farm",
        "mfg"
    ],
    "wof:name":"Glenn Chvatal",
    "wof:placetype":"venue"
},
  "geometry": {"coordinates":[-96.812817,41.350656],"type":"Point"}
}