{
  "type": "Feature",
  "properties": {
    "iso:country":"US",
    "sg:address":"3335 Fowler Ave",
    "sg:city":"Omaha",
    "sg:classifiers":[
        {
            "category":"Organizations",
            "subcategory":"Religious Organization",
            "type":"Services"
        }
    ],
    "sg:phone":"+1 402 455 7807",
    "sg:postcode":"68111",
    "sg:province":"NE",
    "sg:tags":[
        "church"
    ],
    "wof:name":"Abide Network",
    "wof:placetype":"venue"
},
  "geometry": {"coordinates":[-95.96320299999999,41.301201],"type":"Point"}
}