{
  "type": "Feature",
  "properties": {
    "iso:country":"US",
    "sg:address":"4224 Ridgeview Dr",
    "sg:city":"Lincoln",
    "sg:classifiers":[
        {
            "category":"Professional",
            "subcategory":"Business Services",
            "type":"Services"
        }
    ],
    "sg:phone":"+1 402 483 4841",
    "sg:postcode":"68506",
    "sg:province":"NE",
    "wof:name":"Mra & Associates Incorporated",
    "wof:placetype":"venue"
},
  "geometry": {"coordinates":[-96.62886899999999,40.77118],"type":"Point"}
}