{
  "type": "Feature",
  "properties": {
    "addr:full":"111 Kansas St Crofton NE 68730",
    "addr:postcode":"68730",
    "addr:street":"111 Kansas St",
    "iso:country":"US",
    "sg:address":"111 Kansas St",
    "sg:city":"Crofton",
    "sg:classifiers":[
        {
            "category":"Banks & Credit Unions",
            "subcategory":"Bank",
            "type":"Services"
        }
    ],
    "sg:phone":"+1 402 388 4344",
    "sg:postcode":"68730",
    "sg:province":"NE",
    "wof:name":"Farmers & Merchants State Bank",
    "wof:placetype":"venue"
},
  "geometry": {"coordinates":[-97.493897,42.731446],"type":"Point"}
}