{
  "type": "Feature",
  "properties": {
    "addr:full":"1210 S 13th St Norfolk NE 68701",
    "addr:housenumber":"1210",
    "addr:postcode":"68701",
    "addr:street":"S 13Th St",
    "iso:country":"US",
    "sg:address":"1210 S 13th St",
    "sg:city":"Norfolk",
    "sg:classifiers":[
        {
            "category":"Manufacturing",
            "subcategory":"Printing",
            "type":"Manufacturing & Wholesale Goods"
        }
    ],
    "sg:phone":"+1 402 379 1366",
    "sg:postcode":"68701",
    "sg:province":"NE",
    "sg:tags":[
        "commercial"
    ],
    "wof:name":"Gillette Printing",
    "wof:placetype":"venue"
},
  "geometry": {"coordinates":[-97.426417,42.018983],"type":"Point"}
}