{
  "type": "Feature",
  "properties": {
    "iso:country":"US",
    "sg:address":"5402 S 159th Ave",
    "sg:city":"Omaha",
    "sg:classifiers":[
        {
            "category":"Professional",
            "type":"Services"
        }
    ],
    "sg:phone":"+1 402 895 3208",
    "sg:postcode":"68135",
    "sg:province":"NE",
    "sg:tags":[
        "scientist"
    ],
    "wof:name":"Congenial Technologies",
    "wof:placetype":"venue"
},
  "geometry": {"coordinates":[-96.163291,41.202691],"type":"Point"}
}