{
  "type": "Feature",
  "properties": {
    "iso:country":"US",
    "sg:address":"101 N Main St",
    "sg:city":"Fremont",
    "sg:classifiers":[
        {
            "category":"Real Estate",
            "subcategory":"Real Estate Agent",
            "type":"Services"
        }
    ],
    "sg:phone":"+1 402 372 3565",
    "sg:postcode":"68025",
    "sg:province":"NE",
    "sg:tags":[
        "inspection"
    ],
    "wof:name":"United Title & Escrow Co",
    "wof:placetype":"venue"
},
  "geometry": {"coordinates":[-96.496443,41.430133],"type":"Point"}
}