{
  "type": "Feature",
  "properties": {
    "addr:full":"7365 Grant St Omaha NE 68134",
    "addr:housenumber":"7365",
    "addr:postcode":"68134",
    "addr:street":"Grant St",
    "iso:country":"US",
    "sg:address":"7365 Grant St",
    "sg:city":"Omaha",
    "sg:classifiers":[
        {
            "category":"Freight",
            "type":"Transportation"
        }
    ],
    "sg:phone":"+1 402 208 7646",
    "sg:postcode":"68134",
    "sg:province":"NE",
    "sg:tags":[
        "mover"
    ],
    "wof:name":"One Man & A Dolly",
    "wof:placetype":"venue"
},
  "geometry": {"coordinates":[-96.026771,41.279536],"type":"Point"}
}