{
  "type": "Feature",
  "properties": {
    "iso:country":"US",
    "sg:address":"17041 Lakeside Hills Plz",
    "sg:city":"Omaha",
    "sg:classifiers":[
        {
            "category":"Insurance",
            "subcategory":"Insurance Agent",
            "type":"Services"
        }
    ],
    "sg:phone":"+1 402 334 5176",
    "sg:postcode":"68130",
    "sg:province":"NE",
    "sg:website":"www.rainhail.com",
    "wof:name":"Rain & Hail Insurance Svc Inc",
    "wof:placetype":"venue"
},
  "geometry": {"coordinates":[-96.177386,41.237603],"type":"Point"}
}