{
  "type": "Feature",
  "properties": {
    "iso:country":"US",
    "sg:address":"129 S Chestnut St",
    "sg:city":"Kimball",
    "sg:classifiers":[
        {
            "category":"Shopping",
            "subcategory":"Pharmacy",
            "type":"Retail Goods"
        }
    ],
    "sg:phone":"+1 308 235 4644",
    "sg:postcode":"69145",
    "sg:province":"NE",
    "sg:tags":[
        "drug",
        "store"
    ],
    "wof:name":"Walker Pharmacy Inc",
    "wof:placetype":"venue"
},
  "geometry": {"coordinates":[-103.662981,41.238015],"type":"Point"}
}