{
  "type": "Feature",
  "properties": {
    "addr:full":"4650 S 24th St Omaha NE 68107",
    "addr:housenumber":"4650",
    "addr:postcode":"68107",
    "addr:street":"S 24Th St",
    "iso:country":"US",
    "sg:address":"4650 S 24th St",
    "sg:city":"Omaha",
    "sg:classifiers":[
        {
            "category":"Banks & Credit Unions",
            "subcategory":"Bank",
            "type":"Services"
        }
    ],
    "sg:phone":"+1 402 536 2625",
    "sg:postcode":"68107",
    "sg:province":"NE",
    "wof:name":"Wells Fargo Bank Nebraska N A",
    "wof:placetype":"venue"
},
  "geometry": {"coordinates":[-95.947197,41.2127],"type":"Point"}
}