{
  "type": "Feature",
  "properties": {
    "addr:full":"5040 S 81st St Omaha NE 68127",
    "addr:housenumber":"5040",
    "addr:postcode":"68127",
    "addr:street":"S 81St St",
    "iso:country":"US",
    "sg:address":"5040 S 81st St",
    "sg:city":"Omaha",
    "sg:classifiers":[
        {
            "category":"Personal",
            "subcategory":"Beauty Salon",
            "type":"Services"
        }
    ],
    "sg:phone":"+1 402 592 5339",
    "sg:postcode":"68127",
    "sg:province":"NE",
    "sg:tags":[
        "shop"
    ],
    "wof:name":"Beauty Parlour",
    "wof:placetype":"venue"
},
  "geometry": {"coordinates":[-96.03973000000001,41.206027],"type":"Point"}
}