{
  "type": "Feature",
  "properties": {
    "iso:country":"US",
    "sg:address":"1000 Fort Crook Rd N # 100",
    "sg:city":"Bellevue",
    "sg:classifiers":[
        {
            "category":"Wholesale",
            "subcategory":"Machinery & Supplies",
            "type":"Manufacturing & Wholesale Goods"
        }
    ],
    "sg:phone":"+1 402 597 5777",
    "sg:postcode":"68005",
    "sg:province":"NE",
    "sg:tags":[
        "industrial",
        "equipment",
        "used",
        "machinery-new",
        "supplies-wholesale"
    ],
    "sg:website":"http://www.mbasuppliers.com",
    "wof:name":"Mba Suppliers, Inc",
    "wof:placetype":"venue"
},
  "geometry": {"coordinates":[-95.926613,41.17646],"type":"Point"}
}