{
  "type": "Feature",
  "properties": {
    "addr:full":"414 Main St Winside NE 68790",
    "addr:housenumber":"414",
    "addr:postcode":"68790",
    "addr:street":"Main St",
    "iso:country":"US",
    "sg:address":"414 Main St",
    "sg:city":"Winside",
    "sg:classifiers":[
        {
            "category":"Bars & Pubs",
            "type":"Food & Drink"
        }
    ],
    "sg:phone":"+1 402 286 4319",
    "sg:postcode":"68790",
    "sg:province":"NE",
    "wof:name":"D J's Saloon",
    "wof:placetype":"venue"
},
  "geometry": {"coordinates":[-97.176581,42.175735],"type":"Point"}
}