{
  "type": "Feature",
  "properties": {
    "iso:country":"US",
    "sg:address":"7016 Railroad Ave",
    "sg:city":"Bellevue",
    "sg:classifiers":[
        {
            "category":"Autos & Motor Vehicles",
            "subcategory":"Automobile Sales",
            "type":"Retail Goods"
        }
    ],
    "sg:phone":"+1 402 733 7277",
    "sg:postcode":"68147",
    "sg:province":"NE",
    "sg:tags":[
        "used"
    ],
    "wof:name":"All Cars & Trucks",
    "wof:placetype":"venue"
},
  "geometry": {"coordinates":[-95.93498,41.188428],"type":"Point"}
}