{
  "type": "Feature",
  "properties": {
    "iso:country":"US",
    "sg:address":"1317 N 5th St",
    "sg:city":"Oneill",
    "sg:classifiers":[
        {
            "category":"Social Services",
            "subcategory":"Child Care",
            "type":"Services"
        }
    ],
    "sg:phone":"+1 402 336 3683",
    "sg:postcode":"68763",
    "sg:province":"NE",
    "sg:tags":[
        "day"
    ],
    "wof:name":"Cunningham Daycare",
    "wof:placetype":"venue"
},
  "geometry": {"coordinates":[-98.646798,42.468614],"type":"Point"}
}