{
  "type": "Feature",
  "properties": {
    "iso:country":"US",
    "sg:address":"113 E 5th St",
    "sg:city":"Lexington",
    "sg:classifiers":[
        {
            "category":"Manufacturing",
            "subcategory":"Tools & Machinery",
            "type":"Manufacturing & Wholesale Goods"
        }
    ],
    "sg:phone":"+1 308 324 2313",
    "sg:postcode":"68850",
    "sg:province":"NE",
    "sg:tags":[
        "machine",
        "shop"
    ],
    "wof:name":"S & W Auto Parts",
    "wof:placetype":"venue"
},
  "geometry": {"coordinates":[-99.74140800000001,40.777857],"type":"Point"}
}