{
  "type": "Feature",
  "properties": {
    "iso:country":"US",
    "sg:address":"2516 Deer Park Blvd",
    "sg:city":"Omaha",
    "sg:classifiers":[
        {
            "category":"Building & Trades",
            "subcategory":"Construction",
            "type":"Services"
        }
    ],
    "sg:phone":"+1 402 342 1607",
    "sg:postcode":"68105",
    "sg:province":"NE",
    "sg:tags":[
        "bridge",
        "contractor",
        "commercial",
        "paving",
        "general"
    ],
    "sg:website":"www.hawkins1.com",
    "wof:name":"Hawkins Construction Company",
    "wof:placetype":"venue"
},
  "geometry": {"coordinates":[-95.95161299999999,41.229663],"type":"Point"}
}