{
  "type": "Feature",
  "properties": {
    "iso:country":"US",
    "sg:address":"4895 US Hwy 6",
    "sg:city":"Hastings",
    "sg:classifiers":[
        {
            "category":"Real Estate",
            "subcategory":"Real Estate Operator",
            "type":"Services"
        }
    ],
    "sg:phone":"+1 402 463 1972",
    "sg:postcode":"68901",
    "sg:province":"NE",
    "sg:tags":[
        "property",
        "lessor"
    ],
    "wof:name":"Eugene Krabel",
    "wof:placetype":"venue"
},
  "geometry": {"coordinates":[-98.44775,40.567985],"type":"Point"}
}