{
  "type": "Feature",
  "properties": {
    "iso:country":"US",
    "sg:address":"8733 Countryside Plz",
    "sg:city":"Omaha",
    "sg:classifiers":[
        {
            "category":"Shopping",
            "subcategory":"Clothing, Apparel, & Fashions",
            "type":"Retail Goods"
        }
    ],
    "sg:phone":"+1 402 391 1880",
    "sg:postcode":"68114",
    "sg:province":"NE",
    "wof:name":"She LA",
    "wof:placetype":"venue"
},
  "geometry": {"coordinates":[-96.048018,41.24941],"type":"Point"}
}