{
  "type": "Feature",
  "properties": {
    "iso:country":"US",
    "sg:address":"1711 Short St",
    "sg:city":"North Platte",
    "sg:classifiers":[
        {
            "category":"Wholesale",
            "subcategory":"Farm Supplies",
            "type":"Manufacturing & Wholesale Goods"
        }
    ],
    "sg:phone":"+1 308 532 5434",
    "sg:postcode":"69101",
    "sg:province":"NE",
    "sg:tags":[
        "livestock"
    ],
    "wof:name":"Rex Richardson Ranch Co",
    "wof:placetype":"venue"
},
  "geometry": {"coordinates":[-100.784266,41.134539],"type":"Point"}
}