{
  "type": "Feature",
  "properties": {
    "iso:country":"US",
    "sg:address":"514 13th St",
    "sg:city":"Holdrege",
    "sg:classifiers":[
        {
            "category":"Wholesale",
            "subcategory":"Scrap",
            "type":"Manufacturing & Wholesale Goods"
        }
    ],
    "sg:phone":"+1 308 995 4612",
    "sg:postcode":"68949",
    "sg:province":"NE",
    "sg:tags":[
        "recycling",
        "center"
    ],
    "wof:name":"Holdrege Area Recycling",
    "wof:placetype":"venue"
},
  "geometry": {"coordinates":[-99.373746,40.423354],"type":"Point"}
}