{
  "type": "Feature",
  "properties": {
    "addr:full":"9621 N 30th St Omaha NE 68112",
    "addr:housenumber":"9621",
    "addr:postcode":"68112",
    "addr:street":"N 30Th St",
    "iso:country":"US",
    "sg:address":"9621 N 30th St",
    "sg:city":"Omaha",
    "sg:classifiers":[
        {
            "category":"Professional",
            "subcategory":"Business Services",
            "type":"Services"
        }
    ],
    "sg:phone":"+1 402 455 3323",
    "sg:postcode":"68112",
    "sg:province":"NE",
    "sg:tags":[
        "auctioneer"
    ],
    "wof:name":"Hidden Treasures",
    "wof:placetype":"venue"
},
  "geometry": {"coordinates":[-95.963814,41.350055],"type":"Point"}
}