{
  "type": "Feature",
  "properties": {
    "iso:country":"US",
    "sg:address":"2939 Cornhusker Hwy",
    "sg:city":"Lincoln",
    "sg:classifiers":[
        {
            "category":"Wholesale",
            "subcategory":"Hardware",
            "type":"Manufacturing & Wholesale Goods"
        }
    ],
    "sg:phone":"+1 402 435 3828",
    "sg:postcode":"68504",
    "sg:province":"NE",
    "sg:tags":[
        "purifying",
        "cleaning",
        "air"
    ],
    "wof:name":"Ductmedic Air Duct Cleaning",
    "wof:placetype":"venue"
},
  "geometry": {"coordinates":[-96.678089,40.842436],"type":"Point"}
}