{
  "type": "Feature",
  "properties": {
    "iso:country":"US",
    "sg:address":"1240 E 11th St",
    "sg:city":"Fremont",
    "sg:classifiers":[
        {
            "category":"Education",
            "subcategory":"School",
            "type":"Public Place"
        }
    ],
    "sg:phone":"+1 402 727 3178",
    "sg:postcode":"68025",
    "sg:province":"NE",
    "wof:name":"Bell Field Elementary School",
    "wof:placetype":"venue"
},
  "geometry": {"coordinates":[-96.481544,41.439193],"type":"Point"}
}