{
  "type": "Feature",
  "properties": {
    "addr:full":"4839 N 90th St Omaha NE 68134",
    "addr:housenumber":"4839",
    "addr:postcode":"68134",
    "addr:street":"N 90Th St",
    "iso:country":"US",
    "sg:address":"4839 N 90th St",
    "sg:city":"Omaha",
    "sg:classifiers":[
        {
            "category":"Retail",
            "subcategory":"Auto Repair",
            "type":"Services"
        }
    ],
    "sg:phone":"+1 402 571 0944",
    "sg:postcode":"68134",
    "sg:province":"NE",
    "sg:tags":[
        "repairing",
        "automobile",
        "brake"
    ],
    "sg:website":"http://clickserve.dartsearch.net/link/click?lid=43000000313869477&ds_s_kwgid=58000000006820725&ds_e_matchtype={MatchType}&ds_e_kwdid={OrderItemId}&ds_e_adid={AdId}&ds_url_v=2",
    "wof:name":"Meineke Car Care Center",
    "wof:placetype":"venue"
},
  "geometry": {"coordinates":[-96.052048,41.303188],"type":"Point"}
}