{
  "type": "Feature",
  "properties": {
    "addr:full":"1120 S 101st St Omaha NE 68124",
    "addr:housenumber":"1120",
    "addr:postcode":"68124",
    "addr:street":"S 101St St",
    "iso:country":"US",
    "sg:address":"1120 S 101st St",
    "sg:city":"Omaha",
    "sg:classifiers":[
        {
            "category":"Banks & Credit Unions",
            "subcategory":"Investment Brokerage",
            "type":"Services"
        }
    ],
    "sg:phone":"+1 402 392 6100",
    "sg:postcode":"68124",
    "sg:province":"NE",
    "sg:tags":[
        "security"
    ],
    "wof:name":"Rbc Dain Rauscher Corporation",
    "wof:placetype":"venue"
},
  "geometry": {"coordinates":[-96.07007299999999,41.245616],"type":"Point"}
}