{
  "type": "Feature",
  "properties": {
    "addr:full":"416 S 12th St Omaha NE 68102",
    "addr:housenumber":"416",
    "addr:postcode":"68102",
    "addr:street":"S 12Th St",
    "iso:country":"US",
    "sg:address":"416 S 12th St",
    "sg:city":"Omaha",
    "sg:classifiers":[
        {
            "category":"Restaurant",
            "type":"Food & Drink"
        }
    ],
    "sg:phone":"+1 402 408 5566",
    "sg:postcode":"68102",
    "sg:province":"NE",
    "sg:tags":[
        "sushi",
        "bar"
    ],
    "sg:website":"www.bluesushisakegrill.com",
    "wof:name":"Blue Sushi Sake & Grill",
    "wof:placetype":"venue"
},
  "geometry": {"coordinates":[-95.932194,41.255865],"type":"Point"}
}