{
  "type": "Feature",
  "properties": {
    "addr:full":"5208 S 21st St Omaha NE 68107",
    "addr:housenumber":"5208",
    "addr:postcode":"68107",
    "addr:street":"S 21St St",
    "iso:country":"US",
    "sg:address":"5208 S 21st St",
    "sg:city":"Omaha",
    "sg:classifiers":[
        {
            "category":"Retail",
            "subcategory":"Auto Repair",
            "type":"Services"
        }
    ],
    "sg:phone":"+1 402 731 3358",
    "sg:postcode":"68107",
    "sg:province":"NE",
    "sg:tags":[
        "repairing",
        "automobile"
    ],
    "wof:name":"Frank's Automotive",
    "wof:placetype":"venue"
},
  "geometry": {"coordinates":[-95.943113,41.203839],"type":"Point"}
}