{
  "type": "Feature",
  "properties": {
    "iso:country":"US",
    "sg:address":"114 W Main St",
    "sg:city":"Pierce",
    "sg:classifiers":[
        {
            "category":"Professional",
            "subcategory":"Business Services",
            "type":"Services"
        }
    ],
    "sg:phone":"+1 402 329 4831",
    "sg:postcode":"68767",
    "sg:province":"NE",
    "sg:tags":[
        "auctioneer"
    ],
    "wof:name":"Farm & Home Realty & Auction",
    "wof:placetype":"venue"
},
  "geometry": {"coordinates":[-97.52843799999999,42.198942],"type":"Point"}
}