{
  "type": "Feature",
  "properties": {
    "iso:country":"US",
    "sg:address":"612 E 1st St",
    "sg:city":"Stuart",
    "sg:classifiers":[
        {
            "category":"Travel",
            "subcategory":"Hotels & Motels",
            "type":"Entertainment"
        }
    ],
    "sg:phone":"+1 402 924 3133",
    "sg:postcode":"68713",
    "sg:province":"NE",
    "wof:name":"Stuart Village Inn",
    "wof:placetype":"venue"
},
  "geometry": {"coordinates":[-98.972038,42.533196],"type":"Point"}
}