{
  "type": "Feature",
  "properties": {
    "addr:full":"179 Oregon Trl Lincoln NE 68521",
    "addr:housenumber":"179",
    "addr:postcode":"68521",
    "addr:street":"Oregon Trl",
    "iso:country":"US",
    "sg:address":"179 Oregon Trl",
    "sg:city":"Lincoln",
    "sg:classifiers":[
        {
            "category":"Personal",
            "type":"Services"
        }
    ],
    "sg:phone":"+1 402 474 4801",
    "sg:postcode":"68521",
    "sg:province":"NE",
    "sg:tags":[
        "shop",
        "beauty"
    ],
    "wof:name":"Aloha Tanning Salon",
    "wof:placetype":"venue"
},
  "geometry": {"coordinates":[-96.72169,40.844845],"type":"Point"}
}