{
  "type": "Feature",
  "properties": {
    "iso:country":"US",
    "sg:address":"6210 Judson St",
    "sg:city":"Lincoln",
    "sg:classifiers":[
        {
            "category":"Building & Trades",
            "subcategory":"Construction",
            "type":"Services"
        }
    ],
    "sg:phone":"+1 402 429 6277",
    "sg:postcode":"68507",
    "sg:province":"NE",
    "sg:tags":[
        "repairing",
        "remodeling",
        "contractor"
    ],
    "wof:name":"Cole Contracting Svc",
    "wof:placetype":"venue"
},
  "geometry": {"coordinates":[-96.634536,40.845609],"type":"Point"}
}