{
  "type": "Feature",
  "properties": {
    "iso:country":"US",
    "sg:address":"4837 Calvert St",
    "sg:city":"Lincoln",
    "sg:classifiers":[
        {
            "category":"Organizations",
            "subcategory":"Religious Organization",
            "type":"Services"
        }
    ],
    "sg:phone":"+1 402 580 3710",
    "sg:postcode":"68506",
    "sg:province":"NE",
    "sg:tags":[
        "church"
    ],
    "wof:name":"Christian Student Fellowship",
    "wof:placetype":"venue"
},
  "geometry": {"coordinates":[-96.652733,40.776964],"type":"Point"}
}