{
  "type": "Feature",
  "properties": {
    "iso:country":"US",
    "sg:address":"22800 S 148th St",
    "sg:city":"Adams",
    "sg:classifiers":[
        {
            "category":"Professional",
            "subcategory":"Business Services",
            "type":"Services"
        }
    ],
    "sg:phone":"+1 402 788 2210",
    "sg:postcode":"68301",
    "sg:province":"NE",
    "sg:tags":[
        "auctioneer"
    ],
    "wof:name":"Vandertook Auction LLC",
    "wof:placetype":"venue"
},
  "geometry": {"coordinates":[-96.520461,40.587859],"type":"Point"}
}