{
  "type": "Feature",
  "properties": {
    "iso:country":"US",
    "sg:address":"1224 Sunset Dr",
    "sg:city":"Bellevue",
    "sg:classifiers":[
        {
            "category":"Building & Trades",
            "subcategory":"Construction",
            "type":"Services"
        }
    ],
    "sg:phone":"+1 402 292 6087",
    "sg:postcode":"68005",
    "sg:province":"NE",
    "sg:tags":[
        "hanging",
        "painter",
        "contractor"
    ],
    "wof:name":"Ziggy Painting & Dec Inc",
    "wof:placetype":"venue"
},
  "geometry": {"coordinates":[-95.915043,41.138686],"type":"Point"}
}