{
  "type": "Feature",
  "properties": {
    "iso:country":"US",
    "sg:address":"10160 Maple St",
    "sg:city":"Omaha",
    "sg:classifiers":[
        {
            "category":"Deli",
            "type":"Food & Drink"
        }
    ],
    "sg:menulink":"http://www.allmenus.com/ne/omaha/126254-blimpie-subs--sandwiches/menu/",
    "sg:phone":"+1 402 572 4155",
    "sg:postcode":"68134",
    "sg:province":"NE",
    "sg:tags":[
        "wrap",
        "american",
        "sandwich"
    ],
    "wof:name":"Blimpie Subs & Sandwiches",
    "wof:placetype":"venue"
},
  "geometry": {"coordinates":[-96.06970699999999,41.285142],"type":"Point"}
}