{
  "type": "Feature",
  "properties": {
    "iso:country":"US",
    "sg:address":"302 N 4th St",
    "sg:city":"Doniphan",
    "sg:classifiers":[
        {
            "category":"Organizations",
            "subcategory":"Religious Organization",
            "type":"Services"
        }
    ],
    "sg:phone":"+1 402 845 2339",
    "sg:postcode":"68832",
    "sg:province":"NE",
    "sg:tags":[
        "church"
    ],
    "wof:name":"Lutheran Parsonage St Paul",
    "wof:placetype":"venue"
},
  "geometry": {"coordinates":[-98.37486800000001,40.776647],"type":"Point"}
}