{
  "type": "Feature",
  "properties": {
    "addr:full":"674 Rd West D S Ogallala NE 69153",
    "addr:housenumber":"674",
    "addr:postcode":"69153",
    "addr:street":"Rd West D",
    "iso:country":"US",
    "sg:address":"674 Rd West D S",
    "sg:city":"Ogallala",
    "sg:phone":"+1 308 284 3280",
    "sg:postcode":"69153",
    "sg:province":"NE",
    "sg:tags":[
        "farm",
        "corn",
        "wheat"
    ],
    "wof:name":"Martin Flaming",
    "wof:placetype":"venue"
},
  "geometry": {"coordinates":[-101.806659,41.077444],"type":"Point"}
}