{
  "type": "Feature",
  "properties": {
    "iso:country":"US",
    "sg:address":"324 Norris Ave",
    "sg:city":"Mc Cook",
    "sg:classifiers":[
        {
            "category":"Banks & Credit Unions",
            "subcategory":"Bank",
            "type":"Services"
        }
    ],
    "sg:phone":"+1 308 345 7040",
    "sg:postcode":"69001",
    "sg:province":"NE",
    "sg:tags":[
        "federally",
        "chartered"
    ],
    "wof:name":"KRD Federal Credit Union",
    "wof:placetype":"venue"
},
  "geometry": {"coordinates":[-100.625905,40.200396],"type":"Point"}
}