{
  "type": "Feature",
  "properties": {
    "iso:country":"US",
    "sg:address":"1911 N Lincoln Ave",
    "sg:city":"York",
    "sg:classifiers":[
        {
            "category":"Manufacturing",
            "subcategory":"Tools & Machinery",
            "type":"Manufacturing & Wholesale Goods"
        }
    ],
    "sg:phone":"+1 402 362 7769",
    "sg:postcode":"68467",
    "sg:province":"NE",
    "sg:tags":[
        "machine",
        "shop"
    ],
    "wof:name":"Dibbern Machine",
    "wof:placetype":"venue"
},
  "geometry": {"coordinates":[-97.593101,40.879551],"type":"Point"}
}