{
  "type": "Feature",
  "properties": {
    "iso:country":"US",
    "sg:address":"1220 E 26th St",
    "sg:city":"Kearney",
    "sg:classifiers":[
        {
            "category":"Government",
            "subcategory":"Office",
            "type":"Public Place"
        }
    ],
    "sg:phone":"+1 308 233 3268",
    "sg:postcode":"68847",
    "sg:province":"NE",
    "sg:tags":[
        "govt",
        "city"
    ],
    "wof:name":"Kearney Utilities Dept",
    "wof:placetype":"venue"
},
  "geometry": {"coordinates":[-99.066401,40.700282],"type":"Point"}
}