{
  "type": "Feature",
  "properties": {
    "addr:full":"2330 N 154th St Omaha NE 68116",
    "addr:housenumber":"2330",
    "addr:postcode":"68116",
    "addr:street":"N 154Th St",
    "iso:country":"US",
    "sg:address":"2330 N 154th St",
    "sg:city":"Omaha",
    "sg:classifiers":[
        {
            "category":"Insurance",
            "subcategory":"Insurance Agent",
            "type":"Services"
        }
    ],
    "sg:phone":"+1 402 333 6190",
    "sg:postcode":"68116",
    "sg:province":"NE",
    "wof:name":"Modern Woodmen of America",
    "wof:placetype":"venue"
},
  "geometry": {"coordinates":[-96.155232,41.284106],"type":"Point"}
}