{
  "type": "Feature",
  "properties": {
    "iso:country":"US",
    "sg:address":"2720 N 84th St",
    "sg:city":"Omaha",
    "sg:classifiers":[
        {
            "category":"Manufacturing",
            "subcategory":"Pet Food",
            "type":"Manufacturing & Wholesale Goods"
        }
    ],
    "sg:phone":"+1 402 393 7440",
    "sg:postcode":"68134",
    "sg:province":"NE",
    "sg:tags":[
        "product",
        "health",
        "animal"
    ],
    "wof:name":"Bio Corp Animal Health",
    "wof:placetype":"venue"
},
  "geometry": {"coordinates":[-96.043476,41.284884],"type":"Point"}
}