{
  "type": "Feature",
  "properties": {
    "addr:full":"7635 S 38th St Lincoln NE 68516",
    "addr:housenumber":"7635",
    "addr:postcode":"68516",
    "addr:street":"S 38Th St",
    "iso:country":"US",
    "sg:address":"7635 S 38th St",
    "sg:city":"Lincoln",
    "sg:classifiers":[
        {
            "category":"Banks & Credit Unions",
            "subcategory":"Bank",
            "type":"Services"
        }
    ],
    "sg:phone":"+1 402 730 6330",
    "sg:postcode":"68516",
    "sg:province":"NE",
    "sg:tags":[
        "banker",
        "mortgage"
    ],
    "wof:name":"American Mortgage Center",
    "wof:placetype":"venue"
},
  "geometry": {"coordinates":[-96.66587699999999,40.734027],"type":"Point"}
}