{
  "type": "Feature",
  "properties": {
    "iso:country":"US",
    "sg:address":"119 W 3rd St",
    "sg:city":"Grand Island",
    "sg:classifiers":[
        {
            "category":"Communications",
            "subcategory":"Television Station",
            "type":"Services"
        }
    ],
    "sg:phone":"+1 308 384 1300",
    "sg:postcode":"68801",
    "sg:province":"NE",
    "sg:tags":[
        "broadcasting",
        "co"
    ],
    "wof:name":"NTV Grand Island",
    "wof:placetype":"venue"
},
  "geometry": {"coordinates":[-98.34007699999999,40.925695],"type":"Point"}
}