{
  "type": "Feature",
  "properties": {
    "iso:country":"US",
    "sg:address":"75060 Rd 419",
    "sg:city":"Eustis",
    "sg:phone":"+1 308 486 2881",
    "sg:postcode":"69028",
    "sg:province":"NE",
    "sg:tags":[
        "farm",
        "corn",
        "soybean"
    ],
    "wof:name":"Mark Timm Corp The",
    "wof:placetype":"venue"
},
  "geometry": {"coordinates":[-100.014133,40.70859],"type":"Point"}
}