{
  "type": "Feature",
  "properties": {
    "addr:full":"7821 Wakeley Plz Omaha NE 68114",
    "addr:housenumber":"7821",
    "addr:postcode":"68114",
    "addr:street":"Wakeley Plz",
    "iso:country":"US",
    "sg:address":"7821 Wakeley Plz",
    "sg:city":"Omaha",
    "sg:classifiers":[
        {
            "category":"Health Services",
            "subcategory":"Doctor",
            "type":"Services"
        }
    ],
    "sg:phone":"+1 402 399 8500",
    "sg:postcode":"68114",
    "sg:province":"NE",
    "sg:tags":[
        "physician",
        "surgeon"
    ],
    "wof:name":"John F Mc Leay MD",
    "wof:placetype":"venue"
},
  "geometry": {"coordinates":[-96.037976,41.261728],"type":"Point"}
}