{
  "type": "Feature",
  "properties": {
    "iso:country":"US",
    "sg:address":"5170 Q St",
    "sg:city":"Omaha",
    "sg:classifiers":[
        {
            "category":"Food & Beverages",
            "subcategory":"Meat & Fish",
            "type":"Retail Goods"
        }
    ],
    "sg:phone":"+1 402 731 0776",
    "sg:postcode":"68117",
    "sg:province":"NE",
    "sg:tags":[
        "market"
    ],
    "wof:name":"Frank Stoysich Meats",
    "wof:placetype":"venue"
},
  "geometry": {"coordinates":[-95.995634,41.205275],"type":"Point"}
}