{
  "type": "Feature",
  "properties": {
    "iso:country":"US",
    "sg:address":"6464 S 84th St",
    "sg:city":"Omaha",
    "sg:classifiers":[
        {
            "category":"Autos & Motor Vehicles",
            "subcategory":"Auto Supplies",
            "type":"Retail Goods"
        }
    ],
    "sg:phone":"+1 402 592 4557",
    "sg:postcode":"68127",
    "sg:province":"NE",
    "sg:tags":[
        "tire"
    ],
    "wof:name":"Monarch Tires & Wheels Inc",
    "wof:placetype":"venue"
},
  "geometry": {"coordinates":[-96.04306699999999,41.196708],"type":"Point"}
}