{
  "type": "Feature",
  "properties": {
    "addr:full":"2011 Illinois Ave Grand Island NE 68801",
    "addr:housenumber":"2011",
    "addr:postcode":"68801",
    "addr:street":"Illinois Ave",
    "iso:country":"US",
    "sg:address":"2011 Illinois Ave",
    "sg:city":"Grand Island",
    "sg:classifiers":[
        {
            "category":"Manufacturing",
            "subcategory":"Wood Products",
            "type":"Manufacturing & Wholesale Goods"
        }
    ],
    "sg:phone":"+1 308 381 2368",
    "sg:postcode":"68801",
    "sg:province":"NE",
    "sg:tags":[
        "mfg"
    ],
    "wof:name":"Wood Shack",
    "wof:placetype":"venue"
},
  "geometry": {"coordinates":[-98.34455,40.945574],"type":"Point"}
}