{
  "type": "Feature",
  "properties": {
    "iso:country":"US",
    "sg:address":"5612 Pine St",
    "sg:city":"Omaha",
    "sg:classifiers":[
        {
            "category":"Building & Trades",
            "subcategory":"Construction",
            "type":"Services"
        }
    ],
    "sg:phone":"+1 402 553 7171",
    "sg:postcode":"68106",
    "sg:province":"NE",
    "sg:tags":[
        "hanging",
        "contractor"
    ],
    "wof:name":"Painter",
    "wof:placetype":"venue"
},
  "geometry": {"coordinates":[-96.00175299999999,41.244291],"type":"Point"}
}