{
  "type": "Feature",
  "properties": {
    "iso:country":"US",
    "sg:address":"4121 N 21st St",
    "sg:city":"Omaha",
    "sg:classifiers":[
        {
            "category":"Social Services",
            "subcategory":"Child Care",
            "type":"Services"
        }
    ],
    "sg:phone":"+1 402 933 6423",
    "sg:postcode":"68110",
    "sg:province":"NE",
    "wof:name":"White's Child Care Ctr",
    "wof:placetype":"venue"
},
  "geometry": {"coordinates":[-95.943286,41.296798],"type":"Point"}
}