{
  "type": "Feature",
  "properties": {
    "iso:country":"US",
    "sg:address":"1717 Annette Ln",
    "sg:city":"Lincoln",
    "sg:classifiers":[
        {
            "category":"Building & Trades",
            "subcategory":"Construction",
            "type":"Services"
        }
    ],
    "sg:phone":"+1 402 328 8695",
    "sg:postcode":"68512",
    "sg:province":"NE",
    "sg:tags":[
        "contractor"
    ],
    "wof:name":"Huskerland Siding",
    "wof:placetype":"venue"
},
  "geometry": {"coordinates":[-96.69708,40.734239],"type":"Point"}
}