{
  "type": "Feature",
  "properties": {
    "addr:full":"140 N 12th St Lincoln NE 68508",
    "addr:housenumber":"140",
    "addr:postcode":"68508",
    "addr:street":"N 12Th St",
    "iso:country":"US",
    "sg:address":"140 N 12th St",
    "sg:city":"Lincoln",
    "sg:classifiers":[
        {
            "category":"Shopping",
            "subcategory":"Tobacco",
            "type":"Retail Goods"
        }
    ],
    "sg:phone":"+1 402 476 0119",
    "sg:postcode":"68508",
    "sg:province":"NE",
    "sg:tags":[
        "product"
    ],
    "wof:name":"Cliffs  LLC",
    "wof:placetype":"venue"
},
  "geometry": {"coordinates":[-96.703959,40.814103],"type":"Point"}
}