{
  "type": "Feature",
  "properties": {
    "iso:country":"US",
    "sg:address":"1902 S 13th St",
    "sg:city":"Omaha",
    "sg:classifiers":[
        {
            "category":"Shopping",
            "subcategory":"Used Merchandise",
            "type":"Retail Goods"
        }
    ],
    "sg:phone":"+1 402 341 0650",
    "sg:postcode":"68108",
    "sg:province":"NE",
    "sg:tags":[
        "antique"
    ],
    "wof:name":"City Slicker Antiques",
    "wof:placetype":"venue"
},
  "geometry": {"coordinates":[-95.93338799999999,41.239463],"type":"Point"}
}