{
  "type": "Feature",
  "properties": {
    "iso:country":"US",
    "sg:address":"3227 Harney St",
    "sg:city":"Omaha",
    "sg:classifiers":[
        {
            "category":"Professional",
            "subcategory":"Management & Consulting",
            "type":"Services"
        },
        {
            "category":"Professional",
            "subcategory":"Research",
            "type":"Services"
        },
        {
            "category":"Professional",
            "subcategory":"Advertising",
            "type":"Services"
        }
    ],
    "sg:phone":"+1 402 346 1346",
    "sg:postcode":"68131",
    "sg:province":"NE",
    "sg:tags":[
        "marketing",
        "agency",
        "market",
        "analysis",
        "consultant"
    ],
    "wof:name":"Orthopedic Marketing Group",
    "wof:placetype":"venue"
},
  "geometry": {"coordinates":[-95.959897,41.256679],"type":"Point"}
}