{
  "type": "Feature",
  "properties": {
    "iso:country":"US",
    "sg:address":"6802 Park View Ln",
    "sg:city":"Omaha",
    "sg:classifiers":[
        {
            "category":"Communications",
            "subcategory":"Film & Video Production",
            "type":"Services"
        }
    ],
    "sg:phone":"+1 402 571 0988",
    "sg:postcode":"68104",
    "sg:province":"NE",
    "sg:tags":[
        "motion"
    ],
    "wof:name":"Guaranteed Services",
    "wof:placetype":"venue"
},
  "geometry": {"coordinates":[-96.017419,41.309346],"type":"Point"}
}