{
  "type": "Feature",
  "properties": {
    "iso:country":"US",
    "sg:address":"809 N 121st St",
    "sg:city":"Omaha",
    "sg:classifiers":[
        {
            "category":"Real Estate",
            "subcategory":"Real Estate Operator",
            "type":"Services"
        }
    ],
    "sg:phone":"+1 402 493 0990",
    "sg:postcode":"68154",
    "sg:province":"NE",
    "sg:tags":[
        "building",
        "apartment"
    ],
    "wof:name":"Mc Kenna Construction Co",
    "wof:placetype":"venue"
},
  "geometry": {"coordinates":[-96.101226,41.269411],"type":"Point"}
}