{
  "type": "Feature",
  "properties": {
    "addr:full":"2820 24th Rd Clarks NE 68628",
    "addr:housenumber":"2820",
    "addr:postcode":"68628",
    "addr:street":"24Th Rd",
    "iso:country":"US",
    "sg:address":"2820 24th Rd",
    "sg:city":"Clarks",
    "sg:classifiers":[
        {
            "category":"Building & Trades",
            "subcategory":"Construction",
            "type":"Services"
        }
    ],
    "sg:phone":"+1 308 548 2675",
    "sg:postcode":"68628",
    "sg:province":"NE",
    "sg:tags":[
        "house"
    ],
    "wof:name":"Joey Carlson",
    "wof:placetype":"venue"
},
  "geometry": {"coordinates":[-97.848386,41.264629],"type":"Point"}
}