{
  "type": "Feature",
  "properties": {
    "addr:full":"101 N Chestnut St North Platte NE 69101",
    "addr:housenumber":"101",
    "addr:postcode":"69101",
    "addr:street":"N Chestnut St",
    "iso:country":"US",
    "sg:address":"101 N Chestnut St",
    "sg:city":"North Platte",
    "sg:classifiers":[
        {
            "category":"Professional",
            "subcategory":"Accounting & Tax Preparation",
            "type":"Services"
        }
    ],
    "sg:phone":"+1 308 532 8850",
    "sg:postcode":"69101",
    "sg:province":"NE",
    "wof:name":"C Martin James",
    "wof:placetype":"venue"
},
  "geometry": {"coordinates":[-100.76014000000001,41.133614],"type":"Point"}
}