{
  "type": "Feature",
  "properties": {
    "addr:full":"1520 W 3rd St Alliance NE 69301",
    "addr:housenumber":"1520",
    "addr:postcode":"69301",
    "addr:street":"W 3Rd St",
    "iso:country":"US",
    "sg:address":"1520 W 3rd St",
    "sg:city":"Alliance",
    "sg:classifiers":[
        {
            "category":"Organizations",
            "subcategory":"Community Association",
            "type":"Services"
        }
    ],
    "sg:phone":"+1 308 762 3262",
    "sg:postcode":"69301",
    "sg:province":"NE",
    "sg:tags":[
        "fraternal"
    ],
    "wof:name":"Fraternal Order Of Eagles",
    "wof:placetype":"venue"
},
  "geometry": {"coordinates":[-102.894167,42.096814],"type":"Point"}
}