{
  "type": "Feature",
  "properties": {
    "addr:full":"205 E 6th St Neligh NE 68756",
    "addr:housenumber":"205",
    "addr:postcode":"68756",
    "addr:street":"E 6Th St",
    "iso:country":"US",
    "sg:address":"205 E 6th St",
    "sg:city":"Neligh",
    "sg:classifiers":[
        {
            "category":"Government",
            "subcategory":"Police Station",
            "type":"Public Place"
        }
    ],
    "sg:phone":"+1 402 887 4335",
    "sg:postcode":"68756",
    "sg:province":"NE",
    "sg:tags":[
        "department"
    ],
    "wof:name":"Neligh Police Station",
    "wof:placetype":"venue"
},
  "geometry": {"coordinates":[-98.028526,42.130515],"type":"Point"}
}