{
  "type": "Feature",
  "properties": {
    "iso:country":"US",
    "sg:address":"734 2nd St",
    "sg:city":"Chappell",
    "sg:classifiers":[
        {
            "category":"Food & Beverages",
            "subcategory":"Groceries & Convenience Stores",
            "type":"Retail Goods"
        }
    ],
    "sg:phone":"+1 308 874 2701",
    "sg:postcode":"69129",
    "sg:province":"NE",
    "sg:tags":[
        "grocer"
    ],
    "wof:name":"Chappell Super Foods",
    "wof:placetype":"venue"
},
  "geometry": {"coordinates":[-102.47192699999999,41.092649],"type":"Point"}
}