{
  "type": "Feature",
  "properties": {
    "iso:country":"US",
    "sg:address":"5263 Co Rd 33",
    "sg:city":"Blair",
    "sg:classifiers":[
        {
            "category":"Farming",
            "subcategory":"Farm",
            "type":"Manufacturing & Wholesale Goods"
        }
    ],
    "sg:phone":"+1 402 426 9260",
    "sg:postcode":"68008",
    "sg:province":"NE",
    "sg:tags":[
        "crop",
        "general"
    ],
    "wof:name":"Still Meadows Farm",
    "wof:placetype":"venue"
},
  "geometry": {"coordinates":[-96.136596,41.455457],"type":"Point"}
}