{
  "type": "Feature",
  "properties": {
    "iso:country":"US",
    "sg:address":"3602 D St",
    "sg:city":"Omaha",
    "sg:classifiers":[
        {
            "category":"Shopping",
            "type":"Retail Goods"
        }
    ],
    "sg:phone":"+1 402 733 7325",
    "sg:postcode":"68107",
    "sg:province":"NE",
    "sg:tags":[
        "ice"
    ],
    "wof:name":"Arctic Seal LLC",
    "wof:placetype":"venue"
},
  "geometry": {"coordinates":[-95.96992,41.221955],"type":"Point"}
}