{
  "type": "Feature",
  "properties": {
    "addr:full":"2821 15th St Columbus NE 68601",
    "addr:housenumber":"2821",
    "addr:postcode":"68601",
    "addr:street":"15Th St",
    "iso:country":"US",
    "sg:address":"2821 15th St",
    "sg:city":"Columbus",
    "sg:classifiers":[
        {
            "category":"Real Estate",
            "subcategory":"Real Estate Agent",
            "type":"Services"
        }
    ],
    "sg:phone":"+1 402 564 6606",
    "sg:postcode":"68601",
    "sg:province":"NE",
    "wof:name":"Roni Inc",
    "wof:placetype":"venue"
},
  "geometry": {"coordinates":[-97.362939,41.431225],"type":"Point"}
}