{
  "type": "Feature",
  "properties": {
    "iso:country":"US",
    "sg:address":"1600 Charolais Dr",
    "sg:city":"Norfolk",
    "sg:classifiers":[
        {
            "category":"Freight",
            "type":"Transportation"
        }
    ],
    "sg:phone":"+1 402 649 0135",
    "sg:postcode":"68701",
    "sg:province":"NE",
    "sg:tags":[
        "operator",
        "hauling",
        "trucking"
    ],
    "wof:name":"Wurtele Equipment Hauling Inc",
    "wof:placetype":"venue"
},
  "geometry": {"coordinates":[-97.43735599999999,42.052915],"type":"Point"}
}