{
  "type": "Feature",
  "properties": {
    "iso:country":"US",
    "sg:address":"609 E 26th St",
    "sg:city":"Scottsbluff",
    "sg:classifiers":[
        {
            "category":"Shopping",
            "subcategory":"Computers & Home Electronics",
            "type":"Retail Goods"
        }
    ],
    "sg:phone":"+1 308 635 1400",
    "sg:postcode":"69361",
    "sg:province":"NE",
    "sg:tags":[
        "software"
    ],
    "wof:name":"Galaxy Warzone Interactive",
    "wof:placetype":"venue"
},
  "geometry": {"coordinates":[-103.65388900000001,41.872656],"type":"Point"}
}