{
  "type": "Feature",
  "properties": {
    "iso:country":"US",
    "sg:address":"19035 Grand Island Rd",
    "sg:city":"Amherst",
    "sg:classifiers":[
        {
            "category":"Professional",
            "type":"Services"
        }
    ],
    "sg:phone":"+1 308 826 5185",
    "sg:postcode":"68812",
    "sg:province":"NE",
    "wof:name":"Mike Taubenheim",
    "wof:placetype":"venue"
},
  "geometry": {"coordinates":[-99.208806,40.916031],"type":"Point"}
}