{
  "type": "Feature",
  "properties": {
    "iso:country":"US",
    "sg:address":"4109 N 61st St",
    "sg:city":"Omaha",
    "sg:classifiers":[
        {
            "category":"Building & Trades",
            "subcategory":"Construction",
            "type":"Services"
        }
    ],
    "sg:phone":"+1 402 933 1795",
    "sg:postcode":"68104",
    "sg:province":"NE",
    "sg:tags":[
        "grading",
        "contractor"
    ],
    "wof:name":"Hartle Grading Inc",
    "wof:placetype":"venue"
},
  "geometry": {"coordinates":[-96.007013,41.298093],"type":"Point"}
}