{
  "type": "Feature",
  "properties": {
    "iso:country":"US",
    "sg:address":"230 E Calkins Ave",
    "sg:city":"Elm Creek",
    "sg:classifiers":[
        {
            "category":"Education",
            "subcategory":"School",
            "type":"Public Place"
        }
    ],
    "sg:phone":"+1 308 856 4300",
    "sg:postcode":"68836",
    "sg:province":"NE",
    "wof:name":"Elm Creek Elementary School",
    "wof:placetype":"venue"
},
  "geometry": {"coordinates":[-99.37123099999999,40.719274],"type":"Point"}
}