{
  "type": "Feature",
  "properties": {
    "iso:country":"US",
    "sg:address":"703 S Fillmore St",
    "sg:city":"Papillion",
    "sg:classifiers":[
        {
            "category":"Organizations",
            "subcategory":"Community Association",
            "type":"Services"
        }
    ],
    "sg:phone":"+1 402 331 2436",
    "sg:postcode":"68046",
    "sg:province":"NE",
    "wof:name":"Delta Kappa Gamma Society",
    "wof:placetype":"venue"
},
  "geometry": {"coordinates":[-96.05086300000001,41.135421],"type":"Point"}
}