{
  "type": "Feature",
  "properties": {
    "iso:country":"US",
    "sg:address":"170208 Co Rd 29",
    "sg:city":"Gering",
    "sg:classifiers":[
        {
            "category":"Real Estate",
            "subcategory":"Real Estate Operator",
            "type":"Services"
        }
    ],
    "sg:phone":"+1 308 783 1215",
    "sg:postcode":"69341",
    "sg:province":"NE",
    "sg:tags":[
        "property",
        "lessor"
    ],
    "wof:name":"Donald Haas",
    "wof:placetype":"venue"
},
  "geometry": {"coordinates":[-103.51908299999999,41.757094],"type":"Point"}
}