{
  "type": "Feature",
  "properties": {
    "iso:country":"US",
    "sg:address":"7003 S 36th St",
    "sg:city":"Bellevue",
    "sg:classifiers":[
        {
            "category":"Restaurant",
            "type":"Food & Drink"
        }
    ],
    "sg:phone":"+1 402 738 1682",
    "sg:postcode":"68147",
    "sg:province":"NE",
    "wof:name":"China Taste Restaurant",
    "wof:placetype":"venue"
},
  "geometry": {"coordinates":[-95.967326,41.189496],"type":"Point"}
}