{
  "type": "Feature",
  "properties": {
    "iso:country":"US",
    "sg:address":"510 W Old Military Rd",
    "sg:city":"Wood River",
    "sg:classifiers":[
        {
            "category":"Insurance",
            "subcategory":"Insurance Agent",
            "type":"Services"
        }
    ],
    "sg:phone":"+1 308 583 2276",
    "sg:postcode":"68883",
    "sg:province":"NE",
    "wof:name":"Babel Agency",
    "wof:placetype":"venue"
},
  "geometry": {"coordinates":[-98.608627,40.82584],"type":"Point"}
}