{
  "type": "Feature",
  "properties": {
    "addr:full":"2028 R Rd Burr NE 68324",
    "addr:housenumber":"2028",
    "addr:postcode":"68324",
    "addr:street":"R Rd",
    "iso:country":"US",
    "sg:address":"2028 R Rd",
    "sg:city":"Burr",
    "sg:classifiers":[
        {
            "category":"Real Estate",
            "subcategory":"Real Estate Operator",
            "type":"Services"
        }
    ],
    "sg:phone":"+1 402 848 2269",
    "sg:postcode":"68324",
    "sg:province":"NE",
    "sg:tags":[
        "property",
        "lessor"
    ],
    "wof:name":"Klein Lennis",
    "wof:placetype":"venue"
},
  "geometry": {"coordinates":[-96.272087,40.537299],"type":"Point"}
}