{
  "type": "Feature",
  "properties": {
    "iso:country":"US",
    "sg:address":"1183 Co Rd I",
    "sg:city":"Ithaca",
    "sg:phone":"+1 402 624 2099",
    "sg:postcode":"68033",
    "sg:province":"NE",
    "sg:tags":[
        "farm",
        "corn",
        "soybean"
    ],
    "wof:name":"Lonny Hanson",
    "wof:placetype":"venue"
},
  "geometry": {"coordinates":[-96.52203,41.176572],"type":"Point"}
}