{
  "type": "Feature",
  "properties": {
    "addr:full":"55933 840th Rd Norfolk NE 68701",
    "addr:housenumber":"55933",
    "addr:postcode":"68701",
    "addr:street":"840Th Rd",
    "iso:country":"US",
    "sg:address":"55933 840th Rd",
    "sg:city":"Norfolk",
    "sg:classifiers":[
        {
            "category":"Farming",
            "subcategory":"Livestock Farm",
            "type":"Manufacturing & Wholesale Goods"
        }
    ],
    "sg:phone":"+1 402 371 8860",
    "sg:postcode":"68701",
    "sg:province":"NE",
    "sg:tags":[
        "feeding"
    ],
    "wof:name":"Fore-Quarters FEEDLOT LLC",
    "wof:placetype":"venue"
},
  "geometry": {"coordinates":[-97.343813,42.004033],"type":"Point"}
}