{
  "type": "Feature",
  "properties": {
    "iso:country":"US",
    "sg:address":"205 E Roberts St",
    "sg:city":"Grand Island",
    "sg:classifiers":[
        {
            "category":"Freight",
            "type":"Transportation"
        }
    ],
    "sg:phone":"+1 308 381 2111",
    "sg:postcode":"68803",
    "sg:province":"NE",
    "sg:tags":[
        "warehouse",
        "storage"
    ],
    "sg:website":"www.millardref.com",
    "wof:name":"Millard Refrigerated Svc",
    "wof:placetype":"venue"
},
  "geometry": {"coordinates":[-98.35141,40.951111],"type":"Point"}
}