{
  "type": "Feature",
  "properties": {
    "iso:country":"US",
    "sg:address":"13936 Gold Cir Ste B",
    "sg:city":"Omaha",
    "sg:classifiers":[
        {
            "category":"Professional",
            "subcategory":"Employment Agencies",
            "type":"Services"
        }
    ],
    "sg:phone":"+1 402 884 7466",
    "sg:postcode":"68144",
    "sg:province":"NE",
    "sg:tags":[
        "opportunity"
    ],
    "wof:name":"Preferred Partners",
    "wof:placetype":"venue"
},
  "geometry": {"coordinates":[-96.13285500000001,41.234982],"type":"Point"}
}