{
  "type": "Feature",
  "properties": {
    "addr:full":"8112 S 84th St La Vista NE 68128",
    "addr:housenumber":"8112",
    "addr:postcode":"68128",
    "addr:street":"S 84Th St",
    "iso:country":"US",
    "sg:address":"8112 S 84th St",
    "sg:city":"La Vista",
    "sg:classifiers":[
        {
            "category":"Insurance",
            "subcategory":"Insurance Agent",
            "type":"Services"
        }
    ],
    "sg:phone":"+1 402 597 1246",
    "sg:postcode":"68128",
    "sg:province":"NE",
    "wof:name":"Shelter Insurance Co",
    "wof:placetype":"venue"
},
  "geometry": {"coordinates":[-96.043064,41.177564],"type":"Point"}
}