{
  "type": "Feature",
  "properties": {
    "iso:country":"US",
    "sg:address":"1804 Lothrop St",
    "sg:city":"Omaha",
    "sg:classifiers":[
        {
            "category":"Social Services",
            "subcategory":"Child Care",
            "type":"Services"
        }
    ],
    "sg:phone":"+1 402 991 2417",
    "sg:postcode":"68110",
    "sg:province":"NE",
    "sg:tags":[
        "day"
    ],
    "wof:name":"Bernice Ingram",
    "wof:placetype":"venue"
},
  "geometry": {"coordinates":[-95.940518,41.288828],"type":"Point"}
}