{
  "type": "Feature",
  "properties": {
    "addr:full":"2311 Krenzien Dr Norfolk NE 68701",
    "addr:housenumber":"2311",
    "addr:postcode":"68701",
    "addr:street":"Krenzien Dr",
    "iso:country":"US",
    "sg:address":"2311 Krenzien Dr",
    "sg:city":"Norfolk",
    "sg:classifiers":[
        {
            "category":"Retail",
            "subcategory":"Car Wash",
            "type":"Services"
        }
    ],
    "sg:phone":"+1 402 844 4801",
    "sg:postcode":"68701",
    "sg:province":"NE",
    "sg:tags":[
        "polishing",
        "washing"
    ],
    "wof:name":"Super Suds Touchless Auto Wash",
    "wof:placetype":"venue"
},
  "geometry": {"coordinates":[-97.438579,42.021981],"type":"Point"}
}