{
  "type": "Feature",
  "properties": {
    "iso:country":"US",
    "sg:address":"732 Meridian Ave",
    "sg:city":"Cozad",
    "sg:classifiers":[
        {
            "category":"Shopping",
            "subcategory":"Florist",
            "type":"Retail Goods"
        }
    ],
    "sg:phone":"+1 308 784 3181",
    "sg:postcode":"69130",
    "sg:province":"NE",
    "wof:name":"Uptown Floral & Gifts",
    "wof:placetype":"venue"
},
  "geometry": {"coordinates":[-99.985834,40.858638],"type":"Point"}
}