{
  "type": "Feature",
  "properties": {
    "addr:full":"6016 Grover St Omaha NE 68106",
    "addr:housenumber":"6016",
    "addr:postcode":"68106",
    "addr:street":"Grover St",
    "iso:country":"US",
    "sg:address":"6016 Grover St",
    "sg:city":"Omaha",
    "sg:classifiers":[
        {
            "category":"Food & Beverages",
            "subcategory":"Meat & Fish",
            "type":"Retail Goods"
        }
    ],
    "sg:phone":"+1 402 554 1965",
    "sg:postcode":"68106",
    "sg:province":"NE",
    "sg:tags":[
        "shop"
    ],
    "wof:name":"Omaha Meat Processors",
    "wof:placetype":"venue"
},
  "geometry": {"coordinates":[-96.0047,41.2271],"type":"Point"}
}