{
  "type": "Feature",
  "properties": {
    "iso:country":"US",
    "sg:address":"2207 Georgia Ave",
    "sg:city":"Bellevue",
    "sg:classifiers":[
        {
            "category":"Cinema",
            "subcategory":"Movie Rental",
            "type":"Entertainment"
        }
    ],
    "sg:phone":"+1 402 731 9272",
    "sg:postcode":"68005",
    "sg:province":"NE",
    "sg:tags":[
        "leasing",
        "video",
        "disc",
        "tape"
    ],
    "wof:name":"Blockbuster Video",
    "wof:placetype":"venue"
},
  "geometry": {"coordinates":[-95.924663,41.167854],"type":"Point"}
}