{
  "type": "Feature",
  "properties": {
    "iso:country":"US",
    "sg:address":"2104 E 16 Rd",
    "sg:city":"Hampton",
    "sg:classifiers":[
        {
            "category":"Farming",
            "subcategory":"Farm",
            "type":"Manufacturing & Wholesale Goods"
        }
    ],
    "sg:phone":"+1 402 725 3894",
    "sg:postcode":"68843",
    "sg:province":"NE",
    "sg:tags":[
        "crop",
        "general"
    ],
    "wof:name":"Douglas L McHenry Farms",
    "wof:placetype":"venue"
},
  "geometry": {"coordinates":[-97.900035,40.915857],"type":"Point"}
}