{
  "type": "Feature",
  "properties": {
    "iso:country":"US",
    "sg:address":"5140 S 56th St",
    "sg:city":"Lincoln",
    "sg:classifiers":[
        {
            "category":"Health Services",
            "subcategory":"Doctor",
            "type":"Services"
        }
    ],
    "sg:phone":"+1 402 423 1100",
    "sg:postcode":"68516",
    "sg:province":"NE",
    "sg:tags":[
        "dentist"
    ],
    "sg:website":"www.pineridgedental.com",
    "wof:name":"Pine Ridge Dental",
    "wof:placetype":"venue"
},
  "geometry": {"coordinates":[-96.644267,40.762934],"type":"Point"}
}