{
  "type": "Feature",
  "properties": {
    "iso:country":"US",
    "sg:address":"2235 Parkview Dr",
    "sg:city":"Fremont",
    "sg:classifiers":[
        {
            "category":"Personal",
            "subcategory":"Barber",
            "type":"Services"
        }
    ],
    "sg:phone":"+1 402 727 1468",
    "sg:postcode":"68025",
    "sg:province":"NE",
    "sg:tags":[
        "shop"
    ],
    "wof:name":"Allen Emken",
    "wof:placetype":"venue"
},
  "geometry": {"coordinates":[-96.466432,41.438815],"type":"Point"}
}