{
  "type": "Feature",
  "properties": {
    "addr:full":"76726 Rd 416 Gothenburg NE 69138",
    "addr:postcode":"76726;69138",
    "addr:street":"Rd 416",
    "iso:country":"US",
    "sg:address":"76726 Rd 416",
    "sg:city":"Gothenburg",
    "sg:classifiers":[
        {
            "category":"Farming",
            "subcategory":"Fish & Marine Products",
            "type":"Manufacturing & Wholesale Goods"
        }
    ],
    "sg:phone":"+1 308 537 7276",
    "sg:postcode":"69138",
    "sg:province":"NE",
    "wof:name":"Bos Trapping & Predator",
    "wof:placetype":"venue"
},
  "geometry": {"coordinates":[-100.071716,40.949153],"type":"Point"}
}