{
  "type": "Feature",
  "properties": {
    "addr:full":"6003 Meridian Dr Lincoln NE 68504",
    "addr:housenumber":"6003",
    "addr:postcode":"68504",
    "addr:street":"Meridian Dr",
    "iso:country":"US",
    "sg:address":"6003 Meridian Dr",
    "sg:city":"Lincoln",
    "sg:classifiers":[
        {
            "category":"Arts & Performance",
            "subcategory":"Theater",
            "type":"Entertainment"
        }
    ],
    "sg:phone":"+1 402 435 7168",
    "sg:postcode":"68504",
    "sg:province":"NE",
    "sg:tags":[
        "live",
        "music"
    ],
    "wof:name":"Bandstand Music",
    "wof:placetype":"venue"
},
  "geometry": {"coordinates":[-96.67339800000001,40.874244],"type":"Point"}
}