{
  "type": "Feature",
  "properties": {
    "iso:country":"US",
    "sg:address":"935 1st St",
    "sg:city":"Syracuse",
    "sg:classifiers":[
        {
            "category":"Health Services",
            "subcategory":"Doctor",
            "type":"Services"
        }
    ],
    "sg:phone":"+1 402 269 3160",
    "sg:postcode":"68446",
    "sg:province":"NE",
    "sg:tags":[
        "dentist"
    ],
    "wof:name":"Syracuse Dental Clinic",
    "wof:placetype":"venue"
},
  "geometry": {"coordinates":[-96.177729,40.653465],"type":"Point"}
}