{
  "type": "Feature",
  "properties": {
    "addr:full":"6847 N 16th St Omaha NE 68112",
    "addr:housenumber":"6847",
    "addr:postcode":"68112",
    "addr:street":"N 16Th St",
    "iso:country":"US",
    "sg:address":"6847 N 16th St",
    "sg:city":"Omaha",
    "sg:classifiers":[
        {
            "category":"Manufacturing",
            "subcategory":"Tools & Machinery",
            "type":"Manufacturing & Wholesale Goods"
        }
    ],
    "sg:phone":"+1 402 453 9100",
    "sg:postcode":"68112",
    "sg:province":"NE",
    "sg:tags":[
        "farm",
        "mfg",
        "general",
        "war",
        "supply"
    ],
    "wof:name":"Farnam Horse Care Products",
    "wof:placetype":"venue"
},
  "geometry": {"coordinates":[-95.93720399999999,41.317922],"type":"Point"}
}