{
  "type": "Feature",
  "properties": {
    "iso:country":"US",
    "sg:address":"3300 Calvert St",
    "sg:city":"Lincoln",
    "sg:classifiers":[
        {
            "category":"Shopping",
            "type":"Retail Goods"
        }
    ],
    "sg:phone":"+1 402 730 3411",
    "sg:postcode":"68506",
    "sg:province":"NE",
    "sg:tags":[
        "pet",
        "food",
        "supply"
    ],
    "wof:name":"Jeneration Pets",
    "wof:placetype":"venue"
},
  "geometry": {"coordinates":[-96.67180399999999,40.777119],"type":"Point"}
}