{
  "type": "Feature",
  "properties": {
    "iso:country":"US",
    "sg:address":"5210 W Bedford St",
    "sg:city":"Lincoln",
    "sg:classifiers":[
        {
            "category":"Building & Trades",
            "subcategory":"Construction",
            "type":"Services"
        }
    ],
    "sg:phone":"+1 402 477 5275",
    "sg:postcode":"68521",
    "sg:province":"NE",
    "sg:tags":[
        "house"
    ],
    "wof:name":"Pioneer Builders Inc",
    "wof:placetype":"venue"
},
  "geometry": {"coordinates":[-96.726225,40.863168],"type":"Point"}
}