{
  "type": "Feature",
  "properties": {
    "iso:country":"US",
    "sg:address":"708 Benjamin Ave",
    "sg:city":"Norfolk",
    "sg:classifiers":[
        {
            "category":"Shopping",
            "subcategory":"Used Merchandise",
            "type":"Retail Goods"
        }
    ],
    "sg:phone":"+1 402 371 1615",
    "sg:postcode":"68701",
    "sg:province":"NE",
    "sg:tags":[
        "book",
        "rare",
        "dealer"
    ],
    "wof:name":"Book Exchange",
    "wof:placetype":"venue"
},
  "geometry": {"coordinates":[-97.415121,42.047273],"type":"Point"}
}