{
  "type": "Feature",
  "properties": {
    "addr:full":"2106 Sandstone Rd Lincoln NE 68512",
    "addr:housenumber":"2106",
    "addr:postcode":"68512",
    "addr:street":"Sandstone Rd",
    "iso:country":"US",
    "sg:address":"2106 Sandstone Rd",
    "sg:city":"Lincoln",
    "sg:classifiers":[
        {
            "category":"Building & Trades",
            "subcategory":"Construction",
            "type":"Services"
        }
    ],
    "sg:phone":"+1 402 435 4585",
    "sg:postcode":"68512",
    "sg:province":"NE",
    "sg:tags":[
        "commercial",
        "contractor"
    ],
    "wof:name":"First General Services Neb",
    "wof:placetype":"venue"
},
  "geometry": {"coordinates":[-96.688174,40.764817],"type":"Point"}
}