{
  "type": "Feature",
  "properties": {
    "addr:full":"942 N 70th St Lincoln NE 68505",
    "addr:housenumber":"942",
    "addr:postcode":"68505",
    "addr:street":"N 70Th St",
    "iso:country":"US",
    "sg:address":"942 N 70th St",
    "sg:city":"Lincoln",
    "sg:classifiers":[
        {
            "category":"Shopping",
            "subcategory":"Hobbies, Toys, & Games",
            "type":"Retail Goods"
        }
    ],
    "sg:phone":"+1 402 489 4263",
    "sg:postcode":"68505",
    "sg:province":"NE",
    "sg:tags":[
        "supply"
    ],
    "wof:name":"Dog Tags Gaming Ctr",
    "wof:placetype":"venue"
},
  "geometry": {"coordinates":[-96.624916,40.822755],"type":"Point"}
}