{
  "type": "Feature",
  "properties": {
    "iso:country":"US",
    "sg:address":"106 13th Corso",
    "sg:city":"Nebraska City",
    "sg:classifiers":[
        {
            "category":"Professional",
            "subcategory":"Business Services",
            "type":"Services"
        }
    ],
    "sg:phone":"+1 402 873 3676",
    "sg:postcode":"68410",
    "sg:province":"NE",
    "wof:name":"Bruns Alton W",
    "wof:placetype":"venue"
},
  "geometry": {"coordinates":[-95.845364,40.664818],"type":"Point"}
}