{
  "type": "Feature",
  "properties": {
    "addr:full":"80070 Grove St Scottsbluff NE 69361",
    "addr:housenumber":"80070",
    "addr:postcode":"69361",
    "addr:street":"Grove St",
    "iso:country":"US",
    "sg:address":"80070 Grove St",
    "sg:city":"Scottsbluff",
    "sg:classifiers":[
        {
            "category":"Social Services",
            "subcategory":"Child Care",
            "type":"Services"
        }
    ],
    "sg:phone":"+1 308 632 2795",
    "sg:postcode":"69361",
    "sg:province":"NE",
    "sg:tags":[
        "day"
    ],
    "wof:name":"Kid Zone Day Care Inc",
    "wof:placetype":"venue"
},
  "geometry": {"coordinates":[-103.63354200000001,41.89091],"type":"Point"}
}