{
  "type": "Feature",
  "properties": {
    "addr:full":"422 N Webster St Red Cloud NE 68970",
    "addr:housenumber":"422",
    "addr:postcode":"68970",
    "addr:street":"N Webster St",
    "iso:country":"US",
    "sg:address":"422 N Webster St",
    "sg:city":"Red Cloud",
    "sg:classifiers":[
        {
            "category":"Shopping",
            "subcategory":"Crafts & Fabrics",
            "type":"Retail Goods"
        }
    ],
    "sg:phone":"+1 402 746 3592",
    "sg:postcode":"68970",
    "sg:province":"NE",
    "sg:tags":[
        "sewing"
    ],
    "wof:name":"Sewing Box",
    "wof:placetype":"venue"
},
  "geometry": {"coordinates":[-98.519228,40.089619],"type":"Point"}
}