{
  "type": "Feature",
  "properties": {
    "iso:country":"US",
    "sg:address":"4416 S 108th St",
    "sg:city":"Omaha",
    "sg:classifiers":[
        {
            "category":"Wholesale",
            "subcategory":"Groceries",
            "type":"Manufacturing & Wholesale Goods"
        }
    ],
    "sg:phone":"+1 402 339 1133",
    "sg:postcode":"68137",
    "sg:province":"NE",
    "sg:tags":[
        "food",
        "item",
        "specialty"
    ],
    "wof:name":"Dandeli Specialty Foods Inc",
    "wof:placetype":"venue"
},
  "geometry": {"coordinates":[-96.081565,41.214554],"type":"Point"}
}