{
  "type": "Feature",
  "properties": {
    "iso:country":"US",
    "sg:address":"402 E 32nd St",
    "sg:city":"Kearney",
    "sg:classifiers":[
        {
            "category":"Real Estate",
            "subcategory":"Real Estate Operator",
            "type":"Services"
        }
    ],
    "sg:phone":"+1 308 236 5187",
    "sg:postcode":"68847",
    "sg:province":"NE",
    "sg:tags":[
        "property",
        "lessor"
    ],
    "wof:name":"Roger Newcomb",
    "wof:placetype":"venue"
},
  "geometry": {"coordinates":[-99.07631499999999,40.707518],"type":"Point"}
}