{
  "type": "Feature",
  "properties": {
    "iso:country":"US",
    "sg:address":"6316 N 30th St",
    "sg:city":"Omaha",
    "sg:classifiers":[
        {
            "category":"Education",
            "subcategory":"School",
            "type":"Public Place"
        }
    ],
    "sg:phone":"+1 402 455 4030",
    "sg:postcode":"68111",
    "sg:province":"NE",
    "sg:tags":[
        "elementary"
    ],
    "wof:name":"Blessed Sacrament School",
    "wof:placetype":"venue"
},
  "geometry": {"coordinates":[-95.956611,41.31743],"type":"Point"}
}