{
  "type": "Feature",
  "properties": {
    "iso:country":"US",
    "sg:address":"211 W 3rd St",
    "sg:city":"Yankton",
    "sg:classifiers":[
        {
            "category":"Shopping",
            "type":"Retail Goods"
        }
    ],
    "sg:phone":"+1 605 665 8463",
    "sg:postcode":"57078",
    "sg:province":"NE",
    "sg:tags":[
        "book",
        "merchandise"
    ],
    "wof:name":"Vineyard",
    "wof:placetype":"venue"
},
  "geometry": {"coordinates":[-97.395264,42.86976],"type":"Point"}
}