{
  "type": "Feature",
  "properties": {
    "iso:country":"US",
    "sg:address":"4156 S 52nd St",
    "sg:city":"Omaha",
    "sg:classifiers":[
        {
            "category":"Shopping",
            "type":"Retail Goods"
        }
    ],
    "sg:phone":"+1 402 734 6741",
    "sg:postcode":"68117",
    "sg:province":"NE",
    "sg:tags":[
        "equipment",
        "care",
        "health",
        "home"
    ],
    "wof:name":"Children's Home Healthcare",
    "wof:placetype":"venue"
},
  "geometry": {"coordinates":[-95.995293,41.218013],"type":"Point"}
}