{
  "type": "Feature",
  "properties": {
    "addr:full":"10000 California St Omaha NE 68114",
    "addr:housenumber":"10000",
    "addr:postcode":"68114",
    "addr:street":"California St",
    "iso:country":"US",
    "sg:address":"10000 California St",
    "sg:city":"Omaha",
    "sg:classifiers":[
        {
            "category":"Shopping",
            "subcategory":"Shoes",
            "type":"Retail Goods"
        }
    ],
    "sg:phone":"+1 402 392 2257",
    "sg:postcode":"68114",
    "sg:province":"NE",
    "wof:name":"Easy Spirit",
    "wof:placetype":"venue"
},
  "geometry": {"coordinates":[-96.069001,41.264008],"type":"Point"}
}