{
  "type": "Feature",
  "properties": {
    "addr:full":"5490 Rock Rd Alliance NE 69301",
    "addr:housenumber":"5490",
    "addr:postcode":"69301",
    "addr:street":"Rock Rd",
    "iso:country":"US",
    "sg:address":"5490 Rock Rd",
    "sg:city":"Alliance",
    "sg:phone":"+1 308 762 4687",
    "sg:postcode":"69301",
    "sg:province":"NE",
    "sg:tags":[
        "wheat",
        "farm",
        "corn",
        "cash",
        "crop",
        "field",
        "grain"
    ],
    "wof:name":"Fritzler Farm Inc",
    "wof:placetype":"venue"
},
  "geometry": {"coordinates":[-102.769693,42.07664],"type":"Point"}
}