{
  "type": "Feature",
  "properties": {
    "addr:full":"3874 Hamilton St Omaha NE 68131",
    "addr:housenumber":"3874",
    "addr:postcode":"68131",
    "addr:street":"Hamilton St",
    "iso:country":"US",
    "sg:address":"3874 Hamilton St",
    "sg:city":"Omaha",
    "sg:classifiers":[
        {
            "category":"Food & Beverages",
            "subcategory":"Groceries & Convenience Stores",
            "type":"Retail Goods"
        }
    ],
    "sg:phone":"+1 402 551 5094",
    "sg:postcode":"68131",
    "sg:province":"NE",
    "wof:name":"Kum & Go Convenience Stores",
    "wof:placetype":"venue"
},
  "geometry": {"coordinates":[-95.972078,41.272207],"type":"Point"}
}