{
  "type": "Feature",
  "properties": {
    "addr:full":"104 E 6th St Alliance NE 69301",
    "addr:housenumber":"104",
    "addr:postcode":"69301",
    "addr:street":"E 6Th St",
    "iso:country":"US",
    "sg:address":"104 E 6th St",
    "sg:city":"Alliance",
    "sg:classifiers":[
        {
            "category":"Government",
            "subcategory":"Office",
            "type":"Public Place"
        }
    ],
    "sg:phone":"+1 308 762 6644",
    "sg:postcode":"69301",
    "sg:province":"NE",
    "wof:name":"Box Butte County Public Dfndr",
    "wof:placetype":"venue"
},
  "geometry": {"coordinates":[-102.870772,42.10024],"type":"Point"}
}