{
  "type": "Feature",
  "properties": {
    "addr:full":"107 N Sherrill St Atkinson NE 68713",
    "addr:housenumber":"107",
    "addr:postcode":"68713",
    "addr:street":"N Sherrill St",
    "iso:country":"US",
    "sg:address":"107 N Sherrill St",
    "sg:city":"Atkinson",
    "sg:classifiers":[
        {
            "category":"Wholesale",
            "subcategory":"Machinery & Supplies",
            "type":"Manufacturing & Wholesale Goods"
        }
    ],
    "sg:phone":"+1 402 925 5757",
    "sg:postcode":"68713",
    "sg:province":"NE",
    "sg:tags":[
        "burial",
        "vault"
    ],
    "wof:name":"North Nebraska Wilbert Vault",
    "wof:placetype":"venue"
},
  "geometry": {"coordinates":[-98.97941,42.532109],"type":"Point"}
}