{
  "type": "Feature",
  "properties": {
    "iso:country":"US",
    "sg:address":"4110 Central Ave",
    "sg:city":"Kearney",
    "sg:classifiers":[
        {
            "category":"Real Estate",
            "subcategory":"Real Estate Operator",
            "type":"Services"
        }
    ],
    "sg:phone":"+1 308 237 5550",
    "sg:postcode":"68847",
    "sg:province":"NE",
    "sg:tags":[
        "apartment",
        "rental"
    ],
    "wof:name":"Elizabeth House LLC",
    "wof:placetype":"venue"
},
  "geometry": {"coordinates":[-99.08128600000001,40.715866],"type":"Point"}
}