{
  "type": "Feature",
  "properties": {
    "iso:country":"US",
    "sg:address":"222 W 14th St",
    "sg:city":"Hastings",
    "sg:classifiers":[
        {
            "category":"Personal",
            "subcategory":"Beauty Salon",
            "type":"Services"
        }
    ],
    "sg:phone":"+1 402 461 6849",
    "sg:postcode":"68901",
    "sg:province":"NE",
    "wof:name":"2 Pair Of Shears",
    "wof:placetype":"venue"
},
  "geometry": {"coordinates":[-98.38282599999999,40.600786],"type":"Point"}
}