{
  "type": "Feature",
  "properties": {
    "addr:full":"770 N Cotner Blvd Lincoln NE 68505",
    "addr:housenumber":"770",
    "addr:postcode":"68505",
    "addr:street":"N Cotner Blvd",
    "iso:country":"US",
    "sg:address":"770 N Cotner Blvd",
    "sg:city":"Lincoln",
    "sg:classifiers":[
        {
            "category":"Insurance",
            "subcategory":"Life Insurance",
            "type":"Services"
        }
    ],
    "sg:phone":"+1 402 434 5920",
    "sg:postcode":"68505",
    "sg:province":"NE",
    "sg:tags":[
        "carrier"
    ],
    "wof:name":"Principal Life Insurance Co",
    "wof:placetype":"venue"
},
  "geometry": {"coordinates":[-96.63553899999999,40.820482],"type":"Point"}
}