{
  "type": "Feature",
  "properties": {
    "iso:country":"US",
    "sg:address":"220 S 17th St",
    "sg:city":"Lincoln",
    "sg:classifiers":[
        {
            "category":"Health Services",
            "subcategory":"Doctor",
            "type":"Services"
        }
    ],
    "sg:phone":"+1 402 475 7000",
    "sg:postcode":"68508",
    "sg:province":"NE",
    "sg:tags":[
        "physician",
        "surgeon",
        "medical"
    ],
    "wof:name":"Lincoln Centre Clinic PC",
    "wof:placetype":"venue"
},
  "geometry": {"coordinates":[-96.696682,40.811598],"type":"Point"}
}