{
  "type": "Feature",
  "properties": {
    "iso:country":"US",
    "sg:address":"4571 N Parkway Rd",
    "sg:city":"North Platte",
    "sg:classifiers":[
        {
            "category":"Home & Garden",
            "subcategory":"Building Materials",
            "type":"Retail Goods"
        }
    ],
    "sg:phone":"+1 308 535 5972",
    "sg:postcode":"69143",
    "sg:province":"NE",
    "sg:tags":[
        "center"
    ],
    "sg:website":"www.menards.com",
    "wof:name":"Menards",
    "wof:placetype":"venue"
},
  "geometry": {"coordinates":[-100.983289,41.175902],"type":"Point"}
}