{
  "type": "Feature",
  "properties": {
    "addr:full":"818 S 37th Ave Omaha NE 68105",
    "addr:housenumber":"818",
    "addr:postcode":"68105",
    "addr:street":"S 37Th Ave",
    "iso:country":"US",
    "sg:address":"818 S 37th Ave",
    "sg:city":"Omaha",
    "sg:classifiers":[
        {
            "category":"Professional",
            "subcategory":"Business Services",
            "type":"Services"
        }
    ],
    "sg:phone":"+1 402 342 4338",
    "sg:postcode":"68105",
    "sg:province":"NE",
    "sg:tags":[
        "information",
        "referral"
    ],
    "wof:name":"Id Info Data",
    "wof:placetype":"venue"
},
  "geometry": {"coordinates":[-95.968389,41.251404],"type":"Point"}
}