{
  "type": "Feature",
  "properties": {
    "iso:country":"US",
    "sg:address":"4755 W Mill Rd",
    "sg:city":"Raymond",
    "sg:classifiers":[
        {
            "category":"Autos & Motor Vehicles",
            "subcategory":"Automobile Sales",
            "type":"Retail Goods"
        }
    ],
    "sg:phone":"+1 402 890 2052",
    "sg:postcode":"68428",
    "sg:province":"NE",
    "sg:tags":[
        "aircraft"
    ],
    "wof:name":"Ultralight Aviation Ted Miller",
    "wof:placetype":"venue"
},
  "geometry": {"coordinates":[-96.78551400000001,40.944496],"type":"Point"}
}