{
  "type": "Feature",
  "properties": {
    "iso:country":"US",
    "sg:address":"501 N 1st St",
    "sg:city":"Norfolk",
    "sg:classifiers":[
        {
            "category":"Retail",
            "subcategory":"Auto Repair",
            "type":"Services"
        }
    ],
    "sg:phone":"+1 402 844 4050",
    "sg:postcode":"68701",
    "sg:province":"NE",
    "sg:tags":[
        "general"
    ],
    "wof:name":"Auto Doctor",
    "wof:placetype":"venue"
},
  "geometry": {"coordinates":[-97.40701300000001,42.038263],"type":"Point"}
}