{
  "type": "Feature",
  "properties": {
    "addr:full":"260 Regency Parkway Dr Omaha NE 68114",
    "addr:housenumber":"260",
    "addr:postcode":"68114",
    "addr:street":"Regency Parkway Dr",
    "iso:country":"US",
    "sg:address":"260 Regency Parkway Dr",
    "sg:city":"Omaha",
    "sg:classifiers":[
        {
            "category":"Health Services",
            "subcategory":"Doctor",
            "type":"Services"
        }
    ],
    "sg:phone":"+1 402 399 0900",
    "sg:postcode":"68114",
    "sg:province":"NE",
    "wof:name":"Spanel A Kenneth D D S",
    "wof:placetype":"venue"
},
  "geometry": {"coordinates":[-96.07402399999999,41.255676],"type":"Point"}
}