{
  "type": "Feature",
  "properties": {
    "iso:country":"US",
    "sg:address":"1537 Papillion Dr",
    "sg:city":"Papillion",
    "sg:classifiers":[
        {
            "category":"Building & Trades",
            "subcategory":"Landscaping Services",
            "type":"Services"
        }
    ],
    "sg:phone":"+1 402 339 8845",
    "sg:postcode":"68133",
    "sg:province":"NE",
    "sg:tags":[
        "lawn",
        "maintenance",
        "grounds"
    ],
    "wof:name":"Three Seasons Lawn Care",
    "wof:placetype":"venue"
},
  "geometry": {"coordinates":[-96.01902,41.137562],"type":"Point"}
}