{
  "type": "Feature",
  "properties": {
    "iso:country":"US",
    "sg:address":"1604 16th St",
    "sg:city":"Central City",
    "sg:classifiers":[
        {
            "category":"Professional",
            "subcategory":"Computer Services",
            "type":"Services"
        }
    ],
    "sg:phone":"+1 308 946 3458",
    "sg:postcode":"68826",
    "sg:province":"NE",
    "sg:tags":[
        "internet"
    ],
    "sg:website":"www.cconline.net",
    "wof:name":"C C Online",
    "wof:placetype":"venue"
},
  "geometry": {"coordinates":[-98.00038600000001,41.116039],"type":"Point"}
}