{
  "type": "Feature",
  "properties": {
    "iso:country":"US",
    "sg:address":"817 3rd St",
    "sg:city":"Columbus",
    "sg:classifiers":[
        {
            "category":"Social Services",
            "subcategory":"Child Care",
            "type":"Services"
        }
    ],
    "sg:phone":"+1 402 563 3540",
    "sg:postcode":"68601",
    "sg:province":"NE",
    "sg:tags":[
        "day"
    ],
    "wof:name":"Laurel Parsley",
    "wof:placetype":"venue"
},
  "geometry": {"coordinates":[-97.339305,41.418094],"type":"Point"}
}