{
  "type": "Feature",
  "properties": {
    "addr:full":"9303 Pioneers Blvd Lincoln NE 68520",
    "addr:housenumber":"9303",
    "addr:postcode":"68520",
    "addr:street":"Pioneers Blvd",
    "iso:country":"US",
    "sg:address":"9303 Pioneers Blvd",
    "sg:city":"Lincoln",
    "sg:classifiers":[
        {
            "category":"Building & Trades",
            "subcategory":"Landscaping Services",
            "type":"Services"
        }
    ],
    "sg:phone":"+1 402 420 5172",
    "sg:postcode":"68520",
    "sg:province":"NE",
    "sg:tags":[
        "tree"
    ],
    "wof:name":"Acme Tree Svc Nebelsick's",
    "wof:placetype":"venue"
},
  "geometry": {"coordinates":[-96.59366,40.769634],"type":"Point"}
}