{
  "type": "Feature",
  "properties": {
    "iso:country":"US",
    "sg:address":"741 N Cedar St",
    "sg:city":"Red Cloud",
    "sg:phone":"+1 402 746 2947",
    "sg:postcode":"68970",
    "sg:province":"NE",
    "sg:tags":[
        "farm",
        "corn",
        "soybean"
    ],
    "wof:name":"Rod Simonsen",
    "wof:placetype":"venue"
},
  "geometry": {"coordinates":[-98.520753,40.092551],"type":"Point"}
}