{
  "type": "Feature",
  "properties": {
    "iso:country":"US",
    "sg:address":"2416 13th St",
    "sg:city":"Columbus",
    "sg:classifiers":[
        {
            "category":"Shopping",
            "subcategory":"Bicycles & Sporting Goods",
            "type":"Retail Goods"
        }
    ],
    "sg:phone":"+1 402 564 8284",
    "sg:postcode":"68601",
    "sg:province":"NE",
    "wof:name":"Nebraska Cycling & Fitness",
    "wof:placetype":"venue"
},
  "geometry": {"coordinates":[-97.358013,41.429312],"type":"Point"}
}