{
  "type": "Feature",
  "properties": {
    "iso:country":"US",
    "sg:address":"2840 Sissel Rd",
    "sg:city":"Lincoln",
    "sg:classifiers":[
        {
            "category":"Real Estate",
            "subcategory":"Real Estate Operator",
            "type":"Services"
        }
    ],
    "sg:phone":"+1 402 328 8795",
    "sg:postcode":"68516",
    "sg:province":"NE",
    "sg:tags":[
        "building",
        "nonresidential"
    ],
    "wof:name":"Eng Properties LLC",
    "wof:placetype":"venue"
},
  "geometry": {"coordinates":[-96.67878399999999,40.734576],"type":"Point"}
}