{
  "type": "Feature",
  "properties": {
    "addr:full":"792 5th Rd Grand Island NE 68801",
    "addr:housenumber":"792",
    "addr:postcode":"68801",
    "addr:street":"5Th Rd",
    "iso:country":"US",
    "sg:address":"792 5th Rd",
    "sg:city":"Grand Island",
    "sg:classifiers":[
        {
            "category":"Retail",
            "subcategory":"Auto Repair",
            "type":"Services"
        }
    ],
    "sg:phone":"+1 308 986 2312",
    "sg:postcode":"68801",
    "sg:province":"NE",
    "sg:tags":[
        "automotive"
    ],
    "wof:name":"Moocks Towing",
    "wof:placetype":"venue"
},
  "geometry": {"coordinates":[-98.206344,40.966004],"type":"Point"}
}