{
  "type": "Feature",
  "properties": {
    "iso:country":"US",
    "sg:address":"1251 E Rd",
    "sg:city":"West Point",
    "sg:classifiers":[
        {
            "category":"Real Estate",
            "subcategory":"Real Estate Agent",
            "type":"Services"
        }
    ],
    "sg:phone":"+1 402 372 2563",
    "sg:postcode":"68788",
    "sg:province":"NE",
    "sg:tags":[
        "farm",
        "soybean"
    ],
    "wof:name":"Leo Trainer",
    "wof:placetype":"venue"
},
  "geometry": {"coordinates":[-96.797032,41.800692],"type":"Point"}
}