{
  "type": "Feature",
  "properties": {
    "addr:full":"4030 S Lincoln Ave York NE 68467",
    "addr:housenumber":"4030",
    "addr:postcode":"68467",
    "addr:street":"S Lincoln Ave",
    "iso:country":"US",
    "sg:address":"4030 S Lincoln Ave",
    "sg:city":"York",
    "sg:classifiers":[
        {
            "category":"Restaurant",
            "type":"Food & Drink"
        }
    ],
    "sg:menulink":"http://www.allmenus.com/ne/york/158964-arbys/menu/",
    "sg:phone":"+1 402 362 2325",
    "sg:postcode":"68467",
    "sg:province":"NE",
    "sg:tags":[
        "burger",
        "american"
    ],
    "wof:name":"Arby's",
    "wof:placetype":"venue"
},
  "geometry": {"coordinates":[-97.597992,40.827393],"type":"Point"}
}