{
  "type": "Feature",
  "properties": {
    "addr:full":"15011 Willow Creek Dr Omaha NE 68138",
    "addr:housenumber":"15011",
    "addr:postcode":"68138",
    "addr:street":"Willow Creek Dr",
    "iso:country":"US",
    "sg:address":"15011 Willow Creek Dr",
    "sg:city":"Omaha",
    "sg:classifiers":[
        {
            "category":"Real Estate",
            "subcategory":"Real Estate Operator",
            "type":"Services"
        }
    ],
    "sg:phone":"+1 402 894 0692",
    "sg:postcode":"68138",
    "sg:province":"NE",
    "sg:tags":[
        "building",
        "nonresidential"
    ],
    "wof:name":"Alben Properties Inc",
    "wof:placetype":"venue"
},
  "geometry": {"coordinates":[-96.14814200000001,41.187429],"type":"Point"}
}