{
  "type": "Feature",
  "properties": {
    "addr:full":"305 Main St Wayne NE 68787",
    "addr:housenumber":"305",
    "addr:postcode":"68787",
    "addr:street":"Main St",
    "iso:country":"US",
    "sg:address":"305 Main St",
    "sg:city":"Wayne",
    "sg:classifiers":[
        {
            "category":"Insurance",
            "subcategory":"Insurance Agent",
            "type":"Services"
        }
    ],
    "sg:phone":"+1 402 375 4747",
    "sg:postcode":"68787",
    "sg:province":"NE",
    "wof:name":"Cliff Peters Insurance",
    "wof:placetype":"venue"
},
  "geometry": {"coordinates":[-97.017792,42.231913],"type":"Point"}
}