{
  "type": "Feature",
  "properties": {
    "iso:country":"US",
    "sg:address":"2116 W Faidley Ave",
    "sg:city":"Grand Island",
    "sg:classifiers":[
        {
            "category":"Health Services",
            "subcategory":"Doctor",
            "type":"Services"
        }
    ],
    "sg:phone":"+1 308 398 5312",
    "sg:postcode":"68803",
    "sg:province":"NE",
    "sg:tags":[
        "medical"
    ],
    "wof:name":"Third City Community Clinic",
    "wof:placetype":"venue"
},
  "geometry": {"coordinates":[-98.36335800000001,40.924248],"type":"Point"}
}