{
  "type": "Feature",
  "properties": {
    "iso:country":"US",
    "sg:address":"905 E 7th St",
    "sg:city":"Mc Cook",
    "sg:classifiers":[
        {
            "category":"Organizations",
            "subcategory":"Community Association",
            "type":"Services"
        }
    ],
    "sg:phone":"+1 308 345 6467",
    "sg:postcode":"69001",
    "sg:province":"NE",
    "sg:tags":[
        "fraternal"
    ],
    "wof:name":"Elks Lodge 1434",
    "wof:placetype":"venue"
},
  "geometry": {"coordinates":[-100.615971,40.206937],"type":"Point"}
}