{
  "type": "Feature",
  "properties": {
    "iso:country":"US",
    "sg:address":"719 Northwood Ct",
    "sg:city":"Scottsbluff",
    "sg:classifiers":[
        {
            "category":"Food & Beverages",
            "subcategory":"Candy",
            "type":"Retail Goods"
        }
    ],
    "sg:phone":"+1 308 635 7222",
    "sg:postcode":"69361",
    "sg:province":"NE",
    "sg:tags":[
        "confectionery"
    ],
    "wof:name":"Candy Bouquet",
    "wof:placetype":"venue"
},
  "geometry": {"coordinates":[-103.67296399999999,41.88053],"type":"Point"}
}