{
  "type": "Feature",
  "properties": {
    "iso:country":"US",
    "sg:address":"13819 T Plz",
    "sg:city":"Omaha",
    "sg:classifiers":[
        {
            "category":"Health Services",
            "subcategory":"Dentist",
            "type":"Services"
        }
    ],
    "sg:phone":"+1 402 858 1285",
    "sg:postcode":"68137",
    "sg:province":"NE",
    "sg:tags":[
        "dental",
        "dentists-endodontists",
        "clinic"
    ],
    "sg:website":"http://www.mcmanigaldental.com",
    "wof:name":"McManigal Family Dentistry",
    "wof:placetype":"venue"
},
  "geometry": {"coordinates":[-96.129523,41.202256],"type":"Point"}
}