{
  "type": "Feature",
  "properties": {
    "addr:full":"721 W Oklahoma Ave Grand Island NE 68801",
    "addr:housenumber":"721",
    "addr:postcode":"68801",
    "addr:street":"W Oklahoma Ave",
    "iso:country":"US",
    "sg:address":"721 W Oklahoma Ave",
    "sg:city":"Grand Island",
    "sg:classifiers":[
        {
            "category":"Wholesale",
            "subcategory":"Hardware",
            "type":"Manufacturing & Wholesale Goods"
        }
    ],
    "sg:phone":"+1 308 384 2115",
    "sg:postcode":"68801",
    "sg:province":"NE",
    "sg:tags":[
        "plumbing",
        "fixture",
        "supply"
    ],
    "wof:name":"Platte Valley Winnelson",
    "wof:placetype":"venue"
},
  "geometry": {"coordinates":[-98.341086,40.915148],"type":"Point"}
}