{
  "type": "Feature",
  "properties": {
    "iso:country":"US",
    "sg:address":"13043 Arbor St",
    "sg:city":"Omaha",
    "sg:classifiers":[
        {
            "category":"Restaurant",
            "type":"Food & Drink"
        }
    ],
    "sg:menulink":"http://www.allmenus.com/ne/omaha/9934-julios/menu/",
    "sg:phone":"+1 402 330 2110",
    "sg:postcode":"68144",
    "sg:province":"NE",
    "sg:tags":[
        "mexican"
    ],
    "wof:name":"Julio's",
    "wof:placetype":"venue"
},
  "geometry": {"coordinates":[-96.116781,41.236031],"type":"Point"}
}