{
  "type": "Feature",
  "properties": {
    "addr:full":"1205 W Norfolk Ave Norfolk NE 68701",
    "addr:housenumber":"1205",
    "addr:postcode":"68701",
    "addr:street":"W Norfolk Ave",
    "iso:country":"US",
    "sg:address":"1205 W Norfolk Ave",
    "sg:city":"Norfolk",
    "sg:classifiers":[
        {
            "category":"Travel",
            "subcategory":"Travel Agent",
            "type":"Entertainment"
        }
    ],
    "sg:phone":"+1 402 371 8867",
    "sg:postcode":"68701",
    "sg:province":"NE",
    "sg:tags":[
        "agency",
        "bureau"
    ],
    "wof:name":"Ballard Group",
    "wof:placetype":"venue"
},
  "geometry": {"coordinates":[-97.423207,42.032516],"type":"Point"}
}