{
  "type": "Feature",
  "properties": {
    "addr:full":"450 Regency Pkwy Omaha NE 68114",
    "addr:housenumber":"450",
    "addr:postcode":"68114",
    "addr:street":"Regency Pkwy",
    "iso:country":"US",
    "sg:address":"450 Regency Pkwy",
    "sg:city":"Omaha",
    "sg:classifiers":[
        {
            "category":"Professional",
            "subcategory":"Computer Services",
            "type":"Services"
        }
    ],
    "sg:phone":"+1 402 391 2002",
    "sg:postcode":"68114",
    "sg:province":"NE",
    "sg:tags":[
        "processing",
        "datum"
    ],
    "wof:name":"Nova Information Systems",
    "wof:placetype":"venue"
},
  "geometry": {"coordinates":[-96.073826,41.254377],"type":"Point"}
}