{
  "type": "Feature",
  "properties": {
    "addr:full":"1621 W 14th St North Platte NE 69101",
    "addr:housenumber":"1621",
    "addr:postcode":"69101",
    "addr:street":"W 14Th St",
    "iso:country":"US",
    "sg:address":"1621 W 14th St",
    "sg:city":"North Platte",
    "sg:classifiers":[
        {
            "category":"Restaurant",
            "type":"Food & Drink"
        }
    ],
    "sg:phone":"+1 308 534 9019",
    "sg:postcode":"69101",
    "sg:province":"NE",
    "sg:tags":[
        "eating"
    ],
    "wof:name":"Eat-A-Bite",
    "wof:placetype":"venue"
},
  "geometry": {"coordinates":[-100.77948499999999,41.150114],"type":"Point"}
}