{
  "type": "Feature",
  "properties": {
    "iso:country":"US",
    "sg:address":"1304 2nd St",
    "sg:city":"Aurora",
    "sg:classifiers":[
        {
            "category":"Professional",
            "subcategory":"Accounting & Tax Preparation",
            "type":"Services"
        }
    ],
    "sg:phone":"+1 402 694 2520",
    "sg:postcode":"68818",
    "sg:province":"NE",
    "sg:tags":[
        "accountant"
    ],
    "wof:name":"Marilyn E Mc Donald CPA",
    "wof:placetype":"venue"
},
  "geometry": {"coordinates":[-98.015708,40.869249],"type":"Point"}
}