{
  "type": "Feature",
  "properties": {
    "addr:full":"14210 Seward St Omaha NE 68154",
    "addr:housenumber":"14210",
    "addr:postcode":"68154",
    "addr:street":"Seward St",
    "iso:country":"US",
    "sg:address":"14210 Seward St",
    "sg:city":"Omaha",
    "sg:classifiers":[
        {
            "category":"Professional",
            "subcategory":"Business Services",
            "type":"Services"
        }
    ],
    "sg:phone":"+1 402 498 8615",
    "sg:postcode":"68154",
    "sg:province":"NE",
    "wof:name":"Design Direction Inc",
    "wof:placetype":"venue"
},
  "geometry": {"coordinates":[-96.13517,41.275107],"type":"Point"}
}