{
  "type": "Feature",
  "properties": {
    "iso:country":"US",
    "sg:address":"527 Johnson Dr",
    "sg:city":"Grand Island",
    "sg:classifiers":[
        {
            "category":"Freight",
            "type":"Transportation"
        }
    ],
    "sg:phone":"+1 308 384 7110",
    "sg:postcode":"68803",
    "sg:province":"NE",
    "sg:tags":[
        "trucking"
    ],
    "wof:name":"Zrust & Zrust",
    "wof:placetype":"venue"
},
  "geometry": {"coordinates":[-98.376863,40.92209],"type":"Point"}
}