{
  "type": "Feature",
  "properties": {
    "iso:country":"US",
    "sg:address":"774 Co Rd 4",
    "sg:city":"Ashland",
    "sg:classifiers":[
        {
            "category":"Manufacturing",
            "subcategory":"Lumber",
            "type":"Manufacturing & Wholesale Goods"
        }
    ],
    "sg:phone":"+1 402 944 3991",
    "sg:postcode":"68003",
    "sg:province":"NE",
    "sg:tags":[
        "sawmill"
    ],
    "wof:name":"Trade Well Pallet Inc",
    "wof:placetype":"venue"
},
  "geometry": {"coordinates":[-96.368065,41.114011],"type":"Point"}
}