{
  "type": "Feature",
  "properties": {
    "iso:country":"US",
    "sg:address":"2114 Central Ave",
    "sg:city":"Kearney",
    "sg:classifiers":[
        {
            "category":"Manufacturing",
            "subcategory":"Apparel",
            "type":"Manufacturing & Wholesale Goods"
        }
    ],
    "sg:phone":"+1 308 234 9819",
    "sg:postcode":"68847",
    "sg:province":"NE",
    "sg:tags":[
        "drapery",
        "contractor"
    ],
    "wof:name":"Bissell Decorating Studio",
    "wof:placetype":"venue"
},
  "geometry": {"coordinates":[-99.081813,40.697477],"type":"Point"}
}