{
  "type": "Feature",
  "properties": {
    "iso:country":"US",
    "sg:address":"930 Sheldon St",
    "sg:city":"Lodgepole",
    "sg:classifiers":[
        {
            "category":"Food & Beverages",
            "subcategory":"Groceries & Convenience Stores",
            "type":"Retail Goods"
        }
    ],
    "sg:phone":"+1 308 483 5480",
    "sg:postcode":"69149",
    "sg:province":"NE",
    "wof:name":"Panther Den Pit Stop",
    "wof:placetype":"venue"
},
  "geometry": {"coordinates":[-102.634833,41.148021],"type":"Point"}
}