{
  "type": "Feature",
  "properties": {
    "iso:country":"US",
    "sg:address":"410 E 2nd St",
    "sg:city":"Ogallala",
    "sg:classifiers":[
        {
            "category":"Government",
            "subcategory":"Police Station",
            "type":"Public Place"
        }
    ],
    "sg:phone":"+1 308 284 2024",
    "sg:postcode":"69153",
    "sg:province":"NE",
    "sg:tags":[
        "department",
        "protection"
    ],
    "wof:name":"Ogallala Police Department",
    "wof:placetype":"venue"
},
  "geometry": {"coordinates":[-101.714578,41.126145],"type":"Point"}
}