{
  "type": "Feature",
  "properties": {
    "iso:country":"US",
    "sg:address":"1718 Custer St",
    "sg:city":"Saint Paul",
    "sg:classifiers":[
        {
            "category":"Building & Trades",
            "subcategory":"Plumbing",
            "type":"Services"
        }
    ],
    "sg:phone":"+1 308 754 4971",
    "sg:postcode":"68873",
    "sg:province":"NE",
    "sg:tags":[
        "contractor"
    ],
    "wof:name":"Tlb Sprinklers",
    "wof:placetype":"venue"
},
  "geometry": {"coordinates":[-98.469313,41.208689],"type":"Point"}
}