{
  "type": "Feature",
  "properties": {
    "iso:country":"US",
    "sg:address":"7128 F St",
    "sg:city":"Omaha",
    "sg:classifiers":[
        {
            "category":"Food & Beverages",
            "subcategory":"Bakery",
            "type":"Retail Goods"
        }
    ],
    "sg:phone":"+1 402 935 0600",
    "sg:postcode":"68117",
    "sg:province":"NE",
    "sg:tags":[
        "baker"
    ],
    "sg:website":"www.saralee.com",
    "wof:name":"Sara Lee Bakery Group",
    "wof:placetype":"venue"
},
  "geometry": {"coordinates":[-96.020988,41.219796],"type":"Point"}
}