{
  "type": "Feature",
  "properties": {
    "iso:country":"US",
    "sg:address":"2420 Z St",
    "sg:city":"Omaha",
    "sg:phone":"+1 402 734 8500",
    "sg:postcode":"68107",
    "sg:province":"NE",
    "sg:tags":[
        "leather",
        "finishing"
    ],
    "wof:name":"Lackawanna Leather Co",
    "wof:placetype":"venue"
},
  "geometry": {"coordinates":[-95.947862,41.197388],"type":"Point"}
}