{
  "type": "Feature",
  "properties": {
    "iso:country":"US",
    "sg:address":"3924 Ames Ave",
    "sg:city":"Omaha",
    "sg:classifiers":[
        {
            "category":"Personal",
            "subcategory":"Barber",
            "type":"Services"
        }
    ],
    "sg:phone":"+1 402 455 8676",
    "sg:postcode":"68111",
    "sg:province":"NE",
    "wof:name":"Big Jim's Barber Shop",
    "wof:placetype":"venue"
},
  "geometry": {"coordinates":[-95.971901,41.299702],"type":"Point"}
}