{
  "type": "Feature",
  "properties": {
    "iso:country":"US",
    "sg:address":"56048 State Hwy 12",
    "sg:city":"Hartington",
    "sg:classifiers":[
        {
            "category":"Farming",
            "subcategory":"Livestock Farm",
            "type":"Manufacturing & Wholesale Goods"
        }
    ],
    "sg:phone":"+1 402 357 2217",
    "sg:postcode":"68739",
    "sg:province":"NE",
    "sg:tags":[
        "beef",
        "feedlot",
        "cattle"
    ],
    "wof:name":"William Kleinschmit",
    "wof:placetype":"venue"
},
  "geometry": {"coordinates":[-97.311612,42.728266],"type":"Point"}
}