{
  "type": "Feature",
  "properties": {
    "iso:country":"US",
    "sg:address":"12606 W Dodge Rd",
    "sg:city":"Omaha",
    "sg:classifiers":[
        {
            "category":"Farming",
            "subcategory":"Farm",
            "type":"Manufacturing & Wholesale Goods"
        }
    ],
    "sg:phone":"+1 402 563 3256",
    "sg:postcode":"68154",
    "sg:province":"NE",
    "sg:tags":[
        "crop",
        "general"
    ],
    "wof:name":"Howard Townsend",
    "wof:placetype":"venue"
},
  "geometry": {"coordinates":[-96.109883,41.263211],"type":"Point"}
}