{
  "type": "Feature",
  "properties": {
    "iso:country":"US",
    "sg:address":"616 N Thomas Ave",
    "sg:city":"Oakland",
    "sg:classifiers":[
        {
            "category":"Personal",
            "subcategory":"Beauty Salon",
            "type":"Services"
        }
    ],
    "sg:phone":"+1 402 685 5611",
    "sg:postcode":"68045",
    "sg:province":"NE",
    "sg:tags":[
        "shop"
    ],
    "wof:name":"Marys Beauty Shop",
    "wof:placetype":"venue"
},
  "geometry": {"coordinates":[-96.46550499999999,41.840082],"type":"Point"}
}