{
  "type": "Feature",
  "properties": {
    "iso:country":"US",
    "sg:address":"1208 N Airport Rd",
    "sg:city":"Lexington",
    "sg:classifiers":[
        {
            "category":"Building & Trades",
            "subcategory":"Construction",
            "type":"Services"
        }
    ],
    "sg:phone":"+1 308 324 7312",
    "sg:postcode":"68850",
    "sg:province":"NE",
    "sg:tags":[
        "general",
        "contractor"
    ],
    "wof:name":"Jim Phillips Construction",
    "wof:placetype":"venue"
},
  "geometry": {"coordinates":[-99.767792,40.784132],"type":"Point"}
}