{
  "type": "Feature",
  "properties": {
    "iso:country":"US",
    "sg:address":"13205 F St",
    "sg:city":"Omaha",
    "sg:classifiers":[
        {
            "category":"Wholesale",
            "subcategory":"Meat",
            "type":"Manufacturing & Wholesale Goods"
        }
    ],
    "sg:phone":"+1 402 905 2706",
    "sg:postcode":"68137",
    "sg:province":"NE",
    "sg:tags":[
        "packer",
        "equipment",
        "supply"
    ],
    "wof:name":"Glenn Valley Foods",
    "wof:placetype":"venue"
},
  "geometry": {"coordinates":[-96.11960000000001,41.21942],"type":"Point"}
}