{
  "type": "Feature",
  "properties": {
    "iso:country":"US",
    "sg:address":"15333 Mason Plz",
    "sg:city":"Omaha",
    "sg:classifiers":[
        {
            "category":"Real Estate",
            "subcategory":"Real Estate Agent",
            "type":"Services"
        }
    ],
    "sg:phone":"+1 402 991 5014",
    "sg:postcode":"68154",
    "sg:province":"NE",
    "wof:name":"Greatland Realty",
    "wof:placetype":"venue"
},
  "geometry": {"coordinates":[-96.1529,41.249065],"type":"Point"}
}