{
  "type": "Feature",
  "properties": {
    "iso:country":"US",
    "sg:address":"616 E 18th St",
    "sg:city":"South Sioux City",
    "sg:classifiers":[
        {
            "category":"Utilities",
            "subcategory":"Telephone",
            "type":"Services"
        }
    ],
    "sg:phone":"+1 402 494 5188",
    "sg:postcode":"68776",
    "sg:province":"NE",
    "sg:tags":[
        "communications"
    ],
    "wof:name":"Independent Telephone Contrs",
    "wof:placetype":"venue"
},
  "geometry": {"coordinates":[-96.404309,42.472594],"type":"Point"}
}