{
  "type": "Feature",
  "properties": {
    "iso:country":"US",
    "sg:address":"203 E Railroad St",
    "sg:city":"Shelton",
    "sg:classifiers":[
        {
            "category":"Retail",
            "subcategory":"Repair Shop",
            "type":"Services"
        }
    ],
    "sg:phone":"+1 308 647 5203",
    "sg:postcode":"68876",
    "sg:province":"NE",
    "sg:tags":[
        "related"
    ],
    "wof:name":"Willis Repair",
    "wof:placetype":"venue"
},
  "geometry": {"coordinates":[-98.729226,40.780791],"type":"Point"}
}