{
  "type": "Feature",
  "properties": {
    "iso:country":"US",
    "sg:address":"118 S 19th St",
    "sg:city":"Omaha",
    "sg:classifiers":[
        {
            "category":"Building & Trades",
            "subcategory":"Construction",
            "type":"Services"
        }
    ],
    "sg:phone":"+1 402 346 3900",
    "sg:postcode":"68102",
    "sg:province":"NE",
    "sg:tags":[
        "roofing",
        "contractor"
    ],
    "wof:name":"All Storm Repairs Inc",
    "wof:placetype":"venue"
},
  "geometry": {"coordinates":[-95.941214,41.258864],"type":"Point"}
}