{
  "type": "Feature",
  "properties": {
    "iso:country":"US",
    "sg:address":"4745 Prescott Ave",
    "sg:city":"Lincoln",
    "sg:classifiers":[
        {
            "category":"Building & Trades",
            "subcategory":"Construction",
            "type":"Services"
        }
    ],
    "sg:phone":"+1 402 489 6900",
    "sg:postcode":"68506",
    "sg:province":"NE",
    "sg:tags":[
        "general",
        "contractor"
    ],
    "wof:name":"DBG General Contractors Inc",
    "wof:placetype":"venue"
},
  "geometry": {"coordinates":[-96.654534,40.772835],"type":"Point"}
}