{
  "type": "Feature",
  "properties": {
    "addr:full":"1282 Co Rd C Lyons NE 68033",
    "addr:housenumber":"1282",
    "addr:postcode":"68033",
    "addr:street":"Co Rd",
    "iso:country":"US",
    "sg:address":"1282 Co Rd C",
    "sg:city":"Lyons",
    "sg:classifiers":[
        {
            "category":"Real Estate",
            "subcategory":"Real Estate Operator",
            "type":"Services"
        }
    ],
    "sg:phone":"+1 402 687 2905",
    "sg:postcode":"68033",
    "sg:province":"NE",
    "sg:tags":[
        "property",
        "lessor"
    ],
    "wof:name":"Ridge View Farm Inc",
    "wof:placetype":"venue"
},
  "geometry": {"coordinates":[-96.531291,41.088867],"type":"Point"}
}