{
  "type": "Feature",
  "properties": {
    "addr:full":"131 Pacific St Elkhorn NE 68022",
    "addr:housenumber":"131",
    "addr:postcode":"68022",
    "addr:street":"Pacific St",
    "iso:country":"US",
    "sg:address":"131 Pacific St",
    "sg:city":"Elkhorn",
    "sg:classifiers":[
        {
            "category":"Building & Trades",
            "subcategory":"Construction",
            "type":"Services"
        }
    ],
    "sg:phone":"+1 402 706 8419",
    "sg:postcode":"68022",
    "sg:province":"NE",
    "sg:tags":[
        "roofing",
        "contractor"
    ],
    "wof:name":"Superior Roof Systems",
    "wof:placetype":"venue"
},
  "geometry": {"coordinates":[-96.235823,41.28301],"type":"Point"}
}