{
  "type": "Feature",
  "properties": {
    "iso:country":"US",
    "sg:address":"1411 Plum Creek Pkwy",
    "sg:city":"Lexington",
    "sg:classifiers":[
        {
            "category":"Food & Beverages",
            "subcategory":"Groceries & Convenience Stores",
            "type":"Retail Goods"
        }
    ],
    "sg:phone":"+1 308 324 2327",
    "sg:postcode":"68850",
    "sg:province":"NE",
    "sg:tags":[
        "grocer"
    ],
    "wof:name":"Sav-A-Lot Discount Foods",
    "wof:placetype":"venue"
},
  "geometry": {"coordinates":[-99.73977499999999,40.764081],"type":"Point"}
}