{
  "type": "Feature",
  "properties": {
    "iso:country":"US",
    "sg:address":"409 E Park Ave",
    "sg:city":"Norfolk",
    "sg:classifiers":[
        {
            "category":"Building & Trades",
            "subcategory":"Construction",
            "type":"Services"
        }
    ],
    "sg:phone":"+1 402 371 7651",
    "sg:postcode":"68701",
    "sg:province":"NE",
    "sg:tags":[
        "residential"
    ],
    "wof:name":"Jeffrey Ahlman",
    "wof:placetype":"venue"
},
  "geometry": {"coordinates":[-97.401252,42.02933],"type":"Point"}
}