{
  "type": "Feature",
  "properties": {
    "addr:full":"4711 Meredeth St Lincoln NE 68506",
    "addr:housenumber":"4711",
    "addr:postcode":"68506",
    "addr:street":"Meredeth St",
    "iso:country":"US",
    "sg:address":"4711 Meredeth St",
    "sg:city":"Lincoln",
    "sg:classifiers":[
        {
            "category":"Social Services",
            "subcategory":"Adult Care",
            "type":"Services"
        }
    ],
    "sg:phone":"+1 402 489 7452",
    "sg:postcode":"68506",
    "sg:province":"NE",
    "sg:tags":[
        "home",
        "group"
    ],
    "wof:name":"Community Alternatives Ne",
    "wof:placetype":"venue"
},
  "geometry": {"coordinates":[-96.654186,40.770721],"type":"Point"}
}