{
  "type": "Feature",
  "properties": {
    "iso:country":"US",
    "sg:address":"4915 Chicago St",
    "sg:city":"Omaha",
    "sg:classifiers":[
        {
            "category":"Social Services",
            "subcategory":"Child Care",
            "type":"Services"
        },
        {
            "category":"Education",
            "subcategory":"Preschool",
            "type":"Public Place"
        },
        {
            "category":"Education",
            "subcategory":"School",
            "type":"Public Place"
        },
        {
            "category":"Education",
            "subcategory":"University",
            "type":"Public Place"
        }
    ],
    "sg:phone":"+1 402 554 1606",
    "sg:postcode":"68132",
    "sg:province":"NE",
    "sg:tags":[
        "elementary",
        "college",
        "day"
    ],
    "wof:name":"Blossom Time Child Care",
    "wof:placetype":"venue"
},
  "geometry": {"coordinates":[-95.988899,41.262199],"type":"Point"}
}