{
  "type": "Feature",
  "properties": {
    "iso:country":"US",
    "sg:address":"3201 Farnam",
    "sg:city":"Omaha",
    "sg:classifiers":[
        {
            "category":"Bars & Pubs",
            "type":"Food & Drink"
        }
    ],
    "sg:postcode":"68131",
    "sg:province":"NE",
    "wof:name":"Glo Lounge",
    "wof:placetype":"venue"
},
  "geometry": {"coordinates":[-95.960385,41.2577],"type":"Point"}
}