{
  "type": "Feature",
  "properties": {
    "iso:country":"US",
    "sg:address":"1394 US Hwy 20",
    "sg:city":"Jackson",
    "sg:classifiers":[
        {
            "category":"Wholesale",
            "subcategory":"Construction Materials",
            "type":"Manufacturing & Wholesale Goods"
        }
    ],
    "sg:phone":"+1 402 632 4601",
    "sg:postcode":"68743",
    "sg:province":"NE",
    "sg:tags":[
        "pallet",
        "skid"
    ],
    "wof:name":"Gomez Pallets",
    "wof:placetype":"venue"
},
  "geometry": {"coordinates":[-96.618765,42.47353],"type":"Point"}
}