{
  "type": "Feature",
  "properties": {
    "iso:country":"US",
    "sg:address":"5645 S 56th St",
    "sg:city":"Lincoln",
    "sg:classifiers":[
        {
            "category":"Health Services",
            "subcategory":"Health Practitioner",
            "type":"Services"
        }
    ],
    "sg:phone":"+1 402 423 9303",
    "sg:postcode":"68516",
    "sg:province":"NE",
    "sg:tags":[
        "psychologist"
    ],
    "wof:name":"Family Psychological Svc Inc",
    "wof:placetype":"venue"
},
  "geometry": {"coordinates":[-96.64438699999999,40.756262],"type":"Point"}
}