{
  "type": "Feature",
  "properties": {
    "iso:country":"US",
    "sg:address":"11418 Raleigh Dr",
    "sg:city":"Omaha",
    "sg:classifiers":[
        {
            "category":"Professional",
            "subcategory":"Computer Services",
            "type":"Services"
        }
    ],
    "sg:phone":"+1 402 571 4737",
    "sg:postcode":"68164",
    "sg:province":"NE",
    "sg:tags":[
        "related"
    ],
    "wof:name":"Parker Jeffrey",
    "wof:placetype":"venue"
},
  "geometry": {"coordinates":[-96.09044299999999,41.301573],"type":"Point"}
}