{
  "type": "Feature",
  "properties": {
    "addr:full":"15 E 18th St Kearney NE 68847",
    "addr:housenumber":"15",
    "addr:postcode":"68847",
    "addr:street":"E 18Th St",
    "iso:country":"US",
    "sg:address":"15 E 18th St",
    "sg:city":"Kearney",
    "sg:classifiers":[
        {
            "category":"Organizations",
            "subcategory":"Religious Organization",
            "type":"Services"
        }
    ],
    "sg:phone":"+1 308 234 9998",
    "sg:postcode":"68847",
    "sg:province":"NE",
    "sg:tags":[
        "membership"
    ],
    "wof:name":"Salvation Army Thrift Store",
    "wof:placetype":"venue"
},
  "geometry": {"coordinates":[-99.081717,40.692321],"type":"Point"}
}