{
  "type": "Feature",
  "properties": {
    "iso:country":"US",
    "sg:address":"236 N Main St",
    "sg:city":"West Point",
    "sg:classifiers":[
        {
            "category":"Shopping",
            "subcategory":"Pharmacy",
            "type":"Retail Goods"
        }
    ],
    "sg:phone":"+1 402 372 5343",
    "sg:postcode":"68788",
    "sg:province":"NE",
    "wof:name":"Pamida",
    "wof:placetype":"venue"
},
  "geometry": {"coordinates":[-96.71204899999999,41.841706],"type":"Point"}
}