{
  "type": "Feature",
  "properties": {
    "addr:full":"408 Elm St Arapahoe NE 68922",
    "addr:housenumber":"408",
    "addr:postcode":"68922",
    "addr:street":"Elm St",
    "iso:country":"US",
    "sg:address":"408 Elm St",
    "sg:city":"Arapahoe",
    "sg:classifiers":[
        {
            "category":"Professional",
            "type":"Services"
        }
    ],
    "sg:phone":"+1 308 962 7617",
    "sg:postcode":"68922",
    "sg:province":"NE",
    "wof:name":"CRA Gro Crop Service",
    "wof:placetype":"venue"
},
  "geometry": {"coordinates":[-99.894141,40.304549],"type":"Point"}
}