{
  "type": "Feature",
  "properties": {
    "addr:full":"317 Bryan St Gretna NE 68028",
    "addr:housenumber":"317",
    "addr:postcode":"68028",
    "addr:street":"Bryan St",
    "iso:country":"US",
    "sg:address":"317 Bryan St",
    "sg:city":"Gretna",
    "sg:classifiers":[
        {
            "category":"Social Services",
            "subcategory":"Child Care",
            "type":"Services"
        }
    ],
    "sg:phone":"+1 402 332 2841",
    "sg:postcode":"68028",
    "sg:province":"NE",
    "sg:tags":[
        "day"
    ],
    "wof:name":"Patera Erin Day Care",
    "wof:placetype":"venue"
},
  "geometry": {"coordinates":[-96.24384000000001,41.136931],"type":"Point"}
}