{
  "type": "Feature",
  "properties": {
    "iso:country":"US",
    "sg:address":"770 N Cotner Blvd",
    "sg:city":"Lincoln",
    "sg:classifiers":[
        {
            "category":"Professional",
            "subcategory":"Credit Reporting & Collection",
            "type":"Services"
        }
    ],
    "sg:phone":"+1 402 464 7407",
    "sg:postcode":"68505",
    "sg:province":"NE",
    "sg:tags":[
        "agency"
    ],
    "wof:name":"National Account Systems Inc",
    "wof:placetype":"venue"
},
  "geometry": {"coordinates":[-96.63553899999999,40.820482],"type":"Point"}
}