{
  "type": "Feature",
  "properties": {
    "iso:country":"US",
    "sg:address":"510 E 1st St",
    "sg:city":"Ogallala",
    "sg:classifiers":[
        {
            "category":"Farming",
            "subcategory":"Livestock Farm",
            "type":"Manufacturing & Wholesale Goods"
        }
    ],
    "sg:phone":"+1 308 284 4443",
    "sg:postcode":"69153",
    "sg:province":"NE",
    "sg:tags":[
        "ranch"
    ],
    "wof:name":"Lute Ranches",
    "wof:placetype":"venue"
},
  "geometry": {"coordinates":[-101.71319200000001,41.125387],"type":"Point"}
}