{
  "type": "Feature",
  "properties": {
    "iso:country":"US",
    "sg:address":"13929 Gold Cir",
    "sg:city":"Omaha",
    "sg:classifiers":[
        {
            "category":"Travel",
            "subcategory":"Hotels & Motels",
            "type":"Entertainment"
        }
    ],
    "sg:phone":"+1 402 333 3777",
    "sg:postcode":"68144",
    "sg:province":"NE",
    "sg:tags":[
        "inn"
    ],
    "wof:name":"Townhouse Inn",
    "wof:placetype":"venue"
},
  "geometry": {"coordinates":[-96.13109,41.234904],"type":"Point"}
}