{
  "type": "Feature",
  "properties": {
    "iso:country":"US",
    "sg:address":"9371 250th St",
    "sg:city":"Alvo",
    "sg:classifiers":[
        {
            "category":"Professional",
            "subcategory":"Management & Consulting",
            "type":"Services"
        }
    ],
    "sg:phone":"+1 402 473 2818",
    "sg:postcode":"68366",
    "sg:province":"NE",
    "sg:tags":[
        "consultant",
        "business"
    ],
    "wof:name":"Spohr's Consulting Inc",
    "wof:placetype":"venue"
},
  "geometry": {"coordinates":[-96.369978,40.927524],"type":"Point"}
}