{
  "type": "Feature",
  "properties": {
    "iso:country":"US",
    "sg:address":"308 S Main St",
    "sg:city":"Ainsworth",
    "sg:classifiers":[
        {
            "category":"Museum",
            "type":"Entertainment"
        }
    ],
    "sg:phone":"+1 402 925 2726",
    "sg:postcode":"69210",
    "sg:province":"NE",
    "wof:name":"Sturdevant-Mc Kee Museum",
    "wof:placetype":"venue"
},
  "geometry": {"coordinates":[-99.862296,42.543728],"type":"Point"}
}