{
  "type": "Feature",
  "properties": {
    "iso:country":"US",
    "sg:address":"1305 Howard Ave",
    "sg:city":"St Paul",
    "sg:classifiers":[
        {
            "category":"Education",
            "subcategory":"School",
            "type":"Public Place"
        }
    ],
    "sg:phone":"+1 308 754 4433",
    "sg:postcode":"68873",
    "sg:province":"NE",
    "wof:name":"St Paul Public School",
    "wof:placetype":"venue"
},
  "geometry": {"coordinates":[-98.466359,41.213362],"type":"Point"}
}