{
  "type": "Feature",
  "properties": {
    "iso:country":"US",
    "sg:address":"2851 Capehart Rd",
    "sg:city":"Bellevue",
    "sg:classifiers":[
        {
            "category":"Personal",
            "subcategory":"Barber",
            "type":"Services"
        }
    ],
    "sg:phone":"+1 402 293 7630",
    "sg:postcode":"68123",
    "sg:province":"NE",
    "wof:name":"Ashley Lynn's Barber & Beauty",
    "wof:placetype":"venue"
},
  "geometry": {"coordinates":[-95.953402,41.120451],"type":"Point"}
}