{
  "type": "Feature",
  "properties": {
    "iso:country":"US",
    "sg:address":"424 Pine St",
    "sg:city":"Valparaiso",
    "sg:classifiers":[
        {
            "category":"Retail",
            "subcategory":"Funeral Services",
            "type":"Services"
        }
    ],
    "sg:phone":"+1 402 784 2841",
    "sg:postcode":"68065",
    "sg:province":"NE",
    "sg:tags":[
        "director"
    ],
    "wof:name":"Wadlow-Rozanek Funeral Home",
    "wof:placetype":"venue"
},
  "geometry": {"coordinates":[-96.834233,41.079353],"type":"Point"}
}