{
  "type": "Feature",
  "properties": {
    "addr:full":"175 N Sheridan St Gordon NE 69343",
    "addr:housenumber":"175",
    "addr:postcode":"69343",
    "addr:street":"N Sheridan St",
    "iso:country":"US",
    "sg:address":"175 N Sheridan St",
    "sg:city":"Gordon",
    "sg:classifiers":[
        {
            "category":"Building & Trades",
            "subcategory":"Construction",
            "type":"Services"
        }
    ],
    "sg:phone":"+1 308 282 0686",
    "sg:postcode":"69343",
    "sg:province":"NE",
    "sg:tags":[
        "industrial"
    ],
    "wof:name":"Greenamyre Contractor and Bldr",
    "wof:placetype":"venue"
},
  "geometry": {"coordinates":[-102.21191,42.804046],"type":"Point"}
}