{
  "type": "Feature",
  "properties": {
    "addr:full":"13688 Co Rd 38 Kennard NE 68034",
    "addr:housenumber":"13688;38",
    "addr:postcode":"68034",
    "addr:street":"Co Rd",
    "iso:country":"US",
    "sg:address":"13688 Co Rd 38",
    "sg:city":"Kennard",
    "sg:phone":"+1 402 238 2129",
    "sg:postcode":"68034",
    "sg:province":"NE",
    "sg:tags":[
        "farm",
        "corn"
    ],
    "wof:name":"Fred Schumacher",
    "wof:placetype":"venue"
},
  "geometry": {"coordinates":[-96.16908599999999,41.422282],"type":"Point"}
}