{
  "type": "Feature",
  "properties": {
    "iso:country":"US",
    "sg:address":"720 17th St",
    "sg:city":"Aurora",
    "sg:classifiers":[
        {
            "category":"Social Services",
            "subcategory":"Child Care",
            "type":"Services"
        }
    ],
    "sg:phone":"+1 402 694 5070",
    "sg:postcode":"68818",
    "sg:province":"NE",
    "sg:tags":[
        "day"
    ],
    "wof:name":"Tots Learning Center",
    "wof:placetype":"venue"
},
  "geometry": {"coordinates":[-97.99529800000001,40.863886],"type":"Point"}
}