{
  "type": "Feature",
  "properties": {
    "iso:country":"US",
    "sg:address":"4505 S 162nd Ave",
    "sg:city":"Omaha",
    "sg:classifiers":[
        {
            "category":"Building & Trades",
            "subcategory":"Construction",
            "type":"Services"
        }
    ],
    "sg:phone":"+1 402 896 9005",
    "sg:postcode":"68135",
    "sg:province":"NE",
    "sg:tags":[
        "boring",
        "contractor"
    ],
    "wof:name":"Kw Boring Inc",
    "wof:placetype":"venue"
},
  "geometry": {"coordinates":[-96.170225,41.215123],"type":"Point"}
}