{
  "type": "Feature",
  "properties": {
    "iso:country":"US",
    "sg:address":"3205 N 90th St",
    "sg:city":"Omaha",
    "sg:classifiers":[
        {
            "category":"Banks & Credit Unions",
            "subcategory":"Investment Brokerage",
            "type":"Services"
        }
    ],
    "sg:phone":"+1 402 571 2600",
    "sg:postcode":"68134",
    "sg:province":"NE",
    "sg:tags":[
        "consultant",
        "planning",
        "financial",
        "advisory"
    ],
    "wof:name":"Associated Financial Planners",
    "wof:placetype":"venue"
},
  "geometry": {"coordinates":[-96.05252900000001,41.285892],"type":"Point"}
}