{
  "type": "Feature",
  "properties": {
    "addr:full":"14825 Queens Dr Omaha NE 68116",
    "addr:housenumber":"14825",
    "addr:postcode":"68116",
    "addr:street":"Queens Dr",
    "iso:country":"US",
    "sg:address":"14825 Queens Dr",
    "sg:city":"Omaha",
    "sg:classifiers":[
        {
            "category":"Professional",
            "subcategory":"Computer Services",
            "type":"Services"
        }
    ],
    "sg:phone":"+1 402 571 5698",
    "sg:postcode":"68116",
    "sg:province":"NE",
    "sg:tags":[
        "related"
    ],
    "wof:name":"Induction Industries Inc",
    "wof:placetype":"venue"
},
  "geometry": {"coordinates":[-96.147013,41.302161],"type":"Point"}
}