{
  "type": "Feature",
  "properties": {
    "iso:country":"US",
    "sg:address":"805 Sheridan St",
    "sg:city":"St Paul",
    "sg:classifiers":[
        {
            "category":"Wholesale",
            "subcategory":"Machinery & Supplies",
            "type":"Manufacturing & Wholesale Goods"
        }
    ],
    "sg:phone":"+1 308 754 4118",
    "sg:postcode":"68873",
    "sg:province":"NE",
    "sg:tags":[
        "equipment",
        "irrigation",
        "system"
    ],
    "wof:name":"St Paul Irrigation Systems",
    "wof:placetype":"venue"
},
  "geometry": {"coordinates":[-98.463892,41.214327],"type":"Point"}
}