{
  "type": "Feature",
  "properties": {
    "iso:country":"US",
    "sg:address":"14160 S Bladen Ave",
    "sg:city":"Roseland",
    "sg:classifiers":[
        {
            "category":"Farming",
            "subcategory":"Livestock Farm",
            "type":"Manufacturing & Wholesale Goods"
        }
    ],
    "sg:phone":"+1 402 756 6770",
    "sg:postcode":"68973",
    "sg:province":"NE",
    "sg:tags":[
        "corn",
        "beef",
        "feedlot",
        "cattle"
    ],
    "wof:name":"B&B Farms",
    "wof:placetype":"venue"
},
  "geometry": {"coordinates":[-98.591263,40.422717],"type":"Point"}
}