{
  "type": "Feature",
  "properties": {
    "iso:country":"US",
    "sg:address":"13215 Birch Dr",
    "sg:city":"Omaha",
    "sg:classifiers":[
        {
            "category":"Real Estate",
            "subcategory":"Developer",
            "type":"Services"
        }
    ],
    "sg:phone":"+1 402 498 8800",
    "sg:postcode":"68164",
    "sg:province":"NE",
    "sg:tags":[
        "development",
        "land"
    ],
    "wof:name":"Horgan Development Company",
    "wof:placetype":"venue"
},
  "geometry": {"coordinates":[-96.120074,41.290359],"type":"Point"}
}