{
  "type": "Feature",
  "properties": {
    "addr:full":"2410 S 217th St Elkhorn NE 68022",
    "addr:housenumber":"2410",
    "addr:postcode":"68022",
    "addr:street":"S 217Th St",
    "iso:country":"US",
    "sg:address":"2410 S 217th St",
    "sg:city":"Elkhorn",
    "sg:classifiers":[
        {
            "category":"Recreation",
            "type":"Entertainment"
        }
    ],
    "sg:phone":"+1 402 289 3545",
    "sg:postcode":"68022",
    "sg:province":"NE",
    "sg:tags":[
        "course",
        "golf"
    ],
    "wof:name":"Skyline Woods Country Club",
    "wof:placetype":"venue"
},
  "geometry": {"coordinates":[-96.254473,41.236562],"type":"Point"}
}