{
  "type": "Feature",
  "properties": {
    "iso:country":"US",
    "sg:address":"1800 W 24th St",
    "sg:city":"Kearney",
    "sg:classifiers":[
        {
            "category":"Recreation",
            "type":"Entertainment"
        }
    ],
    "sg:phone":"+1 308 234 6543",
    "sg:postcode":"68845",
    "sg:province":"NE",
    "sg:tags":[
        "range",
        "practice",
        "golf"
    ],
    "wof:name":"Kearney Golf Ctr",
    "wof:placetype":"venue"
},
  "geometry": {"coordinates":[-99.104084,40.69935],"type":"Point"}
}