{
  "type": "Feature",
  "properties": {
    "iso:country":"US",
    "sg:address":"4963 Virginia St",
    "sg:city":"Omaha",
    "sg:classifiers":[
        {
            "category":"Social Services",
            "subcategory":"Child Care",
            "type":"Services"
        }
    ],
    "sg:phone":"+1 402 733 5209",
    "sg:postcode":"68157",
    "sg:province":"NE",
    "sg:tags":[
        "day"
    ],
    "wof:name":"Minardi Vicky Day Care",
    "wof:placetype":"venue"
},
  "geometry": {"coordinates":[-95.991434,41.174218],"type":"Point"}
}