{
  "type": "Feature",
  "properties": {
    "iso:country":"US",
    "sg:address":"2330 Paul St",
    "sg:city":"Omaha",
    "sg:classifiers":[
        {
            "category":"Professional",
            "subcategory":"Detective & Security Services",
            "type":"Services"
        }
    ],
    "sg:phone":"+1 402 341 2600",
    "sg:postcode":"68102",
    "sg:province":"NE",
    "sg:tags":[
        "car",
        "armored"
    ],
    "wof:name":"Armored Knights Inc",
    "wof:placetype":"venue"
},
  "geometry": {"coordinates":[-95.946702,41.27179],"type":"Point"}
}