{
  "type": "Feature",
  "properties": {
    "addr:full":"224 State Hwy 61 Scn Ogallala NE 69153",
    "addr:housenumber":"224",
    "addr:postcode":"69153",
    "addr:street":"State Hwy 61 Scn",
    "iso:country":"US",
    "sg:address":"224 State Hwy 61 Scn",
    "sg:city":"Ogallala",
    "sg:classifiers":[
        {
            "category":"Insurance",
            "subcategory":"Insurance Agent",
            "type":"Services"
        }
    ],
    "sg:phone":"+1 308 284 3953",
    "sg:postcode":"69153",
    "sg:province":"NE",
    "wof:name":"Tuffy Barent Insurance",
    "wof:placetype":"venue"
},
  "geometry": {"coordinates":[-101.69521899999999,41.163503],"type":"Point"}
}