{
  "type": "Feature",
  "properties": {
    "addr:full":"410 E Everett St Oneill NE 68763",
    "addr:housenumber":"410",
    "addr:postcode":"68763",
    "addr:street":"E Everett St",
    "iso:country":"US",
    "sg:address":"410 E Everett St",
    "sg:city":"Oneill",
    "sg:classifiers":[
        {
            "category":"Personal",
            "subcategory":"Beauty Salon",
            "type":"Services"
        }
    ],
    "sg:phone":"+1 402 336 3097",
    "sg:postcode":"68763",
    "sg:province":"NE",
    "sg:tags":[
        "shop"
    ],
    "wof:name":"Liquid Hair Salon",
    "wof:placetype":"venue"
},
  "geometry": {"coordinates":[-98.647766,42.45651],"type":"Point"}
}