{
  "type": "Feature",
  "properties": {
    "addr:full":"1220 Saltillo Rd Roca NE 68430",
    "addr:housenumber":"1220",
    "addr:postcode":"68430",
    "addr:street":"Saltillo Rd",
    "iso:country":"US",
    "sg:address":"1220 Saltillo Rd",
    "sg:city":"Roca",
    "sg:classifiers":[
        {
            "category":"Professional",
            "subcategory":"Business Services",
            "type":"Services"
        }
    ],
    "sg:phone":"+1 402 420 0755",
    "sg:postcode":"68430",
    "sg:province":"NE",
    "sg:tags":[
        "water",
        "treatment"
    ],
    "wof:name":"Hawkins Water Treatment Group",
    "wof:placetype":"venue"
},
  "geometry": {"coordinates":[-96.704992,40.697477],"type":"Point"}
}