{
  "type": "Feature",
  "properties": {
    "addr:full":"PO Box 1600 Bellevue NE 68005",
    "addr:housenumber":"po",
    "addr:postcode":"68005",
    "addr:street":"Box 1600",
    "iso:country":"US",
    "sg:address":"PO Box 1600",
    "sg:city":"Bellevue",
    "sg:classifiers":[
        {
            "category":"Professional",
            "subcategory":"Computer Services",
            "type":"Services"
        }
    ],
    "sg:phone":"+1 402 218 2110",
    "sg:postcode":"68005",
    "sg:province":"NE",
    "sg:tags":[
        "saas",
        "software-as-a-service",
        "php",
        "mysql",
        "web-applications",
        "invoicing"
    ],
    "sg:website":"http://beckerwebsolutions.com",
    "wof:name":"Becker Web Solutions",
    "wof:placetype":"venue"
},
  "geometry": {"coordinates":[-95.90395599999999,41.132948],"type":"Point"}
}