{
  "type": "Feature",
  "properties": {
    "iso:country":"US",
    "sg:address":"1455 W 11th St",
    "sg:city":"Crete",
    "sg:classifiers":[
        {
            "category":"Retail",
            "subcategory":"Auto Repair",
            "type":"Services"
        }
    ],
    "sg:phone":"+1 402 826 5191",
    "sg:postcode":"68333",
    "sg:province":"NE",
    "sg:tags":[
        "body",
        "automobile",
        "painting"
    ],
    "wof:name":"Crist's Auto Body Repair",
    "wof:placetype":"venue"
},
  "geometry": {"coordinates":[-96.97817000000001,40.621945],"type":"Point"}
}