{
  "type": "Feature",
  "properties": {
    "addr:full":"401 N Spruce St Ogallala NE 69153",
    "addr:housenumber":"401",
    "addr:postcode":"69153",
    "addr:street":"N Spruce St",
    "iso:country":"US",
    "sg:address":"401 N Spruce St",
    "sg:city":"Ogallala",
    "sg:classifiers":[
        {
            "category":"Education",
            "subcategory":"School",
            "type":"Public Place"
        }
    ],
    "sg:phone":"+1 308 284 9811",
    "sg:postcode":"69153",
    "sg:province":"NE",
    "sg:tags":[
        "academic",
        "special"
    ],
    "wof:name":"Alternative Learning Lane",
    "wof:placetype":"venue"
},
  "geometry": {"coordinates":[-101.719795,41.128316],"type":"Point"}
}