{
  "type": "Feature",
  "properties": {
    "iso:country":"US",
    "sg:address":"43581 Hwy 30",
    "sg:city":"Lexington",
    "sg:classifiers":[
        {
            "category":"Freight",
            "type":"Transportation"
        }
    ],
    "sg:phone":"+1 308 324 6366",
    "sg:postcode":"68850",
    "sg:province":"NE",
    "sg:tags":[
        "distance",
        "long",
        "trucking"
    ],
    "wof:name":"Justa Truck Trucking Inc",
    "wof:placetype":"venue"
},
  "geometry": {"coordinates":[-99.695273,40.766177],"type":"Point"}
}