{
  "type": "Feature",
  "properties": {
    "iso:country":"US",
    "sg:address":"920 State Hwy 50",
    "sg:city":"Yankton",
    "sg:classifiers":[
        {
            "category":"Insurance",
            "subcategory":"Insurance Agent",
            "type":"Services"
        }
    ],
    "sg:phone":"+1 605 665 4147",
    "sg:postcode":"57078",
    "sg:province":"NE",
    "wof:name":"Crop Insurance",
    "wof:placetype":"venue"
},
  "geometry": {"coordinates":[-97.396672,42.877442],"type":"Point"}
}