{
  "type": "Feature",
  "properties": {
    "iso:country":"US",
    "sg:address":"202 E 2nd St",
    "sg:city":"Stuart",
    "sg:classifiers":[
        {
            "category":"Retail",
            "subcategory":"Funeral Services",
            "type":"Services"
        }
    ],
    "sg:phone":"+1 402 924 3158",
    "sg:postcode":"68713",
    "sg:province":"NE",
    "sg:tags":[
        "director"
    ],
    "wof:name":"Seger Funeral Home Inc",
    "wof:placetype":"venue"
},
  "geometry": {"coordinates":[-98.977041,42.534064],"type":"Point"}
}