{
  "type": "Feature",
  "properties": {
    "iso:country":"US",
    "sg:address":"1100 W 14th St",
    "sg:city":"Hastings",
    "sg:classifiers":[
        {
            "category":"Education",
            "subcategory":"School",
            "type":"Public Place"
        }
    ],
    "sg:phone":"+1 402 461 7550",
    "sg:postcode":"68901",
    "sg:province":"NE",
    "wof:name":"Hastings Senior High School",
    "wof:placetype":"venue"
},
  "geometry": {"coordinates":[-98.396878,40.600722],"type":"Point"}
}