{
  "type": "Feature",
  "properties": {
    "addr:full":"614 E 11th St Wood River NE 68883",
    "addr:housenumber":"614",
    "addr:postcode":"68883",
    "addr:street":"E 11Th St",
    "iso:country":"US",
    "sg:address":"614 E 11th St",
    "sg:city":"Wood River",
    "sg:classifiers":[
        {
            "category":"Retail",
            "subcategory":"Auto Repair",
            "type":"Services"
        }
    ],
    "sg:phone":"+1 308 583 2311",
    "sg:postcode":"68883",
    "sg:province":"NE",
    "sg:tags":[
        "repairing",
        "automobile"
    ],
    "wof:name":"Voss's Alignment & Repair",
    "wof:placetype":"venue"
},
  "geometry": {"coordinates":[-98.594594,40.822514],"type":"Point"}
}