{
  "type": "Feature",
  "properties": {
    "addr:full":"907 S Burlington Ave Hastings NE 68901",
    "addr:housenumber":"907",
    "addr:postcode":"68901",
    "addr:street":"S Burlington Ave",
    "iso:country":"US",
    "sg:address":"907 S Burlington Ave",
    "sg:city":"Hastings",
    "sg:classifiers":[
        {
            "category":"Retail",
            "subcategory":"Car Wash",
            "type":"Services"
        }
    ],
    "sg:phone":"+1 402 463 6184",
    "sg:postcode":"68901",
    "sg:province":"NE",
    "sg:tags":[
        "polishing",
        "washing"
    ],
    "wof:name":"Chris's Car Wash & Quick Lube",
    "wof:placetype":"venue"
},
  "geometry": {"coordinates":[-98.392392,40.573341],"type":"Point"}
}