{
  "type": "Feature",
  "properties": {
    "iso:country":"US",
    "sg:address":"1442 Valley Rd",
    "sg:city":"Farwell",
    "sg:classifiers":[
        {
            "category":"Farming",
            "subcategory":"Livestock Farm",
            "type":"Manufacturing & Wholesale Goods"
        }
    ],
    "sg:phone":"+1 308 336 3230",
    "sg:postcode":"68838",
    "sg:province":"NE",
    "sg:tags":[
        "hog",
        "beef",
        "far",
        "corn",
        "cattle",
        "or",
        "feedlot"
    ],
    "wof:name":"Gerald Rathman & Sons",
    "wof:placetype":"venue"
},
  "geometry": {"coordinates":[-98.68982,41.242374],"type":"Point"}
}