{
  "type": "Feature",
  "properties": {
    "addr:full":"429 N Linden St Wahoo NE 68066",
    "addr:housenumber":"429",
    "addr:postcode":"68066",
    "addr:street":"N Linden St",
    "iso:country":"US",
    "sg:address":"429 N Linden St",
    "sg:city":"Wahoo",
    "sg:classifiers":[
        {
            "category":"Insurance",
            "subcategory":"Insurance Agent",
            "type":"Services"
        }
    ],
    "sg:phone":"+1 402 443 1303",
    "sg:postcode":"68066",
    "sg:province":"NE",
    "wof:name":"Farmers Insurance Group",
    "wof:placetype":"venue"
},
  "geometry": {"coordinates":[-96.61870399999999,41.209709],"type":"Point"}
}