{
  "type": "Feature",
  "properties": {
    "iso:country":"US",
    "sg:address":"3711 14th Ave",
    "sg:city":"Kearney",
    "sg:classifiers":[
        {
            "category":"Airport",
            "type":"Transportation"
        }
    ],
    "sg:phone":"+1 308 324 8770",
    "sg:postcode":"68845",
    "sg:province":"NE",
    "sg:tags":[
        "aircraft",
        "design",
        "maintenance",
        "research"
    ],
    "wof:name":"Mays Aircraft Service Inc",
    "wof:placetype":"venue"
},
  "geometry": {"coordinates":[-99.098535,40.712413],"type":"Point"}
}