{
  "type": "Feature",
  "properties": {
    "addr:full":"407 W 29th St South Sioux City NE 68776",
    "addr:housenumber":"407",
    "addr:postcode":"68776",
    "addr:street":"W 29Th St",
    "iso:country":"US",
    "sg:address":"407 W 29th St",
    "sg:city":"South Sioux City",
    "sg:classifiers":[
        {
            "category":"Manufacturing",
            "subcategory":"Tools & Machinery",
            "type":"Manufacturing & Wholesale Goods"
        }
    ],
    "sg:phone":"+1 402 241 0407",
    "sg:postcode":"68776",
    "sg:province":"NE",
    "sg:tags":[
        "industrial",
        "mfg"
    ],
    "wof:name":"R J Automotive Machine",
    "wof:placetype":"venue"
},
  "geometry": {"coordinates":[-96.418567,42.462676],"type":"Point"}
}