{
  "type": "Feature",
  "properties": {
    "addr:full":"2302 8th Ave Plattsmouth NE 68048",
    "addr:housenumber":"2302",
    "addr:postcode":"68048",
    "addr:street":"8Th Ave",
    "iso:country":"US",
    "sg:address":"2302 8th Ave",
    "sg:city":"Plattsmouth",
    "sg:classifiers":[
        {
            "category":"Health Services",
            "subcategory":"Doctor",
            "type":"Services"
        }
    ],
    "sg:phone":"+1 402 296 4451",
    "sg:postcode":"68048",
    "sg:province":"NE",
    "sg:tags":[
        "physician",
        "surgeon"
    ],
    "wof:name":"Family Physicians",
    "wof:placetype":"venue"
},
  "geometry": {"coordinates":[-95.904225,41.002523],"type":"Point"}
}