{
  "type": "Feature",
  "properties": {
    "iso:country":"US",
    "sg:address":"802 N Dewey St",
    "sg:city":"North Platte",
    "sg:classifiers":[
        {
            "category":"Restaurant",
            "type":"Food & Drink"
        }
    ],
    "sg:phone":"+1 308 532 8360",
    "sg:postcode":"69101",
    "sg:province":"NE",
    "sg:tags":[
        "eating"
    ],
    "wof:name":"Dairy Queen",
    "wof:placetype":"venue"
},
  "geometry": {"coordinates":[-100.76064599999999,41.142696],"type":"Point"}
}