{
  "type": "Feature",
  "properties": {
    "addr:full":"367 Co Rd 13 Scribner NE 68057",
    "addr:housenumber":"367;13",
    "addr:postcode":"68057",
    "addr:street":"Co Rd",
    "iso:country":"US",
    "sg:address":"367 Co Rd 13",
    "sg:city":"Scribner",
    "sg:classifiers":[
        {
            "category":"Organizations",
            "subcategory":"Professional Association",
            "type":"Services"
        }
    ],
    "sg:phone":"+1 402 664 3539",
    "sg:postcode":"68057",
    "sg:province":"NE",
    "wof:name":"Maple Creek Co",
    "wof:placetype":"venue"
},
  "geometry": {"coordinates":[-96.67483199999999,41.702811],"type":"Point"}
}