{
  "type": "Feature",
  "properties": {
    "iso:country":"US",
    "sg:address":"4503 2nd Ave",
    "sg:city":"Kearney",
    "sg:classifiers":[
        {
            "category":"Social Services",
            "type":"Services"
        }
    ],
    "sg:phone":"+1 308 338 0082",
    "sg:postcode":"68847",
    "sg:province":"NE",
    "wof:name":"Curfman Joy Prof Cunseling Svc",
    "wof:placetype":"venue"
},
  "geometry": {"coordinates":[-99.083865,40.717657],"type":"Point"}
}