{
  "type": "Feature",
  "properties": {
    "addr:full":"8456 S 42nd St Bellevue NE 68147",
    "addr:housenumber":"8456",
    "addr:postcode":"68147",
    "addr:street":"S 42Nd St",
    "iso:country":"US",
    "sg:address":"8456 S 42nd St",
    "sg:city":"Bellevue",
    "sg:classifiers":[
        {
            "category":"Education",
            "subcategory":"Special Training",
            "type":"Public Place"
        }
    ],
    "sg:phone":"+1 402 731 8627",
    "sg:postcode":"68147",
    "sg:province":"NE",
    "sg:tags":[
        "tutoring"
    ],
    "wof:name":"Mortensen Math Of The Midlands",
    "wof:placetype":"venue"
},
  "geometry": {"coordinates":[-95.976949,41.173971],"type":"Point"}
}