{
  "type": "Feature",
  "properties": {
    "iso:country":"US",
    "sg:address":"802 4th Ave",
    "sg:city":"Holdrege",
    "sg:classifiers":[
        {
            "category":"Utilities",
            "subcategory":"Refuse",
            "type":"Services"
        }
    ],
    "sg:phone":"+1 308 995 5641",
    "sg:postcode":"68949",
    "sg:province":"NE",
    "sg:tags":[
        "garbage",
        "collection"
    ],
    "wof:name":"Orcutt Sanitation & Sewer",
    "wof:placetype":"venue"
},
  "geometry": {"coordinates":[-99.369856,40.437879],"type":"Point"}
}