{
  "type": "Feature",
  "properties": {
    "iso:country":"US",
    "sg:address":"1941 S 42nd St",
    "sg:city":"Omaha",
    "sg:classifiers":[
        {
            "category":"Shopping",
            "subcategory":"Computers & Home Electronics",
            "type":"Retail Goods"
        }
    ],
    "sg:phone":"+1 402 342 7395",
    "sg:postcode":"68105",
    "sg:province":"NE",
    "sg:tags":[
        "software"
    ],
    "wof:name":"Sansoft Systems",
    "wof:placetype":"venue"
},
  "geometry": {"coordinates":[-95.975739,41.240289],"type":"Point"}
}