{
  "type": "Feature",
  "properties": {
    "iso:country":"US",
    "sg:address":"3062 Arcadia Ave",
    "sg:city":"Omaha",
    "sg:classifiers":[
        {
            "category":"Insurance",
            "subcategory":"Insurance Agent",
            "type":"Services"
        }
    ],
    "sg:phone":"+1 402 330 7372",
    "sg:postcode":"68111",
    "sg:province":"NE",
    "wof:name":"State Farm Insurance",
    "wof:placetype":"venue"
},
  "geometry": {"coordinates":[-95.95819400000001,41.312697],"type":"Point"}
}