{
  "type": "Feature",
  "properties": {
    "iso:country":"US",
    "sg:address":"1122 S 9th St",
    "sg:city":"Beatrice",
    "sg:classifiers":[
        {
            "category":"Retail",
            "subcategory":"Animal Services",
            "type":"Services"
        }
    ],
    "sg:phone":"+1 402 228 1267",
    "sg:postcode":"68310",
    "sg:province":"NE",
    "wof:name":"Petagree Grooming",
    "wof:placetype":"venue"
},
  "geometry": {"coordinates":[-96.74259499999999,40.253563],"type":"Point"}
}