{
  "type": "Feature",
  "properties": {
    "addr:full":"2632 N 84th St Omaha NE 68134",
    "addr:housenumber":"2632",
    "addr:postcode":"68134",
    "addr:street":"N 84Th St",
    "iso:country":"US",
    "sg:address":"2632 N 84th St",
    "sg:city":"Omaha",
    "sg:classifiers":[
        {
            "category":"Retail",
            "subcategory":"Laundry & Dry Cleaning",
            "type":"Services"
        },
        {
            "category":"Building & Trades",
            "subcategory":"Construction",
            "type":"Services"
        }
    ],
    "sg:phone":"+1 402 391 6499",
    "sg:postcode":"68134",
    "sg:province":"NE",
    "sg:tags":[
        "repairing",
        "floor",
        "laying",
        "rug",
        "contractor",
        "carpet"
    ],
    "wof:name":"Peyton's Floor Decor",
    "wof:placetype":"venue"
},
  "geometry": {"coordinates":[-96.043465,41.282047],"type":"Point"}
}