{
  "type": "Feature",
  "properties": {
    "iso:country":"US",
    "sg:address":"801 Broadway St",
    "sg:city":"Imperial",
    "sg:classifiers":[
        {
            "category":"Retail",
            "subcategory":"Repair Shop",
            "type":"Services"
        }
    ],
    "sg:phone":"+1 308 882 7700",
    "sg:postcode":"69033",
    "sg:province":"NE",
    "wof:name":"Rod Fuller Inc",
    "wof:placetype":"venue"
},
  "geometry": {"coordinates":[-101.643109,40.518967],"type":"Point"}
}