{
  "type": "Feature",
  "properties": {
    "iso:country":"US",
    "sg:address":"1825 Saybrook Ln",
    "sg:city":"Lincoln",
    "sg:classifiers":[
        {
            "category":"Real Estate",
            "subcategory":"Real Estate Operator",
            "type":"Services"
        }
    ],
    "sg:phone":"+1 402 421 7521",
    "sg:postcode":"68512",
    "sg:province":"NE",
    "sg:tags":[
        "building",
        "apartment"
    ],
    "wof:name":"JRS Enterprises",
    "wof:placetype":"venue"
},
  "geometry": {"coordinates":[-96.69479800000001,40.753223],"type":"Point"}
}