{
  "type": "Feature",
  "properties": {
    "iso:country":"US",
    "sg:address":"9408 Woodney Cir",
    "sg:city":"Omaha",
    "sg:classifiers":[
        {
            "category":"Farming",
            "subcategory":"Farm & Veterinary Services",
            "type":"Manufacturing & Wholesale Goods"
        },
        {
            "category":"Building & Trades",
            "subcategory":"Landscaping Services",
            "type":"Services"
        }
    ],
    "sg:phone":"+1 402 573 0071",
    "sg:postcode":"68122",
    "sg:province":"NE",
    "sg:tags":[
        "preparation",
        "soil",
        "lawn",
        "maintenance",
        "grounds"
    ],
    "wof:name":"Commercial Seeding Contractors",
    "wof:placetype":"venue"
},
  "geometry": {"coordinates":[-96.059382,41.345971],"type":"Point"}
}