{
  "type": "Feature",
  "properties": {
    "addr:full":"1269 Monona Blvd Jackson NE 68743",
    "addr:housenumber":"1269",
    "addr:postcode":"68743",
    "addr:street":"Monona Blvd",
    "iso:country":"US",
    "sg:address":"1269 Monona Blvd",
    "sg:city":"Jackson",
    "sg:classifiers":[
        {
            "category":"Building & Trades",
            "subcategory":"Construction",
            "type":"Services"
        }
    ],
    "sg:phone":"+1 402 632 4699",
    "sg:postcode":"68743",
    "sg:province":"NE",
    "sg:tags":[
        "house"
    ],
    "wof:name":"Murray White Construction",
    "wof:placetype":"venue"
},
  "geometry": {"coordinates":[-96.58110499999999,42.450857],"type":"Point"}
}