{
  "type": "Feature",
  "properties": {
    "addr:full":"717 N Saddle Creek Rd Omaha NE 68132",
    "addr:housenumber":"717",
    "addr:postcode":"68132",
    "addr:street":"N Saddle Creek Rd",
    "iso:country":"US",
    "sg:address":"717 N Saddle Creek Rd",
    "sg:city":"Omaha",
    "sg:classifiers":[
        {
            "category":"Cinema",
            "subcategory":"Movie Rental",
            "type":"Entertainment"
        }
    ],
    "sg:phone":"+1 402 558 8566",
    "sg:postcode":"68132",
    "sg:province":"NE",
    "sg:tags":[
        "game",
        "video"
    ],
    "wof:name":"Blockbuster Video-Saddle Creek Center",
    "wof:placetype":"venue"
},
  "geometry": {"coordinates":[-95.980904,41.266399],"type":"Point"}
}