{
  "type": "Feature",
  "properties": {
    "addr:full":"1615 N Pebble St Fremont NE 68025",
    "addr:housenumber":"1615",
    "addr:postcode":"68025",
    "addr:street":"N Pebble St",
    "iso:country":"US",
    "sg:address":"1615 N Pebble St",
    "sg:city":"Fremont",
    "sg:classifiers":[
        {
            "category":"Personal",
            "type":"Services"
        }
    ],
    "sg:phone":"+1 402 721 4614",
    "sg:postcode":"68025",
    "sg:province":"NE",
    "sg:tags":[
        "therapist",
        "massage"
    ],
    "wof:name":"Healing Touch",
    "wof:placetype":"venue"
},
  "geometry": {"coordinates":[-96.484933,41.445303],"type":"Point"}
}