{
  "type": "Feature",
  "properties": {
    "addr:full":"748 N 10th Ave Broken Bow NE 68822",
    "addr:housenumber":"748",
    "addr:postcode":"68822",
    "addr:street":"N 10Th Ave",
    "iso:country":"US",
    "sg:address":"748 N 10th Ave",
    "sg:city":"Broken Bow",
    "sg:classifiers":[
        {
            "category":"Organizations",
            "subcategory":"Religious Organization",
            "type":"Services"
        }
    ],
    "sg:phone":"+1 308 872 5972",
    "sg:postcode":"68822",
    "sg:province":"NE",
    "sg:tags":[
        "church"
    ],
    "wof:name":"Church Of The Nazarene",
    "wof:placetype":"venue"
},
  "geometry": {"coordinates":[-99.641604,41.411273],"type":"Point"}
}