{
  "type": "Feature",
  "properties": {
    "iso:country":"US",
    "sg:address":"208 Harris Dr",
    "sg:city":"Norfolk",
    "sg:classifiers":[
        {
            "category":"Health Services",
            "subcategory":"Doctor",
            "type":"Services"
        }
    ],
    "sg:phone":"+1 402 644 4382",
    "sg:postcode":"68701",
    "sg:province":"NE",
    "sg:tags":[
        "medical"
    ],
    "wof:name":"Albin LLC",
    "wof:placetype":"venue"
},
  "geometry": {"coordinates":[-97.435202,42.035886],"type":"Point"}
}