{
  "type": "Feature",
  "properties": {
    "iso:country":"US",
    "sg:address":"313 N Maple St",
    "sg:city":"Gordon",
    "sg:classifiers":[
        {
            "category":"Social Services",
            "subcategory":"Child Care",
            "type":"Services"
        }
    ],
    "sg:phone":"+1 308 282 2512",
    "sg:postcode":"69343",
    "sg:province":"NE",
    "sg:tags":[
        "day"
    ],
    "wof:name":"Shannons Day Care",
    "wof:placetype":"venue"
},
  "geometry": {"coordinates":[-102.207442,42.807644],"type":"Point"}
}