{
  "type": "Feature",
  "properties": {
    "iso:country":"US",
    "sg:address":"4550 S 96th St",
    "sg:city":"Omaha",
    "sg:classifiers":[
        {
            "category":"Autos & Motor Vehicles",
            "subcategory":"Recreational Vehicle Sales",
            "type":"Retail Goods"
        },
        {
            "category":"Wholesale",
            "subcategory":"Motor Vehicles",
            "type":"Manufacturing & Wholesale Goods"
        }
    ],
    "sg:phone":"+1 402 331 4740",
    "sg:postcode":"68127",
    "sg:province":"NE",
    "sg:tags":[
        "parts",
        "truck",
        "trailer"
    ],
    "wof:name":"Mid States Utility Trailer Sls",
    "wof:placetype":"venue"
},
  "geometry": {"coordinates":[-96.062287,41.213294],"type":"Point"}
}