{
  "type": "Feature",
  "properties": {
    "iso:country":"US",
    "sg:address":"4220 Bedford Ave",
    "sg:city":"Omaha",
    "sg:classifiers":[
        {
            "category":"Social Services",
            "subcategory":"Child Care",
            "type":"Services"
        }
    ],
    "sg:phone":"+1 402 451 1550",
    "sg:postcode":"68111",
    "sg:province":"NE",
    "wof:name":"Step By Step Child Care",
    "wof:placetype":"venue"
},
  "geometry": {"coordinates":[-95.977328,41.288756],"type":"Point"}
}