{
  "type": "Feature",
  "properties": {
    "iso:country":"US",
    "sg:address":"1106 Nathan Dr",
    "sg:city":"Wayne",
    "sg:classifiers":[
        {
            "category":"Government",
            "subcategory":"Office",
            "type":"Public Place"
        }
    ],
    "sg:phone":"+1 402 375 3659",
    "sg:postcode":"68787",
    "sg:province":"NE",
    "sg:tags":[
        "housing",
        "program"
    ],
    "wof:name":"Meadow View Estates LP",
    "wof:placetype":"venue"
},
  "geometry": {"coordinates":[-97.031475,42.233661],"type":"Point"}
}