{
  "type": "Feature",
  "properties": {
    "iso:country":"US",
    "sg:address":"6210 N 103rd Ave",
    "sg:city":"Omaha",
    "sg:classifiers":[
        {
            "category":"Travel",
            "subcategory":"Travel Agent",
            "type":"Entertainment"
        }
    ],
    "sg:phone":"+1 402 493 2681",
    "sg:postcode":"68134",
    "sg:province":"NE",
    "sg:tags":[
        "agency"
    ],
    "wof:name":"Sea Plus Travel",
    "wof:placetype":"venue"
},
  "geometry": {"coordinates":[-96.07486400000001,41.315755],"type":"Point"}
}