{
  "type": "Feature",
  "properties": {
    "addr:full":"922 23rd St Columbus NE 68601",
    "addr:housenumber":"922",
    "addr:postcode":"68601",
    "addr:street":"23Rd St",
    "iso:country":"US",
    "sg:address":"922 23rd St",
    "sg:city":"Columbus",
    "sg:classifiers":[
        {
            "category":"Travel",
            "subcategory":"Hotels & Motels",
            "type":"Entertainment"
        }
    ],
    "sg:phone":"+1 402 564 3256",
    "sg:postcode":"68601",
    "sg:province":"NE",
    "wof:name":"Rosebud Motel",
    "wof:placetype":"venue"
},
  "geometry": {"coordinates":[-97.33672199999999,41.438321],"type":"Point"}
}