{
  "type": "Feature",
  "properties": {
    "addr:full":"416 N 76th St Omaha NE 68114",
    "addr:housenumber":"416",
    "addr:postcode":"68114",
    "addr:street":"N 76Th St",
    "iso:country":"US",
    "sg:address":"416 N 76th St",
    "sg:city":"Omaha",
    "sg:classifiers":[
        {
            "category":"Building & Trades",
            "subcategory":"Equipment Rental",
            "type":"Services"
        }
    ],
    "sg:phone":"+1 402 397 6633",
    "sg:postcode":"68114",
    "sg:province":"NE",
    "sg:tags":[
        "appliance"
    ],
    "wof:name":"First State Corp",
    "wof:placetype":"venue"
},
  "geometry": {"coordinates":[-96.03156199999999,41.260453],"type":"Point"}
}