{
  "type": "Feature",
  "properties": {
    "iso:country":"US",
    "sg:address":"719 35 Rd",
    "sg:city":"Hastings",
    "sg:classifiers":[
        {
            "category":"Freight",
            "type":"Transportation"
        }
    ],
    "sg:phone":"+1 402 462 8231",
    "sg:postcode":"68959",
    "sg:province":"NE",
    "sg:tags":[
        "building",
        "house",
        "mover"
    ],
    "wof:name":"Williams Midwest Housemovers",
    "wof:placetype":"venue"
},
  "geometry": {"coordinates":[-98.89434199999999,40.364906],"type":"Point"}
}