{
  "type": "Feature",
  "properties": {
    "iso:country":"US",
    "sg:address":"1321 Central Ave",
    "sg:city":"Nebraska City",
    "sg:classifiers":[
        {
            "category":"Autos & Motor Vehicles",
            "subcategory":"Fuel & Gas Station",
            "type":"Retail Goods"
        }
    ],
    "sg:phone":"+1 402 873 7880",
    "sg:postcode":"68410",
    "sg:province":"NE",
    "sg:tags":[
        "station",
        "gasoline"
    ],
    "wof:name":"Greenwood Farmers Cooperative",
    "wof:placetype":"venue"
},
  "geometry": {"coordinates":[-95.862531,40.676641],"type":"Point"}
}