{
  "type": "Feature",
  "properties": {
    "addr:full":"4812 Woodhaven Dr Lincoln NE 68516",
    "addr:housenumber":"4812",
    "addr:postcode":"68516",
    "addr:street":"Woodhaven Dr",
    "iso:country":"US",
    "sg:address":"4812 Woodhaven Dr",
    "sg:city":"Lincoln",
    "sg:classifiers":[
        {
            "category":"Shopping",
            "subcategory":"Clothing, Apparel, & Fashions",
            "type":"Retail Goods"
        }
    ],
    "sg:phone":"+1 402 486 3645",
    "sg:postcode":"68516",
    "sg:province":"NE",
    "wof:name":"Shaner Dressmaker/Jane",
    "wof:placetype":"venue"
},
  "geometry": {"coordinates":[-96.65114800000001,40.765143],"type":"Point"}
}