{
  "type": "Feature",
  "properties": {
    "iso:country":"US",
    "sg:address":"74511 Rd 436",
    "sg:city":"Smithfield",
    "sg:phone":"+1 308 472 3706",
    "sg:postcode":"68976",
    "sg:province":"NE",
    "sg:tags":[
        "farm",
        "corn"
    ],
    "wof:name":"Stan Deboer",
    "wof:placetype":"venue"
},
  "geometry": {"coordinates":[-99.681155,40.627179],"type":"Point"}
}