{
  "type": "Feature",
  "properties": {
    "iso:country":"US",
    "sg:address":"308 Ogden St",
    "sg:city":"Oxford",
    "sg:classifiers":[
        {
            "category":"Organizations",
            "subcategory":"Religious Organization",
            "type":"Services"
        }
    ],
    "sg:phone":"+1 308 824 3490",
    "sg:postcode":"68967",
    "sg:province":"NE",
    "sg:tags":[
        "church"
    ],
    "wof:name":"Oxford Evangelical Free Church",
    "wof:placetype":"venue"
},
  "geometry": {"coordinates":[-99.63355900000001,40.249421],"type":"Point"}
}