{
  "type": "Feature",
  "properties": {
    "iso:country":"US",
    "sg:address":"309 S Main St",
    "sg:city":"Wilber",
    "sg:classifiers":[
        {
            "category":"Government",
            "subcategory":"Police Station",
            "type":"Public Place"
        }
    ],
    "sg:phone":"+1 402 821 2201",
    "sg:postcode":"68465",
    "sg:province":"NE",
    "sg:tags":[
        "department"
    ],
    "wof:name":"Wilber Police Dept",
    "wof:placetype":"venue"
},
  "geometry": {"coordinates":[-96.96064,40.48127],"type":"Point"}
}