{
  "type": "Feature",
  "properties": {
    "iso:country":"US",
    "sg:address":"1924 Irving St",
    "sg:city":"Beatrice",
    "sg:phone":"+1 402 223 4963",
    "sg:postcode":"68310",
    "sg:province":"NE",
    "sg:tags":[
        "farm",
        "corn"
    ],
    "wof:name":"Gary Jurgens",
    "wof:placetype":"venue"
},
  "geometry": {"coordinates":[-96.725756,40.280074],"type":"Point"}
}