{
  "type": "Feature",
  "properties": {
    "iso:country":"US",
    "sg:address":"324 Reichmuth Rd",
    "sg:city":"Valley",
    "sg:classifiers":[
        {
            "category":"Autos & Motor Vehicles",
            "subcategory":"Automobile Sales",
            "type":"Retail Goods"
        }
    ],
    "sg:phone":"+1 402 359 5339",
    "sg:postcode":"68064",
    "sg:province":"NE",
    "sg:tags":[
        "car",
        "dealer"
    ],
    "wof:name":"Wayne Auto Sales",
    "wof:placetype":"venue"
},
  "geometry": {"coordinates":[-96.345946,41.316796],"type":"Point"}
}