{
  "type": "Feature",
  "properties": {
    "iso:country":"US",
    "sg:address":"12525 Burt St",
    "sg:city":"Omaha",
    "sg:classifiers":[
        {
            "category":"Professional",
            "subcategory":"Management & Consulting",
            "type":"Services"
        }
    ],
    "sg:phone":"+1 402 496 4039",
    "sg:postcode":"68154",
    "sg:province":"NE",
    "sg:tags":[
        "consultant"
    ],
    "wof:name":"Latino Banking Solutions",
    "wof:placetype":"venue"
},
  "geometry": {"coordinates":[-96.110101,41.267104],"type":"Point"}
}