{
  "type": "Feature",
  "properties": {
    "iso:country":"US",
    "sg:address":"201 N Sunset St",
    "sg:city":"Pierce",
    "sg:classifiers":[
        {
            "category":"Education",
            "subcategory":"School",
            "type":"Public Place"
        }
    ],
    "sg:phone":"+1 402 329 4677",
    "sg:postcode":"68767",
    "sg:province":"NE",
    "wof:name":"Pierce School Superintendent",
    "wof:placetype":"venue"
},
  "geometry": {"coordinates":[-97.53842899999999,42.200983],"type":"Point"}
}