{
  "type": "Feature",
  "properties": {
    "iso:country":"US",
    "sg:address":"7120 Humann Ct",
    "sg:city":"Lincoln",
    "sg:classifiers":[
        {
            "category":"Building & Trades",
            "subcategory":"Construction",
            "type":"Services"
        }
    ],
    "sg:phone":"+1 402 484 7434",
    "sg:postcode":"68516",
    "sg:province":"NE",
    "sg:tags":[
        "general",
        "contractor"
    ],
    "wof:name":"A & D Construction Inc",
    "wof:placetype":"venue"
},
  "geometry": {"coordinates":[-96.624101,40.756187],"type":"Point"}
}