{
  "type": "Feature",
  "properties": {
    "addr:full":"506 N Jeffers St North Platte NE 69101",
    "addr:housenumber":"506",
    "addr:postcode":"69101",
    "addr:street":"N Jeffers St",
    "iso:country":"US",
    "sg:address":"506 N Jeffers St",
    "sg:city":"North Platte",
    "sg:classifiers":[
        {
            "category":"Restaurant",
            "type":"Food & Drink"
        }
    ],
    "sg:phone":"+1 308 534 0698",
    "sg:postcode":"69101",
    "sg:province":"NE",
    "wof:name":"Chela's",
    "wof:placetype":"venue"
},
  "geometry": {"coordinates":[-100.762899,41.138459],"type":"Point"}
}