{
  "type": "Feature",
  "properties": {
    "addr:full":"1004 S Cherry St Grand Island NE 68801",
    "addr:housenumber":"1004",
    "addr:postcode":"68801",
    "addr:street":"S Cherry St",
    "iso:country":"US",
    "sg:address":"1004 S Cherry St",
    "sg:city":"Grand Island",
    "sg:classifiers":[
        {
            "category":"Social Services",
            "subcategory":"Child Care",
            "type":"Services"
        }
    ],
    "sg:phone":"+1 308 384 1846",
    "sg:postcode":"68801",
    "sg:province":"NE",
    "sg:tags":[
        "day"
    ],
    "wof:name":"Stacey Sliva Day Care",
    "wof:placetype":"venue"
},
  "geometry": {"coordinates":[-98.324883,40.913411],"type":"Point"}
}