{
  "type": "Feature",
  "properties": {
    "iso:country":"US",
    "sg:address":"7344 Lawndale Dr",
    "sg:city":"Omaha",
    "sg:classifiers":[
        {
            "category":"Building & Trades",
            "subcategory":"Construction",
            "type":"Services"
        }
    ],
    "sg:phone":"+1 402 571 1891",
    "sg:postcode":"68134",
    "sg:province":"NE",
    "sg:tags":[
        "home",
        "roofing",
        "siding",
        "work",
        "improvement"
    ],
    "wof:name":"Jerry Folkers Siding Inc",
    "wof:placetype":"venue"
},
  "geometry": {"coordinates":[-96.026921,41.296332],"type":"Point"}
}