{
  "type": "Feature",
  "properties": {
    "iso:country":"US",
    "sg:address":"13301 S 33rd St",
    "sg:city":"Bellevue",
    "sg:classifiers":[
        {
            "category":"Social Services",
            "subcategory":"Child Care",
            "type":"Services"
        }
    ],
    "sg:phone":"+1 402 291 2574",
    "sg:postcode":"68123",
    "sg:province":"NE",
    "sg:tags":[
        "day"
    ],
    "wof:name":"Little Angels Home Daycare",
    "wof:placetype":"venue"
},
  "geometry": {"coordinates":[-95.96150299999999,41.112683],"type":"Point"}
}