{
  "type": "Feature",
  "properties": {
    "addr:full":"522 Maple St Hickman NE 68372",
    "addr:housenumber":"522",
    "addr:postcode":"68372",
    "addr:street":"Maple St",
    "iso:country":"US",
    "sg:address":"522 Maple St",
    "sg:city":"Hickman",
    "sg:classifiers":[
        {
            "category":"Freight",
            "type":"Transportation"
        }
    ],
    "sg:phone":"+1 402 792 2218",
    "sg:postcode":"68372",
    "sg:province":"NE",
    "sg:tags":[
        "local",
        "storage",
        "trucking"
    ],
    "wof:name":"Mike Verbeek Trucking",
    "wof:placetype":"venue"
},
  "geometry": {"coordinates":[-96.635098,40.623876],"type":"Point"}
}