{
  "type": "Feature",
  "properties": {
    "iso:country":"US",
    "sg:address":"652 Main St",
    "sg:city":"Arapahoe",
    "sg:classifiers":[
        {
            "category":"Recreation",
            "type":"Entertainment"
        }
    ],
    "sg:phone":"+1 308 962 7831",
    "sg:postcode":"68922",
    "sg:province":"NE",
    "sg:tags":[
        "hall",
        "auditorium"
    ],
    "wof:name":"Masonic Lodge Hall",
    "wof:placetype":"venue"
},
  "geometry": {"coordinates":[-99.89711,40.302179],"type":"Point"}
}