{
  "type": "Feature",
  "properties": {
    "iso:country":"US",
    "sg:address":"311 W Main St",
    "sg:city":"Cedar Rapids",
    "sg:classifiers":[
        {
            "category":"Freight",
            "type":"Transportation"
        }
    ],
    "sg:phone":"+1 308 358 0740",
    "sg:postcode":"68627",
    "sg:province":"NE",
    "sg:tags":[
        "frozen",
        "food",
        "locker",
        "plant"
    ],
    "wof:name":"Cedar Locker & Processing Plnt",
    "wof:placetype":"venue"
},
  "geometry": {"coordinates":[-98.147597,41.559894],"type":"Point"}
}