{
  "type": "Feature",
  "properties": {
    "addr:full":"201 Winters Ave Glenvil NE 68941",
    "addr:housenumber":"201",
    "addr:postcode":"68941",
    "addr:street":"Winters Ave",
    "iso:country":"US",
    "sg:address":"201 Winters Ave",
    "sg:city":"Glenvil",
    "sg:classifiers":[
        {
            "category":"Government",
            "subcategory":"Office",
            "type":"Public Place"
        }
    ],
    "sg:phone":"+1 402 771 2525",
    "sg:postcode":"68941",
    "sg:province":"NE",
    "sg:tags":[
        "village"
    ],
    "wof:name":"Glenvil Village Marshall",
    "wof:placetype":"venue"
},
  "geometry": {"coordinates":[-98.25306999999999,40.504224],"type":"Point"}
}