{
  "type": "Feature",
  "properties": {
    "iso:country":"US",
    "sg:address":"41968 State Hwy 2",
    "sg:city":"Ravenna",
    "sg:classifiers":[
        {
            "category":"Wholesale",
            "subcategory":"Machinery & Supplies",
            "type":"Manufacturing & Wholesale Goods"
        }
    ],
    "sg:phone":"+1 308 452 3007",
    "sg:postcode":"68869",
    "sg:province":"NE",
    "sg:tags":[
        "equipment",
        "irrigation",
        "system"
    ],
    "wof:name":"Aim Inc",
    "wof:placetype":"venue"
},
  "geometry": {"coordinates":[-98.919481,41.01791],"type":"Point"}
}