{
  "type": "Feature",
  "properties": {
    "iso:country":"US",
    "sg:address":"119 N Main St",
    "sg:city":"Coleridge",
    "sg:classifiers":[
        {
            "category":"Government",
            "subcategory":"Fire Station",
            "type":"Public Place"
        }
    ],
    "sg:phone":"+1 402 283 4218",
    "sg:postcode":"68727",
    "sg:province":"NE",
    "sg:tags":[
        "department"
    ],
    "wof:name":"Coleridge Fire Hall",
    "wof:placetype":"venue"
},
  "geometry": {"coordinates":[-97.203791,42.506578],"type":"Point"}
}