{
  "type": "Feature",
  "properties": {
    "iso:country":"US",
    "sg:address":"7000 Husker Cir",
    "sg:city":"Lincoln",
    "sg:classifiers":[
        {
            "category":"Restaurant",
            "type":"Food & Drink"
        }
    ],
    "sg:menulink":"http://www.allmenus.com/ne/lincoln/158934-arbys/menu/",
    "sg:phone":"+1 402 476 1007",
    "sg:postcode":"68504",
    "sg:province":"NE",
    "sg:tags":[
        "burger",
        "american"
    ],
    "wof:name":"Arby's",
    "wof:placetype":"venue"
},
  "geometry": {"coordinates":[-96.67998900000001,40.882862],"type":"Point"}
}