{
  "type": "Feature",
  "properties": {
    "iso:country":"US",
    "sg:address":"3570 Farnam St",
    "sg:city":"Omaha",
    "sg:classifiers":[
        {
            "category":"Professional",
            "subcategory":"Business Services",
            "type":"Services"
        }
    ],
    "sg:phone":"+1 402 348 0646",
    "sg:postcode":"68131",
    "sg:province":"NE",
    "wof:name":"Anacomp Inc",
    "wof:placetype":"venue"
},
  "geometry": {"coordinates":[-95.96557300000001,41.257804],"type":"Point"}
}