{
  "type": "Feature",
  "properties": {
    "addr:full":"14201 Lisa St Omaha NE 68138",
    "addr:housenumber":"14201",
    "addr:postcode":"68138",
    "addr:street":"Lisa St",
    "iso:country":"US",
    "sg:address":"14201 Lisa St",
    "sg:city":"Omaha",
    "sg:classifiers":[
        {
            "category":"Restaurant",
            "type":"Food & Drink"
        }
    ],
    "sg:phone":"+1 402 895 2952",
    "sg:postcode":"68138",
    "sg:province":"NE",
    "sg:tags":[
        "caterer"
    ],
    "wof:name":"Adventures In Catering",
    "wof:placetype":"venue"
},
  "geometry": {"coordinates":[-96.13498800000001,41.174439],"type":"Point"}
}