{
  "type": "Feature",
  "properties": {
    "iso:country":"US",
    "sg:address":"11 Annin St",
    "sg:city":"Crawford",
    "sg:classifiers":[
        {
            "category":"Farming",
            "subcategory":"Livestock Farm",
            "type":"Manufacturing & Wholesale Goods"
        }
    ],
    "sg:phone":"+1 308 665 1286",
    "sg:postcode":"69339",
    "sg:province":"NE",
    "sg:tags":[
        "beef",
        "feedlot",
        "cattle"
    ],
    "wof:name":"Leeling Feedlot",
    "wof:placetype":"venue"
},
  "geometry": {"coordinates":[-103.41636699999999,42.682954],"type":"Point"}
}