{
  "type": "Feature",
  "properties": {
    "iso:country":"US",
    "sg:address":"2216 11th St",
    "sg:city":"Columbus",
    "sg:classifiers":[
        {
            "category":"Wholesale",
            "subcategory":"Farm Supplies",
            "type":"Manufacturing & Wholesale Goods"
        }
    ],
    "sg:phone":"+1 402 564 8104",
    "sg:postcode":"68601",
    "sg:province":"NE",
    "sg:tags":[
        "underwear",
        "knit",
        "mill"
    ],
    "wof:name":"Columbus Feed & Hatchery",
    "wof:placetype":"venue"
},
  "geometry": {"coordinates":[-97.355558,41.427297],"type":"Point"}
}