{
  "type": "Feature",
  "properties": {
    "iso:country":"US",
    "sg:address":"11306 Z St",
    "sg:city":"Omaha",
    "sg:classifiers":[
        {
            "category":"Wholesale",
            "subcategory":"Electrical",
            "type":"Manufacturing & Wholesale Goods"
        },
        {
            "category":"Wholesale",
            "subcategory":"Durable Goods & Equipment",
            "type":"Manufacturing & Wholesale Goods"
        }
    ],
    "sg:phone":"+1 402 597 0207",
    "sg:postcode":"68137",
    "sg:province":"NE",
    "sg:tags":[
        "control",
        "professional",
        "security",
        "system"
    ],
    "wof:name":"Mid America Security Inc",
    "wof:placetype":"venue"
},
  "geometry": {"coordinates":[-96.090484,41.196931],"type":"Point"}
}