{
  "type": "Feature",
  "properties": {
    "iso:country":"US",
    "sg:address":"202 S Linden St",
    "sg:city":"Wahoo",
    "sg:classifiers":[
        {
            "category":"Education",
            "subcategory":"School",
            "type":"Public Place"
        }
    ],
    "sg:phone":"+1 402 443 4151",
    "sg:postcode":"68066",
    "sg:province":"NE",
    "wof:name":"Bishop Neumann Centl High Schl",
    "wof:placetype":"venue"
},
  "geometry": {"coordinates":[-96.61868,41.205099],"type":"Point"}
}