{
  "type": "Feature",
  "properties": {
    "addr:full":"4212 S 50th St Omaha NE 68117",
    "addr:housenumber":"4212",
    "addr:postcode":"68117",
    "addr:street":"S 50Th St",
    "iso:country":"US",
    "sg:address":"4212 S 50th St",
    "sg:city":"Omaha",
    "sg:classifiers":[
        {
            "category":"Restaurant",
            "type":"Food & Drink"
        }
    ],
    "sg:menulink":"http://www.allmenus.com/ne/omaha/77568-papa-murphys/menu/",
    "sg:phone":"+1 402 731 7272",
    "sg:postcode":"68117",
    "sg:province":"NE",
    "sg:tags":[
        "american",
        "pizza"
    ],
    "wof:name":"Papa Murphy's",
    "wof:placetype":"venue"
},
  "geometry": {"coordinates":[-95.99046199999999,41.217312],"type":"Point"}
}