{
  "type": "Feature",
  "properties": {
    "addr:full":"2105 Avenue E Kearney NE 68847",
    "addr:housenumber":"2105",
    "addr:postcode":"68847",
    "addr:street":"Avenue E",
    "iso:country":"US",
    "sg:address":"2105 Avenue E",
    "sg:city":"Kearney",
    "sg:classifiers":[
        {
            "category":"Wholesale",
            "subcategory":"Hardware",
            "type":"Manufacturing & Wholesale Goods"
        }
    ],
    "sg:phone":"+1 308 236 8811",
    "sg:postcode":"68847",
    "sg:province":"NE",
    "sg:tags":[
        "fastener"
    ],
    "wof:name":"Centaur Enterprises Inc",
    "wof:placetype":"venue"
},
  "geometry": {"coordinates":[-99.074788,40.697479],"type":"Point"}
}