{
  "type": "Feature",
  "properties": {
    "addr:full":"4924 Evans St Omaha NE 68104",
    "addr:housenumber":"4924",
    "addr:postcode":"68104",
    "addr:street":"Evans St",
    "iso:country":"US",
    "sg:address":"4924 Evans St",
    "sg:city":"Omaha",
    "sg:classifiers":[
        {
            "category":"Social Services",
            "subcategory":"Child Care",
            "type":"Services"
        }
    ],
    "sg:phone":"+1 402 451 3042",
    "sg:postcode":"68104",
    "sg:province":"NE",
    "sg:tags":[
        "day"
    ],
    "wof:name":"Childrens Place Child Care",
    "wof:placetype":"venue"
},
  "geometry": {"coordinates":[-95.98980899999999,41.291492],"type":"Point"}
}