{
  "type": "Feature",
  "properties": {
    "iso:country":"US",
    "sg:address":"345 W Church St",
    "sg:city":"Albion",
    "sg:classifiers":[
        {
            "category":"Shopping",
            "subcategory":"Discount & Variety Stores",
            "type":"Retail Goods"
        }
    ],
    "sg:phone":"+1 402 395 2068",
    "sg:postcode":"68620",
    "sg:province":"NE",
    "wof:name":"Dollar General",
    "wof:placetype":"venue"
},
  "geometry": {"coordinates":[-97.999972,41.691784],"type":"Point"}
}