{
  "type": "Feature",
  "properties": {
    "iso:country":"US",
    "sg:address":"1730 Illinois St",
    "sg:city":"Sidney",
    "sg:classifiers":[
        {
            "category":"Autos & Motor Vehicles",
            "subcategory":"Fuel & Gas Station",
            "type":"Retail Goods"
        },
        {
            "category":"Retail",
            "subcategory":"Auto Repair",
            "type":"Services"
        }
    ],
    "sg:phone":"+1 308 254 2301",
    "sg:postcode":"69162",
    "sg:province":"NE",
    "sg:tags":[
        "repairing",
        "automobile",
        "station"
    ],
    "wof:name":"Sidney 66 Oil Inc",
    "wof:placetype":"venue"
},
  "geometry": {"coordinates":[-102.986452,41.144653],"type":"Point"}
}