{
  "type": "Feature",
  "properties": {
    "iso:country":"US",
    "sg:address":"123 S 6th St",
    "sg:city":"Plattsmouth",
    "sg:classifiers":[
        {
            "category":"Government",
            "subcategory":"Office",
            "type":"Public Place"
        }
    ],
    "sg:phone":"+1 402 296 3375",
    "sg:postcode":"68048",
    "sg:province":"NE",
    "sg:tags":[
        "executive"
    ],
    "wof:name":"Cass County Public Defender",
    "wof:placetype":"venue"
},
  "geometry": {"coordinates":[-95.886174,41.010884],"type":"Point"}
}