{
  "type": "Feature",
  "properties": {
    "iso:country":"US",
    "sg:address":"5945 R St",
    "sg:city":"Lincoln",
    "sg:classifiers":[
        {
            "category":"Professional",
            "subcategory":"Business Services",
            "type":"Services"
        },
        {
            "category":"Government",
            "subcategory":"Post Office",
            "type":"Public Place"
        }
    ],
    "sg:phone":"+1 800 275 8777",
    "sg:postcode":"68505",
    "sg:province":"NE",
    "sg:tags":[
        "mail",
        "shipping"
    ],
    "sg:website":"http://www.usps.com",
    "wof:name":"USPS - United States Post Office - Gateway Station",
    "wof:placetype":"venue"
},
  "geometry": {"coordinates":[-96.640344,40.816973],"type":"Point"}
}