{
  "type": "Feature",
  "properties": {
    "addr:full":"3205 Fontenelle Blvd Omaha NE 68104",
    "addr:housenumber":"3205",
    "addr:postcode":"68104",
    "addr:street":"Fontenelle Blvd",
    "iso:country":"US",
    "sg:address":"3205 Fontenelle Blvd",
    "sg:city":"Omaha",
    "sg:classifiers":[
        {
            "category":"Building & Trades",
            "subcategory":"Construction",
            "type":"Services"
        }
    ],
    "sg:phone":"+1 402 453 3701",
    "sg:postcode":"68104",
    "sg:province":"NE",
    "sg:tags":[
        "carpentry",
        "contractor"
    ],
    "wof:name":"Tyronne Miller",
    "wof:placetype":"venue"
},
  "geometry": {"coordinates":[-95.982957,41.288648],"type":"Point"}
}