{
  "type": "Feature",
  "properties": {
    "iso:country":"US",
    "sg:address":"668 N 114th St",
    "sg:city":"Omaha",
    "sg:classifiers":[
        {
            "category":"Restaurant",
            "type":"Food & Drink"
        }
    ],
    "sg:phone":"+1 402 496 3981",
    "sg:postcode":"68154",
    "sg:province":"NE",
    "sg:tags":[
        "eating"
    ],
    "wof:name":"TCBY",
    "wof:placetype":"venue"
},
  "geometry": {"coordinates":[-96.09105,41.26514],"type":"Point"}
}