{
  "type": "Feature",
  "properties": {
    "iso:country":"US",
    "sg:address":"4600 Birch Creek Dr",
    "sg:city":"Lincoln",
    "sg:classifiers":[
        {
            "category":"Building & Trades",
            "subcategory":"Construction",
            "type":"Services"
        }
    ],
    "sg:phone":"+1 402 420 1621",
    "sg:postcode":"68516",
    "sg:province":"NE",
    "sg:tags":[
        "concrete",
        "contractor"
    ],
    "wof:name":"David R & Sandra Wolfe",
    "wof:placetype":"venue"
},
  "geometry": {"coordinates":[-96.654838,40.736429],"type":"Point"}
}