{
  "type": "Feature",
  "properties": {
    "addr:full":"1942 Co Rd 18 Dodge NE 68633",
    "addr:housenumber":"1942;18",
    "addr:postcode":"68633",
    "addr:street":"Co Rd",
    "iso:country":"US",
    "sg:address":"1942 Co Rd 18",
    "sg:city":"Dodge",
    "sg:phone":"+1 402 693 2391",
    "sg:postcode":"68633",
    "sg:province":"NE",
    "sg:tags":[
        "soybean",
        "farm",
        "corn",
        "crop",
        "general",
        "animal"
    ],
    "wof:name":"David Semerad",
    "wof:placetype":"venue"
},
  "geometry": {"coordinates":[-96.92532,41.664515],"type":"Point"}
}