{
  "type": "Feature",
  "properties": {
    "addr:full":"6616 Old Dominion Rd Lincoln NE 68516",
    "addr:housenumber":"6616",
    "addr:postcode":"68516",
    "addr:street":"Old Dominion Rd",
    "iso:country":"US",
    "sg:address":"6616 Old Dominion Rd",
    "sg:city":"Lincoln",
    "sg:classifiers":[
        {
            "category":"Building & Trades",
            "subcategory":"Construction",
            "type":"Services"
        }
    ],
    "sg:phone":"+1 402 432 2163",
    "sg:postcode":"68516",
    "sg:province":"NE",
    "sg:tags":[
        "hanging",
        "contractor"
    ],
    "wof:name":"Marbllous Dcrtive Pntg By Mria",
    "wof:placetype":"venue"
},
  "geometry": {"coordinates":[-96.666842,40.745253],"type":"Point"}
}