{
  "type": "Feature",
  "properties": {
    "iso:country":"US",
    "sg:address":"509 W 9th St",
    "sg:city":"Minden",
    "sg:classifiers":[
        {
            "category":"Building & Trades",
            "subcategory":"Construction",
            "type":"Services"
        }
    ],
    "sg:phone":"+1 308 832 1284",
    "sg:postcode":"68959",
    "sg:province":"NE",
    "sg:tags":[
        "road",
        "contractor"
    ],
    "wof:name":"Roads Dept",
    "wof:placetype":"venue"
},
  "geometry": {"coordinates":[-98.95674699999999,40.502855],"type":"Point"}
}