{
  "type": "Feature",
  "properties": {
    "addr:full":"314 W 2nd St Valparaiso NE 68065",
    "addr:housenumber":"314",
    "addr:postcode":"68065",
    "addr:street":"W 2Nd St",
    "iso:country":"US",
    "sg:address":"314 W 2nd St",
    "sg:city":"Valparaiso",
    "sg:classifiers":[
        {
            "category":"Food & Beverages",
            "subcategory":"Groceries & Convenience Stores",
            "type":"Retail Goods"
        }
    ],
    "sg:phone":"+1 402 784 3501",
    "sg:postcode":"68065",
    "sg:province":"NE",
    "sg:tags":[
        "grocer"
    ],
    "wof:name":"Val Market",
    "wof:placetype":"venue"
},
  "geometry": {"coordinates":[-96.834373,41.081488],"type":"Point"}
}