{
  "type": "Feature",
  "properties": {
    "addr:full":"13824 Manderson Cir Omaha NE 68164",
    "addr:housenumber":"13824",
    "addr:postcode":"68164",
    "addr:street":"Manderson Cir",
    "iso:country":"US",
    "sg:address":"13824 Manderson Cir",
    "sg:city":"Omaha",
    "sg:classifiers":[
        {
            "category":"Personal",
            "subcategory":"Tanning Parlor",
            "type":"Services"
        },
        {
            "category":"Personal",
            "type":"Services"
        }
    ],
    "sg:phone":"+1 402 431 0504",
    "sg:postcode":"68164",
    "sg:province":"NE",
    "sg:tags":[
        "salon",
        "massage"
    ],
    "wof:name":"Soleil Tanning Salons Inc",
    "wof:placetype":"venue"
},
  "geometry": {"coordinates":[-96.12935,41.293163],"type":"Point"}
}