{
  "type": "Feature",
  "properties": {
    "addr:full":"222 Water St Brownville NE 68321",
    "addr:housenumber":"222",
    "addr:postcode":"68321",
    "addr:street":"Water St",
    "iso:country":"US",
    "sg:address":"222 Water St",
    "sg:city":"Brownville",
    "sg:classifiers":[
        {
            "category":"Cinema",
            "subcategory":"Movie Theater",
            "type":"Entertainment"
        }
    ],
    "sg:phone":"+1 402 825 4121",
    "sg:postcode":"68321",
    "sg:province":"NE",
    "wof:name":"Brownville Village Theatre",
    "wof:placetype":"venue"
},
  "geometry": {"coordinates":[-95.658237,40.396465],"type":"Point"}
}