{
  "type": "Feature",
  "properties": {
    "addr:full":"4407 1st Ave Pl Kearney NE 68847",
    "addr:housenumber":"4407",
    "addr:postcode":"68847",
    "addr:street":"1St Ave Pl",
    "iso:country":"US",
    "sg:address":"4407 1st Ave Pl",
    "sg:city":"Kearney",
    "sg:classifiers":[
        {
            "category":"Building & Trades",
            "subcategory":"Construction",
            "type":"Services"
        }
    ],
    "sg:phone":"+1 308 234 2421",
    "sg:postcode":"68847",
    "sg:province":"NE",
    "sg:tags":[
        "general",
        "contractor"
    ],
    "wof:name":"Central Contracting Corp",
    "wof:placetype":"venue"
},
  "geometry": {"coordinates":[-99.082649,40.717791],"type":"Point"}
}