{
  "type": "Feature",
  "properties": {
    "iso:country":"US",
    "sg:address":"1600 E 2nd St",
    "sg:city":"North Platte",
    "sg:classifiers":[
        {
            "category":"Organizations",
            "subcategory":"Religious Organization",
            "type":"Services"
        }
    ],
    "sg:phone":"+1 308 532 1355",
    "sg:postcode":"69101",
    "sg:province":"NE",
    "sg:tags":[
        "church"
    ],
    "wof:name":"Riverside Baptist Church",
    "wof:placetype":"venue"
},
  "geometry": {"coordinates":[-100.745311,41.132154],"type":"Point"}
}