{
  "type": "Feature",
  "properties": {
    "iso:country":"US",
    "sg:address":"1412 Prospect St",
    "sg:city":"Blair",
    "sg:classifiers":[
        {
            "category":"Building & Trades",
            "subcategory":"Construction",
            "type":"Services"
        }
    ],
    "sg:phone":"+1 402 426 3483",
    "sg:postcode":"68008",
    "sg:province":"NE",
    "sg:tags":[
        "general",
        "contractor"
    ],
    "wof:name":"Lloyd D Peterson Contractor",
    "wof:placetype":"venue"
},
  "geometry": {"coordinates":[-96.131973,41.535096],"type":"Point"}
}