{
  "type": "Feature",
  "properties": {
    "addr:full":"10731 J St Omaha NE 68127",
    "addr:housenumber":"10731",
    "addr:postcode":"68127",
    "addr:street":"J St",
    "iso:country":"US",
    "sg:address":"10731 J St",
    "sg:city":"Omaha",
    "sg:classifiers":[
        {
            "category":"Travel",
            "subcategory":"Hotels & Motels",
            "type":"Entertainment"
        }
    ],
    "sg:phone":"+1 402 331 5531",
    "sg:postcode":"68127",
    "sg:province":"NE",
    "sg:tags":[
        "administrative"
    ],
    "wof:name":"Hampton Inn",
    "wof:placetype":"venue"
},
  "geometry": {"coordinates":[-96.07488499999999,41.214138],"type":"Point"}
}