{
  "type": "Feature",
  "properties": {
    "addr:full":"908 State Hwy 14 Aurora NE 68818",
    "addr:housenumber":"908",
    "addr:postcode":"68818",
    "addr:street":"State Hwy 14",
    "iso:country":"US",
    "sg:address":"908 State Hwy 14",
    "sg:city":"Aurora",
    "sg:classifiers":[
        {
            "category":"Manufacturing",
            "subcategory":"Signs",
            "type":"Manufacturing & Wholesale Goods"
        }
    ],
    "sg:phone":"+1 402 694 3340",
    "sg:postcode":"68818",
    "sg:province":"NE",
    "wof:name":"Sign Designs",
    "wof:placetype":"venue"
},
  "geometry": {"coordinates":[-97.99696900000001,40.816714],"type":"Point"}
}