{
  "type": "Feature",
  "properties": {
    "addr:full":"502 S W Rd Aurora NE 68818",
    "addr:housenumber":"502",
    "addr:postcode":"68818",
    "addr:street":"S W Rd",
    "iso:country":"US",
    "sg:address":"502 S W Rd",
    "sg:city":"Aurora",
    "sg:phone":"+1 402 723 4234",
    "sg:postcode":"68818",
    "sg:province":"NE",
    "sg:tags":[
        "farm",
        "corn"
    ],
    "wof:name":"Bryan Goertzen",
    "wof:placetype":"venue"
},
  "geometry": {"coordinates":[-97.882884,40.75898],"type":"Point"}
}