{
  "type": "Feature",
  "properties": {
    "iso:country":"US",
    "sg:address":"321 Lessman St",
    "sg:city":"Dalton",
    "sg:classifiers":[
        {
            "category":"Utilities",
            "subcategory":"Telephone",
            "type":"Services"
        }
    ],
    "sg:phone":"+1 308 377 2311",
    "sg:postcode":"69131",
    "sg:province":"NE",
    "sg:tags":[
        "company"
    ],
    "wof:name":"Dalton Telephone Co",
    "wof:placetype":"venue"
},
  "geometry": {"coordinates":[-102.967482,41.408874],"type":"Point"}
}