{
  "type": "Feature",
  "properties": {
    "iso:country":"US",
    "sg:address":"1802 Cherokee Ln",
    "sg:city":"Broken Bow",
    "sg:classifiers":[
        {
            "category":"Social Services",
            "subcategory":"Child Care",
            "type":"Services"
        }
    ],
    "sg:phone":"+1 308 872 5816",
    "sg:postcode":"68822",
    "sg:province":"NE",
    "sg:tags":[
        "day"
    ],
    "wof:name":"Bartram Marta Day Care",
    "wof:placetype":"venue"
},
  "geometry": {"coordinates":[-99.65096800000001,41.410821],"type":"Point"}
}