{
  "type": "Feature",
  "properties": {
    "addr:full":"12909 Laurel Ave Omaha NE 68164",
    "addr:housenumber":"12909",
    "addr:postcode":"68164",
    "addr:street":"Laurel Ave",
    "iso:country":"US",
    "sg:address":"12909 Laurel Ave",
    "sg:city":"Omaha",
    "sg:classifiers":[
        {
            "category":"Utilities",
            "subcategory":"Telephone",
            "type":"Services"
        }
    ],
    "sg:phone":"+1 402 452 2604",
    "sg:postcode":"68164",
    "sg:province":"NE",
    "sg:tags":[
        "communication",
        "datum"
    ],
    "sg:website":"www.dtn.com",
    "wof:name":"DATA Transmission Network",
    "wof:placetype":"venue"
},
  "geometry": {"coordinates":[-96.11873,41.312584],"type":"Point"}
}