{
  "type": "Feature",
  "properties": {
    "addr:full":"5312 Miller Ave Omaha NE 68127",
    "addr:housenumber":"5312",
    "addr:postcode":"68127",
    "addr:street":"Miller Ave",
    "iso:country":"US",
    "sg:address":"5312 Miller Ave",
    "sg:city":"Omaha",
    "sg:classifiers":[
        {
            "category":"Professional",
            "subcategory":"Management & Consulting",
            "type":"Services"
        }
    ],
    "sg:phone":"+1 402 592 9549",
    "sg:postcode":"68127",
    "sg:province":"NE",
    "wof:name":"Business Management Solutions",
    "wof:placetype":"venue"
},
  "geometry": {"coordinates":[-96.03327899999999,41.20327],"type":"Point"}
}