{
  "type": "Feature",
  "properties": {
    "addr:full":"1815 Montini Dr Lincoln NE 68521",
    "addr:housenumber":"1815",
    "addr:postcode":"68521",
    "addr:street":"Montini Dr",
    "iso:country":"US",
    "sg:address":"1815 Montini Dr",
    "sg:city":"Lincoln",
    "sg:classifiers":[
        {
            "category":"Professional",
            "type":"Services"
        }
    ],
    "sg:phone":"+1 402 435 8226",
    "sg:postcode":"68521",
    "sg:province":"NE",
    "sg:tags":[
        "establishment"
    ],
    "wof:name":"Paul Vi Heights",
    "wof:placetype":"venue"
},
  "geometry": {"coordinates":[-96.694276,40.855999],"type":"Point"}
}