{
  "type": "Feature",
  "properties": {
    "iso:country":"US",
    "sg:address":"5540 O St",
    "sg:city":"Lincoln",
    "sg:classifiers":[
        {
            "category":"Restaurant",
            "type":"Food & Drink"
        }
    ],
    "sg:menulink":"http://www.allmenus.com/ne/lincoln/158936-arbys/menu/",
    "sg:phone":"+1 402 467 3300",
    "sg:postcode":"68510",
    "sg:province":"NE",
    "sg:tags":[
        "burger",
        "american"
    ],
    "wof:name":"Arby's",
    "wof:placetype":"venue"
},
  "geometry": {"coordinates":[-96.644648,40.81375],"type":"Point"}
}