{
  "type": "Feature",
  "properties": {
    "iso:country":"US",
    "sg:address":"117 S 25th St",
    "sg:city":"Omaha",
    "sg:classifiers":[
        {
            "category":"Wholesale",
            "subcategory":"Medical Equipment & Supplies",
            "type":"Manufacturing & Wholesale Goods"
        },
        {
            "category":"Shopping",
            "subcategory":"Pharmacy",
            "type":"Retail Goods"
        }
    ],
    "sg:phone":"+1 402 344 4200",
    "sg:postcode":"68131",
    "sg:province":"NE",
    "sg:tags":[
        "laboratory",
        "care",
        "health",
        "home"
    ],
    "wof:name":"Primus Sterilizer Co",
    "wof:placetype":"venue"
},
  "geometry": {"coordinates":[-95.94823100000001,41.25961],"type":"Point"}
}