{
  "type": "Feature",
  "properties": {
    "iso:country":"US",
    "sg:address":"3734 S 13th St",
    "sg:city":"Omaha",
    "sg:classifiers":[
        {
            "category":"Organizations",
            "subcategory":"Religious Organization",
            "type":"Services"
        }
    ],
    "sg:phone":"+1 402 733 3383",
    "sg:postcode":"68107",
    "sg:province":"NE",
    "sg:tags":[
        "church"
    ],
    "wof:name":"Korean Presbyterian Church",
    "wof:placetype":"venue"
},
  "geometry": {"coordinates":[-95.933409,41.224788],"type":"Point"}
}