{
  "type": "Feature",
  "properties": {
    "addr:full":"3007 S 83rd Plz Omaha NE 68124",
    "addr:housenumber":"3007",
    "addr:postcode":"68124",
    "addr:street":"S 83Rd",
    "iso:country":"US",
    "sg:address":"3007 S 83rd Plz",
    "sg:city":"Omaha",
    "sg:classifiers":[
        {
            "category":"Restaurant",
            "type":"Food & Drink"
        }
    ],
    "sg:phone":"+1 402 391 2923",
    "sg:postcode":"68124",
    "sg:province":"NE",
    "sg:website":"http://www.hectorsomaha.com",
    "wof:name":"Hector's",
    "wof:placetype":"venue"
},
  "geometry": {"coordinates":[-96.041977,41.231772],"type":"Point"}
}