{
  "type": "Feature",
  "properties": {
    "addr:full":"5300 Fairdale Rd Lincoln NE 68510",
    "addr:housenumber":"5300",
    "addr:postcode":"68510",
    "addr:street":"Fairdale Rd",
    "iso:country":"US",
    "sg:address":"5300 Fairdale Rd",
    "sg:city":"Lincoln",
    "sg:classifiers":[
        {
            "category":"Professional",
            "subcategory":"Management & Consulting",
            "type":"Services"
        }
    ],
    "sg:phone":"+1 402 488 0578",
    "sg:postcode":"68510",
    "sg:province":"NE",
    "sg:tags":[
        "business"
    ],
    "wof:name":"Future Leadership",
    "wof:placetype":"venue"
},
  "geometry": {"coordinates":[-96.64612700000001,40.805554],"type":"Point"}
}