{
  "type": "Feature",
  "properties": {
    "iso:country":"US",
    "sg:address":"178 Airport Rd",
    "sg:city":"Ogallala",
    "sg:classifiers":[
        {
            "category":"Communications",
            "subcategory":"Radio Station",
            "type":"Services"
        }
    ],
    "sg:phone":"+1 308 284 4935",
    "sg:postcode":"69153",
    "sg:province":"NE",
    "sg:tags":[
        "company",
        "broadcasting"
    ],
    "wof:name":"Clear Channel",
    "wof:placetype":"venue"
},
  "geometry": {"coordinates":[-101.761268,41.119952],"type":"Point"}
}