{
  "type": "Feature",
  "properties": {
    "addr:full":"3007 V St Omaha NE 68107",
    "addr:housenumber":"3007",
    "addr:postcode":"68107",
    "addr:street":"V St",
    "iso:country":"US",
    "sg:address":"3007 V St",
    "sg:city":"Omaha",
    "sg:classifiers":[
        {
            "category":"Shopping",
            "subcategory":"Department Store",
            "type":"Retail Goods"
        }
    ],
    "sg:phone":"+1 402 734 3683",
    "sg:postcode":"68107",
    "sg:province":"NE",
    "sg:tags":[
        "discount"
    ],
    "wof:name":"Darrell Greenamyer",
    "wof:placetype":"venue"
},
  "geometry": {"coordinates":[-95.95931899999999,41.200571],"type":"Point"}
}