{
  "type": "Feature",
  "properties": {
    "addr:full":"700 S 89th St Omaha NE 68114",
    "addr:housenumber":"700",
    "addr:postcode":"68114",
    "addr:street":"S 89Th St",
    "iso:country":"US",
    "sg:address":"700 S 89th St",
    "sg:city":"Omaha",
    "sg:classifiers":[
        {
            "category":"Building & Trades",
            "subcategory":"Construction",
            "type":"Services"
        }
    ],
    "sg:phone":"+1 402 455 7000",
    "sg:postcode":"68114",
    "sg:province":"NE",
    "sg:tags":[
        "painter"
    ],
    "wof:name":"Reputable Services Inc",
    "wof:placetype":"venue"
},
  "geometry": {"coordinates":[-96.05125099999999,41.250343],"type":"Point"}
}