{
  "type": "Feature",
  "properties": {
    "iso:country":"US",
    "sg:address":"3600 W Agnew Rd",
    "sg:city":"Valparaiso",
    "sg:phone":"+1 402 783 3301",
    "sg:postcode":"68065",
    "sg:province":"NE",
    "sg:tags":[
        "farm",
        "field",
        "crop"
    ],
    "wof:name":"Michael Kane",
    "wof:placetype":"venue"
},
  "geometry": {"coordinates":[-96.771985,41.01685],"type":"Point"}
}