{
  "type": "Feature",
  "properties": {
    "addr:full":"9505 I St Omaha NE 68127",
    "addr:housenumber":"9505",
    "addr:postcode":"68127",
    "addr:street":"I St",
    "iso:country":"US",
    "sg:address":"9505 I St",
    "sg:city":"Omaha",
    "sg:classifiers":[
        {
            "category":"Manufacturing",
            "subcategory":"Metals",
            "type":"Manufacturing & Wholesale Goods"
        }
    ],
    "sg:phone":"+1 402 331 0275",
    "sg:postcode":"68127",
    "sg:province":"NE",
    "sg:tags":[
        "mfg"
    ],
    "wof:name":"Optimus Corporation",
    "wof:placetype":"venue"
},
  "geometry": {"coordinates":[-96.061789,41.216152],"type":"Point"}
}