{
  "type": "Feature",
  "properties": {
    "addr:full":"712 State St Bassett NE 68714",
    "addr:housenumber":"712",
    "addr:postcode":"68714",
    "addr:street":"State St",
    "iso:country":"US",
    "sg:address":"712 State St",
    "sg:city":"Bassett",
    "sg:classifiers":[
        {
            "category":"Retail",
            "subcategory":"Repair Shop",
            "type":"Services"
        }
    ],
    "sg:phone":"+1 402 684 3437",
    "sg:postcode":"68714",
    "sg:province":"NE",
    "sg:tags":[
        "appliance"
    ],
    "wof:name":"Delmar Worden Repair",
    "wof:placetype":"venue"
},
  "geometry": {"coordinates":[-99.53646000000001,42.576663],"type":"Point"}
}