{
  "type": "Feature",
  "properties": {
    "addr:full":"4911 S 118th St Omaha NE 68137",
    "addr:housenumber":"4911",
    "addr:postcode":"68137",
    "addr:street":"S 118Th St",
    "iso:country":"US",
    "sg:address":"4911 S 118th St",
    "sg:city":"Omaha",
    "sg:classifiers":[
        {
            "category":"Professional",
            "subcategory":"Business Services",
            "type":"Services"
        }
    ],
    "sg:phone":"+1 402 334 8496",
    "sg:postcode":"68137",
    "sg:province":"NE",
    "wof:name":"Petco",
    "wof:placetype":"venue"
},
  "geometry": {"coordinates":[-96.098179,41.208656],"type":"Point"}
}