{
  "type": "Feature",
  "properties": {
    "addr:full":"562 I Rd Chapman NE 68827",
    "addr:housenumber":"562",
    "addr:postcode":"68827",
    "addr:street":"I Rd",
    "iso:country":"US",
    "sg:address":"562 I Rd",
    "sg:city":"Chapman",
    "sg:phone":"+1 308 986 2680",
    "sg:postcode":"68827",
    "sg:province":"NE",
    "sg:tags":[
        "farm",
        "grain",
        "cash"
    ],
    "wof:name":"Stoppkotte Milton H & Kay",
    "wof:placetype":"venue"
},
  "geometry": {"coordinates":[-98.188419,41.046057],"type":"Point"}
}