{
  "type": "Feature",
  "properties": {
    "iso:country":"US",
    "sg:address":"1611 Stagecoach Rd",
    "sg:city":"Grand Island",
    "sg:classifiers":[
        {
            "category":"Farming",
            "subcategory":"Farm",
            "type":"Manufacturing & Wholesale Goods"
        }
    ],
    "sg:phone":"+1 308 381 6655",
    "sg:postcode":"68801",
    "sg:province":"NE",
    "sg:tags":[
        "crop",
        "general"
    ],
    "wof:name":"George Wanitschke",
    "wof:placetype":"venue"
},
  "geometry": {"coordinates":[-98.35196000000001,40.894727],"type":"Point"}
}