{
  "type": "Feature",
  "properties": {
    "iso:country":"US",
    "sg:address":"19888 SW 117th Rd",
    "sg:city":"De Witt",
    "sg:phone":"+1 402 683 4405",
    "sg:postcode":"68341",
    "sg:province":"NE",
    "sg:tags":[
        "farm",
        "corn",
        "grain",
        "cash"
    ],
    "wof:name":"Eugene Wollenburg",
    "wof:placetype":"venue"
},
  "geometry": {"coordinates":[-96.879537,40.3225],"type":"Point"}
}