{
  "type": "Feature",
  "properties": {
    "iso:country":"US",
    "sg:address":"16511 Arbor St",
    "sg:city":"Omaha",
    "sg:classifiers":[
        {
            "category":"Building & Trades",
            "subcategory":"Landscaping Services",
            "type":"Services"
        }
    ],
    "sg:phone":"+1 402 333 2494",
    "sg:postcode":"68130",
    "sg:province":"NE",
    "sg:tags":[
        "lawn",
        "garden"
    ],
    "wof:name":"Paradise Lawn Care Inc",
    "wof:placetype":"venue"
},
  "geometry": {"coordinates":[-96.171745,41.235542],"type":"Point"}
}