{
  "type": "Feature",
  "properties": {
    "addr:full":"208 N Main St Gordon NE 69343",
    "addr:housenumber":"208",
    "addr:postcode":"69343",
    "addr:street":"N Main St",
    "iso:country":"US",
    "sg:address":"208 N Main St",
    "sg:city":"Gordon",
    "sg:classifiers":[
        {
            "category":"Personal",
            "subcategory":"Beauty Salon",
            "type":"Services"
        }
    ],
    "sg:phone":"+1 308 282 1678",
    "sg:postcode":"69343",
    "sg:province":"NE",
    "sg:tags":[
        "shop"
    ],
    "wof:name":"Iona's Beauty Shop",
    "wof:placetype":"venue"
},
  "geometry": {"coordinates":[-102.203356,42.805869],"type":"Point"}
}