{
  "type": "Feature",
  "properties": {
    "iso:country":"US",
    "sg:address":"12808 Augusta Ave",
    "sg:city":"Omaha",
    "sg:classifiers":[
        {
            "category":"Health Services",
            "subcategory":"Doctor",
            "type":"Services"
        }
    ],
    "sg:phone":"+1 402 330 5690",
    "sg:postcode":"68144",
    "sg:province":"NE",
    "sg:tags":[
        "clinic",
        "pediatrician"
    ],
    "wof:name":"Omaha Children's Clinic",
    "wof:placetype":"venue"
},
  "geometry": {"coordinates":[-96.113038,41.230681],"type":"Point"}
}