{
  "type": "Feature",
  "properties": {
    "iso:country":"US",
    "sg:address":"1403 Galvin Rd S",
    "sg:city":"Bellevue",
    "sg:classifiers":[
        {
            "category":"Building & Trades",
            "subcategory":"Landscaping Services",
            "type":"Services"
        }
    ],
    "sg:phone":"+1 402 293 0869",
    "sg:postcode":"68005",
    "sg:province":"NE",
    "sg:tags":[
        "tree"
    ],
    "wof:name":"Urban Tree & Lawn",
    "wof:placetype":"venue"
},
  "geometry": {"coordinates":[-95.914316,41.147422],"type":"Point"}
}