{
  "type": "Feature",
  "properties": {
    "addr:full":"57250 721st Rd Jansen NE 68352",
    "addr:housenumber":"57250",
    "addr:postcode":"68352",
    "addr:street":"721St Rd",
    "iso:country":"US",
    "sg:address":"57250 721st Rd",
    "sg:city":"Jansen",
    "sg:classifiers":[
        {
            "category":"Farming",
            "subcategory":"Livestock Farm",
            "type":"Manufacturing & Wholesale Goods"
        }
    ],
    "sg:phone":"+1 402 656 4817",
    "sg:postcode":"68352",
    "sg:province":"NE",
    "sg:tags":[
        "hog",
        "corn",
        "cash",
        "grain",
        "or",
        "feedlot"
    ],
    "wof:name":"Heidemann Farm",
    "wof:placetype":"venue"
},
  "geometry": {"coordinates":[-97.104119,40.27705],"type":"Point"}
}