{
  "type": "Feature",
  "properties": {
    "addr:full":"1050 N St Lincoln NE 68508",
    "addr:housenumber":"1050",
    "addr:postcode":"68508",
    "addr:street":"N St",
    "iso:country":"US",
    "sg:address":"1050 N St",
    "sg:city":"Lincoln",
    "sg:classifiers":[
        {
            "category":"Government",
            "subcategory":"Office",
            "type":"Public Place"
        }
    ],
    "sg:phone":"+1 402 471 7000",
    "sg:postcode":"68508",
    "sg:province":"NE",
    "sg:tags":[
        "state",
        "program",
        "health"
    ],
    "wof:name":"Dept Health & Human Svc",
    "wof:placetype":"venue"
},
  "geometry": {"coordinates":[-96.70610000000001,40.812582],"type":"Point"}
}