{
  "type": "Feature",
  "properties": {
    "iso:country":"US",
    "sg:address":"2011 N St",
    "sg:city":"Aurora",
    "sg:classifiers":[
        {
            "category":"Home & Garden",
            "subcategory":"Home Furnishings",
            "type":"Retail Goods"
        }
    ],
    "sg:phone":"+1 402 694 5688",
    "sg:postcode":"68818",
    "sg:province":"NE",
    "sg:tags":[
        "curtain",
        "made",
        "drapery"
    ],
    "wof:name":"Ronda's Drapery Shop",
    "wof:placetype":"venue"
},
  "geometry": {"coordinates":[-97.99266299999999,40.869806],"type":"Point"}
}