{
  "type": "Feature",
  "properties": {
    "addr:full":"1125 S 103rd St Omaha NE 68124",
    "addr:housenumber":"1125",
    "addr:postcode":"68124",
    "addr:street":"S 103Rd St",
    "iso:country":"US",
    "sg:address":"1125 S 103rd St",
    "sg:city":"Omaha",
    "sg:classifiers":[
        {
            "category":"Banks & Credit Unions",
            "subcategory":"Investment Brokerage",
            "type":"Services"
        }
    ],
    "sg:phone":"+1 402 393 1300",
    "sg:postcode":"68124",
    "sg:province":"NE",
    "sg:tags":[
        "advisory",
        "financial"
    ],
    "wof:name":"Mc Carthy & Co",
    "wof:placetype":"venue"
},
  "geometry": {"coordinates":[-96.070526,41.245144],"type":"Point"}
}