{
  "type": "Feature",
  "properties": {
    "addr:full":"210 Main St Crofton NE 68730",
    "addr:housenumber":"210",
    "addr:postcode":"68730",
    "addr:street":"Main St",
    "iso:country":"US",
    "sg:address":"210 Main St",
    "sg:city":"Crofton",
    "sg:classifiers":[
        {
            "category":"Home & Garden",
            "subcategory":"Building Materials",
            "type":"Retail Goods"
        }
    ],
    "sg:phone":"+1 402 388 4330",
    "sg:postcode":"68730",
    "sg:province":"NE",
    "sg:tags":[
        "lumber"
    ],
    "wof:name":"West Lumber & Ready Mix",
    "wof:placetype":"venue"
},
  "geometry": {"coordinates":[-97.49609100000001,42.732452],"type":"Point"}
}