{
  "type": "Feature",
  "properties": {
    "iso:country":"US",
    "sg:address":"810 E Avon Ln",
    "sg:city":"Lincoln",
    "sg:classifiers":[
        {
            "category":"Building & Trades",
            "subcategory":"Landscaping Services",
            "type":"Services"
        }
    ],
    "sg:phone":"+1 402 429 2548",
    "sg:postcode":"68505",
    "sg:province":"NE",
    "sg:tags":[
        "lawn",
        "maintenance",
        "grounds"
    ],
    "wof:name":"Rush Co Lawn Care",
    "wof:placetype":"venue"
},
  "geometry": {"coordinates":[-96.617549,40.822182],"type":"Point"}
}