{
  "type": "Feature",
  "properties": {
    "iso:country":"US",
    "sg:address":"767 Co Rd 364",
    "sg:city":"Beaver Crossing",
    "sg:classifiers":[
        {
            "category":"Farming",
            "subcategory":"Farm",
            "type":"Manufacturing & Wholesale Goods"
        }
    ],
    "sg:phone":"+1 402 532 2011",
    "sg:postcode":"68313",
    "sg:province":"NE",
    "wof:name":"Walnut Ridge Farms",
    "wof:placetype":"venue"
},
  "geometry": {"coordinates":[-97.216098,40.791499],"type":"Point"}
}