{
  "type": "Feature",
  "properties": {
    "addr:full":"234 Beech St Chadron NE 69337",
    "addr:housenumber":"234",
    "addr:postcode":"69337",
    "addr:street":"Beech St",
    "iso:country":"US",
    "sg:address":"234 Beech St",
    "sg:city":"Chadron",
    "sg:classifiers":[
        {
            "category":"Manufacturing",
            "subcategory":"Food",
            "type":"Manufacturing & Wholesale Goods"
        }
    ],
    "sg:phone":"+1 308 432 2262",
    "sg:postcode":"69337",
    "sg:province":"NE",
    "sg:tags":[
        "bottler"
    ],
    "wof:name":"Coca-Cola Bottling Co",
    "wof:placetype":"venue"
},
  "geometry": {"coordinates":[-102.98934300000001,42.829395],"type":"Point"}
}