{
  "type": "Feature",
  "properties": {
    "iso:country":"US",
    "sg:address":"4750 Lafayette Ave",
    "sg:city":"Omaha",
    "sg:classifiers":[
        {
            "category":"Real Estate",
            "subcategory":"Real Estate Operator",
            "type":"Services"
        }
    ],
    "sg:phone":"+1 402 614 1697",
    "sg:postcode":"68132",
    "sg:province":"NE",
    "sg:tags":[
        "apartment"
    ],
    "wof:name":"Taulborg Apartments",
    "wof:placetype":"venue"
},
  "geometry": {"coordinates":[-95.98360099999999,41.271118],"type":"Point"}
}