{
  "type": "Feature",
  "properties": {
    "iso:country":"US",
    "sg:address":"418 W Pine St",
    "sg:city":"Pleasant Dale",
    "sg:classifiers":[
        {
            "category":"Education",
            "subcategory":"School",
            "type":"Public Place"
        }
    ],
    "sg:phone":"+1 402 795 3780",
    "sg:postcode":"68423",
    "sg:province":"NE",
    "wof:name":"Pleasant Dale Elementary Schl",
    "wof:placetype":"venue"
},
  "geometry": {"coordinates":[-96.93083799999999,40.790502],"type":"Point"}
}