{
  "type": "Feature",
  "properties": {
    "iso:country":"US",
    "sg:address":"5631 S 56th St",
    "sg:city":"Lincoln",
    "sg:classifiers":[
        {
            "category":"Shopping",
            "subcategory":"Used Merchandise",
            "type":"Retail Goods"
        }
    ],
    "sg:phone":"+1 402 421 6099",
    "sg:postcode":"68516",
    "sg:province":"NE",
    "wof:name":"Jr Legue Consignment Thrift Sp",
    "wof:placetype":"venue"
},
  "geometry": {"coordinates":[-96.64438699999999,40.756262],"type":"Point"}
}