{
  "type": "Feature",
  "properties": {
    "addr:full":"111 N 9th St Norfolk NE 68701",
    "addr:housenumber":"111",
    "addr:postcode":"68701",
    "addr:street":"N 9Th St",
    "iso:country":"US",
    "sg:address":"111 N 9th St",
    "sg:city":"Norfolk",
    "sg:classifiers":[
        {
            "category":"Social Services",
            "type":"Services"
        }
    ],
    "sg:phone":"+1 402 371 6484",
    "sg:postcode":"68701",
    "sg:province":"NE",
    "sg:tags":[
        "mission"
    ],
    "wof:name":"Norfolk Rescue Mission",
    "wof:placetype":"venue"
},
  "geometry": {"coordinates":[-97.419325,42.033032],"type":"Point"}
}