{
  "type": "Feature",
  "properties": {
    "iso:country":"US",
    "sg:address":"4337 S 90th St",
    "sg:city":"Omaha",
    "sg:classifiers":[
        {
            "category":"Shopping",
            "subcategory":"Used Merchandise",
            "type":"Retail Goods"
        }
    ],
    "sg:phone":"+1 402 331 4622",
    "sg:postcode":"68127",
    "sg:province":"NE",
    "sg:tags":[
        "shop",
        "consignment"
    ],
    "wof:name":"Econsignit Of Omaha",
    "wof:placetype":"venue"
},
  "geometry": {"coordinates":[-96.052571,41.216566],"type":"Point"}
}