{
  "type": "Feature",
  "properties": {
    "iso:country":"US",
    "sg:address":"9413 I St",
    "sg:city":"Omaha",
    "sg:classifiers":[
        {
            "category":"Building & Trades",
            "subcategory":"Construction",
            "type":"Services"
        }
    ],
    "sg:phone":"+1 402 592 8898",
    "sg:postcode":"68127",
    "sg:province":"NE",
    "sg:tags":[
        "tile",
        "dealer"
    ],
    "wof:name":"Accent Tile",
    "wof:placetype":"venue"
},
  "geometry": {"coordinates":[-96.059752,41.216146],"type":"Point"}
}