{
  "type": "Feature",
  "properties": {
    "iso:country":"US",
    "sg:address":"2100 S 51st St",
    "sg:city":"Omaha",
    "sg:classifiers":[
        {
            "category":"Organizations",
            "subcategory":"Religious Organization",
            "type":"Services"
        }
    ],
    "sg:phone":"+1 402 551 0608",
    "sg:postcode":"68106",
    "sg:province":"NE",
    "sg:tags":[
        "church"
    ],
    "wof:name":"Eastern Nebraska Baptist Assoc Sbc",
    "wof:placetype":"venue"
},
  "geometry": {"coordinates":[-95.992897,41.2393],"type":"Point"}
}