{
  "type": "Feature",
  "properties": {
    "iso:country":"US",
    "sg:address":"9321 Forest Glen Dr",
    "sg:city":"Lincoln",
    "sg:classifiers":[
        {
            "category":"Shopping",
            "subcategory":"Hobbies, Toys, & Games",
            "type":"Retail Goods"
        }
    ],
    "sg:phone":"+1 402 601 6904",
    "sg:postcode":"68526",
    "sg:province":"NE",
    "sg:tags":[
        "supply"
    ],
    "wof:name":"Big Air Brothers LLC",
    "wof:placetype":"venue"
},
  "geometry": {"coordinates":[-96.59342700000001,40.750575],"type":"Point"}
}