{
  "type": "Feature",
  "properties": {
    "iso:country":"US",
    "sg:address":"916 N 70th St",
    "sg:city":"Lincoln",
    "sg:classifiers":[
        {
            "category":"Insurance",
            "subcategory":"Insurance Agent",
            "type":"Services"
        }
    ],
    "sg:phone":"+1 402 489 3323",
    "sg:postcode":"68505",
    "sg:province":"NE",
    "wof:name":"Carey Dart",
    "wof:placetype":"venue"
},
  "geometry": {"coordinates":[-96.624916,40.8217],"type":"Point"}
}