{
  "type": "Feature",
  "properties": {
    "iso:country":"US",
    "sg:address":"812 W Main St",
    "sg:city":"Alma",
    "sg:classifiers":[
        {
            "category":"Shopping",
            "subcategory":"Bicycles & Sporting Goods",
            "type":"Retail Goods"
        }
    ],
    "sg:phone":"+1 308 928 2316",
    "sg:postcode":"68920",
    "sg:province":"NE",
    "sg:website":"www.thesportsshack.com",
    "wof:name":"Sports Shack Inc",
    "wof:placetype":"venue"
},
  "geometry": {"coordinates":[-99.364576,40.097422],"type":"Point"}
}