{
  "type": "Feature",
  "properties": {
    "iso:country":"US",
    "sg:address":"1203 Murray Pt",
    "sg:city":"Plattsmouth",
    "sg:classifiers":[
        {
            "category":"Shopping",
            "subcategory":"Gifts & Souvenirs",
            "type":"Retail Goods"
        }
    ],
    "sg:phone":"+1 402 235 3349",
    "sg:postcode":"68048",
    "sg:province":"NE",
    "wof:name":"Husker Elvis LLC",
    "wof:placetype":"venue"
},
  "geometry": {"coordinates":[-95.89305,40.920685],"type":"Point"}
}