{
  "type": "Feature",
  "properties": {
    "iso:country":"US",
    "sg:address":"2345 E Blue Valley Rd",
    "sg:city":"Blue Hill",
    "sg:classifiers":[
        {
            "category":"Farming",
            "subcategory":"Farm",
            "type":"Manufacturing & Wholesale Goods"
        }
    ],
    "sg:phone":"+1 402 756 2377",
    "sg:postcode":"68930",
    "sg:province":"NE",
    "sg:tags":[
        "crop",
        "general"
    ],
    "wof:name":"A M Woods Inc",
    "wof:placetype":"venue"
},
  "geometry": {"coordinates":[-98.348283,40.350377],"type":"Point"}
}