{
  "type": "Feature",
  "properties": {
    "addr:full":"2426 Woodsdale Blvd Lincoln NE 68502",
    "addr:housenumber":"2426",
    "addr:postcode":"68502",
    "addr:street":"Woodsdale Blvd",
    "iso:country":"US",
    "sg:address":"2426 Woodsdale Blvd",
    "sg:city":"Lincoln",
    "sg:classifiers":[
        {
            "category":"Professional",
            "subcategory":"Advertising",
            "type":"Services"
        }
    ],
    "sg:phone":"+1 402 489 7174",
    "sg:postcode":"68502",
    "sg:province":"NE",
    "sg:tags":[
        "agency"
    ],
    "wof:name":"Advertising Co The",
    "wof:placetype":"venue"
},
  "geometry": {"coordinates":[-96.68639899999999,40.782405],"type":"Point"}
}