{
  "type": "Feature",
  "properties": {
    "addr:full":"14006 Charles St Omaha NE 68154",
    "addr:housenumber":"14006",
    "addr:postcode":"68154",
    "addr:street":"Charles St",
    "iso:country":"US",
    "sg:address":"14006 Charles St",
    "sg:city":"Omaha",
    "sg:classifiers":[
        {
            "category":"Organizations",
            "subcategory":"Religious Organization",
            "type":"Services"
        }
    ],
    "sg:phone":"+1 402 498 4491",
    "sg:postcode":"68154",
    "sg:province":"NE",
    "sg:tags":[
        "clergy"
    ],
    "wof:name":"Martha Freeman",
    "wof:placetype":"venue"
},
  "geometry": {"coordinates":[-96.13134100000001,41.274969],"type":"Point"}
}