{
  "type": "Feature",
  "properties": {
    "iso:country":"US",
    "sg:address":"2204 14th St",
    "sg:city":"Columbus",
    "sg:classifiers":[
        {
            "category":"Health Services",
            "subcategory":"Hospital",
            "type":"Services"
        }
    ],
    "sg:phone":"+1 402 562 7728",
    "sg:postcode":"68601",
    "sg:province":"NE",
    "sg:tags":[
        "mental"
    ],
    "wof:name":"Charla Lambert",
    "wof:placetype":"venue"
},
  "geometry": {"coordinates":[-97.355587,41.430286],"type":"Point"}
}