{
  "type": "Feature",
  "properties": {
    "iso:country":"US",
    "sg:address":"1113 S 44th St",
    "sg:city":"Lincoln",
    "sg:classifiers":[
        {
            "category":"Building & Trades",
            "subcategory":"Construction",
            "type":"Services"
        }
    ],
    "sg:phone":"+1 402 486 1388",
    "sg:postcode":"68510",
    "sg:province":"NE",
    "sg:tags":[
        "contractor"
    ],
    "wof:name":"Doug Maughn Masonry",
    "wof:placetype":"venue"
},
  "geometry": {"coordinates":[-96.658545,40.801768],"type":"Point"}
}