{
  "type": "Feature",
  "properties": {
    "addr:full":"223 E 14th St Hastings NE 68901",
    "addr:housenumber":"223",
    "addr:postcode":"68901",
    "addr:street":"E 14Th St",
    "iso:country":"US",
    "sg:address":"223 E 14th St",
    "sg:city":"Hastings",
    "sg:classifiers":[
        {
            "category":"Social Services",
            "type":"Services"
        }
    ],
    "sg:phone":"+1 402 463 1119",
    "sg:postcode":"68901",
    "sg:province":"NE",
    "sg:tags":[
        "counselor",
        "marriage",
        "family"
    ],
    "wof:name":"Catholic Charities",
    "wof:placetype":"venue"
},
  "geometry": {"coordinates":[-98.37952199999999,40.600793],"type":"Point"}
}