{
  "type": "Feature",
  "properties": {
    "addr:full":"6025 Oak Hills Dr Omaha NE 68137",
    "addr:housenumber":"6025",
    "addr:postcode":"68137",
    "addr:street":"Oak Hills Dr",
    "iso:country":"US",
    "sg:address":"6025 Oak Hills Dr",
    "sg:city":"Omaha",
    "sg:classifiers":[
        {
            "category":"Wholesale",
            "subcategory":"Drugs",
            "type":"Manufacturing & Wholesale Goods"
        }
    ],
    "sg:phone":"+1 402 932 5172",
    "sg:postcode":"68137",
    "sg:province":"NE",
    "sg:tags":[
        "pharmaceutical",
        "product"
    ],
    "wof:name":"BWB Enterprises",
    "wof:placetype":"venue"
},
  "geometry": {"coordinates":[-96.10540899999999,41.197386],"type":"Point"}
}