{
  "type": "Feature",
  "properties": {
    "addr:full":"2312 O St Auburn NE 68305",
    "addr:housenumber":"2312",
    "addr:postcode":"68305",
    "addr:street":"O St",
    "iso:country":"US",
    "sg:address":"2312 O St",
    "sg:city":"Auburn",
    "sg:classifiers":[
        {
            "category":"Building & Trades",
            "subcategory":"Construction",
            "type":"Services"
        }
    ],
    "sg:phone":"+1 402 274 3317",
    "sg:postcode":"68305",
    "sg:province":"NE",
    "sg:tags":[
        "general",
        "contractor"
    ],
    "wof:name":"Drake's Construction",
    "wof:placetype":"venue"
},
  "geometry": {"coordinates":[-95.845438,40.38121],"type":"Point"}
}