{
  "type": "Feature",
  "properties": {
    "addr:full":"2933 S 108th St Omaha NE 68144",
    "addr:housenumber":"2933",
    "addr:postcode":"68144",
    "addr:street":"S 108Th St",
    "iso:country":"US",
    "sg:address":"2933 S 108th St",
    "sg:city":"Omaha",
    "sg:classifiers":[
        {
            "category":"Shopping",
            "subcategory":"Clothing, Apparel, & Fashions",
            "type":"Retail Goods"
        }
    ],
    "sg:phone":"+1 402 397 2525",
    "sg:postcode":"68144",
    "sg:province":"NE",
    "sg:tags":[
        "shop",
        "bridal"
    ],
    "wof:name":"Bridal Traditions Ltd",
    "wof:placetype":"venue"
},
  "geometry": {"coordinates":[-96.08139300000001,41.232225],"type":"Point"}
}