{
  "type": "Feature",
  "properties": {
    "addr:full":"501 N Jeffers St North Platte NE 69101",
    "addr:housenumber":"501",
    "addr:postcode":"69101",
    "addr:street":"N Jeffers St",
    "iso:country":"US",
    "sg:address":"501 N Jeffers St",
    "sg:city":"North Platte",
    "sg:classifiers":[
        {
            "category":"Banks & Credit Unions",
            "subcategory":"Investment Brokerage",
            "type":"Services"
        }
    ],
    "sg:phone":"+1 308 534 8210",
    "sg:postcode":"69101",
    "sg:province":"NE",
    "sg:tags":[
        "security"
    ],
    "wof:name":"AIG Advisor Group",
    "wof:placetype":"venue"
},
  "geometry": {"coordinates":[-100.762974,41.137496],"type":"Point"}
}