{
  "type": "Feature",
  "properties": {
    "addr:full":"136 E 2nd St Ainsworth NE 69210",
    "addr:housenumber":"136",
    "addr:postcode":"69210",
    "addr:street":"E 2Nd St",
    "iso:country":"US",
    "sg:address":"136 E 2nd St",
    "sg:city":"Ainsworth",
    "sg:classifiers":[
        {
            "category":"Autos & Motor Vehicles",
            "subcategory":"Automobile Sales",
            "type":"Retail Goods"
        }
    ],
    "sg:phone":"+1 402 387 1681",
    "sg:postcode":"69210",
    "sg:province":"NE",
    "sg:tags":[
        "car",
        "truck",
        "dealer"
    ],
    "wof:name":"Ainsworth Motors Inc",
    "wof:placetype":"venue"
},
  "geometry": {"coordinates":[-99.862089,42.54693],"type":"Point"}
}