{
  "type": "Feature",
  "properties": {
    "iso:country":"US",
    "sg:address":"906 Main St",
    "sg:city":"Wood River",
    "sg:classifiers":[
        {
            "category":"Shopping",
            "subcategory":"News",
            "type":"Retail Goods"
        }
    ],
    "sg:phone":"+1 308 583 0124",
    "sg:postcode":"68883",
    "sg:province":"NE",
    "sg:tags":[
        "dealer"
    ],
    "wof:name":"Woodriver Sunbeam",
    "wof:placetype":"venue"
},
  "geometry": {"coordinates":[-98.60172300000001,40.820941],"type":"Point"}
}