{
  "type": "Feature",
  "properties": {
    "addr:full":"8416 N 29th St Omaha NE 68112",
    "addr:housenumber":"8416",
    "addr:postcode":"68112",
    "addr:street":"N 29Th St",
    "iso:country":"US",
    "sg:address":"8416 N 29th St",
    "sg:city":"Omaha",
    "sg:classifiers":[
        {
            "category":"Building & Trades",
            "subcategory":"Electrical",
            "type":"Services"
        }
    ],
    "sg:phone":"+1 402 451 3900",
    "sg:postcode":"68112",
    "sg:province":"NE",
    "sg:tags":[
        "electric",
        "contractor"
    ],
    "wof:name":"Gatchell Electric",
    "wof:placetype":"venue"
},
  "geometry": {"coordinates":[-95.959,41.336899],"type":"Point"}
}