{
  "type": "Feature",
  "properties": {
    "iso:country":"US",
    "sg:address":"7134 Pacific St",
    "sg:city":"Omaha",
    "sg:classifiers":[
        {
            "category":"Professional",
            "subcategory":"Lawyer & Legal Services",
            "type":"Services"
        }
    ],
    "sg:phone":"+1 402 397 1898",
    "sg:postcode":"68106",
    "sg:province":"NE",
    "sg:tags":[
        "attorney"
    ],
    "wof:name":"Kirkpatrick Jeffery R",
    "wof:placetype":"venue"
},
  "geometry": {"coordinates":[-96.02297799999999,41.248849],"type":"Point"}
}