{
  "type": "Feature",
  "properties": {
    "iso:country":"US",
    "sg:address":"630 Arbor Cir",
    "sg:city":"Bennet",
    "sg:classifiers":[
        {
            "category":"Building & Trades",
            "subcategory":"Construction",
            "type":"Services"
        }
    ],
    "sg:phone":"+1 402 782 2098",
    "sg:postcode":"68317",
    "sg:province":"NE",
    "sg:tags":[
        "house"
    ],
    "wof:name":"Mp Homes",
    "wof:placetype":"venue"
},
  "geometry": {"coordinates":[-96.49942299999999,40.679843],"type":"Point"}
}