{
  "type": "Feature",
  "properties": {
    "iso:country":"US",
    "sg:address":"4420 Leavenworth St",
    "sg:city":"Omaha",
    "sg:classifiers":[
        {
            "category":"Retail",
            "subcategory":"Auto Repair",
            "type":"Services"
        }
    ],
    "sg:phone":"+1 402 551 3015",
    "sg:postcode":"68105",
    "sg:province":"NE",
    "sg:tags":[
        "repairing",
        "automobile",
        "automotive"
    ],
    "wof:name":"Exclusive Honda & Acura Repair",
    "wof:placetype":"venue"
},
  "geometry": {"coordinates":[-95.98020200000001,41.252499],"type":"Point"}
}