{
  "type": "Feature",
  "properties": {
    "iso:country":"US",
    "sg:address":"985 Y Rd",
    "sg:city":"Pender",
    "sg:classifiers":[
        {
            "category":"Shopping",
            "subcategory":"Crafts & Fabrics",
            "type":"Retail Goods"
        }
    ],
    "sg:phone":"+1 402 385 2454",
    "sg:postcode":"68047",
    "sg:province":"NE",
    "sg:tags":[
        "sewing"
    ],
    "wof:name":"Needle Magic",
    "wof:placetype":"venue"
},
  "geometry": {"coordinates":[-96.84437,42.090419],"type":"Point"}
}