{
  "type": "Feature",
  "properties": {
    "iso:country":"US",
    "sg:address":"3218 N 7th St",
    "sg:city":"Beatrice",
    "sg:classifiers":[
        {
            "category":"Retail",
            "subcategory":"Auto Repair",
            "type":"Services"
        }
    ],
    "sg:phone":"+1 402 228 7033",
    "sg:postcode":"68310",
    "sg:province":"NE",
    "sg:tags":[
        "general"
    ],
    "wof:name":"All Makes Auto Repair",
    "wof:placetype":"venue"
},
  "geometry": {"coordinates":[-96.745599,40.297392],"type":"Point"}
}