{
  "type": "Feature",
  "properties": {
    "iso:country":"US",
    "sg:address":"223 2nd St",
    "sg:city":"Brunswick",
    "sg:classifiers":[
        {
            "category":"Bars & Pubs",
            "type":"Food & Drink"
        }
    ],
    "sg:phone":"+1 402 842 2020",
    "sg:postcode":"68752",
    "sg:province":"NE",
    "sg:tags":[
        "drinking"
    ],
    "wof:name":"B & R Bar & Grill",
    "wof:placetype":"venue"
},
  "geometry": {"coordinates":[-97.734207,42.031445],"type":"Point"}
}