{
  "type": "Feature",
  "properties": {
    "iso:country":"US",
    "sg:address":"707 N 120th St",
    "sg:city":"Omaha",
    "sg:classifiers":[
        {
            "category":"Autos & Motor Vehicles",
            "subcategory":"Fuel & Gas Station",
            "type":"Retail Goods"
        },
        {
            "category":"Autos & Motor Vehicles",
            "subcategory":"Auto Supplies",
            "type":"Retail Goods"
        },
        {
            "category":"Retail",
            "subcategory":"Auto Repair",
            "type":"Services"
        },
        {
            "category":"Autos & Motor Vehicles",
            "subcategory":"Recreational Vehicle Sales",
            "type":"Retail Goods"
        }
    ],
    "sg:phone":"+1 402 496 2450",
    "sg:postcode":"68154",
    "sg:province":"NE",
    "sg:tags":[
        "automobile",
        "diagnostic",
        "inspection",
        "tire",
        "equipment-service"
    ],
    "sg:website":"http://www.jensentire.com",
    "wof:name":"Jensen Tire & Auto",
    "wof:placetype":"venue"
},
  "geometry": {"coordinates":[-96.100566,41.265424],"type":"Point"}
}