{
  "type": "Feature",
  "properties": {
    "iso:country":"US",
    "sg:address":"501 S Cedar St",
    "sg:city":"Grand Island",
    "sg:classifiers":[
        {
            "category":"Retail",
            "subcategory":"Photofinishing",
            "type":"Services"
        }
    ],
    "sg:phone":"+1 308 384 9765",
    "sg:postcode":"68801",
    "sg:province":"NE",
    "sg:tags":[
        "laboratory"
    ],
    "wof:name":"Sunbeam Gallery",
    "wof:placetype":"venue"
},
  "geometry": {"coordinates":[-98.34067400000001,40.91883],"type":"Point"}
}