{
  "type": "Feature",
  "properties": {
    "iso:country":"US",
    "sg:address":"50 Plaza Blvd",
    "sg:city":"Kearney",
    "sg:classifiers":[
        {
            "category":"Real Estate",
            "subcategory":"Real Estate Operator",
            "type":"Services"
        }
    ],
    "sg:phone":"+1 308 234 4757",
    "sg:postcode":"68845",
    "sg:province":"NE",
    "sg:tags":[
        "apartment"
    ],
    "wof:name":"Normandy Apartments",
    "wof:placetype":"venue"
},
  "geometry": {"coordinates":[-99.11795100000001,40.692664],"type":"Point"}
}