{
  "type": "Feature",
  "properties": {
    "iso:country":"US",
    "sg:address":"122 S 52nd St",
    "sg:city":"Lincoln",
    "sg:classifiers":[
        {
            "category":"Shopping",
            "subcategory":"Clothing, Apparel, & Fashions",
            "type":"Retail Goods"
        }
    ],
    "sg:phone":"+1 402 483 2263",
    "sg:postcode":"68510",
    "sg:province":"NE",
    "sg:tags":[
        "leather",
        "shoes",
        "ga",
        "accessory"
    ],
    "sg:website":"www.boogs.com",
    "wof:name":"Boog's Rock 'n Roll Boutique",
    "wof:placetype":"venue"
},
  "geometry": {"coordinates":[-96.648853,40.812709],"type":"Point"}
}