{
  "type": "Feature",
  "properties": {
    "iso:country":"US",
    "sg:address":"2604 Norfolk Ave",
    "sg:city":"Norfolk",
    "sg:classifiers":[
        {
            "category":"Shopping",
            "type":"Retail Goods"
        }
    ],
    "sg:phone":"+1 402 371 6550",
    "sg:postcode":"68701",
    "sg:province":"NE",
    "sg:tags":[
        "equipment",
        "medical",
        "convalescent",
        "lease"
    ],
    "wof:name":"Home Health Medical Equipment",
    "wof:placetype":"venue"
},
  "geometry": {"coordinates":[-97.359576,42.032965],"type":"Point"}
}