{
  "type": "Feature",
  "properties": {
    "iso:country":"US",
    "sg:address":"800 S 13th St",
    "sg:city":"Norfolk",
    "sg:classifiers":[
        {
            "category":"Bars & Pubs",
            "type":"Food & Drink"
        }
    ],
    "sg:phone":"+1 402 371 4340",
    "sg:postcode":"68701",
    "sg:province":"NE",
    "sg:tags":[
        "lounge",
        "drinking",
        "cocktail"
    ],
    "wof:name":"Ricardo's Back Door Lounge",
    "wof:placetype":"venue"
},
  "geometry": {"coordinates":[-97.426503,42.02354],"type":"Point"}
}