{
  "type": "Feature",
  "properties": {
    "iso:country":"US",
    "sg:address":"6009 Maple St",
    "sg:city":"Omaha",
    "sg:classifiers":[
        {
            "category":"Restaurant",
            "type":"Food & Drink"
        }
    ],
    "sg:menulink":"http://www.allmenus.com/ne/omaha/129543-subway/menu/",
    "sg:phone":"+1 402 933 2077",
    "sg:postcode":"68104",
    "sg:province":"NE",
    "sg:tags":[
        "american",
        "sandwich"
    ],
    "wof:name":"Subway",
    "wof:placetype":"venue"
},
  "geometry": {"coordinates":[-96.00528199999999,41.284697],"type":"Point"}
}