{
  "type": "Feature",
  "properties": {
    "iso:country":"US",
    "sg:address":"800 N 17th St",
    "sg:city":"Lincoln",
    "sg:classifiers":[
        {
            "category":"Autos & Motor Vehicles",
            "subcategory":"Fuel & Gas Station",
            "type":"Retail Goods"
        }
    ],
    "sg:phone":"+1 402 475 3223",
    "sg:postcode":"68508",
    "sg:province":"NE",
    "sg:tags":[
        "station",
        "gasoline"
    ],
    "wof:name":"Texaco",
    "wof:placetype":"venue"
},
  "geometry": {"coordinates":[-96.696519,40.823574],"type":"Point"}
}