{
  "type": "Feature",
  "properties": {
    "iso:country":"US",
    "sg:address":"12600 W Holdrege St",
    "sg:city":"Lincoln",
    "sg:phone":"+1 402 475 0319",
    "sg:postcode":"68528",
    "sg:province":"NE",
    "sg:tags":[
        "farm",
        "soybean"
    ],
    "wof:name":"Donald Borgmann",
    "wof:placetype":"venue"
},
  "geometry": {"coordinates":[-96.892146,40.828478],"type":"Point"}
}