{
  "type": "Feature",
  "properties": {
    "addr:full":"33 Gateway Mall Lincoln NE 68505",
    "addr:housenumber":"33",
    "addr:postcode":"68505",
    "addr:street":"Gateway Mall",
    "iso:country":"US",
    "sg:address":"33 Gateway Mall",
    "sg:city":"Lincoln",
    "sg:classifiers":[
        {
            "category":"Shopping",
            "subcategory":"Clothing, Apparel, & Fashions",
            "type":"Retail Goods"
        }
    ],
    "sg:phone":"+1 402 466 1103",
    "sg:postcode":"68505",
    "sg:province":"NE",
    "wof:name":"Express",
    "wof:placetype":"venue"
},
  "geometry": {"coordinates":[-96.641294,40.814108],"type":"Point"}
}