{
  "type": "Feature",
  "properties": {
    "iso:country":"US",
    "sg:address":"2512 N 72nd St",
    "sg:city":"Omaha",
    "sg:classifiers":[
        {
            "category":"Social Services",
            "subcategory":"Job Training",
            "type":"Services"
        }
    ],
    "sg:phone":"+1 402 884 8884",
    "sg:postcode":"68134",
    "sg:province":"NE",
    "sg:tags":[
        "disabled",
        "for",
        "mentally",
        "vocational"
    ],
    "wof:name":"Better Living Inc",
    "wof:placetype":"venue"
},
  "geometry": {"coordinates":[-96.023954,41.282572],"type":"Point"}
}