{
  "type": "Feature",
  "properties": {
    "iso:country":"US",
    "sg:address":"111 S 18th St",
    "sg:city":"Omaha",
    "sg:classifiers":[
        {
            "category":"Government",
            "subcategory":"Office",
            "type":"Public Place"
        }
    ],
    "sg:phone":"+1 402 221 4682",
    "sg:postcode":"68102",
    "sg:province":"NE",
    "sg:tags":[
        "federal",
        "wage",
        "control",
        "agency"
    ],
    "wof:name":"Wage and Hour Div Area Off",
    "wof:placetype":"venue"
},
  "geometry": {"coordinates":[-95.93974,41.258777],"type":"Point"}
}