{
  "type": "Feature",
  "properties": {
    "addr:full":"3800 Old Cheney Rd Lincoln NE 68516",
    "addr:housenumber":"3800",
    "addr:postcode":"68516",
    "addr:street":"Old Cheney Rd",
    "iso:country":"US",
    "sg:address":"3800 Old Cheney Rd",
    "sg:city":"Lincoln",
    "sg:classifiers":[
        {
            "category":"Personal",
            "subcategory":"Beauty Salon",
            "type":"Services"
        }
    ],
    "sg:phone":"+1 402 420 5717",
    "sg:postcode":"68516",
    "sg:province":"NE",
    "wof:name":"Hair Masters",
    "wof:placetype":"venue"
},
  "geometry": {"coordinates":[-96.66466800000001,40.755446],"type":"Point"}
}