{
  "type": "Feature",
  "properties": {
    "iso:country":"US",
    "sg:address":"540 Prairie Ln",
    "sg:city":"South Sioux City",
    "sg:classifiers":[
        {
            "category":"Professional",
            "type":"Services"
        }
    ],
    "sg:phone":"+1 402 494 5408",
    "sg:postcode":"68776",
    "sg:province":"NE",
    "wof:name":"Mechwerks",
    "wof:placetype":"venue"
},
  "geometry": {"coordinates":[-96.44528800000001,42.442379],"type":"Point"}
}