{
  "type": "Feature",
  "properties": {
    "addr:full":"6224 S 150th St Omaha NE 68137",
    "addr:housenumber":"6224",
    "addr:postcode":"68137",
    "addr:street":"S 150Th St",
    "iso:country":"US",
    "sg:address":"6224 S 150th St",
    "sg:city":"Omaha",
    "sg:classifiers":[
        {
            "category":"Arts & Performance",
            "subcategory":"Theater",
            "type":"Entertainment"
        }
    ],
    "sg:phone":"+1 402 896 6097",
    "sg:postcode":"68137",
    "sg:province":"NE",
    "sg:tags":[
        "musician"
    ],
    "wof:name":"Gerard Music Co",
    "wof:placetype":"venue"
},
  "geometry": {"coordinates":[-96.148112,41.192365],"type":"Point"}
}