{
  "type": "Feature",
  "properties": {
    "addr:full":"646 Main St Plattsmouth NE 68048",
    "addr:housenumber":"646",
    "addr:postcode":"68048",
    "addr:street":"Main St",
    "iso:country":"US",
    "sg:address":"646 Main St",
    "sg:city":"Plattsmouth",
    "sg:classifiers":[
        {
            "category":"Museum",
            "type":"Entertainment"
        }
    ],
    "sg:phone":"+1 402 296 4770",
    "sg:postcode":"68048",
    "sg:province":"NE",
    "sg:tags":[
        "place",
        "historical"
    ],
    "wof:name":"Cass County Historical Museum",
    "wof:placetype":"venue"
},
  "geometry": {"coordinates":[-95.886791,41.011184],"type":"Point"}
}