{
  "type": "Feature",
  "properties": {
    "addr:city":"Plattsmouth",
    "addr:full":"646 Main St Plattsmouth, Ne 68048-1852",
    "addr:house_number":"646",
    "addr:housenumber":"646",
    "addr:phone":"+1 402-296-4770",
    "addr:postcode":"68048-1852",
    "addr:road":"Main St",
    "addr:state":"NE",
    "addr:street":"Main St",
    "iso:country":"US",
    "sg:address":"646 Main St",
    "sg:city":"Plattsmouth",
    "sg:classifiers":[
        {
            "category":"Museum",
            "type":"Entertainment"
        }
    ],
    "sg:phone":"+1 402 296 4770",
    "sg:postcode":"68048",
    "sg:province":"NE",
    "sg:tags":[
        "place",
        "historical"
    ],
    "wof:airports":[
        102529985
    ],
    "wof:name":"Cass County Historical Society Foundation",
    "wof:placetype":"venue"
},
  "geometry": {"coordinates":[-95.88687,41.01127],"type":"Point"}
}