{
  "type": "Feature",
  "properties": {
    "iso:country":"US",
    "sg:address":"1205 Co Rd 2000",
    "sg:city":"Wilber",
    "sg:phone":"+1 402 821 3138",
    "sg:postcode":"68465",
    "sg:province":"NE",
    "sg:tags":[
        "farm",
        "corn",
        "wheat",
        "soybean"
    ],
    "wof:name":"Kastanek John",
    "wof:placetype":"venue"
},
  "geometry": {"coordinates":[-97.00749999999999,40.537502],"type":"Point"}
}