{
  "type": "Feature",
  "properties": {
    "iso:country":"US",
    "sg:address":"630 Pioneer Ave",
    "sg:city":"Alliance",
    "sg:classifiers":[
        {
            "category":"Building & Trades",
            "subcategory":"Electrical",
            "type":"Services"
        }
    ],
    "sg:phone":"+1 308 762 5346",
    "sg:postcode":"69301",
    "sg:province":"NE",
    "sg:tags":[
        "electrical",
        "contractor"
    ],
    "wof:name":"Neils Electric Service",
    "wof:placetype":"venue"
},
  "geometry": {"coordinates":[-102.84101200000001,42.087751],"type":"Point"}
}