{
  "type": "Feature",
  "properties": {
    "iso:country":"US",
    "sg:address":"601 Central Ave",
    "sg:city":"Nebraska City",
    "sg:classifiers":[
        {
            "category":"Social Services",
            "type":"Services"
        }
    ],
    "sg:phone":"+1 402 873 5447",
    "sg:postcode":"68410",
    "sg:province":"NE",
    "sg:tags":[
        "counselor",
        "marriage",
        "family"
    ],
    "wof:name":"Better Living Counseling Svc",
    "wof:placetype":"venue"
},
  "geometry": {"coordinates":[-95.85377099999999,40.676575],"type":"Point"}
}