{
  "type": "Feature",
  "properties": {
    "iso:country":"US",
    "sg:address":"6514 N 91st Plz",
    "sg:city":"Omaha",
    "sg:classifiers":[
        {
            "category":"Utilities",
            "subcategory":"Refuse",
            "type":"Services"
        }
    ],
    "sg:phone":"+1 402 571 7562",
    "sg:postcode":"68134",
    "sg:province":"NE",
    "sg:tags":[
        "garbage",
        "collection"
    ],
    "wof:name":"Weekly Pick Up Svc",
    "wof:placetype":"venue"
},
  "geometry": {"coordinates":[-96.054605,41.317249],"type":"Point"}
}