{
  "type": "Feature",
  "properties": {
    "iso:country":"US",
    "sg:address":"520 Harrison St",
    "sg:city":"Beemer",
    "sg:classifiers":[
        {
            "category":"Farming",
            "subcategory":"Farm",
            "type":"Manufacturing & Wholesale Goods"
        }
    ],
    "sg:phone":"+1 402 528 3663",
    "sg:postcode":"68716",
    "sg:province":"NE",
    "sg:tags":[
        "crop",
        "general"
    ],
    "wof:name":"Batenhorst Winfred Farm",
    "wof:placetype":"venue"
},
  "geometry": {"coordinates":[-96.80474700000001,41.932788],"type":"Point"}
}