{
  "type": "Feature",
  "properties": {
    "iso:country":"US",
    "sg:address":"4504 Central Ave",
    "sg:city":"Kearney",
    "sg:classifiers":[
        {
            "category":"Freight",
            "type":"Transportation"
        }
    ],
    "sg:phone":"+1 308 234 4364",
    "sg:postcode":"68847",
    "sg:province":"NE",
    "sg:tags":[
        "operator",
        "local",
        "trucking"
    ],
    "wof:name":"Donald Unick",
    "wof:placetype":"venue"
},
  "geometry": {"coordinates":[-99.081215,40.718645],"type":"Point"}
}