{
  "type": "Feature",
  "properties": {
    "iso:country":"US",
    "sg:address":"1622 Co Rd C",
    "sg:city":"Scribner",
    "sg:phone":"+1 402 664 3302",
    "sg:postcode":"68057",
    "sg:province":"NE",
    "sg:tags":[
        "farm",
        "corn"
    ],
    "wof:name":"Fred Hasemann",
    "wof:placetype":"venue"
},
  "geometry": {"coordinates":[-96.606357,41.712993],"type":"Point"}
}