{
  "type": "Feature",
  "properties": {
    "iso:country":"US",
    "sg:address":"807 S X Rd",
    "sg:city":"Henderson",
    "sg:phone":"+1 402 723 5881",
    "sg:postcode":"68371",
    "sg:province":"NE",
    "sg:tags":[
        "farm",
        "corn"
    ],
    "wof:name":"Thieszen L Farm",
    "wof:placetype":"venue"
},
  "geometry": {"coordinates":[-97.86410100000001,40.808383],"type":"Point"}
}