{
  "type": "Feature",
  "properties": {
    "addr:full":"1721 E 6th St North Platte NE 69101",
    "addr:housenumber":"1721",
    "addr:postcode":"69101",
    "addr:street":"E 6Th St",
    "iso:country":"US",
    "sg:address":"1721 E 6th St",
    "sg:city":"North Platte",
    "sg:classifiers":[
        {
            "category":"Retail",
            "subcategory":"Auto Repair",
            "type":"Services"
        }
    ],
    "sg:phone":"+1 308 532 0337",
    "sg:postcode":"69101",
    "sg:province":"NE",
    "sg:tags":[
        "body",
        "automobile",
        "painting"
    ],
    "wof:name":"Evan Brown's Collision Ctr Inc",
    "wof:placetype":"venue"
},
  "geometry": {"coordinates":[-100.743253,41.135915],"type":"Point"}
}