{
  "type": "Feature",
  "properties": {
    "iso:country":"US",
    "sg:address":"306 N Farragut St",
    "sg:city":"West Point",
    "sg:classifiers":[
        {
            "category":"Professional",
            "subcategory":"Business Services",
            "type":"Services"
        }
    ],
    "sg:phone":"+1 402 372 2167",
    "sg:postcode":"68788",
    "sg:province":"NE",
    "sg:tags":[
        "interior",
        "designer"
    ],
    "wof:name":"Interiors Unlimited Inc",
    "wof:placetype":"venue"
},
  "geometry": {"coordinates":[-96.70534499999999,41.842858],"type":"Point"}
}