{
  "type": "Feature",
  "properties": {
    "addr:full":"2205 N 6th St Beatrice NE 68310",
    "addr:housenumber":"2205",
    "addr:postcode":"68310",
    "addr:street":"N 6Th St",
    "iso:country":"US",
    "sg:address":"2205 N 6th St",
    "sg:city":"Beatrice",
    "sg:classifiers":[
        {
            "category":"Food & Beverages",
            "subcategory":"Specialty",
            "type":"Retail Goods"
        }
    ],
    "sg:phone":"+1 402 223 2376",
    "sg:postcode":"68310",
    "sg:province":"NE",
    "sg:tags":[
        "health",
        "diet"
    ],
    "wof:name":"GNC",
    "wof:placetype":"venue"
},
  "geometry": {"coordinates":[-96.74688,40.286732],"type":"Point"}
}