{
  "type": "Feature",
  "properties": {
    "iso:country":"US",
    "sg:address":"305 N 3rd St",
    "sg:city":"Arlington",
    "sg:classifiers":[
        {
            "category":"Government",
            "subcategory":"Office",
            "type":"Public Place"
        }
    ],
    "sg:phone":"+1 402 478 4774",
    "sg:postcode":"68002",
    "sg:province":"NE",
    "sg:tags":[
        "village"
    ],
    "wof:name":"Arlington Nutrition Site",
    "wof:placetype":"venue"
},
  "geometry": {"coordinates":[-96.351043,41.453683],"type":"Point"}
}