{
  "type": "Feature",
  "properties": {
    "iso:country":"US",
    "sg:address":"341 N 6th St",
    "sg:city":"Seward",
    "sg:classifiers":[
        {
            "category":"Insurance",
            "subcategory":"Insurance Agent",
            "type":"Services"
        }
    ],
    "sg:phone":"+1 402 643 2900",
    "sg:postcode":"68434",
    "sg:province":"NE",
    "wof:name":"Kolterman Agency Inc",
    "wof:placetype":"venue"
},
  "geometry": {"coordinates":[-97.09921,40.910272],"type":"Point"}
}