{
  "type": "Feature",
  "properties": {
    "iso:country":"US",
    "sg:address":"10905 Cottonwood Ln",
    "sg:city":"Omaha",
    "sg:classifiers":[
        {
            "category":"Professional",
            "subcategory":"Business Services",
            "type":"Services"
        }
    ],
    "sg:phone":"+1 402 614 9680",
    "sg:postcode":"68164",
    "sg:province":"NE",
    "sg:tags":[
        "medical",
        "consultants-medical",
        "administration",
        "billing"
    ],
    "wof:name":"Accurate Medical Billing Inc.",
    "wof:placetype":"venue"
},
  "geometry": {"coordinates":[-96.083996,41.285964],"type":"Point"}
}