{
  "type": "Feature",
  "properties": {
    "addr:full":"6601 S 84th St Lincoln NE 68516",
    "addr:housenumber":"6601",
    "addr:postcode":"68516",
    "addr:street":"S 84Th St",
    "iso:country":"US",
    "sg:address":"6601 S 84th St",
    "sg:city":"Lincoln",
    "sg:classifiers":[
        {
            "category":"Sports & Exercise",
            "subcategory":"Golf",
            "type":"Entertainment"
        }
    ],
    "sg:phone":"+1 402 488 7105",
    "sg:postcode":"68516",
    "sg:province":"NE",
    "sg:tags":[
        "course"
    ],
    "wof:name":"Pine Lake Golf & Tennis",
    "wof:placetype":"venue"
},
  "geometry": {"coordinates":[-96.606184,40.743589],"type":"Point"}
}