{
  "type": "Feature",
  "properties": {
    "addr:full":"511 N 20th St Dakota City NE 68731",
    "addr:housenumber":"511",
    "addr:postcode":"68731",
    "addr:street":"N 20Th St",
    "iso:country":"US",
    "sg:address":"511 N 20th St",
    "sg:city":"Dakota City",
    "sg:classifiers":[
        {
            "category":"Manufacturing",
            "subcategory":"Chemicals & Compounds",
            "type":"Manufacturing & Wholesale Goods"
        }
    ],
    "sg:phone":"+1 402 987 3766",
    "sg:postcode":"68731",
    "sg:province":"NE",
    "wof:name":"Elementis LTP Inc",
    "wof:placetype":"venue"
},
  "geometry": {"coordinates":[-96.42411300000001,42.422079],"type":"Point"}
}