{
  "type": "Feature",
  "properties": {
    "iso:country":"US",
    "sg:address":"85160 563rd Ave",
    "sg:city":"Winside",
    "sg:classifiers":[
        {
            "category":"Farming",
            "subcategory":"Farm & Veterinary Services",
            "type":"Manufacturing & Wholesale Goods"
        }
    ],
    "sg:phone":"+1 402 286 4117",
    "sg:postcode":"68740",
    "sg:province":"NE",
    "sg:tags":[
        "breeder",
        "livestock"
    ],
    "wof:name":"Premium Pork",
    "wof:placetype":"venue"
},
  "geometry": {"coordinates":[-97.27130099999999,42.172351],"type":"Point"}
}