{
  "type": "Feature",
  "properties": {
    "addr:full":"3405 Oak View Dr Omaha NE 68144",
    "addr:housenumber":"3405",
    "addr:postcode":"68144",
    "addr:street":"Oak View Dr",
    "iso:country":"US",
    "sg:address":"3405 Oak View Dr",
    "sg:city":"Omaha",
    "sg:classifiers":[
        {
            "category":"Banks & Credit Unions",
            "subcategory":"Bank",
            "type":"Services"
        }
    ],
    "sg:phone":"+1 402 758 9164",
    "sg:postcode":"68144",
    "sg:province":"NE",
    "sg:tags":[
        "federal"
    ],
    "wof:name":"Commercial Federal Bank",
    "wof:placetype":"venue"
},
  "geometry": {"coordinates":[-96.13473999999999,41.226762],"type":"Point"}
}