{
  "type": "Feature",
  "properties": {
    "iso:country":"US",
    "sg:address":"4436 Dahlman Ave",
    "sg:city":"Omaha",
    "sg:classifiers":[
        {
            "category":"Wholesale",
            "subcategory":"Books, Periodicals, & Newspapers",
            "type":"Manufacturing & Wholesale Goods"
        }
    ],
    "sg:phone":"+1 402 734 3333",
    "sg:postcode":"68107",
    "sg:province":"NE",
    "sg:tags":[
        "magazine"
    ],
    "wof:name":"Gopher News Inc",
    "wof:placetype":"venue"
},
  "geometry": {"coordinates":[-95.958618,41.21443],"type":"Point"}
}