{
  "type": "Feature",
  "properties": {
    "iso:country":"US",
    "sg:address":"308 Caribou St",
    "sg:city":"Farnam",
    "sg:classifiers":[
        {
            "category":"Organizations",
            "subcategory":"Religious Organization",
            "type":"Services"
        }
    ],
    "sg:phone":"+1 308 569 2532",
    "sg:postcode":"69029",
    "sg:province":"NE",
    "sg:tags":[
        "church"
    ],
    "wof:name":"United Methodist Church",
    "wof:placetype":"venue"
},
  "geometry": {"coordinates":[-100.21542700000001,40.709761],"type":"Point"}
}