{
  "type": "Feature",
  "properties": {
    "addr:full":"2400 N Lincoln Ave Fremont NE 68025",
    "addr:housenumber":"2400",
    "addr:postcode":"68025",
    "addr:street":"N Lincoln Ave",
    "iso:country":"US",
    "sg:address":"2400 N Lincoln Ave",
    "sg:city":"Fremont",
    "sg:classifiers":[
        {
            "category":"Professional",
            "subcategory":"Business Services",
            "type":"Services"
        }
    ],
    "sg:phone":"+1 402 721 1631",
    "sg:postcode":"68025",
    "sg:province":"NE",
    "sg:tags":[
        "telemarketing"
    ],
    "wof:name":"Transaction Teleservices",
    "wof:placetype":"venue"
},
  "geometry": {"coordinates":[-96.478082,41.452965],"type":"Point"}
}