{
  "type": "Feature",
  "properties": {
    "iso:country":"US",
    "sg:address":"2340 Cornhusker Rd",
    "sg:city":"Bellevue",
    "sg:classifiers":[
        {
            "category":"Restaurant",
            "type":"Food & Drink"
        }
    ],
    "sg:menulink":"http://www.allmenus.com/ne/highland-ii/129496-subway/menu/",
    "sg:phone":"+1 402 292 3845",
    "sg:postcode":"68123",
    "sg:province":"NE",
    "sg:tags":[
        "american",
        "sandwich"
    ],
    "wof:name":"Subway",
    "wof:placetype":"venue"
},
  "geometry": {"coordinates":[-95.94598499999999,41.159397],"type":"Point"}
}