{
  "type": "Feature",
  "properties": {
    "iso:country":"US",
    "sg:address":"1703 Phillip Ave",
    "sg:city":"Norfolk",
    "sg:classifiers":[
        {
            "category":"Education",
            "subcategory":"School",
            "type":"Public Place"
        }
    ],
    "sg:phone":"+1 402 644 2561",
    "sg:postcode":"68701",
    "sg:province":"NE",
    "wof:name":"Westside Grade School",
    "wof:placetype":"venue"
},
  "geometry": {"coordinates":[-97.43323700000001,42.030095],"type":"Point"}
}