{
  "type": "Feature",
  "properties": {
    "iso:country":"US",
    "sg:address":"4502 Center St",
    "sg:city":"Omaha",
    "sg:classifiers":[
        {
            "category":"Banks & Credit Unions",
            "subcategory":"Bank",
            "type":"Services"
        }
    ],
    "sg:phone":"+1 402 556 2012",
    "sg:postcode":"68106",
    "sg:province":"NE",
    "wof:name":"Moore Jeff Ins",
    "wof:placetype":"venue"
},
  "geometry": {"coordinates":[-95.980698,41.2416],"type":"Point"}
}