{
  "type": "Feature",
  "properties": {
    "iso:country":"US",
    "sg:address":"1439 N 9th St",
    "sg:city":"David City",
    "sg:phone":"+1 402 367 3789",
    "sg:postcode":"68632",
    "sg:province":"NE",
    "sg:tags":[
        "farm",
        "corn",
        "soybean"
    ],
    "wof:name":"Kastl Brothers",
    "wof:placetype":"venue"
},
  "geometry": {"coordinates":[-97.122778,41.264116],"type":"Point"}
}