{
  "type": "Feature",
  "properties": {
    "addr:full":"5415 N 72nd St Omaha NE 68134",
    "addr:housenumber":"5415",
    "addr:postcode":"68134",
    "addr:street":"N 72Nd St",
    "iso:country":"US",
    "sg:address":"5415 N 72nd St",
    "sg:city":"Omaha",
    "sg:classifiers":[
        {
            "category":"Recreation",
            "type":"Entertainment"
        }
    ],
    "sg:phone":"+1 402 571 4653",
    "sg:postcode":"68134",
    "sg:province":"NE",
    "sg:tags":[
        "range",
        "practice",
        "golf"
    ],
    "wof:name":"Practice Tee",
    "wof:placetype":"venue"
},
  "geometry": {"coordinates":[-96.023748,41.308221],"type":"Point"}
}