{
  "type": "Feature",
  "properties": {
    "iso:country":"US",
    "sg:address":"601 E 1st St",
    "sg:city":"Mc Cook",
    "sg:classifiers":[
        {
            "category":"Social Services",
            "subcategory":"Child Care",
            "type":"Services"
        }
    ],
    "sg:phone":"+1 308 345 6385",
    "sg:postcode":"69001",
    "sg:province":"NE",
    "sg:tags":[
        "day"
    ],
    "wof:name":"Ahlers Pamela Day Care",
    "wof:placetype":"venue"
},
  "geometry": {"coordinates":[-100.62433,40.203675],"type":"Point"}
}