{
  "type": "Feature",
  "properties": {
    "iso:country":"US",
    "sg:address":"1305 Rodeo Rd",
    "sg:city":"North Platte",
    "sg:classifiers":[
        {
            "category":"Building & Trades",
            "subcategory":"Construction",
            "type":"Services"
        }
    ],
    "sg:phone":"+1 308 532 8760",
    "sg:postcode":"69101",
    "sg:province":"NE",
    "sg:tags":[
        "paving",
        "contractor"
    ],
    "wof:name":"General Paving Co",
    "wof:placetype":"venue"
},
  "geometry": {"coordinates":[-100.776966,41.148101],"type":"Point"}
}