{
  "type": "Feature",
  "properties": {
    "iso:country":"US",
    "sg:address":"9009 N 216th St",
    "sg:city":"Elkhorn",
    "sg:classifiers":[
        {
            "category":"Building & Trades",
            "subcategory":"Construction",
            "type":"Services"
        }
    ],
    "sg:phone":"+1 402 289 4920",
    "sg:postcode":"68022",
    "sg:province":"NE",
    "sg:tags":[
        "general",
        "contractor"
    ],
    "wof:name":"Goss Mann Construction Co",
    "wof:placetype":"venue"
},
  "geometry": {"coordinates":[-96.253666,41.341004],"type":"Point"}
}