{
  "type": "Feature",
  "properties": {
    "iso:country":"US",
    "sg:address":"3706 S 132nd St",
    "sg:city":"Omaha",
    "sg:classifiers":[
        {
            "category":"Manufacturing",
            "subcategory":"Tools & Machinery",
            "type":"Manufacturing & Wholesale Goods"
        }
    ],
    "sg:phone":"+1 402 330 5050",
    "sg:postcode":"68144",
    "sg:province":"NE",
    "sg:tags":[
        "mfg",
        "lithographic",
        "commercial",
        "trade",
        "p",
        "printing"
    ],
    "wof:name":"Sir Speedy",
    "wof:placetype":"venue"
},
  "geometry": {"coordinates":[-96.119528,41.221561],"type":"Point"}
}