{
  "type": "Feature",
  "properties": {
    "addr:full":"303 S Robinson Ave Hartington NE 68739",
    "addr:housenumber":"303",
    "addr:postcode":"68739",
    "addr:street":"S Robinson Ave",
    "iso:country":"US",
    "sg:address":"303 S Robinson Ave",
    "sg:city":"Hartington",
    "sg:classifiers":[
        {
            "category":"Food & Beverages",
            "subcategory":"Liquor & Beverages",
            "type":"Retail Goods"
        }
    ],
    "sg:phone":"+1 402 254 6771",
    "sg:postcode":"68739",
    "sg:province":"NE",
    "wof:name":"Scott's Package Liquor",
    "wof:placetype":"venue"
},
  "geometry": {"coordinates":[-97.269425,42.618669],"type":"Point"}
}