{
  "type": "Feature",
  "properties": {
    "iso:country":"US",
    "sg:address":"609 Clay St",
    "sg:city":"Tecumseh",
    "sg:classifiers":[
        {
            "category":"Government",
            "subcategory":"Office",
            "type":"Public Place"
        }
    ],
    "sg:phone":"+1 402 335 3676",
    "sg:postcode":"68450",
    "sg:province":"NE",
    "sg:tags":[
        "village"
    ],
    "wof:name":"Tecumseh Power Plant",
    "wof:placetype":"venue"
},
  "geometry": {"coordinates":[-96.191011,40.366648],"type":"Point"}
}