{
  "type": "Feature",
  "properties": {
    "addr:full":"617 Chief St Benkelman NE 69021",
    "addr:housenumber":"617",
    "addr:postcode":"69021",
    "addr:street":"Chief St",
    "iso:country":"US",
    "sg:address":"617 Chief St",
    "sg:city":"Benkelman",
    "sg:classifiers":[
        {
            "category":"Shopping",
            "subcategory":"Optical Goods",
            "type":"Retail Goods"
        }
    ],
    "sg:phone":"+1 308 423 2152",
    "sg:postcode":"69021",
    "sg:province":"NE",
    "sg:tags":[
        "contact",
        "lense"
    ],
    "wof:name":"Burrows Vision Clinic LLC",
    "wof:placetype":"venue"
},
  "geometry": {"coordinates":[-101.53299,40.049318],"type":"Point"}
}