{
  "type": "Feature",
  "properties": {
    "iso:country":"US",
    "sg:address":"1413 K St",
    "sg:city":"Fairbury",
    "sg:classifiers":[
        {
            "category":"Restaurant",
            "type":"Food & Drink"
        }
    ],
    "sg:menulink":"http://www.allmenus.com/ne/fairbury/129466-subway/menu/",
    "sg:phone":"+1 402 729 3995",
    "sg:postcode":"68352",
    "sg:province":"NE",
    "sg:tags":[
        "american",
        "sandwich"
    ],
    "wof:name":"Subway",
    "wof:placetype":"venue"
},
  "geometry": {"coordinates":[-97.171167,40.14669],"type":"Point"}
}