{
  "type": "Feature",
  "properties": {
    "iso:country":"US",
    "sg:address":"4224 S 89th St",
    "sg:city":"Omaha",
    "sg:classifiers":[
        {
            "category":"Autos & Motor Vehicles",
            "subcategory":"Automobile Sales",
            "type":"Retail Goods"
        }
    ],
    "sg:phone":"+1 402 331 8200",
    "sg:postcode":"68127",
    "sg:province":"NE",
    "sg:tags":[
        "shop",
        "repair",
        "used",
        "general"
    ],
    "wof:name":"A-1 Body",
    "wof:placetype":"venue"
},
  "geometry": {"coordinates":[-96.049009,41.219162],"type":"Point"}
}