{
  "type": "Feature",
  "properties": {
    "iso:country":"US",
    "sg:address":"Braiker Brandeis",
    "sg:city":"Omaha",
    "sg:classifiers":[
        {
            "category":"Restaurant",
            "type":"Food & Drink"
        }
    ],
    "sg:phone":"+1 402 341 0779",
    "sg:postcode":"68102",
    "sg:province":"NE",
    "wof:name":"Little King Deli & Subs",
    "wof:placetype":"venue"
},
  "geometry": {"coordinates":[-95.937202,41.258499],"type":"Point"}
}