{
  "type": "Feature",
  "properties": {
    "addr:full":"1807 Lloyd St Bellevue NE 68005",
    "addr:housenumber":"1807",
    "addr:postcode":"68005",
    "addr:street":"Lloyd St",
    "iso:country":"US",
    "sg:address":"1807 Lloyd St",
    "sg:city":"Bellevue",
    "sg:classifiers":[
        {
            "category":"Manufacturing",
            "subcategory":"Printing",
            "type":"Manufacturing & Wholesale Goods"
        }
    ],
    "sg:phone":"+1 402 292 0819",
    "sg:postcode":"68005",
    "sg:province":"NE",
    "sg:tags":[
        "printer"
    ],
    "wof:name":"K M Printing",
    "wof:placetype":"venue"
},
  "geometry": {"coordinates":[-95.918109,41.148487],"type":"Point"}
}