{
  "type": "Feature",
  "properties": {
    "addr:full":"3027 E 38th St Columbus NE 68601",
    "addr:housenumber":"3027",
    "addr:postcode":"68601",
    "addr:street":"E 38Th St",
    "iso:country":"US",
    "sg:address":"3027 E 38th St",
    "sg:city":"Columbus",
    "sg:classifiers":[
        {
            "category":"Organizations",
            "subcategory":"Religious Organization",
            "type":"Services"
        }
    ],
    "sg:phone":"+1 402 562 5647",
    "sg:postcode":"68601",
    "sg:province":"NE",
    "sg:tags":[
        "church"
    ],
    "wof:name":"Columbus Berean Church",
    "wof:placetype":"venue"
},
  "geometry": {"coordinates":[-97.287451,41.453043],"type":"Point"}
}