{
  "type": "Feature",
  "properties": {
    "iso:country":"US",
    "sg:address":"330 S 44th St",
    "sg:city":"Omaha",
    "sg:classifiers":[
        {
            "category":"Education",
            "subcategory":"School",
            "type":"Public Place"
        }
    ],
    "sg:phone":"+1 402 554 6771",
    "sg:postcode":"68131",
    "sg:province":"NE",
    "sg:tags":[
        "high",
        "middle",
        "elementary"
    ],
    "wof:name":"Omaha Public Schools",
    "wof:placetype":"venue"
},
  "geometry": {"coordinates":[-95.978782,41.257666],"type":"Point"}
}