{
  "type": "Feature",
  "properties": {
    "addr:full":"204 2nd St Verdigre NE 68783",
    "addr:housenumber":"204",
    "addr:postcode":"68783",
    "addr:street":"2Nd St",
    "iso:country":"US",
    "sg:address":"204 2nd St",
    "sg:city":"Verdigre",
    "sg:classifiers":[
        {
            "category":"Education",
            "subcategory":"School",
            "type":"Public Place"
        }
    ],
    "sg:phone":"+1 402 668 2275",
    "sg:postcode":"68783",
    "sg:province":"NE",
    "wof:name":"Verdigre Jr Sr High School",
    "wof:placetype":"venue"
},
  "geometry": {"coordinates":[-98.03701100000001,42.604186],"type":"Point"}
}