{
  "type": "Feature",
  "properties": {
    "addr:full":"381 Co Rd 8 Ashland NE 68003",
    "addr:housenumber":"381",
    "addr:postcode":"68003",
    "addr:street":"Co Rd 8",
    "iso:country":"US",
    "sg:address":"381 Co Rd 8",
    "sg:city":"Ashland",
    "sg:phone":"+1 402 944 2480",
    "sg:postcode":"68003",
    "sg:province":"NE",
    "sg:tags":[
        "beef",
        "farm",
        "corn",
        "cash",
        "grain",
        "soybean",
        "cattle"
    ],
    "wof:name":"Hanson Bros",
    "wof:placetype":"venue"
},
  "geometry": {"coordinates":[-96.44481399999999,41.058356],"type":"Point"}
}