{
  "type": "Feature",
  "properties": {
    "iso:country":"US",
    "sg:address":"3222 S 5th St",
    "sg:city":"Omaha",
    "sg:classifiers":[
        {
            "category":"Building & Trades",
            "subcategory":"Locksmith",
            "type":"Services"
        }
    ],
    "sg:phone":"+1 402 881 3828",
    "sg:postcode":"68108",
    "sg:province":"NE",
    "sg:tags":[
        "key"
    ],
    "wof:name":"3 Always A Locksmith",
    "wof:placetype":"venue"
},
  "geometry": {"coordinates":[-95.92283500000001,41.22927],"type":"Point"}
}