{
  "type": "Feature",
  "properties": {
    "iso:country":"US",
    "sg:address":"643 G St",
    "sg:city":"Pawnee City",
    "sg:classifiers":[
        {
            "category":"Shopping",
            "subcategory":"Pharmacy",
            "type":"Retail Goods"
        }
    ],
    "sg:phone":"+1 402 852 2321",
    "sg:postcode":"68420",
    "sg:province":"NE",
    "wof:name":"Pete's Pharmacy",
    "wof:placetype":"venue"
},
  "geometry": {"coordinates":[-96.153063,40.109045],"type":"Point"}
}