{
  "type": "Feature",
  "properties": {
    "addr:full":"451 N Central Ave Superior NE 68978",
    "addr:housenumber":"451",
    "addr:postcode":"68978",
    "addr:street":"N Central Ave",
    "iso:country":"US",
    "sg:address":"451 N Central Ave",
    "sg:city":"Superior",
    "sg:classifiers":[
        {
            "category":"Social Services",
            "type":"Services"
        }
    ],
    "sg:phone":"+1 402 879 4038",
    "sg:postcode":"68978",
    "sg:province":"NE",
    "sg:tags":[
        "organization",
        "welfare"
    ],
    "wof:name":"Midland Care Advocacy",
    "wof:placetype":"venue"
},
  "geometry": {"coordinates":[-98.071483,40.020404],"type":"Point"}
}