{
  "type": "Feature",
  "properties": {
    "addr:full":"312 Main St Verdigre NE 68783",
    "addr:housenumber":"312",
    "addr:postcode":"68783",
    "addr:street":"Main St",
    "iso:country":"US",
    "sg:address":"312 Main St",
    "sg:city":"Verdigre",
    "sg:phone":"+1 402 668 2627",
    "sg:postcode":"68783",
    "sg:province":"NE",
    "sg:tags":[
        "gas"
    ],
    "wof:name":"N & B Gas Co",
    "wof:placetype":"venue"
},
  "geometry": {"coordinates":[-98.03482099999999,42.602942],"type":"Point"}
}