{
  "type": "Feature",
  "properties": {
    "iso:country":"US",
    "sg:address":"14503 310th St",
    "sg:city":"Ashland",
    "sg:classifiers":[
        {
            "category":"Retail",
            "subcategory":"Animal Services",
            "type":"Services"
        }
    ],
    "sg:phone":"+1 402 944 2422",
    "sg:postcode":"68003",
    "sg:province":"NE",
    "wof:name":"Lakota Stables Inc",
    "wof:placetype":"venue"
},
  "geometry": {"coordinates":[-96.27404300000001,40.983684],"type":"Point"}
}