{
  "type": "Feature",
  "properties": {
    "iso:country":"US",
    "sg:address":"12941 Margo St",
    "sg:city":"Omaha",
    "sg:classifiers":[
        {
            "category":"Wholesale",
            "subcategory":"Construction Materials",
            "type":"Manufacturing & Wholesale Goods"
        }
    ],
    "sg:phone":"+1 402 895 6364",
    "sg:postcode":"68138",
    "sg:province":"NE",
    "sg:tags":[
        "fence"
    ],
    "wof:name":"Miller Custom Concrete & Fence",
    "wof:placetype":"venue"
},
  "geometry": {"coordinates":[-96.116327,41.184504],"type":"Point"}
}