{
  "type": "Feature",
  "properties": {
    "iso:country":"US",
    "sg:address":"1621 W 10th St",
    "sg:city":"Fremont",
    "sg:classifiers":[
        {
            "category":"Social Services",
            "subcategory":"Child Care",
            "type":"Services"
        }
    ],
    "sg:phone":"+1 402 721 1492",
    "sg:postcode":"68025",
    "sg:province":"NE",
    "sg:tags":[
        "day"
    ],
    "wof:name":"Dockerty Shawn Day Care",
    "wof:placetype":"venue"
},
  "geometry": {"coordinates":[-96.521188,41.439157],"type":"Point"}
}