{
  "type": "Feature",
  "properties": {
    "iso:country":"US",
    "sg:address":"113 S 16th St",
    "sg:city":"Aurora",
    "sg:classifiers":[
        {
            "category":"Building & Trades",
            "subcategory":"Equipment Rental",
            "type":"Services"
        }
    ],
    "sg:phone":"+1 402 694 6469",
    "sg:postcode":"68818",
    "sg:province":"NE",
    "sg:tags":[
        "yard"
    ],
    "wof:name":"ABC Rental",
    "wof:placetype":"venue"
},
  "geometry": {"coordinates":[-97.99664900000001,40.857684],"type":"Point"}
}