{
  "type": "Feature",
  "properties": {
    "iso:country":"US",
    "sg:address":"602 S Sherman St",
    "sg:city":"Holdrege",
    "sg:classifiers":[
        {
            "category":"Shopping",
            "type":"Retail Goods"
        }
    ],
    "sg:phone":"+1 308 995 8009",
    "sg:postcode":"68949",
    "sg:province":"NE",
    "sg:tags":[
        "monument"
    ],
    "wof:name":"Pristavec Monument",
    "wof:placetype":"venue"
},
  "geometry": {"coordinates":[-99.36452300000001,40.430827],"type":"Point"}
}