{
  "type": "Feature",
  "properties": {
    "iso:country":"US",
    "sg:address":"8442 Park Dr",
    "sg:city":"Omaha",
    "sg:classifiers":[
        {
            "category":"Shopping",
            "subcategory":"Jewelry",
            "type":"Retail Goods"
        }
    ],
    "sg:phone":"+1 402 339 2174",
    "sg:postcode":"68127",
    "sg:province":"NE",
    "sg:tags":[
        "repair",
        "jeweler"
    ],
    "wof:name":"Enrique's Jeweler",
    "wof:placetype":"venue"
},
  "geometry": {"coordinates":[-96.043646,41.200851],"type":"Point"}
}