{
  "type": "Feature",
  "properties": {
    "addr:full":"13302 Millard Ave Omaha NE 68137",
    "addr:housenumber":"13302",
    "addr:postcode":"68137",
    "addr:street":"Millard Ave",
    "iso:country":"US",
    "sg:address":"13302 Millard Ave",
    "sg:city":"Omaha",
    "sg:classifiers":[
        {
            "category":"Wholesale",
            "subcategory":"Groceries",
            "type":"Manufacturing & Wholesale Goods"
        }
    ],
    "sg:phone":"+1 402 896 5300",
    "sg:postcode":"68137",
    "sg:province":"NE",
    "sg:tags":[
        "food",
        "broker"
    ],
    "wof:name":"Regency Brokerage Inc",
    "wof:placetype":"venue"
},
  "geometry": {"coordinates":[-96.12357299999999,41.21019],"type":"Point"}
}