{
  "type": "Feature",
  "properties": {
    "addr:full":"10343 Pacific St Omaha NE 68114",
    "addr:housenumber":"10343",
    "addr:postcode":"68114",
    "addr:street":"Pacific St",
    "iso:country":"US",
    "sg:address":"10343 Pacific St",
    "sg:city":"Omaha",
    "sg:classifiers":[
        {
            "category":"Shopping",
            "subcategory":"Department Store",
            "type":"Retail Goods"
        }
    ],
    "sg:phone":"+1 402 391 6425",
    "sg:postcode":"68114",
    "sg:province":"NE",
    "wof:name":"Talbots",
    "wof:placetype":"venue"
},
  "geometry": {"coordinates":[-96.07592099999999,41.248684],"type":"Point"}
}