{
  "type": "Feature",
  "properties": {
    "iso:country":"US",
    "sg:address":"10114 Fieldcrest Dr",
    "sg:city":"Omaha",
    "sg:classifiers":[
        {
            "category":"Professional",
            "type":"Services"
        }
    ],
    "sg:phone":"+1 402 391 2391",
    "sg:postcode":"68114",
    "sg:province":"NE",
    "wof:name":"Sybil G Thailing Inc",
    "wof:placetype":"venue"
},
  "geometry": {"coordinates":[-96.073385,41.250948],"type":"Point"}
}