{
  "type": "Feature",
  "properties": {
    "addr:full":"1121 Butler Ave Lincoln NE 68521",
    "addr:housenumber":"1121",
    "addr:postcode":"68521",
    "addr:street":"Butler Ave",
    "iso:country":"US",
    "sg:address":"1121 Butler Ave",
    "sg:city":"Lincoln",
    "sg:classifiers":[
        {
            "category":"Shopping",
            "subcategory":"Hobbies, Toys, & Games",
            "type":"Retail Goods"
        }
    ],
    "sg:phone":"+1 402 435 4678",
    "sg:postcode":"68521",
    "sg:province":"NE",
    "wof:name":"Winfrey Sales",
    "wof:placetype":"venue"
},
  "geometry": {"coordinates":[-96.704188,40.841919],"type":"Point"}
}