{
  "type": "Feature",
  "properties": {
    "iso:country":"US",
    "sg:address":"414 S 10th St",
    "sg:city":"Omaha",
    "sg:classifiers":[
        {
            "category":"Restaurant",
            "type":"Food & Drink"
        }
    ],
    "sg:phone":"+1 402 991 5448",
    "sg:postcode":"68102",
    "sg:province":"NE",
    "sg:tags":[
        "caterer"
    ],
    "wof:name":"Das Rheinland",
    "wof:placetype":"venue"
},
  "geometry": {"coordinates":[-95.92932500000001,41.255618],"type":"Point"}
}