{
  "type": "Feature",
  "properties": {
    "addr:full":"930 S 48th St Omaha NE 68106",
    "addr:housenumber":"930",
    "addr:postcode":"68106",
    "addr:street":"S 48Th St",
    "iso:country":"US",
    "sg:address":"930 S 48th St",
    "sg:city":"Omaha",
    "sg:classifiers":[
        {
            "category":"Building & Trades",
            "subcategory":"Construction",
            "type":"Services"
        }
    ],
    "sg:phone":"+1 402 553 7000",
    "sg:postcode":"68106",
    "sg:province":"NE",
    "sg:tags":[
        "equipment",
        "industrial",
        "installation"
    ],
    "sg:website":"www.accesselevatorinc.com",
    "wof:name":"Access Elevator Inc",
    "wof:placetype":"venue"
},
  "geometry": {"coordinates":[-95.985501,41.251863],"type":"Point"}
}