{
  "type": "Feature",
  "properties": {
    "iso:country":"US",
    "sg:address":"8117 Park View Blvd",
    "sg:city":"La Vista",
    "sg:classifiers":[
        {
            "category":"Real Estate",
            "subcategory":"Real Estate Operator",
            "type":"Services"
        }
    ],
    "sg:phone":"+1 402 592 0525",
    "sg:postcode":"68128",
    "sg:province":"NE",
    "sg:tags":[
        "apartment"
    ],
    "wof:name":"Brentwood Townhomes",
    "wof:placetype":"venue"
},
  "geometry": {"coordinates":[-96.039309,41.18678],"type":"Point"}
}