{
  "type": "Feature",
  "properties": {
    "iso:country":"US",
    "sg:address":"4626 Englewood Ave",
    "sg:city":"Omaha",
    "sg:classifiers":[
        {
            "category":"Professional",
            "subcategory":"Computer Services",
            "type":"Services"
        }
    ],
    "sg:phone":"+1 402 933 9335",
    "sg:postcode":"68137",
    "sg:province":"NE",
    "sg:tags":[
        "repair"
    ],
    "wof:name":"America's Mobile Computer Tech",
    "wof:placetype":"venue"
},
  "geometry": {"coordinates":[-96.14002600000001,41.212176],"type":"Point"}
}