{
  "type": "Feature",
  "properties": {
    "iso:country":"US",
    "sg:address":"822 E 21st St",
    "sg:city":"Kearney",
    "sg:classifiers":[
        {
            "category":"Wholesale",
            "subcategory":"Farm Supplies",
            "type":"Manufacturing & Wholesale Goods"
        }
    ],
    "sg:phone":"+1 308 234 2569",
    "sg:postcode":"68847",
    "sg:province":"NE",
    "sg:tags":[
        "feed"
    ],
    "wof:name":"Mid-Nebraska Feed Inc",
    "wof:placetype":"venue"
},
  "geometry": {"coordinates":[-99.070623,40.696487],"type":"Point"}
}