{
  "type": "Feature",
  "properties": {
    "addr:full":"909 Illinois St Sidney NE 69162",
    "addr:housenumber":"909",
    "addr:postcode":"69162",
    "addr:street":"Illinois St",
    "iso:country":"US",
    "sg:address":"909 Illinois St",
    "sg:city":"Sidney",
    "sg:classifiers":[
        {
            "category":"Building & Trades",
            "subcategory":"Construction",
            "type":"Services"
        }
    ],
    "sg:phone":"+1 308 254 4027",
    "sg:postcode":"69162",
    "sg:province":"NE",
    "sg:tags":[
        "auto",
        "contractor",
        "glass",
        "replacement"
    ],
    "wof:name":"Sidney Glass",
    "wof:placetype":"venue"
},
  "geometry": {"coordinates":[-102.976669,41.144715],"type":"Point"}
}