{
  "type": "Feature",
  "properties": {
    "addr:full":"3641 Q St Omaha NE 68107",
    "addr:housenumber":"3641",
    "addr:postcode":"68107",
    "addr:street":"Q St",
    "iso:country":"US",
    "sg:address":"3641 Q St",
    "sg:city":"Omaha",
    "sg:classifiers":[
        {
            "category":"Autos & Motor Vehicles",
            "subcategory":"Automobile Sales",
            "type":"Retail Goods"
        }
    ],
    "sg:phone":"+1 402 734 0966",
    "sg:postcode":"68107",
    "sg:province":"NE",
    "sg:tags":[
        "car",
        "dealer"
    ],
    "wof:name":"A & R Auto Sales",
    "wof:placetype":"venue"
},
  "geometry": {"coordinates":[-95.96878700000001,41.205316],"type":"Point"}
}