{
  "type": "Feature",
  "properties": {
    "iso:country":"US",
    "sg:address":"4901 Walnut St",
    "sg:city":"Omaha",
    "sg:classifiers":[
        {
            "category":"Organizations",
            "subcategory":"Religious Organization",
            "type":"Services"
        }
    ],
    "sg:phone":"+1 402 556 4358",
    "sg:postcode":"68106",
    "sg:province":"NE",
    "sg:tags":[
        "clergy"
    ],
    "wof:name":"T J Redwycce",
    "wof:placetype":"venue"
},
  "geometry": {"coordinates":[-95.99022100000001,41.242073],"type":"Point"}
}