{
  "type": "Feature",
  "properties": {
    "addr:full":"113 S 7th St Nebraska City NE 68410",
    "addr:housenumber":"113",
    "addr:postcode":"68410",
    "addr:street":"S 7Th St",
    "iso:country":"US",
    "sg:address":"113 S 7th St",
    "sg:city":"Nebraska City",
    "sg:classifiers":[
        {
            "category":"Personal",
            "type":"Services"
        }
    ],
    "sg:phone":"+1 402 873 7311",
    "sg:postcode":"68410",
    "sg:province":"NE",
    "sg:tags":[
        "shop",
        "beauty"
    ],
    "wof:name":"Shear Magic",
    "wof:placetype":"venue"
},
  "geometry": {"coordinates":[-95.853713,40.675666],"type":"Point"}
}