{
  "type": "Feature",
  "properties": {
    "addr:full":"1710 S 10th St Omaha NE 68108",
    "addr:housenumber":"1710",
    "addr:postcode":"68108",
    "addr:street":"S 10Th St",
    "iso:country":"US",
    "sg:address":"1710 S 10th St",
    "sg:city":"Omaha",
    "sg:classifiers":[
        {
            "category":"Manufacturing",
            "subcategory":"Textiles",
            "type":"Manufacturing & Wholesale Goods"
        }
    ],
    "sg:phone":"+1 402 449 9121",
    "sg:postcode":"68108",
    "sg:province":"NE",
    "sg:tags":[
        "mill",
        "fabric"
    ],
    "wof:name":"C JS Saloon",
    "wof:placetype":"venue"
},
  "geometry": {"coordinates":[-95.92947100000001,41.241436],"type":"Point"}
}