{
  "type": "Feature",
  "properties": {
    "iso:country":"US",
    "sg:address":"335 W Elkhorn Dr",
    "sg:city":"Arlington",
    "sg:classifiers":[
        {
            "category":"Restaurant",
            "type":"Food & Drink"
        }
    ],
    "sg:phone":"+1 402 478 4191",
    "sg:postcode":"68002",
    "sg:province":"NE",
    "sg:tags":[
        "parlor",
        "ice",
        "cream"
    ],
    "wof:name":"Dairy King",
    "wof:placetype":"venue"
},
  "geometry": {"coordinates":[-96.351294,41.451256],"type":"Point"}
}