{
  "type": "Feature",
  "properties": {
    "iso:country":"US",
    "sg:address":"802 21st Ave",
    "sg:city":"Scottsbluff",
    "sg:classifiers":[
        {
            "category":"Restaurant",
            "type":"Food & Drink"
        }
    ],
    "sg:phone":"+1 308 632 3534",
    "sg:postcode":"69361",
    "sg:province":"NE",
    "wof:name":"El Charrito Restaurant",
    "wof:placetype":"venue"
},
  "geometry": {"coordinates":[-103.63628,41.855316],"type":"Point"}
}