{
  "type": "Feature",
  "properties": {
    "iso:country":"US",
    "sg:address":"2205 N 143rd Ave",
    "sg:city":"Omaha",
    "sg:classifiers":[
        {
            "category":"Building & Trades",
            "subcategory":"Plumbing",
            "type":"Services"
        }
    ],
    "sg:phone":"+1 402 493 6298",
    "sg:postcode":"68164",
    "sg:province":"NE",
    "sg:tags":[
        "contractor"
    ],
    "wof:name":"Parks Irrigation",
    "wof:placetype":"venue"
},
  "geometry": {"coordinates":[-96.137725,41.278782],"type":"Point"}
}