{
  "type": "Feature",
  "properties": {
    "addr:full":"3130 23rd St Columbus NE 68601",
    "addr:housenumber":"3130",
    "addr:postcode":"68601",
    "addr:street":"23Rd St",
    "iso:country":"US",
    "sg:address":"3130 23rd St",
    "sg:city":"Columbus",
    "sg:classifiers":[
        {
            "category":"Autos & Motor Vehicles",
            "subcategory":"Automobile Sales",
            "type":"Retail Goods"
        }
    ],
    "sg:phone":"+1 402 563 0255",
    "sg:postcode":"68601",
    "sg:province":"NE",
    "sg:tags":[
        "truck",
        "trailer"
    ],
    "wof:name":"Sahling Kenworth Inc",
    "wof:placetype":"venue"
},
  "geometry": {"coordinates":[-97.36647000000001,41.438778],"type":"Point"}
}