{
  "type": "Feature",
  "properties": {
    "iso:country":"US",
    "sg:address":"123 S 84th St",
    "sg:city":"Lincoln",
    "sg:classifiers":[
        {
            "category":"Personal",
            "subcategory":"Beauty Salon",
            "type":"Services"
        }
    ],
    "sg:phone":"+1 402 488 3050",
    "sg:postcode":"68510",
    "sg:province":"NE",
    "wof:name":"Elegant Face Permanent",
    "wof:placetype":"venue"
},
  "geometry": {"coordinates":[-96.60608499999999,40.813376],"type":"Point"}
}