{
  "type": "Feature",
  "properties": {
    "iso:country":"US",
    "sg:address":"1208 Stone St",
    "sg:city":"Falls City",
    "sg:classifiers":[
        {
            "category":"Retail",
            "subcategory":"Auto Repair",
            "type":"Services"
        }
    ],
    "sg:phone":"+1 402 245 5831",
    "sg:postcode":"68355",
    "sg:province":"NE",
    "sg:tags":[
        "repairing",
        "automobile"
    ],
    "wof:name":"Campbell Auto Repair",
    "wof:placetype":"venue"
},
  "geometry": {"coordinates":[-95.60283,40.05767],"type":"Point"}
}