{
  "type": "Feature",
  "properties": {
    "iso:country":"US",
    "sg:address":"312 W 9th St",
    "sg:city":"Mc Cook",
    "sg:classifiers":[
        {
            "category":"Banks & Credit Unions",
            "subcategory":"Investment Brokerage",
            "type":"Services"
        }
    ],
    "sg:phone":"+1 308 345 4533",
    "sg:postcode":"69001",
    "sg:province":"NE",
    "sg:tags":[
        "commodity",
        "contract"
    ],
    "wof:name":"Agri Marketing Service",
    "wof:placetype":"venue"
},
  "geometry": {"coordinates":[-100.637731,40.200492],"type":"Point"}
}