{
  "type": "Feature",
  "properties": {
    "iso:country":"US",
    "sg:address":"7016 Maple St",
    "sg:city":"Omaha",
    "sg:classifiers":[
        {
            "category":"Shopping",
            "subcategory":"Stationery & Office Supplies",
            "type":"Retail Goods"
        }
    ],
    "sg:phone":"+1 402 573 1133",
    "sg:postcode":"68104",
    "sg:province":"NE",
    "sg:tags":[
        "equipment",
        "filing",
        "system"
    ],
    "wof:name":"DBJ Office Products",
    "wof:placetype":"venue"
},
  "geometry": {"coordinates":[-96.020824,41.285121],"type":"Point"}
}