{
  "type": "Feature",
  "properties": {
    "iso:country":"US",
    "sg:address":"390 Hughbanks Rd",
    "sg:city":"Hay Springs",
    "sg:classifiers":[
        {
            "category":"Wholesale",
            "subcategory":"Farm Supplies",
            "type":"Manufacturing & Wholesale Goods"
        }
    ],
    "sg:phone":"+1 308 232 4580",
    "sg:postcode":"69347",
    "sg:province":"NE",
    "sg:tags":[
        "corn",
        "livestock",
        "soybean"
    ],
    "wof:name":"Rory Hughbanks",
    "wof:placetype":"venue"
},
  "geometry": {"coordinates":[-102.81007700000001,42.555062],"type":"Point"}
}