{
  "type": "Feature",
  "properties": {
    "iso:country":"US",
    "sg:address":"5616 Fort St",
    "sg:city":"Omaha",
    "sg:classifiers":[
        {
            "category":"Organizations",
            "subcategory":"Religious Organization",
            "type":"Services"
        }
    ],
    "sg:phone":"+1 402 455 5100",
    "sg:postcode":"68104",
    "sg:province":"NE",
    "wof:name":"Gods Missionary",
    "wof:placetype":"venue"
},
  "geometry": {"coordinates":[-96.004491,41.306835],"type":"Point"}
}