{
  "type": "Feature",
  "properties": {
    "iso:country":"US",
    "sg:address":"1570 33rd Ave",
    "sg:city":"Columbus",
    "sg:classifiers":[
        {
            "category":"Organizations",
            "subcategory":"Non-profit Organization",
            "type":"Services"
        }
    ],
    "sg:phone":"+1 402 564 8822",
    "sg:postcode":"68601",
    "sg:province":"NE",
    "sg:website":"www.phgsc.org",
    "wof:name":"Prairie Hills Girl Scouts",
    "wof:placetype":"venue"
},
  "geometry": {"coordinates":[-97.368334,41.432074],"type":"Point"}
}