{
  "type": "Feature",
  "properties": {
    "iso:country":"US",
    "sg:address":"3014 Ave C",
    "sg:city":"Scottsbluff",
    "sg:classifiers":[
        {
            "category":"Building & Trades",
            "subcategory":"Construction",
            "type":"Services"
        }
    ],
    "sg:phone":"+1 308 635 1285",
    "sg:postcode":"69361",
    "sg:province":"NE",
    "sg:tags":[
        "masonry",
        "contractor"
    ],
    "wof:name":"Robert Nation Inc",
    "wof:placetype":"venue"
},
  "geometry": {"coordinates":[-103.66712200000001,41.876],"type":"Point"}
}