{
  "type": "Feature",
  "properties": {
    "addr:full":"1422 R Rd Beemer NE 68716",
    "addr:housenumber":"1422",
    "addr:postcode":"68716",
    "addr:street":"R Rd",
    "iso:country":"US",
    "sg:address":"1422 R Rd",
    "sg:city":"Beemer",
    "sg:classifiers":[
        {
            "category":"Real Estate",
            "subcategory":"Real Estate Operator",
            "type":"Services"
        }
    ],
    "sg:phone":"+1 402 528 3627",
    "sg:postcode":"68716",
    "sg:province":"NE",
    "sg:tags":[
        "feedlot",
        "property",
        "beef",
        "lessor",
        "cattle"
    ],
    "wof:name":"Schantz Rueben Farm",
    "wof:placetype":"venue"
},
  "geometry": {"coordinates":[-96.764138,41.989183],"type":"Point"}
}