{
  "type": "Feature",
  "properties": {
    "addr:full":"3530 W 13th St Grand Island NE 68803",
    "addr:housenumber":"3530",
    "addr:postcode":"68803",
    "addr:street":"W 13Th St",
    "iso:country":"US",
    "sg:address":"3530 W 13th St",
    "sg:city":"Grand Island",
    "sg:classifiers":[
        {
            "category":"Restaurant",
            "type":"Food & Drink"
        }
    ],
    "sg:phone":"+1 308 389 3893",
    "sg:postcode":"68803",
    "sg:province":"NE",
    "wof:name":"Mc Donald's",
    "wof:placetype":"venue"
},
  "geometry": {"coordinates":[-98.388334,40.931599],"type":"Point"}
}