{
  "type": "Feature",
  "properties": {
    "iso:country":"US",
    "sg:address":"522 S 6th St",
    "sg:city":"Beatrice",
    "sg:classifiers":[
        {
            "category":"Autos & Motor Vehicles",
            "subcategory":"Automobile Sales",
            "type":"Retail Goods"
        }
    ],
    "sg:phone":"+1 402 223 5400",
    "sg:postcode":"68310",
    "sg:province":"NE",
    "sg:tags":[
        "car",
        "dealer"
    ],
    "wof:name":"Homestead Auto Co",
    "wof:placetype":"venue"
},
  "geometry": {"coordinates":[-96.746669,40.260773],"type":"Point"}
}