{
  "type": "Feature",
  "properties": {
    "iso:country":"US",
    "sg:address":"112 S Thayer St",
    "sg:city":"Spencer",
    "sg:classifiers":[
        {
            "category":"Utilities",
            "subcategory":"Water",
            "type":"Services"
        }
    ],
    "sg:phone":"+1 402 589 1502",
    "sg:postcode":"68777",
    "sg:province":"NE",
    "sg:tags":[
        "company",
        "sewage"
    ],
    "wof:name":"Rural Water District",
    "wof:placetype":"venue"
},
  "geometry": {"coordinates":[-98.701261,42.873846],"type":"Point"}
}