{
  "type": "Feature",
  "properties": {
    "addr:full":"134 S 13th St Lincoln NE 68502",
    "addr:housenumber":"134",
    "addr:postcode":"68502",
    "addr:street":"S 13Th St",
    "iso:country":"US",
    "sg:address":"134 S 13th St",
    "sg:city":"Lincoln",
    "sg:classifiers":[
        {
            "category":"Professional",
            "subcategory":"Management & Consulting",
            "type":"Services"
        }
    ],
    "sg:phone":"+1 402 438 2500",
    "sg:postcode":"68502",
    "sg:province":"NE",
    "sg:tags":[
        "business"
    ],
    "wof:name":"Gordon De Mars",
    "wof:placetype":"venue"
},
  "geometry": {"coordinates":[-96.7026,40.813583],"type":"Point"}
}