{
  "type": "Feature",
  "properties": {
    "iso:country":"US",
    "sg:address":"55762 852nd Rd",
    "sg:city":"Pierce",
    "sg:phone":"+1 402 371 2023",
    "sg:postcode":"68767",
    "sg:province":"NE",
    "sg:tags":[
        "farm",
        "corn"
    ],
    "wof:name":"Laubsch Eldred",
    "wof:placetype":"venue"
},
  "geometry": {"coordinates":[-97.381395,42.177767],"type":"Point"}
}