{
  "type": "Feature",
  "properties": {
    "iso:country":"US",
    "sg:address":"4959 NW Radial Hwy",
    "sg:city":"Omaha",
    "sg:classifiers":[
        {
            "category":"Building & Trades",
            "subcategory":"Construction",
            "type":"Services"
        }
    ],
    "sg:phone":"+1 402 551 2215",
    "sg:postcode":"68104",
    "sg:province":"NE",
    "sg:tags":[
        "air",
        "heating",
        "conditioning/hvac"
    ],
    "wof:name":"Hi-Tech Heating & Air Conditioning Inc",
    "wof:placetype":"venue"
},
  "geometry": {"coordinates":[-95.989152,41.281283],"type":"Point"}
}