{
  "type": "Feature",
  "properties": {
    "iso:country":"US",
    "sg:address":"635 N 46th St",
    "sg:city":"Omaha",
    "sg:classifiers":[
        {
            "category":"Restaurant",
            "type":"Food & Drink"
        }
    ],
    "sg:menulink":"http://www.allmenus.com/ne/omaha/81150-papa-johns-pizza/menu/",
    "sg:phone":"+1 402 408 0037",
    "sg:postcode":"68132",
    "sg:province":"NE",
    "sg:tags":[
        "american",
        "pizza"
    ],
    "wof:name":"Papa John's Pizza",
    "wof:placetype":"venue"
},
  "geometry": {"coordinates":[-95.98306700000001,41.266313],"type":"Point"}
}