{
  "type": "Feature",
  "properties": {
    "iso:country":"US",
    "sg:address":"705 20th St",
    "sg:city":"Gothenburg",
    "sg:classifiers":[
        {
            "category":"Wholesale",
            "subcategory":"Electrical",
            "type":"Manufacturing & Wholesale Goods"
        }
    ],
    "sg:phone":"+1 308 537 2622",
    "sg:postcode":"69138",
    "sg:province":"NE",
    "sg:tags":[
        "fire",
        "equipment",
        "protection"
    ],
    "wof:name":"Fyr Tek Inc",
    "wof:placetype":"venue"
},
  "geometry": {"coordinates":[-100.155663,40.938036],"type":"Point"}
}