{
  "type": "Feature",
  "properties": {
    "addr:full":"7001 Colfax St Lincoln NE 68507",
    "addr:housenumber":"7001",
    "addr:postcode":"68507",
    "addr:street":"Colfax St",
    "iso:country":"US",
    "sg:address":"7001 Colfax St",
    "sg:city":"Lincoln",
    "sg:classifiers":[
        {
            "category":"Wholesale",
            "subcategory":"Electrical",
            "type":"Manufacturing & Wholesale Goods"
        }
    ],
    "sg:phone":"+1 402 466 1439",
    "sg:postcode":"68507",
    "sg:province":"NE",
    "sg:tags":[
        "distribution",
        "engineering"
    ],
    "wof:name":"G & C Enterprises",
    "wof:placetype":"venue"
},
  "geometry": {"coordinates":[-96.622967,40.850636],"type":"Point"}
}