{
  "type": "Feature",
  "properties": {
    "addr:full":"2523 W John St Grand Island NE 68803",
    "addr:housenumber":"2523",
    "addr:postcode":"68803",
    "addr:street":"W John St",
    "iso:country":"US",
    "sg:address":"2523 W John St",
    "sg:city":"Grand Island",
    "sg:classifiers":[
        {
            "category":"Organizations",
            "subcategory":"Community Association",
            "type":"Services"
        }
    ],
    "sg:phone":"+1 308 384 1950",
    "sg:postcode":"68803",
    "sg:province":"NE",
    "wof:name":"Military Order of Purple Heart",
    "wof:placetype":"venue"
},
  "geometry": {"coordinates":[-98.362071,40.908691],"type":"Point"}
}