{
  "type": "Feature",
  "properties": {
    "addr:full":"605 2nd St Scribner NE 68057",
    "addr:housenumber":"605",
    "addr:postcode":"68057",
    "addr:street":"2Nd St",
    "iso:country":"US",
    "sg:address":"605 2nd St",
    "sg:city":"Scribner",
    "sg:classifiers":[
        {
            "category":"Retail",
            "subcategory":"Repair Shop",
            "type":"Services"
        }
    ],
    "sg:phone":"+1 402 664 2737",
    "sg:postcode":"68057",
    "sg:province":"NE",
    "sg:tags":[
        "equipment",
        "hydraulic"
    ],
    "wof:name":"Bernard's Repair",
    "wof:placetype":"venue"
},
  "geometry": {"coordinates":[-96.66825799999999,41.668299],"type":"Point"}
}