{
  "type": "Feature",
  "properties": {
    "iso:country":"US",
    "sg:address":"1880 US Hwy 75",
    "sg:city":"Decatur",
    "sg:classifiers":[
        {
            "category":"Professional",
            "type":"Services"
        }
    ],
    "sg:phone":"+1 402 374 2588",
    "sg:postcode":"68020",
    "sg:province":"NE",
    "wof:name":"Larry Mussack",
    "wof:placetype":"venue"
},
  "geometry": {"coordinates":[-96.252583,42.001904],"type":"Point"}
}