{
  "type": "Feature",
  "properties": {
    "iso:country":"US",
    "sg:address":"348 Petersen St",
    "sg:city":"Sidney",
    "sg:classifiers":[
        {
            "category":"Retail",
            "subcategory":"Repair Shop",
            "type":"Services"
        }
    ],
    "sg:phone":"+1 308 254 2662",
    "sg:postcode":"69162",
    "sg:province":"NE",
    "sg:tags":[
        "lock",
        "locksmith"
    ],
    "wof:name":"Al's Locksmith Shop",
    "wof:placetype":"venue"
},
  "geometry": {"coordinates":[-103.108895,41.217316],"type":"Point"}
}