{
  "type": "Feature",
  "properties": {
    "iso:country":"US",
    "sg:address":"89 Willow Ln",
    "sg:city":"Lexington",
    "sg:classifiers":[
        {
            "category":"Real Estate",
            "subcategory":"Developer",
            "type":"Services"
        },
        {
            "category":"Real Estate",
            "subcategory":"Real Estate Operator",
            "type":"Services"
        }
    ],
    "sg:phone":"+1 308 324 7748",
    "sg:postcode":"68850",
    "sg:province":"NE",
    "sg:tags":[
        "mobile",
        "home",
        "community"
    ],
    "wof:name":"Willow Ridge Court",
    "wof:placetype":"venue"
},
  "geometry": {"coordinates":[-99.728667,40.774518],"type":"Point"}
}