{
  "type": "Feature",
  "properties": {
    "addr:full":"239 S 9th St Blair NE 68008",
    "addr:housenumber":"239",
    "addr:postcode":"68008",
    "addr:street":"S 9Th St",
    "iso:country":"US",
    "sg:address":"239 S 9th St",
    "sg:city":"Blair",
    "sg:classifiers":[
        {
            "category":"Wholesale",
            "subcategory":"Hardware",
            "type":"Manufacturing & Wholesale Goods"
        }
    ],
    "sg:phone":"+1 402 426 9122",
    "sg:postcode":"68008",
    "sg:province":"NE",
    "sg:tags":[
        "manufactured",
        "fastener"
    ],
    "wof:name":"Fastenal Company",
    "wof:placetype":"venue"
},
  "geometry": {"coordinates":[-96.12481,41.542364],"type":"Point"}
}