{
  "type": "Feature",
  "properties": {
    "iso:country":"US",
    "sg:address":"9270 Pioneer Ct",
    "sg:city":"Lincoln",
    "sg:classifiers":[
        {
            "category":"Wholesale",
            "subcategory":"Non-durable Goods",
            "type":"Manufacturing & Wholesale Goods"
        }
    ],
    "sg:phone":"+1 402 730 3132",
    "sg:postcode":"68520",
    "sg:province":"NE",
    "sg:tags":[
        "advertising"
    ],
    "wof:name":"Pioneer Promotions",
    "wof:placetype":"venue"
},
  "geometry": {"coordinates":[-96.595332,40.77003],"type":"Point"}
}