{
  "type": "Feature",
  "properties": {
    "iso:country":"US",
    "sg:address":"625 W Prospector Ct",
    "sg:city":"Lincoln",
    "sg:classifiers":[
        {
            "category":"Manufacturing",
            "subcategory":"Tools & Machinery",
            "type":"Manufacturing & Wholesale Goods"
        }
    ],
    "sg:phone":"+1 402 438 1155",
    "sg:postcode":"68522",
    "sg:province":"NE",
    "sg:tags":[
        "equipment",
        "conveyor",
        "conveying"
    ],
    "sg:website":"www.sportstec-inc.com",
    "wof:name":"Dynamic Fusion Inc",
    "wof:placetype":"venue"
},
  "geometry": {"coordinates":[-96.730232,40.784635],"type":"Point"}
}