{
  "type": "Feature",
  "properties": {
    "addr:full":"27 Lowell Rd Gibbon NE 68840",
    "addr:housenumber":"27",
    "addr:postcode":"68840",
    "addr:street":"Lowell Rd",
    "iso:country":"US",
    "sg:address":"27 Lowell Rd",
    "sg:city":"Gibbon",
    "sg:classifiers":[
        {
            "category":"Farming",
            "subcategory":"Livestock Farm",
            "type":"Manufacturing & Wholesale Goods"
        }
    ],
    "sg:phone":"+1 308 468 5679",
    "sg:postcode":"68840",
    "sg:province":"NE",
    "sg:tags":[
        "corn",
        "beef",
        "feedlot",
        "cattle"
    ],
    "wof:name":"Wayne Lange",
    "wof:placetype":"venue"
},
  "geometry": {"coordinates":[-98.84727100000001,40.641503],"type":"Point"}
}