{
  "type": "Feature",
  "properties": {
    "iso:country":"US",
    "sg:address":"2949 N 27th St Ste 202",
    "sg:city":"Lincoln",
    "sg:classifiers":[
        {
            "category":"Professional",
            "subcategory":"Employment Agencies",
            "type":"Services"
        }
    ],
    "sg:phone":"+1 402 328 0142",
    "sg:postcode":"68521",
    "sg:province":"NE",
    "wof:name":"Advance Services, Inc.",
    "wof:placetype":"venue"
},
  "geometry": {"coordinates":[-96.682125,40.841755],"type":"Point"}
}