{
  "type": "Feature",
  "properties": {
    "iso:country":"US",
    "sg:address":"5724 Culwells Rd",
    "sg:city":"Lincoln",
    "sg:classifiers":[
        {
            "category":"Building & Trades",
            "subcategory":"Construction",
            "type":"Services"
        }
    ],
    "sg:phone":"+1 402 483 1130",
    "sg:postcode":"68516",
    "sg:province":"NE",
    "sg:tags":[
        "home",
        "builder",
        "construct",
        "family"
    ],
    "wof:name":"Tomasek Homes Inc",
    "wof:placetype":"venue"
},
  "geometry": {"coordinates":[-96.62067399999999,40.753781],"type":"Point"}
}