{
  "type": "Feature",
  "properties": {
    "iso:country":"US",
    "sg:address":"2520 28th St",
    "sg:city":"Columbus",
    "sg:classifiers":[
        {
            "category":"Education",
            "subcategory":"School",
            "type":"Public Place"
        }
    ],
    "sg:phone":"+1 402 564 8423",
    "sg:postcode":"68601",
    "sg:province":"NE",
    "wof:name":"Immanuel Lutheran School",
    "wof:placetype":"venue"
},
  "geometry": {"coordinates":[-97.358553,41.443758],"type":"Point"}
}