{
  "type": "Feature",
  "properties": {
    "iso:country":"US",
    "sg:address":"1910 1st Ave",
    "sg:city":"Kearney",
    "sg:classifiers":[
        {
            "category":"Recreation",
            "subcategory":"Arcade",
            "type":"Entertainment"
        }
    ],
    "sg:phone":"+1 308 237 2000",
    "sg:postcode":"68847",
    "sg:province":"NE",
    "sg:tags":[
        "amusement",
        "devices"
    ],
    "wof:name":"VVS Canteen",
    "wof:placetype":"venue"
},
  "geometry": {"coordinates":[-99.08274299999999,40.694471],"type":"Point"}
}