{
  "type": "Feature",
  "properties": {
    "iso:country":"US",
    "sg:address":"3248 Starr St",
    "sg:city":"Lincoln",
    "sg:classifiers":[
        {
            "category":"Organizations",
            "subcategory":"Community Association",
            "type":"Services"
        }
    ],
    "sg:phone":"+1 402 436 6344",
    "sg:postcode":"68503",
    "sg:province":"NE",
    "sg:tags":[
        "sorority",
        "fraternity"
    ],
    "wof:name":"Alpha Gamma Nu",
    "wof:placetype":"venue"
},
  "geometry": {"coordinates":[-96.67376299999999,40.827173],"type":"Point"}
}