{
  "type": "Feature",
  "properties": {
    "iso:country":"US",
    "sg:address":"7210 N Baltimore Ave",
    "sg:city":"Hastings",
    "sg:classifiers":[
        {
            "category":"Farming",
            "subcategory":"Farm",
            "type":"Manufacturing & Wholesale Goods"
        }
    ],
    "sg:phone":"+1 402 463 1677",
    "sg:postcode":"68901",
    "sg:province":"NE",
    "sg:tags":[
        "crop",
        "general"
    ],
    "wof:name":"Hohlen R Pocket Farms Inc",
    "wof:placetype":"venue"
},
  "geometry": {"coordinates":[-98.401093,40.656611],"type":"Point"}
}