{
  "type": "Feature",
  "properties": {
    "addr:full":"3614 Twin Creek Dr Bellevue NE 68123",
    "addr:housenumber":"3614",
    "addr:postcode":"68123",
    "addr:street":"Twin Creek Dr",
    "iso:country":"US",
    "sg:address":"3614 Twin Creek Dr",
    "sg:city":"Bellevue",
    "sg:classifiers":[
        {
            "category":"Banks & Credit Unions",
            "subcategory":"Bank",
            "type":"Services"
        }
    ],
    "sg:phone":"+1 402 293 7530",
    "sg:postcode":"68123",
    "sg:province":"NE",
    "sg:tags":[
        "state",
        "commercial"
    ],
    "wof:name":"U M B Bank  N A",
    "wof:placetype":"venue"
},
  "geometry": {"coordinates":[-95.968024,41.141121],"type":"Point"}
}