{
  "type": "Feature",
  "properties": {
    "addr:full":"2829 N 33rd St Lincoln NE 68504",
    "addr:housenumber":"2829",
    "addr:postcode":"68504",
    "addr:street":"N 33Rd St",
    "iso:country":"US",
    "sg:address":"2829 N 33rd St",
    "sg:city":"Lincoln",
    "sg:classifiers":[
        {
            "category":"Shopping",
            "type":"Retail Goods"
        },
        {
            "category":"Manufacturing",
            "subcategory":"Electronics",
            "type":"Manufacturing & Wholesale Goods"
        }
    ],
    "sg:phone":"+1 402 467 2121",
    "sg:postcode":"68504",
    "sg:province":"NE",
    "sg:tags":[
        "equipment",
        "telephone",
        "merchandise",
        "system"
    ],
    "sg:website":"www.cctelephone.com",
    "wof:name":"Capitol City Telephone Inc",
    "wof:placetype":"venue"
},
  "geometry": {"coordinates":[-96.672882,40.842487],"type":"Point"}
}