{
  "type": "Feature",
  "properties": {
    "iso:country":"US",
    "sg:address":"2731 S 87th Ave",
    "sg:city":"Omaha",
    "sg:classifiers":[
        {
            "category":"Restaurant",
            "type":"Food & Drink"
        }
    ],
    "sg:phone":"+1 402 390 0561",
    "sg:postcode":"68124",
    "sg:province":"NE",
    "wof:name":"Romeo's Inc",
    "wof:placetype":"venue"
},
  "geometry": {"coordinates":[-96.049537,41.232278],"type":"Point"}
}