{
  "type": "Feature",
  "properties": {
    "iso:country":"US",
    "sg:address":"237 N Burlington Ave",
    "sg:city":"Hastings",
    "sg:classifiers":[
        {
            "category":"Autos & Motor Vehicles",
            "subcategory":"Auto Supplies",
            "type":"Retail Goods"
        }
    ],
    "sg:phone":"+1 402 463 4800",
    "sg:postcode":"68901",
    "sg:province":"NE",
    "sg:tags":[
        "tire"
    ],
    "wof:name":"Berck's Cooper Tire & Muffler",
    "wof:placetype":"venue"
},
  "geometry": {"coordinates":[-98.392492,40.5858],"type":"Point"}
}