{
  "type": "Feature",
  "properties": {
    "iso:country":"US",
    "sg:address":"612 W Mission Ave",
    "sg:city":"Bellevue",
    "sg:classifiers":[
        {
            "category":"Insurance",
            "subcategory":"Insurance Agent",
            "type":"Services"
        }
    ],
    "sg:phone":"+1 402 292 5670",
    "sg:postcode":"68005",
    "sg:province":"NE",
    "wof:name":"One Way Insurance",
    "wof:placetype":"venue"
},
  "geometry": {"coordinates":[-95.901489,41.136579],"type":"Point"}
}