{
  "type": "Feature",
  "properties": {
    "addr:full":"1129 E 6th St York NE 68467",
    "addr:housenumber":"1129",
    "addr:postcode":"68467",
    "addr:street":"E 6Th St",
    "iso:country":"US",
    "sg:address":"1129 E 6th St",
    "sg:city":"York",
    "sg:classifiers":[
        {
            "category":"Government",
            "subcategory":"Office",
            "type":"Public Place"
        }
    ],
    "sg:phone":"+1 402 362 6050",
    "sg:postcode":"68467",
    "sg:province":"NE",
    "sg:tags":[
        "national",
        "guard"
    ],
    "wof:name":"Nebraska Army National Guard",
    "wof:placetype":"venue"
},
  "geometry": {"coordinates":[-97.579609,40.867018],"type":"Point"}
}