{
  "type": "Feature",
  "properties": {
    "iso:country":"US",
    "sg:address":"853 E St",
    "sg:city":"Lincoln",
    "sg:classifiers":[
        {
            "category":"Organizations",
            "subcategory":"Religious Organization",
            "type":"Services"
        }
    ],
    "sg:phone":"+1 402 489 1294",
    "sg:postcode":"68508",
    "sg:province":"NE",
    "sg:tags":[
        "church"
    ],
    "wof:name":"Zion Presbyterian Church",
    "wof:placetype":"venue"
},
  "geometry": {"coordinates":[-96.709135,40.803594],"type":"Point"}
}