{
  "type": "Feature",
  "properties": {
    "iso:country":"US",
    "sg:address":"30630 Ravenna Rd",
    "sg:city":"Ravenna",
    "sg:classifiers":[
        {
            "category":"Farming",
            "subcategory":"Livestock Farm",
            "type":"Manufacturing & Wholesale Goods"
        }
    ],
    "sg:phone":"+1 308 452 3988",
    "sg:postcode":"68869",
    "sg:province":"NE",
    "sg:tags":[
        "general"
    ],
    "wof:name":"Royal M Betke",
    "wof:placetype":"venue"
},
  "geometry": {"coordinates":[-98.913082,40.974434],"type":"Point"}
}