{
  "type": "Feature",
  "properties": {
    "iso:country":"US",
    "sg:address":"2175 15th Rd",
    "sg:city":"Pender",
    "sg:classifiers":[
        {
            "category":"Organizations",
            "subcategory":"Religious Organization",
            "type":"Services"
        }
    ],
    "sg:phone":"+1 402 385 2447",
    "sg:postcode":"68047",
    "sg:province":"NE",
    "sg:tags":[
        "church"
    ],
    "wof:name":"St John's Lutheran Church Mo",
    "wof:placetype":"venue"
},
  "geometry": {"coordinates":[-96.74891,42.042628],"type":"Point"}
}