{
  "type": "Feature",
  "properties": {
    "addr:full":"3012 State Hwy 35 Norfolk NE 68701",
    "addr:housenumber":"3012",
    "addr:postcode":"68701",
    "addr:street":"State Hwy 35 Norfolk",
    "iso:country":"US",
    "sg:address":"3012 State Hwy 35",
    "sg:city":"Norfolk",
    "sg:classifiers":[
        {
            "category":"Autos & Motor Vehicles",
            "subcategory":"Automobile Sales",
            "type":"Retail Goods"
        }
    ],
    "sg:phone":"+1 402 371 3338",
    "sg:postcode":"68701",
    "sg:province":"NE",
    "sg:tags":[
        "used"
    ],
    "wof:name":"Red Bull Auto Sales",
    "wof:placetype":"venue"
},
  "geometry": {"coordinates":[-97.351196,42.061049],"type":"Point"}
}