{
  "type": "Feature",
  "properties": {
    "iso:country":"US",
    "sg:address":"912 Monroe Ave",
    "sg:city":"Norfolk",
    "sg:classifiers":[
        {
            "category":"Retail",
            "subcategory":"Auto Repair",
            "type":"Services"
        }
    ],
    "sg:phone":"+1 402 371 3696",
    "sg:postcode":"68701",
    "sg:province":"NE",
    "sg:tags":[
        "trailer"
    ],
    "wof:name":"Wayne's Welding",
    "wof:placetype":"venue"
},
  "geometry": {"coordinates":[-97.42285099999999,42.010958],"type":"Point"}
}