{
  "type": "Feature",
  "properties": {
    "iso:country":"US",
    "sg:address":"400 Park St",
    "sg:city":"Yankton",
    "sg:classifiers":[
        {
            "category":"Health Services",
            "subcategory":"Health Practitioner",
            "type":"Services"
        }
    ],
    "sg:phone":"+1 605 668 9466",
    "sg:postcode":"57078",
    "sg:province":"NE",
    "sg:tags":[
        "therapist",
        "physical"
    ],
    "wof:name":"Nova Care Orthotics & Prsthcs",
    "wof:placetype":"venue"
},
  "geometry": {"coordinates":[-97.405473,42.871522],"type":"Point"}
}