{
  "type": "Feature",
  "properties": {
    "iso:country":"US",
    "sg:address":"2818 N 70th St",
    "sg:city":"Omaha",
    "sg:classifiers":[
        {
            "category":"Organizations",
            "subcategory":"Religious Organization",
            "type":"Services"
        }
    ],
    "sg:phone":"+1 402 556 2325",
    "sg:postcode":"68104",
    "sg:province":"NE",
    "wof:name":"Pilgrim Christian Church",
    "wof:placetype":"venue"
},
  "geometry": {"coordinates":[-96.020397,41.284821],"type":"Point"}
}