{
  "type": "Feature",
  "properties": {
    "iso:country":"US",
    "sg:address":"635 W 2nd St",
    "sg:city":"Hastings",
    "sg:classifiers":[
        {
            "category":"Restaurant",
            "type":"Food & Drink"
        }
    ],
    "sg:phone":"+1 402 462 5214",
    "sg:postcode":"68901",
    "sg:province":"NE",
    "sg:tags":[
        "shop",
        "coffee"
    ],
    "wof:name":"Blue Moon Coffee Co",
    "wof:placetype":"venue"
},
  "geometry": {"coordinates":[-98.389574,40.585127],"type":"Point"}
}