{
  "type": "Feature",
  "properties": {
    "addr:full":"2600 S 48th St Lincoln NE 68506",
    "addr:housenumber":"2600",
    "addr:postcode":"68506",
    "addr:street":"S 48Th St",
    "iso:country":"US",
    "sg:address":"2600 S 48th St",
    "sg:city":"Lincoln",
    "sg:classifiers":[
        {
            "category":"Restaurant",
            "type":"Food & Drink"
        }
    ],
    "sg:phone":"+1 402 488 3939",
    "sg:postcode":"68506",
    "sg:province":"NE",
    "sg:tags":[
        "eating"
    ],
    "wof:name":"El Toro Mexican Restaurant",
    "wof:placetype":"venue"
},
  "geometry": {"coordinates":[-96.653701,40.78769],"type":"Point"}
}