{
  "type": "Feature",
  "properties": {
    "iso:country":"US",
    "sg:address":"7728 Pratt St",
    "sg:city":"Omaha",
    "sg:classifiers":[
        {
            "category":"Manufacturing",
            "subcategory":"Printing",
            "type":"Manufacturing & Wholesale Goods"
        }
    ],
    "sg:phone":"+1 402 571 1371",
    "sg:postcode":"68134",
    "sg:province":"NE",
    "sg:tags":[
        "book"
    ],
    "wof:name":"Camel Phase Graphics",
    "wof:placetype":"venue"
},
  "geometry": {"coordinates":[-96.03313199999999,41.292319],"type":"Point"}
}