{
  "type": "Feature",
  "properties": {
    "iso:country":"US",
    "sg:address":"10338 Newport Ave",
    "sg:city":"Omaha",
    "sg:classifiers":[
        {
            "category":"Retail",
            "subcategory":"Auto Repair",
            "type":"Services"
        }
    ],
    "sg:phone":"+1 402 496 4117",
    "sg:postcode":"68122",
    "sg:province":"NE",
    "sg:tags":[
        "transmission"
    ],
    "wof:name":"Transmission Doctor",
    "wof:placetype":"venue"
},
  "geometry": {"coordinates":[-96.074849,41.319725],"type":"Point"}
}