{
  "type": "Feature",
  "properties": {
    "addr:full":"415 N Lincoln Ave North Platte NE 69101",
    "addr:housenumber":"415",
    "addr:postcode":"69101",
    "addr:street":"N Lincoln Ave",
    "iso:country":"US",
    "sg:address":"415 N Lincoln Ave",
    "sg:city":"North Platte",
    "sg:classifiers":[
        {
            "category":"Retail",
            "subcategory":"Animal Services",
            "type":"Services"
        }
    ],
    "sg:phone":"+1 308 534 7788",
    "sg:postcode":"69101",
    "sg:province":"NE",
    "wof:name":"T L C Pet Sitters",
    "wof:placetype":"venue"
},
  "geometry": {"coordinates":[-100.7753,41.13848],"type":"Point"}
}