{
  "type": "Feature",
  "properties": {
    "iso:country":"US",
    "sg:address":"901 N 24th St",
    "sg:city":"Omaha",
    "sg:classifiers":[
        {
            "category":"Autos & Motor Vehicles",
            "subcategory":"Fuel & Gas Station",
            "type":"Retail Goods"
        }
    ],
    "sg:phone":"+1 402 342 3903",
    "sg:postcode":"68102",
    "sg:province":"NE",
    "wof:name":"Sinclair Gas Station",
    "wof:placetype":"venue"
},
  "geometry": {"coordinates":[-95.946828,41.267959],"type":"Point"}
}