{
  "type": "Feature",
  "properties": {
    "addr:full":"2022 Ave A Kearney NE 68847",
    "addr:postcode":"68847",
    "addr:street":"2022 Ave A",
    "iso:country":"US",
    "sg:address":"2022 Ave A",
    "sg:city":"Kearney",
    "sg:classifiers":[
        {
            "category":"Organizations",
            "subcategory":"Non-profit Organization",
            "type":"Services"
        }
    ],
    "sg:phone":"+1 308 237 4343",
    "sg:postcode":"68847",
    "sg:province":"NE",
    "sg:tags":[
        "social"
    ],
    "wof:name":"ARC of Buffalo County",
    "wof:placetype":"venue"
},
  "geometry": {"coordinates":[-99.080473,40.696324],"type":"Point"}
}