{
  "type": "Feature",
  "properties": {
    "iso:country":"US",
    "sg:address":"636 N 12th St",
    "sg:city":"Geneva",
    "sg:phone":"+1 402 759 3329",
    "sg:postcode":"68361",
    "sg:province":"NE",
    "sg:tags":[
        "farm",
        "corn",
        "soybean"
    ],
    "wof:name":"Lauber Seed Farm",
    "wof:placetype":"venue"
},
  "geometry": {"coordinates":[-97.597689,40.532916],"type":"Point"}
}