{
  "type": "Feature",
  "properties": {
    "iso:country":"US",
    "sg:address":"332 E Main St",
    "sg:city":"Pierce",
    "sg:classifiers":[
        {
            "category":"Retail",
            "subcategory":"Auto Repair",
            "type":"Services"
        }
    ],
    "sg:phone":"+1 402 329 6795",
    "sg:postcode":"68767",
    "sg:province":"NE",
    "sg:tags":[
        "gasoline",
        "station",
        "petroleum",
        "general"
    ],
    "wof:name":"Toms Service A A A",
    "wof:placetype":"venue"
},
  "geometry": {"coordinates":[-97.523994,42.198987],"type":"Point"}
}