{
  "type": "Feature",
  "properties": {
    "iso:country":"US",
    "sg:address":"7902 N 36th St",
    "sg:city":"Omaha",
    "sg:classifiers":[
        {
            "category":"Education",
            "subcategory":"School",
            "type":"Public Place"
        }
    ],
    "sg:phone":"+1 402 457 5818",
    "sg:postcode":"68112",
    "sg:province":"NE",
    "sg:tags":[
        "high",
        "middle",
        "elementary"
    ],
    "sg:website":"www.ops.org",
    "wof:name":"Florence Elementary School",
    "wof:placetype":"venue"
},
  "geometry": {"coordinates":[-95.96820099999999,41.330101],"type":"Point"}
}