{
  "type": "Feature",
  "properties": {
    "iso:country":"US",
    "sg:address":"242 N Commercial Ave",
    "sg:city":"Wallace",
    "sg:classifiers":[
        {
            "category":"Health Services",
            "subcategory":"Clinic",
            "type":"Services"
        }
    ],
    "sg:phone":"+1 308 387 4386",
    "sg:postcode":"69169",
    "sg:province":"NE",
    "sg:tags":[
        "home"
    ],
    "wof:name":"Frontier Home Medical",
    "wof:placetype":"venue"
},
  "geometry": {"coordinates":[-101.165015,40.84087],"type":"Point"}
}