{
  "type": "Feature",
  "properties": {
    "iso:country":"US",
    "sg:address":"6444 Ballard Ave",
    "sg:city":"Lincoln",
    "sg:classifiers":[
        {
            "category":"Manufacturing",
            "subcategory":"Lumber",
            "type":"Manufacturing & Wholesale Goods"
        }
    ],
    "sg:phone":"+1 402 890 2709",
    "sg:postcode":"68507",
    "sg:province":"NE",
    "sg:tags":[
        "riffle",
        "barrels"
    ],
    "wof:name":"Advanced Barrel Systems Inc",
    "wof:placetype":"venue"
},
  "geometry": {"coordinates":[-96.632169,40.856008],"type":"Point"}
}