{
  "type": "Feature",
  "properties": {
    "iso:country":"US",
    "sg:address":"1201 Nicholas St",
    "sg:city":"Omaha",
    "sg:classifiers":[
        {
            "category":"Wholesale",
            "subcategory":"Hardware",
            "type":"Manufacturing & Wholesale Goods"
        }
    ],
    "sg:phone":"+1 402 341 8511",
    "sg:postcode":"68102",
    "sg:province":"NE",
    "sg:tags":[
        "air",
        "parts",
        "conditioning",
        "supply"
    ],
    "sg:website":"www.ashadistributing.com",
    "wof:name":"ASHA Distributing Inc",
    "wof:placetype":"venue"
},
  "geometry": {"coordinates":[-95.933109,41.269995],"type":"Point"}
}