{
  "type": "Feature",
  "properties": {
    "iso:country":"US",
    "sg:address":"305 S 11th St",
    "sg:city":"Seward",
    "sg:classifiers":[
        {
            "category":"Sports & Exercise",
            "subcategory":"Gym",
            "type":"Entertainment"
        }
    ],
    "sg:phone":"+1 402 643 2888",
    "sg:postcode":"68434",
    "sg:province":"NE",
    "sg:tags":[
        "fitness",
        "physical",
        "facility"
    ],
    "wof:name":"Health Horizons Wellness Ctr",
    "wof:placetype":"venue"
},
  "geometry": {"coordinates":[-97.105017,40.905933],"type":"Point"}
}