{
  "type": "Feature",
  "properties": {
    "iso:country":"US",
    "sg:address":"47645 SW 117th Rd",
    "sg:city":"Odell",
    "sg:classifiers":[
        {
            "category":"Farming",
            "subcategory":"Farm",
            "type":"Manufacturing & Wholesale Goods"
        }
    ],
    "sg:phone":"+1 402 766 4261",
    "sg:postcode":"68415",
    "sg:province":"NE",
    "sg:tags":[
        "crop",
        "general"
    ],
    "wof:name":"Kandice Jurgens",
    "wof:placetype":"venue"
},
  "geometry": {"coordinates":[-96.877803,40.044491],"type":"Point"}
}