{
  "type": "Feature",
  "properties": {
    "iso:country":"US",
    "sg:address":"1700 Center Park Rd",
    "sg:city":"Lincoln",
    "sg:classifiers":[
        {
            "category":"Professional",
            "type":"Services"
        }
    ],
    "sg:phone":"+1 402 421 1480",
    "sg:postcode":"68512",
    "sg:province":"NE",
    "sg:tags":[
        "establishment"
    ],
    "wof:name":"Premier Logistics",
    "wof:placetype":"venue"
},
  "geometry": {"coordinates":[-96.695587,40.766101],"type":"Point"}
}