{
  "type": "Feature",
  "properties": {
    "iso:country":"US",
    "sg:address":"936 N 24th St",
    "sg:city":"Omaha",
    "sg:classifiers":[
        {
            "category":"Insurance",
            "subcategory":"Insurance Agent",
            "type":"Services"
        }
    ],
    "sg:phone":"+1 402 930 2220",
    "sg:postcode":"68102",
    "sg:province":"NE",
    "wof:name":"State Farm Insurance",
    "wof:placetype":"venue"
},
  "geometry": {"coordinates":[-95.947087,41.269255],"type":"Point"}
}