{
  "type": "Feature",
  "properties": {
    "addr:full":"35355 Arrow Rd Miller NE 68858",
    "addr:housenumber":"35355",
    "addr:postcode":"68858",
    "addr:street":"Arrow Rd",
    "iso:country":"US",
    "sg:address":"35355 Arrow Rd",
    "sg:city":"Miller",
    "sg:classifiers":[
        {
            "category":"Farming",
            "subcategory":"Livestock Farm",
            "type":"Manufacturing & Wholesale Goods"
        }
    ],
    "sg:phone":"+1 308 457 2505",
    "sg:postcode":"68858",
    "sg:province":"NE",
    "sg:tags":[
        "animal",
        "general"
    ],
    "wof:name":"Triangle J Ranch",
    "wof:placetype":"venue"
},
  "geometry": {"coordinates":[-99.40648299999999,41.011592],"type":"Point"}
}