{
  "type": "Feature",
  "properties": {
    "iso:country":"US",
    "sg:address":"1221 Evergreen Dr",
    "sg:city":"Lincoln",
    "sg:classifiers":[
        {
            "category":"Manufacturing",
            "subcategory":"Buildings",
            "type":"Manufacturing & Wholesale Goods"
        },
        {
            "category":"Building & Trades",
            "subcategory":"Construction",
            "type":"Services"
        }
    ],
    "sg:phone":"+1 402 488 5650",
    "sg:postcode":"68510",
    "sg:province":"NE",
    "sg:tags":[
        "industrial",
        "system",
        "specialty",
        "builder",
        "heating",
        "contractor",
        "contractors-commercial",
        "home",
        "air conditioning"
    ],
    "wof:name":"Robison Design Build",
    "wof:placetype":"venue"
},
  "geometry": {"coordinates":[-96.631851,40.801741],"type":"Point"}
}