{
  "type": "Feature",
  "properties": {
    "iso:country":"US",
    "sg:address":"118 E 21st St",
    "sg:city":"South Sioux City",
    "sg:classifiers":[
        {
            "category":"Personal",
            "subcategory":"Beauty Salon",
            "type":"Services"
        }
    ],
    "sg:phone":"+1 402 494 4066",
    "sg:postcode":"68776",
    "sg:province":"NE",
    "sg:tags":[
        "shop"
    ],
    "wof:name":"Hair Cottage",
    "wof:placetype":"venue"
},
  "geometry": {"coordinates":[-96.41337300000001,42.469771],"type":"Point"}
}