{
  "type": "Feature",
  "properties": {
    "iso:country":"US",
    "sg:address":"2521 W L St",
    "sg:city":"Lincoln",
    "sg:classifiers":[
        {
            "category":"Food & Beverages",
            "subcategory":"Meat & Fish",
            "type":"Retail Goods"
        }
    ],
    "sg:phone":"+1 402 477 4147",
    "sg:postcode":"68522",
    "sg:province":"NE",
    "wof:name":"Countryside Meats",
    "wof:placetype":"venue"
},
  "geometry": {"coordinates":[-96.75728100000001,40.810804],"type":"Point"}
}