{
  "type": "Feature",
  "properties": {
    "iso:country":"US",
    "sg:address":"1601 Broadway St",
    "sg:city":"Dakota City",
    "sg:classifiers":[
        {
            "category":"Government",
            "subcategory":"Court House",
            "type":"Public Place"
        }
    ],
    "sg:phone":"+1 402 987 2139",
    "sg:postcode":"68731",
    "sg:province":"NE",
    "sg:tags":[
        "county",
        "counsel"
    ],
    "wof:name":"Public Defender",
    "wof:placetype":"venue"
},
  "geometry": {"coordinates":[-96.42009299999999,42.415923],"type":"Point"}
}