{
  "type": "Feature",
  "properties": {
    "addr:full":"2731 Odessa Ct Lincoln NE 68516",
    "addr:housenumber":"2731",
    "addr:postcode":"68516",
    "addr:street":"Odessa Ct",
    "iso:country":"US",
    "sg:address":"2731 Odessa Ct",
    "sg:city":"Lincoln",
    "sg:classifiers":[
        {
            "category":"Real Estate",
            "subcategory":"Real Estate Agent",
            "type":"Services"
        }
    ],
    "sg:phone":"+1 402 421 6340",
    "sg:postcode":"68516",
    "sg:province":"NE",
    "sg:tags":[
        "photography",
        "commercial"
    ],
    "wof:name":"W H Digital Inc",
    "wof:placetype":"venue"
},
  "geometry": {"coordinates":[-96.68099599999999,40.745824],"type":"Point"}
}