{
  "type": "Feature",
  "properties": {
    "iso:country":"US",
    "sg:address":"101 E 22nd St",
    "sg:city":"Scottsbluff",
    "sg:classifiers":[
        {
            "category":"Insurance",
            "subcategory":"Insurance Agent",
            "type":"Services"
        }
    ],
    "sg:phone":"+1 308 436 0530",
    "sg:postcode":"69361",
    "sg:province":"NE",
    "wof:name":"Farm Bureau Insurance",
    "wof:placetype":"venue"
},
  "geometry": {"coordinates":[-103.661383,41.868584],"type":"Point"}
}