{
  "type": "Feature",
  "properties": {
    "iso:country":"US",
    "sg:address":"2923 Dover Dr",
    "sg:city":"Norfolk",
    "sg:classifiers":[
        {
            "category":"Freight",
            "type":"Transportation"
        }
    ],
    "sg:phone":"+1 402 844 4728",
    "sg:postcode":"68701",
    "sg:province":"NE",
    "sg:tags":[
        "operator",
        "local",
        "trucking"
    ],
    "wof:name":"Fastrak Delivery LLC",
    "wof:placetype":"venue"
},
  "geometry": {"coordinates":[-97.45062900000001,42.05388],"type":"Point"}
}