{
  "type": "Feature",
  "properties": {
    "iso:country":"US",
    "sg:address":"2628 W 2nd St",
    "sg:city":"Hastings",
    "sg:classifiers":[
        {
            "category":"Health Services",
            "subcategory":"Doctor",
            "type":"Services"
        }
    ],
    "sg:phone":"+1 402 462 5546",
    "sg:postcode":"68901",
    "sg:province":"NE",
    "sg:tags":[
        "dentist"
    ],
    "wof:name":"Lebsack Dental Office",
    "wof:placetype":"venue"
},
  "geometry": {"coordinates":[-98.418514,40.585432],"type":"Point"}
}