{
  "type": "Feature",
  "properties": {
    "iso:country":"US",
    "sg:address":"2201 N Cotner Blvd",
    "sg:city":"Lincoln",
    "sg:classifiers":[
        {
            "category":"Retail",
            "subcategory":"Repair Shop",
            "type":"Services"
        }
    ],
    "sg:phone":"+1 402 466 1022",
    "sg:postcode":"68505",
    "sg:province":"NE",
    "sg:tags":[
        "electrical"
    ],
    "wof:name":"Major Appliance",
    "wof:placetype":"venue"
},
  "geometry": {"coordinates":[-96.630482,40.835201],"type":"Point"}
}