{
  "type": "Feature",
  "properties": {
    "addr:full":"10841 Q St Ste 113 Omaha NE 68137",
    "addr:housenumber":"10841",
    "addr:postcode":"68137",
    "addr:street":"Q St Ste 113",
    "iso:country":"US",
    "sg:address":"10841 Q St Ste 113",
    "sg:city":"Omaha",
    "sg:classifiers":[
        {
            "category":"Professional",
            "subcategory":"Management & Consulting",
            "type":"Services"
        },
        {
            "category":"Professional",
            "subcategory":"Research",
            "type":"Services"
        },
        {
            "category":"Professional",
            "subcategory":"Advertising",
            "type":"Services"
        }
    ],
    "sg:phone":"+1 402 597 1044",
    "sg:postcode":"68137",
    "sg:province":"NE",
    "sg:tags":[
        "marketing",
        "program",
        "market",
        "analysis",
        "consultant"
    ],
    "sg:website":"http://www.promodata.com",
    "wof:name":"Add Activity Marketing Service",
    "wof:placetype":"venue"
},
  "geometry": {"coordinates":[-96.08208399999999,41.205282],"type":"Point"}
}