{
  "type": "Feature",
  "properties": {
    "iso:country":"US",
    "sg:address":"520 W Boyd Ave",
    "sg:city":"Elm Creek",
    "sg:classifiers":[
        {
            "category":"Freight",
            "type":"Transportation"
        }
    ],
    "sg:phone":"+1 308 856 4303",
    "sg:postcode":"68836",
    "sg:province":"NE",
    "sg:tags":[
        "executive",
        "general"
    ],
    "wof:name":"Elm Creek Village Shop",
    "wof:placetype":"venue"
},
  "geometry": {"coordinates":[-99.37878499999999,40.720559],"type":"Point"}
}