{
  "type": "Feature",
  "properties": {
    "iso:country":"US",
    "sg:address":"6538 S 139th Cir",
    "sg:city":"Omaha",
    "sg:classifiers":[
        {
            "category":"Building & Trades",
            "subcategory":"Construction",
            "type":"Services"
        }
    ],
    "sg:phone":"+1 402 933 8223",
    "sg:postcode":"68137",
    "sg:province":"NE",
    "sg:tags":[
        "heavy",
        "fabricator",
        "structural",
        "timber"
    ],
    "wof:name":"Structural Woodcraft Inc",
    "wof:placetype":"venue"
},
  "geometry": {"coordinates":[-96.12997,41.19373],"type":"Point"}
}