{
  "type": "Feature",
  "properties": {
    "iso:country":"US",
    "sg:address":"700 W 3rd St",
    "sg:city":"Madison",
    "sg:classifiers":[
        {
            "category":"Freight",
            "type":"Transportation"
        }
    ],
    "sg:phone":"+1 402 454 2999",
    "sg:postcode":"68748",
    "sg:province":"NE",
    "sg:tags":[
        "grain",
        "elevator"
    ],
    "wof:name":"Battle Creek Farmer's Pride",
    "wof:placetype":"venue"
},
  "geometry": {"coordinates":[-97.461844,41.827912],"type":"Point"}
}