{
  "type": "Feature",
  "properties": {
    "addr:full":"1411 SW 9th St Lincoln NE 68522",
    "addr:housenumber":"1411",
    "addr:postcode":"68522",
    "addr:street":"Sw 9Th St",
    "iso:country":"US",
    "sg:address":"1411 SW 9th St",
    "sg:city":"Lincoln",
    "sg:classifiers":[
        {
            "category":"Organizations",
            "subcategory":"Labor Organization",
            "type":"Services"
        }
    ],
    "sg:phone":"+1 402 435 2114",
    "sg:postcode":"68522",
    "sg:province":"NE",
    "wof:name":"Machinists AFL CIO Lg 612",
    "wof:placetype":"venue"
},
  "geometry": {"coordinates":[-96.735061,40.799047],"type":"Point"}
}