{
  "type": "Feature",
  "properties": {
    "iso:country":"US",
    "sg:address":"638 North Ave",
    "sg:city":"Seward",
    "sg:classifiers":[
        {
            "category":"Professional",
            "subcategory":"Art Services",
            "type":"Services"
        }
    ],
    "sg:phone":"+1 402 643 6881",
    "sg:postcode":"68434",
    "sg:province":"NE",
    "sg:tags":[
        "commercial",
        "design"
    ],
    "wof:name":"Summit Design",
    "wof:placetype":"venue"
},
  "geometry": {"coordinates":[-97.100033,40.919348],"type":"Point"}
}