{
  "type": "Feature",
  "properties": {
    "iso:country":"US",
    "sg:address":"1665 State St",
    "sg:city":"Blair",
    "sg:classifiers":[
        {
            "category":"Building & Trades",
            "subcategory":"Plumbing",
            "type":"Services"
        }
    ],
    "sg:phone":"+1 402 426 3683",
    "sg:postcode":"68008",
    "sg:province":"NE",
    "sg:tags":[
        "plumbing",
        "contractor"
    ],
    "wof:name":"Blair Plumbing",
    "wof:placetype":"venue"
},
  "geometry": {"coordinates":[-96.13672200000001,41.54595],"type":"Point"}
}