{
  "type": "Feature",
  "properties": {
    "iso:country":"US",
    "sg:address":"676 7th Ave",
    "sg:city":"Columbus",
    "sg:classifiers":[
        {
            "category":"Social Services",
            "subcategory":"Child Care",
            "type":"Services"
        }
    ],
    "sg:phone":"+1 402 563 1250",
    "sg:postcode":"68601",
    "sg:province":"NE",
    "sg:tags":[
        "day"
    ],
    "wof:name":"Dee M Chohon",
    "wof:placetype":"venue"
},
  "geometry": {"coordinates":[-97.334945,41.423276],"type":"Point"}
}