{
  "type": "Feature",
  "properties": {
    "iso:country":"US",
    "sg:address":"10868 W Dodge Rd",
    "sg:city":"Omaha",
    "sg:classifiers":[
        {
            "category":"Professional",
            "subcategory":"Management & Consulting",
            "type":"Services"
        }
    ],
    "sg:phone":"+1 402 595 1158",
    "sg:postcode":"68154",
    "sg:province":"NE",
    "sg:tags":[
        "consultant",
        "business"
    ],
    "wof:name":"NBDC Entrepreneurshop",
    "wof:placetype":"venue"
},
  "geometry": {"coordinates":[-96.082393,41.263388],"type":"Point"}
}