{
  "type": "Feature",
  "properties": {
    "iso:country":"US",
    "sg:address":"1650 Lake St",
    "sg:city":"Lincoln",
    "sg:classifiers":[
        {
            "category":"Health Services",
            "subcategory":"Hospital",
            "type":"Services"
        }
    ],
    "sg:phone":"+1 402 481 5268",
    "sg:postcode":"68502",
    "sg:province":"NE",
    "sg:tags":[
        "specialty"
    ],
    "wof:name":"Bryanlgh Independence Center",
    "wof:placetype":"venue"
},
  "geometry": {"coordinates":[-96.698374,40.788177],"type":"Point"}
}