{
  "type": "Feature",
  "properties": {
    "iso:country":"US",
    "sg:address":"514 N 16th St",
    "sg:city":"Omaha",
    "sg:classifiers":[
        {
            "category":"Shopping",
            "subcategory":"Used Merchandise",
            "type":"Retail Goods"
        }
    ],
    "sg:phone":"+1 402 342 2956",
    "sg:postcode":"68102",
    "sg:province":"NE",
    "wof:name":"Sauls Pawn Shop",
    "wof:placetype":"venue"
},
  "geometry": {"coordinates":[-95.937202,41.264633],"type":"Point"}
}