{
  "type": "Feature",
  "properties": {
    "iso:country":"US",
    "sg:address":"417 Main St",
    "sg:city":"Burchard",
    "sg:classifiers":[
        {
            "category":"Utilities",
            "subcategory":"Telephone",
            "type":"Services"
        }
    ],
    "sg:phone":"+1 402 248 6501",
    "sg:postcode":"68377",
    "sg:province":"NE",
    "sg:tags":[
        "company"
    ],
    "wof:name":"Blue Valley Telephone Co",
    "wof:placetype":"venue"
},
  "geometry": {"coordinates":[-96.97424100000001,40.191204],"type":"Point"}
}