{
  "type": "Feature",
  "properties": {
    "iso:country":"US",
    "sg:address":"503 Wright Ave",
    "sg:city":"Eustis",
    "sg:classifiers":[
        {
            "category":"Farming",
            "subcategory":"Farm & Veterinary Services",
            "type":"Manufacturing & Wholesale Goods"
        }
    ],
    "sg:phone":"+1 308 785 2100",
    "sg:postcode":"69028",
    "sg:province":"NE",
    "sg:tags":[
        "aerial",
        "applicator"
    ],
    "wof:name":"Johnson Lake Flying Svc",
    "wof:placetype":"venue"
},
  "geometry": {"coordinates":[-100.03596899999999,40.667038],"type":"Point"}
}