{
  "type": "Feature",
  "properties": {
    "iso:country":"US",
    "sg:address":"4400 Rodeo Rd",
    "sg:city":"North Platte",
    "sg:classifiers":[
        {
            "category":"Home & Garden",
            "subcategory":"Mobile Homes",
            "type":"Retail Goods"
        }
    ],
    "sg:phone":"+1 308 532 4707",
    "sg:postcode":"69101",
    "sg:province":"NE",
    "wof:name":"Swanson Mobile Homes Inc",
    "wof:placetype":"venue"
},
  "geometry": {"coordinates":[-100.812166,41.155483],"type":"Point"}
}