{
  "type": "Feature",
  "properties": {
    "iso:country":"US",
    "sg:address":"130 Walnut St",
    "sg:city":"West Point",
    "sg:classifiers":[
        {
            "category":"Health Services",
            "subcategory":"Health Practitioner",
            "type":"Services"
        }
    ],
    "sg:phone":"+1 402 372 6903",
    "sg:postcode":"68788",
    "sg:province":"NE",
    "sg:tags":[
        "nutritionist"
    ],
    "wof:name":"Stone Creek Nutrition LLC",
    "wof:placetype":"venue"
},
  "geometry": {"coordinates":[-96.71180200000001,41.842126],"type":"Point"}
}