{
  "type": "Feature",
  "properties": {
    "addr:full":"419 S 11th Ave Broken Bow NE 68822",
    "addr:housenumber":"419",
    "addr:postcode":"68822",
    "addr:street":"S 11Th Ave",
    "iso:country":"US",
    "sg:address":"419 S 11th Ave",
    "sg:city":"Broken Bow",
    "sg:classifiers":[
        {
            "category":"Social Services",
            "type":"Services"
        }
    ],
    "sg:phone":"+1 308 872 6651",
    "sg:postcode":"68822",
    "sg:province":"NE",
    "sg:tags":[
        "counselor",
        "marriage",
        "family"
    ],
    "wof:name":"New Potentials Counseling",
    "wof:placetype":"venue"
},
  "geometry": {"coordinates":[-99.64296899999999,41.402512],"type":"Point"}
}