{
  "type": "Feature",
  "properties": {
    "iso:country":"US",
    "sg:address":"219 N Oakland Ave",
    "sg:city":"Oakland",
    "sg:classifiers":[
        {
            "category":"Insurance",
            "subcategory":"Insurance Agent",
            "type":"Services"
        }
    ],
    "sg:phone":"+1 402 685 5005",
    "sg:postcode":"68045",
    "sg:province":"NE",
    "wof:name":"Logan Valley Insurance Agency",
    "wof:placetype":"venue"
},
  "geometry": {"coordinates":[-96.466649,41.83544],"type":"Point"}
}