{
  "type": "Feature",
  "properties": {
    "iso:country":"US",
    "sg:address":"2001 W Raymond Rd",
    "sg:city":"Raymond",
    "sg:classifiers":[
        {
            "category":"Manufacturing",
            "subcategory":"Food",
            "type":"Manufacturing & Wholesale Goods"
        }
    ],
    "sg:phone":"+1 402 783 5255",
    "sg:postcode":"68428",
    "sg:province":"NE",
    "sg:tags":[
        "eating",
        "winery",
        "mfg"
    ],
    "wof:name":"James Arthur Vineyard Inc",
    "wof:placetype":"venue"
},
  "geometry": {"coordinates":[-96.756608,40.958626],"type":"Point"}
}