{
  "type": "Feature",
  "properties": {
    "addr:full":"13232 C St Omaha NE 68144",
    "addr:housenumber":"13232",
    "addr:postcode":"68144",
    "addr:street":"C St",
    "iso:country":"US",
    "sg:address":"13232 C St",
    "sg:city":"Omaha",
    "sg:classifiers":[
        {
            "category":"Wholesale",
            "subcategory":"Office Equipment",
            "type":"Manufacturing & Wholesale Goods"
        }
    ],
    "sg:phone":"+1 402 330 3979",
    "sg:postcode":"68144",
    "sg:province":"NE",
    "sg:tags":[
        "machine",
        "mailing"
    ],
    "sg:website":"www.claritus.com",
    "wof:name":"Claritus",
    "wof:placetype":"venue"
},
  "geometry": {"coordinates":[-96.127476,41.222538],"type":"Point"}
}