{
  "type": "Feature",
  "properties": {
    "iso:country":"US",
    "sg:address":"11025 M St",
    "sg:city":"Omaha",
    "sg:classifiers":[
        {
            "category":"Travel",
            "subcategory":"Hotels & Motels",
            "type":"Entertainment"
        }
    ],
    "sg:phone":"+1 402 331 0101",
    "sg:postcode":"68137",
    "sg:province":"NE",
    "sg:website":"www.hawtorn.com",
    "wof:name":"Hawthorn Suites",
    "wof:placetype":"venue"
},
  "geometry": {"coordinates":[-96.08479800000001,41.211894],"type":"Point"}
}