{
  "type": "Feature",
  "properties": {
    "iso:country":"US",
    "sg:address":"1046 N Webster St",
    "sg:city":"Red Cloud",
    "sg:classifiers":[
        {
            "category":"Home & Garden",
            "subcategory":"Building Materials",
            "type":"Retail Goods"
        }
    ],
    "sg:phone":"+1 402 746 2253",
    "sg:postcode":"68970",
    "sg:province":"NE",
    "sg:tags":[
        "lumberyard"
    ],
    "wof:name":"Kennys Lumber & Home Center",
    "wof:placetype":"venue"
},
  "geometry": {"coordinates":[-98.51921,40.095611],"type":"Point"}
}