{
  "type": "Feature",
  "properties": {
    "iso:country":"US",
    "sg:address":"7015 Railroad Ave",
    "sg:city":"Bellevue",
    "sg:classifiers":[
        {
            "category":"Autos & Motor Vehicles",
            "subcategory":"Auto Supplies",
            "type":"Retail Goods"
        }
    ],
    "sg:phone":"+1 402 731 2130",
    "sg:postcode":"68147",
    "sg:province":"NE",
    "wof:name":"Auto Value",
    "wof:placetype":"venue"
},
  "geometry": {"coordinates":[-95.935036,41.18882],"type":"Point"}
}