{
  "type": "Feature",
  "properties": {
    "iso:country":"US",
    "sg:address":"1025 21st St",
    "sg:city":"Gering",
    "sg:classifiers":[
        {
            "category":"Organizations",
            "subcategory":"Religious Organization",
            "type":"Services"
        }
    ],
    "sg:phone":"+1 308 436 3212",
    "sg:postcode":"69341",
    "sg:province":"NE",
    "sg:tags":[
        "church"
    ],
    "wof:name":"Rejoice Lutheran Church",
    "wof:placetype":"venue"
},
  "geometry": {"coordinates":[-103.674729,41.821305],"type":"Point"}
}