{
  "type": "Feature",
  "properties": {
    "addr:full":"404 N Eddy St Grand Island NE 68801",
    "addr:housenumber":"404",
    "addr:postcode":"68801",
    "addr:street":"N Eddy St",
    "iso:country":"US",
    "sg:address":"404 N Eddy St",
    "sg:city":"Grand Island",
    "sg:classifiers":[
        {
            "category":"Retail",
            "subcategory":"Auto Repair",
            "type":"Services"
        }
    ],
    "sg:phone":"+1 308 384 4985",
    "sg:postcode":"68801",
    "sg:province":"NE",
    "sg:tags":[
        "general"
    ],
    "wof:name":"Shop The",
    "wof:placetype":"venue"
},
  "geometry": {"coordinates":[-98.349914,40.925731],"type":"Point"}
}