{
  "type": "Feature",
  "properties": {
    "addr:full":"311 Arapahoe Ave Grand Island NE 68803",
    "addr:housenumber":"311",
    "addr:postcode":"68803",
    "addr:street":"Arapahoe Ave",
    "iso:country":"US",
    "sg:address":"311 Arapahoe Ave",
    "sg:city":"Grand Island",
    "sg:classifiers":[
        {
            "category":"Social Services",
            "subcategory":"Child Care",
            "type":"Services"
        }
    ],
    "sg:phone":"+1 308 382 7355",
    "sg:postcode":"68803",
    "sg:province":"NE",
    "sg:tags":[
        "day"
    ],
    "wof:name":"Knapp Jodi Day Care",
    "wof:placetype":"venue"
},
  "geometry": {"coordinates":[-98.409717,40.921529],"type":"Point"}
}