{
  "type": "Feature",
  "properties": {
    "iso:country":"US",
    "sg:address":"402 W 5th St",
    "sg:city":"Mc Cook",
    "sg:classifiers":[
        {
            "category":"Shopping",
            "subcategory":"Department Store",
            "type":"Retail Goods"
        }
    ],
    "sg:phone":"+1 308 345 5511",
    "sg:postcode":"69001",
    "sg:province":"NE",
    "wof:name":"Sears Roebuck & Co",
    "wof:placetype":"venue"
},
  "geometry": {"coordinates":[-100.632773,40.201767],"type":"Point"}
}