{
  "type": "Feature",
  "properties": {
    "iso:country":"US",
    "sg:address":"4745 S Marian Rd",
    "sg:city":"Hastings",
    "sg:classifiers":[
        {
            "category":"Retail",
            "subcategory":"Auto Repair",
            "type":"Services"
        }
    ],
    "sg:phone":"+1 402 463 3505",
    "sg:postcode":"68901",
    "sg:province":"NE",
    "sg:tags":[
        "repairing",
        "automobile"
    ],
    "wof:name":"S & S Auto Repair",
    "wof:placetype":"venue"
},
  "geometry": {"coordinates":[-98.420953,40.525125],"type":"Point"}
}