{
  "type": "Feature",
  "properties": {
    "addr:full":"802 W 9th St Lexington NE 68850",
    "addr:housenumber":"802",
    "addr:postcode":"68850",
    "addr:street":"W 9Th St",
    "iso:country":"US",
    "sg:address":"802 W 9th St",
    "sg:city":"Lexington",
    "sg:classifiers":[
        {
            "category":"Building & Trades",
            "subcategory":"Construction",
            "type":"Services"
        }
    ],
    "sg:phone":"+1 308 324 2280",
    "sg:postcode":"68850",
    "sg:province":"NE",
    "sg:tags":[
        "house"
    ],
    "wof:name":"Montiels Construction",
    "wof:placetype":"venue"
},
  "geometry": {"coordinates":[-99.75024999999999,40.781913],"type":"Point"}
}