{
  "type": "Feature",
  "properties": {
    "addr:full":"465 N Broadway St Wahoo NE 68066",
    "addr:housenumber":"465",
    "addr:postcode":"68066",
    "addr:street":"N Broadway St",
    "iso:country":"US",
    "sg:address":"465 N Broadway St",
    "sg:city":"Wahoo",
    "sg:classifiers":[
        {
            "category":"Shopping",
            "subcategory":"Discount & Variety Stores",
            "type":"Retail Goods"
        }
    ],
    "sg:phone":"+1 402 443 4272",
    "sg:postcode":"68066",
    "sg:province":"NE",
    "wof:name":"Dollar General",
    "wof:placetype":"venue"
},
  "geometry": {"coordinates":[-96.620086,41.209356],"type":"Point"}
}