{
  "type": "Feature",
  "properties": {
    "addr:full":"3736 S Locust St Grand Island NE 68801",
    "addr:housenumber":"3736",
    "addr:postcode":"68801",
    "addr:street":"S Locust St",
    "iso:country":"US",
    "sg:address":"3736 S Locust St",
    "sg:city":"Grand Island",
    "sg:classifiers":[
        {
            "category":"Communications",
            "subcategory":"Film & Video Production",
            "type":"Services"
        }
    ],
    "sg:phone":"+1 308 379 0100",
    "sg:postcode":"68801",
    "sg:province":"NE",
    "sg:tags":[
        "taping"
    ],
    "wof:name":"Airesonic Video Productions",
    "wof:placetype":"venue"
},
  "geometry": {"coordinates":[-98.33972199999999,40.879313],"type":"Point"}
}