{
  "type": "Feature",
  "properties": {
    "addr:full":"707 Annie St Newcastle NE 68757",
    "addr:housenumber":"707",
    "addr:postcode":"68757",
    "addr:street":"Annie St",
    "iso:country":"US",
    "sg:address":"707 Annie St",
    "sg:city":"Newcastle",
    "sg:classifiers":[
        {
            "category":"Organizations",
            "subcategory":"Religious Organization",
            "type":"Services"
        }
    ],
    "sg:phone":"+1 402 355 2305",
    "sg:postcode":"68757",
    "sg:province":"NE",
    "sg:tags":[
        "church"
    ],
    "wof:name":"Gospel Church",
    "wof:placetype":"venue"
},
  "geometry": {"coordinates":[-96.87866699999999,42.652462],"type":"Point"}
}