{
  "type": "Feature",
  "properties": {
    "addr:full":"6068 Maple St Omaha NE 68104",
    "addr:housenumber":"6068",
    "addr:postcode":"68104",
    "addr:street":"Maple St",
    "iso:country":"US",
    "sg:address":"6068 Maple St",
    "sg:city":"Omaha",
    "sg:classifiers":[
        {
            "category":"Professional",
            "subcategory":"Accounting & Tax Preparation",
            "type":"Services"
        }
    ],
    "sg:phone":"+1 402 551 9525",
    "sg:postcode":"68104",
    "sg:province":"NE",
    "sg:tags":[
        "accountant"
    ],
    "wof:name":"Egan Vincent P PC",
    "wof:placetype":"venue"
},
  "geometry": {"coordinates":[-96.00700399999999,41.285099],"type":"Point"}
}