{
  "type": "Feature",
  "properties": {
    "addr:full":"6323 Skylark Ln Lincoln NE 68516",
    "addr:housenumber":"6323",
    "addr:postcode":"68516",
    "addr:street":"Skylark Ln",
    "iso:country":"US",
    "sg:address":"6323 Skylark Ln",
    "sg:city":"Lincoln",
    "sg:classifiers":[
        {
            "category":"Home & Garden",
            "subcategory":"Hardware",
            "type":"Retail Goods"
        }
    ],
    "sg:phone":"+1 402 483 2686",
    "sg:postcode":"68516",
    "sg:province":"NE",
    "wof:name":"True Design",
    "wof:placetype":"venue"
},
  "geometry": {"coordinates":[-96.634394,40.76286],"type":"Point"}
}