{
  "type": "Feature",
  "properties": {
    "addr:full":"10800 W Center Rd Omaha NE 68144",
    "addr:housenumber":"10800",
    "addr:postcode":"68144",
    "addr:street":"W Center Rd",
    "iso:country":"US",
    "sg:address":"10800 W Center Rd",
    "sg:city":"Omaha",
    "sg:classifiers":[
        {
            "category":"Recreation",
            "type":"Entertainment"
        }
    ],
    "sg:phone":"+1 402 391 9102",
    "sg:postcode":"68144",
    "sg:province":"NE",
    "sg:tags":[
        "pool",
        "swimming"
    ],
    "wof:name":"Rockbrook Swimming Pool",
    "wof:placetype":"venue"
},
  "geometry": {"coordinates":[-96.08329999999999,41.234176],"type":"Point"}
}