{
  "type": "Feature",
  "properties": {
    "iso:country":"US",
    "sg:address":"560 S 126th St",
    "sg:city":"Omaha",
    "sg:classifiers":[
        {
            "category":"Shopping",
            "subcategory":"Gifts & Souvenirs",
            "type":"Retail Goods"
        }
    ],
    "sg:phone":"+1 402 333 3639",
    "sg:postcode":"68154",
    "sg:province":"NE",
    "wof:name":"Heartlines",
    "wof:placetype":"venue"
},
  "geometry": {"coordinates":[-96.109589,41.253904],"type":"Point"}
}