{
  "type": "Feature",
  "properties": {
    "iso:country":"US",
    "sg:address":"2416 Davenport St",
    "sg:city":"Omaha",
    "sg:classifiers":[
        {
            "category":"Personal",
            "subcategory":"Barber",
            "type":"Services"
        }
    ],
    "sg:phone":"+1 402 345 1377",
    "sg:postcode":"68131",
    "sg:province":"NE",
    "wof:name":"Moore's Precision Cut",
    "wof:placetype":"venue"
},
  "geometry": {"coordinates":[-95.947256,41.261774],"type":"Point"}
}