{
  "type": "Feature",
  "properties": {
    "iso:country":"US",
    "sg:address":"141 Koenig Dr",
    "sg:city":"Ogallala",
    "sg:classifiers":[
        {
            "category":"Organizations",
            "subcategory":"Community Association",
            "type":"Services"
        }
    ],
    "sg:phone":"+1 308 284 2526",
    "sg:postcode":"69153",
    "sg:province":"NE",
    "wof:name":"International Assn Lions",
    "wof:placetype":"venue"
},
  "geometry": {"coordinates":[-101.723096,41.08477],"type":"Point"}
}