{
  "type": "Feature",
  "properties": {
    "iso:country":"US",
    "sg:address":"707 A St",
    "sg:city":"Lincoln",
    "sg:classifiers":[
        {
            "category":"Shopping",
            "type":"Retail Goods"
        }
    ],
    "sg:phone":"+1 402 466 8102",
    "sg:postcode":"68502",
    "sg:province":"NE",
    "sg:tags":[
        "merchandise"
    ],
    "wof:name":"Crazy Cracker Fireworks Inc",
    "wof:placetype":"venue"
},
  "geometry": {"coordinates":[-96.71011,40.79915],"type":"Point"}
}