{
  "type": "Feature",
  "properties": {
    "addr:full":"304 Elliot St Dalton NE 69131",
    "addr:housenumber":"304",
    "addr:postcode":"69131",
    "addr:street":"Elliot St",
    "iso:country":"US",
    "sg:address":"304 Elliot St",
    "sg:city":"Dalton",
    "sg:classifiers":[
        {
            "category":"Building & Trades",
            "subcategory":"Landscaping Services",
            "type":"Services"
        }
    ],
    "sg:phone":"+1 308 377 2665",
    "sg:postcode":"69131",
    "sg:province":"NE",
    "sg:tags":[
        "landscape",
        "contractor"
    ],
    "wof:name":"LCIS",
    "wof:placetype":"venue"
},
  "geometry": {"coordinates":[-102.97287900000001,41.40909],"type":"Point"}
}