{
  "type": "Feature",
  "properties": {
    "iso:country":"US",
    "sg:address":"7021 Lafayette Ave",
    "sg:city":"Omaha",
    "sg:classifiers":[
        {
            "category":"Shopping",
            "type":"Retail Goods"
        }
    ],
    "sg:phone":"+1 402 573 0400",
    "sg:postcode":"68132",
    "sg:province":"NE",
    "sg:tags":[
        "merchandise"
    ],
    "wof:name":"Amazing Aquatics",
    "wof:placetype":"venue"
},
  "geometry": {"coordinates":[-96.023642,41.271386],"type":"Point"}
}