{
  "type": "Feature",
  "properties": {
    "iso:country":"US",
    "sg:address":"222 S Mayne St",
    "sg:city":"Valley",
    "sg:classifiers":[
        {
            "category":"Retail",
            "subcategory":"Funeral Services",
            "type":"Services"
        }
    ],
    "sg:phone":"+1 402 359 2222",
    "sg:postcode":"68064",
    "sg:province":"NE",
    "sg:tags":[
        "director"
    ],
    "wof:name":"Reichmuth Funeral Homes",
    "wof:placetype":"venue"
},
  "geometry": {"coordinates":[-96.34699999999999,41.310975],"type":"Point"}
}