{
  "type": "Feature",
  "properties": {
    "addr:full":"4500 Cornhusker Hwy Lincoln NE 68504",
    "addr:housenumber":"4500",
    "addr:postcode":"68504",
    "addr:street":"Cornhusker Hwy",
    "iso:country":"US",
    "sg:address":"4500 Cornhusker Hwy",
    "sg:city":"Lincoln",
    "sg:classifiers":[
        {
            "category":"Insurance",
            "subcategory":"Insurance Agent",
            "type":"Services"
        }
    ],
    "sg:phone":"+1 402 477 4044",
    "sg:postcode":"68504",
    "sg:province":"NE",
    "wof:name":"American Family Insurance",
    "wof:placetype":"venue"
},
  "geometry": {"coordinates":[-96.654715,40.851352],"type":"Point"}
}