{
  "type": "Feature",
  "properties": {
    "addr:full":"6949 S 107th St La Vista NE 68128",
    "addr:housenumber":"6949",
    "addr:postcode":"68128",
    "addr:street":"S 107Th St",
    "iso:country":"US",
    "sg:address":"6949 S 107th St",
    "sg:city":"La Vista",
    "sg:classifiers":[
        {
            "category":"Wholesale",
            "subcategory":"Construction Materials",
            "type":"Manufacturing & Wholesale Goods"
        }
    ],
    "sg:phone":"+1 402 592 0260",
    "sg:postcode":"68128",
    "sg:province":"NE",
    "sg:tags":[
        "steel",
        "windows",
        "frame",
        "door"
    ],
    "wof:name":"Metal Doors & Hardware Co",
    "wof:placetype":"venue"
},
  "geometry": {"coordinates":[-96.079294,41.189527],"type":"Point"}
}