{
  "type": "Feature",
  "properties": {
    "addr:full":"1020 Eads Ave Hebron NE 68370",
    "addr:housenumber":"1020",
    "addr:postcode":"68370",
    "addr:street":"Eads Ave",
    "iso:country":"US",
    "sg:address":"1020 Eads Ave",
    "sg:city":"Hebron",
    "sg:classifiers":[
        {
            "category":"Education",
            "subcategory":"School",
            "type":"Public Place"
        }
    ],
    "sg:phone":"+1 402 768 7287",
    "sg:postcode":"68370",
    "sg:province":"NE",
    "wof:name":"Thayer Central Elementary Schl",
    "wof:placetype":"venue"
},
  "geometry": {"coordinates":[-97.581721,40.170222],"type":"Point"}
}