{
  "type": "Feature",
  "properties": {
    "iso:country":"US",
    "sg:address":"501 N 87th St",
    "sg:city":"Omaha",
    "sg:classifiers":[
        {
            "category":"Personal",
            "type":"Services"
        }
    ],
    "sg:phone":"+1 402 578 6279",
    "sg:postcode":"68114",
    "sg:province":"NE",
    "sg:tags":[
        "electrolysis"
    ],
    "wof:name":"Absolute Perfection",
    "wof:placetype":"venue"
},
  "geometry": {"coordinates":[-96.04773299999999,41.265122],"type":"Point"}
}