{
  "type": "Feature",
  "properties": {
    "addr:full":"3541 Merritt Dr Lincoln NE 68506",
    "addr:housenumber":"3541",
    "addr:postcode":"68506",
    "addr:street":"Merritt Dr",
    "iso:country":"US",
    "sg:address":"3541 Merritt Dr",
    "sg:city":"Lincoln",
    "sg:classifiers":[
        {
            "category":"Education",
            "subcategory":"Special Training",
            "type":"Public Place"
        }
    ],
    "sg:phone":"+1 402 484 8284",
    "sg:postcode":"68506",
    "sg:province":"NE",
    "wof:name":"Defrain Music Studio",
    "wof:placetype":"venue"
},
  "geometry": {"coordinates":[-96.671471,40.777546],"type":"Point"}
}