{
  "type": "Feature",
  "properties": {
    "addr:full":"12009 S 84th St Papillion NE 68046",
    "addr:housenumber":"12009",
    "addr:postcode":"68046",
    "addr:street":"S 84Th St",
    "iso:country":"US",
    "sg:address":"12009 S 84th St",
    "sg:city":"Papillion",
    "sg:classifiers":[
        {
            "category":"Organizations",
            "subcategory":"Religious Organization",
            "type":"Services"
        }
    ],
    "sg:phone":"+1 402 339 0461",
    "sg:postcode":"68046",
    "sg:province":"NE",
    "sg:tags":[
        "church"
    ],
    "wof:name":"Church Of Jesus Christ Of Lds",
    "wof:placetype":"venue"
},
  "geometry": {"coordinates":[-96.042835,41.13337],"type":"Point"}
}