{
  "type": "Feature",
  "properties": {
    "addr:full":"1720 US Hwy 30 Kearney NE 68847",
    "addr:housenumber":"1720",
    "addr:postcode":"68847",
    "addr:street":"Us Hwy 30",
    "iso:country":"US",
    "sg:address":"1720 US Hwy 30",
    "sg:city":"Kearney",
    "sg:classifiers":[
        {
            "category":"Wholesale",
            "subcategory":"Machinery & Supplies",
            "type":"Manufacturing & Wholesale Goods"
        }
    ],
    "sg:phone":"+1 308 236 5496",
    "sg:postcode":"68847",
    "sg:province":"NE",
    "sg:tags":[
        "construction",
        "nonresidential"
    ],
    "wof:name":"Mid-Sttes Irrgation of Kearney",
    "wof:placetype":"venue"
},
  "geometry": {"coordinates":[-99.06100600000001,40.700092],"type":"Point"}
}