{
  "type": "Feature",
  "properties": {
    "iso:country":"US",
    "sg:address":"1505 Sycamore St",
    "sg:city":"Bellevue",
    "sg:classifiers":[
        {
            "category":"Autos & Motor Vehicles",
            "subcategory":"Boat Sales",
            "type":"Retail Goods"
        }
    ],
    "sg:phone":"+1 402 502 0500",
    "sg:postcode":"68005",
    "sg:province":"NE",
    "sg:tags":[
        "dealer",
        "sales"
    ],
    "wof:name":"Mid American Boats Inc",
    "wof:placetype":"venue"
},
  "geometry": {"coordinates":[-95.916138,41.160651],"type":"Point"}
}