{
  "type": "Feature",
  "properties": {
    "addr:full":"1063 N 204th Ave Elkhorn NE 68022",
    "addr:housenumber":"1063",
    "addr:postcode":"68022",
    "addr:street":"N 204Th Ave",
    "iso:country":"US",
    "sg:address":"1063 N 204th Ave",
    "sg:city":"Elkhorn",
    "sg:classifiers":[
        {
            "category":"Real Estate",
            "subcategory":"Surveying",
            "type":"Services"
        }
    ],
    "sg:phone":"+1 402 763 9475",
    "sg:postcode":"68022",
    "sg:province":"NE",
    "sg:tags":[
        "surveyor"
    ],
    "wof:name":"3DS2",
    "wof:placetype":"venue"
},
  "geometry": {"coordinates":[-96.23490700000001,41.26755],"type":"Point"}
}