{
  "type": "Feature",
  "properties": {
    "addr:full":"754 W A St Lincoln NE 68522",
    "addr:housenumber":"754",
    "addr:postcode":"68522",
    "addr:street":"W A St",
    "iso:country":"US",
    "sg:address":"754 W A St",
    "sg:city":"Lincoln",
    "sg:classifiers":[
        {
            "category":"Building & Trades",
            "subcategory":"Construction",
            "type":"Services"
        }
    ],
    "sg:phone":"+1 402 432 7857",
    "sg:postcode":"68522",
    "sg:province":"NE",
    "sg:tags":[
        "contractor"
    ],
    "wof:name":"Capital Glass & Mirror",
    "wof:placetype":"venue"
},
  "geometry": {"coordinates":[-96.73159699999999,40.799191],"type":"Point"}
}