{
  "type": "Feature",
  "properties": {
    "iso:country":"US",
    "sg:address":"8121 Lake St",
    "sg:city":"Omaha",
    "sg:classifiers":[
        {
            "category":"Building & Trades",
            "subcategory":"Construction",
            "type":"Services"
        }
    ],
    "sg:phone":"+1 402 391 4464",
    "sg:postcode":"68134",
    "sg:province":"NE",
    "sg:tags":[
        "general",
        "contractor"
    ],
    "wof:name":"Kenneth W Church Contractor",
    "wof:placetype":"venue"
},
  "geometry": {"coordinates":[-96.041875,41.281363],"type":"Point"}
}