{
  "type": "Feature",
  "properties": {
    "iso:country":"US",
    "sg:address":"1306 Maberly St",
    "sg:city":"Holdrege",
    "sg:classifiers":[
        {
            "category":"Real Estate",
            "subcategory":"Real Estate Operator",
            "type":"Services"
        }
    ],
    "sg:phone":"+1 308 995 4200",
    "sg:postcode":"68949",
    "sg:province":"NE",
    "sg:tags":[
        "property",
        "lessor"
    ],
    "wof:name":"Virgil Sims Farm",
    "wof:placetype":"venue"
},
  "geometry": {"coordinates":[-99.38555700000001,40.447772],"type":"Point"}
}