{
  "type": "Feature",
  "properties": {
    "addr:full":"410 W Railway St Scottsbluff NE 69361",
    "addr:housenumber":"410",
    "addr:postcode":"69361",
    "addr:street":"W Railway St",
    "iso:country":"US",
    "sg:address":"410 W Railway St",
    "sg:city":"Scottsbluff",
    "sg:phone":"+1 308 632 4777",
    "sg:postcode":"69361",
    "sg:province":"NE",
    "sg:tags":[
        "oil"
    ],
    "wof:name":"Haiston Oil Co",
    "wof:placetype":"venue"
},
  "geometry": {"coordinates":[-103.66959799999999,41.865215],"type":"Point"}
}