{
  "type": "Feature",
  "properties": {
    "iso:country":"US",
    "sg:address":"505 N 66th St",
    "sg:city":"Lincoln",
    "sg:classifiers":[
        {
            "category":"Retail",
            "subcategory":"Animal Services",
            "type":"Services"
        }
    ],
    "sg:phone":"+1 402 464 7666",
    "sg:postcode":"68505",
    "sg:province":"NE",
    "sg:tags":[
        "pet",
        "grooming",
        "washing"
    ],
    "wof:name":"Certified Grooming",
    "wof:placetype":"venue"
},
  "geometry": {"coordinates":[-96.63065899999999,40.817665],"type":"Point"}
}