{
  "type": "Feature",
  "properties": {
    "iso:country":"US",
    "sg:address":"845 10th St",
    "sg:city":"Gering",
    "sg:classifiers":[
        {
            "category":"Retail",
            "subcategory":"Portrait Studio",
            "type":"Services"
        }
    ],
    "sg:phone":"+1 308 436 4236",
    "sg:postcode":"69341",
    "sg:province":"NE",
    "sg:tags":[
        "photographer"
    ],
    "wof:name":"Photos By Gene Inc",
    "wof:placetype":"venue"
},
  "geometry": {"coordinates":[-103.660528,41.81753],"type":"Point"}
}