{
  "type": "Feature",
  "properties": {
    "addr:full":"18021 R Plz Suite 1 Omaha NE 68135",
    "addr:housenumber":"18021",
    "addr:postcode":"68135",
    "addr:street":"R Plz Suite 1",
    "iso:country":"US",
    "sg:address":"18021 R Plz Suite 1",
    "sg:city":"Omaha",
    "sg:classifiers":[
        {
            "category":"Health Services",
            "subcategory":"Dentist",
            "type":"Services"
        }
    ],
    "sg:phone":"+1 866 969 5921",
    "sg:postcode":"68135",
    "sg:province":"NE",
    "sg:tags":[
        "dentists-cosmetic",
        "dentistry"
    ],
    "sg:website":"http://www.belcherfamilydentistry.com",
    "wof:name":"Belcher Family Dentistry",
    "wof:placetype":"venue"
},
  "geometry": {"coordinates":[-96.196797,41.203623],"type":"Point"}
}