{
  "type": "Feature",
  "properties": {
    "addr:full":"1460 W 23rd St Fremont NE 68025",
    "addr:housenumber":"1460",
    "addr:postcode":"68025",
    "addr:street":"W 23Rd St",
    "iso:country":"US",
    "sg:address":"1460 W 23rd St",
    "sg:city":"Fremont",
    "sg:classifiers":[
        {
            "category":"Professional",
            "subcategory":"Management & Consulting",
            "type":"Services"
        }
    ],
    "sg:phone":"+1 402 727 6053",
    "sg:postcode":"68025",
    "sg:province":"NE",
    "sg:tags":[
        "business"
    ],
    "wof:name":"U-Haul",
    "wof:placetype":"venue"
},
  "geometry": {"coordinates":[-96.515944,41.451173],"type":"Point"}
}