{
  "type": "Feature",
  "properties": {
    "iso:country":"US",
    "sg:address":"2318 Central Ave",
    "sg:city":"Kearney",
    "sg:classifiers":[
        {
            "category":"Cinema",
            "subcategory":"Movie Theater",
            "type":"Entertainment"
        }
    ],
    "sg:phone":"+1 308 236 5791",
    "sg:postcode":"68847",
    "sg:province":"NE",
    "wof:name":"World II Theatre",
    "wof:placetype":"venue"
},
  "geometry": {"coordinates":[-99.08176400000001,40.6992],"type":"Point"}
}