{
  "type": "Feature",
  "properties": {
    "addr:full":"801 Galvin Rd Omaha NE 68102",
    "addr:housenumber":"801",
    "addr:postcode":"68102",
    "addr:street":"Galvin Rd",
    "iso:country":"US",
    "sg:address":"801 Galvin Rd",
    "sg:city":"Omaha",
    "sg:classifiers":[
        {
            "category":"Shopping",
            "subcategory":"Pharmacy",
            "type":"Retail Goods"
        },
        {
            "category":"Food & Beverages",
            "subcategory":"Groceries & Convenience Stores",
            "type":"Retail Goods"
        }
    ],
    "sg:phone":"+1 402 292 0331",
    "sg:postcode":"68102",
    "sg:province":"NE",
    "sg:tags":[
        "drugstore"
    ],
    "wof:name":"Baker's Pharmacies",
    "wof:placetype":"venue"
},
  "geometry": {"coordinates":[-95.937202,41.257198],"type":"Point"}
}