{
  "type": "Feature",
  "properties": {
    "addr:full":"226 Denver St Holdrege NE 68949",
    "addr:housenumber":"226",
    "addr:postcode":"68949",
    "addr:street":"Denver St",
    "iso:country":"US",
    "sg:address":"226 Denver St",
    "sg:city":"Holdrege",
    "sg:classifiers":[
        {
            "category":"Wholesale",
            "subcategory":"Machinery & Supplies",
            "type":"Manufacturing & Wholesale Goods"
        }
    ],
    "sg:phone":"+1 308 995 8459",
    "sg:postcode":"68949",
    "sg:province":"NE",
    "sg:tags":[
        "farm",
        "equipment"
    ],
    "wof:name":"Orscheln Farm & Home",
    "wof:placetype":"venue"
},
  "geometry": {"coordinates":[-99.387075,40.436149],"type":"Point"}
}