{
  "type": "Feature",
  "properties": {
    "addr:full":"3075 Arcadia Ave Omaha NE 68111",
    "addr:housenumber":"3075",
    "addr:postcode":"68111",
    "addr:street":"Arcadia Ave",
    "iso:country":"US",
    "sg:address":"3075 Arcadia Ave",
    "sg:city":"Omaha",
    "sg:classifiers":[
        {
            "category":"Social Services",
            "subcategory":"Child Care",
            "type":"Services"
        }
    ],
    "sg:phone":"+1 402 455 6144",
    "sg:postcode":"68111",
    "sg:province":"NE",
    "sg:tags":[
        "day"
    ],
    "wof:name":"Hickerson Hellecia Day Care",
    "wof:placetype":"venue"
},
  "geometry": {"coordinates":[-95.958505,41.312548],"type":"Point"}
}