{
  "type": "Feature",
  "properties": {
    "iso:country":"US",
    "sg:address":"1309 N B St",
    "sg:city":"Broken Bow",
    "sg:classifiers":[
        {
            "category":"Health Services",
            "subcategory":"Hospital",
            "type":"Services"
        }
    ],
    "sg:phone":"+1 308 872 6063",
    "sg:postcode":"68822",
    "sg:province":"NE",
    "sg:tags":[
        "mental"
    ],
    "wof:name":"Mental Retardation Region III",
    "wof:placetype":"venue"
},
  "geometry": {"coordinates":[-99.64640300000001,41.406525],"type":"Point"}
}