{
  "type": "Feature",
  "properties": {
    "iso:country":"US",
    "sg:address":"1324 4th St",
    "sg:city":"Fairbury",
    "sg:classifiers":[
        {
            "category":"Retail",
            "subcategory":"Repair Shop",
            "type":"Services"
        }
    ],
    "sg:phone":"+1 402 729 6286",
    "sg:postcode":"68352",
    "sg:province":"NE",
    "wof:name":"Maxs TV Service",
    "wof:placetype":"venue"
},
  "geometry": {"coordinates":[-97.168458,40.135086],"type":"Point"}
}