{
  "type": "Feature",
  "properties": {
    "addr:full":"120 E 6th St Lexington NE 68850",
    "addr:housenumber":"120",
    "addr:postcode":"68850",
    "addr:street":"E 6Th St",
    "iso:country":"US",
    "sg:address":"120 E 6th St",
    "sg:city":"Lexington",
    "sg:classifiers":[
        {
            "category":"Manufacturing",
            "subcategory":"Printing",
            "type":"Manufacturing & Wholesale Goods"
        }
    ],
    "sg:phone":"+1 308 324 4686",
    "sg:postcode":"68850",
    "sg:province":"NE",
    "sg:tags":[
        "newspaper"
    ],
    "wof:name":"Tri-City Trib",
    "wof:placetype":"venue"
},
  "geometry": {"coordinates":[-99.741317,40.778745],"type":"Point"}
}