{
  "type": "Feature",
  "properties": {
    "addr:full":"111 S 14th St Fort Calhoun NE 68023",
    "addr:housenumber":"111",
    "addr:postcode":"68023",
    "addr:street":"S 14Th St",
    "iso:country":"US",
    "sg:address":"111 S 14th St",
    "sg:city":"Fort Calhoun",
    "sg:classifiers":[
        {
            "category":"Autos & Motor Vehicles",
            "subcategory":"Fuel & Gas Station",
            "type":"Retail Goods"
        }
    ],
    "sg:phone":"+1 402 468 5715",
    "sg:postcode":"68023",
    "sg:province":"NE",
    "sg:tags":[
        "oil"
    ],
    "wof:name":"Conoco-Calhoun Oil Co",
    "wof:placetype":"venue"
},
  "geometry": {"coordinates":[-96.026297,41.455664],"type":"Point"}
}