{
  "type": "Feature",
  "properties": {
    "addr:full":"911 Maberly St Holdrege NE 68949",
    "addr:housenumber":"911",
    "addr:postcode":"68949",
    "addr:street":"Maberly St",
    "iso:country":"US",
    "sg:address":"911 Maberly St",
    "sg:city":"Holdrege",
    "sg:classifiers":[
        {
            "category":"Wholesale",
            "subcategory":"Auto Parts",
            "type":"Manufacturing & Wholesale Goods"
        }
    ],
    "sg:phone":"+1 308 995 4212",
    "sg:postcode":"68949",
    "sg:province":"NE",
    "sg:tags":[
        "automobile",
        "rebuilt"
    ],
    "wof:name":"Richardson & Son Auto Wrecking",
    "wof:placetype":"venue"
},
  "geometry": {"coordinates":[-99.38590600000001,40.445077],"type":"Point"}
}