{
  "type": "Feature",
  "properties": {
    "iso:country":"US",
    "sg:address":"701 Lakeside Dr",
    "sg:city":"Lincoln",
    "sg:classifiers":[
        {
            "category":"Real Estate",
            "subcategory":"Real Estate Operator",
            "type":"Services"
        }
    ],
    "sg:phone":"+1 402 476 5000",
    "sg:postcode":"68528",
    "sg:province":"NE",
    "sg:tags":[
        "apartment"
    ],
    "wof:name":"Lakeside Village",
    "wof:placetype":"venue"
},
  "geometry": {"coordinates":[-96.75067199999999,40.819137],"type":"Point"}
}