{
  "type": "Feature",
  "properties": {
    "iso:country":"US",
    "sg:address":"25 Sara Dr",
    "sg:city":"Hastings",
    "sg:classifiers":[
        {
            "category":"Professional",
            "subcategory":"Business Services",
            "type":"Services"
        }
    ],
    "sg:phone":"+1 402 462 9181",
    "sg:postcode":"68901",
    "sg:province":"NE",
    "sg:tags":[
        "cleaning"
    ],
    "wof:name":"Supreme Cleaning Services",
    "wof:placetype":"venue"
},
  "geometry": {"coordinates":[-98.36264799999999,40.588085],"type":"Point"}
}