{
  "type": "Feature",
  "properties": {
    "addr:full":"5945 N 70th St Lincoln NE 68507",
    "addr:housenumber":"5945",
    "addr:postcode":"68507",
    "addr:street":"N 70Th St",
    "iso:country":"US",
    "sg:address":"5945 N 70th St",
    "sg:city":"Lincoln",
    "sg:classifiers":[
        {
            "category":"Manufacturing",
            "subcategory":"Metals",
            "type":"Manufacturing & Wholesale Goods"
        }
    ],
    "sg:phone":"+1 402 464 7466",
    "sg:postcode":"68507",
    "sg:province":"NE",
    "sg:tags":[
        "foundry"
    ],
    "sg:website":"www.deeter.com",
    "wof:name":"Deeter Foundry Inc",
    "wof:placetype":"venue"
},
  "geometry": {"coordinates":[-96.624666,40.870338],"type":"Point"}
}