{
  "type": "Feature",
  "properties": {
    "iso:country":"US",
    "sg:address":"1002 2nd St",
    "sg:city":"Chappell",
    "sg:classifiers":[
        {
            "category":"Professional",
            "type":"Services"
        }
    ],
    "sg:phone":"+1 308 874 3030",
    "sg:postcode":"69129",
    "sg:province":"NE",
    "sg:tags":[
        "establishment"
    ],
    "wof:name":"Sweden Creme",
    "wof:placetype":"venue"
},
  "geometry": {"coordinates":[-102.46813,41.09265],"type":"Point"}
}