{
  "type": "Feature",
  "properties": {
    "addr:full":"1933 S 51st St Omaha NE 68106",
    "addr:housenumber":"1933",
    "addr:postcode":"68106",
    "addr:street":"S 51St St",
    "iso:country":"US",
    "sg:address":"1933 S 51st St",
    "sg:city":"Omaha",
    "sg:classifiers":[
        {
            "category":"Personal",
            "subcategory":"Beauty Salon",
            "type":"Services"
        }
    ],
    "sg:phone":"+1 402 334 2434",
    "sg:postcode":"68106",
    "sg:province":"NE",
    "sg:tags":[
        "treatment",
        "skin"
    ],
    "wof:name":"Dermappeal Inc",
    "wof:placetype":"venue"
},
  "geometry": {"coordinates":[-95.99266299999999,41.239901],"type":"Point"}
}