{
  "type": "Feature",
  "properties": {
    "addr:full":"3716 S 132nd St Omaha NE 68144",
    "addr:housenumber":"3716",
    "addr:postcode":"68144",
    "addr:street":"S 132Nd St",
    "iso:country":"US",
    "sg:address":"3716 S 132nd St",
    "sg:city":"Omaha",
    "sg:classifiers":[
        {
            "category":"Wholesale",
            "subcategory":"Machinery & Supplies",
            "type":"Manufacturing & Wholesale Goods"
        }
    ],
    "sg:phone":"+1 402 334 7652",
    "sg:postcode":"68144",
    "sg:province":"NE",
    "sg:tags":[
        "shop",
        "equipment",
        "salon",
        "barber",
        "beauty"
    ],
    "wof:name":"Sally Beauty Supply 315",
    "wof:placetype":"venue"
},
  "geometry": {"coordinates":[-96.119511,41.221671],"type":"Point"}
}