{
  "type": "Feature",
  "properties": {
    "iso:country":"US",
    "sg:address":"1232 Campfire Cir",
    "sg:city":"Lincoln",
    "sg:classifiers":[
        {
            "category":"Building & Trades",
            "subcategory":"Electrical",
            "type":"Services"
        }
    ],
    "sg:phone":"+1 402 421 2006",
    "sg:postcode":"68512",
    "sg:province":"NE",
    "sg:tags":[
        "electrical",
        "contractor"
    ],
    "wof:name":"Nucleus Construction",
    "wof:placetype":"venue"
},
  "geometry": {"coordinates":[-96.703773,40.745795],"type":"Point"}
}