{
  "type": "Feature",
  "properties": {
    "addr:full":"11027 I St Omaha NE 68137",
    "addr:housenumber":"11027",
    "addr:postcode":"68137",
    "addr:street":"I St",
    "iso:country":"US",
    "sg:address":"11027 I St",
    "sg:city":"Omaha",
    "sg:classifiers":[
        {
            "category":"Utilities",
            "subcategory":"Telephone",
            "type":"Services"
        }
    ],
    "sg:phone":"+1 402 331 9066",
    "sg:postcode":"68137",
    "sg:province":"NE",
    "sg:tags":[
        "communications"
    ],
    "wof:name":"AT&T",
    "wof:placetype":"venue"
},
  "geometry": {"coordinates":[-96.08742599999999,41.216157],"type":"Point"}
}