{
  "type": "Feature",
  "properties": {
    "iso:country":"US",
    "sg:address":"507 W 3rd St",
    "sg:city":"Mc Cook",
    "sg:classifiers":[
        {
            "category":"Organizations",
            "subcategory":"Religious Organization",
            "type":"Services"
        }
    ],
    "sg:phone":"+1 308 345 2330",
    "sg:postcode":"69001",
    "sg:province":"NE",
    "sg:tags":[
        "church"
    ],
    "wof:name":"Cornerstone Fellowship",
    "wof:placetype":"venue"
},
  "geometry": {"coordinates":[-100.629897,40.202709],"type":"Point"}
}