{
  "type": "Feature",
  "properties": {
    "addr:full":"4035 Woods Blvd Lincoln NE 68502",
    "addr:housenumber":"4035",
    "addr:postcode":"68502",
    "addr:street":"Woods Blvd",
    "iso:country":"US",
    "sg:address":"4035 Woods Blvd",
    "sg:city":"Lincoln",
    "sg:classifiers":[
        {
            "category":"Wholesale",
            "subcategory":"Machinery & Supplies",
            "type":"Manufacturing & Wholesale Goods"
        }
    ],
    "sg:phone":"+1 402 540 6930",
    "sg:postcode":"68502",
    "sg:province":"NE",
    "sg:tags":[
        "equipment",
        "industrial"
    ],
    "wof:name":"Select Service",
    "wof:placetype":"venue"
},
  "geometry": {"coordinates":[-96.689516,40.773793],"type":"Point"}
}