{
  "type": "Feature",
  "properties": {
    "addr:full":"1511 N 113th Plz Omaha NE 68154",
    "addr:housenumber":"1511",
    "addr:postcode":"68154",
    "addr:street":"N 113Th",
    "iso:country":"US",
    "sg:address":"1511 N 113th Plz",
    "sg:city":"Omaha",
    "sg:classifiers":[
        {
            "category":"Arena",
            "subcategory":"Sports Club",
            "type":"Entertainment"
        }
    ],
    "sg:phone":"+1 402 829 0345",
    "sg:postcode":"68154",
    "sg:province":"NE",
    "wof:name":"Setag Sports Management",
    "wof:placetype":"venue"
},
  "geometry": {"coordinates":[-96.090878,41.27485],"type":"Point"}
}