{
  "type": "Feature",
  "properties": {
    "addr:full":"304 Mc Pherson St Crawford NE 69339",
    "addr:housenumber":"304",
    "addr:postcode":"69339",
    "addr:street":"Mc Pherson St",
    "iso:country":"US",
    "sg:address":"304 Mc Pherson St",
    "sg:city":"Crawford",
    "sg:classifiers":[
        {
            "category":"Travel",
            "subcategory":"Hotels & Motels",
            "type":"Entertainment"
        }
    ],
    "sg:phone":"+1 308 665 1144",
    "sg:postcode":"69339",
    "sg:province":"NE",
    "wof:name":"Hilltop Motel",
    "wof:placetype":"venue"
},
  "geometry": {"coordinates":[-103.41058,42.677816],"type":"Point"}
}