{
  "type": "Feature",
  "properties": {
    "iso:country":"US",
    "sg:address":"1122 W 11th St",
    "sg:city":"Crete",
    "sg:classifiers":[
        {
            "category":"Retail",
            "subcategory":"Car Wash",
            "type":"Services"
        }
    ],
    "sg:phone":"+1 402 826 2828",
    "sg:postcode":"68333",
    "sg:province":"NE",
    "sg:tags":[
        "carwash"
    ],
    "wof:name":"Crete Truck/Car Wash & Sales",
    "wof:placetype":"venue"
},
  "geometry": {"coordinates":[-96.973949,40.623381],"type":"Point"}
}