{
  "type": "Feature",
  "properties": {
    "addr:full":"2067 N 120th St Omaha NE 68164",
    "addr:housenumber":"2067",
    "addr:postcode":"68164",
    "addr:street":"N 120Th St",
    "iso:country":"US",
    "sg:address":"2067 N 120th St",
    "sg:city":"Omaha",
    "sg:classifiers":[
        {
            "category":"Health Services",
            "subcategory":"Doctor",
            "type":"Services"
        }
    ],
    "sg:phone":"+1 402 492 8626",
    "sg:postcode":"68164",
    "sg:province":"NE",
    "wof:name":"Countryside Dental",
    "wof:placetype":"venue"
},
  "geometry": {"coordinates":[-96.100449,41.279733],"type":"Point"}
}