{
  "type": "Feature",
  "properties": {
    "iso:country":"US",
    "sg:address":"9817 Harney Pkwy S",
    "sg:city":"Omaha",
    "sg:classifiers":[
        {
            "category":"Health Services",
            "subcategory":"Doctor",
            "type":"Services"
        }
    ],
    "sg:phone":"+1 402 559 4416",
    "sg:postcode":"68114",
    "sg:province":"NE",
    "sg:tags":[
        "physician",
        "surgeon"
    ],
    "wof:name":"University Medical Ctr",
    "wof:placetype":"venue"
},
  "geometry": {"coordinates":[-96.06509699999999,41.253266],"type":"Point"}
}