{
  "type": "Feature",
  "properties": {
    "iso:country":"US",
    "sg:address":"413 D St",
    "sg:city":"Fairfield",
    "sg:classifiers":[
        {
            "category":"Organizations",
            "subcategory":"Professional Association",
            "type":"Services"
        }
    ],
    "sg:phone":"+1 402 726 2304",
    "sg:postcode":"68938",
    "sg:province":"NE",
    "wof:name":"Fairfield American Legion",
    "wof:placetype":"venue"
},
  "geometry": {"coordinates":[-98.105845,40.431289],"type":"Point"}
}