{
  "type": "Feature",
  "properties": {
    "iso:country":"US",
    "sg:address":"2400 8th Ave",
    "sg:city":"Plattsmouth",
    "sg:classifiers":[
        {
            "category":"Food & Beverages",
            "subcategory":"Groceries & Convenience Stores",
            "type":"Retail Goods"
        }
    ],
    "sg:phone":"+1 402 296 3355",
    "sg:postcode":"68048",
    "sg:province":"NE",
    "sg:tags":[
        "grocer"
    ],
    "sg:website":"www.nofrillssupermarkets.com",
    "wof:name":"No Frills Supermarket",
    "wof:placetype":"venue"
},
  "geometry": {"coordinates":[-95.905406,41.002527],"type":"Point"}
}