{
  "type": "Feature",
  "properties": {
    "addr:full":"11810 Nicholas St Omaha NE 68154",
    "addr:housenumber":"11810",
    "addr:postcode":"68154",
    "addr:street":"Nicholas St",
    "iso:country":"US",
    "sg:address":"11810 Nicholas St",
    "sg:city":"Omaha",
    "sg:classifiers":[
        {
            "category":"Professional",
            "subcategory":"Computer Services",
            "type":"Services"
        }
    ],
    "sg:phone":"+1 402 222 1217",
    "sg:postcode":"68154",
    "sg:province":"NE",
    "sg:tags":[
        "credit",
        "short",
        "datum",
        "business"
    ],
    "wof:name":"First Data",
    "wof:placetype":"venue"
},
  "geometry": {"coordinates":[-96.098348,41.269316],"type":"Point"}
}