{
  "type": "Feature",
  "properties": {
    "iso:country":"US",
    "sg:address":"3420 Oak View Dr",
    "sg:city":"Omaha",
    "sg:classifiers":[
        {
            "category":"Autos & Motor Vehicles",
            "subcategory":"Auto Supplies",
            "type":"Retail Goods"
        },
        {
            "category":"Retail",
            "subcategory":"Auto Repair",
            "type":"Services"
        }
    ],
    "sg:phone":"+1 402 334 3728",
    "sg:postcode":"68144",
    "sg:province":"NE",
    "sg:tags":[
        "oil",
        "tire",
        "automobile",
        "accessory",
        "lube",
        "part",
        "supplies-used",
        "brake",
        "rebuilt"
    ],
    "sg:website":"http://www.sears.com/shc/s/v_10153_12605_Automotive?adCell=AH",
    "wof:name":"Sears Auto Center",
    "wof:placetype":"venue"
},
  "geometry": {"coordinates":[-96.13612999999999,41.226957],"type":"Point"}
}