{
  "type": "Feature",
  "properties": {
    "iso:country":"US",
    "sg:address":"930 N 70th St",
    "sg:city":"Lincoln",
    "sg:classifiers":[
        {
            "category":"Building & Trades",
            "subcategory":"Construction",
            "type":"Services"
        }
    ],
    "sg:phone":"+1 402 489 6733",
    "sg:postcode":"68505",
    "sg:province":"NE",
    "sg:tags":[
        "restoration",
        "preservation"
    ],
    "wof:name":"Siemens Building Technologies",
    "wof:placetype":"venue"
},
  "geometry": {"coordinates":[-96.624916,40.82139],"type":"Point"}
}