{
  "type": "Feature",
  "properties": {
    "iso:country":"US",
    "sg:address":"7809 F St",
    "sg:city":"Omaha",
    "sg:classifiers":[
        {
            "category":"Government",
            "subcategory":"Office",
            "type":"Public Place"
        }
    ],
    "sg:phone":"+1 402 444 5782",
    "sg:postcode":"68127",
    "sg:province":"NE",
    "sg:tags":[
        "village"
    ],
    "wof:name":"Vehicle Impound Lot",
    "wof:placetype":"venue"
},
  "geometry": {"coordinates":[-96.033664,41.219655],"type":"Point"}
}