{
  "type": "Feature",
  "properties": {
    "addr:full":"4852 S 61st St Omaha NE 68117",
    "addr:housenumber":"4852",
    "addr:postcode":"68117",
    "addr:street":"S 61St St",
    "iso:country":"US",
    "sg:address":"4852 S 61st St",
    "sg:city":"Omaha",
    "sg:classifiers":[
        {
            "category":"Retail",
            "subcategory":"Auto Repair",
            "type":"Services"
        }
    ],
    "sg:phone":"+1 402 734 5515",
    "sg:postcode":"68117",
    "sg:province":"NE",
    "sg:tags":[
        "general"
    ],
    "wof:name":"Import Specialists",
    "wof:placetype":"venue"
},
  "geometry": {"coordinates":[-96.007119,41.210082],"type":"Point"}
}