{
  "type": "Feature",
  "properties": {
    "addr:full":"1110 Jackson St Beatrice NE 68310",
    "addr:housenumber":"1110",
    "addr:postcode":"68310",
    "addr:street":"Jackson St",
    "iso:country":"US",
    "sg:address":"1110 Jackson St",
    "sg:city":"Beatrice",
    "sg:classifiers":[
        {
            "category":"Health Services",
            "subcategory":"Doctor",
            "type":"Services"
        }
    ],
    "sg:phone":"+1 402 228 4236",
    "sg:postcode":"68310",
    "sg:province":"NE",
    "sg:tags":[
        "physician",
        "surgeon"
    ],
    "wof:name":"Southeast Nebraska Surgery",
    "wof:placetype":"venue"
},
  "geometry": {"coordinates":[-96.737273,40.277994],"type":"Point"}
}