{
  "type": "Feature",
  "properties": {
    "iso:country":"US",
    "sg:address":"3101 O St",
    "sg:city":"Lincoln",
    "sg:classifiers":[
        {
            "category":"Shopping",
            "subcategory":"Computers & Home Electronics",
            "type":"Retail Goods"
        }
    ],
    "sg:phone":"+1 402 435 8990",
    "sg:postcode":"68510",
    "sg:province":"NE",
    "sg:tags":[
        "recorder",
        "time"
    ],
    "sg:website":"www.nbesolutions.com",
    "wof:name":"Nebraska Business Electronics",
    "wof:placetype":"venue"
},
  "geometry": {"coordinates":[-96.67501799999999,40.813423],"type":"Point"}
}