{
  "type": "Feature",
  "properties": {
    "addr:full":"2748 S St Lincoln NE 68503",
    "addr:housenumber":"2748",
    "addr:postcode":"68503",
    "addr:street":"S St",
    "iso:country":"US",
    "sg:address":"2748 S St",
    "sg:city":"Lincoln",
    "sg:classifiers":[
        {
            "category":"Organizations",
            "subcategory":"Non-profit Organization",
            "type":"Services"
        }
    ],
    "sg:phone":"+1 402 438 5214",
    "sg:postcode":"68503",
    "sg:province":"NE",
    "sg:tags":[
        "social"
    ],
    "wof:name":"Aa",
    "wof:placetype":"venue"
},
  "geometry": {"coordinates":[-96.681455,40.8182],"type":"Point"}
}