{
  "type": "Feature",
  "properties": {
    "iso:country":"US",
    "sg:address":"265 N Maloney Dr",
    "sg:city":"North Platte",
    "sg:classifiers":[
        {
            "category":"Building & Trades",
            "subcategory":"Electrical",
            "type":"Services"
        }
    ],
    "sg:phone":"+1 308 534 8067",
    "sg:postcode":"69101",
    "sg:province":"NE",
    "sg:tags":[
        "electrical",
        "contractor"
    ],
    "wof:name":"Orlin Satalite Sales",
    "wof:placetype":"venue"
},
  "geometry": {"coordinates":[-100.79735700000001,41.040881],"type":"Point"}
}