{
  "type": "Feature",
  "properties": {
    "addr:full":"905 224th Milford NE 68405",
    "addr:housenumber":"905",
    "addr:postcode":"68405",
    "addr:street":"224Th",
    "iso:country":"US",
    "sg:address":"905 224th",
    "sg:city":"Milford",
    "sg:classifiers":[
        {
            "category":"Mining & Drilling",
            "type":"Manufacturing & Wholesale Goods"
        }
    ],
    "sg:phone":"+1 402 761 2933",
    "sg:postcode":"68405",
    "sg:province":"NE",
    "sg:tags":[
        "construction"
    ],
    "wof:name":"Ackerman Rock & Gravel Co",
    "wof:placetype":"venue"
},
  "geometry": {"coordinates":[-97.025532,40.814181],"type":"Point"}
}