{
  "type": "Feature",
  "properties": {
    "addr:full":"4929 N 104th St Omaha NE 68134",
    "addr:housenumber":"4929",
    "addr:postcode":"68134",
    "addr:street":"N 104Th St",
    "iso:country":"US",
    "sg:address":"4929 N 104th St",
    "sg:city":"Omaha",
    "sg:phone":"+1 402 496 4784",
    "sg:postcode":"68134",
    "sg:province":"NE",
    "sg:tags":[
        "farm",
        "field",
        "crop"
    ],
    "wof:name":"Sue Penner",
    "wof:placetype":"venue"
},
  "geometry": {"coordinates":[-96.076538,41.304917],"type":"Point"}
}