{
  "type": "Feature",
  "properties": {
    "iso:country":"US",
    "sg:address":"1505 S 108th St",
    "sg:city":"Omaha",
    "sg:classifiers":[
        {
            "category":"Professional",
            "subcategory":"Lawyer & Legal Services",
            "type":"Services"
        }
    ],
    "sg:phone":"+1 402 397 1050",
    "sg:postcode":"68144",
    "sg:province":"NE",
    "sg:tags":[
        "attorney"
    ],
    "wof:name":"Bruce G Mason Law Offices",
    "wof:placetype":"venue"
},
  "geometry": {"coordinates":[-96.081323,41.245065],"type":"Point"}
}