{
  "type": "Feature",
  "properties": {
    "addr:full":"2600 Mimick Dr Norfolk NE 68701",
    "addr:housenumber":"2600",
    "addr:postcode":"68701",
    "addr:street":"Mimick Dr",
    "iso:country":"US",
    "sg:address":"2600 Mimick Dr",
    "sg:city":"Norfolk",
    "sg:classifiers":[
        {
            "category":"Building & Trades",
            "subcategory":"Construction",
            "type":"Services"
        }
    ],
    "sg:phone":"+1 402 841 4007",
    "sg:postcode":"68701",
    "sg:province":"NE",
    "sg:tags":[
        "concrete",
        "contractor"
    ],
    "wof:name":"M & B Quality Concrete",
    "wof:placetype":"venue"
},
  "geometry": {"coordinates":[-97.446726,42.056326],"type":"Point"}
}