{
  "type": "Feature",
  "properties": {
    "iso:country":"US",
    "sg:address":"508 N Ash St",
    "sg:city":"Gordon",
    "sg:classifiers":[
        {
            "category":"Building & Trades",
            "subcategory":"Electrical",
            "type":"Services"
        }
    ],
    "sg:phone":"+1 308 282 0214",
    "sg:postcode":"69343",
    "sg:province":"NE",
    "sg:tags":[
        "electrical",
        "refrigeration",
        "contractor"
    ],
    "wof:name":"Evert Electric Inc",
    "wof:placetype":"venue"
},
  "geometry": {"coordinates":[-102.200518,42.809759],"type":"Point"}
}