{
  "type": "Feature",
  "properties": {
    "iso:country":"US",
    "sg:address":"3906 S 38 Rd",
    "sg:city":"Cortland",
    "sg:phone":"+1 402 798 7831",
    "sg:postcode":"68331",
    "sg:province":"NE",
    "sg:tags":[
        "farm",
        "grain",
        "cash",
        "soybean"
    ],
    "wof:name":"Don Walman",
    "wof:placetype":"venue"
},
  "geometry": {"coordinates":[-96.666618,40.482743],"type":"Point"}
}