{
  "type": "Feature",
  "properties": {
    "addr:full":"700 Johnson St Fullerton NE 68638",
    "addr:housenumber":"700",
    "addr:postcode":"68638",
    "addr:street":"Johnson St",
    "iso:country":"US",
    "sg:address":"700 Johnson St",
    "sg:city":"Fullerton",
    "sg:classifiers":[
        {
            "category":"Restaurant",
            "type":"Food & Drink"
        }
    ],
    "sg:phone":"+1 308 536 2678",
    "sg:postcode":"68638",
    "sg:province":"NE",
    "wof:name":"San Anna Pizza & Mexican",
    "wof:placetype":"venue"
},
  "geometry": {"coordinates":[-97.97677899999999,41.362505],"type":"Point"}
}