{
  "type": "Feature",
  "properties": {
    "addr:full":"135 S 16th St Ord NE 68862",
    "addr:housenumber":"135",
    "addr:postcode":"68862",
    "addr:street":"S 16Th St",
    "iso:country":"US",
    "sg:address":"135 S 16th St",
    "sg:city":"Ord",
    "sg:classifiers":[
        {
            "category":"Home & Garden",
            "subcategory":"Hardware",
            "type":"Retail Goods"
        }
    ],
    "sg:phone":"+1 308 728 3800",
    "sg:postcode":"68862",
    "sg:province":"NE",
    "wof:name":"Brown Hardware",
    "wof:placetype":"venue"
},
  "geometry": {"coordinates":[-98.92936400000001,41.602724],"type":"Point"}
}