{
  "type": "Feature",
  "properties": {
    "iso:country":"US",
    "sg:address":"1250 Aldrich Rd",
    "sg:city":"Lincoln",
    "sg:classifiers":[
        {
            "category":"Retail",
            "subcategory":"Portrait Studio",
            "type":"Services"
        }
    ],
    "sg:phone":"+1 402 488 0271",
    "sg:postcode":"68510",
    "sg:province":"NE",
    "sg:tags":[
        "photographer",
        "photo"
    ],
    "wof:name":"J R Wurtz Photography Inc",
    "wof:placetype":"venue"
},
  "geometry": {"coordinates":[-96.650065,40.799491],"type":"Point"}
}