{
  "type": "Feature",
  "properties": {
    "iso:country":"US",
    "sg:address":"1011 Mason St",
    "sg:city":"Omaha",
    "sg:classifiers":[
        {
            "category":"Wholesale",
            "subcategory":"Hardware",
            "type":"Manufacturing & Wholesale Goods"
        }
    ],
    "sg:phone":"+1 402 342 0778",
    "sg:postcode":"68108",
    "sg:province":"NE",
    "sg:tags":[
        "plumbing",
        "fixture",
        "supply"
    ],
    "wof:name":"Briggs Inc",
    "wof:placetype":"venue"
},
  "geometry": {"coordinates":[-95.930441,41.250113],"type":"Point"}
}