{
  "type": "Feature",
  "properties": {
    "iso:country":"US",
    "sg:address":"305 N 3rd St",
    "sg:city":"Plainview",
    "sg:classifiers":[
        {
            "category":"Travel",
            "subcategory":"Hotels & Motels",
            "type":"Entertainment"
        }
    ],
    "sg:phone":"+1 402 582 4708",
    "sg:postcode":"68769",
    "sg:province":"NE",
    "sg:tags":[
        "breakfast",
        "accommodation",
        "bed"
    ],
    "wof:name":"Rose Garden Inn",
    "wof:placetype":"venue"
},
  "geometry": {"coordinates":[-97.784966,42.354359],"type":"Point"}
}