{
  "type": "Feature",
  "properties": {
    "iso:country":"US",
    "sg:address":"224 W 17th St",
    "sg:city":"Falls City",
    "sg:classifiers":[
        {
            "category":"Building & Trades",
            "subcategory":"Construction",
            "type":"Services"
        }
    ],
    "sg:phone":"+1 402 245 5287",
    "sg:postcode":"68355",
    "sg:province":"NE",
    "sg:tags":[
        "downspouts",
        "gutter"
    ],
    "wof:name":"Haworth Seamless Gutters",
    "wof:placetype":"venue"
},
  "geometry": {"coordinates":[-95.604911,40.061792],"type":"Point"}
}