{
  "type": "Feature",
  "properties": {
    "iso:country":"US",
    "sg:address":"15225 Douglas Cir",
    "sg:city":"Omaha",
    "sg:phone":"+1 402 334 8603",
    "sg:postcode":"68154",
    "sg:province":"NE",
    "sg:tags":[
        "farm",
        "grain",
        "cash"
    ],
    "wof:name":"Wolsmann John",
    "wof:placetype":"venue"
},
  "geometry": {"coordinates":[-96.15197000000001,41.257756],"type":"Point"}
}