{
  "type": "Feature",
  "properties": {
    "addr:full":"12515 N St Omaha NE 68137",
    "addr:housenumber":"12515",
    "addr:postcode":"68137",
    "addr:street":"N St",
    "iso:country":"US",
    "sg:address":"12515 N St",
    "sg:city":"Omaha",
    "sg:classifiers":[
        {
            "category":"Professional",
            "type":"Services"
        }
    ],
    "sg:phone":"+1 402 895 6979",
    "sg:postcode":"68137",
    "sg:province":"NE",
    "sg:tags":[
        "establishment"
    ],
    "wof:name":"Bill Mar",
    "wof:placetype":"venue"
},
  "geometry": {"coordinates":[-96.10670500000001,41.209794],"type":"Point"}
}