{
  "type": "Feature",
  "properties": {
    "iso:country":"US",
    "sg:address":"222 Main St",
    "sg:city":"Wayne",
    "sg:classifiers":[
        {
            "category":"Shopping",
            "subcategory":"Computers & Home Electronics",
            "type":"Retail Goods"
        }
    ],
    "sg:phone":"+1 402 375 1353",
    "sg:postcode":"68787",
    "sg:province":"NE",
    "sg:tags":[
        "equipment",
        "satellite",
        "system"
    ],
    "wof:name":"Kaup's TV Svc",
    "wof:placetype":"venue"
},
  "geometry": {"coordinates":[-97.01778899999999,42.230274],"type":"Point"}
}