{
  "type": "Feature",
  "properties": {
    "addr:full":"820 Hershey St Gibbon NE 68840",
    "addr:housenumber":"820",
    "addr:postcode":"68840",
    "addr:street":"Hershey St",
    "iso:country":"US",
    "sg:address":"820 Hershey St",
    "sg:city":"Gibbon",
    "sg:classifiers":[
        {
            "category":"Building & Trades",
            "subcategory":"Electrical",
            "type":"Services"
        }
    ],
    "sg:phone":"+1 308 468 5834",
    "sg:postcode":"68840",
    "sg:province":"NE",
    "sg:tags":[
        "electric",
        "contractor"
    ],
    "wof:name":"Godfrey Electric",
    "wof:placetype":"venue"
},
  "geometry": {"coordinates":[-98.844813,40.753238],"type":"Point"}
}