{
  "type": "Feature",
  "properties": {
    "iso:country":"US",
    "sg:address":"11641 Spaulding St",
    "sg:city":"Omaha",
    "sg:classifiers":[
        {
            "category":"Building & Trades",
            "subcategory":"Construction",
            "type":"Services"
        }
    ],
    "sg:phone":"+1 402 493 8151",
    "sg:postcode":"68164",
    "sg:province":"NE",
    "sg:tags":[
        "nonresidential"
    ],
    "wof:name":"William Knox D B A Knox Cnstr",
    "wof:placetype":"venue"
},
  "geometry": {"coordinates":[-96.09092699999999,41.295478],"type":"Point"}
}