{
  "type": "Feature",
  "properties": {
    "iso:country":"US",
    "sg:address":"318 E Commercial St",
    "sg:city":"Brady",
    "sg:classifiers":[
        {
            "category":"Retail",
            "subcategory":"Repair Shop",
            "type":"Services"
        }
    ],
    "sg:phone":"+1 308 584 3552",
    "sg:postcode":"69123",
    "sg:province":"NE",
    "sg:tags":[
        "upholsterer"
    ],
    "wof:name":"Whipple's Fix-It Shoppe",
    "wof:placetype":"venue"
},
  "geometry": {"coordinates":[-100.364378,41.020919],"type":"Point"}
}