{
  "type": "Feature",
  "properties": {
    "addr:full":"204 S Luke St Ohiowa NE 68416",
    "addr:housenumber":"204",
    "addr:postcode":"68416",
    "addr:street":"S Luke St",
    "iso:country":"US",
    "sg:address":"204 S Luke St",
    "sg:city":"Ohiowa",
    "sg:classifiers":[
        {
            "category":"Building & Trades",
            "subcategory":"Construction",
            "type":"Services"
        }
    ],
    "sg:phone":"+1 402 295 2586",
    "sg:postcode":"68416",
    "sg:province":"NE",
    "sg:tags":[
        "excavating",
        "contractor"
    ],
    "wof:name":"Drake Construction",
    "wof:placetype":"venue"
},
  "geometry": {"coordinates":[-97.454599,40.411435],"type":"Point"}
}