{
  "type": "Feature",
  "properties": {
    "addr:full":"3200 N 20th St Lincoln NE 68521",
    "addr:housenumber":"3200",
    "addr:postcode":"68521",
    "addr:street":"N 20Th St",
    "iso:country":"US",
    "sg:address":"3200 N 20th St",
    "sg:city":"Lincoln",
    "sg:classifiers":[
        {
            "category":"Building & Trades",
            "subcategory":"Construction",
            "type":"Services"
        }
    ],
    "sg:phone":"+1 402 466 4003",
    "sg:postcode":"68521",
    "sg:province":"NE",
    "sg:tags":[
        "handyman"
    ],
    "wof:name":"All Trade Solutions",
    "wof:placetype":"venue"
},
  "geometry": {"coordinates":[-96.691547,40.845254],"type":"Point"}
}