{
  "type": "Feature",
  "properties": {
    "addr:full":"318 8th St Gothenburg NE 69138",
    "addr:housenumber":"318",
    "addr:postcode":"69138",
    "addr:street":"8Th St",
    "iso:country":"US",
    "sg:address":"318 8th St",
    "sg:city":"Gothenburg",
    "sg:classifiers":[
        {
            "category":"Food & Beverages",
            "subcategory":"Liquor & Beverages",
            "type":"Retail Goods"
        }
    ],
    "sg:phone":"+1 308 537 7220",
    "sg:postcode":"69138",
    "sg:province":"NE",
    "sg:tags":[
        "alcoholic"
    ],
    "wof:name":"O & K Bottle Shop",
    "wof:placetype":"venue"
},
  "geometry": {"coordinates":[-100.164878,40.927867],"type":"Point"}
}