{
  "type": "Feature",
  "properties": {
    "iso:country":"US",
    "sg:address":"101 S Aberley Ave",
    "sg:city":"Hartington",
    "sg:classifiers":[
        {
            "category":"Social Services",
            "subcategory":"Child Care",
            "type":"Services"
        }
    ],
    "sg:phone":"+1 402 254 6378",
    "sg:postcode":"68739",
    "sg:province":"NE",
    "sg:tags":[
        "kindergarten",
        "academic",
        "school",
        "day"
    ],
    "wof:name":"Tiny Tots Pre-School",
    "wof:placetype":"venue"
},
  "geometry": {"coordinates":[-97.25783199999999,42.620518],"type":"Point"}
}