{
  "type": "Feature",
  "properties": {
    "addr:full":"4677 L St Omaha NE 68117",
    "addr:housenumber":"4677",
    "addr:postcode":"68117",
    "addr:street":"L St",
    "iso:country":"US",
    "sg:address":"4677 L St",
    "sg:city":"Omaha",
    "sg:classifiers":[
        {
            "category":"Autos & Motor Vehicles",
            "subcategory":"Automobile Sales",
            "type":"Retail Goods"
        }
    ],
    "sg:phone":"+1 402 502 2806",
    "sg:postcode":"68117",
    "sg:province":"NE",
    "sg:tags":[
        "car",
        "dealer"
    ],
    "wof:name":"Prime Auto Sales Inc",
    "wof:placetype":"venue"
},
  "geometry": {"coordinates":[-95.98487799999999,41.212478],"type":"Point"}
}