{
  "type": "Feature",
  "properties": {
    "addr:full":"165 N Rd Hallam NE 68344",
    "addr:housenumber":"165",
    "addr:postcode":"68344",
    "addr:street":"N Rd",
    "iso:country":"US",
    "sg:address":"165 N Rd",
    "sg:city":"Hallam",
    "sg:classifiers":[
        {
            "category":"Building & Trades",
            "subcategory":"Electrical",
            "type":"Services"
        }
    ],
    "sg:phone":"+1 402 432 5618",
    "sg:postcode":"68344",
    "sg:province":"NE",
    "sg:tags":[
        "electric",
        "contractor"
    ],
    "wof:name":"J W Electric",
    "wof:placetype":"venue"
},
  "geometry": {"coordinates":[-96.45178799999999,40.59188],"type":"Point"}
}