{
  "type": "Feature",
  "properties": {
    "addr:full":"5905 S 136th St Omaha NE 68137",
    "addr:housenumber":"5905",
    "addr:postcode":"68137",
    "addr:street":"S 136Th St",
    "iso:country":"US",
    "sg:address":"5905 S 136th St",
    "sg:city":"Omaha",
    "sg:classifiers":[
        {
            "category":"Home & Garden",
            "subcategory":"Building Materials",
            "type":"Retail Goods"
        }
    ],
    "sg:phone":"+1 402 895 7236",
    "sg:postcode":"68137",
    "sg:province":"NE",
    "sg:tags":[
        "glass",
        "leaded"
    ],
    "wof:name":"Richman Stained Glass",
    "wof:placetype":"venue"
},
  "geometry": {"coordinates":[-96.127743,41.198808],"type":"Point"}
}