{
  "type": "Feature",
  "properties": {
    "iso:country":"US",
    "sg:address":"301 N C St",
    "sg:city":"Edgar",
    "sg:classifiers":[
        {
            "category":"Shopping",
            "type":"Retail Goods"
        }
    ],
    "sg:phone":"+1 402 224 3211",
    "sg:postcode":"68935",
    "sg:province":"NE",
    "sg:tags":[
        "candle"
    ],
    "sg:website":"www.sugarshackcandles.com",
    "wof:name":"Sugar Shack Country Candles",
    "wof:placetype":"venue"
},
  "geometry": {"coordinates":[-97.970089,40.3713],"type":"Point"}
}