{
  "type": "Feature",
  "properties": {
    "iso:country":"US",
    "sg:address":"14211 Pacific St",
    "sg:city":"Omaha",
    "sg:classifiers":[
        {
            "category":"Insurance",
            "subcategory":"Insurance Agent",
            "type":"Services"
        }
    ],
    "sg:phone":"+1 402 493 5000",
    "sg:postcode":"68154",
    "sg:province":"NE",
    "wof:name":"American Family Insurance",
    "wof:placetype":"venue"
},
  "geometry": {"coordinates":[-96.135879,41.248507],"type":"Point"}
}