{
  "type": "Feature",
  "properties": {
    "addr:full":"105 E D St Wymore NE 68466",
    "addr:housenumber":"105",
    "addr:postcode":"68466",
    "addr:street":"E D St",
    "iso:country":"US",
    "sg:address":"105 E D St",
    "sg:city":"Wymore",
    "sg:classifiers":[
        {
            "category":"Health Services",
            "subcategory":"Nursing And Care Facility",
            "type":"Services"
        }
    ],
    "sg:phone":"+1 402 645 3354",
    "sg:postcode":"68466",
    "sg:province":"NE",
    "sg:tags":[
        "home",
        "convalescent"
    ],
    "wof:name":"Wymore Good Samaritan Center",
    "wof:placetype":"venue"
},
  "geometry": {"coordinates":[-96.661463,40.119162],"type":"Point"}
}