{
  "type": "Feature",
  "properties": {
    "iso:country":"US",
    "sg:address":"201 E 2nd St",
    "sg:city":"Ogallala",
    "sg:classifiers":[
        {
            "category":"Insurance",
            "subcategory":"Insurance Agent",
            "type":"Services"
        }
    ],
    "sg:phone":"+1 308 284 3755",
    "sg:postcode":"69153",
    "sg:province":"NE",
    "wof:name":"Pinnacle Agency",
    "wof:placetype":"venue"
},
  "geometry": {"coordinates":[-101.71688,41.125958],"type":"Point"}
}