{
  "type": "Feature",
  "properties": {
    "iso:country":"US",
    "sg:address":"419 Westridge Dr",
    "sg:city":"Ord",
    "sg:classifiers":[
        {
            "category":"Farming",
            "subcategory":"Livestock Farm",
            "type":"Manufacturing & Wholesale Goods"
        }
    ],
    "sg:phone":"+1 308 728 5832",
    "sg:postcode":"68862",
    "sg:province":"NE",
    "sg:tags":[
        "corn",
        "beef",
        "feedlot",
        "cattle"
    ],
    "wof:name":"Ed Kruml",
    "wof:placetype":"venue"
},
  "geometry": {"coordinates":[-98.939029,41.59988],"type":"Point"}
}