{
  "type": "Feature",
  "properties": {
    "iso:country":"US",
    "sg:address":"1106 Howard St",
    "sg:city":"Omaha",
    "sg:classifiers":[
        {
            "category":"Professional",
            "subcategory":"Lawyer & Legal Services",
            "type":"Services"
        }
    ],
    "sg:phone":"+1 402 978 7878",
    "sg:postcode":"68102",
    "sg:province":"NE",
    "sg:tags":[
        "attorney"
    ],
    "wof:name":"Boyle & Assoc",
    "wof:placetype":"venue"
},
  "geometry": {"coordinates":[-95.931837,41.255539],"type":"Point"}
}