{
  "type": "Feature",
  "properties": {
    "addr:full":"1400 Logan St Norfolk NE 68701",
    "addr:housenumber":"1400",
    "addr:postcode":"68701",
    "addr:street":"Logan St",
    "iso:country":"US",
    "sg:address":"1400 Logan St",
    "sg:city":"Norfolk",
    "sg:classifiers":[
        {
            "category":"Building & Trades",
            "subcategory":"Electrical",
            "type":"Services"
        }
    ],
    "sg:phone":"+1 402 371 4756",
    "sg:postcode":"68701",
    "sg:province":"NE",
    "sg:tags":[
        "electric",
        "contractor"
    ],
    "wof:name":"Lee Electric",
    "wof:placetype":"venue"
},
  "geometry": {"coordinates":[-97.40291999999999,42.017026],"type":"Point"}
}