{
  "type": "Feature",
  "properties": {
    "addr:full":"1308 N Adams St Lexington NE 68850",
    "addr:housenumber":"1308",
    "addr:postcode":"68850",
    "addr:street":"N Adams St",
    "iso:country":"US",
    "sg:address":"1308 N Adams St",
    "sg:city":"Lexington",
    "sg:classifiers":[
        {
            "category":"Organizations",
            "subcategory":"Non-profit Organization",
            "type":"Services"
        }
    ],
    "sg:phone":"+1 308 324 4266",
    "sg:postcode":"68850",
    "sg:province":"NE",
    "sg:tags":[
        "human"
    ],
    "wof:name":"NAF Multicultural Human Dev",
    "wof:placetype":"venue"
},
  "geometry": {"coordinates":[-99.748769,40.788465],"type":"Point"}
}