{
  "type": "Feature",
  "properties": {
    "iso:country":"US",
    "sg:address":"810 E B St",
    "sg:city":"Mc Cook",
    "sg:classifiers":[
        {
            "category":"Restaurant",
            "type":"Food & Drink"
        },
        {
            "category":"Food & Beverages",
            "subcategory":"Groceries & Convenience Stores",
            "type":"Retail Goods"
        }
    ],
    "sg:menulink":"http://www.allmenus.com/ne/mccook/225173-caseys-general-store/menu/",
    "sg:phone":"+1 308 345 6425",
    "sg:postcode":"69001",
    "sg:province":"NE",
    "sg:tags":[
        "american",
        "pizza"
    ],
    "wof:name":"Casey's General Store",
    "wof:placetype":"venue"
},
  "geometry": {"coordinates":[-100.616012,40.198372],"type":"Point"}
}