{
  "type": "Feature",
  "properties": {
    "addr:full":"14333 US Hwy 30 Gretna NE 68008",
    "addr:housenumber":"14333",
    "addr:postcode":"68008",
    "addr:street":"Us Hwy 30;Ne",
    "iso:country":"US",
    "sg:address":"14333 US Hwy 30",
    "sg:city":"Gretna",
    "sg:classifiers":[
        {
            "category":"Shopping",
            "subcategory":"Shoes",
            "type":"Retail Goods"
        }
    ],
    "sg:phone":"+1 402 332 4255",
    "sg:postcode":"68008",
    "sg:province":"NE",
    "wof:name":"Nine West",
    "wof:placetype":"venue"
},
  "geometry": {"coordinates":[-96.180555,41.483403],"type":"Point"}
}