{
  "type": "Feature",
  "properties": {
    "iso:country":"US",
    "sg:address":"908 N Howard Ave",
    "sg:city":"Grand Island",
    "sg:classifiers":[
        {
            "category":"Health Services",
            "subcategory":"Doctor",
            "type":"Services"
        }
    ],
    "sg:phone":"+1 308 381 0167",
    "sg:postcode":"68803",
    "sg:province":"NE",
    "wof:name":"Lofgreen David V DDS",
    "wof:placetype":"venue"
},
  "geometry": {"coordinates":[-98.369837,40.927723],"type":"Point"}
}