{
  "type": "Feature",
  "properties": {
    "iso:country":"US",
    "sg:address":"4428 S 140th St",
    "sg:city":"Omaha",
    "sg:classifiers":[
        {
            "category":"Banks & Credit Unions",
            "subcategory":"Bank",
            "type":"Services"
        }
    ],
    "sg:phone":"+1 402 895 2977",
    "sg:postcode":"68137",
    "sg:province":"NE",
    "wof:name":"First National Bank",
    "wof:placetype":"venue"
},
  "geometry": {"coordinates":[-96.13372099999999,41.215292],"type":"Point"}
}