{
  "type": "Feature",
  "properties": {
    "iso:country":"US",
    "sg:address":"328 W Prairie St",
    "sg:city":"Albion",
    "sg:classifiers":[
        {
            "category":"Real Estate",
            "subcategory":"Developer",
            "type":"Services"
        }
    ],
    "sg:phone":"+1 402 395 2884",
    "sg:postcode":"68620",
    "sg:province":"NE",
    "sg:tags":[
        "cemetery"
    ],
    "wof:name":"Rose Hill Cemetary",
    "wof:placetype":"venue"
},
  "geometry": {"coordinates":[-98.000052,41.688899],"type":"Point"}
}