{
  "type": "Feature",
  "properties": {
    "addr:full":"1315 Ave A Gothenburg NE 69138",
    "addr:postcode":"69138",
    "addr:street":"1315 Ave A",
    "iso:country":"US",
    "sg:address":"1315 Ave A",
    "sg:city":"Gothenburg",
    "sg:classifiers":[
        {
            "category":"Freight",
            "type":"Transportation"
        }
    ],
    "sg:phone":"+1 308 537 3137",
    "sg:postcode":"69138",
    "sg:province":"NE",
    "sg:tags":[
        "operator",
        "local",
        "trucking"
    ],
    "wof:name":"Ron Crisman Trucking Inc",
    "wof:placetype":"venue"
},
  "geometry": {"coordinates":[-100.165627,40.931894],"type":"Point"}
}