{
  "type": "Feature",
  "properties": {
    "iso:country":"US",
    "sg:address":"114 US Hwy 20",
    "sg:city":"Gordon",
    "sg:classifiers":[
        {
            "category":"Shopping",
            "subcategory":"Used Merchandise",
            "type":"Retail Goods"
        }
    ],
    "sg:phone":"+1 308 282 9988",
    "sg:postcode":"69343",
    "sg:province":"NE",
    "sg:tags":[
        "second",
        "store",
        "hand"
    ],
    "wof:name":"Trading Post",
    "wof:placetype":"venue"
},
  "geometry": {"coordinates":[-102.205428,42.799853],"type":"Point"}
}