{
  "type": "Feature",
  "properties": {
    "iso:country":"US",
    "sg:address":"1245 E 2nd St",
    "sg:city":"Fremont",
    "sg:phone":"+1 402 721 7166",
    "sg:postcode":"68025",
    "sg:province":"NE",
    "sg:tags":[
        "farm",
        "corn"
    ],
    "wof:name":"Person Chersty",
    "wof:placetype":"venue"
},
  "geometry": {"coordinates":[-96.48283000000001,41.430447],"type":"Point"}
}