{
  "type": "Feature",
  "properties": {
    "addr:full":"15650 Grant Cir Omaha NE 68116",
    "addr:housenumber":"15650",
    "addr:postcode":"68116",
    "addr:street":"Grant Cir",
    "iso:country":"US",
    "sg:address":"15650 Grant Cir",
    "sg:city":"Omaha",
    "sg:classifiers":[
        {
            "category":"Building & Trades",
            "subcategory":"Construction",
            "type":"Services"
        }
    ],
    "sg:phone":"+1 402 551 4272",
    "sg:postcode":"68116",
    "sg:province":"NE",
    "sg:tags":[
        "house"
    ],
    "wof:name":"Luke Custom Homes LLC",
    "wof:placetype":"venue"
},
  "geometry": {"coordinates":[-96.16140900000001,41.280339],"type":"Point"}
}