{
  "type": "Feature",
  "properties": {
    "addr:full":"5019 Calvert St Lincoln NE 68506",
    "addr:housenumber":"5019",
    "addr:postcode":"68506",
    "addr:street":"Calvert St",
    "iso:country":"US",
    "sg:address":"5019 Calvert St",
    "sg:city":"Lincoln",
    "sg:classifiers":[
        {
            "category":"Building & Trades",
            "subcategory":"Landscaping Services",
            "type":"Services"
        }
    ],
    "sg:phone":"+1 402 432 0515",
    "sg:postcode":"68506",
    "sg:province":"NE",
    "wof:name":"Hornby Lawn Mowing",
    "wof:placetype":"venue"
},
  "geometry": {"coordinates":[-96.65064599999999,40.776951],"type":"Point"}
}