{
  "type": "Feature",
  "properties": {
    "addr:full":"1707 Frontage Rd Nebraska City NE 68410",
    "addr:housenumber":"1707",
    "addr:postcode":"68410",
    "addr:street":"Frontage Rd",
    "iso:country":"US",
    "sg:address":"1707 Frontage Rd",
    "sg:city":"Nebraska City",
    "sg:classifiers":[
        {
            "category":"Wholesale",
            "subcategory":"Farm Supplies",
            "type":"Manufacturing & Wholesale Goods"
        }
    ],
    "sg:phone":"+1 402 873 3706",
    "sg:postcode":"68410",
    "sg:province":"NE",
    "wof:name":"Orscheln Farm & Home",
    "wof:placetype":"venue"
},
  "geometry": {"coordinates":[-95.865239,40.686552],"type":"Point"}
}