{
  "type": "Feature",
  "properties": {
    "iso:country":"US",
    "sg:address":"1708 Broadway",
    "sg:city":"Scottsbluff",
    "sg:classifiers":[
        {
            "category":"Shopping",
            "subcategory":"Gifts & Souvenirs",
            "type":"Retail Goods"
        }
    ],
    "sg:phone":"+1 308 632 7458",
    "sg:postcode":"69361",
    "sg:province":"NE",
    "sg:tags":[
        "shop"
    ],
    "wof:name":"Nail Factory & Gift Shop",
    "wof:placetype":"venue"
},
  "geometry": {"coordinates":[-103.662824,41.864175],"type":"Point"}
}