{
  "type": "Feature",
  "properties": {
    "iso:country":"US",
    "sg:address":"10235 Wiesman Dr",
    "sg:city":"Omaha",
    "sg:classifiers":[
        {
            "category":"Education",
            "subcategory":"Dance Studio",
            "type":"Public Place"
        }
    ],
    "sg:phone":"+1 402 493 3177",
    "sg:postcode":"68134",
    "sg:province":"NE",
    "sg:tags":[
        "instruction",
        "dancing"
    ],
    "wof:name":"Dance Inspiration",
    "wof:placetype":"venue"
},
  "geometry": {"coordinates":[-96.07380499999999,41.310971],"type":"Point"}
}