{
  "type": "Feature",
  "properties": {
    "addr:full":"3309 A St Lincoln NE 68510",
    "addr:housenumber":"3309",
    "addr:postcode":"68510",
    "addr:street":"A St",
    "iso:country":"US",
    "sg:address":"3309 A St",
    "sg:city":"Lincoln",
    "sg:classifiers":[
        {
            "category":"Retail",
            "subcategory":"Laundry & Dry Cleaning",
            "type":"Services"
        }
    ],
    "sg:phone":"+1 402 474 5145",
    "sg:postcode":"68510",
    "sg:province":"NE",
    "sg:tags":[
        "cleaners",
        "plant",
        "drycleaning"
    ],
    "wof:name":"Nelson Cleaners Inc",
    "wof:placetype":"venue"
},
  "geometry": {"coordinates":[-96.670517,40.798866],"type":"Point"}
}