{
  "type": "Feature",
  "properties": {
    "iso:country":"US",
    "sg:address":"103 N 4th St",
    "sg:city":"Norfolk",
    "sg:classifiers":[
        {
            "category":"Retail",
            "subcategory":"Portrait Studio",
            "type":"Services"
        }
    ],
    "sg:phone":"+1 402 371 3878",
    "sg:postcode":"68701",
    "sg:province":"NE",
    "sg:tags":[
        "photographer"
    ],
    "wof:name":"Images Portrait Studio",
    "wof:placetype":"venue"
},
  "geometry": {"coordinates":[-97.411878,42.033359],"type":"Point"}
}