{
  "type": "Feature",
  "properties": {
    "iso:country":"US",
    "sg:address":"1803 Market St",
    "sg:city":"Beatrice",
    "sg:classifiers":[
        {
            "category":"Utilities",
            "type":"Services"
        }
    ],
    "sg:phone":"+1 402 223 2505",
    "sg:postcode":"68310",
    "sg:province":"NE",
    "sg:tags":[
        "sanitary",
        "c",
        "mach"
    ],
    "wof:name":"R T C Landscaping",
    "wof:placetype":"venue"
},
  "geometry": {"coordinates":[-96.729461,40.264676],"type":"Point"}
}