{
  "type": "Feature",
  "properties": {
    "addr:full":"4420 Dewey Ave Omaha NE 68105",
    "addr:housenumber":"4420",
    "addr:postcode":"68105",
    "addr:street":"Dewey Ave",
    "iso:country":"US",
    "sg:address":"4420 Dewey Ave",
    "sg:city":"Omaha",
    "sg:classifiers":[
        {
            "category":"Shopping",
            "type":"Retail Goods"
        }
    ],
    "sg:phone":"+1 402 559 5800",
    "sg:postcode":"68105",
    "sg:province":"NE",
    "sg:tags":[
        "orthopedic",
        "appliance"
    ],
    "wof:name":"Brace Place",
    "wof:placetype":"venue"
},
  "geometry": {"coordinates":[-95.98032600000001,41.256124],"type":"Point"}
}