{
  "type": "Feature",
  "properties": {
    "iso:country":"US",
    "sg:address":"2215 N Kansas Ave",
    "sg:city":"Hastings",
    "sg:classifiers":[
        {
            "category":"Health Services",
            "subcategory":"Doctor",
            "type":"Services"
        }
    ],
    "sg:phone":"+1 402 462 4380",
    "sg:postcode":"68901",
    "sg:province":"NE",
    "sg:tags":[
        "medical"
    ],
    "wof:name":"Medical Pk Dagnstc Ctr M L M H",
    "wof:placetype":"venue"
},
  "geometry": {"coordinates":[-98.386016,40.606946],"type":"Point"}
}