{
  "type": "Feature",
  "properties": {
    "addr:full":"7928 W Dodge Rd Omaha NE 68114",
    "addr:housenumber":"7928",
    "addr:postcode":"68114",
    "addr:street":"W Dodge Rd",
    "iso:country":"US",
    "sg:address":"7928 W Dodge Rd",
    "sg:city":"Omaha",
    "sg:classifiers":[
        {
            "category":"Shopping",
            "subcategory":"Bicycles & Sporting Goods",
            "type":"Retail Goods"
        }
    ],
    "sg:phone":"+1 402 393 3003",
    "sg:postcode":"68114",
    "sg:province":"NE",
    "sg:website":"www.playitagainsports.com",
    "wof:name":"Play It Again Sports",
    "wof:placetype":"venue"
},
  "geometry": {"coordinates":[-96.038783,41.260227],"type":"Point"}
}