{
  "type": "Feature",
  "properties": {
    "iso:country":"US",
    "sg:address":"20055 Hackberry Dr",
    "sg:city":"Gretna",
    "sg:classifiers":[
        {
            "category":"Cinema",
            "subcategory":"Movie Rental",
            "type":"Entertainment"
        }
    ],
    "sg:phone":"+1 402 332 3716",
    "sg:postcode":"68028",
    "sg:province":"NE",
    "sg:tags":[
        "leasing",
        "video",
        "disc",
        "tape"
    ],
    "wof:name":"Double D Video",
    "wof:placetype":"venue"
},
  "geometry": {"coordinates":[-96.22942999999999,41.14384],"type":"Point"}
}