{
  "type": "Feature",
  "properties": {
    "iso:country":"US",
    "sg:address":"1304 Co Rd II",
    "sg:city":"Dorchester",
    "sg:phone":"+1 402 946 4951",
    "sg:postcode":"68343",
    "sg:province":"NE",
    "sg:tags":[
        "farm",
        "corn"
    ],
    "wof:name":"Raymond Rezabek",
    "wof:placetype":"venue"
},
  "geometry": {"coordinates":[-97.140311,40.571283],"type":"Point"}
}