{
  "type": "Feature",
  "properties": {
    "iso:country":"US",
    "sg:address":"211 W 6th St",
    "sg:city":"South Sioux City",
    "sg:classifiers":[
        {
            "category":"Wholesale",
            "subcategory":"Durable Goods & Equipment",
            "type":"Manufacturing & Wholesale Goods"
        }
    ],
    "sg:phone":"+1 402 494 1858",
    "sg:postcode":"68776",
    "sg:province":"NE",
    "sg:tags":[
        "fire",
        "extinguisher"
    ],
    "wof:name":"M-Y Supply Inc",
    "wof:placetype":"venue"
},
  "geometry": {"coordinates":[-96.41546700000001,42.483799],"type":"Point"}
}