{
  "type": "Feature",
  "properties": {
    "iso:country":"US",
    "sg:address":"6909 Pratt St",
    "sg:city":"Omaha",
    "sg:classifiers":[
        {
            "category":"Professional",
            "subcategory":"Management & Consulting",
            "type":"Services"
        }
    ],
    "sg:phone":"+1 402 571 4397",
    "sg:postcode":"68104",
    "sg:province":"NE",
    "sg:tags":[
        "home",
        "organizing",
        "for"
    ],
    "wof:name":"Organizing Plus",
    "wof:placetype":"venue"
},
  "geometry": {"coordinates":[-96.021156,41.292244],"type":"Point"}
}