{
  "type": "Feature",
  "properties": {
    "iso:country":"US",
    "sg:address":"6 Lincoln Ave",
    "sg:city":"Chappell",
    "sg:classifiers":[
        {
            "category":"Retail",
            "subcategory":"Funeral Services",
            "type":"Services"
        }
    ],
    "sg:phone":"+1 308 874 2907",
    "sg:postcode":"69129",
    "sg:province":"NE",
    "wof:name":"Holechek Funeral Home Services",
    "wof:placetype":"venue"
},
  "geometry": {"coordinates":[-102.461179,41.091509],"type":"Point"}
}