{
  "type": "Feature",
  "properties": {
    "iso:country":"US",
    "sg:address":"4015 S 80th St",
    "sg:city":"Lincoln",
    "sg:classifiers":[
        {
            "category":"Bars & Pubs",
            "type":"Food & Drink"
        }
    ],
    "sg:phone":"+1 402 489 1303",
    "sg:postcode":"68506",
    "sg:province":"NE",
    "sg:tags":[
        "drinking"
    ],
    "wof:name":"Game Day Bar & Grill",
    "wof:placetype":"venue"
},
  "geometry": {"coordinates":[-96.61134,40.772642],"type":"Point"}
}