{
  "type": "Feature",
  "properties": {
    "addr:full":"17637 Jones St Omaha NE 68118",
    "addr:housenumber":"17637",
    "addr:postcode":"68118",
    "addr:street":"Jones St",
    "iso:country":"US",
    "sg:address":"17637 Jones St",
    "sg:city":"Omaha",
    "sg:classifiers":[
        {
            "category":"Manufacturing",
            "subcategory":"Paper Products",
            "type":"Manufacturing & Wholesale Goods"
        }
    ],
    "sg:phone":"+1 402 334 3420",
    "sg:postcode":"68118",
    "sg:province":"NE",
    "sg:tags":[
        "mill",
        "printing",
        "commercial"
    ],
    "wof:name":"A Note For You",
    "wof:placetype":"venue"
},
  "geometry": {"coordinates":[-96.188607,41.251157],"type":"Point"}
}