{
  "type": "Feature",
  "properties": {
    "iso:country":"US",
    "sg:address":"110 Thomas Lake",
    "sg:city":"Ashland",
    "sg:classifiers":[
        {
            "category":"Organizations",
            "subcategory":"Community Association",
            "type":"Services"
        }
    ],
    "sg:phone":"+1 402 944 6057",
    "sg:postcode":"68003",
    "sg:province":"NE",
    "wof:name":"Nebraska Gamma Chapter of",
    "wof:placetype":"venue"
},
  "geometry": {"coordinates":[-96.34001600000001,41.10049],"type":"Point"}
}