{
  "type": "Feature",
  "properties": {
    "iso:country":"US",
    "sg:address":"313 E 6th St",
    "sg:city":"Curtis",
    "sg:classifiers":[
        {
            "category":"Organizations",
            "subcategory":"Religious Organization",
            "type":"Services"
        }
    ],
    "sg:phone":"+1 308 367 4280",
    "sg:postcode":"69025",
    "sg:province":"NE",
    "sg:tags":[
        "church"
    ],
    "wof:name":"St James Catholic Church",
    "wof:placetype":"venue"
},
  "geometry": {"coordinates":[-100.51208,40.633839],"type":"Point"}
}