{
  "type": "Feature",
  "properties": {
    "addr:full":"8816 286th St Murdock NE 68407",
    "addr:housenumber":"8816",
    "addr:postcode":"68407",
    "addr:street":"286Th St",
    "iso:country":"US",
    "sg:address":"8816 286th St",
    "sg:city":"Murdock",
    "sg:classifiers":[
        {
            "category":"Sports & Exercise",
            "subcategory":"Gym",
            "type":"Entertainment"
        }
    ],
    "sg:phone":"+1 402 867 2041",
    "sg:postcode":"68407",
    "sg:province":"NE",
    "sg:tags":[
        "fitness",
        "physical",
        "facility"
    ],
    "wof:name":"Sports Courts of Lincoln",
    "wof:placetype":"venue"
},
  "geometry": {"coordinates":[-96.312628,40.926611],"type":"Point"}
}