{
  "type": "Feature",
  "properties": {
    "addr:full":"310 Co Rd 420 Friend NE 68359",
    "addr:housenumber":"310;420",
    "addr:postcode":"68359",
    "addr:street":"Co Rd",
    "iso:country":"US",
    "sg:address":"310 Co Rd 420",
    "sg:city":"Friend",
    "sg:phone":"+1 402 532 5575",
    "sg:postcode":"68359",
    "sg:province":"NE",
    "sg:tags":[
        "farm",
        "corn",
        "grain",
        "cash",
        "soybean"
    ],
    "wof:name":"Norman Cross",
    "wof:placetype":"venue"
},
  "geometry": {"coordinates":[-97.29198599999999,40.735383],"type":"Point"}
}