{
  "type": "Feature",
  "properties": {
    "iso:country":"US",
    "sg:address":"8532 College Park Rd",
    "sg:city":"Lincoln",
    "sg:classifiers":[
        {
            "category":"Professional",
            "subcategory":"Art Services",
            "type":"Services"
        }
    ],
    "sg:phone":"+1 402 540 1077",
    "sg:postcode":"68505",
    "sg:province":"NE",
    "sg:tags":[
        "graphic",
        "designer"
    ],
    "sg:website":"www.aijalon.net",
    "wof:name":"AIJALON.NET",
    "wof:placetype":"venue"
},
  "geometry": {"coordinates":[-96.60500399999999,40.814995],"type":"Point"}
}