{
  "type": "Feature",
  "properties": {
    "iso:country":"US",
    "sg:address":"411 James St",
    "sg:city":"Homer",
    "sg:classifiers":[
        {
            "category":"Organizations",
            "subcategory":"Religious Organization",
            "type":"Services"
        }
    ],
    "sg:phone":"+1 402 698 2321",
    "sg:postcode":"68030",
    "sg:province":"NE",
    "sg:tags":[
        "church"
    ],
    "wof:name":"St Paul's Lutheran Church",
    "wof:placetype":"venue"
},
  "geometry": {"coordinates":[-96.49512799999999,42.320515],"type":"Point"}
}