{
  "type": "Feature",
  "properties": {
    "addr:full":"2400 Central Ave Nebraska City NE 68410",
    "addr:housenumber":"2400",
    "addr:postcode":"68410",
    "addr:street":"Central Ave",
    "iso:country":"US",
    "sg:address":"2400 Central Ave",
    "sg:city":"Nebraska City",
    "sg:classifiers":[
        {
            "category":"Organizations",
            "subcategory":"Religious Organization",
            "type":"Services"
        }
    ],
    "sg:phone":"+1 402 873 6218",
    "sg:postcode":"68410",
    "sg:province":"NE",
    "wof:name":"Bethel United Church Of Christ",
    "wof:placetype":"venue"
},
  "geometry": {"coordinates":[-95.873525,40.676907],"type":"Point"}
}