{
  "type": "Feature",
  "properties": {
    "addr:full":"401 E M St Mc Cool Junction NE 68401",
    "addr:housenumber":"401",
    "addr:postcode":"68401",
    "addr:street":"E M St",
    "iso:country":"US",
    "sg:address":"401 E M St",
    "sg:city":"Mc Cool Junction",
    "sg:classifiers":[
        {
            "category":"Banks & Credit Unions",
            "subcategory":"Bank",
            "type":"Services"
        }
    ],
    "sg:phone":"+1 402 724 2121",
    "sg:postcode":"68401",
    "sg:province":"NE",
    "wof:name":"Cornerstone Bank",
    "wof:placetype":"venue"
},
  "geometry": {"coordinates":[-97.59362299999999,40.744136],"type":"Point"}
}