{
  "type": "Feature",
  "properties": {
    "iso:country":"US",
    "sg:address":"233 S 23rd St",
    "sg:city":"Lincoln",
    "sg:classifiers":[
        {
            "category":"Recreation",
            "type":"Entertainment"
        }
    ],
    "sg:phone":"+1 402 441 7892",
    "sg:postcode":"68510",
    "sg:province":"NE",
    "sg:tags":[
        "parks"
    ],
    "wof:name":"Lincoln Parks & Recreation",
    "wof:placetype":"venue"
},
  "geometry": {"coordinates":[-96.68834200000001,40.81208],"type":"Point"}
}