{
  "type": "Feature",
  "properties": {
    "addr:full":"3110 S 7th St Lincoln NE 68502",
    "addr:housenumber":"3110",
    "addr:postcode":"68502",
    "addr:street":"S 7Th St",
    "iso:country":"US",
    "sg:address":"3110 S 7th St",
    "sg:city":"Lincoln",
    "sg:classifiers":[
        {
            "category":"Building & Trades",
            "subcategory":"Plumbing",
            "type":"Services"
        }
    ],
    "sg:phone":"+1 402 421 9644",
    "sg:postcode":"68502",
    "sg:province":"NE",
    "sg:tags":[
        "mechanical",
        "contractor"
    ],
    "wof:name":"Ryan & Associates Inc",
    "wof:placetype":"venue"
},
  "geometry": {"coordinates":[-96.71146899999999,40.790093],"type":"Point"}
}