{
  "type": "Feature",
  "properties": {
    "iso:country":"US",
    "sg:address":"502 S 11th St",
    "sg:city":"Omaha",
    "sg:classifiers":[
        {
            "category":"Restaurant",
            "type":"Food & Drink"
        }
    ],
    "sg:menulink":"http://www.allmenus.com/ne/omaha/10994-spaghetti-works/menu/",
    "sg:phone":"+1 402 422 0770",
    "sg:postcode":"68102",
    "sg:province":"NE",
    "sg:tags":[
        "american"
    ],
    "wof:name":"Spaghetti Works",
    "wof:placetype":"venue"
},
  "geometry": {"coordinates":[-95.930573,41.255427],"type":"Point"}
}