{
  "type": "Feature",
  "properties": {
    "iso:country":"US",
    "sg:address":"3200 S 24th St",
    "sg:city":"Lincoln",
    "sg:classifiers":[
        {
            "category":"Recreation",
            "type":"Entertainment"
        }
    ],
    "sg:phone":"+1 402 423 8502",
    "sg:postcode":"68502",
    "sg:province":"NE",
    "sg:tags":[
        "club",
        "membership",
        "sport",
        "eating",
        "drinking"
    ],
    "wof:name":"Country Club Of Lincoln",
    "wof:placetype":"venue"
},
  "geometry": {"coordinates":[-96.68723199999999,40.781215],"type":"Point"}
}