{
  "type": "Feature",
  "properties": {
    "addr:full":"3770 18th St Columbus NE 68601",
    "addr:housenumber":"3770",
    "addr:postcode":"68601",
    "addr:street":"18Th St",
    "iso:country":"US",
    "sg:address":"3770 18th St",
    "sg:city":"Columbus",
    "sg:classifiers":[
        {
            "category":"Organizations",
            "subcategory":"Religious Organization",
            "type":"Services"
        }
    ],
    "sg:phone":"+1 402 563 4223",
    "sg:postcode":"68601",
    "sg:province":"NE",
    "sg:tags":[
        "church"
    ],
    "wof:name":"North Park Baptist Church",
    "wof:placetype":"venue"
},
  "geometry": {"coordinates":[-97.37355599999999,41.434159],"type":"Point"}
}