{
  "type": "Feature",
  "properties": {
    "iso:country":"US",
    "sg:address":"610 W 23rd St",
    "sg:city":"Yankton",
    "sg:classifiers":[
        {
            "category":"Government",
            "subcategory":"Office",
            "type":"Public Place"
        }
    ],
    "sg:phone":"+1 605 665 2662",
    "sg:postcode":"57078",
    "sg:province":"NE",
    "sg:tags":[
        "federal"
    ],
    "wof:name":"US Consolidated Farm Svc Agcy",
    "wof:placetype":"venue"
},
  "geometry": {"coordinates":[-97.399624,42.894385],"type":"Point"}
}