{
  "type": "Feature",
  "properties": {
    "iso:country":"US",
    "sg:address":"203 N Burr St",
    "sg:city":"Wilcox",
    "sg:classifiers":[
        {
            "category":"Wholesale",
            "subcategory":"Farm Supplies",
            "type":"Manufacturing & Wholesale Goods"
        }
    ],
    "sg:phone":"+1 308 478 5231",
    "sg:postcode":"68982",
    "sg:province":"NE",
    "sg:tags":[
        "fertilizer"
    ],
    "wof:name":"Midland Co-Op Assn",
    "wof:placetype":"venue"
},
  "geometry": {"coordinates":[-99.16848899999999,40.366973],"type":"Point"}
}