{
  "type": "Feature",
  "properties": {
    "addr:full":"10730 Pacific St Omaha NE 68114",
    "addr:housenumber":"10730",
    "addr:postcode":"68114",
    "addr:street":"Pacific St",
    "iso:country":"US",
    "sg:address":"10730 Pacific St",
    "sg:city":"Omaha",
    "sg:classifiers":[
        {
            "category":"Banks & Credit Unions",
            "subcategory":"Investment Brokerage",
            "type":"Services"
        }
    ],
    "sg:phone":"+1 402 391 0134",
    "sg:postcode":"68114",
    "sg:province":"NE",
    "sg:tags":[
        "advisory",
        "financial"
    ],
    "wof:name":"Strategic Financial",
    "wof:placetype":"venue"
},
  "geometry": {"coordinates":[-96.081284,41.248805],"type":"Point"}
}