{
  "type": "Feature",
  "properties": {
    "iso:country":"US",
    "sg:address":"1839 23rd St",
    "sg:city":"Columbus",
    "sg:classifiers":[
        {
            "category":"Wholesale",
            "subcategory":"Office Equipment",
            "type":"Manufacturing & Wholesale Goods"
        }
    ],
    "sg:phone":"+1 402 564 4200",
    "sg:postcode":"68601",
    "sg:province":"NE",
    "sg:tags":[
        "machine",
        "duplicating",
        "copying"
    ],
    "wof:name":"Office Systems Co",
    "wof:placetype":"venue"
},
  "geometry": {"coordinates":[-97.35117099999999,41.438443],"type":"Point"}
}