{
  "type": "Feature",
  "properties": {
    "addr:full":"715 J E George Blvd Omaha NE 68132",
    "addr:housenumber":"715",
    "addr:postcode":"68132",
    "addr:street":"J E George Blvd",
    "iso:country":"US",
    "sg:address":"715 J E George Blvd",
    "sg:city":"Omaha",
    "sg:classifiers":[
        {
            "category":"Communications",
            "subcategory":"Film & Video Production",
            "type":"Services"
        }
    ],
    "sg:phone":"+1 402 558 5762",
    "sg:postcode":"68132",
    "sg:province":"NE",
    "sg:tags":[
        "motion"
    ],
    "wof:name":"Prairie Dog Productions L",
    "wof:placetype":"venue"
},
  "geometry": {"coordinates":[-96.00180899999999,41.269669],"type":"Point"}
}