{
  "type": "Feature",
  "properties": {
    "iso:country":"US",
    "sg:address":"3534 S 48th St",
    "sg:city":"Lincoln",
    "sg:classifiers":[
        {
            "category":"Professional",
            "subcategory":"Engineering",
            "type":"Services"
        }
    ],
    "sg:phone":"+1 402 483 5466",
    "sg:postcode":"68506",
    "sg:province":"NE",
    "sg:tags":[
        "engineer"
    ],
    "sg:website":"www.speecelewis.com",
    "wof:name":"Speece & Lewis Engineers",
    "wof:placetype":"venue"
},
  "geometry": {"coordinates":[-96.65373599999999,40.777945],"type":"Point"}
}