{
  "type": "Feature",
  "properties": {
    "addr:full":"1505 Ave G Kearney NE 68847",
    "addr:housenumber":"1505",
    "addr:postcode":"68847",
    "addr:street":"Ave G",
    "iso:country":"US",
    "sg:address":"1505 Ave G",
    "sg:city":"Kearney",
    "sg:classifiers":[
        {
            "category":"Organizations",
            "subcategory":"Religious Organization",
            "type":"Services"
        }
    ],
    "sg:phone":"+1 308 236 6115",
    "sg:postcode":"68847",
    "sg:province":"NE",
    "wof:name":"St George Orthodox Church",
    "wof:placetype":"venue"
},
  "geometry": {"coordinates":[-99.072273,40.690116],"type":"Point"}
}