{
  "type": "Feature",
  "properties": {
    "iso:country":"US",
    "sg:address":"4111 4th Ave",
    "sg:city":"Kearney",
    "sg:classifiers":[
        {
            "category":"Banks & Credit Unions",
            "subcategory":"Investment Brokerage",
            "type":"Services"
        }
    ],
    "sg:phone":"+1 308 237 2525",
    "sg:postcode":"68845",
    "sg:province":"NE",
    "sg:tags":[
        "security"
    ],
    "sg:website":"www.securitiesamerica.org",
    "wof:name":"Securities America Inc",
    "wof:placetype":"venue"
},
  "geometry": {"coordinates":[-99.086692,40.715677],"type":"Point"}
}