{
  "type": "Feature",
  "properties": {
    "iso:country":"US",
    "sg:address":"2647 Winthrop Rd",
    "sg:city":"Lincoln",
    "sg:classifiers":[
        {
            "category":"Personal",
            "type":"Services"
        }
    ],
    "sg:phone":"+1 402 486 4307",
    "sg:postcode":"68502",
    "sg:province":"NE",
    "wof:name":"In Touch Massage Therapy",
    "wof:placetype":"venue"
},
  "geometry": {"coordinates":[-96.676059,40.78564],"type":"Point"}
}