{
  "type": "Feature",
  "properties": {
    "addr:full":"4138 McKelvie Rd Utica NE 68456",
    "addr:housenumber":"4138",
    "addr:postcode":"68456",
    "addr:street":"Mckelvie Rd",
    "iso:country":"US",
    "sg:address":"4138 McKelvie Rd",
    "sg:city":"Utica",
    "sg:phone":"+1 402 534 3518",
    "sg:postcode":"68456",
    "sg:province":"NE",
    "sg:tags":[
        "farm",
        "corn",
        "soybean"
    ],
    "wof:name":"Woolven Farm",
    "wof:placetype":"venue"
},
  "geometry": {"coordinates":[-97.284137,40.901801],"type":"Point"}
}