{
  "type": "Feature",
  "properties": {
    "addr:full":"2302 Frontage Rd Scottsbluff NE 69361",
    "addr:housenumber":"2302",
    "addr:postcode":"69361",
    "addr:street":"Frontage Rd",
    "iso:country":"US",
    "sg:address":"2302 Frontage Rd",
    "sg:city":"Scottsbluff",
    "sg:classifiers":[
        {
            "category":"Retail",
            "subcategory":"Repair Shop",
            "type":"Services"
        }
    ],
    "sg:phone":"+1 308 632 1526",
    "sg:postcode":"69361",
    "sg:province":"NE",
    "sg:tags":[
        "appliance"
    ],
    "wof:name":"TMS For Appliances",
    "wof:placetype":"venue"
},
  "geometry": {"coordinates":[-103.646445,41.869582],"type":"Point"}
}