{
  "type": "Feature",
  "properties": {
    "iso:country":"US",
    "sg:address":"1739 S 11th St",
    "sg:city":"Nebraska City",
    "sg:classifiers":[
        {
            "category":"Home & Garden",
            "subcategory":"Garden Supply",
            "type":"Retail Goods"
        }
    ],
    "sg:phone":"+1 402 873 6589",
    "sg:postcode":"68410",
    "sg:province":"NE",
    "sg:tags":[
        "merchandise"
    ],
    "wof:name":"Earl May Nursery & Garden Ctr",
    "wof:placetype":"venue"
},
  "geometry": {"coordinates":[-95.85910699999999,40.659975],"type":"Point"}
}