{
  "type": "Feature",
  "properties": {
    "iso:country":"US",
    "sg:address":"301 W 29th St",
    "sg:city":"South Sioux City",
    "sg:classifiers":[
        {
            "category":"Retail",
            "subcategory":"Veterinary Services",
            "type":"Services"
        }
    ],
    "sg:phone":"+1 402 494 3844",
    "sg:postcode":"68776",
    "sg:province":"NE",
    "sg:tags":[
        "veterinarian"
    ],
    "wof:name":"South Sioux Animal Hospital",
    "wof:placetype":"venue"
},
  "geometry": {"coordinates":[-96.41618800000001,42.462589],"type":"Point"}
}