{
  "type": "Feature",
  "properties": {
    "iso:country":"US",
    "sg:address":"109 Crestridge Dr",
    "sg:city":"Bellevue",
    "sg:classifiers":[
        {
            "category":"Building & Trades",
            "subcategory":"Plumbing",
            "type":"Services"
        }
    ],
    "sg:phone":"+1 402 991 4294",
    "sg:postcode":"68005",
    "sg:province":"NE",
    "sg:tags":[
        "plumbing",
        "contractor"
    ],
    "wof:name":"J C Frey Plumbing",
    "wof:placetype":"venue"
},
  "geometry": {"coordinates":[-95.91757,41.136316],"type":"Point"}
}