{
  "type": "Feature",
  "properties": {
    "iso:country":"US",
    "sg:address":"4111 1/2 D St",
    "sg:city":"Omaha",
    "sg:classifiers":[
        {
            "category":"Real Estate",
            "subcategory":"Real Estate Operator",
            "type":"Services"
        }
    ],
    "sg:phone":"+1 402 734 2555",
    "sg:postcode":"68107",
    "sg:province":"NE",
    "sg:tags":[
        "apartment"
    ],
    "wof:name":"Village Gate Apartments",
    "wof:placetype":"venue"
},
  "geometry": {"coordinates":[-95.974226,41.222054],"type":"Point"}
}