{
  "type": "Feature",
  "properties": {
    "iso:country":"US",
    "sg:address":"13911 Gold Cir",
    "sg:city":"Omaha",
    "sg:classifiers":[
        {
            "category":"Health Services",
            "subcategory":"Health Practitioner",
            "type":"Services"
        }
    ],
    "sg:phone":"+1 402 333 8464",
    "sg:postcode":"68144",
    "sg:province":"NE",
    "sg:tags":[
        "therapist",
        "physical"
    ],
    "wof:name":"Family Physical Therapy Svcs",
    "wof:placetype":"venue"
},
  "geometry": {"coordinates":[-96.13057000000001,41.234905],"type":"Point"}
}