{
  "type": "Feature",
  "properties": {
    "iso:country":"US",
    "sg:address":"1407 W 37th St",
    "sg:city":"Kearney",
    "sg:classifiers":[
        {
            "category":"Organizations",
            "subcategory":"Community Association",
            "type":"Services"
        }
    ],
    "sg:phone":"+1 308 237 3851",
    "sg:postcode":"68845",
    "sg:province":"NE",
    "wof:name":"Lions International Miller",
    "wof:placetype":"venue"
},
  "geometry": {"coordinates":[-99.102941,40.712275],"type":"Point"}
}