{
  "type": "Feature",
  "properties": {
    "iso:country":"US",
    "sg:address":"402 Washington Ave",
    "sg:city":"Chappell",
    "sg:classifiers":[
        {
            "category":"Recreation",
            "type":"Entertainment"
        }
    ],
    "sg:phone":"+1 308 874 2510",
    "sg:postcode":"69129",
    "sg:province":"NE",
    "sg:tags":[
        "pool",
        "swimming"
    ],
    "wof:name":"Chappell City Swimming Pool",
    "wof:placetype":"venue"
},
  "geometry": {"coordinates":[-102.462576,41.095163],"type":"Point"}
}