{
  "type": "Feature",
  "properties": {
    "iso:country":"US",
    "sg:address":"1205 Birch St",
    "sg:city":"Wahoo",
    "sg:classifiers":[
        {
            "category":"Real Estate",
            "subcategory":"Real Estate Operator",
            "type":"Services"
        }
    ],
    "sg:phone":"+1 402 443 5398",
    "sg:postcode":"68066",
    "sg:province":"NE",
    "sg:tags":[
        "building",
        "apartment"
    ],
    "wof:name":"Bruner Evergreen Acres LLC",
    "wof:placetype":"venue"
},
  "geometry": {"coordinates":[-96.630182,41.218858],"type":"Point"}
}