{
  "type": "Feature",
  "properties": {
    "iso:country":"US",
    "sg:address":"16710 US Hwy 30",
    "sg:city":"Chappell",
    "sg:classifiers":[
        {
            "category":"Wholesale",
            "subcategory":"Scrap",
            "type":"Manufacturing & Wholesale Goods"
        }
    ],
    "sg:phone":"+1 308 874 3045",
    "sg:postcode":"69129",
    "sg:province":"NE",
    "sg:tags":[
        "recycling",
        "center"
    ],
    "wof:name":"Dewey's Recycling Svc",
    "wof:placetype":"venue"
},
  "geometry": {"coordinates":[-102.45667899999999,41.092646],"type":"Point"}
}