{
  "type": "Feature",
  "properties": {
    "iso:country":"US",
    "sg:address":"1911 N 98th St",
    "sg:city":"Lincoln",
    "sg:classifiers":[
        {
            "category":"Shopping",
            "subcategory":"Gifts & Souvenirs",
            "type":"Retail Goods"
        }
    ],
    "sg:phone":"+1 402 483 2697",
    "sg:postcode":"68505",
    "sg:province":"NE",
    "wof:name":"Tomlan Gifts",
    "wof:placetype":"venue"
},
  "geometry": {"coordinates":[-96.58690799999999,40.831527],"type":"Point"}
}