{
  "type": "Feature",
  "properties": {
    "addr:full":"36 Hwy 370 Omaha NE 68102",
    "addr:postcode":"68102",
    "addr:street":"36 Hwy 370",
    "iso:country":"US",
    "sg:address":"36 Hwy 370",
    "sg:city":"Omaha",
    "sg:classifiers":[
        {
            "category":"Restaurant",
            "type":"Food & Drink"
        }
    ],
    "sg:phone":"+1 402 291 2999",
    "sg:postcode":"68102",
    "sg:province":"NE",
    "sg:tags":[
        "pizza"
    ],
    "wof:name":"Pizza Hut",
    "wof:placetype":"venue"
},
  "geometry": {"coordinates":[-95.937202,41.257198],"type":"Point"}
}