{
  "type": "Feature",
  "properties": {
    "iso:country":"US",
    "sg:address":"4550 Crown Point Ave",
    "sg:city":"Omaha",
    "sg:classifiers":[
        {
            "category":"Professional",
            "subcategory":"Computer Services",
            "type":"Services"
        }
    ],
    "sg:phone":"+1 402 457 5926",
    "sg:postcode":"68104",
    "sg:province":"NE",
    "sg:tags":[
        "repair"
    ],
    "wof:name":"Computer Rescue Svc",
    "wof:placetype":"venue"
},
  "geometry": {"coordinates":[-95.98042599999999,41.312959],"type":"Point"}
}