{
  "type": "Feature",
  "properties": {
    "addr:full":"909 2nd St Crawford NE 69339",
    "addr:housenumber":"909",
    "addr:postcode":"69339",
    "addr:street":"2Nd St",
    "iso:country":"US",
    "sg:address":"909 2nd St",
    "sg:city":"Crawford",
    "sg:classifiers":[
        {
            "category":"Insurance",
            "subcategory":"Life Insurance",
            "type":"Services"
        }
    ],
    "sg:phone":"+1 308 665 2252",
    "sg:postcode":"69339",
    "sg:province":"NE",
    "sg:tags":[
        "carrier"
    ],
    "wof:name":"Royal Neighbors of America",
    "wof:placetype":"venue"
},
  "geometry": {"coordinates":[-103.41318,42.680879],"type":"Point"}
}