{
  "type": "Feature",
  "properties": {
    "addr:full":"1430 S 10th St Lincoln NE 68502",
    "addr:housenumber":"1430",
    "addr:postcode":"68502",
    "addr:street":"S 10Th St",
    "iso:country":"US",
    "sg:address":"1430 S 10th St",
    "sg:city":"Lincoln",
    "sg:classifiers":[
        {
            "category":"Retail",
            "subcategory":"Repair Shop",
            "type":"Services"
        }
    ],
    "sg:phone":"+1 402 477 3529",
    "sg:postcode":"68502",
    "sg:province":"NE",
    "sg:tags":[
        "plumbing",
        "drain",
        "cleaning",
        "sewer"
    ],
    "wof:name":"A 1 Drain & Sewer Svc",
    "wof:placetype":"venue"
},
  "geometry": {"coordinates":[-96.70703,40.79845],"type":"Point"}
}