{
  "type": "Feature",
  "properties": {
    "iso:country":"US",
    "sg:address":"104 N 24th St",
    "sg:city":"Beatrice",
    "sg:classifiers":[
        {
            "category":"Personal",
            "subcategory":"Tanning Parlor",
            "type":"Services"
        }
    ],
    "sg:phone":"+1 402 223 3775",
    "sg:postcode":"68310",
    "sg:province":"NE",
    "sg:tags":[
        "salon"
    ],
    "wof:name":"Pat's Video Sun & Sport Inc",
    "wof:placetype":"venue"
},
  "geometry": {"coordinates":[-96.72115700000001,40.266093],"type":"Point"}
}