{
  "type": "Feature",
  "properties": {
    "iso:country":"US",
    "sg:address":"713 Co Rd 15",
    "sg:city":"Schuyler",
    "sg:classifiers":[
        {
            "category":"Farming",
            "subcategory":"Livestock Farm",
            "type":"Manufacturing & Wholesale Goods"
        }
    ],
    "sg:phone":"+1 402 352 5884",
    "sg:postcode":"68661",
    "sg:province":"NE",
    "sg:tags":[
        "hog",
        "beef",
        "far",
        "corn",
        "cattle",
        "or",
        "feedlot"
    ],
    "wof:name":"Prairie Valley Farms Inc",
    "wof:placetype":"venue"
},
  "geometry": {"coordinates":[-96.983332,41.482767],"type":"Point"}
}