{
  "type": "Feature",
  "properties": {
    "addr:full":"11623 Arbor St Omaha NE 68144",
    "addr:housenumber":"11623",
    "addr:postcode":"68144",
    "addr:street":"Arbor St",
    "iso:country":"US",
    "sg:address":"11623 Arbor St",
    "sg:city":"Omaha",
    "sg:classifiers":[
        {
            "category":"Health Services",
            "subcategory":"Health Practitioner",
            "type":"Services"
        }
    ],
    "sg:phone":"+1 402 334 1919",
    "sg:postcode":"68144",
    "sg:province":"NE",
    "sg:tags":[
        "therapist",
        "physical"
    ],
    "wof:name":"Rehab Visions",
    "wof:placetype":"venue"
},
  "geometry": {"coordinates":[-96.094103,41.235891],"type":"Point"}
}