{
  "type": "Feature",
  "properties": {
    "iso:country":"US",
    "sg:address":"2702 N 61st St",
    "sg:city":"Omaha",
    "sg:classifiers":[
        {
            "category":"Organizations",
            "subcategory":"Religious Organization",
            "type":"Services"
        }
    ],
    "sg:phone":"+1 402 553 2955",
    "sg:postcode":"68104",
    "sg:province":"NE",
    "wof:name":"Temple Baptst Church G A R B C",
    "wof:placetype":"venue"
},
  "geometry": {"coordinates":[-96.007251,41.284964],"type":"Point"}
}