{
  "type": "Feature",
  "properties": {
    "addr:full":"3021 15th St Columbus NE 68601",
    "addr:housenumber":"3021",
    "addr:postcode":"68601",
    "addr:street":"15Th St",
    "iso:country":"US",
    "sg:address":"3021 15th St",
    "sg:city":"Columbus",
    "sg:classifiers":[
        {
            "category":"Health Services",
            "subcategory":"Clinic",
            "type":"Services"
        }
    ],
    "sg:phone":"+1 402 564 2694",
    "sg:postcode":"68601",
    "sg:province":"NE",
    "sg:tags":[
        "home"
    ],
    "wof:name":"Tooley Drug & Hm Care After",
    "wof:placetype":"venue"
},
  "geometry": {"coordinates":[-97.36545099999999,41.431278],"type":"Point"}
}