{
  "type": "Feature",
  "properties": {
    "addr:full":"917 Paddock St Beatrice NE 68310",
    "addr:housenumber":"917",
    "addr:postcode":"68310",
    "addr:street":"Paddock St",
    "iso:country":"US",
    "sg:address":"917 Paddock St",
    "sg:city":"Beatrice",
    "sg:phone":"+1 402 228 5917",
    "sg:postcode":"68310",
    "sg:province":"NE",
    "sg:tags":[
        "farm",
        "corn"
    ],
    "wof:name":"Geno Schlake Express",
    "wof:placetype":"venue"
},
  "geometry": {"coordinates":[-96.772814,40.268418],"type":"Point"}
}