{
  "type": "Feature",
  "properties": {
    "iso:country":"US",
    "sg:address":"3200 Sumner St",
    "sg:city":"Lincoln",
    "sg:classifiers":[
        {
            "category":"Social Services",
            "subcategory":"Child Care",
            "type":"Services"
        }
    ],
    "sg:phone":"+1 402 476 3200",
    "sg:postcode":"68502",
    "sg:province":"NE",
    "sg:tags":[
        "day"
    ],
    "wof:name":"Child Advocacy LLC",
    "wof:placetype":"venue"
},
  "geometry": {"coordinates":[-96.674646,40.795372],"type":"Point"}
}