{
  "type": "Feature",
  "properties": {
    "iso:country":"US",
    "sg:address":"2806 Nottingham Dr",
    "sg:city":"Bellevue",
    "sg:classifiers":[
        {
            "category":"Organizations",
            "subcategory":"Community Association",
            "type":"Services"
        }
    ],
    "sg:phone":"+1 402 291 6338",
    "sg:postcode":"68123",
    "sg:province":"NE",
    "wof:name":"American Exprisoners of War",
    "wof:placetype":"venue"
},
  "geometry": {"coordinates":[-95.95164699999999,41.113181],"type":"Point"}
}