{
  "type": "Feature",
  "properties": {
    "iso:country":"US",
    "sg:address":"507 E 3rd St",
    "sg:city":"Alliance",
    "sg:classifiers":[
        {
            "category":"Personal",
            "subcategory":"Beauty Salon",
            "type":"Services"
        }
    ],
    "sg:phone":"+1 308 762 6525",
    "sg:postcode":"69301",
    "sg:province":"NE",
    "wof:name":"Special Effects Hair Styling",
    "wof:placetype":"venue"
},
  "geometry": {"coordinates":[-102.864996,42.097154],"type":"Point"}
}