{
  "type": "Feature",
  "properties": {
    "iso:country":"US",
    "sg:address":"1300 Taylor Ave",
    "sg:city":"Norfolk",
    "sg:classifiers":[
        {
            "category":"Professional",
            "subcategory":"Lawyer & Legal Services",
            "type":"Services"
        }
    ],
    "sg:phone":"+1 402 371 4330",
    "sg:postcode":"68701",
    "sg:province":"NE",
    "sg:tags":[
        "attorney"
    ],
    "wof:name":"Mueting & Stoffer",
    "wof:placetype":"venue"
},
  "geometry": {"coordinates":[-97.42658299999999,42.026892],"type":"Point"}
}