{
  "type": "Feature",
  "properties": {
    "addr:full":"1824 E 7th St Grand Island NE 68801",
    "addr:housenumber":"1824",
    "addr:postcode":"68801",
    "addr:street":"E 7Th St",
    "iso:country":"US",
    "sg:address":"1824 E 7th St",
    "sg:city":"Grand Island",
    "sg:classifiers":[
        {
            "category":"Building & Trades",
            "subcategory":"Construction",
            "type":"Services"
        }
    ],
    "sg:phone":"+1 308 382 0177",
    "sg:postcode":"68801",
    "sg:province":"NE",
    "sg:tags":[
        "home",
        "improvement"
    ],
    "wof:name":"Pete's Home Improvement",
    "wof:placetype":"venue"
},
  "geometry": {"coordinates":[-98.323958,40.938242],"type":"Point"}
}