{
  "type": "Feature",
  "properties": {
    "iso:country":"US",
    "sg:address":"2001 Leavenworth St",
    "sg:city":"Omaha",
    "sg:classifiers":[
        {
            "category":"Banks & Credit Unions",
            "subcategory":"Investment Brokerage",
            "type":"Services"
        }
    ],
    "sg:phone":"+1 402 884 7944",
    "sg:postcode":"68102",
    "sg:province":"NE",
    "sg:tags":[
        "advisory",
        "financial"
    ],
    "wof:name":"First City Financial",
    "wof:placetype":"venue"
},
  "geometry": {"coordinates":[-95.943477,41.252372],"type":"Point"}
}