{
  "type": "Feature",
  "properties": {
    "addr:full":"105 Main St Wakefield NE 68784",
    "addr:housenumber":"105",
    "addr:postcode":"68784",
    "addr:street":"Main St",
    "iso:country":"US",
    "sg:address":"105 Main St",
    "sg:city":"Wakefield",
    "sg:classifiers":[
        {
            "category":"Wholesale",
            "subcategory":"Poultry",
            "type":"Manufacturing & Wholesale Goods"
        }
    ],
    "sg:phone":"+1 402 287 2211",
    "sg:postcode":"68784",
    "sg:province":"NE",
    "sg:tags":[
        "eggs"
    ],
    "sg:website":"www.michaelfoods.com",
    "wof:name":"Michael Foods Inc",
    "wof:placetype":"venue"
},
  "geometry": {"coordinates":[-96.865262,42.258924],"type":"Point"}
}