{
  "type": "Feature",
  "properties": {
    "addr:full":"24135 S 12th St Martell NE 68404",
    "addr:housenumber":"24135",
    "addr:postcode":"68404",
    "addr:street":"S 12Th St",
    "iso:country":"US",
    "sg:address":"24135 S 12th St",
    "sg:city":"Martell",
    "sg:classifiers":[
        {
            "category":"Restaurant",
            "type":"Food & Drink"
        }
    ],
    "sg:phone":"+1 402 798 7025",
    "sg:postcode":"68404",
    "sg:province":"NE",
    "sg:tags":[
        "eating"
    ],
    "wof:name":"Princeton Tavern",
    "wof:placetype":"venue"
},
  "geometry": {"coordinates":[-96.704515,40.573412],"type":"Point"}
}