{
  "type": "Feature",
  "properties": {
    "iso:country":"US",
    "sg:address":"56779 Golf Course Rd",
    "sg:city":"Stanton",
    "sg:classifiers":[
        {
            "category":"Farming",
            "subcategory":"Livestock Farm",
            "type":"Manufacturing & Wholesale Goods"
        }
    ],
    "sg:phone":"+1 402 439 2313",
    "sg:postcode":"68779",
    "sg:province":"NE",
    "sg:tags":[
        "feedlot",
        "corn",
        "soybean",
        "beef",
        "cattle"
    ],
    "wof:name":"Dennis Kment Farm",
    "wof:placetype":"venue"
},
  "geometry": {"coordinates":[-97.16814100000001,41.938948],"type":"Point"}
}