{
  "type": "Feature",
  "properties": {
    "addr:full":"1611 Broadway Scottsbluff NE 69361",
    "addr:housenumber":"1611",
    "addr:postcode":"69361",
    "addr:street":"Broadway",
    "iso:country":"US",
    "sg:address":"1611 Broadway",
    "sg:city":"Scottsbluff",
    "sg:classifiers":[
        {
            "category":"Personal",
            "type":"Services"
        }
    ],
    "sg:phone":"+1 308 632 3227",
    "sg:postcode":"69361",
    "sg:province":"NE",
    "sg:tags":[
        "shop",
        "beauty"
    ],
    "wof:name":"Salon West",
    "wof:placetype":"venue"
},
  "geometry": {"coordinates":[-103.662656,41.863166],"type":"Point"}
}