{
  "type": "Feature",
  "properties": {
    "addr:full":"1003 11th Ave Plattsmouth NE 68048",
    "addr:housenumber":"1003",
    "addr:postcode":"68048",
    "addr:street":"11Th Ave",
    "iso:country":"US",
    "sg:address":"1003 11th Ave",
    "sg:city":"Plattsmouth",
    "sg:classifiers":[
        {
            "category":"Education",
            "subcategory":"Dance Studio",
            "type":"Public Place"
        }
    ],
    "sg:phone":"+1 402 296 2772",
    "sg:postcode":"68048",
    "sg:province":"NE",
    "sg:tags":[
        "mobile",
        "gymnastics"
    ],
    "wof:name":"Tumble Bus Inc",
    "wof:placetype":"venue"
},
  "geometry": {"coordinates":[-95.890506,41.000542],"type":"Point"}
}