{
  "type": "Feature",
  "properties": {
    "iso:country":"US",
    "sg:address":"509 E 2nd Ave",
    "sg:city":"Arnold",
    "sg:classifiers":[
        {
            "category":"Wholesale",
            "subcategory":"Farm Supplies",
            "type":"Manufacturing & Wholesale Goods"
        }
    ],
    "sg:phone":"+1 308 848 3215",
    "sg:postcode":"69120",
    "sg:province":"NE",
    "sg:tags":[
        "fertilizer"
    ],
    "wof:name":"Agri Alliance",
    "wof:placetype":"venue"
},
  "geometry": {"coordinates":[-100.18883,41.420762],"type":"Point"}
}