{
  "type": "Feature",
  "properties": {
    "iso:country":"US",
    "sg:address":"339 Main St",
    "sg:city":"Plattsmouth",
    "sg:classifiers":[
        {
            "category":"Insurance",
            "subcategory":"Insurance Agent",
            "type":"Services"
        }
    ],
    "sg:phone":"+1 402 296 6114",
    "sg:postcode":"68048",
    "sg:province":"NE",
    "sg:tags":[
        "legal"
    ],
    "wof:name":"Thomas E Ranney",
    "wof:placetype":"venue"
},
  "geometry": {"coordinates":[-95.882969,41.011089],"type":"Point"}
}