{
  "type": "Feature",
  "properties": {
    "iso:country":"US",
    "sg:address":"104 W Fulton St",
    "sg:city":"Hooper",
    "sg:classifiers":[
        {
            "category":"Personal",
            "subcategory":"Beauty Salon",
            "type":"Services"
        }
    ],
    "sg:phone":"+1 402 654 3519",
    "sg:postcode":"68031",
    "sg:province":"NE",
    "wof:name":"Clip & Comb",
    "wof:placetype":"venue"
},
  "geometry": {"coordinates":[-96.548316,41.610932],"type":"Point"}
}