{
  "type": "Feature",
  "properties": {
    "iso:country":"US",
    "sg:address":"1413 S 13th St",
    "sg:city":"Lincoln",
    "sg:classifiers":[
        {
            "category":"Health Services",
            "subcategory":"Doctor",
            "type":"Services"
        }
    ],
    "sg:phone":"+1 402 474 5504",
    "sg:postcode":"68502",
    "sg:province":"NE",
    "sg:tags":[
        "dentist"
    ],
    "wof:name":"Jennifer Kurth DDS",
    "wof:placetype":"venue"
},
  "geometry": {"coordinates":[-96.70283000000001,40.798235],"type":"Point"}
}