{
  "type": "Feature",
  "properties": {
    "iso:country":"US",
    "sg:address":"1742 N 48th St",
    "sg:city":"Lincoln",
    "sg:classifiers":[
        {
            "category":"Home & Garden",
            "subcategory":"Garden Supply",
            "type":"Retail Goods"
        }
    ],
    "sg:phone":"+1 402 466 1981",
    "sg:postcode":"68504",
    "sg:province":"NE",
    "sg:tags":[
        "nursery"
    ],
    "wof:name":"Williams Flowers",
    "wof:placetype":"venue"
},
  "geometry": {"coordinates":[-96.653637,40.829917],"type":"Point"}
}