{
  "type": "Feature",
  "properties": {
    "addr:full":"666 Co Rd 8 Scribner NE 68057",
    "addr:housenumber":"666",
    "addr:postcode":"68057",
    "addr:street":"Co Rd 8 Scribner Ne",
    "iso:country":"US",
    "sg:address":"666 Co Rd 8",
    "sg:city":"Scribner",
    "sg:classifiers":[
        {
            "category":"Farming",
            "subcategory":"Livestock Farm",
            "type":"Manufacturing & Wholesale Goods"
        }
    ],
    "sg:phone":"+1 402 568 2561",
    "sg:postcode":"68057",
    "sg:province":"NE",
    "sg:tags":[
        "hog",
        "or",
        "feedlot"
    ],
    "wof:name":"Daniel K & Mishele K Beerbohm",
    "wof:placetype":"venue"
},
  "geometry": {"coordinates":[-96.77084600000001,41.660199],"type":"Point"}
}