{
  "type": "Feature",
  "properties": {
    "iso:country":"US",
    "sg:address":"2417 Chase St",
    "sg:city":"Falls City",
    "sg:classifiers":[
        {
            "category":"Professional",
            "subcategory":"Lawyer & Legal Services",
            "type":"Services"
        }
    ],
    "sg:phone":"+1 402 245 2826",
    "sg:postcode":"68355",
    "sg:province":"NE",
    "sg:tags":[
        "attorney"
    ],
    "wof:name":"Harold C Prichard",
    "wof:placetype":"venue"
},
  "geometry": {"coordinates":[-95.604204,40.069473],"type":"Point"}
}