{
  "type": "Feature",
  "properties": {
    "iso:country":"US",
    "sg:address":"202 W 4th St",
    "sg:city":"Axtell",
    "sg:classifiers":[
        {
            "category":"Retail",
            "subcategory":"Funeral Services",
            "type":"Services"
        }
    ],
    "sg:phone":"+1 308 743 2101",
    "sg:postcode":"68924",
    "sg:province":"NE",
    "sg:tags":[
        "director"
    ],
    "wof:name":"Freeland-Layton Funeral Home",
    "wof:placetype":"venue"
},
  "geometry": {"coordinates":[-99.12870700000001,40.479447],"type":"Point"}
}