{
  "type": "Feature",
  "properties": {
    "iso:country":"US",
    "sg:address":"2600 W Adams St",
    "sg:city":"Lincoln",
    "sg:classifiers":[
        {
            "category":"Government",
            "subcategory":"Office",
            "type":"Public Place"
        }
    ],
    "sg:phone":"+1 402 474 3011",
    "sg:postcode":"68524",
    "sg:province":"NE",
    "sg:tags":[
        "control",
        "tower",
        "traffic",
        "air"
    ],
    "wof:name":"Airport Traffic Control Tower",
    "wof:placetype":"venue"
},
  "geometry": {"coordinates":[-96.749483,40.842991],"type":"Point"}
}