{
  "type": "Feature",
  "properties": {
    "iso:country":"US",
    "sg:address":"13649 W Holling Rd",
    "sg:city":"Wood River",
    "sg:classifiers":[
        {
            "category":"Retail",
            "subcategory":"Animal Services",
            "type":"Services"
        }
    ],
    "sg:phone":"+1 308 583 2591",
    "sg:postcode":"68883",
    "sg:province":"NE",
    "wof:name":"Packs Pups Kennel",
    "wof:placetype":"venue"
},
  "geometry": {"coordinates":[-98.601854,40.800644],"type":"Point"}
}