{
  "type": "Feature",
  "properties": {
    "addr:full":"125 Center Ave Morrill NE 69358",
    "addr:housenumber":"125",
    "addr:postcode":"69358",
    "addr:street":"Center Ave",
    "iso:country":"US",
    "sg:address":"125 Center Ave",
    "sg:city":"Morrill",
    "sg:classifiers":[
        {
            "category":"Government",
            "subcategory":"Post Office",
            "type":"Public Place"
        }
    ],
    "sg:phone":"+1 308 247 2095",
    "sg:postcode":"69358",
    "sg:province":"NE",
    "wof:name":"US Post Office",
    "wof:placetype":"venue"
},
  "geometry": {"coordinates":[-103.926153,41.963104],"type":"Point"}
}