{
  "type": "Feature",
  "properties": {
    "iso:country":"US",
    "sg:address":"111 S 1st St",
    "sg:city":"Pierce",
    "sg:classifiers":[
        {
            "category":"Government",
            "subcategory":"Office",
            "type":"Public Place"
        }
    ],
    "sg:phone":"+1 402 329 4810",
    "sg:postcode":"68767",
    "sg:province":"NE",
    "wof:name":"Pierce County Drivers Examiner",
    "wof:placetype":"venue"
},
  "geometry": {"coordinates":[-97.52461099999999,42.198209],"type":"Point"}
}