{
  "type": "Feature",
  "properties": {
    "iso:country":"US",
    "sg:address":"102 Scotia Ave",
    "sg:city":"Scotia",
    "sg:classifiers":[
        {
            "category":"Professional",
            "type":"Services"
        }
    ],
    "sg:phone":"+1 308 245 4190",
    "sg:postcode":"68875",
    "sg:province":"NE",
    "sg:tags":[
        "establishment"
    ],
    "wof:name":"C B Snodgrass",
    "wof:placetype":"venue"
},
  "geometry": {"coordinates":[-98.709216,41.466456],"type":"Point"}
}