{
  "type": "Feature",
  "properties": {
    "iso:country":"US",
    "sg:address":"17330 W Center Rd",
    "sg:city":"Omaha",
    "sg:classifiers":[
        {
            "category":"Shopping",
            "subcategory":"Computers & Home Electronics",
            "type":"Retail Goods"
        }
    ],
    "sg:phone":"+1 402 697 0222",
    "sg:postcode":"68130",
    "sg:province":"NE",
    "sg:tags":[
        "equipment",
        "dealer"
    ],
    "wof:name":"Computer Renaissance Inc",
    "wof:placetype":"venue"
},
  "geometry": {"coordinates":[-96.184983,41.234203],"type":"Point"}
}