{
  "type": "Feature",
  "properties": {
    "iso:country":"US",
    "sg:address":"11825 Q St",
    "sg:city":"Omaha",
    "sg:classifiers":[
        {
            "category":"Professional",
            "subcategory":"Management & Consulting",
            "type":"Services"
        }
    ],
    "sg:phone":"+1 402 891 0009",
    "sg:postcode":"68137",
    "sg:province":"NE",
    "sg:tags":[
        "personnel",
        "consultant"
    ],
    "sg:website":"www.ca-industries.com",
    "wof:name":"C & A Industries",
    "wof:placetype":"venue"
},
  "geometry": {"coordinates":[-96.100335,41.205235],"type":"Point"}
}