{
  "type": "Feature",
  "properties": {
    "iso:country":"US",
    "sg:address":"418 N Spruce St",
    "sg:city":"Ogallala",
    "sg:classifiers":[
        {
            "category":"Professional",
            "subcategory":"Lawyer & Legal Services",
            "type":"Services"
        }
    ],
    "sg:phone":"+1 308 284 3974",
    "sg:postcode":"69153",
    "sg:province":"NE",
    "sg:tags":[
        "attorney"
    ],
    "wof:name":"Krajewski Law Office",
    "wof:placetype":"venue"
},
  "geometry": {"coordinates":[-101.719842,41.12814],"type":"Point"}
}