{
  "type": "Feature",
  "properties": {
    "addr:full":"1036 S Burlington Ave Hastings NE 68901",
    "addr:housenumber":"1036",
    "addr:postcode":"68901",
    "addr:street":"S Burlington Ave",
    "iso:country":"US",
    "sg:address":"1036 S Burlington Ave",
    "sg:city":"Hastings",
    "sg:classifiers":[
        {
            "category":"Restaurant",
            "type":"Food & Drink"
        }
    ],
    "sg:phone":"+1 402 463 2788",
    "sg:postcode":"68901",
    "sg:province":"NE",
    "sg:tags":[
        "eating"
    ],
    "wof:name":"88 China Buffet",
    "wof:placetype":"venue"
},
  "geometry": {"coordinates":[-98.39259199999999,40.569773],"type":"Point"}
}