{
  "type": "Feature",
  "properties": {
    "iso:country":"US",
    "sg:address":"729 E Eldora Ln",
    "sg:city":"Lincoln",
    "sg:classifiers":[
        {
            "category":"Building & Trades",
            "subcategory":"Construction",
            "type":"Services"
        }
    ],
    "sg:phone":"+1 402 483 0660",
    "sg:postcode":"68505",
    "sg:province":"NE",
    "sg:tags":[
        "residential",
        "general",
        "nonresidential",
        "contractor"
    ],
    "wof:name":"Carl's Contracting",
    "wof:placetype":"venue"
},
  "geometry": {"coordinates":[-96.623459,40.818718],"type":"Point"}
}