{
  "type": "Feature",
  "properties": {
    "iso:country":"US",
    "sg:address":"2932 S 132nd St",
    "sg:city":"Omaha",
    "sg:classifiers":[
        {
            "category":"Personal",
            "subcategory":"Barber",
            "type":"Services"
        }
    ],
    "sg:phone":"+1 402 333 0219",
    "sg:postcode":"68144",
    "sg:province":"NE",
    "sg:tags":[
        "shop"
    ],
    "wof:name":"Baker Square Barber Shop",
    "wof:placetype":"venue"
},
  "geometry": {"coordinates":[-96.119585,41.233539],"type":"Point"}
}