{
  "type": "Feature",
  "properties": {
    "iso:country":"US",
    "sg:address":"408 E Fillmore Ave",
    "sg:city":"De Witt",
    "sg:classifiers":[
        {
            "category":"Government",
            "subcategory":"Fire Station",
            "type":"Public Place"
        }
    ],
    "sg:phone":"+1 402 683 2245",
    "sg:postcode":"68341",
    "sg:province":"NE",
    "sg:tags":[
        "department"
    ],
    "wof:name":"De WITT Fire Dept",
    "wof:placetype":"venue"
},
  "geometry": {"coordinates":[-96.91908599999999,40.394662],"type":"Point"}
}