{
  "type": "Feature",
  "properties": {
    "iso:country":"US",
    "sg:address":"19100 Capehart Rd",
    "sg:city":"Gretna",
    "sg:classifiers":[
        {
            "category":"Professional",
            "type":"Services"
        }
    ],
    "sg:phone":"+1 402 332 3985",
    "sg:postcode":"68028",
    "sg:province":"NE",
    "sg:tags":[
        "establishment"
    ],
    "wof:name":"SBA Inc",
    "wof:placetype":"venue"
},
  "geometry": {"coordinates":[-96.21423,41.117689],"type":"Point"}
}