{
  "type": "Feature",
  "properties": {
    "iso:country":"US",
    "sg:address":"1810 1st Ave",
    "sg:city":"Scottsbluff",
    "sg:classifiers":[
        {
            "category":"Personal",
            "subcategory":"Barber",
            "type":"Services"
        }
    ],
    "sg:phone":"+1 308 635 2220",
    "sg:postcode":"69361",
    "sg:province":"NE",
    "wof:name":"Shear Class",
    "wof:placetype":"venue"
},
  "geometry": {"coordinates":[-103.66139800000001,41.865136],"type":"Point"}
}