{
  "type": "Feature",
  "properties": {
    "addr:full":"998 Candice St Valentine NE 69201",
    "addr:housenumber":"998",
    "addr:postcode":"69201",
    "addr:street":"Candice St",
    "iso:country":"US",
    "sg:address":"998 Candice St",
    "sg:city":"Valentine",
    "sg:classifiers":[
        {
            "category":"Building & Trades",
            "subcategory":"Cleaning & Sanitation",
            "type":"Services"
        }
    ],
    "sg:phone":"+1 402 376 1806",
    "sg:postcode":"69201",
    "sg:province":"NE",
    "sg:tags":[
        "maintenance"
    ],
    "wof:name":"Brian Stec",
    "wof:placetype":"venue"
},
  "geometry": {"coordinates":[-100.566411,42.875457],"type":"Point"}
}