{
  "type": "Feature",
  "properties": {
    "addr:full":"5409 N 90th St Omaha NE 68134",
    "addr:housenumber":"5409",
    "addr:postcode":"68134",
    "addr:street":"N 90Th St",
    "iso:country":"US",
    "sg:address":"5409 N 90th St",
    "sg:city":"Omaha",
    "sg:classifiers":[
        {
            "category":"Personal",
            "subcategory":"Beauty Salon",
            "type":"Services"
        }
    ],
    "sg:phone":"+1 402 572 6349",
    "sg:postcode":"68134",
    "sg:province":"NE",
    "sg:tags":[
        "shop"
    ],
    "wof:name":"Great Clips",
    "wof:placetype":"venue"
},
  "geometry": {"coordinates":[-96.052543,41.307772],"type":"Point"}
}