{
  "type": "Feature",
  "properties": {
    "iso:country":"US",
    "sg:address":"845 S D St",
    "sg:city":"Broken Bow",
    "sg:classifiers":[
        {
            "category":"Shopping",
            "subcategory":"Jewelry",
            "type":"Retail Goods"
        }
    ],
    "sg:phone":"+1 308 872 2839",
    "sg:postcode":"68822",
    "sg:province":"NE",
    "sg:tags":[
        "jeweler"
    ],
    "wof:name":"Midwest Jewelry",
    "wof:placetype":"venue"
},
  "geometry": {"coordinates":[-99.640168,41.402746],"type":"Point"}
}