{
  "type": "Feature",
  "properties": {
    "addr:full":"4822 S 133rd St Omaha NE 68137",
    "addr:housenumber":"4822",
    "addr:postcode":"68137",
    "addr:street":"S 133Rd St",
    "iso:country":"US",
    "sg:address":"4822 S 133rd St",
    "sg:city":"Omaha",
    "sg:classifiers":[
        {
            "category":"Wholesale",
            "subcategory":"Durable Goods & Equipment",
            "type":"Manufacturing & Wholesale Goods"
        }
    ],
    "sg:phone":"+1 402 894 5812",
    "sg:postcode":"68137",
    "sg:province":"NE",
    "sg:tags":[
        "representative",
        "manufacturer"
    ],
    "wof:name":"Larry Johnson Sales Inc",
    "wof:placetype":"venue"
},
  "geometry": {"coordinates":[-96.12379199999999,41.211899],"type":"Point"}
}