{
  "type": "Feature",
  "properties": {
    "iso:country":"US",
    "sg:address":"2941 Keystone Dr",
    "sg:city":"Omaha",
    "sg:classifiers":[
        {
            "category":"Building & Trades",
            "subcategory":"Construction",
            "type":"Services"
        }
    ],
    "sg:phone":"+1 402 498 2906",
    "sg:postcode":"68134",
    "sg:province":"NE",
    "sg:tags":[
        "dry wall",
        "contractor"
    ],
    "wof:name":"Christensen Drywall Contr",
    "wof:placetype":"venue"
},
  "geometry": {"coordinates":[-96.047369,41.286408],"type":"Point"}
}