{
  "type": "Feature",
  "properties": {
    "iso:country":"US",
    "sg:address":"715 S 14th St",
    "sg:city":"Lincoln",
    "sg:classifiers":[
        {
            "category":"Organizations",
            "subcategory":"Non-profit Organization",
            "type":"Services"
        },
        {
            "category":"Organizations",
            "subcategory":"Professional Association",
            "type":"Services"
        }
    ],
    "sg:phone":"+1 402 475 3859",
    "sg:postcode":"68508",
    "sg:province":"NE",
    "wof:name":"Nebraska Nurses Association",
    "wof:placetype":"venue"
},
  "geometry": {"coordinates":[-96.701206,40.805841],"type":"Point"}
}