{
  "type": "Feature",
  "properties": {
    "addr:full":"1755 N Bell St Fremont NE 68025",
    "addr:housenumber":"1755",
    "addr:postcode":"68025",
    "addr:street":"N Bell St",
    "iso:country":"US",
    "sg:address":"1755 N Bell St",
    "sg:city":"Fremont",
    "sg:classifiers":[
        {
            "category":"Restaurant",
            "type":"Food & Drink"
        }
    ],
    "sg:menulink":"http://www.allmenus.com/ne/fremont/181589-wendys/menu/",
    "sg:phone":"+1 402 727 4490",
    "sg:postcode":"68025",
    "sg:province":"NE",
    "sg:tags":[
        "burger",
        "american",
        "soup"
    ],
    "wof:name":"Wendy's",
    "wof:placetype":"venue"
},
  "geometry": {"coordinates":[-96.48351099999999,41.446025],"type":"Point"}
}