{
  "type": "Feature",
  "properties": {
    "iso:country":"US",
    "sg:address":"2206 Home St",
    "sg:city":"Hastings",
    "sg:classifiers":[
        {
            "category":"Building & Trades",
            "subcategory":"Construction",
            "type":"Services"
        }
    ],
    "sg:phone":"+1 402 463 0767",
    "sg:postcode":"68901",
    "sg:province":"NE",
    "sg:tags":[
        "remodeling",
        "contractor"
    ],
    "wof:name":"Vic Kyle",
    "wof:placetype":"venue"
},
  "geometry": {"coordinates":[-98.412676,40.596127],"type":"Point"}
}