{
  "type": "Feature",
  "properties": {
    "iso:country":"US",
    "sg:address":"113 S 4th St",
    "sg:city":"Nebraska City",
    "sg:classifiers":[
        {
            "category":"Building & Trades",
            "subcategory":"Plumbing",
            "type":"Services"
        }
    ],
    "sg:phone":"+1 402 873 3944",
    "sg:postcode":"68410",
    "sg:province":"NE",
    "sg:tags":[
        "contractor"
    ],
    "wof:name":"Bowers Refrigeration & Heating",
    "wof:placetype":"venue"
},
  "geometry": {"coordinates":[-95.849875,40.676397],"type":"Point"}
}