{
  "type": "Feature",
  "properties": {
    "iso:country":"US",
    "sg:address":"4333 S 90th St",
    "sg:city":"Omaha",
    "sg:classifiers":[
        {
            "category":"Building & Trades",
            "subcategory":"Plumbing",
            "type":"Services"
        }
    ],
    "sg:phone":"+1 402 572 1900",
    "sg:postcode":"68127",
    "sg:province":"NE",
    "sg:tags":[
        "conditioning",
        "air",
        "system",
        "contractor"
    ],
    "wof:name":"All Temperature Control Inc",
    "wof:placetype":"venue"
},
  "geometry": {"coordinates":[-96.05257,41.216511],"type":"Point"}
}