{
  "type": "Feature",
  "properties": {
    "iso:country":"US",
    "sg:address":"15514 Windsor Dr",
    "sg:city":"Omaha",
    "sg:classifiers":[
        {
            "category":"Social Services",
            "subcategory":"Child Care",
            "type":"Services"
        }
    ],
    "sg:phone":"+1 402 492 3119",
    "sg:postcode":"68154",
    "sg:province":"NE",
    "sg:tags":[
        "day"
    ],
    "wof:name":"A Childs Choice",
    "wof:placetype":"venue"
},
  "geometry": {"coordinates":[-96.155795,41.275578],"type":"Point"}
}