{
  "type": "Feature",
  "properties": {
    "iso:country":"US",
    "sg:address":"520 S Main St",
    "sg:city":"Friend",
    "sg:classifiers":[
        {
            "category":"Building & Trades",
            "subcategory":"Construction",
            "type":"Services"
        }
    ],
    "sg:phone":"+1 402 947 9521",
    "sg:postcode":"68359",
    "sg:province":"NE",
    "sg:tags":[
        "floor",
        "laying",
        "contractor"
    ],
    "wof:name":"Fine Line Installation LLC",
    "wof:placetype":"venue"
},
  "geometry": {"coordinates":[-97.287689,40.650535],"type":"Point"}
}