{
  "type": "Feature",
  "properties": {
    "addr:full":"5200 Francis St Lincoln NE 68504",
    "addr:housenumber":"5200",
    "addr:postcode":"68504",
    "addr:street":"Francis St",
    "iso:country":"US",
    "sg:address":"5200 Francis St",
    "sg:city":"Lincoln",
    "sg:classifiers":[
        {
            "category":"Organizations",
            "subcategory":"Religious Organization",
            "type":"Services"
        }
    ],
    "sg:phone":"+1 402 466 9201",
    "sg:postcode":"68504",
    "sg:province":"NE",
    "wof:name":"Fourth Presbyterian Church",
    "wof:placetype":"venue"
},
  "geometry": {"coordinates":[-96.647149,40.831323],"type":"Point"}
}