{
  "type": "Feature",
  "properties": {
    "iso:country":"US",
    "sg:address":"210 E 8th St",
    "sg:city":"Lexington",
    "sg:classifiers":[
        {
            "category":"Retail",
            "subcategory":"Repair Shop",
            "type":"Services"
        }
    ],
    "sg:phone":"+1 308 324 4879",
    "sg:postcode":"68850",
    "sg:province":"NE",
    "wof:name":"Ss Repair",
    "wof:placetype":"venue"
},
  "geometry": {"coordinates":[-99.740027,40.780831],"type":"Point"}
}