{
  "type": "Feature",
  "properties": {
    "addr:full":"43680 Rd 752 Lexington NE 68850",
    "addr:postcode":"43680;68850",
    "addr:street":"Rd 752",
    "iso:country":"US",
    "sg:address":"43680 Rd 752",
    "sg:city":"Lexington",
    "sg:phone":"+1 308 324 4762",
    "sg:postcode":"68850",
    "sg:province":"NE",
    "sg:tags":[
        "farm",
        "corn"
    ],
    "wof:name":"Racek Farms Inc",
    "wof:placetype":"venue"
},
  "geometry": {"coordinates":[-99.67774799999999,40.728989],"type":"Point"}
}