{
  "type": "Feature",
  "properties": {
    "iso:country":"US",
    "sg:address":"1060 E 23rd St",
    "sg:city":"Fremont",
    "sg:classifiers":[
        {
            "category":"Autos & Motor Vehicles",
            "subcategory":"Auto Supplies",
            "type":"Retail Goods"
        }
    ],
    "sg:phone":"+1 402 727 7700",
    "sg:postcode":"68025",
    "sg:province":"NE",
    "sg:tags":[
        "recap",
        "repair",
        "retread",
        "tire"
    ],
    "sg:website":"http://www.tiresplus.com",
    "wof:name":"Team Tires Plus",
    "wof:placetype":"venue"
},
  "geometry": {"coordinates":[-96.483138,41.451456],"type":"Point"}
}