{
  "type": "Feature",
  "properties": {
    "iso:country":"US",
    "sg:address":"9425 N 48th St",
    "sg:city":"Omaha",
    "sg:classifiers":[
        {
            "category":"Manufacturing",
            "subcategory":"Food",
            "type":"Manufacturing & Wholesale Goods"
        }
    ],
    "sg:phone":"+1 402 571 4113",
    "sg:postcode":"68152",
    "sg:province":"NE",
    "sg:tags":[
        "preparation",
        "grocery",
        "mfg"
    ],
    "wof:name":"D & D Foods Inc",
    "wof:placetype":"venue"
},
  "geometry": {"coordinates":[-95.985311,41.345547],"type":"Point"}
}