{
  "type": "Feature",
  "properties": {
    "iso:country":"US",
    "sg:address":"419 S Main St",
    "sg:city":"Rushville",
    "sg:classifiers":[
        {
            "category":"Organizations",
            "subcategory":"Religious Organization",
            "type":"Services"
        }
    ],
    "sg:phone":"+1 308 327 2220",
    "sg:postcode":"69360",
    "sg:province":"NE",
    "sg:tags":[
        "church"
    ],
    "wof:name":"St Paul's Lutheran Church",
    "wof:placetype":"venue"
},
  "geometry": {"coordinates":[-102.463848,42.714781],"type":"Point"}
}