{
  "type": "Feature",
  "properties": {
    "addr:full":"13221 C St Omaha NE 68144",
    "addr:housenumber":"13221",
    "addr:postcode":"68144",
    "addr:street":"C St",
    "iso:country":"US",
    "sg:address":"13221 C St",
    "sg:city":"Omaha",
    "sg:classifiers":[
        {
            "category":"Shopping",
            "type":"Retail Goods"
        }
    ],
    "sg:phone":"+1 402 334 3485",
    "sg:postcode":"68144",
    "sg:province":"NE",
    "sg:tags":[
        "cards",
        "sport",
        "baseball",
        "memorabilia"
    ],
    "wof:name":"Casey's Sports Cards/Collectbl",
    "wof:placetype":"venue"
},
  "geometry": {"coordinates":[-96.12761500000001,41.222407],"type":"Point"}
}