{
  "type": "Feature",
  "properties": {
    "addr:full":"1111 10th Ave Nebraska City NE 68410",
    "addr:housenumber":"1111",
    "addr:postcode":"68410",
    "addr:street":"10Th Ave",
    "iso:country":"US",
    "sg:address":"1111 10th Ave",
    "sg:city":"Nebraska City",
    "sg:classifiers":[
        {
            "category":"Building & Trades",
            "subcategory":"Construction",
            "type":"Services"
        }
    ],
    "sg:phone":"+1 402 873 6293",
    "sg:postcode":"68410",
    "sg:province":"NE",
    "sg:tags":[
        "general",
        "contractor"
    ],
    "wof:name":"Viox Construction",
    "wof:placetype":"venue"
},
  "geometry": {"coordinates":[-95.859928,40.68591],"type":"Point"}
}