{
  "type": "Feature",
  "properties": {
    "iso:country":"US",
    "sg:address":"504 Galvin Rd S",
    "sg:city":"Bellevue",
    "sg:classifiers":[
        {
            "category":"Food & Beverages",
            "subcategory":"Bakery",
            "type":"Retail Goods"
        }
    ],
    "sg:phone":"+1 402 292 4825",
    "sg:postcode":"68005",
    "sg:province":"NE",
    "wof:name":"Wonder Hostess Thrift Shop",
    "wof:placetype":"venue"
},
  "geometry": {"coordinates":[-95.920008,41.158383],"type":"Point"}
}