{
  "type": "Feature",
  "properties": {
    "iso:country":"US",
    "sg:address":"13740 Jefferson Cir",
    "sg:city":"Omaha",
    "sg:classifiers":[
        {
            "category":"Building & Trades",
            "subcategory":"Construction",
            "type":"Services"
        }
    ],
    "sg:phone":"+1 402 861 1880",
    "sg:postcode":"68137",
    "sg:province":"NE",
    "sg:tags":[
        "residential"
    ],
    "wof:name":"Bosworth Construction",
    "wof:placetype":"venue"
},
  "geometry": {"coordinates":[-96.127278,41.196772],"type":"Point"}
}