{
  "type": "Feature",
  "properties": {
    "addr:full":"2525 N 33rd St Lincoln NE 68504",
    "addr:housenumber":"2525",
    "addr:postcode":"68504",
    "addr:street":"N 33Rd St",
    "iso:country":"US",
    "sg:address":"2525 N 33rd St",
    "sg:city":"Lincoln",
    "sg:classifiers":[
        {
            "category":"Building & Trades",
            "subcategory":"Construction",
            "type":"Services"
        }
    ],
    "sg:phone":"+1 402 464 2525",
    "sg:postcode":"68504",
    "sg:province":"NE",
    "sg:tags":[
        "material",
        "laying",
        "floor",
        "contractor"
    ],
    "wof:name":"Supreme Surface Counter Tops",
    "wof:placetype":"venue"
},
  "geometry": {"coordinates":[-96.67288499999999,40.837993],"type":"Point"}
}