{
  "type": "Feature",
  "properties": {
    "iso:country":"US",
    "sg:address":"290006 Main Rd",
    "sg:city":"Minatare",
    "sg:classifiers":[
        {
            "category":"Mining & Drilling",
            "type":"Manufacturing & Wholesale Goods"
        }
    ],
    "sg:phone":"+1 308 783 2288",
    "sg:postcode":"69356",
    "sg:province":"NE",
    "sg:tags":[
        "field"
    ],
    "wof:name":"Edward L Ehrhart",
    "wof:placetype":"venue"
},
  "geometry": {"coordinates":[-103.508771,41.923284],"type":"Point"}
}