{
  "type": "Feature",
  "properties": {
    "iso:country":"US",
    "sg:address":"5610 Seward Ave",
    "sg:city":"Lincoln",
    "sg:classifiers":[
        {
            "category":"Social Services",
            "type":"Services"
        }
    ],
    "sg:phone":"+1 402 467 1010",
    "sg:postcode":"68507",
    "sg:province":"NE",
    "sg:tags":[
        "business",
        "association"
    ],
    "wof:name":"Junior Achievement of Lincoln",
    "wof:placetype":"venue"
},
  "geometry": {"coordinates":[-96.642915,40.851838],"type":"Point"}
}