{
  "type": "Feature",
  "properties": {
    "iso:country":"US",
    "sg:address":"636 S Shady Bend Rd",
    "sg:city":"Grand Island",
    "sg:classifiers":[
        {
            "category":"Education",
            "subcategory":"School",
            "type":"Public Place"
        }
    ],
    "sg:phone":"+1 308 384 1480",
    "sg:postcode":"68801",
    "sg:province":"NE",
    "wof:name":"Seventh-Day Adventist School",
    "wof:placetype":"venue"
},
  "geometry": {"coordinates":[-98.30172399999999,40.918427],"type":"Point"}
}