{
  "type": "Feature",
  "properties": {
    "iso:country":"US",
    "sg:address":"815 Morrison Rd",
    "sg:city":"Gering",
    "sg:classifiers":[
        {
            "category":"Restaurant",
            "type":"Food & Drink"
        }
    ],
    "sg:phone":"+1 308 436 5766",
    "sg:postcode":"69341",
    "sg:province":"NE",
    "sg:tags":[
        "cafeteria"
    ],
    "wof:name":"Feedbunk Cafe",
    "wof:placetype":"venue"
},
  "geometry": {"coordinates":[-103.656795,41.834055],"type":"Point"}
}