{
  "type": "Feature",
  "properties": {
    "addr:full":"Eppley Airfield 4501 Abbott Drive Omaha NE 68110",
    "addr:housenumber":"4501",
    "addr:postcode":"68110",
    "addr:street":"Abbott Drive",
    "iso:country":"US",
    "sg:address":"Eppley Airfield 4501 Abbott Drive",
    "sg:city":"Omaha",
    "sg:classifiers":[
        {
            "category":"Coffee & Tea",
            "type":"Food & Drink"
        }
    ],
    "sg:postcode":"68110",
    "sg:province":"NE",
    "sg:website":"www.scooterscoffeehouse.com",
    "wof:name":"Scooter's Coffeehouse",
    "wof:placetype":"venue"
},
  "geometry": {"coordinates":[-95.90146,41.300153],"type":"Point"}
}