{
  "type": "Feature",
  "properties": {
    "iso:country":"US",
    "sg:address":"117 Guthrie St",
    "sg:city":"Broadwater",
    "sg:classifiers":[
        {
            "category":"Food & Beverages",
            "subcategory":"Groceries & Convenience Stores",
            "type":"Retail Goods"
        }
    ],
    "sg:phone":"+1 308 489 0100",
    "sg:postcode":"69125",
    "sg:province":"NE",
    "wof:name":"Broadwater Country Store",
    "wof:placetype":"venue"
},
  "geometry": {"coordinates":[-102.853675,41.596159],"type":"Point"}
}