{
  "type": "Feature",
  "properties": {
    "iso:country":"US",
    "sg:address":"1801 Saint Marys Ave",
    "sg:city":"Omaha",
    "sg:classifiers":[
        {
            "category":"Real Estate",
            "subcategory":"Real Estate Services",
            "type":"Services"
        }
    ],
    "sg:phone":"+1 402 341 8400",
    "sg:postcode":"68102",
    "sg:province":"NE",
    "sg:tags":[
        "company",
        "abstract",
        "title"
    ],
    "wof:name":"Dakota Title & Escrow Co Inc",
    "wof:placetype":"venue"
},
  "geometry": {"coordinates":[-95.940896,41.254715],"type":"Point"}
}