{
  "type": "Feature",
  "properties": {
    "iso:country":"US",
    "sg:address":"1621 Stone St",
    "sg:city":"Falls City",
    "sg:classifiers":[
        {
            "category":"Professional",
            "subcategory":"Accounting & Tax Preparation",
            "type":"Services"
        }
    ],
    "sg:phone":"+1 402 245 5566",
    "sg:postcode":"68355",
    "sg:province":"NE",
    "sg:tags":[
        "accountant"
    ],
    "wof:name":"Robert W Aitken PC",
    "wof:placetype":"venue"
},
  "geometry": {"coordinates":[-95.60296700000001,40.061509],"type":"Point"}
}