{
  "type": "Feature",
  "properties": {
    "iso:country":"US",
    "sg:address":"2130 S 17th St",
    "sg:city":"Lincoln",
    "sg:classifiers":[
        {
            "category":"Shopping",
            "type":"Retail Goods"
        }
    ],
    "sg:phone":"+1 402 438 4340",
    "sg:postcode":"68502",
    "sg:province":"NE",
    "sg:tags":[
        "orthopedic",
        "appliance",
        "merchandise"
    ],
    "wof:name":"Family Orthotics & Prosthetics",
    "wof:placetype":"venue"
},
  "geometry": {"coordinates":[-96.69674500000001,40.791697],"type":"Point"}
}