{
  "type": "Feature",
  "properties": {
    "iso:country":"US",
    "sg:address":"49 Sonja Dr",
    "sg:city":"Doniphan",
    "sg:classifiers":[
        {
            "category":"Professional",
            "subcategory":"Advertising",
            "type":"Services"
        }
    ],
    "sg:phone":"+1 402 845 2040",
    "sg:postcode":"68832",
    "sg:province":"NE",
    "sg:tags":[
        "counselor"
    ],
    "wof:name":"Jeanne Gunther Design & Advg",
    "wof:placetype":"venue"
},
  "geometry": {"coordinates":[-98.397959,40.77873],"type":"Point"}
}