{
  "type": "Feature",
  "properties": {
    "iso:country":"US",
    "sg:address":"309 Saline St",
    "sg:city":"Bruning",
    "sg:classifiers":[
        {
            "category":"Building & Trades",
            "subcategory":"Construction",
            "type":"Services"
        }
    ],
    "sg:phone":"+1 402 353 4975",
    "sg:postcode":"68322",
    "sg:province":"NE",
    "sg:tags":[
        "general",
        "contractor"
    ],
    "wof:name":"Krest Contractors",
    "wof:placetype":"venue"
},
  "geometry": {"coordinates":[-97.56285200000001,40.333819],"type":"Point"}
}