{
  "type": "Feature",
  "properties": {
    "iso:country":"US",
    "sg:address":"2430 Rd 8",
    "sg:city":"Clarkson",
    "sg:classifiers":[
        {
            "category":"Shopping",
            "subcategory":"Gifts & Souvenirs",
            "type":"Retail Goods"
        }
    ],
    "sg:phone":"+1 402 892 9871",
    "sg:postcode":"68629",
    "sg:province":"NE",
    "sg:tags":[
        "shop"
    ],
    "wof:name":"Myrrhwood Farm-Little Splash",
    "wof:placetype":"venue"
},
  "geometry": {"coordinates":[-97.116282,41.730647],"type":"Point"}
}