{
  "type": "Feature",
  "properties": {
    "addr:full":"10365 Pacific St Omaha NE 68114",
    "addr:housenumber":"10365",
    "addr:postcode":"68114",
    "addr:street":"Pacific St",
    "iso:country":"US",
    "sg:address":"10365 Pacific St",
    "sg:city":"Omaha",
    "sg:classifiers":[
        {
            "category":"Shopping",
            "subcategory":"Clothing, Apparel, & Fashions",
            "type":"Retail Goods"
        }
    ],
    "sg:phone":"+1 402 293 2881",
    "sg:postcode":"68114",
    "sg:province":"NE",
    "sg:tags":[
        "infant",
        "wear"
    ],
    "wof:name":"Gap Kids",
    "wof:placetype":"venue"
},
  "geometry": {"coordinates":[-96.075631,41.248685],"type":"Point"}
}