{
  "type": "Feature",
  "properties": {
    "addr:full":"903 Prospect Dr North Platte NE 69101",
    "addr:housenumber":"903",
    "addr:postcode":"69101",
    "addr:street":"Prospect Dr",
    "iso:country":"US",
    "sg:address":"903 Prospect Dr",
    "sg:city":"North Platte",
    "sg:classifiers":[
        {
            "category":"Wholesale",
            "subcategory":"Vending Machines",
            "type":"Manufacturing & Wholesale Goods"
        }
    ],
    "sg:phone":"+1 308 534 6008",
    "sg:postcode":"69101",
    "sg:province":"NE",
    "wof:name":"Great Plains Vending",
    "wof:placetype":"venue"
},
  "geometry": {"coordinates":[-100.73624700000001,41.126108],"type":"Point"}
}