{
  "type": "Feature",
  "properties": {
    "iso:country":"US",
    "sg:address":"235 S 70th St",
    "sg:city":"Lincoln",
    "sg:classifiers":[
        {
            "category":"Personal",
            "type":"Services"
        }
    ],
    "sg:phone":"+1 402 483 7373",
    "sg:postcode":"68510",
    "sg:province":"NE",
    "sg:tags":[
        "credit",
        "debt",
        "counseling"
    ],
    "wof:name":"Primerica",
    "wof:placetype":"venue"
},
  "geometry": {"coordinates":[-96.625252,40.811056],"type":"Point"}
}