{
  "type": "Feature",
  "properties": {
    "iso:country":"US",
    "sg:address":"2906 Co Rd 15",
    "sg:city":"Cedar Bluffs",
    "sg:classifiers":[
        {
            "category":"Social Services",
            "type":"Services"
        }
    ],
    "sg:phone":"+1 402 628 8148",
    "sg:postcode":"68015",
    "sg:province":"NE",
    "sg:tags":[
        "youth",
        "organization",
        "center"
    ],
    "wof:name":"Boy Scouts Of America The Hut",
    "wof:placetype":"venue"
},
  "geometry": {"coordinates":[-96.567199,41.427647],"type":"Point"}
}