{
  "type": "Feature",
  "properties": {
    "iso:country":"US",
    "sg:address":"15005 Q St",
    "sg:city":"Omaha",
    "sg:classifiers":[
        {
            "category":"Organizations",
            "subcategory":"Religious Organization",
            "type":"Services"
        }
    ],
    "sg:phone":"+1 402 895 1500",
    "sg:postcode":"68137",
    "sg:province":"NE",
    "sg:tags":[
        "church"
    ],
    "wof:name":"Divine Shepherd Lutheran",
    "wof:placetype":"venue"
},
  "geometry": {"coordinates":[-96.14749999999999,41.205274],"type":"Point"}
}