{
  "type": "Feature",
  "properties": {
    "addr:full":"205 E 7th St Lexington NE 68850",
    "addr:housenumber":"205",
    "addr:postcode":"68850",
    "addr:street":"E 7Th St",
    "iso:country":"US",
    "sg:address":"205 E 7th St",
    "sg:city":"Lexington",
    "sg:classifiers":[
        {
            "category":"Social Services",
            "subcategory":"Adult Care",
            "type":"Services"
        }
    ],
    "sg:phone":"+1 308 324 2428",
    "sg:postcode":"68850",
    "sg:province":"NE",
    "sg:tags":[
        "organization",
        "senior",
        "citizen"
    ],
    "wof:name":"Chore Services Inc",
    "wof:placetype":"venue"
},
  "geometry": {"coordinates":[-99.740101,40.779926],"type":"Point"}
}