{
  "type": "Feature",
  "properties": {
    "addr:full":"4021 Ave B Scottsbluff NE 69361",
    "addr:housenumber":"4021",
    "addr:postcode":"69361",
    "addr:street":"Ave B",
    "iso:country":"US",
    "sg:address":"4021 Ave B",
    "sg:city":"Scottsbluff",
    "sg:classifiers":[
        {
            "category":"Health Services",
            "subcategory":"Medical Lab",
            "type":"Services"
        }
    ],
    "sg:phone":"+1 308 635 1360",
    "sg:postcode":"69361",
    "sg:province":"NE",
    "sg:tags":[
        "laboratory",
        "testing"
    ],
    "wof:name":"Laboratory Corporation America",
    "wof:placetype":"venue"
},
  "geometry": {"coordinates":[-103.66574799999999,41.886947],"type":"Point"}
}