{
  "type": "Feature",
  "properties": {
    "addr:full":"9817 Rock Creek Rd Plattsmouth NE 68048",
    "addr:housenumber":"9817",
    "addr:postcode":"68048",
    "addr:street":"Rock Creek Rd",
    "iso:country":"US",
    "sg:address":"9817 Rock Creek Rd",
    "sg:city":"Plattsmouth",
    "sg:classifiers":[
        {
            "category":"Manufacturing",
            "subcategory":"Printing",
            "type":"Manufacturing & Wholesale Goods"
        }
    ],
    "sg:phone":"+1 402 298 8001",
    "sg:postcode":"68048",
    "sg:province":"NE",
    "sg:tags":[
        "newspaper"
    ],
    "wof:name":"Cassgram",
    "wof:placetype":"venue"
},
  "geometry": {"coordinates":[-95.89196099999999,40.93196],"type":"Point"}
}