{
  "type": "Feature",
  "properties": {
    "iso:country":"US",
    "sg:address":"112 el Camino Dr",
    "sg:city":"Norfolk",
    "sg:classifiers":[
        {
            "category":"Personal",
            "subcategory":"Beauty Salon",
            "type":"Services"
        }
    ],
    "sg:phone":"+1 402 439 2060",
    "sg:postcode":"68701",
    "sg:province":"NE",
    "wof:name":"Mary Ann's Beauty Shop",
    "wof:placetype":"venue"
},
  "geometry": {"coordinates":[-97.374077,42.037288],"type":"Point"}
}