{
  "type": "Feature",
  "properties": {
    "addr:full":"10476 W Husker Hwy Wood River NE 68883",
    "addr:housenumber":"10476",
    "addr:postcode":"68883",
    "addr:street":"W Husker Hwy",
    "iso:country":"US",
    "sg:address":"10476 W Husker Hwy",
    "sg:city":"Wood River",
    "sg:classifiers":[
        {
            "category":"Real Estate",
            "subcategory":"Real Estate Operator",
            "type":"Services"
        }
    ],
    "sg:phone":"+1 308 226 2235",
    "sg:postcode":"68883",
    "sg:province":"NE",
    "sg:tags":[
        "property",
        "lessor"
    ],
    "wof:name":"Scott Mc Afee",
    "wof:placetype":"venue"
},
  "geometry": {"coordinates":[-98.540586,40.887915],"type":"Point"}
}