{
  "type": "Feature",
  "properties": {
    "iso:country":"US",
    "sg:address":"241 N 23rd St",
    "sg:city":"Blair",
    "sg:classifiers":[
        {
            "category":"Banks & Credit Unions",
            "subcategory":"Financial Services",
            "type":"Services"
        }
    ],
    "sg:phone":"+1 402 426 2832",
    "sg:postcode":"68008",
    "sg:province":"NE",
    "sg:tags":[
        "trust",
        "management"
    ],
    "wof:name":"Kay J Erwin Living Trust",
    "wof:placetype":"venue"
},
  "geometry": {"coordinates":[-96.14746100000001,41.54569],"type":"Point"}
}