{
  "type": "Feature",
  "properties": {
    "addr:full":"3020 18th St Columbus NE 68601",
    "addr:housenumber":"3020",
    "addr:postcode":"68601",
    "addr:street":"18Th St",
    "iso:country":"US",
    "sg:address":"3020 18th St",
    "sg:city":"Columbus",
    "sg:classifiers":[
        {
            "category":"Organizations",
            "subcategory":"Non-profit Organization",
            "type":"Services"
        }
    ],
    "sg:phone":"+1 402 563 1699",
    "sg:postcode":"68601",
    "sg:province":"NE",
    "sg:tags":[
        "disability"
    ],
    "wof:name":"Association-Retarded Citizens",
    "wof:placetype":"venue"
},
  "geometry": {"coordinates":[-97.365134,41.434354],"type":"Point"}
}