{
  "type": "Feature",
  "properties": {
    "iso:country":"US",
    "sg:address":"4900 Elk Ridge Rd",
    "sg:city":"Lincoln",
    "sg:classifiers":[
        {
            "category":"Shopping",
            "type":"Retail Goods"
        }
    ],
    "sg:phone":"+1 402 421 4643",
    "sg:postcode":"68516",
    "sg:province":"NE",
    "sg:tags":[
        "merchandise"
    ],
    "wof:name":"Sheng WEI Medical Equipment",
    "wof:placetype":"venue"
},
  "geometry": {"coordinates":[-96.64967900000001,40.741395],"type":"Point"}
}