{
  "type": "Feature",
  "properties": {
    "iso:country":"US",
    "sg:address":"2531 Country Club Ave",
    "sg:city":"Omaha",
    "sg:classifiers":[
        {
            "category":"Shopping",
            "subcategory":"Gifts & Souvenirs",
            "type":"Retail Goods"
        }
    ],
    "sg:phone":"+1 402 553 1539",
    "sg:postcode":"68104",
    "sg:province":"NE",
    "wof:name":"Wow Antiques",
    "wof:placetype":"venue"
},
  "geometry": {"coordinates":[-95.99735099999999,41.282932],"type":"Point"}
}