{
  "type": "Feature",
  "properties": {
    "iso:country":"US",
    "sg:address":"3827 Lake St",
    "sg:city":"Omaha",
    "sg:classifiers":[
        {
            "category":"Manufacturing",
            "subcategory":"Building Materials",
            "type":"Manufacturing & Wholesale Goods"
        }
    ],
    "sg:phone":"+1 402 556 4600",
    "sg:postcode":"68111",
    "sg:province":"NE",
    "sg:tags":[
        "mfg",
        "casework",
        "fabricated",
        "laminated",
        "plastic"
    ],
    "wof:name":"Western Laminates Inc",
    "wof:placetype":"venue"
},
  "geometry": {"coordinates":[-95.97211299999999,41.281335],"type":"Point"}
}