{
  "type": "Feature",
  "properties": {
    "iso:country":"US",
    "sg:address":"6450 O St",
    "sg:city":"Lincoln",
    "sg:classifiers":[
        {
            "category":"Shopping",
            "subcategory":"Shoes",
            "type":"Retail Goods"
        }
    ],
    "sg:phone":"+1 402 466 7463",
    "sg:postcode":"68510",
    "sg:province":"NE",
    "wof:name":"Comfort Plus Shoe Ctr",
    "wof:placetype":"venue"
},
  "geometry": {"coordinates":[-96.634463,40.813512],"type":"Point"}
}