{
  "type": "Feature",
  "properties": {
    "iso:country":"US",
    "sg:address":"310 S 5th St",
    "sg:city":"Columbus",
    "sg:classifiers":[
        {
            "category":"Sports & Exercise",
            "subcategory":"Golf",
            "type":"Entertainment"
        },
        {
            "category":"Retail",
            "subcategory":"Repair Shop",
            "type":"Services"
        }
    ],
    "sg:phone":"+1 402 564 1313",
    "sg:postcode":"68601",
    "sg:province":"NE",
    "sg:tags":[
        "course",
        "refinishing",
        "equipment"
    ],
    "sg:website":"www.quailrungolf.com",
    "wof:name":"Quail Run Golf Course",
    "wof:placetype":"venue"
},
  "geometry": {"coordinates":[-97.330162,41.412976],"type":"Point"}
}