{
  "type": "Feature",
  "properties": {
    "addr:full":"1710 W 42nd St Kearney NE 68845",
    "addr:housenumber":"1710",
    "addr:postcode":"68845",
    "addr:street":"W 42Nd St",
    "iso:country":"US",
    "sg:address":"1710 W 42nd St",
    "sg:city":"Kearney",
    "sg:classifiers":[
        {
            "category":"Manufacturing",
            "subcategory":"Electronics",
            "type":"Manufacturing & Wholesale Goods"
        }
    ],
    "sg:phone":"+1 308 234 4136",
    "sg:postcode":"68845",
    "sg:province":"NE",
    "sg:tags":[
        "mfg",
        "equipment",
        "contractor",
        "electrical",
        "home"
    ],
    "wof:name":"T D L Sound",
    "wof:placetype":"venue"
},
  "geometry": {"coordinates":[-99.1031,40.717043],"type":"Point"}
}