{
  "type": "Feature",
  "properties": {
    "addr:full":"741 S D St Broken Bow NE 68822",
    "addr:housenumber":"741",
    "addr:postcode":"68822",
    "addr:street":"S D St",
    "iso:country":"US",
    "sg:address":"741 S D St",
    "sg:city":"Broken Bow",
    "sg:classifiers":[
        {
            "category":"Government",
            "subcategory":"Post Office",
            "type":"Public Place"
        }
    ],
    "sg:phone":"+1 308 872 2211",
    "sg:postcode":"68822",
    "sg:province":"NE",
    "wof:name":"US Post Office",
    "wof:placetype":"venue"
},
  "geometry": {"coordinates":[-99.639043,41.402742],"type":"Point"}
}