{
  "type": "Feature",
  "properties": {
    "addr:full":"107 W Plum St Doniphan NE 68832",
    "addr:housenumber":"107",
    "addr:postcode":"68832",
    "addr:street":"W Plum St",
    "iso:country":"US",
    "sg:address":"107 W Plum St",
    "sg:city":"Doniphan",
    "sg:classifiers":[
        {
            "category":"Professional",
            "subcategory":"Accounting & Tax Preparation",
            "type":"Services"
        }
    ],
    "sg:phone":"+1 402 845 2288",
    "sg:postcode":"68832",
    "sg:province":"NE",
    "sg:tags":[
        "return",
        "filing"
    ],
    "wof:name":"Ray Scholl & Assoc",
    "wof:placetype":"venue"
},
  "geometry": {"coordinates":[-98.370892,40.771961],"type":"Point"}
}