{
  "type": "Feature",
  "properties": {
    "iso:country":"US",
    "sg:address":"241 S 12 Rd",
    "sg:city":"Mitchell",
    "sg:classifiers":[
        {
            "category":"Farming",
            "subcategory":"Farm",
            "type":"Manufacturing & Wholesale Goods"
        }
    ],
    "sg:phone":"+1 308 247 2857",
    "sg:postcode":"69357",
    "sg:province":"NE",
    "sg:tags":[
        "crop",
        "general"
    ],
    "wof:name":"Thomas Family Farms Inc",
    "wof:placetype":"venue"
},
  "geometry": {"coordinates":[-103.853421,42.020241],"type":"Point"}
}