{
  "type": "Feature",
  "properties": {
    "addr:full":"301 Eastridge Dr Lincoln NE 68510",
    "addr:housenumber":"301",
    "addr:postcode":"68510",
    "addr:street":"Eastridge Dr",
    "iso:country":"US",
    "sg:address":"301 Eastridge Dr",
    "sg:city":"Lincoln",
    "sg:classifiers":[
        {
            "category":"Professional",
            "subcategory":"Business Services",
            "type":"Services"
        }
    ],
    "sg:phone":"+1 402 489 9395",
    "sg:postcode":"68510",
    "sg:province":"NE",
    "wof:name":"Stehlik Brothers",
    "wof:placetype":"venue"
},
  "geometry": {"coordinates":[-96.639174,40.811296],"type":"Point"}
}