{
  "type": "Feature",
  "properties": {
    "addr:full":"321 Commercial St Stromsburg NE 68666",
    "addr:housenumber":"321",
    "addr:postcode":"68666",
    "addr:street":"Commercial St",
    "iso:country":"US",
    "sg:address":"321 Commercial St",
    "sg:city":"Stromsburg",
    "sg:classifiers":[
        {
            "category":"Coffee & Tea",
            "type":"Food & Drink"
        },
        {
            "category":"Bakery",
            "type":"Food & Drink"
        },
        {
            "category":"Donuts",
            "type":"Food & Drink"
        }
    ],
    "sg:menulink":"http://www.allmenus.com/ne/west-stromsburg/231057-daylight-donuts/menu/",
    "sg:phone":"+1 402 764 2176",
    "sg:postcode":"68666",
    "sg:province":"NE",
    "sg:tags":[
        "american",
        "pastry"
    ],
    "wof:name":"Daylight Donuts",
    "wof:placetype":"venue"
},
  "geometry": {"coordinates":[-97.596979,41.113267],"type":"Point"}
}