{
  "type": "Feature",
  "properties": {
    "addr:full":"1925 23rd St Columbus NE 68601",
    "addr:housenumber":"1925",
    "addr:postcode":"68601",
    "addr:street":"23Rd St",
    "iso:country":"US",
    "sg:address":"1925 23rd St",
    "sg:city":"Columbus",
    "sg:classifiers":[
        {
            "category":"Restaurant",
            "type":"Food & Drink"
        }
    ],
    "sg:menulink":"http://www.allmenus.com/ne/columbus/129482-subway/menu/",
    "sg:phone":"+1 402 563 2705",
    "sg:postcode":"68601",
    "sg:province":"NE",
    "sg:tags":[
        "american",
        "sandwich"
    ],
    "wof:name":"Subway",
    "wof:placetype":"venue"
},
  "geometry": {"coordinates":[-97.350633,41.43854],"type":"Point"}
}