{
  "type": "Feature",
  "properties": {
    "iso:country":"US",
    "sg:address":"354 N Commercial Ave",
    "sg:city":"Superior",
    "sg:classifiers":[
        {
            "category":"Real Estate",
            "subcategory":"Real Estate Services",
            "type":"Services"
        }
    ],
    "sg:phone":"+1 402 879 4341",
    "sg:postcode":"68978",
    "sg:province":"NE",
    "sg:tags":[
        "company",
        "title"
    ],
    "wof:name":"Benchmark Title Co",
    "wof:placetype":"venue"
},
  "geometry": {"coordinates":[-98.069973,40.019329],"type":"Point"}
}