{
  "type": "Feature",
  "properties": {
    "addr:full":"15418 W Center Rd Omaha NE 68144",
    "addr:housenumber":"15418",
    "addr:postcode":"68144",
    "addr:street":"W Center Rd",
    "iso:country":"US",
    "sg:address":"15418 W Center Rd",
    "sg:city":"Omaha",
    "sg:classifiers":[
        {
            "category":"Home & Garden",
            "subcategory":"Building Materials",
            "type":"Retail Goods"
        }
    ],
    "sg:phone":"+1 402 333 3250",
    "sg:postcode":"68144",
    "sg:province":"NE",
    "sg:tags":[
        "paint"
    ],
    "wof:name":"Diamond Vogel Paints",
    "wof:placetype":"venue"
},
  "geometry": {"coordinates":[-96.154268,41.233581],"type":"Point"}
}