{
  "type": "Feature",
  "properties": {
    "addr:full":"112 W Hudspith St Valley NE 68064",
    "addr:housenumber":"112",
    "addr:postcode":"68064",
    "addr:street":"W Hudspith St",
    "iso:country":"US",
    "sg:address":"112 W Hudspith St",
    "sg:city":"Valley",
    "sg:classifiers":[
        {
            "category":"Professional",
            "type":"Services"
        }
    ],
    "sg:phone":"+1 402 359 4197",
    "sg:postcode":"68064",
    "sg:province":"NE",
    "wof:name":"Mm Service",
    "wof:placetype":"venue"
},
  "geometry": {"coordinates":[-96.347483,41.308131],"type":"Point"}
}