{
  "type": "Feature",
  "properties": {
    "iso:country":"US",
    "sg:address":"1511 Center Park Rd",
    "sg:city":"Lincoln",
    "sg:classifiers":[
        {
            "category":"Travel",
            "subcategory":"Hotels & Motels",
            "type":"Entertainment"
        },
        {
            "category":"Retail",
            "subcategory":"Event Space",
            "type":"Services"
        },
        {
            "category":"Conference Center",
            "type":"Public Place"
        }
    ],
    "sg:phone":"+1 402 423 3131",
    "sg:postcode":"68512",
    "sg:province":"NE",
    "sg:tags":[
        "facility",
        "convention",
        "banquet",
        "reception",
        "lodging",
        "hall"
    ],
    "sg:website":"http://www.ramada.com/hotel/11284&cid=RANE",
    "wof:name":"Ramada Limited South Lincoln",
    "wof:placetype":"venue"
},
  "geometry": {"coordinates":[-96.699665,40.765871],"type":"Point"}
}