{
  "type": "Feature",
  "properties": {
    "iso:country":"US",
    "sg:address":"1541 Duke Dr",
    "sg:city":"York",
    "sg:classifiers":[
        {
            "category":"Social Services",
            "subcategory":"Child Care",
            "type":"Services"
        }
    ],
    "sg:phone":"+1 402 362 5852",
    "sg:postcode":"68467",
    "sg:province":"NE",
    "sg:tags":[
        "day"
    ],
    "wof:name":"Little Friends Preschool",
    "wof:placetype":"venue"
},
  "geometry": {"coordinates":[-97.57668200000001,40.876188],"type":"Point"}
}