{
  "type": "Feature",
  "properties": {
    "addr:full":"807 N 50th St Omaha NE 68132",
    "addr:housenumber":"807",
    "addr:postcode":"68132",
    "addr:street":"N 50Th St",
    "iso:country":"US",
    "sg:address":"807 N 50th St",
    "sg:city":"Omaha",
    "sg:classifiers":[
        {
            "category":"Shopping",
            "subcategory":"Jewelry",
            "type":"Retail Goods"
        }
    ],
    "sg:phone":"+1 402 991 3055",
    "sg:postcode":"68132",
    "sg:province":"NE",
    "sg:tags":[
        "jeweler"
    ],
    "wof:name":"Vawter Jewelry",
    "wof:placetype":"venue"
},
  "geometry": {"coordinates":[-95.990224,41.267759],"type":"Point"}
}