{
  "type": "Feature",
  "properties": {
    "iso:country":"US",
    "sg:address":"14230 Hillsdale Cir",
    "sg:city":"Omaha",
    "sg:classifiers":[
        {
            "category":"Building & Trades",
            "subcategory":"Plumbing",
            "type":"Services"
        }
    ],
    "sg:phone":"+1 402 861 0681",
    "sg:postcode":"68137",
    "sg:province":"NE",
    "sg:tags":[
        "contractor",
        "mechanical"
    ],
    "wof:name":"Midwest Mechanical Contractors",
    "wof:placetype":"venue"
},
  "geometry": {"coordinates":[-96.137151,41.215205],"type":"Point"}
}