{
  "type": "Feature",
  "properties": {
    "iso:country":"US",
    "sg:address":"315 S Maple St",
    "sg:city":"Nelson",
    "sg:classifiers":[
        {
            "category":"Bars & Pubs",
            "type":"Food & Drink"
        }
    ],
    "sg:phone":"+1 402 225 4106",
    "sg:postcode":"68961",
    "sg:province":"NE",
    "wof:name":"Saloon",
    "wof:placetype":"venue"
},
  "geometry": {"coordinates":[-98.07132900000001,40.201804],"type":"Point"}
}