{
  "type": "Feature",
  "properties": {
    "iso:country":"US",
    "sg:address":"1246 Main Ave",
    "sg:city":"Crete",
    "sg:classifiers":[
        {
            "category":"Shopping",
            "subcategory":"Stationery & Office Supplies",
            "type":"Retail Goods"
        }
    ],
    "sg:phone":"+1 402 826 4545",
    "sg:postcode":"68333",
    "sg:province":"NE",
    "wof:name":"Gallery",
    "wof:placetype":"venue"
},
  "geometry": {"coordinates":[-96.96143499999999,40.624794],"type":"Point"}
}