{
  "type": "Feature",
  "properties": {
    "addr:full":"605 Howard Ave St Paul NE 68873",
    "addr:housenumber":"605",
    "addr:postcode":"68873",
    "addr:street":"Howard Ave",
    "iso:country":"US",
    "sg:address":"605 Howard Ave",
    "sg:city":"St Paul",
    "sg:classifiers":[
        {
            "category":"Restaurant",
            "type":"Food & Drink"
        }
    ],
    "sg:phone":"+1 308 754 4900",
    "sg:postcode":"68873",
    "sg:province":"NE",
    "sg:tags":[
        "eating"
    ],
    "wof:name":"Sweet Shoppe",
    "wof:placetype":"venue"
},
  "geometry": {"coordinates":[-98.45805799999999,41.213306],"type":"Point"}
}