{
  "type": "Feature",
  "properties": {
    "addr:full":"17103 Harney St Omaha NE 68118",
    "addr:housenumber":"17103",
    "addr:postcode":"68118",
    "addr:street":"Harney St",
    "iso:country":"US",
    "sg:address":"17103 Harney St",
    "sg:city":"Omaha",
    "sg:classifiers":[
        {
            "category":"Professional",
            "subcategory":"Management & Consulting",
            "type":"Services"
        }
    ],
    "sg:phone":"+1 402 502 9504",
    "sg:postcode":"68118",
    "sg:province":"NE",
    "sg:tags":[
        "merchant",
        "credit",
        "cards"
    ],
    "wof:name":"Strategic Management Partners",
    "wof:placetype":"venue"
},
  "geometry": {"coordinates":[-96.180086,41.25679],"type":"Point"}
}