{
  "type": "Feature",
  "properties": {
    "iso:country":"US",
    "sg:address":"719 S 75th St",
    "sg:city":"Omaha",
    "sg:classifiers":[
        {
            "category":"Professional",
            "subcategory":"Management & Consulting",
            "type":"Services"
        }
    ],
    "sg:phone":"+1 402 392 1420",
    "sg:postcode":"68114",
    "sg:province":"NE",
    "sg:tags":[
        "consultant",
        "business"
    ],
    "wof:name":"Charles Trimble Co",
    "wof:placetype":"venue"
},
  "geometry": {"coordinates":[-96.029335,41.248904],"type":"Point"}
}