{
  "type": "Feature",
  "properties": {
    "iso:country":"US",
    "sg:address":"6800 Pine Lake Rd",
    "sg:city":"Lincoln",
    "sg:classifiers":[
        {
            "category":"Organizations",
            "subcategory":"Religious Organization",
            "type":"Services"
        }
    ],
    "sg:phone":"+1 402 420 2144",
    "sg:postcode":"68516",
    "sg:province":"NE",
    "sg:tags":[
        "church"
    ],
    "wof:name":"Lincoln Spanish Kingdom Hall",
    "wof:placetype":"venue"
},
  "geometry": {"coordinates":[-96.625353,40.740879],"type":"Point"}
}