{
  "type": "Feature",
  "properties": {
    "addr:full":"2402 3rd Ave Scottsbluff NE 69361",
    "addr:housenumber":"2402",
    "addr:postcode":"69361",
    "addr:street":"3Rd Ave",
    "iso:country":"US",
    "sg:address":"2402 3rd Ave",
    "sg:city":"Scottsbluff",
    "sg:classifiers":[
        {
            "category":"Real Estate",
            "subcategory":"Real Estate Operator",
            "type":"Services"
        }
    ],
    "sg:phone":"+1 308 632 6508",
    "sg:postcode":"69361",
    "sg:province":"NE",
    "sg:tags":[
        "property",
        "lessor"
    ],
    "wof:name":"Catherine Dalton",
    "wof:placetype":"venue"
},
  "geometry": {"coordinates":[-103.658754,41.87254],"type":"Point"}
}