{
  "type": "Feature",
  "properties": {
    "addr:full":"102 State Hwy 23 Grant NE 69170",
    "addr:housenumber":"102",
    "addr:postcode":"69170",
    "addr:street":"State Hwy 23",
    "iso:country":"US",
    "sg:address":"102 State Hwy 23",
    "sg:city":"Grant",
    "sg:classifiers":[
        {
            "category":"Home & Garden",
            "subcategory":"Building Materials",
            "type":"Retail Goods"
        }
    ],
    "sg:phone":"+1 308 352 2489",
    "sg:postcode":"69170",
    "sg:province":"NE",
    "wof:name":"Innovative Building Products",
    "wof:placetype":"venue"
},
  "geometry": {"coordinates":[-100.75503399999999,40.827054],"type":"Point"}
}