{
  "type": "Feature",
  "properties": {
    "addr:full":"4710 S 57th St Lincoln NE 68516",
    "addr:housenumber":"4710",
    "addr:postcode":"68516",
    "addr:street":"S 57Th St",
    "iso:country":"US",
    "sg:address":"4710 S 57th St",
    "sg:city":"Lincoln",
    "sg:classifiers":[
        {
            "category":"Manufacturing",
            "subcategory":"Tools & Machinery",
            "type":"Manufacturing & Wholesale Goods"
        }
    ],
    "sg:phone":"+1 402 488 0113",
    "sg:postcode":"68516",
    "sg:province":"NE",
    "sg:tags":[
        "industrial",
        "mfg"
    ],
    "wof:name":"Rivers Group Inc",
    "wof:placetype":"venue"
},
  "geometry": {"coordinates":[-96.64247899999999,40.763586],"type":"Point"}
}