{
  "type": "Feature",
  "properties": {
    "iso:country":"US",
    "sg:address":"737 14th Rd",
    "sg:city":"West Point",
    "sg:classifiers":[
        {
            "category":"Farming",
            "subcategory":"Farm",
            "type":"Manufacturing & Wholesale Goods"
        }
    ],
    "sg:phone":"+1 402 372 2597",
    "sg:postcode":"68788",
    "sg:province":"NE",
    "sg:tags":[
        "crop",
        "general"
    ],
    "wof:name":"Dan Reeson",
    "wof:placetype":"venue"
},
  "geometry": {"coordinates":[-96.767966,41.836907],"type":"Point"}
}