{
  "type": "Feature",
  "properties": {
    "addr:full":"125 N Main St West Point NE 68788",
    "addr:housenumber":"125",
    "addr:postcode":"68788",
    "addr:street":"N Main St",
    "iso:country":"US",
    "sg:address":"125 N Main St",
    "sg:city":"West Point",
    "sg:classifiers":[
        {
            "category":"Shopping",
            "subcategory":"Jewelry",
            "type":"Retail Goods"
        }
    ],
    "sg:phone":"+1 402 372 2206",
    "sg:postcode":"68788",
    "sg:province":"NE",
    "sg:tags":[
        "gift",
        "store"
    ],
    "wof:name":"Yarger Diamond Center Inc",
    "wof:placetype":"venue"
},
  "geometry": {"coordinates":[-96.71222,41.84089],"type":"Point"}
}