{
  "type": "Feature",
  "properties": {
    "iso:country":"US",
    "sg:address":"1530 S 70th St",
    "sg:city":"Lincoln",
    "sg:classifiers":[
        {
            "category":"Health Services",
            "subcategory":"Doctor",
            "type":"Services"
        }
    ],
    "sg:phone":"+1 402 483 1009",
    "sg:postcode":"68506",
    "sg:province":"NE",
    "sg:tags":[
        "dentist"
    ],
    "wof:name":"Brett R Cascini DDS",
    "wof:placetype":"venue"
},
  "geometry": {"coordinates":[-96.62521700000001,40.793739],"type":"Point"}
}