{
  "type": "Feature",
  "properties": {
    "iso:country":"US",
    "sg:address":"1909 Krenzien Dr",
    "sg:city":"Norfolk",
    "sg:classifiers":[
        {
            "category":"Travel",
            "subcategory":"Hotels & Motels",
            "type":"Entertainment"
        }
    ],
    "sg:phone":"+1 402 371 7157",
    "sg:postcode":"68701",
    "sg:province":"NE",
    "wof:name":"Eco Lux Inn",
    "wof:placetype":"venue"
},
  "geometry": {"coordinates":[-97.43662999999999,42.01994],"type":"Point"}
}