{
  "type": "Feature",
  "properties": {
    "iso:country":"US",
    "sg:address":"705 E 7th St",
    "sg:city":"Hastings",
    "sg:classifiers":[
        {
            "category":"Education",
            "subcategory":"Library",
            "type":"Public Place"
        }
    ],
    "sg:phone":"+1 402 461 7330",
    "sg:postcode":"68901",
    "sg:province":"NE",
    "wof:name":"Perkins Library",
    "wof:placetype":"venue"
},
  "geometry": {"coordinates":[-98.37311,40.589883],"type":"Point"}
}