{
  "type": "Feature",
  "properties": {
    "iso:country":"US",
    "sg:address":"2320 N Custer Ave",
    "sg:city":"Grand Island",
    "sg:classifiers":[
        {
            "category":"Shopping",
            "subcategory":"Used Merchandise",
            "type":"Retail Goods"
        }
    ],
    "sg:phone":"+1 308 382 3025",
    "sg:postcode":"68803",
    "sg:province":"NE",
    "wof:name":"Jabs Antiques",
    "wof:placetype":"venue"
},
  "geometry": {"coordinates":[-98.36851,40.944337],"type":"Point"}
}