{
  "type": "Feature",
  "properties": {
    "iso:country":"US",
    "sg:address":"225 E 6th St",
    "sg:city":"Fremont",
    "sg:classifiers":[
        {
            "category":"Personal",
            "subcategory":"Beauty Salon",
            "type":"Services"
        }
    ],
    "sg:phone":"+1 402 727 6615",
    "sg:postcode":"68025",
    "sg:province":"NE",
    "sg:tags":[
        "manicuring"
    ],
    "wof:name":"Cabana Nail Spa",
    "wof:placetype":"venue"
},
  "geometry": {"coordinates":[-96.49582700000001,41.434614],"type":"Point"}
}