{
  "type": "Feature",
  "properties": {
    "iso:country":"US",
    "sg:address":"409 S Lincoln St",
    "sg:city":"West Point",
    "sg:classifiers":[
        {
            "category":"Banks & Credit Unions",
            "subcategory":"Bank",
            "type":"Services"
        }
    ],
    "sg:phone":"+1 402 372 5900",
    "sg:postcode":"68788",
    "sg:province":"NE",
    "wof:name":"Farmers & Merchants Natl Bank",
    "wof:placetype":"venue"
},
  "geometry": {"coordinates":[-96.71098000000001,41.837186],"type":"Point"}
}