{
  "type": "Feature",
  "properties": {
    "iso:country":"US",
    "sg:address":"1315 Stagecoach Rd",
    "sg:city":"Grand Island",
    "sg:classifiers":[
        {
            "category":"Farming",
            "subcategory":"Farm",
            "type":"Manufacturing & Wholesale Goods"
        }
    ],
    "sg:phone":"+1 402 854 3395",
    "sg:postcode":"68801",
    "sg:province":"NE",
    "sg:tags":[
        "general"
    ],
    "wof:name":"Kauffman Farms Inc",
    "wof:placetype":"venue"
},
  "geometry": {"coordinates":[-98.347442,40.894195],"type":"Point"}
}