{
  "type": "Feature",
  "properties": {
    "iso:country":"US",
    "sg:address":"2406 Ave I",
    "sg:city":"Scottsbluff",
    "sg:classifiers":[
        {
            "category":"Freight",
            "type":"Transportation"
        }
    ],
    "sg:phone":"+1 308 632 7617",
    "sg:postcode":"69361",
    "sg:province":"NE",
    "sg:tags":[
        "commercial",
        "storage"
    ],
    "wof:name":"C & C Mini Storage",
    "wof:placetype":"venue"
},
  "geometry": {"coordinates":[-103.675551,41.870965],"type":"Point"}
}