{
  "type": "Feature",
  "properties": {
    "iso:country":"US",
    "sg:address":"202 S 163rd St",
    "sg:city":"Omaha",
    "sg:classifiers":[
        {
            "category":"Building & Trades",
            "subcategory":"Construction",
            "type":"Services"
        }
    ],
    "sg:phone":"+1 402 679 8326",
    "sg:postcode":"68118",
    "sg:province":"NE",
    "sg:tags":[
        "builder",
        "repairer",
        "chimney"
    ],
    "wof:name":"A-1 Chimney Svc",
    "wof:placetype":"venue"
},
  "geometry": {"coordinates":[-96.17058299999999,41.256163],"type":"Point"}
}