{
  "type": "Feature",
  "properties": {
    "addr:full":"4203 S 147th Plz Omaha NE 68137",
    "addr:housenumber":"4203",
    "addr:postcode":"68137",
    "addr:street":"S 147Th",
    "iso:country":"US",
    "sg:address":"4203 S 147th Plz",
    "sg:city":"Omaha",
    "sg:classifiers":[
        {
            "category":"Professional",
            "subcategory":"Computer Services",
            "type":"Services"
        }
    ],
    "sg:phone":"+1 402 968 4018",
    "sg:postcode":"68137",
    "sg:province":"NE",
    "sg:tags":[
        "related"
    ],
    "wof:name":"Jam Co",
    "wof:placetype":"venue"
},
  "geometry": {"coordinates":[-96.142715,41.218049],"type":"Point"}
}