{
  "type": "Feature",
  "properties": {
    "iso:country":"US",
    "sg:address":"132 W 4th Ave",
    "sg:city":"Holdrege",
    "sg:classifiers":[
        {
            "category":"Restaurant",
            "type":"Food & Drink"
        }
    ],
    "sg:phone":"+1 308 995 6611",
    "sg:postcode":"68949",
    "sg:province":"NE",
    "wof:name":"Villager The",
    "wof:placetype":"venue"
},
  "geometry": {"coordinates":[-99.381243,40.437975],"type":"Point"}
}