{
  "type": "Feature",
  "properties": {
    "iso:country":"US",
    "sg:address":"3361 D Rd",
    "sg:city":"Rising City",
    "sg:classifiers":[
        {
            "category":"Banks & Credit Unions",
            "subcategory":"Investment Brokerage",
            "type":"Services"
        }
    ],
    "sg:phone":"+1 402 542 2564",
    "sg:postcode":"68658",
    "sg:province":"NE",
    "sg:tags":[
        "consultant",
        "planning",
        "financial"
    ],
    "wof:name":"Scow Financial Consultant",
    "wof:placetype":"venue"
},
  "geometry": {"coordinates":[-97.310328,41.235917],"type":"Point"}
}