{
  "type": "Feature",
  "properties": {
    "iso:country":"US",
    "sg:address":"6818 Grover St Ste 203",
    "sg:city":"Omaha",
    "sg:classifiers":[
        {
            "category":"Communications",
            "type":"Services"
        }
    ],
    "sg:phone":"+1 402 399 1658",
    "sg:postcode":"68106",
    "sg:province":"NE",
    "sg:tags":[
        "web",
        "design"
    ],
    "wof:name":"Soho's Net Corp",
    "wof:placetype":"venue"
},
  "geometry": {"coordinates":[-96.018204,41.227001],"type":"Point"}
}