{
  "type": "Feature",
  "properties": {
    "iso:country":"US",
    "sg:address":"102 W 30th St",
    "sg:city":"Kearney",
    "sg:classifiers":[
        {
            "category":"Shopping",
            "subcategory":"Hobbies, Toys, & Games",
            "type":"Retail Goods"
        }
    ],
    "sg:phone":"+1 308 234 1806",
    "sg:postcode":"68847",
    "sg:province":"NE",
    "sg:tags":[
        "model",
        "supply"
    ],
    "wof:name":"Funtime Hobby",
    "wof:placetype":"venue"
},
  "geometry": {"coordinates":[-99.08423999999999,40.704919],"type":"Point"}
}