{
  "type": "Feature",
  "properties": {
    "addr:full":"1005 Georgia Ave Norfolk NE 68701",
    "addr:housenumber":"1005",
    "addr:postcode":"68701",
    "addr:street":"Georgia Ave",
    "iso:country":"US",
    "sg:address":"1005 Georgia Ave",
    "sg:city":"Norfolk",
    "sg:classifiers":[
        {
            "category":"Building & Trades",
            "subcategory":"Construction",
            "type":"Services"
        }
    ],
    "sg:phone":"+1 402 371 2713",
    "sg:postcode":"68701",
    "sg:province":"NE",
    "sg:tags":[
        "hanging",
        "contractor"
    ],
    "wof:name":"Nicks Parking Lot",
    "wof:placetype":"venue"
},
  "geometry": {"coordinates":[-97.42015499999999,42.043496],"type":"Point"}
}