{
  "type": "Feature",
  "properties": {
    "addr:full":"110 N 35th St Lincoln NE 68503",
    "addr:housenumber":"110",
    "addr:postcode":"68503",
    "addr:street":"N 35Th St",
    "iso:country":"US",
    "sg:address":"110 N 35th St",
    "sg:city":"Lincoln",
    "sg:classifiers":[
        {
            "category":"Government",
            "subcategory":"Post Office",
            "type":"Public Place"
        }
    ],
    "sg:phone":"+1 402 000 1111",
    "sg:postcode":"68503",
    "sg:province":"NE",
    "wof:name":"US Post Office",
    "wof:placetype":"venue"
},
  "geometry": {"coordinates":[-96.670117,40.814416],"type":"Point"}
}