{
  "type": "Feature",
  "properties": {
    "iso:country":"US",
    "sg:address":"2402 N 22nd St",
    "sg:city":"Omaha",
    "sg:classifiers":[
        {
            "category":"Organizations",
            "subcategory":"Religious Organization",
            "type":"Services"
        }
    ],
    "sg:phone":"+1 402 345 1070",
    "sg:postcode":"68110",
    "sg:province":"NE",
    "wof:name":"St John AME Church",
    "wof:placetype":"venue"
},
  "geometry": {"coordinates":[-95.945032,41.281503],"type":"Point"}
}