{
  "type": "Feature",
  "properties": {
    "iso:country":"US",
    "sg:address":"4973 Center St",
    "sg:city":"Omaha",
    "sg:classifiers":[
        {
            "category":"Manufacturing",
            "subcategory":"Textiles",
            "type":"Manufacturing & Wholesale Goods"
        }
    ],
    "sg:phone":"+1 402 556 0867",
    "sg:postcode":"68106",
    "sg:province":"NE",
    "sg:tags":[
        "mill",
        "bar",
        "fabric",
        "diva"
    ],
    "wof:name":"The Elbow Room",
    "wof:placetype":"venue"
},
  "geometry": {"coordinates":[-95.99009700000001,41.241402],"type":"Point"}
}