{
  "type": "Feature",
  "properties": {
    "iso:country":"US",
    "sg:address":"4323 31st St",
    "sg:city":"Columbus",
    "sg:classifiers":[
        {
            "category":"Professional",
            "subcategory":"Computer Services",
            "type":"Services"
        }
    ],
    "sg:phone":"+1 402 563 3398",
    "sg:postcode":"68601",
    "sg:province":"NE",
    "wof:name":"Specialty Wiring",
    "wof:placetype":"venue"
},
  "geometry": {"coordinates":[-97.380903,41.446302],"type":"Point"}
}