{
  "type": "Feature",
  "properties": {
    "iso:country":"US",
    "sg:address":"113 N Main St",
    "sg:city":"West Point",
    "sg:classifiers":[
        {
            "category":"Wholesale",
            "subcategory":"Medical Equipment & Supplies",
            "type":"Manufacturing & Wholesale Goods"
        }
    ],
    "sg:phone":"+1 402 372 0187",
    "sg:postcode":"68788",
    "sg:province":"NE",
    "sg:tags":[
        "hospital"
    ],
    "wof:name":"Home Health Medical Equipment",
    "wof:placetype":"venue"
},
  "geometry": {"coordinates":[-96.712219,41.840999],"type":"Point"}
}