{
  "type": "Feature",
  "properties": {
    "iso:country":"US",
    "sg:address":"2501 Fox Run Pkwy",
    "sg:city":"Yankton",
    "sg:classifiers":[
        {
            "category":"Retail",
            "subcategory":"Auto Repair",
            "type":"Services"
        }
    ],
    "sg:phone":"+1 605 665 1810",
    "sg:postcode":"57078",
    "sg:province":"NE",
    "sg:tags":[
        "general"
    ],
    "wof:name":"Fox Run Quik Lube",
    "wof:placetype":"venue"
},
  "geometry": {"coordinates":[-97.39989799999999,42.901502],"type":"Point"}
}