{
  "type": "Feature",
  "properties": {
    "addr:full":"2213 Towle St Falls City NE 68355",
    "addr:housenumber":"2213",
    "addr:postcode":"68355",
    "addr:street":"Towle St",
    "iso:country":"US",
    "sg:address":"2213 Towle St",
    "sg:city":"Falls City",
    "sg:classifiers":[
        {
            "category":"Home & Garden",
            "subcategory":"Home Furnishings",
            "type":"Retail Goods"
        }
    ],
    "sg:phone":"+1 402 245 4847",
    "sg:postcode":"68355",
    "sg:province":"NE",
    "wof:name":"Draperies Plus",
    "wof:placetype":"venue"
},
  "geometry": {"coordinates":[-95.606341,40.06753],"type":"Point"}
}