{
  "type": "Feature",
  "properties": {
    "iso:country":"US",
    "sg:address":"1010 S 8th St",
    "sg:city":"Norfolk",
    "sg:classifiers":[
        {
            "category":"Government",
            "subcategory":"Office",
            "type":"Public Place"
        }
    ],
    "sg:phone":"+1 402 844 2180",
    "sg:postcode":"68701",
    "sg:province":"NE",
    "sg:tags":[
        "village"
    ],
    "sg:website":"www.ci.norfolk.ne.us",
    "wof:name":"Norfolk City Street Div",
    "wof:placetype":"venue"
},
  "geometry": {"coordinates":[-97.41794899999999,42.020837],"type":"Point"}
}