{
  "type": "Feature",
  "properties": {
    "iso:country":"US",
    "sg:address":"4400 S 86th St Ste 100",
    "sg:city":"Lincoln",
    "sg:classifiers":[
        {
            "category":"Professional",
            "subcategory":"Lawyer & Legal Services",
            "type":"Services"
        }
    ],
    "sg:phone":"+1 402 488 5044",
    "sg:postcode":"68526",
    "sg:province":"NE",
    "sg:tags":[
        "litigation",
        "tort",
        "attorney",
        "practice"
    ],
    "sg:website":"http://www.shivelylaw.com",
    "wof:name":"Shively Law Offices",
    "wof:placetype":"venue"
},
  "geometry": {"coordinates":[-96.60356899999999,40.769009],"type":"Point"}
}