{
  "type": "Feature",
  "properties": {
    "iso:country":"US",
    "sg:address":"11000 W A St",
    "sg:city":"Lincoln",
    "sg:classifiers":[
        {
            "category":"Wholesale",
            "subcategory":"Construction Materials",
            "type":"Manufacturing & Wholesale Goods"
        }
    ],
    "sg:phone":"+1 402 440 7406",
    "sg:postcode":"68532",
    "sg:province":"NE",
    "sg:tags":[
        "sand",
        "gravel"
    ],
    "wof:name":"Mel Petty Trucking",
    "wof:placetype":"venue"
},
  "geometry": {"coordinates":[-96.863108,40.799377],"type":"Point"}
}