{
  "type": "Feature",
  "properties": {
    "iso:country":"US",
    "sg:address":"8945 J St",
    "sg:city":"Omaha",
    "sg:classifiers":[
        {
            "category":"Shopping",
            "subcategory":"Computers & Home Electronics",
            "type":"Retail Goods"
        }
    ],
    "sg:phone":"+1 402 502 8667",
    "sg:postcode":"68127",
    "sg:province":"NE",
    "sg:tags":[
        "printer"
    ],
    "wof:name":"Toner Express Inc",
    "wof:placetype":"venue"
},
  "geometry": {"coordinates":[-96.05133499999999,41.215323],"type":"Point"}
}