{
  "type": "Feature",
  "properties": {
    "iso:country":"US",
    "sg:address":"211 Queen Ave",
    "sg:city":"Ames",
    "sg:classifiers":[
        {
            "category":"Freight",
            "type":"Transportation"
        }
    ],
    "sg:phone":"+1 402 727 7786",
    "sg:postcode":"68621",
    "sg:province":"NE",
    "sg:tags":[
        "firm",
        "trucking"
    ],
    "wof:name":"Kline Trucking Inc",
    "wof:placetype":"venue"
},
  "geometry": {"coordinates":[-96.57796999999999,41.462885],"type":"Point"}
}