{
  "type": "Feature",
  "properties": {
    "iso:country":"US",
    "sg:address":"1721 Hillcrest Rd",
    "sg:city":"Wisner",
    "sg:classifiers":[
        {
            "category":"Farming",
            "subcategory":"Livestock Farm",
            "type":"Manufacturing & Wholesale Goods"
        }
    ],
    "sg:phone":"+1 402 529 6506",
    "sg:postcode":"68791",
    "sg:province":"NE",
    "sg:tags":[
        "hog",
        "or",
        "feedlot"
    ],
    "wof:name":"Steve McGuire",
    "wof:placetype":"venue"
},
  "geometry": {"coordinates":[-96.91967699999999,41.996095],"type":"Point"}
}