{
  "type": "Feature",
  "properties": {
    "addr:full":"1115 Nasby St Cambridge NE 69022",
    "addr:housenumber":"1115",
    "addr:postcode":"69022",
    "addr:street":"Nasby St",
    "iso:country":"US",
    "sg:address":"1115 Nasby St",
    "sg:city":"Cambridge",
    "sg:classifiers":[
        {
            "category":"Restaurant",
            "type":"Food & Drink"
        }
    ],
    "sg:phone":"+1 308 697 4170",
    "sg:postcode":"69022",
    "sg:province":"NE",
    "wof:name":"Frontier Cafe'",
    "wof:placetype":"venue"
},
  "geometry": {"coordinates":[-100.175753,40.281201],"type":"Point"}
}