{
  "type": "Feature",
  "properties": {
    "iso:country":"US",
    "sg:address":"1410 Rd X",
    "sg:city":"Strang",
    "sg:phone":"+1 402 759 4742",
    "sg:postcode":"68456",
    "sg:province":"NE",
    "sg:tags":[
        "farm",
        "soybean"
    ],
    "wof:name":"Delwin Myers",
    "wof:placetype":"venue"
},
  "geometry": {"coordinates":[-97.368213,40.888303],"type":"Point"}
}