{
  "type": "Feature",
  "properties": {
    "iso:country":"US",
    "sg:address":"209 Market St",
    "sg:city":"Shickley",
    "sg:classifiers":[
        {
            "category":"Building & Trades",
            "subcategory":"Construction",
            "type":"Services"
        }
    ],
    "sg:phone":"+1 402 627 7665",
    "sg:postcode":"68436",
    "sg:province":"NE",
    "sg:tags":[
        "home",
        "builder"
    ],
    "wof:name":"Home Place",
    "wof:placetype":"venue"
},
  "geometry": {"coordinates":[-97.723353,40.415281],"type":"Point"}
}