{
  "type": "Feature",
  "properties": {
    "iso:country":"US",
    "sg:address":"5115 S 25th St",
    "sg:city":"Omaha",
    "sg:classifiers":[
        {
            "category":"Building & Trades",
            "subcategory":"Plumbing",
            "type":"Services"
        }
    ],
    "sg:phone":"+1 402 731 6136",
    "sg:postcode":"68107",
    "sg:province":"NE",
    "sg:tags":[
        "air",
        "heating",
        "contractor",
        "system",
        "conditioning"
    ],
    "wof:name":"Town & Country Heating & Coolg",
    "wof:placetype":"venue"
},
  "geometry": {"coordinates":[-95.948477,41.205785],"type":"Point"}
}