{
  "type": "Feature",
  "properties": {
    "iso:country":"US",
    "sg:address":"1750 7th St",
    "sg:city":"Gering",
    "sg:classifiers":[
        {
            "category":"Shopping",
            "subcategory":"Gifts & Souvenirs",
            "type":"Retail Goods"
        }
    ],
    "sg:phone":"+1 308 436 3849",
    "sg:postcode":"69341",
    "sg:province":"NE",
    "sg:tags":[
        "collectible"
    ],
    "wof:name":"Gering Collectables",
    "wof:placetype":"venue"
},
  "geometry": {"coordinates":[-103.655399,41.826318],"type":"Point"}
}