{
  "type": "Feature",
  "properties": {
    "iso:country":"US",
    "sg:address":"5204 S 192nd St",
    "sg:city":"Omaha",
    "sg:classifiers":[
        {
            "category":"Building & Trades",
            "subcategory":"Construction",
            "type":"Services"
        }
    ],
    "sg:phone":"+1 402 895 5232",
    "sg:postcode":"68135",
    "sg:province":"NE",
    "sg:tags":[
        "hanging",
        "contractor"
    ],
    "wof:name":"Langmaack Construction Inc",
    "wof:placetype":"venue"
},
  "geometry": {"coordinates":[-96.215681,41.201835],"type":"Point"}
}