{
  "type": "Feature",
  "properties": {
    "iso:country":"US",
    "sg:address":"8410 Q St",
    "sg:city":"Omaha",
    "sg:classifiers":[
        {
            "category":"Banks & Credit Unions",
            "subcategory":"Bank",
            "type":"Services"
        }
    ],
    "sg:phone":"+1 402 596 1010",
    "sg:postcode":"68127",
    "sg:province":"NE",
    "sg:tags":[
        "cashing",
        "check"
    ],
    "wof:name":"American Check Casher",
    "wof:placetype":"venue"
},
  "geometry": {"coordinates":[-96.045385,41.205383],"type":"Point"}
}