{
  "type": "Feature",
  "properties": {
    "iso:country":"US",
    "sg:address":"17038 Patterson Dr",
    "sg:city":"Omaha",
    "sg:classifiers":[
        {
            "category":"Professional",
            "subcategory":"Management & Consulting",
            "type":"Services"
        }
    ],
    "sg:phone":"+1 402 895 7524",
    "sg:postcode":"68135",
    "sg:province":"NE",
    "wof:name":"Atlas Global Research Inc",
    "wof:placetype":"venue"
},
  "geometry": {"coordinates":[-96.183119,41.214124],"type":"Point"}
}