{
  "type": "Feature",
  "properties": {
    "addr:full":"1111 S 103rd St Omaha NE 68124",
    "addr:housenumber":"1111",
    "addr:postcode":"68124",
    "addr:street":"S 103Rd St",
    "iso:country":"US",
    "sg:address":"1111 S 103rd St",
    "sg:city":"Omaha",
    "sg:phone":"+1 402 398 7200",
    "sg:postcode":"68124",
    "sg:province":"NE",
    "sg:tags":[
        "fuel"
    ],
    "wof:name":"Northern Natural Gas Co",
    "wof:placetype":"venue"
},
  "geometry": {"coordinates":[-96.070336,41.245342],"type":"Point"}
}