{
  "type": "Feature",
  "properties": {
    "iso:country":"US",
    "sg:address":"512 N Morehead St",
    "sg:city":"Chadron",
    "sg:classifiers":[
        {
            "category":"Retail",
            "subcategory":"Repair Shop",
            "type":"Services"
        }
    ],
    "sg:phone":"+1 308 432 5610",
    "sg:postcode":"69337",
    "sg:province":"NE",
    "wof:name":"Douglas V Murdock",
    "wof:placetype":"venue"
},
  "geometry": {"coordinates":[-103.00130799999999,42.843049],"type":"Point"}
}