{
  "type": "Feature",
  "properties": {
    "addr:full":"206 N Wheeler Ave Grand Island NE 68801",
    "addr:housenumber":"206",
    "addr:postcode":"68801",
    "addr:street":"N Wheeler Ave",
    "iso:country":"US",
    "sg:address":"206 N Wheeler Ave",
    "sg:city":"Grand Island",
    "sg:classifiers":[
        {
            "category":"Shopping",
            "subcategory":"Clothing, Apparel, & Fashions",
            "type":"Retail Goods"
        }
    ],
    "sg:phone":"+1 308 384 0624",
    "sg:postcode":"68801",
    "sg:province":"NE",
    "sg:tags":[
        "shop",
        "bridal"
    ],
    "wof:name":"Bridal Dreams By Donna's Fshn",
    "wof:placetype":"venue"
},
  "geometry": {"coordinates":[-98.34182699999999,40.924272],"type":"Point"}
}