{
  "type": "Feature",
  "properties": {
    "iso:country":"US",
    "sg:address":"8035 Bauman Ave",
    "sg:city":"Omaha",
    "sg:classifiers":[
        {
            "category":"Professional",
            "subcategory":"Business Services",
            "type":"Services"
        }
    ],
    "sg:phone":"+1 402 934 4480",
    "sg:postcode":"68122",
    "sg:province":"NE",
    "sg:tags":[
        "transcribing",
        "disc"
    ],
    "wof:name":"Mc Guire's Medical Trnscrptn",
    "wof:placetype":"venue"
},
  "geometry": {"coordinates":[-96.039169,41.318007],"type":"Point"}
}