{
  "type": "Feature",
  "properties": {
    "iso:country":"US",
    "sg:address":"4318 2nd Ave",
    "sg:city":"Kearney",
    "sg:classifiers":[
        {
            "category":"Home & Garden",
            "subcategory":"Carpets & Floor Coverings",
            "type":"Retail Goods"
        }
    ],
    "sg:phone":"+1 308 234 2404",
    "sg:postcode":"68847",
    "sg:province":"NE",
    "sg:tags":[
        "furnishing"
    ],
    "sg:website":"www.tophatfurniture.com",
    "wof:name":"Top Hat Furniture",
    "wof:placetype":"venue"
},
  "geometry": {"coordinates":[-99.084025,40.716765],"type":"Point"}
}