{
  "type": "Feature",
  "properties": {
    "iso:country":"US",
    "sg:address":"445 N Broad St",
    "sg:city":"Fremont",
    "sg:classifiers":[
        {
            "category":"Building & Trades",
            "subcategory":"Construction",
            "type":"Services"
        }
    ],
    "sg:phone":"+1 402 721 2413",
    "sg:postcode":"68025",
    "sg:province":"NE",
    "sg:tags":[
        "roofing",
        "contractor"
    ],
    "wof:name":"Roof Floater",
    "wof:placetype":"venue"
},
  "geometry": {"coordinates":[-96.498822,41.433479],"type":"Point"}
}