{
  "type": "Feature",
  "properties": {
    "iso:country":"US",
    "sg:address":"112 Vine St",
    "sg:city":"Table Rock",
    "sg:classifiers":[
        {
            "category":"Wholesale",
            "subcategory":"Farm Supplies",
            "type":"Manufacturing & Wholesale Goods"
        }
    ],
    "sg:phone":"+1 402 839 2024",
    "sg:postcode":"68442",
    "sg:province":"NE",
    "sg:tags":[
        "feed"
    ],
    "wof:name":"Farmers Coop Elevator",
    "wof:placetype":"venue"
},
  "geometry": {"coordinates":[-95.772245,40.229728],"type":"Point"}
}