{
  "type": "Feature",
  "properties": {
    "iso:country":"US",
    "sg:address":"1908 Burt St",
    "sg:city":"Omaha",
    "sg:classifiers":[
        {
            "category":"Wholesale",
            "subcategory":"Machinery & Supplies",
            "type":"Manufacturing & Wholesale Goods"
        }
    ],
    "sg:phone":"+1 402 344 8055",
    "sg:postcode":"68102",
    "sg:province":"NE",
    "sg:tags":[
        "industrial",
        "miscellaneous"
    ],
    "wof:name":"Modern Equipment Co Inc",
    "wof:placetype":"venue"
},
  "geometry": {"coordinates":[-95.942329,41.266987],"type":"Point"}
}