{
  "type": "Feature",
  "properties": {
    "iso:country":"US",
    "sg:address":"202 E Douglas St",
    "sg:city":"Oneill",
    "sg:phone":"+1 402 336 2781",
    "sg:postcode":"68763",
    "sg:province":"NE",
    "sg:tags":[
        "oil"
    ],
    "wof:name":"Gokie's Oil Co",
    "wof:placetype":"venue"
},
  "geometry": {"coordinates":[-98.65105200000001,42.457717],"type":"Point"}
}