{
  "type": "Feature",
  "properties": {
    "iso:country":"US",
    "sg:address":"1571 Deer Creek Dr",
    "sg:city":"Fort Calhoun",
    "sg:classifiers":[
        {
            "category":"Building & Trades",
            "subcategory":"Construction",
            "type":"Services"
        }
    ],
    "sg:phone":"+1 402 926 4757",
    "sg:postcode":"68023",
    "sg:province":"NE",
    "wof:name":"Nebcon Inc",
    "wof:placetype":"venue"
},
  "geometry": {"coordinates":[-96.013769,41.404996],"type":"Point"}
}