{
  "type": "Feature",
  "properties": {
    "iso:country":"US",
    "sg:address":"3702 20th Ave",
    "sg:city":"Kearney",
    "sg:classifiers":[
        {
            "category":"Professional",
            "subcategory":"Management & Consulting",
            "type":"Services"
        }
    ],
    "sg:phone":"+1 308 234 4958",
    "sg:postcode":"68845",
    "sg:province":"NE",
    "sg:tags":[
        "accounting",
        "consultant",
        "marketing"
    ],
    "wof:name":"Mid West Agri-Planters",
    "wof:placetype":"venue"
},
  "geometry": {"coordinates":[-99.10784700000001,40.712992],"type":"Point"}
}