{
  "type": "Feature",
  "properties": {
    "addr:full":"509 S 14th St Ord NE 68862",
    "addr:housenumber":"509",
    "addr:postcode":"68862",
    "addr:street":"S 14Th St",
    "iso:country":"US",
    "sg:address":"509 S 14th St",
    "sg:city":"Ord",
    "sg:classifiers":[
        {
            "category":"Autos & Motor Vehicles",
            "subcategory":"Automobile Sales",
            "type":"Retail Goods"
        }
    ],
    "sg:phone":"+1 308 728 5521",
    "sg:postcode":"68862",
    "sg:province":"NE",
    "sg:tags":[
        "car",
        "dealer"
    ],
    "wof:name":"Edghill's Used Cars & Repair",
    "wof:placetype":"venue"
},
  "geometry": {"coordinates":[-98.927054,41.599294],"type":"Point"}
}