{
  "type": "Feature",
  "properties": {
    "iso:country":"US",
    "sg:address":"6339 Hamilton St",
    "sg:city":"Omaha",
    "sg:classifiers":[
        {
            "category":"Professional",
            "subcategory":"Advertising",
            "type":"Services"
        }
    ],
    "sg:phone":"+1 402 991 5073",
    "sg:postcode":"68132",
    "sg:province":"NE",
    "wof:name":"M & A Advertising",
    "wof:placetype":"venue"
},
  "geometry": {"coordinates":[-96.011652,41.27224],"type":"Point"}
}