{
  "type": "Feature",
  "properties": {
    "addr:full":"42550 Rd 760 Cozad NE 69130",
    "addr:postcode":"42550;69130",
    "addr:street":"Rd 760",
    "iso:country":"US",
    "sg:address":"42550 Rd 760",
    "sg:city":"Cozad",
    "sg:phone":"+1 308 784 2450",
    "sg:postcode":"69130",
    "sg:province":"NE",
    "sg:tags":[
        "beef",
        "farm",
        "cash",
        "grain",
        "cattle",
        "feedlot"
    ],
    "wof:name":"Bill Geiger Farm",
    "wof:placetype":"venue"
},
  "geometry": {"coordinates":[-99.89128700000001,40.844728],"type":"Point"}
}