{
  "type": "Feature",
  "properties": {
    "iso:country":"US",
    "sg:address":"3221 N 71st St",
    "sg:city":"Lincoln",
    "sg:classifiers":[
        {
            "category":"Social Services",
            "subcategory":"Job Training",
            "type":"Services"
        }
    ],
    "sg:phone":"+1 402 466 2559",
    "sg:postcode":"68507",
    "sg:province":"NE",
    "wof:name":"Excutive Speaker The",
    "wof:placetype":"venue"
},
  "geometry": {"coordinates":[-96.62436099999999,40.845582],"type":"Point"}
}