{
  "type": "Feature",
  "properties": {
    "addr:full":"1835 Page Rd Elba NE 68835",
    "addr:housenumber":"1835",
    "addr:postcode":"68835",
    "addr:street":"Page Rd",
    "iso:country":"US",
    "sg:address":"1835 Page Rd",
    "sg:city":"Elba",
    "sg:phone":"+1 308 863 2108",
    "sg:postcode":"68835",
    "sg:province":"NE",
    "sg:tags":[
        "farm",
        "corn"
    ],
    "wof:name":"Harold Burmood Farm",
    "wof:placetype":"venue"
},
  "geometry": {"coordinates":[-98.593598,41.294055],"type":"Point"}
}