{
  "type": "Feature",
  "properties": {
    "iso:country":"US",
    "sg:address":"105 W 9th St",
    "sg:city":"Wood River",
    "sg:classifiers":[
        {
            "category":"Freight",
            "type":"Transportation"
        }
    ],
    "sg:phone":"+1 308 583 2272",
    "sg:postcode":"68883",
    "sg:province":"NE",
    "sg:tags":[
        "storage"
    ],
    "wof:name":"KLW Storage",
    "wof:placetype":"venue"
},
  "geometry": {"coordinates":[-98.60302299999999,40.820528],"type":"Point"}
}