{
  "type": "Feature",
  "properties": {
    "iso:country":"US",
    "sg:address":"14609 Prairie Corners Rd",
    "sg:city":"Omaha",
    "sg:classifiers":[
        {
            "category":"Building & Trades",
            "subcategory":"Electrical",
            "type":"Services"
        }
    ],
    "sg:phone":"+1 402 895 7795",
    "sg:postcode":"68138",
    "sg:province":"NE",
    "sg:tags":[
        "electrical",
        "contractor"
    ],
    "wof:name":"Feldhacker Electric Co",
    "wof:placetype":"venue"
},
  "geometry": {"coordinates":[-96.142188,41.154557],"type":"Point"}
}