{
  "type": "Feature",
  "properties": {
    "iso:country":"US",
    "sg:address":"5170 Leavenworth St",
    "sg:city":"Omaha",
    "sg:classifiers":[
        {
            "category":"Organizations",
            "subcategory":"Community Association",
            "type":"Services"
        }
    ],
    "sg:phone":"+1 402 933 5792",
    "sg:postcode":"68106",
    "sg:province":"NE",
    "sg:tags":[
        "club"
    ],
    "wof:name":"Sierra Club Omaha Office",
    "wof:placetype":"venue"
},
  "geometry": {"coordinates":[-95.994361,41.252469],"type":"Point"}
}