{
  "type": "Feature",
  "properties": {
    "addr:full":"1818 32 Rd Minden NE 68959",
    "addr:housenumber":"1818",
    "addr:postcode":"68959",
    "addr:street":"32 Rd",
    "iso:country":"US",
    "sg:address":"1818 32 Rd",
    "sg:city":"Minden",
    "sg:classifiers":[
        {
            "category":"Farming",
            "subcategory":"Livestock Farm",
            "type":"Manufacturing & Wholesale Goods"
        }
    ],
    "sg:phone":"+1 308 832 1360",
    "sg:postcode":"68959",
    "sg:province":"NE",
    "sg:tags":[
        "feeding"
    ],
    "wof:name":"Fort Kearney Consolidated",
    "wof:placetype":"venue"
},
  "geometry": {"coordinates":[-98.951593,40.35492],"type":"Point"}
}