{
  "type": "Feature",
  "properties": {
    "iso:country":"US",
    "sg:address":"4526 S 140th St",
    "sg:city":"Omaha",
    "sg:classifiers":[
        {
            "category":"Retail",
            "subcategory":"Repair Shop",
            "type":"Services"
        }
    ],
    "sg:phone":"+1 402 341 1529",
    "sg:postcode":"68137",
    "sg:province":"NE",
    "sg:tags":[
        "installs",
        "com",
        "radio",
        "same"
    ],
    "sg:website":"www.mobileomaha.com",
    "wof:name":"Mobile Communications Inc",
    "wof:placetype":"venue"
},
  "geometry": {"coordinates":[-96.133745,41.214276],"type":"Point"}
}