{
  "type": "Feature",
  "properties": {
    "iso:country":"US",
    "sg:address":"125 S 10th St",
    "sg:city":"Geneva",
    "sg:classifiers":[
        {
            "category":"Retail",
            "subcategory":"Repair Shop",
            "type":"Services"
        }
    ],
    "sg:phone":"+1 402 759 3111",
    "sg:postcode":"68361",
    "sg:province":"NE",
    "sg:tags":[
        "electrical"
    ],
    "wof:name":"Alltel",
    "wof:placetype":"venue"
},
  "geometry": {"coordinates":[-97.601032,40.525367],"type":"Point"}
}