{
  "type": "Feature",
  "properties": {
    "addr:full":"829 W Garfield St Lincoln NE 68522",
    "addr:housenumber":"829",
    "addr:postcode":"68522",
    "addr:street":"W Garfield St",
    "iso:country":"US",
    "sg:address":"829 W Garfield St",
    "sg:city":"Lincoln",
    "sg:classifiers":[
        {
            "category":"Communications",
            "subcategory":"Film & Video Production",
            "type":"Services"
        }
    ],
    "sg:phone":"+1 402 432 2671",
    "sg:postcode":"68522",
    "sg:province":"NE",
    "sg:tags":[
        "taping"
    ],
    "wof:name":"Longshots Video Creations",
    "wof:placetype":"venue"
},
  "geometry": {"coordinates":[-96.73447899999999,40.797239],"type":"Point"}
}