{
  "type": "Feature",
  "properties": {
    "iso:country":"US",
    "sg:address":"800 W 6th St",
    "sg:city":"Chadron",
    "sg:classifiers":[
        {
            "category":"Building & Trades",
            "subcategory":"Pest Control",
            "type":"Services"
        }
    ],
    "sg:phone":"+1 308 432 5108",
    "sg:postcode":"69337",
    "sg:province":"NE",
    "wof:name":"Pests Go",
    "wof:placetype":"venue"
},
  "geometry": {"coordinates":[-103.010907,42.826042],"type":"Point"}
}