{
  "type": "Feature",
  "properties": {
    "iso:country":"US",
    "sg:address":"11240 Davenport St",
    "sg:city":"Omaha",
    "sg:classifiers":[
        {
            "category":"Professional",
            "subcategory":"Lawyer & Legal Services",
            "type":"Services"
        }
    ],
    "sg:phone":"+1 402 330 6300",
    "sg:postcode":"68154",
    "sg:province":"NE",
    "sg:tags":[
        "attorney"
    ],
    "wof:name":"Walentine O'Toole Mc Quillan",
    "wof:placetype":"venue"
},
  "geometry": {"coordinates":[-96.08921100000001,41.260512],"type":"Point"}
}