{
  "type": "Feature",
  "properties": {
    "iso:country":"US",
    "sg:address":"804 Howard Ave",
    "sg:city":"St Paul",
    "sg:classifiers":[
        {
            "category":"Organizations",
            "subcategory":"Community Association",
            "type":"Services"
        }
    ],
    "sg:phone":"+1 308 754 5497",
    "sg:postcode":"68873",
    "sg:province":"NE",
    "sg:tags":[
        "military"
    ],
    "wof:name":"American Legion",
    "wof:placetype":"venue"
},
  "geometry": {"coordinates":[-98.460064,41.213453],"type":"Point"}
}