{
  "type": "Feature",
  "properties": {
    "addr:full":"401 N Central Ave Superior NE 68978",
    "addr:housenumber":"401",
    "addr:postcode":"68978",
    "addr:street":"N Central Ave",
    "iso:country":"US",
    "sg:address":"401 N Central Ave",
    "sg:city":"Superior",
    "sg:classifiers":[
        {
            "category":"Insurance",
            "subcategory":"Insurance Agent",
            "type":"Services"
        }
    ],
    "sg:phone":"+1 402 879 3913",
    "sg:postcode":"68978",
    "sg:province":"NE",
    "wof:name":"Gary Thompson Insurance",
    "wof:placetype":"venue"
},
  "geometry": {"coordinates":[-98.07140800000001,40.020938],"type":"Point"}
}