{
  "type": "Feature",
  "properties": {
    "iso:country":"US",
    "sg:address":"2809 S 160th St",
    "sg:city":"Omaha",
    "sg:classifiers":[
        {
            "category":"Wholesale",
            "subcategory":"Electrical",
            "type":"Manufacturing & Wholesale Goods"
        }
    ],
    "sg:phone":"+1 402 330 4800",
    "sg:postcode":"68130",
    "sg:province":"NE",
    "sg:tags":[
        "equipment"
    ],
    "wof:name":"Siemens Energy & Automation",
    "wof:placetype":"venue"
},
  "geometry": {"coordinates":[-96.164952,41.232629],"type":"Point"}
}