{
  "type": "Feature",
  "properties": {
    "iso:country":"US",
    "sg:address":"1608 S Locust St",
    "sg:city":"Grand Island",
    "sg:classifiers":[
        {
            "category":"Restaurant",
            "type":"Food & Drink"
        }
    ],
    "sg:phone":"+1 308 384 8600",
    "sg:postcode":"68801",
    "sg:province":"NE",
    "sg:tags":[
        "pizza"
    ],
    "wof:name":"Pizza Hut",
    "wof:placetype":"venue"
},
  "geometry": {"coordinates":[-98.33986899999999,40.904528],"type":"Point"}
}