{
  "type": "Feature",
  "properties": {
    "iso:country":"US",
    "sg:address":"3707 S 67th St",
    "sg:city":"Omaha",
    "sg:classifiers":[
        {
            "category":"Building & Trades",
            "subcategory":"Construction",
            "type":"Services"
        }
    ],
    "sg:phone":"+1 402 399 8699",
    "sg:postcode":"68106",
    "sg:province":"NE",
    "sg:tags":[
        "concrete",
        "contractor"
    ],
    "wof:name":"A-1 Concrete Removal",
    "wof:placetype":"venue"
},
  "geometry": {"coordinates":[-96.01660699999999,41.224734],"type":"Point"}
}