{
  "type": "Feature",
  "properties": {
    "iso:country":"US",
    "sg:address":"401 E Military Ave",
    "sg:city":"Fremont",
    "sg:classifiers":[
        {
            "category":"Social Services",
            "subcategory":"Child Care",
            "type":"Services"
        }
    ],
    "sg:phone":"+1 402 727 6300",
    "sg:postcode":"68025",
    "sg:province":"NE",
    "wof:name":"Salem Little Saints Christian",
    "wof:placetype":"venue"
},
  "geometry": {"coordinates":[-96.49341099999999,41.435579],"type":"Point"}
}