{
  "type": "Feature",
  "properties": {
    "addr:full":"6200 N 16th St Omaha NE 68110",
    "addr:housenumber":"6200",
    "addr:postcode":"68110",
    "addr:street":"N 16Th St",
    "iso:country":"US",
    "sg:address":"6200 N 16th St",
    "sg:city":"Omaha",
    "sg:classifiers":[
        {
            "category":"Home & Garden",
            "subcategory":"Building Materials",
            "type":"Retail Goods"
        }
    ],
    "sg:phone":"+1 402 346 4344",
    "sg:postcode":"68110",
    "sg:province":"NE",
    "sg:tags":[
        "door"
    ],
    "wof:name":"Tiger Door",
    "wof:placetype":"venue"
},
  "geometry": {"coordinates":[-95.937375,41.31184],"type":"Point"}
}