{
  "type": "Feature",
  "properties": {
    "addr:full":"701 S 13th St Norfolk NE 68701",
    "addr:housenumber":"701",
    "addr:postcode":"68701",
    "addr:street":"S 13Th St",
    "iso:country":"US",
    "sg:address":"701 S 13th St",
    "sg:city":"Norfolk",
    "sg:classifiers":[
        {
            "category":"Restaurant",
            "type":"Food & Drink"
        }
    ],
    "sg:menulink":"http://www.allmenus.com/ne/norfolk/191285-burger-king/menu/",
    "sg:phone":"+1 402 371 9482",
    "sg:postcode":"68701",
    "sg:province":"NE",
    "sg:tags":[
        "burger",
        "american"
    ],
    "wof:name":"Burger King",
    "wof:placetype":"venue"
},
  "geometry": {"coordinates":[-97.426518,42.025569],"type":"Point"}
}