{
  "type": "Feature",
  "properties": {
    "iso:country":"US",
    "sg:address":"503 E Douglas St",
    "sg:city":"Oneill",
    "sg:classifiers":[
        {
            "category":"Autos & Motor Vehicles",
            "subcategory":"Fuel & Gas Station",
            "type":"Retail Goods"
        }
    ],
    "sg:phone":"+1 402 336 4520",
    "sg:postcode":"68763",
    "sg:province":"NE",
    "sg:tags":[
        "station",
        "gasoline"
    ],
    "wof:name":"Randys Service",
    "wof:placetype":"venue"
},
  "geometry": {"coordinates":[-98.64618900000001,42.457592],"type":"Point"}
}