{
  "type": "Feature",
  "properties": {
    "iso:country":"US",
    "sg:address":"17171 S 255th St",
    "sg:city":"Gretna",
    "sg:classifiers":[
        {
            "category":"Wholesale",
            "subcategory":"Construction Materials",
            "type":"Manufacturing & Wholesale Goods"
        }
    ],
    "sg:phone":"+1 402 359 2522",
    "sg:postcode":"68028",
    "sg:province":"NE",
    "sg:tags":[
        "sand",
        "gravel"
    ],
    "wof:name":"Lyman-Richey Sand & Gravel",
    "wof:placetype":"venue"
},
  "geometry": {"coordinates":[-96.31829500000001,41.064374],"type":"Point"}
}