{
  "type": "Feature",
  "properties": {
    "iso:country":"US",
    "sg:address":"217 E 7th St",
    "sg:city":"Minden",
    "sg:phone":"+1 308 832 2360",
    "sg:postcode":"68959",
    "sg:province":"NE",
    "sg:tags":[
        "farm",
        "corn"
    ],
    "wof:name":"Younkin Farms Inc",
    "wof:placetype":"venue"
},
  "geometry": {"coordinates":[-98.950301,40.50115],"type":"Point"}
}