{
  "type": "Feature",
  "properties": {
    "addr:full":"500 Pearl St Scribner NE 68057",
    "addr:housenumber":"500",
    "addr:postcode":"68057",
    "addr:street":"Pearl St",
    "iso:country":"US",
    "sg:address":"500 Pearl St",
    "sg:city":"Scribner",
    "sg:classifiers":[
        {
            "category":"Professional",
            "subcategory":"Lawyer & Legal Services",
            "type":"Services"
        }
    ],
    "sg:phone":"+1 402 664 2597",
    "sg:postcode":"68057",
    "sg:province":"NE",
    "sg:tags":[
        "attorney"
    ],
    "wof:name":"Gallant Law Office",
    "wof:placetype":"venue"
},
  "geometry": {"coordinates":[-96.66446999999999,41.66554],"type":"Point"}
}