{
  "type": "Feature",
  "properties": {
    "addr:full":"3030 Upland Pkwy Omaha NE 68107",
    "addr:housenumber":"3030",
    "addr:postcode":"68107",
    "addr:street":"Upland Pkwy",
    "iso:country":"US",
    "sg:address":"3030 Upland Pkwy",
    "sg:city":"Omaha",
    "sg:classifiers":[
        {
            "category":"Building & Trades",
            "subcategory":"Construction",
            "type":"Services"
        }
    ],
    "sg:phone":"+1 402 733 0555",
    "sg:postcode":"68107",
    "sg:province":"NE",
    "sg:tags":[
        "general",
        "contractor"
    ],
    "wof:name":"Veylupek Construction Inc",
    "wof:placetype":"venue"
},
  "geometry": {"coordinates":[-95.960365,41.197774],"type":"Point"}
}