{
  "type": "Feature",
  "properties": {
    "iso:country":"US",
    "sg:address":"715 K St",
    "sg:city":"Milligan",
    "sg:classifiers":[
        {
            "category":"Retail",
            "subcategory":"Repair Shop",
            "type":"Services"
        }
    ],
    "sg:phone":"+1 402 629 4557",
    "sg:postcode":"68406",
    "sg:province":"NE",
    "wof:name":"Roits Repair",
    "wof:placetype":"venue"
},
  "geometry": {"coordinates":[-97.39104,40.50262],"type":"Point"}
}