{
  "type": "Feature",
  "properties": {
    "iso:country":"US",
    "sg:address":"109 E 2nd St",
    "sg:city":"North Platte",
    "sg:classifiers":[
        {
            "category":"Organizations",
            "subcategory":"Religious Organization",
            "type":"Services"
        }
    ],
    "sg:phone":"+1 308 534 1170",
    "sg:postcode":"69101",
    "sg:province":"NE",
    "sg:tags":[
        "church"
    ],
    "sg:website":"www.oregontrailbaptist.com",
    "wof:name":"Oregon Trail Baptist Assoc",
    "wof:placetype":"venue"
},
  "geometry": {"coordinates":[-100.763583,41.134629],"type":"Point"}
}