{
  "type": "Feature",
  "properties": {
    "iso:country":"US",
    "sg:address":"4430 S 25th St",
    "sg:city":"Omaha",
    "sg:classifiers":[
        {
            "category":"Shopping",
            "subcategory":"Hobbies, Toys, & Games",
            "type":"Retail Goods"
        }
    ],
    "sg:phone":"+1 402 734 1442",
    "sg:postcode":"68107",
    "sg:province":"NE",
    "sg:tags":[
        "craft"
    ],
    "wof:name":"Jacob's Crafts",
    "wof:placetype":"venue"
},
  "geometry": {"coordinates":[-95.94861400000001,41.215125],"type":"Point"}
}