{
  "type": "Feature",
  "properties": {
    "addr:full":"644 F St Pawnee City NE 68420",
    "addr:housenumber":"644",
    "addr:postcode":"68420",
    "addr:street":"F St",
    "iso:country":"US",
    "sg:address":"644 F St",
    "sg:city":"Pawnee City",
    "sg:classifiers":[
        {
            "category":"Organizations",
            "subcategory":"Community Association",
            "type":"Services"
        }
    ],
    "sg:phone":"+1 402 852 2931",
    "sg:postcode":"68420",
    "sg:province":"NE",
    "sg:tags":[
        "fraternal"
    ],
    "wof:name":"Veterans Of Foreign Wars",
    "wof:placetype":"venue"
},
  "geometry": {"coordinates":[-96.15425,40.108518],"type":"Point"}
}