{
  "type": "Feature",
  "properties": {
    "addr:full":"902 21st Ave Scottsbluff NE 69361",
    "addr:housenumber":"902",
    "addr:postcode":"69361",
    "addr:street":"21St Ave",
    "iso:country":"US",
    "sg:address":"902 21st Ave",
    "sg:city":"Scottsbluff",
    "sg:classifiers":[
        {
            "category":"Utilities",
            "subcategory":"Mobile Phone",
            "type":"Services"
        }
    ],
    "sg:phone":"+1 308 635 7943",
    "sg:postcode":"69361",
    "sg:province":"NE",
    "sg:tags":[
        "merchandise"
    ],
    "wof:name":"Alltel",
    "wof:placetype":"venue"
},
  "geometry": {"coordinates":[-103.636268,41.854423],"type":"Point"}
}