{
  "type": "Feature",
  "properties": {
    "iso:country":"US",
    "sg:address":"3900 Webster St",
    "sg:city":"Omaha",
    "sg:classifiers":[
        {
            "category":"Social Services",
            "subcategory":"Child Care",
            "type":"Services"
        }
    ],
    "sg:phone":"+1 402 553 1708",
    "sg:postcode":"68131",
    "sg:province":"NE",
    "sg:tags":[
        "day"
    ],
    "wof:name":"St Cecilia Cathedral Day Care",
    "wof:placetype":"venue"
},
  "geometry": {"coordinates":[-95.969797,41.265959],"type":"Point"}
}