{
  "type": "Feature",
  "properties": {
    "addr:full":"4200 D St Lincoln NE 68510",
    "addr:housenumber":"4200",
    "addr:postcode":"68510",
    "addr:street":"D St",
    "iso:country":"US",
    "sg:address":"4200 D St",
    "sg:city":"Lincoln",
    "sg:classifiers":[
        {
            "category":"Manufacturing",
            "subcategory":"Metals",
            "type":"Manufacturing & Wholesale Goods"
        }
    ],
    "sg:phone":"+1 402 488 8343",
    "sg:postcode":"68510",
    "sg:province":"NE",
    "sg:tags":[
        "fence"
    ],
    "wof:name":"Superior Fence",
    "wof:placetype":"venue"
},
  "geometry": {"coordinates":[-96.65938199999999,40.80264],"type":"Point"}
}