{
  "type": "Feature",
  "properties": {
    "addr:full":"1018 W 1st Ave Wayne NE 68787",
    "addr:housenumber":"1018",
    "addr:postcode":"68787",
    "addr:street":"W 1St Ave",
    "iso:country":"US",
    "sg:address":"1018 W 1st Ave",
    "sg:city":"Wayne",
    "sg:classifiers":[
        {
            "category":"Building & Trades",
            "subcategory":"Construction",
            "type":"Services"
        }
    ],
    "sg:phone":"+1 402 375 3811",
    "sg:postcode":"68787",
    "sg:province":"NE",
    "sg:tags":[
        "house",
        "contract"
    ],
    "wof:name":"Jon A Haase Remodeling",
    "wof:placetype":"venue"
},
  "geometry": {"coordinates":[-97.03161900000001,42.229762],"type":"Point"}
}