{
  "type": "Feature",
  "properties": {
    "addr:full":"1142 Cornhusker Hwy Lincoln NE 68521",
    "addr:housenumber":"1142",
    "addr:postcode":"68521",
    "addr:street":"Cornhusker Hwy",
    "iso:country":"US",
    "sg:address":"1142 Cornhusker Hwy",
    "sg:city":"Lincoln",
    "sg:classifiers":[
        {
            "category":"Retail",
            "subcategory":"Self-service Laundry",
            "type":"Services"
        }
    ],
    "sg:phone":"+1 402 466 8353",
    "sg:postcode":"68521",
    "sg:province":"NE",
    "wof:name":"Belmont City Laundry",
    "wof:placetype":"venue"
},
  "geometry": {"coordinates":[-96.702325,40.838577],"type":"Point"}
}