{
  "type": "Feature",
  "properties": {
    "addr:full":"729 S Burlington Ave Hastings NE 68901",
    "addr:housenumber":"729",
    "addr:postcode":"68901",
    "addr:street":"S Burlington Ave",
    "iso:country":"US",
    "sg:address":"729 S Burlington Ave",
    "sg:city":"Hastings",
    "sg:classifiers":[
        {
            "category":"Restaurant",
            "type":"Food & Drink"
        }
    ],
    "sg:menulink":"http://www.allmenus.com/ne/hastings/96351-taco-johns/menu/",
    "sg:phone":"+1 402 462 4211",
    "sg:postcode":"68901",
    "sg:province":"NE",
    "sg:tags":[
        "american",
        "mexican"
    ],
    "wof:name":"Taco John's",
    "wof:placetype":"venue"
},
  "geometry": {"coordinates":[-98.39248600000001,40.5766],"type":"Point"}
}