{
  "type": "Feature",
  "properties": {
    "addr:full":"414 Pine St Omaha NE 68108",
    "addr:housenumber":"414",
    "addr:postcode":"68108",
    "addr:street":"Pine St",
    "iso:country":"US",
    "sg:address":"414 Pine St",
    "sg:city":"Omaha",
    "sg:classifiers":[
        {
            "category":"Health Services",
            "subcategory":"Health Practitioner",
            "type":"Services"
        }
    ],
    "sg:phone":"+1 402 346 3795",
    "sg:postcode":"68108",
    "sg:province":"NE",
    "wof:name":"Massage Good Shepherd",
    "wof:placetype":"venue"
},
  "geometry": {"coordinates":[-95.922622,41.243884],"type":"Point"}
}