{
  "type": "Feature",
  "properties": {
    "iso:country":"US",
    "sg:address":"508 Lincoln St",
    "sg:city":"Wausa",
    "sg:classifiers":[
        {
            "category":"Insurance",
            "subcategory":"Insurance Agent",
            "type":"Services"
        }
    ],
    "sg:phone":"+1 402 586 2448",
    "sg:postcode":"68786",
    "sg:province":"NE",
    "wof:name":"Acklie Insurance Agency",
    "wof:placetype":"venue"
},
  "geometry": {"coordinates":[-97.540663,42.495417],"type":"Point"}
}