{
  "type": "Feature",
  "properties": {
    "addr:full":"17610 Storage Rd Omaha NE 68136",
    "addr:housenumber":"17610",
    "addr:postcode":"68136",
    "addr:street":"Storage Rd",
    "iso:country":"US",
    "sg:address":"17610 Storage Rd",
    "sg:city":"Omaha",
    "sg:classifiers":[
        {
            "category":"Building & Trades",
            "subcategory":"Construction",
            "type":"Services"
        }
    ],
    "sg:phone":"+1 402 894 0657",
    "sg:postcode":"68136",
    "sg:province":"NE",
    "sg:tags":[
        "masonry",
        "contractor"
    ],
    "wof:name":"WALZ Masonry Inc",
    "wof:placetype":"venue"
},
  "geometry": {"coordinates":[-96.19044100000001,41.182949],"type":"Point"}
}