{
  "type": "Feature",
  "properties": {
    "iso:country":"US",
    "sg:address":"2318 N 189th Cir",
    "sg:city":"Elkhorn",
    "sg:classifiers":[
        {
            "category":"Building & Trades",
            "subcategory":"Pest Control",
            "type":"Services"
        }
    ],
    "sg:phone":"+1 402 315 9318",
    "sg:postcode":"68022",
    "sg:province":"NE",
    "wof:name":"Good Fellas Exterminating",
    "wof:placetype":"venue"
},
  "geometry": {"coordinates":[-96.212557,41.280726],"type":"Point"}
}