{
  "type": "Feature",
  "properties": {
    "iso:country":"US",
    "sg:address":"6900 NW 140th St",
    "sg:city":"Pleasant Dale",
    "sg:phone":"+1 402 588 2417",
    "sg:postcode":"68423",
    "sg:province":"NE",
    "sg:tags":[
        "farm",
        "field",
        "corn",
        "soybean",
        "crop"
    ],
    "wof:name":"Richard Gehle",
    "wof:placetype":"venue"
},
  "geometry": {"coordinates":[-96.910437,40.883499],"type":"Point"}
}