{
  "type": "Feature",
  "properties": {
    "iso:country":"US",
    "sg:address":"3179 31st Ave",
    "sg:city":"Columbus",
    "sg:classifiers":[
        {
            "category":"Real Estate",
            "subcategory":"Real Estate Agent",
            "type":"Services"
        }
    ],
    "sg:phone":"+1 402 564 9043",
    "sg:postcode":"68601",
    "sg:province":"NE",
    "sg:tags":[
        "appraiser"
    ],
    "wof:name":"Dave Mullin",
    "wof:placetype":"venue"
},
  "geometry": {"coordinates":[-97.366124,41.446379],"type":"Point"}
}