{
  "type": "Feature",
  "properties": {
    "iso:country":"US",
    "sg:address":"18150 Wright St",
    "sg:city":"Omaha",
    "sg:classifiers":[
        {
            "category":"Retail",
            "subcategory":"Laundry & Dry Cleaning",
            "type":"Services"
        }
    ],
    "sg:phone":"+1 402 330 3750",
    "sg:postcode":"68130",
    "sg:province":"NE",
    "sg:tags":[
        "cleaners"
    ],
    "sg:website":"www.maxiwalker.com",
    "wof:name":"Max I Walker 70",
    "wof:placetype":"venue"
},
  "geometry": {"coordinates":[-96.199684,41.23319],"type":"Point"}
}