{
  "type": "Feature",
  "properties": {
    "addr:full":"201 N 13th St Lincoln NE 68508",
    "addr:housenumber":"201",
    "addr:postcode":"68508",
    "addr:street":"N 13Th St",
    "iso:country":"US",
    "sg:address":"201 N 13th St",
    "sg:city":"Lincoln",
    "sg:classifiers":[
        {
            "category":"Real Estate",
            "subcategory":"Developer",
            "type":"Services"
        }
    ],
    "sg:phone":"+1 402 474 4909",
    "sg:postcode":"68508",
    "sg:province":"NE",
    "wof:name":"Center Associates",
    "wof:placetype":"venue"
},
  "geometry": {"coordinates":[-96.70257599999999,40.815844],"type":"Point"}
}