{
  "type": "Feature",
  "properties": {
    "iso:country":"US",
    "sg:address":"1800 N Nye Ave",
    "sg:city":"Fremont",
    "sg:classifiers":[
        {
            "category":"Professional",
            "type":"Services"
        }
    ],
    "sg:phone":"+1 402 727 7872",
    "sg:postcode":"68025",
    "sg:province":"NE",
    "sg:tags":[
        "establishment"
    ],
    "wof:name":"Mock Clarence E",
    "wof:placetype":"venue"
},
  "geometry": {"coordinates":[-96.501819,41.446383],"type":"Point"}
}