{
  "type": "Feature",
  "properties": {
    "iso:country":"US",
    "sg:address":"103 Hillcrest Ave",
    "sg:city":"Bellevue",
    "sg:classifiers":[
        {
            "category":"Social Services",
            "type":"Services"
        }
    ],
    "sg:phone":"+1 402 449 2571",
    "sg:postcode":"68005",
    "sg:province":"NE",
    "sg:tags":[
        "counselor",
        "marriage",
        "family"
    ],
    "wof:name":"Team Counseling Svc",
    "wof:placetype":"venue"
},
  "geometry": {"coordinates":[-95.91609800000001,41.160674],"type":"Point"}
}