{
  "type": "Feature",
  "properties": {
    "iso:country":"US",
    "sg:address":"3001 Cornhusker Hwy",
    "sg:city":"Lincoln",
    "sg:classifiers":[
        {
            "category":"Freight",
            "type":"Transportation"
        }
    ],
    "sg:phone":"+1 402 466 8411",
    "sg:postcode":"68504",
    "sg:province":"NE",
    "sg:tags":[
        "grain",
        "elevator"
    ],
    "sg:website":"www.cargill.com",
    "wof:name":"Cargill Ag Horizons",
    "wof:placetype":"venue"
},
  "geometry": {"coordinates":[-96.67823300000001,40.842434],"type":"Point"}
}