{
  "type": "Feature",
  "properties": {
    "addr:full":"6790 Grover St Omaha NE 68106",
    "addr:housenumber":"6790",
    "addr:postcode":"68106",
    "addr:street":"Grover St",
    "iso:country":"US",
    "sg:address":"6790 Grover St",
    "sg:city":"Omaha",
    "sg:classifiers":[
        {
            "category":"Professional",
            "subcategory":"Business Services",
            "type":"Services"
        }
    ],
    "sg:phone":"+1 402 894 0476",
    "sg:postcode":"68106",
    "sg:province":"NE",
    "wof:name":"National Business Svc",
    "wof:placetype":"venue"
},
  "geometry": {"coordinates":[-96.017089,41.227103],"type":"Point"}
}