{
  "type": "Feature",
  "properties": {
    "addr:full":"4417 Q St Omaha NE 68107",
    "addr:housenumber":"4417",
    "addr:postcode":"68107",
    "addr:street":"Q St",
    "iso:country":"US",
    "sg:address":"4417 Q St",
    "sg:city":"Omaha",
    "sg:classifiers":[
        {
            "category":"Autos & Motor Vehicles",
            "subcategory":"Automobile Sales",
            "type":"Retail Goods"
        }
    ],
    "sg:phone":"+1 402 734 2278",
    "sg:postcode":"68107",
    "sg:province":"NE",
    "sg:tags":[
        "cart"
    ],
    "wof:name":"Jody's Kart Shop",
    "wof:placetype":"venue"
},
  "geometry": {"coordinates":[-95.981527,41.205262],"type":"Point"}
}