{
  "type": "Feature",
  "properties": {
    "iso:country":"US",
    "sg:address":"2665 Farnam St",
    "sg:city":"Omaha",
    "sg:classifiers":[
        {
            "category":"Organizations",
            "subcategory":"Membership Organization",
            "type":"Services"
        }
    ],
    "sg:phone":"+1 402 344 2242",
    "sg:postcode":"68131",
    "sg:province":"NE",
    "sg:tags":[
        "charitable"
    ],
    "wof:name":"Leukemia Soc Amer Neb Chapter",
    "wof:placetype":"venue"
},
  "geometry": {"coordinates":[-95.95116899999999,41.257596],"type":"Point"}
}