{
  "type": "Feature",
  "properties": {
    "addr:full":"2212 O St Lincoln NE 68510",
    "addr:housenumber":"2212",
    "addr:postcode":"68510",
    "addr:street":"O St",
    "iso:country":"US",
    "sg:address":"2212 O St",
    "sg:city":"Lincoln",
    "sg:classifiers":[
        {
            "category":"Retail",
            "subcategory":"Auto Repair",
            "type":"Services"
        }
    ],
    "sg:phone":"+1 402 477 2244",
    "sg:postcode":"68510",
    "sg:province":"NE",
    "sg:tags":[
        "automobile",
        "co",
        "drive",
        "transporter"
    ],
    "wof:name":"Nebraska Auto Transport",
    "wof:placetype":"venue"
},
  "geometry": {"coordinates":[-96.688209,40.813668],"type":"Point"}
}