{
  "type": "Feature",
  "properties": {
    "iso:country":"US",
    "sg:address":"380 S Maple St",
    "sg:city":"Nelson",
    "sg:classifiers":[
        {
            "category":"Museum",
            "type":"Entertainment"
        }
    ],
    "sg:phone":"+1 402 225 4117",
    "sg:postcode":"68961",
    "sg:province":"NE",
    "wof:name":"Vietnam War Museum",
    "wof:placetype":"venue"
},
  "geometry": {"coordinates":[-98.071472,40.201486],"type":"Point"}
}