{
  "type": "Feature",
  "properties": {
    "addr:city":"Nelson",
    "addr:full":"380 S Maple St Nelson, Ne 68961",
    "addr:house_number":"380",
    "addr:housenumber":"380",
    "addr:phone":"+1 402-225-2351",
    "addr:postcode":"68961",
    "addr:road":"S Maple St",
    "addr:state":"NE",
    "addr:street":"S Maple St",
    "iso:country":"US",
    "sg:address":"380 S Maple St",
    "sg:city":"Nelson",
    "sg:classifiers":[
        {
            "category":"Museum",
            "type":"Entertainment"
        }
    ],
    "sg:phone":"+1 402 225 4117",
    "sg:postcode":"68961",
    "sg:province":"NE",
    "wof:name":"Vietnam War National Museum",
    "wof:placetype":"venue"
},
  "geometry": {"coordinates":[-98.04995,40.20213],"type":"Point"}
}