{
  "type": "Feature",
  "properties": {
    "addr:full":"333 N Cotner Blvd Lincoln NE 68505",
    "addr:housenumber":"333",
    "addr:postcode":"68505",
    "addr:street":"N Cotner Blvd",
    "iso:country":"US",
    "sg:address":"333 N Cotner Blvd",
    "sg:city":"Lincoln",
    "sg:classifiers":[
        {
            "category":"Personal",
            "type":"Services"
        }
    ],
    "sg:phone":"+1 402 464 0001",
    "sg:postcode":"68505",
    "sg:province":"NE",
    "sg:tags":[
        "spa",
        "tanning"
    ],
    "wof:name":"Sun Palace Tanning Spas",
    "wof:placetype":"venue"
},
  "geometry": {"coordinates":[-96.64134199999999,40.816338],"type":"Point"}
}