{
  "type": "Feature",
  "properties": {
    "iso:country":"US",
    "sg:address":"5446 N 90th St",
    "sg:city":"Omaha",
    "sg:classifiers":[
        {
            "category":"Restaurant",
            "type":"Food & Drink"
        }
    ],
    "sg:phone":"+1 402 571 2000",
    "sg:postcode":"68134",
    "sg:province":"NE",
    "wof:name":"House Of Lee",
    "wof:placetype":"venue"
},
  "geometry": {"coordinates":[-96.05269199999999,41.308107],"type":"Point"}
}