{
  "type": "Feature",
  "properties": {
    "iso:country":"US",
    "sg:address":"2501 Ames Ave",
    "sg:city":"Omaha",
    "sg:classifiers":[
        {
            "category":"Recreation",
            "type":"Entertainment"
        },
        {
            "category":"Organizations",
            "subcategory":"Community Association",
            "type":"Services"
        }
    ],
    "sg:phone":"+1 402 451 5714",
    "sg:postcode":"68111",
    "sg:province":"NE",
    "sg:tags":[
        "club",
        "membership"
    ],
    "wof:name":"Los -Diablos Motorcycle Club",
    "wof:placetype":"venue"
},
  "geometry": {"coordinates":[-95.94935599999999,41.299603],"type":"Point"}
}