{
  "type": "Feature",
  "properties": {
    "addr:full":"2281 Stork Cir Fremont NE 68025",
    "addr:housenumber":"2281",
    "addr:postcode":"68025",
    "addr:street":"Stork Cir",
    "iso:country":"US",
    "sg:address":"2281 Stork Cir",
    "sg:city":"Fremont",
    "sg:classifiers":[
        {
            "category":"Building & Trades",
            "subcategory":"Construction",
            "type":"Services"
        }
    ],
    "sg:phone":"+1 402 727 8981",
    "sg:postcode":"68025",
    "sg:province":"NE",
    "sg:tags":[
        "house"
    ],
    "wof:name":"Tradewind Homes Corp",
    "wof:placetype":"venue"
},
  "geometry": {"coordinates":[-96.467388,41.421582],"type":"Point"}
}