{
  "type": "Feature",
  "properties": {
    "iso:country":"US",
    "sg:address":"420 W Norfolk Ave",
    "sg:city":"Norfolk",
    "sg:classifiers":[
        {
            "category":"Deli",
            "type":"Food & Drink"
        },
        {
            "category":"Restaurant",
            "type":"Food & Drink"
        }
    ],
    "sg:menulink":"http://www.allmenus.com/ne/norfolk/233122-little-king/menu/",
    "sg:phone":"+1 402 371 1124",
    "sg:postcode":"68701",
    "sg:province":"NE",
    "sg:tags":[
        "deli",
        "wrap",
        "american",
        "sandwich"
    ],
    "wof:name":"Little King",
    "wof:placetype":"venue"
},
  "geometry": {"coordinates":[-97.41233099999999,42.032787],"type":"Point"}
}