{
  "type": "Feature",
  "properties": {
    "addr:full":"1125 Beal St Grand Island NE 68801",
    "addr:housenumber":"1125",
    "addr:postcode":"68801",
    "addr:street":"Beal St",
    "iso:country":"US",
    "sg:address":"1125 Beal St",
    "sg:city":"Grand Island",
    "sg:classifiers":[
        {
            "category":"Organizations",
            "subcategory":"Religious Organization",
            "type":"Services"
        }
    ],
    "sg:phone":"+1 308 384 2268",
    "sg:postcode":"68801",
    "sg:province":"NE",
    "wof:name":"Harvest Time Baptist Church",
    "wof:placetype":"venue"
},
  "geometry": {"coordinates":[-98.335967,40.937534],"type":"Point"}
}