{
  "type": "Feature",
  "properties": {
    "addr:full":"1950 Jefferson Ave Lincoln NE 68502",
    "addr:housenumber":"1950",
    "addr:postcode":"68502",
    "addr:street":"Jefferson Ave",
    "iso:country":"US",
    "sg:address":"1950 Jefferson Ave",
    "sg:city":"Lincoln",
    "sg:classifiers":[
        {
            "category":"Real Estate",
            "subcategory":"Real Estate Agent",
            "type":"Services"
        }
    ],
    "sg:phone":"+1 402 483 6233",
    "sg:postcode":"68502",
    "sg:province":"NE",
    "wof:name":"J&J Ventures",
    "wof:placetype":"venue"
},
  "geometry": {"coordinates":[-96.678478,40.793137],"type":"Point"}
}