{
  "type": "Feature",
  "properties": {
    "iso:country":"US",
    "sg:address":"2851 Capehart Rd",
    "sg:city":"Bellevue",
    "sg:classifiers":[
        {
            "category":"Cinema",
            "subcategory":"Movie Rental",
            "type":"Entertainment"
        }
    ],
    "sg:phone":"+1 402 292 2240",
    "sg:postcode":"68123",
    "sg:province":"NE",
    "sg:tags":[
        "video",
        "tape"
    ],
    "wof:name":"Main Street Movies",
    "wof:placetype":"venue"
},
  "geometry": {"coordinates":[-95.953402,41.120451],"type":"Point"}
}