{
  "type": "Feature",
  "properties": {
    "iso:country":"US",
    "sg:address":"3420 N 22nd St",
    "sg:city":"Lincoln",
    "sg:classifiers":[
        {
            "category":"Wholesale",
            "subcategory":"Auto Parts",
            "type":"Manufacturing & Wholesale Goods"
        }
    ],
    "sg:phone":"+1 402 435 3030",
    "sg:postcode":"68521",
    "sg:province":"NE",
    "sg:tags":[
        "used"
    ],
    "wof:name":"Genes Hubcaps",
    "wof:placetype":"venue"
},
  "geometry": {"coordinates":[-96.68969,40.847537],"type":"Point"}
}