{
  "type": "Feature",
  "properties": {
    "iso:country":"US",
    "sg:address":"1505 Stable Dr",
    "sg:city":"South Sioux City",
    "sg:classifiers":[
        {
            "category":"Autos & Motor Vehicles",
            "subcategory":"Automobile Sales",
            "type":"Retail Goods"
        }
    ],
    "sg:phone":"+1 402 494 7649",
    "sg:postcode":"68776",
    "sg:province":"NE",
    "sg:tags":[
        "car",
        "dealer"
    ],
    "wof:name":"Rezcar",
    "wof:placetype":"venue"
},
  "geometry": {"coordinates":[-96.43123900000001,42.438481],"type":"Point"}
}