{
  "type": "Feature",
  "properties": {
    "addr:full":"1007 S C Rd Phillips NE 68865",
    "addr:housenumber":"1007",
    "addr:postcode":"68865",
    "addr:street":"S C Rd",
    "iso:country":"US",
    "sg:address":"1007 S C Rd",
    "sg:city":"Phillips",
    "sg:classifiers":[
        {
            "category":"Building & Trades",
            "subcategory":"Landscaping Services",
            "type":"Services"
        }
    ],
    "sg:phone":"+1 402 886 2578",
    "sg:postcode":"68865",
    "sg:province":"NE",
    "sg:tags":[
        "landscape"
    ],
    "wof:name":"Country Pride",
    "wof:placetype":"venue"
},
  "geometry": {"coordinates":[-98.245272,40.831305],"type":"Point"}
}