{
  "type": "Feature",
  "properties": {
    "iso:country":"US",
    "sg:address":"602 S 72nd St",
    "sg:city":"Omaha",
    "sg:classifiers":[
        {
            "category":"Home & Garden",
            "subcategory":"Building Materials",
            "type":"Retail Goods"
        }
    ],
    "sg:phone":"+1 402 397 2600",
    "sg:postcode":"68114",
    "sg:province":"NE",
    "wof:name":"Oreck",
    "wof:placetype":"venue"
},
  "geometry": {"coordinates":[-96.02391,41.25534],"type":"Point"}
}