{
  "type": "Feature",
  "properties": {
    "iso:country":"US",
    "sg:address":"1308 Douglas St",
    "sg:city":"Wayne",
    "sg:classifiers":[
        {
            "category":"Farming",
            "subcategory":"Farm",
            "type":"Manufacturing & Wholesale Goods"
        }
    ],
    "sg:phone":"+1 402 375 1142",
    "sg:postcode":"68787",
    "sg:province":"NE",
    "sg:tags":[
        "crop",
        "general"
    ],
    "wof:name":"Rolling Hills Farm",
    "wof:placetype":"venue"
},
  "geometry": {"coordinates":[-97.02227999999999,42.241482],"type":"Point"}
}