{
  "type": "Feature",
  "properties": {
    "iso:country":"US",
    "sg:address":"1107 O St",
    "sg:city":"Neligh",
    "sg:classifiers":[
        {
            "category":"Travel",
            "subcategory":"Hotels & Motels",
            "type":"Entertainment"
        }
    ],
    "sg:phone":"+1 402 887 4186",
    "sg:postcode":"68756",
    "sg:province":"NE",
    "wof:name":"West Hill View Motel",
    "wof:placetype":"venue"
},
  "geometry": {"coordinates":[-98.03218099999999,42.138606],"type":"Point"}
}