{
  "type": "Feature",
  "properties": {
    "iso:country":"US",
    "sg:address":"2800 Towle St",
    "sg:city":"Falls City",
    "sg:classifiers":[
        {
            "category":"Health Services",
            "subcategory":"Nursing And Care Facility",
            "type":"Services"
        }
    ],
    "sg:phone":"+1 402 245 5252",
    "sg:postcode":"68355",
    "sg:province":"NE",
    "sg:tags":[
        "home",
        "convalescent"
    ],
    "wof:name":"Falls City Care Center",
    "wof:placetype":"venue"
},
  "geometry": {"coordinates":[-95.606241,40.072206],"type":"Point"}
}