{
  "type": "Feature",
  "properties": {
    "addr:full":"905 S Kimball St Grand Island NE 68801",
    "addr:housenumber":"905",
    "addr:postcode":"68801",
    "addr:street":"S Kimball St",
    "iso:country":"US",
    "sg:address":"905 S Kimball St",
    "sg:city":"Grand Island",
    "sg:classifiers":[
        {
            "category":"Communications",
            "subcategory":"Radio Station",
            "type":"Services"
        }
    ],
    "sg:phone":"+1 308 384 6004",
    "sg:postcode":"68801",
    "sg:province":"NE",
    "sg:tags":[
        "company",
        "broadcasting"
    ],
    "wof:name":"KFAB",
    "wof:placetype":"venue"
},
  "geometry": {"coordinates":[-98.336066,40.914666],"type":"Point"}
}