{
  "type": "Feature",
  "properties": {
    "iso:country":"US",
    "sg:address":"5643 S 114th St",
    "sg:city":"Omaha",
    "sg:classifiers":[
        {
            "category":"Personal",
            "subcategory":"Beauty Salon",
            "type":"Services"
        }
    ],
    "sg:phone":"+1 402 339 2695",
    "sg:postcode":"68137",
    "sg:province":"NE",
    "sg:tags":[
        "shop"
    ],
    "wof:name":"Bevs Beauty Shop",
    "wof:placetype":"venue"
},
  "geometry": {"coordinates":[-96.09031299999999,41.200973],"type":"Point"}
}