{
  "type": "Feature",
  "properties": {
    "iso:country":"US",
    "sg:address":"123 N 7th St",
    "sg:city":"Loup City",
    "sg:classifiers":[
        {
            "category":"Retail",
            "subcategory":"Funeral Services",
            "type":"Services"
        }
    ],
    "sg:phone":"+1 308 745 0344",
    "sg:postcode":"68853",
    "sg:province":"NE",
    "sg:tags":[
        "director"
    ],
    "wof:name":"Peters Funeral Home",
    "wof:placetype":"venue"
},
  "geometry": {"coordinates":[-98.967365,41.276773],"type":"Point"}
}