{
  "type": "Feature",
  "properties": {
    "addr:full":"6901 N 72nd St Omaha NE 68122",
    "addr:housenumber":"6901",
    "addr:postcode":"68122",
    "addr:street":"N 72Nd St",
    "iso:country":"US",
    "sg:address":"6901 N 72nd St",
    "sg:city":"Omaha",
    "sg:classifiers":[
        {
            "category":"Health Services",
            "subcategory":"Doctor",
            "type":"Services"
        }
    ],
    "sg:phone":"+1 402 572 2960",
    "sg:postcode":"68122",
    "sg:province":"NE",
    "sg:tags":[
        "medical"
    ],
    "wof:name":"David Schmidt MD",
    "wof:placetype":"venue"
},
  "geometry": {"coordinates":[-96.023833,41.320732],"type":"Point"}
}