{
  "type": "Feature",
  "properties": {
    "iso:country":"US",
    "sg:address":"1606 S 62nd Rd",
    "sg:city":"Nebraska City",
    "sg:classifiers":[
        {
            "category":"Farming",
            "subcategory":"Farm",
            "type":"Manufacturing & Wholesale Goods"
        }
    ],
    "sg:phone":"+1 402 873 3098",
    "sg:postcode":"68410",
    "sg:province":"NE",
    "sg:tags":[
        "crop",
        "general"
    ],
    "wof:name":"Vock John",
    "wof:placetype":"venue"
},
  "geometry": {"coordinates":[-95.878489,40.558536],"type":"Point"}
}