{
  "type": "Feature",
  "properties": {
    "addr:full":"600 7th St Utica NE 68456",
    "addr:housenumber":"600",
    "addr:postcode":"68456",
    "addr:street":"7Th St",
    "iso:country":"US",
    "sg:address":"600 7th St",
    "sg:city":"Utica",
    "sg:phone":"+1 402 534 2391",
    "sg:postcode":"68456",
    "sg:province":"NE",
    "sg:tags":[
        "farm",
        "corn",
        "soybean"
    ],
    "wof:name":"William D Luebbe",
    "wof:placetype":"venue"
},
  "geometry": {"coordinates":[-97.34391599999999,40.900055],"type":"Point"}
}