{
  "type": "Feature",
  "properties": {
    "addr:full":"470 State Hwy 11 Dannebrog NE 68831",
    "addr:housenumber":"470",
    "addr:postcode":"68831",
    "addr:street":"State Hwy 11 Dannebrog Ne",
    "iso:country":"US",
    "sg:address":"470 State Hwy 11",
    "sg:city":"Dannebrog",
    "sg:classifiers":[
        {
            "category":"Recreation",
            "type":"Entertainment"
        }
    ],
    "sg:phone":"+1 308 226 2436",
    "sg:postcode":"68831",
    "sg:province":"NE",
    "wof:name":"Loup Valley Retreat LLC",
    "wof:placetype":"venue"
},
  "geometry": {"coordinates":[-98.55891800000001,41.098511],"type":"Point"}
}