{
  "type": "Feature",
  "properties": {
    "iso:country":"US",
    "sg:address":"2105 Jefferson St",
    "sg:city":"Beatrice",
    "sg:classifiers":[
        {
            "category":"Social Services",
            "subcategory":"Child Care",
            "type":"Services"
        }
    ],
    "sg:phone":"+1 402 228 2749",
    "sg:postcode":"68310",
    "sg:province":"NE",
    "sg:tags":[
        "day"
    ],
    "wof:name":"Carolyn Junker",
    "wof:placetype":"venue"
},
  "geometry": {"coordinates":[-96.724701,40.274295],"type":"Point"}
}