{
  "type": "Feature",
  "properties": {
    "iso:country":"US",
    "sg:address":"2 Market St",
    "sg:city":"Beatrice",
    "sg:classifiers":[
        {
            "category":"Autos & Motor Vehicles",
            "subcategory":"Auto Supplies",
            "type":"Retail Goods"
        }
    ],
    "sg:phone":"+1 402 228 3791",
    "sg:postcode":"68310",
    "sg:province":"NE",
    "wof:name":"Cats Auto Supply",
    "wof:placetype":"venue"
},
  "geometry": {"coordinates":[-96.75290099999999,40.264799],"type":"Point"}
}