{
  "type": "Feature",
  "properties": {
    "iso:country":"US",
    "sg:address":"4309 Randolph St",
    "sg:city":"Lincoln",
    "sg:classifiers":[
        {
            "category":"Social Services",
            "type":"Services"
        }
    ],
    "sg:phone":"+1 402 327 9812",
    "sg:postcode":"68510",
    "sg:province":"NE",
    "wof:name":"Judy C Magnuson PHD",
    "wof:placetype":"venue"
},
  "geometry": {"coordinates":[-96.65854400000001,40.806115],"type":"Point"}
}