{
  "type": "Feature",
  "properties": {
    "addr:full":"2609 Sheridan Rd Bellevue NE 68123",
    "addr:housenumber":"2609",
    "addr:postcode":"68123",
    "addr:street":"Sheridan Rd",
    "iso:country":"US",
    "sg:address":"2609 Sheridan Rd",
    "sg:city":"Bellevue",
    "sg:classifiers":[
        {
            "category":"Shopping",
            "subcategory":"Hobbies, Toys, & Games",
            "type":"Retail Goods"
        }
    ],
    "sg:phone":"+1 402 292 6290",
    "sg:postcode":"68123",
    "sg:province":"NE",
    "sg:tags":[
        "basket"
    ],
    "sg:website":"www.longaberger.com",
    "wof:name":"Longaberger",
    "wof:placetype":"venue"
},
  "geometry": {"coordinates":[-95.95148399999999,41.111257],"type":"Point"}
}