{
  "type": "Feature",
  "properties": {
    "iso:country":"US",
    "sg:address":"4866 S 96th St",
    "sg:city":"Omaha",
    "sg:classifiers":[
        {
            "category":"Health Services",
            "subcategory":"Doctor",
            "type":"Services"
        }
    ],
    "sg:phone":"+1 402 331 4444",
    "sg:postcode":"68127",
    "sg:province":"NE",
    "sg:tags":[
        "dentist"
    ],
    "wof:name":"Matthew Bolamperti DDS",
    "wof:placetype":"venue"
},
  "geometry": {"coordinates":[-96.06209699999999,41.208973],"type":"Point"}
}