{
  "type": "Feature",
  "properties": {
    "iso:country":"US",
    "sg:address":"1917 46th St",
    "sg:city":"Columbus",
    "sg:phone":"+1 402 564 5366",
    "sg:postcode":"68601",
    "sg:province":"NE",
    "sg:tags":[
        "farm",
        "corn",
        "soybean"
    ],
    "wof:name":"Norman Behrens",
    "wof:placetype":"venue"
},
  "geometry": {"coordinates":[-97.34962,41.46134],"type":"Point"}
}