{
  "type": "Feature",
  "properties": {
    "iso:country":"US",
    "sg:address":"1506 S 60th St",
    "sg:city":"Omaha",
    "sg:classifiers":[
        {
            "category":"Bars & Pubs",
            "type":"Food & Drink"
        }
    ],
    "sg:phone":"+1 402 556 7686",
    "sg:postcode":"68106",
    "sg:province":"NE",
    "sg:tags":[
        "drinking"
    ],
    "wof:name":"Trackside Lounge",
    "wof:placetype":"venue"
},
  "geometry": {"coordinates":[-96.00479900000001,41.245098],"type":"Point"}
}