{
  "type": "Feature",
  "properties": {
    "addr:full":"703 Broadway St Imperial NE 69033",
    "addr:housenumber":"703",
    "addr:postcode":"69033",
    "addr:street":"Broadway St",
    "iso:country":"US",
    "sg:address":"703 Broadway St",
    "sg:city":"Imperial",
    "sg:classifiers":[
        {
            "category":"Education",
            "subcategory":"Library",
            "type":"Public Place"
        }
    ],
    "sg:phone":"+1 308 882 4754",
    "sg:postcode":"69033",
    "sg:province":"NE",
    "wof:name":"Imperial Public Library",
    "wof:placetype":"venue"
},
  "geometry": {"coordinates":[-101.643035,40.518006],"type":"Point"}
}