{
  "type": "Feature",
  "properties": {
    "addr:full":"820 W 17th St Hastings NE 68901",
    "addr:housenumber":"820",
    "addr:postcode":"68901",
    "addr:street":"W 17Th St",
    "iso:country":"US",
    "sg:address":"820 W 17th St",
    "sg:city":"Hastings",
    "sg:classifiers":[
        {
            "category":"Home & Garden",
            "subcategory":"Garden Supply",
            "type":"Retail Goods"
        }
    ],
    "sg:phone":"+1 402 462 8757",
    "sg:postcode":"68901",
    "sg:province":"NE",
    "sg:tags":[
        "repair"
    ],
    "wof:name":"Genes Repair",
    "wof:placetype":"venue"
},
  "geometry": {"coordinates":[-98.391572,40.603427],"type":"Point"}
}