{
  "type": "Feature",
  "properties": {
    "iso:country":"US",
    "sg:address":"1037 Eagle Rd",
    "sg:city":"Saint Paul",
    "sg:phone":"+1 308 754 4214",
    "sg:postcode":"68873",
    "sg:province":"NE",
    "sg:tags":[
        "farm",
        "field",
        "wheat",
        "crop"
    ],
    "wof:name":"Bill Reimers",
    "wof:placetype":"venue"
},
  "geometry": {"coordinates":[-98.383223,41.188685],"type":"Point"}
}