{
  "type": "Feature",
  "properties": {
    "addr:full":"16401 Dyson Hollow Rd Bellevue NE 68123",
    "addr:housenumber":"16401",
    "addr:postcode":"68123",
    "addr:street":"Dyson Hollow Rd",
    "iso:country":"US",
    "sg:address":"16401 Dyson Hollow Rd",
    "sg:city":"Bellevue",
    "sg:classifiers":[
        {
            "category":"Recreation",
            "type":"Entertainment"
        }
    ],
    "sg:phone":"+1 402 292 2822",
    "sg:postcode":"68123",
    "sg:province":"NE",
    "sg:tags":[
        "stable"
    ],
    "wof:name":"Phoenix Equestrian Ctr Inc",
    "wof:placetype":"venue"
},
  "geometry": {"coordinates":[-95.951741,41.075135],"type":"Point"}
}