{
  "type": "Feature",
  "properties": {
    "iso:country":"US",
    "sg:address":"304 8th St",
    "sg:city":"Scribner",
    "sg:classifiers":[
        {
            "category":"Retail",
            "subcategory":"Repair Shop",
            "type":"Services"
        }
    ],
    "sg:phone":"+1 402 664 3336",
    "sg:postcode":"68057",
    "sg:province":"NE",
    "sg:tags":[
        "appliance"
    ],
    "wof:name":"Glen's Home Appliance Svc",
    "wof:placetype":"venue"
},
  "geometry": {"coordinates":[-96.66018800000001,41.663582],"type":"Point"}
}