{
  "type": "Feature",
  "properties": {
    "addr:full":"1300 Broadway St Mitchell NE 69357",
    "addr:housenumber":"1300",
    "addr:postcode":"69357",
    "addr:street":"Broadway St",
    "iso:country":"US",
    "sg:address":"1300 Broadway St",
    "sg:city":"Mitchell",
    "sg:classifiers":[
        {
            "category":"Restaurant",
            "type":"Food & Drink"
        }
    ],
    "sg:menulink":"http://www.allmenus.com/ne/mitchell/129459-subway/menu/",
    "sg:phone":"+1 308 632 3068",
    "sg:postcode":"69357",
    "sg:province":"NE",
    "sg:tags":[
        "american",
        "sandwich"
    ],
    "wof:name":"Subway",
    "wof:placetype":"venue"
},
  "geometry": {"coordinates":[-103.800087,41.940062],"type":"Point"}
}