{
  "type": "Feature",
  "properties": {
    "iso:country":"US",
    "sg:address":"717 Lake Ave",
    "sg:city":"Gothenburg",
    "sg:classifiers":[
        {
            "category":"Manufacturing",
            "subcategory":"Glass & Minerals",
            "type":"Manufacturing & Wholesale Goods"
        }
    ],
    "sg:phone":"+1 308 537 2608",
    "sg:postcode":"69138",
    "sg:province":"NE",
    "sg:tags":[
        "ready"
    ],
    "wof:name":"Paulsen Inc",
    "wof:placetype":"venue"
},
  "geometry": {"coordinates":[-100.163304,40.925977],"type":"Point"}
}