{
  "type": "Feature",
  "properties": {
    "iso:country":"US",
    "sg:address":"1709 Oakdale Ave",
    "sg:city":"Lincoln",
    "sg:classifiers":[
        {
            "category":"Professional",
            "subcategory":"Business Services",
            "type":"Services"
        }
    ],
    "sg:phone":"+1 402 488 9053",
    "sg:postcode":"68506",
    "sg:province":"NE",
    "wof:name":"Hoenig Enterprises",
    "wof:placetype":"venue"
},
  "geometry": {"coordinates":[-96.61027900000001,40.794167],"type":"Point"}
}