{
  "type": "Feature",
  "properties": {
    "iso:country":"US",
    "sg:address":"1501 M St",
    "sg:city":"Ord",
    "sg:classifiers":[
        {
            "category":"Health Services",
            "subcategory":"Optometrist",
            "type":"Services"
        }
    ],
    "sg:phone":"+1 308 728 3229",
    "sg:postcode":"68862",
    "sg:province":"NE",
    "wof:name":"Professional Eyecare",
    "wof:placetype":"venue"
},
  "geometry": {"coordinates":[-98.929317,41.602139],"type":"Point"}
}