{
  "type": "Feature",
  "properties": {
    "iso:country":"US",
    "sg:address":"814 15th Ave",
    "sg:city":"Franklin",
    "sg:classifiers":[
        {
            "category":"Retail",
            "subcategory":"Auto Repair",
            "type":"Services"
        }
    ],
    "sg:phone":"+1 308 425 6833",
    "sg:postcode":"68939",
    "sg:province":"NE",
    "sg:tags":[
        "repairing",
        "automobile",
        "general"
    ],
    "wof:name":"Sweet's Garage",
    "wof:placetype":"venue"
},
  "geometry": {"coordinates":[-98.953524,40.093399],"type":"Point"}
}