{
  "type": "Feature",
  "properties": {
    "addr:full":"119 E Pierce St Pierce NE 68767",
    "addr:housenumber":"119",
    "addr:postcode":"68767",
    "addr:street":"E Pierce St",
    "iso:country":"US",
    "sg:address":"119 E Pierce St",
    "sg:city":"Pierce",
    "sg:classifiers":[
        {
            "category":"Building & Trades",
            "subcategory":"Plumbing",
            "type":"Services"
        }
    ],
    "sg:phone":"+1 402 329 4792",
    "sg:postcode":"68767",
    "sg:province":"NE",
    "sg:tags":[
        "plumbing",
        "contractor"
    ],
    "wof:name":"J & S Plumbing LLC",
    "wof:placetype":"venue"
},
  "geometry": {"coordinates":[-97.52715999999999,42.200984],"type":"Point"}
}