{
  "type": "Feature",
  "properties": {
    "iso:country":"US",
    "sg:address":"2665 Farnam St",
    "sg:city":"Omaha",
    "sg:classifiers":[
        {
            "category":"Arts & Performance",
            "subcategory":"Arts Center",
            "type":"Entertainment"
        }
    ],
    "sg:phone":"+1 402 342 8835",
    "sg:postcode":"68131",
    "sg:province":"NE",
    "sg:tags":[
        "performing"
    ],
    "wof:name":"Omaha Theater Company For Young People",
    "wof:placetype":"venue"
},
  "geometry": {"coordinates":[-95.9515,41.257599],"type":"Point"}
}