{
  "type": "Feature",
  "properties": {
    "iso:country":"US",
    "sg:address":"720 N 18th Ave",
    "sg:city":"Blair",
    "sg:classifiers":[
        {
            "category":"Real Estate",
            "subcategory":"Real Estate Operator",
            "type":"Services"
        }
    ],
    "sg:phone":"+1 402 426 9199",
    "sg:postcode":"68008",
    "sg:province":"NE",
    "sg:tags":[
        "apartment"
    ],
    "wof:name":"Quail Run Apartments",
    "wof:placetype":"venue"
},
  "geometry": {"coordinates":[-96.141206,41.550527],"type":"Point"}
}