{
  "type": "Feature",
  "properties": {
    "iso:country":"US",
    "sg:address":"16060 Co Rd 25",
    "sg:city":"Blair",
    "sg:classifiers":[
        {
            "category":"Building & Trades",
            "subcategory":"Construction",
            "type":"Services"
        }
    ],
    "sg:phone":"+1 402 533 2500",
    "sg:postcode":"68008",
    "sg:province":"NE",
    "sg:tags":[
        "general",
        "contractor"
    ],
    "wof:name":"Logan Construction Inc",
    "wof:placetype":"venue"
},
  "geometry": {"coordinates":[-96.213064,41.60959],"type":"Point"}
}