{
  "type": "Feature",
  "properties": {
    "iso:country":"US",
    "sg:address":"10160 L St",
    "sg:city":"Omaha",
    "sg:classifiers":[
        {
            "category":"Professional",
            "type":"Services"
        }
    ],
    "sg:phone":"+1 402 537 7300",
    "sg:postcode":"68127",
    "sg:province":"NE",
    "sg:tags":[
        "establishment"
    ],
    "wof:name":"Nebraska Broadband LLC",
    "wof:placetype":"venue"
},
  "geometry": {"coordinates":[-96.062986,41.21256],"type":"Point"}
}