{
  "type": "Feature",
  "properties": {
    "addr:full":"8814 J St Omaha NE 68127",
    "addr:housenumber":"8814",
    "addr:postcode":"68127",
    "addr:street":"J St",
    "iso:country":"US",
    "sg:address":"8814 J St",
    "sg:city":"Omaha",
    "sg:classifiers":[
        {
            "category":"Manufacturing",
            "subcategory":"Printing",
            "type":"Manufacturing & Wholesale Goods"
        }
    ],
    "sg:phone":"+1 402 553 0107",
    "sg:postcode":"68127",
    "sg:province":"NE",
    "sg:tags":[
        "computer",
        "printer",
        "supply"
    ],
    "wof:name":"Healy & Healy Inc",
    "wof:placetype":"venue"
},
  "geometry": {"coordinates":[-96.048231,41.215439],"type":"Point"}
}