{
  "type": "Feature",
  "properties": {
    "iso:country":"US",
    "sg:address":"1515 S Harrison St",
    "sg:city":"Grand Island",
    "sg:classifiers":[
        {
            "category":"Organizations",
            "subcategory":"Religious Organization",
            "type":"Services"
        }
    ],
    "sg:phone":"+1 308 382 2973",
    "sg:postcode":"68803",
    "sg:province":"NE",
    "sg:tags":[
        "church"
    ],
    "sg:website":"www.stpaulsgi.org",
    "wof:name":"St Pauls Lutheran Church Elca",
    "wof:placetype":"venue"
},
  "geometry": {"coordinates":[-98.35388500000001,40.906655],"type":"Point"}
}