{
  "type": "Feature",
  "properties": {
    "addr:full":"1001 I St Palmyra NE 68418",
    "addr:housenumber":"1001",
    "addr:postcode":"68418",
    "addr:street":"I St",
    "iso:country":"US",
    "sg:address":"1001 I St",
    "sg:city":"Palmyra",
    "sg:classifiers":[
        {
            "category":"Restaurant",
            "type":"Food & Drink"
        }
    ],
    "sg:menulink":"http://www.allmenus.com/ne/north-palmyra/225182-caseys-general-store/menu/",
    "sg:phone":"+1 402 780 5767",
    "sg:postcode":"68418",
    "sg:province":"NE",
    "sg:tags":[
        "american",
        "pizza"
    ],
    "wof:name":"Casey's General Store",
    "wof:placetype":"venue"
},
  "geometry": {"coordinates":[-96.396984,40.708445],"type":"Point"}
}