{
  "type": "Feature",
  "properties": {
    "addr:full":"3426 N 58th St Lincoln NE 68507",
    "addr:housenumber":"3426",
    "addr:postcode":"68507",
    "addr:street":"N 58Th St",
    "iso:country":"US",
    "sg:address":"3426 N 58th St",
    "sg:city":"Lincoln",
    "sg:classifiers":[
        {
            "category":"Retail",
            "subcategory":"Repair Shop",
            "type":"Services"
        }
    ],
    "sg:phone":"+1 402 489 6725",
    "sg:postcode":"68507",
    "sg:province":"NE",
    "sg:tags":[
        "equipment",
        "conditioning",
        "air"
    ],
    "wof:name":"Steve Halleen Svc",
    "wof:placetype":"venue"
},
  "geometry": {"coordinates":[-96.64144,40.847314],"type":"Point"}
}