{
  "type": "Feature",
  "properties": {
    "iso:country":"US",
    "sg:address":"1401 High School Dr",
    "sg:city":"Bellevue",
    "sg:classifiers":[
        {
            "category":"Education",
            "subcategory":"School",
            "type":"Public Place"
        }
    ],
    "sg:phone":"+1 402 293 4150",
    "sg:postcode":"68005",
    "sg:province":"NE",
    "sg:tags":[
        "elementary",
        "secondary"
    ],
    "wof:name":"Bellevue East Sr High School",
    "wof:placetype":"venue"
},
  "geometry": {"coordinates":[-95.90333800000001,41.145264],"type":"Point"}
}