{
  "type": "Feature",
  "properties": {
    "iso:country":"US",
    "sg:address":"4512 N 21st Ave",
    "sg:city":"Omaha",
    "sg:classifiers":[
        {
            "category":"Building & Trades",
            "subcategory":"Locksmith",
            "type":"Services"
        }
    ],
    "sg:phone":"+1 402 881 3835",
    "sg:postcode":"68110",
    "sg:province":"NE",
    "sg:tags":[
        "key"
    ],
    "wof:name":"24 All Day Locksmith",
    "wof:placetype":"venue"
},
  "geometry": {"coordinates":[-95.943825,41.299722],"type":"Point"}
}