{
  "type": "Feature",
  "properties": {
    "iso:country":"US",
    "sg:address":"3025 Farnam St",
    "sg:city":"Omaha",
    "sg:classifiers":[
        {
            "category":"Restaurant",
            "type":"Food & Drink"
        }
    ],
    "sg:phone":"+1 402 932 9188",
    "sg:postcode":"68131",
    "sg:province":"NE",
    "sg:tags":[
        "african"
    ],
    "wof:name":"Safari Restaurant",
    "wof:placetype":"venue"
},
  "geometry": {"coordinates":[-95.957296,41.257563],"type":"Point"}
}