{
  "type": "Feature",
  "properties": {
    "iso:country":"US",
    "sg:address":"412 Morris St",
    "sg:city":"Clarks",
    "sg:classifiers":[
        {
            "category":"Freight",
            "type":"Transportation"
        }
    ],
    "sg:phone":"+1 308 548 2116",
    "sg:postcode":"68628",
    "sg:province":"NE",
    "sg:tags":[
        "trucking"
    ],
    "wof:name":"Hay Dot Trucking LLC",
    "wof:placetype":"venue"
},
  "geometry": {"coordinates":[-97.842161,41.215054],"type":"Point"}
}