{
  "type": "Feature",
  "properties": {
    "addr:full":"1010 A St Lincoln NE 68502",
    "addr:housenumber":"1010",
    "addr:postcode":"68502",
    "addr:street":"A St",
    "iso:country":"US",
    "sg:address":"1010 A St",
    "sg:city":"Lincoln",
    "sg:classifiers":[
        {
            "category":"Insurance",
            "subcategory":"Insurance Agent",
            "type":"Services"
        }
    ],
    "sg:phone":"+1 402 438 6800",
    "sg:postcode":"68502",
    "sg:province":"NE",
    "wof:name":"Midmex Insurance Inc",
    "wof:placetype":"venue"
},
  "geometry": {"coordinates":[-96.705733,40.799285],"type":"Point"}
}