{
  "type": "Feature",
  "properties": {
    "addr:full":"2277 22nd Ave Columbus NE 68601",
    "addr:housenumber":"2277",
    "addr:postcode":"68601",
    "addr:street":"22Nd Ave",
    "iso:country":"US",
    "sg:address":"2277 22nd Ave",
    "sg:city":"Columbus",
    "sg:classifiers":[
        {
            "category":"Insurance",
            "subcategory":"Insurance Agent",
            "type":"Services"
        }
    ],
    "sg:phone":"+1 402 564 3421",
    "sg:postcode":"68601",
    "sg:province":"NE",
    "wof:name":"Farmers Insurance Group",
    "wof:placetype":"venue"
},
  "geometry": {"coordinates":[-97.35412100000001,41.438337],"type":"Point"}
}