{
  "type": "Feature",
  "properties": {
    "iso:country":"US",
    "sg:address":"2100 Court St",
    "sg:city":"Beatrice",
    "sg:classifiers":[
        {
            "category":"Insurance",
            "subcategory":"Insurance Agent",
            "type":"Services"
        }
    ],
    "sg:phone":"+1 402 223 2288",
    "sg:postcode":"68310",
    "sg:province":"NE",
    "wof:name":"Transportation Risk Solutions",
    "wof:placetype":"venue"
},
  "geometry": {"coordinates":[-96.724127,40.265861],"type":"Point"}
}