{
  "type": "Feature",
  "properties": {
    "iso:country":"US",
    "sg:address":"115 W 6th St",
    "sg:city":"Wahoo",
    "sg:classifiers":[
        {
            "category":"Insurance",
            "subcategory":"Hazard Insurance",
            "type":"Services"
        }
    ],
    "sg:phone":"+1 402 443 3556",
    "sg:postcode":"68066",
    "sg:province":"NE",
    "sg:tags":[
        "employee",
        "benefit",
        "compensation",
        "plan"
    ],
    "wof:name":"True Script LLC",
    "wof:placetype":"venue"
},
  "geometry": {"coordinates":[-96.621109,41.210929],"type":"Point"}
}