{
  "type": "Feature",
  "properties": {
    "addr:full":"555 S 10th St Lincoln NE 68508",
    "addr:housenumber":"555",
    "addr:postcode":"68508",
    "addr:street":"S 10Th St",
    "iso:country":"US",
    "sg:address":"555 S 10th St",
    "sg:city":"Lincoln",
    "sg:classifiers":[
        {
            "category":"Government",
            "subcategory":"Office",
            "type":"Public Place"
        }
    ],
    "sg:phone":"+1 402 441 7277",
    "sg:postcode":"68508",
    "sg:province":"NE",
    "sg:tags":[
        "village"
    ],
    "wof:name":"Lincoln Violations Bureau",
    "wof:placetype":"venue"
},
  "geometry": {"coordinates":[-96.707037,40.806953],"type":"Point"}
}