{
  "type": "Feature",
  "properties": {
    "addr:full":"567 E 20th St South Sioux City NE 68776",
    "addr:housenumber":"567",
    "addr:postcode":"68776",
    "addr:street":"E 20Th St",
    "iso:country":"US",
    "sg:address":"567 E 20th St",
    "sg:city":"South Sioux City",
    "sg:classifiers":[
        {
            "category":"Wholesale",
            "subcategory":"Auto Parts",
            "type":"Manufacturing & Wholesale Goods"
        }
    ],
    "sg:phone":"+1 402 494 6866",
    "sg:postcode":"68776",
    "sg:province":"NE",
    "sg:tags":[
        "equipment",
        "rebuilt",
        "truck"
    ],
    "sg:website":"www.candhtruck.com",
    "wof:name":"C & H Truck Parts",
    "wof:placetype":"venue"
},
  "geometry": {"coordinates":[-96.40705699999999,42.470827],"type":"Point"}
}