{
  "type": "Feature",
  "properties": {
    "addr:full":"1309 N 9th St Norfolk NE 68701",
    "addr:housenumber":"1309",
    "addr:postcode":"68701",
    "addr:street":"N 9Th St",
    "iso:country":"US",
    "sg:address":"1309 N 9th St",
    "sg:city":"Norfolk",
    "sg:classifiers":[
        {
            "category":"Social Services",
            "type":"Services"
        }
    ],
    "sg:phone":"+1 402 844 3073",
    "sg:postcode":"68701",
    "sg:province":"NE",
    "sg:tags":[
        "counselor",
        "marriage",
        "family"
    ],
    "wof:name":"Liane Bode",
    "wof:placetype":"venue"
},
  "geometry": {"coordinates":[-97.419383,42.047193],"type":"Point"}
}