{
  "type": "Feature",
  "properties": {
    "addr:full":"4145 Garfield St Lincoln NE 68506",
    "addr:housenumber":"4145",
    "addr:postcode":"68506",
    "addr:street":"Garfield St",
    "iso:country":"US",
    "sg:address":"4145 Garfield St",
    "sg:city":"Lincoln",
    "sg:classifiers":[
        {
            "category":"Home & Garden",
            "subcategory":"Hardware",
            "type":"Retail Goods"
        }
    ],
    "sg:phone":"+1 402 488 0963",
    "sg:postcode":"68506",
    "sg:province":"NE",
    "wof:name":"Midwest Plumbing Supply Co",
    "wof:placetype":"venue"
},
  "geometry": {"coordinates":[-96.66006400000001,40.796139],"type":"Point"}
}