{
  "type": "Feature",
  "properties": {
    "addr:full":"705 5th St Arapahoe NE 68922",
    "addr:housenumber":"705",
    "addr:postcode":"68922",
    "addr:street":"5Th St",
    "iso:country":"US",
    "sg:address":"705 5th St",
    "sg:city":"Arapahoe",
    "sg:classifiers":[
        {
            "category":"Organizations",
            "subcategory":"Religious Organization",
            "type":"Services"
        }
    ],
    "sg:phone":"+1 308 962 7278",
    "sg:postcode":"68922",
    "sg:province":"NE",
    "sg:tags":[
        "church"
    ],
    "wof:name":"First United Methodist Church",
    "wof:placetype":"venue"
},
  "geometry": {"coordinates":[-99.894988,40.306222],"type":"Point"}
}