{
  "type": "Feature",
  "properties": {
    "iso:country":"US",
    "sg:address":"1118 J St",
    "sg:city":"Auburn",
    "sg:classifiers":[
        {
            "category":"Shopping",
            "subcategory":"Pharmacy",
            "type":"Retail Goods"
        }
    ],
    "sg:phone":"+1 402 274 4315",
    "sg:postcode":"68305",
    "sg:province":"NE",
    "wof:name":"Allison Pharmacy",
    "wof:placetype":"venue"
},
  "geometry": {"coordinates":[-95.83889000000001,40.393657],"type":"Point"}
}