{
  "type": "Feature",
  "properties": {
    "iso:country":"US",
    "sg:address":"3019 Farnam St",
    "sg:city":"Omaha",
    "sg:classifiers":[
        {
            "category":"Food & Beverages",
            "subcategory":"Groceries & Convenience Stores",
            "type":"Retail Goods"
        }
    ],
    "sg:phone":"+1 402 344 2490",
    "sg:postcode":"68131",
    "sg:province":"NE",
    "sg:tags":[
        "convenient",
        "liquor",
        "package"
    ],
    "wof:name":"Sam's Food & Liquor",
    "wof:placetype":"venue"
},
  "geometry": {"coordinates":[-95.95700100000001,41.257599],"type":"Point"}
}