{
  "type": "Feature",
  "properties": {
    "iso:country":"US",
    "sg:address":"307 S French Ave",
    "sg:city":"Sutton",
    "sg:classifiers":[
        {
            "category":"Retail",
            "subcategory":"Auto Repair",
            "type":"Services"
        }
    ],
    "sg:phone":"+1 402 773 4756",
    "sg:postcode":"68979",
    "sg:province":"NE",
    "sg:tags":[
        "body"
    ],
    "wof:name":"Becker Auto & Body Shop",
    "wof:placetype":"venue"
},
  "geometry": {"coordinates":[-97.853554,40.609618],"type":"Point"}
}