{
  "type": "Feature",
  "properties": {
    "iso:country":"US",
    "sg:address":"2630 Cottonmill Ave",
    "sg:city":"Kearney",
    "sg:classifiers":[
        {
            "category":"Freight",
            "type":"Transportation"
        }
    ],
    "sg:phone":"+1 308 440 2545",
    "sg:postcode":"68845",
    "sg:province":"NE",
    "sg:tags":[
        "product",
        "relocation",
        "engineer"
    ],
    "wof:name":"James L Perdue",
    "wof:placetype":"venue"
},
  "geometry": {"coordinates":[-99.148096,40.70312],"type":"Point"}
}