{
  "type": "Feature",
  "properties": {
    "iso:country":"US",
    "sg:address":"212 Block Ave",
    "sg:city":"Hildreth",
    "sg:classifiers":[
        {
            "category":"Retail",
            "subcategory":"Funeral Services",
            "type":"Services"
        }
    ],
    "sg:phone":"+1 308 938 2195",
    "sg:postcode":"68947",
    "sg:province":"NE",
    "sg:tags":[
        "home"
    ],
    "wof:name":"Jelden-Layton Funeral Home",
    "wof:placetype":"venue"
},
  "geometry": {"coordinates":[-99.042035,40.337867],"type":"Point"}
}