{
  "type": "Feature",
  "properties": {
    "iso:country":"US",
    "sg:address":"6708 S 161st Ave",
    "sg:city":"Omaha",
    "sg:classifiers":[
        {
            "category":"Education",
            "subcategory":"School",
            "type":"Public Place"
        }
    ],
    "sg:phone":"+1 402 894 6200",
    "sg:postcode":"68135",
    "sg:province":"NE",
    "sg:website":"www.mpsomaha.org/blackelk",
    "wof:name":"Black Elk Elementary School",
    "wof:placetype":"venue"
},
  "geometry": {"coordinates":[-96.166574,41.193096],"type":"Point"}
}