{
  "type": "Feature",
  "properties": {
    "addr:full":"6319 Maple St Omaha NE 68104",
    "addr:housenumber":"6319",
    "addr:postcode":"68104",
    "addr:street":"Maple St",
    "iso:country":"US",
    "sg:address":"6319 Maple St",
    "sg:city":"Omaha",
    "sg:classifiers":[
        {
            "category":"Organizations",
            "subcategory":"Religious Organization",
            "type":"Services"
        }
    ],
    "sg:phone":"+1 402 551 1512",
    "sg:postcode":"68104",
    "sg:province":"NE",
    "sg:tags":[
        "church"
    ],
    "sg:website":"www.omahabbc.com",
    "wof:name":"Benson Baptist Church ABC",
    "wof:placetype":"venue"
},
  "geometry": {"coordinates":[-96.010611,41.284931],"type":"Point"}
}