{
  "type": "Feature",
  "properties": {
    "addr:full":"100 E 5th St North Platte NE 69101",
    "addr:housenumber":"100",
    "addr:postcode":"69101",
    "addr:street":"E 5Th St",
    "iso:country":"US",
    "sg:address":"100 E 5th St",
    "sg:city":"North Platte",
    "sg:classifiers":[
        {
            "category":"Social Services",
            "type":"Services"
        }
    ],
    "sg:phone":"+1 308 534 6251",
    "sg:postcode":"69101",
    "sg:province":"NE",
    "sg:tags":[
        "organization",
        "welfare"
    ],
    "wof:name":"Habitat For Humanity",
    "wof:placetype":"venue"
},
  "geometry": {"coordinates":[-100.762974,41.137496],"type":"Point"}
}