{
  "type": "Feature",
  "properties": {
    "addr:full":"9600 SW 98th St Denton NE 68339",
    "addr:housenumber":"9600",
    "addr:postcode":"68339",
    "addr:street":"Sw 98Th St",
    "iso:country":"US",
    "sg:address":"9600 SW 98th St",
    "sg:city":"Denton",
    "sg:classifiers":[
        {
            "category":"Farming",
            "subcategory":"Farm",
            "type":"Manufacturing & Wholesale Goods"
        }
    ],
    "sg:phone":"+1 402 797 7580",
    "sg:postcode":"68339",
    "sg:province":"NE",
    "sg:tags":[
        "crop",
        "general"
    ],
    "wof:name":"Ronald Trouba",
    "wof:placetype":"venue"
},
  "geometry": {"coordinates":[-96.853799,40.716444],"type":"Point"}
}