{
  "type": "Feature",
  "properties": {
    "iso:country":"US",
    "sg:address":"300 W 9th St",
    "sg:city":"Gordon",
    "sg:classifiers":[
        {
            "category":"Organizations",
            "subcategory":"Religious Organization",
            "type":"Services"
        }
    ],
    "sg:phone":"+1 308 282 1705",
    "sg:postcode":"69343",
    "sg:province":"NE",
    "sg:tags":[
        "church"
    ],
    "wof:name":"Gordon Bible Church",
    "wof:placetype":"venue"
},
  "geometry": {"coordinates":[-102.20675300000001,42.813202],"type":"Point"}
}