{
  "type": "Feature",
  "properties": {
    "addr:full":"6700 Southfork Cir Lincoln NE 68516",
    "addr:housenumber":"6700",
    "addr:postcode":"68516",
    "addr:street":"Southfork Cir",
    "iso:country":"US",
    "sg:address":"6700 Southfork Cir",
    "sg:city":"Lincoln",
    "sg:classifiers":[
        {
            "category":"Professional",
            "subcategory":"Business Services",
            "type":"Services"
        }
    ],
    "sg:phone":"+1 402 421 6168",
    "sg:postcode":"68516",
    "sg:province":"NE",
    "wof:name":"Washington Enterprises Inc",
    "wof:placetype":"venue"
},
  "geometry": {"coordinates":[-96.628942,40.749286],"type":"Point"}
}