{
  "type": "Feature",
  "properties": {
    "iso:country":"US",
    "sg:address":"1900 E Military Ave",
    "sg:city":"Fremont",
    "sg:classifiers":[
        {
            "category":"Restaurant",
            "type":"Food & Drink"
        }
    ],
    "sg:menulink":"http://www.allmenus.com/ne/fremont/223282-gambinos-pizza/menu/",
    "sg:phone":"+1 402 727 1333",
    "sg:postcode":"68025",
    "sg:province":"NE",
    "sg:tags":[
        "american",
        "pizza"
    ],
    "wof:name":"Gambino's Pizza",
    "wof:placetype":"venue"
},
  "geometry": {"coordinates":[-96.47245100000001,41.434483],"type":"Point"}
}