{
  "type": "Feature",
  "properties": {
    "iso:country":"US",
    "sg:address":"1827 Industrial Dr",
    "sg:city":"David City",
    "sg:classifiers":[
        {
            "category":"Manufacturing",
            "subcategory":"Motor Vehicles & Parts",
            "type":"Manufacturing & Wholesale Goods"
        }
    ],
    "sg:phone":"+1 402 367 3056",
    "sg:postcode":"68632",
    "sg:province":"NE",
    "sg:tags":[
        "industrial",
        "truck",
        "trailer",
        "mfg"
    ],
    "wof:name":"Timpte Industries Inc",
    "wof:placetype":"venue"
},
  "geometry": {"coordinates":[-97.132085,41.269637],"type":"Point"}
}