{
  "type": "Feature",
  "properties": {
    "iso:country":"US",
    "sg:address":"1723 S 139th St",
    "sg:city":"Omaha",
    "sg:classifiers":[
        {
            "category":"Professional",
            "subcategory":"Business Services",
            "type":"Services"
        }
    ],
    "sg:phone":"+1 402 334 8724",
    "sg:postcode":"68144",
    "sg:province":"NE",
    "wof:name":"Bridgeware Solutions Inc",
    "wof:placetype":"venue"
},
  "geometry": {"coordinates":[-96.129555,41.242197],"type":"Point"}
}