{
  "type": "Feature",
  "properties": {
    "iso:country":"US",
    "sg:address":"1721 E 8th St",
    "sg:city":"North Platte",
    "sg:classifiers":[
        {
            "category":"Retail",
            "subcategory":"Animal Services",
            "type":"Services"
        }
    ],
    "sg:phone":"+1 308 534 6252",
    "sg:postcode":"69101",
    "sg:province":"NE",
    "wof:name":"A Bark Above",
    "wof:placetype":"venue"
},
  "geometry": {"coordinates":[-100.742304,41.139797],"type":"Point"}
}