{
  "type": "Feature",
  "properties": {
    "addr:full":"1700 Farnam St Omaha NE 68102",
    "addr:housenumber":"1700",
    "addr:postcode":"68102",
    "addr:street":"Farnam St",
    "iso:country":"US",
    "sg:address":"1700 Farnam St",
    "sg:city":"Omaha",
    "sg:classifiers":[
        {
            "category":"Professional",
            "subcategory":"Lawyer & Legal Services",
            "type":"Services"
        }
    ],
    "sg:phone":"+1 402 348 7907",
    "sg:postcode":"68102",
    "sg:province":"NE",
    "sg:tags":[
        "attorney"
    ],
    "wof:name":"Melvin R Katskee",
    "wof:placetype":"venue"
},
  "geometry": {"coordinates":[-95.93983900000001,41.257616],"type":"Point"}
}