{
  "type": "Feature",
  "properties": {
    "iso:country":"US",
    "sg:address":"15332 Weber St",
    "sg:city":"Bennington",
    "sg:classifiers":[
        {
            "category":"Professional",
            "subcategory":"Business Services",
            "type":"Services"
        }
    ],
    "sg:phone":"+1 402 315 9333",
    "sg:postcode":"68007",
    "sg:province":"NE",
    "wof:name":"Erb Group Inc",
    "wof:placetype":"venue"
},
  "geometry": {"coordinates":[-96.152288,41.326343],"type":"Point"}
}