{
  "type": "Feature",
  "properties": {
    "iso:country":"US",
    "sg:address":"317 S 11th St",
    "sg:city":"Lincoln",
    "sg:classifiers":[
        {
            "category":"Bars & Pubs",
            "type":"Food & Drink"
        }
    ],
    "sg:phone":"+1 402 477 3880",
    "sg:postcode":"68508",
    "sg:province":"NE",
    "wof:name":"Libations",
    "wof:placetype":"venue"
},
  "geometry": {"coordinates":[-96.70561600000001,40.810486],"type":"Point"}
}