{
  "type": "Feature",
  "properties": {
    "iso:country":"US",
    "sg:address":"2508 N R Rd",
    "sg:city":"Marquette",
    "sg:classifiers":[
        {
            "category":"Wholesale",
            "subcategory":"Meat",
            "type":"Manufacturing & Wholesale Goods"
        }
    ],
    "sg:phone":"+1 308 946 2338",
    "sg:postcode":"68854",
    "sg:province":"NE",
    "sg:tags":[
        "process",
        "ostrich"
    ],
    "wof:name":"Autritech LLC",
    "wof:placetype":"venue"
},
  "geometry": {"coordinates":[-97.98122600000001,41.052433],"type":"Point"}
}