{
  "type": "Feature",
  "properties": {
    "iso:country":"US",
    "sg:address":"16604 Bestman Dr",
    "sg:city":"Plattsmouth",
    "sg:classifiers":[
        {
            "category":"Restaurant",
            "type":"Food & Drink"
        }
    ],
    "sg:phone":"+1 402 298 7500",
    "sg:postcode":"68048",
    "sg:province":"NE",
    "sg:tags":[
        "eating",
        "product",
        "dairy"
    ],
    "wof:name":"Subway",
    "wof:placetype":"venue"
},
  "geometry": {"coordinates":[-95.90941599999999,41.014877],"type":"Point"}
}