{
  "type": "Feature",
  "properties": {
    "addr:full":"5105 NW 84th St Malcolm NE 68402",
    "addr:housenumber":"5105",
    "addr:postcode":"68402",
    "addr:street":"Nw 84Th St",
    "iso:country":"US",
    "sg:address":"5105 NW 84th St",
    "sg:city":"Malcolm",
    "sg:classifiers":[
        {
            "category":"Social Services",
            "subcategory":"Child Care",
            "type":"Services"
        }
    ],
    "sg:phone":"+1 402 470 2133",
    "sg:postcode":"68402",
    "sg:province":"NE",
    "sg:tags":[
        "day"
    ],
    "wof:name":"Lightning Bug Daycare",
    "wof:placetype":"venue"
},
  "geometry": {"coordinates":[-96.83440899999999,40.859004],"type":"Point"}
}