{
  "type": "Feature",
  "properties": {
    "iso:country":"US",
    "sg:address":"530 N St",
    "sg:city":"Bridgeport",
    "sg:classifiers":[
        {
            "category":"Social Services",
            "subcategory":"Child Care",
            "type":"Services"
        }
    ],
    "sg:phone":"+1 308 262 1047",
    "sg:postcode":"69336",
    "sg:province":"NE",
    "wof:name":"Kristy Kiddy Corner",
    "wof:placetype":"venue"
},
  "geometry": {"coordinates":[-103.098107,41.670088],"type":"Point"}
}