{
  "type": "Feature",
  "properties": {
    "iso:country":"US",
    "sg:address":"200398 Rolling Hills Rd",
    "sg:city":"Scottsbluff",
    "sg:classifiers":[
        {
            "category":"Building & Trades",
            "subcategory":"Plumbing",
            "type":"Services"
        }
    ],
    "sg:phone":"+1 308 632 3590",
    "sg:postcode":"69361",
    "sg:province":"NE",
    "sg:tags":[
        "contractor"
    ],
    "wof:name":"Steves Sprinkler Systems",
    "wof:placetype":"venue"
},
  "geometry": {"coordinates":[-103.680043,41.92391],"type":"Point"}
}