{
  "type": "Feature",
  "properties": {
    "addr:full":"108 Center Ave Holbrook NE 68948",
    "addr:housenumber":"108",
    "addr:postcode":"68948",
    "addr:street":"Center Ave",
    "iso:country":"US",
    "sg:address":"108 Center Ave",
    "sg:city":"Holbrook",
    "sg:classifiers":[
        {
            "category":"Wholesale",
            "subcategory":"Farm Supplies",
            "type":"Manufacturing & Wholesale Goods"
        }
    ],
    "sg:phone":"+1 308 493 5444",
    "sg:postcode":"68948",
    "sg:province":"NE",
    "sg:tags":[
        "alfalfa",
        "hay"
    ],
    "wof:name":"Harper's Hay Barn",
    "wof:placetype":"venue"
},
  "geometry": {"coordinates":[-100.010091,40.303064],"type":"Point"}
}