{
  "type": "Feature",
  "properties": {
    "iso:country":"US",
    "sg:address":"210 W Cornhusker Hwy",
    "sg:city":"Lincoln",
    "sg:classifiers":[
        {
            "category":"Autos & Motor Vehicles",
            "subcategory":"Automobile Sales",
            "type":"Retail Goods"
        }
    ],
    "sg:phone":"+1 402 474 3696",
    "sg:postcode":"68521",
    "sg:province":"NE",
    "sg:tags":[
        "used"
    ],
    "wof:name":"Harmans Corvettes",
    "wof:placetype":"venue"
},
  "geometry": {"coordinates":[-96.72385800000001,40.835738],"type":"Point"}
}