{
  "type": "Feature",
  "properties": {
    "iso:country":"US",
    "sg:address":"235 E 4th St",
    "sg:city":"Wahoo",
    "sg:classifiers":[
        {
            "category":"Social Services",
            "type":"Services"
        }
    ],
    "sg:phone":"+1 402 443 4887",
    "sg:postcode":"68066",
    "sg:province":"NE",
    "sg:tags":[
        "individual",
        "family"
    ],
    "wof:name":"Dining Meal Reservations",
    "wof:placetype":"venue"
},
  "geometry": {"coordinates":[-96.618313,41.208903],"type":"Point"}
}