{
  "type": "Feature",
  "properties": {
    "iso:country":"US",
    "sg:address":"2634 S 156th Cir",
    "sg:city":"Omaha",
    "sg:classifiers":[
        {
            "category":"Shopping",
            "type":"Retail Goods"
        }
    ],
    "sg:phone":"+1 402 758 1330",
    "sg:postcode":"68130",
    "sg:province":"NE",
    "sg:tags":[
        "spa",
        "hot",
        "tub"
    ],
    "wof:name":"Backyard Oasis Pool & Spa",
    "wof:placetype":"venue"
},
  "geometry": {"coordinates":[-96.159519,41.238626],"type":"Point"}
}