{
  "type": "Feature",
  "properties": {
    "iso:country":"US",
    "sg:address":"6132 Military Ave",
    "sg:city":"Omaha",
    "sg:classifiers":[
        {
            "category":"Retail",
            "subcategory":"Auto Repair",
            "type":"Services"
        }
    ],
    "sg:phone":"+1 402 553 1040",
    "sg:postcode":"68104",
    "sg:province":"NE",
    "sg:tags":[
        "body"
    ],
    "wof:name":"Triangle Body Shop",
    "wof:placetype":"venue"
},
  "geometry": {"coordinates":[-96.00958199999999,41.287423],"type":"Point"}
}