{
  "type": "Feature",
  "properties": {
    "iso:country":"US",
    "sg:address":"16902 Wright Plz",
    "sg:city":"Omaha",
    "sg:classifiers":[
        {
            "category":"Coffee & Tea",
            "type":"Food & Drink"
        },
        {
            "category":"Cafe",
            "type":"Food & Drink"
        },
        {
            "category":"Bakery",
            "type":"Food & Drink"
        }
    ],
    "sg:menulink":"http://www.allmenus.com/ne/millard/234043-nestle-toll-house-cafe/menu/",
    "sg:phone":"+1 402 934 3770",
    "sg:postcode":"68130",
    "sg:province":"NE",
    "sg:tags":[
        "american",
        "pastry"
    ],
    "wof:name":"Nestle Toll House Cafe",
    "wof:placetype":"venue"
},
  "geometry": {"coordinates":[-96.17885,41.233264],"type":"Point"}
}