{
  "type": "Feature",
  "properties": {
    "addr:full":"74602 L Rd Elm Creek NE 68836",
    "addr:housenumber":"74602",
    "addr:postcode":"68836",
    "addr:street":"L Rd",
    "iso:country":"US",
    "sg:address":"74602 L Rd",
    "sg:city":"Elm Creek",
    "sg:phone":"+1 308 856 4474",
    "sg:postcode":"68836",
    "sg:province":"NE",
    "sg:tags":[
        "farm",
        "corn"
    ],
    "wof:name":"Sam Robinson",
    "wof:placetype":"venue"
},
  "geometry": {"coordinates":[-99.417496,40.656199],"type":"Point"}
}