{
  "type": "Feature",
  "properties": {
    "iso:country":"US",
    "sg:address":"1475 State Hwy 61 Scn",
    "sg:city":"Ogallala",
    "sg:classifiers":[
        {
            "category":"Government",
            "subcategory":"Office",
            "type":"Public Place"
        }
    ],
    "sg:phone":"+1 308 284 8800",
    "sg:postcode":"69153",
    "sg:province":"NE",
    "sg:tags":[
        "state"
    ],
    "wof:name":"Game & Parks Commission",
    "wof:placetype":"venue"
},
  "geometry": {"coordinates":[-101.66371100000001,41.199159],"type":"Point"}
}