{
  "type": "Feature",
  "properties": {
    "iso:country":"US",
    "sg:address":"205 W 3rd St",
    "sg:city":"Atkinson",
    "sg:classifiers":[
        {
            "category":"Retail",
            "subcategory":"Auto Repair",
            "type":"Services"
        }
    ],
    "sg:phone":"+1 402 925 2318",
    "sg:postcode":"68713",
    "sg:province":"NE",
    "sg:tags":[
        "automobile",
        "lubrication"
    ],
    "wof:name":"Osborne's Lube Express",
    "wof:placetype":"venue"
},
  "geometry": {"coordinates":[-98.980709,42.534809],"type":"Point"}
}