{
  "type": "Feature",
  "properties": {
    "iso:country":"US",
    "sg:address":"1329 O St",
    "sg:city":"Omaha",
    "sg:classifiers":[
        {
            "category":"Shopping",
            "type":"Retail Goods"
        }
    ],
    "sg:phone":"+1 402 731 0914",
    "sg:postcode":"68107",
    "sg:province":"NE",
    "sg:tags":[
        "merchandise"
    ],
    "wof:name":"Assoc of Zoo & Aquarium D",
    "wof:placetype":"venue"
},
  "geometry": {"coordinates":[-95.93776200000001,41.208376],"type":"Point"}
}