{
  "type": "Feature",
  "properties": {
    "iso:country":"US",
    "sg:address":"504 Prospect Ave",
    "sg:city":"Norfolk",
    "sg:classifiers":[
        {
            "category":"Organizations",
            "subcategory":"Non-profit Organization",
            "type":"Services"
        },
        {
            "category":"Shopping",
            "subcategory":"Books",
            "type":"Retail Goods"
        }
    ],
    "sg:phone":"+1 402 370 3113",
    "sg:postcode":"68701",
    "sg:province":"NE",
    "sg:tags":[
        "info",
        "addiction",
        "abuse",
        "treatment",
        "drug"
    ],
    "wof:name":"Prevention Pathways Inc",
    "wof:placetype":"venue"
},
  "geometry": {"coordinates":[-97.41485900000001,42.03641],"type":"Point"}
}