{
  "type": "Feature",
  "properties": {
    "addr:full":"410 N 10th St Nebraska City NE 68410",
    "addr:housenumber":"410",
    "addr:postcode":"68410",
    "addr:street":"N 10Th St",
    "iso:country":"US",
    "sg:address":"410 N 10th St",
    "sg:city":"Nebraska City",
    "sg:classifiers":[
        {
            "category":"Building & Trades",
            "subcategory":"Construction",
            "type":"Services"
        }
    ],
    "sg:phone":"+1 402 873 3040",
    "sg:postcode":"68410",
    "sg:province":"NE",
    "sg:tags":[
        "nonresidential"
    ],
    "wof:name":"Stark & Associates",
    "wof:placetype":"venue"
},
  "geometry": {"coordinates":[-95.85746399999999,40.679808],"type":"Point"}
}