{
  "type": "Feature",
  "properties": {
    "iso:country":"US",
    "sg:address":"4651 A St",
    "sg:city":"Omaha",
    "sg:classifiers":[
        {
            "category":"Building & Trades",
            "subcategory":"Plumbing",
            "type":"Services"
        }
    ],
    "sg:phone":"+1 402 558 1418",
    "sg:postcode":"68106",
    "sg:province":"NE",
    "sg:tags":[
        "plumbing",
        "contractor"
    ],
    "wof:name":"Radden Plumbing Inc",
    "wof:placetype":"venue"
},
  "geometry": {"coordinates":[-95.984917,41.225692],"type":"Point"}
}