{
  "type": "Feature",
  "properties": {
    "iso:country":"US",
    "sg:address":"711 S 6th St",
    "sg:city":"Beatrice",
    "sg:classifiers":[
        {
            "category":"Manufacturing",
            "subcategory":"Tools & Machinery",
            "type":"Manufacturing & Wholesale Goods"
        }
    ],
    "sg:phone":"+1 402 223 4026",
    "sg:postcode":"68310",
    "sg:province":"NE",
    "sg:tags":[
        "equipment",
        "pump",
        "pumping"
    ],
    "sg:website":"www.dempsterinc.com",
    "wof:name":"Dempster Industries Inc",
    "wof:placetype":"venue"
},
  "geometry": {"coordinates":[-96.74683899999999,40.259157],"type":"Point"}
}