{
  "type": "Feature",
  "properties": {
    "addr:full":"1757 Co Rd C Ceresco NE 68017",
    "addr:housenumber":"1757",
    "addr:postcode":"68017",
    "addr:street":"Co Rd",
    "iso:country":"US",
    "sg:address":"1757 Co Rd C",
    "sg:city":"Ceresco",
    "sg:phone":"+1 402 665 2119",
    "sg:postcode":"68017",
    "sg:province":"NE",
    "sg:tags":[
        "farm",
        "corn"
    ],
    "wof:name":"Glen Otto",
    "wof:placetype":"venue"
},
  "geometry": {"coordinates":[-96.629211,41.089024],"type":"Point"}
}