{
  "type": "Feature",
  "properties": {
    "iso:country":"US",
    "sg:address":"210 Truman Ave",
    "sg:city":"Republican City",
    "sg:phone":"+1 308 799 3405",
    "sg:postcode":"68971",
    "sg:province":"NE",
    "sg:tags":[
        "farm",
        "corn"
    ],
    "wof:name":"Don Fegter",
    "wof:placetype":"venue"
},
  "geometry": {"coordinates":[-99.220856,40.099229],"type":"Point"}
}