{
  "type": "Feature",
  "properties": {
    "addr:full":"7200 World Communications Dr Omaha NE 68122",
    "addr:housenumber":"7200",
    "addr:postcode":"68122",
    "addr:street":"World Communications Dr",
    "iso:country":"US",
    "sg:address":"7200 World Communications Dr",
    "sg:city":"Omaha",
    "sg:classifiers":[
        {
            "category":"Utilities",
            "subcategory":"Telephone",
            "type":"Services"
        }
    ],
    "sg:phone":"+1 402 398 4100",
    "sg:postcode":"68122",
    "sg:province":"NE",
    "sg:tags":[
        "information",
        "industry",
        "telecommunication",
        "enhanced",
        "for"
    ],
    "sg:website":"www.prairiesystems.com",
    "wof:name":"Prairie Systems Inc",
    "wof:placetype":"venue"
},
  "geometry": {"coordinates":[-96.023821,41.337832],"type":"Point"}
}