{
  "type": "Feature",
  "properties": {
    "addr:full":"15911 Josephine St Omaha NE 68136",
    "addr:housenumber":"15911",
    "addr:postcode":"68136",
    "addr:street":"Josephine St",
    "iso:country":"US",
    "sg:address":"15911 Josephine St",
    "sg:city":"Omaha",
    "sg:classifiers":[
        {
            "category":"Food & Beverages",
            "subcategory":"Groceries & Convenience Stores",
            "type":"Retail Goods"
        }
    ],
    "sg:phone":"+1 402 896 3812",
    "sg:postcode":"68136",
    "sg:province":"NE",
    "wof:name":"Gage Food Products",
    "wof:placetype":"venue"
},
  "geometry": {"coordinates":[-96.16323,41.186505],"type":"Point"}
}