{
  "type": "Feature",
  "properties": {
    "iso:country":"US",
    "sg:address":"4820 S 61st St",
    "sg:city":"Omaha",
    "sg:classifiers":[
        {
            "category":"Autos & Motor Vehicles",
            "subcategory":"Auto Supplies",
            "type":"Retail Goods"
        }
    ],
    "sg:phone":"+1 402 734 6645",
    "sg:postcode":"68117",
    "sg:province":"NE",
    "sg:tags":[
        "tire"
    ],
    "wof:name":"T O Haas Tires Co",
    "wof:placetype":"venue"
},
  "geometry": {"coordinates":[-96.00711699999999,41.211183],"type":"Point"}
}