{
  "type": "Feature",
  "properties": {
    "addr:full":"6212 S 172nd St Omaha NE 68135",
    "addr:housenumber":"6212",
    "addr:postcode":"68135",
    "addr:street":"S 172Nd St",
    "iso:country":"US",
    "sg:address":"6212 S 172nd St",
    "sg:city":"Omaha",
    "sg:classifiers":[
        {
            "category":"Insurance",
            "subcategory":"Insurance Agent",
            "type":"Services"
        }
    ],
    "sg:phone":"+1 402 896 9193",
    "sg:postcode":"68135",
    "sg:province":"NE",
    "wof:name":"Lund Insurance",
    "wof:placetype":"venue"
},
  "geometry": {"coordinates":[-96.182171,41.195716],"type":"Point"}
}