{
  "type": "Feature",
  "properties": {
    "iso:country":"US",
    "sg:address":"2514 J St",
    "sg:city":"Ord",
    "sg:classifiers":[
        {
            "category":"Wholesale",
            "subcategory":"Construction Materials",
            "type":"Manufacturing & Wholesale Goods"
        },
        {
            "category":"Mining & Drilling",
            "type":"Manufacturing & Wholesale Goods"
        }
    ],
    "sg:phone":"+1 308 728 5062",
    "sg:postcode":"68862",
    "sg:province":"NE",
    "sg:tags":[
        "sand",
        "gravel"
    ],
    "wof:name":"Ulrich Gravel Inc",
    "wof:placetype":"venue"
},
  "geometry": {"coordinates":[-98.941693,41.605005],"type":"Point"}
}