{
  "type": "Feature",
  "properties": {
    "iso:country":"US",
    "sg:address":"801 S 16th St",
    "sg:city":"Omaha",
    "sg:classifiers":[
        {
            "category":"Home & Garden",
            "subcategory":"Carpets & Floor Coverings",
            "type":"Retail Goods"
        }
    ],
    "sg:phone":"+1 402 342 5349",
    "sg:postcode":"68108",
    "sg:province":"NE",
    "sg:tags":[
        "mattress"
    ],
    "wof:name":"Mattress Warehouse",
    "wof:placetype":"venue"
},
  "geometry": {"coordinates":[-95.937103,41.251999],"type":"Point"}
}