{
  "type": "Feature",
  "properties": {
    "iso:country":"US",
    "sg:address":"942 Ave B",
    "sg:city":"Bayard",
    "sg:classifiers":[
        {
            "category":"Organizations",
            "subcategory":"Religious Organization",
            "type":"Services"
        }
    ],
    "sg:phone":"+1 308 586 1160",
    "sg:postcode":"69334",
    "sg:province":"NE",
    "sg:tags":[
        "church"
    ],
    "wof:name":"Sacred Heart Catholic Church",
    "wof:placetype":"venue"
},
  "geometry": {"coordinates":[-103.326927,41.760056],"type":"Point"}
}