{
  "type": "Feature",
  "properties": {
    "iso:country":"US",
    "sg:address":"123 17th St",
    "sg:city":"Syracuse",
    "sg:classifiers":[
        {
            "category":"Manufacturing",
            "subcategory":"Printing",
            "type":"Manufacturing & Wholesale Goods"
        }
    ],
    "sg:phone":"+1 402 269 2135",
    "sg:postcode":"68446",
    "sg:province":"NE",
    "sg:tags":[
        "newspaper",
        "publishing"
    ],
    "sg:website":"www.newwestnews.com",
    "wof:name":"Maverick Media Inc",
    "wof:placetype":"venue"
},
  "geometry": {"coordinates":[-96.188351,40.66793],"type":"Point"}
}