{
  "type": "Feature",
  "properties": {
    "iso:country":"US",
    "sg:address":"1221 S 24th St",
    "sg:city":"Omaha",
    "sg:classifiers":[
        {
            "category":"Retail",
            "subcategory":"Auto Repair",
            "type":"Services"
        }
    ],
    "sg:phone":"+1 402 341 8973",
    "sg:postcode":"68108",
    "sg:province":"NE",
    "sg:tags":[
        "body",
        "shop",
        "painting",
        "automobile"
    ],
    "wof:name":"A B Competitive Auto Sales",
    "wof:placetype":"venue"
},
  "geometry": {"coordinates":[-95.946899,41.247398],"type":"Point"}
}