{
  "type": "Feature",
  "properties": {
    "iso:country":"US",
    "sg:address":"57065 720th Rd",
    "sg:city":"Fairbury",
    "sg:phone":"+1 402 729 4012",
    "sg:postcode":"68352",
    "sg:province":"NE",
    "sg:tags":[
        "farm",
        "grain",
        "cash"
    ],
    "wof:name":"Ervin Sokolik Farm",
    "wof:placetype":"venue"
},
  "geometry": {"coordinates":[-97.13060900000001,40.262666],"type":"Point"}
}