{
  "type": "Feature",
  "properties": {
    "iso:country":"US",
    "sg:address":"1105 C St",
    "sg:city":"Geneva",
    "sg:classifiers":[
        {
            "category":"Farming",
            "subcategory":"Livestock Farm",
            "type":"Manufacturing & Wholesale Goods"
        }
    ],
    "sg:phone":"+1 402 759 4716",
    "sg:postcode":"68361",
    "sg:province":"NE",
    "sg:tags":[
        "hog",
        "corn",
        "or",
        "feedlot"
    ],
    "wof:name":"Mumm Paul Farm",
    "wof:placetype":"venue"
},
  "geometry": {"coordinates":[-97.599318,40.520299],"type":"Point"}
}