{
  "type": "Feature",
  "properties": {
    "iso:country":"US",
    "sg:address":"801 S St",
    "sg:city":"Ord",
    "sg:classifiers":[
        {
            "category":"Government",
            "subcategory":"Office",
            "type":"Public Place"
        }
    ],
    "sg:phone":"+1 308 728 5071",
    "sg:postcode":"68862",
    "sg:province":"NE",
    "wof:name":"Valley County Extension Office",
    "wof:placetype":"venue"
},
  "geometry": {"coordinates":[-98.919077,41.597041],"type":"Point"}
}