{
  "type": "Feature",
  "properties": {
    "iso:country":"US",
    "sg:address":"1178 Co Rd 17",
    "sg:city":"Hooper",
    "sg:phone":"+1 402 654 3696",
    "sg:postcode":"68031",
    "sg:province":"NE",
    "sg:tags":[
        "farm",
        "corn"
    ],
    "wof:name":"Louis Thernes",
    "wof:placetype":"venue"
},
  "geometry": {"coordinates":[-96.597155,41.584979],"type":"Point"}
}