{
  "type": "Feature",
  "properties": {
    "addr:full":"2016 N 54th St Omaha NE 68104",
    "addr:housenumber":"2016",
    "addr:postcode":"68104",
    "addr:street":"N 54Th St",
    "iso:country":"US",
    "sg:address":"2016 N 54th St",
    "sg:city":"Omaha",
    "sg:classifiers":[
        {
            "category":"Arts & Performance",
            "subcategory":"Theater",
            "type":"Entertainment"
        }
    ],
    "sg:phone":"+1 402 827 4424",
    "sg:postcode":"68104",
    "sg:province":"NE",
    "sg:tags":[
        "talent",
        "agency",
        "casting"
    ],
    "wof:name":"Fugitive Booking & Talent Inc",
    "wof:placetype":"venue"
},
  "geometry": {"coordinates":[-95.997517,41.279934],"type":"Point"}
}