{
  "type": "Feature",
  "properties": {
    "iso:country":"US",
    "sg:address":"106 E Main St",
    "sg:city":"Murray",
    "sg:classifiers":[
        {
            "category":"Government",
            "subcategory":"Office",
            "type":"Public Place"
        }
    ],
    "sg:phone":"+1 402 235 2119",
    "sg:postcode":"68409",
    "sg:province":"NE",
    "sg:tags":[
        "city"
    ],
    "wof:name":"Murray Town Hall",
    "wof:placetype":"venue"
},
  "geometry": {"coordinates":[-95.928844,40.915114],"type":"Point"}
}