{
  "type": "Feature",
  "properties": {
    "iso:country":"US",
    "sg:address":"124 S 9th St",
    "sg:city":"Lincoln",
    "sg:classifiers":[
        {
            "category":"Wholesale",
            "subcategory":"Jewelry",
            "type":"Manufacturing & Wholesale Goods"
        }
    ],
    "sg:phone":"+1 402 483 4180",
    "sg:postcode":"68508",
    "sg:province":"NE",
    "sg:tags":[
        "beads"
    ],
    "wof:name":"5 Z's",
    "wof:placetype":"venue"
},
  "geometry": {"coordinates":[-96.708409,40.81278],"type":"Point"}
}