{
  "type": "Feature",
  "properties": {
    "iso:country":"US",
    "sg:address":"923 W 3rd St",
    "sg:city":"Alliance",
    "sg:classifiers":[
        {
            "category":"Autos & Motor Vehicles",
            "subcategory":"Auto Supplies",
            "type":"Retail Goods"
        }
    ],
    "sg:phone":"+1 308 762 3826",
    "sg:postcode":"69301",
    "sg:province":"NE",
    "wof:name":"Alliance Wrecking & Salvage Co",
    "wof:placetype":"venue"
},
  "geometry": {"coordinates":[-102.882705,42.096794],"type":"Point"}
}