{
  "type": "Feature",
  "properties": {
    "iso:country":"US",
    "sg:address":"12074 Burdette Cir",
    "sg:city":"Omaha",
    "sg:classifiers":[
        {
            "category":"Health Services",
            "subcategory":"Hospital",
            "type":"Services"
        }
    ],
    "sg:phone":"+1 402 496 9794",
    "sg:postcode":"68164",
    "sg:province":"NE",
    "sg:tags":[
        "specialty"
    ],
    "wof:name":"Larsen Dicks Services",
    "wof:placetype":"venue"
},
  "geometry": {"coordinates":[-96.101949,41.279029],"type":"Point"}
}