{
  "type": "Feature",
  "properties": {
    "iso:country":"US",
    "sg:address":"2300 N Webb Rd",
    "sg:city":"Grand Island",
    "sg:classifiers":[
        {
            "category":"Banks & Credit Unions",
            "subcategory":"Bank",
            "type":"Services"
        }
    ],
    "sg:phone":"+1 308 384 4765",
    "sg:postcode":"68803",
    "sg:province":"NE",
    "sg:tags":[
        "cashing",
        "check"
    ],
    "wof:name":"Express Check Advance",
    "wof:placetype":"venue"
},
  "geometry": {"coordinates":[-98.378766,40.943207],"type":"Point"}
}