{
  "type": "Feature",
  "properties": {
    "addr:full":"152 Slim Buttes Rd Chadron NE 69337",
    "addr:housenumber":"152",
    "addr:postcode":"69337",
    "addr:street":"Slim Buttes Rd",
    "iso:country":"US",
    "sg:address":"152 Slim Buttes Rd",
    "sg:city":"Chadron",
    "sg:classifiers":[
        {
            "category":"Farming",
            "subcategory":"Nursery",
            "type":"Manufacturing & Wholesale Goods"
        }
    ],
    "sg:phone":"+1 308 432 8170",
    "sg:postcode":"69337",
    "sg:province":"NE",
    "sg:tags":[
        "ornamental"
    ],
    "wof:name":"Lakota Greenhouses",
    "wof:placetype":"venue"
},
  "geometry": {"coordinates":[-102.949697,42.853432],"type":"Point"}
}