{
  "type": "Feature",
  "properties": {
    "iso:country":"US",
    "sg:address":"15531 Arbor St",
    "sg:city":"Omaha",
    "sg:classifiers":[
        {
            "category":"Building & Trades",
            "subcategory":"Plumbing",
            "type":"Services"
        }
    ],
    "sg:phone":"+1 402 334 6866",
    "sg:postcode":"68144",
    "sg:province":"NE",
    "sg:tags":[
        "plumbing",
        "contractor"
    ],
    "wof:name":"Jeff Mumm Plumbing Inc",
    "wof:placetype":"venue"
},
  "geometry": {"coordinates":[-96.157252,41.239164],"type":"Point"}
}