{
  "type": "Feature",
  "properties": {
    "iso:country":"US",
    "sg:address":"521 Easy St",
    "sg:city":"North Platte",
    "sg:classifiers":[
        {
            "category":"Restaurant",
            "type":"Food & Drink"
        }
    ],
    "sg:phone":"+1 308 532 1059",
    "sg:postcode":"69101",
    "sg:province":"NE",
    "sg:tags":[
        "caterer"
    ],
    "wof:name":"Nebraska Catering",
    "wof:placetype":"venue"
},
  "geometry": {"coordinates":[-100.75914400000001,41.123811],"type":"Point"}
}