{
  "type": "Feature",
  "properties": {
    "iso:country":"US",
    "sg:address":"8635 Military Rd",
    "sg:city":"Omaha",
    "sg:classifiers":[
        {
            "category":"Home & Garden",
            "subcategory":"Building Materials",
            "type":"Retail Goods"
        },
        {
            "category":"Building & Trades",
            "subcategory":"Construction",
            "type":"Services"
        },
        {
            "category":"Train Station",
            "subcategory":"Rail",
            "type":"Transportation"
        }
    ],
    "sg:phone":"+1 402 403 0187",
    "sg:postcode":"68134",
    "sg:province":"NE",
    "sg:tags":[
        "stairway",
        "fence",
        "rails",
        "accessory",
        "railing",
        "contractor",
        "fence-sales"
    ],
    "sg:website":"http://www.acreagefences.com",
    "wof:name":"Acreage Fences Inc",
    "wof:placetype":"venue"
},
  "geometry": {"coordinates":[-96.049474,41.310604],"type":"Point"}
}