{
  "type": "Feature",
  "properties": {
    "iso:country":"US",
    "sg:address":"233 N 48th St",
    "sg:city":"Lincoln",
    "sg:classifiers":[
        {
            "category":"Banks & Credit Unions",
            "subcategory":"Bank",
            "type":"Services"
        }
    ],
    "sg:phone":"+1 402 466 0044",
    "sg:postcode":"68504",
    "sg:province":"NE",
    "sg:tags":[
        "cashing",
        "check"
    ],
    "wof:name":"Easy Money",
    "wof:placetype":"venue"
},
  "geometry": {"coordinates":[-96.653869,40.815776],"type":"Point"}
}