{
  "type": "Feature",
  "properties": {
    "iso:country":"US",
    "sg:address":"5697 N 13th St",
    "sg:city":"Omaha",
    "sg:classifiers":[
        {
            "category":"Building & Trades",
            "subcategory":"Construction",
            "type":"Services"
        }
    ],
    "sg:phone":"+1 402 457 5000",
    "sg:postcode":"68110",
    "sg:province":"NE",
    "sg:tags":[
        "general",
        "contractor"
    ],
    "sg:website":"www.channellconstruction.com",
    "wof:name":"Channell Construction Company",
    "wof:placetype":"venue"
},
  "geometry": {"coordinates":[-95.932458,41.309395],"type":"Point"}
}