{
  "type": "Feature",
  "properties": {
    "iso:country":"US",
    "sg:address":"701 N 114th St",
    "sg:city":"Omaha",
    "sg:classifiers":[
        {
            "category":"Food & Beverages",
            "subcategory":"Liquor & Beverages",
            "type":"Retail Goods"
        }
    ],
    "sg:phone":"+1 402 431 8558",
    "sg:postcode":"68154",
    "sg:province":"NE",
    "sg:tags":[
        "alcoholic"
    ],
    "wof:name":"Omaha Wine Company",
    "wof:placetype":"venue"
},
  "geometry": {"coordinates":[-96.090897,41.265385],"type":"Point"}
}