{
  "type": "Feature",
  "properties": {
    "iso:country":"US",
    "sg:address":"6865 Turkey Creek Rd",
    "sg:city":"Elm Creek",
    "sg:phone":"+1 308 856 4276",
    "sg:postcode":"68836",
    "sg:province":"NE",
    "sg:tags":[
        "farm",
        "field",
        "corn",
        "soybean",
        "crop"
    ],
    "wof:name":"Harold Hubbard",
    "wof:placetype":"venue"
},
  "geometry": {"coordinates":[-99.389073,40.742223],"type":"Point"}
}