{
  "type": "Feature",
  "properties": {
    "iso:country":"US",
    "sg:address":"5919 S 118th Cir",
    "sg:city":"Omaha",
    "sg:classifiers":[
        {
            "category":"Communications",
            "subcategory":"Film & Video Production",
            "type":"Services"
        }
    ],
    "sg:phone":"+1 402 884 2043",
    "sg:postcode":"68137",
    "sg:province":"NE",
    "sg:tags":[
        "taping"
    ],
    "wof:name":"Vision Media",
    "wof:placetype":"venue"
},
  "geometry": {"coordinates":[-96.093789,41.199224],"type":"Point"}
}