{
  "type": "Feature",
  "properties": {
    "addr:full":"1624 O St Lincoln NE 68508",
    "addr:housenumber":"1624",
    "addr:postcode":"68508",
    "addr:street":"O St",
    "iso:country":"US",
    "sg:address":"1624 O St",
    "sg:city":"Lincoln",
    "sg:classifiers":[
        {
            "category":"Bars & Pubs",
            "type":"Food & Drink"
        }
    ],
    "sg:phone":"+1 402 435 4582",
    "sg:postcode":"68508",
    "sg:province":"NE",
    "sg:tags":[
        "lounge",
        "cocktail"
    ],
    "wof:name":"Spigot",
    "wof:placetype":"venue"
},
  "geometry": {"coordinates":[-96.697013,40.813702],"type":"Point"}
}