{
  "type": "Feature",
  "properties": {
    "iso:country":"US",
    "sg:address":"8533 E State Hwy 41",
    "sg:city":"Adams",
    "sg:classifiers":[
        {
            "category":"Building & Trades",
            "subcategory":"Electrical",
            "type":"Services"
        }
    ],
    "sg:phone":"+1 402 610 2270",
    "sg:postcode":"68301",
    "sg:province":"NE",
    "sg:tags":[
        "electric",
        "contractor"
    ],
    "wof:name":"Blain's Electric",
    "wof:placetype":"venue"
},
  "geometry": {"coordinates":[-96.60535299999999,40.465254],"type":"Point"}
}