{
  "type": "Feature",
  "properties": {
    "iso:country":"US",
    "sg:address":"201 Harrison St",
    "sg:city":"Allen",
    "sg:classifiers":[
        {
            "category":"Government",
            "subcategory":"Fire Station",
            "type":"Public Place"
        }
    ],
    "sg:phone":"+1 402 635 2141",
    "sg:postcode":"68710",
    "sg:province":"NE",
    "sg:tags":[
        "department"
    ],
    "wof:name":"Allen Fire Station",
    "wof:placetype":"venue"
},
  "geometry": {"coordinates":[-96.84388800000001,42.416136],"type":"Point"}
}