{
  "type": "Feature",
  "properties": {
    "addr:full":"413 N Ash St Gordon NE 69343",
    "addr:housenumber":"413",
    "addr:postcode":"69343",
    "addr:street":"N Ash St",
    "iso:country":"US",
    "sg:address":"413 N Ash St",
    "sg:city":"Gordon",
    "sg:classifiers":[
        {
            "category":"Farming",
            "subcategory":"Livestock Farm",
            "type":"Manufacturing & Wholesale Goods"
        }
    ],
    "sg:phone":"+1 308 282 1786",
    "sg:postcode":"69343",
    "sg:province":"NE",
    "sg:tags":[
        "animal",
        "general"
    ],
    "wof:name":"Hardin Family Farms LLC",
    "wof:placetype":"venue"
},
  "geometry": {"coordinates":[-102.200377,42.808701],"type":"Point"}
}