{
  "type": "Feature",
  "properties": {
    "iso:country":"US",
    "sg:address":"405 Church St",
    "sg:city":"Jansen",
    "sg:classifiers":[
        {
            "category":"Wholesale",
            "subcategory":"Non-durable Goods",
            "type":"Manufacturing & Wholesale Goods"
        }
    ],
    "sg:phone":"+1 402 424 3655",
    "sg:postcode":"68377",
    "sg:province":"NE",
    "sg:tags":[
        "advertising"
    ],
    "wof:name":"Art Friesen Co",
    "wof:placetype":"venue"
},
  "geometry": {"coordinates":[-97.08153,40.186404],"type":"Point"}
}