{
  "type": "Feature",
  "properties": {
    "addr:full":"655 W 23rd St Fremont NE 68025",
    "addr:housenumber":"655",
    "addr:postcode":"68025",
    "addr:street":"W 23Rd St",
    "iso:country":"US",
    "sg:address":"655 W 23rd St",
    "sg:city":"Fremont",
    "sg:classifiers":[
        {
            "category":"Social Services",
            "subcategory":"Adult Care",
            "type":"Services"
        }
    ],
    "sg:phone":"+1 402 721 9224",
    "sg:postcode":"68025",
    "sg:province":"NE",
    "sg:tags":[
        "home",
        "residential"
    ],
    "wof:name":"Nye Square Retirement Comnty",
    "wof:placetype":"venue"
},
  "geometry": {"coordinates":[-96.505318,41.451336],"type":"Point"}
}