{
  "type": "Feature",
  "properties": {
    "addr:full":"509 S Adams St Kimball NE 69145",
    "addr:housenumber":"509",
    "addr:postcode":"69145",
    "addr:street":"S Adams St",
    "iso:country":"US",
    "sg:address":"509 S Adams St",
    "sg:city":"Kimball",
    "sg:classifiers":[
        {
            "category":"Organizations",
            "subcategory":"Religious Organization",
            "type":"Services"
        }
    ],
    "sg:phone":"+1 308 235 4588",
    "sg:postcode":"69145",
    "sg:province":"NE",
    "wof:name":"St Hildas Episcopal Church",
    "wof:placetype":"venue"
},
  "geometry": {"coordinates":[-103.64790499999999,41.233025],"type":"Point"}
}