{
  "type": "Feature",
  "properties": {
    "iso:country":"US",
    "sg:address":"1914 D St",
    "sg:city":"Schuyler",
    "sg:classifiers":[
        {
            "category":"Building & Trades",
            "subcategory":"Construction",
            "type":"Services"
        }
    ],
    "sg:phone":"+1 402 352 3546",
    "sg:postcode":"68661",
    "sg:province":"NE",
    "sg:tags":[
        "contractor",
        "laying",
        "floor",
        "covering"
    ],
    "wof:name":"Dennys Floor Covering",
    "wof:placetype":"venue"
},
  "geometry": {"coordinates":[-97.05471799999999,41.457393],"type":"Point"}
}