{
  "type": "Feature",
  "properties": {
    "addr:full":"2365 B Rd Campbell NE 68982",
    "addr:housenumber":"2365 b",
    "addr:postcode":"68982",
    "addr:street":"Rd",
    "iso:country":"US",
    "sg:address":"2365 B Rd",
    "sg:city":"Campbell",
    "sg:classifiers":[
        {
            "category":"Farming",
            "subcategory":"Farm & Veterinary Services",
            "type":"Manufacturing & Wholesale Goods"
        }
    ],
    "sg:phone":"+1 402 756 8888",
    "sg:postcode":"68982",
    "sg:province":"NE",
    "sg:tags":[
        "aerial",
        "applicator"
    ],
    "wof:name":"Campbell Aerial Spraying Inc",
    "wof:placetype":"venue"
},
  "geometry": {"coordinates":[-98.749259,40.364927],"type":"Point"}
}