{
  "type": "Feature",
  "properties": {
    "addr:full":"103 E 2nd St Hoskins NE 68740",
    "addr:housenumber":"103",
    "addr:postcode":"68740",
    "addr:street":"E 2Nd St",
    "iso:country":"US",
    "sg:address":"103 E 2nd St",
    "sg:city":"Hoskins",
    "sg:classifiers":[
        {
            "category":"Retail",
            "subcategory":"Auto Repair",
            "type":"Services"
        }
    ],
    "sg:phone":"+1 402 565 4394",
    "sg:postcode":"68740",
    "sg:province":"NE",
    "sg:tags":[
        "repairing",
        "automobile"
    ],
    "wof:name":"Hoskins Motor & Auto Body",
    "wof:placetype":"venue"
},
  "geometry": {"coordinates":[-97.30633899999999,42.112458],"type":"Point"}
}