{
  "type": "Feature",
  "properties": {
    "addr:full":"626 S Ross Ave Hastings NE 68901",
    "addr:housenumber":"626",
    "addr:postcode":"68901",
    "addr:street":"S Ross Ave",
    "iso:country":"US",
    "sg:address":"626 S Ross Ave",
    "sg:city":"Hastings",
    "sg:classifiers":[
        {
            "category":"Personal",
            "subcategory":"Beauty Salon",
            "type":"Services"
        }
    ],
    "sg:phone":"+1 402 463 1188",
    "sg:postcode":"68901",
    "sg:province":"NE",
    "wof:name":"Blades Hair & Nails",
    "wof:placetype":"venue"
},
  "geometry": {"coordinates":[-98.381731,40.577906],"type":"Point"}
}