{
  "type": "Feature",
  "properties": {
    "addr:full":"103 Nebraska St Bartley NE 69020",
    "addr:housenumber":"103",
    "addr:postcode":"69020",
    "addr:street":"Nebraska St",
    "iso:country":"US",
    "sg:address":"103 Nebraska St",
    "sg:city":"Bartley",
    "sg:classifiers":[
        {
            "category":"Education",
            "subcategory":"School",
            "type":"Public Place"
        }
    ],
    "sg:phone":"+1 308 692 3223",
    "sg:postcode":"69020",
    "sg:province":"NE",
    "wof:name":"Twin Valley Public School",
    "wof:placetype":"venue"
},
  "geometry": {"coordinates":[-100.301564,40.25549],"type":"Point"}
}