{
  "type": "Feature",
  "properties": {
    "addr:full":"1717 Vinton St Omaha NE 68108",
    "addr:housenumber":"1717",
    "addr:postcode":"68108",
    "addr:street":"Vinton St",
    "iso:country":"US",
    "sg:address":"1717 Vinton St",
    "sg:city":"Omaha",
    "sg:classifiers":[
        {
            "category":"Home & Garden",
            "subcategory":"Carpets & Floor Coverings",
            "type":"Retail Goods"
        }
    ],
    "sg:phone":"+1 402 422 0270",
    "sg:postcode":"68108",
    "sg:province":"NE",
    "wof:name":"Mario Carpet Service",
    "wof:placetype":"venue"
},
  "geometry": {"coordinates":[-95.93953399999999,41.233522],"type":"Point"}
}