{
  "type": "Feature",
  "properties": {
    "iso:country":"US",
    "sg:address":"2336 23rd St",
    "sg:city":"Columbus",
    "sg:classifiers":[
        {
            "category":"Health Services",
            "subcategory":"Clinic",
            "type":"Services"
        }
    ],
    "sg:phone":"+1 402 562 8802",
    "sg:postcode":"68601",
    "sg:province":"NE",
    "sg:tags":[
        "home"
    ],
    "wof:name":"Beches Home Care",
    "wof:placetype":"venue"
},
  "geometry": {"coordinates":[-97.356354,41.438657],"type":"Point"}
}