{
  "type": "Feature",
  "properties": {
    "addr:full":"1340 K St Lincoln NE 68508",
    "addr:housenumber":"1340",
    "addr:postcode":"68508",
    "addr:street":"K St",
    "iso:country":"US",
    "sg:address":"1340 K St",
    "sg:city":"Lincoln",
    "sg:classifiers":[
        {
            "category":"Organizations",
            "subcategory":"Religious Organization",
            "type":"Services"
        }
    ],
    "sg:phone":"+1 402 477 4198",
    "sg:postcode":"68508",
    "sg:province":"NE",
    "sg:tags":[
        "church"
    ],
    "sg:website":"www.fbclincoln.org",
    "wof:name":"First Baptist Church",
    "wof:placetype":"venue"
},
  "geometry": {"coordinates":[-96.70162500000001,40.80927],"type":"Point"}
}