{
  "type": "Feature",
  "properties": {
    "iso:country":"US",
    "sg:address":"712 J St",
    "sg:city":"Geneva",
    "sg:classifiers":[
        {
            "category":"Building & Trades",
            "subcategory":"Construction",
            "type":"Services"
        }
    ],
    "sg:phone":"+1 402 759 4917",
    "sg:postcode":"68361",
    "sg:province":"NE",
    "sg:tags":[
        "silo"
    ],
    "wof:name":"Huskerland",
    "wof:placetype":"venue"
},
  "geometry": {"coordinates":[-97.606056,40.529772],"type":"Point"}
}