{
  "type": "Feature",
  "properties": {
    "iso:country":"US",
    "sg:address":"4865 Center St",
    "sg:city":"Omaha",
    "sg:classifiers":[
        {
            "category":"Shopping",
            "subcategory":"Tobacco",
            "type":"Retail Goods"
        }
    ],
    "sg:phone":"+1 402 558 0039",
    "sg:postcode":"68106",
    "sg:province":"NE",
    "sg:tags":[
        "shop",
        "cigarette",
        "cigar"
    ],
    "wof:name":"Tobacco Hut 10",
    "wof:placetype":"venue"
},
  "geometry": {"coordinates":[-95.986801,41.241501],"type":"Point"}
}