{
  "type": "Feature",
  "properties": {
    "iso:country":"US",
    "sg:address":"15 W 8th St",
    "sg:city":"Kearney",
    "sg:classifiers":[
        {
            "category":"Travel",
            "subcategory":"Hotels & Motels",
            "type":"Entertainment"
        }
    ],
    "sg:phone":"+1 308 234 5513",
    "sg:postcode":"68847",
    "sg:province":"NE",
    "sg:tags":[
        "operation"
    ],
    "sg:website":"www.super8.com",
    "wof:name":"Super 8 Motel",
    "wof:placetype":"venue"
},
  "geometry": {"coordinates":[-99.082346,40.681896],"type":"Point"}
}