{
  "type": "Feature",
  "properties": {
    "addr:full":"16647 Farnam St Omaha NE 68118",
    "addr:postcode":"16647;68118",
    "addr:street":"Farnam St",
    "iso:country":"US",
    "sg:address":"16647 Farnam St",
    "sg:city":"Omaha",
    "sg:classifiers":[
        {
            "category":"Professional",
            "subcategory":"Management & Consulting",
            "type":"Services"
        }
    ],
    "sg:phone":"+1 402 333 4279",
    "sg:postcode":"68118",
    "sg:province":"NE",
    "sg:tags":[
        "business"
    ],
    "wof:name":"Garrigan Richard P & Assoc",
    "wof:placetype":"venue"
},
  "geometry": {"coordinates":[-96.175363,41.256295],"type":"Point"}
}