{
  "type": "Feature",
  "properties": {
    "iso:country":"US",
    "sg:address":"120 Diers Ave",
    "sg:city":"Grand Island",
    "sg:classifiers":[
        {
            "category":"Autos & Motor Vehicles",
            "subcategory":"Automobile Sales",
            "type":"Retail Goods"
        }
    ],
    "sg:phone":"+1 308 384 1700",
    "sg:postcode":"68803",
    "sg:province":"NE",
    "sg:tags":[
        "car",
        "dealer"
    ],
    "sg:website":"www.andersonautogroup.com",
    "wof:name":"Anderson Ford Lincoln Mercury",
    "wof:placetype":"venue"
},
  "geometry": {"coordinates":[-98.383771,40.91934],"type":"Point"}
}