{
  "type": "Feature",
  "properties": {
    "addr:full":"653 Co Rd 44 Tekamah NE 68061",
    "addr:housenumber":"653;44",
    "addr:postcode":"68061",
    "addr:street":"Co Rd",
    "iso:country":"US",
    "sg:address":"653 Co Rd 44",
    "sg:city":"Tekamah",
    "sg:classifiers":[
        {
            "category":"Farming",
            "subcategory":"Farm",
            "type":"Manufacturing & Wholesale Goods"
        }
    ],
    "sg:phone":"+1 402 374 1190",
    "sg:postcode":"68061",
    "sg:province":"NE",
    "sg:tags":[
        "crop",
        "general"
    ],
    "wof:name":"Quick Kord",
    "wof:placetype":"venue"
},
  "geometry": {"coordinates":[-96.144069,41.763507],"type":"Point"}
}