{
  "type": "Feature",
  "properties": {
    "addr:full":"912 River Rd Beemer NE 68716",
    "addr:housenumber":"912",
    "addr:postcode":"68716",
    "addr:street":"River Rd",
    "iso:country":"US",
    "sg:address":"912 River Rd",
    "sg:city":"Beemer",
    "sg:classifiers":[
        {
            "category":"Farming",
            "subcategory":"Livestock Farm",
            "type":"Manufacturing & Wholesale Goods"
        }
    ],
    "sg:phone":"+1 402 528 3737",
    "sg:postcode":"68716",
    "sg:province":"NE",
    "sg:tags":[
        "hog"
    ],
    "wof:name":"Grandview Inc",
    "wof:placetype":"venue"
},
  "geometry": {"coordinates":[-96.862933,41.916726],"type":"Point"}
}