{
  "type": "Feature",
  "properties": {
    "addr:full":"1116 Nelson St Saint Paul NE 68873",
    "addr:housenumber":"1116",
    "addr:postcode":"68873",
    "addr:street":"Nelson St",
    "iso:country":"US",
    "sg:address":"1116 Nelson St",
    "sg:city":"Saint Paul",
    "sg:classifiers":[
        {
            "category":"Building & Trades",
            "subcategory":"Landscaping Services",
            "type":"Services"
        }
    ],
    "sg:phone":"+1 308 754 4589",
    "sg:postcode":"68873",
    "sg:province":"NE",
    "sg:tags":[
        "lawn",
        "care"
    ],
    "wof:name":"Reams Lawns",
    "wof:placetype":"venue"
},
  "geometry": {"coordinates":[-98.46870800000001,41.216958],"type":"Point"}
}