{
  "type": "Feature",
  "properties": {
    "addr:full":"600 S 42nd St Omaha NE 68105",
    "addr:housenumber":"600",
    "addr:postcode":"68105",
    "addr:street":"S 42Nd St",
    "iso:country":"US",
    "sg:address":"600 S 42nd St",
    "sg:city":"Omaha",
    "sg:classifiers":[
        {
            "category":"Health Services",
            "subcategory":"Doctor",
            "type":"Services"
        }
    ],
    "sg:phone":"+1 402 552 3257",
    "sg:postcode":"68105",
    "sg:province":"NE",
    "sg:tags":[
        "physician",
        "surgeon"
    ],
    "wof:name":"Nebraska Medical Ctr",
    "wof:placetype":"venue"
},
  "geometry": {"coordinates":[-95.97577099999999,41.257248],"type":"Point"}
}