{
  "type": "Feature",
  "properties": {
    "iso:country":"US",
    "sg:address":"5310 S 56th St",
    "sg:city":"Lincoln",
    "sg:classifiers":[
        {
            "category":"Bars & Pubs",
            "type":"Food & Drink"
        }
    ],
    "sg:phone":"+1 402 420 6494",
    "sg:postcode":"68516",
    "sg:province":"NE",
    "wof:name":"Libations Too",
    "wof:placetype":"venue"
},
  "geometry": {"coordinates":[-96.644176,40.756398],"type":"Point"}
}