{
  "type": "Feature",
  "properties": {
    "addr:full":"106 E 2nd St Mc Cook NE 69001",
    "addr:housenumber":"106",
    "addr:postcode":"69001",
    "addr:street":"E 2Nd St Mc Cook Ne",
    "iso:country":"US",
    "sg:address":"106 E 2nd St",
    "sg:city":"Mc Cook",
    "sg:classifiers":[
        {
            "category":"Retail",
            "subcategory":"Repair Shop",
            "type":"Services"
        }
    ],
    "sg:phone":"+1 308 345 6174",
    "sg:postcode":"69001",
    "sg:province":"NE",
    "sg:tags":[
        "lock",
        "locksmith"
    ],
    "wof:name":"7-D Lockshop",
    "wof:placetype":"venue"
},
  "geometry": {"coordinates":[-100.623228,40.198499],"type":"Point"}
}