{
  "type": "Feature",
  "properties": {
    "iso:country":"US",
    "sg:address":"7528 Washington St",
    "sg:city":"Omaha",
    "sg:classifiers":[
        {
            "category":"Social Services",
            "subcategory":"Child Care",
            "type":"Services"
        }
    ],
    "sg:phone":"+1 402 597 2712",
    "sg:postcode":"68127",
    "sg:province":"NE",
    "sg:tags":[
        "day"
    ],
    "wof:name":"Rugrats Day Care",
    "wof:placetype":"venue"
},
  "geometry": {"coordinates":[-96.031786,41.196655],"type":"Point"}
}