{
  "type": "Feature",
  "properties": {
    "iso:country":"US",
    "sg:address":"840 11th Ave",
    "sg:city":"Sidney",
    "sg:classifiers":[
        {
            "category":"Insurance",
            "subcategory":"Hazard Insurance",
            "type":"Services"
        }
    ],
    "sg:phone":"+1 308 254 5678",
    "sg:postcode":"69162",
    "sg:province":"NE",
    "sg:tags":[
        "carrier"
    ],
    "wof:name":"Formers",
    "wof:placetype":"venue"
},
  "geometry": {"coordinates":[-102.978099,41.145332],"type":"Point"}
}