{
  "type": "Feature",
  "properties": {
    "iso:country":"US",
    "sg:address":"17600 N Ridge Ln",
    "sg:city":"Davey",
    "sg:classifiers":[
        {
            "category":"Sports & Exercise",
            "subcategory":"Golf",
            "type":"Entertainment"
        }
    ],
    "sg:phone":"+1 402 785 3695",
    "sg:postcode":"68336",
    "sg:province":"NE",
    "sg:tags":[
        "equipment",
        "supply",
        "course"
    ],
    "wof:name":"D & S Aerification Inc",
    "wof:placetype":"venue"
},
  "geometry": {"coordinates":[-96.707382,40.98526],"type":"Point"}
}