{
  "type": "Feature",
  "properties": {
    "iso:country":"US",
    "sg:address":"13808 Wright St",
    "sg:city":"Omaha",
    "sg:classifiers":[
        {
            "category":"Professional",
            "type":"Services"
        }
    ],
    "sg:phone":"+1 402 330 4663",
    "sg:postcode":"68144",
    "sg:province":"NE",
    "sg:tags":[
        "arts",
        "artist"
    ],
    "wof:name":"K M Dovel",
    "wof:placetype":"venue"
},
  "geometry": {"coordinates":[-96.129099,41.233466],"type":"Point"}
}