{
  "type": "Feature",
  "properties": {
    "addr:full":"302 US Hwy 20 Gordon NE 69343",
    "addr:housenumber":"302",
    "addr:postcode":"69343",
    "addr:street":"Us Hwy 20",
    "iso:country":"US",
    "sg:address":"302 US Hwy 20",
    "sg:city":"Gordon",
    "sg:classifiers":[
        {
            "category":"Autos & Motor Vehicles",
            "subcategory":"Automobile Sales",
            "type":"Retail Goods"
        }
    ],
    "sg:phone":"+1 308 282 0330",
    "sg:postcode":"69343",
    "sg:province":"NE",
    "sg:tags":[
        "car",
        "dealer"
    ],
    "sg:website":"www.miskiminsmotors.com",
    "wof:name":"Miskimins Motor Co Inc",
    "wof:placetype":"venue"
},
  "geometry": {"coordinates":[-102.200553,42.799957],"type":"Point"}
}