{
  "type": "Feature",
  "properties": {
    "addr:full":"510 Lincoln Ave York NE 68467",
    "addr:housenumber":"510",
    "addr:postcode":"68467",
    "addr:street":"Lincoln Ave",
    "iso:country":"US",
    "sg:address":"510 Lincoln Ave",
    "sg:city":"York",
    "sg:classifiers":[
        {
            "category":"Government",
            "subcategory":"Court House",
            "type":"Public Place"
        }
    ],
    "sg:phone":"+1 402 362 5428",
    "sg:postcode":"68467",
    "sg:province":"NE",
    "sg:tags":[
        "county"
    ],
    "wof:name":"York County Judge",
    "wof:placetype":"venue"
},
  "geometry": {"coordinates":[-97.592956,40.866782],"type":"Point"}
}