{
  "type": "Feature",
  "properties": {
    "iso:country":"US",
    "sg:address":"43572 Rd 737",
    "sg:city":"Bertrand",
    "sg:classifiers":[
        {
            "category":"Farming",
            "subcategory":"Farm",
            "type":"Manufacturing & Wholesale Goods"
        }
    ],
    "sg:phone":"+1 308 472 3742",
    "sg:postcode":"68927",
    "sg:province":"NE",
    "sg:tags":[
        "crop",
        "general"
    ],
    "wof:name":"Raymond Renken",
    "wof:placetype":"venue"
},
  "geometry": {"coordinates":[-99.687153,40.510208],"type":"Point"}
}