{
  "type": "Feature",
  "properties": {
    "iso:country":"US",
    "sg:address":"2206 Franklin St",
    "sg:city":"Bellevue",
    "sg:classifiers":[
        {
            "category":"Organizations",
            "subcategory":"Religious Organization",
            "type":"Services"
        }
    ],
    "sg:phone":"+1 402 932 6320",
    "sg:postcode":"68005",
    "sg:province":"NE",
    "sg:tags":[
        "church"
    ],
    "wof:name":"New Testament Fellowship Chr",
    "wof:placetype":"venue"
},
  "geometry": {"coordinates":[-95.893764,41.137159],"type":"Point"}
}