{
  "type": "Feature",
  "properties": {
    "iso:country":"US",
    "sg:address":"2417 Kingsgate Rd",
    "sg:city":"Scottsbluff",
    "sg:classifiers":[
        {
            "category":"Building & Trades",
            "subcategory":"Construction",
            "type":"Services"
        }
    ],
    "sg:phone":"+1 308 630 7997",
    "sg:postcode":"69361",
    "sg:province":"NE",
    "sg:tags":[
        "house"
    ],
    "wof:name":"Quality Renovations",
    "wof:placetype":"venue"
},
  "geometry": {"coordinates":[-103.692301,41.893915],"type":"Point"}
}