{
  "type": "Feature",
  "properties": {
    "addr:full":"2111 Edith Ct Alliance NE 69301",
    "addr:housenumber":"2111",
    "addr:postcode":"69301",
    "addr:street":"Edith Ct",
    "iso:country":"US",
    "sg:address":"2111 Edith Ct",
    "sg:city":"Alliance",
    "sg:classifiers":[
        {
            "category":"Health Services",
            "subcategory":"Medical Lab",
            "type":"Services"
        }
    ],
    "sg:phone":"+1 308 762 4991",
    "sg:postcode":"69301",
    "sg:province":"NE",
    "sg:tags":[
        "detection",
        "equipment",
        "drug"
    ],
    "wof:name":"WPCI",
    "wof:placetype":"venue"
},
  "geometry": {"coordinates":[-102.873935,42.116933],"type":"Point"}
}