{
  "type": "Feature",
  "properties": {
    "iso:country":"US",
    "sg:address":"421 Park Ave",
    "sg:city":"Omaha",
    "sg:classifiers":[
        {
            "category":"Organizations",
            "subcategory":"Religious Organization",
            "type":"Services"
        }
    ],
    "sg:phone":"+1 402 345 5009",
    "sg:postcode":"68131",
    "sg:province":"NE",
    "sg:tags":[
        "church"
    ],
    "sg:website":"www.fbcomaha.com",
    "wof:name":"First Baptist Church ABC",
    "wof:placetype":"venue"
},
  "geometry": {"coordinates":[-95.955777,41.256123],"type":"Point"}
}