{
  "type": "Feature",
  "properties": {
    "iso:country":"US",
    "sg:address":"87252 State Hwy 15",
    "sg:city":"Coleridge",
    "sg:classifiers":[
        {
            "category":"Professional",
            "type":"Services"
        }
    ],
    "sg:phone":"+1 402 283 4862",
    "sg:postcode":"68727",
    "sg:province":"NE",
    "sg:tags":[
        "establishment"
    ],
    "wof:name":"Dac Inc",
    "wof:placetype":"venue"
},
  "geometry": {"coordinates":[-97.211101,42.474601],"type":"Point"}
}