{
  "type": "Feature",
  "properties": {
    "addr:full":"1104 3rd Corso Nebraska City NE 68410",
    "addr:housenumber":"1104",
    "addr:postcode":"68410",
    "addr:street":"3Rd Corso",
    "iso:country":"US",
    "sg:address":"1104 3rd Corso",
    "sg:city":"Nebraska City",
    "sg:classifiers":[
        {
            "category":"Shopping",
            "subcategory":"Bicycles & Sporting Goods",
            "type":"Retail Goods"
        }
    ],
    "sg:phone":"+1 402 873 7509",
    "sg:postcode":"68410",
    "sg:province":"NE",
    "wof:name":"Thurmans Bike & Sport",
    "wof:placetype":"venue"
},
  "geometry": {"coordinates":[-95.86020499999999,40.673968],"type":"Point"}
}