{
  "type": "Feature",
  "properties": {
    "iso:country":"US",
    "sg:address":"10800 N 72nd St",
    "sg:city":"Omaha",
    "sg:classifiers":[
        {
            "category":"Retail",
            "subcategory":"Animal Services",
            "type":"Services"
        }
    ],
    "sg:phone":"+1 402 572 7276",
    "sg:postcode":"68122",
    "sg:province":"NE",
    "sg:tags":[
        "training",
        "dog"
    ],
    "wof:name":"Companion Dog Club",
    "wof:placetype":"venue"
},
  "geometry": {"coordinates":[-96.023893,41.355854],"type":"Point"}
}