{
  "type": "Feature",
  "properties": {
    "iso:country":"US",
    "sg:address":"11128 John Galt Blvd # 125",
    "sg:city":"Omaha",
    "sg:classifiers":[
        {
            "category":"Shopping",
            "subcategory":"Pharmacy",
            "type":"Retail Goods"
        }
    ],
    "sg:phone":"+1 402 592 9667",
    "sg:postcode":"68137",
    "sg:province":"NE",
    "sg:tags":[
        "medicines-patent",
        "proprietary"
    ],
    "sg:website":"http://www.ortho-mcneil.com",
    "wof:name":"Ortho-Mcneil Pharmaceutical, Inc.",
    "wof:placetype":"venue"
},
  "geometry": {"coordinates":[-96.087781,41.20911],"type":"Point"}
}