{
  "type": "Feature",
  "properties": {
    "addr:full":"435 Cherry St Riverdale NE 68870",
    "addr:housenumber":"435",
    "addr:postcode":"68870",
    "addr:street":"Cherry St",
    "iso:country":"US",
    "sg:address":"435 Cherry St",
    "sg:city":"Riverdale",
    "sg:classifiers":[
        {
            "category":"Building & Trades",
            "subcategory":"Construction",
            "type":"Services"
        }
    ],
    "sg:phone":"+1 308 893 2006",
    "sg:postcode":"68870",
    "sg:province":"NE",
    "sg:tags":[
        "resurfacing",
        "laying",
        "refinishing",
        "floor"
    ],
    "wof:name":"Garringer Customer Wood Floors",
    "wof:placetype":"venue"
},
  "geometry": {"coordinates":[-99.164311,40.78609],"type":"Point"}
}