{
  "type": "Feature",
  "properties": {
    "addr:full":"331 W State St Grand Island NE 68801",
    "addr:housenumber":"331",
    "addr:postcode":"68801",
    "addr:street":"W State St",
    "iso:country":"US",
    "sg:address":"331 W State St",
    "sg:city":"Grand Island",
    "sg:classifiers":[
        {
            "category":"Shopping",
            "subcategory":"Gifts & Souvenirs",
            "type":"Retail Goods"
        }
    ],
    "sg:phone":"+1 308 382 3971",
    "sg:postcode":"68801",
    "sg:province":"NE",
    "sg:tags":[
        "shop"
    ],
    "wof:name":"Nana's Country Store",
    "wof:placetype":"venue"
},
  "geometry": {"coordinates":[-98.353548,40.93851],"type":"Point"}
}