{
  "type": "Feature",
  "properties": {
    "iso:country":"US",
    "sg:address":"4430 N North Rd",
    "sg:city":"Grand Island",
    "sg:classifiers":[
        {
            "category":"Wholesale",
            "subcategory":"Motor Vehicles",
            "type":"Manufacturing & Wholesale Goods"
        }
    ],
    "sg:phone":"+1 308 382 3384",
    "sg:postcode":"68803",
    "sg:province":"NE",
    "sg:tags":[
        "trailer"
    ],
    "wof:name":"180 Trailer Sales",
    "wof:placetype":"venue"
},
  "geometry": {"coordinates":[-98.39793400000001,40.974995],"type":"Point"}
}