{
  "type": "Feature",
  "properties": {
    "iso:country":"US",
    "sg:address":"211 12th Corso",
    "sg:city":"Nebraska City",
    "sg:classifiers":[
        {
            "category":"Building & Trades",
            "subcategory":"Landscaping Services",
            "type":"Services"
        }
    ],
    "sg:phone":"+1 402 873 4753",
    "sg:postcode":"68410",
    "sg:province":"NE",
    "sg:tags":[
        "lawn"
    ],
    "wof:name":"Bales-K-Lawn",
    "wof:placetype":"venue"
},
  "geometry": {"coordinates":[-95.847157,40.665623],"type":"Point"}
}