{
  "type": "Feature",
  "properties": {
    "iso:country":"US",
    "sg:address":"10000 California St",
    "sg:city":"Omaha",
    "sg:classifiers":[
        {
            "category":"Restaurant",
            "type":"Food & Drink"
        }
    ],
    "sg:menulink":"http://www.allmenus.com/ne/omaha/181127-great-wraps/menu/",
    "sg:phone":"+1 402 398 9727",
    "sg:postcode":"68114",
    "sg:province":"NE",
    "sg:tags":[
        "wrap",
        "american",
        "sandwich"
    ],
    "wof:name":"Great Wraps",
    "wof:placetype":"venue"
},
  "geometry": {"coordinates":[-96.068697,41.266264],"type":"Point"}
}