{
  "type": "Feature",
  "properties": {
    "addr:full":"12914 W Scott Rd Beatrice NE 68310",
    "addr:housenumber":"12914",
    "addr:postcode":"68310",
    "addr:street":"W Scott Rd",
    "iso:country":"US",
    "sg:address":"12914 W Scott Rd",
    "sg:city":"Beatrice",
    "sg:classifiers":[
        {
            "category":"Farming",
            "subcategory":"Livestock Farm",
            "type":"Manufacturing & Wholesale Goods"
        }
    ],
    "sg:phone":"+1 402 228 0789",
    "sg:postcode":"68310",
    "sg:province":"NE",
    "sg:tags":[
        "hog",
        "confinement"
    ],
    "wof:name":"Hamhocks Inc",
    "wof:placetype":"venue"
},
  "geometry": {"coordinates":[-96.895668,40.26284],"type":"Point"}
}