{
  "type": "Feature",
  "properties": {
    "iso:country":"US",
    "sg:address":"101 Grand Ave",
    "sg:city":"Ravenna",
    "sg:classifiers":[
        {
            "category":"Railroad",
            "type":"Transportation"
        }
    ],
    "sg:phone":"+1 308 452 4280",
    "sg:postcode":"68869",
    "sg:province":"NE",
    "wof:name":"Burlington Northern Santa Fe",
    "wof:placetype":"venue"
},
  "geometry": {"coordinates":[-98.91272499999999,41.024329],"type":"Point"}
}