{
  "type": "Feature",
  "properties": {
    "iso:country":"US",
    "sg:address":"4363 G Rd",
    "sg:city":"Dunbar",
    "sg:phone":"+1 402 259 3750",
    "sg:postcode":"68346",
    "sg:province":"NE",
    "sg:tags":[
        "farm",
        "grain",
        "cash"
    ],
    "wof:name":"Hobbie Farm & Seed",
    "wof:placetype":"venue"
},
  "geometry": {"coordinates":[-96.04887100000001,40.697124],"type":"Point"}
}