{
  "type": "Feature",
  "properties": {
    "addr:full":"15900 Midway Rd Bennet NE 68317",
    "addr:housenumber":"15900",
    "addr:postcode":"68317",
    "addr:street":"Midway Rd",
    "iso:country":"US",
    "sg:address":"15900 Midway Rd",
    "sg:city":"Bennet",
    "sg:classifiers":[
        {
            "category":"Building & Trades",
            "subcategory":"Construction",
            "type":"Services"
        }
    ],
    "sg:phone":"+1 402 466 1464",
    "sg:postcode":"68317",
    "sg:province":"NE",
    "sg:tags":[
        "painter"
    ],
    "wof:name":"Doug Delaney's Painting",
    "wof:placetype":"venue"
},
  "geometry": {"coordinates":[-96.505934,40.733393],"type":"Point"}
}