{
  "type": "Feature",
  "properties": {
    "iso:country":"US",
    "sg:address":"21700 W Angus Rd",
    "sg:city":"Gretna",
    "sg:classifiers":[
        {
            "category":"Building & Trades",
            "subcategory":"Construction",
            "type":"Services"
        }
    ],
    "sg:phone":"+1 402 332 4395",
    "sg:postcode":"68028",
    "sg:province":"NE",
    "sg:tags":[
        "house"
    ],
    "wof:name":"American Best Construction",
    "wof:placetype":"venue"
},
  "geometry": {"coordinates":[-96.25471,41.139642],"type":"Point"}
}