{
  "type": "Feature",
  "properties": {
    "addr:full":"1516 10th St Gering NE 69341",
    "addr:housenumber":"1516",
    "addr:postcode":"69341",
    "addr:street":"10Th St",
    "iso:country":"US",
    "sg:address":"1516 10th St",
    "sg:city":"Gering",
    "sg:classifiers":[
        {
            "category":"Restaurant",
            "type":"Food & Drink"
        }
    ],
    "sg:phone":"+1 308 436 5669",
    "sg:postcode":"69341",
    "sg:province":"NE",
    "sg:tags":[
        "eating"
    ],
    "wof:name":"China House Restaurant",
    "wof:placetype":"venue"
},
  "geometry": {"coordinates":[-103.660251,41.824019],"type":"Point"}
}