{
  "type": "Feature",
  "properties": {
    "iso:country":"US",
    "sg:address":"13613 Stanford St",
    "sg:city":"Omaha",
    "sg:classifiers":[
        {
            "category":"Building & Trades",
            "subcategory":"Landscaping Services",
            "type":"Services"
        }
    ],
    "sg:phone":"+1 402 330 3719",
    "sg:postcode":"68144",
    "sg:province":"NE",
    "sg:tags":[
        "lawn",
        "maintenance",
        "grounds"
    ],
    "wof:name":"Green Thumb Lawn Svc",
    "wof:placetype":"venue"
},
  "geometry": {"coordinates":[-96.127262,41.235631],"type":"Point"}
}