{
  "type": "Feature",
  "properties": {
    "iso:country":"US",
    "sg:address":"349 E 4th St",
    "sg:city":"Minden",
    "sg:classifiers":[
        {
            "category":"Organizations",
            "subcategory":"Religious Organization",
            "type":"Services"
        }
    ],
    "sg:phone":"+1 308 832 1303",
    "sg:postcode":"68959",
    "sg:province":"NE",
    "sg:tags":[
        "church"
    ],
    "wof:name":"Bethel Baptist Church",
    "wof:placetype":"venue"
},
  "geometry": {"coordinates":[-98.948211,40.498433],"type":"Point"}
}