{
  "type": "Feature",
  "properties": {
    "iso:country":"US",
    "sg:address":"904 Central Ave",
    "sg:city":"Nebraska City",
    "sg:classifiers":[
        {
            "category":"Shopping",
            "subcategory":"Jewelry",
            "type":"Retail Goods"
        }
    ],
    "sg:phone":"+1 402 873 5058",
    "sg:postcode":"68410",
    "sg:province":"NE",
    "sg:tags":[
        "jeweler"
    ],
    "wof:name":"Martin Jewelry & Gifts",
    "wof:placetype":"venue"
},
  "geometry": {"coordinates":[-95.85700900000001,40.676701],"type":"Point"}
}