{
  "type": "Feature",
  "properties": {
    "addr:full":"300 Cherokee Rd Lexington NE 68850",
    "addr:housenumber":"300",
    "addr:postcode":"68850",
    "addr:street":"Cherokee Rd",
    "iso:country":"US",
    "sg:address":"300 Cherokee Rd",
    "sg:city":"Lexington",
    "sg:classifiers":[
        {
            "category":"Wholesale",
            "subcategory":"Electrical",
            "type":"Manufacturing & Wholesale Goods"
        }
    ],
    "sg:phone":"+1 308 324 6828",
    "sg:postcode":"68850",
    "sg:province":"NE",
    "sg:tags":[
        "communication",
        "radio",
        "system"
    ],
    "wof:name":"Motorola Communications",
    "wof:placetype":"venue"
},
  "geometry": {"coordinates":[-99.742901,40.795648],"type":"Point"}
}