{
  "type": "Feature",
  "properties": {
    "iso:country":"US",
    "sg:address":"200322 Rolling Hills Rd",
    "sg:city":"Scottsbluff",
    "sg:classifiers":[
        {
            "category":"Social Services",
            "type":"Services"
        }
    ],
    "sg:phone":"+1 308 632 7000",
    "sg:postcode":"69361",
    "sg:province":"NE",
    "wof:name":"Michael Slosnerick PHD",
    "wof:placetype":"venue"
},
  "geometry": {"coordinates":[-103.677863,41.923591],"type":"Point"}
}