{
  "type": "Feature",
  "properties": {
    "iso:country":"US",
    "sg:address":"121 E S St",
    "sg:city":"Ogallala",
    "sg:classifiers":[
        {
            "category":"Real Estate",
            "subcategory":"Real Estate Agent",
            "type":"Services"
        }
    ],
    "sg:phone":"+1 308 284 6701",
    "sg:postcode":"69153",
    "sg:province":"NE",
    "wof:name":"Hines Construction Co",
    "wof:placetype":"venue"
},
  "geometry": {"coordinates":[-101.69689,41.127719],"type":"Point"}
}