{
  "type": "Feature",
  "properties": {
    "iso:country":"US",
    "sg:address":"827 W 1st St",
    "sg:city":"Hastings",
    "sg:classifiers":[
        {
            "category":"Wholesale",
            "subcategory":"Machinery & Supplies",
            "type":"Manufacturing & Wholesale Goods"
        }
    ],
    "sg:phone":"+1 402 462 9700",
    "sg:postcode":"68901",
    "sg:province":"NE",
    "sg:tags":[
        "industrial"
    ],
    "wof:name":"Fastenal Company",
    "wof:placetype":"venue"
},
  "geometry": {"coordinates":[-98.391965,40.584193],"type":"Point"}
}