{
  "type": "Feature",
  "properties": {
    "addr:full":"3416 Woolworth Ave Omaha NE 68105",
    "addr:housenumber":"3416",
    "addr:postcode":"68105",
    "addr:street":"Woolworth Ave",
    "iso:country":"US",
    "sg:address":"3416 Woolworth Ave",
    "sg:city":"Omaha",
    "sg:classifiers":[
        {
            "category":"Organizations",
            "subcategory":"Religious Organization",
            "type":"Services"
        }
    ],
    "sg:phone":"+1 402 345 5423",
    "sg:postcode":"68105",
    "sg:province":"NE",
    "sg:tags":[
        "church"
    ],
    "wof:name":"Westminster Presbyterian Chr",
    "wof:placetype":"venue"
},
  "geometry": {"coordinates":[-95.963628,41.245354],"type":"Point"}
}