{
  "type": "Feature",
  "properties": {
    "iso:country":"US",
    "sg:address":"2885 Laurel St",
    "sg:city":"Lincoln",
    "sg:classifiers":[
        {
            "category":"Professional",
            "subcategory":"Lawyer & Legal Services",
            "type":"Services"
        }
    ],
    "sg:phone":"+1 402 328 9899",
    "sg:postcode":"68502",
    "sg:province":"NE",
    "sg:tags":[
        "attorney"
    ],
    "wof:name":"Brown Immigration Law LLC",
    "wof:placetype":"venue"
},
  "geometry": {"coordinates":[-96.680869,40.780317],"type":"Point"}
}