{
  "type": "Feature",
  "properties": {
    "addr:full":"506 W 12 Rd Phillips NE 68865",
    "addr:housenumber":"506",
    "addr:postcode":"68865",
    "addr:street":"W 12 Rd",
    "iso:country":"US",
    "sg:address":"506 W 12 Rd",
    "sg:city":"Phillips",
    "sg:classifiers":[
        {
            "category":"Building & Trades",
            "subcategory":"Construction",
            "type":"Services"
        }
    ],
    "sg:phone":"+1 402 886 2336",
    "sg:postcode":"68865",
    "sg:province":"NE",
    "sg:tags":[
        "contractor"
    ],
    "wof:name":"Contract Exploration Drilling",
    "wof:placetype":"venue"
},
  "geometry": {"coordinates":[-98.197936,40.857819],"type":"Point"}
}