{
  "type": "Feature",
  "properties": {
    "addr:full":"830 N Chestnut St Wahoo NE 68066",
    "addr:housenumber":"830",
    "addr:postcode":"68066",
    "addr:street":"N Chestnut St",
    "iso:country":"US",
    "sg:address":"830 N Chestnut St",
    "sg:city":"Wahoo",
    "sg:classifiers":[
        {
            "category":"Autos & Motor Vehicles",
            "subcategory":"Automobile Sales",
            "type":"Retail Goods"
        }
    ],
    "sg:phone":"+1 402 443 3538",
    "sg:postcode":"68066",
    "sg:province":"NE",
    "sg:tags":[
        "repair",
        "used",
        "general"
    ],
    "wof:name":"Cudas Auto-Towing & Repair",
    "wof:placetype":"venue"
},
  "geometry": {"coordinates":[-96.622195,41.213542],"type":"Point"}
}