{
  "type": "Feature",
  "properties": {
    "addr:full":"5210 S 49th St Lincoln NE 68516",
    "addr:housenumber":"5210",
    "addr:postcode":"68516",
    "addr:street":"S 49Th St",
    "iso:country":"US",
    "sg:address":"5210 S 49th St",
    "sg:city":"Lincoln",
    "sg:classifiers":[
        {
            "category":"Building & Trades",
            "subcategory":"Electrical",
            "type":"Services"
        }
    ],
    "sg:phone":"+1 402 489 4564",
    "sg:postcode":"68516",
    "sg:province":"NE",
    "sg:tags":[
        "electric",
        "contractor"
    ],
    "wof:name":"Hubert Electric Co",
    "wof:placetype":"venue"
},
  "geometry": {"coordinates":[-96.65247100000001,40.760593],"type":"Point"}
}