{
  "type": "Feature",
  "properties": {
    "iso:country":"US",
    "sg:address":"7559 Main St",
    "sg:city":"Ralston",
    "sg:classifiers":[
        {
            "category":"Professional",
            "type":"Services"
        }
    ],
    "sg:phone":"+1 402 537 0700",
    "sg:postcode":"68127",
    "sg:province":"NE",
    "sg:tags":[
        "establishment"
    ],
    "wof:name":"North American Directory",
    "wof:placetype":"venue"
},
  "geometry": {"coordinates":[-96.028583,41.201627],"type":"Point"}
}