{
  "type": "Feature",
  "properties": {
    "iso:country":"US",
    "sg:address":"1334 Dodge St",
    "sg:city":"Omaha",
    "sg:classifiers":[
        {
            "category":"Manufacturing",
            "subcategory":"Printing",
            "type":"Manufacturing & Wholesale Goods"
        }
    ],
    "sg:phone":"+1 402 444 1290",
    "sg:postcode":"68102",
    "sg:province":"NE",
    "sg:tags":[
        "newspaper",
        "publisher"
    ],
    "wof:name":"Street Sales Dept",
    "wof:placetype":"venue"
},
  "geometry": {"coordinates":[-95.93416499999999,41.259769],"type":"Point"}
}