{
  "type": "Feature",
  "properties": {
    "addr:full":"405 S 3rd St Nebraska City NE 68410",
    "addr:housenumber":"405",
    "addr:postcode":"68410",
    "addr:street":"S 3Rd St",
    "iso:country":"US",
    "sg:address":"405 S 3rd St",
    "sg:city":"Nebraska City",
    "sg:classifiers":[
        {
            "category":"Freight",
            "type":"Transportation"
        }
    ],
    "sg:phone":"+1 402 873 7554",
    "sg:postcode":"68410",
    "sg:province":"NE",
    "sg:tags":[
        "grain",
        "elevator"
    ],
    "wof:name":"Grain Service Co Inc",
    "wof:placetype":"venue"
},
  "geometry": {"coordinates":[-95.848364,40.674208],"type":"Point"}
}