{
  "type": "Feature",
  "properties": {
    "iso:country":"US",
    "sg:address":"1244 N 1st St",
    "sg:city":"Seward",
    "sg:classifiers":[
        {
            "category":"Real Estate",
            "subcategory":"Real Estate Agent",
            "type":"Services"
        }
    ],
    "sg:phone":"+1 402 641 0661",
    "sg:postcode":"68434",
    "sg:province":"NE",
    "wof:name":"Woods Bros Realty",
    "wof:placetype":"venue"
},
  "geometry": {"coordinates":[-97.09300500000001,40.917405],"type":"Point"}
}