{
  "type": "Feature",
  "properties": {
    "addr:full":"5018 Ames Ave Omaha NE 68104",
    "addr:housenumber":"5018",
    "addr:postcode":"68104",
    "addr:street":"Ames Ave",
    "iso:country":"US",
    "sg:address":"5018 Ames Ave",
    "sg:city":"Omaha",
    "sg:classifiers":[
        {
            "category":"Food & Beverages",
            "subcategory":"Groceries & Convenience Stores",
            "type":"Retail Goods"
        }
    ],
    "sg:phone":"+1 402 827 3223",
    "sg:postcode":"68104",
    "sg:province":"NE",
    "sg:tags":[
        "grocer"
    ],
    "wof:name":"Super Saver",
    "wof:placetype":"venue"
},
  "geometry": {"coordinates":[-95.994702,41.299661],"type":"Point"}
}