{
  "type": "Feature",
  "properties": {
    "iso:country":"US",
    "sg:address":"145 W 5th St",
    "sg:city":"Superior",
    "sg:classifiers":[
        {
            "category":"Shopping",
            "subcategory":"Florist",
            "type":"Retail Goods"
        },
        {
            "category":"Farming",
            "subcategory":"Nursery",
            "type":"Manufacturing & Wholesale Goods"
        }
    ],
    "sg:phone":"+1 402 879 4014",
    "sg:postcode":"68978",
    "sg:province":"NE",
    "sg:tags":[
        "ornamental"
    ],
    "wof:name":"Superior Floral Co",
    "wof:placetype":"venue"
},
  "geometry": {"coordinates":[-98.071637,40.020863],"type":"Point"}
}