{
  "type": "Feature",
  "properties": {
    "iso:country":"US",
    "sg:address":"1006 Ella St",
    "sg:city":"Beatrice",
    "sg:classifiers":[
        {
            "category":"Retail",
            "subcategory":"Repair Shop",
            "type":"Services"
        }
    ],
    "sg:phone":"+1 402 223 3753",
    "sg:postcode":"68310",
    "sg:province":"NE",
    "sg:tags":[
        "lock",
        "locksmith"
    ],
    "wof:name":"AAA Lock & Key",
    "wof:placetype":"venue"
},
  "geometry": {"coordinates":[-96.74032,40.266948],"type":"Point"}
}