{
  "type": "Feature",
  "properties": {
    "iso:country":"US",
    "sg:address":"230 Manatt Ct",
    "sg:city":"Lincoln",
    "sg:classifiers":[
        {
            "category":"Personal",
            "type":"Services"
        }
    ],
    "sg:phone":"+1 402 430 5955",
    "sg:postcode":"68521",
    "sg:province":"NE",
    "wof:name":"Occasions By Design",
    "wof:placetype":"venue"
},
  "geometry": {"coordinates":[-96.718484,40.848586],"type":"Point"}
}