{
  "type": "Feature",
  "properties": {
    "addr:full":"710 S Kimball St Grand Island NE 68801",
    "addr:housenumber":"710",
    "addr:postcode":"68801",
    "addr:street":"S Kimball St",
    "iso:country":"US",
    "sg:address":"710 S Kimball St",
    "sg:city":"Grand Island",
    "sg:classifiers":[
        {
            "category":"Social Services",
            "subcategory":"Child Care",
            "type":"Services"
        }
    ],
    "sg:phone":"+1 308 381 6863",
    "sg:postcode":"68801",
    "sg:province":"NE",
    "sg:tags":[
        "day"
    ],
    "wof:name":"Annies Little Rugrats",
    "wof:placetype":"venue"
},
  "geometry": {"coordinates":[-98.33599,40.916461],"type":"Point"}
}