{
  "type": "Feature",
  "properties": {
    "iso:country":"US",
    "sg:address":"106 W 3rd St",
    "sg:city":"Mc Cook",
    "sg:classifiers":[
        {
            "category":"Insurance",
            "subcategory":"Insurance Agent",
            "type":"Services"
        }
    ],
    "sg:phone":"+1 308 345 2408",
    "sg:postcode":"69001",
    "sg:province":"NE",
    "wof:name":"Security First Insurance",
    "wof:placetype":"venue"
},
  "geometry": {"coordinates":[-100.630151,40.198652],"type":"Point"}
}