{
  "type": "Feature",
  "properties": {
    "iso:country":"US",
    "sg:address":"1756 S 52nd Rd",
    "sg:city":"Talmage",
    "sg:classifiers":[
        {
            "category":"Farming",
            "subcategory":"Farm",
            "type":"Manufacturing & Wholesale Goods"
        }
    ],
    "sg:phone":"+1 402 264 4205",
    "sg:postcode":"68448",
    "sg:province":"NE",
    "sg:tags":[
        "crop",
        "general"
    ],
    "wof:name":"Teten Reinhold",
    "wof:placetype":"venue"
},
  "geometry": {"coordinates":[-95.972897,40.547184],"type":"Point"}
}