{
  "type": "Feature",
  "properties": {
    "iso:country":"US",
    "sg:address":"2801 Homeland Pl",
    "sg:city":"Lincoln",
    "sg:classifiers":[
        {
            "category":"Shopping",
            "type":"Retail Goods"
        }
    ],
    "sg:phone":"+1 402 435 7609",
    "sg:postcode":"68521",
    "sg:province":"NE",
    "sg:tags":[
        "candle"
    ],
    "wof:name":"Angels & Heavenly Scents",
    "wof:placetype":"venue"
},
  "geometry": {"coordinates":[-96.731488,40.840406],"type":"Point"}
}