{
  "type": "Feature",
  "properties": {
    "addr:full":"715 6th St Milford NE 68405",
    "addr:housenumber":"715",
    "addr:postcode":"68405",
    "addr:street":"6Th St",
    "iso:country":"US",
    "sg:address":"715 6th St",
    "sg:city":"Milford",
    "sg:classifiers":[
        {
            "category":"Organizations",
            "subcategory":"Membership Organization",
            "type":"Services"
        }
    ],
    "sg:phone":"+1 402 761 2894",
    "sg:postcode":"68405",
    "sg:province":"NE",
    "sg:website":"www.aa.org",
    "wof:name":"Alcoholics Anonymous",
    "wof:placetype":"venue"
},
  "geometry": {"coordinates":[-97.055154,40.76902],"type":"Point"}
}