{
  "type": "Feature",
  "properties": {
    "iso:country":"US",
    "sg:address":"851 H Rd",
    "sg:city":"Chapman",
    "sg:classifiers":[
        {
            "category":"Building & Trades",
            "subcategory":"Construction",
            "type":"Services"
        }
    ],
    "sg:phone":"+1 308 986 2333",
    "sg:postcode":"68827",
    "sg:province":"NE",
    "sg:tags":[
        "steel",
        "erection",
        "silo"
    ],
    "wof:name":"Rathman-Manning Corporation",
    "wof:placetype":"venue"
},
  "geometry": {"coordinates":[-98.13908499999999,41.031628],"type":"Point"}
}