{
  "type": "Feature",
  "properties": {
    "iso:country":"US",
    "sg:address":"915 W 35th St",
    "sg:city":"Kearney",
    "sg:classifiers":[
        {
            "category":"Education",
            "subcategory":"School",
            "type":"Public Place"
        }
    ],
    "sg:phone":"+1 308 698 8142",
    "sg:postcode":"68845",
    "sg:province":"NE",
    "wof:name":"Kearney Public Schools",
    "wof:placetype":"venue"
},
  "geometry": {"coordinates":[-99.095134,40.710355],"type":"Point"}
}