{
  "type": "Feature",
  "properties": {
    "iso:country":"US",
    "sg:address":"49625 115th Rd",
    "sg:city":"Gibbon",
    "sg:classifiers":[
        {
            "category":"Farming",
            "subcategory":"Farm",
            "type":"Manufacturing & Wholesale Goods"
        }
    ],
    "sg:phone":"+1 308 468 5231",
    "sg:postcode":"68840",
    "sg:province":"NE",
    "sg:tags":[
        "crop",
        "animal",
        "general"
    ],
    "wof:name":"Lance Bailey",
    "wof:placetype":"venue"
},
  "geometry": {"coordinates":[-98.824235,40.786059],"type":"Point"}
}