{
  "type": "Feature",
  "properties": {
    "iso:country":"US",
    "sg:address":"1702 US Hwy 83",
    "sg:city":"Mc Cook",
    "sg:classifiers":[
        {
            "category":"Real Estate",
            "subcategory":"Real Estate Operator",
            "type":"Services"
        }
    ],
    "sg:phone":"+1 308 345 4488",
    "sg:postcode":"69001",
    "sg:province":"NE",
    "sg:tags":[
        "property",
        "lessor"
    ],
    "wof:name":"A Bishop",
    "wof:placetype":"venue"
},
  "geometry": {"coordinates":[-100.650267,40.215824],"type":"Point"}
}