{
  "type": "Feature",
  "properties": {
    "addr:full":"336 N Elm St Red Cloud NE 68970",
    "addr:housenumber":"336",
    "addr:postcode":"68970",
    "addr:street":"N Elm St",
    "iso:country":"US",
    "sg:address":"336 N Elm St",
    "sg:city":"Red Cloud",
    "sg:classifiers":[
        {
            "category":"Building & Trades",
            "subcategory":"Electrical",
            "type":"Services"
        }
    ],
    "sg:phone":"+1 402 746 2747",
    "sg:postcode":"68970",
    "sg:province":"NE",
    "sg:tags":[
        "electric",
        "contractor"
    ],
    "wof:name":"Chief Electric",
    "wof:placetype":"venue"
},
  "geometry": {"coordinates":[-98.518022,40.088429],"type":"Point"}
}