{
  "type": "Feature",
  "properties": {
    "addr:full":"145 L Rd Saint Libory NE 68872",
    "addr:housenumber":"145",
    "addr:postcode":"68872",
    "addr:street":"L Rd",
    "iso:country":"US",
    "sg:address":"145 L Rd",
    "sg:city":"Saint Libory",
    "sg:classifiers":[
        {
            "category":"Building & Trades",
            "subcategory":"Landscaping Services",
            "type":"Services"
        }
    ],
    "sg:phone":"+1 308 383 2052",
    "sg:postcode":"68872",
    "sg:province":"NE",
    "sg:tags":[
        "landscape"
    ],
    "wof:name":"Sunset Greenery",
    "wof:placetype":"venue"
},
  "geometry": {"coordinates":[-98.28119700000001,41.089798],"type":"Point"}
}