{
  "type": "Feature",
  "properties": {
    "addr:full":"29 Camelot Way Kearney NE 68845",
    "addr:housenumber":"29",
    "addr:postcode":"68845",
    "addr:street":"Camelot Way",
    "iso:country":"US",
    "sg:address":"29 Camelot Way",
    "sg:city":"Kearney",
    "sg:classifiers":[
        {
            "category":"Professional",
            "subcategory":"Management & Consulting",
            "type":"Services"
        }
    ],
    "sg:phone":"+1 308 236 8475",
    "sg:postcode":"68845",
    "sg:province":"NE",
    "wof:name":"Lind Financial Services",
    "wof:placetype":"venue"
},
  "geometry": {"coordinates":[-99.11241099999999,40.708197],"type":"Point"}
}