{
  "type": "Feature",
  "properties": {
    "addr:full":"849 F St Pawnee City NE 68420",
    "addr:housenumber":"849",
    "addr:postcode":"68420",
    "addr:street":"F St",
    "iso:country":"US",
    "sg:address":"849 F St",
    "sg:city":"Pawnee City",
    "sg:classifiers":[
        {
            "category":"Organizations",
            "subcategory":"Religious Organization",
            "type":"Services"
        }
    ],
    "sg:phone":"+1 402 852 2088",
    "sg:postcode":"68420",
    "sg:province":"NE",
    "sg:tags":[
        "church"
    ],
    "wof:name":"United Methodist Church",
    "wof:placetype":"venue"
},
  "geometry": {"coordinates":[-96.154274,40.110521],"type":"Point"}
}