{
  "type": "Feature",
  "properties": {
    "iso:country":"US",
    "sg:address":"101 Franklin Ave",
    "sg:city":"Beatrice",
    "sg:classifiers":[
        {
            "category":"Retail",
            "subcategory":"Repair Shop",
            "type":"Services"
        }
    ],
    "sg:phone":"+1 402 228 9524",
    "sg:postcode":"68310",
    "sg:province":"NE",
    "wof:name":"Personal Touch Cleaning Svcs",
    "wof:placetype":"venue"
},
  "geometry": {"coordinates":[-96.751904,40.246208],"type":"Point"}
}