{
  "type": "Feature",
  "properties": {
    "iso:country":"US",
    "sg:address":"1019 Ivy St",
    "sg:city":"Stanton",
    "sg:classifiers":[
        {
            "category":"Banks & Credit Unions",
            "subcategory":"Bank",
            "type":"Services"
        }
    ],
    "sg:phone":"+1 402 439 2168",
    "sg:postcode":"68779",
    "sg:province":"NE",
    "wof:name":"First Nebraska Bank",
    "wof:placetype":"venue"
},
  "geometry": {"coordinates":[-97.22494,41.950311],"type":"Point"}
}