{
  "type": "Feature",
  "properties": {
    "iso:country":"US",
    "sg:address":"238 Pine St",
    "sg:city":"Clarkson",
    "sg:classifiers":[
        {
            "category":"Insurance",
            "subcategory":"Insurance Agent",
            "type":"Services"
        }
    ],
    "sg:phone":"+1 402 892 3481",
    "sg:postcode":"68629",
    "sg:province":"NE",
    "wof:name":"Dan Bowlin Insurance",
    "wof:placetype":"venue"
},
  "geometry": {"coordinates":[-97.122158,41.726347],"type":"Point"}
}