{
  "type": "Feature",
  "properties": {
    "iso:country":"US",
    "sg:address":"1025 N 63rd St",
    "sg:city":"Lincoln",
    "sg:classifiers":[
        {
            "category":"Real Estate",
            "subcategory":"Real Estate Operator",
            "type":"Services"
        },
        {
            "category":"Professional",
            "subcategory":"Accounting & Tax Preparation",
            "type":"Services"
        }
    ],
    "sg:phone":"+1 402 464 8351",
    "sg:postcode":"68505",
    "sg:province":"NE",
    "sg:tags":[
        "apartment",
        "developer"
    ],
    "sg:website":"www.chateaudev.com",
    "wof:name":"Chateau Development LLC",
    "wof:placetype":"venue"
},
  "geometry": {"coordinates":[-96.634655,40.8226],"type":"Point"}
}