{
  "type": "Feature",
  "properties": {
    "iso:country":"US",
    "sg:address":"13887 US Hwy 75",
    "sg:city":"Blair",
    "sg:classifiers":[
        {
            "category":"Farming",
            "subcategory":"Livestock Farm",
            "type":"Manufacturing & Wholesale Goods"
        }
    ],
    "sg:phone":"+1 402 426 4673",
    "sg:postcode":"68008",
    "sg:province":"NE",
    "sg:tags":[
        "equine"
    ],
    "wof:name":"Jensen Arabians Inc",
    "wof:placetype":"venue"
},
  "geometry": {"coordinates":[-96.167793,41.58388],"type":"Point"}
}