{
  "type": "Feature",
  "properties": {
    "iso:country":"US",
    "sg:address":"1818 Ave A",
    "sg:city":"Scottsbluff",
    "sg:classifiers":[
        {
            "category":"Recreation",
            "type":"Entertainment"
        }
    ],
    "sg:phone":"+1 308 630 6238",
    "sg:postcode":"69361",
    "sg:province":"NE",
    "sg:tags":[
        "parks"
    ],
    "wof:name":"Scottsbluff Recreation Dept",
    "wof:placetype":"venue"
},
  "geometry": {"coordinates":[-103.66424499999999,41.865051],"type":"Point"}
}