{
  "type": "Feature",
  "properties": {
    "addr:full":"5611 2nd Ave W Kearney NE 68847",
    "addr:housenumber":"5611",
    "addr:postcode":"68847",
    "addr:street":"2Nd Ave W",
    "iso:country":"US",
    "sg:address":"5611 2nd Ave W",
    "sg:city":"Kearney",
    "sg:classifiers":[
        {
            "category":"Restaurant",
            "type":"Food & Drink"
        }
    ],
    "sg:menulink":"http://www.allmenus.com/ne/kearney/81141-papa-johns-pizza/menu/",
    "sg:phone":"+1 308 236 5455",
    "sg:postcode":"68847",
    "sg:province":"NE",
    "sg:tags":[
        "american",
        "pizza"
    ],
    "wof:name":"Papa John's Pizza",
    "wof:placetype":"venue"
},
  "geometry": {"coordinates":[-99.083721,40.729674],"type":"Point"}
}