{
  "type": "Feature",
  "properties": {
    "iso:country":"US",
    "sg:address":"6120 Van Dorn St",
    "sg:city":"Nehawka",
    "sg:phone":"+1 402 227 2034",
    "sg:postcode":"68413",
    "sg:province":"NE",
    "sg:tags":[
        "farm",
        "corn"
    ],
    "wof:name":"Rick Meyer",
    "wof:placetype":"venue"
},
  "geometry": {"coordinates":[-96.008934,40.784117],"type":"Point"}
}