{
  "type": "Feature",
  "properties": {
    "addr:full":"1018 Co Rd 18 Rogers NE 68659",
    "addr:housenumber":"1018;18",
    "addr:postcode":"68659",
    "addr:street":"Co Rd",
    "iso:country":"US",
    "sg:address":"1018 Co Rd 18",
    "sg:city":"Rogers",
    "sg:phone":"+1 402 352 8733",
    "sg:postcode":"68659",
    "sg:province":"NE",
    "sg:tags":[
        "hog",
        "beef",
        "farm",
        "cash",
        "grain",
        "cattle",
        "or",
        "feedlot"
    ],
    "wof:name":"Gary Krula",
    "wof:placetype":"venue"
},
  "geometry": {"coordinates":[-96.925394,41.527084],"type":"Point"}
}