{
  "type": "Feature",
  "properties": {
    "iso:country":"US",
    "sg:address":"14810 M St",
    "sg:city":"Omaha",
    "sg:classifiers":[
        {
            "category":"Shopping",
            "subcategory":"Used Merchandise",
            "type":"Retail Goods"
        }
    ],
    "sg:phone":"+1 402 895 3293",
    "sg:postcode":"68137",
    "sg:province":"NE",
    "wof:name":"Duerfeldts Attic Treasure",
    "wof:placetype":"venue"
},
  "geometry": {"coordinates":[-96.145082,41.211595],"type":"Point"}
}