{
  "type": "Feature",
  "properties": {
    "addr:full":"709 N Brown Ave Minden NE 68959",
    "addr:housenumber":"709",
    "addr:postcode":"68959",
    "addr:street":"N Brown Ave",
    "iso:country":"US",
    "sg:address":"709 N Brown Ave",
    "sg:city":"Minden",
    "sg:classifiers":[
        {
            "category":"Restaurant",
            "type":"Food & Drink"
        }
    ],
    "sg:phone":"+1 308 832 1014",
    "sg:postcode":"68959",
    "sg:province":"NE",
    "wof:name":"Amigos",
    "wof:placetype":"venue"
},
  "geometry": {"coordinates":[-98.951899,40.50209],"type":"Point"}
}