{
  "type": "Feature",
  "properties": {
    "addr:full":"1486 12th Rd Beemer NE 68716",
    "addr:housenumber":"1486",
    "addr:postcode":"68716",
    "addr:street":"12Th Rd",
    "iso:country":"US",
    "sg:address":"1486 12th Rd",
    "sg:city":"Beemer",
    "sg:classifiers":[
        {
            "category":"Manufacturing",
            "subcategory":"Tools & Machinery",
            "type":"Manufacturing & Wholesale Goods"
        }
    ],
    "sg:phone":"+1 402 528 3861",
    "sg:postcode":"68716",
    "sg:province":"NE",
    "sg:tags":[
        "farm",
        "equipment"
    ],
    "sg:website":"www.mightygiant.com",
    "wof:name":"Jones Manufacturing Inc",
    "wof:placetype":"venue"
},
  "geometry": {"coordinates":[-96.806952,41.943743],"type":"Point"}
}