{
  "type": "Feature",
  "properties": {
    "iso:country":"US",
    "sg:address":"310 N Main St",
    "sg:city":"Bridgeport",
    "sg:classifiers":[
        {
            "category":"Shopping",
            "subcategory":"Pharmacy",
            "type":"Retail Goods"
        }
    ],
    "sg:phone":"+1 308 262 0580",
    "sg:postcode":"69343",
    "sg:province":"NE",
    "wof:name":"Sonny's Pharmacy",
    "wof:placetype":"venue"
},
  "geometry": {"coordinates":[-102.20334200000001,42.807659],"type":"Point"}
}