{
  "type": "Feature",
  "properties": {
    "addr:full":"355 Clay St Tecumseh NE 68450",
    "addr:housenumber":"355",
    "addr:postcode":"68450",
    "addr:street":"Clay St",
    "iso:country":"US",
    "sg:address":"355 Clay St",
    "sg:city":"Tecumseh",
    "sg:classifiers":[
        {
            "category":"Government",
            "subcategory":"Office",
            "type":"Public Place"
        }
    ],
    "sg:phone":"+1 402 335 9901",
    "sg:postcode":"68450",
    "sg:province":"NE",
    "sg:tags":[
        "village"
    ],
    "wof:name":"Tecumseh Community Building",
    "wof:placetype":"venue"
},
  "geometry": {"coordinates":[-96.194975,40.366661],"type":"Point"}
}