{
  "type": "Feature",
  "properties": {
    "iso:country":"US",
    "sg:address":"104 S Fir Ave",
    "sg:city":"Davenport",
    "sg:classifiers":[
        {
            "category":"Professional",
            "subcategory":"Accounting & Tax Preparation",
            "type":"Services"
        }
    ],
    "sg:phone":"+1 402 364 2418",
    "sg:postcode":"68335",
    "sg:province":"NE",
    "sg:tags":[
        "return",
        "filing"
    ],
    "wof:name":"Grone Tax Svc",
    "wof:placetype":"venue"
},
  "geometry": {"coordinates":[-97.80926700000001,40.312713],"type":"Point"}
}