{
  "type": "Feature",
  "properties": {
    "iso:country":"US",
    "sg:address":"16522 Spring Cir",
    "sg:city":"Omaha",
    "sg:classifiers":[
        {
            "category":"Professional",
            "subcategory":"Business Services",
            "type":"Services"
        }
    ],
    "sg:phone":"+1 402 330 2871",
    "sg:postcode":"68130",
    "sg:province":"NE",
    "sg:tags":[
        "banking",
        "consulting"
    ],
    "wof:name":"Eugene Koenig",
    "wof:placetype":"venue"
},
  "geometry": {"coordinates":[-96.171458,41.22845],"type":"Point"}
}