{
  "type": "Feature",
  "properties": {
    "iso:country":"US",
    "sg:address":"213 Sunny Dr",
    "sg:city":"Doniphan",
    "sg:classifiers":[
        {
            "category":"Professional",
            "subcategory":"Business Services",
            "type":"Services"
        }
    ],
    "sg:phone":"+1 402 845 6645",
    "sg:postcode":"68832",
    "sg:province":"NE",
    "wof:name":"Amerispec Home Inspection Svc",
    "wof:placetype":"venue"
},
  "geometry": {"coordinates":[-98.395814,40.770471],"type":"Point"}
}