{
  "type": "Feature",
  "properties": {
    "iso:country":"US",
    "sg:address":"216 Co Rd 16",
    "sg:city":"Plymouth",
    "sg:classifiers":[
        {
            "category":"Autos & Motor Vehicles",
            "subcategory":"Fuel & Gas Station",
            "type":"Retail Goods"
        }
    ],
    "sg:phone":"+1 402 656 3905",
    "sg:postcode":"68454",
    "sg:province":"NE",
    "sg:tags":[
        "grocery",
        "station",
        "gasoline"
    ],
    "wof:name":"Country Store",
    "wof:placetype":"venue"
},
  "geometry": {"coordinates":[-96.312687,40.677949],"type":"Point"}
}