{
  "type": "Feature",
  "properties": {
    "iso:country":"US",
    "sg:address":"355 Autogate Rd",
    "sg:city":"Chadron",
    "sg:classifiers":[
        {
            "category":"Real Estate",
            "subcategory":"Real Estate Operator",
            "type":"Services"
        }
    ],
    "sg:phone":"+1 308 432 5857",
    "sg:postcode":"69337",
    "sg:province":"NE",
    "sg:tags":[
        "property",
        "lessor"
    ],
    "wof:name":"Faye Stewart",
    "wof:placetype":"venue"
},
  "geometry": {"coordinates":[-103.01049399999999,42.557148],"type":"Point"}
}