{
  "type": "Feature",
  "properties": {
    "iso:country":"US",
    "sg:address":"3745 Himebaugh Ave",
    "sg:city":"Omaha",
    "sg:classifiers":[
        {
            "category":"Social Services",
            "subcategory":"Child Care",
            "type":"Services"
        }
    ],
    "sg:phone":"+1 402 932 1117",
    "sg:postcode":"68111",
    "sg:province":"NE",
    "sg:tags":[
        "day"
    ],
    "wof:name":"Byrds Nest Leaning Center",
    "wof:placetype":"venue"
},
  "geometry": {"coordinates":[-95.970502,41.311171],"type":"Point"}
}