{
  "type": "Feature",
  "properties": {
    "addr:full":"806 E 27th St Scottsbluff NE 69361",
    "addr:housenumber":"806",
    "addr:postcode":"69361",
    "addr:street":"E 27Th St",
    "iso:country":"US",
    "sg:address":"806 E 27th St",
    "sg:city":"Scottsbluff",
    "sg:classifiers":[
        {
            "category":"Restaurant",
            "type":"Food & Drink"
        }
    ],
    "sg:menulink":"http://www.allmenus.com/ne/scottsbluff/81153-papa-johns-pizza/menu/",
    "sg:phone":"+1 308 632 7474",
    "sg:postcode":"69361",
    "sg:province":"NE",
    "sg:tags":[
        "american",
        "pizza"
    ],
    "wof:name":"Papa John's Pizza",
    "wof:placetype":"venue"
},
  "geometry": {"coordinates":[-103.65164799999999,41.873979],"type":"Point"}
}