{
  "type": "Feature",
  "properties": {
    "iso:country":"US",
    "sg:address":"329 Pine St",
    "sg:city":"Clarkson",
    "sg:classifiers":[
        {
            "category":"Health Services",
            "subcategory":"Doctor",
            "type":"Services"
        }
    ],
    "sg:phone":"+1 402 892 3466",
    "sg:postcode":"68629",
    "sg:province":"NE",
    "sg:tags":[
        "physician",
        "surgeon"
    ],
    "wof:name":"Alegent Health Clarkson Clinic",
    "wof:placetype":"venue"
},
  "geometry": {"coordinates":[-97.122168,41.724884],"type":"Point"}
}