{
  "type": "Feature",
  "properties": {
    "iso:country":"US",
    "sg:address":"207 S O Rd",
    "sg:city":"Harvard",
    "sg:classifiers":[
        {
            "category":"Building & Trades",
            "subcategory":"Construction",
            "type":"Services"
        }
    ],
    "sg:phone":"+1 402 737 3327",
    "sg:postcode":"68944",
    "sg:province":"NE",
    "sg:tags":[
        "house"
    ],
    "wof:name":"Tree House Remodeling & Repair",
    "wof:placetype":"venue"
},
  "geometry": {"coordinates":[-98.03528,40.712869],"type":"Point"}
}