{
  "type": "Feature",
  "properties": {
    "iso:country":"US",
    "sg:address":"12155 Pedersen Dr",
    "sg:city":"Omaha",
    "sg:classifiers":[
        {
            "category":"Building & Trades",
            "subcategory":"Construction",
            "type":"Services"
        }
    ],
    "sg:phone":"+1 402 691 0698",
    "sg:postcode":"68144",
    "sg:province":"NE",
    "sg:tags":[
        "concrete",
        "contractor"
    ],
    "wof:name":"Bear Construction",
    "wof:placetype":"venue"
},
  "geometry": {"coordinates":[-96.10442,41.224395],"type":"Point"}
}