{
  "type": "Feature",
  "properties": {
    "iso:country":"US",
    "sg:address":"8828 E Cherry Rd",
    "sg:city":"Adams",
    "sg:phone":"+1 402 988 3745",
    "sg:postcode":"68301",
    "sg:province":"NE",
    "sg:tags":[
        "farm",
        "corn"
    ],
    "wof:name":"Terry Wallman",
    "wof:placetype":"venue"
},
  "geometry": {"coordinates":[-96.59258199999999,40.407192],"type":"Point"}
}