{
  "type": "Feature",
  "properties": {
    "iso:country":"US",
    "sg:address":"1303 Andrews Dr",
    "sg:city":"Norfolk",
    "sg:classifiers":[
        {
            "category":"Health Services",
            "subcategory":"Doctor",
            "type":"Services"
        }
    ],
    "sg:phone":"+1 402 379 3379",
    "sg:postcode":"68701",
    "sg:province":"NE",
    "sg:tags":[
        "dentist"
    ],
    "wof:name":"Skyview Medical Ctr",
    "wof:placetype":"venue"
},
  "geometry": {"coordinates":[-97.410239,42.047517],"type":"Point"}
}