{
  "type": "Feature",
  "properties": {
    "iso:country":"US",
    "sg:address":"6527 Wirt St",
    "sg:city":"Omaha",
    "sg:classifiers":[
        {
            "category":"Building & Trades",
            "subcategory":"Locksmith",
            "type":"Services"
        }
    ],
    "sg:phone":"+1 402 881 3571",
    "sg:postcode":"68104",
    "sg:province":"NE",
    "sg:tags":[
        "key"
    ],
    "wof:name":"1 Always A Emerg Locksmith",
    "wof:placetype":"venue"
},
  "geometry": {"coordinates":[-96.012597,41.286696],"type":"Point"}
}