{
  "type": "Feature",
  "properties": {
    "iso:country":"US",
    "sg:address":"1925 S 25th St",
    "sg:city":"Lincoln",
    "sg:classifiers":[
        {
            "category":"Building & Trades",
            "subcategory":"Construction",
            "type":"Services"
        }
    ],
    "sg:phone":"+1 402 474 5400",
    "sg:postcode":"68502",
    "sg:province":"NE",
    "sg:tags":[
        "house"
    ],
    "wof:name":"D M Services",
    "wof:placetype":"venue"
},
  "geometry": {"coordinates":[-96.685998,40.791943],"type":"Point"}
}