{
  "type": "Feature",
  "properties": {
    "iso:country":"US",
    "sg:address":"1700 W 4th St",
    "sg:city":"Mc Cook",
    "sg:classifiers":[
        {
            "category":"Farming",
            "subcategory":"Nursery",
            "type":"Manufacturing & Wholesale Goods"
        }
    ],
    "sg:phone":"+1 308 345 1900",
    "sg:postcode":"69001",
    "sg:province":"NE",
    "sg:tags":[
        "greenhouse"
    ],
    "wof:name":"Fairacres Greenery",
    "wof:placetype":"venue"
},
  "geometry": {"coordinates":[-100.63181299999999,40.215053],"type":"Point"}
}