{
  "type": "Feature",
  "properties": {
    "iso:country":"US",
    "sg:address":"116 Pine Logging Rd",
    "sg:city":"Wahoo",
    "sg:classifiers":[
        {
            "category":"Building & Trades",
            "subcategory":"Construction",
            "type":"Services"
        }
    ],
    "sg:phone":"+1 402 443 5942",
    "sg:postcode":"68066",
    "sg:province":"NE",
    "sg:tags":[
        "house"
    ],
    "wof:name":"Mark McGill Construction",
    "wof:placetype":"venue"
},
  "geometry": {"coordinates":[-96.61510199999999,41.190392],"type":"Point"}
}