{
  "type": "Feature",
  "properties": {
    "iso:country":"US",
    "sg:address":"4300 23rd St",
    "sg:city":"Columbus",
    "sg:classifiers":[
        {
            "category":"Shopping",
            "subcategory":"Pharmacy",
            "type":"Retail Goods"
        }
    ],
    "sg:phone":"+1 402 564 2883",
    "sg:postcode":"68601",
    "sg:province":"NE",
    "sg:tags":[
        "drug",
        "store"
    ],
    "wof:name":"Bobs Sunmart Pharmacy",
    "wof:placetype":"venue"
},
  "geometry": {"coordinates":[-97.38108800000001,41.438725],"type":"Point"}
}