{
  "type": "Feature",
  "properties": {
    "iso:country":"US",
    "sg:address":"3211 Ave Q",
    "sg:city":"Kearney",
    "sg:classifiers":[
        {
            "category":"Organizations",
            "subcategory":"Religious Organization",
            "type":"Services"
        }
    ],
    "sg:phone":"+1 308 234 9047",
    "sg:postcode":"68847",
    "sg:province":"NE",
    "sg:tags":[
        "church"
    ],
    "sg:website":"www.nazarenelink.net/kearneyfirstnazaren",
    "wof:name":"First Church Of The Nazarene",
    "wof:placetype":"venue"
},
  "geometry": {"coordinates":[-99.061578,40.707488],"type":"Point"}
}