{
  "type": "Feature",
  "properties": {
    "iso:country":"US",
    "sg:address":"1605 10th St",
    "sg:city":"Aurora",
    "sg:classifiers":[
        {
            "category":"Restaurant",
            "type":"Food & Drink"
        }
    ],
    "sg:menulink":"http://www.allmenus.com/ne/aurora/155518-runza/menu/",
    "sg:phone":"+1 402 694 4262",
    "sg:postcode":"68818",
    "sg:province":"NE",
    "sg:tags":[
        "wrap",
        "american",
        "sandwich"
    ],
    "wof:name":"Runza",
    "wof:placetype":"venue"
},
  "geometry": {"coordinates":[-98.00593499999999,40.872457],"type":"Point"}
}