{
  "type": "Feature",
  "properties": {
    "iso:country":"US",
    "sg:address":"2159 37th Ave",
    "sg:city":"Columbus",
    "sg:classifiers":[
        {
            "category":"Building & Trades",
            "subcategory":"Construction",
            "type":"Services"
        }
    ],
    "sg:phone":"+1 402 562 7202",
    "sg:postcode":"68601",
    "sg:province":"NE",
    "sg:tags":[
        "contractor"
    ],
    "wof:name":"JD Services",
    "wof:placetype":"venue"
},
  "geometry": {"coordinates":[-97.37349399999999,41.43715],"type":"Point"}
}