{
  "type": "Feature",
  "properties": {
    "iso:country":"US",
    "sg:address":"1312 S 298th St",
    "sg:city":"Elmwood",
    "sg:classifiers":[
        {
            "category":"Farming",
            "subcategory":"Livestock Farm",
            "type":"Manufacturing & Wholesale Goods"
        }
    ],
    "sg:phone":"+1 402 994 5065",
    "sg:postcode":"68349",
    "sg:province":"NE",
    "sg:tags":[
        "hog",
        "or",
        "feedlot"
    ],
    "wof:name":"Stove Creek Farms Inc",
    "wof:placetype":"venue"
},
  "geometry": {"coordinates":[-96.293479,40.797932],"type":"Point"}
}