{
  "type": "Feature",
  "properties": {
    "iso:country":"US",
    "sg:address":"2640 S 39th St",
    "sg:city":"Lincoln",
    "sg:classifiers":[
        {
            "category":"Shopping",
            "subcategory":"Bicycles & Sporting Goods",
            "type":"Retail Goods"
        }
    ],
    "sg:phone":"+1 402 488 7109",
    "sg:postcode":"68506",
    "sg:province":"NE",
    "wof:name":"La Ferns Crystals",
    "wof:placetype":"venue"
},
  "geometry": {"coordinates":[-96.664395,40.787503],"type":"Point"}
}