{
  "type": "Feature",
  "properties": {
    "iso:country":"US",
    "sg:address":"2412 Pioneer Blvd",
    "sg:city":"Grand Island",
    "sg:classifiers":[
        {
            "category":"Communications",
            "type":"Services"
        }
    ],
    "sg:phone":"+1 308 370 6051",
    "sg:postcode":"68801",
    "sg:province":"NE",
    "sg:tags":[
        "communication"
    ],
    "wof:name":"Midwest Media Inc",
    "wof:placetype":"venue"
},
  "geometry": {"coordinates":[-98.355729,40.897396],"type":"Point"}
}