{
  "type": "Feature",
  "properties": {
    "iso:country":"US",
    "sg:address":"850 Park Ave",
    "sg:city":"Polk",
    "sg:classifiers":[
        {
            "category":"Retail",
            "subcategory":"Funeral Services",
            "type":"Services"
        }
    ],
    "sg:phone":"+1 402 765 2181",
    "sg:postcode":"68654",
    "sg:province":"NE",
    "sg:tags":[
        "director"
    ],
    "wof:name":"Solt Funeral Home",
    "wof:placetype":"venue"
},
  "geometry": {"coordinates":[-97.789591,41.075595],"type":"Point"}
}