{
  "type": "Feature",
  "properties": {
    "iso:country":"US",
    "sg:address":"8725 S 138th St",
    "sg:city":"Omaha",
    "sg:classifiers":[
        {
            "category":"Building & Trades",
            "subcategory":"Construction",
            "type":"Services"
        }
    ],
    "sg:phone":"+1 402 895 7603",
    "sg:postcode":"68138",
    "sg:province":"NE",
    "sg:tags":[
        "hardwood",
        "mill",
        "floor",
        "laying",
        "contractor"
    ],
    "wof:name":"Aspers Floors & More",
    "wof:placetype":"venue"
},
  "geometry": {"coordinates":[-96.12966400000001,41.173717],"type":"Point"}
}