{
  "type": "Feature",
  "properties": {
    "iso:country":"US",
    "sg:address":"15364 Burt St",
    "sg:city":"Omaha",
    "sg:classifiers":[
        {
            "category":"Professional",
            "subcategory":"Engineering",
            "type":"Services"
        }
    ],
    "sg:phone":"+1 402 493 9124",
    "sg:postcode":"68154",
    "sg:province":"NE",
    "sg:tags":[
        "engineer"
    ],
    "wof:name":"Failla Engineering",
    "wof:placetype":"venue"
},
  "geometry": {"coordinates":[-96.153243,41.268741],"type":"Point"}
}