{
  "type": "Feature",
  "properties": {
    "iso:country":"US",
    "sg:address":"2020 Elm St",
    "sg:city":"Yankton",
    "sg:classifiers":[
        {
            "category":"Shopping",
            "subcategory":"Discount & Variety Stores",
            "type":"Retail Goods"
        }
    ],
    "sg:phone":"+1 605 665 0123",
    "sg:postcode":"57078",
    "sg:province":"NE",
    "wof:name":"Dollar Discount",
    "wof:placetype":"venue"
},
  "geometry": {"coordinates":[-97.39599200000001,42.890277],"type":"Point"}
}