{
  "type": "Feature",
  "properties": {
    "iso:country":"US",
    "sg:address":"112 N 7th St",
    "sg:city":"Norfolk",
    "sg:classifiers":[
        {
            "category":"Organizations",
            "subcategory":"Religious Organization",
            "type":"Services"
        }
    ],
    "sg:phone":"+1 402 379 4663",
    "sg:postcode":"68701",
    "sg:province":"NE",
    "sg:tags":[
        "membership"
    ],
    "wof:name":"Salvation Army Thrift Store",
    "wof:placetype":"venue"
},
  "geometry": {"coordinates":[-97.416792,42.033023],"type":"Point"}
}