{
  "type": "Feature",
  "properties": {
    "addr:full":"136 N 5th St Plattsmouth NE 68048",
    "addr:housenumber":"136",
    "addr:postcode":"68048",
    "addr:street":"N 5Th St",
    "iso:country":"US",
    "sg:address":"136 N 5th St",
    "sg:city":"Plattsmouth",
    "sg:classifiers":[
        {
            "category":"Government",
            "subcategory":"Office",
            "type":"Public Place"
        }
    ],
    "sg:phone":"+1 402 296 2155",
    "sg:postcode":"68048",
    "sg:province":"NE",
    "sg:tags":[
        "executive"
    ],
    "wof:name":"City Hall",
    "wof:placetype":"venue"
},
  "geometry": {"coordinates":[-95.88509999999999,41.011333],"type":"Point"}
}