{
  "type": "Feature",
  "properties": {
    "iso:country":"US",
    "sg:address":"21 E 24th St",
    "sg:city":"Kearney",
    "sg:classifiers":[
        {
            "category":"Building & Trades",
            "subcategory":"Plumbing",
            "type":"Services"
        }
    ],
    "sg:phone":"+1 308 234 2533",
    "sg:postcode":"68847",
    "sg:province":"NE",
    "sg:tags":[
        "heating",
        "contractor"
    ],
    "wof:name":"Thurston Heating & Air Cond",
    "wof:placetype":"venue"
},
  "geometry": {"coordinates":[-99.081474,40.699239],"type":"Point"}
}