{
  "type": "Feature",
  "properties": {
    "addr:full":"300 Pierce St Papillion NE 68046",
    "addr:housenumber":"300",
    "addr:postcode":"68046",
    "addr:street":"Pierce St",
    "iso:country":"US",
    "sg:address":"300 Pierce St",
    "sg:city":"Papillion",
    "sg:classifiers":[
        {
            "category":"Retail",
            "subcategory":"Laundry & Dry Cleaning",
            "type":"Services"
        }
    ],
    "sg:phone":"+1 402 592 7017",
    "sg:postcode":"68046",
    "sg:province":"NE",
    "sg:tags":[
        "cleaners",
        "rug",
        "carpet"
    ],
    "wof:name":"Chris' Carpet Care",
    "wof:placetype":"venue"
},
  "geometry": {"coordinates":[-96.05176400000001,41.153096],"type":"Point"}
}