{
  "type": "Feature",
  "properties": {
    "iso:country":"US",
    "sg:address":"6773 Co Rd 7",
    "sg:city":"Arlington",
    "sg:classifiers":[
        {
            "category":"Building & Trades",
            "subcategory":"Landscaping Services",
            "type":"Services"
        }
    ],
    "sg:phone":"+1 402 478 4453",
    "sg:postcode":"68002",
    "sg:province":"NE",
    "wof:name":"John M Odell & Co",
    "wof:placetype":"venue"
},
  "geometry": {"coordinates":[-96.386636,41.477369],"type":"Point"}
}