{
  "type": "Feature",
  "properties": {
    "iso:country":"US",
    "sg:address":"45049 Brennemann Rd",
    "sg:city":"Hyannis",
    "sg:classifiers":[
        {
            "category":"Farming",
            "subcategory":"Livestock Farm",
            "type":"Manufacturing & Wholesale Goods"
        }
    ],
    "sg:phone":"+1 308 458 2411",
    "sg:postcode":"69350",
    "sg:province":"NE",
    "sg:tags":[
        "beef",
        "feedlot",
        "cattle"
    ],
    "wof:name":"Brennemann Farms LLC",
    "wof:placetype":"venue"
},
  "geometry": {"coordinates":[-101.848341,42.0826],"type":"Point"}
}