{
  "type": "Feature",
  "properties": {
    "iso:country":"US",
    "sg:address":"7220 Oxford Rd",
    "sg:city":"Lincoln",
    "sg:classifiers":[
        {
            "category":"Wholesale",
            "subcategory":"Non-durable Goods",
            "type":"Manufacturing & Wholesale Goods"
        }
    ],
    "sg:phone":"+1 402 483 0464",
    "sg:postcode":"68506",
    "sg:province":"NE",
    "sg:tags":[
        "advertising"
    ],
    "wof:name":"Action Advertising Inc",
    "wof:placetype":"venue"
},
  "geometry": {"coordinates":[-96.621347,40.793243],"type":"Point"}
}