{
  "type": "Feature",
  "properties": {
    "iso:country":"US",
    "sg:address":"16050 S 120th St",
    "sg:city":"Springfield",
    "sg:classifiers":[
        {
            "category":"Building & Trades",
            "subcategory":"Construction",
            "type":"Services"
        }
    ],
    "sg:phone":"+1 402 253 2965",
    "sg:postcode":"68059",
    "sg:province":"NE",
    "sg:tags":[
        "residential",
        "house"
    ],
    "wof:name":"Precision Enterprise",
    "wof:placetype":"venue"
},
  "geometry": {"coordinates":[-96.100362,41.075506],"type":"Point"}
}