{
  "type": "Feature",
  "properties": {
    "iso:country":"US",
    "sg:address":"3219 S 23rd St",
    "sg:city":"Omaha",
    "sg:classifiers":[
        {
            "category":"Professional",
            "subcategory":"Business Services",
            "type":"Services"
        }
    ],
    "sg:phone":"+1 402 681 5978",
    "sg:postcode":"68108",
    "sg:province":"NE",
    "sg:tags":[
        "home"
    ],
    "wof:name":"Nelson Tremblay",
    "wof:placetype":"venue"
},
  "geometry": {"coordinates":[-95.945504,41.228394],"type":"Point"}
}