{
  "type": "Feature",
  "properties": {
    "iso:country":"US",
    "sg:address":"40675 190th Rd",
    "sg:city":"Gibbon",
    "sg:classifiers":[
        {
            "category":"Farming",
            "subcategory":"Farm",
            "type":"Manufacturing & Wholesale Goods"
        }
    ],
    "sg:phone":"+1 308 452 4483",
    "sg:postcode":"68840",
    "sg:province":"NE",
    "sg:tags":[
        "crop",
        "general"
    ],
    "wof:name":"Patrick Paitz",
    "wof:placetype":"venue"
},
  "geometry": {"coordinates":[-98.93616299999999,40.858512],"type":"Point"}
}