{
  "type": "Feature",
  "properties": {
    "iso:country":"US",
    "sg:address":"4305 S 23rd St",
    "sg:city":"Omaha",
    "sg:classifiers":[
        {
            "category":"Retail",
            "subcategory":"Auto Repair",
            "type":"Services"
        }
    ],
    "sg:phone":"+1 402 210 9038",
    "sg:postcode":"68107",
    "sg:province":"NE",
    "sg:tags":[
        "wrecker"
    ],
    "wof:name":"Alberts Towing",
    "wof:placetype":"venue"
},
  "geometry": {"coordinates":[-95.945482,41.21614],"type":"Point"}
}