{
  "type": "Feature",
  "properties": {
    "iso:country":"US",
    "sg:address":"117 W 3rd St",
    "sg:city":"Wayne",
    "sg:classifiers":[
        {
            "category":"Health Services",
            "subcategory":"Clinic",
            "type":"Services"
        }
    ],
    "sg:phone":"+1 402 375 2200",
    "sg:postcode":"68787",
    "sg:province":"NE",
    "sg:tags":[
        "department",
        "quad",
        "public"
    ],
    "wof:name":"Northeast Neb Pub Hlth Dept",
    "wof:placetype":"venue"
},
  "geometry": {"coordinates":[-97.01797000000001,42.231279],"type":"Point"}
}