{
  "type": "Feature",
  "properties": {
    "iso:country":"US",
    "sg:address":"3425 S 42nd St",
    "sg:city":"Lincoln",
    "sg:classifiers":[
        {
            "category":"Building & Trades",
            "subcategory":"Construction",
            "type":"Services"
        }
    ],
    "sg:phone":"+1 402 770 5184",
    "sg:postcode":"68506",
    "sg:province":"NE",
    "sg:tags":[
        "general",
        "contractor"
    ],
    "wof:name":"Carey Construction",
    "wof:placetype":"venue"
},
  "geometry": {"coordinates":[-96.66051899999999,40.777542],"type":"Point"}
}