{
  "type": "Feature",
  "properties": {
    "addr:full":"5757 Stockwell St Lincoln NE 68506",
    "addr:housenumber":"5757",
    "addr:postcode":"68506",
    "addr:street":"Stockwell St",
    "iso:country":"US",
    "sg:address":"5757 Stockwell St",
    "sg:city":"Lincoln",
    "sg:classifiers":[
        {
            "category":"Building & Trades",
            "subcategory":"Construction",
            "type":"Services"
        }
    ],
    "sg:phone":"+1 402 420 7532",
    "sg:postcode":"68506",
    "sg:province":"NE",
    "sg:tags":[
        "operator",
        "apartment",
        "contractor"
    ],
    "wof:name":"Goetz Foundation Coating",
    "wof:placetype":"venue"
},
  "geometry": {"coordinates":[-96.642567,40.774414],"type":"Point"}
}