{
  "type": "Feature",
  "properties": {
    "iso:country":"US",
    "sg:address":"5088 S 107th St",
    "sg:city":"Omaha",
    "sg:classifiers":[
        {
            "category":"Building & Trades",
            "subcategory":"Plumbing",
            "type":"Services"
        }
    ],
    "sg:phone":"+1 402 733 2589",
    "sg:postcode":"68127",
    "sg:province":"NE",
    "sg:tags":[
        "air",
        "heating",
        "contractor",
        "system",
        "conditioning"
    ],
    "wof:name":"Wichita Heating and Cooling",
    "wof:placetype":"venue"
},
  "geometry": {"coordinates":[-96.078908,41.206156],"type":"Point"}
}