{
  "type": "Feature",
  "properties": {
    "iso:country":"US",
    "sg:address":"619 Avenue E",
    "sg:city":"Cozad",
    "sg:classifiers":[
        {
            "category":"Food & Beverages",
            "subcategory":"Liquor & Beverages",
            "type":"Retail Goods"
        }
    ],
    "sg:phone":"+1 308 784 3454",
    "sg:postcode":"69130",
    "sg:province":"NE",
    "sg:tags":[
        "alcoholic"
    ],
    "wof:name":"Olds Cork & Cap Liquor",
    "wof:placetype":"venue"
},
  "geometry": {"coordinates":[-99.98325,40.857927],"type":"Point"}
}