{
  "type": "Feature",
  "properties": {
    "addr:full":"237 N Main St Valentine NE 69201",
    "addr:housenumber":"237",
    "addr:postcode":"69201",
    "addr:street":"N Main St",
    "iso:country":"US",
    "sg:address":"237 N Main St",
    "sg:city":"Valentine",
    "sg:classifiers":[
        {
            "category":"Utilities",
            "subcategory":"Fuel Oil & Lpg",
            "type":"Services"
        }
    ],
    "sg:phone":"+1 402 376 2970",
    "sg:postcode":"69201",
    "sg:province":"NE",
    "sg:tags":[
        "gas",
        "bottled",
        "appliance"
    ],
    "wof:name":"Reese Propane & Appliances",
    "wof:placetype":"venue"
},
  "geometry": {"coordinates":[-100.550731,42.874038],"type":"Point"}
}