{
  "type": "Feature",
  "properties": {
    "iso:country":"US",
    "sg:address":"2 W 42nd St",
    "sg:city":"Scottsbluff",
    "sg:classifiers":[
        {
            "category":"Home & Garden",
            "subcategory":"Furniture",
            "type":"Retail Goods"
        },
        {
            "category":"Health Services",
            "subcategory":"Medical Lab",
            "type":"Services"
        }
    ],
    "sg:phone":"+1 308 436 4498",
    "sg:postcode":"69361",
    "sg:province":"NE",
    "sg:tags":[
        "laboratory"
    ],
    "wof:name":"Diagnostic Sleep Solutions LLC",
    "wof:placetype":"venue"
},
  "geometry": {"coordinates":[-103.664536,41.88847],"type":"Point"}
}