{
  "type": "Feature",
  "properties": {
    "iso:country":"US",
    "sg:address":"5002 N Happy Hollow Blvd",
    "sg:city":"Omaha",
    "sg:classifiers":[
        {
            "category":"Retail",
            "subcategory":"Auto Repair",
            "type":"Services"
        }
    ],
    "sg:phone":"+1 402 553 9915",
    "sg:postcode":"68104",
    "sg:province":"NE",
    "sg:tags":[
        "repairing",
        "automobile"
    ],
    "wof:name":"Simpson's Auto Repair",
    "wof:placetype":"venue"
},
  "geometry": {"coordinates":[-95.990426,41.274468],"type":"Point"}
}