{
  "type": "Feature",
  "properties": {
    "iso:country":"US",
    "sg:address":"200 E 10th St",
    "sg:city":"Wayne",
    "sg:classifiers":[
        {
            "category":"Professional",
            "subcategory":"Management & Consulting",
            "type":"Services"
        }
    ],
    "sg:phone":"+1 402 375 7575",
    "sg:postcode":"68787",
    "sg:province":"NE",
    "sg:tags":[
        "consultant",
        "business"
    ],
    "wof:name":"Business Development Ctr",
    "wof:placetype":"venue"
},
  "geometry": {"coordinates":[-97.01634799999999,42.239145],"type":"Point"}
}