{
  "type": "Feature",
  "properties": {
    "iso:country":"US",
    "sg:address":"5 Forestview Cir",
    "sg:city":"Lincoln",
    "sg:classifiers":[
        {
            "category":"Professional",
            "subcategory":"Accounting & Tax Preparation",
            "type":"Services"
        }
    ],
    "sg:phone":"+1 402 477 4439",
    "sg:postcode":"68522",
    "sg:province":"NE",
    "sg:tags":[
        "return"
    ],
    "wof:name":"Tax Back Service Inc",
    "wof:placetype":"venue"
},
  "geometry": {"coordinates":[-96.758162,40.782602],"type":"Point"}
}