{
  "type": "Feature",
  "properties": {
    "iso:country":"US",
    "sg:address":"6701 L St",
    "sg:city":"Omaha",
    "sg:classifiers":[
        {
            "category":"Autos & Motor Vehicles",
            "subcategory":"Automobile Sales",
            "type":"Retail Goods"
        }
    ],
    "sg:phone":"+1 402 504 1342",
    "sg:postcode":"68117",
    "sg:province":"NE",
    "sg:tags":[
        "car",
        "dealer"
    ],
    "wof:name":"Autos 4 You",
    "wof:placetype":"venue"
},
  "geometry": {"coordinates":[-96.017849,41.212488],"type":"Point"}
}