{
  "type": "Feature",
  "properties": {
    "iso:country":"US",
    "sg:address":"13522 L St",
    "sg:city":"Omaha",
    "sg:classifiers":[
        {
            "category":"Manufacturing",
            "subcategory":"Signs",
            "type":"Manufacturing & Wholesale Goods"
        }
    ],
    "sg:phone":"+1 402 896 1603",
    "sg:postcode":"68137",
    "sg:province":"NE",
    "sg:tags":[
        "specialty",
        "mfg"
    ],
    "sg:website":"www.celebrationsolutions.com",
    "wof:name":"Sign Solutions Inc",
    "wof:placetype":"venue"
},
  "geometry": {"coordinates":[-96.13189300000001,41.212627],"type":"Point"}
}