{
  "type": "Feature",
  "properties": {
    "addr:full":"108 S 6th St Beatrice NE 68310",
    "addr:housenumber":"108",
    "addr:postcode":"68310",
    "addr:street":"S 6Th St",
    "iso:country":"US",
    "sg:address":"108 S 6th St",
    "sg:city":"Beatrice",
    "sg:classifiers":[
        {
            "category":"Professional",
            "subcategory":"Lawyer & Legal Services",
            "type":"Services"
        }
    ],
    "sg:phone":"+1 402 228 2224",
    "sg:postcode":"68310",
    "sg:province":"NE",
    "sg:tags":[
        "attorney"
    ],
    "wof:name":"James L Nelson",
    "wof:placetype":"venue"
},
  "geometry": {"coordinates":[-96.746685,40.264703],"type":"Point"}
}