{
  "type": "Feature",
  "properties": {
    "iso:country":"US",
    "sg:address":"1570 E Giltner Rd",
    "sg:city":"Doniphan",
    "sg:classifiers":[
        {
            "category":"Wholesale",
            "subcategory":"Farm Supplies",
            "type":"Manufacturing & Wholesale Goods"
        }
    ],
    "sg:phone":"+1 402 845 2350",
    "sg:postcode":"68832",
    "sg:province":"NE",
    "wof:name":"Happold Farms",
    "wof:placetype":"venue"
},
  "geometry": {"coordinates":[-98.30999199999999,40.770906],"type":"Point"}
}