{
  "type": "Feature",
  "properties": {
    "addr:full":"100 Centennial Mall N Lincoln NE 68508",
    "addr:housenumber":"100",
    "addr:postcode":"68508",
    "addr:street":"Centennial Mall N",
    "iso:country":"US",
    "sg:address":"100 Centennial Mall N",
    "sg:city":"Lincoln",
    "sg:classifiers":[
        {
            "category":"Recreation",
            "type":"Entertainment"
        }
    ],
    "sg:phone":"+1 402 437 5403",
    "sg:postcode":"68508",
    "sg:province":"NE",
    "sg:tags":[
        "parks"
    ],
    "wof:name":"National Park Svc",
    "wof:placetype":"venue"
},
  "geometry": {"coordinates":[-96.699668,40.814738],"type":"Point"}
}