{
  "type": "Feature",
  "properties": {
    "addr:full":"20 Thomas Lake Ashland NE 68003",
    "addr:housenumber":"20",
    "addr:postcode":"68003",
    "addr:street":"Thomas Lake",
    "iso:country":"US",
    "sg:address":"20 Thomas Lake",
    "sg:city":"Ashland",
    "sg:classifiers":[
        {
            "category":"Building & Trades",
            "subcategory":"Construction",
            "type":"Services"
        }
    ],
    "sg:phone":"+1 402 944 7852",
    "sg:postcode":"68003",
    "sg:province":"NE",
    "sg:tags":[
        "dredging"
    ],
    "wof:name":"Thomas Dredging & Excavating",
    "wof:placetype":"venue"
},
  "geometry": {"coordinates":[-96.339793,41.100562],"type":"Point"}
}