{
  "type": "Feature",
  "properties": {
    "iso:country":"US",
    "sg:address":"5510 NW 39th St",
    "sg:city":"Lincoln",
    "sg:classifiers":[
        {
            "category":"Wholesale",
            "subcategory":"Machinery & Supplies",
            "type":"Manufacturing & Wholesale Goods"
        }
    ],
    "sg:phone":"+1 402 470 2510",
    "sg:postcode":"68524",
    "sg:province":"NE",
    "sg:tags":[
        "equipment",
        "foundry"
    ],
    "wof:name":"Sadoff & Rudoy Ind LLP",
    "wof:placetype":"venue"
},
  "geometry": {"coordinates":[-96.776537,40.864026],"type":"Point"}
}