{
  "type": "Feature",
  "properties": {
    "iso:country":"US",
    "sg:address":"401 Rexroad Pl",
    "sg:city":"Bellevue",
    "sg:classifiers":[
        {
            "category":"Building & Trades",
            "subcategory":"Construction",
            "type":"Services"
        }
    ],
    "sg:phone":"+1 402 292 7032",
    "sg:postcode":"68005",
    "sg:province":"NE",
    "sg:tags":[
        "house"
    ],
    "wof:name":"Holkeboer Home Repair & Pntg",
    "wof:placetype":"venue"
},
  "geometry": {"coordinates":[-95.88905699999999,41.154503],"type":"Point"}
}