{
  "type": "Feature",
  "properties": {
    "iso:country":"US",
    "sg:address":"3220 Yuma Ln",
    "sg:city":"Lincoln",
    "sg:classifiers":[
        {
            "category":"Professional",
            "subcategory":"Art Services",
            "type":"Services"
        }
    ],
    "sg:phone":"+1 402 420 7577",
    "sg:postcode":"68516",
    "sg:province":"NE",
    "sg:tags":[
        "commercial",
        "design"
    ],
    "wof:name":"Joe McDermott Grapics",
    "wof:placetype":"venue"
},
  "geometry": {"coordinates":[-96.67267,40.738154],"type":"Point"}
}