{
  "type": "Feature",
  "properties": {
    "addr:full":"629 W Fuller St Albion NE 68620",
    "addr:housenumber":"629",
    "addr:postcode":"68620",
    "addr:street":"W Fuller St",
    "iso:country":"US",
    "sg:address":"629 W Fuller St",
    "sg:city":"Albion",
    "sg:classifiers":[
        {
            "category":"Social Services",
            "subcategory":"Child Care",
            "type":"Services"
        }
    ],
    "sg:phone":"+1 402 395 6225",
    "sg:postcode":"68620",
    "sg:province":"NE",
    "sg:tags":[
        "day"
    ],
    "wof:name":"Tiny Treasures Day Care Center",
    "wof:placetype":"venue"
},
  "geometry": {"coordinates":[-98.004874,41.682426],"type":"Point"}
}