{
  "type": "Feature",
  "properties": {
    "addr:full":"3005 S Southern Hills Dr Hastings NE 68901",
    "addr:housenumber":"3005",
    "addr:postcode":"68901",
    "addr:street":"S Southern Hills Dr",
    "iso:country":"US",
    "sg:address":"3005 S Southern Hills Dr",
    "sg:city":"Hastings",
    "sg:classifiers":[
        {
            "category":"Recreation",
            "type":"Entertainment"
        }
    ],
    "sg:phone":"+1 402 463 8006",
    "sg:postcode":"68901",
    "sg:province":"NE",
    "sg:tags":[
        "club",
        "course",
        "golf",
        "house"
    ],
    "wof:name":"Southern Hills Golf Course",
    "wof:placetype":"venue"
},
  "geometry": {"coordinates":[-98.43996300000001,40.546175],"type":"Point"}
}