{
  "type": "Feature",
  "properties": {
    "addr:full":"3231 S 13th St Lincoln NE 68502",
    "addr:housenumber":"3231",
    "addr:postcode":"68502",
    "addr:street":"S 13Th St",
    "iso:country":"US",
    "sg:address":"3231 S 13th St",
    "sg:city":"Lincoln",
    "sg:classifiers":[
        {
            "category":"Shopping",
            "subcategory":"Hobbies, Toys, & Games",
            "type":"Retail Goods"
        }
    ],
    "sg:phone":"+1 402 420 5060",
    "sg:postcode":"68502",
    "sg:province":"NE",
    "sg:tags":[
        "supply"
    ],
    "wof:name":"Gauntlet Games",
    "wof:placetype":"venue"
},
  "geometry": {"coordinates":[-96.702898,40.779276],"type":"Point"}
}