{
  "type": "Feature",
  "properties": {
    "addr:full":"1730 S 13th St Omaha NE 68108",
    "addr:housenumber":"1730",
    "addr:postcode":"68108",
    "addr:street":"S 13Th St",
    "iso:country":"US",
    "sg:address":"1730 S 13th St",
    "sg:city":"Omaha",
    "sg:classifiers":[
        {
            "category":"Professional",
            "subcategory":"Detective & Security Services",
            "type":"Services"
        }
    ],
    "sg:phone":"+1 402 345 4414",
    "sg:postcode":"68108",
    "sg:province":"NE",
    "sg:tags":[
        "polygraph"
    ],
    "wof:name":"Confidential Polygraph Svc",
    "wof:placetype":"venue"
},
  "geometry": {"coordinates":[-95.93338300000001,41.241606],"type":"Point"}
}