{
  "type": "Feature",
  "properties": {
    "addr:full":"3201 Pioneers Blvd Lincoln NE 68502",
    "addr:housenumber":"3201",
    "addr:postcode":"68502",
    "addr:street":"Pioneers Blvd",
    "iso:country":"US",
    "sg:address":"3201 Pioneers Blvd",
    "sg:city":"Lincoln",
    "sg:classifiers":[
        {
            "category":"Health Services",
            "subcategory":"Clinic",
            "type":"Services"
        }
    ],
    "sg:phone":"+1 402 486 3113",
    "sg:postcode":"68502",
    "sg:province":"NE",
    "sg:tags":[
        "specialty",
        "outpatient"
    ],
    "wof:name":"Frizzll-Pratt Vckie A Ms Plmhp",
    "wof:placetype":"venue"
},
  "geometry": {"coordinates":[-96.672871,40.769866],"type":"Point"}
}