{
  "type": "Feature",
  "properties": {
    "iso:country":"US",
    "sg:address":"121 W 3rd St",
    "sg:city":"Ogallala",
    "sg:classifiers":[
        {
            "category":"Government",
            "subcategory":"Court House",
            "type":"Public Place"
        }
    ],
    "sg:phone":"+1 308 284 2091",
    "sg:postcode":"69153",
    "sg:province":"NE",
    "sg:tags":[
        "county",
        "counsel"
    ],
    "wof:name":"Keith County Attorney",
    "wof:placetype":"venue"
},
  "geometry": {"coordinates":[-101.71960799999999,41.126602],"type":"Point"}
}