{
  "type": "Feature",
  "properties": {
    "addr:full":"105 N Elm St Ainsworth NE 69210",
    "addr:housenumber":"105",
    "addr:postcode":"69210",
    "addr:street":"N Elm St",
    "iso:country":"US",
    "sg:address":"105 N Elm St",
    "sg:city":"Ainsworth",
    "sg:classifiers":[
        {
            "category":"Retail",
            "subcategory":"Portrait Studio",
            "type":"Services"
        }
    ],
    "sg:phone":"+1 402 387 0847",
    "sg:postcode":"69210",
    "sg:province":"NE",
    "sg:tags":[
        "print",
        "shop",
        "photography"
    ],
    "wof:name":"Print Shop The",
    "wof:placetype":"venue"
},
  "geometry": {"coordinates":[-99.856799,42.546865],"type":"Point"}
}