{
  "type": "Feature",
  "properties": {
    "iso:country":"US",
    "sg:address":"14835 Paulsen Ln",
    "sg:city":"Blair",
    "sg:classifiers":[
        {
            "category":"Real Estate",
            "subcategory":"Real Estate Operator",
            "type":"Services"
        }
    ],
    "sg:phone":"+1 402 456 7559",
    "sg:postcode":"68008",
    "sg:province":"NE",
    "sg:tags":[
        "property",
        "lessor"
    ],
    "wof:name":"Paulsen Farm",
    "wof:placetype":"venue"
},
  "geometry": {"coordinates":[-96.18856,41.628463],"type":"Point"}
}