{
  "type": "Feature",
  "properties": {
    "addr:full":"21848 Harrison St Gretna NE 68028",
    "addr:housenumber":"21848",
    "addr:postcode":"68028",
    "addr:street":"Harrison St",
    "iso:country":"US",
    "sg:address":"21848 Harrison St",
    "sg:city":"Gretna",
    "sg:classifiers":[
        {
            "category":"Building & Trades",
            "subcategory":"Construction",
            "type":"Services"
        }
    ],
    "sg:phone":"+1 402 578 8023",
    "sg:postcode":"68028",
    "sg:province":"NE",
    "sg:tags":[
        "contractor"
    ],
    "wof:name":"Michael W Olk",
    "wof:placetype":"venue"
},
  "geometry": {"coordinates":[-96.25648200000001,41.190438],"type":"Point"}
}