{
  "type": "Feature",
  "properties": {
    "iso:country":"US",
    "sg:address":"800 W 23rd St",
    "sg:city":"Fremont",
    "sg:classifiers":[
        {
            "category":"Real Estate",
            "subcategory":"Developer",
            "type":"Services"
        }
    ],
    "sg:phone":"+1 402 721 1442",
    "sg:postcode":"68025",
    "sg:province":"NE",
    "sg:tags":[
        "cemetery",
        "subdivider"
    ],
    "wof:name":"Memorial Cemetery Association",
    "wof:placetype":"venue"
},
  "geometry": {"coordinates":[-96.506034,41.451415],"type":"Point"}
}