{
  "type": "Feature",
  "properties": {
    "addr:full":"220 N Hastings Ave Hastings NE 68901",
    "addr:housenumber":"220",
    "addr:postcode":"68901",
    "addr:street":"N Hastings Ave",
    "iso:country":"US",
    "sg:address":"220 N Hastings Ave",
    "sg:city":"Hastings",
    "sg:classifiers":[
        {
            "category":"Government",
            "subcategory":"Office",
            "type":"Public Place"
        }
    ],
    "sg:phone":"+1 402 461 2329",
    "sg:postcode":"68901",
    "sg:province":"NE",
    "sg:tags":[
        "village"
    ],
    "wof:name":"Hastings Plumbing Inspector",
    "wof:placetype":"venue"
},
  "geometry": {"coordinates":[-98.389837,40.585928],"type":"Point"}
}