{
  "type": "Feature",
  "properties": {
    "iso:country":"US",
    "sg:address":"2114 Central Ave",
    "sg:city":"Kearney",
    "sg:classifiers":[
        {
            "category":"Home & Garden",
            "subcategory":"Home Furnishings",
            "type":"Retail Goods"
        },
        {
            "category":"Shopping",
            "subcategory":"Crafts & Fabrics",
            "type":"Retail Goods"
        }
    ],
    "sg:phone":"+1 308 236 6286",
    "sg:postcode":"68847",
    "sg:province":"NE",
    "sg:tags":[
        "shop",
        "quilting"
    ],
    "sg:website":"www.quilterstrunk.com",
    "wof:name":"Quilters Trunk",
    "wof:placetype":"venue"
},
  "geometry": {"coordinates":[-99.081813,40.697477],"type":"Point"}
}