{
  "type": "Feature",
  "properties": {
    "addr:full":"3102 N 60th St Omaha NE 68104",
    "addr:housenumber":"3102",
    "addr:postcode":"68104",
    "addr:street":"N 60Th St",
    "iso:country":"US",
    "sg:address":"3102 N 60th St",
    "sg:city":"Omaha",
    "sg:classifiers":[
        {
            "category":"Real Estate",
            "subcategory":"Real Estate Operator",
            "type":"Services"
        }
    ],
    "sg:phone":"+1 402 551 4243",
    "sg:postcode":"68104",
    "sg:province":"NE",
    "sg:tags":[
        "apartment"
    ],
    "wof:name":"St James Manor Apts",
    "wof:placetype":"venue"
},
  "geometry": {"coordinates":[-96.00460099999999,41.286701],"type":"Point"}
}