{
  "type": "Feature",
  "properties": {
    "addr:full":"300 N 2nd St Oneill NE 68763",
    "addr:housenumber":"300",
    "addr:postcode":"68763",
    "addr:street":"N 2Nd St",
    "iso:country":"US",
    "sg:address":"300 N 2nd St",
    "sg:city":"Oneill",
    "sg:classifiers":[
        {
            "category":"Health Services",
            "subcategory":"Hospital",
            "type":"Services"
        }
    ],
    "sg:phone":"+1 402 336 2611",
    "sg:postcode":"68763",
    "sg:province":"NE",
    "sg:website":"www.averastanthonys.org",
    "wof:name":"Avera St Anthony's Hospital",
    "wof:placetype":"venue"
},
  "geometry": {"coordinates":[-98.65112999999999,42.461179],"type":"Point"}
}