{
  "type": "Feature",
  "properties": {
    "iso:country":"US",
    "sg:address":"911 E 11th St",
    "sg:city":"Kearney",
    "sg:classifiers":[
        {
            "category":"Freight",
            "type":"Transportation"
        }
    ],
    "sg:phone":"+1 308 237 2244",
    "sg:postcode":"68847",
    "sg:province":"NE",
    "sg:tags":[
        "trucking"
    ],
    "sg:website":"www.browntransfer.com",
    "wof:name":"Brown Transfer Co",
    "wof:placetype":"venue"
},
  "geometry": {"coordinates":[-99.06937600000001,40.68485],"type":"Point"}
}