{
  "type": "Feature",
  "properties": {
    "iso:country":"US",
    "sg:address":"1803 W North Front St",
    "sg:city":"Grand Island",
    "sg:classifiers":[
        {
            "category":"Bars & Pubs",
            "type":"Food & Drink"
        }
    ],
    "sg:phone":"+1 308 384 4586",
    "sg:postcode":"68803",
    "sg:province":"NE",
    "sg:tags":[
        "drinking",
        "eating"
    ],
    "wof:name":"White Horse Tavern Inc",
    "wof:placetype":"venue"
},
  "geometry": {"coordinates":[-98.35875799999999,40.920341],"type":"Point"}
}