{
  "type": "Feature",
  "properties": {
    "addr:full":"4414 S 149th St Omaha NE 68137",
    "addr:housenumber":"4414",
    "addr:postcode":"68137",
    "addr:street":"S 149Th St",
    "iso:country":"US",
    "sg:address":"4414 S 149th St",
    "sg:city":"Omaha",
    "sg:classifiers":[
        {
            "category":"Social Services",
            "subcategory":"Child Care",
            "type":"Services"
        }
    ],
    "sg:phone":"+1 402 896 6769",
    "sg:postcode":"68137",
    "sg:province":"NE",
    "sg:tags":[
        "day"
    ],
    "wof:name":"Kimberly Hayden",
    "wof:placetype":"venue"
},
  "geometry": {"coordinates":[-96.144948,41.214006],"type":"Point"}
}