{
  "type": "Feature",
  "properties": {
    "addr:full":"15160 W Barrows Rd Kenesaw NE 68956",
    "addr:housenumber":"15160",
    "addr:postcode":"68956",
    "addr:street":"W Barrows Rd",
    "iso:country":"US",
    "sg:address":"15160 W Barrows Rd",
    "sg:city":"Kenesaw",
    "sg:classifiers":[
        {
            "category":"Professional",
            "subcategory":"Management & Consulting",
            "type":"Services"
        }
    ],
    "sg:phone":"+1 402 752 3328",
    "sg:postcode":"68956",
    "sg:province":"NE",
    "wof:name":"Vojta Transportation LLC",
    "wof:placetype":"venue"
},
  "geometry": {"coordinates":[-98.626463,40.698822],"type":"Point"}
}