{
  "type": "Feature",
  "properties": {
    "iso:country":"US",
    "sg:address":"515 Walnut St",
    "sg:city":"Verdigre",
    "sg:classifiers":[
        {
            "category":"Education",
            "subcategory":"Library",
            "type":"Public Place"
        }
    ],
    "sg:phone":"+1 402 668 5275",
    "sg:postcode":"68787",
    "sg:province":"NE",
    "wof:name":"Yankton Library",
    "wof:placetype":"venue"
},
  "geometry": {"coordinates":[-97.011876,42.234463],"type":"Point"}
}