{
  "type": "Feature",
  "properties": {
    "addr:full":"267 Main St Harrison NE 69346",
    "addr:housenumber":"267",
    "addr:postcode":"69346",
    "addr:street":"Main St",
    "iso:country":"US",
    "sg:address":"267 Main St",
    "sg:city":"Harrison",
    "sg:classifiers":[
        {
            "category":"Government",
            "subcategory":"Post Office",
            "type":"Public Place"
        }
    ],
    "sg:phone":"+1 308 668 2449",
    "sg:postcode":"69346",
    "sg:province":"NE",
    "wof:name":"US Post Office",
    "wof:placetype":"venue"
},
  "geometry": {"coordinates":[-103.882946,42.687684],"type":"Point"}
}