{
  "type": "Feature",
  "properties": {
    "iso:country":"US",
    "sg:address":"510 S Sunset St",
    "sg:city":"Pierce",
    "sg:classifiers":[
        {
            "category":"Building & Trades",
            "subcategory":"Construction",
            "type":"Services"
        }
    ],
    "sg:phone":"+1 402 329 4165",
    "sg:postcode":"68767",
    "sg:province":"NE",
    "sg:tags":[
        "house"
    ],
    "wof:name":"KB Prep Service & Remodeling",
    "wof:placetype":"venue"
},
  "geometry": {"coordinates":[-97.538343,42.193146],"type":"Point"}
}