{
  "type": "Feature",
  "properties": {
    "iso:country":"US",
    "sg:address":"57225 Pwf Rd",
    "sg:city":"Fairbury",
    "sg:phone":"+1 402 729 5848",
    "sg:postcode":"68352",
    "sg:province":"NE",
    "sg:tags":[
        "farm",
        "corn"
    ],
    "wof:name":"Roger Starck Farm",
    "wof:placetype":"venue"
},
  "geometry": {"coordinates":[-97.100404,40.131903],"type":"Point"}
}