{
  "type": "Feature",
  "properties": {
    "iso:country":"US",
    "sg:address":"5907 N 16th St",
    "sg:city":"Omaha",
    "sg:phone":"+1 402 455 2679",
    "sg:postcode":"68110",
    "sg:province":"NE",
    "sg:tags":[
        "farm"
    ],
    "wof:name":"Sesemanns Gardens",
    "wof:placetype":"venue"
},
  "geometry": {"coordinates":[-95.937224,41.311613],"type":"Point"}
}