{
  "type": "Feature",
  "properties": {
    "iso:country":"US",
    "sg:address":"3667 N 129th St",
    "sg:city":"Omaha",
    "sg:classifiers":[
        {
            "category":"Personal",
            "subcategory":"Beauty Salon",
            "type":"Services"
        }
    ],
    "sg:phone":"+1 402 934 4747",
    "sg:postcode":"68164",
    "sg:province":"NE",
    "wof:name":"Fringes Eagle Run",
    "wof:placetype":"venue"
},
  "geometry": {"coordinates":[-96.115066,41.29278],"type":"Point"}
}