{
  "type": "Feature",
  "properties": {
    "addr:full":"1116 Central Ave Nebraska City NE 68410",
    "addr:housenumber":"1116",
    "addr:postcode":"68410",
    "addr:street":"Central Ave",
    "iso:country":"US",
    "sg:address":"1116 Central Ave",
    "sg:city":"Nebraska City",
    "sg:classifiers":[
        {
            "category":"Autos & Motor Vehicles",
            "subcategory":"Auto Supplies",
            "type":"Retail Goods"
        }
    ],
    "sg:phone":"+1 402 873 6643",
    "sg:postcode":"68410",
    "sg:province":"NE",
    "wof:name":"NAPA Auto Parts",
    "wof:placetype":"venue"
},
  "geometry": {"coordinates":[-95.86002999999999,40.676751],"type":"Point"}
}