{
  "type": "Feature",
  "properties": {
    "addr:full":"4732 S 131st St Omaha NE 68137",
    "addr:housenumber":"4732",
    "addr:postcode":"68137",
    "addr:street":"S 131St St",
    "iso:country":"US",
    "sg:address":"4732 S 131st St",
    "sg:city":"Omaha",
    "sg:classifiers":[
        {
            "category":"Banks & Credit Unions",
            "subcategory":"Bank",
            "type":"Services"
        }
    ],
    "sg:phone":"+1 402 895 2865",
    "sg:postcode":"68137",
    "sg:province":"NE",
    "sg:tags":[
        "broker",
        "mortgage"
    ],
    "wof:name":"Primary Residential Mortgage",
    "wof:placetype":"venue"
},
  "geometry": {"coordinates":[-96.11818,41.210435],"type":"Point"}
}