{
  "type": "Feature",
  "properties": {
    "iso:country":"US",
    "sg:address":"14912 Echo Hills Dr",
    "sg:city":"Omaha",
    "sg:classifiers":[
        {
            "category":"Professional",
            "type":"Services"
        }
    ],
    "sg:phone":"+1 402 894 1420",
    "sg:postcode":"68138",
    "sg:province":"NE",
    "wof:name":"T&C Service",
    "wof:placetype":"venue"
},
  "geometry": {"coordinates":[-96.146508,41.185156],"type":"Point"}
}