{
  "type": "Feature",
  "properties": {
    "addr:full":"1700 Farnam St Fl 3 Omaha NE 68102",
    "addr:housenumber":"1700",
    "addr:postcode":"68102",
    "addr:street":"Farnam St",
    "iso:country":"US",
    "sg:address":"1700 Farnam St Fl 3",
    "sg:city":"Omaha",
    "sg:classifiers":[
        {
            "category":"Banks & Credit Unions",
            "subcategory":"Bank",
            "type":"Services"
        }
    ],
    "sg:phone":"+1 402 348 6000",
    "sg:postcode":"68102",
    "sg:province":"NE",
    "sg:website":"www.usbank.com",
    "wof:name":"U S Bank",
    "wof:placetype":"venue"
},
  "geometry": {"coordinates":[-95.93849899999999,41.257599],"type":"Point"}
}