{
  "type": "Feature",
  "properties": {
    "addr:full":"311 Walnut St Yankton NE 57078",
    "addr:housenumber":"311",
    "addr:postcode":"57078",
    "addr:street":"Walnut St",
    "iso:country":"US",
    "sg:address":"311 Walnut St",
    "sg:city":"Yankton",
    "sg:classifiers":[
        {
            "category":"Social Services",
            "type":"Services"
        }
    ],
    "sg:phone":"+1 605 665 1310",
    "sg:postcode":"57078",
    "sg:province":"NE",
    "sg:tags":[
        "counselor",
        "marriage",
        "family"
    ],
    "wof:name":"Hamvas Counseling Service",
    "wof:placetype":"venue"
},
  "geometry": {"coordinates":[-97.393869,42.870947],"type":"Point"}
}