{
  "type": "Feature",
  "properties": {
    "iso:country":"US",
    "sg:address":"424 Main St",
    "sg:city":"Milligan",
    "sg:classifiers":[
        {
            "category":"Government",
            "subcategory":"Office",
            "type":"Public Place"
        }
    ],
    "sg:phone":"+1 402 629 4302",
    "sg:postcode":"68406",
    "sg:province":"NE",
    "sg:tags":[
        "village"
    ],
    "wof:name":"Milligan Village Clerk",
    "wof:placetype":"venue"
},
  "geometry": {"coordinates":[-97.38893899999999,40.498413],"type":"Point"}
}