{
  "type": "Feature",
  "properties": {
    "addr:full":"6048 S 49th Ave Omaha NE 68117",
    "addr:housenumber":"6048",
    "addr:postcode":"68117",
    "addr:street":"S 49Th Ave",
    "iso:country":"US",
    "sg:address":"6048 S 49th Ave",
    "sg:city":"Omaha",
    "sg:classifiers":[
        {
            "category":"Building & Trades",
            "subcategory":"Construction",
            "type":"Services"
        }
    ],
    "sg:phone":"+1 402 933 2866",
    "sg:postcode":"68117",
    "sg:province":"NE",
    "sg:tags":[
        "house",
        "improvement",
        "home"
    ],
    "wof:name":"D & M Home Improvements",
    "wof:placetype":"venue"
},
  "geometry": {"coordinates":[-95.99029299999999,41.196367],"type":"Point"}
}