{
  "type": "Feature",
  "properties": {
    "iso:country":"US",
    "sg:address":"400 N Oakland Ave",
    "sg:city":"Oakland",
    "sg:classifiers":[
        {
            "category":"Personal",
            "subcategory":"Beauty Salon",
            "type":"Services"
        }
    ],
    "sg:phone":"+1 402 685 5050",
    "sg:postcode":"68045",
    "sg:province":"NE",
    "sg:tags":[
        "shop"
    ],
    "wof:name":"Jeannie's Salon",
    "wof:placetype":"venue"
},
  "geometry": {"coordinates":[-96.46670899999999,41.837914],"type":"Point"}
}