{
  "type": "Feature",
  "properties": {
    "addr:full":"265 N Showboat Blvd Hastings NE 68901",
    "addr:housenumber":"265",
    "addr:postcode":"68901",
    "addr:street":"N Showboat Blvd",
    "iso:country":"US",
    "sg:address":"265 N Showboat Blvd",
    "sg:city":"Hastings",
    "sg:classifiers":[
        {
            "category":"Freight",
            "type":"Transportation"
        }
    ],
    "sg:phone":"+1 402 463 5148",
    "sg:postcode":"68901",
    "sg:province":"NE",
    "sg:tags":[
        "grain",
        "elevator"
    ],
    "wof:name":"Heartland Co-Op",
    "wof:placetype":"venue"
},
  "geometry": {"coordinates":[-98.354517,40.582919],"type":"Point"}
}