{
  "type": "Feature",
  "properties": {
    "addr:full":"76026 Rd 429 Lexington NE 68850",
    "addr:postcode":"76026;68850",
    "addr:street":"Rd 429",
    "iso:country":"US",
    "sg:address":"76026 Rd 429",
    "sg:city":"Lexington",
    "sg:classifiers":[
        {
            "category":"Professional",
            "type":"Services"
        }
    ],
    "sg:phone":"+1 308 324 2840",
    "sg:postcode":"68850",
    "sg:province":"NE",
    "wof:name":"Dlsk Inc",
    "wof:placetype":"venue"
},
  "geometry": {"coordinates":[-99.825371,40.846597],"type":"Point"}
}