{
  "type": "Feature",
  "properties": {
    "iso:country":"US",
    "sg:address":"1448 Center Ave",
    "sg:city":"Mitchell",
    "sg:classifiers":[
        {
            "category":"Insurance",
            "subcategory":"Insurance Agent",
            "type":"Services"
        }
    ],
    "sg:phone":"+1 308 623 2616",
    "sg:postcode":"69357",
    "sg:province":"NE",
    "wof:name":"J G Elliott Insurance Ctr",
    "wof:placetype":"venue"
},
  "geometry": {"coordinates":[-103.808707,41.942752],"type":"Point"}
}