{
  "type": "Feature",
  "properties": {
    "addr:full":"2526 17th St Columbus NE 68601",
    "addr:housenumber":"2526",
    "addr:postcode":"68601",
    "addr:street":"17Th St",
    "iso:country":"US",
    "sg:address":"2526 17th St",
    "sg:city":"Columbus",
    "sg:classifiers":[
        {
            "category":"Health Services",
            "subcategory":"Chiropractor",
            "type":"Services"
        }
    ],
    "sg:phone":"+1 402 562 6776",
    "sg:postcode":"68601",
    "sg:province":"NE",
    "sg:tags":[
        "medical"
    ],
    "wof:name":"Columbus Chiropractic",
    "wof:placetype":"venue"
},
  "geometry": {"coordinates":[-97.359071,41.433252],"type":"Point"}
}