{
  "type": "Feature",
  "properties": {
    "iso:country":"US",
    "sg:address":"412 Kennedy Ct",
    "sg:city":"Grand Island",
    "sg:classifiers":[
        {
            "category":"Social Services",
            "subcategory":"Child Care",
            "type":"Services"
        }
    ],
    "sg:phone":"+1 308 384 8070",
    "sg:postcode":"68803",
    "sg:province":"NE",
    "sg:tags":[
        "day"
    ],
    "wof:name":"Michelle Dramse Day Care",
    "wof:placetype":"venue"
},
  "geometry": {"coordinates":[-98.37539,40.92132],"type":"Point"}
}