{
  "type": "Feature",
  "properties": {
    "iso:country":"US",
    "sg:address":"3000 W O St",
    "sg:city":"Lincoln",
    "sg:classifiers":[
        {
            "category":"Retail",
            "subcategory":"Repair Shop",
            "type":"Services"
        }
    ],
    "sg:phone":"+1 402 435 8337",
    "sg:postcode":"68528",
    "sg:province":"NE",
    "sg:tags":[
        "welding"
    ],
    "wof:name":"Johnson Iron Works",
    "wof:placetype":"venue"
},
  "geometry": {"coordinates":[-96.763214,40.813827],"type":"Point"}
}