{
  "type": "Feature",
  "properties": {
    "iso:country":"US",
    "sg:address":"112 Park St",
    "sg:city":"Syracuse",
    "sg:classifiers":[
        {
            "category":"Health Services",
            "subcategory":"Chiropractor",
            "type":"Services"
        }
    ],
    "sg:phone":"+1 402 269 3130",
    "sg:postcode":"68446",
    "sg:province":"NE",
    "wof:name":"Syracuse Chiropractic Center",
    "wof:placetype":"venue"
},
  "geometry": {"coordinates":[-96.17883500000001,40.653924],"type":"Point"}
}