{
  "type": "Feature",
  "properties": {
    "iso:country":"US",
    "sg:address":"815 Tibbals St",
    "sg:city":"Holdrege",
    "sg:classifiers":[
        {
            "category":"Building & Trades",
            "subcategory":"Construction",
            "type":"Services"
        }
    ],
    "sg:phone":"+1 308 995 5189",
    "sg:postcode":"68949",
    "sg:province":"NE",
    "sg:tags":[
        "consulting",
        "management"
    ],
    "wof:name":"Cv & Assocs Inc",
    "wof:placetype":"venue"
},
  "geometry": {"coordinates":[-99.382338,40.442767],"type":"Point"}
}