{
  "type": "Feature",
  "properties": {
    "iso:country":"US",
    "sg:address":"346 Main St",
    "sg:city":"Plattsmouth",
    "sg:classifiers":[
        {
            "category":"Government",
            "subcategory":"Court House",
            "type":"Public Place"
        }
    ],
    "sg:phone":"+1 402 296 9344",
    "sg:postcode":"68048",
    "sg:province":"NE",
    "sg:tags":[
        "county"
    ],
    "wof:name":"Cass County District Judge",
    "wof:placetype":"venue"
},
  "geometry": {"coordinates":[-95.883043,41.01124],"type":"Point"}
}