{
  "type": "Feature",
  "properties": {
    "iso:country":"US",
    "sg:address":"809 S B Rd",
    "sg:city":"Doniphan",
    "sg:classifiers":[
        {
            "category":"Retail",
            "subcategory":"Auto Repair",
            "type":"Services"
        }
    ],
    "sg:phone":"+1 402 694 6455",
    "sg:postcode":"68832",
    "sg:province":"NE",
    "sg:tags":[
        "wrecker"
    ],
    "wof:name":"Island Towing & Recovery",
    "wof:placetype":"venue"
},
  "geometry": {"coordinates":[-98.26401199999999,40.807384],"type":"Point"}
}