{
  "type": "Feature",
  "properties": {
    "iso:country":"US",
    "sg:address":"2604 S 13th St",
    "sg:city":"Omaha",
    "sg:classifiers":[
        {
            "category":"Food & Beverages",
            "subcategory":"Groceries & Convenience Stores",
            "type":"Retail Goods"
        }
    ],
    "sg:phone":"+1 402 341 7371",
    "sg:postcode":"68108",
    "sg:province":"NE",
    "wof:name":"Fill & Food",
    "wof:placetype":"venue"
},
  "geometry": {"coordinates":[-95.933502,41.234901],"type":"Point"}
}