{
  "type": "Feature",
  "properties": {
    "iso:country":"US",
    "sg:address":"2625 10th St",
    "sg:city":"Gering",
    "sg:classifiers":[
        {
            "category":"Wholesale",
            "subcategory":"Beer",
            "type":"Manufacturing & Wholesale Goods"
        }
    ],
    "sg:phone":"+1 308 632 8833",
    "sg:postcode":"69341",
    "sg:province":"NE",
    "sg:tags":[
        "ale"
    ],
    "wof:name":"Coors",
    "wof:placetype":"venue"
},
  "geometry": {"coordinates":[-103.660709,41.838833],"type":"Point"}
}