{
  "type": "Feature",
  "properties": {
    "addr:full":"1244 Illinois St Sidney NE 69162",
    "addr:housenumber":"1244",
    "addr:postcode":"69162",
    "addr:street":"Illinois St",
    "iso:country":"US",
    "sg:address":"1244 Illinois St",
    "sg:city":"Sidney",
    "sg:classifiers":[
        {
            "category":"Retail",
            "subcategory":"Auto Repair",
            "type":"Services"
        }
    ],
    "sg:phone":"+1 308 254 9045",
    "sg:postcode":"69162",
    "sg:province":"NE",
    "sg:tags":[
        "repairing",
        "automobile"
    ],
    "wof:name":"Randy's Auto Care",
    "wof:placetype":"venue"
},
  "geometry": {"coordinates":[-102.980082,41.144845],"type":"Point"}
}