{
  "type": "Feature",
  "properties": {
    "addr:full":"1317 12th St Aurora NE 68818",
    "addr:housenumber":"1317",
    "addr:postcode":"68818",
    "addr:street":"12Th St",
    "iso:country":"US",
    "sg:address":"1317 12th St",
    "sg:city":"Aurora",
    "sg:classifiers":[
        {
            "category":"Professional",
            "type":"Services"
        }
    ],
    "sg:phone":"+1 402 694 5301",
    "sg:postcode":"68818",
    "sg:province":"NE",
    "sg:tags":[
        "establishment"
    ],
    "wof:name":"Nielsen & Nielsen",
    "wof:placetype":"venue"
},
  "geometry": {"coordinates":[-98.00333500000001,40.870223],"type":"Point"}
}