{
  "type": "Feature",
  "properties": {
    "addr:full":"2421 23rd St Columbus NE 68601",
    "addr:housenumber":"2421",
    "addr:postcode":"68601",
    "addr:street":"23Rd St",
    "iso:country":"US",
    "sg:address":"2421 23rd St",
    "sg:city":"Columbus",
    "sg:classifiers":[
        {
            "category":"Health Services",
            "subcategory":"Chiropractor",
            "type":"Services"
        }
    ],
    "sg:phone":"+1 402 564 9447",
    "sg:postcode":"68601",
    "sg:province":"NE",
    "sg:tags":[
        "center",
        "chiropractic"
    ],
    "wof:name":"Hinze Chiropractic Center",
    "wof:placetype":"venue"
},
  "geometry": {"coordinates":[-97.357778,41.438527],"type":"Point"}
}