{
  "type": "Feature",
  "properties": {
    "iso:country":"US",
    "sg:address":"2424 P St",
    "sg:city":"Omaha",
    "sg:classifiers":[
        {
            "category":"Retail",
            "subcategory":"Repair Shop",
            "type":"Services"
        }
    ],
    "sg:phone":"+1 402 939 8669",
    "sg:postcode":"68107",
    "sg:province":"NE",
    "sg:tags":[
        "television",
        "radio-service"
    ],
    "sg:website":"http://www.abetterwayservice.com",
    "wof:name":"A Better Way Service Company Inc",
    "wof:placetype":"venue"
},
  "geometry": {"coordinates":[-95.947416,41.206909],"type":"Point"}
}