{
  "type": "Feature",
  "properties": {
    "addr:full":"1005 Village Green Dr Norfolk NE 68701",
    "addr:housenumber":"1005",
    "addr:postcode":"68701",
    "addr:street":"Village Green Dr",
    "iso:country":"US",
    "sg:address":"1005 Village Green Dr",
    "sg:city":"Norfolk",
    "sg:classifiers":[
        {
            "category":"Freight",
            "type":"Transportation"
        },
        {
            "category":"Real Estate",
            "subcategory":"Real Estate Operator",
            "type":"Services"
        }
    ],
    "sg:phone":"+1 402 379 8652",
    "sg:postcode":"68701",
    "sg:province":"NE",
    "sg:tags":[
        "building",
        "apartment",
        "special"
    ],
    "wof:name":"Village Green Apartments",
    "wof:placetype":"venue"
},
  "geometry": {"coordinates":[-97.419889,42.051578],"type":"Point"}
}