{
  "type": "Feature",
  "properties": {
    "addr:full":"2401 S 75th St Lincoln NE 68506",
    "addr:housenumber":"2401",
    "addr:postcode":"68506",
    "addr:street":"S 75Th St",
    "iso:country":"US",
    "sg:address":"2401 S 75th St",
    "sg:city":"Lincoln",
    "sg:classifiers":[
        {
            "category":"Social Services",
            "type":"Services"
        }
    ],
    "sg:phone":"+1 402 488 1916",
    "sg:postcode":"68506",
    "sg:province":"NE",
    "sg:tags":[
        "counselor",
        "marriage",
        "family"
    ],
    "wof:name":"Janet Waage Lingren",
    "wof:placetype":"venue"
},
  "geometry": {"coordinates":[-96.617514,40.784265],"type":"Point"}
}