{
  "type": "Feature",
  "properties": {
    "iso:country":"US",
    "sg:address":"10811 N 72nd St",
    "sg:city":"Omaha",
    "sg:classifiers":[
        {
            "category":"Home & Garden",
            "subcategory":"Building Materials",
            "type":"Retail Goods"
        }
    ],
    "sg:phone":"+1 402 572 5725",
    "sg:postcode":"68122",
    "sg:province":"NE",
    "sg:tags":[
        "glass",
        "window",
        "plate"
    ],
    "wof:name":"Autoglass Plus",
    "wof:placetype":"venue"
},
  "geometry": {"coordinates":[-96.02374399999999,41.355926],"type":"Point"}
}