{
  "type": "Feature",
  "properties": {
    "iso:country":"US",
    "sg:address":"222 S 15th St",
    "sg:city":"Omaha",
    "sg:classifiers":[
        {
            "category":"Professional",
            "subcategory":"Management & Consulting",
            "type":"Services"
        }
    ],
    "sg:phone":"+1 402 689 3010",
    "sg:postcode":"68102",
    "sg:province":"NE",
    "wof:name":"Creel Group Inc",
    "wof:placetype":"venue"
},
  "geometry": {"coordinates":[-95.93592200000001,41.258508],"type":"Point"}
}