{
  "type": "Feature",
  "properties": {
    "iso:country":"US",
    "sg:address":"1015 Fairfax Rd",
    "sg:city":"Bellevue",
    "sg:classifiers":[
        {
            "category":"Shopping",
            "type":"Retail Goods"
        }
    ],
    "sg:phone":"+1 402 292 1999",
    "sg:postcode":"68005",
    "sg:province":"NE",
    "sg:tags":[
        "merchandise"
    ],
    "wof:name":"Game Shoppe",
    "wof:placetype":"venue"
},
  "geometry": {"coordinates":[-95.915526,41.151061],"type":"Point"}
}