{
  "type": "Feature",
  "properties": {
    "iso:country":"US",
    "sg:address":"201 E G St",
    "sg:city":"Ogallala",
    "sg:classifiers":[
        {
            "category":"Government",
            "subcategory":"Office",
            "type":"Public Place"
        }
    ],
    "sg:phone":"+1 308 284 6077",
    "sg:postcode":"69153",
    "sg:province":"NE",
    "wof:name":"US Central Nebraska Dev",
    "wof:placetype":"venue"
},
  "geometry": {"coordinates":[-101.710939,41.12757],"type":"Point"}
}