{
  "type": "Feature",
  "properties": {
    "iso:country":"US",
    "sg:address":"515 N 98th St",
    "sg:city":"Omaha",
    "sg:classifiers":[
        {
            "category":"Shopping",
            "subcategory":"Optical Goods",
            "type":"Retail Goods"
        }
    ],
    "sg:phone":"+1 402 884 0599",
    "sg:postcode":"68114",
    "sg:province":"NE",
    "wof:name":"Eyes On The Road",
    "wof:placetype":"venue"
},
  "geometry": {"coordinates":[-96.065398,41.265117],"type":"Point"}
}