{
  "type": "Feature",
  "properties": {
    "iso:country":"US",
    "sg:address":"3420 S 143rd Plz",
    "sg:city":"Omaha",
    "sg:classifiers":[
        {
            "category":"Retail",
            "subcategory":"Auto Repair",
            "type":"Services"
        }
    ],
    "sg:phone":"+1 402 333 0900",
    "sg:postcode":"68144",
    "sg:province":"NE",
    "sg:tags":[
        "automotive"
    ],
    "sg:website":"www.brakemasters.com",
    "wof:name":"Brake Masters",
    "wof:placetype":"venue"
},
  "geometry": {"coordinates":[-96.13741899999999,41.230476],"type":"Point"}
}