{
  "type": "Feature",
  "properties": {
    "iso:country":"US",
    "sg:address":"1050 Saltillo Rd",
    "sg:city":"Roca",
    "sg:classifiers":[
        {
            "category":"Home & Garden",
            "subcategory":"Garden Supply",
            "type":"Retail Goods"
        }
    ],
    "sg:phone":"+1 402 421 8873",
    "sg:postcode":"68430",
    "sg:province":"NE",
    "sg:tags":[
        "lawn",
        "mower"
    ],
    "wof:name":"Lincoln Turf & Tractor Inc",
    "wof:placetype":"venue"
},
  "geometry": {"coordinates":[-96.708303,40.697478],"type":"Point"}
}