{
  "type": "Feature",
  "properties": {
    "iso:country":"US",
    "sg:address":"401 Adam St",
    "sg:city":"Schuyler",
    "sg:classifiers":[
        {
            "category":"Education",
            "subcategory":"School",
            "type":"Public Place"
        }
    ],
    "sg:phone":"+1 402 352 3527",
    "sg:postcode":"68661",
    "sg:province":"NE",
    "wof:name":"Schuyler Superintendent Office",
    "wof:placetype":"venue"
},
  "geometry": {"coordinates":[-97.061082,41.441562],"type":"Point"}
}