{
  "type": "Feature",
  "properties": {
    "addr:full":"246 S 15th St Ord NE 68862",
    "addr:housenumber":"246",
    "addr:postcode":"68862",
    "addr:street":"S 15Th St",
    "iso:country":"US",
    "sg:address":"246 S 15th St",
    "sg:city":"Ord",
    "sg:classifiers":[
        {
            "category":"Organizations",
            "subcategory":"Community Association",
            "type":"Services"
        }
    ],
    "sg:phone":"+1 308 728 5351",
    "sg:postcode":"68862",
    "sg:province":"NE",
    "sg:tags":[
        "military"
    ],
    "sg:website":"www.vfw.org",
    "wof:name":"Veterans Of Foreign Wars",
    "wof:placetype":"venue"
},
  "geometry": {"coordinates":[-98.928062,41.601699],"type":"Point"}
}