{
  "type": "Feature",
  "properties": {
    "addr:full":"218 W 25th St Kearney NE 68845",
    "addr:housenumber":"218",
    "addr:postcode":"68845",
    "addr:street":"W 25Th St",
    "iso:country":"US",
    "sg:address":"218 W 25th St",
    "sg:city":"Kearney",
    "sg:classifiers":[
        {
            "category":"Restaurant",
            "type":"Food & Drink"
        },
        {
            "category":"Ice Cream",
            "type":"Food & Drink"
        }
    ],
    "sg:menulink":"http://www.allmenus.com/ne/kearney/209119-tcby/menu/",
    "sg:phone":"+1 308 236 6606",
    "sg:postcode":"68845",
    "sg:province":"NE",
    "sg:tags":[
        "smoothy",
        "juice",
        "american",
        "ice",
        "cream"
    ],
    "wof:name":"TCBY",
    "wof:placetype":"venue"
},
  "geometry": {"coordinates":[-99.084656,40.700371],"type":"Point"}
}