{
  "type": "Feature",
  "properties": {
    "addr:full":"10101 Old Cheney Rd Lincoln NE 68526",
    "addr:housenumber":"10101",
    "addr:postcode":"68526",
    "addr:street":"Old Cheney Rd",
    "iso:country":"US",
    "sg:address":"10101 Old Cheney Rd",
    "sg:city":"Lincoln",
    "sg:classifiers":[
        {
            "category":"Retail",
            "subcategory":"Animal Services",
            "type":"Services"
        }
    ],
    "sg:phone":"+1 402 488 8190",
    "sg:postcode":"68526",
    "sg:province":"NE",
    "wof:name":"Kenl Inn",
    "wof:placetype":"venue"
},
  "geometry": {"coordinates":[-96.586895,40.755191],"type":"Point"}
}