{
  "type": "Feature",
  "properties": {
    "iso:country":"US",
    "sg:address":"1805 Q St",
    "sg:city":"Gering",
    "sg:classifiers":[
        {
            "category":"Home & Garden",
            "subcategory":"Furniture",
            "type":"Retail Goods"
        }
    ],
    "sg:phone":"+1 308 436 4802",
    "sg:postcode":"69341",
    "sg:province":"NE",
    "sg:tags":[
        "stationery"
    ],
    "wof:name":"Kissack Co",
    "wof:placetype":"venue"
},
  "geometry": {"coordinates":[-103.67236,41.825613],"type":"Point"}
}