{
  "type": "Feature",
  "properties": {
    "addr:full":"13800 Guildford 7 Waverly NE 68462",
    "addr:housenumber":"13800;7",
    "addr:postcode":"68462",
    "addr:street":"Guildford",
    "iso:country":"US",
    "sg:address":"13800 Guildford 7",
    "sg:city":"Waverly",
    "sg:classifiers":[
        {
            "category":"Bars & Pubs",
            "type":"Food & Drink"
        }
    ],
    "sg:menulink":"http://www.allmenus.com/ne/waverly/11061-trackside-bar--grill/menu/",
    "sg:phone":"+1 402 786 2500",
    "sg:postcode":"68462",
    "sg:province":"NE",
    "sg:tags":[
        "american"
    ],
    "wof:name":"Trackside Bar & Grill",
    "wof:placetype":"venue"
},
  "geometry": {"coordinates":[-96.533389,40.913663],"type":"Point"}
}