{
  "type": "Feature",
  "properties": {
    "iso:country":"US",
    "sg:address":"400 S 39th St",
    "sg:city":"Omaha",
    "sg:classifiers":[
        {
            "category":"Social Services",
            "subcategory":"Child Care",
            "type":"Services"
        },
        {
            "category":"Education",
            "subcategory":"Preschool",
            "type":"Public Place"
        },
        {
            "category":"Education",
            "subcategory":"School",
            "type":"Public Place"
        },
        {
            "category":"Education",
            "subcategory":"University",
            "type":"Public Place"
        }
    ],
    "sg:phone":"+1 402 393 1311",
    "sg:postcode":"68131",
    "sg:province":"NE",
    "sg:tags":[
        "high",
        "middle",
        "college",
        "day",
        "elementary"
    ],
    "wof:name":"Montessori Educational Centers Inc",
    "wof:placetype":"venue"
},
  "geometry": {"coordinates":[-95.972099,41.257099],"type":"Point"}
}