{
  "type": "Feature",
  "properties": {
    "addr:full":"804 W Park Dr Chadron NE 69337",
    "addr:housenumber":"804",
    "addr:postcode":"69337",
    "addr:street":"W Park Dr",
    "iso:country":"US",
    "sg:address":"804 W Park Dr",
    "sg:city":"Chadron",
    "sg:classifiers":[
        {
            "category":"Shopping",
            "subcategory":"Bicycles & Sporting Goods",
            "type":"Retail Goods"
        }
    ],
    "sg:phone":"+1 308 432 3601",
    "sg:postcode":"69337",
    "sg:province":"NE",
    "wof:name":"Little Dirt Compny",
    "wof:placetype":"venue"
},
  "geometry": {"coordinates":[-103.00834399999999,42.82315],"type":"Point"}
}