{
  "type": "Feature",
  "properties": {
    "iso:country":"US",
    "sg:address":"880 Country Club Rd",
    "sg:city":"Gering",
    "sg:classifiers":[
        {
            "category":"Farming",
            "subcategory":"Farm & Veterinary Services",
            "type":"Manufacturing & Wholesale Goods"
        }
    ],
    "sg:phone":"+1 308 489 5603",
    "sg:postcode":"69341",
    "sg:province":"NE",
    "sg:tags":[
        "aerial",
        "applicator"
    ],
    "wof:name":"A G Air",
    "wof:placetype":"venue"
},
  "geometry": {"coordinates":[-103.65920300000001,41.841272],"type":"Point"}
}