{
  "type": "Feature",
  "properties": {
    "iso:country":"US",
    "sg:address":"3404 W 13th St",
    "sg:city":"Grand Island",
    "sg:classifiers":[
        {
            "category":"Shopping",
            "subcategory":"Books",
            "type":"Retail Goods"
        }
    ],
    "sg:phone":"+1 308 384 6503",
    "sg:postcode":"68803",
    "sg:province":"NE",
    "sg:tags":[
        "dealer"
    ],
    "wof:name":"Waldenbooks",
    "wof:placetype":"venue"
},
  "geometry": {"coordinates":[-98.384153,40.9316],"type":"Point"}
}