{
  "type": "Feature",
  "properties": {
    "iso:country":"US",
    "sg:address":"3214 N 60th St",
    "sg:city":"Omaha",
    "sg:classifiers":[
        {
            "category":"Organizations",
            "subcategory":"Religious Organization",
            "type":"Services"
        }
    ],
    "sg:phone":"+1 402 553 4376",
    "sg:postcode":"68104",
    "sg:province":"NE",
    "wof:name":"Sheehan Center Facility Dir",
    "wof:placetype":"venue"
},
  "geometry": {"coordinates":[-96.00460099999999,41.288101],"type":"Point"}
}