{
  "type": "Feature",
  "properties": {
    "iso:country":"US",
    "sg:address":"313 W Cedar St",
    "sg:city":"Cedar Bluffs",
    "sg:classifiers":[
        {
            "category":"Farming",
            "subcategory":"Farm",
            "type":"Manufacturing & Wholesale Goods"
        }
    ],
    "sg:phone":"+1 402 628 6355",
    "sg:postcode":"68015",
    "sg:province":"NE",
    "sg:tags":[
        "crop",
        "general"
    ],
    "wof:name":"Lorenzen Family Partnershi",
    "wof:placetype":"venue"
},
  "geometry": {"coordinates":[-96.616641,41.398994],"type":"Point"}
}