{
  "type": "Feature",
  "properties": {
    "addr:full":"623 US Hwy 6 Gretna NE 68028",
    "addr:housenumber":"623",
    "addr:postcode":"68028",
    "addr:street":"Us Hwy 6;Ne",
    "iso:country":"US",
    "sg:address":"623 US Hwy 6",
    "sg:city":"Gretna",
    "sg:classifiers":[
        {
            "category":"Restaurant",
            "type":"Food & Drink"
        }
    ],
    "sg:phone":"+1 402 332 5077",
    "sg:postcode":"68028",
    "sg:province":"NE",
    "sg:tags":[
        "eating"
    ],
    "wof:name":"Subway",
    "wof:placetype":"venue"
},
  "geometry": {"coordinates":[-96.250855,41.131617],"type":"Point"}
}