{
  "type": "Feature",
  "properties": {
    "addr:full":"114 W 3rd St Wilber NE 68465",
    "addr:housenumber":"114",
    "addr:postcode":"68465",
    "addr:street":"W 3Rd St",
    "iso:country":"US",
    "sg:address":"114 W 3rd St",
    "sg:city":"Wilber",
    "sg:classifiers":[
        {
            "category":"Health Services",
            "subcategory":"Doctor",
            "type":"Services"
        }
    ],
    "sg:phone":"+1 402 821 2829",
    "sg:postcode":"68465",
    "sg:province":"NE",
    "sg:tags":[
        "dentist"
    ],
    "wof:name":"Pinkerton Dentistry",
    "wof:placetype":"venue"
},
  "geometry": {"coordinates":[-96.961685,40.481431],"type":"Point"}
}