{
  "type": "Feature",
  "properties": {
    "iso:country":"US",
    "sg:address":"1700 J St",
    "sg:city":"Lincoln",
    "sg:classifiers":[
        {
            "category":"Building & Trades",
            "subcategory":"Construction",
            "type":"Services"
        }
    ],
    "sg:phone":"+1 402 476 6999",
    "sg:postcode":"68508",
    "sg:province":"NE",
    "sg:tags":[
        "contractor"
    ],
    "wof:name":"Bob Peterson",
    "wof:placetype":"venue"
},
  "geometry": {"coordinates":[-96.696011,40.808128],"type":"Point"}
}