{
  "type": "Feature",
  "properties": {
    "iso:country":"US",
    "sg:address":"220 E Nobes Rd",
    "sg:city":"York",
    "sg:classifiers":[
        {
            "category":"Shopping",
            "subcategory":"Department Store",
            "type":"Retail Goods"
        }
    ],
    "sg:phone":"+1 402 362 3366",
    "sg:postcode":"68467",
    "sg:province":"NE",
    "wof:name":"Wal-Mart",
    "wof:placetype":"venue"
},
  "geometry": {"coordinates":[-97.59145700000001,40.857831],"type":"Point"}
}