{
  "type": "Feature",
  "properties": {
    "iso:country":"US",
    "sg:address":"637 Broadway St",
    "sg:city":"Imperial",
    "sg:classifiers":[
        {
            "category":"Government",
            "subcategory":"Police Station",
            "type":"Public Place"
        }
    ],
    "sg:phone":"+1 308 882 4400",
    "sg:postcode":"69033",
    "sg:province":"NE",
    "sg:tags":[
        "department"
    ],
    "wof:name":"Imperial Police Dept",
    "wof:placetype":"venue"
},
  "geometry": {"coordinates":[-101.643035,40.517368],"type":"Point"}
}