{
  "type": "Feature",
  "properties": {
    "addr:full":"904 State Hwy 14 Aurora NE 68818",
    "addr:housenumber":"904",
    "addr:postcode":"68818",
    "addr:street":"State Hwy 14",
    "iso:country":"US",
    "sg:address":"904 State Hwy 14",
    "sg:city":"Aurora",
    "sg:classifiers":[
        {
            "category":"Autos & Motor Vehicles",
            "subcategory":"Fuel & Gas Station",
            "type":"Retail Goods"
        }
    ],
    "sg:phone":"+1 402 694 5223",
    "sg:postcode":"68818",
    "sg:province":"NE",
    "wof:name":"Fast Fuel",
    "wof:placetype":"venue"
},
  "geometry": {"coordinates":[-97.99706399999999,40.814263],"type":"Point"}
}