{
  "type": "Feature",
  "properties": {
    "iso:country":"US",
    "sg:address":"8240 Cody Dr",
    "sg:city":"Lincoln",
    "sg:classifiers":[
        {
            "category":"Home & Garden",
            "subcategory":"Building Materials",
            "type":"Retail Goods"
        }
    ],
    "sg:phone":"+1 402 420 7155",
    "sg:postcode":"68512",
    "sg:province":"NE",
    "sg:tags":[
        "shower",
        "door",
        "enclosure"
    ],
    "wof:name":"Glass Edge",
    "wof:placetype":"venue"
},
  "geometry": {"coordinates":[-96.69804499999999,40.728003],"type":"Point"}
}