{
  "type": "Feature",
  "properties": {
    "addr:full":"1818 O St Ord NE 68862",
    "addr:housenumber":"1818",
    "addr:postcode":"68862",
    "addr:street":"O St",
    "iso:country":"US",
    "sg:address":"1818 O St",
    "sg:city":"Ord",
    "sg:classifiers":[
        {
            "category":"Social Services",
            "subcategory":"Child Care",
            "type":"Services"
        }
    ],
    "sg:phone":"+1 308 728 5037",
    "sg:postcode":"68862",
    "sg:province":"NE",
    "sg:tags":[
        "day"
    ],
    "wof:name":"Benda Nicole Day Care",
    "wof:placetype":"venue"
},
  "geometry": {"coordinates":[-98.932849,41.600442],"type":"Point"}
}