{
  "type": "Feature",
  "properties": {
    "iso:country":"US",
    "sg:address":"607 Sunrise Ct",
    "sg:city":"Plattsmouth",
    "sg:classifiers":[
        {
            "category":"Real Estate",
            "subcategory":"Real Estate Agent",
            "type":"Services"
        }
    ],
    "sg:phone":"+1 402 296 2133",
    "sg:postcode":"68048",
    "sg:province":"NE",
    "sg:tags":[
        "inspection"
    ],
    "wof:name":"Home Imspection Svc",
    "wof:placetype":"venue"
},
  "geometry": {"coordinates":[-95.885434,41.021531],"type":"Point"}
}