{
  "type": "Feature",
  "properties": {
    "iso:country":"US",
    "sg:address":"9613 Maple Dr",
    "sg:city":"Omaha",
    "sg:classifiers":[
        {
            "category":"Real Estate",
            "subcategory":"Real Estate Agent",
            "type":"Services"
        }
    ],
    "sg:phone":"+1 402 393 2060",
    "sg:postcode":"68134",
    "sg:province":"NE",
    "wof:name":"T R Properties",
    "wof:placetype":"venue"
},
  "geometry": {"coordinates":[-96.062411,41.283357],"type":"Point"}
}