{
  "type": "Feature",
  "properties": {
    "addr:full":"7800 Serum Ave Ralston NE 68127",
    "addr:housenumber":"7800",
    "addr:postcode":"68127",
    "addr:street":"Serum Ave",
    "iso:country":"US",
    "sg:address":"7800 Serum Ave",
    "sg:city":"Ralston",
    "sg:classifiers":[
        {
            "category":"Manufacturing",
            "subcategory":"Tools & Machinery",
            "type":"Manufacturing & Wholesale Goods"
        }
    ],
    "sg:phone":"+1 402 339 7600",
    "sg:postcode":"68127",
    "sg:province":"NE",
    "sg:tags":[
        "apparatus"
    ],
    "wof:name":"Harold K Scholz & Co",
    "wof:placetype":"venue"
},
  "geometry": {"coordinates":[-96.040514,41.197894],"type":"Point"}
}