{
  "type": "Feature",
  "properties": {
    "addr:full":"1512 N Lincoln Ave York NE 68467",
    "addr:housenumber":"1512",
    "addr:postcode":"68467",
    "addr:street":"N Lincoln Ave",
    "iso:country":"US",
    "sg:address":"1512 N Lincoln Ave",
    "sg:city":"York",
    "sg:classifiers":[
        {
            "category":"Personal",
            "subcategory":"Beauty Salon",
            "type":"Services"
        }
    ],
    "sg:phone":"+1 402 362 4153",
    "sg:postcode":"68467",
    "sg:province":"NE",
    "wof:name":"Town & Country Beauty Salon",
    "wof:placetype":"venue"
},
  "geometry": {"coordinates":[-97.592973,40.875438],"type":"Point"}
}