{
  "type": "Feature",
  "properties": {
    "iso:country":"US",
    "sg:address":"602 Barrington Cir",
    "sg:city":"Papillion",
    "sg:classifiers":[
        {
            "category":"Health Services",
            "subcategory":"Doctor",
            "type":"Services"
        }
    ],
    "sg:phone":"+1 402 339 2540",
    "sg:postcode":"68046",
    "sg:province":"NE",
    "wof:name":"Dale R Fredstrom DDS PC",
    "wof:placetype":"venue"
},
  "geometry": {"coordinates":[-96.04930400000001,41.13411],"type":"Point"}
}