{
  "type": "Feature",
  "properties": {
    "iso:country":"US",
    "sg:address":"108 N 4th St",
    "sg:city":"Plattsmouth",
    "sg:classifiers":[
        {
            "category":"Personal",
            "subcategory":"Beauty Salon",
            "type":"Services"
        }
    ],
    "sg:phone":"+1 402 296 3100",
    "sg:postcode":"68048",
    "sg:province":"NE",
    "wof:name":"Clips",
    "wof:placetype":"venue"
},
  "geometry": {"coordinates":[-95.883894,41.011256],"type":"Point"}
}