{
  "type": "Feature",
  "properties": {
    "iso:country":"US",
    "sg:address":"518 Rd C",
    "sg:city":"Schuyler",
    "sg:phone":"+1 402 352 3349",
    "sg:postcode":"68661",
    "sg:province":"NE",
    "sg:tags":[
        "farm",
        "corn",
        "soybean"
    ],
    "wof:name":"Richard Wolta",
    "wof:placetype":"venue"
},
  "geometry": {"coordinates":[-97.070514,41.423725],"type":"Point"}
}