{
  "type": "Feature",
  "properties": {
    "iso:country":"US",
    "sg:address":"4101 N 6th St",
    "sg:city":"Beatrice",
    "sg:classifiers":[
        {
            "category":"Banks & Credit Unions",
            "subcategory":"Bank",
            "type":"Services"
        }
    ],
    "sg:phone":"+1 402 223 2385",
    "sg:postcode":"68310",
    "sg:province":"NE",
    "sg:tags":[
        "loan"
    ],
    "wof:name":"Farm Credit Svc Of America",
    "wof:placetype":"venue"
},
  "geometry": {"coordinates":[-96.74696400000001,40.306261],"type":"Point"}
}