{
  "type": "Feature",
  "properties": {
    "iso:country":"US",
    "sg:address":"2401 Fairfield St",
    "sg:city":"Lincoln",
    "sg:classifiers":[
        {
            "category":"Autos & Motor Vehicles",
            "subcategory":"Automobile Sales",
            "type":"Retail Goods"
        }
    ],
    "sg:phone":"+1 402 477 4426",
    "sg:postcode":"68521",
    "sg:province":"NE",
    "sg:tags":[
        "car",
        "dealer"
    ],
    "wof:name":"Mid America Motors",
    "wof:placetype":"venue"
},
  "geometry": {"coordinates":[-96.69033399999999,40.847632],"type":"Point"}
}