{
  "type": "Feature",
  "properties": {
    "iso:country":"US",
    "sg:address":"1317 Rd 15",
    "sg:city":"Geneva",
    "sg:phone":"+1 402 759 4822",
    "sg:postcode":"68361",
    "sg:province":"NE",
    "sg:tags":[
        "farm",
        "soybean"
    ],
    "wof:name":"Don Kimbrough Jr",
    "wof:placetype":"venue"
},
  "geometry": {"coordinates":[-97.558629,40.532335],"type":"Point"}
}