{
  "type": "Feature",
  "properties": {
    "iso:country":"US",
    "sg:address":"707 S 13th St",
    "sg:city":"Tekamah",
    "sg:classifiers":[
        {
            "category":"Manufacturing",
            "subcategory":"Printing",
            "type":"Manufacturing & Wholesale Goods"
        }
    ],
    "sg:phone":"+1 402 374 2226",
    "sg:postcode":"68061",
    "sg:province":"NE",
    "sg:tags":[
        "newspaper"
    ],
    "sg:website":"www.midwestmessenger.com",
    "wof:name":"Midwest Messenger",
    "wof:placetype":"venue"
},
  "geometry": {"coordinates":[-96.221283,41.771568],"type":"Point"}
}