{
  "type": "Feature",
  "properties": {
    "iso:country":"US",
    "sg:address":"13941 S Plz",
    "sg:city":"Omaha",
    "sg:classifiers":[
        {
            "category":"Shopping",
            "subcategory":"Used Merchandise",
            "type":"Retail Goods"
        }
    ],
    "sg:phone":"+1 402 894 5532",
    "sg:postcode":"68137",
    "sg:province":"NE",
    "sg:tags":[
        "shop",
        "thrift"
    ],
    "wof:name":"Thrift World",
    "wof:placetype":"venue"
},
  "geometry": {"coordinates":[-96.131793,41.20302],"type":"Point"}
}