{
  "type": "Feature",
  "properties": {
    "iso:country":"US",
    "sg:address":"914 W Koenig St",
    "sg:city":"Grand Island",
    "sg:classifiers":[
        {
            "category":"Building & Trades",
            "subcategory":"Construction",
            "type":"Services"
        }
    ],
    "sg:phone":"+1 308 384 6074",
    "sg:postcode":"68801",
    "sg:province":"NE",
    "sg:tags":[
        "hanging",
        "painter",
        "contractor"
    ],
    "wof:name":"M V P-Marty Vlach Painting",
    "wof:placetype":"venue"
},
  "geometry": {"coordinates":[-98.34643,40.918777],"type":"Point"}
}