{
  "type": "Feature",
  "properties": {
    "iso:country":"US",
    "sg:address":"2711 Maris Ln",
    "sg:city":"North Platte",
    "sg:classifiers":[
        {
            "category":"Building & Trades",
            "subcategory":"Construction",
            "type":"Services"
        }
    ],
    "sg:phone":"+1 308 534 3983",
    "sg:postcode":"69101",
    "sg:province":"NE",
    "sg:tags":[
        "house"
    ],
    "wof:name":"Kos Construction",
    "wof:placetype":"venue"
},
  "geometry": {"coordinates":[-100.780514,41.109806],"type":"Point"}
}