{
  "type": "Feature",
  "properties": {
    "iso:country":"US",
    "sg:address":"14610 Woodstock Blvd",
    "sg:city":"Waverly",
    "sg:classifiers":[
        {
            "category":"Manufacturing",
            "subcategory":"Tools & Machinery",
            "type":"Manufacturing & Wholesale Goods"
        }
    ],
    "sg:phone":"+1 402 786 3013",
    "sg:postcode":"68462",
    "sg:province":"NE",
    "sg:tags":[
        "filter"
    ],
    "wof:name":"Vanguard Industries",
    "wof:placetype":"venue"
},
  "geometry": {"coordinates":[-96.523709,40.919214],"type":"Point"}
}