{
  "type": "Feature",
  "properties": {
    "iso:country":"US",
    "sg:address":"512 W 6th St",
    "sg:city":"Neligh",
    "sg:classifiers":[
        {
            "category":"Building & Trades",
            "subcategory":"Construction",
            "type":"Services"
        }
    ],
    "sg:phone":"+1 402 887 4481",
    "sg:postcode":"68756",
    "sg:province":"NE",
    "sg:tags":[
        "contractor"
    ],
    "wof:name":"Tunink Arland Construction",
    "wof:placetype":"venue"
},
  "geometry": {"coordinates":[-98.03581,42.130666],"type":"Point"}
}