{
  "type": "Feature",
  "properties": {
    "addr:full":"2827 S 88th St Omaha NE 68124",
    "addr:housenumber":"2827",
    "addr:postcode":"68124",
    "addr:street":"S 88Th St",
    "iso:country":"US",
    "sg:address":"2827 S 88th St",
    "sg:city":"Omaha",
    "sg:classifiers":[
        {
            "category":"Social Services",
            "type":"Services"
        }
    ],
    "sg:phone":"+1 402 390 2342",
    "sg:postcode":"68124",
    "sg:province":"NE",
    "sg:tags":[
        "counselor",
        "marriage",
        "family"
    ],
    "wof:name":"Partusch Counseling Svc",
    "wof:placetype":"venue"
},
  "geometry": {"coordinates":[-96.050743,41.23284],"type":"Point"}
}