{
  "type": "Feature",
  "properties": {
    "iso:country":"US",
    "sg:address":"3201 Crown Pointe Rd",
    "sg:city":"Lincoln",
    "sg:classifiers":[
        {
            "category":"Real Estate",
            "subcategory":"Architect",
            "type":"Services"
        }
    ],
    "sg:phone":"+1 402 488 4484",
    "sg:postcode":"68506",
    "sg:province":"NE",
    "sg:tags":[
        "architectural"
    ],
    "wof:name":"Signature Kitchens Of Lincoln",
    "wof:placetype":"venue"
},
  "geometry": {"coordinates":[-96.608746,40.778554],"type":"Point"}
}