{
  "type": "Feature",
  "properties": {
    "iso:country":"US",
    "sg:address":"106 N Dewey St",
    "sg:city":"North Platte",
    "sg:classifiers":[
        {
            "category":"Building & Trades",
            "subcategory":"Construction",
            "type":"Services"
        }
    ],
    "sg:phone":"+1 308 532 8939",
    "sg:postcode":"69101",
    "sg:province":"NE",
    "sg:tags":[
        "concrete",
        "contractor"
    ],
    "wof:name":"Alcorps Inc",
    "wof:placetype":"venue"
},
  "geometry": {"coordinates":[-100.76257,41.134365],"type":"Point"}
}