{
  "type": "Feature",
  "properties": {
    "addr:full":"608 Meridian Ave Cozad NE 69130",
    "addr:housenumber":"608",
    "addr:postcode":"69130",
    "addr:street":"Meridian Ave",
    "iso:country":"US",
    "sg:address":"608 Meridian Ave",
    "sg:city":"Cozad",
    "sg:classifiers":[
        {
            "category":"Bars & Pubs",
            "type":"Food & Drink"
        }
    ],
    "sg:phone":"+1 308 784 5300",
    "sg:postcode":"69130",
    "sg:province":"NE",
    "sg:tags":[
        "drinking"
    ],
    "wof:name":"Legal Limits",
    "wof:placetype":"venue"
},
  "geometry": {"coordinates":[-99.985834,40.858413],"type":"Point"}
}