{
  "type": "Feature",
  "properties": {
    "iso:country":"US",
    "sg:address":"1515 Abbott Dr",
    "sg:city":"Omaha",
    "sg:classifiers":[
        {
            "category":"Ferry",
            "type":"Transportation"
        }
    ],
    "sg:phone":"+1 402 342 7827",
    "sg:postcode":"68110",
    "sg:province":"NE",
    "sg:tags":[
        "boat"
    ],
    "wof:name":"River City Star",
    "wof:placetype":"venue"
},
  "geometry": {"coordinates":[-95.920417,41.272792],"type":"Point"}
}