{
  "type": "Feature",
  "properties": {
    "iso:country":"US",
    "sg:address":"4101 Woolworth Ave",
    "sg:city":"Omaha",
    "sg:classifiers":[
        {
            "category":"Shopping",
            "subcategory":"Used Merchandise",
            "type":"Retail Goods"
        }
    ],
    "sg:phone":"+1 402 346 9552",
    "sg:postcode":"68105",
    "sg:province":"NE",
    "sg:tags":[
        "shop",
        "thrift"
    ],
    "wof:name":"Goodwill Grounds Maintenance",
    "wof:placetype":"venue"
},
  "geometry": {"coordinates":[-95.97579399999999,41.245128],"type":"Point"}
}