{
  "type": "Feature",
  "properties": {
    "iso:country":"US",
    "sg:address":"210 Main St",
    "sg:city":"Beemer",
    "sg:classifiers":[
        {
            "category":"Shopping",
            "subcategory":"Books",
            "type":"Retail Goods"
        }
    ],
    "sg:phone":"+1 402 528 3388",
    "sg:postcode":"68716",
    "sg:province":"NE",
    "wof:name":"Carlson Renae",
    "wof:placetype":"venue"
},
  "geometry": {"coordinates":[-96.811744,41.929591],"type":"Point"}
}