{
  "type": "Feature",
  "properties": {
    "iso:country":"US",
    "sg:address":"2609 S 120th St",
    "sg:city":"Omaha",
    "sg:classifiers":[
        {
            "category":"Bars & Pubs",
            "type":"Food & Drink"
        }
    ],
    "sg:phone":"+1 402 502 5656",
    "sg:postcode":"68144",
    "sg:province":"NE",
    "wof:name":"No Where Bar",
    "wof:placetype":"venue"
},
  "geometry": {"coordinates":[-96.100622,41.234094],"type":"Point"}
}