{
  "type": "Feature",
  "properties": {
    "iso:country":"US",
    "sg:address":"1006 S 74th Plz",
    "sg:city":"Omaha",
    "sg:classifiers":[
        {
            "category":"Manufacturing",
            "subcategory":"Printing",
            "type":"Manufacturing & Wholesale Goods"
        }
    ],
    "sg:phone":"+1 402 391 7038",
    "sg:postcode":"68114",
    "sg:province":"NE",
    "sg:tags":[
        "printer"
    ],
    "wof:name":"Insty-Prints",
    "wof:placetype":"venue"
},
  "geometry": {"coordinates":[-96.027854,41.250673],"type":"Point"}
}