{
  "type": "Feature",
  "properties": {
    "addr:full":"14725 Spaulding St Omaha NE 68116",
    "addr:housenumber":"14725",
    "addr:postcode":"68116",
    "addr:street":"Spaulding St",
    "iso:country":"US",
    "sg:address":"14725 Spaulding St",
    "sg:city":"Omaha",
    "sg:classifiers":[
        {
            "category":"Social Services",
            "subcategory":"Child Care",
            "type":"Services"
        }
    ],
    "sg:phone":"+1 402 963 9724",
    "sg:postcode":"68116",
    "sg:province":"NE",
    "sg:tags":[
        "day"
    ],
    "wof:name":"Cindys Day Care",
    "wof:placetype":"venue"
},
  "geometry": {"coordinates":[-96.144809,41.293826],"type":"Point"}
}