{
  "type": "Feature",
  "properties": {
    "iso:country":"US",
    "sg:address":"130 W Benton St",
    "sg:city":"Lincoln",
    "sg:classifiers":[
        {
            "category":"Travel",
            "subcategory":"Hotels & Motels",
            "type":"Entertainment"
        }
    ],
    "sg:phone":"+1 402 441 1248",
    "sg:postcode":"68521",
    "sg:province":"NE",
    "wof:name":"Apple Jack of Nebraska Inc",
    "wof:placetype":"venue"
},
  "geometry": {"coordinates":[-96.721549,40.850356],"type":"Point"}
}