{
  "type": "Feature",
  "properties": {
    "addr:full":"1317 W 2nd St Grand Island NE 68801",
    "addr:housenumber":"1317",
    "addr:postcode":"68801",
    "addr:street":"W 2Nd St",
    "iso:country":"US",
    "sg:address":"1317 W 2nd St",
    "sg:city":"Grand Island",
    "sg:classifiers":[
        {
            "category":"Restaurant",
            "type":"Food & Drink"
        }
    ],
    "sg:menulink":"http://www.allmenus.com/ne/grand-island/194459-mcdonalds/menu/",
    "sg:phone":"+1 308 382 3323",
    "sg:postcode":"68801",
    "sg:province":"NE",
    "sg:tags":[
        "burger",
        "american"
    ],
    "wof:name":"McDonald's",
    "wof:placetype":"venue"
},
  "geometry": {"coordinates":[-98.352707,40.919498],"type":"Point"}
}