{
  "type": "Feature",
  "properties": {
    "iso:country":"US",
    "sg:address":"903 S 40th St",
    "sg:city":"Omaha",
    "sg:classifiers":[
        {
            "category":"Wholesale",
            "subcategory":"Office Equipment",
            "type":"Manufacturing & Wholesale Goods"
        }
    ],
    "sg:phone":"+1 402 342 4955",
    "sg:postcode":"68105",
    "sg:province":"NE",
    "sg:tags":[
        "register",
        "cash",
        "supply"
    ],
    "wof:name":"Larson Paper Products",
    "wof:placetype":"venue"
},
  "geometry": {"coordinates":[-95.973299,41.250008],"type":"Point"}
}