{
  "type": "Feature",
  "properties": {
    "iso:country":"US",
    "sg:address":"426 N Webster St",
    "sg:city":"Red Cloud",
    "sg:classifiers":[
        {
            "category":"Food & Beverages",
            "subcategory":"Groceries & Convenience Stores",
            "type":"Retail Goods"
        }
    ],
    "sg:phone":"+1 402 746 2422",
    "sg:postcode":"68970",
    "sg:province":"NE",
    "sg:tags":[
        "grocer"
    ],
    "wof:name":"Farmers Co-Op Assn",
    "wof:placetype":"venue"
},
  "geometry": {"coordinates":[-98.519228,40.089576],"type":"Point"}
}