{
  "type": "Feature",
  "properties": {
    "iso:country":"US",
    "sg:address":"148 S 15th St",
    "sg:city":"Ord",
    "sg:classifiers":[
        {
            "category":"Autos & Motor Vehicles",
            "subcategory":"Fuel & Gas Station",
            "type":"Retail Goods"
        }
    ],
    "sg:phone":"+1 308 728 5531",
    "sg:postcode":"68862",
    "sg:province":"NE",
    "sg:tags":[
        "oil"
    ],
    "wof:name":"Carl's Standard Svc",
    "wof:placetype":"venue"
},
  "geometry": {"coordinates":[-98.92807000000001,41.602581],"type":"Point"}
}