{
  "type": "Feature",
  "properties": {
    "addr:full":"7204 Jones St Omaha NE 68114",
    "addr:housenumber":"7204",
    "addr:postcode":"68114",
    "addr:street":"Jones St",
    "iso:country":"US",
    "sg:address":"7204 Jones St",
    "sg:city":"Omaha",
    "sg:classifiers":[
        {
            "category":"Retail",
            "subcategory":"Photofinishing",
            "type":"Services"
        }
    ],
    "sg:phone":"+1 402 397 7210",
    "sg:postcode":"68114",
    "sg:province":"NE",
    "sg:tags":[
        "plant",
        "processing",
        "film"
    ],
    "wof:name":"Qualex",
    "wof:placetype":"venue"
},
  "geometry": {"coordinates":[-96.02900200000001,41.254082],"type":"Point"}
}