{
  "type": "Feature",
  "properties": {
    "iso:country":"US",
    "sg:address":"2760 South St",
    "sg:city":"Lincoln",
    "sg:classifiers":[
        {
            "category":"Retail",
            "subcategory":"Laundry & Dry Cleaning",
            "type":"Services"
        }
    ],
    "sg:phone":"+1 402 421 8072",
    "sg:postcode":"68502",
    "sg:province":"NE",
    "sg:tags":[
        "drycleaning",
        "plant"
    ],
    "wof:name":"Kennys Dry Cleaners",
    "wof:placetype":"venue"
},
  "geometry": {"coordinates":[-96.68113,40.791759],"type":"Point"}
}