{
  "type": "Feature",
  "properties": {
    "iso:country":"US",
    "sg:address":"17740 N 2nd St",
    "sg:city":"Davey",
    "sg:classifiers":[
        {
            "category":"Bars & Pubs",
            "type":"Food & Drink"
        }
    ],
    "sg:phone":"+1 402 785 3835",
    "sg:postcode":"68336",
    "sg:province":"NE",
    "wof:name":"Davey Tavern",
    "wof:placetype":"venue"
},
  "geometry": {"coordinates":[-96.668745,40.98518],"type":"Point"}
}