{
  "type": "Feature",
  "properties": {
    "iso:country":"US",
    "sg:address":"275 W Lowry Rd",
    "sg:city":"Doniphan",
    "sg:classifiers":[
        {
            "category":"Wholesale",
            "subcategory":"Machinery & Supplies",
            "type":"Manufacturing & Wholesale Goods"
        }
    ],
    "sg:phone":"+1 402 845 6685",
    "sg:postcode":"68832",
    "sg:province":"NE",
    "sg:tags":[
        "animal",
        "trailer"
    ],
    "wof:name":"Schuppan's Trailer Sales",
    "wof:placetype":"venue"
},
  "geometry": {"coordinates":[-98.347711,40.799948],"type":"Point"}
}