{
  "type": "Feature",
  "properties": {
    "iso:country":"US",
    "sg:address":"8301 Davey Rd",
    "sg:city":"Lincoln",
    "sg:phone":"+1 402 785 7885",
    "sg:postcode":"68517",
    "sg:province":"NE",
    "sg:tags":[
        "farm",
        "corn"
    ],
    "wof:name":"Jerry Minchow",
    "wof:placetype":"venue"
},
  "geometry": {"coordinates":[-96.609855,40.98679],"type":"Point"}
}