{
  "type": "Feature",
  "properties": {
    "iso:country":"US",
    "sg:address":"3605 Q St",
    "sg:city":"Omaha",
    "sg:classifiers":[
        {
            "category":"Professional",
            "subcategory":"Management & Consulting",
            "type":"Services"
        },
        {
            "category":"Government",
            "subcategory":"Office",
            "type":"Public Place"
        }
    ],
    "sg:phone":"+1 402 546 1013",
    "sg:postcode":"68107",
    "sg:province":"NE",
    "sg:tags":[
        "personnel",
        "housing",
        "agency",
        "consultant"
    ],
    "wof:name":"Family Housing Advisory Svcs",
    "wof:placetype":"venue"
},
  "geometry": {"coordinates":[-95.96936700000001,41.205312],"type":"Point"}
}