{
  "type": "Feature",
  "properties": {
    "iso:country":"US",
    "sg:address":"1280 Quince Ave",
    "sg:city":"Crete",
    "sg:classifiers":[
        {
            "category":"Shopping",
            "type":"Retail Goods"
        }
    ],
    "sg:phone":"+1 402 440 0976",
    "sg:postcode":"68333",
    "sg:province":"NE",
    "sg:tags":[
        "hearing",
        "equipment",
        "supply",
        "impaired"
    ],
    "wof:name":"Hearing Health Care Ctr",
    "wof:placetype":"venue"
},
  "geometry": {"coordinates":[-96.96618100000001,40.624752],"type":"Point"}
}