{
  "type": "Feature",
  "properties": {
    "iso:country":"US",
    "sg:address":"14025 Dutch Hall Rd",
    "sg:city":"Bennington",
    "sg:classifiers":[
        {
            "category":"Building & Trades",
            "subcategory":"Landscaping Services",
            "type":"Services"
        }
    ],
    "sg:phone":"+1 402 238 2684",
    "sg:postcode":"68007",
    "sg:province":"NE",
    "sg:tags":[
        "tree"
    ],
    "wof:name":"Webbs Tree Farm",
    "wof:placetype":"venue"
},
  "geometry": {"coordinates":[-96.13015300000001,41.393141],"type":"Point"}
}