{
  "type": "Feature",
  "properties": {
    "addr:full":"3308 Langenheder St Grand Island NE 68801",
    "addr:housenumber":"3308",
    "addr:postcode":"68801",
    "addr:street":"Langenheder St",
    "iso:country":"US",
    "sg:address":"3308 Langenheder St",
    "sg:city":"Grand Island",
    "sg:classifiers":[
        {
            "category":"Shopping",
            "subcategory":"Clothing, Apparel, & Fashions",
            "type":"Retail Goods"
        }
    ],
    "sg:phone":"+1 308 384 4720",
    "sg:postcode":"68801",
    "sg:province":"NE",
    "sg:tags":[
        "lingerie"
    ],
    "wof:name":"Doctor John's Lingerie Btq",
    "wof:placetype":"venue"
},
  "geometry": {"coordinates":[-98.380216,40.888643],"type":"Point"}
}