{
  "type": "Feature",
  "properties": {
    "iso:country":"US",
    "sg:address":"113 Neff St",
    "sg:city":"Scribner",
    "sg:classifiers":[
        {
            "category":"Freight",
            "type":"Transportation"
        }
    ],
    "sg:phone":"+1 402 664 2582",
    "sg:postcode":"68057",
    "sg:province":"NE",
    "sg:tags":[
        "building",
        "house",
        "mover"
    ],
    "wof:name":"Lange Movers",
    "wof:placetype":"venue"
},
  "geometry": {"coordinates":[-96.675631,41.665855],"type":"Point"}
}