{
  "type": "Feature",
  "properties": {
    "addr:full":"4026 Hamilton St Omaha NE 68131",
    "addr:housenumber":"4026",
    "addr:postcode":"68131",
    "addr:street":"Hamilton St",
    "iso:country":"US",
    "sg:address":"4026 Hamilton St",
    "sg:city":"Omaha",
    "sg:classifiers":[
        {
            "category":"Building & Trades",
            "subcategory":"Plumbing",
            "type":"Services"
        }
    ],
    "sg:phone":"+1 402 827 5700",
    "sg:postcode":"68131",
    "sg:province":"NE",
    "sg:tags":[
        "conditioning",
        "air",
        "system",
        "contractor"
    ],
    "wof:name":"Baker Heating & Cooling",
    "wof:placetype":"venue"
},
  "geometry": {"coordinates":[-95.97369,41.272217],"type":"Point"}
}