{
  "type": "Feature",
  "properties": {
    "iso:country":"US",
    "sg:address":"1350 Ohio St",
    "sg:city":"Fremont",
    "sg:classifiers":[
        {
            "category":"Organizations",
            "subcategory":"Labor Organization",
            "type":"Services"
        }
    ],
    "sg:phone":"+1 402 721 9065",
    "sg:postcode":"68025",
    "sg:province":"NE",
    "wof:name":"Brotherhood of Maintenance",
    "wof:placetype":"venue"
},
  "geometry": {"coordinates":[-96.517894,41.453076],"type":"Point"}
}