{
  "type": "Feature",
  "properties": {
    "addr:full":"2740 N 27th St Lincoln NE 68521",
    "addr:housenumber":"2740",
    "addr:postcode":"68521",
    "addr:street":"N 27Th St",
    "iso:country":"US",
    "sg:address":"2740 N 27th St",
    "sg:city":"Lincoln",
    "sg:classifiers":[
        {
            "category":"Wholesale",
            "subcategory":"Construction Materials",
            "type":"Manufacturing & Wholesale Goods"
        }
    ],
    "sg:phone":"+1 402 467 2596",
    "sg:postcode":"68521",
    "sg:province":"NE",
    "wof:name":"Binswinger Glass",
    "wof:placetype":"venue"
},
  "geometry": {"coordinates":[-96.682309,40.841025],"type":"Point"}
}