{
  "type": "Feature",
  "properties": {
    "iso:country":"US",
    "sg:address":"4827 Pioneers Blvd",
    "sg:city":"Lincoln",
    "sg:classifiers":[
        {
            "category":"Professional",
            "subcategory":"Engineering",
            "type":"Services"
        }
    ],
    "sg:phone":"+1 402 484 7342",
    "sg:postcode":"68506",
    "sg:province":"NE",
    "sg:tags":[
        "engineer"
    ],
    "wof:name":"Rega Engineering Group Inc",
    "wof:placetype":"venue"
},
  "geometry": {"coordinates":[-96.65290299999999,40.769686],"type":"Point"}
}