{
  "type": "Feature",
  "properties": {
    "addr:full":"7211 Farnam St Omaha NE 68114",
    "addr:housenumber":"7211",
    "addr:postcode":"68114",
    "addr:street":"Farnam St",
    "iso:country":"US",
    "sg:address":"7211 Farnam St",
    "sg:city":"Omaha",
    "sg:classifiers":[
        {
            "category":"Restaurant",
            "type":"Food & Drink"
        }
    ],
    "sg:phone":"+1 402 397 4778",
    "sg:postcode":"68114",
    "sg:province":"NE",
    "sg:tags":[
        "eating"
    ],
    "wof:name":"LA Hacienda",
    "wof:placetype":"venue"
},
  "geometry": {"coordinates":[-96.025858,41.257875],"type":"Point"}
}