{
  "type": "Feature",
  "properties": {
    "iso:country":"US",
    "sg:address":"500 Ridge St",
    "sg:city":"Dawson",
    "sg:classifiers":[
        {
            "category":"Retail",
            "subcategory":"Auto Repair",
            "type":"Services"
        }
    ],
    "sg:phone":"+1 402 855 2765",
    "sg:postcode":"68337",
    "sg:province":"NE",
    "sg:tags":[
        "repairing",
        "automobile"
    ],
    "wof:name":"Larry's Auto Svc",
    "wof:placetype":"venue"
},
  "geometry": {"coordinates":[-95.83064400000001,40.132023],"type":"Point"}
}