{
  "type": "Feature",
  "properties": {
    "iso:country":"US",
    "sg:address":"411 G St",
    "sg:city":"Central City",
    "sg:classifiers":[
        {
            "category":"Home & Garden",
            "subcategory":"Household Appliances",
            "type":"Retail Goods"
        }
    ],
    "sg:phone":"+1 308 946 2299",
    "sg:postcode":"68826",
    "sg:province":"NE",
    "wof:name":"J & J TV Appliance & Sewing",
    "wof:placetype":"venue"
},
  "geometry": {"coordinates":[-98.00311600000001,41.115],"type":"Point"}
}