{
  "type": "Feature",
  "properties": {
    "iso:country":"US",
    "sg:address":"16365 Z St",
    "sg:city":"Omaha",
    "sg:classifiers":[
        {
            "category":"Autos & Motor Vehicles",
            "subcategory":"Fuel & Gas Station",
            "type":"Retail Goods"
        }
    ],
    "sg:phone":"+1 402 895 4305",
    "sg:postcode":"68135",
    "sg:province":"NE",
    "sg:tags":[
        "station",
        "gasoline"
    ],
    "wof:name":"Bova Shell LLC",
    "wof:placetype":"venue"
},
  "geometry": {"coordinates":[-96.17207399999999,41.197473],"type":"Point"}
}