{
  "type": "Feature",
  "properties": {
    "iso:country":"US",
    "sg:address":"1306 W 3rd St",
    "sg:city":"Grand Island",
    "sg:classifiers":[
        {
            "category":"Professional",
            "subcategory":"Employment Agencies",
            "type":"Services"
        }
    ],
    "sg:phone":"+1 308 385 0640",
    "sg:postcode":"68801",
    "sg:province":"NE",
    "wof:name":"Desi Job Corp",
    "wof:placetype":"venue"
},
  "geometry": {"coordinates":[-98.353241,40.920505],"type":"Point"}
}