{
  "type": "Feature",
  "properties": {
    "addr:full":"316 Ogden St Oxford NE 68967",
    "addr:housenumber":"316",
    "addr:postcode":"68967",
    "addr:street":"Ogden St",
    "iso:country":"US",
    "sg:address":"316 Ogden St",
    "sg:city":"Oxford",
    "sg:classifiers":[
        {
            "category":"Social Services",
            "type":"Services"
        }
    ],
    "sg:phone":"+1 308 824 3878",
    "sg:postcode":"68967",
    "sg:province":"NE",
    "sg:tags":[
        "senior",
        "citizen"
    ],
    "wof:name":"Golden Generation Ctr Inc",
    "wof:placetype":"venue"
},
  "geometry": {"coordinates":[-99.63355799999999,40.249326],"type":"Point"}
}