{
  "type": "Feature",
  "properties": {
    "iso:country":"US",
    "sg:address":"701 N Silber Ave",
    "sg:city":"North Platte",
    "sg:classifiers":[
        {
            "category":"Social Services",
            "subcategory":"Child Care",
            "type":"Services"
        }
    ],
    "sg:phone":"+1 308 534 5261",
    "sg:postcode":"69101",
    "sg:province":"NE",
    "sg:tags":[
        "day"
    ],
    "wof:name":"Inhome Day Care Center",
    "wof:placetype":"venue"
},
  "geometry": {"coordinates":[-100.753394,41.140827],"type":"Point"}
}