{
  "type": "Feature",
  "properties": {
    "iso:country":"US",
    "sg:address":"1621 Paul St",
    "sg:city":"Grand Island",
    "sg:classifiers":[
        {
            "category":"Building & Trades",
            "subcategory":"Construction",
            "type":"Services"
        }
    ],
    "sg:phone":"+1 308 381 0813",
    "sg:postcode":"68873",
    "sg:province":"NE",
    "sg:tags":[
        "house"
    ],
    "wof:name":"JD Homes LLC",
    "wof:placetype":"venue"
},
  "geometry": {"coordinates":[-98.46964800000001,41.220482],"type":"Point"}
}