{
  "type": "Feature",
  "properties": {
    "iso:country":"US",
    "sg:address":"7541 Boone Trl",
    "sg:city":"Lincoln",
    "sg:classifiers":[
        {
            "category":"Building & Trades",
            "subcategory":"Construction",
            "type":"Services"
        }
    ],
    "sg:phone":"+1 402 421 7541",
    "sg:postcode":"68516",
    "sg:province":"NE",
    "sg:tags":[
        "contractor"
    ],
    "wof:name":"C S Construction",
    "wof:placetype":"venue"
},
  "geometry": {"coordinates":[-96.617467,40.733768],"type":"Point"}
}