{
  "type": "Feature",
  "properties": {
    "addr:full":"108 E 2nd St North Platte NE 69101",
    "addr:housenumber":"108",
    "addr:postcode":"69101",
    "addr:street":"E 2Nd St",
    "iso:country":"US",
    "sg:address":"108 E 2nd St",
    "sg:city":"North Platte",
    "sg:classifiers":[
        {
            "category":"Social Services",
            "type":"Services"
        }
    ],
    "sg:phone":"+1 308 534 9271",
    "sg:postcode":"69101",
    "sg:province":"NE",
    "wof:name":"Cornerstone Counseling",
    "wof:placetype":"venue"
},
  "geometry": {"coordinates":[-100.763609,41.134481],"type":"Point"}
}