{
  "type": "Feature",
  "properties": {
    "iso:country":"US",
    "sg:address":"246 Main St",
    "sg:city":"Stapleton",
    "sg:classifiers":[
        {
            "category":"Bars & Pubs",
            "type":"Food & Drink"
        }
    ],
    "sg:phone":"+1 308 636 2509",
    "sg:postcode":"69163",
    "sg:province":"NE",
    "wof:name":"Wagon Wheel Bar & Cafe",
    "wof:placetype":"venue"
},
  "geometry": {"coordinates":[-100.51304399999999,41.481515],"type":"Point"}
}