{
  "type": "Feature",
  "properties": {
    "addr:full":"119 W 19th St Kearney NE 68847",
    "addr:housenumber":"119",
    "addr:postcode":"68847",
    "addr:street":"W 19Th St",
    "iso:country":"US",
    "sg:address":"119 W 19th St",
    "sg:city":"Kearney",
    "sg:classifiers":[
        {
            "category":"Manufacturing",
            "subcategory":"Rubber & Plastics",
            "type":"Manufacturing & Wholesale Goods"
        }
    ],
    "sg:phone":"+1 308 236 5025",
    "sg:postcode":"68847",
    "sg:province":"NE",
    "sg:tags":[
        "product"
    ],
    "sg:website":"www.sandhillplastics.com",
    "wof:name":"Sandhill Plastics",
    "wof:placetype":"venue"
},
  "geometry": {"coordinates":[-99.083381,40.693545],"type":"Point"}
}