{
  "type": "Feature",
  "properties": {
    "addr:full":"12797 Q St Omaha NE 68137",
    "addr:housenumber":"12797",
    "addr:postcode":"68137",
    "addr:street":"Q St",
    "iso:country":"US",
    "sg:address":"12797 Q St",
    "sg:city":"Omaha",
    "sg:classifiers":[
        {
            "category":"Personal",
            "subcategory":"Beauty Salon",
            "type":"Services"
        }
    ],
    "sg:phone":"+1 402 896 9110",
    "sg:postcode":"68137",
    "sg:province":"NE",
    "sg:tags":[
        "shop"
    ],
    "wof:name":"A Cut On Q",
    "wof:placetype":"venue"
},
  "geometry": {"coordinates":[-96.11440399999999,41.205101],"type":"Point"}
}