{
  "type": "Feature",
  "properties": {
    "iso:country":"US",
    "sg:address":"14518 Oak St",
    "sg:city":"Omaha",
    "sg:classifiers":[
        {
            "category":"Professional",
            "subcategory":"Business Services",
            "type":"Services"
        }
    ],
    "sg:phone":"+1 402 333 9533",
    "sg:postcode":"68144",
    "sg:province":"NE",
    "wof:name":"Scarlet Thread Embroidery Inc",
    "wof:placetype":"venue"
},
  "geometry": {"coordinates":[-96.14148900000001,41.231372],"type":"Point"}
}