{
  "type": "Feature",
  "properties": {
    "addr:full":"1220 E 4th St North Platte NE 69101",
    "addr:housenumber":"1220",
    "addr:postcode":"69101",
    "addr:street":"E 4Th St",
    "iso:country":"US",
    "sg:address":"1220 E 4th St",
    "sg:city":"North Platte",
    "sg:classifiers":[
        {
            "category":"Restaurant",
            "type":"Food & Drink"
        }
    ],
    "sg:phone":"+1 308 532 8200",
    "sg:postcode":"69101",
    "sg:province":"NE",
    "wof:name":"Merricks Ranch House",
    "wof:placetype":"venue"
},
  "geometry": {"coordinates":[-100.749551,41.134631],"type":"Point"}
}