{
  "type": "Feature",
  "properties": {
    "addr:full":"3421 N 35th St Lincoln NE 68504",
    "addr:housenumber":"3421",
    "addr:postcode":"68504",
    "addr:street":"N 35Th St",
    "iso:country":"US",
    "sg:address":"3421 N 35th St",
    "sg:city":"Lincoln",
    "sg:classifiers":[
        {
            "category":"Manufacturing",
            "subcategory":"Signs",
            "type":"Manufacturing & Wholesale Goods"
        }
    ],
    "sg:phone":"+1 402 466 7446",
    "sg:postcode":"68504",
    "sg:province":"NE",
    "sg:tags":[
        "sheet",
        "metalwork",
        "m",
        "specialty",
        "mfg"
    ],
    "sg:website":"www.capitolsignco.com",
    "wof:name":"Capitol Sign Co",
    "wof:placetype":"venue"
},
  "geometry": {"coordinates":[-96.670765,40.847576],"type":"Point"}
}