{
  "type": "Feature",
  "properties": {
    "addr:full":"210 S Reed St Beatrice NE 68310",
    "addr:housenumber":"210",
    "addr:postcode":"68310",
    "addr:street":"S Reed St",
    "iso:country":"US",
    "sg:address":"210 S Reed St",
    "sg:city":"Beatrice",
    "sg:classifiers":[
        {
            "category":"Government",
            "subcategory":"Office",
            "type":"Public Place"
        }
    ],
    "sg:phone":"+1 402 223 4340",
    "sg:postcode":"68310",
    "sg:province":"NE",
    "sg:tags":[
        "state",
        "security"
    ],
    "wof:name":"National Guard Armory",
    "wof:placetype":"venue"
},
  "geometry": {"coordinates":[-96.784412,40.252945],"type":"Point"}
}