{
  "type": "Feature",
  "properties": {
    "iso:country":"US",
    "sg:address":"850 N 27th St",
    "sg:city":"Lincoln",
    "sg:classifiers":[
        {
            "category":"Shopping",
            "subcategory":"Used Merchandise",
            "type":"Retail Goods"
        }
    ],
    "sg:phone":"+1 402 474 2065",
    "sg:postcode":"68503",
    "sg:province":"NE",
    "wof:name":"One More Time Furniture",
    "wof:placetype":"venue"
},
  "geometry": {"coordinates":[-96.682159,40.820828],"type":"Point"}
}