{
  "type": "Feature",
  "properties": {
    "addr:full":"6012 Wenninghoff Rd Omaha NE 68134",
    "addr:housenumber":"6012",
    "addr:postcode":"68134",
    "addr:street":"Wenninghoff Rd",
    "iso:country":"US",
    "sg:address":"6012 Wenninghoff Rd",
    "sg:city":"Omaha",
    "sg:classifiers":[
        {
            "category":"Personal",
            "subcategory":"Barber",
            "type":"Services"
        }
    ],
    "sg:phone":"+1 402 572 0525",
    "sg:postcode":"68134",
    "sg:province":"NE",
    "sg:tags":[
        "shop"
    ],
    "wof:name":"Viking Barber Shop",
    "wof:placetype":"venue"
},
  "geometry": {"coordinates":[-96.04644500000001,41.312718],"type":"Point"}
}