{
  "type": "Feature",
  "properties": {
    "iso:country":"US",
    "sg:address":"72345 573rd Ave",
    "sg:city":"Plymouth",
    "sg:phone":"+1 402 656 4794",
    "sg:postcode":"68424",
    "sg:province":"NE",
    "sg:tags":[
        "farm",
        "soybean"
    ],
    "wof:name":"Bradley L Grummert",
    "wof:placetype":"venue"
},
  "geometry": {"coordinates":[-97.085955,40.312496],"type":"Point"}
}