{
  "type": "Feature",
  "properties": {
    "addr:full":"127 N Lexington Ave Hastings NE 68901",
    "addr:housenumber":"127",
    "addr:postcode":"68901",
    "addr:street":"N Lexington Ave",
    "iso:country":"US",
    "sg:address":"127 N Lexington Ave",
    "sg:city":"Hastings",
    "sg:classifiers":[
        {
            "category":"Health Services",
            "subcategory":"Medical Lab",
            "type":"Services"
        }
    ],
    "sg:phone":"+1 402 463 2960",
    "sg:postcode":"68901",
    "sg:province":"NE",
    "sg:tags":[
        "laboratory"
    ],
    "wof:name":"Hastings Dental Ceramics",
    "wof:placetype":"venue"
},
  "geometry": {"coordinates":[-98.393856,40.58499],"type":"Point"}
}