{
  "type": "Feature",
  "properties": {
    "iso:country":"US",
    "sg:address":"4343 S 67th St",
    "sg:city":"Omaha",
    "sg:classifiers":[
        {
            "category":"Building & Trades",
            "subcategory":"Equipment Rental",
            "type":"Services"
        }
    ],
    "sg:phone":"+1 402 592 3668",
    "sg:postcode":"68117",
    "sg:province":"NE",
    "sg:tags":[
        "crane"
    ],
    "sg:website":"www.americancranerental.com",
    "wof:name":"American Crane Rental",
    "wof:placetype":"venue"
},
  "geometry": {"coordinates":[-96.01546999999999,41.217677],"type":"Point"}
}