{
  "type": "Feature",
  "properties": {
    "addr:full":"113 Clark St Bassett NE 68714",
    "addr:housenumber":"113",
    "addr:postcode":"68714",
    "addr:street":"Clark St",
    "iso:country":"US",
    "sg:address":"113 Clark St",
    "sg:city":"Bassett",
    "sg:classifiers":[
        {
            "category":"Shopping",
            "type":"Retail Goods"
        }
    ],
    "sg:phone":"+1 402 684 3346",
    "sg:postcode":"68714",
    "sg:province":"NE",
    "sg:tags":[
        "product",
        "wood"
    ],
    "wof:name":"Niobrara Valley Wood Products",
    "wof:placetype":"venue"
},
  "geometry": {"coordinates":[-99.537851,42.586603],"type":"Point"}
}