{
  "type": "Feature",
  "properties": {
    "iso:country":"US",
    "sg:address":"5901 NW Radial Hwy",
    "sg:city":"Omaha",
    "sg:classifiers":[
        {
            "category":"Banks & Credit Unions",
            "subcategory":"Bank",
            "type":"Services"
        }
    ],
    "sg:phone":"+1 402 551 7300",
    "sg:postcode":"68104",
    "sg:province":"NE",
    "wof:name":"Commercial Federal Bank",
    "wof:placetype":"venue"
},
  "geometry": {"coordinates":[-96.003899,41.286098],"type":"Point"}
}