{
  "type": "Feature",
  "properties": {
    "iso:country":"US",
    "sg:address":"832 E Clay St",
    "sg:city":"Oneill",
    "sg:classifiers":[
        {
            "category":"Professional",
            "subcategory":"Computer Services",
            "type":"Services"
        }
    ],
    "sg:phone":"+1 402 336 3147",
    "sg:postcode":"68763",
    "sg:province":"NE",
    "sg:tags":[
        "repair"
    ],
    "wof:name":"Yesterday's Technology",
    "wof:placetype":"venue"
},
  "geometry": {"coordinates":[-98.64108,42.458991],"type":"Point"}
}