{
  "type": "Feature",
  "properties": {
    "iso:country":"US",
    "sg:address":"902 Eastridge St",
    "sg:city":"Norfolk",
    "sg:classifiers":[
        {
            "category":"Wholesale",
            "subcategory":"Stationery",
            "type":"Manufacturing & Wholesale Goods"
        }
    ],
    "sg:phone":"+1 402 371 4766",
    "sg:postcode":"68701",
    "sg:province":"NE",
    "sg:tags":[
        "container",
        "plastic"
    ],
    "wof:name":"Tupperware",
    "wof:placetype":"venue"
},
  "geometry": {"coordinates":[-97.38428999999999,42.04248],"type":"Point"}
}