{
  "type": "Feature",
  "properties": {
    "iso:country":"US",
    "sg:address":"2791 Co Rd 15",
    "sg:city":"Cedar Bluffs",
    "sg:phone":"+1 402 628 5615",
    "sg:postcode":"68015",
    "sg:province":"NE",
    "sg:tags":[
        "farm",
        "corn",
        "soybean"
    ],
    "wof:name":"Ed Simanek",
    "wof:placetype":"venue"
},
  "geometry": {"coordinates":[-96.56892499999999,41.407699],"type":"Point"}
}