{
  "type": "Feature",
  "properties": {
    "iso:country":"US",
    "sg:address":"1345 S Cotner Blvd",
    "sg:city":"Lincoln",
    "sg:classifiers":[
        {
            "category":"Government",
            "subcategory":"Fire Station",
            "type":"Public Place"
        }
    ],
    "sg:phone":"+1 402 441 8377",
    "sg:postcode":"68510",
    "sg:province":"NE",
    "sg:tags":[
        "department"
    ],
    "wof:name":"Lincoln Fire Dept",
    "wof:placetype":"venue"
},
  "geometry": {"coordinates":[-96.651084,40.799267],"type":"Point"}
}