{
  "type": "Feature",
  "properties": {
    "iso:country":"US",
    "sg:address":"2705 Randolph St",
    "sg:city":"Lincoln",
    "sg:classifiers":[
        {
            "category":"Personal",
            "subcategory":"Beauty Salon",
            "type":"Services"
        }
    ],
    "sg:phone":"+1 402 476 3078",
    "sg:postcode":"68510",
    "sg:province":"NE",
    "sg:tags":[
        "shop"
    ],
    "wof:name":"New Image",
    "wof:placetype":"venue"
},
  "geometry": {"coordinates":[-96.681236,40.806208],"type":"Point"}
}