{
  "type": "Feature",
  "properties": {
    "iso:country":"US",
    "sg:address":"119 E A St",
    "sg:city":"Ogallala",
    "sg:classifiers":[
        {
            "category":"Autos & Motor Vehicles",
            "subcategory":"Auto Supplies",
            "type":"Retail Goods"
        }
    ],
    "sg:phone":"+1 308 284 3664",
    "sg:postcode":"69153",
    "sg:province":"NE",
    "sg:tags":[
        "automobile",
        "parts"
    ],
    "wof:name":"A-One Supply",
    "wof:placetype":"venue"
},
  "geometry": {"coordinates":[-101.71793599999999,41.125663],"type":"Point"}
}