{
  "type": "Feature",
  "properties": {
    "iso:country":"US",
    "sg:address":"123 S Webb Rd",
    "sg:city":"Grand Island",
    "sg:classifiers":[
        {
            "category":"Education",
            "subcategory":"School",
            "type":"Public Place"
        }
    ],
    "sg:phone":"+1 308 385 5900",
    "sg:postcode":"68803",
    "sg:province":"NE",
    "sg:website":"www.gi.esu10.k12.ne.us",
    "wof:name":"School District Of Grand Is",
    "wof:placetype":"venue"
},
  "geometry": {"coordinates":[-98.378356,40.916864],"type":"Point"}
}