{
  "type": "Feature",
  "properties": {
    "iso:country":"US",
    "sg:address":"324 Grand Ave",
    "sg:city":"Ravenna",
    "sg:classifiers":[
        {
            "category":"Professional",
            "type":"Services"
        }
    ],
    "sg:phone":"+1 308 452 3501",
    "sg:postcode":"68869",
    "sg:province":"NE",
    "sg:tags":[
        "establishment"
    ],
    "wof:name":"Micro R & D Inc",
    "wof:placetype":"venue"
},
  "geometry": {"coordinates":[-98.912781,41.026049],"type":"Point"}
}