{
  "type": "Feature",
  "properties": {
    "iso:country":"US",
    "sg:address":"18 E 22nd St",
    "sg:city":"Kearney",
    "sg:classifiers":[
        {
            "category":"Government",
            "subcategory":"Office",
            "type":"Public Place"
        }
    ],
    "sg:phone":"+1 308 233 3213",
    "sg:postcode":"68847",
    "sg:province":"NE",
    "sg:tags":[
        "village"
    ],
    "sg:website":"www.cityofkearney.org",
    "wof:name":"Kearney Finance & Adm",
    "wof:placetype":"venue"
},
  "geometry": {"coordinates":[-99.08156,40.697695],"type":"Point"}
}