{
  "type": "Feature",
  "properties": {
    "iso:country":"US",
    "sg:address":"248 N 129th St",
    "sg:city":"Omaha",
    "sg:classifiers":[
        {
            "category":"Health Services",
            "subcategory":"Doctor",
            "type":"Services"
        }
    ],
    "sg:phone":"+1 402 334 7964",
    "sg:postcode":"68154",
    "sg:province":"NE",
    "sg:tags":[
        "physician",
        "surgeon"
    ],
    "wof:name":"Richard J Holcomb MD",
    "wof:placetype":"venue"
},
  "geometry": {"coordinates":[-96.113581,41.260587],"type":"Point"}
}