{
  "type": "Feature",
  "properties": {
    "iso:country":"US",
    "sg:address":"28105 115th Rd",
    "sg:city":"Kearney",
    "sg:classifiers":[
        {
            "category":"Retail",
            "subcategory":"Animal Services",
            "type":"Services"
        }
    ],
    "sg:phone":"+1 308 234 3317",
    "sg:postcode":"68845",
    "sg:province":"NE",
    "wof:name":"Country Care Kennels",
    "wof:placetype":"venue"
},
  "geometry": {"coordinates":[-99.09372399999999,40.786262],"type":"Point"}
}