{
  "type": "Feature",
  "properties": {
    "iso:country":"US",
    "sg:address":"8715 Oak St",
    "sg:city":"Omaha",
    "sg:classifiers":[
        {
            "category":"Banks & Credit Unions",
            "subcategory":"Bank",
            "type":"Services"
        }
    ],
    "sg:phone":"+1 402 934 1300",
    "sg:postcode":"68124",
    "sg:province":"NE",
    "sg:tags":[
        "broker",
        "mortgage"
    ],
    "wof:name":"First Switzerland Financial",
    "wof:placetype":"venue"
},
  "geometry": {"coordinates":[-96.049234,41.231856],"type":"Point"}
}