{
  "type": "Feature",
  "properties": {
    "iso:country":"US",
    "sg:address":"2031 G Ave",
    "sg:city":"Dakota City",
    "sg:classifiers":[
        {
            "category":"Freight",
            "type":"Transportation"
        }
    ],
    "sg:phone":"+1 402 987 3873",
    "sg:postcode":"68731",
    "sg:province":"NE",
    "sg:tags":[
        "operator",
        "local",
        "trucking"
    ],
    "wof:name":"Heikes Trucking Inc",
    "wof:placetype":"venue"
},
  "geometry": {"coordinates":[-96.48271099999999,42.374556],"type":"Point"}
}