{
  "type": "Feature",
  "properties": {
    "iso:country":"US",
    "sg:address":"17402 W Maple Rd",
    "sg:city":"Omaha",
    "sg:classifiers":[
        {
            "category":"Autos & Motor Vehicles",
            "subcategory":"Motorcycle Sales",
            "type":"Retail Goods"
        }
    ],
    "sg:phone":"+1 402 289 5556",
    "sg:postcode":"68116",
    "sg:province":"NE",
    "sg:tags":[
        "scooter"
    ],
    "wof:name":"Dillon Brothers Harley Dvdsn",
    "wof:placetype":"venue"
},
  "geometry": {"coordinates":[-96.187183,41.292116],"type":"Point"}
}