{
  "type": "Feature",
  "properties": {
    "iso:country":"US",
    "sg:address":"31st Avenue & Dodge",
    "sg:city":"Omaha",
    "sg:classifiers":[
        {
            "category":"Health Services",
            "subcategory":"Doctor",
            "type":"Services"
        }
    ],
    "sg:phone":"+1 402 346 1111",
    "sg:postcode":"68102",
    "sg:province":"NE",
    "sg:tags":[
        "medicine",
        "sport",
        "orthopedist"
    ],
    "wof:name":"Park Plaza Clinic",
    "wof:placetype":"venue"
},
  "geometry": {"coordinates":[-95.937202,41.257198],"type":"Point"}
}