{
  "type": "Feature",
  "properties": {
    "iso:country":"US",
    "sg:address":"1819 Farnam St",
    "sg:city":"Omaha",
    "sg:classifiers":[
        {
            "category":"Government",
            "subcategory":"Court House",
            "type":"Public Place"
        }
    ],
    "sg:phone":"+1 402 444 7194",
    "sg:postcode":"68102",
    "sg:province":"NE",
    "wof:name":"Douglas County Register Deeds",
    "wof:placetype":"venue"
},
  "geometry": {"coordinates":[-95.94096,41.257546],"type":"Point"}
}