{
  "type": "Feature",
  "properties": {
    "iso:country":"US",
    "sg:address":"6042 Havelock Ave",
    "sg:city":"Lincoln",
    "sg:classifiers":[
        {
            "category":"Shopping",
            "subcategory":"Bicycles & Sporting Goods",
            "type":"Retail Goods"
        }
    ],
    "sg:phone":"+1 402 464 4388",
    "sg:postcode":"68507",
    "sg:province":"NE",
    "sg:tags":[
        "equipment",
        "sauna",
        "supply"
    ],
    "wof:name":"Health Mate",
    "wof:placetype":"venue"
},
  "geometry": {"coordinates":[-96.637615,40.857136],"type":"Point"}
}