{
  "type": "Feature",
  "properties": {
    "iso:country":"US",
    "sg:address":"517 D St",
    "sg:city":"Fairbury",
    "sg:classifiers":[
        {
            "category":"Sports & Exercise",
            "subcategory":"Bowling",
            "type":"Entertainment"
        }
    ],
    "sg:phone":"+1 402 729 3670",
    "sg:postcode":"68352",
    "sg:province":"NE",
    "sg:tags":[
        "center"
    ],
    "wof:name":"Pla Mor Lanes",
    "wof:placetype":"venue"
},
  "geometry": {"coordinates":[-97.181355,40.137076],"type":"Point"}
}