{
  "type": "Feature",
  "properties": {
    "iso:country":"US",
    "sg:address":"4451 N 26th St",
    "sg:city":"Lincoln",
    "sg:classifiers":[
        {
            "category":"Utilities",
            "subcategory":"Mobile Phone",
            "type":"Services"
        }
    ],
    "sg:phone":"+1 402 477 2300",
    "sg:postcode":"68521",
    "sg:province":"NE",
    "sg:tags":[
        "telephone",
        "cellular"
    ],
    "wof:name":"AAA Wireless Solutions-Nextel",
    "wof:placetype":"venue"
},
  "geometry": {"coordinates":[-96.68403600000001,40.856338],"type":"Point"}
}