{
  "type": "Feature",
  "properties": {
    "addr:full":"15757 C W Hadan Dr Bennington NE 68007",
    "addr:housenumber":"15757",
    "addr:postcode":"68007",
    "addr:street":"C W Hadan Dr",
    "iso:country":"US",
    "sg:address":"15757 C W Hadan Dr",
    "sg:city":"Bennington",
    "sg:classifiers":[
        {
            "category":"Restaurant",
            "type":"Food & Drink"
        }
    ],
    "sg:menulink":"http://www.allmenus.com/ne/jefferson/155568-runza/menu/",
    "sg:phone":"+1 402 991 7118",
    "sg:postcode":"68007",
    "sg:province":"NE",
    "sg:tags":[
        "wrap",
        "american",
        "sandwich"
    ],
    "wof:name":"Runza",
    "wof:placetype":"venue"
},
  "geometry": {"coordinates":[-96.160079,41.372057],"type":"Point"}
}