{
  "type": "Feature",
  "properties": {
    "iso:country":"US",
    "sg:address":"4503 S 90th St",
    "sg:city":"Omaha",
    "sg:classifiers":[
        {
            "category":"Shopping",
            "type":"Retail Goods"
        },
        {
            "category":"Manufacturing",
            "subcategory":"Electronics",
            "type":"Manufacturing & Wholesale Goods"
        }
    ],
    "sg:phone":"+1 402 339 5003",
    "sg:postcode":"68127",
    "sg:province":"NE",
    "sg:tags":[
        "machine",
        "equipment"
    ],
    "sg:website":"www.jqoffice.com",
    "wof:name":"J Q Office Equipment",
    "wof:placetype":"venue"
},
  "geometry": {"coordinates":[-96.05251199999999,41.213252],"type":"Point"}
}