{
  "type": "Feature",
  "properties": {
    "iso:country":"US",
    "sg:address":"101 Clark St",
    "sg:city":"Bassett",
    "sg:classifiers":[
        {
            "category":"Home & Garden",
            "subcategory":"Building Materials",
            "type":"Retail Goods"
        }
    ],
    "sg:phone":"+1 402 684 3961",
    "sg:postcode":"68714",
    "sg:province":"NE",
    "sg:tags":[
        "lumber"
    ],
    "wof:name":"William Krotter Co",
    "wof:placetype":"venue"
},
  "geometry": {"coordinates":[-99.53777700000001,42.586751],"type":"Point"}
}