{
  "type": "Feature",
  "properties": {
    "iso:country":"US",
    "sg:address":"6920 Van Dorn St",
    "sg:city":"Lincoln",
    "sg:classifiers":[
        {
            "category":"Health Services",
            "subcategory":"Doctor",
            "type":"Services"
        }
    ],
    "sg:phone":"+1 402 488 4111",
    "sg:postcode":"68506",
    "sg:province":"NE",
    "sg:tags":[
        "physician",
        "surgeon"
    ],
    "wof:name":"Lincoln Psychiatric Group",
    "wof:placetype":"venue"
},
  "geometry": {"coordinates":[-96.626458,40.784363],"type":"Point"}
}