{
  "type": "Feature",
  "properties": {
    "iso:country":"US",
    "sg:address":"111 N 13th St",
    "sg:city":"Tekamah",
    "sg:classifiers":[
        {
            "category":"Government",
            "subcategory":"Office",
            "type":"Public Place"
        }
    ],
    "sg:phone":"+1 402 374 2944",
    "sg:postcode":"68061",
    "sg:province":"NE",
    "wof:name":"Burt County Highway Supt",
    "wof:placetype":"venue"
},
  "geometry": {"coordinates":[-96.220997,41.779205],"type":"Point"}
}