{
  "type": "Feature",
  "properties": {
    "iso:country":"US",
    "sg:address":"42576 Hwy 30",
    "sg:city":"Cozad",
    "sg:classifiers":[
        {
            "category":"Mining & Drilling",
            "type":"Manufacturing & Wholesale Goods"
        }
    ],
    "sg:phone":"+1 308 784 4737",
    "sg:postcode":"69130",
    "sg:province":"NE",
    "sg:tags":[
        "oil",
        "gas",
        "producer"
    ],
    "wof:name":"Lexington Co-Op Oil Co-Darr",
    "wof:placetype":"venue"
},
  "geometry": {"coordinates":[-99.89094900000001,40.821943],"type":"Point"}
}