{
  "type": "Feature",
  "properties": {
    "iso:country":"US",
    "sg:address":"964 N Laurel St",
    "sg:city":"Wahoo",
    "sg:classifiers":[
        {
            "category":"Health Services",
            "subcategory":"Doctor",
            "type":"Services"
        }
    ],
    "sg:phone":"+1 402 443 4141",
    "sg:postcode":"68066",
    "sg:province":"NE",
    "wof:name":"Family Healthcare",
    "wof:placetype":"venue"
},
  "geometry": {"coordinates":[-96.626868,41.215301],"type":"Point"}
}