{
  "type": "Feature",
  "properties": {
    "iso:country":"US",
    "sg:address":"11531 Sahler St",
    "sg:city":"Omaha",
    "sg:classifiers":[
        {
            "category":"Restaurant",
            "type":"Food & Drink"
        }
    ],
    "sg:phone":"+1 402 431 8449",
    "sg:postcode":"68164",
    "sg:province":"NE",
    "sg:tags":[
        "caterer"
    ],
    "wof:name":"Dora's Homemade Mexican",
    "wof:placetype":"venue"
},
  "geometry": {"coordinates":[-96.092502,41.29676],"type":"Point"}
}