{
  "type": "Feature",
  "properties": {
    "addr:full":"13818 N 42nd St Omaha NE 68112",
    "addr:housenumber":"13818",
    "addr:postcode":"68112",
    "addr:street":"N 42Nd St",
    "iso:country":"US",
    "sg:address":"13818 N 42nd St",
    "sg:city":"Omaha",
    "sg:classifiers":[
        {
            "category":"Professional",
            "subcategory":"Accounting & Tax Preparation",
            "type":"Services"
        }
    ],
    "sg:phone":"+1 402 451 2653",
    "sg:postcode":"68112",
    "sg:province":"NE",
    "wof:name":"R J Pillege & Associates",
    "wof:placetype":"venue"
},
  "geometry": {"coordinates":[-95.976051,41.377942],"type":"Point"}
}