{
  "type": "Feature",
  "properties": {
    "iso:country":"US",
    "sg:address":"107 E 2nd St",
    "sg:city":"Laurel",
    "sg:classifiers":[
        {
            "category":"Professional",
            "subcategory":"Business Services",
            "type":"Services"
        }
    ],
    "sg:phone":"+1 402 256 9240",
    "sg:postcode":"68745",
    "sg:province":"NE",
    "sg:tags":[
        "auctioneer"
    ],
    "sg:website":"www.nixonauctioneers.com",
    "wof:name":"Nixon Auctioneers",
    "wof:placetype":"venue"
},
  "geometry": {"coordinates":[-97.091036,42.429604],"type":"Point"}
}