{
  "type": "Feature",
  "properties": {
    "iso:country":"US",
    "sg:address":"305 Norris Ave",
    "sg:city":"Mc Cook",
    "sg:classifiers":[
        {
            "category":"Shopping",
            "type":"Retail Goods"
        },
        {
            "category":"Shopping",
            "subcategory":"Books",
            "type":"Retail Goods"
        }
    ],
    "sg:phone":"+1 308 345 7480",
    "sg:postcode":"69001",
    "sg:province":"NE",
    "sg:tags":[
        "picture",
        "frame"
    ],
    "wof:name":"Accents Etc",
    "wof:placetype":"venue"
},
  "geometry": {"coordinates":[-100.62575099999999,40.2006],"type":"Point"}
}