{
  "type": "Feature",
  "properties": {
    "addr:full":"20138 Roberts St Elkhorn NE 68022",
    "addr:housenumber":"20138",
    "addr:postcode":"68022",
    "addr:street":"Roberts St",
    "iso:country":"US",
    "sg:address":"20138 Roberts St",
    "sg:city":"Elkhorn",
    "sg:classifiers":[
        {
            "category":"Sports & Exercise",
            "subcategory":"Gym",
            "type":"Entertainment"
        }
    ],
    "sg:phone":"+1 402 289 0800",
    "sg:postcode":"68022",
    "sg:province":"NE",
    "sg:tags":[
        "fitness",
        "physical",
        "facility"
    ],
    "wof:name":"Curves For Women",
    "wof:placetype":"venue"
},
  "geometry": {"coordinates":[-96.231104,41.273209],"type":"Point"}
}