{
  "type": "Feature",
  "properties": {
    "iso:country":"US",
    "sg:address":"3939 S 84th St",
    "sg:city":"Omaha",
    "sg:classifiers":[
        {
            "category":"Freight",
            "type":"Transportation"
        }
    ],
    "sg:phone":"+1 402 393 1457",
    "sg:postcode":"68124",
    "sg:province":"NE",
    "sg:tags":[
        "commercial",
        "storage"
    ],
    "wof:name":"Metro Self Storage Inc",
    "wof:placetype":"venue"
},
  "geometry": {"coordinates":[-96.043126,41.22177],"type":"Point"}
}