{
  "type": "Feature",
  "properties": {
    "iso:country":"US",
    "sg:address":"733 Broadway",
    "sg:city":"Decatur",
    "sg:classifiers":[
        {
            "category":"Professional",
            "subcategory":"Business Services",
            "type":"Services"
        }
    ],
    "sg:phone":"+1 402 349 2241",
    "sg:postcode":"68020",
    "sg:province":"NE",
    "sg:tags":[
        "embroidery"
    ],
    "wof:name":"Hard Stitch Embroidery",
    "wof:placetype":"venue"
},
  "geometry": {"coordinates":[-96.249921,42.007147],"type":"Point"}
}