{
  "type": "Feature",
  "properties": {
    "addr:full":"1011 Hale Ave Newman Grove NE 68758",
    "addr:housenumber":"1011",
    "addr:postcode":"68758",
    "addr:street":"Hale Ave Newman Grove Ne",
    "iso:country":"US",
    "sg:address":"1011 Hale Ave",
    "sg:city":"Newman Grove",
    "sg:classifiers":[
        {
            "category":"Organizations",
            "subcategory":"Religious Organization",
            "type":"Services"
        }
    ],
    "sg:phone":"+1 402 447 6322",
    "sg:postcode":"68758",
    "sg:province":"NE",
    "sg:tags":[
        "church"
    ],
    "wof:name":"Fellowship Bible Church",
    "wof:placetype":"venue"
},
  "geometry": {"coordinates":[-97.77124000000001,41.746601],"type":"Point"}
}