{
  "type": "Feature",
  "properties": {
    "addr:full":"112 N 21st St Beatrice NE 68310",
    "addr:housenumber":"112",
    "addr:postcode":"68310",
    "addr:street":"N 21St St",
    "iso:country":"US",
    "sg:address":"112 N 21st St",
    "sg:city":"Beatrice",
    "sg:classifiers":[
        {
            "category":"Manufacturing",
            "subcategory":"Metals",
            "type":"Manufacturing & Wholesale Goods"
        }
    ],
    "sg:phone":"+1 402 223 5316",
    "sg:postcode":"68310",
    "sg:province":"NE",
    "sg:tags":[
        "metalwork",
        "sheet",
        "mfg"
    ],
    "wof:name":"Beatrice Window & Door Co",
    "wof:placetype":"venue"
},
  "geometry": {"coordinates":[-96.725105,40.267758],"type":"Point"}
}