{
  "type": "Feature",
  "properties": {
    "iso:country":"US",
    "sg:address":"11010 Emmet St",
    "sg:city":"Omaha",
    "sg:classifiers":[
        {
            "category":"Autos & Motor Vehicles",
            "subcategory":"Motorcycle Sales",
            "type":"Retail Goods"
        }
    ],
    "sg:phone":"+1 402 556 3333",
    "sg:postcode":"68164",
    "sg:province":"NE",
    "sg:tags":[
        "all",
        "scooter"
    ],
    "sg:website":"www.powersportspro.com",
    "wof:name":"Power Sports Pro",
    "wof:placetype":"venue"
},
  "geometry": {"coordinates":[-96.08364400000001,41.289133],"type":"Point"}
}