{
  "type": "Feature",
  "properties": {
    "iso:country":"US",
    "sg:address":"510 Bordeaux St",
    "sg:city":"Chadron",
    "sg:classifiers":[
        {
            "category":"Organizations",
            "subcategory":"Non-profit Organization",
            "type":"Services"
        }
    ],
    "sg:phone":"+1 308 432 3920",
    "sg:postcode":"69337",
    "sg:province":"NE",
    "sg:tags":[
        "information",
        "alcoholism",
        "treatment"
    ],
    "wof:name":"Crossroads Alcohol & Drug",
    "wof:placetype":"venue"
},
  "geometry": {"coordinates":[-102.99994700000001,42.825439],"type":"Point"}
}