{
  "type": "Feature",
  "properties": {
    "iso:country":"US",
    "sg:address":"411 N Hastings Ave",
    "sg:city":"Hastings",
    "sg:classifiers":[
        {
            "category":"Organizations",
            "subcategory":"Non-profit Organization",
            "type":"Services"
        }
    ],
    "sg:phone":"+1 402 463 1518",
    "sg:postcode":"68901",
    "sg:province":"NE",
    "wof:name":"Masonic Temple",
    "wof:placetype":"venue"
},
  "geometry": {"coordinates":[-98.389943,40.58784],"type":"Point"}
}