{
  "type": "Feature",
  "properties": {
    "addr:full":"13520 Discovery Dr Omaha NE 68137",
    "addr:housenumber":"13520",
    "addr:postcode":"68137",
    "addr:street":"Discovery Dr",
    "iso:country":"US",
    "sg:address":"13520 Discovery Dr",
    "sg:city":"Omaha",
    "sg:classifiers":[
        {
            "category":"Professional",
            "subcategory":"Management & Consulting",
            "type":"Services"
        }
    ],
    "sg:phone":"+1 402 502 3248",
    "sg:postcode":"68137",
    "sg:province":"NE",
    "sg:tags":[
        "consultant",
        "business"
    ],
    "wof:name":"Genesis 10",
    "wof:placetype":"venue"
},
  "geometry": {"coordinates":[-96.12606700000001,41.20238],"type":"Point"}
}