{
  "type": "Feature",
  "properties": {
    "iso:country":"US",
    "sg:address":"428 Lincoln Ave",
    "sg:city":"Hebron",
    "sg:classifiers":[
        {
            "category":"Shopping",
            "subcategory":"Pharmacy",
            "type":"Retail Goods"
        }
    ],
    "sg:phone":"+1 402 768 6319",
    "sg:postcode":"68370",
    "sg:province":"NE",
    "sg:tags":[
        "drug",
        "store"
    ],
    "wof:name":"Priefert Pharmacy Inc",
    "wof:placetype":"venue"
},
  "geometry": {"coordinates":[-97.590006,40.166676],"type":"Point"}
}