{
  "type": "Feature",
  "properties": {
    "iso:country":"US",
    "sg:address":"1612 Stone St",
    "sg:city":"Falls City",
    "sg:classifiers":[
        {
            "category":"Shopping",
            "subcategory":"Catalog Store",
            "type":"Retail Goods"
        }
    ],
    "sg:phone":"+1 402 245 5917",
    "sg:postcode":"68355",
    "sg:province":"NE",
    "sg:tags":[
        "mail",
        "order",
        "internet"
    ],
    "wof:name":"J C Penney Catalog Ctr",
    "wof:placetype":"venue"
},
  "geometry": {"coordinates":[-95.602818,40.061591],"type":"Point"}
}