{
  "type": "Feature",
  "properties": {
    "addr:full":"112 Cityside Dr Wayne NE 68787",
    "addr:housenumber":"112",
    "addr:postcode":"68787",
    "addr:street":"Cityside Dr",
    "iso:country":"US",
    "sg:address":"112 Cityside Dr",
    "sg:city":"Wayne",
    "sg:classifiers":[
        {
            "category":"Social Services",
            "subcategory":"Child Care",
            "type":"Services"
        }
    ],
    "sg:phone":"+1 402 375 2950",
    "sg:postcode":"68787",
    "sg:province":"NE",
    "sg:tags":[
        "day"
    ],
    "wof:name":"Pamela Henderson",
    "wof:placetype":"venue"
},
  "geometry": {"coordinates":[-97.001929,42.233959],"type":"Point"}
}