{
  "type": "Feature",
  "properties": {
    "iso:country":"US",
    "sg:address":"3001 S 144th St",
    "sg:city":"Omaha",
    "sg:classifiers":[
        {
            "category":"Personal",
            "type":"Services"
        }
    ],
    "sg:phone":"+1 402 334 6799",
    "sg:postcode":"68144",
    "sg:province":"NE",
    "sg:tags":[
        "formal",
        "retail",
        "wear",
        "rent"
    ],
    "wof:name":"Desmonds Formal Wear",
    "wof:placetype":"venue"
},
  "geometry": {"coordinates":[-96.138488,41.230833],"type":"Point"}
}