{
  "type": "Feature",
  "properties": {
    "iso:country":"US",
    "sg:address":"8670 Thompson Dr",
    "sg:city":"Blair",
    "sg:classifiers":[
        {
            "category":"Real Estate",
            "subcategory":"Real Estate Operator",
            "type":"Services"
        }
    ],
    "sg:phone":"+1 402 426 2008",
    "sg:postcode":"68008",
    "sg:province":"NE",
    "sg:tags":[
        "mobile",
        "home",
        "community"
    ],
    "wof:name":"Knudson Manufactured Homes",
    "wof:placetype":"venue"
},
  "geometry": {"coordinates":[-96.14242,41.50372],"type":"Point"}
}