{
  "type": "Feature",
  "properties": {
    "iso:country":"US",
    "sg:address":"426 Co Rd L",
    "sg:city":"Oakland",
    "sg:classifiers":[
        {
            "category":"Farming",
            "subcategory":"Farm",
            "type":"Manufacturing & Wholesale Goods"
        }
    ],
    "sg:phone":"+1 402 685 5710",
    "sg:postcode":"68045",
    "sg:province":"NE",
    "sg:tags":[
        "crop",
        "general"
    ],
    "wof:name":"Elwood Johnson",
    "wof:placetype":"venue"
},
  "geometry": {"coordinates":[-96.531386,41.84347],"type":"Point"}
}