{
  "type": "Feature",
  "properties": {
    "iso:country":"US",
    "sg:address":"931 19th St",
    "sg:city":"Columbus",
    "sg:classifiers":[
        {
            "category":"Building & Trades",
            "subcategory":"Construction",
            "type":"Services"
        }
    ],
    "sg:phone":"+1 402 562 8020",
    "sg:postcode":"68601",
    "sg:province":"NE",
    "sg:tags":[
        "concrete",
        "pumping"
    ],
    "wof:name":"Heartland Concrete Placement",
    "wof:placetype":"venue"
},
  "geometry": {"coordinates":[-97.33691,41.434619],"type":"Point"}
}