{
  "type": "Feature",
  "properties": {
    "iso:country":"US",
    "sg:address":"1694 462nd",
    "sg:city":"Utica",
    "sg:classifiers":[
        {
            "category":"Farming",
            "subcategory":"Livestock Farm",
            "type":"Manufacturing & Wholesale Goods"
        }
    ],
    "sg:phone":"+1 402 534 2198",
    "sg:postcode":"68456",
    "sg:province":"NE",
    "sg:tags":[
        "hog",
        "or",
        "feedlot"
    ],
    "wof:name":"Larry Naber",
    "wof:placetype":"venue"
},
  "geometry": {"coordinates":[-97.34949400000001,40.930782],"type":"Point"}
}