{
  "type": "Feature",
  "properties": {
    "addr:full":"5702 S 60th St Omaha NE 68117",
    "addr:housenumber":"5702",
    "addr:postcode":"68117",
    "addr:street":"S 60Th St",
    "iso:country":"US",
    "sg:address":"5702 S 60th St",
    "sg:city":"Omaha",
    "sg:classifiers":[
        {
            "category":"Autos & Motor Vehicles",
            "subcategory":"Auto Supplies",
            "type":"Retail Goods"
        }
    ],
    "sg:phone":"+1 402 734 8274",
    "sg:postcode":"68117",
    "sg:province":"NE",
    "sg:tags":[
        "tire"
    ],
    "wof:name":"A 60th Street Used Tires & Rim",
    "wof:placetype":"venue"
},
  "geometry": {"coordinates":[-96.004943,41.198979],"type":"Point"}
}