{
  "type": "Feature",
  "properties": {
    "iso:country":"US",
    "sg:address":"1471 US Hwy 77",
    "sg:city":"Oakland",
    "sg:phone":"+1 402 685 5975",
    "sg:postcode":"68045",
    "sg:province":"NE",
    "sg:tags":[
        "farm",
        "corn",
        "soybean"
    ],
    "wof:name":"Maurice Moderow",
    "wof:placetype":"venue"
},
  "geometry": {"coordinates":[-96.463256,41.885473],"type":"Point"}
}