{
  "type": "Feature",
  "properties": {
    "addr:full":"47850 Grand Island Rd Ravenna NE 68869",
    "addr:housenumber":"47850",
    "addr:postcode":"68869",
    "addr:street":"Grand Island Rd",
    "iso:country":"US",
    "sg:address":"47850 Grand Island Rd",
    "sg:city":"Ravenna",
    "sg:phone":"+1 308 452 3474",
    "sg:postcode":"68869",
    "sg:province":"NE",
    "sg:tags":[
        "farm",
        "corn"
    ],
    "wof:name":"G Behrendt",
    "wof:placetype":"venue"
},
  "geometry": {"coordinates":[-98.844448,40.916511],"type":"Point"}
}