{
  "type": "Feature",
  "properties": {
    "addr:full":"3001 L St Omaha NE 68107",
    "addr:housenumber":"3001",
    "addr:postcode":"68107",
    "addr:street":"L St",
    "iso:country":"US",
    "sg:address":"3001 L St",
    "sg:city":"Omaha",
    "sg:classifiers":[
        {
            "category":"Wholesale",
            "subcategory":"Meat",
            "type":"Manufacturing & Wholesale Goods"
        }
    ],
    "sg:phone":"+1 402 731 3480",
    "sg:postcode":"68107",
    "sg:province":"NE",
    "sg:tags":[
        "packer"
    ],
    "sg:website":"www.greateromaha.com",
    "wof:name":"Greater Omaha Packing Co-Fab",
    "wof:placetype":"venue"
},
  "geometry": {"coordinates":[-95.95777699999999,41.212288],"type":"Point"}
}