{
  "type": "Feature",
  "properties": {
    "iso:country":"US",
    "sg:address":"3116 156th St",
    "sg:city":"Weeping Water",
    "sg:phone":"+1 402 267 5309",
    "sg:postcode":"68463",
    "sg:province":"NE",
    "sg:tags":[
        "farm",
        "soybean"
    ],
    "wof:name":"Charles Shrader",
    "wof:placetype":"venue"
},
  "geometry": {"coordinates":[-96.15911800000001,40.856608],"type":"Point"}
}