{
  "type": "Feature",
  "properties": {
    "addr:full":"210 Broadway St Butte NE 68722",
    "addr:housenumber":"210",
    "addr:postcode":"68722",
    "addr:street":"Broadway St",
    "iso:country":"US",
    "sg:address":"210 Broadway St",
    "sg:city":"Butte",
    "sg:classifiers":[
        {
            "category":"Health Services",
            "subcategory":"Nursing And Care Facility",
            "type":"Services"
        }
    ],
    "sg:phone":"+1 402 775 2355",
    "sg:postcode":"68722",
    "sg:province":"NE",
    "sg:tags":[
        "home",
        "convalescent"
    ],
    "wof:name":"Butte Healthcare Ctr",
    "wof:placetype":"venue"
},
  "geometry": {"coordinates":[-98.841869,42.915253],"type":"Point"}
}