{
  "type": "Feature",
  "properties": {
    "iso:country":"US",
    "sg:address":"5056 Parkview Dr",
    "sg:city":"Omaha",
    "sg:classifiers":[
        {
            "category":"Real Estate",
            "subcategory":"Real Estate Operator",
            "type":"Services"
        }
    ],
    "sg:phone":"+1 402 573 6358",
    "sg:postcode":"68134",
    "sg:province":"NE",
    "sg:tags":[
        "property",
        "management"
    ],
    "wof:name":"Parkview Partners Inc",
    "wof:placetype":"venue"
},
  "geometry": {"coordinates":[-96.06652099999999,41.304621],"type":"Point"}
}