{
  "type": "Feature",
  "properties": {
    "iso:country":"US",
    "sg:address":"4303 S 90th St",
    "sg:city":"Omaha",
    "sg:classifiers":[
        {
            "category":"Wholesale",
            "subcategory":"Stationery",
            "type":"Manufacturing & Wholesale Goods"
        }
    ],
    "sg:phone":"+1 402 339 0400",
    "sg:postcode":"68127",
    "sg:province":"NE",
    "sg:tags":[
        "distributor",
        "material",
        "computer",
        "printed",
        "manufacturer"
    ],
    "wof:name":"Leading Edge Prtg & Forms Inc",
    "wof:placetype":"venue"
},
  "geometry": {"coordinates":[-96.052564,41.2161],"type":"Point"}
}