{
  "type": "Feature",
  "properties": {
    "iso:country":"US",
    "sg:address":"923 Galvin Rd S",
    "sg:city":"Bellevue",
    "sg:classifiers":[
        {
            "category":"Banks & Credit Unions",
            "subcategory":"Bank",
            "type":"Services"
        }
    ],
    "sg:phone":"+1 402 293 3889",
    "sg:postcode":"68005",
    "sg:province":"NE",
    "wof:name":"Omaha Police Federal Credit",
    "wof:placetype":"venue"
},
  "geometry": {"coordinates":[-95.917959,41.152425],"type":"Point"}
}