{
  "type": "Feature",
  "properties": {
    "iso:country":"US",
    "sg:address":"106 Brookline Dr",
    "sg:city":"Grand Island",
    "sg:classifiers":[
        {
            "category":"Building & Trades",
            "subcategory":"Construction",
            "type":"Services"
        }
    ],
    "sg:phone":"+1 308 381 8055",
    "sg:postcode":"68801",
    "sg:province":"NE",
    "sg:tags":[
        "downspouts",
        "gutter"
    ],
    "wof:name":"Nebraskaland Gutter",
    "wof:placetype":"venue"
},
  "geometry": {"coordinates":[-98.33917599999999,40.898038],"type":"Point"}
}