{
  "type": "Feature",
  "properties": {
    "iso:country":"US",
    "sg:address":"4409 S 134th St",
    "sg:city":"Omaha",
    "sg:classifiers":[
        {
            "category":"Building & Trades",
            "subcategory":"Construction",
            "type":"Services"
        }
    ],
    "sg:phone":"+1 402 991 3162",
    "sg:postcode":"68137",
    "sg:province":"NE",
    "sg:tags":[
        "painter"
    ],
    "wof:name":"Opitz Painting",
    "wof:placetype":"venue"
},
  "geometry": {"coordinates":[-96.12335400000001,41.216498],"type":"Point"}
}