{
  "type": "Feature",
  "properties": {
    "iso:country":"US",
    "sg:address":"206 E 4th St",
    "sg:city":"Ainsworth",
    "sg:classifiers":[
        {
            "category":"Professional",
            "type":"Services"
        }
    ],
    "sg:phone":"+1 402 387 0162",
    "sg:postcode":"69210",
    "sg:province":"NE",
    "wof:name":"Carl Tucker",
    "wof:placetype":"venue"
},
  "geometry": {"coordinates":[-99.86112300000001,42.549968],"type":"Point"}
}