{
  "type": "Feature",
  "properties": {
    "iso:country":"US",
    "sg:address":"6550 S 84th St",
    "sg:city":"Omaha",
    "sg:classifiers":[
        {
            "category":"Professional",
            "subcategory":"Business Services",
            "type":"Services"
        }
    ],
    "sg:phone":"+1 402 331 2770",
    "sg:postcode":"68127",
    "sg:province":"NE",
    "sg:tags":[
        "personal"
    ],
    "wof:name":"Ralston Costume",
    "wof:placetype":"venue"
},
  "geometry": {"coordinates":[-96.043043,41.195016],"type":"Point"}
}