{
  "type": "Feature",
  "properties": {
    "addr:full":"805 9th St Gothenburg NE 69138",
    "addr:housenumber":"805",
    "addr:postcode":"69138",
    "addr:street":"9Th St",
    "iso:country":"US",
    "sg:address":"805 9th St",
    "sg:city":"Gothenburg",
    "sg:classifiers":[
        {
            "category":"Insurance",
            "subcategory":"Insurance Agent",
            "type":"Services"
        }
    ],
    "sg:phone":"+1 308 537 3372",
    "sg:postcode":"69138",
    "sg:province":"NE",
    "wof:name":"Abramson & Assoc Insur",
    "wof:placetype":"venue"
},
  "geometry": {"coordinates":[-100.157353,40.925594],"type":"Point"}
}