{
  "type": "Feature",
  "properties": {
    "iso:country":"US",
    "sg:address":"107 W 2nd St",
    "sg:city":"Oakland",
    "sg:classifiers":[
        {
            "category":"Real Estate",
            "subcategory":"Real Estate Agent",
            "type":"Services"
        }
    ],
    "sg:phone":"+1 402 685 5613",
    "sg:postcode":"68045",
    "sg:province":"NE",
    "sg:tags":[
        "cooperative"
    ],
    "sg:website":"www.cvacoop.com",
    "wof:name":"Central Valley Ag",
    "wof:placetype":"venue"
},
  "geometry": {"coordinates":[-96.467276,41.834437],"type":"Point"}
}