{
  "type": "Feature",
  "properties": {
    "iso:country":"US",
    "sg:address":"6307 N 150th St",
    "sg:city":"Omaha",
    "sg:classifiers":[
        {
            "category":"Banks & Credit Unions",
            "subcategory":"Investment Brokerage",
            "type":"Services"
        }
    ],
    "sg:phone":"+1 402 505 6861",
    "sg:postcode":"68116",
    "sg:province":"NE",
    "sg:tags":[
        "advisory",
        "financial"
    ],
    "wof:name":"Rick Young Financial Svc",
    "wof:placetype":"venue"
},
  "geometry": {"coordinates":[-96.14904300000001,41.315671],"type":"Point"}
}