{
  "type": "Feature",
  "properties": {
    "addr:full":"8001 Brookfield Dr Lincoln NE 68506",
    "addr:housenumber":"8001",
    "addr:postcode":"68506",
    "addr:street":"Brookfield Dr",
    "iso:country":"US",
    "sg:address":"8001 Brookfield Dr",
    "sg:city":"Lincoln",
    "sg:classifiers":[
        {
            "category":"Real Estate",
            "subcategory":"Real Estate Operator",
            "type":"Services"
        }
    ],
    "sg:phone":"+1 402 423 9725",
    "sg:postcode":"68506",
    "sg:province":"NE",
    "sg:tags":[
        "property",
        "lessor"
    ],
    "wof:name":"Universal Management",
    "wof:placetype":"venue"
},
  "geometry": {"coordinates":[-96.610088,40.781776],"type":"Point"}
}