{
  "type": "Feature",
  "properties": {
    "addr:full":"3872 Leavenworth St Omaha NE 68105",
    "addr:housenumber":"3872",
    "addr:postcode":"68105",
    "addr:street":"Leavenworth St",
    "iso:country":"US",
    "sg:address":"3872 Leavenworth St",
    "sg:city":"Omaha",
    "sg:classifiers":[
        {
            "category":"Retail",
            "subcategory":"Laundry & Dry Cleaning",
            "type":"Services"
        }
    ],
    "sg:phone":"+1 402 345 4500",
    "sg:postcode":"68105",
    "sg:province":"NE",
    "sg:tags":[
        "plant"
    ],
    "wof:name":"Armstrong Cleaners and Laundry",
    "wof:placetype":"venue"
},
  "geometry": {"coordinates":[-95.971397,41.252499],"type":"Point"}
}