{
  "type": "Feature",
  "properties": {
    "addr:full":"315 Main St Winside NE 68790",
    "addr:housenumber":"315",
    "addr:postcode":"68790",
    "addr:street":"Main St",
    "iso:country":"US",
    "sg:address":"315 Main St",
    "sg:city":"Winside",
    "sg:classifiers":[
        {
            "category":"Wholesale",
            "subcategory":"Meat",
            "type":"Manufacturing & Wholesale Goods"
        }
    ],
    "sg:phone":"+1 402 286 1010",
    "sg:postcode":"68790",
    "sg:province":"NE",
    "sg:tags":[
        "product"
    ],
    "wof:name":"Thies Family Locker",
    "wof:placetype":"venue"
},
  "geometry": {"coordinates":[-97.178028,42.175878],"type":"Point"}
}