{
  "type": "Feature",
  "properties": {
    "addr:full":"4303 S 70th St Lincoln NE 68516",
    "addr:housenumber":"4303",
    "addr:postcode":"68516",
    "addr:street":"S 70Th St",
    "iso:country":"US",
    "sg:address":"4303 S 70th St",
    "sg:city":"Lincoln",
    "sg:classifiers":[
        {
            "category":"Banks & Credit Unions",
            "subcategory":"Bank",
            "type":"Services"
        }
    ],
    "sg:phone":"+1 402 434 4930",
    "sg:postcode":"68516",
    "sg:province":"NE",
    "sg:website":"www.wellsfargo.com",
    "wof:name":"Wells Fargo Bank",
    "wof:placetype":"venue"
},
  "geometry": {"coordinates":[-96.62538000000001,40.768022],"type":"Point"}
}