{
  "type": "Feature",
  "properties": {
    "iso:country":"US",
    "sg:address":"3175 Leavenworth St",
    "sg:city":"Omaha",
    "sg:classifiers":[
        {
            "category":"Personal",
            "subcategory":"Beauty Salon",
            "type":"Services"
        }
    ],
    "sg:phone":"+1 402 422 0359",
    "sg:postcode":"68105",
    "sg:province":"NE",
    "sg:tags":[
        "hair"
    ],
    "wof:name":"Vega's Beauty Salon",
    "wof:placetype":"venue"
},
  "geometry": {"coordinates":[-95.95966,41.252283],"type":"Point"}
}