{
  "type": "Feature",
  "properties": {
    "addr:full":"42826 Rd 759 Cozad NE 69130",
    "addr:postcode":"42826;69130",
    "addr:street":"Rd 759",
    "iso:country":"US",
    "sg:address":"42826 Rd 759",
    "sg:city":"Cozad",
    "sg:classifiers":[
        {
            "category":"Farming",
            "subcategory":"Livestock Farm",
            "type":"Manufacturing & Wholesale Goods"
        }
    ],
    "sg:phone":"+1 308 324 2363",
    "sg:postcode":"69130",
    "sg:province":"NE",
    "sg:tags":[
        "feed",
        "lot",
        "cattle"
    ],
    "wof:name":"Darr Feedlot Inc",
    "wof:placetype":"venue"
},
  "geometry": {"coordinates":[-99.840819,40.830447],"type":"Point"}
}