{
  "type": "Feature",
  "properties": {
    "iso:country":"US",
    "sg:address":"1221 M St",
    "sg:city":"Aurora",
    "sg:classifiers":[
        {
            "category":"Food & Beverages",
            "subcategory":"Bakery",
            "type":"Retail Goods"
        }
    ],
    "sg:phone":"+1 402 694 2673",
    "sg:postcode":"68818",
    "sg:province":"NE",
    "wof:name":"Cakes By Phyllis",
    "wof:placetype":"venue"
},
  "geometry": {"coordinates":[-98.001586,40.868631],"type":"Point"}
}