{
  "type": "Feature",
  "properties": {
    "iso:country":"US",
    "sg:address":"2665 Farnam St",
    "sg:city":"Omaha",
    "sg:classifiers":[
        {
            "category":"Professional",
            "subcategory":"Management & Consulting",
            "type":"Services"
        }
    ],
    "sg:phone":"+1 402 964 2161",
    "sg:postcode":"68131",
    "sg:province":"NE",
    "wof:name":"4 U Inc",
    "wof:placetype":"venue"
},
  "geometry": {"coordinates":[-95.95116899999999,41.257596],"type":"Point"}
}