{
  "type": "Feature",
  "properties": {
    "addr:full":"406 W 6th St Yankton NE 57078",
    "addr:housenumber":"406",
    "addr:postcode":"57078",
    "addr:street":"W 6Th St",
    "iso:country":"US",
    "sg:address":"406 W 6th St",
    "sg:city":"Yankton",
    "sg:classifiers":[
        {
            "category":"Communications",
            "subcategory":"Film & Video Production",
            "type":"Services"
        }
    ],
    "sg:phone":"+1 605 665 4507",
    "sg:postcode":"57078",
    "sg:province":"NE",
    "sg:tags":[
        "motion"
    ],
    "wof:name":"River Rat Productions",
    "wof:placetype":"venue"
},
  "geometry": {"coordinates":[-97.39854699999999,42.873854],"type":"Point"}
}