{
  "type": "Feature",
  "properties": {
    "iso:country":"US",
    "sg:address":"9405 NW 112th St",
    "sg:city":"Malcolm",
    "sg:classifiers":[
        {
            "category":"Home & Garden",
            "subcategory":"Garden Supply",
            "type":"Retail Goods"
        }
    ],
    "sg:phone":"+1 402 796 2191",
    "sg:postcode":"68402",
    "sg:province":"NE",
    "wof:name":"Sam Hill Gardens",
    "wof:placetype":"venue"
},
  "geometry": {"coordinates":[-96.87236,40.911423],"type":"Point"}
}