{
  "type": "Feature",
  "properties": {
    "iso:country":"US",
    "sg:address":"6124 Military Ave",
    "sg:city":"Omaha",
    "sg:classifiers":[
        {
            "category":"Arts & Performance",
            "subcategory":"Theater",
            "type":"Entertainment"
        }
    ],
    "sg:phone":"+1 402 991 9155",
    "sg:postcode":"68104",
    "sg:province":"NE",
    "wof:name":"Baby D Productions",
    "wof:placetype":"venue"
},
  "geometry": {"coordinates":[-96.008122,41.285241],"type":"Point"}
}