{
  "type": "Feature",
  "properties": {
    "iso:country":"US",
    "sg:address":"1830 Yolande Ave",
    "sg:city":"Lincoln",
    "sg:classifiers":[
        {
            "category":"Autos & Motor Vehicles",
            "subcategory":"Automobile Sales",
            "type":"Retail Goods"
        }
    ],
    "sg:phone":"+1 402 474 1800",
    "sg:postcode":"68521",
    "sg:province":"NE",
    "sg:tags":[
        "car",
        "dealer"
    ],
    "wof:name":"Avenue Motors",
    "wof:placetype":"venue"
},
  "geometry": {"coordinates":[-96.689436,40.840903],"type":"Point"}
}