{
  "type": "Feature",
  "properties": {
    "iso:country":"US",
    "sg:address":"2919 N 84th St",
    "sg:city":"Omaha",
    "sg:classifiers":[
        {
            "category":"Wholesale",
            "subcategory":"Construction Materials",
            "type":"Manufacturing & Wholesale Goods"
        }
    ],
    "sg:phone":"+1 402 571 7031",
    "sg:postcode":"68134",
    "sg:province":"NE",
    "wof:name":"American Builders",
    "wof:placetype":"venue"
},
  "geometry": {"coordinates":[-96.043761,41.28658],"type":"Point"}
}