{
  "type": "Feature",
  "properties": {
    "iso:country":"US",
    "sg:address":"504 W 20th St",
    "sg:city":"Yankton",
    "sg:classifiers":[
        {
            "category":"Freight",
            "type":"Transportation"
        }
    ],
    "sg:phone":"+1 605 665 2399",
    "sg:postcode":"57078",
    "sg:province":"NE",
    "sg:tags":[
        "commercial",
        "storage"
    ],
    "wof:name":"Hansen's Self Storage",
    "wof:placetype":"venue"
},
  "geometry": {"coordinates":[-97.398017,42.888905],"type":"Point"}
}