{
  "type": "Feature",
  "properties": {
    "iso:country":"US",
    "sg:address":"6520 S 118th St",
    "sg:city":"Omaha",
    "sg:classifiers":[
        {
            "category":"Personal",
            "type":"Services"
        },
        {
            "category":"Building & Trades",
            "subcategory":"Construction",
            "type":"Services"
        }
    ],
    "sg:phone":"+1 402 829 0600",
    "sg:postcode":"68137",
    "sg:province":"NE",
    "sg:tags":[
        "repairing",
        "remodeling",
        "contractor"
    ],
    "sg:website":"www.beyondrepairs.com",
    "wof:name":"Beyond Repairs Inc",
    "wof:placetype":"venue"
},
  "geometry": {"coordinates":[-96.095038,41.194261],"type":"Point"}
}