{
  "type": "Feature",
  "properties": {
    "addr:full":"100 S 66th St Lincoln NE 68510",
    "addr:housenumber":"100",
    "addr:postcode":"68510",
    "addr:street":"S 66Th St",
    "iso:country":"US",
    "sg:address":"100 S 66th St",
    "sg:city":"Lincoln",
    "sg:classifiers":[
        {
            "category":"Shopping",
            "subcategory":"Shoes",
            "type":"Retail Goods"
        }
    ],
    "sg:phone":"+1 402 488 8448",
    "sg:postcode":"68510",
    "sg:province":"NE",
    "wof:name":"Payless Shoe Source",
    "wof:placetype":"venue"
},
  "geometry": {"coordinates":[-96.63063699999999,40.812324],"type":"Point"}
}