{
  "type": "Feature",
  "properties": {
    "iso:country":"US",
    "sg:address":"4824 S 135th St",
    "sg:city":"Omaha",
    "sg:classifiers":[
        {
            "category":"Manufacturing",
            "subcategory":"Metals",
            "type":"Manufacturing & Wholesale Goods"
        },
        {
            "category":"Building & Trades",
            "subcategory":"Construction",
            "type":"Services"
        }
    ],
    "sg:phone":"+1 402 895 4774",
    "sg:postcode":"68137",
    "sg:province":"NE",
    "sg:tags":[
        "steel",
        "fabricator",
        "fabrication",
        "welding"
    ],
    "wof:name":"Midwest Metal Works Inc",
    "wof:placetype":"venue"
},
  "geometry": {"coordinates":[-96.12694399999999,41.211532],"type":"Point"}
}