{
  "type": "Feature",
  "properties": {
    "iso:country":"US",
    "sg:address":"728 S C St",
    "sg:city":"Broken Bow",
    "sg:classifiers":[
        {
            "category":"Health Services",
            "subcategory":"Hospital",
            "type":"Services"
        },
        {
            "category":"Social Services",
            "type":"Services"
        }
    ],
    "sg:phone":"+1 308 872 6705",
    "sg:postcode":"68822",
    "sg:province":"NE",
    "sg:tags":[
        "counselor",
        "marriage",
        "mental",
        "family"
    ],
    "wof:name":"Mid-Plains Ctr",
    "wof:placetype":"venue"
},
  "geometry": {"coordinates":[-99.63912999999999,41.403472],"type":"Point"}
}