{
  "type": "Feature",
  "properties": {
    "iso:country":"US",
    "sg:address":"1035 Washington St",
    "sg:city":"Blair",
    "sg:classifiers":[
        {
            "category":"Organizations",
            "subcategory":"Community Association",
            "type":"Services"
        }
    ],
    "sg:phone":"+1 402 426 2526",
    "sg:postcode":"68008",
    "sg:province":"NE",
    "sg:tags":[
        "drinking"
    ],
    "wof:name":"American Legion Lounge",
    "wof:placetype":"venue"
},
  "geometry": {"coordinates":[-96.12695100000001,41.543598],"type":"Point"}
}