{
  "type": "Feature",
  "properties": {
    "addr:full":"2005 1st Ave Kearney NE 68847",
    "addr:housenumber":"2005",
    "addr:postcode":"68847",
    "addr:street":"1St Ave",
    "iso:country":"US",
    "sg:address":"2005 1st Ave",
    "sg:city":"Kearney",
    "sg:classifiers":[
        {
            "category":"Museum",
            "type":"Entertainment"
        }
    ],
    "sg:phone":"+1 308 698 2228",
    "sg:postcode":"68847",
    "sg:province":"NE",
    "wof:name":"Kearney Area Children's Museum",
    "wof:placetype":"venue"
},
  "geometry": {"coordinates":[-99.083057,40.695804],"type":"Point"}
}