{
  "type": "Feature",
  "properties": {
    "iso:country":"US",
    "sg:address":"1000 E 1st St",
    "sg:city":"Papillion",
    "sg:classifiers":[
        {
            "category":"Government",
            "subcategory":"Police Station",
            "type":"Public Place"
        }
    ],
    "sg:phone":"+1 402 597 2035",
    "sg:postcode":"68046",
    "sg:province":"NE",
    "sg:tags":[
        "department"
    ],
    "wof:name":"City of Papillion Police Department",
    "wof:placetype":"venue"
},
  "geometry": {"coordinates":[-96.02836000000001,41.156483],"type":"Point"}
}