{
  "type": "Feature",
  "properties": {
    "iso:country":"US",
    "sg:address":"70965 State Hwy 15",
    "sg:city":"Fairbury",
    "sg:classifiers":[
        {
            "category":"Building & Trades",
            "subcategory":"Equipment Rental",
            "type":"Services"
        }
    ],
    "sg:phone":"+1 402 729 5886",
    "sg:postcode":"68352",
    "sg:province":"NE",
    "wof:name":"Experimental Aircraft Assn",
    "wof:placetype":"venue"
},
  "geometry": {"coordinates":[-97.171278,40.114933],"type":"Point"}
}