{
  "type": "Feature",
  "properties": {
    "iso:country":"US",
    "sg:address":"10968 Washington St",
    "sg:city":"Omaha",
    "sg:classifiers":[
        {
            "category":"Professional",
            "subcategory":"Secretarial Services",
            "type":"Services"
        }
    ],
    "sg:phone":"+1 402 597 1525",
    "sg:postcode":"68137",
    "sg:province":"NE",
    "sg:tags":[
        "convention",
        "reporting",
        "court",
        "reporter"
    ],
    "wof:name":"Sagar's Reporting",
    "wof:placetype":"venue"
},
  "geometry": {"coordinates":[-96.083917,41.196279],"type":"Point"}
}