{
  "type": "Feature",
  "properties": {
    "addr:full":"1229 S 180th Plz Omaha NE 68130",
    "addr:housenumber":"1229",
    "addr:postcode":"68130",
    "addr:street":"S 180Th",
    "iso:country":"US",
    "sg:address":"1229 S 180th Plz",
    "sg:city":"Omaha",
    "sg:classifiers":[
        {
            "category":"Food & Beverages",
            "subcategory":"Specialty",
            "type":"Retail Goods"
        }
    ],
    "sg:phone":"+1 402 691 9900",
    "sg:postcode":"68130",
    "sg:province":"NE",
    "sg:tags":[
        "tea",
        "coffee"
    ],
    "wof:name":"Barista's Daily Grind",
    "wof:placetype":"venue"
},
  "geometry": {"coordinates":[-96.196558,41.247633],"type":"Point"}
}