{
  "type": "Feature",
  "properties": {
    "iso:country":"US",
    "sg:address":"6813 S 81st St",
    "sg:city":"Omaha",
    "sg:classifiers":[
        {
            "category":"Building & Trades",
            "subcategory":"Construction",
            "type":"Services"
        }
    ],
    "sg:phone":"+1 402 597 1147",
    "sg:postcode":"68127",
    "sg:province":"NE",
    "sg:tags":[
        "house",
        "contract"
    ],
    "wof:name":"Blake McGill",
    "wof:placetype":"venue"
},
  "geometry": {"coordinates":[-96.03853100000001,41.192491],"type":"Point"}
}