{
  "type": "Feature",
  "properties": {
    "addr:full":"1910 S 112th St Omaha NE 68144",
    "addr:housenumber":"1910",
    "addr:postcode":"68144",
    "addr:street":"S 112Th St",
    "iso:country":"US",
    "sg:address":"1910 S 112th St",
    "sg:city":"Omaha",
    "sg:classifiers":[
        {
            "category":"Organizations",
            "subcategory":"Professional Association",
            "type":"Services"
        }
    ],
    "sg:phone":"+1 402 234 2316",
    "sg:postcode":"68144",
    "sg:province":"NE",
    "sg:tags":[
        "establishment"
    ],
    "wof:name":"Reno & Assoc",
    "wof:placetype":"venue"
},
  "geometry": {"coordinates":[-96.086688,41.240311],"type":"Point"}
}