{
  "type": "Feature",
  "properties": {
    "iso:country":"US",
    "sg:address":"1109 Highland Dr",
    "sg:city":"Superior",
    "sg:phone":"+1 402 879 4620",
    "sg:postcode":"68978",
    "sg:province":"NE",
    "sg:tags":[
        "farm",
        "corn"
    ],
    "wof:name":"Sweet",
    "wof:placetype":"venue"
},
  "geometry": {"coordinates":[-98.061421,40.027271],"type":"Point"}
}