{
  "type": "Feature",
  "properties": {
    "iso:country":"US",
    "sg:address":"422 Nasby St",
    "sg:city":"Cambridge",
    "sg:classifiers":[
        {
            "category":"Restaurant",
            "type":"Food & Drink"
        }
    ],
    "sg:menulink":"http://www.allmenus.com/ne/cambridge/225129-caseys-general-store/menu/",
    "sg:phone":"+1 308 697 4830",
    "sg:postcode":"69022",
    "sg:province":"NE",
    "sg:tags":[
        "american",
        "pizza"
    ],
    "wof:name":"Casey's General Store",
    "wof:placetype":"venue"
},
  "geometry": {"coordinates":[-100.16644599999999,40.282024],"type":"Point"}
}