{
  "type": "Feature",
  "properties": {
    "addr:full":"310 W Elkhorn Dr Arlington NE 68002",
    "addr:housenumber":"310",
    "addr:postcode":"68002",
    "addr:street":"W Elkhorn Dr",
    "iso:country":"US",
    "sg:address":"310 W Elkhorn Dr",
    "sg:city":"Arlington",
    "sg:classifiers":[
        {
            "category":"Building & Trades",
            "subcategory":"Construction",
            "type":"Services"
        }
    ],
    "sg:phone":"+1 402 478 5255",
    "sg:postcode":"68002",
    "sg:province":"NE",
    "sg:tags":[
        "contractor"
    ],
    "wof:name":"Hoffman Dean Construction",
    "wof:placetype":"venue"
},
  "geometry": {"coordinates":[-96.35155399999999,41.451407],"type":"Point"}
}