{
  "type": "Feature",
  "properties": {
    "addr:full":"1334 Silver St Ashland NE 68003",
    "addr:housenumber":"1334",
    "addr:postcode":"68003",
    "addr:street":"Silver St",
    "iso:country":"US",
    "sg:address":"1334 Silver St",
    "sg:city":"Ashland",
    "sg:classifiers":[
        {
            "category":"Building & Trades",
            "subcategory":"Plumbing",
            "type":"Services"
        }
    ],
    "sg:phone":"+1 402 944 7016",
    "sg:postcode":"68003",
    "sg:province":"NE",
    "sg:tags":[
        "plumbing",
        "electrical",
        "heating",
        "contractor"
    ],
    "wof:name":"Todd Valley Plumbing & Heating",
    "wof:placetype":"venue"
},
  "geometry": {"coordinates":[-96.36751099999999,41.039172],"type":"Point"}
}