{
  "type": "Feature",
  "properties": {
    "iso:country":"US",
    "sg:address":"1524 Ave B",
    "sg:city":"Plattsmouth",
    "sg:classifiers":[
        {
            "category":"Farming",
            "subcategory":"Livestock Farm",
            "type":"Manufacturing & Wholesale Goods"
        }
    ],
    "sg:phone":"+1 402 298 8220",
    "sg:postcode":"68048",
    "sg:province":"NE",
    "sg:tags":[
        "beef",
        "feedlot",
        "cattle"
    ],
    "wof:name":"Michael Haecke",
    "wof:placetype":"venue"
},
  "geometry": {"coordinates":[-95.897149,41.013419],"type":"Point"}
}