{
  "type": "Feature",
  "properties": {
    "addr:full":"1819 Farnam St Omaha NE 68102",
    "addr:housenumber":"1819",
    "addr:postcode":"68102",
    "addr:street":"Farnam St",
    "iso:country":"US",
    "sg:address":"1819 Farnam St",
    "sg:city":"Omaha",
    "sg:classifiers":[
        {
            "category":"Banks & Credit Unions",
            "subcategory":"Bank",
            "type":"Services"
        }
    ],
    "sg:phone":"+1 402 444 5999",
    "sg:postcode":"68102",
    "sg:province":"NE",
    "sg:tags":[
        "federal"
    ],
    "wof:name":"Omaha Cy Emplyees Fderal Cr Un",
    "wof:placetype":"venue"
},
  "geometry": {"coordinates":[-95.94096,41.257546],"type":"Point"}
}