{
  "type": "Feature",
  "properties": {
    "iso:country":"US",
    "sg:address":"7710 Mercy Rd",
    "sg:city":"Omaha",
    "sg:classifiers":[
        {
            "category":"Health Services",
            "subcategory":"Medical Lab",
            "type":"Services"
        }
    ],
    "sg:phone":"+1 402 398 6500",
    "sg:postcode":"68124",
    "sg:province":"NE",
    "sg:tags":[
        "detection",
        "equipment",
        "drug"
    ],
    "sg:website":"www.alegent.org",
    "wof:name":"Alegent Health Occupational",
    "wof:placetype":"venue"
},
  "geometry": {"coordinates":[-96.03045299999999,41.237979],"type":"Point"}
}