{
  "type": "Feature",
  "properties": {
    "addr:full":"853 Iowa St Blair NE 68008",
    "addr:housenumber":"853",
    "addr:postcode":"68008",
    "addr:street":"Iowa St",
    "iso:country":"US",
    "sg:address":"853 Iowa St",
    "sg:city":"Blair",
    "sg:classifiers":[
        {
            "category":"Retail",
            "subcategory":"Auto Repair",
            "type":"Services"
        }
    ],
    "sg:phone":"+1 402 426 4246",
    "sg:postcode":"68008",
    "sg:province":"NE",
    "sg:tags":[
        "body"
    ],
    "wof:name":"C & R Automotive Inc",
    "wof:placetype":"venue"
},
  "geometry": {"coordinates":[-96.125034,41.545322],"type":"Point"}
}