{
  "type": "Feature",
  "properties": {
    "iso:country":"US",
    "sg:address":"115 S 49th Ave",
    "sg:city":"Omaha",
    "sg:classifiers":[
        {
            "category":"Organizations",
            "subcategory":"Membership Organization",
            "type":"Services"
        }
    ],
    "sg:phone":"+1 402 561 7580",
    "sg:postcode":"68132",
    "sg:province":"NE",
    "wof:name":"Nonprofit Assn of Midlands",
    "wof:placetype":"venue"
},
  "geometry": {"coordinates":[-95.988992,41.257952],"type":"Point"}
}