{
  "type": "Feature",
  "properties": {
    "iso:country":"US",
    "sg:address":"2604 L St",
    "sg:city":"Ord",
    "sg:classifiers":[
        {
            "category":"Autos & Motor Vehicles",
            "subcategory":"Fuel & Gas Station",
            "type":"Retail Goods"
        }
    ],
    "sg:phone":"+1 308 728 5171",
    "sg:postcode":"68862",
    "sg:province":"NE",
    "sg:tags":[
        "farm",
        "station",
        "gasoline",
        "oil",
        "supply"
    ],
    "wof:name":"Van's Service Station",
    "wof:placetype":"venue"
},
  "geometry": {"coordinates":[-98.941643,41.603267],"type":"Point"}
}