{
  "type": "Feature",
  "properties": {
    "iso:country":"US",
    "sg:address":"801 Bellevue Blvd N",
    "sg:city":"Bellevue",
    "sg:classifiers":[
        {
            "category":"Shopping",
            "subcategory":"Gifts & Souvenirs",
            "type":"Retail Goods"
        }
    ],
    "sg:phone":"+1 402 339 5988",
    "sg:postcode":"68005",
    "sg:province":"NE",
    "wof:name":"Country At Heart",
    "wof:placetype":"venue"
},
  "geometry": {"coordinates":[-95.91908100000001,41.175611],"type":"Point"}
}