{
  "type": "Feature",
  "properties": {
    "iso:country":"US",
    "sg:address":"775 N 2nd St",
    "sg:city":"Blair",
    "sg:classifiers":[
        {
            "category":"Banks & Credit Unions",
            "subcategory":"Investment Brokerage",
            "type":"Services"
        }
    ],
    "sg:phone":"+1 402 426 2415",
    "sg:postcode":"68008",
    "sg:province":"NE",
    "wof:name":"Strike Friday",
    "wof:placetype":"venue"
},
  "geometry": {"coordinates":[-96.113125,41.550001],"type":"Point"}
}