{
  "type": "Feature",
  "properties": {
    "addr:full":"8320 F St Omaha NE 68127",
    "addr:housenumber":"8320",
    "addr:postcode":"68127",
    "addr:street":"F St",
    "iso:country":"US",
    "sg:address":"8320 F St",
    "sg:city":"Omaha",
    "sg:classifiers":[
        {
            "category":"Home & Garden",
            "subcategory":"Building Materials",
            "type":"Retail Goods"
        }
    ],
    "sg:phone":"+1 402 592 1111",
    "sg:postcode":"68127",
    "sg:province":"NE",
    "sg:tags":[
        "paint"
    ],
    "wof:name":"Sophir Morris Paint",
    "wof:placetype":"venue"
},
  "geometry": {"coordinates":[-96.04091699999999,41.219809],"type":"Point"}
}