{
  "type": "Feature",
  "properties": {
    "iso:country":"US",
    "sg:address":"1902 E 23 Rd",
    "sg:city":"Marquette",
    "sg:classifiers":[
        {
            "category":"Farming",
            "subcategory":"Farm",
            "type":"Manufacturing & Wholesale Goods"
        }
    ],
    "sg:phone":"+1 402 854 2699",
    "sg:postcode":"68854",
    "sg:province":"NE",
    "sg:tags":[
        "crop",
        "general"
    ],
    "wof:name":"Jon Hansen",
    "wof:placetype":"venue"
},
  "geometry": {"coordinates":[-97.935543,41.017333],"type":"Point"}
}