{
  "type": "Feature",
  "properties": {
    "iso:country":"US",
    "sg:address":"209 W S St",
    "sg:city":"Mc Cook",
    "sg:classifiers":[
        {
            "category":"Wholesale",
            "subcategory":"Farm Supplies",
            "type":"Manufacturing & Wholesale Goods"
        }
    ],
    "sg:phone":"+1 308 345 6380",
    "sg:postcode":"69001",
    "sg:province":"NE",
    "sg:tags":[
        "feed"
    ],
    "wof:name":"Stockman's Feed & Supply Inc",
    "wof:placetype":"venue"
},
  "geometry": {"coordinates":[-100.628111,40.215422],"type":"Point"}
}