{
  "type": "Feature",
  "properties": {
    "iso:country":"US",
    "sg:address":"3820 N 90th St",
    "sg:city":"Omaha",
    "sg:classifiers":[
        {
            "category":"Retail",
            "subcategory":"Auto Repair",
            "type":"Services"
        }
    ],
    "sg:phone":"+1 402 572 8626",
    "sg:postcode":"68134",
    "sg:province":"NE",
    "sg:tags":[
        "automobile",
        "lubrication"
    ],
    "wof:name":"Grease Monkey",
    "wof:placetype":"venue"
},
  "geometry": {"coordinates":[-96.053218,41.291635],"type":"Point"}
}