{
  "type": "Feature",
  "properties": {
    "addr:full":"523 Central Ave Nebraska City NE 68410",
    "addr:housenumber":"523",
    "addr:postcode":"68410",
    "addr:street":"Central Ave",
    "iso:country":"US",
    "sg:address":"523 Central Ave",
    "sg:city":"Nebraska City",
    "sg:classifiers":[
        {
            "category":"Wholesale",
            "subcategory":"Durable Goods & Equipment",
            "type":"Manufacturing & Wholesale Goods"
        }
    ],
    "sg:phone":"+1 402 873 6277",
    "sg:postcode":"68410",
    "sg:province":"NE",
    "sg:tags":[
        "fire",
        "extinguisher"
    ],
    "wof:name":"Fire Protection Sales & Svc",
    "wof:placetype":"venue"
},
  "geometry": {"coordinates":[-95.85228600000001,40.676474],"type":"Point"}
}