{
  "type": "Feature",
  "properties": {
    "iso:country":"US",
    "sg:address":"7120 Military Ave",
    "sg:city":"Omaha",
    "sg:classifiers":[
        {
            "category":"Restaurant",
            "type":"Food & Drink"
        }
    ],
    "sg:menulink":"http://www.allmenus.com/ne/omaha/199707-sonic/menu/",
    "sg:phone":"+1 402 898 9393",
    "sg:postcode":"68104",
    "sg:province":"NE",
    "sg:tags":[
        "burger",
        "american"
    ],
    "wof:name":"Sonic",
    "wof:placetype":"venue"
},
  "geometry": {"coordinates":[-96.02273,41.297101],"type":"Point"}
}