{
  "type": "Feature",
  "properties": {
    "iso:country":"US",
    "sg:address":"630 Lakewood Dr",
    "sg:city":"Lincoln",
    "sg:classifiers":[
        {
            "category":"Building & Trades",
            "subcategory":"Construction",
            "type":"Services"
        }
    ],
    "sg:phone":"+1 402 488 6555",
    "sg:postcode":"68510",
    "sg:province":"NE",
    "sg:tags":[
        "home",
        "builder"
    ],
    "wof:name":"Willowbrooke Custom Homes",
    "wof:placetype":"venue"
},
  "geometry": {"coordinates":[-96.617938,40.805328],"type":"Point"}
}