{
  "type": "Feature",
  "properties": {
    "iso:country":"US",
    "sg:address":"3353 L St",
    "sg:city":"Omaha",
    "sg:classifiers":[
        {
            "category":"Health Services",
            "subcategory":"Health Practitioner",
            "type":"Services"
        }
    ],
    "sg:phone":"+1 402 354 7730",
    "sg:postcode":"68107",
    "sg:province":"NE",
    "sg:tags":[
        "clinic",
        "therapist",
        "therapy",
        "physical"
    ],
    "wof:name":"Methodist Hospital Physical Therapy",
    "wof:placetype":"venue"
},
  "geometry": {"coordinates":[-95.963858,41.21226],"type":"Point"}
}