{
  "type": "Feature",
  "properties": {
    "iso:country":"US",
    "sg:address":"4211 South 102nd Street",
    "sg:city":"Omaha",
    "sg:classifiers":[
        {
            "category":"Professional",
            "subcategory":"Computer Services",
            "type":"Services"
        }
    ],
    "sg:phone":"+1 212 806 3500",
    "sg:postcode":"68127",
    "sg:province":"NE",
    "sg:website":"http://www.tdameritrade.com/",
    "wof:name":"TD Ameritrade",
    "wof:placetype":"venue"
},
  "geometry": {"coordinates":[-96.071727,41.218993],"type":"Point"}
}