{
  "type": "Feature",
  "properties": {
    "iso:country":"US",
    "sg:address":"1214 E South St",
    "sg:city":"Hastings",
    "sg:classifiers":[
        {
            "category":"Autos & Motor Vehicles",
            "subcategory":"Automobile Sales",
            "type":"Retail Goods"
        }
    ],
    "sg:phone":"+1 402 461 4943",
    "sg:postcode":"68901",
    "sg:province":"NE",
    "sg:tags":[
        "car",
        "dealer"
    ],
    "wof:name":"J & M Cars & Equipment",
    "wof:placetype":"venue"
},
  "geometry": {"coordinates":[-98.365863,40.582451],"type":"Point"}
}