{
  "type": "Feature",
  "properties": {
    "iso:country":"US",
    "sg:address":"421 State Hwy 92 Scn",
    "sg:city":"Lemoyne",
    "sg:classifiers":[
        {
            "category":"Shopping",
            "subcategory":"Catalog Store",
            "type":"Retail Goods"
        }
    ],
    "sg:phone":"+1 308 355 6747",
    "sg:postcode":"69146",
    "sg:province":"NE",
    "sg:tags":[
        "mail",
        "house"
    ],
    "wof:name":"Independent Avon Distributor",
    "wof:placetype":"venue"
},
  "geometry": {"coordinates":[-101.751293,41.261384],"type":"Point"}
}