{
  "type": "Feature",
  "properties": {
    "addr:full":"3608 Cornhusker Dr Omaha NE 68124",
    "addr:housenumber":"3608",
    "addr:postcode":"68124",
    "addr:street":"Cornhusker Dr",
    "iso:country":"US",
    "sg:address":"3608 Cornhusker Dr",
    "sg:city":"Omaha",
    "sg:classifiers":[
        {
            "category":"Shopping",
            "subcategory":"Jewelry",
            "type":"Retail Goods"
        }
    ],
    "sg:phone":"+1 402 391 0072",
    "sg:postcode":"68124",
    "sg:province":"NE",
    "wof:name":"Jewelry Weddings",
    "wof:placetype":"venue"
},
  "geometry": {"coordinates":[-96.052768,41.225618],"type":"Point"}
}