{
  "type": "Feature",
  "properties": {
    "iso:country":"US",
    "sg:address":"6606 S 75th Ave Cir",
    "sg:city":"Omaha",
    "sg:classifiers":[
        {
            "category":"Building & Trades",
            "subcategory":"Cleaning & Sanitation",
            "type":"Services"
        }
    ],
    "sg:phone":"+1 402 614 3749",
    "sg:postcode":"68127",
    "sg:province":"NE",
    "sg:tags":[
        "maintenance"
    ],
    "wof:name":"New Way Building Maintenance",
    "wof:placetype":"venue"
},
  "geometry": {"coordinates":[-96.030422,41.193645],"type":"Point"}
}