{
  "type": "Feature",
  "properties": {
    "iso:country":"US",
    "sg:address":"120 Maud St",
    "sg:city":"Gresham",
    "sg:classifiers":[
        {
            "category":"Real Estate",
            "subcategory":"Real Estate Agent",
            "type":"Services"
        }
    ],
    "sg:phone":"+1 402 735 7292",
    "sg:postcode":"68367",
    "sg:province":"NE",
    "sg:tags":[
        "authorities",
        "housing"
    ],
    "wof:name":"Gresham Housing Authority",
    "wof:placetype":"venue"
},
  "geometry": {"coordinates":[-97.40349399999999,41.025876],"type":"Point"}
}