{
  "type": "Feature",
  "properties": {
    "iso:country":"US",
    "sg:address":"315 Hopper St",
    "sg:city":"Elkhorn",
    "sg:classifiers":[
        {
            "category":"Social Services",
            "subcategory":"Job Training",
            "type":"Services"
        }
    ],
    "sg:phone":"+1 402 289 2572",
    "sg:postcode":"68022",
    "sg:province":"NE",
    "sg:tags":[
        "rehabilitation"
    ],
    "sg:website":"www.lcca.com",
    "wof:name":"Life Care Ctr Of Elkhorn",
    "wof:placetype":"venue"
},
  "geometry": {"coordinates":[-96.229061,41.28911],"type":"Point"}
}