{
  "type": "Feature",
  "properties": {
    "iso:country":"US",
    "sg:address":"901 Lake Ave",
    "sg:city":"Gothenburg",
    "sg:classifiers":[
        {
            "category":"Insurance",
            "subcategory":"Insurance Agent",
            "type":"Services"
        }
    ],
    "sg:phone":"+1 308 537 7365",
    "sg:postcode":"69138",
    "sg:province":"NE",
    "wof:name":"Yancy Insurance Agency Inc",
    "wof:placetype":"venue"
},
  "geometry": {"coordinates":[-100.162047,40.92771],"type":"Point"}
}